globals [DENSITY INITIAL-TREES BURNED-TREES RESULT]
interfaceGlobals [density]
turtles-own [WHO COLOR HEADING XCOR YCOR SHAPE LABEL LABEL-COLOR BREED HIDDEN? SIZE PEN-SIZE PEN-MODE]
patches-own [PXCOR PYCOR PCOLOR PLABEL PLABEL-COLOR FIRE COUNTS]
links-own [END1 END2 COLOR LABEL LABEL-COLOR HIDDEN? BREED THICKNESS SHAPE TIE-MODE]
breeds 
link-breeds 

procedure BENCHMARK:[_repeatlocal:0]{O---}:
[0]_asm_procedurebenchmark_randomseed_0 "random-seed 362" double => void
      _constdouble:362.0 "362" => double
          // parameter final  context
          // parameter final  context
          // parameter final  arg0
         L0
          LDC 362.0D
         L1
          DSTORE 2
          DLOAD 2
          D2L
          LSTORE 4
          LLOAD 4
          LDC -2147483648L
          LCMP
          IFLT L2
          LLOAD 4
          LDC 2147483647L
          LCMP
          IFLE L3
         L2
         FRAME APPEND [D J]
          NEW org/nlogo/nvm/RuntimePrimitiveException
          DUP
          ALOAD 1
          ALOAD 0
          GETSTATIC org/nlogo/api/Dump$.MODULE$ : Lorg/nlogo/api/Dump$;
          DLOAD 2
          INVOKEVIRTUAL org/nlogo/api/Dump$.number (D)Ljava/lang/String;
          INVOKEDYNAMIC makeConcatWithConstants(Ljava/lang/String;)Ljava/lang/String; [
            // handle kind 0x6 : INVOKESTATIC
            java/lang/invoke/StringConcatFactory.makeConcatWithConstants(Ljava/lang/invoke/MethodHandles$Lookup;Ljava/lang/String;Ljava/lang/invoke/MethodType;Ljava/lang/String;[Ljava/lang/Object;)Ljava/lang/invoke/CallSite;
            // arguments:
            "\u0001 is not in the allowable range for random seeds (-2147483648 to 2147483647)"
          ]
          INVOKESPECIAL org/nlogo/nvm/RuntimePrimitiveException.<init> (Lorg/nlogo/api/Context;Lorg/nlogo/nvm/Instruction;Ljava/lang/String;)V
          ATHROW
         L3
         FRAME SAME
          LLOAD 4
          L2I
          ISTORE 6
          ALOAD 1
          GETFIELD org/nlogo/nvm/Context.job : Lorg/nlogo/nvm/Job;
          GETFIELD org/nlogo/nvm/Job.random : Lorg/nlogo/api/MersenneTwisterFast;
          ILOAD 6
          I2L
          INVOKEVIRTUAL org/nlogo/api/MersenneTwisterFast.setSeed (J)V
          ALOAD 1
          GETFIELD org/nlogo/nvm/Context.job : Lorg/nlogo/nvm/Job;
          GETFIELD org/nlogo/nvm/Job.workspace : Lorg/nlogo/nvm/Workspace;
          IFNULL L4
          ALOAD 1
          GETFIELD org/nlogo/nvm/Context.job : Lorg/nlogo/nvm/Job;
          GETFIELD org/nlogo/nvm/Job.random : Lorg/nlogo/api/MersenneTwisterFast;
          ALOAD 1
          GETFIELD org/nlogo/nvm/Context.job : Lorg/nlogo/nvm/Job;
          GETFIELD org/nlogo/nvm/Job.workspace : Lorg/nlogo/nvm/Workspace;
          INVOKEINTERFACE org/nlogo/nvm/Workspace.world ()Lorg/nlogo/agent/World; (itf)
          INVOKEVIRTUAL org/nlogo/agent/World.mainRNG ()Lorg/nlogo/api/MersenneTwisterFast;
          ASTORE 7
          DUP
          IFNONNULL L5
          POP
          ALOAD 7
          IFNULL L6
          GOTO L4
         L5
         FRAME FULL [org/nlogo/prim/_asm_procedurebenchmark_randomseed_0 org/nlogo/nvm/Context D J I org/nlogo/api/MersenneTwisterFast] [org/nlogo/api/MersenneTwisterFast]
          ALOAD 7
          INVOKEVIRTUAL java/lang/Object.equals (Ljava/lang/Object;)Z
          IFEQ L4
         L6
         FRAME SAME
          ALOAD 1
          GETFIELD org/nlogo/nvm/Context.job : Lorg/nlogo/nvm/Job;
          GETFIELD org/nlogo/nvm/Job.workspace : Lorg/nlogo/nvm/Workspace;
          INVOKEINTERFACE org/nlogo/nvm/Workspace.plotRNG ()Lorg/nlogo/api/MersenneTwisterFast; (itf)
          ILOAD 6
          I2L
          INVOKEVIRTUAL org/nlogo/api/MersenneTwisterFast.setSeed (J)V
         L4
         FRAME CHOP 1
          ALOAD 1
          ICONST_1
          PUTFIELD org/nlogo/nvm/Context.ip : I
         L7
          RETURN
[1]_resettimer "reset-timer"
[2]_asm_procedurebenchmark_call_1 "setup"
         L0
          NEW org/nlogo/nvm/Activation
          DUP
          ALOAD 0
          GETFIELD org/nlogo/prim/_asm_procedurebenchmark_call_1.kept1_procedure : Lorg/nlogo/nvm/Procedure;
          ALOAD 1
          GETFIELD org/nlogo/nvm/Context.activation : Lorg/nlogo/nvm/Activation;
          SIPUSH 0
          ANEWARRAY java/lang/Object
          ICONST_3
          INVOKESPECIAL org/nlogo/nvm/Activation.<init> (Lorg/nlogo/nvm/Procedure;Lorg/nlogo/nvm/Activation;[Ljava/lang/Object;I)V
          ALOAD 1
          SWAP
          PUTFIELD org/nlogo/nvm/Context.activation : Lorg/nlogo/nvm/Activation;
          ALOAD 1
          ICONST_0
          PUTFIELD org/nlogo/nvm/Context.ip : I
         L1
          RETURN
[3]_asm_procedurebenchmark_repeatlocal_2 "repeat 100 [ go ]" double => void
      _constdouble:100.0 "100" => double
          // parameter final  context
          // parameter final  context
          // parameter final  arg0
         L0
          LDC 100.0D
         L1
          DSTORE 2
          ALOAD 1
          GETFIELD org/nlogo/nvm/Context.activation : Lorg/nlogo/nvm/Activation;
          GETFIELD org/nlogo/nvm/Activation.args : [Ljava/lang/Object;
          ICONST_0
          NEW org/nlogo/nvm/MutableLong
          DUP
          ALOAD 0
          DLOAD 2
          ALOAD 1
          INVOKEVIRTUAL org/nlogo/prim/_asm_procedurebenchmark_repeatlocal_2.validLong (DLorg/nlogo/nvm/Context;)J
          INVOKESPECIAL org/nlogo/nvm/MutableLong.<init> (J)V
          AASTORE
          ALOAD 1
          ICONST_5
          PUTFIELD org/nlogo/nvm/Context.ip : I
         L2
          RETURN
[4]_asm_procedurebenchmark_call_3 "go"
         L0
          NEW org/nlogo/nvm/Activation
          DUP
          ALOAD 0
          GETFIELD org/nlogo/prim/_asm_procedurebenchmark_call_3.kept1_procedure : Lorg/nlogo/nvm/Procedure;
          ALOAD 1
          GETFIELD org/nlogo/nvm/Context.activation : Lorg/nlogo/nvm/Activation;
          SIPUSH 0
          ANEWARRAY java/lang/Object
          ICONST_5
          INVOKESPECIAL org/nlogo/nvm/Activation.<init> (Lorg/nlogo/nvm/Procedure;Lorg/nlogo/nvm/Activation;[Ljava/lang/Object;I)V
          ALOAD 1
          SWAP
          PUTFIELD org/nlogo/nvm/Context.activation : Lorg/nlogo/nvm/Activation;
          ALOAD 1
          ICONST_0
          PUTFIELD org/nlogo/nvm/Context.ip : I
         L1
          RETURN
[5]_asm_procedurebenchmark_repeatlocalinternal_4 => void
          // parameter final  context
         L0
          ALOAD 1
          GETFIELD org/nlogo/nvm/Context.activation : Lorg/nlogo/nvm/Activation;
          GETFIELD org/nlogo/nvm/Activation.args : [Ljava/lang/Object;
          ICONST_0
          AALOAD
          CHECKCAST org/nlogo/nvm/MutableLong
          ASTORE 2
          ALOAD 2
          INVOKEVIRTUAL org/nlogo/nvm/MutableLong.value ()J
          LCONST_0
          LCMP
          IFGT L1
          ALOAD 1
          BIPUSH 6
          PUTFIELD org/nlogo/nvm/Context.ip : I
          GOTO L2
         L1
         FRAME APPEND [org/nlogo/nvm/MutableLong]
          ALOAD 2
          ALOAD 2
          INVOKEVIRTUAL org/nlogo/nvm/MutableLong.value ()J
          LCONST_1
          LSUB
          INVOKEVIRTUAL org/nlogo/nvm/MutableLong.value_$eq (J)V
          ALOAD 1
          ICONST_4
          PUTFIELD org/nlogo/nvm/Context.ip : I
         L2
         FRAME SAME
          RETURN
[6]_asm_procedurebenchmark_setobservervariable_5 "set result timer" Object => void
      _timer "timer" => double
          // parameter final  context
          // parameter final  context
          // parameter final  arg0
          TRYCATCHBLOCK L0 L1 L2 org/nlogo/api/AgentException
         L3
          ALOAD 0
          GETFIELD org/nlogo/prim/_asm_procedurebenchmark_setobservervariable_5.world : Lorg/nlogo/agent/World;
          INVOKEVIRTUAL org/nlogo/agent/World.timer ()Lorg/nlogo/api/Timer;
          INVOKEVIRTUAL org/nlogo/api/Timer.read ()D
         L4
          DSTORE 2
          NEW java/lang/Double
          DUP
          DLOAD 2
          INVOKESPECIAL java/lang/Double.<init> (D)V
          ASTORE 2
         L0
          ALOAD 0
          GETFIELD org/nlogo/prim/_asm_procedurebenchmark_setobservervariable_5.world : Lorg/nlogo/agent/World;
          INVOKEVIRTUAL org/nlogo/agent/World.observer ()Lorg/nlogo/agent/Observer;
          ICONST_3
          ALOAD 2
          INVOKEVIRTUAL org/nlogo/agent/Observer.setVariable (ILjava/lang/Object;)V
         L1
          GOTO L5
         L2
         FRAME FULL [org/nlogo/prim/_asm_procedurebenchmark_setobservervariable_5 org/nlogo/nvm/Context java/lang/Double] [org/nlogo/api/AgentException]
          ASTORE 3
          NEW org/nlogo/nvm/RuntimePrimitiveException
          DUP
          ALOAD 1
          ALOAD 0
          ALOAD 3
          INVOKEVIRTUAL org/nlogo/api/AgentException.getMessage ()Ljava/lang/String;
          INVOKESPECIAL org/nlogo/nvm/RuntimePrimitiveException.<init> (Lorg/nlogo/api/Context;Lorg/nlogo/nvm/Instruction;Ljava/lang/String;)V
          ATHROW
         L5
         FRAME SAME
          ALOAD 1
          BIPUSH 7
          PUTFIELD org/nlogo/nvm/Context.ip : I
         L6
          RETURN
[7]_asm_procedurebenchmark_return_6 => void
          // parameter final  context
         L0
          ALOAD 1
          INVOKEVIRTUAL org/nlogo/nvm/Context.returnFromProcedure ()V
          ALOAD 1
          ICONST_0
          PUTFIELD org/nlogo/nvm/Context.stopping : Z
         L1
          RETURN

procedure SETUP:[]{O---}:
[0]_clearall "ca"
[1]_resetticks "reset-ticks"
[2]_asm_proceduresetup_ask_0 "ask patches set fire 0 if pxcor > 1 + min-pxcor [ if random 100 < density [ set pcolor green ] ] [ if pxcor = 1 + min-pycor set pcolor red [ set fire 1 ] ]" AgentSet => void
      _patches "patches" => AgentSet
          // parameter final  context
          // parameter final  context
          // parameter final  agents
         L0
          ALOAD 0
          GETFIELD org/nlogo/prim/_asm_proceduresetup_ask_0.world : Lorg/nlogo/agent/World;
          INVOKEVIRTUAL org/nlogo/agent/World.patches ()Lorg/nlogo/agent/IndexedAgentSet;
         L1
          ASTORE 2
          ALOAD 1
          GETFIELD org/nlogo/nvm/Context.agent : Lorg/nlogo/agent/Agent;
          INSTANCEOF org/nlogo/agent/Observer
          IFNE L2
          ALOAD 2
          ALOAD 0
          GETFIELD org/nlogo/prim/_asm_proceduresetup_ask_0.world : Lorg/nlogo/agent/World;
          INVOKEVIRTUAL org/nlogo/agent/World.turtles ()Lorg/nlogo/agent/TreeAgentSet;
          IF_ACMPNE L3
          NEW org/nlogo/nvm/RuntimePrimitiveException
          DUP
          ALOAD 1
          ALOAD 0
          GETSTATIC org/nlogo/core/I18N$.MODULE$ : Lorg/nlogo/core/I18N$;
          INVOKEVIRTUAL org/nlogo/core/I18N$.errors ()Lorg/nlogo/core/I18N$BundleKind;
          LDC "org.nlogo.prim.$common.onlyObserverCanAskAllTurtles"
          INVOKEVIRTUAL org/nlogo/core/I18N$BundleKind.get (Ljava/lang/String;)Ljava/lang/String;
          INVOKESPECIAL org/nlogo/nvm/RuntimePrimitiveException.<init> (Lorg/nlogo/api/Context;Lorg/nlogo/nvm/Instruction;Ljava/lang/String;)V
          ATHROW
         L3
         FRAME APPEND [org/nlogo/agent/IndexedAgentSet]
          ALOAD 2
          ALOAD 0
          GETFIELD org/nlogo/prim/_asm_proceduresetup_ask_0.world : Lorg/nlogo/agent/World;
          INVOKEVIRTUAL org/nlogo/agent/World.patches ()Lorg/nlogo/agent/IndexedAgentSet;
          IF_ACMPNE L2
          NEW org/nlogo/nvm/RuntimePrimitiveException
          DUP
          ALOAD 1
          ALOAD 0
          GETSTATIC org/nlogo/core/I18N$.MODULE$ : Lorg/nlogo/core/I18N$;
          INVOKEVIRTUAL org/nlogo/core/I18N$.errors ()Lorg/nlogo/core/I18N$BundleKind;
          LDC "org.nlogo.prim.$common.onlyObserverCanAskAllPatches"
          INVOKEVIRTUAL org/nlogo/core/I18N$BundleKind.get (Ljava/lang/String;)Ljava/lang/String;
          INVOKESPECIAL org/nlogo/nvm/RuntimePrimitiveException.<init> (Lorg/nlogo/api/Context;Lorg/nlogo/nvm/Instruction;Ljava/lang/String;)V
          ATHROW
         L2
         FRAME SAME
          ALOAD 1
          ALOAD 2
          ICONST_3
          INVOKEVIRTUAL org/nlogo/nvm/Context.runExclusiveJob (Lorg/nlogo/agent/AgentSet;I)V
          ALOAD 1
          BIPUSH 11
          PUTFIELD org/nlogo/nvm/Context.ip : I
         L4
          RETURN
[3]_asm_proceduresetup_setpatchvariable_1 "set fire 0" Object => void
      _constdouble:0.0 "0" => Double
          // parameter final  context
          // parameter final  context
          // parameter final  arg0
          TRYCATCHBLOCK L0 L1 L2 org/nlogo/api/AgentException
         L3
          ALOAD 0
          GETFIELD org/nlogo/prim/_asm_proceduresetup_setpatchvariable_1.kept2_value : Ljava/lang/Double;
         L4
          ASTORE 2
         L0
          ALOAD 1
          GETFIELD org/nlogo/nvm/Context.agent : Lorg/nlogo/agent/Agent;
          ICONST_5
          ALOAD 2
          INVOKEVIRTUAL org/nlogo/agent/Agent.setPatchVariable (ILjava/lang/Object;)V
         L1
          GOTO L5
         L2
         FRAME FULL [org/nlogo/prim/_asm_proceduresetup_setpatchvariable_1 org/nlogo/nvm/Context java/lang/Double] [org/nlogo/api/AgentException]
          ASTORE 3
          NEW org/nlogo/nvm/RuntimePrimitiveException
          DUP
          ALOAD 1
          ALOAD 0
          ALOAD 3
          INVOKEVIRTUAL org/nlogo/api/AgentException.getMessage ()Ljava/lang/String;
          INVOKESPECIAL org/nlogo/nvm/RuntimePrimitiveException.<init> (Lorg/nlogo/api/Context;Lorg/nlogo/nvm/Instruction;Ljava/lang/String;)V
          ATHROW
         L5
         FRAME SAME
          ALOAD 1
          ICONST_4
          PUTFIELD org/nlogo/nvm/Context.ip : I
         L6
          RETURN
[4]_asm_proceduresetup_if_2 "if pxcor > 1 + min-pxcor [ if random 100 < density [ set pcolor green ] ]" boolean => void
      _greaterthan "pxcor > 1 + min-pxcor" double,double => boolean
        _patchvariabledouble:PXCOR "pxcor" => double
        _plus "1 + min-pxcor" double,double => double
          _constdouble:1.0 "1" => double
          _minpxcor "min-pxcor" => double
          // parameter final  context
          // parameter final  context
          // parameter final  context
          // parameter final  context
          // parameter final  d1
          // parameter final  d2
          // parameter final  context
          // parameter final  arg0
          // parameter final  arg1
          // parameter final  context
          // parameter final  arg0
         L0
          ALOAD 1
          GETFIELD org/nlogo/nvm/Context.agent : Lorg/nlogo/agent/Agent;
          ASTORE 2
          ALOAD 2
          INSTANCEOF org/nlogo/agent/Turtle
          IFEQ L1
          ALOAD 2
          CHECKCAST org/nlogo/agent/Turtle
          INVOKEVIRTUAL org/nlogo/agent/Turtle.getPatchHere ()Lorg/nlogo/agent/Patch;
          GOTO L2
         L1
         FRAME APPEND [org/nlogo/agent/Agent]
          ALOAD 2
          INSTANCEOF org/nlogo/agent/Patch
          IFEQ L3
          ALOAD 2
          CHECKCAST org/nlogo/agent/Patch
          GOTO L2
         L3
         FRAME SAME
          NEW java/lang/IllegalStateException
          DUP
          INVOKESPECIAL java/lang/IllegalStateException.<init> ()V
          ATHROW
         L2
         FRAME SAME1 org/nlogo/agent/Patch
          ICONST_0
          INVOKEVIRTUAL org/nlogo/agent/Patch.getPatchVariableDouble (I)D
         L4
          DCONST_1
         L5
          ALOAD 0
          GETFIELD org/nlogo/prim/_asm_proceduresetup_if_2.world : Lorg/nlogo/agent/World;
          INVOKEVIRTUAL org/nlogo/agent/World.minPxcor ()I
          I2D
         L6
          DSTORE 4
          DSTORE 2
          DLOAD 2
          DLOAD 4
          DADD
         L7
          DSTORE 4
          DSTORE 2
          DLOAD 2
          DLOAD 4
          DCMPL
          IFLE L8
          ICONST_1
          GOTO L9
         L8
         FRAME FULL [org/nlogo/prim/_asm_proceduresetup_if_2 org/nlogo/nvm/Context D D] []
          ICONST_0
         L9
         FRAME SAME1 I
          ISTORE 2
          ALOAD 1
          ILOAD 2
          IFEQ L10
          ICONST_5
          GOTO L11
         L10
         FRAME FULL [org/nlogo/prim/_asm_proceduresetup_if_2 org/nlogo/nvm/Context I T D] [org/nlogo/nvm/Context]
          BIPUSH 7
         L11
         FRAME FULL [org/nlogo/prim/_asm_proceduresetup_if_2 org/nlogo/nvm/Context I T D] [org/nlogo/nvm/Context I]
          PUTFIELD org/nlogo/nvm/Context.ip : I
         L12
          RETURN
[5]_asm_proceduresetup_if_3 "if random 100 < density [ set pcolor green ]" boolean => void
      _lessthan "random 100 < density" double,Object => boolean
        _randomconst:100 "random 100" => double
        _observervariable:DENSITY "density" => Object
          // parameter final  context
          // parameter final  context
          // parameter final  context
          // parameter final  arg0
          // parameter final  arg1
          // parameter final  context
          // parameter final  arg0
         L0
          ALOAD 1
          GETFIELD org/nlogo/nvm/Context.job : Lorg/nlogo/nvm/Job;
          GETFIELD org/nlogo/nvm/Job.random : Lorg/nlogo/api/MersenneTwisterFast;
          LDC 100L
          INVOKEVIRTUAL org/nlogo/api/MersenneTwisterFast.nextLong (J)J
          L2D
         L1
          ALOAD 0
          GETFIELD org/nlogo/prim/_asm_proceduresetup_if_3.world : Lorg/nlogo/agent/World;
          INVOKEVIRTUAL org/nlogo/agent/World.observer ()Lorg/nlogo/agent/Observer;
          ICONST_0
          INVOKEVIRTUAL org/nlogo/agent/Observer.getVariable (I)Ljava/lang/Object;
         L2
          ASTORE 4
          DSTORE 2
          ALOAD 4
          INSTANCEOF java/lang/Double
          IFEQ L3
          ALOAD 4
          CHECKCAST java/lang/Double
          ASTORE 5
          DLOAD 2
          ALOAD 5
          INVOKEVIRTUAL java/lang/Double.doubleValue ()D
          DCMPG
          IFGE L4
          ICONST_1
          GOTO L5
         L4
         FRAME APPEND [D java/lang/Object java/lang/Double]
          ICONST_0
          GOTO L5
         L3
         FRAME CHOP 1
          NEW org/nlogo/nvm/RuntimePrimitiveException
          DUP
          ALOAD 1
          ALOAD 0
          GETSTATIC org/nlogo/core/I18N$.MODULE$ : Lorg/nlogo/core/I18N$;
          INVOKEVIRTUAL org/nlogo/core/I18N$.errors ()Lorg/nlogo/core/I18N$BundleKind;
          LDC "org.nlogo.prim._lessthan.cantUseLessthanOnDifferentArgs"
          GETSTATIC scala/runtime/ScalaRunTime$.MODULE$ : Lscala/runtime/ScalaRunTime$;
          ICONST_2
          ANEWARRAY java/lang/Object
          DUP
          ICONST_0
          GETSTATIC org/nlogo/api/TypeNames$.MODULE$ : Lorg/nlogo/api/TypeNames$;
          DLOAD 2
          INVOKESTATIC scala/runtime/BoxesRunTime.boxToDouble (D)Ljava/lang/Double;
          INVOKEVIRTUAL org/nlogo/api/TypeNames$.aName (Ljava/lang/Object;)Ljava/lang/String;
          AASTORE
          DUP
          ICONST_1
          GETSTATIC org/nlogo/api/TypeNames$.MODULE$ : Lorg/nlogo/api/TypeNames$;
          ALOAD 4
          INVOKEVIRTUAL org/nlogo/api/TypeNames$.aName (Ljava/lang/Object;)Ljava/lang/String;
          AASTORE
          INVOKEVIRTUAL scala/runtime/ScalaRunTime$.wrapRefArray ([Ljava/lang/Object;)Lscala/collection/immutable/ArraySeq;
          INVOKEVIRTUAL org/nlogo/core/I18N$BundleKind.getN (Ljava/lang/String;Lscala/collection/immutable/Seq;)Ljava/lang/String;
          INVOKESPECIAL org/nlogo/nvm/RuntimePrimitiveException.<init> (Lorg/nlogo/api/Context;Lorg/nlogo/nvm/Instruction;Ljava/lang/String;)V
          ATHROW
         L5
         FRAME FULL [org/nlogo/prim/_asm_proceduresetup_if_3 org/nlogo/nvm/Context D java/lang/Object java/lang/Double] [I]
          ISTORE 2
          ALOAD 1
          ILOAD 2
          IFEQ L6
          BIPUSH 6
          GOTO L7
         L6
         FRAME FULL [org/nlogo/prim/_asm_proceduresetup_if_3 org/nlogo/nvm/Context I T java/lang/Object java/lang/Double] [org/nlogo/nvm/Context]
          BIPUSH 7
         L7
         FRAME FULL [org/nlogo/prim/_asm_proceduresetup_if_3 org/nlogo/nvm/Context I T java/lang/Object java/lang/Double] [org/nlogo/nvm/Context I]
          PUTFIELD org/nlogo/nvm/Context.ip : I
         L8
          RETURN
[6]_asm_proceduresetup_setpatchvariable_4 "set pcolor green" Object => void
      _constdouble:55.0 "green" => Double
          // parameter final  context
          // parameter final  context
          // parameter final  arg0
          TRYCATCHBLOCK L0 L1 L2 org/nlogo/api/AgentException
         L3
          ALOAD 0
          GETFIELD org/nlogo/prim/_asm_proceduresetup_setpatchvariable_4.kept2_value : Ljava/lang/Double;
         L4
          ASTORE 2
         L0
          ALOAD 1
          GETFIELD org/nlogo/nvm/Context.agent : Lorg/nlogo/agent/Agent;
          ICONST_2
          ALOAD 2
          INVOKEVIRTUAL org/nlogo/agent/Agent.setPatchVariable (ILjava/lang/Object;)V
         L1
          GOTO L5
         L2
         FRAME FULL [org/nlogo/prim/_asm_proceduresetup_setpatchvariable_4 org/nlogo/nvm/Context java/lang/Double] [org/nlogo/api/AgentException]
          ASTORE 3
          NEW org/nlogo/nvm/RuntimePrimitiveException
          DUP
          ALOAD 1
          ALOAD 0
          ALOAD 3
          INVOKEVIRTUAL org/nlogo/api/AgentException.getMessage ()Ljava/lang/String;
          INVOKESPECIAL org/nlogo/nvm/RuntimePrimitiveException.<init> (Lorg/nlogo/api/Context;Lorg/nlogo/nvm/Instruction;Ljava/lang/String;)V
          ATHROW
         L5
         FRAME SAME
          ALOAD 1
          BIPUSH 7
          PUTFIELD org/nlogo/nvm/Context.ip : I
         L6
          RETURN
[7]_asm_proceduresetup_if_5 "if pxcor = 1 + min-pycor set pcolor red [ set fire 1 ]" boolean => void
      _equal "pxcor = 1 + min-pycor" double,double => boolean
        _patchvariabledouble:PXCOR "pxcor" => double
        _plus "1 + min-pycor" double,double => double
          _constdouble:1.0 "1" => double
          _minpycor "min-pycor" => double
          // parameter final  context
          // parameter final  context
          // parameter final  context
          // parameter final  context
          // parameter final  d1
          // parameter final  d2
          // parameter final  context
          // parameter final  d0
          // parameter final  d1
          // parameter final  context
          // parameter final  arg0
         L0
          ALOAD 1
          GETFIELD org/nlogo/nvm/Context.agent : Lorg/nlogo/agent/Agent;
          ASTORE 2
          ALOAD 2
          INSTANCEOF org/nlogo/agent/Turtle
          IFEQ L1
          ALOAD 2
          CHECKCAST org/nlogo/agent/Turtle
          INVOKEVIRTUAL org/nlogo/agent/Turtle.getPatchHere ()Lorg/nlogo/agent/Patch;
          GOTO L2
         L1
         FRAME APPEND [org/nlogo/agent/Agent]
          ALOAD 2
          INSTANCEOF org/nlogo/agent/Patch
          IFEQ L3
          ALOAD 2
          CHECKCAST org/nlogo/agent/Patch
          GOTO L2
         L3
         FRAME SAME
          NEW java/lang/IllegalStateException
          DUP
          INVOKESPECIAL java/lang/IllegalStateException.<init> ()V
          ATHROW
         L2
         FRAME SAME1 org/nlogo/agent/Patch
          ICONST_0
          INVOKEVIRTUAL org/nlogo/agent/Patch.getPatchVariableDouble (I)D
         L4
          DCONST_1
         L5
          ALOAD 0
          GETFIELD org/nlogo/prim/_asm_proceduresetup_if_5.world : Lorg/nlogo/agent/World;
          INVOKEVIRTUAL org/nlogo/agent/World.minPycor ()I
          I2D
         L6
          DSTORE 4
          DSTORE 2
          DLOAD 2
          DLOAD 4
          DADD
         L7
          DSTORE 4
          DSTORE 2
          DLOAD 2
          DLOAD 4
          DCMPL
          IFNE L8
          ICONST_1
          GOTO L9
         L8
         FRAME FULL [org/nlogo/prim/_asm_proceduresetup_if_5 org/nlogo/nvm/Context D D] []
          ICONST_0
         L9
         FRAME SAME1 I
          ISTORE 2
          ALOAD 1
          ILOAD 2
          IFEQ L10
          BIPUSH 8
          GOTO L11
         L10
         FRAME FULL [org/nlogo/prim/_asm_proceduresetup_if_5 org/nlogo/nvm/Context I T D] [org/nlogo/nvm/Context]
          BIPUSH 10
         L11
         FRAME FULL [org/nlogo/prim/_asm_proceduresetup_if_5 org/nlogo/nvm/Context I T D] [org/nlogo/nvm/Context I]
          PUTFIELD org/nlogo/nvm/Context.ip : I
         L12
          RETURN
[8]_asm_proceduresetup_setpatchvariable_6 "set pcolor red" Object => void
      _constdouble:15.0 "red" => Double
          // parameter final  context
          // parameter final  context
          // parameter final  arg0
          TRYCATCHBLOCK L0 L1 L2 org/nlogo/api/AgentException
         L3
          ALOAD 0
          GETFIELD org/nlogo/prim/_asm_proceduresetup_setpatchvariable_6.kept2_value : Ljava/lang/Double;
         L4
          ASTORE 2
         L0
          ALOAD 1
          GETFIELD org/nlogo/nvm/Context.agent : Lorg/nlogo/agent/Agent;
          ICONST_2
          ALOAD 2
          INVOKEVIRTUAL org/nlogo/agent/Agent.setPatchVariable (ILjava/lang/Object;)V
         L1
          GOTO L5
         L2
         FRAME FULL [org/nlogo/prim/_asm_proceduresetup_setpatchvariable_6 org/nlogo/nvm/Context java/lang/Double] [org/nlogo/api/AgentException]
          ASTORE 3
          NEW org/nlogo/nvm/RuntimePrimitiveException
          DUP
          ALOAD 1
          ALOAD 0
          ALOAD 3
          INVOKEVIRTUAL org/nlogo/api/AgentException.getMessage ()Ljava/lang/String;
          INVOKESPECIAL org/nlogo/nvm/RuntimePrimitiveException.<init> (Lorg/nlogo/api/Context;Lorg/nlogo/nvm/Instruction;Ljava/lang/String;)V
          ATHROW
         L5
         FRAME SAME
          ALOAD 1
          BIPUSH 9
          PUTFIELD org/nlogo/nvm/Context.ip : I
         L6
          RETURN
[9]_asm_proceduresetup_setpatchvariable_7 "set fire 1" Object => void
      _constdouble:1.0 "1" => Double
          // parameter final  context
          // parameter final  context
          // parameter final  arg0
          TRYCATCHBLOCK L0 L1 L2 org/nlogo/api/AgentException
         L3
          ALOAD 0
          GETFIELD org/nlogo/prim/_asm_proceduresetup_setpatchvariable_7.kept2_value : Ljava/lang/Double;
         L4
          ASTORE 2
         L0
          ALOAD 1
          GETFIELD org/nlogo/nvm/Context.agent : Lorg/nlogo/agent/Agent;
          ICONST_5
          ALOAD 2
          INVOKEVIRTUAL org/nlogo/agent/Agent.setPatchVariable (ILjava/lang/Object;)V
         L1
          GOTO L5
         L2
         FRAME FULL [org/nlogo/prim/_asm_proceduresetup_setpatchvariable_7 org/nlogo/nvm/Context java/lang/Double] [org/nlogo/api/AgentException]
          ASTORE 3
          NEW org/nlogo/nvm/RuntimePrimitiveException
          DUP
          ALOAD 1
          ALOAD 0
          ALOAD 3
          INVOKEVIRTUAL org/nlogo/api/AgentException.getMessage ()Ljava/lang/String;
          INVOKESPECIAL org/nlogo/nvm/RuntimePrimitiveException.<init> (Lorg/nlogo/api/Context;Lorg/nlogo/nvm/Instruction;Ljava/lang/String;)V
          ATHROW
         L5
         FRAME SAME
          ALOAD 1
          BIPUSH 10
          PUTFIELD org/nlogo/nvm/Context.ip : I
         L6
          RETURN
[10]_asm_proceduresetup_done_8 => void
          // parameter final  context
         L0
          ALOAD 1
          ICONST_1
          PUTFIELD org/nlogo/nvm/Context.finished : Z
         L1
          RETURN
[11]_asm_proceduresetup_setobservervariable_9 "set initial-trees count patches with [ pcolor = green ]" Object => void
      _countwith "count patches with [ pcolor = green ]" AgentSet,Reporter => double
        _patches "patches" => AgentSet
        _asm_proceduresetup_equal_10 "pcolor = green" Object,double => boolean
          _patchvariable:PCOLOR "pcolor" => Object
          _constdouble:55.0 "green" => double
              // parameter final  context
              // parameter final  context
              // parameter final  context
              // parameter final  arg0
              // parameter final  d1
              TRYCATCHBLOCK L0 L1 L2 org/nlogo/api/AgentException
             L0
              ALOAD 1
              GETFIELD org/nlogo/nvm/Context.agent : Lorg/nlogo/agent/Agent;
              ICONST_2
              INVOKEVIRTUAL org/nlogo/agent/Agent.getPatchVariable (I)Ljava/lang/Object;
             L1
              GOTO L3
             L2
             FRAME SAME1 org/nlogo/api/AgentException
              ASTORE 2
              NEW org/nlogo/nvm/RuntimePrimitiveException
              DUP
              ALOAD 1
              ALOAD 0
              ALOAD 2
              INVOKEVIRTUAL org/nlogo/api/AgentException.getMessage ()Ljava/lang/String;
              INVOKESPECIAL org/nlogo/nvm/RuntimePrimitiveException.<init> (Lorg/nlogo/api/Context;Lorg/nlogo/nvm/Instruction;Ljava/lang/String;)V
              ATHROW
             L3
             FRAME SAME1 java/lang/Object
              LDC 55.0D
             L4
              DSTORE 3
              ASTORE 2
              ALOAD 2
              INSTANCEOF java/lang/Double
              IFEQ L5
              ALOAD 2
              CHECKCAST java/lang/Double
              ASTORE 5
              DLOAD 3
              ALOAD 5
              INVOKEVIRTUAL java/lang/Double.doubleValue ()D
              DCMPL
              IFNE L6
              ICONST_1
              GOTO L7
             L6
             FRAME APPEND [java/lang/Object D java/lang/Double]
              ICONST_0
              GOTO L7
             L5
             FRAME CHOP 1
              ICONST_0
             L7
             FRAME SAME1 I
              IFEQ L8
              GETSTATIC java/lang/Boolean.TRUE : Ljava/lang/Boolean;
              GOTO L9
             L8
             FRAME SAME
              GETSTATIC java/lang/Boolean.FALSE : Ljava/lang/Boolean;
             L9
             FRAME SAME1 java/lang/Boolean
              ARETURN
          // parameter final  context
          // parameter final  context
          // parameter final  sourceSet
          // parameter final  block
          // parameter final  context
          // parameter final  arg0
          TRYCATCHBLOCK L0 L1 L2 org/nlogo/api/AgentException
         L3
          ALOAD 0
          GETFIELD org/nlogo/prim/_asm_proceduresetup_setobservervariable_9.world : Lorg/nlogo/agent/World;
          INVOKEVIRTUAL org/nlogo/agent/World.patches ()Lorg/nlogo/agent/IndexedAgentSet;
         L4
          ALOAD 0
          GETFIELD org/nlogo/prim/_asm_proceduresetup_setobservervariable_9.keptinstr4 : Lorg/nlogo/nvm/Reporter;
          ASTORE 3
          ASTORE 2
          ALOAD 3
          ALOAD 2
          ALOAD 1
          INVOKEVIRTUAL org/nlogo/nvm/Reporter.checkAgentSetClass (Lorg/nlogo/agent/AgentSet;Lorg/nlogo/nvm/Context;)V
          NEW org/nlogo/nvm/Context
          DUP
          ALOAD 1
          ALOAD 2
          INVOKESPECIAL org/nlogo/nvm/Context.<init> (Lorg/nlogo/nvm/Context;Lorg/nlogo/agent/AgentSet;)V
          ASTORE 4
          ICONST_0
          ISTORE 5
          ALOAD 2
          INVOKEVIRTUAL org/nlogo/agent/AgentSet.iterator ()Lorg/nlogo/agent/AgentIterator;
          ASTORE 6
         L5
         FRAME FULL [org/nlogo/prim/_asm_proceduresetup_setobservervariable_9 org/nlogo/nvm/Context org/nlogo/agent/IndexedAgentSet org/nlogo/nvm/Reporter org/nlogo/nvm/Context I org/nlogo/agent/AgentIterator] []
          ALOAD 6
          INVOKEINTERFACE org/nlogo/agent/AgentIterator.hasNext ()Z (itf)
          IFEQ L6
          ALOAD 6
          INVOKEINTERFACE org/nlogo/agent/AgentIterator.next ()Lorg/nlogo/agent/Agent; (itf)
          ASTORE 7
          ALOAD 4
          ALOAD 7
          ALOAD 3
          INVOKEVIRTUAL org/nlogo/nvm/Context.evaluateReporter (Lorg/nlogo/agent/Agent;Lorg/nlogo/nvm/Reporter;)Ljava/lang/Object;
          ASTORE 8
          ALOAD 8
          INSTANCEOF java/lang/Boolean
          IFEQ L7
          ALOAD 8
          CHECKCAST java/lang/Boolean
          INVOKEVIRTUAL java/lang/Boolean.booleanValue ()Z
          IFEQ L5
          IINC 5 1
          GOTO L5
         L7
         FRAME APPEND [org/nlogo/agent/Agent java/lang/Object]
          NEW org/nlogo/nvm/RuntimePrimitiveException
          DUP
          ALOAD 1
          ALOAD 0
          GETSTATIC org/nlogo/core/I18N$.MODULE$ : Lorg/nlogo/core/I18N$;
          INVOKEVIRTUAL org/nlogo/core/I18N$.errors ()Lorg/nlogo/core/I18N$BundleKind;
          LDC "org.nlogo.prim.$common.expectedBooleanValue"
          GETSTATIC scala/runtime/ScalaRunTime$.MODULE$ : Lscala/runtime/ScalaRunTime$;
          ICONST_3
          ANEWARRAY java/lang/Object
          DUP
          ICONST_0
          LDC "WITH"
          AASTORE
          DUP
          ICONST_1
          GETSTATIC org/nlogo/api/Dump$.MODULE$ : Lorg/nlogo/api/Dump$;
          ALOAD 7
          INVOKEVIRTUAL org/nlogo/api/Dump$.logoObject (Ljava/lang/Object;)Ljava/lang/String;
          AASTORE
          DUP
          ICONST_2
          GETSTATIC org/nlogo/api/Dump$.MODULE$ : Lorg/nlogo/api/Dump$;
          ALOAD 8
          INVOKEVIRTUAL org/nlogo/api/Dump$.logoObject (Ljava/lang/Object;)Ljava/lang/String;
          AASTORE
          INVOKEVIRTUAL scala/runtime/ScalaRunTime$.wrapRefArray ([Ljava/lang/Object;)Lscala/collection/immutable/ArraySeq;
          INVOKEVIRTUAL org/nlogo/core/I18N$BundleKind.getN (Ljava/lang/String;Lscala/collection/immutable/Seq;)Ljava/lang/String;
          INVOKESPECIAL org/nlogo/nvm/RuntimePrimitiveException.<init> (Lorg/nlogo/api/Context;Lorg/nlogo/nvm/Instruction;Ljava/lang/String;)V
          ATHROW
         L6
         FRAME CHOP 2
          ILOAD 5
          I2D
         L8
          DSTORE 2
          NEW java/lang/Double
          DUP
          DLOAD 2
          INVOKESPECIAL java/lang/Double.<init> (D)V
          ASTORE 2
         L0
          ALOAD 0
          GETFIELD org/nlogo/prim/_asm_proceduresetup_setobservervariable_9.world : Lorg/nlogo/agent/World;
          INVOKEVIRTUAL org/nlogo/agent/World.observer ()Lorg/nlogo/agent/Observer;
          ICONST_1
          ALOAD 2
          INVOKEVIRTUAL org/nlogo/agent/Observer.setVariable (ILjava/lang/Object;)V
         L1
          GOTO L9
         L2
         FRAME FULL [org/nlogo/prim/_asm_proceduresetup_setobservervariable_9 org/nlogo/nvm/Context java/lang/Double T org/nlogo/nvm/Context I org/nlogo/agent/AgentIterator] [org/nlogo/api/AgentException]
          ASTORE 3
          NEW org/nlogo/nvm/RuntimePrimitiveException
          DUP
          ALOAD 1
          ALOAD 0
          ALOAD 3
          INVOKEVIRTUAL org/nlogo/api/AgentException.getMessage ()Ljava/lang/String;
          INVOKESPECIAL org/nlogo/nvm/RuntimePrimitiveException.<init> (Lorg/nlogo/api/Context;Lorg/nlogo/nvm/Instruction;Ljava/lang/String;)V
          ATHROW
         L9
         FRAME SAME
          ALOAD 1
          BIPUSH 12
          PUTFIELD org/nlogo/nvm/Context.ip : I
         L10
          RETURN
[12]_asm_proceduresetup_setobservervariable_11 "set burned-trees 0" Object => void
      _constdouble:0.0 "0" => Double
          // parameter final  context
          // parameter final  context
          // parameter final  arg0
          TRYCATCHBLOCK L0 L1 L2 org/nlogo/api/AgentException
         L3
          ALOAD 0
          GETFIELD org/nlogo/prim/_asm_proceduresetup_setobservervariable_11.kept2_value : Ljava/lang/Double;
         L4
          ASTORE 2
         L0
          ALOAD 0
          GETFIELD org/nlogo/prim/_asm_proceduresetup_setobservervariable_11.world : Lorg/nlogo/agent/World;
          INVOKEVIRTUAL org/nlogo/agent/World.observer ()Lorg/nlogo/agent/Observer;
          ICONST_2
          ALOAD 2
          INVOKEVIRTUAL org/nlogo/agent/Observer.setVariable (ILjava/lang/Object;)V
         L1
          GOTO L5
         L2
         FRAME FULL [org/nlogo/prim/_asm_proceduresetup_setobservervariable_11 org/nlogo/nvm/Context java/lang/Double] [org/nlogo/api/AgentException]
          ASTORE 3
          NEW org/nlogo/nvm/RuntimePrimitiveException
          DUP
          ALOAD 1
          ALOAD 0
          ALOAD 3
          INVOKEVIRTUAL org/nlogo/api/AgentException.getMessage ()Ljava/lang/String;
          INVOKESPECIAL org/nlogo/nvm/RuntimePrimitiveException.<init> (Lorg/nlogo/api/Context;Lorg/nlogo/nvm/Instruction;Ljava/lang/String;)V
          ATHROW
         L5
         FRAME SAME
          ALOAD 1
          BIPUSH 13
          PUTFIELD org/nlogo/nvm/Context.ip : I
         L6
          RETURN
[13]_asm_proceduresetup_return_12 => void
          // parameter final  context
         L0
          ALOAD 1
          INVOKEVIRTUAL org/nlogo/nvm/Context.returnFromProcedure ()V
          ALOAD 1
          ICONST_0
          PUTFIELD org/nlogo/nvm/Context.stopping : Z
         L1
          RETURN

procedure GO:[]{O---}:
[0]_asm_procedurego_if_0 "if count patches with [ burning? ] = 0 [ stop ]" boolean => void
      _not "count patches with [ burning? ] = 0" boolean => boolean
        _anywith "count patches with [ burning? ] = 0" AgentSet,Reporter => boolean
          _patches "patches" => AgentSet
          _asm_procedurego_callreport_1 "burning?"
               L0
                NEW org/nlogo/nvm/Activation
                DUP
                ALOAD 0
                GETFIELD org/nlogo/prim/_asm_procedurego_callreport_1.kept1_procedure : Lorg/nlogo/nvm/Procedure;
                ALOAD 1
                GETFIELD org/nlogo/nvm/Context.activation : Lorg/nlogo/nvm/Activation;
                SIPUSH 0
                ANEWARRAY java/lang/Object
                ICONST_0
                INVOKESPECIAL org/nlogo/nvm/Activation.<init> (Lorg/nlogo/nvm/Procedure;Lorg/nlogo/nvm/Activation;[Ljava/lang/Object;I)V
                ALOAD 1
                SWAP
                INVOKEVIRTUAL org/nlogo/nvm/Context.callReporterProcedure (Lorg/nlogo/nvm/Activation;)Ljava/lang/Object;
                DUP
                IFNONNULL L1
                NEW org/nlogo/nvm/RuntimePrimitiveException
                DUP
                ALOAD 1
                ALOAD 0
                LDC "the BURNING? procedure failed to report a result"
                INVOKESPECIAL org/nlogo/nvm/RuntimePrimitiveException.<init> (Lorg/nlogo/api/Context;Lorg/nlogo/nvm/Instruction;Ljava/lang/String;)V
                ATHROW
               L1
               FRAME SAME1 java/lang/Object
                ARETURN
          // parameter final  context
          // parameter final  context
          // parameter final  sourceSet
          // parameter final  arg1
          // parameter final  context
          // parameter final  arg0
          // parameter final  context
          // parameter final  arg0
         L0
          ALOAD 0
          GETFIELD org/nlogo/prim/_asm_procedurego_if_0.world : Lorg/nlogo/agent/World;
          INVOKEVIRTUAL org/nlogo/agent/World.patches ()Lorg/nlogo/agent/IndexedAgentSet;
         L1
          ALOAD 0
          GETFIELD org/nlogo/prim/_asm_procedurego_if_0.keptinstr5 : Lorg/nlogo/nvm/Reporter;
          ASTORE 3
          ASTORE 2
          NEW org/nlogo/nvm/Context
          DUP
          ALOAD 1
          ALOAD 2
          INVOKESPECIAL org/nlogo/nvm/Context.<init> (Lorg/nlogo/nvm/Context;Lorg/nlogo/agent/AgentSet;)V
          ASTORE 4
          ALOAD 3
          ALOAD 2
          ALOAD 1
          INVOKEVIRTUAL org/nlogo/nvm/Reporter.checkAgentSetClass (Lorg/nlogo/agent/AgentSet;Lorg/nlogo/nvm/Context;)V
          ALOAD 2
          INVOKEVIRTUAL org/nlogo/agent/AgentSet.iterator ()Lorg/nlogo/agent/AgentIterator;
          ASTORE 5
         L2
         FRAME FULL [org/nlogo/prim/_asm_procedurego_if_0 org/nlogo/nvm/Context org/nlogo/agent/IndexedAgentSet org/nlogo/nvm/Reporter org/nlogo/nvm/Context org/nlogo/agent/AgentIterator] []
          ALOAD 5
          INVOKEINTERFACE org/nlogo/agent/AgentIterator.hasNext ()Z (itf)
          IFEQ L3
          ALOAD 5
          INVOKEINTERFACE org/nlogo/agent/AgentIterator.next ()Lorg/nlogo/agent/Agent; (itf)
          ASTORE 6
          ALOAD 4
          ALOAD 6
          ALOAD 3
          INVOKEVIRTUAL org/nlogo/nvm/Context.evaluateReporter (Lorg/nlogo/agent/Agent;Lorg/nlogo/nvm/Reporter;)Ljava/lang/Object;
          ASTORE 7
          ALOAD 7
          INSTANCEOF java/lang/Boolean
          IFEQ L4
          ALOAD 7
          CHECKCAST java/lang/Boolean
          ASTORE 8
          GETSTATIC scala/Predef$.MODULE$ : Lscala/Predef$;
          ALOAD 8
          INVOKEVIRTUAL scala/Predef$.Boolean2boolean (Ljava/lang/Boolean;)Z
          IFEQ L2
          ICONST_1
          GOTO L5
         L4
         FRAME APPEND [org/nlogo/agent/Agent java/lang/Object]
          NEW org/nlogo/nvm/RuntimePrimitiveException
          DUP
          ALOAD 1
          ALOAD 0
          GETSTATIC org/nlogo/core/I18N$.MODULE$ : Lorg/nlogo/core/I18N$;
          INVOKEVIRTUAL org/nlogo/core/I18N$.errors ()Lorg/nlogo/core/I18N$BundleKind;
          LDC "org.nlogo.prim.$common.withExpectedBooleanValue"
          GETSTATIC scala/runtime/ScalaRunTime$.MODULE$ : Lscala/runtime/ScalaRunTime$;
          ICONST_2
          ANEWARRAY java/lang/Object
          DUP
          ICONST_0
          GETSTATIC org/nlogo/api/Dump$.MODULE$ : Lorg/nlogo/api/Dump$;
          ALOAD 6
          INVOKEVIRTUAL org/nlogo/api/Dump$.logoObject (Ljava/lang/Object;)Ljava/lang/String;
          AASTORE
          DUP
          ICONST_1
          GETSTATIC org/nlogo/api/Dump$.MODULE$ : Lorg/nlogo/api/Dump$;
          ALOAD 7
          INVOKEVIRTUAL org/nlogo/api/Dump$.logoObject (Ljava/lang/Object;)Ljava/lang/String;
          AASTORE
          INVOKEVIRTUAL scala/runtime/ScalaRunTime$.wrapRefArray ([Ljava/lang/Object;)Lscala/collection/immutable/ArraySeq;
          INVOKEVIRTUAL org/nlogo/core/I18N$BundleKind.getN (Ljava/lang/String;Lscala/collection/immutable/Seq;)Ljava/lang/String;
          INVOKESPECIAL org/nlogo/nvm/RuntimePrimitiveException.<init> (Lorg/nlogo/api/Context;Lorg/nlogo/nvm/Instruction;Ljava/lang/String;)V
          ATHROW
         L3
         FRAME CHOP 2
          ICONST_0
         L5
         FRAME SAME1 I
          ISTORE 2
          ILOAD 2
          IFNE L6
          ICONST_1
          GOTO L7
         L6
         FRAME FULL [org/nlogo/prim/_asm_procedurego_if_0 org/nlogo/nvm/Context I org/nlogo/nvm/Reporter org/nlogo/nvm/Context org/nlogo/agent/AgentIterator] []
          ICONST_0
         L7
         FRAME SAME1 I
          ISTORE 2
          ALOAD 1
          ILOAD 2
          IFEQ L8
          ICONST_1
          GOTO L9
         L8
         FRAME SAME1 org/nlogo/nvm/Context
          ICONST_2
         L9
         FRAME FULL [org/nlogo/prim/_asm_procedurego_if_0 org/nlogo/nvm/Context I org/nlogo/nvm/Reporter org/nlogo/nvm/Context org/nlogo/agent/AgentIterator] [org/nlogo/nvm/Context I]
          PUTFIELD org/nlogo/nvm/Context.ip : I
         L10
          RETURN
[1]_asm_procedurego_stop_2 "stop" => void
         L0
          ALOAD 1
          INVOKEVIRTUAL org/nlogo/nvm/Context.atTopActivation ()Z
          IFNE L1
          ALOAD 1
          ICONST_1
          PUTFIELD org/nlogo/nvm/Context.finished : Z
          GOTO L2
         L1
         FRAME SAME
          ALOAD 1
          GETFIELD org/nlogo/nvm/Context.activation : Lorg/nlogo/nvm/Activation;
          INVOKEVIRTUAL org/nlogo/nvm/Activation.nonLambdaActivation ()Lorg/nlogo/nvm/Activation;
          INVOKEVIRTUAL org/nlogo/nvm/Activation.procedure ()Lorg/nlogo/core/FrontEndProcedure;
          INVOKEINTERFACE org/nlogo/core/FrontEndProcedure.isReporter ()Z (itf)
          IFEQ L2
          NEW org/nlogo/nvm/RuntimePrimitiveException
          DUP
          ALOAD 1
          ALOAD 0
          INVOKESTATIC org/nlogo/core/I18N.errorsJ ()Lorg/nlogo/core/I18NJava;
          LDC "org.nlogo.prim.etc._stop.notAllowedInsideToReport"
          ICONST_1
          ANEWARRAY java/lang/Object
          DUP
          ICONST_0
          LDC "STOP"
          AASTORE
          INVOKEINTERFACE org/nlogo/core/I18NJava.getN (Ljava/lang/String;[Ljava/lang/Object;)Ljava/lang/String; (itf)
          INVOKESPECIAL org/nlogo/nvm/RuntimePrimitiveException.<init> (Lorg/nlogo/api/Context;Lorg/nlogo/nvm/Instruction;Ljava/lang/String;)V
          ATHROW
         L2
         FRAME SAME
          ALOAD 1
          INVOKEVIRTUAL org/nlogo/nvm/Context.stop ()V
         L3
          RETURN
[2]_asm_procedurego_ask_3 "ask patches [ if pcolor = green [ set counts sum [ fire ] of neighbors4 ] ]" AgentSet => void
      _patches "patches" => AgentSet
          // parameter final  context
          // parameter final  context
          // parameter final  agents
         L0
          ALOAD 0
          GETFIELD org/nlogo/prim/_asm_procedurego_ask_3.world : Lorg/nlogo/agent/World;
          INVOKEVIRTUAL org/nlogo/agent/World.patches ()Lorg/nlogo/agent/IndexedAgentSet;
         L1
          ASTORE 2
          ALOAD 1
          GETFIELD org/nlogo/nvm/Context.agent : Lorg/nlogo/agent/Agent;
          INSTANCEOF org/nlogo/agent/Observer
          IFNE L2
          ALOAD 2
          ALOAD 0
          GETFIELD org/nlogo/prim/_asm_procedurego_ask_3.world : Lorg/nlogo/agent/World;
          INVOKEVIRTUAL org/nlogo/agent/World.turtles ()Lorg/nlogo/agent/TreeAgentSet;
          IF_ACMPNE L3
          NEW org/nlogo/nvm/RuntimePrimitiveException
          DUP
          ALOAD 1
          ALOAD 0
          GETSTATIC org/nlogo/core/I18N$.MODULE$ : Lorg/nlogo/core/I18N$;
          INVOKEVIRTUAL org/nlogo/core/I18N$.errors ()Lorg/nlogo/core/I18N$BundleKind;
          LDC "org.nlogo.prim.$common.onlyObserverCanAskAllTurtles"
          INVOKEVIRTUAL org/nlogo/core/I18N$BundleKind.get (Ljava/lang/String;)Ljava/lang/String;
          INVOKESPECIAL org/nlogo/nvm/RuntimePrimitiveException.<init> (Lorg/nlogo/api/Context;Lorg/nlogo/nvm/Instruction;Ljava/lang/String;)V
          ATHROW
         L3
         FRAME APPEND [org/nlogo/agent/IndexedAgentSet]
          ALOAD 2
          ALOAD 0
          GETFIELD org/nlogo/prim/_asm_procedurego_ask_3.world : Lorg/nlogo/agent/World;
          INVOKEVIRTUAL org/nlogo/agent/World.patches ()Lorg/nlogo/agent/IndexedAgentSet;
          IF_ACMPNE L2
          NEW org/nlogo/nvm/RuntimePrimitiveException
          DUP
          ALOAD 1
          ALOAD 0
          GETSTATIC org/nlogo/core/I18N$.MODULE$ : Lorg/nlogo/core/I18N$;
          INVOKEVIRTUAL org/nlogo/core/I18N$.errors ()Lorg/nlogo/core/I18N$BundleKind;
          LDC "org.nlogo.prim.$common.onlyObserverCanAskAllPatches"
          INVOKEVIRTUAL org/nlogo/core/I18N$BundleKind.get (Ljava/lang/String;)Ljava/lang/String;
          INVOKESPECIAL org/nlogo/nvm/RuntimePrimitiveException.<init> (Lorg/nlogo/api/Context;Lorg/nlogo/nvm/Instruction;Ljava/lang/String;)V
          ATHROW
         L2
         FRAME SAME
          ALOAD 1
          ALOAD 2
          ICONST_3
          INVOKEVIRTUAL org/nlogo/nvm/Context.runExclusiveJob (Lorg/nlogo/agent/AgentSet;I)V
          ALOAD 1
          BIPUSH 6
          PUTFIELD org/nlogo/nvm/Context.ip : I
         L4
          RETURN
[3]_asm_procedurego_if_4 "if pcolor = green [ set counts sum [ fire ] of neighbors4 ]" boolean => void
      _equal "pcolor = green" Object,double => boolean
        _patchvariable:PCOLOR "pcolor" => Object
        _constdouble:55.0 "green" => double
          // parameter final  context
          // parameter final  context
          // parameter final  context
          // parameter final  arg0
          // parameter final  d1
          // parameter final  context
          // parameter final  arg0
          TRYCATCHBLOCK L0 L1 L2 org/nlogo/api/AgentException
         L0
          ALOAD 1
          GETFIELD org/nlogo/nvm/Context.agent : Lorg/nlogo/agent/Agent;
          ICONST_2
          INVOKEVIRTUAL org/nlogo/agent/Agent.getPatchVariable (I)Ljava/lang/Object;
         L1
          GOTO L3
         L2
         FRAME SAME1 org/nlogo/api/AgentException
          ASTORE 2
          NEW org/nlogo/nvm/RuntimePrimitiveException
          DUP
          ALOAD 1
          ALOAD 0
          ALOAD 2
          INVOKEVIRTUAL org/nlogo/api/AgentException.getMessage ()Ljava/lang/String;
          INVOKESPECIAL org/nlogo/nvm/RuntimePrimitiveException.<init> (Lorg/nlogo/api/Context;Lorg/nlogo/nvm/Instruction;Ljava/lang/String;)V
          ATHROW
         L3
         FRAME SAME1 java/lang/Object
          LDC 55.0D
         L4
          DSTORE 3
          ASTORE 2
          ALOAD 2
          INSTANCEOF java/lang/Double
          IFEQ L5
          ALOAD 2
          CHECKCAST java/lang/Double
          ASTORE 5
          DLOAD 3
          ALOAD 5
          INVOKEVIRTUAL java/lang/Double.doubleValue ()D
          DCMPL
          IFNE L6
          ICONST_1
          GOTO L7
         L6
         FRAME APPEND [java/lang/Object D java/lang/Double]
          ICONST_0
          GOTO L7
         L5
         FRAME CHOP 1
          ICONST_0
         L7
         FRAME SAME1 I
          ISTORE 2
          ALOAD 1
          ILOAD 2
          IFEQ L8
          ICONST_4
          GOTO L9
         L8
         FRAME FULL [org/nlogo/prim/_asm_procedurego_if_4 org/nlogo/nvm/Context I D] [org/nlogo/nvm/Context]
          ICONST_5
         L9
         FRAME FULL [org/nlogo/prim/_asm_procedurego_if_4 org/nlogo/nvm/Context I D] [org/nlogo/nvm/Context I]
          PUTFIELD org/nlogo/nvm/Context.ip : I
         L10
          RETURN
[4]_asm_procedurego_setpatchvariable_5 "set counts sum [ fire ] of neighbors4" Object => void
      _nsum4:FIRE "sum [ fire ] of neighbors4" => double
          // parameter final  context
          // parameter final  context
          // parameter final  arg0
          TRYCATCHBLOCK L0 L1 L2 org/nlogo/api/AgentException
         L3
          ALOAD 1
          GETFIELD org/nlogo/nvm/Context.agent : Lorg/nlogo/agent/Agent;
          ASTORE 3
          ALOAD 3
          INSTANCEOF org/nlogo/agent/Turtle
          IFEQ L4
          ALOAD 3
          CHECKCAST org/nlogo/agent/Turtle
          INVOKEVIRTUAL org/nlogo/agent/Turtle.getPatchHere ()Lorg/nlogo/agent/Patch;
          GOTO L5
         L4
         FRAME APPEND [T org/nlogo/agent/Agent]
          ALOAD 3
          INSTANCEOF org/nlogo/agent/Patch
          IFEQ L6
          ALOAD 3
          CHECKCAST org/nlogo/agent/Patch
          GOTO L5
         L6
         FRAME SAME
          NEW java/lang/IllegalStateException
          DUP
          INVOKESPECIAL java/lang/IllegalStateException.<init> ()V
          ATHROW
         L5
         FRAME SAME1 org/nlogo/agent/Patch
          ASTORE 2
          DCONST_0
          DSTORE 4
          ALOAD 2
          INVOKEVIRTUAL org/nlogo/agent/Patch.getNeighbors4 ()Lorg/nlogo/agent/IndexedAgentSet;
          INVOKEVIRTUAL org/nlogo/agent/IndexedAgentSet.iterator ()Lorg/nlogo/agent/AgentIterator;
          ASTORE 6
         L7
         FRAME FULL [org/nlogo/prim/_asm_procedurego_setpatchvariable_5 org/nlogo/nvm/Context org/nlogo/agent/Patch org/nlogo/agent/Agent D org/nlogo/agent/AgentIterator] []
          ALOAD 6
          INVOKEINTERFACE org/nlogo/agent/AgentIterator.hasNext ()Z (itf)
          IFEQ L8
          ALOAD 6
          INVOKEINTERFACE org/nlogo/agent/AgentIterator.next ()Lorg/nlogo/agent/Agent; (itf)
          CHECKCAST org/nlogo/agent/Patch
          ICONST_5
          INVOKEVIRTUAL org/nlogo/agent/Patch.getPatchVariable (I)Ljava/lang/Object;
          ASTORE 7
          ALOAD 7
          INSTANCEOF java/lang/Double
          IFEQ L9
          ALOAD 7
          CHECKCAST java/lang/Double
          ASTORE 8
          DLOAD 4
          ALOAD 8
          INVOKEVIRTUAL java/lang/Double.doubleValue ()D
          DADD
          DSTORE 4
          GOTO L7
         L9
         FRAME APPEND [java/lang/Object]
          NEW org/nlogo/nvm/RuntimePrimitiveException
          DUP
          ALOAD 1
          ALOAD 0
          GETSTATIC org/nlogo/core/I18N$.MODULE$ : Lorg/nlogo/core/I18N$;
          INVOKEVIRTUAL org/nlogo/core/I18N$.errors ()Lorg/nlogo/core/I18N$BundleKind;
          LDC "org.nlogo.prim.$common.noSumOfListWithNonNumbers"
          GETSTATIC scala/runtime/ScalaRunTime$.MODULE$ : Lscala/runtime/ScalaRunTime$;
          ICONST_2
          ANEWARRAY java/lang/Object
          DUP
          ICONST_0
          GETSTATIC org/nlogo/api/Dump$.MODULE$ : Lorg/nlogo/api/Dump$;
          ALOAD 7
          INVOKEVIRTUAL org/nlogo/api/Dump$.logoObject (Ljava/lang/Object;)Ljava/lang/String;
          INVOKEVIRTUAL java/lang/String.toString ()Ljava/lang/String;
          AASTORE
          DUP
          ICONST_1
          GETSTATIC org/nlogo/api/TypeNames$.MODULE$ : Lorg/nlogo/api/TypeNames$;
          ALOAD 7
          INVOKEVIRTUAL org/nlogo/api/TypeNames$.name (Ljava/lang/Object;)Ljava/lang/String;
          AASTORE
          INVOKEVIRTUAL scala/runtime/ScalaRunTime$.wrapRefArray ([Ljava/lang/Object;)Lscala/collection/immutable/ArraySeq;
          INVOKEVIRTUAL org/nlogo/core/I18N$BundleKind.getN (Ljava/lang/String;Lscala/collection/immutable/Seq;)Ljava/lang/String;
          INVOKESPECIAL org/nlogo/nvm/RuntimePrimitiveException.<init> (Lorg/nlogo/api/Context;Lorg/nlogo/nvm/Instruction;Ljava/lang/String;)V
          ATHROW
         L8
         FRAME CHOP 1
          ALOAD 0
          DLOAD 4
          ALOAD 1
          INVOKEVIRTUAL org/nlogo/prim/_asm_procedurego_setpatchvariable_5.validDouble (DLorg/nlogo/nvm/Context;)D
         L10
          DSTORE 2
          NEW java/lang/Double
          DUP
          DLOAD 2
          INVOKESPECIAL java/lang/Double.<init> (D)V
          ASTORE 2
         L0
          ALOAD 1
          GETFIELD org/nlogo/nvm/Context.agent : Lorg/nlogo/agent/Agent;
          BIPUSH 6
          ALOAD 2
          INVOKEVIRTUAL org/nlogo/agent/Agent.setPatchVariable (ILjava/lang/Object;)V
         L1
          GOTO L11
         L2
         FRAME FULL [org/nlogo/prim/_asm_procedurego_setpatchvariable_5 org/nlogo/nvm/Context java/lang/Double T D org/nlogo/agent/AgentIterator] [org/nlogo/api/AgentException]
          ASTORE 3
          NEW org/nlogo/nvm/RuntimePrimitiveException
          DUP
          ALOAD 1
          ALOAD 0
          ALOAD 3
          INVOKEVIRTUAL org/nlogo/api/AgentException.getMessage ()Ljava/lang/String;
          INVOKESPECIAL org/nlogo/nvm/RuntimePrimitiveException.<init> (Lorg/nlogo/api/Context;Lorg/nlogo/nvm/Instruction;Ljava/lang/String;)V
          ATHROW
         L11
         FRAME SAME
          ALOAD 1
          ICONST_5
          PUTFIELD org/nlogo/nvm/Context.ip : I
         L12
          RETURN
[5]_asm_procedurego_done_6 => void
          // parameter final  context
         L0
          ALOAD 1
          ICONST_1
          PUTFIELD org/nlogo/nvm/Context.finished : Z
         L1
          RETURN
[6]_asm_procedurego_ask_7 "ask patches [ ifelse pcolor = green [ if counts > 0 set fire 1 set pcolor red [ set burned-trees burned-trees + 1 ] ] [ if burning? [ set pcolor pcolor - 0.3 ] ] ]" AgentSet => void
      _patches "patches" => AgentSet
          // parameter final  context
          // parameter final  context
          // parameter final  agents
         L0
          ALOAD 0
          GETFIELD org/nlogo/prim/_asm_procedurego_ask_7.world : Lorg/nlogo/agent/World;
          INVOKEVIRTUAL org/nlogo/agent/World.patches ()Lorg/nlogo/agent/IndexedAgentSet;
         L1
          ASTORE 2
          ALOAD 1
          GETFIELD org/nlogo/nvm/Context.agent : Lorg/nlogo/agent/Agent;
          INSTANCEOF org/nlogo/agent/Observer
          IFNE L2
          ALOAD 2
          ALOAD 0
          GETFIELD org/nlogo/prim/_asm_procedurego_ask_7.world : Lorg/nlogo/agent/World;
          INVOKEVIRTUAL org/nlogo/agent/World.turtles ()Lorg/nlogo/agent/TreeAgentSet;
          IF_ACMPNE L3
          NEW org/nlogo/nvm/RuntimePrimitiveException
          DUP
          ALOAD 1
          ALOAD 0
          GETSTATIC org/nlogo/core/I18N$.MODULE$ : Lorg/nlogo/core/I18N$;
          INVOKEVIRTUAL org/nlogo/core/I18N$.errors ()Lorg/nlogo/core/I18N$BundleKind;
          LDC "org.nlogo.prim.$common.onlyObserverCanAskAllTurtles"
          INVOKEVIRTUAL org/nlogo/core/I18N$BundleKind.get (Ljava/lang/String;)Ljava/lang/String;
          INVOKESPECIAL org/nlogo/nvm/RuntimePrimitiveException.<init> (Lorg/nlogo/api/Context;Lorg/nlogo/nvm/Instruction;Ljava/lang/String;)V
          ATHROW
         L3
         FRAME APPEND [org/nlogo/agent/IndexedAgentSet]
          ALOAD 2
          ALOAD 0
          GETFIELD org/nlogo/prim/_asm_procedurego_ask_7.world : Lorg/nlogo/agent/World;
          INVOKEVIRTUAL org/nlogo/agent/World.patches ()Lorg/nlogo/agent/IndexedAgentSet;
          IF_ACMPNE L2
          NEW org/nlogo/nvm/RuntimePrimitiveException
          DUP
          ALOAD 1
          ALOAD 0
          GETSTATIC org/nlogo/core/I18N$.MODULE$ : Lorg/nlogo/core/I18N$;
          INVOKEVIRTUAL org/nlogo/core/I18N$.errors ()Lorg/nlogo/core/I18N$BundleKind;
          LDC "org.nlogo.prim.$common.onlyObserverCanAskAllPatches"
          INVOKEVIRTUAL org/nlogo/core/I18N$BundleKind.get (Ljava/lang/String;)Ljava/lang/String;
          INVOKESPECIAL org/nlogo/nvm/RuntimePrimitiveException.<init> (Lorg/nlogo/api/Context;Lorg/nlogo/nvm/Instruction;Ljava/lang/String;)V
          ATHROW
         L2
         FRAME SAME
          ALOAD 1
          ALOAD 2
          BIPUSH 7
          INVOKEVIRTUAL org/nlogo/nvm/Context.runExclusiveJob (Lorg/nlogo/agent/AgentSet;I)V
          ALOAD 1
          BIPUSH 16
          PUTFIELD org/nlogo/nvm/Context.ip : I
         L4
          RETURN
[7]_asm_procedurego_ifelse_8 "ifelse pcolor = green [ if counts > 0 set fire 1 set pcolor red [ set burned-trees burned-trees + 1 ] ] [ if burning? [ set pcolor pcolor - 0.3 ] ]" boolean => void
      _equal "pcolor = green" Object,double => boolean
        _patchvariable:PCOLOR "pcolor" => Object
        _constdouble:55.0 "green" => double
          // parameter final  context
          // parameter final  context
          // parameter final  context
          // parameter final  arg0
          // parameter final  d1
          // parameter final  context
          // parameter final  cond
          TRYCATCHBLOCK L0 L1 L2 org/nlogo/api/AgentException
         L0
          ALOAD 1
          GETFIELD org/nlogo/nvm/Context.agent : Lorg/nlogo/agent/Agent;
          ICONST_2
          INVOKEVIRTUAL org/nlogo/agent/Agent.getPatchVariable (I)Ljava/lang/Object;
         L1
          GOTO L3
         L2
         FRAME SAME1 org/nlogo/api/AgentException
          ASTORE 2
          NEW org/nlogo/nvm/RuntimePrimitiveException
          DUP
          ALOAD 1
          ALOAD 0
          ALOAD 2
          INVOKEVIRTUAL org/nlogo/api/AgentException.getMessage ()Ljava/lang/String;
          INVOKESPECIAL org/nlogo/nvm/RuntimePrimitiveException.<init> (Lorg/nlogo/api/Context;Lorg/nlogo/nvm/Instruction;Ljava/lang/String;)V
          ATHROW
         L3
         FRAME SAME1 java/lang/Object
          LDC 55.0D
         L4
          DSTORE 3
          ASTORE 2
          ALOAD 2
          INSTANCEOF java/lang/Double
          IFEQ L5
          ALOAD 2
          CHECKCAST java/lang/Double
          ASTORE 5
          DLOAD 3
          ALOAD 5
          INVOKEVIRTUAL java/lang/Double.doubleValue ()D
          DCMPL
          IFNE L6
          ICONST_1
          GOTO L7
         L6
         FRAME APPEND [java/lang/Object D java/lang/Double]
          ICONST_0
          GOTO L7
         L5
         FRAME CHOP 1
          ICONST_0
         L7
         FRAME SAME1 I
          ISTORE 2
          ALOAD 1
          ILOAD 2
          IFEQ L8
          BIPUSH 8
          GOTO L9
         L8
         FRAME FULL [org/nlogo/prim/_asm_procedurego_ifelse_8 org/nlogo/nvm/Context I D] [org/nlogo/nvm/Context]
          BIPUSH 13
         L9
         FRAME FULL [org/nlogo/prim/_asm_procedurego_ifelse_8 org/nlogo/nvm/Context I D] [org/nlogo/nvm/Context I]
          PUTFIELD org/nlogo/nvm/Context.ip : I
         L10
          RETURN
[8]_asm_procedurego_if_9 "if counts > 0 set fire 1 set pcolor red [ set burned-trees burned-trees + 1 ]" boolean => void
      _greaterthan "counts > 0" Object,double => boolean
        _patchvariable:COUNTS "counts" => Object
        _constdouble:0.0 "0" => double
          // parameter final  context
          // parameter final  context
          // parameter final  context
          // parameter final  arg0
          // parameter final  arg1
          // parameter final  context
          // parameter final  arg0
          TRYCATCHBLOCK L0 L1 L2 org/nlogo/api/AgentException
         L0
          ALOAD 1
          GETFIELD org/nlogo/nvm/Context.agent : Lorg/nlogo/agent/Agent;
          BIPUSH 6
          INVOKEVIRTUAL org/nlogo/agent/Agent.getPatchVariable (I)Ljava/lang/Object;
         L1
          GOTO L3
         L2
         FRAME SAME1 org/nlogo/api/AgentException
          ASTORE 2
          NEW org/nlogo/nvm/RuntimePrimitiveException
          DUP
          ALOAD 1
          ALOAD 0
          ALOAD 2
          INVOKEVIRTUAL org/nlogo/api/AgentException.getMessage ()Ljava/lang/String;
          INVOKESPECIAL org/nlogo/nvm/RuntimePrimitiveException.<init> (Lorg/nlogo/api/Context;Lorg/nlogo/nvm/Instruction;Ljava/lang/String;)V
          ATHROW
         L3
         FRAME SAME1 java/lang/Object
          DCONST_0
         L4
          DSTORE 3
          ASTORE 2
          ALOAD 2
          INSTANCEOF java/lang/Double
          IFEQ L5
          ALOAD 2
          CHECKCAST java/lang/Double
          INVOKEVIRTUAL java/lang/Double.doubleValue ()D
          DLOAD 3
          DCMPL
          IFLE L6
          ICONST_1
          GOTO L7
         L6
         FRAME APPEND [java/lang/Object D]
          ICONST_0
          GOTO L7
         L5
         FRAME SAME
          NEW org/nlogo/nvm/RuntimePrimitiveException
          DUP
          ALOAD 1
          ALOAD 0
          GETSTATIC org/nlogo/core/I18N$.MODULE$ : Lorg/nlogo/core/I18N$;
          INVOKEVIRTUAL org/nlogo/core/I18N$.errors ()Lorg/nlogo/core/I18N$BundleKind;
          LDC "org.nlogo.prim._greaterthan.cannotCompareParameters"
          GETSTATIC scala/runtime/ScalaRunTime$.MODULE$ : Lscala/runtime/ScalaRunTime$;
          ICONST_2
          ANEWARRAY java/lang/Object
          DUP
          ICONST_0
          GETSTATIC org/nlogo/api/TypeNames$.MODULE$ : Lorg/nlogo/api/TypeNames$;
          ALOAD 2
          INVOKEVIRTUAL org/nlogo/api/TypeNames$.aName (Ljava/lang/Object;)Ljava/lang/String;
          AASTORE
          DUP
          ICONST_1
          GETSTATIC org/nlogo/api/TypeNames$.MODULE$ : Lorg/nlogo/api/TypeNames$;
          DLOAD 3
          INVOKESTATIC scala/runtime/BoxesRunTime.boxToDouble (D)Ljava/lang/Double;
          INVOKEVIRTUAL org/nlogo/api/TypeNames$.aName (Ljava/lang/Object;)Ljava/lang/String;
          AASTORE
          INVOKEVIRTUAL scala/runtime/ScalaRunTime$.wrapRefArray ([Ljava/lang/Object;)Lscala/collection/immutable/ArraySeq;
          INVOKEVIRTUAL org/nlogo/core/I18N$BundleKind.getN (Ljava/lang/String;Lscala/collection/immutable/Seq;)Ljava/lang/String;
          INVOKESPECIAL org/nlogo/nvm/RuntimePrimitiveException.<init> (Lorg/nlogo/api/Context;Lorg/nlogo/nvm/Instruction;Ljava/lang/String;)V
          ATHROW
         L7
         FRAME SAME1 I
          ISTORE 2
          ALOAD 1
          ILOAD 2
          IFEQ L8
          BIPUSH 9
          GOTO L9
         L8
         FRAME FULL [org/nlogo/prim/_asm_procedurego_if_9 org/nlogo/nvm/Context I D] [org/nlogo/nvm/Context]
          BIPUSH 12
         L9
         FRAME FULL [org/nlogo/prim/_asm_procedurego_if_9 org/nlogo/nvm/Context I D] [org/nlogo/nvm/Context I]
          PUTFIELD org/nlogo/nvm/Context.ip : I
         L10
          RETURN
[9]_asm_procedurego_setpatchvariable_10 "set fire 1" Object => void
      _constdouble:1.0 "1" => Double
          // parameter final  context
          // parameter final  context
          // parameter final  arg0
          TRYCATCHBLOCK L0 L1 L2 org/nlogo/api/AgentException
         L3
          ALOAD 0
          GETFIELD org/nlogo/prim/_asm_procedurego_setpatchvariable_10.kept2_value : Ljava/lang/Double;
         L4
          ASTORE 2
         L0
          ALOAD 1
          GETFIELD org/nlogo/nvm/Context.agent : Lorg/nlogo/agent/Agent;
          ICONST_5
          ALOAD 2
          INVOKEVIRTUAL org/nlogo/agent/Agent.setPatchVariable (ILjava/lang/Object;)V
         L1
          GOTO L5
         L2
         FRAME FULL [org/nlogo/prim/_asm_procedurego_setpatchvariable_10 org/nlogo/nvm/Context java/lang/Double] [org/nlogo/api/AgentException]
          ASTORE 3
          NEW org/nlogo/nvm/RuntimePrimitiveException
          DUP
          ALOAD 1
          ALOAD 0
          ALOAD 3
          INVOKEVIRTUAL org/nlogo/api/AgentException.getMessage ()Ljava/lang/String;
          INVOKESPECIAL org/nlogo/nvm/RuntimePrimitiveException.<init> (Lorg/nlogo/api/Context;Lorg/nlogo/nvm/Instruction;Ljava/lang/String;)V
          ATHROW
         L5
         FRAME SAME
          ALOAD 1
          BIPUSH 10
          PUTFIELD org/nlogo/nvm/Context.ip : I
         L6
          RETURN
[10]_asm_procedurego_setpatchvariable_11 "set pcolor red" Object => void
      _constdouble:15.0 "red" => Double
          // parameter final  context
          // parameter final  context
          // parameter final  arg0
          TRYCATCHBLOCK L0 L1 L2 org/nlogo/api/AgentException
         L3
          ALOAD 0
          GETFIELD org/nlogo/prim/_asm_procedurego_setpatchvariable_11.kept2_value : Ljava/lang/Double;
         L4
          ASTORE 2
         L0
          ALOAD 1
          GETFIELD org/nlogo/nvm/Context.agent : Lorg/nlogo/agent/Agent;
          ICONST_2
          ALOAD 2
          INVOKEVIRTUAL org/nlogo/agent/Agent.setPatchVariable (ILjava/lang/Object;)V
         L1
          GOTO L5
         L2
         FRAME FULL [org/nlogo/prim/_asm_procedurego_setpatchvariable_11 org/nlogo/nvm/Context java/lang/Double] [org/nlogo/api/AgentException]
          ASTORE 3
          NEW org/nlogo/nvm/RuntimePrimitiveException
          DUP
          ALOAD 1
          ALOAD 0
          ALOAD 3
          INVOKEVIRTUAL org/nlogo/api/AgentException.getMessage ()Ljava/lang/String;
          INVOKESPECIAL org/nlogo/nvm/RuntimePrimitiveException.<init> (Lorg/nlogo/api/Context;Lorg/nlogo/nvm/Instruction;Ljava/lang/String;)V
          ATHROW
         L5
         FRAME SAME
          ALOAD 1
          BIPUSH 11
          PUTFIELD org/nlogo/nvm/Context.ip : I
         L6
          RETURN
[11]_asm_procedurego_setobservervariable_12 "set burned-trees burned-trees + 1" Object => void
      _plus "burned-trees + 1" double,double => double
        _observervariable:BURNED-TREES "burned-trees" => Object
        _constdouble:1.0 "1" => double
          // parameter final  context
          // parameter final  context
          // parameter final  context
          // parameter final  d1
          // parameter final  d2
          // parameter final  context
          // parameter final  arg0
          TRYCATCHBLOCK L0 L1 L1 java/lang/ClassCastException
          TRYCATCHBLOCK L2 L3 L4 org/nlogo/api/AgentException
         L5
          ALOAD 0
          GETFIELD org/nlogo/prim/_asm_procedurego_setobservervariable_12.world : Lorg/nlogo/agent/World;
          INVOKEVIRTUAL org/nlogo/agent/World.observer ()Lorg/nlogo/agent/Observer;
          ICONST_2
          INVOKEVIRTUAL org/nlogo/agent/Observer.getVariable (I)Ljava/lang/Object;
         L6
          ASTORE 2
         L0
          ALOAD 2
          CHECKCAST java/lang/Double
          INVOKEVIRTUAL java/lang/Double.doubleValue ()D
          GOTO L7
         L1
         FRAME FULL [org/nlogo/prim/_asm_procedurego_setobservervariable_12 org/nlogo/nvm/Context java/lang/Object] [java/lang/ClassCastException]
          POP
          NEW org/nlogo/nvm/ArgumentTypeException
          DUP
          ALOAD 1
          ALOAD 0
          BIPUSH 0
          LDC 1
          ALOAD 2
          INVOKESPECIAL org/nlogo/nvm/ArgumentTypeException.<init> (Lorg/nlogo/nvm/Context;Lorg/nlogo/nvm/Instruction;IILjava/lang/Object;)V
          ATHROW
         L7
         FRAME SAME1 D
          DCONST_1
         L8
          DSTORE 4
          DSTORE 2
          DLOAD 2
          DLOAD 4
          DADD
         L9
          DSTORE 2
          NEW java/lang/Double
          DUP
          DLOAD 2
          INVOKESPECIAL java/lang/Double.<init> (D)V
          ASTORE 2
         L2
          ALOAD 0
          GETFIELD org/nlogo/prim/_asm_procedurego_setobservervariable_12.world : Lorg/nlogo/agent/World;
          INVOKEVIRTUAL org/nlogo/agent/World.observer ()Lorg/nlogo/agent/Observer;
          ICONST_2
          ALOAD 2
          INVOKEVIRTUAL org/nlogo/agent/Observer.setVariable (ILjava/lang/Object;)V
         L3
          GOTO L10
         L4
         FRAME FULL [org/nlogo/prim/_asm_procedurego_setobservervariable_12 org/nlogo/nvm/Context java/lang/Double T D] [org/nlogo/api/AgentException]
          ASTORE 3
          NEW org/nlogo/nvm/RuntimePrimitiveException
          DUP
          ALOAD 1
          ALOAD 0
          ALOAD 3
          INVOKEVIRTUAL org/nlogo/api/AgentException.getMessage ()Ljava/lang/String;
          INVOKESPECIAL org/nlogo/nvm/RuntimePrimitiveException.<init> (Lorg/nlogo/api/Context;Lorg/nlogo/nvm/Instruction;Ljava/lang/String;)V
          ATHROW
         L10
         FRAME SAME
          ALOAD 1
          BIPUSH 12
          PUTFIELD org/nlogo/nvm/Context.ip : I
         L11
          RETURN
[12]_asm_procedurego_goto_13 => void
          // parameter final  context
         L0
          ALOAD 1
          BIPUSH 15
          PUTFIELD org/nlogo/nvm/Context.ip : I
         L1
          RETURN
[13]_asm_procedurego_if_14 "if burning? [ set pcolor pcolor - 0.3 ]" boolean => void
      _callreport:BURNING? "burning?"
          // parameter final  context
          // parameter final  arg0
          TRYCATCHBLOCK L0 L1 L1 java/lang/ClassCastException
         L2
          NEW org/nlogo/nvm/Activation
          DUP
          ALOAD 0
          GETFIELD org/nlogo/prim/_asm_procedurego_if_14.kept2_procedure : Lorg/nlogo/nvm/Procedure;
          ALOAD 1
          GETFIELD org/nlogo/nvm/Context.activation : Lorg/nlogo/nvm/Activation;
          SIPUSH 0
          ANEWARRAY java/lang/Object
          BIPUSH 13
          INVOKESPECIAL org/nlogo/nvm/Activation.<init> (Lorg/nlogo/nvm/Procedure;Lorg/nlogo/nvm/Activation;[Ljava/lang/Object;I)V
          ALOAD 1
          SWAP
          INVOKEVIRTUAL org/nlogo/nvm/Context.callReporterProcedure (Lorg/nlogo/nvm/Activation;)Ljava/lang/Object;
          DUP
          IFNONNULL L3
          NEW org/nlogo/nvm/RuntimePrimitiveException
          DUP
          ALOAD 1
          ALOAD 0
          LDC "the BURNING? procedure failed to report a result"
          INVOKESPECIAL org/nlogo/nvm/RuntimePrimitiveException.<init> (Lorg/nlogo/api/Context;Lorg/nlogo/nvm/Instruction;Ljava/lang/String;)V
          ATHROW
         L3
         FRAME SAME1 java/lang/Object
          ASTORE 2
         L0
          ALOAD 2
          CHECKCAST java/lang/Boolean
          INVOKEVIRTUAL java/lang/Boolean.booleanValue ()Z
          GOTO L4
         L1
         FRAME FULL [org/nlogo/prim/_asm_procedurego_if_14 org/nlogo/nvm/Context java/lang/Object] [java/lang/ClassCastException]
          POP
          NEW org/nlogo/nvm/ArgumentTypeException
          DUP
          ALOAD 1
          ALOAD 0
          BIPUSH 0
          LDC 2
          ALOAD 2
          INVOKESPECIAL org/nlogo/nvm/ArgumentTypeException.<init> (Lorg/nlogo/nvm/Context;Lorg/nlogo/nvm/Instruction;IILjava/lang/Object;)V
          ATHROW
         L4
         FRAME SAME1 I
          ISTORE 2
          ALOAD 1
          ILOAD 2
          IFEQ L5
          BIPUSH 14
          GOTO L6
         L5
         FRAME FULL [org/nlogo/prim/_asm_procedurego_if_14 org/nlogo/nvm/Context I] [org/nlogo/nvm/Context]
          BIPUSH 15
         L6
         FRAME FULL [org/nlogo/prim/_asm_procedurego_if_14 org/nlogo/nvm/Context I] [org/nlogo/nvm/Context I]
          PUTFIELD org/nlogo/nvm/Context.ip : I
         L7
          RETURN
[14]_asm_procedurego_setpatchvariable_15 "set pcolor pcolor - 0.3" Object => void
      _minus "pcolor - 0.3" double,double => double
        _patchvariable:PCOLOR "pcolor" => Object
        _constdouble:0.3 "0.3" => double
          // parameter final  context
          // parameter final  context
          // parameter final  context
          // parameter final  d0
          // parameter final  d1
          // parameter final  context
          // parameter final  arg0
          TRYCATCHBLOCK L0 L1 L2 org/nlogo/api/AgentException
          TRYCATCHBLOCK L3 L4 L4 java/lang/ClassCastException
          TRYCATCHBLOCK L5 L6 L7 org/nlogo/api/AgentException
         L0
          ALOAD 1
          GETFIELD org/nlogo/nvm/Context.agent : Lorg/nlogo/agent/Agent;
          ICONST_2
          INVOKEVIRTUAL org/nlogo/agent/Agent.getPatchVariable (I)Ljava/lang/Object;
         L1
          GOTO L8
         L2
         FRAME SAME1 org/nlogo/api/AgentException
          ASTORE 2
          NEW org/nlogo/nvm/RuntimePrimitiveException
          DUP
          ALOAD 1
          ALOAD 0
          ALOAD 2
          INVOKEVIRTUAL org/nlogo/api/AgentException.getMessage ()Ljava/lang/String;
          INVOKESPECIAL org/nlogo/nvm/RuntimePrimitiveException.<init> (Lorg/nlogo/api/Context;Lorg/nlogo/nvm/Instruction;Ljava/lang/String;)V
          ATHROW
         L8
         FRAME SAME1 java/lang/Object
          ASTORE 2
         L3
          ALOAD 2
          CHECKCAST java/lang/Double
          INVOKEVIRTUAL java/lang/Double.doubleValue ()D
          GOTO L9
         L4
         FRAME FULL [org/nlogo/prim/_asm_procedurego_setpatchvariable_15 org/nlogo/nvm/Context java/lang/Object] [java/lang/ClassCastException]
          POP
          NEW org/nlogo/nvm/ArgumentTypeException
          DUP
          ALOAD 1
          ALOAD 0
          BIPUSH 0
          LDC 1
          ALOAD 2
          INVOKESPECIAL org/nlogo/nvm/ArgumentTypeException.<init> (Lorg/nlogo/nvm/Context;Lorg/nlogo/nvm/Instruction;IILjava/lang/Object;)V
          ATHROW
         L9
         FRAME SAME1 D
          LDC 0.3D
         L10
          DSTORE 4
          DSTORE 2
          DLOAD 2
          DLOAD 4
          DSUB
         L11
          DSTORE 2
          NEW java/lang/Double
          DUP
          DLOAD 2
          INVOKESPECIAL java/lang/Double.<init> (D)V
          ASTORE 2
         L5
          ALOAD 1
          GETFIELD org/nlogo/nvm/Context.agent : Lorg/nlogo/agent/Agent;
          ICONST_2
          ALOAD 2
          INVOKEVIRTUAL org/nlogo/agent/Agent.setPatchVariable (ILjava/lang/Object;)V
         L6
          GOTO L12
         L7
         FRAME FULL [org/nlogo/prim/_asm_procedurego_setpatchvariable_15 org/nlogo/nvm/Context java/lang/Double T D] [org/nlogo/api/AgentException]
          ASTORE 3
          NEW org/nlogo/nvm/RuntimePrimitiveException
          DUP
          ALOAD 1
          ALOAD 0
          ALOAD 3
          INVOKEVIRTUAL org/nlogo/api/AgentException.getMessage ()Ljava/lang/String;
          INVOKESPECIAL org/nlogo/nvm/RuntimePrimitiveException.<init> (Lorg/nlogo/api/Context;Lorg/nlogo/nvm/Instruction;Ljava/lang/String;)V
          ATHROW
         L12
         FRAME SAME
          ALOAD 1
          BIPUSH 15
          PUTFIELD org/nlogo/nvm/Context.ip : I
         L13
          RETURN
[15]_asm_procedurego_done_16 => void
          // parameter final  context
         L0
          ALOAD 1
          ICONST_1
          PUTFIELD org/nlogo/nvm/Context.finished : Z
         L1
          RETURN
[16]_tick "tick"
[17]_asm_procedurego_return_17 => void
          // parameter final  context
         L0
          ALOAD 1
          INVOKEVIRTUAL org/nlogo/nvm/Context.returnFromProcedure ()V
          ALOAD 1
          ICONST_0
          PUTFIELD org/nlogo/nvm/Context.stopping : Z
         L1
          RETURN

reporter procedure BURNING?:[]{-TP-}:
[0]_asm_procedureburning_report_0 "report pcolor > red - 4 and pcolor < red + 1" Object => void
      _and "pcolor > red - 4 and pcolor < red + 1"
        _greaterthan "pcolor > red - 4" Object,double => boolean
          _patchvariable:PCOLOR "pcolor" => Object
          _constdouble:11.0 "red - 4" => double
        _lessthan "pcolor < red + 1" Object,double => boolean
          _patchvariable:PCOLOR "pcolor" => Object
          _constdouble:16.0 "red + 1" => double
          // parameter final  context
          // parameter final  context
          // parameter final  context
          // parameter final  arg0
          // parameter final  arg1
          // parameter final  context
          // parameter final  context
          // parameter final  context
          // parameter final  arg0
          // parameter final  arg1
          TRYCATCHBLOCK L0 L1 L2 org/nlogo/api/AgentException
          TRYCATCHBLOCK L3 L4 L5 org/nlogo/api/AgentException
         L0
          ALOAD 1
          GETFIELD org/nlogo/nvm/Context.agent : Lorg/nlogo/agent/Agent;
          ICONST_2
          INVOKEVIRTUAL org/nlogo/agent/Agent.getPatchVariable (I)Ljava/lang/Object;
         L1
          GOTO L6
         L2
         FRAME SAME1 org/nlogo/api/AgentException
          ASTORE 2
          NEW org/nlogo/nvm/RuntimePrimitiveException
          DUP
          ALOAD 1
          ALOAD 0
          ALOAD 2
          INVOKEVIRTUAL org/nlogo/api/AgentException.getMessage ()Ljava/lang/String;
          INVOKESPECIAL org/nlogo/nvm/RuntimePrimitiveException.<init> (Lorg/nlogo/api/Context;Lorg/nlogo/nvm/Instruction;Ljava/lang/String;)V
          ATHROW
         L6
         FRAME SAME1 java/lang/Object
          LDC 11.0D
         L7
          DSTORE 3
          ASTORE 2
          ALOAD 2
          INSTANCEOF java/lang/Double
          IFEQ L8
          ALOAD 2
          CHECKCAST java/lang/Double
          INVOKEVIRTUAL java/lang/Double.doubleValue ()D
          DLOAD 3
          DCMPL
          IFLE L9
          ICONST_1
          GOTO L10
         L9
         FRAME APPEND [java/lang/Object D]
          ICONST_0
          GOTO L10
         L8
         FRAME SAME
          NEW org/nlogo/nvm/RuntimePrimitiveException
          DUP
          ALOAD 1
          ALOAD 0
          GETSTATIC org/nlogo/core/I18N$.MODULE$ : Lorg/nlogo/core/I18N$;
          INVOKEVIRTUAL org/nlogo/core/I18N$.errors ()Lorg/nlogo/core/I18N$BundleKind;
          LDC "org.nlogo.prim._greaterthan.cannotCompareParameters"
          GETSTATIC scala/runtime/ScalaRunTime$.MODULE$ : Lscala/runtime/ScalaRunTime$;
          ICONST_2
          ANEWARRAY java/lang/Object
          DUP
          ICONST_0
          GETSTATIC org/nlogo/api/TypeNames$.MODULE$ : Lorg/nlogo/api/TypeNames$;
          ALOAD 2
          INVOKEVIRTUAL org/nlogo/api/TypeNames$.aName (Ljava/lang/Object;)Ljava/lang/String;
          AASTORE
          DUP
          ICONST_1
          GETSTATIC org/nlogo/api/TypeNames$.MODULE$ : Lorg/nlogo/api/TypeNames$;
          DLOAD 3
          INVOKESTATIC scala/runtime/BoxesRunTime.boxToDouble (D)Ljava/lang/Double;
          INVOKEVIRTUAL org/nlogo/api/TypeNames$.aName (Ljava/lang/Object;)Ljava/lang/String;
          AASTORE
          INVOKEVIRTUAL scala/runtime/ScalaRunTime$.wrapRefArray ([Ljava/lang/Object;)Lscala/collection/immutable/ArraySeq;
          INVOKEVIRTUAL org/nlogo/core/I18N$BundleKind.getN (Ljava/lang/String;Lscala/collection/immutable/Seq;)Ljava/lang/String;
          INVOKESPECIAL org/nlogo/nvm/RuntimePrimitiveException.<init> (Lorg/nlogo/api/Context;Lorg/nlogo/nvm/Instruction;Ljava/lang/String;)V
          ATHROW
         L10
         FRAME SAME1 I
          IFEQ L11
         L3
          ALOAD 1
          GETFIELD org/nlogo/nvm/Context.agent : Lorg/nlogo/agent/Agent;
          ICONST_2
          INVOKEVIRTUAL org/nlogo/agent/Agent.getPatchVariable (I)Ljava/lang/Object;
         L4
          GOTO L12
         L5
         FRAME SAME1 org/nlogo/api/AgentException
          ASTORE 2
          NEW org/nlogo/nvm/RuntimePrimitiveException
          DUP
          ALOAD 1
          ALOAD 0
          ALOAD 2
          INVOKEVIRTUAL org/nlogo/api/AgentException.getMessage ()Ljava/lang/String;
          INVOKESPECIAL org/nlogo/nvm/RuntimePrimitiveException.<init> (Lorg/nlogo/api/Context;Lorg/nlogo/nvm/Instruction;Ljava/lang/String;)V
          ATHROW
         L12
         FRAME SAME1 java/lang/Object
          LDC 16.0D
         L13
          DSTORE 3
          ASTORE 2
          ALOAD 2
          INSTANCEOF java/lang/Double
          IFEQ L14
          ALOAD 2
          CHECKCAST java/lang/Double
          INVOKEVIRTUAL java/lang/Double.doubleValue ()D
          DLOAD 3
          DCMPG
          IFGE L15
          ICONST_1
          GOTO L16
         L15
         FRAME SAME
          ICONST_0
          GOTO L16
         L14
         FRAME SAME
          NEW org/nlogo/nvm/RuntimePrimitiveException
          DUP
          ALOAD 1
          ALOAD 0
          GETSTATIC org/nlogo/core/I18N$.MODULE$ : Lorg/nlogo/core/I18N$;
          INVOKEVIRTUAL org/nlogo/core/I18N$.errors ()Lorg/nlogo/core/I18N$BundleKind;
          LDC "org.nlogo.prim._lessthan.cantUseLessthanOnDifferentArgs"
          GETSTATIC scala/runtime/ScalaRunTime$.MODULE$ : Lscala/runtime/ScalaRunTime$;
          ICONST_2
          ANEWARRAY java/lang/Object
          DUP
          ICONST_0
          GETSTATIC org/nlogo/api/TypeNames$.MODULE$ : Lorg/nlogo/api/TypeNames$;
          ALOAD 2
          INVOKEVIRTUAL org/nlogo/api/TypeNames$.aName (Ljava/lang/Object;)Ljava/lang/String;
          AASTORE
          DUP
          ICONST_1
          GETSTATIC org/nlogo/api/TypeNames$.MODULE$ : Lorg/nlogo/api/TypeNames$;
          DLOAD 3
          INVOKESTATIC scala/runtime/BoxesRunTime.boxToDouble (D)Ljava/lang/Double;
          INVOKEVIRTUAL org/nlogo/api/TypeNames$.aName (Ljava/lang/Object;)Ljava/lang/String;
          AASTORE
          INVOKEVIRTUAL scala/runtime/ScalaRunTime$.wrapRefArray ([Ljava/lang/Object;)Lscala/collection/immutable/ArraySeq;
          INVOKEVIRTUAL org/nlogo/core/I18N$BundleKind.getN (Ljava/lang/String;Lscala/collection/immutable/Seq;)Ljava/lang/String;
          INVOKESPECIAL org/nlogo/nvm/RuntimePrimitiveException.<init> (Lorg/nlogo/api/Context;Lorg/nlogo/nvm/Instruction;Ljava/lang/String;)V
          ATHROW
         L16
         FRAME SAME1 I
          GOTO L17
         L11
         FRAME SAME
          ICONST_0
         L17
         FRAME SAME1 I
          IFEQ L18
          GETSTATIC java/lang/Boolean.TRUE : Ljava/lang/Boolean;
          GOTO L19
         L18
         FRAME SAME
          GETSTATIC java/lang/Boolean.FALSE : Ljava/lang/Boolean;
         L19
         FRAME SAME1 java/lang/Boolean
          ASTORE 2
          ALOAD 1
          GETFIELD org/nlogo/nvm/Context.job : Lorg/nlogo/nvm/Job;
          ALOAD 2
          PUTFIELD org/nlogo/nvm/Job.result : Ljava/lang/Object;
          ALOAD 1
          ICONST_0
          PUTFIELD org/nlogo/nvm/Context.stopping : Z
          ALOAD 1
          ICONST_1
          PUTFIELD org/nlogo/nvm/Context.ip : I
          ALOAD 1
          GETFIELD org/nlogo/nvm/Context.activation : Lorg/nlogo/nvm/Activation;
          INVOKEVIRTUAL org/nlogo/nvm/Activation.nonLambdaActivation ()Lorg/nlogo/nvm/Activation;
          GETFIELD org/nlogo/nvm/Activation.procedure : Lorg/nlogo/nvm/Procedure;
          INVOKEVIRTUAL org/nlogo/nvm/Procedure.isReporter ()Z
          IFNE L20
          NEW org/nlogo/nvm/RuntimePrimitiveException
          DUP
          ALOAD 1
          ALOAD 0
          INVOKESTATIC org/nlogo/core/I18N.errorsJ ()Lorg/nlogo/core/I18NJava;
          LDC "org.nlogo.prim._report.canOnlyUseInToReport"
          ICONST_1
          ANEWARRAY java/lang/Object
          DUP
          ICONST_0
          LDC "REPORT"
          AASTORE
          INVOKEINTERFACE org/nlogo/core/I18NJava.getN (Ljava/lang/String;[Ljava/lang/Object;)Ljava/lang/String; (itf)
          INVOKESPECIAL org/nlogo/nvm/RuntimePrimitiveException.<init> (Lorg/nlogo/api/Context;Lorg/nlogo/nvm/Instruction;Ljava/lang/String;)V
          ATHROW
         L20
         FRAME FULL [org/nlogo/prim/_asm_procedureburning_report_0 org/nlogo/nvm/Context java/lang/Boolean D] []
          ALOAD 1
          GETFIELD org/nlogo/nvm/Context.activation : Lorg/nlogo/nvm/Activation;
          GETFIELD org/nlogo/nvm/Activation.procedure : Lorg/nlogo/nvm/Procedure;
          INVOKEVIRTUAL org/nlogo/nvm/Procedure.isLambda ()Z
          IFEQ L21
          NEW org/nlogo/nvm/NonLocalExit
          DUP
          INVOKESPECIAL org/nlogo/nvm/NonLocalExit.<init> ()V
          ATHROW
         L21
         FRAME SAME
          ALOAD 1
          INVOKEVIRTUAL org/nlogo/nvm/Context.atTopActivation ()Z
          IFNE L22
          NEW org/nlogo/nvm/RuntimePrimitiveException
          DUP
          ALOAD 1
          ALOAD 0
          INVOKESTATIC org/nlogo/core/I18N.errorsJ ()Lorg/nlogo/core/I18NJava;
          LDC "org.nlogo.prim._report.mustImmediatelyBeUsedInToReport"
          ICONST_1
          ANEWARRAY java/lang/Object
          DUP
          ICONST_0
          LDC "REPORT"
          AASTORE
          INVOKEINTERFACE org/nlogo/core/I18NJava.getN (Ljava/lang/String;[Ljava/lang/Object;)Ljava/lang/String; (itf)
          INVOKESPECIAL org/nlogo/nvm/RuntimePrimitiveException.<init> (Lorg/nlogo/api/Context;Lorg/nlogo/nvm/Instruction;Ljava/lang/String;)V
          ATHROW
         L22
         FRAME SAME
          RETURN
[1]_asm_procedureburning_returnreport_1 => void
          // parameter final  context
         L0
          NEW org/nlogo/nvm/RuntimePrimitiveException
          DUP
          ALOAD 1
          ALOAD 0
          GETSTATIC org/nlogo/core/I18N$.MODULE$ : Lorg/nlogo/core/I18N$;
          INVOKEVIRTUAL org/nlogo/core/I18N$.errors ()Lorg/nlogo/core/I18N$BundleKind;
          LDC "org.nlogo.prim._returnreport.reportNotCalledInReportProcedure"
          INVOKEVIRTUAL org/nlogo/core/I18N$BundleKind.get (Ljava/lang/String;)Ljava/lang/String;
          INVOKESPECIAL org/nlogo/nvm/RuntimePrimitiveException.<init> (Lorg/nlogo/api/Context;Lorg/nlogo/nvm/Instruction;Ljava/lang/String;)V
          ATHROW
         L1
         FRAME FULL [] [java/lang/Throwable]
          ATHROW

reporter procedure PERCENT-BURNED:[]{OTPL}:
[0]_asm_procedurepercentburned_ifelse_0 "ifelse initial-trees > 0 [ report burned-trees / initial-trees * 100 ] [ report 0 ]" boolean => void
      _greaterthan "initial-trees > 0" Object,double => boolean
        _observervariable:INITIAL-TREES "initial-trees" => Object
        _constdouble:0.0 "0" => double
          // parameter final  context
          // parameter final  context
          // parameter final  context
          // parameter final  arg0
          // parameter final  arg1
          // parameter final  context
          // parameter final  cond
         L0
          ALOAD 0
          GETFIELD org/nlogo/prim/_asm_procedurepercentburned_ifelse_0.world : Lorg/nlogo/agent/World;
          INVOKEVIRTUAL org/nlogo/agent/World.observer ()Lorg/nlogo/agent/Observer;
          ICONST_1
          INVOKEVIRTUAL org/nlogo/agent/Observer.getVariable (I)Ljava/lang/Object;
         L1
          DCONST_0
         L2
          DSTORE 3
          ASTORE 2
          ALOAD 2
          INSTANCEOF java/lang/Double
          IFEQ L3
          ALOAD 2
          CHECKCAST java/lang/Double
          INVOKEVIRTUAL java/lang/Double.doubleValue ()D
          DLOAD 3
          DCMPL
          IFLE L4
          ICONST_1
          GOTO L5
         L4
         FRAME APPEND [java/lang/Object D]
          ICONST_0
          GOTO L5
         L3
         FRAME SAME
          NEW org/nlogo/nvm/RuntimePrimitiveException
          DUP
          ALOAD 1
          ALOAD 0
          GETSTATIC org/nlogo/core/I18N$.MODULE$ : Lorg/nlogo/core/I18N$;
          INVOKEVIRTUAL org/nlogo/core/I18N$.errors ()Lorg/nlogo/core/I18N$BundleKind;
          LDC "org.nlogo.prim._greaterthan.cannotCompareParameters"
          GETSTATIC scala/runtime/ScalaRunTime$.MODULE$ : Lscala/runtime/ScalaRunTime$;
          ICONST_2
          ANEWARRAY java/lang/Object
          DUP
          ICONST_0
          GETSTATIC org/nlogo/api/TypeNames$.MODULE$ : Lorg/nlogo/api/TypeNames$;
          ALOAD 2
          INVOKEVIRTUAL org/nlogo/api/TypeNames$.aName (Ljava/lang/Object;)Ljava/lang/String;
          AASTORE
          DUP
          ICONST_1
          GETSTATIC org/nlogo/api/TypeNames$.MODULE$ : Lorg/nlogo/api/TypeNames$;
          DLOAD 3
          INVOKESTATIC scala/runtime/BoxesRunTime.boxToDouble (D)Ljava/lang/Double;
          INVOKEVIRTUAL org/nlogo/api/TypeNames$.aName (Ljava/lang/Object;)Ljava/lang/String;
          AASTORE
          INVOKEVIRTUAL scala/runtime/ScalaRunTime$.wrapRefArray ([Ljava/lang/Object;)Lscala/collection/immutable/ArraySeq;
          INVOKEVIRTUAL org/nlogo/core/I18N$BundleKind.getN (Ljava/lang/String;Lscala/collection/immutable/Seq;)Ljava/lang/String;
          INVOKESPECIAL org/nlogo/nvm/RuntimePrimitiveException.<init> (Lorg/nlogo/api/Context;Lorg/nlogo/nvm/Instruction;Ljava/lang/String;)V
          ATHROW
         L5
         FRAME SAME1 I
          ISTORE 2
          ALOAD 1
          ILOAD 2
          IFEQ L6
          ICONST_1
          GOTO L7
         L6
         FRAME FULL [org/nlogo/prim/_asm_procedurepercentburned_ifelse_0 org/nlogo/nvm/Context I D] [org/nlogo/nvm/Context]
          ICONST_3
         L7
         FRAME FULL [org/nlogo/prim/_asm_procedurepercentburned_ifelse_0 org/nlogo/nvm/Context I D] [org/nlogo/nvm/Context I]
          PUTFIELD org/nlogo/nvm/Context.ip : I
         L8
          RETURN
[1]_asm_procedurepercentburned_report_1 "report burned-trees / initial-trees * 100" Object => void
      _mult "burned-trees / initial-trees * 100" double,double => double
        _div "burned-trees / initial-trees" double,double => double
          _observervariable:BURNED-TREES "burned-trees" => Object
          _observervariable:INITIAL-TREES "initial-trees" => Object
        _constdouble:100.0 "100" => double
          // parameter final  context
          // parameter final  context
          // parameter final  context
          // parameter final  context
          // parameter final  arg0
          // parameter final  arg1
          TRYCATCHBLOCK L0 L1 L1 java/lang/ClassCastException
          TRYCATCHBLOCK L2 L3 L3 java/lang/ClassCastException
         L4
          ALOAD 0
          GETFIELD org/nlogo/prim/_asm_procedurepercentburned_report_1.world : Lorg/nlogo/agent/World;
          INVOKEVIRTUAL org/nlogo/agent/World.observer ()Lorg/nlogo/agent/Observer;
          ICONST_2
          INVOKEVIRTUAL org/nlogo/agent/Observer.getVariable (I)Ljava/lang/Object;
         L5
          ASTORE 2
         L0
          ALOAD 2
          CHECKCAST java/lang/Double
          INVOKEVIRTUAL java/lang/Double.doubleValue ()D
          GOTO L6
         L1
         FRAME FULL [org/nlogo/prim/_asm_procedurepercentburned_report_1 org/nlogo/nvm/Context java/lang/Object] [java/lang/ClassCastException]
          POP
          NEW org/nlogo/nvm/ArgumentTypeException
          DUP
          ALOAD 1
          ALOAD 0
          BIPUSH 0
          LDC 1
          ALOAD 2
          INVOKESPECIAL org/nlogo/nvm/ArgumentTypeException.<init> (Lorg/nlogo/nvm/Context;Lorg/nlogo/nvm/Instruction;IILjava/lang/Object;)V
          ATHROW
         L6
         FRAME SAME1 D
          ALOAD 0
          GETFIELD org/nlogo/prim/_asm_procedurepercentburned_report_1.world : Lorg/nlogo/agent/World;
          INVOKEVIRTUAL org/nlogo/agent/World.observer ()Lorg/nlogo/agent/Observer;
          ICONST_1
          INVOKEVIRTUAL org/nlogo/agent/Observer.getVariable (I)Ljava/lang/Object;
         L7
          ASTORE 2
         L2
          ALOAD 2
          CHECKCAST java/lang/Double
          INVOKEVIRTUAL java/lang/Double.doubleValue ()D
          GOTO L8
         L3
         FRAME SAME1 java/lang/ClassCastException
          POP
          NEW org/nlogo/nvm/ArgumentTypeException
          DUP
          ALOAD 1
          ALOAD 0
          BIPUSH 1
          LDC 1
          ALOAD 2
          INVOKESPECIAL org/nlogo/nvm/ArgumentTypeException.<init> (Lorg/nlogo/nvm/Context;Lorg/nlogo/nvm/Instruction;IILjava/lang/Object;)V
          ATHROW
         L8
         FRAME FULL [org/nlogo/prim/_asm_procedurepercentburned_report_1 org/nlogo/nvm/Context java/lang/Object] [D D]
          DSTORE 4
          DSTORE 2
          DLOAD 4
          DCONST_0
          DCMPL
          IFNE L9
          NEW org/nlogo/nvm/RuntimePrimitiveException
          DUP
          ALOAD 1
          ALOAD 0
          INVOKESTATIC org/nlogo/core/I18N.errorsJ ()Lorg/nlogo/core/I18NJava;
          LDC "org.nlogo.prim.etc.$common.divByZero"
          INVOKEINTERFACE org/nlogo/core/I18NJava.get (Ljava/lang/String;)Ljava/lang/String; (itf)
          INVOKESPECIAL org/nlogo/nvm/RuntimePrimitiveException.<init> (Lorg/nlogo/api/Context;Lorg/nlogo/nvm/Instruction;Ljava/lang/String;)V
          ATHROW
         L9
         FRAME FULL [org/nlogo/prim/_asm_procedurepercentburned_report_1 org/nlogo/nvm/Context D D] []
          DLOAD 2
          DLOAD 4
          DDIV
         L10
          LDC 100.0D
         L11
          DSTORE 4
          DSTORE 2
          DLOAD 2
          DLOAD 4
          DMUL
         L12
          DSTORE 2
          NEW java/lang/Double
          DUP
          DLOAD 2
          INVOKESPECIAL java/lang/Double.<init> (D)V
          ASTORE 2
          ALOAD 1
          GETFIELD org/nlogo/nvm/Context.job : Lorg/nlogo/nvm/Job;
          ALOAD 2
          PUTFIELD org/nlogo/nvm/Job.result : Ljava/lang/Object;
          ALOAD 1
          ICONST_0
          PUTFIELD org/nlogo/nvm/Context.stopping : Z
          ALOAD 1
          ICONST_2
          PUTFIELD org/nlogo/nvm/Context.ip : I
          ALOAD 1
          GETFIELD org/nlogo/nvm/Context.activation : Lorg/nlogo/nvm/Activation;
          INVOKEVIRTUAL org/nlogo/nvm/Activation.nonLambdaActivation ()Lorg/nlogo/nvm/Activation;
          GETFIELD org/nlogo/nvm/Activation.procedure : Lorg/nlogo/nvm/Procedure;
          INVOKEVIRTUAL org/nlogo/nvm/Procedure.isReporter ()Z
          IFNE L13
          NEW org/nlogo/nvm/RuntimePrimitiveException
          DUP
          ALOAD 1
          ALOAD 0
          INVOKESTATIC org/nlogo/core/I18N.errorsJ ()Lorg/nlogo/core/I18NJava;
          LDC "org.nlogo.prim._report.canOnlyUseInToReport"
          ICONST_1
          ANEWARRAY java/lang/Object
          DUP
          ICONST_0
          LDC "REPORT"
          AASTORE
          INVOKEINTERFACE org/nlogo/core/I18NJava.getN (Ljava/lang/String;[Ljava/lang/Object;)Ljava/lang/String; (itf)
          INVOKESPECIAL org/nlogo/nvm/RuntimePrimitiveException.<init> (Lorg/nlogo/api/Context;Lorg/nlogo/nvm/Instruction;Ljava/lang/String;)V
          ATHROW
         L13
         FRAME FULL [org/nlogo/prim/_asm_procedurepercentburned_report_1 org/nlogo/nvm/Context java/lang/Double T D] []
          ALOAD 1
          GETFIELD org/nlogo/nvm/Context.activation : Lorg/nlogo/nvm/Activation;
          GETFIELD org/nlogo/nvm/Activation.procedure : Lorg/nlogo/nvm/Procedure;
          INVOKEVIRTUAL org/nlogo/nvm/Procedure.isLambda ()Z
          IFEQ L14
          NEW org/nlogo/nvm/NonLocalExit
          DUP
          INVOKESPECIAL org/nlogo/nvm/NonLocalExit.<init> ()V
          ATHROW
         L14
         FRAME SAME
          ALOAD 1
          INVOKEVIRTUAL org/nlogo/nvm/Context.atTopActivation ()Z
          IFNE L15
          NEW org/nlogo/nvm/RuntimePrimitiveException
          DUP
          ALOAD 1
          ALOAD 0
          INVOKESTATIC org/nlogo/core/I18N.errorsJ ()Lorg/nlogo/core/I18NJava;
          LDC "org.nlogo.prim._report.mustImmediatelyBeUsedInToReport"
          ICONST_1
          ANEWARRAY java/lang/Object
          DUP
          ICONST_0
          LDC "REPORT"
          AASTORE
          INVOKEINTERFACE org/nlogo/core/I18NJava.getN (Ljava/lang/String;[Ljava/lang/Object;)Ljava/lang/String; (itf)
          INVOKESPECIAL org/nlogo/nvm/RuntimePrimitiveException.<init> (Lorg/nlogo/api/Context;Lorg/nlogo/nvm/Instruction;Ljava/lang/String;)V
          ATHROW
         L15
         FRAME SAME
          RETURN
[2]_asm_procedurepercentburned_goto_2 => void
          // parameter final  context
         L0
          ALOAD 1
          ICONST_4
          PUTFIELD org/nlogo/nvm/Context.ip : I
         L1
          RETURN
[3]_asm_procedurepercentburned_report_3 "report 0" Object => void
      _constdouble:0.0 "0" => Double
          // parameter final  context
         L0
          ALOAD 0
          GETFIELD org/nlogo/prim/_asm_procedurepercentburned_report_3.kept2_value : Ljava/lang/Double;
         L1
          ASTORE 2
          ALOAD 1
          GETFIELD org/nlogo/nvm/Context.job : Lorg/nlogo/nvm/Job;
          ALOAD 2
          PUTFIELD org/nlogo/nvm/Job.result : Ljava/lang/Object;
          ALOAD 1
          ICONST_0
          PUTFIELD org/nlogo/nvm/Context.stopping : Z
          ALOAD 1
          ICONST_4
          PUTFIELD org/nlogo/nvm/Context.ip : I
          ALOAD 1
          GETFIELD org/nlogo/nvm/Context.activation : Lorg/nlogo/nvm/Activation;
          INVOKEVIRTUAL org/nlogo/nvm/Activation.nonLambdaActivation ()Lorg/nlogo/nvm/Activation;
          GETFIELD org/nlogo/nvm/Activation.procedure : Lorg/nlogo/nvm/Procedure;
          INVOKEVIRTUAL org/nlogo/nvm/Procedure.isReporter ()Z
          IFNE L2
          NEW org/nlogo/nvm/RuntimePrimitiveException
          DUP
          ALOAD 1
          ALOAD 0
          INVOKESTATIC org/nlogo/core/I18N.errorsJ ()Lorg/nlogo/core/I18NJava;
          LDC "org.nlogo.prim._report.canOnlyUseInToReport"
          ICONST_1
          ANEWARRAY java/lang/Object
          DUP
          ICONST_0
          LDC "REPORT"
          AASTORE
          INVOKEINTERFACE org/nlogo/core/I18NJava.getN (Ljava/lang/String;[Ljava/lang/Object;)Ljava/lang/String; (itf)
          INVOKESPECIAL org/nlogo/nvm/RuntimePrimitiveException.<init> (Lorg/nlogo/api/Context;Lorg/nlogo/nvm/Instruction;Ljava/lang/String;)V
          ATHROW
         L2
         FRAME APPEND [java/lang/Double]
          ALOAD 1
          GETFIELD org/nlogo/nvm/Context.activation : Lorg/nlogo/nvm/Activation;
          GETFIELD org/nlogo/nvm/Activation.procedure : Lorg/nlogo/nvm/Procedure;
          INVOKEVIRTUAL org/nlogo/nvm/Procedure.isLambda ()Z
          IFEQ L3
          NEW org/nlogo/nvm/NonLocalExit
          DUP
          INVOKESPECIAL org/nlogo/nvm/NonLocalExit.<init> ()V
          ATHROW
         L3
         FRAME SAME
          ALOAD 1
          INVOKEVIRTUAL org/nlogo/nvm/Context.atTopActivation ()Z
          IFNE L4
          NEW org/nlogo/nvm/RuntimePrimitiveException
          DUP
          ALOAD 1
          ALOAD 0
          INVOKESTATIC org/nlogo/core/I18N.errorsJ ()Lorg/nlogo/core/I18NJava;
          LDC "org.nlogo.prim._report.mustImmediatelyBeUsedInToReport"
          ICONST_1
          ANEWARRAY java/lang/Object
          DUP
          ICONST_0
          LDC "REPORT"
          AASTORE
          INVOKEINTERFACE org/nlogo/core/I18NJava.getN (Ljava/lang/String;[Ljava/lang/Object;)Ljava/lang/String; (itf)
          INVOKESPECIAL org/nlogo/nvm/RuntimePrimitiveException.<init> (Lorg/nlogo/api/Context;Lorg/nlogo/nvm/Instruction;Ljava/lang/String;)V
          ATHROW
         L4
         FRAME SAME
          RETURN
[4]_asm_procedurepercentburned_returnreport_4 => void
          // parameter final  context
         L0
          NEW org/nlogo/nvm/RuntimePrimitiveException
          DUP
          ALOAD 1
          ALOAD 0
          GETSTATIC org/nlogo/core/I18N$.MODULE$ : Lorg/nlogo/core/I18N$;
          INVOKEVIRTUAL org/nlogo/core/I18N$.errors ()Lorg/nlogo/core/I18N$BundleKind;
          LDC "org.nlogo.prim._returnreport.reportNotCalledInReportProcedure"
          INVOKEVIRTUAL org/nlogo/core/I18N$BundleKind.get (Ljava/lang/String;)Ljava/lang/String;
          INVOKESPECIAL org/nlogo/nvm/RuntimePrimitiveException.<init> (Lorg/nlogo/api/Context;Lorg/nlogo/nvm/Instruction;Ljava/lang/String;)V
          ATHROW
         L1
         FRAME FULL [] [java/lang/Throwable]
          ATHROW

