globals [POPULATION MAX-ALIGN-TURN MAX-COHERE-TURN MAX-SEPARATE-TURN VISION MINIMUM-SEPARATION RESULT]
interfaceGlobals [population max-align-turn max-cohere-turn max-separate-turn vision minimum-separation]
turtles-own [WHO COLOR HEADING XCOR YCOR SHAPE LABEL LABEL-COLOR BREED HIDDEN? SIZE PEN-SIZE PEN-MODE FLOCKMATES NEAREST-NEIGHBOR]
patches-own [PXCOR PYCOR PCOLOR PLABEL PLABEL-COLOR]
links-own [END1 END2 COLOR LABEL LABEL-COLOR HIDDEN? BREED THICKNESS SHAPE TIE-MODE]
breeds 
link-breeds 

procedure BENCHMARK:[_repeatlocal:0]{O---}:
[0]_asm_procedurebenchmark_randomseed_0 "random-seed 5454" double => void
      _constdouble:5454.0 "5454" => double
          // parameter final  context
          // parameter final  context
          // parameter final  arg0
         L0
          LDC 5454.0D
         L1
          DSTORE 2
          DLOAD 2
          D2L
          LSTORE 4
          LLOAD 4
          LDC -2147483648L
          LCMP
          IFLT L2
          LLOAD 4
          LDC 2147483647L
          LCMP
          IFLE L3
         L2
         FRAME APPEND [D J]
          NEW org/nlogo/nvm/RuntimePrimitiveException
          DUP
          ALOAD 1
          ALOAD 0
          NEW java/lang/StringBuilder
          DUP
          LDC 75
          INVOKESPECIAL java/lang/StringBuilder.<init> (I)V
          GETSTATIC org/nlogo/api/Dump$.MODULE$ : Lorg/nlogo/api/Dump$;
          DLOAD 2
          INVOKEVIRTUAL org/nlogo/api/Dump$.number (D)Ljava/lang/String;
          INVOKEVIRTUAL java/lang/StringBuilder.append (Ljava/lang/String;)Ljava/lang/StringBuilder;
          LDC " is not in the allowable range for random seeds (-2147483648 to 2147483647)"
          INVOKEVIRTUAL java/lang/StringBuilder.append (Ljava/lang/String;)Ljava/lang/StringBuilder;
          INVOKEVIRTUAL java/lang/StringBuilder.toString ()Ljava/lang/String;
          INVOKESPECIAL org/nlogo/nvm/RuntimePrimitiveException.<init> (Lorg/nlogo/api/Context;Lorg/nlogo/nvm/Instruction;Ljava/lang/String;)V
          ATHROW
         L3
         FRAME SAME
          LLOAD 4
          L2I
          ISTORE 6
          ALOAD 1
          GETFIELD org/nlogo/nvm/Context.job : Lorg/nlogo/nvm/Job;
          GETFIELD org/nlogo/nvm/Job.random : Lorg/nlogo/api/MersenneTwisterFast;
          ILOAD 6
          I2L
          INVOKEVIRTUAL org/nlogo/api/MersenneTwisterFast.setSeed (J)V
          ALOAD 1
          GETFIELD org/nlogo/nvm/Context.job : Lorg/nlogo/nvm/Job;
          GETFIELD org/nlogo/nvm/Job.workspace : Lorg/nlogo/nvm/Workspace;
          IFNULL L4
          ALOAD 1
          GETFIELD org/nlogo/nvm/Context.job : Lorg/nlogo/nvm/Job;
          GETFIELD org/nlogo/nvm/Job.random : Lorg/nlogo/api/MersenneTwisterFast;
          ALOAD 1
          GETFIELD org/nlogo/nvm/Context.job : Lorg/nlogo/nvm/Job;
          GETFIELD org/nlogo/nvm/Job.workspace : Lorg/nlogo/nvm/Workspace;
          INVOKEINTERFACE org/nlogo/nvm/Workspace.world ()Lorg/nlogo/agent/World; (itf)
          INVOKEVIRTUAL org/nlogo/agent/World.mainRNG ()Lorg/nlogo/api/MersenneTwisterFast;
          ASTORE 7
          DUP
          IFNONNULL L5
          POP
          ALOAD 7
          IFNULL L6
          GOTO L4
         L5
         FRAME FULL [org/nlogo/prim/_asm_procedurebenchmark_randomseed_0 org/nlogo/nvm/Context D J I org/nlogo/api/MersenneTwisterFast] [org/nlogo/api/MersenneTwisterFast]
          ALOAD 7
          INVOKEVIRTUAL java/lang/Object.equals (Ljava/lang/Object;)Z
          IFEQ L4
         L6
         FRAME SAME
          ALOAD 1
          GETFIELD org/nlogo/nvm/Context.job : Lorg/nlogo/nvm/Job;
          GETFIELD org/nlogo/nvm/Job.workspace : Lorg/nlogo/nvm/Workspace;
          INVOKEINTERFACE org/nlogo/nvm/Workspace.plotRNG ()Lorg/nlogo/api/MersenneTwisterFast; (itf)
          ILOAD 6
          I2L
          INVOKEVIRTUAL org/nlogo/api/MersenneTwisterFast.setSeed (J)V
         L4
         FRAME CHOP 1
          ALOAD 1
          ICONST_1
          PUTFIELD org/nlogo/nvm/Context.ip : I
         L7
          RETURN
[1]_resettimer "reset-timer"
[2]_asm_procedurebenchmark_call_1 "setup"
         L0
          NEW org/nlogo/nvm/Activation
          DUP
          ALOAD 0
          GETFIELD org/nlogo/prim/_asm_procedurebenchmark_call_1.kept1_procedure : Lorg/nlogo/nvm/Procedure;
          ALOAD 1
          GETFIELD org/nlogo/nvm/Context.activation : Lorg/nlogo/nvm/Activation;
          SIPUSH 0
          ANEWARRAY java/lang/Object
          ICONST_3
          INVOKESPECIAL org/nlogo/nvm/Activation.<init> (Lorg/nlogo/nvm/Procedure;Lorg/nlogo/nvm/Activation;[Ljava/lang/Object;I)V
          ALOAD 1
          SWAP
          PUTFIELD org/nlogo/nvm/Context.activation : Lorg/nlogo/nvm/Activation;
          ALOAD 1
          ICONST_0
          PUTFIELD org/nlogo/nvm/Context.ip : I
         L1
          RETURN
[3]_asm_procedurebenchmark_repeatlocal_2 "repeat 700 [ go ]" double => void
      _constdouble:700.0 "700" => double
          // parameter final  context
          // parameter final  context
          // parameter final  arg0
         L0
          LDC 700.0D
         L1
          DSTORE 2
          ALOAD 1
          GETFIELD org/nlogo/nvm/Context.activation : Lorg/nlogo/nvm/Activation;
          GETFIELD org/nlogo/nvm/Activation.args : [Ljava/lang/Object;
          ICONST_0
          NEW org/nlogo/nvm/MutableLong
          DUP
          ALOAD 0
          DLOAD 2
          ALOAD 1
          INVOKEVIRTUAL org/nlogo/prim/_asm_procedurebenchmark_repeatlocal_2.validLong (DLorg/nlogo/nvm/Context;)J
          INVOKESPECIAL org/nlogo/nvm/MutableLong.<init> (J)V
          AASTORE
          ALOAD 1
          ICONST_5
          PUTFIELD org/nlogo/nvm/Context.ip : I
         L2
          RETURN
[4]_asm_procedurebenchmark_call_3 "go"
         L0
          NEW org/nlogo/nvm/Activation
          DUP
          ALOAD 0
          GETFIELD org/nlogo/prim/_asm_procedurebenchmark_call_3.kept1_procedure : Lorg/nlogo/nvm/Procedure;
          ALOAD 1
          GETFIELD org/nlogo/nvm/Context.activation : Lorg/nlogo/nvm/Activation;
          SIPUSH 0
          ANEWARRAY java/lang/Object
          ICONST_5
          INVOKESPECIAL org/nlogo/nvm/Activation.<init> (Lorg/nlogo/nvm/Procedure;Lorg/nlogo/nvm/Activation;[Ljava/lang/Object;I)V
          ALOAD 1
          SWAP
          PUTFIELD org/nlogo/nvm/Context.activation : Lorg/nlogo/nvm/Activation;
          ALOAD 1
          ICONST_0
          PUTFIELD org/nlogo/nvm/Context.ip : I
         L1
          RETURN
[5]_asm_procedurebenchmark_repeatlocalinternal_4 => void
          // parameter final  context
         L0
          ALOAD 1
          GETFIELD org/nlogo/nvm/Context.activation : Lorg/nlogo/nvm/Activation;
          GETFIELD org/nlogo/nvm/Activation.args : [Ljava/lang/Object;
          ICONST_0
          AALOAD
          CHECKCAST org/nlogo/nvm/MutableLong
          ASTORE 2
          ALOAD 2
          INVOKEVIRTUAL org/nlogo/nvm/MutableLong.value ()J
          LCONST_0
          LCMP
          IFGT L1
          ALOAD 1
          BIPUSH 6
          PUTFIELD org/nlogo/nvm/Context.ip : I
          GOTO L2
         L1
         FRAME APPEND [org/nlogo/nvm/MutableLong]
          ALOAD 2
          ALOAD 2
          INVOKEVIRTUAL org/nlogo/nvm/MutableLong.value ()J
          LCONST_1
          LSUB
          INVOKEVIRTUAL org/nlogo/nvm/MutableLong.value_$eq (J)V
          ALOAD 1
          ICONST_4
          PUTFIELD org/nlogo/nvm/Context.ip : I
         L2
         FRAME SAME
          RETURN
[6]_asm_procedurebenchmark_setobservervariable_5 "set result timer" Object => void
      _timer "timer" => double
          // parameter final  context
          // parameter final  context
          // parameter final  arg0
          TRYCATCHBLOCK L0 L1 L2 org/nlogo/api/AgentException
         L3
          ALOAD 0
          GETFIELD org/nlogo/prim/_asm_procedurebenchmark_setobservervariable_5.world : Lorg/nlogo/agent/World;
          INVOKEVIRTUAL org/nlogo/agent/World.timer ()Lorg/nlogo/api/Timer;
          INVOKEVIRTUAL org/nlogo/api/Timer.read ()D
         L4
          DSTORE 2
          NEW java/lang/Double
          DUP
          DLOAD 2
          INVOKESPECIAL java/lang/Double.<init> (D)V
          ASTORE 2
         L0
          ALOAD 0
          GETFIELD org/nlogo/prim/_asm_procedurebenchmark_setobservervariable_5.world : Lorg/nlogo/agent/World;
          INVOKEVIRTUAL org/nlogo/agent/World.observer ()Lorg/nlogo/agent/Observer;
          BIPUSH 6
          ALOAD 2
          INVOKEVIRTUAL org/nlogo/agent/Observer.setVariable (ILjava/lang/Object;)V
         L1
          GOTO L5
         L2
         FRAME FULL [org/nlogo/prim/_asm_procedurebenchmark_setobservervariable_5 org/nlogo/nvm/Context java/lang/Double] [org/nlogo/api/AgentException]
          ASTORE 3
          NEW org/nlogo/nvm/RuntimePrimitiveException
          DUP
          ALOAD 1
          ALOAD 0
          ALOAD 3
          INVOKEVIRTUAL org/nlogo/api/AgentException.getMessage ()Ljava/lang/String;
          INVOKESPECIAL org/nlogo/nvm/RuntimePrimitiveException.<init> (Lorg/nlogo/api/Context;Lorg/nlogo/nvm/Instruction;Ljava/lang/String;)V
          ATHROW
         L5
         FRAME SAME
          ALOAD 1
          BIPUSH 7
          PUTFIELD org/nlogo/nvm/Context.ip : I
         L6
          RETURN
[7]_asm_procedurebenchmark_return_6 => void
          // parameter final  context
         L0
          ALOAD 1
          INVOKEVIRTUAL org/nlogo/nvm/Context.returnFromProcedure ()V
          ALOAD 1
          ICONST_0
          PUTFIELD org/nlogo/nvm/Context.stopping : Z
         L1
          RETURN

procedure SETUP:[]{O---}:
[0]_clearall "ca"
[1]_resetticks "reset-ticks"
[2]_createorderedturtles:,+7 "cro population set color yellow - 2 + random 7 setxy random-float world-width random-float world-height [ rt random-float 360 ]"
      _asm_proceduresetup_observervariable_0 "population" => Object
            // parameter final  context
           L0
            ALOAD 0
            GETFIELD org/nlogo/prim/_asm_proceduresetup_observervariable_0.world : Lorg/nlogo/agent/World;
            INVOKEVIRTUAL org/nlogo/agent/World.observer ()Lorg/nlogo/agent/Observer;
            ICONST_0
            INVOKEVIRTUAL org/nlogo/agent/Observer.getVariable (I)Ljava/lang/Object;
           L1
            ARETURN
[3]_asm_proceduresetup_setturtleorlinkvariable_1 "set color yellow - 2 + random 7" Object => void
      _plus "yellow - 2 + random 7" double,double => double
        _constdouble:43.0 "yellow - 2" => double
        _randomconst:7 "random 7" => double
          // parameter final  context
          // parameter final  context
          // parameter final  context
          // parameter final  d1
          // parameter final  d2
          // parameter final  context
          // parameter final  value
          TRYCATCHBLOCK L0 L1 L1 org/nlogo/api/AgentException
         L2
          LDC 43.0D
         L3
          ALOAD 1
          GETFIELD org/nlogo/nvm/Context.job : Lorg/nlogo/nvm/Job;
          GETFIELD org/nlogo/nvm/Job.random : Lorg/nlogo/api/MersenneTwisterFast;
          LDC 7L
          INVOKEVIRTUAL org/nlogo/api/MersenneTwisterFast.nextLong (J)J
          L2D
         L4
          DSTORE 4
          DSTORE 2
          DLOAD 2
          DLOAD 4
          DADD
         L5
          DSTORE 2
          NEW java/lang/Double
          DUP
          DLOAD 2
          INVOKESPECIAL java/lang/Double.<init> (D)V
          ASTORE 2
          ALOAD 1
          GETFIELD org/nlogo/nvm/Context.agent : Lorg/nlogo/agent/Agent;
          ASTORE 3
         L0
          ALOAD 3
          INVOKEVIRTUAL org/nlogo/agent/Agent.agentBit ()I
          LOOKUPSWITCH
            2: L6
            8: L7
            default: L8
         L6
         FRAME APPEND [java/lang/Double org/nlogo/agent/Agent D]
          ALOAD 3
          ICONST_1
          ALOAD 2
          INVOKEVIRTUAL org/nlogo/agent/Agent.setTurtleVariable (ILjava/lang/Object;)V
          GOTO L9
         L7
         FRAME SAME
          ALOAD 3
          ICONST_2
          ALOAD 2
          INVOKEVIRTUAL org/nlogo/agent/Agent.setLinkVariable (ILjava/lang/Object;)V
          GOTO L9
         L8
         FRAME SAME
          ALOAD 3
          LDC "COLOR"
          ALOAD 2
          INVOKEVIRTUAL org/nlogo/agent/Agent.setTurtleOrLinkVariable (Ljava/lang/String;Ljava/lang/Object;)V
          GOTO L9
         L1
         FRAME SAME1 org/nlogo/api/AgentException
          ASTORE 4
          NEW org/nlogo/nvm/RuntimePrimitiveException
          DUP
          ALOAD 1
          ALOAD 0
          ALOAD 4
          INVOKEVIRTUAL org/nlogo/api/AgentException.getMessage ()Ljava/lang/String;
          INVOKESPECIAL org/nlogo/nvm/RuntimePrimitiveException.<init> (Lorg/nlogo/api/Context;Lorg/nlogo/nvm/Instruction;Ljava/lang/String;)V
          ATHROW
         L9
         FRAME SAME
          ALOAD 1
          ICONST_4
          PUTFIELD org/nlogo/nvm/Context.ip : I
         L10
          RETURN
[4]_asm_proceduresetup_setxy_2 "setxy random-float world-width random-float world-height" double,double => void
      _randomfloat "random-float world-width" double => double
        _worldwidth "world-width" => double
      _randomfloat "random-float world-height" double => double
        _worldheight "world-height" => double
          // parameter final  context
          // parameter final  context
          // parameter final  d
          // parameter final  context
          // parameter final  context
          // parameter final  d
          TRYCATCHBLOCK L0 L1 L2 org/nlogo/api/AgentException
         L3
          ALOAD 0
          GETFIELD org/nlogo/prim/_asm_proceduresetup_setxy_2.world : Lorg/nlogo/agent/World;
          INVOKEVIRTUAL org/nlogo/agent/World.worldWidth ()I
          I2D
         L4
          DSTORE 2
          DLOAD 2
          ALOAD 1
          GETFIELD org/nlogo/nvm/Context.job : Lorg/nlogo/nvm/Job;
          GETFIELD org/nlogo/nvm/Job.random : Lorg/nlogo/api/MersenneTwisterFast;
          INVOKEVIRTUAL org/nlogo/api/MersenneTwisterFast.nextDouble ()D
          DMUL
         L5
          ALOAD 0
          GETFIELD org/nlogo/prim/_asm_proceduresetup_setxy_2.world : Lorg/nlogo/agent/World;
          INVOKEVIRTUAL org/nlogo/agent/World.worldHeight ()I
          I2D
         L6
          DSTORE 2
          DLOAD 2
          ALOAD 1
          GETFIELD org/nlogo/nvm/Context.job : Lorg/nlogo/nvm/Job;
          GETFIELD org/nlogo/nvm/Job.random : Lorg/nlogo/api/MersenneTwisterFast;
          INVOKEVIRTUAL org/nlogo/api/MersenneTwisterFast.nextDouble ()D
          DMUL
         L7
          DSTORE 4
          DSTORE 2
          ALOAD 1
          GETFIELD org/nlogo/nvm/Context.agent : Lorg/nlogo/agent/Agent;
          CHECKCAST org/nlogo/agent/Turtle
          ASTORE 6
         L0
          ALOAD 6
          ALOAD 6
          DLOAD 2
          INVOKEVIRTUAL org/nlogo/agent/Turtle.shortestPathX (D)D
          ALOAD 6
          DLOAD 4
          INVOKEVIRTUAL org/nlogo/agent/Turtle.shortestPathY (D)D
          INVOKEVIRTUAL org/nlogo/agent/Turtle.xandycor (DD)V
         L1
          GOTO L8
         L2
         FRAME FULL [org/nlogo/prim/_asm_proceduresetup_setxy_2 org/nlogo/nvm/Context D D org/nlogo/agent/Turtle] [org/nlogo/api/AgentException]
          ASTORE 7
          NEW org/nlogo/nvm/RuntimePrimitiveException
          DUP
          ALOAD 1
          ALOAD 0
          INVOKESTATIC org/nlogo/core/I18N.errorsJ ()Lorg/nlogo/core/I18NJava;
          LDC "org.nlogo.prim.etc._setxy.pointOutsideWorld"
          ICONST_2
          ANEWARRAY java/lang/Object
          DUP
          ICONST_0
          DLOAD 2
          INVOKESTATIC java/lang/Double.valueOf (D)Ljava/lang/Double;
          AASTORE
          DUP
          ICONST_1
          DLOAD 4
          INVOKESTATIC java/lang/Double.valueOf (D)Ljava/lang/Double;
          AASTORE
          INVOKEINTERFACE org/nlogo/core/I18NJava.getN (Ljava/lang/String;[Ljava/lang/Object;)Ljava/lang/String; (itf)
          INVOKESPECIAL org/nlogo/nvm/RuntimePrimitiveException.<init> (Lorg/nlogo/api/Context;Lorg/nlogo/nvm/Instruction;Ljava/lang/String;)V
          ATHROW
         L8
         FRAME SAME
          ALOAD 1
          ICONST_5
          PUTFIELD org/nlogo/nvm/Context.ip : I
         L9
          RETURN
[5]_asm_proceduresetup_right_3 "rt random-float 360" double => void
      _randomfloat "random-float 360" double => double
        _constdouble:360.0 "360" => double
          // parameter final  context
          // parameter final  context
          // parameter final  d
          // parameter final  context
          // parameter final  delta
         L0
          LDC 360.0D
         L1
          DSTORE 2
          DLOAD 2
          ALOAD 1
          GETFIELD org/nlogo/nvm/Context.job : Lorg/nlogo/nvm/Job;
          GETFIELD org/nlogo/nvm/Job.random : Lorg/nlogo/api/MersenneTwisterFast;
          INVOKEVIRTUAL org/nlogo/api/MersenneTwisterFast.nextDouble ()D
          DMUL
         L2
          DSTORE 2
          ALOAD 1
          GETFIELD org/nlogo/nvm/Context.agent : Lorg/nlogo/agent/Agent;
          CHECKCAST org/nlogo/agent/Turtle
          DLOAD 2
          INVOKEVIRTUAL org/nlogo/agent/Turtle.turnRight (D)V
          ALOAD 1
          BIPUSH 6
          PUTFIELD org/nlogo/nvm/Context.ip : I
         L3
          RETURN
[6]_asm_proceduresetup_done_4 => void
          // parameter final  context
         L0
          ALOAD 1
          ICONST_1
          PUTFIELD org/nlogo/nvm/Context.finished : Z
         L1
          RETURN
[7]_asm_proceduresetup_return_5 => void
          // parameter final  context
         L0
          ALOAD 1
          INVOKEVIRTUAL org/nlogo/nvm/Context.returnFromProcedure ()V
          ALOAD 1
          ICONST_0
          PUTFIELD org/nlogo/nvm/Context.stopping : Z
         L1
          RETURN

procedure GO:[]{O---}:
[0]_asm_procedurego_ask_0 "ask turtles [ flock ]" AgentSet => void
      _turtles "turtles" => AgentSet
          // parameter final  context
          // parameter final  context
          // parameter final  agents
         L0
          ALOAD 0
          GETFIELD org/nlogo/prim/_asm_procedurego_ask_0.world : Lorg/nlogo/agent/World;
          INVOKEVIRTUAL org/nlogo/agent/World.turtles ()Lorg/nlogo/agent/TreeAgentSet;
         L1
          ASTORE 2
          ALOAD 1
          GETFIELD org/nlogo/nvm/Context.agent : Lorg/nlogo/agent/Agent;
          INSTANCEOF org/nlogo/agent/Observer
          IFNE L2
          ALOAD 2
          ALOAD 0
          GETFIELD org/nlogo/prim/_asm_procedurego_ask_0.world : Lorg/nlogo/agent/World;
          INVOKEVIRTUAL org/nlogo/agent/World.turtles ()Lorg/nlogo/agent/TreeAgentSet;
          IF_ACMPNE L3
          NEW org/nlogo/nvm/RuntimePrimitiveException
          DUP
          ALOAD 1
          ALOAD 0
          GETSTATIC org/nlogo/core/I18N$.MODULE$ : Lorg/nlogo/core/I18N$;
          INVOKEVIRTUAL org/nlogo/core/I18N$.errors ()Lorg/nlogo/core/I18N$BundleKind;
          LDC "org.nlogo.prim.$common.onlyObserverCanAskAllTurtles"
          INVOKEVIRTUAL org/nlogo/core/I18N$BundleKind.get (Ljava/lang/String;)Ljava/lang/String;
          INVOKESPECIAL org/nlogo/nvm/RuntimePrimitiveException.<init> (Lorg/nlogo/api/Context;Lorg/nlogo/nvm/Instruction;Ljava/lang/String;)V
          ATHROW
         L3
         FRAME APPEND [org/nlogo/agent/TreeAgentSet]
          ALOAD 2
          ALOAD 0
          GETFIELD org/nlogo/prim/_asm_procedurego_ask_0.world : Lorg/nlogo/agent/World;
          INVOKEVIRTUAL org/nlogo/agent/World.patches ()Lorg/nlogo/agent/IndexedAgentSet;
          IF_ACMPNE L2
          NEW org/nlogo/nvm/RuntimePrimitiveException
          DUP
          ALOAD 1
          ALOAD 0
          GETSTATIC org/nlogo/core/I18N$.MODULE$ : Lorg/nlogo/core/I18N$;
          INVOKEVIRTUAL org/nlogo/core/I18N$.errors ()Lorg/nlogo/core/I18N$BundleKind;
          LDC "org.nlogo.prim.$common.onlyObserverCanAskAllPatches"
          INVOKEVIRTUAL org/nlogo/core/I18N$BundleKind.get (Ljava/lang/String;)Ljava/lang/String;
          INVOKESPECIAL org/nlogo/nvm/RuntimePrimitiveException.<init> (Lorg/nlogo/api/Context;Lorg/nlogo/nvm/Instruction;Ljava/lang/String;)V
          ATHROW
         L2
         FRAME SAME
          ALOAD 1
          ALOAD 2
          ICONST_1
          INVOKEVIRTUAL org/nlogo/nvm/Context.runExclusiveJob (Lorg/nlogo/agent/AgentSet;I)V
          ALOAD 1
          ICONST_3
          PUTFIELD org/nlogo/nvm/Context.ip : I
         L4
          RETURN
[1]_asm_procedurego_call_1 "flock"
         L0
          NEW org/nlogo/nvm/Activation
          DUP
          ALOAD 0
          GETFIELD org/nlogo/prim/_asm_procedurego_call_1.kept1_procedure : Lorg/nlogo/nvm/Procedure;
          ALOAD 1
          GETFIELD org/nlogo/nvm/Context.activation : Lorg/nlogo/nvm/Activation;
          SIPUSH 0
          ANEWARRAY java/lang/Object
          ICONST_2
          INVOKESPECIAL org/nlogo/nvm/Activation.<init> (Lorg/nlogo/nvm/Procedure;Lorg/nlogo/nvm/Activation;[Ljava/lang/Object;I)V
          ALOAD 1
          SWAP
          PUTFIELD org/nlogo/nvm/Context.activation : Lorg/nlogo/nvm/Activation;
          ALOAD 1
          ICONST_0
          PUTFIELD org/nlogo/nvm/Context.ip : I
         L1
          RETURN
[2]_asm_procedurego_done_2 => void
          // parameter final  context
         L0
          ALOAD 1
          ICONST_1
          PUTFIELD org/nlogo/nvm/Context.finished : Z
         L1
          RETURN
[3]_tick "tick"
[4]_asm_procedurego_return_3 => void
          // parameter final  context
         L0
          ALOAD 1
          INVOKEVIRTUAL org/nlogo/nvm/Context.returnFromProcedure ()V
          ALOAD 1
          ICONST_0
          PUTFIELD org/nlogo/nvm/Context.stopping : Z
         L1
          RETURN

procedure FLOCK:[]{-T--}:
[0]_asm_procedureflock_call_0 "find-flockmates"
         L0
          NEW org/nlogo/nvm/Activation
          DUP
          ALOAD 0
          GETFIELD org/nlogo/prim/_asm_procedureflock_call_0.kept1_procedure : Lorg/nlogo/nvm/Procedure;
          ALOAD 1
          GETFIELD org/nlogo/nvm/Context.activation : Lorg/nlogo/nvm/Activation;
          SIPUSH 0
          ANEWARRAY java/lang/Object
          ICONST_1
          INVOKESPECIAL org/nlogo/nvm/Activation.<init> (Lorg/nlogo/nvm/Procedure;Lorg/nlogo/nvm/Activation;[Ljava/lang/Object;I)V
          ALOAD 1
          SWAP
          PUTFIELD org/nlogo/nvm/Context.activation : Lorg/nlogo/nvm/Activation;
          ALOAD 1
          ICONST_0
          PUTFIELD org/nlogo/nvm/Context.ip : I
         L1
          RETURN
[1]_asm_procedureflock_if_1 "if any? flockmates find-nearest-neighbor [ (ifelse distance nearest-neighbor < minimum-separation [ separate ] align [ cohere ]) ]" boolean => void
      _any "any? flockmates" AgentSet => boolean
        _turtlevariable:FLOCKMATES "flockmates" => Object
          // parameter final  context
          // parameter final  context
          // parameter final  arg0
          // parameter final  context
          // parameter final  arg0
          TRYCATCHBLOCK L0 L1 L2 org/nlogo/api/AgentException
          TRYCATCHBLOCK L3 L4 L4 java/lang/ClassCastException
         L0
          ALOAD 1
          GETFIELD org/nlogo/nvm/Context.agent : Lorg/nlogo/agent/Agent;
          BIPUSH 13
          INVOKEVIRTUAL org/nlogo/agent/Agent.getTurtleVariable (I)Ljava/lang/Object;
         L1
          GOTO L5
         L2
         FRAME SAME1 org/nlogo/api/AgentException
          ASTORE 2
          NEW org/nlogo/nvm/RuntimePrimitiveException
          DUP
          ALOAD 1
          ALOAD 0
          ALOAD 2
          INVOKEVIRTUAL org/nlogo/api/AgentException.getMessage ()Ljava/lang/String;
          INVOKESPECIAL org/nlogo/nvm/RuntimePrimitiveException.<init> (Lorg/nlogo/api/Context;Lorg/nlogo/nvm/Instruction;Ljava/lang/String;)V
          ATHROW
         L5
         FRAME SAME1 java/lang/Object
          ASTORE 2
         L3
          ALOAD 2
          CHECKCAST org/nlogo/agent/AgentSet
          GOTO L6
         L4
         FRAME FULL [org/nlogo/prim/_asm_procedureflock_if_1 org/nlogo/nvm/Context java/lang/Object] [java/lang/ClassCastException]
          POP
          NEW org/nlogo/nvm/ArgumentTypeException
          DUP
          ALOAD 1
          ALOAD 0
          BIPUSH 0
          LDC 112
          ALOAD 2
          INVOKESPECIAL org/nlogo/nvm/ArgumentTypeException.<init> (Lorg/nlogo/nvm/Context;Lorg/nlogo/nvm/Instruction;IILjava/lang/Object;)V
          ATHROW
         L6
         FRAME SAME1 org/nlogo/agent/AgentSet
          ASTORE 2
          ALOAD 2
          INVOKEVIRTUAL org/nlogo/agent/AgentSet.isEmpty ()Z
          IFNE L7
          ICONST_1
          GOTO L8
         L7
         FRAME FULL [org/nlogo/prim/_asm_procedureflock_if_1 org/nlogo/nvm/Context org/nlogo/agent/AgentSet] []
          ICONST_0
         L8
         FRAME SAME1 I
          ISTORE 2
          ALOAD 1
          ILOAD 2
          IFEQ L9
          ICONST_2
          GOTO L10
         L9
         FRAME FULL [org/nlogo/prim/_asm_procedureflock_if_1 org/nlogo/nvm/Context I] [org/nlogo/nvm/Context]
          BIPUSH 8
         L10
         FRAME FULL [org/nlogo/prim/_asm_procedureflock_if_1 org/nlogo/nvm/Context I] [org/nlogo/nvm/Context I]
          PUTFIELD org/nlogo/nvm/Context.ip : I
         L11
          RETURN
[2]_asm_procedureflock_call_2 "find-nearest-neighbor"
         L0
          NEW org/nlogo/nvm/Activation
          DUP
          ALOAD 0
          GETFIELD org/nlogo/prim/_asm_procedureflock_call_2.kept1_procedure : Lorg/nlogo/nvm/Procedure;
          ALOAD 1
          GETFIELD org/nlogo/nvm/Context.activation : Lorg/nlogo/nvm/Activation;
          SIPUSH 0
          ANEWARRAY java/lang/Object
          ICONST_3
          INVOKESPECIAL org/nlogo/nvm/Activation.<init> (Lorg/nlogo/nvm/Procedure;Lorg/nlogo/nvm/Activation;[Ljava/lang/Object;I)V
          ALOAD 1
          SWAP
          PUTFIELD org/nlogo/nvm/Context.activation : Lorg/nlogo/nvm/Activation;
          ALOAD 1
          ICONST_0
          PUTFIELD org/nlogo/nvm/Context.ip : I
         L1
          RETURN
[3]_asm_procedureflock_ifelse_3 "(ifelse distance nearest-neighbor < minimum-separation [ separate ] align [ cohere ])" boolean => void
      _lessthan "distance nearest-neighbor < minimum-separation" double,Object => boolean
        _distance "distance nearest-neighbor" Agent => double
          _turtlevariable:NEAREST-NEIGHBOR "nearest-neighbor" => Object
        _observervariable:MINIMUM-SEPARATION "minimum-separation" => Object
          // parameter final  context
          // parameter final  context
          // parameter final  context
          // parameter final  arg0
          // parameter final  arg1
          // parameter final  context
          // parameter final  cond
          TRYCATCHBLOCK L0 L1 L2 org/nlogo/api/AgentException
          TRYCATCHBLOCK L3 L4 L4 java/lang/ClassCastException
         L0
          ALOAD 1
          GETFIELD org/nlogo/nvm/Context.agent : Lorg/nlogo/agent/Agent;
          BIPUSH 14
          INVOKEVIRTUAL org/nlogo/agent/Agent.getTurtleVariable (I)Ljava/lang/Object;
         L1
          GOTO L5
         L2
         FRAME SAME1 org/nlogo/api/AgentException
          ASTORE 2
          NEW org/nlogo/nvm/RuntimePrimitiveException
          DUP
          ALOAD 1
          ALOAD 0
          ALOAD 2
          INVOKEVIRTUAL org/nlogo/api/AgentException.getMessage ()Ljava/lang/String;
          INVOKESPECIAL org/nlogo/nvm/RuntimePrimitiveException.<init> (Lorg/nlogo/api/Context;Lorg/nlogo/nvm/Instruction;Ljava/lang/String;)V
          ATHROW
         L5
         FRAME SAME1 java/lang/Object
          ASTORE 2
         L3
          ALOAD 2
          CHECKCAST org/nlogo/agent/Agent
          GOTO L6
         L4
         FRAME FULL [org/nlogo/prim/_asm_procedureflock_ifelse_3 org/nlogo/nvm/Context java/lang/Object] [java/lang/ClassCastException]
          POP
          NEW org/nlogo/nvm/ArgumentTypeException
          DUP
          ALOAD 1
          ALOAD 0
          BIPUSH 0
          LDC 1792
          ALOAD 2
          INVOKESPECIAL org/nlogo/nvm/ArgumentTypeException.<init> (Lorg/nlogo/nvm/Context;Lorg/nlogo/nvm/Instruction;IILjava/lang/Object;)V
          ATHROW
         L6
         FRAME SAME1 org/nlogo/agent/Agent
          ASTORE 2
          ALOAD 2
          INSTANCEOF org/nlogo/agent/Link
          IFEQ L7
          NEW org/nlogo/nvm/RuntimePrimitiveException
          DUP
          ALOAD 1
          ALOAD 0
          INVOKESTATIC org/nlogo/core/I18N.errorsJ ()Lorg/nlogo/core/I18NJava;
          LDC "org.nlogo.prim.etc.$common.expectedTurtleOrPatchButGotLink"
          INVOKEINTERFACE org/nlogo/core/I18NJava.get (Ljava/lang/String;)Ljava/lang/String; (itf)
          INVOKESPECIAL org/nlogo/nvm/RuntimePrimitiveException.<init> (Lorg/nlogo/api/Context;Lorg/nlogo/nvm/Instruction;Ljava/lang/String;)V
          ATHROW
         L7
         FRAME FULL [org/nlogo/prim/_asm_procedureflock_ifelse_3 org/nlogo/nvm/Context org/nlogo/agent/Agent] []
          ALOAD 2
          INVOKEVIRTUAL org/nlogo/agent/Agent.id ()J
          LDC -1L
          LCMP
          IFNE L8
          NEW org/nlogo/nvm/RuntimePrimitiveException
          DUP
          ALOAD 1
          ALOAD 0
          INVOKESTATIC org/nlogo/core/I18N.errorsJ ()Lorg/nlogo/core/I18NJava;
          LDC "org.nlogo.$common.thatAgentIsDead"
          ICONST_1
          ANEWARRAY java/lang/Object
          DUP
          ICONST_0
          ALOAD 2
          INVOKEVIRTUAL org/nlogo/agent/Agent.classDisplayName ()Ljava/lang/String;
          AASTORE
          INVOKEINTERFACE org/nlogo/core/I18NJava.getN (Ljava/lang/String;[Ljava/lang/Object;)Ljava/lang/String; (itf)
          INVOKESPECIAL org/nlogo/nvm/RuntimePrimitiveException.<init> (Lorg/nlogo/api/Context;Lorg/nlogo/nvm/Instruction;Ljava/lang/String;)V
          ATHROW
         L8
         FRAME SAME
          ALOAD 0
          GETFIELD org/nlogo/prim/_asm_procedureflock_ifelse_3.world : Lorg/nlogo/agent/World;
          INVOKEVIRTUAL org/nlogo/agent/World.protractor ()Lorg/nlogo/agent/Protractor;
          ALOAD 1
          GETFIELD org/nlogo/nvm/Context.agent : Lorg/nlogo/agent/Agent;
          ALOAD 2
          ICONST_1
          INVOKEVIRTUAL org/nlogo/agent/Protractor.distance (Lorg/nlogo/api/Agent;Lorg/nlogo/api/Agent;Z)D
         L9
          ALOAD 0
          GETFIELD org/nlogo/prim/_asm_procedureflock_ifelse_3.world : Lorg/nlogo/agent/World;
          INVOKEVIRTUAL org/nlogo/agent/World.observer ()Lorg/nlogo/agent/Observer;
          ICONST_5
          INVOKEVIRTUAL org/nlogo/agent/Observer.getVariable (I)Ljava/lang/Object;
         L10
          ASTORE 4
          DSTORE 2
          ALOAD 4
          INSTANCEOF java/lang/Double
          IFEQ L11
          ALOAD 4
          CHECKCAST java/lang/Double
          ASTORE 5
          DLOAD 2
          ALOAD 5
          INVOKEVIRTUAL java/lang/Double.doubleValue ()D
          DCMPG
          IFGE L12
          ICONST_1
          GOTO L13
         L12
         FRAME FULL [org/nlogo/prim/_asm_procedureflock_ifelse_3 org/nlogo/nvm/Context D java/lang/Object java/lang/Double] []
          ICONST_0
          GOTO L13
         L11
         FRAME CHOP 1
          NEW org/nlogo/nvm/RuntimePrimitiveException
          DUP
          ALOAD 1
          ALOAD 0
          GETSTATIC org/nlogo/core/I18N$.MODULE$ : Lorg/nlogo/core/I18N$;
          INVOKEVIRTUAL org/nlogo/core/I18N$.errors ()Lorg/nlogo/core/I18N$BundleKind;
          LDC "org.nlogo.prim._lessthan.cantUseLessthanOnDifferentArgs"
          GETSTATIC scala/Predef$.MODULE$ : Lscala/Predef$;
          ICONST_2
          ANEWARRAY java/lang/Object
          DUP
          ICONST_0
          GETSTATIC org/nlogo/api/TypeNames$.MODULE$ : Lorg/nlogo/api/TypeNames$;
          DLOAD 2
          INVOKESTATIC scala/runtime/BoxesRunTime.boxToDouble (D)Ljava/lang/Double;
          INVOKEVIRTUAL org/nlogo/api/TypeNames$.aName (Ljava/lang/Object;)Ljava/lang/String;
          AASTORE
          DUP
          ICONST_1
          GETSTATIC org/nlogo/api/TypeNames$.MODULE$ : Lorg/nlogo/api/TypeNames$;
          ALOAD 4
          INVOKEVIRTUAL org/nlogo/api/TypeNames$.aName (Ljava/lang/Object;)Ljava/lang/String;
          AASTORE
          INVOKEVIRTUAL scala/Predef$.wrapRefArray ([Ljava/lang/Object;)Lscala/collection/mutable/WrappedArray;
          INVOKEVIRTUAL org/nlogo/core/I18N$BundleKind.getN (Ljava/lang/String;Lscala/collection/Seq;)Ljava/lang/String;
          INVOKESPECIAL org/nlogo/nvm/RuntimePrimitiveException.<init> (Lorg/nlogo/api/Context;Lorg/nlogo/nvm/Instruction;Ljava/lang/String;)V
          ATHROW
         L13
         FRAME FULL [org/nlogo/prim/_asm_procedureflock_ifelse_3 org/nlogo/nvm/Context D java/lang/Object java/lang/Double] [I]
          ISTORE 2
          ALOAD 1
          ILOAD 2
          IFEQ L14
          ICONST_4
          GOTO L15
         L14
         FRAME FULL [org/nlogo/prim/_asm_procedureflock_ifelse_3 org/nlogo/nvm/Context I T java/lang/Object java/lang/Double] [org/nlogo/nvm/Context]
          BIPUSH 6
         L15
         FRAME FULL [org/nlogo/prim/_asm_procedureflock_ifelse_3 org/nlogo/nvm/Context I T java/lang/Object java/lang/Double] [org/nlogo/nvm/Context I]
          PUTFIELD org/nlogo/nvm/Context.ip : I
         L16
          RETURN
[4]_asm_procedureflock_call_4 "separate"
         L0
          NEW org/nlogo/nvm/Activation
          DUP
          ALOAD 0
          GETFIELD org/nlogo/prim/_asm_procedureflock_call_4.kept1_procedure : Lorg/nlogo/nvm/Procedure;
          ALOAD 1
          GETFIELD org/nlogo/nvm/Context.activation : Lorg/nlogo/nvm/Activation;
          SIPUSH 0
          ANEWARRAY java/lang/Object
          ICONST_5
          INVOKESPECIAL org/nlogo/nvm/Activation.<init> (Lorg/nlogo/nvm/Procedure;Lorg/nlogo/nvm/Activation;[Ljava/lang/Object;I)V
          ALOAD 1
          SWAP
          PUTFIELD org/nlogo/nvm/Context.activation : Lorg/nlogo/nvm/Activation;
          ALOAD 1
          ICONST_0
          PUTFIELD org/nlogo/nvm/Context.ip : I
         L1
          RETURN
[5]_asm_procedureflock_goto_5 => void
          // parameter final  context
         L0
          ALOAD 1
          BIPUSH 8
          PUTFIELD org/nlogo/nvm/Context.ip : I
         L1
          RETURN
[6]_asm_procedureflock_call_6 "align"
         L0
          NEW org/nlogo/nvm/Activation
          DUP
          ALOAD 0
          GETFIELD org/nlogo/prim/_asm_procedureflock_call_6.kept1_procedure : Lorg/nlogo/nvm/Procedure;
          ALOAD 1
          GETFIELD org/nlogo/nvm/Context.activation : Lorg/nlogo/nvm/Activation;
          SIPUSH 0
          ANEWARRAY java/lang/Object
          BIPUSH 7
          INVOKESPECIAL org/nlogo/nvm/Activation.<init> (Lorg/nlogo/nvm/Procedure;Lorg/nlogo/nvm/Activation;[Ljava/lang/Object;I)V
          ALOAD 1
          SWAP
          PUTFIELD org/nlogo/nvm/Context.activation : Lorg/nlogo/nvm/Activation;
          ALOAD 1
          ICONST_0
          PUTFIELD org/nlogo/nvm/Context.ip : I
         L1
          RETURN
[7]_asm_procedureflock_call_7 "cohere"
         L0
          NEW org/nlogo/nvm/Activation
          DUP
          ALOAD 0
          GETFIELD org/nlogo/prim/_asm_procedureflock_call_7.kept1_procedure : Lorg/nlogo/nvm/Procedure;
          ALOAD 1
          GETFIELD org/nlogo/nvm/Context.activation : Lorg/nlogo/nvm/Activation;
          SIPUSH 0
          ANEWARRAY java/lang/Object
          BIPUSH 8
          INVOKESPECIAL org/nlogo/nvm/Activation.<init> (Lorg/nlogo/nvm/Procedure;Lorg/nlogo/nvm/Activation;[Ljava/lang/Object;I)V
          ALOAD 1
          SWAP
          PUTFIELD org/nlogo/nvm/Context.activation : Lorg/nlogo/nvm/Activation;
          ALOAD 1
          ICONST_0
          PUTFIELD org/nlogo/nvm/Context.ip : I
         L1
          RETURN
[8]_asm_procedureflock_fd1_8 "fd 1" => void
          // parameter final  context
          TRYCATCHBLOCK L0 L1 L2 org/nlogo/api/AgentException
         L0
          ALOAD 1
          GETFIELD org/nlogo/nvm/Context.agent : Lorg/nlogo/agent/Agent;
          CHECKCAST org/nlogo/agent/Turtle
          DCONST_1
          INVOKEVIRTUAL org/nlogo/agent/Turtle.jump (D)V
         L1
          GOTO L3
         L2
         FRAME SAME1 org/nlogo/api/AgentException
          POP
         L3
         FRAME SAME
          ALOAD 1
          BIPUSH 9
          PUTFIELD org/nlogo/nvm/Context.ip : I
         L4
          RETURN
[9]_asm_procedureflock_return_9 => void
          // parameter final  context
         L0
          ALOAD 1
          INVOKEVIRTUAL org/nlogo/nvm/Context.returnFromProcedure ()V
          ALOAD 1
          ICONST_0
          PUTFIELD org/nlogo/nvm/Context.stopping : Z
         L1
          RETURN

procedure FIND-FLOCKMATES:[]{-T--}:
[0]_asm_procedurefindflockmates_setturtlevariable_0 "set flockmates other turtles in-radius vision" Object => void
      _other "other turtles in-radius vision" AgentSet => AgentSet
        _inradius "turtles in-radius vision"
          _asm_procedurefindflockmates_turtles_1 "turtles" => AgentSet
                // parameter final  context
               L0
                ALOAD 0
                GETFIELD org/nlogo/prim/_asm_procedurefindflockmates_turtles_1.world : Lorg/nlogo/agent/World;
                INVOKEVIRTUAL org/nlogo/agent/World.turtles ()Lorg/nlogo/agent/TreeAgentSet;
               L1
                ARETURN
          _asm_procedurefindflockmates_observervariable_2 "vision" => Object
                // parameter final  context
               L0
                ALOAD 0
                GETFIELD org/nlogo/prim/_asm_procedurefindflockmates_observervariable_2.world : Lorg/nlogo/agent/World;
                INVOKEVIRTUAL org/nlogo/agent/World.observer ()Lorg/nlogo/agent/Observer;
                ICONST_4
                INVOKEVIRTUAL org/nlogo/agent/Observer.getVariable (I)Ljava/lang/Object;
               L1
                ARETURN
          // parameter final  context
          // parameter final  sourceSet
          // parameter final  context
          // parameter final  value
          TRYCATCHBLOCK L0 L1 L1 java/lang/ClassCastException
          TRYCATCHBLOCK L2 L3 L4 org/nlogo/api/AgentException
          ALOAD 0
          GETFIELD org/nlogo/prim/_asm_procedurefindflockmates_setturtlevariable_0.keptinstr3 : Lorg/nlogo/prim/_inradius;
          ALOAD 1
          INVOKEVIRTUAL org/nlogo/prim/_inradius.report (Lorg/nlogo/nvm/Context;)Ljava/lang/Object;
         L5
          ASTORE 2
         L0
          ALOAD 2
          CHECKCAST org/nlogo/agent/AgentSet
          GOTO L6
         L1
         FRAME FULL [org/nlogo/prim/_asm_procedurefindflockmates_setturtlevariable_0 org/nlogo/nvm/Context java/lang/Object] [java/lang/ClassCastException]
          POP
          NEW org/nlogo/nvm/ArgumentTypeException
          DUP
          ALOAD 1
          ALOAD 0
          BIPUSH 0
          LDC 112
          ALOAD 2
          INVOKESPECIAL org/nlogo/nvm/ArgumentTypeException.<init> (Lorg/nlogo/nvm/Context;Lorg/nlogo/nvm/Instruction;IILjava/lang/Object;)V
          ATHROW
         L6
         FRAME SAME1 org/nlogo/agent/AgentSet
          ASTORE 2
          NEW org/nlogo/agent/AgentSetBuilder
          DUP
          ALOAD 2
          INVOKEVIRTUAL org/nlogo/agent/AgentSet.kind ()Lorg/nlogo/core/AgentKind;
          ALOAD 2
          INVOKEVIRTUAL org/nlogo/agent/AgentSet.count ()I
          INVOKESPECIAL org/nlogo/agent/AgentSetBuilder.<init> (Lorg/nlogo/core/AgentKind;I)V
          ASTORE 3
          ALOAD 2
          INVOKEVIRTUAL org/nlogo/agent/AgentSet.iterator ()Lorg/nlogo/agent/AgentIterator;
          ASTORE 4
         L7
         FRAME FULL [org/nlogo/prim/_asm_procedurefindflockmates_setturtlevariable_0 org/nlogo/nvm/Context org/nlogo/agent/AgentSet org/nlogo/agent/AgentSetBuilder org/nlogo/agent/AgentIterator] []
          ALOAD 4
          INVOKEINTERFACE org/nlogo/agent/AgentIterator.hasNext ()Z (itf)
          IFEQ L8
          ALOAD 4
          INVOKEINTERFACE org/nlogo/agent/AgentIterator.next ()Lorg/nlogo/agent/Agent; (itf)
          ASTORE 5
          ALOAD 1
          GETFIELD org/nlogo/nvm/Context.agent : Lorg/nlogo/agent/Agent;
          ALOAD 5
          IF_ACMPEQ L7
          ALOAD 3
          ALOAD 5
          INVOKEVIRTUAL org/nlogo/agent/AgentSetBuilder.add (Lorg/nlogo/agent/Agent;)V
          GOTO L7
         L8
         FRAME SAME
          ALOAD 3
          INVOKEVIRTUAL org/nlogo/agent/AgentSetBuilder.build ()Lorg/nlogo/agent/IndexedAgentSet;
         L9
          ASTORE 2
         L2
          ALOAD 1
          GETFIELD org/nlogo/nvm/Context.agent : Lorg/nlogo/agent/Agent;
          BIPUSH 13
          ALOAD 2
          INVOKEVIRTUAL org/nlogo/agent/Agent.setTurtleVariable (ILjava/lang/Object;)V
         L3
          GOTO L10
         L4
         FRAME FULL [org/nlogo/prim/_asm_procedurefindflockmates_setturtlevariable_0 org/nlogo/nvm/Context org/nlogo/agent/IndexedAgentSet org/nlogo/agent/AgentSetBuilder org/nlogo/agent/AgentIterator] [org/nlogo/api/AgentException]
          ASTORE 3
          NEW org/nlogo/nvm/RuntimePrimitiveException
          DUP
          ALOAD 1
          ALOAD 0
          ALOAD 3
          INVOKEVIRTUAL org/nlogo/api/AgentException.getMessage ()Ljava/lang/String;
          INVOKESPECIAL org/nlogo/nvm/RuntimePrimitiveException.<init> (Lorg/nlogo/api/Context;Lorg/nlogo/nvm/Instruction;Ljava/lang/String;)V
          ATHROW
         L10
         FRAME SAME
          ALOAD 1
          ICONST_1
          PUTFIELD org/nlogo/nvm/Context.ip : I
         L11
          RETURN
[1]_asm_procedurefindflockmates_return_3 => void
          // parameter final  context
         L0
          ALOAD 1
          INVOKEVIRTUAL org/nlogo/nvm/Context.returnFromProcedure ()V
          ALOAD 1
          ICONST_0
          PUTFIELD org/nlogo/nvm/Context.stopping : Z
         L1
          RETURN

procedure FIND-NEAREST-NEIGHBOR:[]{-T--}:
[0]_asm_procedurefindnearestneighbor_setturtlevariable_0 "set nearest-neighbor min-one-of flockmates [ distance myself ]" Object => void
      _minoneof "min-one-of flockmates [ distance myself ]"
        _asm_procedurefindnearestneighbor_turtlevariable_1 "flockmates" => Object
              // parameter final  context
              TRYCATCHBLOCK L0 L1 L2 org/nlogo/api/AgentException
             L0
              ALOAD 1
              GETFIELD org/nlogo/nvm/Context.agent : Lorg/nlogo/agent/Agent;
              BIPUSH 13
              INVOKEVIRTUAL org/nlogo/agent/Agent.getTurtleVariable (I)Ljava/lang/Object;
             L1
              GOTO L3
             L2
             FRAME SAME1 org/nlogo/api/AgentException
              ASTORE 2
              NEW org/nlogo/nvm/RuntimePrimitiveException
              DUP
              ALOAD 1
              ALOAD 0
              ALOAD 2
              INVOKEVIRTUAL org/nlogo/api/AgentException.getMessage ()Ljava/lang/String;
              INVOKESPECIAL org/nlogo/nvm/RuntimePrimitiveException.<init> (Lorg/nlogo/api/Context;Lorg/nlogo/nvm/Instruction;Ljava/lang/String;)V
              ATHROW
             L3
             FRAME SAME1 java/lang/Object
              ARETURN
        _asm_procedurefindnearestneighbor_distance_2 "distance myself" Agent => double
          _myself "myself" => Agent
             L0
              ALOAD 1
              INVOKEVIRTUAL org/nlogo/nvm/Context.myself ()Lorg/nlogo/agent/Agent;
              ASTORE 2
              ALOAD 2
              IFNULL L1
              ALOAD 2
              INSTANCEOF org/nlogo/agent/Observer
              IFEQ L2
             L1
             FRAME APPEND [org/nlogo/agent/Agent]
              NEW org/nlogo/nvm/RuntimePrimitiveException
              DUP
              ALOAD 1
              ALOAD 0
              INVOKESTATIC org/nlogo/core/I18N.errorsJ ()Lorg/nlogo/core/I18NJava;
              LDC "org.nlogo.prim.etc._myself.noAgentMyself"
              INVOKEINTERFACE org/nlogo/core/I18NJava.get (Ljava/lang/String;)Ljava/lang/String; (itf)
              INVOKESPECIAL org/nlogo/nvm/RuntimePrimitiveException.<init> (Lorg/nlogo/api/Context;Lorg/nlogo/nvm/Instruction;Ljava/lang/String;)V
              ATHROW
             L2
             FRAME SAME
              ALOAD 2
             L3
              ASTORE 2
              ALOAD 2
              INSTANCEOF org/nlogo/agent/Link
              IFEQ L4
              NEW org/nlogo/nvm/RuntimePrimitiveException
              DUP
              ALOAD 1
              ALOAD 0
              INVOKESTATIC org/nlogo/core/I18N.errorsJ ()Lorg/nlogo/core/I18NJava;
              LDC "org.nlogo.prim.etc.$common.expectedTurtleOrPatchButGotLink"
              INVOKEINTERFACE org/nlogo/core/I18NJava.get (Ljava/lang/String;)Ljava/lang/String; (itf)
              INVOKESPECIAL org/nlogo/nvm/RuntimePrimitiveException.<init> (Lorg/nlogo/api/Context;Lorg/nlogo/nvm/Instruction;Ljava/lang/String;)V
              ATHROW
             L4
             FRAME SAME
              ALOAD 2
              INVOKEVIRTUAL org/nlogo/agent/Agent.id ()J
              LDC -1L
              LCMP
              IFNE L5
              NEW org/nlogo/nvm/RuntimePrimitiveException
              DUP
              ALOAD 1
              ALOAD 0
              INVOKESTATIC org/nlogo/core/I18N.errorsJ ()Lorg/nlogo/core/I18NJava;
              LDC "org.nlogo.$common.thatAgentIsDead"
              ICONST_1
              ANEWARRAY java/lang/Object
              DUP
              ICONST_0
              ALOAD 2
              INVOKEVIRTUAL org/nlogo/agent/Agent.classDisplayName ()Ljava/lang/String;
              AASTORE
              INVOKEINTERFACE org/nlogo/core/I18NJava.getN (Ljava/lang/String;[Ljava/lang/Object;)Ljava/lang/String; (itf)
              INVOKESPECIAL org/nlogo/nvm/RuntimePrimitiveException.<init> (Lorg/nlogo/api/Context;Lorg/nlogo/nvm/Instruction;Ljava/lang/String;)V
              ATHROW
             L5
             FRAME SAME
              ALOAD 0
              GETFIELD org/nlogo/prim/_asm_procedurefindnearestneighbor_distance_2.world : Lorg/nlogo/agent/World;
              INVOKEVIRTUAL org/nlogo/agent/World.protractor ()Lorg/nlogo/agent/Protractor;
              ALOAD 1
              GETFIELD org/nlogo/nvm/Context.agent : Lorg/nlogo/agent/Agent;
              ALOAD 2
              ICONST_1
              INVOKEVIRTUAL org/nlogo/agent/Protractor.distance (Lorg/nlogo/api/Agent;Lorg/nlogo/api/Agent;Z)D
             L6
              DSTORE 2
              NEW java/lang/Double
              DUP
              DLOAD 2
              INVOKESPECIAL java/lang/Double.<init> (D)V
              ARETURN
          // parameter final  context
          // parameter final  value
          TRYCATCHBLOCK L0 L1 L2 org/nlogo/api/AgentException
          ALOAD 0
          GETFIELD org/nlogo/prim/_asm_procedurefindnearestneighbor_setturtlevariable_0.keptinstr2 : Lorg/nlogo/prim/etc/_minoneof;
          ALOAD 1
          INVOKEVIRTUAL org/nlogo/prim/etc/_minoneof.report (Lorg/nlogo/nvm/Context;)Ljava/lang/Object;
         L3
          ASTORE 2
         L0
          ALOAD 1
          GETFIELD org/nlogo/nvm/Context.agent : Lorg/nlogo/agent/Agent;
          BIPUSH 14
          ALOAD 2
          INVOKEVIRTUAL org/nlogo/agent/Agent.setTurtleVariable (ILjava/lang/Object;)V
         L1
          GOTO L4
         L2
         FRAME FULL [org/nlogo/prim/_asm_procedurefindnearestneighbor_setturtlevariable_0 org/nlogo/nvm/Context java/lang/Object] [org/nlogo/api/AgentException]
          ASTORE 3
          NEW org/nlogo/nvm/RuntimePrimitiveException
          DUP
          ALOAD 1
          ALOAD 0
          ALOAD 3
          INVOKEVIRTUAL org/nlogo/api/AgentException.getMessage ()Ljava/lang/String;
          INVOKESPECIAL org/nlogo/nvm/RuntimePrimitiveException.<init> (Lorg/nlogo/api/Context;Lorg/nlogo/nvm/Instruction;Ljava/lang/String;)V
          ATHROW
         L4
         FRAME SAME
          ALOAD 1
          ICONST_1
          PUTFIELD org/nlogo/nvm/Context.ip : I
         L5
          RETURN
[1]_asm_procedurefindnearestneighbor_return_3 => void
          // parameter final  context
         L0
          ALOAD 1
          INVOKEVIRTUAL org/nlogo/nvm/Context.returnFromProcedure ()V
          ALOAD 1
          ICONST_0
          PUTFIELD org/nlogo/nvm/Context.stopping : Z
         L1
          RETURN

procedure SEPARATE:[]{-T--}:
[0]_asm_procedureseparate_call_0 "turn-away [ heading ] of nearest-neighbor max-separate-turn"
      _turtlevariableof:HEADING "[ heading ] of nearest-neighbor" Object => Object
        _turtlevariable:NEAREST-NEIGHBOR "nearest-neighbor" => Object
      _observervariable:MAX-SEPARATE-TURN "max-separate-turn" => Object
          // parameter final  context
          // parameter final  context
          // parameter final  agentOrSet
          // parameter final  context
          TRYCATCHBLOCK L0 L1 L2 org/nlogo/api/AgentException
          TRYCATCHBLOCK L3 L4 L4 org/nlogo/api/AgentException
         L5
          NEW org/nlogo/nvm/Activation
          DUP
          ALOAD 0
          GETFIELD org/nlogo/prim/_asm_procedureseparate_call_0.kept1_procedure : Lorg/nlogo/nvm/Procedure;
          ALOAD 1
          GETFIELD org/nlogo/nvm/Context.activation : Lorg/nlogo/nvm/Activation;
          SIPUSH 2
          ANEWARRAY java/lang/Object
          DUP
          ICONST_0
         L0
          ALOAD 1
          GETFIELD org/nlogo/nvm/Context.agent : Lorg/nlogo/agent/Agent;
          BIPUSH 14
          INVOKEVIRTUAL org/nlogo/agent/Agent.getTurtleVariable (I)Ljava/lang/Object;
         L1
          GOTO L6
         L2
         FRAME SAME1 org/nlogo/api/AgentException
          ASTORE 2
          NEW org/nlogo/nvm/RuntimePrimitiveException
          DUP
          ALOAD 1
          ALOAD 0
          ALOAD 2
          INVOKEVIRTUAL org/nlogo/api/AgentException.getMessage ()Ljava/lang/String;
          INVOKESPECIAL org/nlogo/nvm/RuntimePrimitiveException.<init> (Lorg/nlogo/api/Context;Lorg/nlogo/nvm/Instruction;Ljava/lang/String;)V
          ATHROW
         L6
         FRAME FULL [org/nlogo/prim/_asm_procedureseparate_call_0 org/nlogo/nvm/Context] [L5 L5 org/nlogo/nvm/Procedure org/nlogo/nvm/Activation [Ljava/lang/Object; [Ljava/lang/Object; I java/lang/Object]
          ASTORE 2
         L3
          ALOAD 2
          INSTANCEOF org/nlogo/agent/Agent
          IFEQ L7
          ALOAD 2
          CHECKCAST org/nlogo/agent/Agent
          ASTORE 3
          ALOAD 3
          INVOKEVIRTUAL org/nlogo/agent/Agent.id ()J
          LDC -1L
          LCMP
          IFNE L8
          NEW org/nlogo/nvm/RuntimePrimitiveException
          DUP
          ALOAD 1
          ALOAD 0
          GETSTATIC org/nlogo/core/I18N$.MODULE$ : Lorg/nlogo/core/I18N$;
          INVOKEVIRTUAL org/nlogo/core/I18N$.errors ()Lorg/nlogo/core/I18N$BundleKind;
          LDC "org.nlogo.$common.thatAgentIsDead"
          GETSTATIC scala/Predef$.MODULE$ : Lscala/Predef$;
          ICONST_1
          ANEWARRAY java/lang/Object
          DUP
          ICONST_0
          ALOAD 3
          INVOKEVIRTUAL org/nlogo/agent/Agent.classDisplayName ()Ljava/lang/String;
          AASTORE
          INVOKEVIRTUAL scala/Predef$.wrapRefArray ([Ljava/lang/Object;)Lscala/collection/mutable/WrappedArray;
          INVOKEVIRTUAL org/nlogo/core/I18N$BundleKind.getN (Ljava/lang/String;Lscala/collection/Seq;)Ljava/lang/String;
          INVOKESPECIAL org/nlogo/nvm/RuntimePrimitiveException.<init> (Lorg/nlogo/api/Context;Lorg/nlogo/nvm/Instruction;Ljava/lang/String;)V
          ATHROW
         L8
         FRAME FULL [org/nlogo/prim/_asm_procedureseparate_call_0 org/nlogo/nvm/Context java/lang/Object org/nlogo/agent/Agent] [L5 L5 org/nlogo/nvm/Procedure org/nlogo/nvm/Activation [Ljava/lang/Object; [Ljava/lang/Object; I]
          ALOAD 3
          ICONST_2
          INVOKEVIRTUAL org/nlogo/agent/Agent.getTurtleVariable (I)Ljava/lang/Object;
          GOTO L9
         L7
         FRAME FULL [org/nlogo/prim/_asm_procedureseparate_call_0 org/nlogo/nvm/Context java/lang/Object] [L5 L5 org/nlogo/nvm/Procedure org/nlogo/nvm/Activation [Ljava/lang/Object; [Ljava/lang/Object; I]
          ALOAD 2
          INSTANCEOF org/nlogo/agent/AgentSet
          IFEQ L10
          ALOAD 2
          CHECKCAST org/nlogo/agent/AgentSet
          ASTORE 4
          NEW org/nlogo/api/LogoListBuilder
          DUP
          INVOKESPECIAL org/nlogo/api/LogoListBuilder.<init> ()V
          ASTORE 5
          ALOAD 4
          ALOAD 1
          GETFIELD org/nlogo/nvm/Context.job : Lorg/nlogo/nvm/Job;
          GETFIELD org/nlogo/nvm/Job.random : Lorg/nlogo/api/MersenneTwisterFast;
          INVOKEVIRTUAL org/nlogo/agent/AgentSet.shufflerator (Lorg/nlogo/api/MersenneTwisterFast;)Lorg/nlogo/agent/AgentIterator;
          ASTORE 6
         L11
         FRAME FULL [org/nlogo/prim/_asm_procedureseparate_call_0 org/nlogo/nvm/Context java/lang/Object T org/nlogo/agent/AgentSet org/nlogo/api/LogoListBuilder org/nlogo/agent/AgentIterator] [L5 L5 org/nlogo/nvm/Procedure org/nlogo/nvm/Activation [Ljava/lang/Object; [Ljava/lang/Object; I]
          ALOAD 6
          INVOKEINTERFACE org/nlogo/agent/AgentIterator.hasNext ()Z (itf)
          IFEQ L12
          ALOAD 5
          ALOAD 6
          INVOKEINTERFACE org/nlogo/agent/AgentIterator.next ()Lorg/nlogo/agent/Agent; (itf)
          ICONST_2
          INVOKEVIRTUAL org/nlogo/agent/Agent.getTurtleVariable (I)Ljava/lang/Object;
          INVOKEVIRTUAL org/nlogo/api/LogoListBuilder.add (Ljava/lang/Object;)V
          GOTO L11
         L12
         FRAME FULL [org/nlogo/prim/_asm_procedureseparate_call_0 org/nlogo/nvm/Context java/lang/Object T org/nlogo/agent/AgentSet org/nlogo/api/LogoListBuilder org/nlogo/agent/AgentIterator] [L5 L5 org/nlogo/nvm/Procedure org/nlogo/nvm/Activation [Ljava/lang/Object; [Ljava/lang/Object; I]
          ALOAD 5
          INVOKEVIRTUAL org/nlogo/api/LogoListBuilder.toLogoList ()Lorg/nlogo/core/LogoList;
          GOTO L9
         L10
         FRAME FULL [org/nlogo/prim/_asm_procedureseparate_call_0 org/nlogo/nvm/Context java/lang/Object] [L5 L5 org/nlogo/nvm/Procedure org/nlogo/nvm/Activation [Ljava/lang/Object; [Ljava/lang/Object; I]
          NEW org/nlogo/nvm/ArgumentTypeException
          DUP
          ALOAD 1
          ALOAD 0
          ICONST_0
          GETSTATIC org/nlogo/core/Syntax$.MODULE$ : Lorg/nlogo/core/Syntax$;
          INVOKEVIRTUAL org/nlogo/core/Syntax$.TurtlesetType ()I
          GETSTATIC org/nlogo/core/Syntax$.MODULE$ : Lorg/nlogo/core/Syntax$;
          INVOKEVIRTUAL org/nlogo/core/Syntax$.TurtleType ()I
          IOR
          ALOAD 2
          INVOKESPECIAL org/nlogo/nvm/ArgumentTypeException.<init> (Lorg/nlogo/nvm/Context;Lorg/nlogo/nvm/Instruction;IILjava/lang/Object;)V
          ATHROW
         L4
         FRAME SAME1 org/nlogo/api/AgentException
          ASTORE 7
          NEW org/nlogo/nvm/RuntimePrimitiveException
          DUP
          ALOAD 1
          ALOAD 0
          ALOAD 7
          INVOKEVIRTUAL org/nlogo/api/AgentException.getMessage ()Ljava/lang/String;
          INVOKESPECIAL org/nlogo/nvm/RuntimePrimitiveException.<init> (Lorg/nlogo/api/Context;Lorg/nlogo/nvm/Instruction;Ljava/lang/String;)V
          ATHROW
         L9
         FRAME FULL [org/nlogo/prim/_asm_procedureseparate_call_0 org/nlogo/nvm/Context java/lang/Object] [L5 L5 org/nlogo/nvm/Procedure org/nlogo/nvm/Activation [Ljava/lang/Object; [Ljava/lang/Object; I java/lang/Object]
          AASTORE
          DUP
          ICONST_1
         L13
          ALOAD 0
          GETFIELD org/nlogo/prim/_asm_procedureseparate_call_0.world : Lorg/nlogo/agent/World;
          INVOKEVIRTUAL org/nlogo/agent/World.observer ()Lorg/nlogo/agent/Observer;
          ICONST_3
          INVOKEVIRTUAL org/nlogo/agent/Observer.getVariable (I)Ljava/lang/Object;
         L14
          AASTORE
          ICONST_1
          INVOKESPECIAL org/nlogo/nvm/Activation.<init> (Lorg/nlogo/nvm/Procedure;Lorg/nlogo/nvm/Activation;[Ljava/lang/Object;I)V
          ALOAD 1
          SWAP
          PUTFIELD org/nlogo/nvm/Context.activation : Lorg/nlogo/nvm/Activation;
          ALOAD 1
          ICONST_0
          PUTFIELD org/nlogo/nvm/Context.ip : I
         L15
          RETURN
[1]_asm_procedureseparate_return_1 => void
          // parameter final  context
         L0
          ALOAD 1
          INVOKEVIRTUAL org/nlogo/nvm/Context.returnFromProcedure ()V
          ALOAD 1
          ICONST_0
          PUTFIELD org/nlogo/nvm/Context.stopping : Z
         L1
          RETURN

procedure ALIGN:[]{-T--}:
[0]_asm_procedurealign_call_0 "turn-towards average-flockmate-heading max-align-turn"
      _callreport:AVERAGE-FLOCKMATE-HEADING "average-flockmate-heading"
      _observervariable:MAX-ALIGN-TURN "max-align-turn" => Object
          // parameter final  context
         L0
          NEW org/nlogo/nvm/Activation
          DUP
          ALOAD 0
          GETFIELD org/nlogo/prim/_asm_procedurealign_call_0.kept1_procedure : Lorg/nlogo/nvm/Procedure;
          ALOAD 1
          GETFIELD org/nlogo/nvm/Context.activation : Lorg/nlogo/nvm/Activation;
          SIPUSH 2
          ANEWARRAY java/lang/Object
          DUP
          ICONST_0
         L1
          NEW org/nlogo/nvm/Activation
          DUP
          ALOAD 0
          GETFIELD org/nlogo/prim/_asm_procedurealign_call_0.kept2_procedure : Lorg/nlogo/nvm/Procedure;
          ALOAD 1
          GETFIELD org/nlogo/nvm/Context.activation : Lorg/nlogo/nvm/Activation;
          SIPUSH 0
          ANEWARRAY java/lang/Object
          ICONST_0
          INVOKESPECIAL org/nlogo/nvm/Activation.<init> (Lorg/nlogo/nvm/Procedure;Lorg/nlogo/nvm/Activation;[Ljava/lang/Object;I)V
          ALOAD 1
          SWAP
          INVOKEVIRTUAL org/nlogo/nvm/Context.callReporterProcedure (Lorg/nlogo/nvm/Activation;)Ljava/lang/Object;
          DUP
          IFNONNULL L2
          NEW org/nlogo/nvm/RuntimePrimitiveException
          DUP
          ALOAD 1
          ALOAD 0
          LDC "the AVERAGE-FLOCKMATE-HEADING procedure failed to report a result"
          INVOKESPECIAL org/nlogo/nvm/RuntimePrimitiveException.<init> (Lorg/nlogo/api/Context;Lorg/nlogo/nvm/Instruction;Ljava/lang/String;)V
          ATHROW
         L2
         FRAME FULL [org/nlogo/prim/_asm_procedurealign_call_0 org/nlogo/nvm/Context] [L0 L0 org/nlogo/nvm/Procedure org/nlogo/nvm/Activation [Ljava/lang/Object; [Ljava/lang/Object; I java/lang/Object]
          AASTORE
          DUP
          ICONST_1
         L3
          ALOAD 0
          GETFIELD org/nlogo/prim/_asm_procedurealign_call_0.world : Lorg/nlogo/agent/World;
          INVOKEVIRTUAL org/nlogo/agent/World.observer ()Lorg/nlogo/agent/Observer;
          ICONST_1
          INVOKEVIRTUAL org/nlogo/agent/Observer.getVariable (I)Ljava/lang/Object;
         L4
          AASTORE
          ICONST_1
          INVOKESPECIAL org/nlogo/nvm/Activation.<init> (Lorg/nlogo/nvm/Procedure;Lorg/nlogo/nvm/Activation;[Ljava/lang/Object;I)V
          ALOAD 1
          SWAP
          PUTFIELD org/nlogo/nvm/Context.activation : Lorg/nlogo/nvm/Activation;
          ALOAD 1
          ICONST_0
          PUTFIELD org/nlogo/nvm/Context.ip : I
         L5
          RETURN
[1]_asm_procedurealign_return_1 => void
          // parameter final  context
         L0
          ALOAD 1
          INVOKEVIRTUAL org/nlogo/nvm/Context.returnFromProcedure ()V
          ALOAD 1
          ICONST_0
          PUTFIELD org/nlogo/nvm/Context.stopping : Z
         L1
          RETURN

reporter procedure AVERAGE-FLOCKMATE-HEADING:[]{-T--}:
[0]_asm_procedureaverageflockmateheading_report_0 "report atan mean [ sin heading ] of flockmates mean [ cos heading ] of flockmates" Object => void
      _atan "atan mean [ sin heading ] of flockmates mean [ cos heading ] of flockmates" double,double => double
        _mean "mean [ sin heading ] of flockmates" LogoList => double
          _of "[ sin heading ] of flockmates"
            _asm_procedureaverageflockmateheading_sin_1 "sin heading" double => double
              _turtlevariabledouble:HEADING "heading" => double
                  // parameter final  context
                  // parameter final  context
                  // parameter final  arg0
                 L0
                  ALOAD 1
                  GETFIELD org/nlogo/nvm/Context.agent : Lorg/nlogo/agent/Agent;
                  CHECKCAST org/nlogo/agent/Turtle
                  ICONST_2
                  INVOKEVIRTUAL org/nlogo/agent/Turtle.getTurtleVariableDouble (I)D
                 L1
                  DSTORE 2
                  DLOAD 2
                  INVOKESTATIC java/lang/StrictMath.toRadians (D)D
                  INVOKESTATIC java/lang/StrictMath.sin (D)D
                 L2
                  DSTORE 2
                  NEW java/lang/Double
                  DUP
                  DLOAD 2
                  INVOKESPECIAL java/lang/Double.<init> (D)V
                  ARETURN
            _asm_procedureaverageflockmateheading_turtlevariable_2 "flockmates" => Object
                  // parameter final  context
                  TRYCATCHBLOCK L0 L1 L2 org/nlogo/api/AgentException
                 L0
                  ALOAD 1
                  GETFIELD org/nlogo/nvm/Context.agent : Lorg/nlogo/agent/Agent;
                  BIPUSH 13
                  INVOKEVIRTUAL org/nlogo/agent/Agent.getTurtleVariable (I)Ljava/lang/Object;
                 L1
                  GOTO L3
                 L2
                 FRAME SAME1 org/nlogo/api/AgentException
                  ASTORE 2
                  NEW org/nlogo/nvm/RuntimePrimitiveException
                  DUP
                  ALOAD 1
                  ALOAD 0
                  ALOAD 2
                  INVOKEVIRTUAL org/nlogo/api/AgentException.getMessage ()Ljava/lang/String;
                  INVOKESPECIAL org/nlogo/nvm/RuntimePrimitiveException.<init> (Lorg/nlogo/api/Context;Lorg/nlogo/nvm/Instruction;Ljava/lang/String;)V
                  ATHROW
                 L3
                 FRAME SAME1 java/lang/Object
                  ARETURN
        _mean "mean [ cos heading ] of flockmates" LogoList => double
          _of "[ cos heading ] of flockmates"
            _asm_procedureaverageflockmateheading_cos_3 "cos heading" double => double
              _turtlevariabledouble:HEADING "heading" => double
                  // parameter final  context
                  // parameter final  context
                  // parameter final  arg0
                 L0
                  ALOAD 1
                  GETFIELD org/nlogo/nvm/Context.agent : Lorg/nlogo/agent/Agent;
                  CHECKCAST org/nlogo/agent/Turtle
                  ICONST_2
                  INVOKEVIRTUAL org/nlogo/agent/Turtle.getTurtleVariableDouble (I)D
                 L1
                  DSTORE 2
                  DLOAD 2
                  INVOKESTATIC java/lang/StrictMath.toRadians (D)D
                  INVOKESTATIC java/lang/StrictMath.cos (D)D
                 L2
                  DSTORE 2
                  NEW java/lang/Double
                  DUP
                  DLOAD 2
                  INVOKESPECIAL java/lang/Double.<init> (D)V
                  ARETURN
            _asm_procedureaverageflockmateheading_turtlevariable_4 "flockmates" => Object
                  // parameter final  context
                  TRYCATCHBLOCK L0 L1 L2 org/nlogo/api/AgentException
                 L0
                  ALOAD 1
                  GETFIELD org/nlogo/nvm/Context.agent : Lorg/nlogo/agent/Agent;
                  BIPUSH 13
                  INVOKEVIRTUAL org/nlogo/agent/Agent.getTurtleVariable (I)Ljava/lang/Object;
                 L1
                  GOTO L3
                 L2
                 FRAME SAME1 org/nlogo/api/AgentException
                  ASTORE 2
                  NEW org/nlogo/nvm/RuntimePrimitiveException
                  DUP
                  ALOAD 1
                  ALOAD 0
                  ALOAD 2
                  INVOKEVIRTUAL org/nlogo/api/AgentException.getMessage ()Ljava/lang/String;
                  INVOKESPECIAL org/nlogo/nvm/RuntimePrimitiveException.<init> (Lorg/nlogo/api/Context;Lorg/nlogo/nvm/Instruction;Ljava/lang/String;)V
                  ATHROW
                 L3
                 FRAME SAME1 java/lang/Object
                  ARETURN
          // parameter final  context
          // parameter final  d1
          // parameter final  d2
          TRYCATCHBLOCK L0 L1 L1 java/lang/ClassCastException
          TRYCATCHBLOCK L2 L3 L3 java/lang/ClassCastException
          ALOAD 0
          GETFIELD org/nlogo/prim/_asm_procedureaverageflockmateheading_report_0.keptinstr4 : Lorg/nlogo/prim/_of;
          ALOAD 1
          INVOKEVIRTUAL org/nlogo/prim/_of.report (Lorg/nlogo/nvm/Context;)Ljava/lang/Object;
         L4
          ASTORE 2
         L0
          ALOAD 2
          CHECKCAST org/nlogo/core/LogoList
          GOTO L5
         L1
         FRAME FULL [org/nlogo/prim/_asm_procedureaverageflockmateheading_report_0 org/nlogo/nvm/Context java/lang/Object] [java/lang/ClassCastException]
          POP
          NEW org/nlogo/nvm/ArgumentTypeException
          DUP
          ALOAD 1
          ALOAD 0
          BIPUSH 0
          LDC 8
          ALOAD 2
          INVOKESPECIAL org/nlogo/nvm/ArgumentTypeException.<init> (Lorg/nlogo/nvm/Context;Lorg/nlogo/nvm/Instruction;IILjava/lang/Object;)V
          ATHROW
         L5
         FRAME SAME1 org/nlogo/core/LogoList
          ASTORE 2
          DCONST_0
          DSTORE 3
          ICONST_0
          ISTORE 5
          ALOAD 2
          INVOKEVIRTUAL org/nlogo/core/LogoList.toJava ()Ljava/util/AbstractSequentialList;
          INVOKEVIRTUAL java/util/AbstractSequentialList.iterator ()Ljava/util/Iterator;
          ASTORE 6
         L6
         FRAME FULL [org/nlogo/prim/_asm_procedureaverageflockmateheading_report_0 org/nlogo/nvm/Context org/nlogo/core/LogoList D I java/util/Iterator] []
          ALOAD 6
          INVOKEINTERFACE java/util/Iterator.hasNext ()Z (itf)
          IFEQ L7
          ALOAD 6
          INVOKEINTERFACE java/util/Iterator.next ()Ljava/lang/Object; (itf)
          ASTORE 7
          ALOAD 7
          INSTANCEOF java/lang/Double
          IFEQ L8
          DLOAD 3
          ALOAD 7
          CHECKCAST java/lang/Double
          INVOKEVIRTUAL java/lang/Double.doubleValue ()D
          DADD
          DSTORE 3
          IINC 5 1
         L8
         FRAME APPEND [java/lang/Object]
          GOTO L6
         L7
         FRAME CHOP 1
          ILOAD 5
          IFNE L9
          INVOKESTATIC org/nlogo/core/I18N.errorsJ ()Lorg/nlogo/core/I18NJava;
          LDC "org.nlogo.prim.etc._mean.cantFindMeanOfListWithNoNumbers"
          ICONST_1
          ANEWARRAY java/lang/Object
          DUP
          ICONST_0
          ALOAD 2
          INVOKESTATIC org/nlogo/api/Dump.logoObject (Ljava/lang/Object;)Ljava/lang/String;
          AASTORE
          INVOKEINTERFACE org/nlogo/core/I18NJava.getN (Ljava/lang/String;[Ljava/lang/Object;)Ljava/lang/String; (itf)
          ASTORE 6
          NEW org/nlogo/nvm/RuntimePrimitiveException
          DUP
          ALOAD 1
          ALOAD 0
          ALOAD 6
          INVOKESPECIAL org/nlogo/nvm/RuntimePrimitiveException.<init> (Lorg/nlogo/api/Context;Lorg/nlogo/nvm/Instruction;Ljava/lang/String;)V
          ATHROW
         L9
         FRAME SAME
          ALOAD 0
          DLOAD 3
          ILOAD 5
          I2D
          DDIV
          ALOAD 1
          INVOKEVIRTUAL org/nlogo/prim/_asm_procedureaverageflockmateheading_report_0.validDouble (DLorg/nlogo/nvm/Context;)D
         L10
          ALOAD 0
          GETFIELD org/nlogo/prim/_asm_procedureaverageflockmateheading_report_0.keptinstr6 : Lorg/nlogo/prim/_of;
          ALOAD 1
          INVOKEVIRTUAL org/nlogo/prim/_of.report (Lorg/nlogo/nvm/Context;)Ljava/lang/Object;
         L11
          ASTORE 2
         L2
          ALOAD 2
          CHECKCAST org/nlogo/core/LogoList
          GOTO L12
         L3
         FRAME FULL [org/nlogo/prim/_asm_procedureaverageflockmateheading_report_0 org/nlogo/nvm/Context java/lang/Object D I java/util/Iterator] [java/lang/ClassCastException]
          POP
          NEW org/nlogo/nvm/ArgumentTypeException
          DUP
          ALOAD 1
          ALOAD 0
          BIPUSH 0
          LDC 8
          ALOAD 2
          INVOKESPECIAL org/nlogo/nvm/ArgumentTypeException.<init> (Lorg/nlogo/nvm/Context;Lorg/nlogo/nvm/Instruction;IILjava/lang/Object;)V
          ATHROW
         L12
         FRAME FULL [org/nlogo/prim/_asm_procedureaverageflockmateheading_report_0 org/nlogo/nvm/Context java/lang/Object D I java/util/Iterator] [D org/nlogo/core/LogoList]
          ASTORE 2
          DCONST_0
          DSTORE 3
          ICONST_0
          ISTORE 5
          ALOAD 2
          INVOKEVIRTUAL org/nlogo/core/LogoList.toJava ()Ljava/util/AbstractSequentialList;
          INVOKEVIRTUAL java/util/AbstractSequentialList.iterator ()Ljava/util/Iterator;
          ASTORE 6
         L13
         FRAME FULL [org/nlogo/prim/_asm_procedureaverageflockmateheading_report_0 org/nlogo/nvm/Context org/nlogo/core/LogoList D I java/util/Iterator] [D]
          ALOAD 6
          INVOKEINTERFACE java/util/Iterator.hasNext ()Z (itf)
          IFEQ L14
          ALOAD 6
          INVOKEINTERFACE java/util/Iterator.next ()Ljava/lang/Object; (itf)
          ASTORE 7
          ALOAD 7
          INSTANCEOF java/lang/Double
          IFEQ L15
          DLOAD 3
          ALOAD 7
          CHECKCAST java/lang/Double
          INVOKEVIRTUAL java/lang/Double.doubleValue ()D
          DADD
          DSTORE 3
          IINC 5 1
         L15
         FRAME FULL [org/nlogo/prim/_asm_procedureaverageflockmateheading_report_0 org/nlogo/nvm/Context org/nlogo/core/LogoList D I java/util/Iterator java/lang/Object] [D]
          GOTO L13
         L14
         FRAME FULL [org/nlogo/prim/_asm_procedureaverageflockmateheading_report_0 org/nlogo/nvm/Context org/nlogo/core/LogoList D I java/util/Iterator] [D]
          ILOAD 5
          IFNE L16
          INVOKESTATIC org/nlogo/core/I18N.errorsJ ()Lorg/nlogo/core/I18NJava;
          LDC "org.nlogo.prim.etc._mean.cantFindMeanOfListWithNoNumbers"
          ICONST_1
          ANEWARRAY java/lang/Object
          DUP
          ICONST_0
          ALOAD 2
          INVOKESTATIC org/nlogo/api/Dump.logoObject (Ljava/lang/Object;)Ljava/lang/String;
          AASTORE
          INVOKEINTERFACE org/nlogo/core/I18NJava.getN (Ljava/lang/String;[Ljava/lang/Object;)Ljava/lang/String; (itf)
          ASTORE 6
          NEW org/nlogo/nvm/RuntimePrimitiveException
          DUP
          ALOAD 1
          ALOAD 0
          ALOAD 6
          INVOKESPECIAL org/nlogo/nvm/RuntimePrimitiveException.<init> (Lorg/nlogo/api/Context;Lorg/nlogo/nvm/Instruction;Ljava/lang/String;)V
          ATHROW
         L16
         FRAME SAME1 D
          ALOAD 0
          DLOAD 3
          ILOAD 5
          I2D
          DDIV
          ALOAD 1
          INVOKEVIRTUAL org/nlogo/prim/_asm_procedureaverageflockmateheading_report_0.validDouble (DLorg/nlogo/nvm/Context;)D
         L17
          DSTORE 4
          DSTORE 2
          DLOAD 2
          ICONST_0
          I2D
          DCMPL
          IFNE L18
          DLOAD 4
          ICONST_0
          I2D
          DCMPL
          IFNE L18
          NEW org/nlogo/nvm/RuntimePrimitiveException
          DUP
          ALOAD 1
          ALOAD 0
          GETSTATIC org/nlogo/core/I18N$.MODULE$ : Lorg/nlogo/core/I18N$;
          INVOKEVIRTUAL org/nlogo/core/I18N$.errors ()Lorg/nlogo/core/I18N$BundleKind;
          LDC "org.nlogo.prim.etc.atan.bothInputsCannotBeZero"
          INVOKEVIRTUAL org/nlogo/core/I18N$BundleKind.get (Ljava/lang/String;)Ljava/lang/String;
          INVOKESPECIAL org/nlogo/nvm/RuntimePrimitiveException.<init> (Lorg/nlogo/api/Context;Lorg/nlogo/nvm/Instruction;Ljava/lang/String;)V
          ATHROW
         L18
         FRAME FULL [org/nlogo/prim/_asm_procedureaverageflockmateheading_report_0 org/nlogo/nvm/Context D D java/util/Iterator] []
          DLOAD 2
          ICONST_0
          I2D
          DCMPL
          IFNE L19
          DLOAD 4
          ICONST_0
          I2D
          DCMPL
          IFLE L20
          DCONST_0
          GOTO L21
         L20
         FRAME SAME
          LDC 180.0D
          GOTO L21
         L19
         FRAME SAME
          DLOAD 4
          ICONST_0
          I2D
          DCMPL
          IFNE L22
          DLOAD 2
          ICONST_0
          I2D
          DCMPL
          IFLE L23
          LDC 90.0D
          GOTO L21
         L23
         FRAME SAME
          LDC 270.0D
          GOTO L21
         L22
         FRAME SAME
          ALOAD 0
          DLOAD 2
          DLOAD 4
          INVOKESTATIC java/lang/StrictMath.atan2 (DD)D
          INVOKESTATIC java/lang/StrictMath.toDegrees (D)D
          SIPUSH 360
          I2D
          DADD
          ALOAD 1
          INVOKEVIRTUAL org/nlogo/prim/_asm_procedureaverageflockmateheading_report_0.validDouble (DLorg/nlogo/nvm/Context;)D
          SIPUSH 360
          I2D
          DREM
         L21
         FRAME SAME1 D
          DSTORE 2
          NEW java/lang/Double
          DUP
          DLOAD 2
          INVOKESPECIAL java/lang/Double.<init> (D)V
          ASTORE 2
          ALOAD 1
          GETFIELD org/nlogo/nvm/Context.job : Lorg/nlogo/nvm/Job;
          ALOAD 2
          PUTFIELD org/nlogo/nvm/Job.result : Ljava/lang/Object;
          ALOAD 1
          ICONST_0
          PUTFIELD org/nlogo/nvm/Context.stopping : Z
          ALOAD 1
          ICONST_1
          PUTFIELD org/nlogo/nvm/Context.ip : I
          ALOAD 1
          GETFIELD org/nlogo/nvm/Context.activation : Lorg/nlogo/nvm/Activation;
          INVOKEVIRTUAL org/nlogo/nvm/Activation.nonLambdaActivation ()Lorg/nlogo/nvm/Activation;
          GETFIELD org/nlogo/nvm/Activation.procedure : Lorg/nlogo/nvm/Procedure;
          INVOKEVIRTUAL org/nlogo/nvm/Procedure.isReporter ()Z
          IFNE L24
          NEW org/nlogo/nvm/RuntimePrimitiveException
          DUP
          ALOAD 1
          ALOAD 0
          INVOKESTATIC org/nlogo/core/I18N.errorsJ ()Lorg/nlogo/core/I18NJava;
          LDC "org.nlogo.prim._report.canOnlyUseInToReport"
          ICONST_1
          ANEWARRAY java/lang/Object
          DUP
          ICONST_0
          LDC "REPORT"
          AASTORE
          INVOKEINTERFACE org/nlogo/core/I18NJava.getN (Ljava/lang/String;[Ljava/lang/Object;)Ljava/lang/String; (itf)
          INVOKESPECIAL org/nlogo/nvm/RuntimePrimitiveException.<init> (Lorg/nlogo/api/Context;Lorg/nlogo/nvm/Instruction;Ljava/lang/String;)V
          ATHROW
         L24
         FRAME FULL [org/nlogo/prim/_asm_procedureaverageflockmateheading_report_0 org/nlogo/nvm/Context java/lang/Double T D java/util/Iterator] []
          ALOAD 1
          GETFIELD org/nlogo/nvm/Context.activation : Lorg/nlogo/nvm/Activation;
          GETFIELD org/nlogo/nvm/Activation.procedure : Lorg/nlogo/nvm/Procedure;
          INVOKEVIRTUAL org/nlogo/nvm/Procedure.isLambda ()Z
          IFEQ L25
          NEW org/nlogo/nvm/NonLocalExit
          DUP
          INVOKESPECIAL org/nlogo/nvm/NonLocalExit.<init> ()V
          ATHROW
         L25
         FRAME SAME
          ALOAD 1
          INVOKEVIRTUAL org/nlogo/nvm/Context.atTopActivation ()Z
          IFNE L26
          NEW org/nlogo/nvm/RuntimePrimitiveException
          DUP
          ALOAD 1
          ALOAD 0
          INVOKESTATIC org/nlogo/core/I18N.errorsJ ()Lorg/nlogo/core/I18NJava;
          LDC "org.nlogo.prim._report.mustImmediatelyBeUsedInToReport"
          ICONST_1
          ANEWARRAY java/lang/Object
          DUP
          ICONST_0
          LDC "REPORT"
          AASTORE
          INVOKEINTERFACE org/nlogo/core/I18NJava.getN (Ljava/lang/String;[Ljava/lang/Object;)Ljava/lang/String; (itf)
          INVOKESPECIAL org/nlogo/nvm/RuntimePrimitiveException.<init> (Lorg/nlogo/api/Context;Lorg/nlogo/nvm/Instruction;Ljava/lang/String;)V
          ATHROW
         L26
         FRAME SAME
          RETURN
[1]_asm_procedureaverageflockmateheading_returnreport_5 => void
          // parameter final  context
         L0
          NEW org/nlogo/nvm/RuntimePrimitiveException
          DUP
          ALOAD 1
          ALOAD 0
          GETSTATIC org/nlogo/core/I18N$.MODULE$ : Lorg/nlogo/core/I18N$;
          INVOKEVIRTUAL org/nlogo/core/I18N$.errors ()Lorg/nlogo/core/I18N$BundleKind;
          LDC "org.nlogo.prim._returnreport.reportNotCalledInReportProcedure"
          INVOKEVIRTUAL org/nlogo/core/I18N$BundleKind.get (Ljava/lang/String;)Ljava/lang/String;
          INVOKESPECIAL org/nlogo/nvm/RuntimePrimitiveException.<init> (Lorg/nlogo/api/Context;Lorg/nlogo/nvm/Instruction;Ljava/lang/String;)V
          ATHROW
         L1
         FRAME FULL [] [java/lang/Throwable]
          ATHROW

procedure COHERE:[]{-T--}:
[0]_asm_procedurecohere_call_0 "turn-towards average-heading-towards-flockmates max-cohere-turn"
      _callreport:AVERAGE-HEADING-TOWARDS-FLOCKMATES "average-heading-towards-flockmates"
      _observervariable:MAX-COHERE-TURN "max-cohere-turn" => Object
          // parameter final  context
         L0
          NEW org/nlogo/nvm/Activation
          DUP
          ALOAD 0
          GETFIELD org/nlogo/prim/_asm_procedurecohere_call_0.kept1_procedure : Lorg/nlogo/nvm/Procedure;
          ALOAD 1
          GETFIELD org/nlogo/nvm/Context.activation : Lorg/nlogo/nvm/Activation;
          SIPUSH 2
          ANEWARRAY java/lang/Object
          DUP
          ICONST_0
         L1
          NEW org/nlogo/nvm/Activation
          DUP
          ALOAD 0
          GETFIELD org/nlogo/prim/_asm_procedurecohere_call_0.kept2_procedure : Lorg/nlogo/nvm/Procedure;
          ALOAD 1
          GETFIELD org/nlogo/nvm/Context.activation : Lorg/nlogo/nvm/Activation;
          SIPUSH 0
          ANEWARRAY java/lang/Object
          ICONST_0
          INVOKESPECIAL org/nlogo/nvm/Activation.<init> (Lorg/nlogo/nvm/Procedure;Lorg/nlogo/nvm/Activation;[Ljava/lang/Object;I)V
          ALOAD 1
          SWAP
          INVOKEVIRTUAL org/nlogo/nvm/Context.callReporterProcedure (Lorg/nlogo/nvm/Activation;)Ljava/lang/Object;
          DUP
          IFNONNULL L2
          NEW org/nlogo/nvm/RuntimePrimitiveException
          DUP
          ALOAD 1
          ALOAD 0
          LDC "the AVERAGE-HEADING-TOWARDS-FLOCKMATES procedure failed to report a result"
          INVOKESPECIAL org/nlogo/nvm/RuntimePrimitiveException.<init> (Lorg/nlogo/api/Context;Lorg/nlogo/nvm/Instruction;Ljava/lang/String;)V
          ATHROW
         L2
         FRAME FULL [org/nlogo/prim/_asm_procedurecohere_call_0 org/nlogo/nvm/Context] [L0 L0 org/nlogo/nvm/Procedure org/nlogo/nvm/Activation [Ljava/lang/Object; [Ljava/lang/Object; I java/lang/Object]
          AASTORE
          DUP
          ICONST_1
         L3
          ALOAD 0
          GETFIELD org/nlogo/prim/_asm_procedurecohere_call_0.world : Lorg/nlogo/agent/World;
          INVOKEVIRTUAL org/nlogo/agent/World.observer ()Lorg/nlogo/agent/Observer;
          ICONST_2
          INVOKEVIRTUAL org/nlogo/agent/Observer.getVariable (I)Ljava/lang/Object;
         L4
          AASTORE
          ICONST_1
          INVOKESPECIAL org/nlogo/nvm/Activation.<init> (Lorg/nlogo/nvm/Procedure;Lorg/nlogo/nvm/Activation;[Ljava/lang/Object;I)V
          ALOAD 1
          SWAP
          PUTFIELD org/nlogo/nvm/Context.activation : Lorg/nlogo/nvm/Activation;
          ALOAD 1
          ICONST_0
          PUTFIELD org/nlogo/nvm/Context.ip : I
         L5
          RETURN
[1]_asm_procedurecohere_return_1 => void
          // parameter final  context
         L0
          ALOAD 1
          INVOKEVIRTUAL org/nlogo/nvm/Context.returnFromProcedure ()V
          ALOAD 1
          ICONST_0
          PUTFIELD org/nlogo/nvm/Context.stopping : Z
         L1
          RETURN

reporter procedure AVERAGE-HEADING-TOWARDS-FLOCKMATES:[]{-T--}:
[0]_asm_procedureaverageheadingtowardsflockmates_report_0 "report atan mean [ sin towards myself + 180 ] of flockmates mean [ cos towards myself + 180 ] of flockmates" Object => void
      _atan "atan mean [ sin towards myself + 180 ] of flockmates mean [ cos towards myself + 180 ] of flockmates" double,double => double
        _mean "mean [ sin towards myself + 180 ] of flockmates" LogoList => double
          _of "[ sin towards myself + 180 ] of flockmates"
            _asm_procedureaverageheadingtowardsflockmates_sin_1 "sin towards myself + 180" double => double
              _plus "towards myself + 180" double,double => double
                _towards "towards myself"
                  _asm_procedureaverageheadingtowardsflockmates_myself_2 "myself" => Agent
                       L0
                        ALOAD 1
                        INVOKEVIRTUAL org/nlogo/nvm/Context.myself ()Lorg/nlogo/agent/Agent;
                        ASTORE 2
                        ALOAD 2
                        IFNULL L1
                        ALOAD 2
                        INSTANCEOF org/nlogo/agent/Observer
                        IFEQ L2
                       L1
                       FRAME APPEND [org/nlogo/agent/Agent]
                        NEW org/nlogo/nvm/RuntimePrimitiveException
                        DUP
                        ALOAD 1
                        ALOAD 0
                        INVOKESTATIC org/nlogo/core/I18N.errorsJ ()Lorg/nlogo/core/I18NJava;
                        LDC "org.nlogo.prim.etc._myself.noAgentMyself"
                        INVOKEINTERFACE org/nlogo/core/I18NJava.get (Ljava/lang/String;)Ljava/lang/String; (itf)
                        INVOKESPECIAL org/nlogo/nvm/RuntimePrimitiveException.<init> (Lorg/nlogo/api/Context;Lorg/nlogo/nvm/Instruction;Ljava/lang/String;)V
                        ATHROW
                       L2
                       FRAME SAME
                        ALOAD 2
                       L3
                        ARETURN
                _constdouble:180.0 "180" => double
                  // parameter final  context
                  // parameter final  context
                  // parameter final  d1
                  // parameter final  d2
                  // parameter final  context
                  // parameter final  arg0
                  TRYCATCHBLOCK L0 L1 L1 java/lang/ClassCastException
                  ALOAD 0
                  GETFIELD org/nlogo/prim/_asm_procedureaverageheadingtowardsflockmates_sin_1.keptinstr3 : Lorg/nlogo/prim/etc/_towards;
                  ALOAD 1
                  INVOKEVIRTUAL org/nlogo/prim/etc/_towards.report (Lorg/nlogo/nvm/Context;)Ljava/lang/Object;
                 L2
                  ASTORE 2
                 L0
                  ALOAD 2
                  CHECKCAST java/lang/Double
                  INVOKEVIRTUAL java/lang/Double.doubleValue ()D
                  GOTO L3
                 L1
                 FRAME FULL [org/nlogo/prim/_asm_procedureaverageheadingtowardsflockmates_sin_1 org/nlogo/nvm/Context java/lang/Object] [java/lang/ClassCastException]
                  POP
                  NEW org/nlogo/nvm/ArgumentTypeException
                  DUP
                  ALOAD 1
                  ALOAD 0
                  BIPUSH 0
                  LDC 1
                  ALOAD 2
                  INVOKESPECIAL org/nlogo/nvm/ArgumentTypeException.<init> (Lorg/nlogo/nvm/Context;Lorg/nlogo/nvm/Instruction;IILjava/lang/Object;)V
                  ATHROW
                 L3
                 FRAME SAME1 D
                  LDC 180.0D
                 L4
                  DSTORE 4
                  DSTORE 2
                  DLOAD 2
                  DLOAD 4
                  DADD
                 L5
                  DSTORE 2
                  DLOAD 2
                  INVOKESTATIC java/lang/StrictMath.toRadians (D)D
                  INVOKESTATIC java/lang/StrictMath.sin (D)D
                 L6
                  DSTORE 2
                  NEW java/lang/Double
                  DUP
                  DLOAD 2
                  INVOKESPECIAL java/lang/Double.<init> (D)V
                  ARETURN
            _asm_procedureaverageheadingtowardsflockmates_turtlevariable_3 "flockmates" => Object
                  // parameter final  context
                  TRYCATCHBLOCK L0 L1 L2 org/nlogo/api/AgentException
                 L0
                  ALOAD 1
                  GETFIELD org/nlogo/nvm/Context.agent : Lorg/nlogo/agent/Agent;
                  BIPUSH 13
                  INVOKEVIRTUAL org/nlogo/agent/Agent.getTurtleVariable (I)Ljava/lang/Object;
                 L1
                  GOTO L3
                 L2
                 FRAME SAME1 org/nlogo/api/AgentException
                  ASTORE 2
                  NEW org/nlogo/nvm/RuntimePrimitiveException
                  DUP
                  ALOAD 1
                  ALOAD 0
                  ALOAD 2
                  INVOKEVIRTUAL org/nlogo/api/AgentException.getMessage ()Ljava/lang/String;
                  INVOKESPECIAL org/nlogo/nvm/RuntimePrimitiveException.<init> (Lorg/nlogo/api/Context;Lorg/nlogo/nvm/Instruction;Ljava/lang/String;)V
                  ATHROW
                 L3
                 FRAME SAME1 java/lang/Object
                  ARETURN
        _mean "mean [ cos towards myself + 180 ] of flockmates" LogoList => double
          _of "[ cos towards myself + 180 ] of flockmates"
            _asm_procedureaverageheadingtowardsflockmates_cos_4 "cos towards myself + 180" double => double
              _plus "towards myself + 180" double,double => double
                _towards "towards myself"
                  _asm_procedureaverageheadingtowardsflockmates_myself_5 "myself" => Agent
                       L0
                        ALOAD 1
                        INVOKEVIRTUAL org/nlogo/nvm/Context.myself ()Lorg/nlogo/agent/Agent;
                        ASTORE 2
                        ALOAD 2
                        IFNULL L1
                        ALOAD 2
                        INSTANCEOF org/nlogo/agent/Observer
                        IFEQ L2
                       L1
                       FRAME APPEND [org/nlogo/agent/Agent]
                        NEW org/nlogo/nvm/RuntimePrimitiveException
                        DUP
                        ALOAD 1
                        ALOAD 0
                        INVOKESTATIC org/nlogo/core/I18N.errorsJ ()Lorg/nlogo/core/I18NJava;
                        LDC "org.nlogo.prim.etc._myself.noAgentMyself"
                        INVOKEINTERFACE org/nlogo/core/I18NJava.get (Ljava/lang/String;)Ljava/lang/String; (itf)
                        INVOKESPECIAL org/nlogo/nvm/RuntimePrimitiveException.<init> (Lorg/nlogo/api/Context;Lorg/nlogo/nvm/Instruction;Ljava/lang/String;)V
                        ATHROW
                       L2
                       FRAME SAME
                        ALOAD 2
                       L3
                        ARETURN
                _constdouble:180.0 "180" => double
                  // parameter final  context
                  // parameter final  context
                  // parameter final  d1
                  // parameter final  d2
                  // parameter final  context
                  // parameter final  arg0
                  TRYCATCHBLOCK L0 L1 L1 java/lang/ClassCastException
                  ALOAD 0
                  GETFIELD org/nlogo/prim/_asm_procedureaverageheadingtowardsflockmates_cos_4.keptinstr3 : Lorg/nlogo/prim/etc/_towards;
                  ALOAD 1
                  INVOKEVIRTUAL org/nlogo/prim/etc/_towards.report (Lorg/nlogo/nvm/Context;)Ljava/lang/Object;
                 L2
                  ASTORE 2
                 L0
                  ALOAD 2
                  CHECKCAST java/lang/Double
                  INVOKEVIRTUAL java/lang/Double.doubleValue ()D
                  GOTO L3
                 L1
                 FRAME FULL [org/nlogo/prim/_asm_procedureaverageheadingtowardsflockmates_cos_4 org/nlogo/nvm/Context java/lang/Object] [java/lang/ClassCastException]
                  POP
                  NEW org/nlogo/nvm/ArgumentTypeException
                  DUP
                  ALOAD 1
                  ALOAD 0
                  BIPUSH 0
                  LDC 1
                  ALOAD 2
                  INVOKESPECIAL org/nlogo/nvm/ArgumentTypeException.<init> (Lorg/nlogo/nvm/Context;Lorg/nlogo/nvm/Instruction;IILjava/lang/Object;)V
                  ATHROW
                 L3
                 FRAME SAME1 D
                  LDC 180.0D
                 L4
                  DSTORE 4
                  DSTORE 2
                  DLOAD 2
                  DLOAD 4
                  DADD
                 L5
                  DSTORE 2
                  DLOAD 2
                  INVOKESTATIC java/lang/StrictMath.toRadians (D)D
                  INVOKESTATIC java/lang/StrictMath.cos (D)D
                 L6
                  DSTORE 2
                  NEW java/lang/Double
                  DUP
                  DLOAD 2
                  INVOKESPECIAL java/lang/Double.<init> (D)V
                  ARETURN
            _asm_procedureaverageheadingtowardsflockmates_turtlevariable_6 "flockmates" => Object
                  // parameter final  context
                  TRYCATCHBLOCK L0 L1 L2 org/nlogo/api/AgentException
                 L0
                  ALOAD 1
                  GETFIELD org/nlogo/nvm/Context.agent : Lorg/nlogo/agent/Agent;
                  BIPUSH 13
                  INVOKEVIRTUAL org/nlogo/agent/Agent.getTurtleVariable (I)Ljava/lang/Object;
                 L1
                  GOTO L3
                 L2
                 FRAME SAME1 org/nlogo/api/AgentException
                  ASTORE 2
                  NEW org/nlogo/nvm/RuntimePrimitiveException
                  DUP
                  ALOAD 1
                  ALOAD 0
                  ALOAD 2
                  INVOKEVIRTUAL org/nlogo/api/AgentException.getMessage ()Ljava/lang/String;
                  INVOKESPECIAL org/nlogo/nvm/RuntimePrimitiveException.<init> (Lorg/nlogo/api/Context;Lorg/nlogo/nvm/Instruction;Ljava/lang/String;)V
                  ATHROW
                 L3
                 FRAME SAME1 java/lang/Object
                  ARETURN
          // parameter final  context
          // parameter final  d1
          // parameter final  d2
          TRYCATCHBLOCK L0 L1 L1 java/lang/ClassCastException
          TRYCATCHBLOCK L2 L3 L3 java/lang/ClassCastException
          ALOAD 0
          GETFIELD org/nlogo/prim/_asm_procedureaverageheadingtowardsflockmates_report_0.keptinstr4 : Lorg/nlogo/prim/_of;
          ALOAD 1
          INVOKEVIRTUAL org/nlogo/prim/_of.report (Lorg/nlogo/nvm/Context;)Ljava/lang/Object;
         L4
          ASTORE 2
         L0
          ALOAD 2
          CHECKCAST org/nlogo/core/LogoList
          GOTO L5
         L1
         FRAME FULL [org/nlogo/prim/_asm_procedureaverageheadingtowardsflockmates_report_0 org/nlogo/nvm/Context java/lang/Object] [java/lang/ClassCastException]
          POP
          NEW org/nlogo/nvm/ArgumentTypeException
          DUP
          ALOAD 1
          ALOAD 0
          BIPUSH 0
          LDC 8
          ALOAD 2
          INVOKESPECIAL org/nlogo/nvm/ArgumentTypeException.<init> (Lorg/nlogo/nvm/Context;Lorg/nlogo/nvm/Instruction;IILjava/lang/Object;)V
          ATHROW
         L5
         FRAME SAME1 org/nlogo/core/LogoList
          ASTORE 2
          DCONST_0
          DSTORE 3
          ICONST_0
          ISTORE 5
          ALOAD 2
          INVOKEVIRTUAL org/nlogo/core/LogoList.toJava ()Ljava/util/AbstractSequentialList;
          INVOKEVIRTUAL java/util/AbstractSequentialList.iterator ()Ljava/util/Iterator;
          ASTORE 6
         L6
         FRAME FULL [org/nlogo/prim/_asm_procedureaverageheadingtowardsflockmates_report_0 org/nlogo/nvm/Context org/nlogo/core/LogoList D I java/util/Iterator] []
          ALOAD 6
          INVOKEINTERFACE java/util/Iterator.hasNext ()Z (itf)
          IFEQ L7
          ALOAD 6
          INVOKEINTERFACE java/util/Iterator.next ()Ljava/lang/Object; (itf)
          ASTORE 7
          ALOAD 7
          INSTANCEOF java/lang/Double
          IFEQ L8
          DLOAD 3
          ALOAD 7
          CHECKCAST java/lang/Double
          INVOKEVIRTUAL java/lang/Double.doubleValue ()D
          DADD
          DSTORE 3
          IINC 5 1
         L8
         FRAME APPEND [java/lang/Object]
          GOTO L6
         L7
         FRAME CHOP 1
          ILOAD 5
          IFNE L9
          INVOKESTATIC org/nlogo/core/I18N.errorsJ ()Lorg/nlogo/core/I18NJava;
          LDC "org.nlogo.prim.etc._mean.cantFindMeanOfListWithNoNumbers"
          ICONST_1
          ANEWARRAY java/lang/Object
          DUP
          ICONST_0
          ALOAD 2
          INVOKESTATIC org/nlogo/api/Dump.logoObject (Ljava/lang/Object;)Ljava/lang/String;
          AASTORE
          INVOKEINTERFACE org/nlogo/core/I18NJava.getN (Ljava/lang/String;[Ljava/lang/Object;)Ljava/lang/String; (itf)
          ASTORE 6
          NEW org/nlogo/nvm/RuntimePrimitiveException
          DUP
          ALOAD 1
          ALOAD 0
          ALOAD 6
          INVOKESPECIAL org/nlogo/nvm/RuntimePrimitiveException.<init> (Lorg/nlogo/api/Context;Lorg/nlogo/nvm/Instruction;Ljava/lang/String;)V
          ATHROW
         L9
         FRAME SAME
          ALOAD 0
          DLOAD 3
          ILOAD 5
          I2D
          DDIV
          ALOAD 1
          INVOKEVIRTUAL org/nlogo/prim/_asm_procedureaverageheadingtowardsflockmates_report_0.validDouble (DLorg/nlogo/nvm/Context;)D
         L10
          ALOAD 0
          GETFIELD org/nlogo/prim/_asm_procedureaverageheadingtowardsflockmates_report_0.keptinstr6 : Lorg/nlogo/prim/_of;
          ALOAD 1
          INVOKEVIRTUAL org/nlogo/prim/_of.report (Lorg/nlogo/nvm/Context;)Ljava/lang/Object;
         L11
          ASTORE 2
         L2
          ALOAD 2
          CHECKCAST org/nlogo/core/LogoList
          GOTO L12
         L3
         FRAME FULL [org/nlogo/prim/_asm_procedureaverageheadingtowardsflockmates_report_0 org/nlogo/nvm/Context java/lang/Object D I java/util/Iterator] [java/lang/ClassCastException]
          POP
          NEW org/nlogo/nvm/ArgumentTypeException
          DUP
          ALOAD 1
          ALOAD 0
          BIPUSH 0
          LDC 8
          ALOAD 2
          INVOKESPECIAL org/nlogo/nvm/ArgumentTypeException.<init> (Lorg/nlogo/nvm/Context;Lorg/nlogo/nvm/Instruction;IILjava/lang/Object;)V
          ATHROW
         L12
         FRAME FULL [org/nlogo/prim/_asm_procedureaverageheadingtowardsflockmates_report_0 org/nlogo/nvm/Context java/lang/Object D I java/util/Iterator] [D org/nlogo/core/LogoList]
          ASTORE 2
          DCONST_0
          DSTORE 3
          ICONST_0
          ISTORE 5
          ALOAD 2
          INVOKEVIRTUAL org/nlogo/core/LogoList.toJava ()Ljava/util/AbstractSequentialList;
          INVOKEVIRTUAL java/util/AbstractSequentialList.iterator ()Ljava/util/Iterator;
          ASTORE 6
         L13
         FRAME FULL [org/nlogo/prim/_asm_procedureaverageheadingtowardsflockmates_report_0 org/nlogo/nvm/Context org/nlogo/core/LogoList D I java/util/Iterator] [D]
          ALOAD 6
          INVOKEINTERFACE java/util/Iterator.hasNext ()Z (itf)
          IFEQ L14
          ALOAD 6
          INVOKEINTERFACE java/util/Iterator.next ()Ljava/lang/Object; (itf)
          ASTORE 7
          ALOAD 7
          INSTANCEOF java/lang/Double
          IFEQ L15
          DLOAD 3
          ALOAD 7
          CHECKCAST java/lang/Double
          INVOKEVIRTUAL java/lang/Double.doubleValue ()D
          DADD
          DSTORE 3
          IINC 5 1
         L15
         FRAME FULL [org/nlogo/prim/_asm_procedureaverageheadingtowardsflockmates_report_0 org/nlogo/nvm/Context org/nlogo/core/LogoList D I java/util/Iterator java/lang/Object] [D]
          GOTO L13
         L14
         FRAME FULL [org/nlogo/prim/_asm_procedureaverageheadingtowardsflockmates_report_0 org/nlogo/nvm/Context org/nlogo/core/LogoList D I java/util/Iterator] [D]
          ILOAD 5
          IFNE L16
          INVOKESTATIC org/nlogo/core/I18N.errorsJ ()Lorg/nlogo/core/I18NJava;
          LDC "org.nlogo.prim.etc._mean.cantFindMeanOfListWithNoNumbers"
          ICONST_1
          ANEWARRAY java/lang/Object
          DUP
          ICONST_0
          ALOAD 2
          INVOKESTATIC org/nlogo/api/Dump.logoObject (Ljava/lang/Object;)Ljava/lang/String;
          AASTORE
          INVOKEINTERFACE org/nlogo/core/I18NJava.getN (Ljava/lang/String;[Ljava/lang/Object;)Ljava/lang/String; (itf)
          ASTORE 6
          NEW org/nlogo/nvm/RuntimePrimitiveException
          DUP
          ALOAD 1
          ALOAD 0
          ALOAD 6
          INVOKESPECIAL org/nlogo/nvm/RuntimePrimitiveException.<init> (Lorg/nlogo/api/Context;Lorg/nlogo/nvm/Instruction;Ljava/lang/String;)V
          ATHROW
         L16
         FRAME SAME1 D
          ALOAD 0
          DLOAD 3
          ILOAD 5
          I2D
          DDIV
          ALOAD 1
          INVOKEVIRTUAL org/nlogo/prim/_asm_procedureaverageheadingtowardsflockmates_report_0.validDouble (DLorg/nlogo/nvm/Context;)D
         L17
          DSTORE 4
          DSTORE 2
          DLOAD 2
          ICONST_0
          I2D
          DCMPL
          IFNE L18
          DLOAD 4
          ICONST_0
          I2D
          DCMPL
          IFNE L18
          NEW org/nlogo/nvm/RuntimePrimitiveException
          DUP
          ALOAD 1
          ALOAD 0
          GETSTATIC org/nlogo/core/I18N$.MODULE$ : Lorg/nlogo/core/I18N$;
          INVOKEVIRTUAL org/nlogo/core/I18N$.errors ()Lorg/nlogo/core/I18N$BundleKind;
          LDC "org.nlogo.prim.etc.atan.bothInputsCannotBeZero"
          INVOKEVIRTUAL org/nlogo/core/I18N$BundleKind.get (Ljava/lang/String;)Ljava/lang/String;
          INVOKESPECIAL org/nlogo/nvm/RuntimePrimitiveException.<init> (Lorg/nlogo/api/Context;Lorg/nlogo/nvm/Instruction;Ljava/lang/String;)V
          ATHROW
         L18
         FRAME FULL [org/nlogo/prim/_asm_procedureaverageheadingtowardsflockmates_report_0 org/nlogo/nvm/Context D D java/util/Iterator] []
          DLOAD 2
          ICONST_0
          I2D
          DCMPL
          IFNE L19
          DLOAD 4
          ICONST_0
          I2D
          DCMPL
          IFLE L20
          DCONST_0
          GOTO L21
         L20
         FRAME SAME
          LDC 180.0D
          GOTO L21
         L19
         FRAME SAME
          DLOAD 4
          ICONST_0
          I2D
          DCMPL
          IFNE L22
          DLOAD 2
          ICONST_0
          I2D
          DCMPL
          IFLE L23
          LDC 90.0D
          GOTO L21
         L23
         FRAME SAME
          LDC 270.0D
          GOTO L21
         L22
         FRAME SAME
          ALOAD 0
          DLOAD 2
          DLOAD 4
          INVOKESTATIC java/lang/StrictMath.atan2 (DD)D
          INVOKESTATIC java/lang/StrictMath.toDegrees (D)D
          SIPUSH 360
          I2D
          DADD
          ALOAD 1
          INVOKEVIRTUAL org/nlogo/prim/_asm_procedureaverageheadingtowardsflockmates_report_0.validDouble (DLorg/nlogo/nvm/Context;)D
          SIPUSH 360
          I2D
          DREM
         L21
         FRAME SAME1 D
          DSTORE 2
          NEW java/lang/Double
          DUP
          DLOAD 2
          INVOKESPECIAL java/lang/Double.<init> (D)V
          ASTORE 2
          ALOAD 1
          GETFIELD org/nlogo/nvm/Context.job : Lorg/nlogo/nvm/Job;
          ALOAD 2
          PUTFIELD org/nlogo/nvm/Job.result : Ljava/lang/Object;
          ALOAD 1
          ICONST_0
          PUTFIELD org/nlogo/nvm/Context.stopping : Z
          ALOAD 1
          ICONST_1
          PUTFIELD org/nlogo/nvm/Context.ip : I
          ALOAD 1
          GETFIELD org/nlogo/nvm/Context.activation : Lorg/nlogo/nvm/Activation;
          INVOKEVIRTUAL org/nlogo/nvm/Activation.nonLambdaActivation ()Lorg/nlogo/nvm/Activation;
          GETFIELD org/nlogo/nvm/Activation.procedure : Lorg/nlogo/nvm/Procedure;
          INVOKEVIRTUAL org/nlogo/nvm/Procedure.isReporter ()Z
          IFNE L24
          NEW org/nlogo/nvm/RuntimePrimitiveException
          DUP
          ALOAD 1
          ALOAD 0
          INVOKESTATIC org/nlogo/core/I18N.errorsJ ()Lorg/nlogo/core/I18NJava;
          LDC "org.nlogo.prim._report.canOnlyUseInToReport"
          ICONST_1
          ANEWARRAY java/lang/Object
          DUP
          ICONST_0
          LDC "REPORT"
          AASTORE
          INVOKEINTERFACE org/nlogo/core/I18NJava.getN (Ljava/lang/String;[Ljava/lang/Object;)Ljava/lang/String; (itf)
          INVOKESPECIAL org/nlogo/nvm/RuntimePrimitiveException.<init> (Lorg/nlogo/api/Context;Lorg/nlogo/nvm/Instruction;Ljava/lang/String;)V
          ATHROW
         L24
         FRAME FULL [org/nlogo/prim/_asm_procedureaverageheadingtowardsflockmates_report_0 org/nlogo/nvm/Context java/lang/Double T D java/util/Iterator] []
          ALOAD 1
          GETFIELD org/nlogo/nvm/Context.activation : Lorg/nlogo/nvm/Activation;
          GETFIELD org/nlogo/nvm/Activation.procedure : Lorg/nlogo/nvm/Procedure;
          INVOKEVIRTUAL org/nlogo/nvm/Procedure.isLambda ()Z
          IFEQ L25
          NEW org/nlogo/nvm/NonLocalExit
          DUP
          INVOKESPECIAL org/nlogo/nvm/NonLocalExit.<init> ()V
          ATHROW
         L25
         FRAME SAME
          ALOAD 1
          INVOKEVIRTUAL org/nlogo/nvm/Context.atTopActivation ()Z
          IFNE L26
          NEW org/nlogo/nvm/RuntimePrimitiveException
          DUP
          ALOAD 1
          ALOAD 0
          INVOKESTATIC org/nlogo/core/I18N.errorsJ ()Lorg/nlogo/core/I18NJava;
          LDC "org.nlogo.prim._report.mustImmediatelyBeUsedInToReport"
          ICONST_1
          ANEWARRAY java/lang/Object
          DUP
          ICONST_0
          LDC "REPORT"
          AASTORE
          INVOKEINTERFACE org/nlogo/core/I18NJava.getN (Ljava/lang/String;[Ljava/lang/Object;)Ljava/lang/String; (itf)
          INVOKESPECIAL org/nlogo/nvm/RuntimePrimitiveException.<init> (Lorg/nlogo/api/Context;Lorg/nlogo/nvm/Instruction;Ljava/lang/String;)V
          ATHROW
         L26
         FRAME SAME
          RETURN
[1]_asm_procedureaverageheadingtowardsflockmates_returnreport_7 => void
          // parameter final  context
         L0
          NEW org/nlogo/nvm/RuntimePrimitiveException
          DUP
          ALOAD 1
          ALOAD 0
          GETSTATIC org/nlogo/core/I18N$.MODULE$ : Lorg/nlogo/core/I18N$;
          INVOKEVIRTUAL org/nlogo/core/I18N$.errors ()Lorg/nlogo/core/I18N$BundleKind;
          LDC "org.nlogo.prim._returnreport.reportNotCalledInReportProcedure"
          INVOKEVIRTUAL org/nlogo/core/I18N$BundleKind.get (Ljava/lang/String;)Ljava/lang/String;
          INVOKESPECIAL org/nlogo/nvm/RuntimePrimitiveException.<init> (Lorg/nlogo/api/Context;Lorg/nlogo/nvm/Instruction;Ljava/lang/String;)V
          ATHROW
         L1
         FRAME FULL [] [java/lang/Throwable]
          ATHROW

procedure TURN-TOWARDS:[NEW-HEADING MAX-TURN]{-T--}:
[0]_asm_procedureturntowards_call_0 "turn-at-most my-subtract-headings new-heading heading max-turn"
      _callreport:MY-SUBTRACT-HEADINGS "my-subtract-headings new-heading heading"
        _procedurevariable:NEW-HEADING "new-heading" => Object
        _turtlevariabledouble:HEADING "heading" => Double
      _procedurevariable:MAX-TURN "max-turn" => Object
          // parameter final  context
          // parameter final  context
          // parameter final  context
          TRYCATCHBLOCK L0 L1 L2 org/nlogo/api/AgentException
         L3
          NEW org/nlogo/nvm/Activation
          DUP
          ALOAD 0
          GETFIELD org/nlogo/prim/_asm_procedureturntowards_call_0.kept1_procedure : Lorg/nlogo/nvm/Procedure;
          ALOAD 1
          GETFIELD org/nlogo/nvm/Context.activation : Lorg/nlogo/nvm/Activation;
          SIPUSH 2
          ANEWARRAY java/lang/Object
          DUP
          ICONST_0
         L4
          NEW org/nlogo/nvm/Activation
          DUP
          ALOAD 0
          GETFIELD org/nlogo/prim/_asm_procedureturntowards_call_0.kept2_procedure : Lorg/nlogo/nvm/Procedure;
          ALOAD 1
          GETFIELD org/nlogo/nvm/Context.activation : Lorg/nlogo/nvm/Activation;
          SIPUSH 2
          ANEWARRAY java/lang/Object
          DUP
          ICONST_0
         L5
          ALOAD 1
          GETFIELD org/nlogo/nvm/Context.activation : Lorg/nlogo/nvm/Activation;
          GETFIELD org/nlogo/nvm/Activation.args : [Ljava/lang/Object;
          ICONST_0
          AALOAD
         L6
          AASTORE
          DUP
          ICONST_1
         L0
          ALOAD 1
          GETFIELD org/nlogo/nvm/Context.agent : Lorg/nlogo/agent/Agent;
          ICONST_2
          INVOKEVIRTUAL org/nlogo/agent/Agent.getTurtleVariable (I)Ljava/lang/Object;
          CHECKCAST java/lang/Double
         L1
          GOTO L7
         L2
         FRAME SAME1 org/nlogo/api/AgentException
          ASTORE 2
          NEW org/nlogo/nvm/RuntimePrimitiveException
          DUP
          ALOAD 1
          ALOAD 0
          ALOAD 2
          INVOKEVIRTUAL org/nlogo/api/AgentException.getMessage ()Ljava/lang/String;
          INVOKESPECIAL org/nlogo/nvm/RuntimePrimitiveException.<init> (Lorg/nlogo/api/Context;Lorg/nlogo/nvm/Instruction;Ljava/lang/String;)V
          ATHROW
         L7
         FRAME FULL [org/nlogo/prim/_asm_procedureturntowards_call_0 org/nlogo/nvm/Context] [L3 L3 org/nlogo/nvm/Procedure org/nlogo/nvm/Activation [Ljava/lang/Object; [Ljava/lang/Object; I L4 L4 org/nlogo/nvm/Procedure org/nlogo/nvm/Activation [Ljava/lang/Object; [Ljava/lang/Object; I java/lang/Double]
          AASTORE
          ICONST_0
          INVOKESPECIAL org/nlogo/nvm/Activation.<init> (Lorg/nlogo/nvm/Procedure;Lorg/nlogo/nvm/Activation;[Ljava/lang/Object;I)V
          ALOAD 1
          SWAP
          INVOKEVIRTUAL org/nlogo/nvm/Context.callReporterProcedure (Lorg/nlogo/nvm/Activation;)Ljava/lang/Object;
          DUP
          IFNONNULL L8
          NEW org/nlogo/nvm/RuntimePrimitiveException
          DUP
          ALOAD 1
          ALOAD 0
          LDC "the MY-SUBTRACT-HEADINGS procedure failed to report a result"
          INVOKESPECIAL org/nlogo/nvm/RuntimePrimitiveException.<init> (Lorg/nlogo/api/Context;Lorg/nlogo/nvm/Instruction;Ljava/lang/String;)V
          ATHROW
         L8
         FRAME FULL [org/nlogo/prim/_asm_procedureturntowards_call_0 org/nlogo/nvm/Context] [L3 L3 org/nlogo/nvm/Procedure org/nlogo/nvm/Activation [Ljava/lang/Object; [Ljava/lang/Object; I java/lang/Object]
          AASTORE
          DUP
          ICONST_1
         L9
          ALOAD 1
          GETFIELD org/nlogo/nvm/Context.activation : Lorg/nlogo/nvm/Activation;
          GETFIELD org/nlogo/nvm/Activation.args : [Ljava/lang/Object;
          ICONST_1
          AALOAD
         L10
          AASTORE
          ICONST_1
          INVOKESPECIAL org/nlogo/nvm/Activation.<init> (Lorg/nlogo/nvm/Procedure;Lorg/nlogo/nvm/Activation;[Ljava/lang/Object;I)V
          ALOAD 1
          SWAP
          PUTFIELD org/nlogo/nvm/Context.activation : Lorg/nlogo/nvm/Activation;
          ALOAD 1
          ICONST_0
          PUTFIELD org/nlogo/nvm/Context.ip : I
         L11
          RETURN
[1]_asm_procedureturntowards_return_1 => void
          // parameter final  context
         L0
          ALOAD 1
          INVOKEVIRTUAL org/nlogo/nvm/Context.returnFromProcedure ()V
          ALOAD 1
          ICONST_0
          PUTFIELD org/nlogo/nvm/Context.stopping : Z
         L1
          RETURN

procedure TURN-AWAY:[NEW-HEADING MAX-TURN]{-T--}:
[0]_asm_procedureturnaway_call_0 "turn-at-most my-subtract-headings heading new-heading max-turn"
      _callreport:MY-SUBTRACT-HEADINGS "my-subtract-headings heading new-heading"
        _turtlevariabledouble:HEADING "heading" => Double
        _procedurevariable:NEW-HEADING "new-heading" => Object
      _procedurevariable:MAX-TURN "max-turn" => Object
          // parameter final  context
          // parameter final  context
          // parameter final  context
          TRYCATCHBLOCK L0 L1 L2 org/nlogo/api/AgentException
         L3
          NEW org/nlogo/nvm/Activation
          DUP
          ALOAD 0
          GETFIELD org/nlogo/prim/_asm_procedureturnaway_call_0.kept1_procedure : Lorg/nlogo/nvm/Procedure;
          ALOAD 1
          GETFIELD org/nlogo/nvm/Context.activation : Lorg/nlogo/nvm/Activation;
          SIPUSH 2
          ANEWARRAY java/lang/Object
          DUP
          ICONST_0
         L4
          NEW org/nlogo/nvm/Activation
          DUP
          ALOAD 0
          GETFIELD org/nlogo/prim/_asm_procedureturnaway_call_0.kept2_procedure : Lorg/nlogo/nvm/Procedure;
          ALOAD 1
          GETFIELD org/nlogo/nvm/Context.activation : Lorg/nlogo/nvm/Activation;
          SIPUSH 2
          ANEWARRAY java/lang/Object
          DUP
          ICONST_0
         L0
          ALOAD 1
          GETFIELD org/nlogo/nvm/Context.agent : Lorg/nlogo/agent/Agent;
          ICONST_2
          INVOKEVIRTUAL org/nlogo/agent/Agent.getTurtleVariable (I)Ljava/lang/Object;
          CHECKCAST java/lang/Double
         L1
          GOTO L5
         L2
         FRAME SAME1 org/nlogo/api/AgentException
          ASTORE 2
          NEW org/nlogo/nvm/RuntimePrimitiveException
          DUP
          ALOAD 1
          ALOAD 0
          ALOAD 2
          INVOKEVIRTUAL org/nlogo/api/AgentException.getMessage ()Ljava/lang/String;
          INVOKESPECIAL org/nlogo/nvm/RuntimePrimitiveException.<init> (Lorg/nlogo/api/Context;Lorg/nlogo/nvm/Instruction;Ljava/lang/String;)V
          ATHROW
         L5
         FRAME FULL [org/nlogo/prim/_asm_procedureturnaway_call_0 org/nlogo/nvm/Context] [L3 L3 org/nlogo/nvm/Procedure org/nlogo/nvm/Activation [Ljava/lang/Object; [Ljava/lang/Object; I L4 L4 org/nlogo/nvm/Procedure org/nlogo/nvm/Activation [Ljava/lang/Object; [Ljava/lang/Object; I java/lang/Double]
          AASTORE
          DUP
          ICONST_1
         L6
          ALOAD 1
          GETFIELD org/nlogo/nvm/Context.activation : Lorg/nlogo/nvm/Activation;
          GETFIELD org/nlogo/nvm/Activation.args : [Ljava/lang/Object;
          ICONST_0
          AALOAD
         L7
          AASTORE
          ICONST_0
          INVOKESPECIAL org/nlogo/nvm/Activation.<init> (Lorg/nlogo/nvm/Procedure;Lorg/nlogo/nvm/Activation;[Ljava/lang/Object;I)V
          ALOAD 1
          SWAP
          INVOKEVIRTUAL org/nlogo/nvm/Context.callReporterProcedure (Lorg/nlogo/nvm/Activation;)Ljava/lang/Object;
          DUP
          IFNONNULL L8
          NEW org/nlogo/nvm/RuntimePrimitiveException
          DUP
          ALOAD 1
          ALOAD 0
          LDC "the MY-SUBTRACT-HEADINGS procedure failed to report a result"
          INVOKESPECIAL org/nlogo/nvm/RuntimePrimitiveException.<init> (Lorg/nlogo/api/Context;Lorg/nlogo/nvm/Instruction;Ljava/lang/String;)V
          ATHROW
         L8
         FRAME FULL [org/nlogo/prim/_asm_procedureturnaway_call_0 org/nlogo/nvm/Context] [L3 L3 org/nlogo/nvm/Procedure org/nlogo/nvm/Activation [Ljava/lang/Object; [Ljava/lang/Object; I java/lang/Object]
          AASTORE
          DUP
          ICONST_1
         L9
          ALOAD 1
          GETFIELD org/nlogo/nvm/Context.activation : Lorg/nlogo/nvm/Activation;
          GETFIELD org/nlogo/nvm/Activation.args : [Ljava/lang/Object;
          ICONST_1
          AALOAD
         L10
          AASTORE
          ICONST_1
          INVOKESPECIAL org/nlogo/nvm/Activation.<init> (Lorg/nlogo/nvm/Procedure;Lorg/nlogo/nvm/Activation;[Ljava/lang/Object;I)V
          ALOAD 1
          SWAP
          PUTFIELD org/nlogo/nvm/Context.activation : Lorg/nlogo/nvm/Activation;
          ALOAD 1
          ICONST_0
          PUTFIELD org/nlogo/nvm/Context.ip : I
         L11
          RETURN
[1]_asm_procedureturnaway_return_1 => void
          // parameter final  context
         L0
          ALOAD 1
          INVOKEVIRTUAL org/nlogo/nvm/Context.returnFromProcedure ()V
          ALOAD 1
          ICONST_0
          PUTFIELD org/nlogo/nvm/Context.stopping : Z
         L1
          RETURN

procedure TURN-AT-MOST:[TURN MAX-TURN]{-T--}:
[0]_asm_procedureturnatmost_ifelse_0 "ifelse abs turn > max-turn [ ifelse turn > 0 [ rt max-turn ] [ lt max-turn ] ] [ rt turn ]" boolean => void
      _greaterthan "abs turn > max-turn" double,Object => boolean
        _abs "abs turn" double => double
          _procedurevariable:TURN "turn" => Object
        _procedurevariable:MAX-TURN "max-turn" => Object
          // parameter final  context
          // parameter final  context
          // parameter final  d
          // parameter final  context
          // parameter final  context
          // parameter final  arg0
          // parameter final  arg1
          // parameter final  context
          // parameter final  cond
          TRYCATCHBLOCK L0 L1 L1 java/lang/ClassCastException
         L2
          ALOAD 1
          GETFIELD org/nlogo/nvm/Context.activation : Lorg/nlogo/nvm/Activation;
          GETFIELD org/nlogo/nvm/Activation.args : [Ljava/lang/Object;
          ICONST_0
          AALOAD
         L3
          ASTORE 2
         L0
          ALOAD 2
          CHECKCAST java/lang/Double
          INVOKEVIRTUAL java/lang/Double.doubleValue ()D
          GOTO L4
         L1
         FRAME FULL [org/nlogo/prim/_asm_procedureturnatmost_ifelse_0 org/nlogo/nvm/Context java/lang/Object] [java/lang/ClassCastException]
          POP
          NEW org/nlogo/nvm/ArgumentTypeException
          DUP
          ALOAD 1
          ALOAD 0
          BIPUSH 0
          LDC 1
          ALOAD 2
          INVOKESPECIAL org/nlogo/nvm/ArgumentTypeException.<init> (Lorg/nlogo/nvm/Context;Lorg/nlogo/nvm/Instruction;IILjava/lang/Object;)V
          ATHROW
         L4
         FRAME SAME1 D
          DSTORE 2
          DLOAD 2
          ICONST_0
          I2D
          DCMPG
          IFGE L5
          DLOAD 2
          DNEG
          GOTO L6
         L5
         FRAME FULL [org/nlogo/prim/_asm_procedureturnatmost_ifelse_0 org/nlogo/nvm/Context D] []
          DLOAD 2
         L6
         FRAME SAME1 D
          ALOAD 1
          GETFIELD org/nlogo/nvm/Context.activation : Lorg/nlogo/nvm/Activation;
          GETFIELD org/nlogo/nvm/Activation.args : [Ljava/lang/Object;
          ICONST_1
          AALOAD
         L7
          ASTORE 4
          DSTORE 2
          ALOAD 4
          INSTANCEOF java/lang/Double
          IFEQ L8
          ALOAD 4
          CHECKCAST java/lang/Double
          ASTORE 5
          DLOAD 2
          ALOAD 5
          INVOKEVIRTUAL java/lang/Double.doubleValue ()D
          DCMPL
          IFLE L9
          ICONST_1
          GOTO L10
         L9
         FRAME APPEND [java/lang/Object java/lang/Double]
          ICONST_0
          GOTO L10
         L8
         FRAME CHOP 1
          NEW org/nlogo/nvm/RuntimePrimitiveException
          DUP
          ALOAD 1
          ALOAD 0
          GETSTATIC org/nlogo/core/I18N$.MODULE$ : Lorg/nlogo/core/I18N$;
          INVOKEVIRTUAL org/nlogo/core/I18N$.errors ()Lorg/nlogo/core/I18N$BundleKind;
          LDC "org.nlogo.prim._greaterthan.cannotCompareParameters"
          GETSTATIC scala/Predef$.MODULE$ : Lscala/Predef$;
          ICONST_2
          ANEWARRAY java/lang/Object
          DUP
          ICONST_0
          GETSTATIC org/nlogo/api/TypeNames$.MODULE$ : Lorg/nlogo/api/TypeNames$;
          DLOAD 2
          INVOKESTATIC scala/runtime/BoxesRunTime.boxToDouble (D)Ljava/lang/Double;
          INVOKEVIRTUAL org/nlogo/api/TypeNames$.aName (Ljava/lang/Object;)Ljava/lang/String;
          AASTORE
          DUP
          ICONST_1
          GETSTATIC org/nlogo/api/TypeNames$.MODULE$ : Lorg/nlogo/api/TypeNames$;
          ALOAD 4
          INVOKEVIRTUAL org/nlogo/api/TypeNames$.aName (Ljava/lang/Object;)Ljava/lang/String;
          AASTORE
          INVOKEVIRTUAL scala/Predef$.wrapRefArray ([Ljava/lang/Object;)Lscala/collection/mutable/WrappedArray;
          INVOKEVIRTUAL org/nlogo/core/I18N$BundleKind.getN (Ljava/lang/String;Lscala/collection/Seq;)Ljava/lang/String;
          INVOKESPECIAL org/nlogo/nvm/RuntimePrimitiveException.<init> (Lorg/nlogo/api/Context;Lorg/nlogo/nvm/Instruction;Ljava/lang/String;)V
          ATHROW
         L10
         FRAME FULL [org/nlogo/prim/_asm_procedureturnatmost_ifelse_0 org/nlogo/nvm/Context D java/lang/Object java/lang/Double] [I]
          ISTORE 2
          ALOAD 1
          ILOAD 2
          IFEQ L11
          ICONST_1
          GOTO L12
         L11
         FRAME FULL [org/nlogo/prim/_asm_procedureturnatmost_ifelse_0 org/nlogo/nvm/Context I T java/lang/Object java/lang/Double] [org/nlogo/nvm/Context]
          BIPUSH 6
         L12
         FRAME FULL [org/nlogo/prim/_asm_procedureturnatmost_ifelse_0 org/nlogo/nvm/Context I T java/lang/Object java/lang/Double] [org/nlogo/nvm/Context I]
          PUTFIELD org/nlogo/nvm/Context.ip : I
         L13
          RETURN
[1]_asm_procedureturnatmost_ifelse_1 "ifelse turn > 0 [ rt max-turn ] [ lt max-turn ]" boolean => void
      _greaterthan "turn > 0" Object,double => boolean
        _procedurevariable:TURN "turn" => Object
        _constdouble:0.0 "0" => double
          // parameter final  context
          // parameter final  context
          // parameter final  context
          // parameter final  arg0
          // parameter final  arg1
          // parameter final  context
          // parameter final  cond
         L0
          ALOAD 1
          GETFIELD org/nlogo/nvm/Context.activation : Lorg/nlogo/nvm/Activation;
          GETFIELD org/nlogo/nvm/Activation.args : [Ljava/lang/Object;
          ICONST_0
          AALOAD
         L1
          DCONST_0
         L2
          DSTORE 3
          ASTORE 2
          ALOAD 2
          INSTANCEOF java/lang/Double
          IFEQ L3
          ALOAD 2
          CHECKCAST java/lang/Double
          INVOKEVIRTUAL java/lang/Double.doubleValue ()D
          DLOAD 3
          DCMPL
          IFLE L4
          ICONST_1
          GOTO L5
         L4
         FRAME APPEND [java/lang/Object D]
          ICONST_0
          GOTO L5
         L3
         FRAME SAME
          NEW org/nlogo/nvm/RuntimePrimitiveException
          DUP
          ALOAD 1
          ALOAD 0
          GETSTATIC org/nlogo/core/I18N$.MODULE$ : Lorg/nlogo/core/I18N$;
          INVOKEVIRTUAL org/nlogo/core/I18N$.errors ()Lorg/nlogo/core/I18N$BundleKind;
          LDC "org.nlogo.prim._greaterthan.cannotCompareParameters"
          GETSTATIC scala/Predef$.MODULE$ : Lscala/Predef$;
          ICONST_2
          ANEWARRAY java/lang/Object
          DUP
          ICONST_0
          GETSTATIC org/nlogo/api/TypeNames$.MODULE$ : Lorg/nlogo/api/TypeNames$;
          ALOAD 2
          INVOKEVIRTUAL org/nlogo/api/TypeNames$.aName (Ljava/lang/Object;)Ljava/lang/String;
          AASTORE
          DUP
          ICONST_1
          GETSTATIC org/nlogo/api/TypeNames$.MODULE$ : Lorg/nlogo/api/TypeNames$;
          DLOAD 3
          INVOKESTATIC scala/runtime/BoxesRunTime.boxToDouble (D)Ljava/lang/Double;
          INVOKEVIRTUAL org/nlogo/api/TypeNames$.aName (Ljava/lang/Object;)Ljava/lang/String;
          AASTORE
          INVOKEVIRTUAL scala/Predef$.wrapRefArray ([Ljava/lang/Object;)Lscala/collection/mutable/WrappedArray;
          INVOKEVIRTUAL org/nlogo/core/I18N$BundleKind.getN (Ljava/lang/String;Lscala/collection/Seq;)Ljava/lang/String;
          INVOKESPECIAL org/nlogo/nvm/RuntimePrimitiveException.<init> (Lorg/nlogo/api/Context;Lorg/nlogo/nvm/Instruction;Ljava/lang/String;)V
          ATHROW
         L5
         FRAME SAME1 I
          ISTORE 2
          ALOAD 1
          ILOAD 2
          IFEQ L6
          ICONST_2
          GOTO L7
         L6
         FRAME FULL [org/nlogo/prim/_asm_procedureturnatmost_ifelse_1 org/nlogo/nvm/Context I D] [org/nlogo/nvm/Context]
          ICONST_4
         L7
         FRAME FULL [org/nlogo/prim/_asm_procedureturnatmost_ifelse_1 org/nlogo/nvm/Context I D] [org/nlogo/nvm/Context I]
          PUTFIELD org/nlogo/nvm/Context.ip : I
         L8
          RETURN
[2]_asm_procedureturnatmost_right_2 "rt max-turn" double => void
      _procedurevariable:MAX-TURN "max-turn" => Object
          // parameter final  context
          // parameter final  context
          // parameter final  delta
          TRYCATCHBLOCK L0 L1 L1 java/lang/ClassCastException
         L2
          ALOAD 1
          GETFIELD org/nlogo/nvm/Context.activation : Lorg/nlogo/nvm/Activation;
          GETFIELD org/nlogo/nvm/Activation.args : [Ljava/lang/Object;
          ICONST_1
          AALOAD
         L3
          ASTORE 2
         L0
          ALOAD 2
          CHECKCAST java/lang/Double
          INVOKEVIRTUAL java/lang/Double.doubleValue ()D
          GOTO L4
         L1
         FRAME FULL [org/nlogo/prim/_asm_procedureturnatmost_right_2 org/nlogo/nvm/Context java/lang/Object] [java/lang/ClassCastException]
          POP
          NEW org/nlogo/nvm/ArgumentTypeException
          DUP
          ALOAD 1
          ALOAD 0
          BIPUSH 0
          LDC 1
          ALOAD 2
          INVOKESPECIAL org/nlogo/nvm/ArgumentTypeException.<init> (Lorg/nlogo/nvm/Context;Lorg/nlogo/nvm/Instruction;IILjava/lang/Object;)V
          ATHROW
         L4
         FRAME SAME1 D
          DSTORE 2
          ALOAD 1
          GETFIELD org/nlogo/nvm/Context.agent : Lorg/nlogo/agent/Agent;
          CHECKCAST org/nlogo/agent/Turtle
          DLOAD 2
          INVOKEVIRTUAL org/nlogo/agent/Turtle.turnRight (D)V
          ALOAD 1
          ICONST_3
          PUTFIELD org/nlogo/nvm/Context.ip : I
         L5
          RETURN
[3]_asm_procedureturnatmost_goto_3 => void
          // parameter final  context
         L0
          ALOAD 1
          ICONST_5
          PUTFIELD org/nlogo/nvm/Context.ip : I
         L1
          RETURN
[4]_asm_procedureturnatmost_left_4 "lt max-turn" double => void
      _procedurevariable:MAX-TURN "max-turn" => Object
          // parameter final  context
          // parameter final  context
          // parameter final  delta
          TRYCATCHBLOCK L0 L1 L1 java/lang/ClassCastException
         L2
          ALOAD 1
          GETFIELD org/nlogo/nvm/Context.activation : Lorg/nlogo/nvm/Activation;
          GETFIELD org/nlogo/nvm/Activation.args : [Ljava/lang/Object;
          ICONST_1
          AALOAD
         L3
          ASTORE 2
         L0
          ALOAD 2
          CHECKCAST java/lang/Double
          INVOKEVIRTUAL java/lang/Double.doubleValue ()D
          GOTO L4
         L1
         FRAME FULL [org/nlogo/prim/_asm_procedureturnatmost_left_4 org/nlogo/nvm/Context java/lang/Object] [java/lang/ClassCastException]
          POP
          NEW org/nlogo/nvm/ArgumentTypeException
          DUP
          ALOAD 1
          ALOAD 0
          BIPUSH 0
          LDC 1
          ALOAD 2
          INVOKESPECIAL org/nlogo/nvm/ArgumentTypeException.<init> (Lorg/nlogo/nvm/Context;Lorg/nlogo/nvm/Instruction;IILjava/lang/Object;)V
          ATHROW
         L4
         FRAME SAME1 D
          DSTORE 2
          ALOAD 1
          GETFIELD org/nlogo/nvm/Context.agent : Lorg/nlogo/agent/Agent;
          CHECKCAST org/nlogo/agent/Turtle
          DLOAD 2
          DNEG
          INVOKEVIRTUAL org/nlogo/agent/Turtle.turnRight (D)V
          ALOAD 1
          ICONST_5
          PUTFIELD org/nlogo/nvm/Context.ip : I
         L5
          RETURN
[5]_asm_procedureturnatmost_goto_5 => void
          // parameter final  context
         L0
          ALOAD 1
          BIPUSH 7
          PUTFIELD org/nlogo/nvm/Context.ip : I
         L1
          RETURN
[6]_asm_procedureturnatmost_right_6 "rt turn" double => void
      _procedurevariable:TURN "turn" => Object
          // parameter final  context
          // parameter final  context
          // parameter final  delta
          TRYCATCHBLOCK L0 L1 L1 java/lang/ClassCastException
         L2
          ALOAD 1
          GETFIELD org/nlogo/nvm/Context.activation : Lorg/nlogo/nvm/Activation;
          GETFIELD org/nlogo/nvm/Activation.args : [Ljava/lang/Object;
          ICONST_0
          AALOAD
         L3
          ASTORE 2
         L0
          ALOAD 2
          CHECKCAST java/lang/Double
          INVOKEVIRTUAL java/lang/Double.doubleValue ()D
          GOTO L4
         L1
         FRAME FULL [org/nlogo/prim/_asm_procedureturnatmost_right_6 org/nlogo/nvm/Context java/lang/Object] [java/lang/ClassCastException]
          POP
          NEW org/nlogo/nvm/ArgumentTypeException
          DUP
          ALOAD 1
          ALOAD 0
          BIPUSH 0
          LDC 1
          ALOAD 2
          INVOKESPECIAL org/nlogo/nvm/ArgumentTypeException.<init> (Lorg/nlogo/nvm/Context;Lorg/nlogo/nvm/Instruction;IILjava/lang/Object;)V
          ATHROW
         L4
         FRAME SAME1 D
          DSTORE 2
          ALOAD 1
          GETFIELD org/nlogo/nvm/Context.agent : Lorg/nlogo/agent/Agent;
          CHECKCAST org/nlogo/agent/Turtle
          DLOAD 2
          INVOKEVIRTUAL org/nlogo/agent/Turtle.turnRight (D)V
          ALOAD 1
          BIPUSH 7
          PUTFIELD org/nlogo/nvm/Context.ip : I
         L5
          RETURN
[7]_asm_procedureturnatmost_return_7 => void
          // parameter final  context
         L0
          ALOAD 1
          INVOKEVIRTUAL org/nlogo/nvm/Context.returnFromProcedure ()V
          ALOAD 1
          ICONST_0
          PUTFIELD org/nlogo/nvm/Context.stopping : Z
         L1
          RETURN

reporter procedure MY-SUBTRACT-HEADINGS:[H1 H2]{OTPL}:
[0]_asm_proceduremysubtractheadings_ifelse_0 "ifelse abs h1 - h2 <= 180 [ report h1 - h2 ] [ ifelse h1 > h2 [ report h1 - h2 - 360 ] [ report h1 - h2 + 360 ] ]" boolean => void
      _lessorequal "abs h1 - h2 <= 180" double,double => boolean
        _abs "abs h1 - h2" double => double
          _minus "h1 - h2" double,double => double
            _procedurevariable:H1 "h1" => Object
            _procedurevariable:H2 "h2" => Object
        _constdouble:180.0 "180" => double
          // parameter final  context
          // parameter final  context
          // parameter final  context
          // parameter final  d0
          // parameter final  d1
          // parameter final  context
          // parameter final  d
          // parameter final  context
          // parameter final  context
          // parameter final  cond
          TRYCATCHBLOCK L0 L1 L1 java/lang/ClassCastException
          TRYCATCHBLOCK L2 L3 L3 java/lang/ClassCastException
         L4
          ALOAD 1
          GETFIELD org/nlogo/nvm/Context.activation : Lorg/nlogo/nvm/Activation;
          GETFIELD org/nlogo/nvm/Activation.args : [Ljava/lang/Object;
          ICONST_0
          AALOAD
         L5
          ASTORE 2
         L0
          ALOAD 2
          CHECKCAST java/lang/Double
          INVOKEVIRTUAL java/lang/Double.doubleValue ()D
          GOTO L6
         L1
         FRAME FULL [org/nlogo/prim/_asm_proceduremysubtractheadings_ifelse_0 org/nlogo/nvm/Context java/lang/Object] [java/lang/ClassCastException]
          POP
          NEW org/nlogo/nvm/ArgumentTypeException
          DUP
          ALOAD 1
          ALOAD 0
          BIPUSH 0
          LDC 1
          ALOAD 2
          INVOKESPECIAL org/nlogo/nvm/ArgumentTypeException.<init> (Lorg/nlogo/nvm/Context;Lorg/nlogo/nvm/Instruction;IILjava/lang/Object;)V
          ATHROW
         L6
         FRAME SAME1 D
          ALOAD 1
          GETFIELD org/nlogo/nvm/Context.activation : Lorg/nlogo/nvm/Activation;
          GETFIELD org/nlogo/nvm/Activation.args : [Ljava/lang/Object;
          ICONST_1
          AALOAD
         L7
          ASTORE 2
         L2
          ALOAD 2
          CHECKCAST java/lang/Double
          INVOKEVIRTUAL java/lang/Double.doubleValue ()D
          GOTO L8
         L3
         FRAME SAME1 java/lang/ClassCastException
          POP
          NEW org/nlogo/nvm/ArgumentTypeException
          DUP
          ALOAD 1
          ALOAD 0
          BIPUSH 1
          LDC 1
          ALOAD 2
          INVOKESPECIAL org/nlogo/nvm/ArgumentTypeException.<init> (Lorg/nlogo/nvm/Context;Lorg/nlogo/nvm/Instruction;IILjava/lang/Object;)V
          ATHROW
         L8
         FRAME FULL [org/nlogo/prim/_asm_proceduremysubtractheadings_ifelse_0 org/nlogo/nvm/Context java/lang/Object] [D D]
          DSTORE 4
          DSTORE 2
          DLOAD 2
          DLOAD 4
          DSUB
         L9
          DSTORE 2
          DLOAD 2
          ICONST_0
          I2D
          DCMPG
          IFGE L10
          DLOAD 2
          DNEG
          GOTO L11
         L10
         FRAME FULL [org/nlogo/prim/_asm_proceduremysubtractheadings_ifelse_0 org/nlogo/nvm/Context D D] []
          DLOAD 2
         L11
         FRAME SAME1 D
          LDC 180.0D
         L12
          DSTORE 4
          DSTORE 2
          DLOAD 2
          DLOAD 4
          DCMPG
          IFGT L13
          ICONST_1
          GOTO L14
         L13
         FRAME SAME
          ICONST_0
         L14
         FRAME SAME1 I
          ISTORE 2
          ALOAD 1
          ILOAD 2
          IFEQ L15
          ICONST_1
          GOTO L16
         L15
         FRAME FULL [org/nlogo/prim/_asm_proceduremysubtractheadings_ifelse_0 org/nlogo/nvm/Context I T D] [org/nlogo/nvm/Context]
          ICONST_3
         L16
         FRAME FULL [org/nlogo/prim/_asm_proceduremysubtractheadings_ifelse_0 org/nlogo/nvm/Context I T D] [org/nlogo/nvm/Context I]
          PUTFIELD org/nlogo/nvm/Context.ip : I
         L17
          RETURN
[1]_asm_proceduremysubtractheadings_report_1 "report h1 - h2" Object => void
      _minus "h1 - h2" double,double => double
        _procedurevariable:H1 "h1" => Object
        _procedurevariable:H2 "h2" => Object
          // parameter final  context
          // parameter final  context
          // parameter final  context
          // parameter final  d0
          // parameter final  d1
          TRYCATCHBLOCK L0 L1 L1 java/lang/ClassCastException
          TRYCATCHBLOCK L2 L3 L3 java/lang/ClassCastException
         L4
          ALOAD 1
          GETFIELD org/nlogo/nvm/Context.activation : Lorg/nlogo/nvm/Activation;
          GETFIELD org/nlogo/nvm/Activation.args : [Ljava/lang/Object;
          ICONST_0
          AALOAD
         L5
          ASTORE 2
         L0
          ALOAD 2
          CHECKCAST java/lang/Double
          INVOKEVIRTUAL java/lang/Double.doubleValue ()D
          GOTO L6
         L1
         FRAME FULL [org/nlogo/prim/_asm_proceduremysubtractheadings_report_1 org/nlogo/nvm/Context java/lang/Object] [java/lang/ClassCastException]
          POP
          NEW org/nlogo/nvm/ArgumentTypeException
          DUP
          ALOAD 1
          ALOAD 0
          BIPUSH 0
          LDC 1
          ALOAD 2
          INVOKESPECIAL org/nlogo/nvm/ArgumentTypeException.<init> (Lorg/nlogo/nvm/Context;Lorg/nlogo/nvm/Instruction;IILjava/lang/Object;)V
          ATHROW
         L6
         FRAME SAME1 D
          ALOAD 1
          GETFIELD org/nlogo/nvm/Context.activation : Lorg/nlogo/nvm/Activation;
          GETFIELD org/nlogo/nvm/Activation.args : [Ljava/lang/Object;
          ICONST_1
          AALOAD
         L7
          ASTORE 2
         L2
          ALOAD 2
          CHECKCAST java/lang/Double
          INVOKEVIRTUAL java/lang/Double.doubleValue ()D
          GOTO L8
         L3
         FRAME SAME1 java/lang/ClassCastException
          POP
          NEW org/nlogo/nvm/ArgumentTypeException
          DUP
          ALOAD 1
          ALOAD 0
          BIPUSH 1
          LDC 1
          ALOAD 2
          INVOKESPECIAL org/nlogo/nvm/ArgumentTypeException.<init> (Lorg/nlogo/nvm/Context;Lorg/nlogo/nvm/Instruction;IILjava/lang/Object;)V
          ATHROW
         L8
         FRAME FULL [org/nlogo/prim/_asm_proceduremysubtractheadings_report_1 org/nlogo/nvm/Context java/lang/Object] [D D]
          DSTORE 4
          DSTORE 2
          DLOAD 2
          DLOAD 4
          DSUB
         L9
          DSTORE 2
          NEW java/lang/Double
          DUP
          DLOAD 2
          INVOKESPECIAL java/lang/Double.<init> (D)V
          ASTORE 2
          ALOAD 1
          GETFIELD org/nlogo/nvm/Context.job : Lorg/nlogo/nvm/Job;
          ALOAD 2
          PUTFIELD org/nlogo/nvm/Job.result : Ljava/lang/Object;
          ALOAD 1
          ICONST_0
          PUTFIELD org/nlogo/nvm/Context.stopping : Z
          ALOAD 1
          ICONST_2
          PUTFIELD org/nlogo/nvm/Context.ip : I
          ALOAD 1
          GETFIELD org/nlogo/nvm/Context.activation : Lorg/nlogo/nvm/Activation;
          INVOKEVIRTUAL org/nlogo/nvm/Activation.nonLambdaActivation ()Lorg/nlogo/nvm/Activation;
          GETFIELD org/nlogo/nvm/Activation.procedure : Lorg/nlogo/nvm/Procedure;
          INVOKEVIRTUAL org/nlogo/nvm/Procedure.isReporter ()Z
          IFNE L10
          NEW org/nlogo/nvm/RuntimePrimitiveException
          DUP
          ALOAD 1
          ALOAD 0
          INVOKESTATIC org/nlogo/core/I18N.errorsJ ()Lorg/nlogo/core/I18NJava;
          LDC "org.nlogo.prim._report.canOnlyUseInToReport"
          ICONST_1
          ANEWARRAY java/lang/Object
          DUP
          ICONST_0
          LDC "REPORT"
          AASTORE
          INVOKEINTERFACE org/nlogo/core/I18NJava.getN (Ljava/lang/String;[Ljava/lang/Object;)Ljava/lang/String; (itf)
          INVOKESPECIAL org/nlogo/nvm/RuntimePrimitiveException.<init> (Lorg/nlogo/api/Context;Lorg/nlogo/nvm/Instruction;Ljava/lang/String;)V
          ATHROW
         L10
         FRAME FULL [org/nlogo/prim/_asm_proceduremysubtractheadings_report_1 org/nlogo/nvm/Context java/lang/Double T D] []
          ALOAD 1
          GETFIELD org/nlogo/nvm/Context.activation : Lorg/nlogo/nvm/Activation;
          GETFIELD org/nlogo/nvm/Activation.procedure : Lorg/nlogo/nvm/Procedure;
          INVOKEVIRTUAL org/nlogo/nvm/Procedure.isLambda ()Z
          IFEQ L11
          NEW org/nlogo/nvm/NonLocalExit
          DUP
          INVOKESPECIAL org/nlogo/nvm/NonLocalExit.<init> ()V
          ATHROW
         L11
         FRAME SAME
          ALOAD 1
          INVOKEVIRTUAL org/nlogo/nvm/Context.atTopActivation ()Z
          IFNE L12
          NEW org/nlogo/nvm/RuntimePrimitiveException
          DUP
          ALOAD 1
          ALOAD 0
          INVOKESTATIC org/nlogo/core/I18N.errorsJ ()Lorg/nlogo/core/I18NJava;
          LDC "org.nlogo.prim._report.mustImmediatelyBeUsedInToReport"
          ICONST_1
          ANEWARRAY java/lang/Object
          DUP
          ICONST_0
          LDC "REPORT"
          AASTORE
          INVOKEINTERFACE org/nlogo/core/I18NJava.getN (Ljava/lang/String;[Ljava/lang/Object;)Ljava/lang/String; (itf)
          INVOKESPECIAL org/nlogo/nvm/RuntimePrimitiveException.<init> (Lorg/nlogo/api/Context;Lorg/nlogo/nvm/Instruction;Ljava/lang/String;)V
          ATHROW
         L12
         FRAME SAME
          RETURN
[2]_asm_proceduremysubtractheadings_goto_2 => void
          // parameter final  context
         L0
          ALOAD 1
          BIPUSH 7
          PUTFIELD org/nlogo/nvm/Context.ip : I
         L1
          RETURN
[3]_asm_proceduremysubtractheadings_ifelse_3 "ifelse h1 > h2 [ report h1 - h2 - 360 ] [ report h1 - h2 + 360 ]" boolean => void
      _greaterthan "h1 > h2" Object,Object => boolean
        _procedurevariable:H1 "h1" => Object
        _procedurevariable:H2 "h2" => Object
          // parameter final  context
          // parameter final  context
          // parameter final  context
          // parameter final  o1
          // parameter final  o2
          // parameter final  context
          // parameter final  cond
         L0
          ALOAD 1
          GETFIELD org/nlogo/nvm/Context.activation : Lorg/nlogo/nvm/Activation;
          GETFIELD org/nlogo/nvm/Activation.args : [Ljava/lang/Object;
          ICONST_0
          AALOAD
         L1
          ALOAD 1
          GETFIELD org/nlogo/nvm/Context.activation : Lorg/nlogo/nvm/Activation;
          GETFIELD org/nlogo/nvm/Activation.args : [Ljava/lang/Object;
          ICONST_1
          AALOAD
         L2
          ASTORE 3
          ASTORE 2
          ALOAD 2
          INSTANCEOF java/lang/Double
          IFEQ L3
          ALOAD 3
          INSTANCEOF java/lang/Double
          IFEQ L3
          ALOAD 2
          CHECKCAST java/lang/Double
          INVOKEVIRTUAL java/lang/Double.doubleValue ()D
          ALOAD 3
          CHECKCAST java/lang/Double
          INVOKEVIRTUAL java/lang/Double.doubleValue ()D
          DCMPL
          IFLE L4
          ICONST_1
          GOTO L5
         L4
         FRAME APPEND [java/lang/Object java/lang/Object]
          ICONST_0
          GOTO L5
         L3
         FRAME SAME
          ALOAD 2
          INSTANCEOF java/lang/String
          IFEQ L6
          ALOAD 3
          INSTANCEOF java/lang/String
          IFEQ L6
          ALOAD 2
          CHECKCAST java/lang/String
          ALOAD 3
          CHECKCAST java/lang/String
          INVOKEVIRTUAL java/lang/String.compareTo (Ljava/lang/String;)I
          ICONST_0
          IF_ICMPLE L7
          ICONST_1
          GOTO L5
         L7
         FRAME SAME
          ICONST_0
          GOTO L5
         L6
         FRAME SAME
          ALOAD 2
          INSTANCEOF org/nlogo/agent/Agent
          IFEQ L8
          ALOAD 3
          INSTANCEOF org/nlogo/agent/Agent
          IFEQ L8
          ALOAD 2
          CHECKCAST org/nlogo/agent/Agent
          ASTORE 4
          ALOAD 3
          CHECKCAST org/nlogo/agent/Agent
          ASTORE 5
          ALOAD 4
          INVOKEVIRTUAL org/nlogo/agent/Agent.agentBit ()I
          ALOAD 5
          INVOKEVIRTUAL org/nlogo/agent/Agent.agentBit ()I
          IF_ICMPNE L8
          ALOAD 4
          ALOAD 5
          INVOKEVIRTUAL org/nlogo/agent/Agent.compareTo (Lorg/nlogo/agent/Agent;)I
          ICONST_0
          IF_ICMPLE L9
          ICONST_1
          GOTO L5
         L9
         FRAME APPEND [org/nlogo/agent/Agent org/nlogo/agent/Agent]
          ICONST_0
          GOTO L5
         L8
         FRAME CHOP 2
          NEW org/nlogo/nvm/RuntimePrimitiveException
          DUP
          ALOAD 1
          ALOAD 0
          GETSTATIC org/nlogo/core/I18N$.MODULE$ : Lorg/nlogo/core/I18N$;
          INVOKEVIRTUAL org/nlogo/core/I18N$.errors ()Lorg/nlogo/core/I18N$BundleKind;
          LDC "org.nlogo.prim._greaterthan.cannotCompareParameters"
          GETSTATIC scala/Predef$.MODULE$ : Lscala/Predef$;
          ICONST_2
          ANEWARRAY java/lang/Object
          DUP
          ICONST_0
          GETSTATIC org/nlogo/api/TypeNames$.MODULE$ : Lorg/nlogo/api/TypeNames$;
          ALOAD 2
          INVOKEVIRTUAL org/nlogo/api/TypeNames$.aName (Ljava/lang/Object;)Ljava/lang/String;
          AASTORE
          DUP
          ICONST_1
          GETSTATIC org/nlogo/api/TypeNames$.MODULE$ : Lorg/nlogo/api/TypeNames$;
          ALOAD 3
          INVOKEVIRTUAL org/nlogo/api/TypeNames$.aName (Ljava/lang/Object;)Ljava/lang/String;
          AASTORE
          INVOKEVIRTUAL scala/Predef$.wrapRefArray ([Ljava/lang/Object;)Lscala/collection/mutable/WrappedArray;
          INVOKEVIRTUAL org/nlogo/core/I18N$BundleKind.getN (Ljava/lang/String;Lscala/collection/Seq;)Ljava/lang/String;
          INVOKESPECIAL org/nlogo/nvm/RuntimePrimitiveException.<init> (Lorg/nlogo/api/Context;Lorg/nlogo/nvm/Instruction;Ljava/lang/String;)V
          ATHROW
         L5
         FRAME SAME1 I
          ISTORE 2
          ALOAD 1
          ILOAD 2
          IFEQ L10
          ICONST_4
          GOTO L11
         L10
         FRAME FULL [org/nlogo/prim/_asm_proceduremysubtractheadings_ifelse_3 org/nlogo/nvm/Context I java/lang/Object] [org/nlogo/nvm/Context]
          BIPUSH 6
         L11
         FRAME FULL [org/nlogo/prim/_asm_proceduremysubtractheadings_ifelse_3 org/nlogo/nvm/Context I java/lang/Object] [org/nlogo/nvm/Context I]
          PUTFIELD org/nlogo/nvm/Context.ip : I
         L12
          RETURN
[4]_asm_proceduremysubtractheadings_report_4 "report h1 - h2 - 360" Object => void
      _minus "h1 - h2 - 360" double,double => double
        _minus "h1 - h2" double,double => double
          _procedurevariable:H1 "h1" => Object
          _procedurevariable:H2 "h2" => Object
        _constdouble:360.0 "360" => double
          // parameter final  context
          // parameter final  context
          // parameter final  context
          // parameter final  d0
          // parameter final  d1
          // parameter final  context
          // parameter final  context
          // parameter final  d0
          // parameter final  d1
          TRYCATCHBLOCK L0 L1 L1 java/lang/ClassCastException
          TRYCATCHBLOCK L2 L3 L3 java/lang/ClassCastException
         L4
          ALOAD 1
          GETFIELD org/nlogo/nvm/Context.activation : Lorg/nlogo/nvm/Activation;
          GETFIELD org/nlogo/nvm/Activation.args : [Ljava/lang/Object;
          ICONST_0
          AALOAD
         L5
          ASTORE 2
         L0
          ALOAD 2
          CHECKCAST java/lang/Double
          INVOKEVIRTUAL java/lang/Double.doubleValue ()D
          GOTO L6
         L1
         FRAME FULL [org/nlogo/prim/_asm_proceduremysubtractheadings_report_4 org/nlogo/nvm/Context java/lang/Object] [java/lang/ClassCastException]
          POP
          NEW org/nlogo/nvm/ArgumentTypeException
          DUP
          ALOAD 1
          ALOAD 0
          BIPUSH 0
          LDC 1
          ALOAD 2
          INVOKESPECIAL org/nlogo/nvm/ArgumentTypeException.<init> (Lorg/nlogo/nvm/Context;Lorg/nlogo/nvm/Instruction;IILjava/lang/Object;)V
          ATHROW
         L6
         FRAME SAME1 D
          ALOAD 1
          GETFIELD org/nlogo/nvm/Context.activation : Lorg/nlogo/nvm/Activation;
          GETFIELD org/nlogo/nvm/Activation.args : [Ljava/lang/Object;
          ICONST_1
          AALOAD
         L7
          ASTORE 2
         L2
          ALOAD 2
          CHECKCAST java/lang/Double
          INVOKEVIRTUAL java/lang/Double.doubleValue ()D
          GOTO L8
         L3
         FRAME SAME1 java/lang/ClassCastException
          POP
          NEW org/nlogo/nvm/ArgumentTypeException
          DUP
          ALOAD 1
          ALOAD 0
          BIPUSH 1
          LDC 1
          ALOAD 2
          INVOKESPECIAL org/nlogo/nvm/ArgumentTypeException.<init> (Lorg/nlogo/nvm/Context;Lorg/nlogo/nvm/Instruction;IILjava/lang/Object;)V
          ATHROW
         L8
         FRAME FULL [org/nlogo/prim/_asm_proceduremysubtractheadings_report_4 org/nlogo/nvm/Context java/lang/Object] [D D]
          DSTORE 4
          DSTORE 2
          DLOAD 2
          DLOAD 4
          DSUB
         L9
          LDC 360.0D
         L10
          DSTORE 4
          DSTORE 2
          DLOAD 2
          DLOAD 4
          DSUB
         L11
          DSTORE 2
          NEW java/lang/Double
          DUP
          DLOAD 2
          INVOKESPECIAL java/lang/Double.<init> (D)V
          ASTORE 2
          ALOAD 1
          GETFIELD org/nlogo/nvm/Context.job : Lorg/nlogo/nvm/Job;
          ALOAD 2
          PUTFIELD org/nlogo/nvm/Job.result : Ljava/lang/Object;
          ALOAD 1
          ICONST_0
          PUTFIELD org/nlogo/nvm/Context.stopping : Z
          ALOAD 1
          ICONST_5
          PUTFIELD org/nlogo/nvm/Context.ip : I
          ALOAD 1
          GETFIELD org/nlogo/nvm/Context.activation : Lorg/nlogo/nvm/Activation;
          INVOKEVIRTUAL org/nlogo/nvm/Activation.nonLambdaActivation ()Lorg/nlogo/nvm/Activation;
          GETFIELD org/nlogo/nvm/Activation.procedure : Lorg/nlogo/nvm/Procedure;
          INVOKEVIRTUAL org/nlogo/nvm/Procedure.isReporter ()Z
          IFNE L12
          NEW org/nlogo/nvm/RuntimePrimitiveException
          DUP
          ALOAD 1
          ALOAD 0
          INVOKESTATIC org/nlogo/core/I18N.errorsJ ()Lorg/nlogo/core/I18NJava;
          LDC "org.nlogo.prim._report.canOnlyUseInToReport"
          ICONST_1
          ANEWARRAY java/lang/Object
          DUP
          ICONST_0
          LDC "REPORT"
          AASTORE
          INVOKEINTERFACE org/nlogo/core/I18NJava.getN (Ljava/lang/String;[Ljava/lang/Object;)Ljava/lang/String; (itf)
          INVOKESPECIAL org/nlogo/nvm/RuntimePrimitiveException.<init> (Lorg/nlogo/api/Context;Lorg/nlogo/nvm/Instruction;Ljava/lang/String;)V
          ATHROW
         L12
         FRAME FULL [org/nlogo/prim/_asm_proceduremysubtractheadings_report_4 org/nlogo/nvm/Context java/lang/Double T D] []
          ALOAD 1
          GETFIELD org/nlogo/nvm/Context.activation : Lorg/nlogo/nvm/Activation;
          GETFIELD org/nlogo/nvm/Activation.procedure : Lorg/nlogo/nvm/Procedure;
          INVOKEVIRTUAL org/nlogo/nvm/Procedure.isLambda ()Z
          IFEQ L13
          NEW org/nlogo/nvm/NonLocalExit
          DUP
          INVOKESPECIAL org/nlogo/nvm/NonLocalExit.<init> ()V
          ATHROW
         L13
         FRAME SAME
          ALOAD 1
          INVOKEVIRTUAL org/nlogo/nvm/Context.atTopActivation ()Z
          IFNE L14
          NEW org/nlogo/nvm/RuntimePrimitiveException
          DUP
          ALOAD 1
          ALOAD 0
          INVOKESTATIC org/nlogo/core/I18N.errorsJ ()Lorg/nlogo/core/I18NJava;
          LDC "org.nlogo.prim._report.mustImmediatelyBeUsedInToReport"
          ICONST_1
          ANEWARRAY java/lang/Object
          DUP
          ICONST_0
          LDC "REPORT"
          AASTORE
          INVOKEINTERFACE org/nlogo/core/I18NJava.getN (Ljava/lang/String;[Ljava/lang/Object;)Ljava/lang/String; (itf)
          INVOKESPECIAL org/nlogo/nvm/RuntimePrimitiveException.<init> (Lorg/nlogo/api/Context;Lorg/nlogo/nvm/Instruction;Ljava/lang/String;)V
          ATHROW
         L14
         FRAME SAME
          RETURN
[5]_asm_proceduremysubtractheadings_goto_5 => void
          // parameter final  context
         L0
          ALOAD 1
          BIPUSH 7
          PUTFIELD org/nlogo/nvm/Context.ip : I
         L1
          RETURN
[6]_asm_proceduremysubtractheadings_report_6 "report h1 - h2 + 360" Object => void
      _plus "h1 - h2 + 360" double,double => double
        _minus "h1 - h2" double,double => double
          _procedurevariable:H1 "h1" => Object
          _procedurevariable:H2 "h2" => Object
        _constdouble:360.0 "360" => double
          // parameter final  context
          // parameter final  context
          // parameter final  context
          // parameter final  d0
          // parameter final  d1
          // parameter final  context
          // parameter final  context
          // parameter final  d1
          // parameter final  d2
          TRYCATCHBLOCK L0 L1 L1 java/lang/ClassCastException
          TRYCATCHBLOCK L2 L3 L3 java/lang/ClassCastException
         L4
          ALOAD 1
          GETFIELD org/nlogo/nvm/Context.activation : Lorg/nlogo/nvm/Activation;
          GETFIELD org/nlogo/nvm/Activation.args : [Ljava/lang/Object;
          ICONST_0
          AALOAD
         L5
          ASTORE 2
         L0
          ALOAD 2
          CHECKCAST java/lang/Double
          INVOKEVIRTUAL java/lang/Double.doubleValue ()D
          GOTO L6
         L1
         FRAME FULL [org/nlogo/prim/_asm_proceduremysubtractheadings_report_6 org/nlogo/nvm/Context java/lang/Object] [java/lang/ClassCastException]
          POP
          NEW org/nlogo/nvm/ArgumentTypeException
          DUP
          ALOAD 1
          ALOAD 0
          BIPUSH 0
          LDC 1
          ALOAD 2
          INVOKESPECIAL org/nlogo/nvm/ArgumentTypeException.<init> (Lorg/nlogo/nvm/Context;Lorg/nlogo/nvm/Instruction;IILjava/lang/Object;)V
          ATHROW
         L6
         FRAME SAME1 D
          ALOAD 1
          GETFIELD org/nlogo/nvm/Context.activation : Lorg/nlogo/nvm/Activation;
          GETFIELD org/nlogo/nvm/Activation.args : [Ljava/lang/Object;
          ICONST_1
          AALOAD
         L7
          ASTORE 2
         L2
          ALOAD 2
          CHECKCAST java/lang/Double
          INVOKEVIRTUAL java/lang/Double.doubleValue ()D
          GOTO L8
         L3
         FRAME SAME1 java/lang/ClassCastException
          POP
          NEW org/nlogo/nvm/ArgumentTypeException
          DUP
          ALOAD 1
          ALOAD 0
          BIPUSH 1
          LDC 1
          ALOAD 2
          INVOKESPECIAL org/nlogo/nvm/ArgumentTypeException.<init> (Lorg/nlogo/nvm/Context;Lorg/nlogo/nvm/Instruction;IILjava/lang/Object;)V
          ATHROW
         L8
         FRAME FULL [org/nlogo/prim/_asm_proceduremysubtractheadings_report_6 org/nlogo/nvm/Context java/lang/Object] [D D]
          DSTORE 4
          DSTORE 2
          DLOAD 2
          DLOAD 4
          DSUB
         L9
          LDC 360.0D
         L10
          DSTORE 4
          DSTORE 2
          DLOAD 2
          DLOAD 4
          DADD
         L11
          DSTORE 2
          NEW java/lang/Double
          DUP
          DLOAD 2
          INVOKESPECIAL java/lang/Double.<init> (D)V
          ASTORE 2
          ALOAD 1
          GETFIELD org/nlogo/nvm/Context.job : Lorg/nlogo/nvm/Job;
          ALOAD 2
          PUTFIELD org/nlogo/nvm/Job.result : Ljava/lang/Object;
          ALOAD 1
          ICONST_0
          PUTFIELD org/nlogo/nvm/Context.stopping : Z
          ALOAD 1
          BIPUSH 7
          PUTFIELD org/nlogo/nvm/Context.ip : I
          ALOAD 1
          GETFIELD org/nlogo/nvm/Context.activation : Lorg/nlogo/nvm/Activation;
          INVOKEVIRTUAL org/nlogo/nvm/Activation.nonLambdaActivation ()Lorg/nlogo/nvm/Activation;
          GETFIELD org/nlogo/nvm/Activation.procedure : Lorg/nlogo/nvm/Procedure;
          INVOKEVIRTUAL org/nlogo/nvm/Procedure.isReporter ()Z
          IFNE L12
          NEW org/nlogo/nvm/RuntimePrimitiveException
          DUP
          ALOAD 1
          ALOAD 0
          INVOKESTATIC org/nlogo/core/I18N.errorsJ ()Lorg/nlogo/core/I18NJava;
          LDC "org.nlogo.prim._report.canOnlyUseInToReport"
          ICONST_1
          ANEWARRAY java/lang/Object
          DUP
          ICONST_0
          LDC "REPORT"
          AASTORE
          INVOKEINTERFACE org/nlogo/core/I18NJava.getN (Ljava/lang/String;[Ljava/lang/Object;)Ljava/lang/String; (itf)
          INVOKESPECIAL org/nlogo/nvm/RuntimePrimitiveException.<init> (Lorg/nlogo/api/Context;Lorg/nlogo/nvm/Instruction;Ljava/lang/String;)V
          ATHROW
         L12
         FRAME FULL [org/nlogo/prim/_asm_proceduremysubtractheadings_report_6 org/nlogo/nvm/Context java/lang/Double T D] []
          ALOAD 1
          GETFIELD org/nlogo/nvm/Context.activation : Lorg/nlogo/nvm/Activation;
          GETFIELD org/nlogo/nvm/Activation.procedure : Lorg/nlogo/nvm/Procedure;
          INVOKEVIRTUAL org/nlogo/nvm/Procedure.isLambda ()Z
          IFEQ L13
          NEW org/nlogo/nvm/NonLocalExit
          DUP
          INVOKESPECIAL org/nlogo/nvm/NonLocalExit.<init> ()V
          ATHROW
         L13
         FRAME SAME
          ALOAD 1
          INVOKEVIRTUAL org/nlogo/nvm/Context.atTopActivation ()Z
          IFNE L14
          NEW org/nlogo/nvm/RuntimePrimitiveException
          DUP
          ALOAD 1
          ALOAD 0
          INVOKESTATIC org/nlogo/core/I18N.errorsJ ()Lorg/nlogo/core/I18NJava;
          LDC "org.nlogo.prim._report.mustImmediatelyBeUsedInToReport"
          ICONST_1
          ANEWARRAY java/lang/Object
          DUP
          ICONST_0
          LDC "REPORT"
          AASTORE
          INVOKEINTERFACE org/nlogo/core/I18NJava.getN (Ljava/lang/String;[Ljava/lang/Object;)Ljava/lang/String; (itf)
          INVOKESPECIAL org/nlogo/nvm/RuntimePrimitiveException.<init> (Lorg/nlogo/api/Context;Lorg/nlogo/nvm/Instruction;Ljava/lang/String;)V
          ATHROW
         L14
         FRAME SAME
          RETURN
[7]_asm_proceduremysubtractheadings_returnreport_7 => void
          // parameter final  context
         L0
          NEW org/nlogo/nvm/RuntimePrimitiveException
          DUP
          ALOAD 1
          ALOAD 0
          GETSTATIC org/nlogo/core/I18N$.MODULE$ : Lorg/nlogo/core/I18N$;
          INVOKEVIRTUAL org/nlogo/core/I18N$.errors ()Lorg/nlogo/core/I18N$BundleKind;
          LDC "org.nlogo.prim._returnreport.reportNotCalledInReportProcedure"
          INVOKEVIRTUAL org/nlogo/core/I18N$BundleKind.get (Ljava/lang/String;)Ljava/lang/String;
          INVOKESPECIAL org/nlogo/nvm/RuntimePrimitiveException.<init> (Lorg/nlogo/api/Context;Lorg/nlogo/nvm/Instruction;Ljava/lang/String;)V
          ATHROW
         L1
         FRAME FULL [] [java/lang/Throwable]
          ATHROW

