globals [RESULT]
interfaceGlobals []
turtles-own [WHO COLOR HEADING XCOR YCOR SHAPE LABEL LABEL-COLOR BREED HIDDEN? SIZE PEN-SIZE PEN-MODE]
patches-own [PXCOR PYCOR PCOLOR PLABEL PLABEL-COLOR]
links-own [END1 END2 COLOR LABEL LABEL-COLOR HIDDEN? BREED THICKNESS SHAPE TIE-MODE]
breeds 
link-breeds 

procedure BENCHMARK:[_repeatlocal:0]{O---}:
[0]_asm_procedurebenchmark_randomseed_0 "random-seed 121862" double => void
      _constdouble:121862.0 "121862" => double
          // parameter final  context
          // parameter final  context
          // parameter final  arg0
         L0
          LDC 121862.0D
         L1
          DSTORE 2
          DLOAD 2
          D2L
          LSTORE 4
          LLOAD 4
          LDC -2147483648L
          LCMP
          IFLT L2
          LLOAD 4
          LDC 2147483647L
          LCMP
          IFLE L3
         L2
         FRAME APPEND [D J]
          NEW org/nlogo/nvm/RuntimePrimitiveException
          DUP
          ALOAD 1
          ALOAD 0
          GETSTATIC org/nlogo/api/Dump$.MODULE$ : Lorg/nlogo/api/Dump$;
          DLOAD 2
          INVOKEVIRTUAL org/nlogo/api/Dump$.number (D)Ljava/lang/String;
          INVOKEDYNAMIC makeConcatWithConstants(Ljava/lang/String;)Ljava/lang/String; [
            // handle kind 0x6 : INVOKESTATIC
            java/lang/invoke/StringConcatFactory.makeConcatWithConstants(Ljava/lang/invoke/MethodHandles$Lookup;Ljava/lang/String;Ljava/lang/invoke/MethodType;Ljava/lang/String;[Ljava/lang/Object;)Ljava/lang/invoke/CallSite;
            // arguments:
            "\u0001 is not in the allowable range for random seeds (-2147483648 to 2147483647)"
          ]
          INVOKESPECIAL org/nlogo/nvm/RuntimePrimitiveException.<init> (Lorg/nlogo/api/Context;Lorg/nlogo/nvm/Instruction;Ljava/lang/String;)V
          ATHROW
         L3
         FRAME SAME
          LLOAD 4
          L2I
          ISTORE 6
          ALOAD 1
          GETFIELD org/nlogo/nvm/Context.job : Lorg/nlogo/nvm/Job;
          GETFIELD org/nlogo/nvm/Job.random : Lorg/nlogo/api/MersenneTwisterFast;
          GETSTATIC scala/Int$.MODULE$ : Lscala/Int$;
          ILOAD 6
          INVOKEVIRTUAL scala/Int$.int2long (I)J
          INVOKEVIRTUAL org/nlogo/api/MersenneTwisterFast.setSeed (J)V
          ALOAD 1
          GETFIELD org/nlogo/nvm/Context.job : Lorg/nlogo/nvm/Job;
          GETFIELD org/nlogo/nvm/Job.workspace : Lorg/nlogo/nvm/Workspace;
          IFNULL L4
          ALOAD 1
          GETFIELD org/nlogo/nvm/Context.job : Lorg/nlogo/nvm/Job;
          GETFIELD org/nlogo/nvm/Job.random : Lorg/nlogo/api/MersenneTwisterFast;
          ALOAD 1
          GETFIELD org/nlogo/nvm/Context.job : Lorg/nlogo/nvm/Job;
          GETFIELD org/nlogo/nvm/Job.workspace : Lorg/nlogo/nvm/Workspace;
          INVOKEINTERFACE org/nlogo/nvm/Workspace.world ()Lorg/nlogo/agent/World; (itf)
          INVOKEVIRTUAL org/nlogo/agent/World.mainRNG ()Lorg/nlogo/api/MersenneTwisterFast;
          ASTORE 7
          DUP
          IFNONNULL L5
          POP
          ALOAD 7
          IFNULL L6
          GOTO L4
         L5
         FRAME FULL [org/nlogo/prim/_asm_procedurebenchmark_randomseed_0 org/nlogo/nvm/Context D J I org/nlogo/api/MersenneTwisterFast] [org/nlogo/api/MersenneTwisterFast]
          ALOAD 7
          INVOKEVIRTUAL java/lang/Object.equals (Ljava/lang/Object;)Z
          IFEQ L4
         L6
         FRAME SAME
          ALOAD 1
          GETFIELD org/nlogo/nvm/Context.job : Lorg/nlogo/nvm/Job;
          GETFIELD org/nlogo/nvm/Job.workspace : Lorg/nlogo/nvm/Workspace;
          INVOKEINTERFACE org/nlogo/nvm/Workspace.plotRNG ()Lorg/nlogo/api/MersenneTwisterFast; (itf)
          GETSTATIC scala/Int$.MODULE$ : Lscala/Int$;
          ILOAD 6
          INVOKEVIRTUAL scala/Int$.int2long (I)J
          INVOKEVIRTUAL org/nlogo/api/MersenneTwisterFast.setSeed (J)V
         L4
         FRAME CHOP 1
          ALOAD 1
          ICONST_1
          PUTFIELD org/nlogo/nvm/Context.ip : I
         L7
          RETURN
[1]_resettimer "reset-timer"
[2]_asm_procedurebenchmark_call_1 "setup"
         L0
          NEW org/nlogo/nvm/Activation
          DUP
          ALOAD 0
          GETFIELD org/nlogo/prim/_asm_procedurebenchmark_call_1.kept1_procedure : Lorg/nlogo/nvm/Procedure;
          ALOAD 1
          GETFIELD org/nlogo/nvm/Context.activation : Lorg/nlogo/nvm/Activation;
          SIPUSH 0
          ANEWARRAY java/lang/Object
          ICONST_3
          INVOKESPECIAL org/nlogo/nvm/Activation.<init> (Lorg/nlogo/nvm/Procedure;Lorg/nlogo/nvm/Activation;[Ljava/lang/Object;I)V
          ALOAD 1
          SWAP
          PUTFIELD org/nlogo/nvm/Context.activation : Lorg/nlogo/nvm/Activation;
          ALOAD 1
          ICONST_0
          PUTFIELD org/nlogo/nvm/Context.ip : I
         L1
          RETURN
[3]_asm_procedurebenchmark_repeatlocal_2 "repeat 3000 [ go ]" double => void
      _constdouble:3000.0 "3000" => double
          // parameter final  context
          // parameter final  context
          // parameter final  arg0
         L0
          LDC 3000.0D
         L1
          DSTORE 2
          ALOAD 1
          GETFIELD org/nlogo/nvm/Context.activation : Lorg/nlogo/nvm/Activation;
          GETFIELD org/nlogo/nvm/Activation.args : [Ljava/lang/Object;
          ICONST_0
          NEW org/nlogo/nvm/MutableLong
          DUP
          ALOAD 0
          DLOAD 2
          ALOAD 1
          INVOKEVIRTUAL org/nlogo/prim/_asm_procedurebenchmark_repeatlocal_2.validLong (DLorg/nlogo/nvm/Context;)J
          INVOKESPECIAL org/nlogo/nvm/MutableLong.<init> (J)V
          AASTORE
          ALOAD 1
          ICONST_5
          PUTFIELD org/nlogo/nvm/Context.ip : I
         L2
          RETURN
[4]_asm_procedurebenchmark_call_3 "go"
         L0
          NEW org/nlogo/nvm/Activation
          DUP
          ALOAD 0
          GETFIELD org/nlogo/prim/_asm_procedurebenchmark_call_3.kept1_procedure : Lorg/nlogo/nvm/Procedure;
          ALOAD 1
          GETFIELD org/nlogo/nvm/Context.activation : Lorg/nlogo/nvm/Activation;
          SIPUSH 0
          ANEWARRAY java/lang/Object
          ICONST_5
          INVOKESPECIAL org/nlogo/nvm/Activation.<init> (Lorg/nlogo/nvm/Procedure;Lorg/nlogo/nvm/Activation;[Ljava/lang/Object;I)V
          ALOAD 1
          SWAP
          PUTFIELD org/nlogo/nvm/Context.activation : Lorg/nlogo/nvm/Activation;
          ALOAD 1
          ICONST_0
          PUTFIELD org/nlogo/nvm/Context.ip : I
         L1
          RETURN
[5]_asm_procedurebenchmark_repeatlocalinternal_4 => void
          // parameter final  context
         L0
          ALOAD 1
          GETFIELD org/nlogo/nvm/Context.activation : Lorg/nlogo/nvm/Activation;
          GETFIELD org/nlogo/nvm/Activation.args : [Ljava/lang/Object;
          ICONST_0
          AALOAD
          CHECKCAST org/nlogo/nvm/MutableLong
          ASTORE 2
          ALOAD 2
          INVOKEVIRTUAL org/nlogo/nvm/MutableLong.value ()J
          LCONST_0
          LCMP
          IFGT L1
          ALOAD 1
          BIPUSH 6
          PUTFIELD org/nlogo/nvm/Context.ip : I
          GOTO L2
         L1
         FRAME APPEND [org/nlogo/nvm/MutableLong]
          ALOAD 2
          ALOAD 2
          INVOKEVIRTUAL org/nlogo/nvm/MutableLong.value ()J
          LCONST_1
          LSUB
          INVOKEVIRTUAL org/nlogo/nvm/MutableLong.value_$eq (J)V
          ALOAD 1
          ICONST_4
          PUTFIELD org/nlogo/nvm/Context.ip : I
         L2
         FRAME SAME
          RETURN
[6]_asm_procedurebenchmark_setobservervariable_5 "set result timer" Object => void
      _timer "timer" => double
          // parameter final  context
          // parameter final  context
          // parameter final  arg0
          TRYCATCHBLOCK L0 L1 L2 org/nlogo/api/AgentException
         L3
          ALOAD 0
          GETFIELD org/nlogo/prim/_asm_procedurebenchmark_setobservervariable_5.world : Lorg/nlogo/agent/World;
          INVOKEVIRTUAL org/nlogo/agent/World.timer ()Lorg/nlogo/api/Timer;
          INVOKEVIRTUAL org/nlogo/api/Timer.read ()D
         L4
          DSTORE 2
          NEW java/lang/Double
          DUP
          DLOAD 2
          INVOKESPECIAL java/lang/Double.<init> (D)V
          ASTORE 2
         L0
          ALOAD 0
          GETFIELD org/nlogo/prim/_asm_procedurebenchmark_setobservervariable_5.world : Lorg/nlogo/agent/World;
          INVOKEVIRTUAL org/nlogo/agent/World.observer ()Lorg/nlogo/agent/Observer;
          ICONST_0
          ALOAD 2
          INVOKEVIRTUAL org/nlogo/agent/Observer.setVariable (ILjava/lang/Object;)V
         L1
          GOTO L5
         L2
         FRAME FULL [org/nlogo/prim/_asm_procedurebenchmark_setobservervariable_5 org/nlogo/nvm/Context java/lang/Double] [org/nlogo/api/AgentException]
          ASTORE 3
          NEW org/nlogo/nvm/RuntimePrimitiveException
          DUP
          ALOAD 1
          ALOAD 0
          ALOAD 3
          INVOKEVIRTUAL org/nlogo/api/AgentException.getMessage ()Ljava/lang/String;
          INVOKESPECIAL org/nlogo/nvm/RuntimePrimitiveException.<init> (Lorg/nlogo/api/Context;Lorg/nlogo/nvm/Instruction;Ljava/lang/String;)V
          ATHROW
         L6
         FRAME FULL [] [java/lang/Throwable]
          NOP
          NOP
          ATHROW
         L5
         FRAME APPEND [org/nlogo/prim/_asm_procedurebenchmark_setobservervariable_5 org/nlogo/nvm/Context java/lang/Double]
          ALOAD 1
          BIPUSH 7
          PUTFIELD org/nlogo/nvm/Context.ip : I
         L7
          RETURN
[7]_asm_procedurebenchmark_return_6 => void
          // parameter final  context
         L0
          ALOAD 1
          INVOKEVIRTUAL org/nlogo/nvm/Context.returnFromProcedure ()V
          ALOAD 1
          ICONST_0
          PUTFIELD org/nlogo/nvm/Context.stopping : Z
         L1
          RETURN

procedure SETUP:[]{O---}:
[0]_clearall "ca"
[1]_resetticks "reset-ticks"
[2]_setdefaultshape "set-default-shape turtles "circle""
      _asm_proceduresetup_turtles_0 "turtles" => AgentSet
            // parameter final  context
           L0
            ALOAD 0
            GETFIELD org/nlogo/prim/_asm_proceduresetup_turtles_0.world : Lorg/nlogo/agent/World;
            INVOKEVIRTUAL org/nlogo/agent/World.turtles ()Lorg/nlogo/agent/TreeAgentSet;
           L1
            ARETURN
      _asm_proceduresetup_conststring_1 ""circle"" => String
            // parameter final  context
           L0
            LDC "circle"
           L1
            ARETURN
[3]_asm_proceduresetup_call_2 "make-node nobody"
      _nobody "nobody" => Nobody$
          // parameter final  context
         L0
          NEW org/nlogo/nvm/Activation
          DUP
          ALOAD 0
          GETFIELD org/nlogo/prim/_asm_proceduresetup_call_2.kept1_procedure : Lorg/nlogo/nvm/Procedure;
          ALOAD 1
          GETFIELD org/nlogo/nvm/Context.activation : Lorg/nlogo/nvm/Activation;
          SIPUSH 1
          ANEWARRAY java/lang/Object
          DUP
          ICONST_0
         L1
          GETSTATIC org/nlogo/core/Nobody$.MODULE$ : Lorg/nlogo/core/Nobody$;
         L2
          AASTORE
          ICONST_4
          INVOKESPECIAL org/nlogo/nvm/Activation.<init> (Lorg/nlogo/nvm/Procedure;Lorg/nlogo/nvm/Activation;[Ljava/lang/Object;I)V
          ALOAD 1
          SWAP
          PUTFIELD org/nlogo/nvm/Context.activation : Lorg/nlogo/nvm/Activation;
          ALOAD 1
          ICONST_0
          PUTFIELD org/nlogo/nvm/Context.ip : I
         L3
          RETURN
[4]_asm_proceduresetup_call_3 "make-node turtle 0"
      _turtle "turtle 0" double => Object
        _constdouble:0.0 "0" => double
          // parameter final  context
          // parameter final  context
          // parameter final  idDouble
         L0
          NEW org/nlogo/nvm/Activation
          DUP
          ALOAD 0
          GETFIELD org/nlogo/prim/_asm_proceduresetup_call_3.kept1_procedure : Lorg/nlogo/nvm/Procedure;
          ALOAD 1
          GETFIELD org/nlogo/nvm/Context.activation : Lorg/nlogo/nvm/Activation;
          SIPUSH 1
          ANEWARRAY java/lang/Object
          DUP
          ICONST_0
         L1
          DCONST_0
         L2
          DSTORE 2
          ALOAD 0
          DLOAD 2
          ALOAD 1
          INVOKEVIRTUAL org/nlogo/prim/_asm_proceduresetup_call_3.validLong (DLorg/nlogo/nvm/Context;)J
          LSTORE 4
          LLOAD 4
          L2D
          DLOAD 2
          DCMPL
          IFEQ L3
          NEW org/nlogo/nvm/RuntimePrimitiveException
          DUP
          ALOAD 1
          ALOAD 0
          DLOAD 2
          INVOKEDYNAMIC makeConcatWithConstants(D)Ljava/lang/String; [
            // handle kind 0x6 : INVOKESTATIC
            java/lang/invoke/StringConcatFactory.makeConcatWithConstants(Ljava/lang/invoke/MethodHandles$Lookup;Ljava/lang/String;Ljava/lang/invoke/MethodType;Ljava/lang/String;[Ljava/lang/Object;)Ljava/lang/invoke/CallSite;
            // arguments:
            "\u0001 is not an integer"
          ]
          INVOKESPECIAL org/nlogo/nvm/RuntimePrimitiveException.<init> (Lorg/nlogo/api/Context;Lorg/nlogo/nvm/Instruction;Ljava/lang/String;)V
          ATHROW
         L3
         FRAME FULL [org/nlogo/prim/_asm_proceduresetup_call_3 org/nlogo/nvm/Context D J] [L0 L0 org/nlogo/nvm/Procedure org/nlogo/nvm/Activation [Ljava/lang/Object; [Ljava/lang/Object; I]
          ALOAD 0
          GETFIELD org/nlogo/prim/_asm_proceduresetup_call_3.world : Lorg/nlogo/agent/World;
          LLOAD 4
          INVOKEVIRTUAL org/nlogo/agent/World.getTurtle (J)Lorg/nlogo/agent/Turtle;
          ASTORE 6
          ALOAD 6
          IFNONNULL L4
          GETSTATIC org/nlogo/core/Nobody$.MODULE$ : Lorg/nlogo/core/Nobody$;
          GOTO L5
         L4
         FRAME FULL [org/nlogo/prim/_asm_proceduresetup_call_3 org/nlogo/nvm/Context D J org/nlogo/agent/Turtle] [L0 L0 org/nlogo/nvm/Procedure org/nlogo/nvm/Activation [Ljava/lang/Object; [Ljava/lang/Object; I]
          ALOAD 6
         L5
         FRAME FULL [org/nlogo/prim/_asm_proceduresetup_call_3 org/nlogo/nvm/Context D J org/nlogo/agent/Turtle] [L0 L0 org/nlogo/nvm/Procedure org/nlogo/nvm/Activation [Ljava/lang/Object; [Ljava/lang/Object; I java/lang/Object]
          AASTORE
          ICONST_5
          INVOKESPECIAL org/nlogo/nvm/Activation.<init> (Lorg/nlogo/nvm/Procedure;Lorg/nlogo/nvm/Activation;[Ljava/lang/Object;I)V
          ALOAD 1
          SWAP
          PUTFIELD org/nlogo/nvm/Context.activation : Lorg/nlogo/nvm/Activation;
          ALOAD 1
          ICONST_0
          PUTFIELD org/nlogo/nvm/Context.ip : I
         L6
          RETURN
[5]_asm_proceduresetup_return_4 => void
          // parameter final  context
         L0
          ALOAD 1
          INVOKEVIRTUAL org/nlogo/nvm/Context.returnFromProcedure ()V
          ALOAD 1
          ICONST_0
          PUTFIELD org/nlogo/nvm/Context.stopping : Z
         L1
          RETURN

procedure GO:[]{O---}:
[0]_asm_procedurego_ask_0 "ask links [ set color gray ]" AgentSet => void
      _links "links" => AgentSet
          // parameter final  context
          // parameter final  context
          // parameter final  agents
         L0
          ALOAD 0
          GETFIELD org/nlogo/prim/_asm_procedurego_ask_0.world : Lorg/nlogo/agent/World;
          INVOKEVIRTUAL org/nlogo/agent/World.links ()Lorg/nlogo/agent/TreeAgentSet;
         L1
          ASTORE 2
          ALOAD 1
          GETFIELD org/nlogo/nvm/Context.agent : Lorg/nlogo/agent/Agent;
          INSTANCEOF org/nlogo/agent/Observer
          IFNE L2
          ALOAD 2
          ALOAD 0
          GETFIELD org/nlogo/prim/_asm_procedurego_ask_0.world : Lorg/nlogo/agent/World;
          INVOKEVIRTUAL org/nlogo/agent/World.turtles ()Lorg/nlogo/agent/TreeAgentSet;
          IF_ACMPNE L3
          NEW org/nlogo/nvm/RuntimePrimitiveException
          DUP
          ALOAD 1
          ALOAD 0
          GETSTATIC org/nlogo/core/I18N$.MODULE$ : Lorg/nlogo/core/I18N$;
          INVOKEVIRTUAL org/nlogo/core/I18N$.errors ()Lorg/nlogo/core/I18N$BundleKind;
          LDC "org.nlogo.prim.$common.onlyObserverCanAskAllTurtles"
          INVOKEVIRTUAL org/nlogo/core/I18N$BundleKind.get (Ljava/lang/String;)Ljava/lang/String;
          INVOKESPECIAL org/nlogo/nvm/RuntimePrimitiveException.<init> (Lorg/nlogo/api/Context;Lorg/nlogo/nvm/Instruction;Ljava/lang/String;)V
          ATHROW
         L3
         FRAME APPEND [org/nlogo/agent/TreeAgentSet]
          ALOAD 2
          ALOAD 0
          GETFIELD org/nlogo/prim/_asm_procedurego_ask_0.world : Lorg/nlogo/agent/World;
          INVOKEVIRTUAL org/nlogo/agent/World.patches ()Lorg/nlogo/agent/IndexedAgentSet;
          IF_ACMPNE L2
          NEW org/nlogo/nvm/RuntimePrimitiveException
          DUP
          ALOAD 1
          ALOAD 0
          GETSTATIC org/nlogo/core/I18N$.MODULE$ : Lorg/nlogo/core/I18N$;
          INVOKEVIRTUAL org/nlogo/core/I18N$.errors ()Lorg/nlogo/core/I18N$BundleKind;
          LDC "org.nlogo.prim.$common.onlyObserverCanAskAllPatches"
          INVOKEVIRTUAL org/nlogo/core/I18N$BundleKind.get (Ljava/lang/String;)Ljava/lang/String;
          INVOKESPECIAL org/nlogo/nvm/RuntimePrimitiveException.<init> (Lorg/nlogo/api/Context;Lorg/nlogo/nvm/Instruction;Ljava/lang/String;)V
          ATHROW
         L2
         FRAME SAME
          ALOAD 1
          ALOAD 2
          ICONST_1
          INVOKEVIRTUAL org/nlogo/nvm/Context.runExclusiveJob (Lorg/nlogo/agent/AgentSet;I)V
          ALOAD 1
          ICONST_3
          PUTFIELD org/nlogo/nvm/Context.ip : I
         L4
          RETURN
[1]_asm_procedurego_setturtleorlinkvariable_1 "set color gray" Object => void
      _constdouble:5.0 "gray" => Double
          // parameter final  context
          // parameter final  context
          // parameter final  value
          TRYCATCHBLOCK L0 L1 L2 org/nlogo/api/AgentException
         L3
          ALOAD 0
          GETFIELD org/nlogo/prim/_asm_procedurego_setturtleorlinkvariable_1.kept2_value : Ljava/lang/Double;
         L4
          ASTORE 2
          ALOAD 1
          GETFIELD org/nlogo/nvm/Context.agent : Lorg/nlogo/agent/Agent;
          ASTORE 3
         L0
          ALOAD 3
          INVOKEVIRTUAL org/nlogo/agent/Agent.agentBit ()I
          ISTORE 4
          ICONST_2
          ILOAD 4
          IF_ICMPNE L5
          ALOAD 3
          ICONST_1
          ALOAD 2
          INVOKEVIRTUAL org/nlogo/agent/Agent.setTurtleVariable (ILjava/lang/Object;)V
          GOTO L1
         L5
         FRAME APPEND [java/lang/Double org/nlogo/agent/Agent I]
          BIPUSH 8
          ILOAD 4
          IF_ICMPNE L6
          ALOAD 3
          ICONST_2
          ALOAD 2
          INVOKEVIRTUAL org/nlogo/agent/Agent.setLinkVariable (ILjava/lang/Object;)V
          GOTO L1
         L6
         FRAME SAME
          ALOAD 3
          LDC "COLOR"
          ALOAD 2
          INVOKEVIRTUAL org/nlogo/agent/Agent.setTurtleOrLinkVariable (Ljava/lang/String;Ljava/lang/Object;)V
         L1
         FRAME SAME
          GOTO L7
         L2
         FRAME FULL [org/nlogo/prim/_asm_procedurego_setturtleorlinkvariable_1 org/nlogo/nvm/Context java/lang/Double org/nlogo/agent/Agent] [org/nlogo/api/AgentException]
          ASTORE 5
          NEW org/nlogo/nvm/RuntimePrimitiveException
          DUP
          ALOAD 1
          ALOAD 0
          ALOAD 5
          INVOKEVIRTUAL org/nlogo/api/AgentException.getMessage ()Ljava/lang/String;
          INVOKESPECIAL org/nlogo/nvm/RuntimePrimitiveException.<init> (Lorg/nlogo/api/Context;Lorg/nlogo/nvm/Instruction;Ljava/lang/String;)V
          ATHROW
         L8
         FRAME FULL [] [java/lang/Throwable]
          NOP
          NOP
          ATHROW
         L7
         FRAME FULL [org/nlogo/prim/_asm_procedurego_setturtleorlinkvariable_1 org/nlogo/nvm/Context java/lang/Double org/nlogo/agent/Agent I] []
          ALOAD 1
          ICONST_2
          PUTFIELD org/nlogo/nvm/Context.ip : I
         L9
          RETURN
[2]_asm_procedurego_done_2 => void
          // parameter final  context
         L0
          ALOAD 1
          ICONST_1
          PUTFIELD org/nlogo/nvm/Context.finished : Z
         L1
          RETURN
[3]_asm_procedurego_call_3 "make-node find-partner"
      _callreport:FIND-PARTNER "find-partner"
         L0
          NEW org/nlogo/nvm/Activation
          DUP
          ALOAD 0
          GETFIELD org/nlogo/prim/_asm_procedurego_call_3.kept1_procedure : Lorg/nlogo/nvm/Procedure;
          ALOAD 1
          GETFIELD org/nlogo/nvm/Context.activation : Lorg/nlogo/nvm/Activation;
          SIPUSH 1
          ANEWARRAY java/lang/Object
          DUP
          ICONST_0
         L1
          NEW org/nlogo/nvm/Activation
          DUP
          ALOAD 0
          GETFIELD org/nlogo/prim/_asm_procedurego_call_3.kept2_procedure : Lorg/nlogo/nvm/Procedure;
          ALOAD 1
          GETFIELD org/nlogo/nvm/Context.activation : Lorg/nlogo/nvm/Activation;
          SIPUSH 2
          ANEWARRAY java/lang/Object
          ICONST_3
          INVOKESPECIAL org/nlogo/nvm/Activation.<init> (Lorg/nlogo/nvm/Procedure;Lorg/nlogo/nvm/Activation;[Ljava/lang/Object;I)V
          ALOAD 1
          SWAP
          INVOKEVIRTUAL org/nlogo/nvm/Context.callReporterProcedure (Lorg/nlogo/nvm/Activation;)Ljava/lang/Object;
          DUP
          IFNONNULL L2
          NEW org/nlogo/nvm/RuntimePrimitiveException
          DUP
          ALOAD 1
          ALOAD 0
          LDC "the FIND-PARTNER procedure failed to report a result"
          INVOKESPECIAL org/nlogo/nvm/RuntimePrimitiveException.<init> (Lorg/nlogo/api/Context;Lorg/nlogo/nvm/Instruction;Ljava/lang/String;)V
          ATHROW
         L2
         FRAME FULL [org/nlogo/prim/_asm_procedurego_call_3 org/nlogo/nvm/Context] [L0 L0 org/nlogo/nvm/Procedure org/nlogo/nvm/Activation [Ljava/lang/Object; [Ljava/lang/Object; I java/lang/Object]
          AASTORE
          ICONST_4
          INVOKESPECIAL org/nlogo/nvm/Activation.<init> (Lorg/nlogo/nvm/Procedure;Lorg/nlogo/nvm/Activation;[Ljava/lang/Object;I)V
          ALOAD 1
          SWAP
          PUTFIELD org/nlogo/nvm/Context.activation : Lorg/nlogo/nvm/Activation;
          ALOAD 1
          ICONST_0
          PUTFIELD org/nlogo/nvm/Context.ip : I
         L3
          RETURN
[4]_tick "tick"
[5]_asm_procedurego_return_4 => void
          // parameter final  context
         L0
          ALOAD 1
          INVOKEVIRTUAL org/nlogo/nvm/Context.returnFromProcedure ()V
          ALOAD 1
          ICONST_0
          PUTFIELD org/nlogo/nvm/Context.stopping : Z
         L1
          RETURN

procedure MAKE-NODE:[OLD-NODE]{O---}:
[0]_createorderedturtles:,+11 "cro 1 set color red [ if old-node != nobody create-link-with old-node [ set color green ] move-to old-node rt random 360 [ fd 8 ] ]"
      _asm_proceduremakenode_constdouble_0 "1" => Double
            // parameter final  context
           L0
            ALOAD 0
            GETFIELD org/nlogo/prim/_asm_proceduremakenode_constdouble_0.kept1_value : Ljava/lang/Double;
           L1
            ARETURN
[1]_asm_proceduremakenode_setturtleorlinkvariable_1 "set color red" Object => void
      _constdouble:15.0 "red" => Double
          // parameter final  context
          // parameter final  context
          // parameter final  value
          TRYCATCHBLOCK L0 L1 L2 org/nlogo/api/AgentException
         L3
          ALOAD 0
          GETFIELD org/nlogo/prim/_asm_proceduremakenode_setturtleorlinkvariable_1.kept2_value : Ljava/lang/Double;
         L4
          ASTORE 2
          ALOAD 1
          GETFIELD org/nlogo/nvm/Context.agent : Lorg/nlogo/agent/Agent;
          ASTORE 3
         L0
          ALOAD 3
          INVOKEVIRTUAL org/nlogo/agent/Agent.agentBit ()I
          ISTORE 4
          ICONST_2
          ILOAD 4
          IF_ICMPNE L5
          ALOAD 3
          ICONST_1
          ALOAD 2
          INVOKEVIRTUAL org/nlogo/agent/Agent.setTurtleVariable (ILjava/lang/Object;)V
          GOTO L1
         L5
         FRAME APPEND [java/lang/Double org/nlogo/agent/Agent I]
          BIPUSH 8
          ILOAD 4
          IF_ICMPNE L6
          ALOAD 3
          ICONST_2
          ALOAD 2
          INVOKEVIRTUAL org/nlogo/agent/Agent.setLinkVariable (ILjava/lang/Object;)V
          GOTO L1
         L6
         FRAME SAME
          ALOAD 3
          LDC "COLOR"
          ALOAD 2
          INVOKEVIRTUAL org/nlogo/agent/Agent.setTurtleOrLinkVariable (Ljava/lang/String;Ljava/lang/Object;)V
         L1
         FRAME SAME
          GOTO L7
         L2
         FRAME FULL [org/nlogo/prim/_asm_proceduremakenode_setturtleorlinkvariable_1 org/nlogo/nvm/Context java/lang/Double org/nlogo/agent/Agent] [org/nlogo/api/AgentException]
          ASTORE 5
          NEW org/nlogo/nvm/RuntimePrimitiveException
          DUP
          ALOAD 1
          ALOAD 0
          ALOAD 5
          INVOKEVIRTUAL org/nlogo/api/AgentException.getMessage ()Ljava/lang/String;
          INVOKESPECIAL org/nlogo/nvm/RuntimePrimitiveException.<init> (Lorg/nlogo/api/Context;Lorg/nlogo/nvm/Instruction;Ljava/lang/String;)V
          ATHROW
         L8
         FRAME FULL [] [java/lang/Throwable]
          NOP
          NOP
          ATHROW
         L7
         FRAME FULL [org/nlogo/prim/_asm_proceduremakenode_setturtleorlinkvariable_1 org/nlogo/nvm/Context java/lang/Double org/nlogo/agent/Agent I] []
          ALOAD 1
          ICONST_2
          PUTFIELD org/nlogo/nvm/Context.ip : I
         L9
          RETURN
[2]_asm_proceduremakenode_if_2 "if old-node != nobody create-link-with old-node [ set color green ] move-to old-node rt random 360 [ fd 8 ]" boolean => void
      _notequal "old-node != nobody" Object,Object => boolean
        _procedurevariable:OLD-NODE "old-node" => Object
        _nobody "nobody" => Nobody$
          // parameter final  context
          // parameter final  context
          // parameter final  context
          // parameter final  arg0
          // parameter final  arg1
          // parameter final  context
          // parameter final  arg0
         L0
          ALOAD 1
          GETFIELD org/nlogo/nvm/Context.activation : Lorg/nlogo/nvm/Activation;
          GETFIELD org/nlogo/nvm/Activation.args : [Ljava/lang/Object;
          ICONST_0
          AALOAD
         L1
          GETSTATIC org/nlogo/core/Nobody$.MODULE$ : Lorg/nlogo/core/Nobody$;
         L2
          ASTORE 3
          ASTORE 2
          GETSTATIC org/nlogo/api/Equality$.MODULE$ : Lorg/nlogo/api/Equality$;
          ALOAD 2
          ALOAD 3
          INVOKEVIRTUAL org/nlogo/api/Equality$.equals (Ljava/lang/Object;Ljava/lang/Object;)Z
          IFNE L3
          ICONST_1
          GOTO L4
         L3
         FRAME APPEND [java/lang/Object org/nlogo/core/Nobody$]
          ICONST_0
         L4
         FRAME SAME1 I
          ISTORE 2
          ALOAD 1
          ILOAD 2
          IFEQ L5
          ICONST_3
          GOTO L6
         L5
         FRAME FULL [org/nlogo/prim/_asm_proceduremakenode_if_2 org/nlogo/nvm/Context I org/nlogo/core/Nobody$] [org/nlogo/nvm/Context]
          BIPUSH 10
         L6
         FRAME FULL [org/nlogo/prim/_asm_proceduremakenode_if_2 org/nlogo/nvm/Context I org/nlogo/core/Nobody$] [org/nlogo/nvm/Context I]
          PUTFIELD org/nlogo/nvm/Context.ip : I
         L7
          RETURN
[3]_createlinkwith:,+6 "create-link-with old-node [ set color green ]"
      _asm_proceduremakenode_procedurevariable_3 "old-node" => Object
            // parameter final  context
           L0
            ALOAD 1
            GETFIELD org/nlogo/nvm/Context.activation : Lorg/nlogo/nvm/Activation;
            GETFIELD org/nlogo/nvm/Activation.args : [Ljava/lang/Object;
            ICONST_0
            AALOAD
           L1
            ARETURN
[4]_asm_proceduremakenode_setturtleorlinkvariable_4 "set color green" Object => void
      _constdouble:55.0 "green" => Double
          // parameter final  context
          // parameter final  context
          // parameter final  value
          TRYCATCHBLOCK L0 L1 L2 org/nlogo/api/AgentException
         L3
          ALOAD 0
          GETFIELD org/nlogo/prim/_asm_proceduremakenode_setturtleorlinkvariable_4.kept2_value : Ljava/lang/Double;
         L4
          ASTORE 2
          ALOAD 1
          GETFIELD org/nlogo/nvm/Context.agent : Lorg/nlogo/agent/Agent;
          ASTORE 3
         L0
          ALOAD 3
          INVOKEVIRTUAL org/nlogo/agent/Agent.agentBit ()I
          ISTORE 4
          ICONST_2
          ILOAD 4
          IF_ICMPNE L5
          ALOAD 3
          ICONST_1
          ALOAD 2
          INVOKEVIRTUAL org/nlogo/agent/Agent.setTurtleVariable (ILjava/lang/Object;)V
          GOTO L1
         L5
         FRAME APPEND [java/lang/Double org/nlogo/agent/Agent I]
          BIPUSH 8
          ILOAD 4
          IF_ICMPNE L6
          ALOAD 3
          ICONST_2
          ALOAD 2
          INVOKEVIRTUAL org/nlogo/agent/Agent.setLinkVariable (ILjava/lang/Object;)V
          GOTO L1
         L6
         FRAME SAME
          ALOAD 3
          LDC "COLOR"
          ALOAD 2
          INVOKEVIRTUAL org/nlogo/agent/Agent.setTurtleOrLinkVariable (Ljava/lang/String;Ljava/lang/Object;)V
         L1
         FRAME SAME
          GOTO L7
         L2
         FRAME FULL [org/nlogo/prim/_asm_proceduremakenode_setturtleorlinkvariable_4 org/nlogo/nvm/Context java/lang/Double org/nlogo/agent/Agent] [org/nlogo/api/AgentException]
          ASTORE 5
          NEW org/nlogo/nvm/RuntimePrimitiveException
          DUP
          ALOAD 1
          ALOAD 0
          ALOAD 5
          INVOKEVIRTUAL org/nlogo/api/AgentException.getMessage ()Ljava/lang/String;
          INVOKESPECIAL org/nlogo/nvm/RuntimePrimitiveException.<init> (Lorg/nlogo/api/Context;Lorg/nlogo/nvm/Instruction;Ljava/lang/String;)V
          ATHROW
         L8
         FRAME FULL [] [java/lang/Throwable]
          NOP
          NOP
          ATHROW
         L7
         FRAME FULL [org/nlogo/prim/_asm_proceduremakenode_setturtleorlinkvariable_4 org/nlogo/nvm/Context java/lang/Double org/nlogo/agent/Agent I] []
          ALOAD 1
          ICONST_5
          PUTFIELD org/nlogo/nvm/Context.ip : I
         L9
          RETURN
[5]_asm_proceduremakenode_done_5 => void
          // parameter final  context
         L0
          ALOAD 1
          ICONST_1
          PUTFIELD org/nlogo/nvm/Context.finished : Z
         L1
          RETURN
[6]_moveto "move-to old-node"
      _asm_proceduremakenode_procedurevariable_6 "old-node" => Object
            // parameter final  context
           L0
            ALOAD 1
            GETFIELD org/nlogo/nvm/Context.activation : Lorg/nlogo/nvm/Activation;
            GETFIELD org/nlogo/nvm/Activation.args : [Ljava/lang/Object;
            ICONST_0
            AALOAD
           L1
            ARETURN
[7]_asm_proceduremakenode_right_7 "rt random 360" double => void
      _randomconst:360 "random 360" => double
          // parameter final  context
          // parameter final  context
          // parameter final  delta
         L0
          ALOAD 1
          GETFIELD org/nlogo/nvm/Context.job : Lorg/nlogo/nvm/Job;
          GETFIELD org/nlogo/nvm/Job.random : Lorg/nlogo/api/MersenneTwisterFast;
          LDC 360L
          INVOKEVIRTUAL org/nlogo/api/MersenneTwisterFast.nextLong (J)J
          L2D
         L1
          DSTORE 2
          ALOAD 1
          GETFIELD org/nlogo/nvm/Context.agent : Lorg/nlogo/agent/Agent;
          CHECKCAST org/nlogo/agent/Turtle
          DLOAD 2
          INVOKEVIRTUAL org/nlogo/agent/Turtle.turnRight (D)V
          ALOAD 1
          BIPUSH 8
          PUTFIELD org/nlogo/nvm/Context.ip : I
         L2
          RETURN
[8]_asm_proceduremakenode_fd_8 "fd 8" double => void
      _constdouble:8.0 "8" => double
          // parameter final  context
          // parameter final  context
          // parameter final  d
         L0
          LDC 8.0D
         L1
          DSTORE 2
          ALOAD 1
          GETFIELD org/nlogo/nvm/Context.activation : Lorg/nlogo/nvm/Activation;
          GETFIELD org/nlogo/nvm/Activation.binding : Lorg/nlogo/nvm/Binding;
          ALOAD 0
          GETFIELD org/nlogo/prim/_asm_proceduremakenode_fd_8.kept1__let : Lorg/nlogo/core/Let;
          NEW org/nlogo/nvm/MutableDouble
          DUP
          DLOAD 2
          INVOKESPECIAL org/nlogo/nvm/MutableDouble.<init> (D)V
          INVOKEVIRTUAL org/nlogo/nvm/Binding.let (Lorg/nlogo/core/Let;Ljava/lang/Object;)V
          ALOAD 1
          BIPUSH 9
          PUTFIELD org/nlogo/nvm/Context.ip : I
         L2
          RETURN
[9]_asm_proceduremakenode_fdinternal_9 => void
          // parameter final  context
          TRYCATCHBLOCK L0 L1 L2 org/nlogo/api/AgentException
          TRYCATCHBLOCK L3 L4 L5 org/nlogo/api/AgentException
         L6
          ALOAD 1
          GETFIELD org/nlogo/nvm/Context.agent : Lorg/nlogo/agent/Agent;
          CHECKCAST org/nlogo/agent/Turtle
          ASTORE 2
          ALOAD 1
          GETFIELD org/nlogo/nvm/Context.activation : Lorg/nlogo/nvm/Activation;
          GETFIELD org/nlogo/nvm/Activation.binding : Lorg/nlogo/nvm/Binding;
          ALOAD 0
          GETFIELD org/nlogo/prim/_asm_proceduremakenode_fdinternal_9.kept1_let : Lorg/nlogo/core/Let;
          INVOKEVIRTUAL org/nlogo/nvm/Binding.getLet (Lorg/nlogo/core/Let;)Ljava/lang/Object;
          CHECKCAST org/nlogo/nvm/MutableDouble
          ASTORE 3
          ALOAD 3
          INVOKEVIRTUAL org/nlogo/nvm/MutableDouble.value ()D
          DSTORE 4
          DLOAD 4
          INVOKESTATIC java/lang/StrictMath.abs (D)D
          DSTORE 6
          DLOAD 6
          GETSTATIC org/nlogo/api/Numbers$.MODULE$ : Lorg/nlogo/api/Numbers$;
          INVOKEVIRTUAL org/nlogo/api/Numbers$.Infinitesimal ()D
          DCMPG
          IFGT L7
          ALOAD 1
          BIPUSH 10
          PUTFIELD org/nlogo/nvm/Context.ip : I
          GOTO L8
         L7
         FRAME FULL [org/nlogo/prim/_asm_proceduremakenode_fdinternal_9 org/nlogo/nvm/Context org/nlogo/agent/Turtle org/nlogo/nvm/MutableDouble D D] []
          DLOAD 6
          DCONST_1
          DCMPG
          IFGT L9
         L0
          ALOAD 2
          DLOAD 4
          INVOKEVIRTUAL org/nlogo/agent/Turtle.jump (D)V
         L1
          GOTO L10
         L2
         FRAME SAME1 org/nlogo/api/AgentException
          POP
         L10
         FRAME SAME
          ALOAD 1
          BIPUSH 10
          PUTFIELD org/nlogo/nvm/Context.ip : I
          GOTO L8
         L9
         FRAME SAME
          DLOAD 4
          ICONST_0
          I2D
          DCMPL
          IFLE L11
          ICONST_1
          GOTO L12
         L11
         FRAME SAME
          ICONST_M1
         L12
         FRAME SAME1 I
          ISTORE 8
         L3
          ALOAD 2
          GETSTATIC scala/Int$.MODULE$ : Lscala/Int$;
          ILOAD 8
          INVOKEVIRTUAL scala/Int$.int2double (I)D
          INVOKEVIRTUAL org/nlogo/agent/Turtle.jump (D)V
          ALOAD 3
          ALOAD 3
          INVOKEVIRTUAL org/nlogo/nvm/MutableDouble.value ()D
          ILOAD 8
          I2D
          DSUB
          INVOKEVIRTUAL org/nlogo/nvm/MutableDouble.value_$eq (D)V
         L4
          GOTO L8
         L5
         FRAME FULL [org/nlogo/prim/_asm_proceduremakenode_fdinternal_9 org/nlogo/nvm/Context org/nlogo/agent/Turtle org/nlogo/nvm/MutableDouble D D I] [org/nlogo/api/AgentException]
          POP
          ALOAD 1
          BIPUSH 10
          PUTFIELD org/nlogo/nvm/Context.ip : I
         L8
         FRAME CHOP 1
          RETURN
[10]_asm_proceduremakenode_done_10 => void
          // parameter final  context
         L0
          ALOAD 1
          ICONST_1
          PUTFIELD org/nlogo/nvm/Context.finished : Z
         L1
          RETURN
[11]_asm_proceduremakenode_return_11 => void
          // parameter final  context
         L0
          ALOAD 1
          INVOKEVIRTUAL org/nlogo/nvm/Context.returnFromProcedure ()V
          ALOAD 1
          ICONST_0
          PUTFIELD org/nlogo/nvm/Context.stopping : Z
         L1
          RETURN

reporter procedure FIND-PARTNER:[TOTAL PARTNER]{OTPL}:
[0]_asm_procedurefindpartner_setprocedurevariable_0 "let random-float sum [ count link-neighbors ] of turtles" Object => void
      _randomfloat "random-float sum [ count link-neighbors ] of turtles" double => double
        _sum "sum [ count link-neighbors ] of turtles" LogoList => double
          _of "[ count link-neighbors ] of turtles"
            _asm_procedurefindpartner_count_1 "count link-neighbors" AgentSet => double
              _linkneighbors:null "link-neighbors" => AgentSet
                  // parameter final  context
                  // parameter final  context
                  // parameter final  arg0
                 L0
                  ALOAD 0
                  GETFIELD org/nlogo/prim/_asm_procedurefindpartner_count_1.kept2_breedName : Ljava/lang/String;
                  IFNONNULL L1
                  ALOAD 0
                  GETFIELD org/nlogo/prim/_asm_procedurefindpartner_count_1.world : Lorg/nlogo/agent/World;
                  INVOKEVIRTUAL org/nlogo/agent/World.links ()Lorg/nlogo/agent/TreeAgentSet;
                  GOTO L2
                 L1
                 FRAME SAME
                  ALOAD 0
                  GETFIELD org/nlogo/prim/_asm_procedurefindpartner_count_1.world : Lorg/nlogo/agent/World;
                  ALOAD 0
                  GETFIELD org/nlogo/prim/_asm_procedurefindpartner_count_1.kept2_breedName : Ljava/lang/String;
                  INVOKEVIRTUAL org/nlogo/agent/World.getLinkBreed (Ljava/lang/String;)Lorg/nlogo/agent/AgentSet;
                 L2
                 FRAME SAME1 org/nlogo/agent/AgentSet
                  ASTORE 2
                  GETSTATIC org/nlogo/agent/AgentSet$.MODULE$ : Lorg/nlogo/agent/AgentSet$;
                  GETSTATIC org/nlogo/core/AgentKind$Turtle$.MODULE$ : Lorg/nlogo/core/AgentKind$Turtle$;
                  ALOAD 0
                  GETFIELD org/nlogo/prim/_asm_procedurefindpartner_count_1.world : Lorg/nlogo/agent/World;
                  INVOKEVIRTUAL org/nlogo/agent/World.linkManager ()Lorg/nlogo/agent/LinkManager;
                  ALOAD 1
                  GETFIELD org/nlogo/nvm/Context.agent : Lorg/nlogo/agent/Agent;
                  CHECKCAST org/nlogo/agent/Turtle
                  ALOAD 2
                  INVOKEINTERFACE org/nlogo/agent/LinkManager.neighbors (Lorg/nlogo/agent/Turtle;Lorg/nlogo/agent/AgentSet;)[Lorg/nlogo/agent/Turtle; (itf)
                  INVOKEVIRTUAL org/nlogo/agent/AgentSet$.fromArray (Lorg/nlogo/core/AgentKind;[Lorg/nlogo/agent/Agent;)Lorg/nlogo/agent/IndexedAgentSet;
                 L3
                  ASTORE 2
                  GETSTATIC scala/Int$.MODULE$ : Lscala/Int$;
                  ALOAD 2
                  INVOKEVIRTUAL org/nlogo/agent/AgentSet.count ()I
                  INVOKEVIRTUAL scala/Int$.int2double (I)D
                 L4
                  DSTORE 2
                  NEW java/lang/Double
                  DUP
                  DLOAD 2
                  INVOKESPECIAL java/lang/Double.<init> (D)V
                  ARETURN
            _asm_procedurefindpartner_turtles_2 "turtles" => AgentSet
                  // parameter final  context
                 L0
                  ALOAD 0
                  GETFIELD org/nlogo/prim/_asm_procedurefindpartner_turtles_2.world : Lorg/nlogo/agent/World;
                  INVOKEVIRTUAL org/nlogo/agent/World.turtles ()Lorg/nlogo/agent/TreeAgentSet;
                 L1
                  ARETURN
          // parameter final  context
          // parameter final  l0
          // parameter final  context
          // parameter final  d
          // parameter final  context
          // parameter final  arg0
          TRYCATCHBLOCK L0 L1 L1 java/lang/ClassCastException
          ALOAD 0
          GETFIELD org/nlogo/prim/_asm_procedurefindpartner_setprocedurevariable_0.keptinstr4 : Lorg/nlogo/prim/_of;
          ALOAD 1
          INVOKEVIRTUAL org/nlogo/prim/_of.report (Lorg/nlogo/nvm/Context;)Ljava/lang/Object;
         L2
          ASTORE 2
         L0
          ALOAD 2
          CHECKCAST org/nlogo/core/LogoList
          GOTO L3
         L1
         FRAME FULL [org/nlogo/prim/_asm_procedurefindpartner_setprocedurevariable_0 org/nlogo/nvm/Context java/lang/Object] [java/lang/ClassCastException]
          POP
          NEW org/nlogo/nvm/ArgumentTypeException
          DUP
          ALOAD 1
          ALOAD 0
          BIPUSH 0
          LDC 8
          ALOAD 2
          INVOKESPECIAL org/nlogo/nvm/ArgumentTypeException.<init> (Lorg/nlogo/nvm/Context;Lorg/nlogo/nvm/Instruction;IILjava/lang/Object;)V
          ATHROW
         L3
         FRAME SAME1 org/nlogo/core/LogoList
          ASTORE 2
          DCONST_0
          DSTORE 3
          ALOAD 2
          INVOKEVIRTUAL org/nlogo/core/LogoList.javaIterator ()Ljava/util/Iterator;
          ASTORE 5
         L4
         FRAME FULL [org/nlogo/prim/_asm_procedurefindpartner_setprocedurevariable_0 org/nlogo/nvm/Context org/nlogo/core/LogoList D java/util/Iterator] []
          ALOAD 5
          INVOKEINTERFACE java/util/Iterator.hasNext ()Z (itf)
          IFEQ L5
          ALOAD 5
          INVOKEINTERFACE java/util/Iterator.next ()Ljava/lang/Object; (itf)
          ASTORE 6
          ALOAD 6
          INSTANCEOF java/lang/Double
          IFEQ L6
          ALOAD 6
          CHECKCAST java/lang/Double
          ASTORE 7
          DLOAD 3
          ALOAD 7
          INVOKEVIRTUAL java/lang/Double.doubleValue ()D
          DADD
          DSTORE 3
          GOTO L4
         L6
         FRAME APPEND [java/lang/Object]
          GOTO L4
         L5
         FRAME CHOP 1
          ALOAD 0
          DLOAD 3
          ALOAD 1
          INVOKEVIRTUAL org/nlogo/prim/_asm_procedurefindpartner_setprocedurevariable_0.validDouble (DLorg/nlogo/nvm/Context;)D
         L7
          DSTORE 2
          DLOAD 2
          ALOAD 1
          GETFIELD org/nlogo/nvm/Context.job : Lorg/nlogo/nvm/Job;
          GETFIELD org/nlogo/nvm/Job.random : Lorg/nlogo/api/MersenneTwisterFast;
          INVOKEVIRTUAL org/nlogo/api/MersenneTwisterFast.nextDouble ()D
          DMUL
         L8
          DSTORE 2
          NEW java/lang/Double
          DUP
          DLOAD 2
          INVOKESPECIAL java/lang/Double.<init> (D)V
          ASTORE 2
          ALOAD 1
          GETFIELD org/nlogo/nvm/Context.activation : Lorg/nlogo/nvm/Activation;
          GETFIELD org/nlogo/nvm/Activation.args : [Ljava/lang/Object;
          ICONST_0
          ALOAD 2
          AASTORE
          ALOAD 1
          ICONST_1
          PUTFIELD org/nlogo/nvm/Context.ip : I
         L9
          RETURN
[1]_asm_procedurefindpartner_setprocedurevariable_3 "let nobody" Object => void
      _nobody "nobody" => Nobody$
          // parameter final  context
          // parameter final  context
          // parameter final  arg0
         L0
          GETSTATIC org/nlogo/core/Nobody$.MODULE$ : Lorg/nlogo/core/Nobody$;
         L1
          ASTORE 2
          ALOAD 1
          GETFIELD org/nlogo/nvm/Context.activation : Lorg/nlogo/nvm/Activation;
          GETFIELD org/nlogo/nvm/Activation.args : [Ljava/lang/Object;
          ICONST_1
          ALOAD 2
          AASTORE
          ALOAD 1
          ICONST_2
          PUTFIELD org/nlogo/nvm/Context.ip : I
         L2
          RETURN
[2]_asm_procedurefindpartner_ask_4 "ask turtles let count link-neighbors [ if partner = nobody [ ifelse nc > total [ set partner self ] [ set total total - nc ] ] ]" AgentSet => void
      _turtles "turtles" => AgentSet
          // parameter final  context
          // parameter final  context
          // parameter final  agents
         L0
          ALOAD 0
          GETFIELD org/nlogo/prim/_asm_procedurefindpartner_ask_4.world : Lorg/nlogo/agent/World;
          INVOKEVIRTUAL org/nlogo/agent/World.turtles ()Lorg/nlogo/agent/TreeAgentSet;
         L1
          ASTORE 2
          ALOAD 1
          GETFIELD org/nlogo/nvm/Context.agent : Lorg/nlogo/agent/Agent;
          INSTANCEOF org/nlogo/agent/Observer
          IFNE L2
          ALOAD 2
          ALOAD 0
          GETFIELD org/nlogo/prim/_asm_procedurefindpartner_ask_4.world : Lorg/nlogo/agent/World;
          INVOKEVIRTUAL org/nlogo/agent/World.turtles ()Lorg/nlogo/agent/TreeAgentSet;
          IF_ACMPNE L3
          NEW org/nlogo/nvm/RuntimePrimitiveException
          DUP
          ALOAD 1
          ALOAD 0
          GETSTATIC org/nlogo/core/I18N$.MODULE$ : Lorg/nlogo/core/I18N$;
          INVOKEVIRTUAL org/nlogo/core/I18N$.errors ()Lorg/nlogo/core/I18N$BundleKind;
          LDC "org.nlogo.prim.$common.onlyObserverCanAskAllTurtles"
          INVOKEVIRTUAL org/nlogo/core/I18N$BundleKind.get (Ljava/lang/String;)Ljava/lang/String;
          INVOKESPECIAL org/nlogo/nvm/RuntimePrimitiveException.<init> (Lorg/nlogo/api/Context;Lorg/nlogo/nvm/Instruction;Ljava/lang/String;)V
          ATHROW
         L3
         FRAME APPEND [org/nlogo/agent/TreeAgentSet]
          ALOAD 2
          ALOAD 0
          GETFIELD org/nlogo/prim/_asm_procedurefindpartner_ask_4.world : Lorg/nlogo/agent/World;
          INVOKEVIRTUAL org/nlogo/agent/World.patches ()Lorg/nlogo/agent/IndexedAgentSet;
          IF_ACMPNE L2
          NEW org/nlogo/nvm/RuntimePrimitiveException
          DUP
          ALOAD 1
          ALOAD 0
          GETSTATIC org/nlogo/core/I18N$.MODULE$ : Lorg/nlogo/core/I18N$;
          INVOKEVIRTUAL org/nlogo/core/I18N$.errors ()Lorg/nlogo/core/I18N$BundleKind;
          LDC "org.nlogo.prim.$common.onlyObserverCanAskAllPatches"
          INVOKEVIRTUAL org/nlogo/core/I18N$BundleKind.get (Ljava/lang/String;)Ljava/lang/String;
          INVOKESPECIAL org/nlogo/nvm/RuntimePrimitiveException.<init> (Lorg/nlogo/api/Context;Lorg/nlogo/nvm/Instruction;Ljava/lang/String;)V
          ATHROW
         L2
         FRAME SAME
          ALOAD 1
          ALOAD 2
          ICONST_3
          INVOKEVIRTUAL org/nlogo/nvm/Context.runExclusiveJob (Lorg/nlogo/agent/AgentSet;I)V
          ALOAD 1
          BIPUSH 10
          PUTFIELD org/nlogo/nvm/Context.ip : I
         L4
          RETURN
[3]_asm_procedurefindpartner_let_5 "let count link-neighbors" Object => void
      _count "count link-neighbors" AgentSet => double
        _linkneighbors:null "link-neighbors" => AgentSet
          // parameter final  context
          // parameter final  context
          // parameter final  arg0
          // parameter final  context
          // parameter final  arg0
         L0
          ALOAD 0
          GETFIELD org/nlogo/prim/_asm_procedurefindpartner_let_5.kept3_breedName : Ljava/lang/String;
          IFNONNULL L1
          ALOAD 0
          GETFIELD org/nlogo/prim/_asm_procedurefindpartner_let_5.world : Lorg/nlogo/agent/World;
          INVOKEVIRTUAL org/nlogo/agent/World.links ()Lorg/nlogo/agent/TreeAgentSet;
          GOTO L2
         L1
         FRAME SAME
          ALOAD 0
          GETFIELD org/nlogo/prim/_asm_procedurefindpartner_let_5.world : Lorg/nlogo/agent/World;
          ALOAD 0
          GETFIELD org/nlogo/prim/_asm_procedurefindpartner_let_5.kept3_breedName : Ljava/lang/String;
          INVOKEVIRTUAL org/nlogo/agent/World.getLinkBreed (Ljava/lang/String;)Lorg/nlogo/agent/AgentSet;
         L2
         FRAME SAME1 org/nlogo/agent/AgentSet
          ASTORE 2
          GETSTATIC org/nlogo/agent/AgentSet$.MODULE$ : Lorg/nlogo/agent/AgentSet$;
          GETSTATIC org/nlogo/core/AgentKind$Turtle$.MODULE$ : Lorg/nlogo/core/AgentKind$Turtle$;
          ALOAD 0
          GETFIELD org/nlogo/prim/_asm_procedurefindpartner_let_5.world : Lorg/nlogo/agent/World;
          INVOKEVIRTUAL org/nlogo/agent/World.linkManager ()Lorg/nlogo/agent/LinkManager;
          ALOAD 1
          GETFIELD org/nlogo/nvm/Context.agent : Lorg/nlogo/agent/Agent;
          CHECKCAST org/nlogo/agent/Turtle
          ALOAD 2
          INVOKEINTERFACE org/nlogo/agent/LinkManager.neighbors (Lorg/nlogo/agent/Turtle;Lorg/nlogo/agent/AgentSet;)[Lorg/nlogo/agent/Turtle; (itf)
          INVOKEVIRTUAL org/nlogo/agent/AgentSet$.fromArray (Lorg/nlogo/core/AgentKind;[Lorg/nlogo/agent/Agent;)Lorg/nlogo/agent/IndexedAgentSet;
         L3
          ASTORE 2
          GETSTATIC scala/Int$.MODULE$ : Lscala/Int$;
          ALOAD 2
          INVOKEVIRTUAL org/nlogo/agent/AgentSet.count ()I
          INVOKEVIRTUAL scala/Int$.int2double (I)D
         L4
          DSTORE 2
          NEW java/lang/Double
          DUP
          DLOAD 2
          INVOKESPECIAL java/lang/Double.<init> (D)V
          ASTORE 2
          ALOAD 1
          GETFIELD org/nlogo/nvm/Context.activation : Lorg/nlogo/nvm/Activation;
          GETFIELD org/nlogo/nvm/Activation.binding : Lorg/nlogo/nvm/Binding;
          ALOAD 0
          GETFIELD org/nlogo/prim/_asm_procedurefindpartner_let_5.kept1__let : Lorg/nlogo/core/Let;
          ALOAD 2
          INVOKEVIRTUAL org/nlogo/nvm/Binding.let (Lorg/nlogo/core/Let;Ljava/lang/Object;)V
          ALOAD 1
          ICONST_4
          PUTFIELD org/nlogo/nvm/Context.ip : I
         L5
          RETURN
[4]_asm_procedurefindpartner_if_6 "if partner = nobody [ ifelse nc > total [ set partner self ] [ set total total - nc ] ]" boolean => void
      _equal "partner = nobody" Object,Object => boolean
        _procedurevariable:PARTNER "partner" => Object
        _nobody "nobody" => Nobody$
          // parameter final  context
          // parameter final  context
          // parameter final  context
          // parameter final  arg0
          // parameter final  arg1
          // parameter final  context
          // parameter final  arg0
         L0
          ALOAD 1
          GETFIELD org/nlogo/nvm/Context.activation : Lorg/nlogo/nvm/Activation;
          GETFIELD org/nlogo/nvm/Activation.args : [Ljava/lang/Object;
          ICONST_1
          AALOAD
         L1
          GETSTATIC org/nlogo/core/Nobody$.MODULE$ : Lorg/nlogo/core/Nobody$;
         L2
          ASTORE 3
          ASTORE 2
          GETSTATIC org/nlogo/api/Equality$.MODULE$ : Lorg/nlogo/api/Equality$;
          ALOAD 2
          ALOAD 3
          INVOKEVIRTUAL org/nlogo/api/Equality$.equals (Ljava/lang/Object;Ljava/lang/Object;)Z
         L3
          ISTORE 2
          ALOAD 1
          ILOAD 2
          IFEQ L4
          ICONST_5
          GOTO L5
         L4
         FRAME FULL [org/nlogo/prim/_asm_procedurefindpartner_if_6 org/nlogo/nvm/Context I org/nlogo/core/Nobody$] [org/nlogo/nvm/Context]
          BIPUSH 9
         L5
         FRAME FULL [org/nlogo/prim/_asm_procedurefindpartner_if_6 org/nlogo/nvm/Context I org/nlogo/core/Nobody$] [org/nlogo/nvm/Context I]
          PUTFIELD org/nlogo/nvm/Context.ip : I
         L6
          RETURN
[5]_asm_procedurefindpartner_ifelse_7 "ifelse nc > total [ set partner self ] [ set total total - nc ]" boolean => void
      _greaterthan "nc > total" Object,Object => boolean
        _letvariable(Let(NC)) "nc" => Object
        _procedurevariable:TOTAL "total" => Object
          // parameter final  context
          // parameter final  context
          // parameter final  context
          // parameter final  o1
          // parameter final  o2
          // parameter final  context
          // parameter final  cond
         L0
          ALOAD 1
          GETFIELD org/nlogo/nvm/Context.activation : Lorg/nlogo/nvm/Activation;
          GETFIELD org/nlogo/nvm/Activation.binding : Lorg/nlogo/nvm/Binding;
          ALOAD 0
          GETFIELD org/nlogo/prim/_asm_procedurefindpartner_ifelse_7.kept3__let : Lorg/nlogo/core/Let;
          INVOKEVIRTUAL org/nlogo/nvm/Binding.getLet (Lorg/nlogo/core/Let;)Ljava/lang/Object;
         L1
          ALOAD 1
          GETFIELD org/nlogo/nvm/Context.activation : Lorg/nlogo/nvm/Activation;
          GETFIELD org/nlogo/nvm/Activation.args : [Ljava/lang/Object;
          ICONST_0
          AALOAD
         L2
          ASTORE 3
          ASTORE 2
          ALOAD 2
          INSTANCEOF java/lang/Double
          IFEQ L3
          ALOAD 3
          INSTANCEOF java/lang/Double
          IFEQ L3
          ALOAD 2
          CHECKCAST java/lang/Double
          INVOKEVIRTUAL java/lang/Double.doubleValue ()D
          ALOAD 3
          CHECKCAST java/lang/Double
          INVOKEVIRTUAL java/lang/Double.doubleValue ()D
          DCMPL
          IFLE L4
          ICONST_1
          GOTO L5
         L4
         FRAME APPEND [java/lang/Object java/lang/Object]
          ICONST_0
         L5
         FRAME SAME1 I
          GOTO L6
         L3
         FRAME SAME
          ALOAD 2
          INSTANCEOF java/lang/String
          IFEQ L7
          ALOAD 3
          INSTANCEOF java/lang/String
          IFEQ L7
          ALOAD 2
          CHECKCAST java/lang/String
          ALOAD 3
          CHECKCAST java/lang/String
          INVOKEVIRTUAL java/lang/String.compareTo (Ljava/lang/String;)I
          ICONST_0
          IF_ICMPLE L8
          ICONST_1
          GOTO L9
         L8
         FRAME SAME
          ICONST_0
         L9
         FRAME SAME1 I
          GOTO L6
         L7
         FRAME SAME
          ALOAD 2
          INSTANCEOF org/nlogo/agent/Agent
          IFEQ L10
          ALOAD 3
          INSTANCEOF org/nlogo/agent/Agent
          IFEQ L10
          ALOAD 2
          CHECKCAST org/nlogo/agent/Agent
          ASTORE 4
          ALOAD 3
          CHECKCAST org/nlogo/agent/Agent
          ASTORE 5
          ALOAD 4
          INVOKEVIRTUAL org/nlogo/agent/Agent.agentBit ()I
          ALOAD 5
          INVOKEVIRTUAL org/nlogo/agent/Agent.agentBit ()I
          IF_ICMPNE L10
          ALOAD 4
          ALOAD 5
          INVOKEVIRTUAL org/nlogo/agent/Agent.compareTo (Lorg/nlogo/agent/Agent;)I
          ICONST_0
          IF_ICMPLE L11
          ICONST_1
          GOTO L12
         L11
         FRAME APPEND [org/nlogo/agent/Agent org/nlogo/agent/Agent]
          ICONST_0
         L12
         FRAME SAME1 I
          GOTO L6
         L10
         FRAME CHOP 2
          NEW org/nlogo/nvm/RuntimePrimitiveException
          DUP
          ALOAD 1
          ALOAD 0
          GETSTATIC org/nlogo/core/I18N$.MODULE$ : Lorg/nlogo/core/I18N$;
          INVOKEVIRTUAL org/nlogo/core/I18N$.errors ()Lorg/nlogo/core/I18N$BundleKind;
          LDC "org.nlogo.prim._greaterthan.cannotCompareParameters"
          GETSTATIC scala/runtime/ScalaRunTime$.MODULE$ : Lscala/runtime/ScalaRunTime$;
          ICONST_2
          ANEWARRAY java/lang/Object
          DUP
          ICONST_0
          GETSTATIC org/nlogo/api/TypeNames$.MODULE$ : Lorg/nlogo/api/TypeNames$;
          ALOAD 2
          INVOKEVIRTUAL org/nlogo/api/TypeNames$.aName (Ljava/lang/Object;)Ljava/lang/String;
          AASTORE
          DUP
          ICONST_1
          GETSTATIC org/nlogo/api/TypeNames$.MODULE$ : Lorg/nlogo/api/TypeNames$;
          ALOAD 3
          INVOKEVIRTUAL org/nlogo/api/TypeNames$.aName (Ljava/lang/Object;)Ljava/lang/String;
          AASTORE
          INVOKEVIRTUAL scala/runtime/ScalaRunTime$.wrapRefArray ([Ljava/lang/Object;)Lscala/collection/immutable/ArraySeq;
          INVOKEVIRTUAL org/nlogo/core/I18N$BundleKind.getN (Ljava/lang/String;Lscala/collection/immutable/Seq;)Ljava/lang/String;
          INVOKESPECIAL org/nlogo/nvm/RuntimePrimitiveException.<init> (Lorg/nlogo/api/Context;Lorg/nlogo/nvm/Instruction;Ljava/lang/String;)V
          ATHROW
         L6
         FRAME SAME1 I
          ISTORE 2
          ALOAD 1
          ILOAD 2
          IFEQ L13
          BIPUSH 6
          GOTO L14
         L13
         FRAME FULL [org/nlogo/prim/_asm_procedurefindpartner_ifelse_7 org/nlogo/nvm/Context I java/lang/Object] [org/nlogo/nvm/Context]
          BIPUSH 8
         L14
         FRAME FULL [org/nlogo/prim/_asm_procedurefindpartner_ifelse_7 org/nlogo/nvm/Context I java/lang/Object] [org/nlogo/nvm/Context I]
          PUTFIELD org/nlogo/nvm/Context.ip : I
         L15
          RETURN
[6]_asm_procedurefindpartner_setprocedurevariable_8 "set partner self" Object => void
      _self "self" => Agent
          // parameter final  context
          // parameter final  context
          // parameter final  arg0
         L0
          ALOAD 1
          GETFIELD org/nlogo/nvm/Context.agent : Lorg/nlogo/agent/Agent;
         L1
          ASTORE 2
          ALOAD 1
          GETFIELD org/nlogo/nvm/Context.activation : Lorg/nlogo/nvm/Activation;
          GETFIELD org/nlogo/nvm/Activation.args : [Ljava/lang/Object;
          ICONST_1
          ALOAD 2
          AASTORE
          ALOAD 1
          BIPUSH 7
          PUTFIELD org/nlogo/nvm/Context.ip : I
         L2
          RETURN
[7]_asm_procedurefindpartner_goto_9 => void
          // parameter final  context
         L0
          ALOAD 1
          BIPUSH 9
          PUTFIELD org/nlogo/nvm/Context.ip : I
         L1
          RETURN
[8]_asm_procedurefindpartner_setprocedurevariable_10 "set total total - nc" Object => void
      _minus "total - nc" double,double => double
        _procedurevariable:TOTAL "total" => Object
        _letvariable(Let(NC)) "nc" => Object
          // parameter final  context
          // parameter final  context
          // parameter final  context
          // parameter final  d0
          // parameter final  d1
          // parameter final  context
          // parameter final  arg0
          TRYCATCHBLOCK L0 L1 L1 java/lang/ClassCastException
          TRYCATCHBLOCK L2 L3 L3 java/lang/ClassCastException
         L4
          ALOAD 1
          GETFIELD org/nlogo/nvm/Context.activation : Lorg/nlogo/nvm/Activation;
          GETFIELD org/nlogo/nvm/Activation.args : [Ljava/lang/Object;
          ICONST_0
          AALOAD
         L5
          ASTORE 2
         L0
          ALOAD 2
          CHECKCAST java/lang/Double
          INVOKEVIRTUAL java/lang/Double.doubleValue ()D
          GOTO L6
         L1
         FRAME FULL [org/nlogo/prim/_asm_procedurefindpartner_setprocedurevariable_10 org/nlogo/nvm/Context java/lang/Object] [java/lang/ClassCastException]
          POP
          NEW org/nlogo/nvm/ArgumentTypeException
          DUP
          ALOAD 1
          ALOAD 0
          BIPUSH 0
          LDC 1
          ALOAD 2
          INVOKESPECIAL org/nlogo/nvm/ArgumentTypeException.<init> (Lorg/nlogo/nvm/Context;Lorg/nlogo/nvm/Instruction;IILjava/lang/Object;)V
          ATHROW
         L6
         FRAME SAME1 D
          ALOAD 1
          GETFIELD org/nlogo/nvm/Context.activation : Lorg/nlogo/nvm/Activation;
          GETFIELD org/nlogo/nvm/Activation.binding : Lorg/nlogo/nvm/Binding;
          ALOAD 0
          GETFIELD org/nlogo/prim/_asm_procedurefindpartner_setprocedurevariable_10.kept4__let : Lorg/nlogo/core/Let;
          INVOKEVIRTUAL org/nlogo/nvm/Binding.getLet (Lorg/nlogo/core/Let;)Ljava/lang/Object;
         L7
          ASTORE 2
         L2
          ALOAD 2
          CHECKCAST java/lang/Double
          INVOKEVIRTUAL java/lang/Double.doubleValue ()D
          GOTO L8
         L3
         FRAME SAME1 java/lang/ClassCastException
          POP
          NEW org/nlogo/nvm/ArgumentTypeException
          DUP
          ALOAD 1
          ALOAD 0
          BIPUSH 1
          LDC 1
          ALOAD 2
          INVOKESPECIAL org/nlogo/nvm/ArgumentTypeException.<init> (Lorg/nlogo/nvm/Context;Lorg/nlogo/nvm/Instruction;IILjava/lang/Object;)V
          ATHROW
         L8
         FRAME FULL [org/nlogo/prim/_asm_procedurefindpartner_setprocedurevariable_10 org/nlogo/nvm/Context java/lang/Object] [D D]
          DSTORE 4
          DSTORE 2
          DLOAD 2
          DLOAD 4
          DSUB
         L9
          DSTORE 2
          NEW java/lang/Double
          DUP
          DLOAD 2
          INVOKESPECIAL java/lang/Double.<init> (D)V
          ASTORE 2
          ALOAD 1
          GETFIELD org/nlogo/nvm/Context.activation : Lorg/nlogo/nvm/Activation;
          GETFIELD org/nlogo/nvm/Activation.args : [Ljava/lang/Object;
          ICONST_0
          ALOAD 2
          AASTORE
          ALOAD 1
          BIPUSH 9
          PUTFIELD org/nlogo/nvm/Context.ip : I
         L10
          RETURN
[9]_asm_procedurefindpartner_done_11 => void
          // parameter final  context
         L0
          ALOAD 1
          ICONST_1
          PUTFIELD org/nlogo/nvm/Context.finished : Z
         L1
          RETURN
[10]_asm_procedurefindpartner_report_12 "report partner" Object => void
      _procedurevariable:PARTNER "partner" => Object
          // parameter final  context
         L0
          ALOAD 1
          GETFIELD org/nlogo/nvm/Context.activation : Lorg/nlogo/nvm/Activation;
          GETFIELD org/nlogo/nvm/Activation.args : [Ljava/lang/Object;
          ICONST_1
          AALOAD
         L1
          ASTORE 2
          ALOAD 1
          GETFIELD org/nlogo/nvm/Context.job : Lorg/nlogo/nvm/Job;
          ALOAD 2
          PUTFIELD org/nlogo/nvm/Job.result : Ljava/lang/Object;
          ALOAD 1
          ICONST_0
          PUTFIELD org/nlogo/nvm/Context.stopping : Z
          ALOAD 1
          BIPUSH 11
          PUTFIELD org/nlogo/nvm/Context.ip : I
          ALOAD 1
          GETFIELD org/nlogo/nvm/Context.activation : Lorg/nlogo/nvm/Activation;
          INVOKEVIRTUAL org/nlogo/nvm/Activation.nonLambdaActivation ()Lorg/nlogo/nvm/Activation;
          GETFIELD org/nlogo/nvm/Activation.procedure : Lorg/nlogo/nvm/Procedure;
          INVOKEVIRTUAL org/nlogo/nvm/Procedure.isReporter ()Z
          IFNE L2
          NEW org/nlogo/nvm/RuntimePrimitiveException
          DUP
          ALOAD 1
          ALOAD 0
          INVOKESTATIC org/nlogo/core/I18N.errorsJ ()Lorg/nlogo/core/I18NJava;
          LDC "org.nlogo.prim._report.canOnlyUseInToReport"
          ICONST_1
          ANEWARRAY java/lang/Object
          DUP
          ICONST_0
          LDC "REPORT"
          AASTORE
          INVOKEINTERFACE org/nlogo/core/I18NJava.getN (Ljava/lang/String;[Ljava/lang/Object;)Ljava/lang/String; (itf)
          INVOKESPECIAL org/nlogo/nvm/RuntimePrimitiveException.<init> (Lorg/nlogo/api/Context;Lorg/nlogo/nvm/Instruction;Ljava/lang/String;)V
          ATHROW
         L2
         FRAME APPEND [java/lang/Object]
          ALOAD 1
          GETFIELD org/nlogo/nvm/Context.activation : Lorg/nlogo/nvm/Activation;
          GETFIELD org/nlogo/nvm/Activation.procedure : Lorg/nlogo/nvm/Procedure;
          INVOKEVIRTUAL org/nlogo/nvm/Procedure.isLambda ()Z
          IFEQ L3
          NEW org/nlogo/nvm/NonLocalExit
          DUP
          INVOKESPECIAL org/nlogo/nvm/NonLocalExit.<init> ()V
          ATHROW
         L3
         FRAME SAME
          ALOAD 1
          INVOKEVIRTUAL org/nlogo/nvm/Context.atTopActivation ()Z
          IFNE L4
          NEW org/nlogo/nvm/RuntimePrimitiveException
          DUP
          ALOAD 1
          ALOAD 0
          INVOKESTATIC org/nlogo/core/I18N.errorsJ ()Lorg/nlogo/core/I18NJava;
          LDC "org.nlogo.prim._report.mustImmediatelyBeUsedInToReport"
          ICONST_1
          ANEWARRAY java/lang/Object
          DUP
          ICONST_0
          LDC "REPORT"
          AASTORE
          INVOKEINTERFACE org/nlogo/core/I18NJava.getN (Ljava/lang/String;[Ljava/lang/Object;)Ljava/lang/String; (itf)
          INVOKESPECIAL org/nlogo/nvm/RuntimePrimitiveException.<init> (Lorg/nlogo/api/Context;Lorg/nlogo/nvm/Instruction;Ljava/lang/String;)V
          ATHROW
         L4
         FRAME SAME
          RETURN
[11]_asm_procedurefindpartner_returnreport_13 => void
          // parameter final  context
         L0
          NEW org/nlogo/nvm/RuntimePrimitiveException
          DUP
          ALOAD 1
          ALOAD 0
          GETSTATIC org/nlogo/core/I18N$.MODULE$ : Lorg/nlogo/core/I18N$;
          INVOKEVIRTUAL org/nlogo/core/I18N$.errors ()Lorg/nlogo/core/I18N$BundleKind;
          LDC "org.nlogo.prim._returnreport.reportNotCalledInReportProcedure"
          INVOKEVIRTUAL org/nlogo/core/I18N$BundleKind.get (Ljava/lang/String;)Ljava/lang/String;
          INVOKESPECIAL org/nlogo/nvm/RuntimePrimitiveException.<init> (Lorg/nlogo/api/Context;Lorg/nlogo/nvm/Instruction;Ljava/lang/String;)V
          ATHROW
         L1
         FRAME FULL [] [java/lang/Throwable]
          ATHROW

procedure LAYOUT:[_repeatlocal:0]{OTPL}:
[0]_asm_procedurelayout_repeatlocal_0 "repeat 3 layout-spring turtles links 0.5 1.0 0.4 [ display ]" double => void
      _constdouble:3.0 "3" => double
          // parameter final  context
          // parameter final  context
          // parameter final  arg0
         L0
          LDC 3.0D
         L1
          DSTORE 2
          ALOAD 1
          GETFIELD org/nlogo/nvm/Context.activation : Lorg/nlogo/nvm/Activation;
          GETFIELD org/nlogo/nvm/Activation.args : [Ljava/lang/Object;
          ICONST_0
          NEW org/nlogo/nvm/MutableLong
          DUP
          ALOAD 0
          DLOAD 2
          ALOAD 1
          INVOKEVIRTUAL org/nlogo/prim/_asm_procedurelayout_repeatlocal_0.validLong (DLorg/nlogo/nvm/Context;)J
          INVOKESPECIAL org/nlogo/nvm/MutableLong.<init> (J)V
          AASTORE
          ALOAD 1
          ICONST_3
          PUTFIELD org/nlogo/nvm/Context.ip : I
         L2
          RETURN
[1]_layoutspring "layout-spring turtles links 0.5 1.0 0.4"
      _asm_procedurelayout_turtles_1 "turtles" => AgentSet
            // parameter final  context
           L0
            ALOAD 0
            GETFIELD org/nlogo/prim/_asm_procedurelayout_turtles_1.world : Lorg/nlogo/agent/World;
            INVOKEVIRTUAL org/nlogo/agent/World.turtles ()Lorg/nlogo/agent/TreeAgentSet;
           L1
            ARETURN
      _asm_procedurelayout_links_2 "links" => AgentSet
            // parameter final  context
           L0
            ALOAD 0
            GETFIELD org/nlogo/prim/_asm_procedurelayout_links_2.world : Lorg/nlogo/agent/World;
            INVOKEVIRTUAL org/nlogo/agent/World.links ()Lorg/nlogo/agent/TreeAgentSet;
           L1
            ARETURN
      _asm_procedurelayout_constdouble_3 "0.5" => Double
            // parameter final  context
           L0
            ALOAD 0
            GETFIELD org/nlogo/prim/_asm_procedurelayout_constdouble_3.kept1_value : Ljava/lang/Double;
           L1
            ARETURN
      _asm_procedurelayout_constdouble_4 "1.0" => Double
            // parameter final  context
           L0
            ALOAD 0
            GETFIELD org/nlogo/prim/_asm_procedurelayout_constdouble_4.kept1_value : Ljava/lang/Double;
           L1
            ARETURN
      _asm_procedurelayout_constdouble_5 "0.4" => Double
            // parameter final  context
           L0
            ALOAD 0
            GETFIELD org/nlogo/prim/_asm_procedurelayout_constdouble_5.kept1_value : Ljava/lang/Double;
           L1
            ARETURN
[2]_display "display"
[3]_asm_procedurelayout_repeatlocalinternal_6 => void
          // parameter final  context
         L0
          ALOAD 1
          GETFIELD org/nlogo/nvm/Context.activation : Lorg/nlogo/nvm/Activation;
          GETFIELD org/nlogo/nvm/Activation.args : [Ljava/lang/Object;
          ICONST_0
          AALOAD
          CHECKCAST org/nlogo/nvm/MutableLong
          ASTORE 2
          ALOAD 2
          INVOKEVIRTUAL org/nlogo/nvm/MutableLong.value ()J
          LCONST_0
          LCMP
          IFGT L1
          ALOAD 1
          ICONST_4
          PUTFIELD org/nlogo/nvm/Context.ip : I
          GOTO L2
         L1
         FRAME APPEND [org/nlogo/nvm/MutableLong]
          ALOAD 2
          ALOAD 2
          INVOKEVIRTUAL org/nlogo/nvm/MutableLong.value ()J
          LCONST_1
          LSUB
          INVOKEVIRTUAL org/nlogo/nvm/MutableLong.value_$eq (J)V
          ALOAD 1
          ICONST_1
          PUTFIELD org/nlogo/nvm/Context.ip : I
         L2
         FRAME SAME
          RETURN
[4]_asm_procedurelayout_return_7 => void
          // parameter final  context
         L0
          ALOAD 1
          INVOKEVIRTUAL org/nlogo/nvm/Context.returnFromProcedure ()V
          ALOAD 1
          ICONST_0
          PUTFIELD org/nlogo/nvm/Context.stopping : Z
         L1
          RETURN

