globals [DIFFUSION-RATE EVAPORATION-RATE PLOT? ANTS RESULT]
interfaceGlobals [diffusion-rate evaporation-rate plot? ants]
turtles-own [WHO COLOR HEADING XCOR YCOR SHAPE LABEL LABEL-COLOR BREED HIDDEN? SIZE PEN-SIZE PEN-MODE CARRYING-FOOD? DROP-SIZE]
patches-own [PXCOR PYCOR PCOLOR PLABEL PLABEL-COLOR CHEMICAL FOOD NEST? NEST-SCENT FOOD-SOURCE-NUMBER]
links-own [END1 END2 COLOR LABEL LABEL-COLOR HIDDEN? BREED THICKNESS SHAPE TIE-MODE]
breeds 
link-breeds 

procedure GO:[]{O---}:
[0]_asm_procedurego_ask_0 "ask turtles [ go-turtles ]" AgentSet => void
      _turtles "turtles" => AgentSet
         L0
          ALOAD 0
          GETFIELD org/nlogo/prim/_asm_procedurego_ask_0.world : Lorg/nlogo/agent/World;
          INVOKEVIRTUAL org/nlogo/agent/World.turtles ()Lorg/nlogo/agent/AgentSet;
         L1
          ASTORE 2
          ALOAD 1
          GETFIELD org/nlogo/nvm/Context.agent : Lorg/nlogo/agent/Agent;
          INSTANCEOF org/nlogo/agent/Observer
          IFNE L2
          ALOAD 2
          ALOAD 0
          GETFIELD org/nlogo/prim/_asm_procedurego_ask_0.world : Lorg/nlogo/agent/World;
          INVOKEVIRTUAL org/nlogo/agent/World.turtles ()Lorg/nlogo/agent/AgentSet;
          IF_ACMPNE L3
          NEW org/nlogo/nvm/EngineException
          DUP
          ALOAD 1
          ALOAD 0
          INVOKESTATIC org/nlogo/core/I18N.errorsJ ()Lorg/nlogo/core/I18NJava;
          LDC "org.nlogo.prim.$common.onlyObserverCanAskAllTurtles"
          INVOKEINTERFACE org/nlogo/core/I18NJava.get (Ljava/lang/String;)Ljava/lang/String;
          INVOKESPECIAL org/nlogo/nvm/EngineException.<init> (Lorg/nlogo/nvm/Context;Lorg/nlogo/nvm/Instruction;Ljava/lang/String;)V
          ATHROW
         L3
         FRAME APPEND [org/nlogo/agent/AgentSet]
          ALOAD 2
          ALOAD 0
          GETFIELD org/nlogo/prim/_asm_procedurego_ask_0.world : Lorg/nlogo/agent/World;
          INVOKEVIRTUAL org/nlogo/agent/World.patches ()Lorg/nlogo/agent/AgentSet;
          IF_ACMPNE L2
          NEW org/nlogo/nvm/EngineException
          DUP
          ALOAD 1
          ALOAD 0
          INVOKESTATIC org/nlogo/core/I18N.errorsJ ()Lorg/nlogo/core/I18NJava;
          LDC "org.nlogo.prim.$common.onlyObserverCanAskAllPatches"
          INVOKEINTERFACE org/nlogo/core/I18NJava.get (Ljava/lang/String;)Ljava/lang/String;
          INVOKESPECIAL org/nlogo/nvm/EngineException.<init> (Lorg/nlogo/nvm/Context;Lorg/nlogo/nvm/Instruction;Ljava/lang/String;)V
          ATHROW
         L2
         FRAME SAME
          ALOAD 1
          ALOAD 2
          ICONST_1
          INVOKEVIRTUAL org/nlogo/nvm/Context.runExclusiveJob (Lorg/nlogo/agent/AgentSet;I)V
          ALOAD 1
          ICONST_3
          PUTFIELD org/nlogo/nvm/Context.ip : I
         L4
          RETURN
[1]_asm_procedurego_call_1 "go-turtles"
         L0
          NEW org/nlogo/nvm/Activation
          DUP
          ALOAD 0
          GETFIELD org/nlogo/prim/_asm_procedurego_call_1.kept1_procedure : Lorg/nlogo/nvm/Procedure;
          ALOAD 1
          GETFIELD org/nlogo/nvm/Context.activation : Lorg/nlogo/nvm/Activation;
          ICONST_2
          INVOKESPECIAL org/nlogo/nvm/Activation.<init> (Lorg/nlogo/nvm/Procedure;Lorg/nlogo/nvm/Activation;I)V
          ALOAD 1
          SWAP
          PUTFIELD org/nlogo/nvm/Context.activation : Lorg/nlogo/nvm/Activation;
          ALOAD 1
          ICONST_0
          PUTFIELD org/nlogo/nvm/Context.ip : I
         L1
          RETURN
[2]_asm_procedurego_done_2 => void
         L0
          ALOAD 1
          ICONST_1
          PUTFIELD org/nlogo/nvm/Context.finished : Z
         L1
          RETURN
[3]_diffuse:CHEMICAL "diffuse diffusion-rate / 100"
      _asm_procedurego_div_3 "diffusion-rate / 100" double,double => double
        _observervariable:DIFFUSION-RATE "diffusion-rate" => Object
        _constdouble:100.0 "100" => double
            TRYCATCHBLOCK L0 L1 L1 java/lang/ClassCastException
           L2
            ALOAD 1
            GETFIELD org/nlogo/nvm/Context.agent : Lorg/nlogo/agent/Agent;
            ICONST_0
            INVOKEVIRTUAL org/nlogo/agent/Agent.getObserverVariable (I)Ljava/lang/Object;
           L3
            ASTORE 2
           L0
            ALOAD 2
            CHECKCAST java/lang/Double
            INVOKEVIRTUAL java/lang/Double.doubleValue ()D
            GOTO L4
           L1
           FRAME FULL [org/nlogo/prim/_asm_procedurego_div_3 org/nlogo/nvm/Context java/lang/Object] [java/lang/ClassCastException]
            POP
            NEW org/nlogo/nvm/ArgumentTypeException
            DUP
            ALOAD 1
            ALOAD 0
            BIPUSH 0
            LDC 1
            ALOAD 2
            INVOKESPECIAL org/nlogo/nvm/ArgumentTypeException.<init> (Lorg/nlogo/nvm/Context;Lorg/nlogo/nvm/Instruction;IILjava/lang/Object;)V
            ATHROW
           L4
           FRAME SAME1 D
            LDC 100.0
           L5
            DSTORE 4
            DSTORE 2
            DLOAD 4
            DCONST_0
            DCMPL
            IFNE L6
            NEW org/nlogo/nvm/EngineException
            DUP
            ALOAD 1
            ALOAD 0
            INVOKESTATIC org/nlogo/core/I18N.errorsJ ()Lorg/nlogo/core/I18NJava;
            LDC "org.nlogo.prim.etc.$common.divByZero"
            INVOKEINTERFACE org/nlogo/core/I18NJava.get (Ljava/lang/String;)Ljava/lang/String;
            INVOKESPECIAL org/nlogo/nvm/EngineException.<init> (Lorg/nlogo/nvm/Context;Lorg/nlogo/nvm/Instruction;Ljava/lang/String;)V
            ATHROW
           L6
           FRAME FULL [org/nlogo/prim/_asm_procedurego_div_3 org/nlogo/nvm/Context D D] []
            ALOAD 0
            DLOAD 2
            DLOAD 4
            DDIV
            INVOKEVIRTUAL org/nlogo/prim/_asm_procedurego_div_3.validDouble (D)D
           L7
            DSTORE 2
            NEW java/lang/Double
            DUP
            DLOAD 2
            INVOKESPECIAL java/lang/Double.<init> (D)V
            ARETURN
[4]_asm_procedurego_ask_4 "ask patches [ go-patches ]" AgentSet => void
      _patches "patches" => AgentSet
         L0
          ALOAD 0
          GETFIELD org/nlogo/prim/_asm_procedurego_ask_4.world : Lorg/nlogo/agent/World;
          INVOKEVIRTUAL org/nlogo/agent/World.patches ()Lorg/nlogo/agent/AgentSet;
         L1
          ASTORE 2
          ALOAD 1
          GETFIELD org/nlogo/nvm/Context.agent : Lorg/nlogo/agent/Agent;
          INSTANCEOF org/nlogo/agent/Observer
          IFNE L2
          ALOAD 2
          ALOAD 0
          GETFIELD org/nlogo/prim/_asm_procedurego_ask_4.world : Lorg/nlogo/agent/World;
          INVOKEVIRTUAL org/nlogo/agent/World.turtles ()Lorg/nlogo/agent/AgentSet;
          IF_ACMPNE L3
          NEW org/nlogo/nvm/EngineException
          DUP
          ALOAD 1
          ALOAD 0
          INVOKESTATIC org/nlogo/core/I18N.errorsJ ()Lorg/nlogo/core/I18NJava;
          LDC "org.nlogo.prim.$common.onlyObserverCanAskAllTurtles"
          INVOKEINTERFACE org/nlogo/core/I18NJava.get (Ljava/lang/String;)Ljava/lang/String;
          INVOKESPECIAL org/nlogo/nvm/EngineException.<init> (Lorg/nlogo/nvm/Context;Lorg/nlogo/nvm/Instruction;Ljava/lang/String;)V
          ATHROW
         L3
         FRAME APPEND [org/nlogo/agent/AgentSet]
          ALOAD 2
          ALOAD 0
          GETFIELD org/nlogo/prim/_asm_procedurego_ask_4.world : Lorg/nlogo/agent/World;
          INVOKEVIRTUAL org/nlogo/agent/World.patches ()Lorg/nlogo/agent/AgentSet;
          IF_ACMPNE L2
          NEW org/nlogo/nvm/EngineException
          DUP
          ALOAD 1
          ALOAD 0
          INVOKESTATIC org/nlogo/core/I18N.errorsJ ()Lorg/nlogo/core/I18NJava;
          LDC "org.nlogo.prim.$common.onlyObserverCanAskAllPatches"
          INVOKEINTERFACE org/nlogo/core/I18NJava.get (Ljava/lang/String;)Ljava/lang/String;
          INVOKESPECIAL org/nlogo/nvm/EngineException.<init> (Lorg/nlogo/nvm/Context;Lorg/nlogo/nvm/Instruction;Ljava/lang/String;)V
          ATHROW
         L2
         FRAME SAME
          ALOAD 1
          ALOAD 2
          ICONST_5
          INVOKEVIRTUAL org/nlogo/nvm/Context.runExclusiveJob (Lorg/nlogo/agent/AgentSet;I)V
          ALOAD 1
          BIPUSH 7
          PUTFIELD org/nlogo/nvm/Context.ip : I
         L4
          RETURN
[5]_asm_procedurego_call_5 "go-patches"
         L0
          NEW org/nlogo/nvm/Activation
          DUP
          ALOAD 0
          GETFIELD org/nlogo/prim/_asm_procedurego_call_5.kept1_procedure : Lorg/nlogo/nvm/Procedure;
          ALOAD 1
          GETFIELD org/nlogo/nvm/Context.activation : Lorg/nlogo/nvm/Activation;
          BIPUSH 6
          INVOKESPECIAL org/nlogo/nvm/Activation.<init> (Lorg/nlogo/nvm/Procedure;Lorg/nlogo/nvm/Activation;I)V
          ALOAD 1
          SWAP
          PUTFIELD org/nlogo/nvm/Context.activation : Lorg/nlogo/nvm/Activation;
          ALOAD 1
          ICONST_0
          PUTFIELD org/nlogo/nvm/Context.ip : I
         L1
          RETURN
[6]_asm_procedurego_done_6 => void
         L0
          ALOAD 1
          ICONST_1
          PUTFIELD org/nlogo/nvm/Context.finished : Z
         L1
          RETURN
[7]_tick "tick"
[8]_asm_procedurego_call_7 "do-plotting"
         L0
          NEW org/nlogo/nvm/Activation
          DUP
          ALOAD 0
          GETFIELD org/nlogo/prim/_asm_procedurego_call_7.kept1_procedure : Lorg/nlogo/nvm/Procedure;
          ALOAD 1
          GETFIELD org/nlogo/nvm/Context.activation : Lorg/nlogo/nvm/Activation;
          BIPUSH 9
          INVOKESPECIAL org/nlogo/nvm/Activation.<init> (Lorg/nlogo/nvm/Procedure;Lorg/nlogo/nvm/Activation;I)V
          ALOAD 1
          SWAP
          PUTFIELD org/nlogo/nvm/Context.activation : Lorg/nlogo/nvm/Activation;
          ALOAD 1
          ICONST_0
          PUTFIELD org/nlogo/nvm/Context.ip : I
         L1
          RETURN
[9]_asm_procedurego_return_8 => void
         L0
          ALOAD 1
          INVOKEVIRTUAL org/nlogo/nvm/Context.returnFromProcedure ()V
          ALOAD 1
          ICONST_0
          PUTFIELD org/nlogo/nvm/Context.stopping : Z
         L1
          RETURN

procedure DO-PLOTTING:[]{OTPL}:
[0]_asm_proceduredoplotting_if_0 "if not plot? [ stop ]" boolean => void
      _not "not plot?" boolean => boolean
        _observervariable:PLOT? "plot?" => Object
          TRYCATCHBLOCK L0 L1 L1 java/lang/ClassCastException
         L2
          ALOAD 1
          GETFIELD org/nlogo/nvm/Context.agent : Lorg/nlogo/agent/Agent;
          ICONST_2
          INVOKEVIRTUAL org/nlogo/agent/Agent.getObserverVariable (I)Ljava/lang/Object;
         L3
          ASTORE 2
         L0
          ALOAD 2
          CHECKCAST java/lang/Boolean
          INVOKEVIRTUAL java/lang/Boolean.booleanValue ()Z
          GOTO L4
         L1
         FRAME FULL [org/nlogo/prim/_asm_proceduredoplotting_if_0 org/nlogo/nvm/Context java/lang/Object] [java/lang/ClassCastException]
          POP
          NEW org/nlogo/nvm/ArgumentTypeException
          DUP
          ALOAD 1
          ALOAD 0
          BIPUSH 0
          LDC 2
          ALOAD 2
          INVOKESPECIAL org/nlogo/nvm/ArgumentTypeException.<init> (Lorg/nlogo/nvm/Context;Lorg/nlogo/nvm/Instruction;IILjava/lang/Object;)V
          ATHROW
         L4
         FRAME SAME1 I
          ISTORE 2
          ILOAD 2
          IFNE L5
          ICONST_1
          GOTO L6
         L5
         FRAME FULL [org/nlogo/prim/_asm_proceduredoplotting_if_0 org/nlogo/nvm/Context I] []
          ICONST_0
         L6
         FRAME SAME1 I
          ISTORE 2
          ALOAD 1
          ILOAD 2
          IFEQ L7
          ICONST_1
          GOTO L8
         L7
         FRAME SAME1 org/nlogo/nvm/Context
          ICONST_2
         L8
         FRAME FULL [org/nlogo/prim/_asm_proceduredoplotting_if_0 org/nlogo/nvm/Context I] [org/nlogo/nvm/Context I]
          PUTFIELD org/nlogo/nvm/Context.ip : I
         L9
          RETURN
[1]_asm_proceduredoplotting_stop_1 "stop" => void
         L0
          ALOAD 1
          INVOKEVIRTUAL org/nlogo/nvm/Context.atTopActivation ()Z
          IFNE L1
          ALOAD 1
          ICONST_1
          PUTFIELD org/nlogo/nvm/Context.finished : Z
          GOTO L2
         L1
         FRAME SAME
          ALOAD 1
          GETFIELD org/nlogo/nvm/Context.activation : Lorg/nlogo/nvm/Activation;
          GETFIELD org/nlogo/nvm/Activation.procedure : Lorg/nlogo/nvm/Procedure;
          INVOKEVIRTUAL org/nlogo/nvm/Procedure.isReporter ()Z
          IFNE L3
          ALOAD 1
          GETFIELD org/nlogo/nvm/Context.activation : Lorg/nlogo/nvm/Activation;
          GETFIELD org/nlogo/nvm/Activation.procedure : Lorg/nlogo/nvm/Procedure;
          INVOKEVIRTUAL org/nlogo/nvm/Procedure.isTask ()Z
          IFEQ L4
          ALOAD 1
          GETFIELD org/nlogo/nvm/Context.activation : Lorg/nlogo/nvm/Activation;
          GETFIELD org/nlogo/nvm/Activation.procedure : Lorg/nlogo/nvm/Procedure;
          INVOKEVIRTUAL org/nlogo/nvm/Procedure.parent ()Lorg/nlogo/nvm/Procedure;
          INVOKEVIRTUAL org/nlogo/nvm/Procedure.isReporter ()Z
          IFEQ L4
         L3
         FRAME SAME
          NEW org/nlogo/nvm/EngineException
          DUP
          ALOAD 1
          ALOAD 0
          INVOKESTATIC org/nlogo/core/I18N.errorsJ ()Lorg/nlogo/core/I18NJava;
          LDC "org.nlogo.prim.etc._stop.notAllowedInsideToReport"
          ICONST_1
          ANEWARRAY java/lang/Object
          DUP
          ICONST_0
          LDC "STOP"
          AASTORE
          INVOKEINTERFACE org/nlogo/core/I18NJava.getN (Ljava/lang/String;[Ljava/lang/Object;)Ljava/lang/String;
          INVOKESPECIAL org/nlogo/nvm/EngineException.<init> (Lorg/nlogo/nvm/Context;Lorg/nlogo/nvm/Instruction;Ljava/lang/String;)V
          ATHROW
         L4
         FRAME SAME
          ALOAD 1
          INVOKEVIRTUAL org/nlogo/nvm/Context.stop ()V
         L2
         FRAME SAME
          RETURN
[2]_setcurrentplot "set-current-plot "Food in each pile""
      _asm_proceduredoplotting_conststring_2 ""Food in each pile"" => String
           L0
            LDC "Food in each pile"
           L1
            ARETURN
[3]_setcurrentplotpen "set-current-plot-pen "food-in-pile1""
      _asm_proceduredoplotting_conststring_3 ""food-in-pile1"" => String
           L0
            LDC "food-in-pile1"
           L1
            ARETURN
[4]_plot "plot count patches with [ pcolor = cyan ]"
      _asm_proceduredoplotting_countwith_4 "count patches with [ pcolor = cyan ]" AgentSet,Reporter => double
        _patches "patches" => AgentSet
        _asm_proceduredoplotting_equal_5 "pcolor = cyan" Object,double => boolean
          _patchvariable:PCOLOR "pcolor" => Object
          _constdouble:85.0 "cyan" => double
              TRYCATCHBLOCK L0 L1 L2 org/nlogo/api/AgentException
             L0
              ALOAD 1
              GETFIELD org/nlogo/nvm/Context.agent : Lorg/nlogo/agent/Agent;
              ICONST_2
              INVOKEVIRTUAL org/nlogo/agent/Agent.getPatchVariable (I)Ljava/lang/Object;
             L1
              GOTO L3
             L2
             FRAME SAME1 org/nlogo/api/AgentException
              ASTORE 2
              NEW org/nlogo/nvm/EngineException
              DUP
              ALOAD 1
              ALOAD 0
              ALOAD 2
              INVOKEVIRTUAL org/nlogo/api/AgentException.getMessage ()Ljava/lang/String;
              INVOKESPECIAL org/nlogo/nvm/EngineException.<init> (Lorg/nlogo/nvm/Context;Lorg/nlogo/nvm/Instruction;Ljava/lang/String;)V
              ATHROW
             L3
             FRAME SAME1 java/lang/Object
              LDC 85.0
             L4
              DSTORE 3
              ASTORE 2
              ALOAD 2
              INSTANCEOF java/lang/Double
              IFEQ L5
              DLOAD 3
              ALOAD 2
              CHECKCAST java/lang/Double
              INVOKEVIRTUAL java/lang/Double.doubleValue ()D
              DCMPL
              IFNE L5
              ICONST_1
              GOTO L6
             L5
             FRAME APPEND [java/lang/Object D]
              ICONST_0
             L6
             FRAME SAME1 I
              IFEQ L7
              GETSTATIC java/lang/Boolean.TRUE : Ljava/lang/Boolean;
              GOTO L8
             L7
             FRAME SAME
              GETSTATIC java/lang/Boolean.FALSE : Ljava/lang/Boolean;
             L8
             FRAME SAME1 java/lang/Boolean
              ARETURN
           L0
            ALOAD 0
            GETFIELD org/nlogo/prim/_asm_proceduredoplotting_countwith_4.world : Lorg/nlogo/agent/World;
            INVOKEVIRTUAL org/nlogo/agent/World.patches ()Lorg/nlogo/agent/AgentSet;
           L1
            ALOAD 0
            GETFIELD org/nlogo/prim/_asm_proceduredoplotting_countwith_4.keptinstr3 : Lorg/nlogo/nvm/Reporter;
            ASTORE 3
            ASTORE 2
            ALOAD 3
            ALOAD 2
            ALOAD 1
            INVOKEVIRTUAL org/nlogo/nvm/Reporter.checkAgentSetClass (Lorg/nlogo/agent/AgentSet;Lorg/nlogo/nvm/Context;)V
            NEW org/nlogo/nvm/Context
            DUP
            ALOAD 1
            ALOAD 2
            INVOKESPECIAL org/nlogo/nvm/Context.<init> (Lorg/nlogo/nvm/Context;Lorg/nlogo/agent/AgentSet;)V
            ASTORE 4
            ICONST_0
            ISTORE 5
            ALOAD 2
            INVOKEVIRTUAL org/nlogo/agent/AgentSet.iterator ()Lorg/nlogo/agent/AgentSet$Iterator;
            ASTORE 6
           L2
           FRAME FULL [org/nlogo/prim/_asm_proceduredoplotting_countwith_4 org/nlogo/nvm/Context org/nlogo/agent/AgentSet org/nlogo/nvm/Reporter org/nlogo/nvm/Context I org/nlogo/agent/AgentSet$Iterator] []
            ALOAD 6
            INVOKEINTERFACE org/nlogo/agent/AgentSet$Iterator.hasNext ()Z
            IFEQ L3
            ALOAD 6
            INVOKEINTERFACE org/nlogo/agent/AgentSet$Iterator.next ()Lorg/nlogo/agent/Agent;
            ASTORE 7
            ALOAD 4
            ALOAD 7
            ALOAD 3
            INVOKEVIRTUAL org/nlogo/nvm/Context.evaluateReporter (Lorg/nlogo/agent/Agent;Lorg/nlogo/nvm/Reporter;)Ljava/lang/Object;
            ASTORE 8
            ALOAD 8
            INSTANCEOF java/lang/Boolean
            IFNE L4
            NEW org/nlogo/nvm/EngineException
            DUP
            ALOAD 1
            ALOAD 0
            INVOKESTATIC org/nlogo/core/I18N.errorsJ ()Lorg/nlogo/core/I18NJava;
            LDC "org.nlogo.prim.$common.expectedBooleanValue"
            ICONST_3
            ANEWARRAY java/lang/Object
            DUP
            ICONST_0
            LDC "COUNT"
            AASTORE
            DUP
            ICONST_1
            ALOAD 7
            INVOKESTATIC org/nlogo/api/Dump.logoObject (Ljava/lang/Object;)Ljava/lang/String;
            AASTORE
            DUP
            ICONST_2
            ALOAD 8
            INVOKESTATIC org/nlogo/api/Dump.logoObject (Ljava/lang/Object;)Ljava/lang/String;
            AASTORE
            INVOKEINTERFACE org/nlogo/core/I18NJava.getN (Ljava/lang/String;[Ljava/lang/Object;)Ljava/lang/String;
            INVOKESPECIAL org/nlogo/nvm/EngineException.<init> (Lorg/nlogo/nvm/Context;Lorg/nlogo/nvm/Instruction;Ljava/lang/String;)V
            ATHROW
           L4
           FRAME APPEND [org/nlogo/agent/Agent java/lang/Object]
            ALOAD 8
            CHECKCAST java/lang/Boolean
            INVOKEVIRTUAL java/lang/Boolean.booleanValue ()Z
            IFEQ L5
            IINC 5 1
           L5
           FRAME SAME
            GOTO L2
           L3
           FRAME CHOP 2
            ILOAD 5
            I2D
           L6
            DSTORE 2
            NEW java/lang/Double
            DUP
            DLOAD 2
            INVOKESPECIAL java/lang/Double.<init> (D)V
            ARETURN
[5]_setcurrentplotpen "set-current-plot-pen "food-in-pile2""
      _asm_proceduredoplotting_conststring_6 ""food-in-pile2"" => String
           L0
            LDC "food-in-pile2"
           L1
            ARETURN
[6]_plot "plot count patches with [ pcolor = sky ]"
      _asm_proceduredoplotting_countwith_7 "count patches with [ pcolor = sky ]" AgentSet,Reporter => double
        _patches "patches" => AgentSet
        _asm_proceduredoplotting_equal_8 "pcolor = sky" Object,double => boolean
          _patchvariable:PCOLOR "pcolor" => Object
          _constdouble:95.0 "sky" => double
              TRYCATCHBLOCK L0 L1 L2 org/nlogo/api/AgentException
             L0
              ALOAD 1
              GETFIELD org/nlogo/nvm/Context.agent : Lorg/nlogo/agent/Agent;
              ICONST_2
              INVOKEVIRTUAL org/nlogo/agent/Agent.getPatchVariable (I)Ljava/lang/Object;
             L1
              GOTO L3
             L2
             FRAME SAME1 org/nlogo/api/AgentException
              ASTORE 2
              NEW org/nlogo/nvm/EngineException
              DUP
              ALOAD 1
              ALOAD 0
              ALOAD 2
              INVOKEVIRTUAL org/nlogo/api/AgentException.getMessage ()Ljava/lang/String;
              INVOKESPECIAL org/nlogo/nvm/EngineException.<init> (Lorg/nlogo/nvm/Context;Lorg/nlogo/nvm/Instruction;Ljava/lang/String;)V
              ATHROW
             L3
             FRAME SAME1 java/lang/Object
              LDC 95.0
             L4
              DSTORE 3
              ASTORE 2
              ALOAD 2
              INSTANCEOF java/lang/Double
              IFEQ L5
              DLOAD 3
              ALOAD 2
              CHECKCAST java/lang/Double
              INVOKEVIRTUAL java/lang/Double.doubleValue ()D
              DCMPL
              IFNE L5
              ICONST_1
              GOTO L6
             L5
             FRAME APPEND [java/lang/Object D]
              ICONST_0
             L6
             FRAME SAME1 I
              IFEQ L7
              GETSTATIC java/lang/Boolean.TRUE : Ljava/lang/Boolean;
              GOTO L8
             L7
             FRAME SAME
              GETSTATIC java/lang/Boolean.FALSE : Ljava/lang/Boolean;
             L8
             FRAME SAME1 java/lang/Boolean
              ARETURN
           L0
            ALOAD 0
            GETFIELD org/nlogo/prim/_asm_proceduredoplotting_countwith_7.world : Lorg/nlogo/agent/World;
            INVOKEVIRTUAL org/nlogo/agent/World.patches ()Lorg/nlogo/agent/AgentSet;
           L1
            ALOAD 0
            GETFIELD org/nlogo/prim/_asm_proceduredoplotting_countwith_7.keptinstr3 : Lorg/nlogo/nvm/Reporter;
            ASTORE 3
            ASTORE 2
            ALOAD 3
            ALOAD 2
            ALOAD 1
            INVOKEVIRTUAL org/nlogo/nvm/Reporter.checkAgentSetClass (Lorg/nlogo/agent/AgentSet;Lorg/nlogo/nvm/Context;)V
            NEW org/nlogo/nvm/Context
            DUP
            ALOAD 1
            ALOAD 2
            INVOKESPECIAL org/nlogo/nvm/Context.<init> (Lorg/nlogo/nvm/Context;Lorg/nlogo/agent/AgentSet;)V
            ASTORE 4
            ICONST_0
            ISTORE 5
            ALOAD 2
            INVOKEVIRTUAL org/nlogo/agent/AgentSet.iterator ()Lorg/nlogo/agent/AgentSet$Iterator;
            ASTORE 6
           L2
           FRAME FULL [org/nlogo/prim/_asm_proceduredoplotting_countwith_7 org/nlogo/nvm/Context org/nlogo/agent/AgentSet org/nlogo/nvm/Reporter org/nlogo/nvm/Context I org/nlogo/agent/AgentSet$Iterator] []
            ALOAD 6
            INVOKEINTERFACE org/nlogo/agent/AgentSet$Iterator.hasNext ()Z
            IFEQ L3
            ALOAD 6
            INVOKEINTERFACE org/nlogo/agent/AgentSet$Iterator.next ()Lorg/nlogo/agent/Agent;
            ASTORE 7
            ALOAD 4
            ALOAD 7
            ALOAD 3
            INVOKEVIRTUAL org/nlogo/nvm/Context.evaluateReporter (Lorg/nlogo/agent/Agent;Lorg/nlogo/nvm/Reporter;)Ljava/lang/Object;
            ASTORE 8
            ALOAD 8
            INSTANCEOF java/lang/Boolean
            IFNE L4
            NEW org/nlogo/nvm/EngineException
            DUP
            ALOAD 1
            ALOAD 0
            INVOKESTATIC org/nlogo/core/I18N.errorsJ ()Lorg/nlogo/core/I18NJava;
            LDC "org.nlogo.prim.$common.expectedBooleanValue"
            ICONST_3
            ANEWARRAY java/lang/Object
            DUP
            ICONST_0
            LDC "COUNT"
            AASTORE
            DUP
            ICONST_1
            ALOAD 7
            INVOKESTATIC org/nlogo/api/Dump.logoObject (Ljava/lang/Object;)Ljava/lang/String;
            AASTORE
            DUP
            ICONST_2
            ALOAD 8
            INVOKESTATIC org/nlogo/api/Dump.logoObject (Ljava/lang/Object;)Ljava/lang/String;
            AASTORE
            INVOKEINTERFACE org/nlogo/core/I18NJava.getN (Ljava/lang/String;[Ljava/lang/Object;)Ljava/lang/String;
            INVOKESPECIAL org/nlogo/nvm/EngineException.<init> (Lorg/nlogo/nvm/Context;Lorg/nlogo/nvm/Instruction;Ljava/lang/String;)V
            ATHROW
           L4
           FRAME APPEND [org/nlogo/agent/Agent java/lang/Object]
            ALOAD 8
            CHECKCAST java/lang/Boolean
            INVOKEVIRTUAL java/lang/Boolean.booleanValue ()Z
            IFEQ L5
            IINC 5 1
           L5
           FRAME SAME
            GOTO L2
           L3
           FRAME CHOP 2
            ILOAD 5
            I2D
           L6
            DSTORE 2
            NEW java/lang/Double
            DUP
            DLOAD 2
            INVOKESPECIAL java/lang/Double.<init> (D)V
            ARETURN
[7]_setcurrentplotpen "set-current-plot-pen "food-in-pile3""
      _asm_proceduredoplotting_conststring_9 ""food-in-pile3"" => String
           L0
            LDC "food-in-pile3"
           L1
            ARETURN
[8]_plot "plot count patches with [ pcolor = blue ]"
      _asm_proceduredoplotting_countwith_10 "count patches with [ pcolor = blue ]" AgentSet,Reporter => double
        _patches "patches" => AgentSet
        _asm_proceduredoplotting_equal_11 "pcolor = blue" Object,double => boolean
          _patchvariable:PCOLOR "pcolor" => Object
          _constdouble:105.0 "blue" => double
              TRYCATCHBLOCK L0 L1 L2 org/nlogo/api/AgentException
             L0
              ALOAD 1
              GETFIELD org/nlogo/nvm/Context.agent : Lorg/nlogo/agent/Agent;
              ICONST_2
              INVOKEVIRTUAL org/nlogo/agent/Agent.getPatchVariable (I)Ljava/lang/Object;
             L1
              GOTO L3
             L2
             FRAME SAME1 org/nlogo/api/AgentException
              ASTORE 2
              NEW org/nlogo/nvm/EngineException
              DUP
              ALOAD 1
              ALOAD 0
              ALOAD 2
              INVOKEVIRTUAL org/nlogo/api/AgentException.getMessage ()Ljava/lang/String;
              INVOKESPECIAL org/nlogo/nvm/EngineException.<init> (Lorg/nlogo/nvm/Context;Lorg/nlogo/nvm/Instruction;Ljava/lang/String;)V
              ATHROW
             L3
             FRAME SAME1 java/lang/Object
              LDC 105.0
             L4
              DSTORE 3
              ASTORE 2
              ALOAD 2
              INSTANCEOF java/lang/Double
              IFEQ L5
              DLOAD 3
              ALOAD 2
              CHECKCAST java/lang/Double
              INVOKEVIRTUAL java/lang/Double.doubleValue ()D
              DCMPL
              IFNE L5
              ICONST_1
              GOTO L6
             L5
             FRAME APPEND [java/lang/Object D]
              ICONST_0
             L6
             FRAME SAME1 I
              IFEQ L7
              GETSTATIC java/lang/Boolean.TRUE : Ljava/lang/Boolean;
              GOTO L8
             L7
             FRAME SAME
              GETSTATIC java/lang/Boolean.FALSE : Ljava/lang/Boolean;
             L8
             FRAME SAME1 java/lang/Boolean
              ARETURN
           L0
            ALOAD 0
            GETFIELD org/nlogo/prim/_asm_proceduredoplotting_countwith_10.world : Lorg/nlogo/agent/World;
            INVOKEVIRTUAL org/nlogo/agent/World.patches ()Lorg/nlogo/agent/AgentSet;
           L1
            ALOAD 0
            GETFIELD org/nlogo/prim/_asm_proceduredoplotting_countwith_10.keptinstr3 : Lorg/nlogo/nvm/Reporter;
            ASTORE 3
            ASTORE 2
            ALOAD 3
            ALOAD 2
            ALOAD 1
            INVOKEVIRTUAL org/nlogo/nvm/Reporter.checkAgentSetClass (Lorg/nlogo/agent/AgentSet;Lorg/nlogo/nvm/Context;)V
            NEW org/nlogo/nvm/Context
            DUP
            ALOAD 1
            ALOAD 2
            INVOKESPECIAL org/nlogo/nvm/Context.<init> (Lorg/nlogo/nvm/Context;Lorg/nlogo/agent/AgentSet;)V
            ASTORE 4
            ICONST_0
            ISTORE 5
            ALOAD 2
            INVOKEVIRTUAL org/nlogo/agent/AgentSet.iterator ()Lorg/nlogo/agent/AgentSet$Iterator;
            ASTORE 6
           L2
           FRAME FULL [org/nlogo/prim/_asm_proceduredoplotting_countwith_10 org/nlogo/nvm/Context org/nlogo/agent/AgentSet org/nlogo/nvm/Reporter org/nlogo/nvm/Context I org/nlogo/agent/AgentSet$Iterator] []
            ALOAD 6
            INVOKEINTERFACE org/nlogo/agent/AgentSet$Iterator.hasNext ()Z
            IFEQ L3
            ALOAD 6
            INVOKEINTERFACE org/nlogo/agent/AgentSet$Iterator.next ()Lorg/nlogo/agent/Agent;
            ASTORE 7
            ALOAD 4
            ALOAD 7
            ALOAD 3
            INVOKEVIRTUAL org/nlogo/nvm/Context.evaluateReporter (Lorg/nlogo/agent/Agent;Lorg/nlogo/nvm/Reporter;)Ljava/lang/Object;
            ASTORE 8
            ALOAD 8
            INSTANCEOF java/lang/Boolean
            IFNE L4
            NEW org/nlogo/nvm/EngineException
            DUP
            ALOAD 1
            ALOAD 0
            INVOKESTATIC org/nlogo/core/I18N.errorsJ ()Lorg/nlogo/core/I18NJava;
            LDC "org.nlogo.prim.$common.expectedBooleanValue"
            ICONST_3
            ANEWARRAY java/lang/Object
            DUP
            ICONST_0
            LDC "COUNT"
            AASTORE
            DUP
            ICONST_1
            ALOAD 7
            INVOKESTATIC org/nlogo/api/Dump.logoObject (Ljava/lang/Object;)Ljava/lang/String;
            AASTORE
            DUP
            ICONST_2
            ALOAD 8
            INVOKESTATIC org/nlogo/api/Dump.logoObject (Ljava/lang/Object;)Ljava/lang/String;
            AASTORE
            INVOKEINTERFACE org/nlogo/core/I18NJava.getN (Ljava/lang/String;[Ljava/lang/Object;)Ljava/lang/String;
            INVOKESPECIAL org/nlogo/nvm/EngineException.<init> (Lorg/nlogo/nvm/Context;Lorg/nlogo/nvm/Instruction;Ljava/lang/String;)V
            ATHROW
           L4
           FRAME APPEND [org/nlogo/agent/Agent java/lang/Object]
            ALOAD 8
            CHECKCAST java/lang/Boolean
            INVOKEVIRTUAL java/lang/Boolean.booleanValue ()Z
            IFEQ L5
            IINC 5 1
           L5
           FRAME SAME
            GOTO L2
           L3
           FRAME CHOP 2
            ILOAD 5
            I2D
           L6
            DSTORE 2
            NEW java/lang/Double
            DUP
            DLOAD 2
            INVOKESPECIAL java/lang/Double.<init> (D)V
            ARETURN
[9]_asm_proceduredoplotting_return_12 => void
         L0
          ALOAD 1
          INVOKEVIRTUAL org/nlogo/nvm/Context.returnFromProcedure ()V
          ALOAD 1
          ICONST_0
          PUTFIELD org/nlogo/nvm/Context.stopping : Z
         L1
          RETURN

procedure LOOK-FOR-FOOD:[]{-T--}:
[0]_asm_procedurelookforfood_if_0 "if food > 0 set carrying-food? true set food food - 1 set drop-size 60 rt 180 [ stop ]" boolean => void
      _greaterthan "food > 0" Object,double => boolean
        _patchvariable:FOOD "food" => Object
        _constdouble:0.0 "0" => double
          TRYCATCHBLOCK L0 L1 L2 org/nlogo/api/AgentException
         L0
          ALOAD 1
          GETFIELD org/nlogo/nvm/Context.agent : Lorg/nlogo/agent/Agent;
          BIPUSH 6
          INVOKEVIRTUAL org/nlogo/agent/Agent.getPatchVariable (I)Ljava/lang/Object;
         L1
          GOTO L3
         L2
         FRAME SAME1 org/nlogo/api/AgentException
          ASTORE 2
          NEW org/nlogo/nvm/EngineException
          DUP
          ALOAD 1
          ALOAD 0
          ALOAD 2
          INVOKEVIRTUAL org/nlogo/api/AgentException.getMessage ()Ljava/lang/String;
          INVOKESPECIAL org/nlogo/nvm/EngineException.<init> (Lorg/nlogo/nvm/Context;Lorg/nlogo/nvm/Instruction;Ljava/lang/String;)V
          ATHROW
         L3
         FRAME SAME1 java/lang/Object
          DCONST_0
         L4
          DSTORE 3
          ASTORE 2
          ALOAD 2
          INSTANCEOF java/lang/Double
          IFEQ L5
          ALOAD 2
          CHECKCAST java/lang/Double
          INVOKEVIRTUAL java/lang/Double.doubleValue ()D
          DLOAD 3
          DCMPL
          IFLE L6
          ICONST_1
          GOTO L7
         L6
         FRAME APPEND [java/lang/Object D]
          ICONST_0
         L7
         FRAME SAME1 I
          GOTO L8
         L5
         FRAME SAME
          NEW org/nlogo/nvm/EngineException
          DUP
          ALOAD 1
          ALOAD 0
          INVOKESTATIC org/nlogo/core/I18N.errorsJ ()Lorg/nlogo/core/I18NJava;
          LDC "org.nlogo.prim._greaterthan.cannotCompareParameters"
          ICONST_2
          ANEWARRAY java/lang/Object
          DUP
          ICONST_0
          ALOAD 2
          INVOKESTATIC org/nlogo/api/TypeNames.aName (Ljava/lang/Object;)Ljava/lang/String;
          AASTORE
          DUP
          ICONST_1
          DLOAD 3
          INVOKESTATIC java/lang/Double.valueOf (D)Ljava/lang/Double;
          INVOKESTATIC org/nlogo/api/TypeNames.aName (Ljava/lang/Object;)Ljava/lang/String;
          AASTORE
          INVOKEINTERFACE org/nlogo/core/I18NJava.getN (Ljava/lang/String;[Ljava/lang/Object;)Ljava/lang/String;
          INVOKESPECIAL org/nlogo/nvm/EngineException.<init> (Lorg/nlogo/nvm/Context;Lorg/nlogo/nvm/Instruction;Ljava/lang/String;)V
          ATHROW
         L8
         FRAME SAME1 I
          ISTORE 2
          ALOAD 1
          ILOAD 2
          IFEQ L9
          ICONST_1
          GOTO L10
         L9
         FRAME FULL [org/nlogo/prim/_asm_procedurelookforfood_if_0 org/nlogo/nvm/Context I D] [org/nlogo/nvm/Context]
          BIPUSH 6
         L10
         FRAME FULL [org/nlogo/prim/_asm_procedurelookforfood_if_0 org/nlogo/nvm/Context I D] [org/nlogo/nvm/Context I]
          PUTFIELD org/nlogo/nvm/Context.ip : I
         L11
          RETURN
[1]_asm_procedurelookforfood_setturtlevariable_1 "set carrying-food? true" Object => void
      _constboolean:true "true" => Boolean
          TRYCATCHBLOCK L0 L1 L2 org/nlogo/api/AgentException
         L3
          ALOAD 0
          GETFIELD org/nlogo/prim/_asm_procedurelookforfood_setturtlevariable_1.kept2_value : Ljava/lang/Boolean;
         L4
          ASTORE 2
         L0
          ALOAD 1
          GETFIELD org/nlogo/nvm/Context.agent : Lorg/nlogo/agent/Agent;
          BIPUSH 13
          ALOAD 2
          INVOKEVIRTUAL org/nlogo/agent/Agent.setTurtleVariable (ILjava/lang/Object;)V
         L1
          GOTO L5
         L2
         FRAME FULL [org/nlogo/prim/_asm_procedurelookforfood_setturtlevariable_1 org/nlogo/nvm/Context java/lang/Boolean] [org/nlogo/api/AgentException]
          ASTORE 3
          NEW org/nlogo/nvm/EngineException
          DUP
          ALOAD 1
          ALOAD 0
          ALOAD 3
          INVOKEVIRTUAL org/nlogo/api/AgentException.getMessage ()Ljava/lang/String;
          INVOKESPECIAL org/nlogo/nvm/EngineException.<init> (Lorg/nlogo/nvm/Context;Lorg/nlogo/nvm/Instruction;Ljava/lang/String;)V
          ATHROW
         L5
         FRAME SAME
          ALOAD 1
          ICONST_2
          PUTFIELD org/nlogo/nvm/Context.ip : I
         L6
          RETURN
[2]_asm_procedurelookforfood_setpatchvariable_2 "set food food - 1" Object => void
      _minus "food - 1" double,double => double
        _patchvariable:FOOD "food" => Object
        _constdouble:1.0 "1" => double
          TRYCATCHBLOCK L0 L1 L2 org/nlogo/api/AgentException
          TRYCATCHBLOCK L3 L4 L4 java/lang/ClassCastException
          TRYCATCHBLOCK L5 L6 L7 org/nlogo/api/AgentException
         L0
          ALOAD 1
          GETFIELD org/nlogo/nvm/Context.agent : Lorg/nlogo/agent/Agent;
          BIPUSH 6
          INVOKEVIRTUAL org/nlogo/agent/Agent.getPatchVariable (I)Ljava/lang/Object;
         L1
          GOTO L8
         L2
         FRAME SAME1 org/nlogo/api/AgentException
          ASTORE 2
          NEW org/nlogo/nvm/EngineException
          DUP
          ALOAD 1
          ALOAD 0
          ALOAD 2
          INVOKEVIRTUAL org/nlogo/api/AgentException.getMessage ()Ljava/lang/String;
          INVOKESPECIAL org/nlogo/nvm/EngineException.<init> (Lorg/nlogo/nvm/Context;Lorg/nlogo/nvm/Instruction;Ljava/lang/String;)V
          ATHROW
         L8
         FRAME SAME1 java/lang/Object
          ASTORE 2
         L3
          ALOAD 2
          CHECKCAST java/lang/Double
          INVOKEVIRTUAL java/lang/Double.doubleValue ()D
          GOTO L9
         L4
         FRAME FULL [org/nlogo/prim/_asm_procedurelookforfood_setpatchvariable_2 org/nlogo/nvm/Context java/lang/Object] [java/lang/ClassCastException]
          POP
          NEW org/nlogo/nvm/ArgumentTypeException
          DUP
          ALOAD 1
          ALOAD 0
          BIPUSH 0
          LDC 1
          ALOAD 2
          INVOKESPECIAL org/nlogo/nvm/ArgumentTypeException.<init> (Lorg/nlogo/nvm/Context;Lorg/nlogo/nvm/Instruction;IILjava/lang/Object;)V
          ATHROW
         L9
         FRAME SAME1 D
          DCONST_1
         L10
          DSTORE 4
          DSTORE 2
          ALOAD 0
          DLOAD 2
          DLOAD 4
          DSUB
          INVOKEVIRTUAL org/nlogo/prim/_asm_procedurelookforfood_setpatchvariable_2.validDouble (D)D
         L11
          DSTORE 2
          NEW java/lang/Double
          DUP
          DLOAD 2
          INVOKESPECIAL java/lang/Double.<init> (D)V
          ASTORE 2
         L5
          ALOAD 1
          GETFIELD org/nlogo/nvm/Context.agent : Lorg/nlogo/agent/Agent;
          BIPUSH 6
          ALOAD 2
          INVOKEVIRTUAL org/nlogo/agent/Agent.setPatchVariable (ILjava/lang/Object;)V
         L6
          GOTO L12
         L7
         FRAME FULL [org/nlogo/prim/_asm_procedurelookforfood_setpatchvariable_2 org/nlogo/nvm/Context java/lang/Double T D] [org/nlogo/api/AgentException]
          ASTORE 3
          NEW org/nlogo/nvm/EngineException
          DUP
          ALOAD 1
          ALOAD 0
          ALOAD 3
          INVOKEVIRTUAL org/nlogo/api/AgentException.getMessage ()Ljava/lang/String;
          INVOKESPECIAL org/nlogo/nvm/EngineException.<init> (Lorg/nlogo/nvm/Context;Lorg/nlogo/nvm/Instruction;Ljava/lang/String;)V
          ATHROW
         L12
         FRAME SAME
          ALOAD 1
          ICONST_3
          PUTFIELD org/nlogo/nvm/Context.ip : I
         L13
          RETURN
[3]_asm_procedurelookforfood_setturtlevariable_3 "set drop-size 60" Object => void
      _constdouble:60.0 "60" => Double
          TRYCATCHBLOCK L0 L1 L2 org/nlogo/api/AgentException
         L3
          ALOAD 0
          GETFIELD org/nlogo/prim/_asm_procedurelookforfood_setturtlevariable_3.kept2_value : Ljava/lang/Double;
         L4
          ASTORE 2
         L0
          ALOAD 1
          GETFIELD org/nlogo/nvm/Context.agent : Lorg/nlogo/agent/Agent;
          BIPUSH 14
          ALOAD 2
          INVOKEVIRTUAL org/nlogo/agent/Agent.setTurtleVariable (ILjava/lang/Object;)V
         L1
          GOTO L5
         L2
         FRAME FULL [org/nlogo/prim/_asm_procedurelookforfood_setturtlevariable_3 org/nlogo/nvm/Context java/lang/Double] [org/nlogo/api/AgentException]
          ASTORE 3
          NEW org/nlogo/nvm/EngineException
          DUP
          ALOAD 1
          ALOAD 0
          ALOAD 3
          INVOKEVIRTUAL org/nlogo/api/AgentException.getMessage ()Ljava/lang/String;
          INVOKESPECIAL org/nlogo/nvm/EngineException.<init> (Lorg/nlogo/nvm/Context;Lorg/nlogo/nvm/Instruction;Ljava/lang/String;)V
          ATHROW
         L5
         FRAME SAME
          ALOAD 1
          ICONST_4
          PUTFIELD org/nlogo/nvm/Context.ip : I
         L6
          RETURN
[4]_asm_procedurelookforfood_right_4 "rt 180" double => void
      _constdouble:180.0 "180" => double
         L0
          LDC 180.0
         L1
          DSTORE 2
          ALOAD 1
          GETFIELD org/nlogo/nvm/Context.agent : Lorg/nlogo/agent/Agent;
          CHECKCAST org/nlogo/agent/Turtle
          DLOAD 2
          INVOKEVIRTUAL org/nlogo/agent/Turtle.turnRight (D)V
          ALOAD 1
          ICONST_5
          PUTFIELD org/nlogo/nvm/Context.ip : I
         L2
          RETURN
[5]_asm_procedurelookforfood_stop_5 "stop" => void
         L0
          ALOAD 1
          INVOKEVIRTUAL org/nlogo/nvm/Context.atTopActivation ()Z
          IFNE L1
          ALOAD 1
          ICONST_1
          PUTFIELD org/nlogo/nvm/Context.finished : Z
          GOTO L2
         L1
         FRAME SAME
          ALOAD 1
          GETFIELD org/nlogo/nvm/Context.activation : Lorg/nlogo/nvm/Activation;
          GETFIELD org/nlogo/nvm/Activation.procedure : Lorg/nlogo/nvm/Procedure;
          INVOKEVIRTUAL org/nlogo/nvm/Procedure.isReporter ()Z
          IFNE L3
          ALOAD 1
          GETFIELD org/nlogo/nvm/Context.activation : Lorg/nlogo/nvm/Activation;
          GETFIELD org/nlogo/nvm/Activation.procedure : Lorg/nlogo/nvm/Procedure;
          INVOKEVIRTUAL org/nlogo/nvm/Procedure.isTask ()Z
          IFEQ L4
          ALOAD 1
          GETFIELD org/nlogo/nvm/Context.activation : Lorg/nlogo/nvm/Activation;
          GETFIELD org/nlogo/nvm/Activation.procedure : Lorg/nlogo/nvm/Procedure;
          INVOKEVIRTUAL org/nlogo/nvm/Procedure.parent ()Lorg/nlogo/nvm/Procedure;
          INVOKEVIRTUAL org/nlogo/nvm/Procedure.isReporter ()Z
          IFEQ L4
         L3
         FRAME SAME
          NEW org/nlogo/nvm/EngineException
          DUP
          ALOAD 1
          ALOAD 0
          INVOKESTATIC org/nlogo/core/I18N.errorsJ ()Lorg/nlogo/core/I18NJava;
          LDC "org.nlogo.prim.etc._stop.notAllowedInsideToReport"
          ICONST_1
          ANEWARRAY java/lang/Object
          DUP
          ICONST_0
          LDC "STOP"
          AASTORE
          INVOKEINTERFACE org/nlogo/core/I18NJava.getN (Ljava/lang/String;[Ljava/lang/Object;)Ljava/lang/String;
          INVOKESPECIAL org/nlogo/nvm/EngineException.<init> (Lorg/nlogo/nvm/Context;Lorg/nlogo/nvm/Instruction;Ljava/lang/String;)V
          ATHROW
         L4
         FRAME SAME
          ALOAD 1
          INVOKEVIRTUAL org/nlogo/nvm/Context.stop ()V
         L2
         FRAME SAME
          RETURN
[6]_asm_procedurelookforfood_ifelse_6 "ifelse chemical > 2 [ fd 1 ] [ ifelse chemical < 0.05 wiggle [ fd 1 ] uphill-chemical [ fd 1 ] ]" boolean => void
      _greaterthan "chemical > 2" Object,double => boolean
        _patchvariable:CHEMICAL "chemical" => Object
        _constdouble:2.0 "2" => double
          TRYCATCHBLOCK L0 L1 L2 org/nlogo/api/AgentException
         L0
          ALOAD 1
          GETFIELD org/nlogo/nvm/Context.agent : Lorg/nlogo/agent/Agent;
          ICONST_5
          INVOKEVIRTUAL org/nlogo/agent/Agent.getPatchVariable (I)Ljava/lang/Object;
         L1
          GOTO L3
         L2
         FRAME SAME1 org/nlogo/api/AgentException
          ASTORE 2
          NEW org/nlogo/nvm/EngineException
          DUP
          ALOAD 1
          ALOAD 0
          ALOAD 2
          INVOKEVIRTUAL org/nlogo/api/AgentException.getMessage ()Ljava/lang/String;
          INVOKESPECIAL org/nlogo/nvm/EngineException.<init> (Lorg/nlogo/nvm/Context;Lorg/nlogo/nvm/Instruction;Ljava/lang/String;)V
          ATHROW
         L3
         FRAME SAME1 java/lang/Object
          LDC 2.0
         L4
          DSTORE 3
          ASTORE 2
          ALOAD 2
          INSTANCEOF java/lang/Double
          IFEQ L5
          ALOAD 2
          CHECKCAST java/lang/Double
          INVOKEVIRTUAL java/lang/Double.doubleValue ()D
          DLOAD 3
          DCMPL
          IFLE L6
          ICONST_1
          GOTO L7
         L6
         FRAME APPEND [java/lang/Object D]
          ICONST_0
         L7
         FRAME SAME1 I
          GOTO L8
         L5
         FRAME SAME
          NEW org/nlogo/nvm/EngineException
          DUP
          ALOAD 1
          ALOAD 0
          INVOKESTATIC org/nlogo/core/I18N.errorsJ ()Lorg/nlogo/core/I18NJava;
          LDC "org.nlogo.prim._greaterthan.cannotCompareParameters"
          ICONST_2
          ANEWARRAY java/lang/Object
          DUP
          ICONST_0
          ALOAD 2
          INVOKESTATIC org/nlogo/api/TypeNames.aName (Ljava/lang/Object;)Ljava/lang/String;
          AASTORE
          DUP
          ICONST_1
          DLOAD 3
          INVOKESTATIC java/lang/Double.valueOf (D)Ljava/lang/Double;
          INVOKESTATIC org/nlogo/api/TypeNames.aName (Ljava/lang/Object;)Ljava/lang/String;
          AASTORE
          INVOKEINTERFACE org/nlogo/core/I18NJava.getN (Ljava/lang/String;[Ljava/lang/Object;)Ljava/lang/String;
          INVOKESPECIAL org/nlogo/nvm/EngineException.<init> (Lorg/nlogo/nvm/Context;Lorg/nlogo/nvm/Instruction;Ljava/lang/String;)V
          ATHROW
         L8
         FRAME SAME1 I
          ISTORE 2
          ALOAD 1
          ILOAD 2
          IFEQ L9
          BIPUSH 7
          GOTO L10
         L9
         FRAME FULL [org/nlogo/prim/_asm_procedurelookforfood_ifelse_6 org/nlogo/nvm/Context I D] [org/nlogo/nvm/Context]
          BIPUSH 9
         L10
         FRAME FULL [org/nlogo/prim/_asm_procedurelookforfood_ifelse_6 org/nlogo/nvm/Context I D] [org/nlogo/nvm/Context I]
          PUTFIELD org/nlogo/nvm/Context.ip : I
         L11
          RETURN
[7]_asm_procedurelookforfood_fd1_7 "fd 1" => void
          TRYCATCHBLOCK L0 L1 L2 org/nlogo/api/AgentException
         L0
          ALOAD 1
          GETFIELD org/nlogo/nvm/Context.agent : Lorg/nlogo/agent/Agent;
          CHECKCAST org/nlogo/agent/Turtle
          DCONST_1
          INVOKEVIRTUAL org/nlogo/agent/Turtle.jump (D)V
         L1
          GOTO L3
         L2
         FRAME SAME1 org/nlogo/api/AgentException
          ASTORE 2
         L3
         FRAME SAME
          ALOAD 1
          BIPUSH 8
          PUTFIELD org/nlogo/nvm/Context.ip : I
         L4
          RETURN
[8]_asm_procedurelookforfood_goto_8 => void
         L0
          ALOAD 1
          BIPUSH 15
          PUTFIELD org/nlogo/nvm/Context.ip : I
         L1
          RETURN
[9]_asm_procedurelookforfood_ifelse_9 "ifelse chemical < 0.05 wiggle [ fd 1 ] uphill-chemical [ fd 1 ]" boolean => void
      _lessthan "chemical < 0.05" Object,double => boolean
        _patchvariable:CHEMICAL "chemical" => Object
        _constdouble:0.05 "0.05" => double
          TRYCATCHBLOCK L0 L1 L2 org/nlogo/api/AgentException
         L0
          ALOAD 1
          GETFIELD org/nlogo/nvm/Context.agent : Lorg/nlogo/agent/Agent;
          ICONST_5
          INVOKEVIRTUAL org/nlogo/agent/Agent.getPatchVariable (I)Ljava/lang/Object;
         L1
          GOTO L3
         L2
         FRAME SAME1 org/nlogo/api/AgentException
          ASTORE 2
          NEW org/nlogo/nvm/EngineException
          DUP
          ALOAD 1
          ALOAD 0
          ALOAD 2
          INVOKEVIRTUAL org/nlogo/api/AgentException.getMessage ()Ljava/lang/String;
          INVOKESPECIAL org/nlogo/nvm/EngineException.<init> (Lorg/nlogo/nvm/Context;Lorg/nlogo/nvm/Instruction;Ljava/lang/String;)V
          ATHROW
         L3
         FRAME SAME1 java/lang/Object
          LDC 0.05
         L4
          DSTORE 3
          ASTORE 2
          ALOAD 2
          INSTANCEOF java/lang/Double
          IFEQ L5
          ALOAD 2
          CHECKCAST java/lang/Double
          INVOKEVIRTUAL java/lang/Double.doubleValue ()D
          DLOAD 3
          DCMPG
          IFGE L6
          ICONST_1
          GOTO L7
         L6
         FRAME APPEND [java/lang/Object D]
          ICONST_0
         L7
         FRAME SAME1 I
          GOTO L8
         L5
         FRAME SAME
          NEW org/nlogo/nvm/EngineException
          DUP
          ALOAD 1
          ALOAD 0
          INVOKESTATIC org/nlogo/core/I18N.errorsJ ()Lorg/nlogo/core/I18NJava;
          LDC "org.nlogo.prim._lessthan.cantUseLessthanOnDifferentArgs"
          ICONST_2
          ANEWARRAY java/lang/Object
          DUP
          ICONST_0
          ALOAD 2
          INVOKESTATIC org/nlogo/api/TypeNames.aName (Ljava/lang/Object;)Ljava/lang/String;
          AASTORE
          DUP
          ICONST_1
          DLOAD 3
          INVOKESTATIC java/lang/Double.valueOf (D)Ljava/lang/Double;
          INVOKESTATIC org/nlogo/api/TypeNames.aName (Ljava/lang/Object;)Ljava/lang/String;
          AASTORE
          INVOKEINTERFACE org/nlogo/core/I18NJava.getN (Ljava/lang/String;[Ljava/lang/Object;)Ljava/lang/String;
          INVOKESPECIAL org/nlogo/nvm/EngineException.<init> (Lorg/nlogo/nvm/Context;Lorg/nlogo/nvm/Instruction;Ljava/lang/String;)V
          ATHROW
         L8
         FRAME SAME1 I
          ISTORE 2
          ALOAD 1
          ILOAD 2
          IFEQ L9
          BIPUSH 10
          GOTO L10
         L9
         FRAME FULL [org/nlogo/prim/_asm_procedurelookforfood_ifelse_9 org/nlogo/nvm/Context I D] [org/nlogo/nvm/Context]
          BIPUSH 13
         L10
         FRAME FULL [org/nlogo/prim/_asm_procedurelookforfood_ifelse_9 org/nlogo/nvm/Context I D] [org/nlogo/nvm/Context I]
          PUTFIELD org/nlogo/nvm/Context.ip : I
         L11
          RETURN
[10]_asm_procedurelookforfood_call_10 "wiggle"
         L0
          NEW org/nlogo/nvm/Activation
          DUP
          ALOAD 0
          GETFIELD org/nlogo/prim/_asm_procedurelookforfood_call_10.kept1_procedure : Lorg/nlogo/nvm/Procedure;
          ALOAD 1
          GETFIELD org/nlogo/nvm/Context.activation : Lorg/nlogo/nvm/Activation;
          BIPUSH 11
          INVOKESPECIAL org/nlogo/nvm/Activation.<init> (Lorg/nlogo/nvm/Procedure;Lorg/nlogo/nvm/Activation;I)V
          ALOAD 1
          SWAP
          PUTFIELD org/nlogo/nvm/Context.activation : Lorg/nlogo/nvm/Activation;
          ALOAD 1
          ICONST_0
          PUTFIELD org/nlogo/nvm/Context.ip : I
         L1
          RETURN
[11]_asm_procedurelookforfood_fd1_11 "fd 1" => void
          TRYCATCHBLOCK L0 L1 L2 org/nlogo/api/AgentException
         L0
          ALOAD 1
          GETFIELD org/nlogo/nvm/Context.agent : Lorg/nlogo/agent/Agent;
          CHECKCAST org/nlogo/agent/Turtle
          DCONST_1
          INVOKEVIRTUAL org/nlogo/agent/Turtle.jump (D)V
         L1
          GOTO L3
         L2
         FRAME SAME1 org/nlogo/api/AgentException
          ASTORE 2
         L3
         FRAME SAME
          ALOAD 1
          BIPUSH 12
          PUTFIELD org/nlogo/nvm/Context.ip : I
         L4
          RETURN
[12]_asm_procedurelookforfood_goto_12 => void
         L0
          ALOAD 1
          BIPUSH 15
          PUTFIELD org/nlogo/nvm/Context.ip : I
         L1
          RETURN
[13]_asm_procedurelookforfood_call_13 "uphill-chemical"
         L0
          NEW org/nlogo/nvm/Activation
          DUP
          ALOAD 0
          GETFIELD org/nlogo/prim/_asm_procedurelookforfood_call_13.kept1_procedure : Lorg/nlogo/nvm/Procedure;
          ALOAD 1
          GETFIELD org/nlogo/nvm/Context.activation : Lorg/nlogo/nvm/Activation;
          BIPUSH 14
          INVOKESPECIAL org/nlogo/nvm/Activation.<init> (Lorg/nlogo/nvm/Procedure;Lorg/nlogo/nvm/Activation;I)V
          ALOAD 1
          SWAP
          PUTFIELD org/nlogo/nvm/Context.activation : Lorg/nlogo/nvm/Activation;
          ALOAD 1
          ICONST_0
          PUTFIELD org/nlogo/nvm/Context.ip : I
         L1
          RETURN
[14]_asm_procedurelookforfood_fd1_14 "fd 1" => void
          TRYCATCHBLOCK L0 L1 L2 org/nlogo/api/AgentException
         L0
          ALOAD 1
          GETFIELD org/nlogo/nvm/Context.agent : Lorg/nlogo/agent/Agent;
          CHECKCAST org/nlogo/agent/Turtle
          DCONST_1
          INVOKEVIRTUAL org/nlogo/agent/Turtle.jump (D)V
         L1
          GOTO L3
         L2
         FRAME SAME1 org/nlogo/api/AgentException
          ASTORE 2
         L3
         FRAME SAME
          ALOAD 1
          BIPUSH 15
          PUTFIELD org/nlogo/nvm/Context.ip : I
         L4
          RETURN
[15]_asm_procedurelookforfood_return_15 => void
         L0
          ALOAD 1
          INVOKEVIRTUAL org/nlogo/nvm/Context.returnFromProcedure ()V
          ALOAD 1
          ICONST_0
          PUTFIELD org/nlogo/nvm/Context.stopping : Z
         L1
          RETURN

procedure SETUP-PATCHES:[]{OTPL}:
[0]_asm_proceduresetuppatches_ask_0 "ask patches set chemical 0 set food 0 set food-source-number -1 setup-nest setup-food [ update-display ]" AgentSet => void
      _patches "patches" => AgentSet
         L0
          ALOAD 0
          GETFIELD org/nlogo/prim/_asm_proceduresetuppatches_ask_0.world : Lorg/nlogo/agent/World;
          INVOKEVIRTUAL org/nlogo/agent/World.patches ()Lorg/nlogo/agent/AgentSet;
         L1
          ASTORE 2
          ALOAD 1
          GETFIELD org/nlogo/nvm/Context.agent : Lorg/nlogo/agent/Agent;
          INSTANCEOF org/nlogo/agent/Observer
          IFNE L2
          ALOAD 2
          ALOAD 0
          GETFIELD org/nlogo/prim/_asm_proceduresetuppatches_ask_0.world : Lorg/nlogo/agent/World;
          INVOKEVIRTUAL org/nlogo/agent/World.turtles ()Lorg/nlogo/agent/AgentSet;
          IF_ACMPNE L3
          NEW org/nlogo/nvm/EngineException
          DUP
          ALOAD 1
          ALOAD 0
          INVOKESTATIC org/nlogo/core/I18N.errorsJ ()Lorg/nlogo/core/I18NJava;
          LDC "org.nlogo.prim.$common.onlyObserverCanAskAllTurtles"
          INVOKEINTERFACE org/nlogo/core/I18NJava.get (Ljava/lang/String;)Ljava/lang/String;
          INVOKESPECIAL org/nlogo/nvm/EngineException.<init> (Lorg/nlogo/nvm/Context;Lorg/nlogo/nvm/Instruction;Ljava/lang/String;)V
          ATHROW
         L3
         FRAME APPEND [org/nlogo/agent/AgentSet]
          ALOAD 2
          ALOAD 0
          GETFIELD org/nlogo/prim/_asm_proceduresetuppatches_ask_0.world : Lorg/nlogo/agent/World;
          INVOKEVIRTUAL org/nlogo/agent/World.patches ()Lorg/nlogo/agent/AgentSet;
          IF_ACMPNE L2
          NEW org/nlogo/nvm/EngineException
          DUP
          ALOAD 1
          ALOAD 0
          INVOKESTATIC org/nlogo/core/I18N.errorsJ ()Lorg/nlogo/core/I18NJava;
          LDC "org.nlogo.prim.$common.onlyObserverCanAskAllPatches"
          INVOKEINTERFACE org/nlogo/core/I18NJava.get (Ljava/lang/String;)Ljava/lang/String;
          INVOKESPECIAL org/nlogo/nvm/EngineException.<init> (Lorg/nlogo/nvm/Context;Lorg/nlogo/nvm/Instruction;Ljava/lang/String;)V
          ATHROW
         L2
         FRAME SAME
          ALOAD 1
          ALOAD 2
          ICONST_1
          INVOKEVIRTUAL org/nlogo/nvm/Context.runExclusiveJob (Lorg/nlogo/agent/AgentSet;I)V
          ALOAD 1
          BIPUSH 8
          PUTFIELD org/nlogo/nvm/Context.ip : I
         L4
          RETURN
[1]_asm_proceduresetuppatches_setpatchvariable_1 "set chemical 0" Object => void
      _constdouble:0.0 "0" => Double
          TRYCATCHBLOCK L0 L1 L2 org/nlogo/api/AgentException
         L3
          ALOAD 0
          GETFIELD org/nlogo/prim/_asm_proceduresetuppatches_setpatchvariable_1.kept2_value : Ljava/lang/Double;
         L4
          ASTORE 2
         L0
          ALOAD 1
          GETFIELD org/nlogo/nvm/Context.agent : Lorg/nlogo/agent/Agent;
          ICONST_5
          ALOAD 2
          INVOKEVIRTUAL org/nlogo/agent/Agent.setPatchVariable (ILjava/lang/Object;)V
         L1
          GOTO L5
         L2
         FRAME FULL [org/nlogo/prim/_asm_proceduresetuppatches_setpatchvariable_1 org/nlogo/nvm/Context java/lang/Double] [org/nlogo/api/AgentException]
          ASTORE 3
          NEW org/nlogo/nvm/EngineException
          DUP
          ALOAD 1
          ALOAD 0
          ALOAD 3
          INVOKEVIRTUAL org/nlogo/api/AgentException.getMessage ()Ljava/lang/String;
          INVOKESPECIAL org/nlogo/nvm/EngineException.<init> (Lorg/nlogo/nvm/Context;Lorg/nlogo/nvm/Instruction;Ljava/lang/String;)V
          ATHROW
         L5
         FRAME SAME
          ALOAD 1
          ICONST_2
          PUTFIELD org/nlogo/nvm/Context.ip : I
         L6
          RETURN
[2]_asm_proceduresetuppatches_setpatchvariable_2 "set food 0" Object => void
      _constdouble:0.0 "0" => Double
          TRYCATCHBLOCK L0 L1 L2 org/nlogo/api/AgentException
         L3
          ALOAD 0
          GETFIELD org/nlogo/prim/_asm_proceduresetuppatches_setpatchvariable_2.kept2_value : Ljava/lang/Double;
         L4
          ASTORE 2
         L0
          ALOAD 1
          GETFIELD org/nlogo/nvm/Context.agent : Lorg/nlogo/agent/Agent;
          BIPUSH 6
          ALOAD 2
          INVOKEVIRTUAL org/nlogo/agent/Agent.setPatchVariable (ILjava/lang/Object;)V
         L1
          GOTO L5
         L2
         FRAME FULL [org/nlogo/prim/_asm_proceduresetuppatches_setpatchvariable_2 org/nlogo/nvm/Context java/lang/Double] [org/nlogo/api/AgentException]
          ASTORE 3
          NEW org/nlogo/nvm/EngineException
          DUP
          ALOAD 1
          ALOAD 0
          ALOAD 3
          INVOKEVIRTUAL org/nlogo/api/AgentException.getMessage ()Ljava/lang/String;
          INVOKESPECIAL org/nlogo/nvm/EngineException.<init> (Lorg/nlogo/nvm/Context;Lorg/nlogo/nvm/Instruction;Ljava/lang/String;)V
          ATHROW
         L5
         FRAME SAME
          ALOAD 1
          ICONST_3
          PUTFIELD org/nlogo/nvm/Context.ip : I
         L6
          RETURN
[3]_asm_proceduresetuppatches_setpatchvariable_3 "set food-source-number -1" Object => void
      _constdouble:-1.0 "-1" => Double
          TRYCATCHBLOCK L0 L1 L2 org/nlogo/api/AgentException
         L3
          ALOAD 0
          GETFIELD org/nlogo/prim/_asm_proceduresetuppatches_setpatchvariable_3.kept2_value : Ljava/lang/Double;
         L4
          ASTORE 2
         L0
          ALOAD 1
          GETFIELD org/nlogo/nvm/Context.agent : Lorg/nlogo/agent/Agent;
          BIPUSH 9
          ALOAD 2
          INVOKEVIRTUAL org/nlogo/agent/Agent.setPatchVariable (ILjava/lang/Object;)V
         L1
          GOTO L5
         L2
         FRAME FULL [org/nlogo/prim/_asm_proceduresetuppatches_setpatchvariable_3 org/nlogo/nvm/Context java/lang/Double] [org/nlogo/api/AgentException]
          ASTORE 3
          NEW org/nlogo/nvm/EngineException
          DUP
          ALOAD 1
          ALOAD 0
          ALOAD 3
          INVOKEVIRTUAL org/nlogo/api/AgentException.getMessage ()Ljava/lang/String;
          INVOKESPECIAL org/nlogo/nvm/EngineException.<init> (Lorg/nlogo/nvm/Context;Lorg/nlogo/nvm/Instruction;Ljava/lang/String;)V
          ATHROW
         L5
         FRAME SAME
          ALOAD 1
          ICONST_4
          PUTFIELD org/nlogo/nvm/Context.ip : I
         L6
          RETURN
[4]_asm_proceduresetuppatches_call_4 "setup-nest"
         L0
          NEW org/nlogo/nvm/Activation
          DUP
          ALOAD 0
          GETFIELD org/nlogo/prim/_asm_proceduresetuppatches_call_4.kept1_procedure : Lorg/nlogo/nvm/Procedure;
          ALOAD 1
          GETFIELD org/nlogo/nvm/Context.activation : Lorg/nlogo/nvm/Activation;
          ICONST_5
          INVOKESPECIAL org/nlogo/nvm/Activation.<init> (Lorg/nlogo/nvm/Procedure;Lorg/nlogo/nvm/Activation;I)V
          ALOAD 1
          SWAP
          PUTFIELD org/nlogo/nvm/Context.activation : Lorg/nlogo/nvm/Activation;
          ALOAD 1
          ICONST_0
          PUTFIELD org/nlogo/nvm/Context.ip : I
         L1
          RETURN
[5]_asm_proceduresetuppatches_call_5 "setup-food"
         L0
          NEW org/nlogo/nvm/Activation
          DUP
          ALOAD 0
          GETFIELD org/nlogo/prim/_asm_proceduresetuppatches_call_5.kept1_procedure : Lorg/nlogo/nvm/Procedure;
          ALOAD 1
          GETFIELD org/nlogo/nvm/Context.activation : Lorg/nlogo/nvm/Activation;
          BIPUSH 6
          INVOKESPECIAL org/nlogo/nvm/Activation.<init> (Lorg/nlogo/nvm/Procedure;Lorg/nlogo/nvm/Activation;I)V
          ALOAD 1
          SWAP
          PUTFIELD org/nlogo/nvm/Context.activation : Lorg/nlogo/nvm/Activation;
          ALOAD 1
          ICONST_0
          PUTFIELD org/nlogo/nvm/Context.ip : I
         L1
          RETURN
[6]_asm_proceduresetuppatches_call_6 "update-display"
         L0
          NEW org/nlogo/nvm/Activation
          DUP
          ALOAD 0
          GETFIELD org/nlogo/prim/_asm_proceduresetuppatches_call_6.kept1_procedure : Lorg/nlogo/nvm/Procedure;
          ALOAD 1
          GETFIELD org/nlogo/nvm/Context.activation : Lorg/nlogo/nvm/Activation;
          BIPUSH 7
          INVOKESPECIAL org/nlogo/nvm/Activation.<init> (Lorg/nlogo/nvm/Procedure;Lorg/nlogo/nvm/Activation;I)V
          ALOAD 1
          SWAP
          PUTFIELD org/nlogo/nvm/Context.activation : Lorg/nlogo/nvm/Activation;
          ALOAD 1
          ICONST_0
          PUTFIELD org/nlogo/nvm/Context.ip : I
         L1
          RETURN
[7]_asm_proceduresetuppatches_done_7 => void
         L0
          ALOAD 1
          ICONST_1
          PUTFIELD org/nlogo/nvm/Context.finished : Z
         L1
          RETURN
[8]_asm_proceduresetuppatches_return_8 => void
         L0
          ALOAD 1
          INVOKEVIRTUAL org/nlogo/nvm/Context.returnFromProcedure ()V
          ALOAD 1
          ICONST_0
          PUTFIELD org/nlogo/nvm/Context.stopping : Z
         L1
          RETURN

procedure BENCHMARK:[_repeatlocal:0]{O---}:
[0]_asm_procedurebenchmark_randomseed_0 "random-seed 337" double => void
      _constdouble:337.0 "337" => double
         L0
          LDC 337.0
         L1
          DSTORE 2
          DLOAD 2
          D2L
          LSTORE 4
          LLOAD 4
          LDC -2147483648
          LCMP
          IFLT L2
          LLOAD 4
          LDC 2147483647
          LCMP
          IFLE L3
         L2
         FRAME APPEND [D J]
          NEW org/nlogo/nvm/EngineException
          DUP
          ALOAD 1
          ALOAD 0
          NEW scala/collection/mutable/StringBuilder
          DUP
          INVOKESPECIAL scala/collection/mutable/StringBuilder.<init> ()V
          GETSTATIC org/nlogo/api/Dump$.MODULE$ : Lorg/nlogo/api/Dump$;
          DLOAD 2
          INVOKEVIRTUAL org/nlogo/api/Dump$.number (D)Ljava/lang/String;
          INVOKEVIRTUAL scala/collection/mutable/StringBuilder.append (Ljava/lang/Object;)Lscala/collection/mutable/StringBuilder;
          LDC " is not in the allowable range for random seeds (-2147483648 to 2147483647)"
          INVOKEVIRTUAL scala/collection/mutable/StringBuilder.append (Ljava/lang/Object;)Lscala/collection/mutable/StringBuilder;
          INVOKEVIRTUAL scala/collection/mutable/StringBuilder.toString ()Ljava/lang/String;
          INVOKESPECIAL org/nlogo/nvm/EngineException.<init> (Lorg/nlogo/nvm/Context;Lorg/nlogo/nvm/Instruction;Ljava/lang/String;)V
          ATHROW
         L3
         FRAME SAME
          ALOAD 1
          GETFIELD org/nlogo/nvm/Context.job : Lorg/nlogo/nvm/Job;
          GETFIELD org/nlogo/nvm/Job.random : Lorg/nlogo/api/MersenneTwisterFast;
          LLOAD 4
          L2I
          I2L
          INVOKEVIRTUAL org/nlogo/api/MersenneTwisterFast.setSeed (J)V
          ALOAD 1
          ICONST_1
          PUTFIELD org/nlogo/nvm/Context.ip : I
         L4
          RETURN
[1]_resettimer "reset-timer"
[2]_asm_procedurebenchmark_call_1 "setup"
         L0
          NEW org/nlogo/nvm/Activation
          DUP
          ALOAD 0
          GETFIELD org/nlogo/prim/_asm_procedurebenchmark_call_1.kept1_procedure : Lorg/nlogo/nvm/Procedure;
          ALOAD 1
          GETFIELD org/nlogo/nvm/Context.activation : Lorg/nlogo/nvm/Activation;
          ICONST_3
          INVOKESPECIAL org/nlogo/nvm/Activation.<init> (Lorg/nlogo/nvm/Procedure;Lorg/nlogo/nvm/Activation;I)V
          ALOAD 1
          SWAP
          PUTFIELD org/nlogo/nvm/Context.activation : Lorg/nlogo/nvm/Activation;
          ALOAD 1
          ICONST_0
          PUTFIELD org/nlogo/nvm/Context.ip : I
         L1
          RETURN
[3]_asm_procedurebenchmark_repeatlocal_2 "repeat 800 [ go ]" double => void
      _constdouble:800.0 "800" => double
         L0
          LDC 800.0
         L1
          DSTORE 2
          ALOAD 1
          GETFIELD org/nlogo/nvm/Context.activation : Lorg/nlogo/nvm/Activation;
          GETFIELD org/nlogo/nvm/Activation.args : [Ljava/lang/Object;
          ICONST_0
          NEW org/nlogo/nvm/MutableLong
          DUP
          ALOAD 0
          DLOAD 2
          INVOKEVIRTUAL org/nlogo/prim/_asm_procedurebenchmark_repeatlocal_2.validLong (D)J
          INVOKESPECIAL org/nlogo/nvm/MutableLong.<init> (J)V
          AASTORE
          ALOAD 1
          ICONST_5
          PUTFIELD org/nlogo/nvm/Context.ip : I
         L2
          RETURN
[4]_asm_procedurebenchmark_call_3 "go"
         L0
          NEW org/nlogo/nvm/Activation
          DUP
          ALOAD 0
          GETFIELD org/nlogo/prim/_asm_procedurebenchmark_call_3.kept1_procedure : Lorg/nlogo/nvm/Procedure;
          ALOAD 1
          GETFIELD org/nlogo/nvm/Context.activation : Lorg/nlogo/nvm/Activation;
          ICONST_5
          INVOKESPECIAL org/nlogo/nvm/Activation.<init> (Lorg/nlogo/nvm/Procedure;Lorg/nlogo/nvm/Activation;I)V
          ALOAD 1
          SWAP
          PUTFIELD org/nlogo/nvm/Context.activation : Lorg/nlogo/nvm/Activation;
          ALOAD 1
          ICONST_0
          PUTFIELD org/nlogo/nvm/Context.ip : I
         L1
          RETURN
[5]_asm_procedurebenchmark_repeatlocalinternal_4 => void
         L0
          ALOAD 1
          GETFIELD org/nlogo/nvm/Context.activation : Lorg/nlogo/nvm/Activation;
          GETFIELD org/nlogo/nvm/Activation.args : [Ljava/lang/Object;
          ICONST_0
          AALOAD
          CHECKCAST org/nlogo/nvm/MutableLong
          ASTORE 2
          ALOAD 2
          INVOKEVIRTUAL org/nlogo/nvm/MutableLong.value ()J
          LCONST_0
          LCMP
          IFGT L1
          ALOAD 1
          BIPUSH 6
          PUTFIELD org/nlogo/nvm/Context.ip : I
          GOTO L2
         L1
         FRAME APPEND [org/nlogo/nvm/MutableLong]
          ALOAD 2
          ALOAD 2
          INVOKEVIRTUAL org/nlogo/nvm/MutableLong.value ()J
          LCONST_1
          LSUB
          INVOKEVIRTUAL org/nlogo/nvm/MutableLong.value_$eq (J)V
          ALOAD 1
          ICONST_4
          PUTFIELD org/nlogo/nvm/Context.ip : I
         L2
         FRAME SAME
          RETURN
[6]_asm_procedurebenchmark_setobservervariable_5 "set result timer" Object => void
      _timer "timer" => double
          TRYCATCHBLOCK L0 L1 L2 org/nlogo/api/AgentException
         L3
          ALOAD 0
          GETFIELD org/nlogo/prim/_asm_procedurebenchmark_setobservervariable_5.world : Lorg/nlogo/agent/World;
          INVOKEVIRTUAL org/nlogo/agent/World.timer ()Lorg/nlogo/api/Timer;
          INVOKEVIRTUAL org/nlogo/api/Timer.read ()D
         L4
          DSTORE 2
          NEW java/lang/Double
          DUP
          DLOAD 2
          INVOKESPECIAL java/lang/Double.<init> (D)V
          ASTORE 2
         L0
          ALOAD 1
          GETFIELD org/nlogo/nvm/Context.agent : Lorg/nlogo/agent/Agent;
          ICONST_4
          ALOAD 2
          INVOKEVIRTUAL org/nlogo/agent/Agent.setObserverVariable (ILjava/lang/Object;)V
         L1
          GOTO L5
         L2
         FRAME FULL [org/nlogo/prim/_asm_procedurebenchmark_setobservervariable_5 org/nlogo/nvm/Context java/lang/Double] [org/nlogo/api/AgentException]
          ASTORE 3
          NEW org/nlogo/nvm/EngineException
          DUP
          ALOAD 1
          ALOAD 0
          ALOAD 3
          INVOKEVIRTUAL org/nlogo/api/AgentException.getMessage ()Ljava/lang/String;
          INVOKESPECIAL org/nlogo/nvm/EngineException.<init> (Lorg/nlogo/nvm/Context;Lorg/nlogo/nvm/Instruction;Ljava/lang/String;)V
          ATHROW
         L5
         FRAME SAME
          ALOAD 1
          BIPUSH 7
          PUTFIELD org/nlogo/nvm/Context.ip : I
         L6
          RETURN
[7]_asm_procedurebenchmark_return_6 => void
         L0
          ALOAD 1
          INVOKEVIRTUAL org/nlogo/nvm/Context.returnFromProcedure ()V
          ALOAD 1
          ICONST_0
          PUTFIELD org/nlogo/nvm/Context.stopping : Z
         L1
          RETURN

procedure UPHILL-NEST-SCENT:[SCENT-AHEAD SCENT-RIGHT SCENT-LEFT]{-T--}:
[0]_asm_procedureuphillnestscent_call_0 "wiggle"
         L0
          NEW org/nlogo/nvm/Activation
          DUP
          ALOAD 0
          GETFIELD org/nlogo/prim/_asm_procedureuphillnestscent_call_0.kept1_procedure : Lorg/nlogo/nvm/Procedure;
          ALOAD 1
          GETFIELD org/nlogo/nvm/Context.activation : Lorg/nlogo/nvm/Activation;
          ICONST_1
          INVOKESPECIAL org/nlogo/nvm/Activation.<init> (Lorg/nlogo/nvm/Procedure;Lorg/nlogo/nvm/Activation;I)V
          ALOAD 1
          SWAP
          PUTFIELD org/nlogo/nvm/Context.activation : Lorg/nlogo/nvm/Activation;
          ALOAD 1
          ICONST_0
          PUTFIELD org/nlogo/nvm/Context.ip : I
         L1
          RETURN
[1]_asm_procedureuphillnestscent_setprocedurevariable_1 "let [ nest-scent ] of patch-ahead 1" Object => void
      _patchvariableof:NEST-SCENT "[ nest-scent ] of patch-ahead 1" Object => Object
        _patchahead "patch-ahead 1"
          _asm_procedureuphillnestscent_constdouble_2 "1" => Double
               L0
                ALOAD 0
                GETFIELD org/nlogo/prim/_asm_procedureuphillnestscent_constdouble_2.kept1_value : Ljava/lang/Double;
               L1
                ARETURN
          TRYCATCHBLOCK L0 L1 L2 org/nlogo/api/AgentException
          TRYCATCHBLOCK L3 L4 L5 org/nlogo/api/AgentException
          ALOAD 0
          GETFIELD org/nlogo/prim/_asm_procedureuphillnestscent_setprocedurevariable_1.keptinstr3 : Lorg/nlogo/prim/etc/_patchahead;
          ALOAD 1
          INVOKEVIRTUAL org/nlogo/prim/etc/_patchahead.report (Lorg/nlogo/nvm/Context;)Ljava/lang/Object;
         L6
          ASTORE 2
          ALOAD 2
          ASTORE 3
          ALOAD 3
          INSTANCEOF org/nlogo/agent/Agent
          IFEQ L7
          ALOAD 3
          CHECKCAST org/nlogo/agent/Agent
          ASTORE 4
          ALOAD 4
          GETFIELD org/nlogo/agent/Agent.id : J
          LDC -1
          LCMP
          IFNE L3
          NEW org/nlogo/nvm/EngineException
          DUP
          ALOAD 1
          ALOAD 0
          GETSTATIC org/nlogo/core/I18N$.MODULE$ : Lorg/nlogo/core/I18N$;
          INVOKEVIRTUAL org/nlogo/core/I18N$.errors ()Lorg/nlogo/core/I18N$BundleKind;
          LDC "org.nlogo.$common.thatAgentIsDead"
          GETSTATIC scala/Predef$.MODULE$ : Lscala/Predef$;
          ICONST_1
          ANEWARRAY java/lang/Object
          DUP
          ICONST_0
          ALOAD 4
          INVOKEVIRTUAL org/nlogo/agent/Agent.classDisplayName ()Ljava/lang/String;
          AASTORE
          INVOKEVIRTUAL scala/Predef$.wrapRefArray ([Ljava/lang/Object;)Lscala/collection/mutable/WrappedArray;
          INVOKEVIRTUAL org/nlogo/core/I18N$BundleKind.getN (Ljava/lang/String;Lscala/collection/Seq;)Ljava/lang/String;
          INVOKESPECIAL org/nlogo/nvm/EngineException.<init> (Lorg/nlogo/nvm/Context;Lorg/nlogo/nvm/Instruction;Ljava/lang/String;)V
          ATHROW
         L3
         FRAME APPEND [java/lang/Object java/lang/Object org/nlogo/agent/Agent]
          ALOAD 4
          BIPUSH 8
          INVOKEVIRTUAL org/nlogo/agent/Agent.getPatchVariable (I)Ljava/lang/Object;
         L4
          ASTORE 5
          GOTO L8
         L7
         FRAME CHOP 1
          ALOAD 3
          INSTANCEOF org/nlogo/agent/AgentSet
          IFEQ L9
          ALOAD 3
          CHECKCAST org/nlogo/agent/AgentSet
          ASTORE 7
          NEW org/nlogo/api/LogoListBuilder
          DUP
          INVOKESPECIAL org/nlogo/api/LogoListBuilder.<init> ()V
          ASTORE 8
         L0
          ALOAD 7
          ALOAD 1
          GETFIELD org/nlogo/nvm/Context.job : Lorg/nlogo/nvm/Job;
          GETFIELD org/nlogo/nvm/Job.random : Lorg/nlogo/api/MersenneTwisterFast;
          INVOKEVIRTUAL org/nlogo/agent/AgentSet.shufflerator (Lorg/nlogo/api/MersenneTwisterFast;)Lorg/nlogo/agent/AgentSet$Iterator;
          ASTORE 10
         L10
         FRAME FULL [org/nlogo/prim/_asm_procedureuphillnestscent_setprocedurevariable_1 org/nlogo/nvm/Context java/lang/Object java/lang/Object T T T org/nlogo/agent/AgentSet org/nlogo/api/LogoListBuilder T org/nlogo/agent/AgentSet$Iterator] []
          ALOAD 10
          INVOKEINTERFACE org/nlogo/agent/AgentSet$Iterator.hasNext ()Z
          IFEQ L1
          ALOAD 8
          ALOAD 10
          INVOKEINTERFACE org/nlogo/agent/AgentSet$Iterator.next ()Lorg/nlogo/agent/Agent;
          BIPUSH 8
          INVOKEVIRTUAL org/nlogo/agent/Agent.getPatchVariable (I)Ljava/lang/Object;
          INVOKEVIRTUAL org/nlogo/api/LogoListBuilder.add (Ljava/lang/Object;)V
          GOTO L10
         L1
         FRAME SAME
          ALOAD 8
          INVOKEVIRTUAL org/nlogo/api/LogoListBuilder.toLogoList ()Lorg/nlogo/core/LogoList;
          ASTORE 5
         L8
         FRAME FULL [org/nlogo/prim/_asm_procedureuphillnestscent_setprocedurevariable_1 org/nlogo/nvm/Context java/lang/Object java/lang/Object T java/lang/Object] []
          ALOAD 5
          GOTO L11
         L9
         FRAME CHOP 2
          NEW org/nlogo/nvm/ArgumentTypeException
          DUP
          ALOAD 1
          ALOAD 0
          ICONST_0
          GETSTATIC org/nlogo/core/Syntax$.MODULE$ : Lorg/nlogo/core/Syntax$;
          INVOKEVIRTUAL org/nlogo/core/Syntax$.TurtleType ()I
          GETSTATIC org/nlogo/core/Syntax$.MODULE$ : Lorg/nlogo/core/Syntax$;
          INVOKEVIRTUAL org/nlogo/core/Syntax$.PatchType ()I
          IOR
          GETSTATIC org/nlogo/core/Syntax$.MODULE$ : Lorg/nlogo/core/Syntax$;
          INVOKEVIRTUAL org/nlogo/core/Syntax$.TurtlesetType ()I
          IOR
          GETSTATIC org/nlogo/core/Syntax$.MODULE$ : Lorg/nlogo/core/Syntax$;
          INVOKEVIRTUAL org/nlogo/core/Syntax$.PatchsetType ()I
          IOR
          ALOAD 2
          INVOKESPECIAL org/nlogo/nvm/ArgumentTypeException.<init> (Lorg/nlogo/nvm/Context;Lorg/nlogo/nvm/Instruction;IILjava/lang/Object;)V
          ATHROW
         L5
         FRAME FULL [org/nlogo/prim/_asm_procedureuphillnestscent_setprocedurevariable_1 org/nlogo/nvm/Context java/lang/Object java/lang/Object org/nlogo/agent/Agent] [org/nlogo/api/AgentException]
          ASTORE 6
          NEW org/nlogo/nvm/EngineException
          DUP
          ALOAD 1
          ALOAD 0
          ALOAD 6
          INVOKEVIRTUAL org/nlogo/api/AgentException.getMessage ()Ljava/lang/String;
          INVOKESPECIAL org/nlogo/nvm/EngineException.<init> (Lorg/nlogo/nvm/Context;Lorg/nlogo/nvm/Instruction;Ljava/lang/String;)V
          ATHROW
         L2
         FRAME FULL [org/nlogo/prim/_asm_procedureuphillnestscent_setprocedurevariable_1 org/nlogo/nvm/Context java/lang/Object java/lang/Object T T T org/nlogo/agent/AgentSet org/nlogo/api/LogoListBuilder] [org/nlogo/api/AgentException]
          ASTORE 9
          NEW org/nlogo/nvm/EngineException
          DUP
          ALOAD 1
          ALOAD 0
          ALOAD 9
          INVOKEVIRTUAL org/nlogo/api/AgentException.getMessage ()Ljava/lang/String;
          INVOKESPECIAL org/nlogo/nvm/EngineException.<init> (Lorg/nlogo/nvm/Context;Lorg/nlogo/nvm/Instruction;Ljava/lang/String;)V
          ATHROW
         L11
         FRAME FULL [org/nlogo/prim/_asm_procedureuphillnestscent_setprocedurevariable_1 org/nlogo/nvm/Context java/lang/Object java/lang/Object T java/lang/Object] [java/lang/Object]
          ASTORE 2
          ALOAD 1
          GETFIELD org/nlogo/nvm/Context.activation : Lorg/nlogo/nvm/Activation;
          GETFIELD org/nlogo/nvm/Activation.args : [Ljava/lang/Object;
          ICONST_0
          ALOAD 2
          AASTORE
          ALOAD 1
          ICONST_2
          PUTFIELD org/nlogo/nvm/Context.ip : I
         L12
          RETURN
[2]_asm_procedureuphillnestscent_setprocedurevariable_3 "let get-nest-scent 45" Object => void
      _callreport:GET-NEST-SCENT "get-nest-scent 45"
        _constdouble:45.0 "45" => Double
         L0
          NEW org/nlogo/nvm/Activation
          DUP
          ALOAD 0
          GETFIELD org/nlogo/prim/_asm_procedureuphillnestscent_setprocedurevariable_3.kept2_procedure : Lorg/nlogo/nvm/Procedure;
          ALOAD 1
          GETFIELD org/nlogo/nvm/Context.activation : Lorg/nlogo/nvm/Activation;
          ICONST_2
          INVOKESPECIAL org/nlogo/nvm/Activation.<init> (Lorg/nlogo/nvm/Procedure;Lorg/nlogo/nvm/Activation;I)V
          DUP
          GETFIELD org/nlogo/nvm/Activation.args : [Ljava/lang/Object;
          ICONST_0
         L1
          ALOAD 0
          GETFIELD org/nlogo/prim/_asm_procedureuphillnestscent_setprocedurevariable_3.kept3_value : Ljava/lang/Double;
         L2
          AASTORE
          ALOAD 1
          SWAP
          INVOKEVIRTUAL org/nlogo/nvm/Context.callReporterProcedure (Lorg/nlogo/nvm/Activation;)Ljava/lang/Object;
          DUP
          IFNONNULL L3
          NEW org/nlogo/nvm/EngineException
          DUP
          ALOAD 1
          ALOAD 0
          LDC "the GET-NEST-SCENT procedure failed to report a result"
          INVOKESPECIAL org/nlogo/nvm/EngineException.<init> (Lorg/nlogo/nvm/Context;Lorg/nlogo/nvm/Instruction;Ljava/lang/String;)V
          ATHROW
         L3
         FRAME SAME1 java/lang/Object
          ASTORE 2
          ALOAD 1
          GETFIELD org/nlogo/nvm/Context.activation : Lorg/nlogo/nvm/Activation;
          GETFIELD org/nlogo/nvm/Activation.args : [Ljava/lang/Object;
          ICONST_1
          ALOAD 2
          AASTORE
          ALOAD 1
          ICONST_3
          PUTFIELD org/nlogo/nvm/Context.ip : I
         L4
          RETURN
[3]_asm_procedureuphillnestscent_setprocedurevariable_4 "let get-nest-scent -45" Object => void
      _callreport:GET-NEST-SCENT "get-nest-scent -45"
        _constdouble:-45.0 "-45" => Double
         L0
          NEW org/nlogo/nvm/Activation
          DUP
          ALOAD 0
          GETFIELD org/nlogo/prim/_asm_procedureuphillnestscent_setprocedurevariable_4.kept2_procedure : Lorg/nlogo/nvm/Procedure;
          ALOAD 1
          GETFIELD org/nlogo/nvm/Context.activation : Lorg/nlogo/nvm/Activation;
          ICONST_3
          INVOKESPECIAL org/nlogo/nvm/Activation.<init> (Lorg/nlogo/nvm/Procedure;Lorg/nlogo/nvm/Activation;I)V
          DUP
          GETFIELD org/nlogo/nvm/Activation.args : [Ljava/lang/Object;
          ICONST_0
         L1
          ALOAD 0
          GETFIELD org/nlogo/prim/_asm_procedureuphillnestscent_setprocedurevariable_4.kept3_value : Ljava/lang/Double;
         L2
          AASTORE
          ALOAD 1
          SWAP
          INVOKEVIRTUAL org/nlogo/nvm/Context.callReporterProcedure (Lorg/nlogo/nvm/Activation;)Ljava/lang/Object;
          DUP
          IFNONNULL L3
          NEW org/nlogo/nvm/EngineException
          DUP
          ALOAD 1
          ALOAD 0
          LDC "the GET-NEST-SCENT procedure failed to report a result"
          INVOKESPECIAL org/nlogo/nvm/EngineException.<init> (Lorg/nlogo/nvm/Context;Lorg/nlogo/nvm/Instruction;Ljava/lang/String;)V
          ATHROW
         L3
         FRAME SAME1 java/lang/Object
          ASTORE 2
          ALOAD 1
          GETFIELD org/nlogo/nvm/Context.activation : Lorg/nlogo/nvm/Activation;
          GETFIELD org/nlogo/nvm/Activation.args : [Ljava/lang/Object;
          ICONST_2
          ALOAD 2
          AASTORE
          ALOAD 1
          ICONST_4
          PUTFIELD org/nlogo/nvm/Context.ip : I
         L4
          RETURN
[4]_asm_procedureuphillnestscent_if_5 "if scent-right > scent-ahead or scent-left > scent-ahead [ ifelse scent-right > scent-left [ rt 45 ] [ lt 45 ] ]" boolean => void
      _or "scent-right > scent-ahead or scent-left > scent-ahead"
        _greaterthan "scent-right > scent-ahead" Object,Object => boolean
          _procedurevariable:SCENT-RIGHT "scent-right" => Object
          _procedurevariable:SCENT-AHEAD "scent-ahead" => Object
        _greaterthan "scent-left > scent-ahead" Object,Object => boolean
          _procedurevariable:SCENT-LEFT "scent-left" => Object
          _procedurevariable:SCENT-AHEAD "scent-ahead" => Object
         L0
          ALOAD 1
          GETFIELD org/nlogo/nvm/Context.activation : Lorg/nlogo/nvm/Activation;
          GETFIELD org/nlogo/nvm/Activation.args : [Ljava/lang/Object;
          ICONST_1
          AALOAD
         L1
          ALOAD 1
          GETFIELD org/nlogo/nvm/Context.activation : Lorg/nlogo/nvm/Activation;
          GETFIELD org/nlogo/nvm/Activation.args : [Ljava/lang/Object;
          ICONST_0
          AALOAD
         L2
          ASTORE 3
          ASTORE 2
          ALOAD 2
          INSTANCEOF java/lang/Double
          IFEQ L3
          ALOAD 3
          INSTANCEOF java/lang/Double
          IFEQ L3
          ALOAD 2
          CHECKCAST java/lang/Double
          INVOKEVIRTUAL java/lang/Double.doubleValue ()D
          ALOAD 3
          CHECKCAST java/lang/Double
          INVOKEVIRTUAL java/lang/Double.doubleValue ()D
          DCMPL
          IFLE L4
          ICONST_1
          GOTO L5
         L4
         FRAME APPEND [java/lang/Object java/lang/Object]
          ICONST_0
         L5
         FRAME SAME1 I
          GOTO L6
         L3
         FRAME SAME
          ALOAD 2
          INSTANCEOF java/lang/String
          IFEQ L7
          ALOAD 3
          INSTANCEOF java/lang/String
          IFEQ L7
          ALOAD 2
          CHECKCAST java/lang/String
          ALOAD 3
          CHECKCAST java/lang/String
          INVOKEVIRTUAL java/lang/String.compareTo (Ljava/lang/String;)I
          IFLE L8
          ICONST_1
          GOTO L9
         L8
         FRAME SAME
          ICONST_0
         L9
         FRAME SAME1 I
          GOTO L6
         L7
         FRAME SAME
          ALOAD 2
          INSTANCEOF org/nlogo/agent/Agent
          IFEQ L10
          ALOAD 3
          INSTANCEOF org/nlogo/agent/Agent
          IFEQ L10
          ALOAD 2
          CHECKCAST org/nlogo/agent/Agent
          ASTORE 4
          ALOAD 3
          CHECKCAST org/nlogo/agent/Agent
          ASTORE 5
          ALOAD 4
          INVOKEVIRTUAL org/nlogo/agent/Agent.getAgentBit ()I
          ALOAD 5
          INVOKEVIRTUAL org/nlogo/agent/Agent.getAgentBit ()I
          IF_ICMPNE L10
          ALOAD 4
          ALOAD 5
          INVOKEVIRTUAL org/nlogo/agent/Agent.compareTo (Lorg/nlogo/agent/Agent;)I
          IFLE L11
          ICONST_1
          GOTO L12
         L11
         FRAME APPEND [org/nlogo/agent/Agent org/nlogo/agent/Agent]
          ICONST_0
         L12
         FRAME SAME1 I
          GOTO L6
         L10
         FRAME CHOP 2
          NEW org/nlogo/nvm/EngineException
          DUP
          ALOAD 1
          ALOAD 0
          INVOKESTATIC org/nlogo/core/I18N.errorsJ ()Lorg/nlogo/core/I18NJava;
          LDC "org.nlogo.prim._greaterthan.cannotCompareParameters"
          ICONST_2
          ANEWARRAY java/lang/Object
          DUP
          ICONST_0
          ALOAD 2
          INVOKESTATIC org/nlogo/api/TypeNames.aName (Ljava/lang/Object;)Ljava/lang/String;
          AASTORE
          DUP
          ICONST_1
          ALOAD 3
          INVOKESTATIC org/nlogo/api/TypeNames.aName (Ljava/lang/Object;)Ljava/lang/String;
          AASTORE
          INVOKEINTERFACE org/nlogo/core/I18NJava.getN (Ljava/lang/String;[Ljava/lang/Object;)Ljava/lang/String;
          INVOKESPECIAL org/nlogo/nvm/EngineException.<init> (Lorg/nlogo/nvm/Context;Lorg/nlogo/nvm/Instruction;Ljava/lang/String;)V
          ATHROW
         L6
         FRAME SAME1 I
          IFNE L13
         L14
          ALOAD 1
          GETFIELD org/nlogo/nvm/Context.activation : Lorg/nlogo/nvm/Activation;
          GETFIELD org/nlogo/nvm/Activation.args : [Ljava/lang/Object;
          ICONST_2
          AALOAD
         L15
          ALOAD 1
          GETFIELD org/nlogo/nvm/Context.activation : Lorg/nlogo/nvm/Activation;
          GETFIELD org/nlogo/nvm/Activation.args : [Ljava/lang/Object;
          ICONST_0
          AALOAD
         L16
          ASTORE 3
          ASTORE 2
          ALOAD 2
          INSTANCEOF java/lang/Double
          IFEQ L17
          ALOAD 3
          INSTANCEOF java/lang/Double
          IFEQ L17
          ALOAD 2
          CHECKCAST java/lang/Double
          INVOKEVIRTUAL java/lang/Double.doubleValue ()D
          ALOAD 3
          CHECKCAST java/lang/Double
          INVOKEVIRTUAL java/lang/Double.doubleValue ()D
          DCMPL
          IFLE L18
          ICONST_1
          GOTO L19
         L18
         FRAME SAME
          ICONST_0
         L19
         FRAME SAME1 I
          GOTO L20
         L17
         FRAME SAME
          ALOAD 2
          INSTANCEOF java/lang/String
          IFEQ L21
          ALOAD 3
          INSTANCEOF java/lang/String
          IFEQ L21
          ALOAD 2
          CHECKCAST java/lang/String
          ALOAD 3
          CHECKCAST java/lang/String
          INVOKEVIRTUAL java/lang/String.compareTo (Ljava/lang/String;)I
          IFLE L22
          ICONST_1
          GOTO L23
         L22
         FRAME SAME
          ICONST_0
         L23
         FRAME SAME1 I
          GOTO L20
         L21
         FRAME SAME
          ALOAD 2
          INSTANCEOF org/nlogo/agent/Agent
          IFEQ L24
          ALOAD 3
          INSTANCEOF org/nlogo/agent/Agent
          IFEQ L24
          ALOAD 2
          CHECKCAST org/nlogo/agent/Agent
          ASTORE 4
          ALOAD 3
          CHECKCAST org/nlogo/agent/Agent
          ASTORE 5
          ALOAD 4
          INVOKEVIRTUAL org/nlogo/agent/Agent.getAgentBit ()I
          ALOAD 5
          INVOKEVIRTUAL org/nlogo/agent/Agent.getAgentBit ()I
          IF_ICMPNE L24
          ALOAD 4
          ALOAD 5
          INVOKEVIRTUAL org/nlogo/agent/Agent.compareTo (Lorg/nlogo/agent/Agent;)I
          IFLE L25
          ICONST_1
          GOTO L26
         L25
         FRAME APPEND [org/nlogo/agent/Agent org/nlogo/agent/Agent]
          ICONST_0
         L26
         FRAME SAME1 I
          GOTO L20
         L24
         FRAME CHOP 2
          NEW org/nlogo/nvm/EngineException
          DUP
          ALOAD 1
          ALOAD 0
          INVOKESTATIC org/nlogo/core/I18N.errorsJ ()Lorg/nlogo/core/I18NJava;
          LDC "org.nlogo.prim._greaterthan.cannotCompareParameters"
          ICONST_2
          ANEWARRAY java/lang/Object
          DUP
          ICONST_0
          ALOAD 2
          INVOKESTATIC org/nlogo/api/TypeNames.aName (Ljava/lang/Object;)Ljava/lang/String;
          AASTORE
          DUP
          ICONST_1
          ALOAD 3
          INVOKESTATIC org/nlogo/api/TypeNames.aName (Ljava/lang/Object;)Ljava/lang/String;
          AASTORE
          INVOKEINTERFACE org/nlogo/core/I18NJava.getN (Ljava/lang/String;[Ljava/lang/Object;)Ljava/lang/String;
          INVOKESPECIAL org/nlogo/nvm/EngineException.<init> (Lorg/nlogo/nvm/Context;Lorg/nlogo/nvm/Instruction;Ljava/lang/String;)V
          ATHROW
         L20
         FRAME SAME1 I
          GOTO L27
         L13
         FRAME SAME
          ICONST_1
         L27
         FRAME SAME1 I
          ISTORE 2
          ALOAD 1
          ILOAD 2
          IFEQ L28
          ICONST_5
          GOTO L29
         L28
         FRAME FULL [org/nlogo/prim/_asm_procedureuphillnestscent_if_5 org/nlogo/nvm/Context I java/lang/Object] [org/nlogo/nvm/Context]
          BIPUSH 9
         L29
         FRAME FULL [org/nlogo/prim/_asm_procedureuphillnestscent_if_5 org/nlogo/nvm/Context I java/lang/Object] [org/nlogo/nvm/Context I]
          PUTFIELD org/nlogo/nvm/Context.ip : I
         L30
          RETURN
[5]_asm_procedureuphillnestscent_ifelse_6 "ifelse scent-right > scent-left [ rt 45 ] [ lt 45 ]" boolean => void
      _greaterthan "scent-right > scent-left" Object,Object => boolean
        _procedurevariable:SCENT-RIGHT "scent-right" => Object
        _procedurevariable:SCENT-LEFT "scent-left" => Object
         L0
          ALOAD 1
          GETFIELD org/nlogo/nvm/Context.activation : Lorg/nlogo/nvm/Activation;
          GETFIELD org/nlogo/nvm/Activation.args : [Ljava/lang/Object;
          ICONST_1
          AALOAD
         L1
          ALOAD 1
          GETFIELD org/nlogo/nvm/Context.activation : Lorg/nlogo/nvm/Activation;
          GETFIELD org/nlogo/nvm/Activation.args : [Ljava/lang/Object;
          ICONST_2
          AALOAD
         L2
          ASTORE 3
          ASTORE 2
          ALOAD 2
          INSTANCEOF java/lang/Double
          IFEQ L3
          ALOAD 3
          INSTANCEOF java/lang/Double
          IFEQ L3
          ALOAD 2
          CHECKCAST java/lang/Double
          INVOKEVIRTUAL java/lang/Double.doubleValue ()D
          ALOAD 3
          CHECKCAST java/lang/Double
          INVOKEVIRTUAL java/lang/Double.doubleValue ()D
          DCMPL
          IFLE L4
          ICONST_1
          GOTO L5
         L4
         FRAME APPEND [java/lang/Object java/lang/Object]
          ICONST_0
         L5
         FRAME SAME1 I
          GOTO L6
         L3
         FRAME SAME
          ALOAD 2
          INSTANCEOF java/lang/String
          IFEQ L7
          ALOAD 3
          INSTANCEOF java/lang/String
          IFEQ L7
          ALOAD 2
          CHECKCAST java/lang/String
          ALOAD 3
          CHECKCAST java/lang/String
          INVOKEVIRTUAL java/lang/String.compareTo (Ljava/lang/String;)I
          IFLE L8
          ICONST_1
          GOTO L9
         L8
         FRAME SAME
          ICONST_0
         L9
         FRAME SAME1 I
          GOTO L6
         L7
         FRAME SAME
          ALOAD 2
          INSTANCEOF org/nlogo/agent/Agent
          IFEQ L10
          ALOAD 3
          INSTANCEOF org/nlogo/agent/Agent
          IFEQ L10
          ALOAD 2
          CHECKCAST org/nlogo/agent/Agent
          ASTORE 4
          ALOAD 3
          CHECKCAST org/nlogo/agent/Agent
          ASTORE 5
          ALOAD 4
          INVOKEVIRTUAL org/nlogo/agent/Agent.getAgentBit ()I
          ALOAD 5
          INVOKEVIRTUAL org/nlogo/agent/Agent.getAgentBit ()I
          IF_ICMPNE L10
          ALOAD 4
          ALOAD 5
          INVOKEVIRTUAL org/nlogo/agent/Agent.compareTo (Lorg/nlogo/agent/Agent;)I
          IFLE L11
          ICONST_1
          GOTO L12
         L11
         FRAME APPEND [org/nlogo/agent/Agent org/nlogo/agent/Agent]
          ICONST_0
         L12
         FRAME SAME1 I
          GOTO L6
         L10
         FRAME CHOP 2
          NEW org/nlogo/nvm/EngineException
          DUP
          ALOAD 1
          ALOAD 0
          INVOKESTATIC org/nlogo/core/I18N.errorsJ ()Lorg/nlogo/core/I18NJava;
          LDC "org.nlogo.prim._greaterthan.cannotCompareParameters"
          ICONST_2
          ANEWARRAY java/lang/Object
          DUP
          ICONST_0
          ALOAD 2
          INVOKESTATIC org/nlogo/api/TypeNames.aName (Ljava/lang/Object;)Ljava/lang/String;
          AASTORE
          DUP
          ICONST_1
          ALOAD 3
          INVOKESTATIC org/nlogo/api/TypeNames.aName (Ljava/lang/Object;)Ljava/lang/String;
          AASTORE
          INVOKEINTERFACE org/nlogo/core/I18NJava.getN (Ljava/lang/String;[Ljava/lang/Object;)Ljava/lang/String;
          INVOKESPECIAL org/nlogo/nvm/EngineException.<init> (Lorg/nlogo/nvm/Context;Lorg/nlogo/nvm/Instruction;Ljava/lang/String;)V
          ATHROW
         L6
         FRAME SAME1 I
          ISTORE 2
          ALOAD 1
          ILOAD 2
          IFEQ L13
          BIPUSH 6
          GOTO L14
         L13
         FRAME FULL [org/nlogo/prim/_asm_procedureuphillnestscent_ifelse_6 org/nlogo/nvm/Context I java/lang/Object] [org/nlogo/nvm/Context]
          BIPUSH 8
         L14
         FRAME FULL [org/nlogo/prim/_asm_procedureuphillnestscent_ifelse_6 org/nlogo/nvm/Context I java/lang/Object] [org/nlogo/nvm/Context I]
          PUTFIELD org/nlogo/nvm/Context.ip : I
         L15
          RETURN
[6]_asm_procedureuphillnestscent_right_7 "rt 45" double => void
      _constdouble:45.0 "45" => double
         L0
          LDC 45.0
         L1
          DSTORE 2
          ALOAD 1
          GETFIELD org/nlogo/nvm/Context.agent : Lorg/nlogo/agent/Agent;
          CHECKCAST org/nlogo/agent/Turtle
          DLOAD 2
          INVOKEVIRTUAL org/nlogo/agent/Turtle.turnRight (D)V
          ALOAD 1
          BIPUSH 7
          PUTFIELD org/nlogo/nvm/Context.ip : I
         L2
          RETURN
[7]_asm_procedureuphillnestscent_goto_8 => void
         L0
          ALOAD 1
          BIPUSH 9
          PUTFIELD org/nlogo/nvm/Context.ip : I
         L1
          RETURN
[8]_asm_procedureuphillnestscent_left_9 "lt 45" double => void
      _constdouble:45.0 "45" => double
         L0
          LDC 45.0
         L1
          DSTORE 2
          ALOAD 1
          GETFIELD org/nlogo/nvm/Context.agent : Lorg/nlogo/agent/Agent;
          CHECKCAST org/nlogo/agent/Turtle
          DLOAD 2
          DNEG
          INVOKEVIRTUAL org/nlogo/agent/Turtle.turnRight (D)V
          ALOAD 1
          BIPUSH 9
          PUTFIELD org/nlogo/nvm/Context.ip : I
         L2
          RETURN
[9]_asm_procedureuphillnestscent_return_10 => void
         L0
          ALOAD 1
          INVOKEVIRTUAL org/nlogo/nvm/Context.returnFromProcedure ()V
          ALOAD 1
          ICONST_0
          PUTFIELD org/nlogo/nvm/Context.stopping : Z
         L1
          RETURN

procedure UPHILL-CHEMICAL:[SCENT-AHEAD SCENT-RIGHT SCENT-LEFT]{-T--}:
[0]_asm_procedureuphillchemical_call_0 "wiggle"
         L0
          NEW org/nlogo/nvm/Activation
          DUP
          ALOAD 0
          GETFIELD org/nlogo/prim/_asm_procedureuphillchemical_call_0.kept1_procedure : Lorg/nlogo/nvm/Procedure;
          ALOAD 1
          GETFIELD org/nlogo/nvm/Context.activation : Lorg/nlogo/nvm/Activation;
          ICONST_1
          INVOKESPECIAL org/nlogo/nvm/Activation.<init> (Lorg/nlogo/nvm/Procedure;Lorg/nlogo/nvm/Activation;I)V
          ALOAD 1
          SWAP
          PUTFIELD org/nlogo/nvm/Context.activation : Lorg/nlogo/nvm/Activation;
          ALOAD 1
          ICONST_0
          PUTFIELD org/nlogo/nvm/Context.ip : I
         L1
          RETURN
[1]_asm_procedureuphillchemical_setprocedurevariable_1 "let [ chemical ] of patch-ahead 1" Object => void
      _patchvariableof:CHEMICAL "[ chemical ] of patch-ahead 1" Object => Object
        _patchahead "patch-ahead 1"
          _asm_procedureuphillchemical_constdouble_2 "1" => Double
               L0
                ALOAD 0
                GETFIELD org/nlogo/prim/_asm_procedureuphillchemical_constdouble_2.kept1_value : Ljava/lang/Double;
               L1
                ARETURN
          TRYCATCHBLOCK L0 L1 L2 org/nlogo/api/AgentException
          TRYCATCHBLOCK L3 L4 L5 org/nlogo/api/AgentException
          ALOAD 0
          GETFIELD org/nlogo/prim/_asm_procedureuphillchemical_setprocedurevariable_1.keptinstr3 : Lorg/nlogo/prim/etc/_patchahead;
          ALOAD 1
          INVOKEVIRTUAL org/nlogo/prim/etc/_patchahead.report (Lorg/nlogo/nvm/Context;)Ljava/lang/Object;
         L6
          ASTORE 2
          ALOAD 2
          ASTORE 3
          ALOAD 3
          INSTANCEOF org/nlogo/agent/Agent
          IFEQ L7
          ALOAD 3
          CHECKCAST org/nlogo/agent/Agent
          ASTORE 4
          ALOAD 4
          GETFIELD org/nlogo/agent/Agent.id : J
          LDC -1
          LCMP
          IFNE L3
          NEW org/nlogo/nvm/EngineException
          DUP
          ALOAD 1
          ALOAD 0
          GETSTATIC org/nlogo/core/I18N$.MODULE$ : Lorg/nlogo/core/I18N$;
          INVOKEVIRTUAL org/nlogo/core/I18N$.errors ()Lorg/nlogo/core/I18N$BundleKind;
          LDC "org.nlogo.$common.thatAgentIsDead"
          GETSTATIC scala/Predef$.MODULE$ : Lscala/Predef$;
          ICONST_1
          ANEWARRAY java/lang/Object
          DUP
          ICONST_0
          ALOAD 4
          INVOKEVIRTUAL org/nlogo/agent/Agent.classDisplayName ()Ljava/lang/String;
          AASTORE
          INVOKEVIRTUAL scala/Predef$.wrapRefArray ([Ljava/lang/Object;)Lscala/collection/mutable/WrappedArray;
          INVOKEVIRTUAL org/nlogo/core/I18N$BundleKind.getN (Ljava/lang/String;Lscala/collection/Seq;)Ljava/lang/String;
          INVOKESPECIAL org/nlogo/nvm/EngineException.<init> (Lorg/nlogo/nvm/Context;Lorg/nlogo/nvm/Instruction;Ljava/lang/String;)V
          ATHROW
         L3
         FRAME APPEND [java/lang/Object java/lang/Object org/nlogo/agent/Agent]
          ALOAD 4
          ICONST_5
          INVOKEVIRTUAL org/nlogo/agent/Agent.getPatchVariable (I)Ljava/lang/Object;
         L4
          ASTORE 5
          GOTO L8
         L7
         FRAME CHOP 1
          ALOAD 3
          INSTANCEOF org/nlogo/agent/AgentSet
          IFEQ L9
          ALOAD 3
          CHECKCAST org/nlogo/agent/AgentSet
          ASTORE 7
          NEW org/nlogo/api/LogoListBuilder
          DUP
          INVOKESPECIAL org/nlogo/api/LogoListBuilder.<init> ()V
          ASTORE 8
         L0
          ALOAD 7
          ALOAD 1
          GETFIELD org/nlogo/nvm/Context.job : Lorg/nlogo/nvm/Job;
          GETFIELD org/nlogo/nvm/Job.random : Lorg/nlogo/api/MersenneTwisterFast;
          INVOKEVIRTUAL org/nlogo/agent/AgentSet.shufflerator (Lorg/nlogo/api/MersenneTwisterFast;)Lorg/nlogo/agent/AgentSet$Iterator;
          ASTORE 10
         L10
         FRAME FULL [org/nlogo/prim/_asm_procedureuphillchemical_setprocedurevariable_1 org/nlogo/nvm/Context java/lang/Object java/lang/Object T T T org/nlogo/agent/AgentSet org/nlogo/api/LogoListBuilder T org/nlogo/agent/AgentSet$Iterator] []
          ALOAD 10
          INVOKEINTERFACE org/nlogo/agent/AgentSet$Iterator.hasNext ()Z
          IFEQ L1
          ALOAD 8
          ALOAD 10
          INVOKEINTERFACE org/nlogo/agent/AgentSet$Iterator.next ()Lorg/nlogo/agent/Agent;
          ICONST_5
          INVOKEVIRTUAL org/nlogo/agent/Agent.getPatchVariable (I)Ljava/lang/Object;
          INVOKEVIRTUAL org/nlogo/api/LogoListBuilder.add (Ljava/lang/Object;)V
          GOTO L10
         L1
         FRAME SAME
          ALOAD 8
          INVOKEVIRTUAL org/nlogo/api/LogoListBuilder.toLogoList ()Lorg/nlogo/core/LogoList;
          ASTORE 5
         L8
         FRAME FULL [org/nlogo/prim/_asm_procedureuphillchemical_setprocedurevariable_1 org/nlogo/nvm/Context java/lang/Object java/lang/Object T java/lang/Object] []
          ALOAD 5
          GOTO L11
         L9
         FRAME CHOP 2
          NEW org/nlogo/nvm/ArgumentTypeException
          DUP
          ALOAD 1
          ALOAD 0
          ICONST_0
          GETSTATIC org/nlogo/core/Syntax$.MODULE$ : Lorg/nlogo/core/Syntax$;
          INVOKEVIRTUAL org/nlogo/core/Syntax$.TurtleType ()I
          GETSTATIC org/nlogo/core/Syntax$.MODULE$ : Lorg/nlogo/core/Syntax$;
          INVOKEVIRTUAL org/nlogo/core/Syntax$.PatchType ()I
          IOR
          GETSTATIC org/nlogo/core/Syntax$.MODULE$ : Lorg/nlogo/core/Syntax$;
          INVOKEVIRTUAL org/nlogo/core/Syntax$.TurtlesetType ()I
          IOR
          GETSTATIC org/nlogo/core/Syntax$.MODULE$ : Lorg/nlogo/core/Syntax$;
          INVOKEVIRTUAL org/nlogo/core/Syntax$.PatchsetType ()I
          IOR
          ALOAD 2
          INVOKESPECIAL org/nlogo/nvm/ArgumentTypeException.<init> (Lorg/nlogo/nvm/Context;Lorg/nlogo/nvm/Instruction;IILjava/lang/Object;)V
          ATHROW
         L5
         FRAME FULL [org/nlogo/prim/_asm_procedureuphillchemical_setprocedurevariable_1 org/nlogo/nvm/Context java/lang/Object java/lang/Object org/nlogo/agent/Agent] [org/nlogo/api/AgentException]
          ASTORE 6
          NEW org/nlogo/nvm/EngineException
          DUP
          ALOAD 1
          ALOAD 0
          ALOAD 6
          INVOKEVIRTUAL org/nlogo/api/AgentException.getMessage ()Ljava/lang/String;
          INVOKESPECIAL org/nlogo/nvm/EngineException.<init> (Lorg/nlogo/nvm/Context;Lorg/nlogo/nvm/Instruction;Ljava/lang/String;)V
          ATHROW
         L2
         FRAME FULL [org/nlogo/prim/_asm_procedureuphillchemical_setprocedurevariable_1 org/nlogo/nvm/Context java/lang/Object java/lang/Object T T T org/nlogo/agent/AgentSet org/nlogo/api/LogoListBuilder] [org/nlogo/api/AgentException]
          ASTORE 9
          NEW org/nlogo/nvm/EngineException
          DUP
          ALOAD 1
          ALOAD 0
          ALOAD 9
          INVOKEVIRTUAL org/nlogo/api/AgentException.getMessage ()Ljava/lang/String;
          INVOKESPECIAL org/nlogo/nvm/EngineException.<init> (Lorg/nlogo/nvm/Context;Lorg/nlogo/nvm/Instruction;Ljava/lang/String;)V
          ATHROW
         L11
         FRAME FULL [org/nlogo/prim/_asm_procedureuphillchemical_setprocedurevariable_1 org/nlogo/nvm/Context java/lang/Object java/lang/Object T java/lang/Object] [java/lang/Object]
          ASTORE 2
          ALOAD 1
          GETFIELD org/nlogo/nvm/Context.activation : Lorg/nlogo/nvm/Activation;
          GETFIELD org/nlogo/nvm/Activation.args : [Ljava/lang/Object;
          ICONST_0
          ALOAD 2
          AASTORE
          ALOAD 1
          ICONST_2
          PUTFIELD org/nlogo/nvm/Context.ip : I
         L12
          RETURN
[2]_asm_procedureuphillchemical_setprocedurevariable_3 "let chemical-scent 45" Object => void
      _callreport:CHEMICAL-SCENT "chemical-scent 45"
        _constdouble:45.0 "45" => Double
         L0
          NEW org/nlogo/nvm/Activation
          DUP
          ALOAD 0
          GETFIELD org/nlogo/prim/_asm_procedureuphillchemical_setprocedurevariable_3.kept2_procedure : Lorg/nlogo/nvm/Procedure;
          ALOAD 1
          GETFIELD org/nlogo/nvm/Context.activation : Lorg/nlogo/nvm/Activation;
          ICONST_2
          INVOKESPECIAL org/nlogo/nvm/Activation.<init> (Lorg/nlogo/nvm/Procedure;Lorg/nlogo/nvm/Activation;I)V
          DUP
          GETFIELD org/nlogo/nvm/Activation.args : [Ljava/lang/Object;
          ICONST_0
         L1
          ALOAD 0
          GETFIELD org/nlogo/prim/_asm_procedureuphillchemical_setprocedurevariable_3.kept3_value : Ljava/lang/Double;
         L2
          AASTORE
          ALOAD 1
          SWAP
          INVOKEVIRTUAL org/nlogo/nvm/Context.callReporterProcedure (Lorg/nlogo/nvm/Activation;)Ljava/lang/Object;
          DUP
          IFNONNULL L3
          NEW org/nlogo/nvm/EngineException
          DUP
          ALOAD 1
          ALOAD 0
          LDC "the CHEMICAL-SCENT procedure failed to report a result"
          INVOKESPECIAL org/nlogo/nvm/EngineException.<init> (Lorg/nlogo/nvm/Context;Lorg/nlogo/nvm/Instruction;Ljava/lang/String;)V
          ATHROW
         L3
         FRAME SAME1 java/lang/Object
          ASTORE 2
          ALOAD 1
          GETFIELD org/nlogo/nvm/Context.activation : Lorg/nlogo/nvm/Activation;
          GETFIELD org/nlogo/nvm/Activation.args : [Ljava/lang/Object;
          ICONST_1
          ALOAD 2
          AASTORE
          ALOAD 1
          ICONST_3
          PUTFIELD org/nlogo/nvm/Context.ip : I
         L4
          RETURN
[3]_asm_procedureuphillchemical_setprocedurevariable_4 "let chemical-scent -45" Object => void
      _callreport:CHEMICAL-SCENT "chemical-scent -45"
        _constdouble:-45.0 "-45" => Double
         L0
          NEW org/nlogo/nvm/Activation
          DUP
          ALOAD 0
          GETFIELD org/nlogo/prim/_asm_procedureuphillchemical_setprocedurevariable_4.kept2_procedure : Lorg/nlogo/nvm/Procedure;
          ALOAD 1
          GETFIELD org/nlogo/nvm/Context.activation : Lorg/nlogo/nvm/Activation;
          ICONST_3
          INVOKESPECIAL org/nlogo/nvm/Activation.<init> (Lorg/nlogo/nvm/Procedure;Lorg/nlogo/nvm/Activation;I)V
          DUP
          GETFIELD org/nlogo/nvm/Activation.args : [Ljava/lang/Object;
          ICONST_0
         L1
          ALOAD 0
          GETFIELD org/nlogo/prim/_asm_procedureuphillchemical_setprocedurevariable_4.kept3_value : Ljava/lang/Double;
         L2
          AASTORE
          ALOAD 1
          SWAP
          INVOKEVIRTUAL org/nlogo/nvm/Context.callReporterProcedure (Lorg/nlogo/nvm/Activation;)Ljava/lang/Object;
          DUP
          IFNONNULL L3
          NEW org/nlogo/nvm/EngineException
          DUP
          ALOAD 1
          ALOAD 0
          LDC "the CHEMICAL-SCENT procedure failed to report a result"
          INVOKESPECIAL org/nlogo/nvm/EngineException.<init> (Lorg/nlogo/nvm/Context;Lorg/nlogo/nvm/Instruction;Ljava/lang/String;)V
          ATHROW
         L3
         FRAME SAME1 java/lang/Object
          ASTORE 2
          ALOAD 1
          GETFIELD org/nlogo/nvm/Context.activation : Lorg/nlogo/nvm/Activation;
          GETFIELD org/nlogo/nvm/Activation.args : [Ljava/lang/Object;
          ICONST_2
          ALOAD 2
          AASTORE
          ALOAD 1
          ICONST_4
          PUTFIELD org/nlogo/nvm/Context.ip : I
         L4
          RETURN
[4]_asm_procedureuphillchemical_if_5 "if scent-right > scent-ahead or scent-left > scent-ahead [ ifelse scent-right > scent-left [ rt 45 ] [ lt 45 ] ]" boolean => void
      _or "scent-right > scent-ahead or scent-left > scent-ahead"
        _greaterthan "scent-right > scent-ahead" Object,Object => boolean
          _procedurevariable:SCENT-RIGHT "scent-right" => Object
          _procedurevariable:SCENT-AHEAD "scent-ahead" => Object
        _greaterthan "scent-left > scent-ahead" Object,Object => boolean
          _procedurevariable:SCENT-LEFT "scent-left" => Object
          _procedurevariable:SCENT-AHEAD "scent-ahead" => Object
         L0
          ALOAD 1
          GETFIELD org/nlogo/nvm/Context.activation : Lorg/nlogo/nvm/Activation;
          GETFIELD org/nlogo/nvm/Activation.args : [Ljava/lang/Object;
          ICONST_1
          AALOAD
         L1
          ALOAD 1
          GETFIELD org/nlogo/nvm/Context.activation : Lorg/nlogo/nvm/Activation;
          GETFIELD org/nlogo/nvm/Activation.args : [Ljava/lang/Object;
          ICONST_0
          AALOAD
         L2
          ASTORE 3
          ASTORE 2
          ALOAD 2
          INSTANCEOF java/lang/Double
          IFEQ L3
          ALOAD 3
          INSTANCEOF java/lang/Double
          IFEQ L3
          ALOAD 2
          CHECKCAST java/lang/Double
          INVOKEVIRTUAL java/lang/Double.doubleValue ()D
          ALOAD 3
          CHECKCAST java/lang/Double
          INVOKEVIRTUAL java/lang/Double.doubleValue ()D
          DCMPL
          IFLE L4
          ICONST_1
          GOTO L5
         L4
         FRAME APPEND [java/lang/Object java/lang/Object]
          ICONST_0
         L5
         FRAME SAME1 I
          GOTO L6
         L3
         FRAME SAME
          ALOAD 2
          INSTANCEOF java/lang/String
          IFEQ L7
          ALOAD 3
          INSTANCEOF java/lang/String
          IFEQ L7
          ALOAD 2
          CHECKCAST java/lang/String
          ALOAD 3
          CHECKCAST java/lang/String
          INVOKEVIRTUAL java/lang/String.compareTo (Ljava/lang/String;)I
          IFLE L8
          ICONST_1
          GOTO L9
         L8
         FRAME SAME
          ICONST_0
         L9
         FRAME SAME1 I
          GOTO L6
         L7
         FRAME SAME
          ALOAD 2
          INSTANCEOF org/nlogo/agent/Agent
          IFEQ L10
          ALOAD 3
          INSTANCEOF org/nlogo/agent/Agent
          IFEQ L10
          ALOAD 2
          CHECKCAST org/nlogo/agent/Agent
          ASTORE 4
          ALOAD 3
          CHECKCAST org/nlogo/agent/Agent
          ASTORE 5
          ALOAD 4
          INVOKEVIRTUAL org/nlogo/agent/Agent.getAgentBit ()I
          ALOAD 5
          INVOKEVIRTUAL org/nlogo/agent/Agent.getAgentBit ()I
          IF_ICMPNE L10
          ALOAD 4
          ALOAD 5
          INVOKEVIRTUAL org/nlogo/agent/Agent.compareTo (Lorg/nlogo/agent/Agent;)I
          IFLE L11
          ICONST_1
          GOTO L12
         L11
         FRAME APPEND [org/nlogo/agent/Agent org/nlogo/agent/Agent]
          ICONST_0
         L12
         FRAME SAME1 I
          GOTO L6
         L10
         FRAME CHOP 2
          NEW org/nlogo/nvm/EngineException
          DUP
          ALOAD 1
          ALOAD 0
          INVOKESTATIC org/nlogo/core/I18N.errorsJ ()Lorg/nlogo/core/I18NJava;
          LDC "org.nlogo.prim._greaterthan.cannotCompareParameters"
          ICONST_2
          ANEWARRAY java/lang/Object
          DUP
          ICONST_0
          ALOAD 2
          INVOKESTATIC org/nlogo/api/TypeNames.aName (Ljava/lang/Object;)Ljava/lang/String;
          AASTORE
          DUP
          ICONST_1
          ALOAD 3
          INVOKESTATIC org/nlogo/api/TypeNames.aName (Ljava/lang/Object;)Ljava/lang/String;
          AASTORE
          INVOKEINTERFACE org/nlogo/core/I18NJava.getN (Ljava/lang/String;[Ljava/lang/Object;)Ljava/lang/String;
          INVOKESPECIAL org/nlogo/nvm/EngineException.<init> (Lorg/nlogo/nvm/Context;Lorg/nlogo/nvm/Instruction;Ljava/lang/String;)V
          ATHROW
         L6
         FRAME SAME1 I
          IFNE L13
         L14
          ALOAD 1
          GETFIELD org/nlogo/nvm/Context.activation : Lorg/nlogo/nvm/Activation;
          GETFIELD org/nlogo/nvm/Activation.args : [Ljava/lang/Object;
          ICONST_2
          AALOAD
         L15
          ALOAD 1
          GETFIELD org/nlogo/nvm/Context.activation : Lorg/nlogo/nvm/Activation;
          GETFIELD org/nlogo/nvm/Activation.args : [Ljava/lang/Object;
          ICONST_0
          AALOAD
         L16
          ASTORE 3
          ASTORE 2
          ALOAD 2
          INSTANCEOF java/lang/Double
          IFEQ L17
          ALOAD 3
          INSTANCEOF java/lang/Double
          IFEQ L17
          ALOAD 2
          CHECKCAST java/lang/Double
          INVOKEVIRTUAL java/lang/Double.doubleValue ()D
          ALOAD 3
          CHECKCAST java/lang/Double
          INVOKEVIRTUAL java/lang/Double.doubleValue ()D
          DCMPL
          IFLE L18
          ICONST_1
          GOTO L19
         L18
         FRAME SAME
          ICONST_0
         L19
         FRAME SAME1 I
          GOTO L20
         L17
         FRAME SAME
          ALOAD 2
          INSTANCEOF java/lang/String
          IFEQ L21
          ALOAD 3
          INSTANCEOF java/lang/String
          IFEQ L21
          ALOAD 2
          CHECKCAST java/lang/String
          ALOAD 3
          CHECKCAST java/lang/String
          INVOKEVIRTUAL java/lang/String.compareTo (Ljava/lang/String;)I
          IFLE L22
          ICONST_1
          GOTO L23
         L22
         FRAME SAME
          ICONST_0
         L23
         FRAME SAME1 I
          GOTO L20
         L21
         FRAME SAME
          ALOAD 2
          INSTANCEOF org/nlogo/agent/Agent
          IFEQ L24
          ALOAD 3
          INSTANCEOF org/nlogo/agent/Agent
          IFEQ L24
          ALOAD 2
          CHECKCAST org/nlogo/agent/Agent
          ASTORE 4
          ALOAD 3
          CHECKCAST org/nlogo/agent/Agent
          ASTORE 5
          ALOAD 4
          INVOKEVIRTUAL org/nlogo/agent/Agent.getAgentBit ()I
          ALOAD 5
          INVOKEVIRTUAL org/nlogo/agent/Agent.getAgentBit ()I
          IF_ICMPNE L24
          ALOAD 4
          ALOAD 5
          INVOKEVIRTUAL org/nlogo/agent/Agent.compareTo (Lorg/nlogo/agent/Agent;)I
          IFLE L25
          ICONST_1
          GOTO L26
         L25
         FRAME APPEND [org/nlogo/agent/Agent org/nlogo/agent/Agent]
          ICONST_0
         L26
         FRAME SAME1 I
          GOTO L20
         L24
         FRAME CHOP 2
          NEW org/nlogo/nvm/EngineException
          DUP
          ALOAD 1
          ALOAD 0
          INVOKESTATIC org/nlogo/core/I18N.errorsJ ()Lorg/nlogo/core/I18NJava;
          LDC "org.nlogo.prim._greaterthan.cannotCompareParameters"
          ICONST_2
          ANEWARRAY java/lang/Object
          DUP
          ICONST_0
          ALOAD 2
          INVOKESTATIC org/nlogo/api/TypeNames.aName (Ljava/lang/Object;)Ljava/lang/String;
          AASTORE
          DUP
          ICONST_1
          ALOAD 3
          INVOKESTATIC org/nlogo/api/TypeNames.aName (Ljava/lang/Object;)Ljava/lang/String;
          AASTORE
          INVOKEINTERFACE org/nlogo/core/I18NJava.getN (Ljava/lang/String;[Ljava/lang/Object;)Ljava/lang/String;
          INVOKESPECIAL org/nlogo/nvm/EngineException.<init> (Lorg/nlogo/nvm/Context;Lorg/nlogo/nvm/Instruction;Ljava/lang/String;)V
          ATHROW
         L20
         FRAME SAME1 I
          GOTO L27
         L13
         FRAME SAME
          ICONST_1
         L27
         FRAME SAME1 I
          ISTORE 2
          ALOAD 1
          ILOAD 2
          IFEQ L28
          ICONST_5
          GOTO L29
         L28
         FRAME FULL [org/nlogo/prim/_asm_procedureuphillchemical_if_5 org/nlogo/nvm/Context I java/lang/Object] [org/nlogo/nvm/Context]
          BIPUSH 9
         L29
         FRAME FULL [org/nlogo/prim/_asm_procedureuphillchemical_if_5 org/nlogo/nvm/Context I java/lang/Object] [org/nlogo/nvm/Context I]
          PUTFIELD org/nlogo/nvm/Context.ip : I
         L30
          RETURN
[5]_asm_procedureuphillchemical_ifelse_6 "ifelse scent-right > scent-left [ rt 45 ] [ lt 45 ]" boolean => void
      _greaterthan "scent-right > scent-left" Object,Object => boolean
        _procedurevariable:SCENT-RIGHT "scent-right" => Object
        _procedurevariable:SCENT-LEFT "scent-left" => Object
         L0
          ALOAD 1
          GETFIELD org/nlogo/nvm/Context.activation : Lorg/nlogo/nvm/Activation;
          GETFIELD org/nlogo/nvm/Activation.args : [Ljava/lang/Object;
          ICONST_1
          AALOAD
         L1
          ALOAD 1
          GETFIELD org/nlogo/nvm/Context.activation : Lorg/nlogo/nvm/Activation;
          GETFIELD org/nlogo/nvm/Activation.args : [Ljava/lang/Object;
          ICONST_2
          AALOAD
         L2
          ASTORE 3
          ASTORE 2
          ALOAD 2
          INSTANCEOF java/lang/Double
          IFEQ L3
          ALOAD 3
          INSTANCEOF java/lang/Double
          IFEQ L3
          ALOAD 2
          CHECKCAST java/lang/Double
          INVOKEVIRTUAL java/lang/Double.doubleValue ()D
          ALOAD 3
          CHECKCAST java/lang/Double
          INVOKEVIRTUAL java/lang/Double.doubleValue ()D
          DCMPL
          IFLE L4
          ICONST_1
          GOTO L5
         L4
         FRAME APPEND [java/lang/Object java/lang/Object]
          ICONST_0
         L5
         FRAME SAME1 I
          GOTO L6
         L3
         FRAME SAME
          ALOAD 2
          INSTANCEOF java/lang/String
          IFEQ L7
          ALOAD 3
          INSTANCEOF java/lang/String
          IFEQ L7
          ALOAD 2
          CHECKCAST java/lang/String
          ALOAD 3
          CHECKCAST java/lang/String
          INVOKEVIRTUAL java/lang/String.compareTo (Ljava/lang/String;)I
          IFLE L8
          ICONST_1
          GOTO L9
         L8
         FRAME SAME
          ICONST_0
         L9
         FRAME SAME1 I
          GOTO L6
         L7
         FRAME SAME
          ALOAD 2
          INSTANCEOF org/nlogo/agent/Agent
          IFEQ L10
          ALOAD 3
          INSTANCEOF org/nlogo/agent/Agent
          IFEQ L10
          ALOAD 2
          CHECKCAST org/nlogo/agent/Agent
          ASTORE 4
          ALOAD 3
          CHECKCAST org/nlogo/agent/Agent
          ASTORE 5
          ALOAD 4
          INVOKEVIRTUAL org/nlogo/agent/Agent.getAgentBit ()I
          ALOAD 5
          INVOKEVIRTUAL org/nlogo/agent/Agent.getAgentBit ()I
          IF_ICMPNE L10
          ALOAD 4
          ALOAD 5
          INVOKEVIRTUAL org/nlogo/agent/Agent.compareTo (Lorg/nlogo/agent/Agent;)I
          IFLE L11
          ICONST_1
          GOTO L12
         L11
         FRAME APPEND [org/nlogo/agent/Agent org/nlogo/agent/Agent]
          ICONST_0
         L12
         FRAME SAME1 I
          GOTO L6
         L10
         FRAME CHOP 2
          NEW org/nlogo/nvm/EngineException
          DUP
          ALOAD 1
          ALOAD 0
          INVOKESTATIC org/nlogo/core/I18N.errorsJ ()Lorg/nlogo/core/I18NJava;
          LDC "org.nlogo.prim._greaterthan.cannotCompareParameters"
          ICONST_2
          ANEWARRAY java/lang/Object
          DUP
          ICONST_0
          ALOAD 2
          INVOKESTATIC org/nlogo/api/TypeNames.aName (Ljava/lang/Object;)Ljava/lang/String;
          AASTORE
          DUP
          ICONST_1
          ALOAD 3
          INVOKESTATIC org/nlogo/api/TypeNames.aName (Ljava/lang/Object;)Ljava/lang/String;
          AASTORE
          INVOKEINTERFACE org/nlogo/core/I18NJava.getN (Ljava/lang/String;[Ljava/lang/Object;)Ljava/lang/String;
          INVOKESPECIAL org/nlogo/nvm/EngineException.<init> (Lorg/nlogo/nvm/Context;Lorg/nlogo/nvm/Instruction;Ljava/lang/String;)V
          ATHROW
         L6
         FRAME SAME1 I
          ISTORE 2
          ALOAD 1
          ILOAD 2
          IFEQ L13
          BIPUSH 6
          GOTO L14
         L13
         FRAME FULL [org/nlogo/prim/_asm_procedureuphillchemical_ifelse_6 org/nlogo/nvm/Context I java/lang/Object] [org/nlogo/nvm/Context]
          BIPUSH 8
         L14
         FRAME FULL [org/nlogo/prim/_asm_procedureuphillchemical_ifelse_6 org/nlogo/nvm/Context I java/lang/Object] [org/nlogo/nvm/Context I]
          PUTFIELD org/nlogo/nvm/Context.ip : I
         L15
          RETURN
[6]_asm_procedureuphillchemical_right_7 "rt 45" double => void
      _constdouble:45.0 "45" => double
         L0
          LDC 45.0
         L1
          DSTORE 2
          ALOAD 1
          GETFIELD org/nlogo/nvm/Context.agent : Lorg/nlogo/agent/Agent;
          CHECKCAST org/nlogo/agent/Turtle
          DLOAD 2
          INVOKEVIRTUAL org/nlogo/agent/Turtle.turnRight (D)V
          ALOAD 1
          BIPUSH 7
          PUTFIELD org/nlogo/nvm/Context.ip : I
         L2
          RETURN
[7]_asm_procedureuphillchemical_goto_8 => void
         L0
          ALOAD 1
          BIPUSH 9
          PUTFIELD org/nlogo/nvm/Context.ip : I
         L1
          RETURN
[8]_asm_procedureuphillchemical_left_9 "lt 45" double => void
      _constdouble:45.0 "45" => double
         L0
          LDC 45.0
         L1
          DSTORE 2
          ALOAD 1
          GETFIELD org/nlogo/nvm/Context.agent : Lorg/nlogo/agent/Agent;
          CHECKCAST org/nlogo/agent/Turtle
          DLOAD 2
          DNEG
          INVOKEVIRTUAL org/nlogo/agent/Turtle.turnRight (D)V
          ALOAD 1
          BIPUSH 9
          PUTFIELD org/nlogo/nvm/Context.ip : I
         L2
          RETURN
[9]_asm_procedureuphillchemical_return_10 => void
         L0
          ALOAD 1
          INVOKEVIRTUAL org/nlogo/nvm/Context.returnFromProcedure ()V
          ALOAD 1
          ICONST_0
          PUTFIELD org/nlogo/nvm/Context.stopping : Z
         L1
          RETURN

procedure GO-PATCHES:[]{-TP-}:
[0]_asm_proceduregopatches_setpatchvariable_0 "set chemical chemical * 100 - evaporation-rate / 100" Object => void
      _div "chemical * 100 - evaporation-rate / 100" double,double => double
        _mult "chemical * 100 - evaporation-rate" double,double => double
          _patchvariable:CHEMICAL "chemical" => Object
          _minus "100 - evaporation-rate" double,double => double
            _constdouble:100.0 "100" => double
            _observervariable:EVAPORATION-RATE "evaporation-rate" => Object
        _constdouble:100.0 "100" => double
          TRYCATCHBLOCK L0 L1 L2 org/nlogo/api/AgentException
          TRYCATCHBLOCK L3 L4 L4 java/lang/ClassCastException
          TRYCATCHBLOCK L5 L6 L6 java/lang/ClassCastException
          TRYCATCHBLOCK L7 L8 L9 org/nlogo/api/AgentException
         L0
          ALOAD 1
          GETFIELD org/nlogo/nvm/Context.agent : Lorg/nlogo/agent/Agent;
          ICONST_5
          INVOKEVIRTUAL org/nlogo/agent/Agent.getPatchVariable (I)Ljava/lang/Object;
         L1
          GOTO L10
         L2
         FRAME SAME1 org/nlogo/api/AgentException
          ASTORE 2
          NEW org/nlogo/nvm/EngineException
          DUP
          ALOAD 1
          ALOAD 0
          ALOAD 2
          INVOKEVIRTUAL org/nlogo/api/AgentException.getMessage ()Ljava/lang/String;
          INVOKESPECIAL org/nlogo/nvm/EngineException.<init> (Lorg/nlogo/nvm/Context;Lorg/nlogo/nvm/Instruction;Ljava/lang/String;)V
          ATHROW
         L10
         FRAME SAME1 java/lang/Object
          ASTORE 2
         L3
          ALOAD 2
          CHECKCAST java/lang/Double
          INVOKEVIRTUAL java/lang/Double.doubleValue ()D
          GOTO L11
         L4
         FRAME FULL [org/nlogo/prim/_asm_proceduregopatches_setpatchvariable_0 org/nlogo/nvm/Context java/lang/Object] [java/lang/ClassCastException]
          POP
          NEW org/nlogo/nvm/ArgumentTypeException
          DUP
          ALOAD 1
          ALOAD 0
          BIPUSH 0
          LDC 1
          ALOAD 2
          INVOKESPECIAL org/nlogo/nvm/ArgumentTypeException.<init> (Lorg/nlogo/nvm/Context;Lorg/nlogo/nvm/Instruction;IILjava/lang/Object;)V
          ATHROW
         L11
         FRAME SAME1 D
          LDC 100.0
         L12
          ALOAD 1
          GETFIELD org/nlogo/nvm/Context.agent : Lorg/nlogo/agent/Agent;
          ICONST_1
          INVOKEVIRTUAL org/nlogo/agent/Agent.getObserverVariable (I)Ljava/lang/Object;
         L13
          ASTORE 2
         L5
          ALOAD 2
          CHECKCAST java/lang/Double
          INVOKEVIRTUAL java/lang/Double.doubleValue ()D
          GOTO L14
         L6
         FRAME SAME1 java/lang/ClassCastException
          POP
          NEW org/nlogo/nvm/ArgumentTypeException
          DUP
          ALOAD 1
          ALOAD 0
          BIPUSH 1
          LDC 1
          ALOAD 2
          INVOKESPECIAL org/nlogo/nvm/ArgumentTypeException.<init> (Lorg/nlogo/nvm/Context;Lorg/nlogo/nvm/Instruction;IILjava/lang/Object;)V
          ATHROW
         L14
         FRAME FULL [org/nlogo/prim/_asm_proceduregopatches_setpatchvariable_0 org/nlogo/nvm/Context java/lang/Object] [D D D]
          DSTORE 4
          DSTORE 2
          ALOAD 0
          DLOAD 2
          DLOAD 4
          DSUB
          INVOKEVIRTUAL org/nlogo/prim/_asm_proceduregopatches_setpatchvariable_0.validDouble (D)D
         L15
          DSTORE 4
          DSTORE 2
          ALOAD 0
          DLOAD 2
          DLOAD 4
          DMUL
          INVOKEVIRTUAL org/nlogo/prim/_asm_proceduregopatches_setpatchvariable_0.validDouble (D)D
         L16
          LDC 100.0
         L17
          DSTORE 4
          DSTORE 2
          DLOAD 4
          DCONST_0
          DCMPL
          IFNE L18
          NEW org/nlogo/nvm/EngineException
          DUP
          ALOAD 1
          ALOAD 0
          INVOKESTATIC org/nlogo/core/I18N.errorsJ ()Lorg/nlogo/core/I18NJava;
          LDC "org.nlogo.prim.etc.$common.divByZero"
          INVOKEINTERFACE org/nlogo/core/I18NJava.get (Ljava/lang/String;)Ljava/lang/String;
          INVOKESPECIAL org/nlogo/nvm/EngineException.<init> (Lorg/nlogo/nvm/Context;Lorg/nlogo/nvm/Instruction;Ljava/lang/String;)V
          ATHROW
         L18
         FRAME FULL [org/nlogo/prim/_asm_proceduregopatches_setpatchvariable_0 org/nlogo/nvm/Context D D] []
          ALOAD 0
          DLOAD 2
          DLOAD 4
          DDIV
          INVOKEVIRTUAL org/nlogo/prim/_asm_proceduregopatches_setpatchvariable_0.validDouble (D)D
         L19
          DSTORE 2
          NEW java/lang/Double
          DUP
          DLOAD 2
          INVOKESPECIAL java/lang/Double.<init> (D)V
          ASTORE 2
         L7
          ALOAD 1
          GETFIELD org/nlogo/nvm/Context.agent : Lorg/nlogo/agent/Agent;
          ICONST_5
          ALOAD 2
          INVOKEVIRTUAL org/nlogo/agent/Agent.setPatchVariable (ILjava/lang/Object;)V
         L8
          GOTO L20
         L9
         FRAME FULL [org/nlogo/prim/_asm_proceduregopatches_setpatchvariable_0 org/nlogo/nvm/Context java/lang/Double T D] [org/nlogo/api/AgentException]
          ASTORE 3
          NEW org/nlogo/nvm/EngineException
          DUP
          ALOAD 1
          ALOAD 0
          ALOAD 3
          INVOKEVIRTUAL org/nlogo/api/AgentException.getMessage ()Ljava/lang/String;
          INVOKESPECIAL org/nlogo/nvm/EngineException.<init> (Lorg/nlogo/nvm/Context;Lorg/nlogo/nvm/Instruction;Ljava/lang/String;)V
          ATHROW
         L20
         FRAME SAME
          ALOAD 1
          ICONST_1
          PUTFIELD org/nlogo/nvm/Context.ip : I
         L21
          RETURN
[1]_asm_proceduregopatches_call_1 "update-display"
         L0
          NEW org/nlogo/nvm/Activation
          DUP
          ALOAD 0
          GETFIELD org/nlogo/prim/_asm_proceduregopatches_call_1.kept1_procedure : Lorg/nlogo/nvm/Procedure;
          ALOAD 1
          GETFIELD org/nlogo/nvm/Context.activation : Lorg/nlogo/nvm/Activation;
          ICONST_2
          INVOKESPECIAL org/nlogo/nvm/Activation.<init> (Lorg/nlogo/nvm/Procedure;Lorg/nlogo/nvm/Activation;I)V
          ALOAD 1
          SWAP
          PUTFIELD org/nlogo/nvm/Context.activation : Lorg/nlogo/nvm/Activation;
          ALOAD 1
          ICONST_0
          PUTFIELD org/nlogo/nvm/Context.ip : I
         L1
          RETURN
[2]_asm_proceduregopatches_return_2 => void
         L0
          ALOAD 1
          INVOKEVIRTUAL org/nlogo/nvm/Context.returnFromProcedure ()V
          ALOAD 1
          ICONST_0
          PUTFIELD org/nlogo/nvm/Context.stopping : Z
         L1
          RETURN

reporter procedure CHEMICAL-SCENT:[ANGLE P]{-T--}:
[0]_asm_procedurechemicalscent_setprocedurevariable_0 "let patch-right-and-ahead angle 1" Object => void
      _patchrightandahead "patch-right-and-ahead angle 1"
        _asm_procedurechemicalscent_procedurevariable_1 "angle" => Object
             L0
              ALOAD 1
              GETFIELD org/nlogo/nvm/Context.activation : Lorg/nlogo/nvm/Activation;
              GETFIELD org/nlogo/nvm/Activation.args : [Ljava/lang/Object;
              ICONST_0
              AALOAD
             L1
              ARETURN
        _asm_procedurechemicalscent_constdouble_2 "1" => Double
             L0
              ALOAD 0
              GETFIELD org/nlogo/prim/_asm_procedurechemicalscent_constdouble_2.kept1_value : Ljava/lang/Double;
             L1
              ARETURN
          ALOAD 0
          GETFIELD org/nlogo/prim/_asm_procedurechemicalscent_setprocedurevariable_0.keptinstr2 : Lorg/nlogo/prim/etc/_patchrightandahead;
          ALOAD 1
          INVOKEVIRTUAL org/nlogo/prim/etc/_patchrightandahead.report (Lorg/nlogo/nvm/Context;)Ljava/lang/Object;
         L0
          ASTORE 2
          ALOAD 1
          GETFIELD org/nlogo/nvm/Context.activation : Lorg/nlogo/nvm/Activation;
          GETFIELD org/nlogo/nvm/Activation.args : [Ljava/lang/Object;
          ICONST_1
          ALOAD 2
          AASTORE
          ALOAD 1
          ICONST_1
          PUTFIELD org/nlogo/nvm/Context.ip : I
         L1
          RETURN
[1]_asm_procedurechemicalscent_if_3 "if p != nobody [ report [ chemical ] of p ]" boolean => void
      _notequal "p != nobody" Object,Object => boolean
        _procedurevariable:P "p" => Object
        _nobody "nobody" => Nobody$
         L0
          ALOAD 1
          GETFIELD org/nlogo/nvm/Context.activation : Lorg/nlogo/nvm/Activation;
          GETFIELD org/nlogo/nvm/Activation.args : [Ljava/lang/Object;
          ICONST_1
          AALOAD
         L1
          GETSTATIC org/nlogo/core/Nobody$.MODULE$ : Lorg/nlogo/core/Nobody$;
         L2
          ASTORE 3
          ASTORE 2
          ALOAD 2
          ALOAD 3
          INVOKESTATIC org/nlogo/api/Equality.equals (Ljava/lang/Object;Ljava/lang/Object;)Z
          IFNE L3
          ICONST_1
          GOTO L4
         L3
         FRAME APPEND [java/lang/Object org/nlogo/core/Nobody$]
          ICONST_0
         L4
         FRAME SAME1 I
          ISTORE 2
          ALOAD 1
          ILOAD 2
          IFEQ L5
          ICONST_2
          GOTO L6
         L5
         FRAME FULL [org/nlogo/prim/_asm_procedurechemicalscent_if_3 org/nlogo/nvm/Context I org/nlogo/core/Nobody$] [org/nlogo/nvm/Context]
          ICONST_3
         L6
         FRAME FULL [org/nlogo/prim/_asm_procedurechemicalscent_if_3 org/nlogo/nvm/Context I org/nlogo/core/Nobody$] [org/nlogo/nvm/Context I]
          PUTFIELD org/nlogo/nvm/Context.ip : I
         L7
          RETURN
[2]_asm_procedurechemicalscent_report_4 "report [ chemical ] of p" Object => void
      _patchvariableof:CHEMICAL "[ chemical ] of p" Object => Object
        _procedurevariable:P "p" => Object
          TRYCATCHBLOCK L0 L1 L2 org/nlogo/api/AgentException
          TRYCATCHBLOCK L3 L4 L5 org/nlogo/api/AgentException
         L6
          ALOAD 1
          GETFIELD org/nlogo/nvm/Context.activation : Lorg/nlogo/nvm/Activation;
          GETFIELD org/nlogo/nvm/Activation.args : [Ljava/lang/Object;
          ICONST_1
          AALOAD
         L7
          ASTORE 2
          ALOAD 2
          ASTORE 3
          ALOAD 3
          INSTANCEOF org/nlogo/agent/Agent
          IFEQ L8
          ALOAD 3
          CHECKCAST org/nlogo/agent/Agent
          ASTORE 4
          ALOAD 4
          GETFIELD org/nlogo/agent/Agent.id : J
          LDC -1
          LCMP
          IFNE L3
          NEW org/nlogo/nvm/EngineException
          DUP
          ALOAD 1
          ALOAD 0
          GETSTATIC org/nlogo/core/I18N$.MODULE$ : Lorg/nlogo/core/I18N$;
          INVOKEVIRTUAL org/nlogo/core/I18N$.errors ()Lorg/nlogo/core/I18N$BundleKind;
          LDC "org.nlogo.$common.thatAgentIsDead"
          GETSTATIC scala/Predef$.MODULE$ : Lscala/Predef$;
          ICONST_1
          ANEWARRAY java/lang/Object
          DUP
          ICONST_0
          ALOAD 4
          INVOKEVIRTUAL org/nlogo/agent/Agent.classDisplayName ()Ljava/lang/String;
          AASTORE
          INVOKEVIRTUAL scala/Predef$.wrapRefArray ([Ljava/lang/Object;)Lscala/collection/mutable/WrappedArray;
          INVOKEVIRTUAL org/nlogo/core/I18N$BundleKind.getN (Ljava/lang/String;Lscala/collection/Seq;)Ljava/lang/String;
          INVOKESPECIAL org/nlogo/nvm/EngineException.<init> (Lorg/nlogo/nvm/Context;Lorg/nlogo/nvm/Instruction;Ljava/lang/String;)V
          ATHROW
         L3
         FRAME APPEND [java/lang/Object java/lang/Object org/nlogo/agent/Agent]
          ALOAD 4
          ICONST_5
          INVOKEVIRTUAL org/nlogo/agent/Agent.getPatchVariable (I)Ljava/lang/Object;
         L4
          ASTORE 5
          GOTO L9
         L8
         FRAME CHOP 1
          ALOAD 3
          INSTANCEOF org/nlogo/agent/AgentSet
          IFEQ L10
          ALOAD 3
          CHECKCAST org/nlogo/agent/AgentSet
          ASTORE 7
          NEW org/nlogo/api/LogoListBuilder
          DUP
          INVOKESPECIAL org/nlogo/api/LogoListBuilder.<init> ()V
          ASTORE 8
         L0
          ALOAD 7
          ALOAD 1
          GETFIELD org/nlogo/nvm/Context.job : Lorg/nlogo/nvm/Job;
          GETFIELD org/nlogo/nvm/Job.random : Lorg/nlogo/api/MersenneTwisterFast;
          INVOKEVIRTUAL org/nlogo/agent/AgentSet.shufflerator (Lorg/nlogo/api/MersenneTwisterFast;)Lorg/nlogo/agent/AgentSet$Iterator;
          ASTORE 10
         L11
         FRAME FULL [org/nlogo/prim/_asm_procedurechemicalscent_report_4 org/nlogo/nvm/Context java/lang/Object java/lang/Object T T T org/nlogo/agent/AgentSet org/nlogo/api/LogoListBuilder T org/nlogo/agent/AgentSet$Iterator] []
          ALOAD 10
          INVOKEINTERFACE org/nlogo/agent/AgentSet$Iterator.hasNext ()Z
          IFEQ L1
          ALOAD 8
          ALOAD 10
          INVOKEINTERFACE org/nlogo/agent/AgentSet$Iterator.next ()Lorg/nlogo/agent/Agent;
          ICONST_5
          INVOKEVIRTUAL org/nlogo/agent/Agent.getPatchVariable (I)Ljava/lang/Object;
          INVOKEVIRTUAL org/nlogo/api/LogoListBuilder.add (Ljava/lang/Object;)V
          GOTO L11
         L1
         FRAME SAME
          ALOAD 8
          INVOKEVIRTUAL org/nlogo/api/LogoListBuilder.toLogoList ()Lorg/nlogo/core/LogoList;
          ASTORE 5
         L9
         FRAME FULL [org/nlogo/prim/_asm_procedurechemicalscent_report_4 org/nlogo/nvm/Context java/lang/Object java/lang/Object T java/lang/Object] []
          ALOAD 5
          GOTO L12
         L10
         FRAME CHOP 2
          NEW org/nlogo/nvm/ArgumentTypeException
          DUP
          ALOAD 1
          ALOAD 0
          ICONST_0
          GETSTATIC org/nlogo/core/Syntax$.MODULE$ : Lorg/nlogo/core/Syntax$;
          INVOKEVIRTUAL org/nlogo/core/Syntax$.TurtleType ()I
          GETSTATIC org/nlogo/core/Syntax$.MODULE$ : Lorg/nlogo/core/Syntax$;
          INVOKEVIRTUAL org/nlogo/core/Syntax$.PatchType ()I
          IOR
          GETSTATIC org/nlogo/core/Syntax$.MODULE$ : Lorg/nlogo/core/Syntax$;
          INVOKEVIRTUAL org/nlogo/core/Syntax$.TurtlesetType ()I
          IOR
          GETSTATIC org/nlogo/core/Syntax$.MODULE$ : Lorg/nlogo/core/Syntax$;
          INVOKEVIRTUAL org/nlogo/core/Syntax$.PatchsetType ()I
          IOR
          ALOAD 2
          INVOKESPECIAL org/nlogo/nvm/ArgumentTypeException.<init> (Lorg/nlogo/nvm/Context;Lorg/nlogo/nvm/Instruction;IILjava/lang/Object;)V
          ATHROW
         L5
         FRAME FULL [org/nlogo/prim/_asm_procedurechemicalscent_report_4 org/nlogo/nvm/Context java/lang/Object java/lang/Object org/nlogo/agent/Agent] [org/nlogo/api/AgentException]
          ASTORE 6
          NEW org/nlogo/nvm/EngineException
          DUP
          ALOAD 1
          ALOAD 0
          ALOAD 6
          INVOKEVIRTUAL org/nlogo/api/AgentException.getMessage ()Ljava/lang/String;
          INVOKESPECIAL org/nlogo/nvm/EngineException.<init> (Lorg/nlogo/nvm/Context;Lorg/nlogo/nvm/Instruction;Ljava/lang/String;)V
          ATHROW
         L2
         FRAME FULL [org/nlogo/prim/_asm_procedurechemicalscent_report_4 org/nlogo/nvm/Context java/lang/Object java/lang/Object T T T org/nlogo/agent/AgentSet org/nlogo/api/LogoListBuilder] [org/nlogo/api/AgentException]
          ASTORE 9
          NEW org/nlogo/nvm/EngineException
          DUP
          ALOAD 1
          ALOAD 0
          ALOAD 9
          INVOKEVIRTUAL org/nlogo/api/AgentException.getMessage ()Ljava/lang/String;
          INVOKESPECIAL org/nlogo/nvm/EngineException.<init> (Lorg/nlogo/nvm/Context;Lorg/nlogo/nvm/Instruction;Ljava/lang/String;)V
          ATHROW
         L12
         FRAME FULL [org/nlogo/prim/_asm_procedurechemicalscent_report_4 org/nlogo/nvm/Context java/lang/Object java/lang/Object T java/lang/Object] [java/lang/Object]
          ASTORE 2
          ALOAD 1
          GETFIELD org/nlogo/nvm/Context.job : Lorg/nlogo/nvm/Job;
          ALOAD 2
          PUTFIELD org/nlogo/nvm/Job.result : Ljava/lang/Object;
          ALOAD 1
          ICONST_0
          PUTFIELD org/nlogo/nvm/Context.stopping : Z
          ALOAD 1
          ICONST_3
          PUTFIELD org/nlogo/nvm/Context.ip : I
          ALOAD 1
          GETFIELD org/nlogo/nvm/Context.activation : Lorg/nlogo/nvm/Activation;
          GETFIELD org/nlogo/nvm/Activation.procedure : Lorg/nlogo/nvm/Procedure;
          INVOKEVIRTUAL org/nlogo/nvm/Procedure.isTask ()Z
          IFEQ L13
          GETSTATIC org/nlogo/nvm/NonLocalExit$.MODULE$ : Lorg/nlogo/nvm/NonLocalExit$;
          ATHROW
         L13
         FRAME SAME
          ALOAD 1
          GETFIELD org/nlogo/nvm/Context.activation : Lorg/nlogo/nvm/Activation;
          GETFIELD org/nlogo/nvm/Activation.procedure : Lorg/nlogo/nvm/Procedure;
          INVOKEVIRTUAL org/nlogo/nvm/Procedure.isReporter ()Z
          IFNE L14
          NEW org/nlogo/nvm/EngineException
          DUP
          ALOAD 1
          ALOAD 0
          INVOKESTATIC org/nlogo/core/I18N.errorsJ ()Lorg/nlogo/core/I18NJava;
          LDC "org.nlogo.prim._report.canOnlyUseInToReport"
          ICONST_1
          ANEWARRAY java/lang/Object
          DUP
          ICONST_0
          LDC "REPORT"
          AASTORE
          INVOKEINTERFACE org/nlogo/core/I18NJava.getN (Ljava/lang/String;[Ljava/lang/Object;)Ljava/lang/String;
          INVOKESPECIAL org/nlogo/nvm/EngineException.<init> (Lorg/nlogo/nvm/Context;Lorg/nlogo/nvm/Instruction;Ljava/lang/String;)V
          ATHROW
         L14
         FRAME SAME
          ALOAD 1
          INVOKEVIRTUAL org/nlogo/nvm/Context.atTopActivation ()Z
          IFNE L15
          NEW org/nlogo/nvm/EngineException
          DUP
          ALOAD 1
          ALOAD 0
          INVOKESTATIC org/nlogo/core/I18N.errorsJ ()Lorg/nlogo/core/I18NJava;
          LDC "org.nlogo.prim._report.mustImmediatelyBeUsedInToReport"
          ICONST_1
          ANEWARRAY java/lang/Object
          DUP
          ICONST_0
          LDC "REPORT"
          AASTORE
          INVOKEINTERFACE org/nlogo/core/I18NJava.getN (Ljava/lang/String;[Ljava/lang/Object;)Ljava/lang/String;
          INVOKESPECIAL org/nlogo/nvm/EngineException.<init> (Lorg/nlogo/nvm/Context;Lorg/nlogo/nvm/Instruction;Ljava/lang/String;)V
          ATHROW
         L15
         FRAME SAME
          RETURN
[3]_asm_procedurechemicalscent_report_5 "report 0" Object => void
      _constdouble:0.0 "0" => Double
         L0
          ALOAD 0
          GETFIELD org/nlogo/prim/_asm_procedurechemicalscent_report_5.kept2_value : Ljava/lang/Double;
         L1
          ASTORE 2
          ALOAD 1
          GETFIELD org/nlogo/nvm/Context.job : Lorg/nlogo/nvm/Job;
          ALOAD 2
          PUTFIELD org/nlogo/nvm/Job.result : Ljava/lang/Object;
          ALOAD 1
          ICONST_0
          PUTFIELD org/nlogo/nvm/Context.stopping : Z
          ALOAD 1
          ICONST_4
          PUTFIELD org/nlogo/nvm/Context.ip : I
          ALOAD 1
          GETFIELD org/nlogo/nvm/Context.activation : Lorg/nlogo/nvm/Activation;
          GETFIELD org/nlogo/nvm/Activation.procedure : Lorg/nlogo/nvm/Procedure;
          INVOKEVIRTUAL org/nlogo/nvm/Procedure.isTask ()Z
          IFEQ L2
          GETSTATIC org/nlogo/nvm/NonLocalExit$.MODULE$ : Lorg/nlogo/nvm/NonLocalExit$;
          ATHROW
         L2
         FRAME APPEND [java/lang/Double]
          ALOAD 1
          GETFIELD org/nlogo/nvm/Context.activation : Lorg/nlogo/nvm/Activation;
          GETFIELD org/nlogo/nvm/Activation.procedure : Lorg/nlogo/nvm/Procedure;
          INVOKEVIRTUAL org/nlogo/nvm/Procedure.isReporter ()Z
          IFNE L3
          NEW org/nlogo/nvm/EngineException
          DUP
          ALOAD 1
          ALOAD 0
          INVOKESTATIC org/nlogo/core/I18N.errorsJ ()Lorg/nlogo/core/I18NJava;
          LDC "org.nlogo.prim._report.canOnlyUseInToReport"
          ICONST_1
          ANEWARRAY java/lang/Object
          DUP
          ICONST_0
          LDC "REPORT"
          AASTORE
          INVOKEINTERFACE org/nlogo/core/I18NJava.getN (Ljava/lang/String;[Ljava/lang/Object;)Ljava/lang/String;
          INVOKESPECIAL org/nlogo/nvm/EngineException.<init> (Lorg/nlogo/nvm/Context;Lorg/nlogo/nvm/Instruction;Ljava/lang/String;)V
          ATHROW
         L3
         FRAME SAME
          ALOAD 1
          INVOKEVIRTUAL org/nlogo/nvm/Context.atTopActivation ()Z
          IFNE L4
          NEW org/nlogo/nvm/EngineException
          DUP
          ALOAD 1
          ALOAD 0
          INVOKESTATIC org/nlogo/core/I18N.errorsJ ()Lorg/nlogo/core/I18NJava;
          LDC "org.nlogo.prim._report.mustImmediatelyBeUsedInToReport"
          ICONST_1
          ANEWARRAY java/lang/Object
          DUP
          ICONST_0
          LDC "REPORT"
          AASTORE
          INVOKEINTERFACE org/nlogo/core/I18NJava.getN (Ljava/lang/String;[Ljava/lang/Object;)Ljava/lang/String;
          INVOKESPECIAL org/nlogo/nvm/EngineException.<init> (Lorg/nlogo/nvm/Context;Lorg/nlogo/nvm/Instruction;Ljava/lang/String;)V
          ATHROW
         L4
         FRAME SAME
          RETURN
[4]_asm_procedurechemicalscent_returnreport_6 => void
         L0
          NEW org/nlogo/nvm/EngineException
          DUP
          ALOAD 1
          ALOAD 0
          INVOKESTATIC org/nlogo/core/I18N.errorsJ ()Lorg/nlogo/core/I18NJava;
          LDC "org.nlogo.prim._returnreport.reportNotCalledInReportProcedure"
          INVOKEINTERFACE org/nlogo/core/I18NJava.get (Ljava/lang/String;)Ljava/lang/String;
          INVOKESPECIAL org/nlogo/nvm/EngineException.<init> (Lorg/nlogo/nvm/Context;Lorg/nlogo/nvm/Instruction;Ljava/lang/String;)V
          ATHROW
         L1
         FRAME FULL [] [java/lang/Throwable]
          ATHROW

procedure SETUP:[]{O---}:
[0]_clearall "ca"
[1]_resetticks "reset-ticks"
[2]_asm_proceduresetup_call_0 "setup-turtles"
         L0
          NEW org/nlogo/nvm/Activation
          DUP
          ALOAD 0
          GETFIELD org/nlogo/prim/_asm_proceduresetup_call_0.kept1_procedure : Lorg/nlogo/nvm/Procedure;
          ALOAD 1
          GETFIELD org/nlogo/nvm/Context.activation : Lorg/nlogo/nvm/Activation;
          ICONST_3
          INVOKESPECIAL org/nlogo/nvm/Activation.<init> (Lorg/nlogo/nvm/Procedure;Lorg/nlogo/nvm/Activation;I)V
          ALOAD 1
          SWAP
          PUTFIELD org/nlogo/nvm/Context.activation : Lorg/nlogo/nvm/Activation;
          ALOAD 1
          ICONST_0
          PUTFIELD org/nlogo/nvm/Context.ip : I
         L1
          RETURN
[3]_asm_proceduresetup_call_1 "setup-patches"
         L0
          NEW org/nlogo/nvm/Activation
          DUP
          ALOAD 0
          GETFIELD org/nlogo/prim/_asm_proceduresetup_call_1.kept1_procedure : Lorg/nlogo/nvm/Procedure;
          ALOAD 1
          GETFIELD org/nlogo/nvm/Context.activation : Lorg/nlogo/nvm/Activation;
          ICONST_4
          INVOKESPECIAL org/nlogo/nvm/Activation.<init> (Lorg/nlogo/nvm/Procedure;Lorg/nlogo/nvm/Activation;I)V
          ALOAD 1
          SWAP
          PUTFIELD org/nlogo/nvm/Context.activation : Lorg/nlogo/nvm/Activation;
          ALOAD 1
          ICONST_0
          PUTFIELD org/nlogo/nvm/Context.ip : I
         L1
          RETURN
[4]_asm_proceduresetup_call_2 "do-plotting"
         L0
          NEW org/nlogo/nvm/Activation
          DUP
          ALOAD 0
          GETFIELD org/nlogo/prim/_asm_proceduresetup_call_2.kept1_procedure : Lorg/nlogo/nvm/Procedure;
          ALOAD 1
          GETFIELD org/nlogo/nvm/Context.activation : Lorg/nlogo/nvm/Activation;
          ICONST_5
          INVOKESPECIAL org/nlogo/nvm/Activation.<init> (Lorg/nlogo/nvm/Procedure;Lorg/nlogo/nvm/Activation;I)V
          ALOAD 1
          SWAP
          PUTFIELD org/nlogo/nvm/Context.activation : Lorg/nlogo/nvm/Activation;
          ALOAD 1
          ICONST_0
          PUTFIELD org/nlogo/nvm/Context.ip : I
         L1
          RETURN
[5]_asm_proceduresetup_return_3 => void
         L0
          ALOAD 1
          INVOKEVIRTUAL org/nlogo/nvm/Context.returnFromProcedure ()V
          ALOAD 1
          ICONST_0
          PUTFIELD org/nlogo/nvm/Context.stopping : Z
         L1
          RETURN

procedure RETURN-TO-NEST:[]{-T--}:
[0]_asm_procedurereturntonest_ifelse_0 "ifelse nest? set carrying-food? false rt 180 [ fd 1 ] set chemical chemical + drop-size set drop-size drop-size - 1.5 if drop-size < 1 [ set drop-size 1 ] uphill-nest-scent wiggle [ fd 1 ]" boolean => void
      _patchvariable:NEST? "nest?" => Object
          TRYCATCHBLOCK L0 L1 L2 org/nlogo/api/AgentException
          TRYCATCHBLOCK L3 L4 L4 java/lang/ClassCastException
         L0
          ALOAD 1
          GETFIELD org/nlogo/nvm/Context.agent : Lorg/nlogo/agent/Agent;
          BIPUSH 7
          INVOKEVIRTUAL org/nlogo/agent/Agent.getPatchVariable (I)Ljava/lang/Object;
         L1
          GOTO L5
         L2
         FRAME SAME1 org/nlogo/api/AgentException
          ASTORE 2
          NEW org/nlogo/nvm/EngineException
          DUP
          ALOAD 1
          ALOAD 0
          ALOAD 2
          INVOKEVIRTUAL org/nlogo/api/AgentException.getMessage ()Ljava/lang/String;
          INVOKESPECIAL org/nlogo/nvm/EngineException.<init> (Lorg/nlogo/nvm/Context;Lorg/nlogo/nvm/Instruction;Ljava/lang/String;)V
          ATHROW
         L5
         FRAME SAME1 java/lang/Object
          ASTORE 2
         L3
          ALOAD 2
          CHECKCAST java/lang/Boolean
          INVOKEVIRTUAL java/lang/Boolean.booleanValue ()Z
          GOTO L6
         L4
         FRAME FULL [org/nlogo/prim/_asm_procedurereturntonest_ifelse_0 org/nlogo/nvm/Context java/lang/Object] [java/lang/ClassCastException]
          POP
          NEW org/nlogo/nvm/ArgumentTypeException
          DUP
          ALOAD 1
          ALOAD 0
          BIPUSH 0
          LDC 2
          ALOAD 2
          INVOKESPECIAL org/nlogo/nvm/ArgumentTypeException.<init> (Lorg/nlogo/nvm/Context;Lorg/nlogo/nvm/Instruction;IILjava/lang/Object;)V
          ATHROW
         L6
         FRAME SAME1 I
          ISTORE 2
          ALOAD 1
          ILOAD 2
          IFEQ L7
          ICONST_1
          GOTO L8
         L7
         FRAME FULL [org/nlogo/prim/_asm_procedurereturntonest_ifelse_0 org/nlogo/nvm/Context I] [org/nlogo/nvm/Context]
          ICONST_5
         L8
         FRAME FULL [org/nlogo/prim/_asm_procedurereturntonest_ifelse_0 org/nlogo/nvm/Context I] [org/nlogo/nvm/Context I]
          PUTFIELD org/nlogo/nvm/Context.ip : I
         L9
          RETURN
[1]_asm_procedurereturntonest_setturtlevariable_1 "set carrying-food? false" Object => void
      _constboolean:false "false" => Boolean
          TRYCATCHBLOCK L0 L1 L2 org/nlogo/api/AgentException
         L3
          ALOAD 0
          GETFIELD org/nlogo/prim/_asm_procedurereturntonest_setturtlevariable_1.kept2_value : Ljava/lang/Boolean;
         L4
          ASTORE 2
         L0
          ALOAD 1
          GETFIELD org/nlogo/nvm/Context.agent : Lorg/nlogo/agent/Agent;
          BIPUSH 13
          ALOAD 2
          INVOKEVIRTUAL org/nlogo/agent/Agent.setTurtleVariable (ILjava/lang/Object;)V
         L1
          GOTO L5
         L2
         FRAME FULL [org/nlogo/prim/_asm_procedurereturntonest_setturtlevariable_1 org/nlogo/nvm/Context java/lang/Boolean] [org/nlogo/api/AgentException]
          ASTORE 3
          NEW org/nlogo/nvm/EngineException
          DUP
          ALOAD 1
          ALOAD 0
          ALOAD 3
          INVOKEVIRTUAL org/nlogo/api/AgentException.getMessage ()Ljava/lang/String;
          INVOKESPECIAL org/nlogo/nvm/EngineException.<init> (Lorg/nlogo/nvm/Context;Lorg/nlogo/nvm/Instruction;Ljava/lang/String;)V
          ATHROW
         L5
         FRAME SAME
          ALOAD 1
          ICONST_2
          PUTFIELD org/nlogo/nvm/Context.ip : I
         L6
          RETURN
[2]_asm_procedurereturntonest_right_2 "rt 180" double => void
      _constdouble:180.0 "180" => double
         L0
          LDC 180.0
         L1
          DSTORE 2
          ALOAD 1
          GETFIELD org/nlogo/nvm/Context.agent : Lorg/nlogo/agent/Agent;
          CHECKCAST org/nlogo/agent/Turtle
          DLOAD 2
          INVOKEVIRTUAL org/nlogo/agent/Turtle.turnRight (D)V
          ALOAD 1
          ICONST_3
          PUTFIELD org/nlogo/nvm/Context.ip : I
         L2
          RETURN
[3]_asm_procedurereturntonest_fd1_3 "fd 1" => void
          TRYCATCHBLOCK L0 L1 L2 org/nlogo/api/AgentException
         L0
          ALOAD 1
          GETFIELD org/nlogo/nvm/Context.agent : Lorg/nlogo/agent/Agent;
          CHECKCAST org/nlogo/agent/Turtle
          DCONST_1
          INVOKEVIRTUAL org/nlogo/agent/Turtle.jump (D)V
         L1
          GOTO L3
         L2
         FRAME SAME1 org/nlogo/api/AgentException
          ASTORE 2
         L3
         FRAME SAME
          ALOAD 1
          ICONST_4
          PUTFIELD org/nlogo/nvm/Context.ip : I
         L4
          RETURN
[4]_asm_procedurereturntonest_goto_4 => void
         L0
          ALOAD 1
          BIPUSH 12
          PUTFIELD org/nlogo/nvm/Context.ip : I
         L1
          RETURN
[5]_asm_procedurereturntonest_setpatchvariable_5 "set chemical chemical + drop-size" Object => void
      _plus "chemical + drop-size" double,double => double
        _patchvariable:CHEMICAL "chemical" => Object
        _turtlevariable:DROP-SIZE "drop-size" => Object
          TRYCATCHBLOCK L0 L1 L2 org/nlogo/api/AgentException
          TRYCATCHBLOCK L3 L4 L4 java/lang/ClassCastException
          TRYCATCHBLOCK L5 L6 L7 org/nlogo/api/AgentException
          TRYCATCHBLOCK L8 L9 L9 java/lang/ClassCastException
          TRYCATCHBLOCK L10 L11 L12 org/nlogo/api/AgentException
         L0
          ALOAD 1
          GETFIELD org/nlogo/nvm/Context.agent : Lorg/nlogo/agent/Agent;
          ICONST_5
          INVOKEVIRTUAL org/nlogo/agent/Agent.getPatchVariable (I)Ljava/lang/Object;
         L1
          GOTO L13
         L2
         FRAME SAME1 org/nlogo/api/AgentException
          ASTORE 2
          NEW org/nlogo/nvm/EngineException
          DUP
          ALOAD 1
          ALOAD 0
          ALOAD 2
          INVOKEVIRTUAL org/nlogo/api/AgentException.getMessage ()Ljava/lang/String;
          INVOKESPECIAL org/nlogo/nvm/EngineException.<init> (Lorg/nlogo/nvm/Context;Lorg/nlogo/nvm/Instruction;Ljava/lang/String;)V
          ATHROW
         L13
         FRAME SAME1 java/lang/Object
          ASTORE 2
         L3
          ALOAD 2
          CHECKCAST java/lang/Double
          INVOKEVIRTUAL java/lang/Double.doubleValue ()D
          GOTO L5
         L4
         FRAME FULL [org/nlogo/prim/_asm_procedurereturntonest_setpatchvariable_5 org/nlogo/nvm/Context java/lang/Object] [java/lang/ClassCastException]
          POP
          NEW org/nlogo/nvm/ArgumentTypeException
          DUP
          ALOAD 1
          ALOAD 0
          BIPUSH 0
          LDC 1
          ALOAD 2
          INVOKESPECIAL org/nlogo/nvm/ArgumentTypeException.<init> (Lorg/nlogo/nvm/Context;Lorg/nlogo/nvm/Instruction;IILjava/lang/Object;)V
          ATHROW
         L5
         FRAME SAME1 D
          ALOAD 1
          GETFIELD org/nlogo/nvm/Context.agent : Lorg/nlogo/agent/Agent;
          BIPUSH 14
          INVOKEVIRTUAL org/nlogo/agent/Agent.getTurtleVariable (I)Ljava/lang/Object;
         L6
          GOTO L14
         L7
         FRAME SAME1 org/nlogo/api/AgentException
          ASTORE 2
          NEW org/nlogo/nvm/EngineException
          DUP
          ALOAD 1
          ALOAD 0
          ALOAD 2
          INVOKEVIRTUAL org/nlogo/api/AgentException.getMessage ()Ljava/lang/String;
          INVOKESPECIAL org/nlogo/nvm/EngineException.<init> (Lorg/nlogo/nvm/Context;Lorg/nlogo/nvm/Instruction;Ljava/lang/String;)V
          ATHROW
         L14
         FRAME FULL [org/nlogo/prim/_asm_procedurereturntonest_setpatchvariable_5 org/nlogo/nvm/Context java/lang/Object] [D java/lang/Object]
          ASTORE 2
         L8
          ALOAD 2
          CHECKCAST java/lang/Double
          INVOKEVIRTUAL java/lang/Double.doubleValue ()D
          GOTO L15
         L9
         FRAME SAME1 java/lang/ClassCastException
          POP
          NEW org/nlogo/nvm/ArgumentTypeException
          DUP
          ALOAD 1
          ALOAD 0
          BIPUSH 1
          LDC 1
          ALOAD 2
          INVOKESPECIAL org/nlogo/nvm/ArgumentTypeException.<init> (Lorg/nlogo/nvm/Context;Lorg/nlogo/nvm/Instruction;IILjava/lang/Object;)V
          ATHROW
         L15
         FRAME FULL [org/nlogo/prim/_asm_procedurereturntonest_setpatchvariable_5 org/nlogo/nvm/Context java/lang/Object] [D D]
          DSTORE 4
          DSTORE 2
          ALOAD 0
          DLOAD 2
          DLOAD 4
          DADD
          INVOKEVIRTUAL org/nlogo/prim/_asm_procedurereturntonest_setpatchvariable_5.validDouble (D)D
         L16
          DSTORE 2
          NEW java/lang/Double
          DUP
          DLOAD 2
          INVOKESPECIAL java/lang/Double.<init> (D)V
          ASTORE 2
         L10
          ALOAD 1
          GETFIELD org/nlogo/nvm/Context.agent : Lorg/nlogo/agent/Agent;
          ICONST_5
          ALOAD 2
          INVOKEVIRTUAL org/nlogo/agent/Agent.setPatchVariable (ILjava/lang/Object;)V
         L11
          GOTO L17
         L12
         FRAME FULL [org/nlogo/prim/_asm_procedurereturntonest_setpatchvariable_5 org/nlogo/nvm/Context java/lang/Double T D] [org/nlogo/api/AgentException]
          ASTORE 3
          NEW org/nlogo/nvm/EngineException
          DUP
          ALOAD 1
          ALOAD 0
          ALOAD 3
          INVOKEVIRTUAL org/nlogo/api/AgentException.getMessage ()Ljava/lang/String;
          INVOKESPECIAL org/nlogo/nvm/EngineException.<init> (Lorg/nlogo/nvm/Context;Lorg/nlogo/nvm/Instruction;Ljava/lang/String;)V
          ATHROW
         L17
         FRAME SAME
          ALOAD 1
          BIPUSH 6
          PUTFIELD org/nlogo/nvm/Context.ip : I
         L18
          RETURN
[6]_asm_procedurereturntonest_setturtlevariable_6 "set drop-size drop-size - 1.5" Object => void
      _minus "drop-size - 1.5" double,double => double
        _turtlevariable:DROP-SIZE "drop-size" => Object
        _constdouble:1.5 "1.5" => double
          TRYCATCHBLOCK L0 L1 L2 org/nlogo/api/AgentException
          TRYCATCHBLOCK L3 L4 L4 java/lang/ClassCastException
          TRYCATCHBLOCK L5 L6 L7 org/nlogo/api/AgentException
         L0
          ALOAD 1
          GETFIELD org/nlogo/nvm/Context.agent : Lorg/nlogo/agent/Agent;
          BIPUSH 14
          INVOKEVIRTUAL org/nlogo/agent/Agent.getTurtleVariable (I)Ljava/lang/Object;
         L1
          GOTO L8
         L2
         FRAME SAME1 org/nlogo/api/AgentException
          ASTORE 2
          NEW org/nlogo/nvm/EngineException
          DUP
          ALOAD 1
          ALOAD 0
          ALOAD 2
          INVOKEVIRTUAL org/nlogo/api/AgentException.getMessage ()Ljava/lang/String;
          INVOKESPECIAL org/nlogo/nvm/EngineException.<init> (Lorg/nlogo/nvm/Context;Lorg/nlogo/nvm/Instruction;Ljava/lang/String;)V
          ATHROW
         L8
         FRAME SAME1 java/lang/Object
          ASTORE 2
         L3
          ALOAD 2
          CHECKCAST java/lang/Double
          INVOKEVIRTUAL java/lang/Double.doubleValue ()D
          GOTO L9
         L4
         FRAME FULL [org/nlogo/prim/_asm_procedurereturntonest_setturtlevariable_6 org/nlogo/nvm/Context java/lang/Object] [java/lang/ClassCastException]
          POP
          NEW org/nlogo/nvm/ArgumentTypeException
          DUP
          ALOAD 1
          ALOAD 0
          BIPUSH 0
          LDC 1
          ALOAD 2
          INVOKESPECIAL org/nlogo/nvm/ArgumentTypeException.<init> (Lorg/nlogo/nvm/Context;Lorg/nlogo/nvm/Instruction;IILjava/lang/Object;)V
          ATHROW
         L9
         FRAME SAME1 D
          LDC 1.5
         L10
          DSTORE 4
          DSTORE 2
          ALOAD 0
          DLOAD 2
          DLOAD 4
          DSUB
          INVOKEVIRTUAL org/nlogo/prim/_asm_procedurereturntonest_setturtlevariable_6.validDouble (D)D
         L11
          DSTORE 2
          NEW java/lang/Double
          DUP
          DLOAD 2
          INVOKESPECIAL java/lang/Double.<init> (D)V
          ASTORE 2
         L5
          ALOAD 1
          GETFIELD org/nlogo/nvm/Context.agent : Lorg/nlogo/agent/Agent;
          BIPUSH 14
          ALOAD 2
          INVOKEVIRTUAL org/nlogo/agent/Agent.setTurtleVariable (ILjava/lang/Object;)V
         L6
          GOTO L12
         L7
         FRAME FULL [org/nlogo/prim/_asm_procedurereturntonest_setturtlevariable_6 org/nlogo/nvm/Context java/lang/Double T D] [org/nlogo/api/AgentException]
          ASTORE 3
          NEW org/nlogo/nvm/EngineException
          DUP
          ALOAD 1
          ALOAD 0
          ALOAD 3
          INVOKEVIRTUAL org/nlogo/api/AgentException.getMessage ()Ljava/lang/String;
          INVOKESPECIAL org/nlogo/nvm/EngineException.<init> (Lorg/nlogo/nvm/Context;Lorg/nlogo/nvm/Instruction;Ljava/lang/String;)V
          ATHROW
         L12
         FRAME SAME
          ALOAD 1
          BIPUSH 7
          PUTFIELD org/nlogo/nvm/Context.ip : I
         L13
          RETURN
[7]_asm_procedurereturntonest_if_7 "if drop-size < 1 [ set drop-size 1 ]" boolean => void
      _lessthan "drop-size < 1" Object,double => boolean
        _turtlevariable:DROP-SIZE "drop-size" => Object
        _constdouble:1.0 "1" => double
          TRYCATCHBLOCK L0 L1 L2 org/nlogo/api/AgentException
         L0
          ALOAD 1
          GETFIELD org/nlogo/nvm/Context.agent : Lorg/nlogo/agent/Agent;
          BIPUSH 14
          INVOKEVIRTUAL org/nlogo/agent/Agent.getTurtleVariable (I)Ljava/lang/Object;
         L1
          GOTO L3
         L2
         FRAME SAME1 org/nlogo/api/AgentException
          ASTORE 2
          NEW org/nlogo/nvm/EngineException
          DUP
          ALOAD 1
          ALOAD 0
          ALOAD 2
          INVOKEVIRTUAL org/nlogo/api/AgentException.getMessage ()Ljava/lang/String;
          INVOKESPECIAL org/nlogo/nvm/EngineException.<init> (Lorg/nlogo/nvm/Context;Lorg/nlogo/nvm/Instruction;Ljava/lang/String;)V
          ATHROW
         L3
         FRAME SAME1 java/lang/Object
          DCONST_1
         L4
          DSTORE 3
          ASTORE 2
          ALOAD 2
          INSTANCEOF java/lang/Double
          IFEQ L5
          ALOAD 2
          CHECKCAST java/lang/Double
          INVOKEVIRTUAL java/lang/Double.doubleValue ()D
          DLOAD 3
          DCMPG
          IFGE L6
          ICONST_1
          GOTO L7
         L6
         FRAME APPEND [java/lang/Object D]
          ICONST_0
         L7
         FRAME SAME1 I
          GOTO L8
         L5
         FRAME SAME
          NEW org/nlogo/nvm/EngineException
          DUP
          ALOAD 1
          ALOAD 0
          INVOKESTATIC org/nlogo/core/I18N.errorsJ ()Lorg/nlogo/core/I18NJava;
          LDC "org.nlogo.prim._lessthan.cantUseLessthanOnDifferentArgs"
          ICONST_2
          ANEWARRAY java/lang/Object
          DUP
          ICONST_0
          ALOAD 2
          INVOKESTATIC org/nlogo/api/TypeNames.aName (Ljava/lang/Object;)Ljava/lang/String;
          AASTORE
          DUP
          ICONST_1
          DLOAD 3
          INVOKESTATIC java/lang/Double.valueOf (D)Ljava/lang/Double;
          INVOKESTATIC org/nlogo/api/TypeNames.aName (Ljava/lang/Object;)Ljava/lang/String;
          AASTORE
          INVOKEINTERFACE org/nlogo/core/I18NJava.getN (Ljava/lang/String;[Ljava/lang/Object;)Ljava/lang/String;
          INVOKESPECIAL org/nlogo/nvm/EngineException.<init> (Lorg/nlogo/nvm/Context;Lorg/nlogo/nvm/Instruction;Ljava/lang/String;)V
          ATHROW
         L8
         FRAME SAME1 I
          ISTORE 2
          ALOAD 1
          ILOAD 2
          IFEQ L9
          BIPUSH 8
          GOTO L10
         L9
         FRAME FULL [org/nlogo/prim/_asm_procedurereturntonest_if_7 org/nlogo/nvm/Context I D] [org/nlogo/nvm/Context]
          BIPUSH 9
         L10
         FRAME FULL [org/nlogo/prim/_asm_procedurereturntonest_if_7 org/nlogo/nvm/Context I D] [org/nlogo/nvm/Context I]
          PUTFIELD org/nlogo/nvm/Context.ip : I
         L11
          RETURN
[8]_asm_procedurereturntonest_setturtlevariable_8 "set drop-size 1" Object => void
      _constdouble:1.0 "1" => Double
          TRYCATCHBLOCK L0 L1 L2 org/nlogo/api/AgentException
         L3
          ALOAD 0
          GETFIELD org/nlogo/prim/_asm_procedurereturntonest_setturtlevariable_8.kept2_value : Ljava/lang/Double;
         L4
          ASTORE 2
         L0
          ALOAD 1
          GETFIELD org/nlogo/nvm/Context.agent : Lorg/nlogo/agent/Agent;
          BIPUSH 14
          ALOAD 2
          INVOKEVIRTUAL org/nlogo/agent/Agent.setTurtleVariable (ILjava/lang/Object;)V
         L1
          GOTO L5
         L2
         FRAME FULL [org/nlogo/prim/_asm_procedurereturntonest_setturtlevariable_8 org/nlogo/nvm/Context java/lang/Double] [org/nlogo/api/AgentException]
          ASTORE 3
          NEW org/nlogo/nvm/EngineException
          DUP
          ALOAD 1
          ALOAD 0
          ALOAD 3
          INVOKEVIRTUAL org/nlogo/api/AgentException.getMessage ()Ljava/lang/String;
          INVOKESPECIAL org/nlogo/nvm/EngineException.<init> (Lorg/nlogo/nvm/Context;Lorg/nlogo/nvm/Instruction;Ljava/lang/String;)V
          ATHROW
         L5
         FRAME SAME
          ALOAD 1
          BIPUSH 9
          PUTFIELD org/nlogo/nvm/Context.ip : I
         L6
          RETURN
[9]_asm_procedurereturntonest_call_9 "uphill-nest-scent"
         L0
          NEW org/nlogo/nvm/Activation
          DUP
          ALOAD 0
          GETFIELD org/nlogo/prim/_asm_procedurereturntonest_call_9.kept1_procedure : Lorg/nlogo/nvm/Procedure;
          ALOAD 1
          GETFIELD org/nlogo/nvm/Context.activation : Lorg/nlogo/nvm/Activation;
          BIPUSH 10
          INVOKESPECIAL org/nlogo/nvm/Activation.<init> (Lorg/nlogo/nvm/Procedure;Lorg/nlogo/nvm/Activation;I)V
          ALOAD 1
          SWAP
          PUTFIELD org/nlogo/nvm/Context.activation : Lorg/nlogo/nvm/Activation;
          ALOAD 1
          ICONST_0
          PUTFIELD org/nlogo/nvm/Context.ip : I
         L1
          RETURN
[10]_asm_procedurereturntonest_call_10 "wiggle"
         L0
          NEW org/nlogo/nvm/Activation
          DUP
          ALOAD 0
          GETFIELD org/nlogo/prim/_asm_procedurereturntonest_call_10.kept1_procedure : Lorg/nlogo/nvm/Procedure;
          ALOAD 1
          GETFIELD org/nlogo/nvm/Context.activation : Lorg/nlogo/nvm/Activation;
          BIPUSH 11
          INVOKESPECIAL org/nlogo/nvm/Activation.<init> (Lorg/nlogo/nvm/Procedure;Lorg/nlogo/nvm/Activation;I)V
          ALOAD 1
          SWAP
          PUTFIELD org/nlogo/nvm/Context.activation : Lorg/nlogo/nvm/Activation;
          ALOAD 1
          ICONST_0
          PUTFIELD org/nlogo/nvm/Context.ip : I
         L1
          RETURN
[11]_asm_procedurereturntonest_fd1_11 "fd 1" => void
          TRYCATCHBLOCK L0 L1 L2 org/nlogo/api/AgentException
         L0
          ALOAD 1
          GETFIELD org/nlogo/nvm/Context.agent : Lorg/nlogo/agent/Agent;
          CHECKCAST org/nlogo/agent/Turtle
          DCONST_1
          INVOKEVIRTUAL org/nlogo/agent/Turtle.jump (D)V
         L1
          GOTO L3
         L2
         FRAME SAME1 org/nlogo/api/AgentException
          ASTORE 2
         L3
         FRAME SAME
          ALOAD 1
          BIPUSH 12
          PUTFIELD org/nlogo/nvm/Context.ip : I
         L4
          RETURN
[12]_asm_procedurereturntonest_return_12 => void
         L0
          ALOAD 1
          INVOKEVIRTUAL org/nlogo/nvm/Context.returnFromProcedure ()V
          ALOAD 1
          ICONST_0
          PUTFIELD org/nlogo/nvm/Context.stopping : Z
         L1
          RETURN

procedure UPDATE-DISPLAY:[]{-TP-}:
[0]_asm_procedureupdatedisplay_ifelse_0 "ifelse nest? [ set pcolor violet ] [ ifelse food > 0 if food-source-number = 1 [ set pcolor cyan ] if food-source-number = 2 [ set pcolor sky ] [ if food-source-number = 3 [ set pcolor blue ] ] [ set pcolor scale-color green chemical 0.1 5 ] ]" boolean => void
      _patchvariable:NEST? "nest?" => Object
          TRYCATCHBLOCK L0 L1 L2 org/nlogo/api/AgentException
          TRYCATCHBLOCK L3 L4 L4 java/lang/ClassCastException
         L0
          ALOAD 1
          GETFIELD org/nlogo/nvm/Context.agent : Lorg/nlogo/agent/Agent;
          BIPUSH 7
          INVOKEVIRTUAL org/nlogo/agent/Agent.getPatchVariable (I)Ljava/lang/Object;
         L1
          GOTO L5
         L2
         FRAME SAME1 org/nlogo/api/AgentException
          ASTORE 2
          NEW org/nlogo/nvm/EngineException
          DUP
          ALOAD 1
          ALOAD 0
          ALOAD 2
          INVOKEVIRTUAL org/nlogo/api/AgentException.getMessage ()Ljava/lang/String;
          INVOKESPECIAL org/nlogo/nvm/EngineException.<init> (Lorg/nlogo/nvm/Context;Lorg/nlogo/nvm/Instruction;Ljava/lang/String;)V
          ATHROW
         L5
         FRAME SAME1 java/lang/Object
          ASTORE 2
         L3
          ALOAD 2
          CHECKCAST java/lang/Boolean
          INVOKEVIRTUAL java/lang/Boolean.booleanValue ()Z
          GOTO L6
         L4
         FRAME FULL [org/nlogo/prim/_asm_procedureupdatedisplay_ifelse_0 org/nlogo/nvm/Context java/lang/Object] [java/lang/ClassCastException]
          POP
          NEW org/nlogo/nvm/ArgumentTypeException
          DUP
          ALOAD 1
          ALOAD 0
          BIPUSH 0
          LDC 2
          ALOAD 2
          INVOKESPECIAL org/nlogo/nvm/ArgumentTypeException.<init> (Lorg/nlogo/nvm/Context;Lorg/nlogo/nvm/Instruction;IILjava/lang/Object;)V
          ATHROW
         L6
         FRAME SAME1 I
          ISTORE 2
          ALOAD 1
          ILOAD 2
          IFEQ L7
          ICONST_1
          GOTO L8
         L7
         FRAME FULL [org/nlogo/prim/_asm_procedureupdatedisplay_ifelse_0 org/nlogo/nvm/Context I] [org/nlogo/nvm/Context]
          ICONST_3
         L8
         FRAME FULL [org/nlogo/prim/_asm_procedureupdatedisplay_ifelse_0 org/nlogo/nvm/Context I] [org/nlogo/nvm/Context I]
          PUTFIELD org/nlogo/nvm/Context.ip : I
         L9
          RETURN
[1]_asm_procedureupdatedisplay_setpatchvariable_1 "set pcolor violet" Object => void
      _constdouble:115.0 "violet" => Double
          TRYCATCHBLOCK L0 L1 L2 org/nlogo/api/AgentException
         L3
          ALOAD 0
          GETFIELD org/nlogo/prim/_asm_procedureupdatedisplay_setpatchvariable_1.kept2_value : Ljava/lang/Double;
         L4
          ASTORE 2
         L0
          ALOAD 1
          GETFIELD org/nlogo/nvm/Context.agent : Lorg/nlogo/agent/Agent;
          ICONST_2
          ALOAD 2
          INVOKEVIRTUAL org/nlogo/agent/Agent.setPatchVariable (ILjava/lang/Object;)V
         L1
          GOTO L5
         L2
         FRAME FULL [org/nlogo/prim/_asm_procedureupdatedisplay_setpatchvariable_1 org/nlogo/nvm/Context java/lang/Double] [org/nlogo/api/AgentException]
          ASTORE 3
          NEW org/nlogo/nvm/EngineException
          DUP
          ALOAD 1
          ALOAD 0
          ALOAD 3
          INVOKEVIRTUAL org/nlogo/api/AgentException.getMessage ()Ljava/lang/String;
          INVOKESPECIAL org/nlogo/nvm/EngineException.<init> (Lorg/nlogo/nvm/Context;Lorg/nlogo/nvm/Instruction;Ljava/lang/String;)V
          ATHROW
         L5
         FRAME SAME
          ALOAD 1
          ICONST_2
          PUTFIELD org/nlogo/nvm/Context.ip : I
         L6
          RETURN
[2]_asm_procedureupdatedisplay_goto_2 => void
         L0
          ALOAD 1
          BIPUSH 12
          PUTFIELD org/nlogo/nvm/Context.ip : I
         L1
          RETURN
[3]_asm_procedureupdatedisplay_ifelse_3 "ifelse food > 0 if food-source-number = 1 [ set pcolor cyan ] if food-source-number = 2 [ set pcolor sky ] [ if food-source-number = 3 [ set pcolor blue ] ] [ set pcolor scale-color green chemical 0.1 5 ]" boolean => void
      _greaterthan "food > 0" Object,double => boolean
        _patchvariable:FOOD "food" => Object
        _constdouble:0.0 "0" => double
          TRYCATCHBLOCK L0 L1 L2 org/nlogo/api/AgentException
         L0
          ALOAD 1
          GETFIELD org/nlogo/nvm/Context.agent : Lorg/nlogo/agent/Agent;
          BIPUSH 6
          INVOKEVIRTUAL org/nlogo/agent/Agent.getPatchVariable (I)Ljava/lang/Object;
         L1
          GOTO L3
         L2
         FRAME SAME1 org/nlogo/api/AgentException
          ASTORE 2
          NEW org/nlogo/nvm/EngineException
          DUP
          ALOAD 1
          ALOAD 0
          ALOAD 2
          INVOKEVIRTUAL org/nlogo/api/AgentException.getMessage ()Ljava/lang/String;
          INVOKESPECIAL org/nlogo/nvm/EngineException.<init> (Lorg/nlogo/nvm/Context;Lorg/nlogo/nvm/Instruction;Ljava/lang/String;)V
          ATHROW
         L3
         FRAME SAME1 java/lang/Object
          DCONST_0
         L4
          DSTORE 3
          ASTORE 2
          ALOAD 2
          INSTANCEOF java/lang/Double
          IFEQ L5
          ALOAD 2
          CHECKCAST java/lang/Double
          INVOKEVIRTUAL java/lang/Double.doubleValue ()D
          DLOAD 3
          DCMPL
          IFLE L6
          ICONST_1
          GOTO L7
         L6
         FRAME APPEND [java/lang/Object D]
          ICONST_0
         L7
         FRAME SAME1 I
          GOTO L8
         L5
         FRAME SAME
          NEW org/nlogo/nvm/EngineException
          DUP
          ALOAD 1
          ALOAD 0
          INVOKESTATIC org/nlogo/core/I18N.errorsJ ()Lorg/nlogo/core/I18NJava;
          LDC "org.nlogo.prim._greaterthan.cannotCompareParameters"
          ICONST_2
          ANEWARRAY java/lang/Object
          DUP
          ICONST_0
          ALOAD 2
          INVOKESTATIC org/nlogo/api/TypeNames.aName (Ljava/lang/Object;)Ljava/lang/String;
          AASTORE
          DUP
          ICONST_1
          DLOAD 3
          INVOKESTATIC java/lang/Double.valueOf (D)Ljava/lang/Double;
          INVOKESTATIC org/nlogo/api/TypeNames.aName (Ljava/lang/Object;)Ljava/lang/String;
          AASTORE
          INVOKEINTERFACE org/nlogo/core/I18NJava.getN (Ljava/lang/String;[Ljava/lang/Object;)Ljava/lang/String;
          INVOKESPECIAL org/nlogo/nvm/EngineException.<init> (Lorg/nlogo/nvm/Context;Lorg/nlogo/nvm/Instruction;Ljava/lang/String;)V
          ATHROW
         L8
         FRAME SAME1 I
          ISTORE 2
          ALOAD 1
          ILOAD 2
          IFEQ L9
          ICONST_4
          GOTO L10
         L9
         FRAME FULL [org/nlogo/prim/_asm_procedureupdatedisplay_ifelse_3 org/nlogo/nvm/Context I D] [org/nlogo/nvm/Context]
          BIPUSH 11
         L10
         FRAME FULL [org/nlogo/prim/_asm_procedureupdatedisplay_ifelse_3 org/nlogo/nvm/Context I D] [org/nlogo/nvm/Context I]
          PUTFIELD org/nlogo/nvm/Context.ip : I
         L11
          RETURN
[4]_asm_procedureupdatedisplay_if_4 "if food-source-number = 1 [ set pcolor cyan ]" boolean => void
      _equal "food-source-number = 1" Object,double => boolean
        _patchvariable:FOOD-SOURCE-NUMBER "food-source-number" => Object
        _constdouble:1.0 "1" => double
          TRYCATCHBLOCK L0 L1 L2 org/nlogo/api/AgentException
         L0
          ALOAD 1
          GETFIELD org/nlogo/nvm/Context.agent : Lorg/nlogo/agent/Agent;
          BIPUSH 9
          INVOKEVIRTUAL org/nlogo/agent/Agent.getPatchVariable (I)Ljava/lang/Object;
         L1
          GOTO L3
         L2
         FRAME SAME1 org/nlogo/api/AgentException
          ASTORE 2
          NEW org/nlogo/nvm/EngineException
          DUP
          ALOAD 1
          ALOAD 0
          ALOAD 2
          INVOKEVIRTUAL org/nlogo/api/AgentException.getMessage ()Ljava/lang/String;
          INVOKESPECIAL org/nlogo/nvm/EngineException.<init> (Lorg/nlogo/nvm/Context;Lorg/nlogo/nvm/Instruction;Ljava/lang/String;)V
          ATHROW
         L3
         FRAME SAME1 java/lang/Object
          DCONST_1
         L4
          DSTORE 3
          ASTORE 2
          ALOAD 2
          INSTANCEOF java/lang/Double
          IFEQ L5
          DLOAD 3
          ALOAD 2
          CHECKCAST java/lang/Double
          INVOKEVIRTUAL java/lang/Double.doubleValue ()D
          DCMPL
          IFNE L5
          ICONST_1
          GOTO L6
         L5
         FRAME APPEND [java/lang/Object D]
          ICONST_0
         L6
         FRAME SAME1 I
          ISTORE 2
          ALOAD 1
          ILOAD 2
          IFEQ L7
          ICONST_5
          GOTO L8
         L7
         FRAME FULL [org/nlogo/prim/_asm_procedureupdatedisplay_if_4 org/nlogo/nvm/Context I D] [org/nlogo/nvm/Context]
          BIPUSH 6
         L8
         FRAME FULL [org/nlogo/prim/_asm_procedureupdatedisplay_if_4 org/nlogo/nvm/Context I D] [org/nlogo/nvm/Context I]
          PUTFIELD org/nlogo/nvm/Context.ip : I
         L9
          RETURN
[5]_asm_procedureupdatedisplay_setpatchvariable_5 "set pcolor cyan" Object => void
      _constdouble:85.0 "cyan" => Double
          TRYCATCHBLOCK L0 L1 L2 org/nlogo/api/AgentException
         L3
          ALOAD 0
          GETFIELD org/nlogo/prim/_asm_procedureupdatedisplay_setpatchvariable_5.kept2_value : Ljava/lang/Double;
         L4
          ASTORE 2
         L0
          ALOAD 1
          GETFIELD org/nlogo/nvm/Context.agent : Lorg/nlogo/agent/Agent;
          ICONST_2
          ALOAD 2
          INVOKEVIRTUAL org/nlogo/agent/Agent.setPatchVariable (ILjava/lang/Object;)V
         L1
          GOTO L5
         L2
         FRAME FULL [org/nlogo/prim/_asm_procedureupdatedisplay_setpatchvariable_5 org/nlogo/nvm/Context java/lang/Double] [org/nlogo/api/AgentException]
          ASTORE 3
          NEW org/nlogo/nvm/EngineException
          DUP
          ALOAD 1
          ALOAD 0
          ALOAD 3
          INVOKEVIRTUAL org/nlogo/api/AgentException.getMessage ()Ljava/lang/String;
          INVOKESPECIAL org/nlogo/nvm/EngineException.<init> (Lorg/nlogo/nvm/Context;Lorg/nlogo/nvm/Instruction;Ljava/lang/String;)V
          ATHROW
         L5
         FRAME SAME
          ALOAD 1
          BIPUSH 6
          PUTFIELD org/nlogo/nvm/Context.ip : I
         L6
          RETURN
[6]_asm_procedureupdatedisplay_if_6 "if food-source-number = 2 [ set pcolor sky ]" boolean => void
      _equal "food-source-number = 2" Object,double => boolean
        _patchvariable:FOOD-SOURCE-NUMBER "food-source-number" => Object
        _constdouble:2.0 "2" => double
          TRYCATCHBLOCK L0 L1 L2 org/nlogo/api/AgentException
         L0
          ALOAD 1
          GETFIELD org/nlogo/nvm/Context.agent : Lorg/nlogo/agent/Agent;
          BIPUSH 9
          INVOKEVIRTUAL org/nlogo/agent/Agent.getPatchVariable (I)Ljava/lang/Object;
         L1
          GOTO L3
         L2
         FRAME SAME1 org/nlogo/api/AgentException
          ASTORE 2
          NEW org/nlogo/nvm/EngineException
          DUP
          ALOAD 1
          ALOAD 0
          ALOAD 2
          INVOKEVIRTUAL org/nlogo/api/AgentException.getMessage ()Ljava/lang/String;
          INVOKESPECIAL org/nlogo/nvm/EngineException.<init> (Lorg/nlogo/nvm/Context;Lorg/nlogo/nvm/Instruction;Ljava/lang/String;)V
          ATHROW
         L3
         FRAME SAME1 java/lang/Object
          LDC 2.0
         L4
          DSTORE 3
          ASTORE 2
          ALOAD 2
          INSTANCEOF java/lang/Double
          IFEQ L5
          DLOAD 3
          ALOAD 2
          CHECKCAST java/lang/Double
          INVOKEVIRTUAL java/lang/Double.doubleValue ()D
          DCMPL
          IFNE L5
          ICONST_1
          GOTO L6
         L5
         FRAME APPEND [java/lang/Object D]
          ICONST_0
         L6
         FRAME SAME1 I
          ISTORE 2
          ALOAD 1
          ILOAD 2
          IFEQ L7
          BIPUSH 7
          GOTO L8
         L7
         FRAME FULL [org/nlogo/prim/_asm_procedureupdatedisplay_if_6 org/nlogo/nvm/Context I D] [org/nlogo/nvm/Context]
          BIPUSH 8
         L8
         FRAME FULL [org/nlogo/prim/_asm_procedureupdatedisplay_if_6 org/nlogo/nvm/Context I D] [org/nlogo/nvm/Context I]
          PUTFIELD org/nlogo/nvm/Context.ip : I
         L9
          RETURN
[7]_asm_procedureupdatedisplay_setpatchvariable_7 "set pcolor sky" Object => void
      _constdouble:95.0 "sky" => Double
          TRYCATCHBLOCK L0 L1 L2 org/nlogo/api/AgentException
         L3
          ALOAD 0
          GETFIELD org/nlogo/prim/_asm_procedureupdatedisplay_setpatchvariable_7.kept2_value : Ljava/lang/Double;
         L4
          ASTORE 2
         L0
          ALOAD 1
          GETFIELD org/nlogo/nvm/Context.agent : Lorg/nlogo/agent/Agent;
          ICONST_2
          ALOAD 2
          INVOKEVIRTUAL org/nlogo/agent/Agent.setPatchVariable (ILjava/lang/Object;)V
         L1
          GOTO L5
         L2
         FRAME FULL [org/nlogo/prim/_asm_procedureupdatedisplay_setpatchvariable_7 org/nlogo/nvm/Context java/lang/Double] [org/nlogo/api/AgentException]
          ASTORE 3
          NEW org/nlogo/nvm/EngineException
          DUP
          ALOAD 1
          ALOAD 0
          ALOAD 3
          INVOKEVIRTUAL org/nlogo/api/AgentException.getMessage ()Ljava/lang/String;
          INVOKESPECIAL org/nlogo/nvm/EngineException.<init> (Lorg/nlogo/nvm/Context;Lorg/nlogo/nvm/Instruction;Ljava/lang/String;)V
          ATHROW
         L5
         FRAME SAME
          ALOAD 1
          BIPUSH 8
          PUTFIELD org/nlogo/nvm/Context.ip : I
         L6
          RETURN
[8]_asm_procedureupdatedisplay_if_8 "if food-source-number = 3 [ set pcolor blue ]" boolean => void
      _equal "food-source-number = 3" Object,double => boolean
        _patchvariable:FOOD-SOURCE-NUMBER "food-source-number" => Object
        _constdouble:3.0 "3" => double
          TRYCATCHBLOCK L0 L1 L2 org/nlogo/api/AgentException
         L0
          ALOAD 1
          GETFIELD org/nlogo/nvm/Context.agent : Lorg/nlogo/agent/Agent;
          BIPUSH 9
          INVOKEVIRTUAL org/nlogo/agent/Agent.getPatchVariable (I)Ljava/lang/Object;
         L1
          GOTO L3
         L2
         FRAME SAME1 org/nlogo/api/AgentException
          ASTORE 2
          NEW org/nlogo/nvm/EngineException
          DUP
          ALOAD 1
          ALOAD 0
          ALOAD 2
          INVOKEVIRTUAL org/nlogo/api/AgentException.getMessage ()Ljava/lang/String;
          INVOKESPECIAL org/nlogo/nvm/EngineException.<init> (Lorg/nlogo/nvm/Context;Lorg/nlogo/nvm/Instruction;Ljava/lang/String;)V
          ATHROW
         L3
         FRAME SAME1 java/lang/Object
          LDC 3.0
         L4
          DSTORE 3
          ASTORE 2
          ALOAD 2
          INSTANCEOF java/lang/Double
          IFEQ L5
          DLOAD 3
          ALOAD 2
          CHECKCAST java/lang/Double
          INVOKEVIRTUAL java/lang/Double.doubleValue ()D
          DCMPL
          IFNE L5
          ICONST_1
          GOTO L6
         L5
         FRAME APPEND [java/lang/Object D]
          ICONST_0
         L6
         FRAME SAME1 I
          ISTORE 2
          ALOAD 1
          ILOAD 2
          IFEQ L7
          BIPUSH 9
          GOTO L8
         L7
         FRAME FULL [org/nlogo/prim/_asm_procedureupdatedisplay_if_8 org/nlogo/nvm/Context I D] [org/nlogo/nvm/Context]
          BIPUSH 10
         L8
         FRAME FULL [org/nlogo/prim/_asm_procedureupdatedisplay_if_8 org/nlogo/nvm/Context I D] [org/nlogo/nvm/Context I]
          PUTFIELD org/nlogo/nvm/Context.ip : I
         L9
          RETURN
[9]_asm_procedureupdatedisplay_setpatchvariable_9 "set pcolor blue" Object => void
      _constdouble:105.0 "blue" => Double
          TRYCATCHBLOCK L0 L1 L2 org/nlogo/api/AgentException
         L3
          ALOAD 0
          GETFIELD org/nlogo/prim/_asm_procedureupdatedisplay_setpatchvariable_9.kept2_value : Ljava/lang/Double;
         L4
          ASTORE 2
         L0
          ALOAD 1
          GETFIELD org/nlogo/nvm/Context.agent : Lorg/nlogo/agent/Agent;
          ICONST_2
          ALOAD 2
          INVOKEVIRTUAL org/nlogo/agent/Agent.setPatchVariable (ILjava/lang/Object;)V
         L1
          GOTO L5
         L2
         FRAME FULL [org/nlogo/prim/_asm_procedureupdatedisplay_setpatchvariable_9 org/nlogo/nvm/Context java/lang/Double] [org/nlogo/api/AgentException]
          ASTORE 3
          NEW org/nlogo/nvm/EngineException
          DUP
          ALOAD 1
          ALOAD 0
          ALOAD 3
          INVOKEVIRTUAL org/nlogo/api/AgentException.getMessage ()Ljava/lang/String;
          INVOKESPECIAL org/nlogo/nvm/EngineException.<init> (Lorg/nlogo/nvm/Context;Lorg/nlogo/nvm/Instruction;Ljava/lang/String;)V
          ATHROW
         L5
         FRAME SAME
          ALOAD 1
          BIPUSH 10
          PUTFIELD org/nlogo/nvm/Context.ip : I
         L6
          RETURN
[10]_asm_procedureupdatedisplay_goto_10 => void
         L0
          ALOAD 1
          BIPUSH 12
          PUTFIELD org/nlogo/nvm/Context.ip : I
         L1
          RETURN
[11]_asm_procedureupdatedisplay_setpatchvariable_11 "set pcolor scale-color green chemical 0.1 5" Object => void
      _scalecolor "scale-color green chemical 0.1 5" double,double,double,double => double
        _constdouble:55.0 "green" => double
        _patchvariable:CHEMICAL "chemical" => Object
        _constdouble:0.1 "0.1" => double
        _constdouble:5.0 "5" => double
          TRYCATCHBLOCK L0 L1 L2 org/nlogo/api/AgentException
          TRYCATCHBLOCK L3 L4 L4 java/lang/ClassCastException
          TRYCATCHBLOCK L5 L6 L7 org/nlogo/api/AgentException
         L8
          LDC 55.0
         L0
          ALOAD 1
          GETFIELD org/nlogo/nvm/Context.agent : Lorg/nlogo/agent/Agent;
          ICONST_5
          INVOKEVIRTUAL org/nlogo/agent/Agent.getPatchVariable (I)Ljava/lang/Object;
         L1
          GOTO L9
         L2
         FRAME SAME1 org/nlogo/api/AgentException
          ASTORE 2
          NEW org/nlogo/nvm/EngineException
          DUP
          ALOAD 1
          ALOAD 0
          ALOAD 2
          INVOKEVIRTUAL org/nlogo/api/AgentException.getMessage ()Ljava/lang/String;
          INVOKESPECIAL org/nlogo/nvm/EngineException.<init> (Lorg/nlogo/nvm/Context;Lorg/nlogo/nvm/Instruction;Ljava/lang/String;)V
          ATHROW
         L9
         FRAME FULL [org/nlogo/prim/_asm_procedureupdatedisplay_setpatchvariable_11 org/nlogo/nvm/Context] [D java/lang/Object]
          ASTORE 2
         L3
          ALOAD 2
          CHECKCAST java/lang/Double
          INVOKEVIRTUAL java/lang/Double.doubleValue ()D
          GOTO L10
         L4
         FRAME FULL [org/nlogo/prim/_asm_procedureupdatedisplay_setpatchvariable_11 org/nlogo/nvm/Context java/lang/Object] [java/lang/ClassCastException]
          POP
          NEW org/nlogo/nvm/ArgumentTypeException
          DUP
          ALOAD 1
          ALOAD 0
          BIPUSH 1
          LDC 1
          ALOAD 2
          INVOKESPECIAL org/nlogo/nvm/ArgumentTypeException.<init> (Lorg/nlogo/nvm/Context;Lorg/nlogo/nvm/Instruction;IILjava/lang/Object;)V
          ATHROW
         L10
         FRAME FULL [org/nlogo/prim/_asm_procedureupdatedisplay_setpatchvariable_11 org/nlogo/nvm/Context java/lang/Object] [D D]
          LDC 0.1
         L11
          LDC 5.0
         L12
          DSTORE 8
          DSTORE 6
          DSTORE 4
          DSTORE 2
          DLOAD 2
          INVOKESTATIC org/nlogo/api/Color.findCentralColorNumber (D)D
          LDC 5.0
          DSUB
          DSTORE 2
          DCONST_0
          DSTORE 10
          DLOAD 6
          DLOAD 8
          DCMPL
          IFLE L13
          DLOAD 4
          DLOAD 8
          DCMPG
          IFGE L14
          DCONST_1
          DSTORE 10
          GOTO L15
         L14
         FRAME FULL [org/nlogo/prim/_asm_procedureupdatedisplay_setpatchvariable_11 org/nlogo/nvm/Context D D D D D] []
          DLOAD 4
          DLOAD 6
          DCMPL
          IFLE L16
          DCONST_0
          DSTORE 10
          GOTO L15
         L16
         FRAME SAME
          DLOAD 6
          DLOAD 4
          DSUB
          DSTORE 12
          DLOAD 6
          DLOAD 8
          DSUB
          DSTORE 14
          DLOAD 12
          DLOAD 14
          DDIV
          DSTORE 10
          GOTO L15
         L13
         FRAME SAME
          DLOAD 4
          DLOAD 8
          DCMPL
          IFLE L17
          DCONST_1
          DSTORE 10
          GOTO L15
         L17
         FRAME SAME
          DLOAD 4
          DLOAD 6
          DCMPG
          IFGE L18
          DCONST_0
          DSTORE 10
          GOTO L15
         L18
         FRAME SAME
          DLOAD 4
          DLOAD 6
          DSUB
          DSTORE 12
          DLOAD 8
          DLOAD 6
          DSUB
          DSTORE 14
          DLOAD 12
          DLOAD 14
          DDIV
          DSTORE 10
         L15
         FRAME SAME
          DLOAD 10
          LDC 10.0
          DMUL
          DSTORE 10
          DLOAD 10
          LDC 9.9999
          DCMPL
          IFLT L19
          LDC 9.9999
          DSTORE 10
          GOTO L20
         L19
         FRAME SAME
          DLOAD 10
          DCONST_0
          DCMPG
          IFGE L20
          DCONST_0
          DSTORE 10
         L20
         FRAME SAME
          ALOAD 0
          DLOAD 2
          DLOAD 10
          DADD
          INVOKEVIRTUAL org/nlogo/prim/_asm_procedureupdatedisplay_setpatchvariable_11.validDouble (D)D
         L21
          DSTORE 2
          NEW java/lang/Double
          DUP
          DLOAD 2
          INVOKESPECIAL java/lang/Double.<init> (D)V
          ASTORE 2
         L5
          ALOAD 1
          GETFIELD org/nlogo/nvm/Context.agent : Lorg/nlogo/agent/Agent;
          ICONST_2
          ALOAD 2
          INVOKEVIRTUAL org/nlogo/agent/Agent.setPatchVariable (ILjava/lang/Object;)V
         L6
          GOTO L22
         L7
         FRAME FULL [org/nlogo/prim/_asm_procedureupdatedisplay_setpatchvariable_11 org/nlogo/nvm/Context java/lang/Double T D D D D] [org/nlogo/api/AgentException]
          ASTORE 3
          NEW org/nlogo/nvm/EngineException
          DUP
          ALOAD 1
          ALOAD 0
          ALOAD 3
          INVOKEVIRTUAL org/nlogo/api/AgentException.getMessage ()Ljava/lang/String;
          INVOKESPECIAL org/nlogo/nvm/EngineException.<init> (Lorg/nlogo/nvm/Context;Lorg/nlogo/nvm/Instruction;Ljava/lang/String;)V
          ATHROW
         L22
         FRAME SAME
          ALOAD 1
          BIPUSH 12
          PUTFIELD org/nlogo/nvm/Context.ip : I
         L23
          RETURN
[12]_asm_procedureupdatedisplay_return_12 => void
         L0
          ALOAD 1
          INVOKEVIRTUAL org/nlogo/nvm/Context.returnFromProcedure ()V
          ALOAD 1
          ICONST_0
          PUTFIELD org/nlogo/nvm/Context.stopping : Z
         L1
          RETURN

procedure SETUP-TURTLES:[]{O---}:
[0]_setdefaultshape "set-default-shape turtles "bug""
      _asm_proceduresetupturtles_turtles_0 "turtles" => AgentSet
           L0
            ALOAD 0
            GETFIELD org/nlogo/prim/_asm_proceduresetupturtles_turtles_0.world : Lorg/nlogo/agent/World;
            INVOKEVIRTUAL org/nlogo/agent/World.turtles ()Lorg/nlogo/agent/AgentSet;
           L1
            ARETURN
      _asm_proceduresetupturtles_conststring_1 ""bug"" => String
           L0
            LDC "bug"
           L1
            ARETURN
[1]_createorderedturtles:,+7 "cro ants set size 2 rt random-float 360 set color red [ set carrying-food? false ]"
      _asm_proceduresetupturtles_observervariable_2 "ants" => Object
           L0
            ALOAD 1
            GETFIELD org/nlogo/nvm/Context.agent : Lorg/nlogo/agent/Agent;
            ICONST_3
            INVOKEVIRTUAL org/nlogo/agent/Agent.getObserverVariable (I)Ljava/lang/Object;
           L1
            ARETURN
[2]_asm_proceduresetupturtles_setturtlevariable_3 "set size 2" Object => void
      _constdouble:2.0 "2" => Double
          TRYCATCHBLOCK L0 L1 L2 org/nlogo/api/AgentException
         L3
          ALOAD 0
          GETFIELD org/nlogo/prim/_asm_proceduresetupturtles_setturtlevariable_3.kept2_value : Ljava/lang/Double;
         L4
          ASTORE 2
         L0
          ALOAD 1
          GETFIELD org/nlogo/nvm/Context.agent : Lorg/nlogo/agent/Agent;
          BIPUSH 10
          ALOAD 2
          INVOKEVIRTUAL org/nlogo/agent/Agent.setTurtleVariable (ILjava/lang/Object;)V
         L1
          GOTO L5
         L2
         FRAME FULL [org/nlogo/prim/_asm_proceduresetupturtles_setturtlevariable_3 org/nlogo/nvm/Context java/lang/Double] [org/nlogo/api/AgentException]
          ASTORE 3
          NEW org/nlogo/nvm/EngineException
          DUP
          ALOAD 1
          ALOAD 0
          ALOAD 3
          INVOKEVIRTUAL org/nlogo/api/AgentException.getMessage ()Ljava/lang/String;
          INVOKESPECIAL org/nlogo/nvm/EngineException.<init> (Lorg/nlogo/nvm/Context;Lorg/nlogo/nvm/Instruction;Ljava/lang/String;)V
          ATHROW
         L5
         FRAME SAME
          ALOAD 1
          ICONST_3
          PUTFIELD org/nlogo/nvm/Context.ip : I
         L6
          RETURN
[3]_asm_proceduresetupturtles_right_4 "rt random-float 360" double => void
      _randomfloat "random-float 360" double => double
        _constdouble:360.0 "360" => double
         L0
          LDC 360.0
         L1
          DSTORE 2
          ALOAD 0
          DLOAD 2
          ALOAD 1
          GETFIELD org/nlogo/nvm/Context.job : Lorg/nlogo/nvm/Job;
          GETFIELD org/nlogo/nvm/Job.random : Lorg/nlogo/api/MersenneTwisterFast;
          INVOKEVIRTUAL org/nlogo/api/MersenneTwisterFast.nextDouble ()D
          DMUL
          INVOKEVIRTUAL org/nlogo/prim/_asm_proceduresetupturtles_right_4.validDouble (D)D
         L2
          DSTORE 2
          ALOAD 1
          GETFIELD org/nlogo/nvm/Context.agent : Lorg/nlogo/agent/Agent;
          CHECKCAST org/nlogo/agent/Turtle
          DLOAD 2
          INVOKEVIRTUAL org/nlogo/agent/Turtle.turnRight (D)V
          ALOAD 1
          ICONST_4
          PUTFIELD org/nlogo/nvm/Context.ip : I
         L3
          RETURN
[4]_asm_proceduresetupturtles_setturtleorlinkvariable_5 "set color red" Object => void
      _constdouble:15.0 "red" => Double
          TRYCATCHBLOCK L0 L1 L2 org/nlogo/api/AgentException
         L3
          ALOAD 0
          GETFIELD org/nlogo/prim/_asm_proceduresetupturtles_setturtleorlinkvariable_5.kept2_value : Ljava/lang/Double;
         L4
          ASTORE 2
         L0
          ALOAD 1
          GETFIELD org/nlogo/nvm/Context.agent : Lorg/nlogo/agent/Agent;
          LDC "COLOR"
          ALOAD 2
          INVOKEVIRTUAL org/nlogo/agent/Agent.setTurtleOrLinkVariable (Ljava/lang/String;Ljava/lang/Object;)V
         L1
          GOTO L5
         L2
         FRAME FULL [org/nlogo/prim/_asm_proceduresetupturtles_setturtleorlinkvariable_5 org/nlogo/nvm/Context java/lang/Double] [org/nlogo/api/AgentException]
          ASTORE 3
          NEW org/nlogo/nvm/EngineException
          DUP
          ALOAD 1
          ALOAD 0
          ALOAD 3
          INVOKEVIRTUAL org/nlogo/api/AgentException.getMessage ()Ljava/lang/String;
          INVOKESPECIAL org/nlogo/nvm/EngineException.<init> (Lorg/nlogo/nvm/Context;Lorg/nlogo/nvm/Instruction;Ljava/lang/String;)V
          ATHROW
         L5
         FRAME SAME
          ALOAD 1
          ICONST_5
          PUTFIELD org/nlogo/nvm/Context.ip : I
         L6
          RETURN
[5]_asm_proceduresetupturtles_setturtlevariable_6 "set carrying-food? false" Object => void
      _constboolean:false "false" => Boolean
          TRYCATCHBLOCK L0 L1 L2 org/nlogo/api/AgentException
         L3
          ALOAD 0
          GETFIELD org/nlogo/prim/_asm_proceduresetupturtles_setturtlevariable_6.kept2_value : Ljava/lang/Boolean;
         L4
          ASTORE 2
         L0
          ALOAD 1
          GETFIELD org/nlogo/nvm/Context.agent : Lorg/nlogo/agent/Agent;
          BIPUSH 13
          ALOAD 2
          INVOKEVIRTUAL org/nlogo/agent/Agent.setTurtleVariable (ILjava/lang/Object;)V
         L1
          GOTO L5
         L2
         FRAME FULL [org/nlogo/prim/_asm_proceduresetupturtles_setturtlevariable_6 org/nlogo/nvm/Context java/lang/Boolean] [org/nlogo/api/AgentException]
          ASTORE 3
          NEW org/nlogo/nvm/EngineException
          DUP
          ALOAD 1
          ALOAD 0
          ALOAD 3
          INVOKEVIRTUAL org/nlogo/api/AgentException.getMessage ()Ljava/lang/String;
          INVOKESPECIAL org/nlogo/nvm/EngineException.<init> (Lorg/nlogo/nvm/Context;Lorg/nlogo/nvm/Instruction;Ljava/lang/String;)V
          ATHROW
         L5
         FRAME SAME
          ALOAD 1
          BIPUSH 6
          PUTFIELD org/nlogo/nvm/Context.ip : I
         L6
          RETURN
[6]_asm_proceduresetupturtles_done_7 => void
         L0
          ALOAD 1
          ICONST_1
          PUTFIELD org/nlogo/nvm/Context.finished : Z
         L1
          RETURN
[7]_asm_proceduresetupturtles_return_8 => void
         L0
          ALOAD 1
          INVOKEVIRTUAL org/nlogo/nvm/Context.returnFromProcedure ()V
          ALOAD 1
          ICONST_0
          PUTFIELD org/nlogo/nvm/Context.stopping : Z
         L1
          RETURN

procedure WIGGLE:[]{-T--}:
[0]_asm_procedurewiggle_right_0 "rt random 40 - random 40" double => void
      _minus "random 40 - random 40" double,double => double
        _randomconst:40 "random 40" => double
        _randomconst:40 "random 40" => double
         L0
          ALOAD 1
          GETFIELD org/nlogo/nvm/Context.job : Lorg/nlogo/nvm/Job;
          GETFIELD org/nlogo/nvm/Job.random : Lorg/nlogo/api/MersenneTwisterFast;
          LDC 40
          INVOKEVIRTUAL org/nlogo/api/MersenneTwisterFast.nextLong (J)J
          L2D
         L1
          ALOAD 1
          GETFIELD org/nlogo/nvm/Context.job : Lorg/nlogo/nvm/Job;
          GETFIELD org/nlogo/nvm/Job.random : Lorg/nlogo/api/MersenneTwisterFast;
          LDC 40
          INVOKEVIRTUAL org/nlogo/api/MersenneTwisterFast.nextLong (J)J
          L2D
         L2
          DSTORE 4
          DSTORE 2
          ALOAD 0
          DLOAD 2
          DLOAD 4
          DSUB
          INVOKEVIRTUAL org/nlogo/prim/_asm_procedurewiggle_right_0.validDouble (D)D
         L3
          DSTORE 2
          ALOAD 1
          GETFIELD org/nlogo/nvm/Context.agent : Lorg/nlogo/agent/Agent;
          CHECKCAST org/nlogo/agent/Turtle
          DLOAD 2
          INVOKEVIRTUAL org/nlogo/agent/Turtle.turnRight (D)V
          ALOAD 1
          ICONST_1
          PUTFIELD org/nlogo/nvm/Context.ip : I
         L4
          RETURN
[1]_asm_procedurewiggle_if_1 "if not can-move? 1 [ rt 180 ]" boolean => void
      _not "not can-move? 1" boolean => boolean
        _canmove "can-move? 1"
          _asm_procedurewiggle_constdouble_2 "1" => Double
               L0
                ALOAD 0
                GETFIELD org/nlogo/prim/_asm_procedurewiggle_constdouble_2.kept1_value : Ljava/lang/Double;
               L1
                ARETURN
          TRYCATCHBLOCK L0 L1 L1 java/lang/ClassCastException
          ALOAD 0
          GETFIELD org/nlogo/prim/_asm_procedurewiggle_if_1.keptinstr3 : Lorg/nlogo/prim/etc/_canmove;
          ALOAD 1
          INVOKEVIRTUAL org/nlogo/prim/etc/_canmove.report (Lorg/nlogo/nvm/Context;)Ljava/lang/Object;
         L2
          ASTORE 2
         L0
          ALOAD 2
          CHECKCAST java/lang/Boolean
          INVOKEVIRTUAL java/lang/Boolean.booleanValue ()Z
          GOTO L3
         L1
         FRAME FULL [org/nlogo/prim/_asm_procedurewiggle_if_1 org/nlogo/nvm/Context java/lang/Object] [java/lang/ClassCastException]
          POP
          NEW org/nlogo/nvm/ArgumentTypeException
          DUP
          ALOAD 1
          ALOAD 0
          BIPUSH 0
          LDC 2
          ALOAD 2
          INVOKESPECIAL org/nlogo/nvm/ArgumentTypeException.<init> (Lorg/nlogo/nvm/Context;Lorg/nlogo/nvm/Instruction;IILjava/lang/Object;)V
          ATHROW
         L3
         FRAME SAME1 I
          ISTORE 2
          ILOAD 2
          IFNE L4
          ICONST_1
          GOTO L5
         L4
         FRAME FULL [org/nlogo/prim/_asm_procedurewiggle_if_1 org/nlogo/nvm/Context I] []
          ICONST_0
         L5
         FRAME SAME1 I
          ISTORE 2
          ALOAD 1
          ILOAD 2
          IFEQ L6
          ICONST_2
          GOTO L7
         L6
         FRAME SAME1 org/nlogo/nvm/Context
          ICONST_3
         L7
         FRAME FULL [org/nlogo/prim/_asm_procedurewiggle_if_1 org/nlogo/nvm/Context I] [org/nlogo/nvm/Context I]
          PUTFIELD org/nlogo/nvm/Context.ip : I
         L8
          RETURN
[2]_asm_procedurewiggle_right_3 "rt 180" double => void
      _constdouble:180.0 "180" => double
         L0
          LDC 180.0
         L1
          DSTORE 2
          ALOAD 1
          GETFIELD org/nlogo/nvm/Context.agent : Lorg/nlogo/agent/Agent;
          CHECKCAST org/nlogo/agent/Turtle
          DLOAD 2
          INVOKEVIRTUAL org/nlogo/agent/Turtle.turnRight (D)V
          ALOAD 1
          ICONST_3
          PUTFIELD org/nlogo/nvm/Context.ip : I
         L2
          RETURN
[3]_asm_procedurewiggle_return_4 => void
         L0
          ALOAD 1
          INVOKEVIRTUAL org/nlogo/nvm/Context.returnFromProcedure ()V
          ALOAD 1
          ICONST_0
          PUTFIELD org/nlogo/nvm/Context.stopping : Z
         L1
          RETURN

reporter procedure GET-NEST-SCENT:[ANGLE P]{-T--}:
[0]_asm_proceduregetnestscent_setprocedurevariable_0 "let patch-right-and-ahead angle 1" Object => void
      _patchrightandahead "patch-right-and-ahead angle 1"
        _asm_proceduregetnestscent_procedurevariable_1 "angle" => Object
             L0
              ALOAD 1
              GETFIELD org/nlogo/nvm/Context.activation : Lorg/nlogo/nvm/Activation;
              GETFIELD org/nlogo/nvm/Activation.args : [Ljava/lang/Object;
              ICONST_0
              AALOAD
             L1
              ARETURN
        _asm_proceduregetnestscent_constdouble_2 "1" => Double
             L0
              ALOAD 0
              GETFIELD org/nlogo/prim/_asm_proceduregetnestscent_constdouble_2.kept1_value : Ljava/lang/Double;
             L1
              ARETURN
          ALOAD 0
          GETFIELD org/nlogo/prim/_asm_proceduregetnestscent_setprocedurevariable_0.keptinstr2 : Lorg/nlogo/prim/etc/_patchrightandahead;
          ALOAD 1
          INVOKEVIRTUAL org/nlogo/prim/etc/_patchrightandahead.report (Lorg/nlogo/nvm/Context;)Ljava/lang/Object;
         L0
          ASTORE 2
          ALOAD 1
          GETFIELD org/nlogo/nvm/Context.activation : Lorg/nlogo/nvm/Activation;
          GETFIELD org/nlogo/nvm/Activation.args : [Ljava/lang/Object;
          ICONST_1
          ALOAD 2
          AASTORE
          ALOAD 1
          ICONST_1
          PUTFIELD org/nlogo/nvm/Context.ip : I
         L1
          RETURN
[1]_asm_proceduregetnestscent_if_3 "if p != nobody [ report [ nest-scent ] of p ]" boolean => void
      _notequal "p != nobody" Object,Object => boolean
        _procedurevariable:P "p" => Object
        _nobody "nobody" => Nobody$
         L0
          ALOAD 1
          GETFIELD org/nlogo/nvm/Context.activation : Lorg/nlogo/nvm/Activation;
          GETFIELD org/nlogo/nvm/Activation.args : [Ljava/lang/Object;
          ICONST_1
          AALOAD
         L1
          GETSTATIC org/nlogo/core/Nobody$.MODULE$ : Lorg/nlogo/core/Nobody$;
         L2
          ASTORE 3
          ASTORE 2
          ALOAD 2
          ALOAD 3
          INVOKESTATIC org/nlogo/api/Equality.equals (Ljava/lang/Object;Ljava/lang/Object;)Z
          IFNE L3
          ICONST_1
          GOTO L4
         L3
         FRAME APPEND [java/lang/Object org/nlogo/core/Nobody$]
          ICONST_0
         L4
         FRAME SAME1 I
          ISTORE 2
          ALOAD 1
          ILOAD 2
          IFEQ L5
          ICONST_2
          GOTO L6
         L5
         FRAME FULL [org/nlogo/prim/_asm_proceduregetnestscent_if_3 org/nlogo/nvm/Context I org/nlogo/core/Nobody$] [org/nlogo/nvm/Context]
          ICONST_3
         L6
         FRAME FULL [org/nlogo/prim/_asm_proceduregetnestscent_if_3 org/nlogo/nvm/Context I org/nlogo/core/Nobody$] [org/nlogo/nvm/Context I]
          PUTFIELD org/nlogo/nvm/Context.ip : I
         L7
          RETURN
[2]_asm_proceduregetnestscent_report_4 "report [ nest-scent ] of p" Object => void
      _patchvariableof:NEST-SCENT "[ nest-scent ] of p" Object => Object
        _procedurevariable:P "p" => Object
          TRYCATCHBLOCK L0 L1 L2 org/nlogo/api/AgentException
          TRYCATCHBLOCK L3 L4 L5 org/nlogo/api/AgentException
         L6
          ALOAD 1
          GETFIELD org/nlogo/nvm/Context.activation : Lorg/nlogo/nvm/Activation;
          GETFIELD org/nlogo/nvm/Activation.args : [Ljava/lang/Object;
          ICONST_1
          AALOAD
         L7
          ASTORE 2
          ALOAD 2
          ASTORE 3
          ALOAD 3
          INSTANCEOF org/nlogo/agent/Agent
          IFEQ L8
          ALOAD 3
          CHECKCAST org/nlogo/agent/Agent
          ASTORE 4
          ALOAD 4
          GETFIELD org/nlogo/agent/Agent.id : J
          LDC -1
          LCMP
          IFNE L3
          NEW org/nlogo/nvm/EngineException
          DUP
          ALOAD 1
          ALOAD 0
          GETSTATIC org/nlogo/core/I18N$.MODULE$ : Lorg/nlogo/core/I18N$;
          INVOKEVIRTUAL org/nlogo/core/I18N$.errors ()Lorg/nlogo/core/I18N$BundleKind;
          LDC "org.nlogo.$common.thatAgentIsDead"
          GETSTATIC scala/Predef$.MODULE$ : Lscala/Predef$;
          ICONST_1
          ANEWARRAY java/lang/Object
          DUP
          ICONST_0
          ALOAD 4
          INVOKEVIRTUAL org/nlogo/agent/Agent.classDisplayName ()Ljava/lang/String;
          AASTORE
          INVOKEVIRTUAL scala/Predef$.wrapRefArray ([Ljava/lang/Object;)Lscala/collection/mutable/WrappedArray;
          INVOKEVIRTUAL org/nlogo/core/I18N$BundleKind.getN (Ljava/lang/String;Lscala/collection/Seq;)Ljava/lang/String;
          INVOKESPECIAL org/nlogo/nvm/EngineException.<init> (Lorg/nlogo/nvm/Context;Lorg/nlogo/nvm/Instruction;Ljava/lang/String;)V
          ATHROW
         L3
         FRAME APPEND [java/lang/Object java/lang/Object org/nlogo/agent/Agent]
          ALOAD 4
          BIPUSH 8
          INVOKEVIRTUAL org/nlogo/agent/Agent.getPatchVariable (I)Ljava/lang/Object;
         L4
          ASTORE 5
          GOTO L9
         L8
         FRAME CHOP 1
          ALOAD 3
          INSTANCEOF org/nlogo/agent/AgentSet
          IFEQ L10
          ALOAD 3
          CHECKCAST org/nlogo/agent/AgentSet
          ASTORE 7
          NEW org/nlogo/api/LogoListBuilder
          DUP
          INVOKESPECIAL org/nlogo/api/LogoListBuilder.<init> ()V
          ASTORE 8
         L0
          ALOAD 7
          ALOAD 1
          GETFIELD org/nlogo/nvm/Context.job : Lorg/nlogo/nvm/Job;
          GETFIELD org/nlogo/nvm/Job.random : Lorg/nlogo/api/MersenneTwisterFast;
          INVOKEVIRTUAL org/nlogo/agent/AgentSet.shufflerator (Lorg/nlogo/api/MersenneTwisterFast;)Lorg/nlogo/agent/AgentSet$Iterator;
          ASTORE 10
         L11
         FRAME FULL [org/nlogo/prim/_asm_proceduregetnestscent_report_4 org/nlogo/nvm/Context java/lang/Object java/lang/Object T T T org/nlogo/agent/AgentSet org/nlogo/api/LogoListBuilder T org/nlogo/agent/AgentSet$Iterator] []
          ALOAD 10
          INVOKEINTERFACE org/nlogo/agent/AgentSet$Iterator.hasNext ()Z
          IFEQ L1
          ALOAD 8
          ALOAD 10
          INVOKEINTERFACE org/nlogo/agent/AgentSet$Iterator.next ()Lorg/nlogo/agent/Agent;
          BIPUSH 8
          INVOKEVIRTUAL org/nlogo/agent/Agent.getPatchVariable (I)Ljava/lang/Object;
          INVOKEVIRTUAL org/nlogo/api/LogoListBuilder.add (Ljava/lang/Object;)V
          GOTO L11
         L1
         FRAME SAME
          ALOAD 8
          INVOKEVIRTUAL org/nlogo/api/LogoListBuilder.toLogoList ()Lorg/nlogo/core/LogoList;
          ASTORE 5
         L9
         FRAME FULL [org/nlogo/prim/_asm_proceduregetnestscent_report_4 org/nlogo/nvm/Context java/lang/Object java/lang/Object T java/lang/Object] []
          ALOAD 5
          GOTO L12
         L10
         FRAME CHOP 2
          NEW org/nlogo/nvm/ArgumentTypeException
          DUP
          ALOAD 1
          ALOAD 0
          ICONST_0
          GETSTATIC org/nlogo/core/Syntax$.MODULE$ : Lorg/nlogo/core/Syntax$;
          INVOKEVIRTUAL org/nlogo/core/Syntax$.TurtleType ()I
          GETSTATIC org/nlogo/core/Syntax$.MODULE$ : Lorg/nlogo/core/Syntax$;
          INVOKEVIRTUAL org/nlogo/core/Syntax$.PatchType ()I
          IOR
          GETSTATIC org/nlogo/core/Syntax$.MODULE$ : Lorg/nlogo/core/Syntax$;
          INVOKEVIRTUAL org/nlogo/core/Syntax$.TurtlesetType ()I
          IOR
          GETSTATIC org/nlogo/core/Syntax$.MODULE$ : Lorg/nlogo/core/Syntax$;
          INVOKEVIRTUAL org/nlogo/core/Syntax$.PatchsetType ()I
          IOR
          ALOAD 2
          INVOKESPECIAL org/nlogo/nvm/ArgumentTypeException.<init> (Lorg/nlogo/nvm/Context;Lorg/nlogo/nvm/Instruction;IILjava/lang/Object;)V
          ATHROW
         L5
         FRAME FULL [org/nlogo/prim/_asm_proceduregetnestscent_report_4 org/nlogo/nvm/Context java/lang/Object java/lang/Object org/nlogo/agent/Agent] [org/nlogo/api/AgentException]
          ASTORE 6
          NEW org/nlogo/nvm/EngineException
          DUP
          ALOAD 1
          ALOAD 0
          ALOAD 6
          INVOKEVIRTUAL org/nlogo/api/AgentException.getMessage ()Ljava/lang/String;
          INVOKESPECIAL org/nlogo/nvm/EngineException.<init> (Lorg/nlogo/nvm/Context;Lorg/nlogo/nvm/Instruction;Ljava/lang/String;)V
          ATHROW
         L2
         FRAME FULL [org/nlogo/prim/_asm_proceduregetnestscent_report_4 org/nlogo/nvm/Context java/lang/Object java/lang/Object T T T org/nlogo/agent/AgentSet org/nlogo/api/LogoListBuilder] [org/nlogo/api/AgentException]
          ASTORE 9
          NEW org/nlogo/nvm/EngineException
          DUP
          ALOAD 1
          ALOAD 0
          ALOAD 9
          INVOKEVIRTUAL org/nlogo/api/AgentException.getMessage ()Ljava/lang/String;
          INVOKESPECIAL org/nlogo/nvm/EngineException.<init> (Lorg/nlogo/nvm/Context;Lorg/nlogo/nvm/Instruction;Ljava/lang/String;)V
          ATHROW
         L12
         FRAME FULL [org/nlogo/prim/_asm_proceduregetnestscent_report_4 org/nlogo/nvm/Context java/lang/Object java/lang/Object T java/lang/Object] [java/lang/Object]
          ASTORE 2
          ALOAD 1
          GETFIELD org/nlogo/nvm/Context.job : Lorg/nlogo/nvm/Job;
          ALOAD 2
          PUTFIELD org/nlogo/nvm/Job.result : Ljava/lang/Object;
          ALOAD 1
          ICONST_0
          PUTFIELD org/nlogo/nvm/Context.stopping : Z
          ALOAD 1
          ICONST_3
          PUTFIELD org/nlogo/nvm/Context.ip : I
          ALOAD 1
          GETFIELD org/nlogo/nvm/Context.activation : Lorg/nlogo/nvm/Activation;
          GETFIELD org/nlogo/nvm/Activation.procedure : Lorg/nlogo/nvm/Procedure;
          INVOKEVIRTUAL org/nlogo/nvm/Procedure.isTask ()Z
          IFEQ L13
          GETSTATIC org/nlogo/nvm/NonLocalExit$.MODULE$ : Lorg/nlogo/nvm/NonLocalExit$;
          ATHROW
         L13
         FRAME SAME
          ALOAD 1
          GETFIELD org/nlogo/nvm/Context.activation : Lorg/nlogo/nvm/Activation;
          GETFIELD org/nlogo/nvm/Activation.procedure : Lorg/nlogo/nvm/Procedure;
          INVOKEVIRTUAL org/nlogo/nvm/Procedure.isReporter ()Z
          IFNE L14
          NEW org/nlogo/nvm/EngineException
          DUP
          ALOAD 1
          ALOAD 0
          INVOKESTATIC org/nlogo/core/I18N.errorsJ ()Lorg/nlogo/core/I18NJava;
          LDC "org.nlogo.prim._report.canOnlyUseInToReport"
          ICONST_1
          ANEWARRAY java/lang/Object
          DUP
          ICONST_0
          LDC "REPORT"
          AASTORE
          INVOKEINTERFACE org/nlogo/core/I18NJava.getN (Ljava/lang/String;[Ljava/lang/Object;)Ljava/lang/String;
          INVOKESPECIAL org/nlogo/nvm/EngineException.<init> (Lorg/nlogo/nvm/Context;Lorg/nlogo/nvm/Instruction;Ljava/lang/String;)V
          ATHROW
         L14
         FRAME SAME
          ALOAD 1
          INVOKEVIRTUAL org/nlogo/nvm/Context.atTopActivation ()Z
          IFNE L15
          NEW org/nlogo/nvm/EngineException
          DUP
          ALOAD 1
          ALOAD 0
          INVOKESTATIC org/nlogo/core/I18N.errorsJ ()Lorg/nlogo/core/I18NJava;
          LDC "org.nlogo.prim._report.mustImmediatelyBeUsedInToReport"
          ICONST_1
          ANEWARRAY java/lang/Object
          DUP
          ICONST_0
          LDC "REPORT"
          AASTORE
          INVOKEINTERFACE org/nlogo/core/I18NJava.getN (Ljava/lang/String;[Ljava/lang/Object;)Ljava/lang/String;
          INVOKESPECIAL org/nlogo/nvm/EngineException.<init> (Lorg/nlogo/nvm/Context;Lorg/nlogo/nvm/Instruction;Ljava/lang/String;)V
          ATHROW
         L15
         FRAME SAME
          RETURN
[3]_asm_proceduregetnestscent_report_5 "report 0" Object => void
      _constdouble:0.0 "0" => Double
         L0
          ALOAD 0
          GETFIELD org/nlogo/prim/_asm_proceduregetnestscent_report_5.kept2_value : Ljava/lang/Double;
         L1
          ASTORE 2
          ALOAD 1
          GETFIELD org/nlogo/nvm/Context.job : Lorg/nlogo/nvm/Job;
          ALOAD 2
          PUTFIELD org/nlogo/nvm/Job.result : Ljava/lang/Object;
          ALOAD 1
          ICONST_0
          PUTFIELD org/nlogo/nvm/Context.stopping : Z
          ALOAD 1
          ICONST_4
          PUTFIELD org/nlogo/nvm/Context.ip : I
          ALOAD 1
          GETFIELD org/nlogo/nvm/Context.activation : Lorg/nlogo/nvm/Activation;
          GETFIELD org/nlogo/nvm/Activation.procedure : Lorg/nlogo/nvm/Procedure;
          INVOKEVIRTUAL org/nlogo/nvm/Procedure.isTask ()Z
          IFEQ L2
          GETSTATIC org/nlogo/nvm/NonLocalExit$.MODULE$ : Lorg/nlogo/nvm/NonLocalExit$;
          ATHROW
         L2
         FRAME APPEND [java/lang/Double]
          ALOAD 1
          GETFIELD org/nlogo/nvm/Context.activation : Lorg/nlogo/nvm/Activation;
          GETFIELD org/nlogo/nvm/Activation.procedure : Lorg/nlogo/nvm/Procedure;
          INVOKEVIRTUAL org/nlogo/nvm/Procedure.isReporter ()Z
          IFNE L3
          NEW org/nlogo/nvm/EngineException
          DUP
          ALOAD 1
          ALOAD 0
          INVOKESTATIC org/nlogo/core/I18N.errorsJ ()Lorg/nlogo/core/I18NJava;
          LDC "org.nlogo.prim._report.canOnlyUseInToReport"
          ICONST_1
          ANEWARRAY java/lang/Object
          DUP
          ICONST_0
          LDC "REPORT"
          AASTORE
          INVOKEINTERFACE org/nlogo/core/I18NJava.getN (Ljava/lang/String;[Ljava/lang/Object;)Ljava/lang/String;
          INVOKESPECIAL org/nlogo/nvm/EngineException.<init> (Lorg/nlogo/nvm/Context;Lorg/nlogo/nvm/Instruction;Ljava/lang/String;)V
          ATHROW
         L3
         FRAME SAME
          ALOAD 1
          INVOKEVIRTUAL org/nlogo/nvm/Context.atTopActivation ()Z
          IFNE L4
          NEW org/nlogo/nvm/EngineException
          DUP
          ALOAD 1
          ALOAD 0
          INVOKESTATIC org/nlogo/core/I18N.errorsJ ()Lorg/nlogo/core/I18NJava;
          LDC "org.nlogo.prim._report.mustImmediatelyBeUsedInToReport"
          ICONST_1
          ANEWARRAY java/lang/Object
          DUP
          ICONST_0
          LDC "REPORT"
          AASTORE
          INVOKEINTERFACE org/nlogo/core/I18NJava.getN (Ljava/lang/String;[Ljava/lang/Object;)Ljava/lang/String;
          INVOKESPECIAL org/nlogo/nvm/EngineException.<init> (Lorg/nlogo/nvm/Context;Lorg/nlogo/nvm/Instruction;Ljava/lang/String;)V
          ATHROW
         L4
         FRAME SAME
          RETURN
[4]_asm_proceduregetnestscent_returnreport_6 => void
         L0
          NEW org/nlogo/nvm/EngineException
          DUP
          ALOAD 1
          ALOAD 0
          INVOKESTATIC org/nlogo/core/I18N.errorsJ ()Lorg/nlogo/core/I18NJava;
          LDC "org.nlogo.prim._returnreport.reportNotCalledInReportProcedure"
          INVOKEINTERFACE org/nlogo/core/I18NJava.get (Ljava/lang/String;)Ljava/lang/String;
          INVOKESPECIAL org/nlogo/nvm/EngineException.<init> (Lorg/nlogo/nvm/Context;Lorg/nlogo/nvm/Instruction;Ljava/lang/String;)V
          ATHROW
         L1
         FRAME FULL [] [java/lang/Throwable]
          ATHROW

procedure GO-TURTLES:[]{-T--}:
[0]_asm_proceduregoturtles_if_0 "if who < ticks [ ifelse carrying-food? set color orange + 1 [ return-to-nest ] set color red [ look-for-food ] ]" boolean => void
      _lessthan "who < ticks" double,double => boolean
        _turtlevariabledouble:WHO "who" => double
        _ticks "ticks" => double
         L0
          ALOAD 1
          GETFIELD org/nlogo/nvm/Context.agent : Lorg/nlogo/agent/Agent;
          CHECKCAST org/nlogo/agent/Turtle
          ICONST_0
          INVOKEVIRTUAL org/nlogo/agent/Turtle.getTurtleVariableDouble (I)D
         L1
          ALOAD 0
          GETFIELD org/nlogo/prim/_asm_proceduregoturtles_if_0.world : Lorg/nlogo/agent/World;
          INVOKEVIRTUAL org/nlogo/agent/World.ticks ()D
          DSTORE 2
          DLOAD 2
          LDC -1.0
          DCMPL
          IFNE L2
          NEW org/nlogo/nvm/EngineException
          DUP
          ALOAD 1
          ALOAD 0
          INVOKESTATIC org/nlogo/core/I18N.errorsJ ()Lorg/nlogo/core/I18NJava;
          LDC "org.nlogo.prim.etc.$common.tickCounterNotStarted"
          INVOKEINTERFACE org/nlogo/core/I18NJava.get (Ljava/lang/String;)Ljava/lang/String;
          INVOKESPECIAL org/nlogo/nvm/EngineException.<init> (Lorg/nlogo/nvm/Context;Lorg/nlogo/nvm/Instruction;Ljava/lang/String;)V
          ATHROW
         L2
         FRAME FULL [org/nlogo/prim/_asm_proceduregoturtles_if_0 org/nlogo/nvm/Context D] [D]
          DLOAD 2
         L3
          DSTORE 4
          DSTORE 2
          DLOAD 2
          DLOAD 4
          DCMPG
          IFGE L4
          ICONST_1
          GOTO L5
         L4
         FRAME APPEND [D]
          ICONST_0
         L5
         FRAME SAME1 I
          ISTORE 2
          ALOAD 1
          ILOAD 2
          IFEQ L6
          ICONST_1
          GOTO L7
         L6
         FRAME FULL [org/nlogo/prim/_asm_proceduregoturtles_if_0 org/nlogo/nvm/Context I T D] [org/nlogo/nvm/Context]
          BIPUSH 7
         L7
         FRAME FULL [org/nlogo/prim/_asm_proceduregoturtles_if_0 org/nlogo/nvm/Context I T D] [org/nlogo/nvm/Context I]
          PUTFIELD org/nlogo/nvm/Context.ip : I
         L8
          RETURN
[1]_asm_proceduregoturtles_ifelse_1 "ifelse carrying-food? set color orange + 1 [ return-to-nest ] set color red [ look-for-food ]" boolean => void
      _turtlevariable:CARRYING-FOOD? "carrying-food?" => Object
          TRYCATCHBLOCK L0 L1 L2 org/nlogo/api/AgentException
          TRYCATCHBLOCK L3 L4 L4 java/lang/ClassCastException
         L0
          ALOAD 1
          GETFIELD org/nlogo/nvm/Context.agent : Lorg/nlogo/agent/Agent;
          BIPUSH 13
          INVOKEVIRTUAL org/nlogo/agent/Agent.getTurtleVariable (I)Ljava/lang/Object;
         L1
          GOTO L5
         L2
         FRAME SAME1 org/nlogo/api/AgentException
          ASTORE 2
          NEW org/nlogo/nvm/EngineException
          DUP
          ALOAD 1
          ALOAD 0
          ALOAD 2
          INVOKEVIRTUAL org/nlogo/api/AgentException.getMessage ()Ljava/lang/String;
          INVOKESPECIAL org/nlogo/nvm/EngineException.<init> (Lorg/nlogo/nvm/Context;Lorg/nlogo/nvm/Instruction;Ljava/lang/String;)V
          ATHROW
         L5
         FRAME SAME1 java/lang/Object
          ASTORE 2
         L3
          ALOAD 2
          CHECKCAST java/lang/Boolean
          INVOKEVIRTUAL java/lang/Boolean.booleanValue ()Z
          GOTO L6
         L4
         FRAME FULL [org/nlogo/prim/_asm_proceduregoturtles_ifelse_1 org/nlogo/nvm/Context java/lang/Object] [java/lang/ClassCastException]
          POP
          NEW org/nlogo/nvm/ArgumentTypeException
          DUP
          ALOAD 1
          ALOAD 0
          BIPUSH 0
          LDC 2
          ALOAD 2
          INVOKESPECIAL org/nlogo/nvm/ArgumentTypeException.<init> (Lorg/nlogo/nvm/Context;Lorg/nlogo/nvm/Instruction;IILjava/lang/Object;)V
          ATHROW
         L6
         FRAME SAME1 I
          ISTORE 2
          ALOAD 1
          ILOAD 2
          IFEQ L7
          ICONST_2
          GOTO L8
         L7
         FRAME FULL [org/nlogo/prim/_asm_proceduregoturtles_ifelse_1 org/nlogo/nvm/Context I] [org/nlogo/nvm/Context]
          ICONST_5
         L8
         FRAME FULL [org/nlogo/prim/_asm_proceduregoturtles_ifelse_1 org/nlogo/nvm/Context I] [org/nlogo/nvm/Context I]
          PUTFIELD org/nlogo/nvm/Context.ip : I
         L9
          RETURN
[2]_asm_proceduregoturtles_setturtleorlinkvariable_2 "set color orange + 1" Object => void
      _constdouble:26.0 "orange + 1" => Double
          TRYCATCHBLOCK L0 L1 L2 org/nlogo/api/AgentException
         L3
          ALOAD 0
          GETFIELD org/nlogo/prim/_asm_proceduregoturtles_setturtleorlinkvariable_2.kept2_value : Ljava/lang/Double;
         L4
          ASTORE 2
         L0
          ALOAD 1
          GETFIELD org/nlogo/nvm/Context.agent : Lorg/nlogo/agent/Agent;
          LDC "COLOR"
          ALOAD 2
          INVOKEVIRTUAL org/nlogo/agent/Agent.setTurtleOrLinkVariable (Ljava/lang/String;Ljava/lang/Object;)V
         L1
          GOTO L5
         L2
         FRAME FULL [org/nlogo/prim/_asm_proceduregoturtles_setturtleorlinkvariable_2 org/nlogo/nvm/Context java/lang/Double] [org/nlogo/api/AgentException]
          ASTORE 3
          NEW org/nlogo/nvm/EngineException
          DUP
          ALOAD 1
          ALOAD 0
          ALOAD 3
          INVOKEVIRTUAL org/nlogo/api/AgentException.getMessage ()Ljava/lang/String;
          INVOKESPECIAL org/nlogo/nvm/EngineException.<init> (Lorg/nlogo/nvm/Context;Lorg/nlogo/nvm/Instruction;Ljava/lang/String;)V
          ATHROW
         L5
         FRAME SAME
          ALOAD 1
          ICONST_3
          PUTFIELD org/nlogo/nvm/Context.ip : I
         L6
          RETURN
[3]_asm_proceduregoturtles_call_3 "return-to-nest"
         L0
          NEW org/nlogo/nvm/Activation
          DUP
          ALOAD 0
          GETFIELD org/nlogo/prim/_asm_proceduregoturtles_call_3.kept1_procedure : Lorg/nlogo/nvm/Procedure;
          ALOAD 1
          GETFIELD org/nlogo/nvm/Context.activation : Lorg/nlogo/nvm/Activation;
          ICONST_4
          INVOKESPECIAL org/nlogo/nvm/Activation.<init> (Lorg/nlogo/nvm/Procedure;Lorg/nlogo/nvm/Activation;I)V
          ALOAD 1
          SWAP
          PUTFIELD org/nlogo/nvm/Context.activation : Lorg/nlogo/nvm/Activation;
          ALOAD 1
          ICONST_0
          PUTFIELD org/nlogo/nvm/Context.ip : I
         L1
          RETURN
[4]_asm_proceduregoturtles_goto_4 => void
         L0
          ALOAD 1
          BIPUSH 7
          PUTFIELD org/nlogo/nvm/Context.ip : I
         L1
          RETURN
[5]_asm_proceduregoturtles_setturtleorlinkvariable_5 "set color red" Object => void
      _constdouble:15.0 "red" => Double
          TRYCATCHBLOCK L0 L1 L2 org/nlogo/api/AgentException
         L3
          ALOAD 0
          GETFIELD org/nlogo/prim/_asm_proceduregoturtles_setturtleorlinkvariable_5.kept2_value : Ljava/lang/Double;
         L4
          ASTORE 2
         L0
          ALOAD 1
          GETFIELD org/nlogo/nvm/Context.agent : Lorg/nlogo/agent/Agent;
          LDC "COLOR"
          ALOAD 2
          INVOKEVIRTUAL org/nlogo/agent/Agent.setTurtleOrLinkVariable (Ljava/lang/String;Ljava/lang/Object;)V
         L1
          GOTO L5
         L2
         FRAME FULL [org/nlogo/prim/_asm_proceduregoturtles_setturtleorlinkvariable_5 org/nlogo/nvm/Context java/lang/Double] [org/nlogo/api/AgentException]
          ASTORE 3
          NEW org/nlogo/nvm/EngineException
          DUP
          ALOAD 1
          ALOAD 0
          ALOAD 3
          INVOKEVIRTUAL org/nlogo/api/AgentException.getMessage ()Ljava/lang/String;
          INVOKESPECIAL org/nlogo/nvm/EngineException.<init> (Lorg/nlogo/nvm/Context;Lorg/nlogo/nvm/Instruction;Ljava/lang/String;)V
          ATHROW
         L5
         FRAME SAME
          ALOAD 1
          BIPUSH 6
          PUTFIELD org/nlogo/nvm/Context.ip : I
         L6
          RETURN
[6]_asm_proceduregoturtles_call_6 "look-for-food"
         L0
          NEW org/nlogo/nvm/Activation
          DUP
          ALOAD 0
          GETFIELD org/nlogo/prim/_asm_proceduregoturtles_call_6.kept1_procedure : Lorg/nlogo/nvm/Procedure;
          ALOAD 1
          GETFIELD org/nlogo/nvm/Context.activation : Lorg/nlogo/nvm/Activation;
          BIPUSH 7
          INVOKESPECIAL org/nlogo/nvm/Activation.<init> (Lorg/nlogo/nvm/Procedure;Lorg/nlogo/nvm/Activation;I)V
          ALOAD 1
          SWAP
          PUTFIELD org/nlogo/nvm/Context.activation : Lorg/nlogo/nvm/Activation;
          ALOAD 1
          ICONST_0
          PUTFIELD org/nlogo/nvm/Context.ip : I
         L1
          RETURN
[7]_asm_proceduregoturtles_return_7 => void
         L0
          ALOAD 1
          INVOKEVIRTUAL org/nlogo/nvm/Context.returnFromProcedure ()V
          ALOAD 1
          ICONST_0
          PUTFIELD org/nlogo/nvm/Context.stopping : Z
         L1
          RETURN

procedure SETUP-NEST:[]{-TP-}:
[0]_asm_proceduresetupnest_setpatchvariable_0 "set nest? distancexy 0 0 < 5" Object => void
      _lessthan "distancexy 0 0 < 5" double,double => boolean
        _distancexy "distancexy 0 0" double,double => double
          _constdouble:0.0 "0" => double
          _constdouble:0.0 "0" => double
        _constdouble:5.0 "5" => double
          TRYCATCHBLOCK L0 L1 L2 org/nlogo/api/AgentException
         L3
          DCONST_0
         L4
          DCONST_0
         L5
          DSTORE 4
          DSTORE 2
          ALOAD 0
          ALOAD 0
          GETFIELD org/nlogo/prim/_asm_proceduresetupnest_setpatchvariable_0.world : Lorg/nlogo/agent/World;
          INVOKEVIRTUAL org/nlogo/agent/World.protractor ()Lorg/nlogo/agent/Protractor;
          ALOAD 1
          GETFIELD org/nlogo/nvm/Context.agent : Lorg/nlogo/agent/Agent;
          DLOAD 2
          DLOAD 4
          ICONST_1
          INVOKEVIRTUAL org/nlogo/agent/Protractor.distance (Lorg/nlogo/api/Agent;DDZ)D
          INVOKEVIRTUAL org/nlogo/prim/_asm_proceduresetupnest_setpatchvariable_0.validDouble (D)D
         L6
          LDC 5.0
         L7
          DSTORE 4
          DSTORE 2
          DLOAD 2
          DLOAD 4
          DCMPG
          IFGE L8
          ICONST_1
          GOTO L9
         L8
         FRAME APPEND [D D]
          ICONST_0
         L9
         FRAME SAME1 I
          IFEQ L10
          GETSTATIC java/lang/Boolean.TRUE : Ljava/lang/Boolean;
          GOTO L11
         L10
         FRAME SAME
          GETSTATIC java/lang/Boolean.FALSE : Ljava/lang/Boolean;
         L11
         FRAME SAME1 java/lang/Boolean
          ASTORE 2
         L0
          ALOAD 1
          GETFIELD org/nlogo/nvm/Context.agent : Lorg/nlogo/agent/Agent;
          BIPUSH 7
          ALOAD 2
          INVOKEVIRTUAL org/nlogo/agent/Agent.setPatchVariable (ILjava/lang/Object;)V
         L1
          GOTO L12
         L2
         FRAME FULL [org/nlogo/prim/_asm_proceduresetupnest_setpatchvariable_0 org/nlogo/nvm/Context java/lang/Boolean T D] [org/nlogo/api/AgentException]
          ASTORE 3
          NEW org/nlogo/nvm/EngineException
          DUP
          ALOAD 1
          ALOAD 0
          ALOAD 3
          INVOKEVIRTUAL org/nlogo/api/AgentException.getMessage ()Ljava/lang/String;
          INVOKESPECIAL org/nlogo/nvm/EngineException.<init> (Lorg/nlogo/nvm/Context;Lorg/nlogo/nvm/Instruction;Ljava/lang/String;)V
          ATHROW
         L12
         FRAME SAME
          ALOAD 1
          ICONST_1
          PUTFIELD org/nlogo/nvm/Context.ip : I
         L13
          RETURN
[1]_asm_proceduresetupnest_setpatchvariable_1 "set nest-scent 200 - distancexy 0 0" Object => void
      _minus "200 - distancexy 0 0" double,double => double
        _constdouble:200.0 "200" => double
        _distancexy "distancexy 0 0" double,double => double
          _constdouble:0.0 "0" => double
          _constdouble:0.0 "0" => double
          TRYCATCHBLOCK L0 L1 L2 org/nlogo/api/AgentException
         L3
          LDC 200.0
         L4
          DCONST_0
         L5
          DCONST_0
         L6
          DSTORE 4
          DSTORE 2
          ALOAD 0
          ALOAD 0
          GETFIELD org/nlogo/prim/_asm_proceduresetupnest_setpatchvariable_1.world : Lorg/nlogo/agent/World;
          INVOKEVIRTUAL org/nlogo/agent/World.protractor ()Lorg/nlogo/agent/Protractor;
          ALOAD 1
          GETFIELD org/nlogo/nvm/Context.agent : Lorg/nlogo/agent/Agent;
          DLOAD 2
          DLOAD 4
          ICONST_1
          INVOKEVIRTUAL org/nlogo/agent/Protractor.distance (Lorg/nlogo/api/Agent;DDZ)D
          INVOKEVIRTUAL org/nlogo/prim/_asm_proceduresetupnest_setpatchvariable_1.validDouble (D)D
         L7
          DSTORE 4
          DSTORE 2
          ALOAD 0
          DLOAD 2
          DLOAD 4
          DSUB
          INVOKEVIRTUAL org/nlogo/prim/_asm_proceduresetupnest_setpatchvariable_1.validDouble (D)D
         L8
          DSTORE 2
          NEW java/lang/Double
          DUP
          DLOAD 2
          INVOKESPECIAL java/lang/Double.<init> (D)V
          ASTORE 2
         L0
          ALOAD 1
          GETFIELD org/nlogo/nvm/Context.agent : Lorg/nlogo/agent/Agent;
          BIPUSH 8
          ALOAD 2
          INVOKEVIRTUAL org/nlogo/agent/Agent.setPatchVariable (ILjava/lang/Object;)V
         L1
          GOTO L9
         L2
         FRAME FULL [org/nlogo/prim/_asm_proceduresetupnest_setpatchvariable_1 org/nlogo/nvm/Context java/lang/Double T D] [org/nlogo/api/AgentException]
          ASTORE 3
          NEW org/nlogo/nvm/EngineException
          DUP
          ALOAD 1
          ALOAD 0
          ALOAD 3
          INVOKEVIRTUAL org/nlogo/api/AgentException.getMessage ()Ljava/lang/String;
          INVOKESPECIAL org/nlogo/nvm/EngineException.<init> (Lorg/nlogo/nvm/Context;Lorg/nlogo/nvm/Instruction;Ljava/lang/String;)V
          ATHROW
         L9
         FRAME SAME
          ALOAD 1
          ICONST_2
          PUTFIELD org/nlogo/nvm/Context.ip : I
         L10
          RETURN
[2]_asm_proceduresetupnest_return_2 => void
         L0
          ALOAD 1
          INVOKEVIRTUAL org/nlogo/nvm/Context.returnFromProcedure ()V
          ALOAD 1
          ICONST_0
          PUTFIELD org/nlogo/nvm/Context.stopping : Z
         L1
          RETURN

procedure SETUP-FOOD:[]{-TP-}:
[0]_asm_proceduresetupfood_if_0 "if distancexy 0.6 * max-pxcor 0 < 5 [ set food-source-number 1 ]" boolean => void
      _lessthan "distancexy 0.6 * max-pxcor 0 < 5" double,double => boolean
        _distancexy "distancexy 0.6 * max-pxcor 0" double,double => double
          _mult "0.6 * max-pxcor" double,double => double
            _constdouble:0.6 "0.6" => double
            _maxpxcor "max-pxcor" => double
          _constdouble:0.0 "0" => double
        _constdouble:5.0 "5" => double
         L0
          LDC 0.6
         L1
          ALOAD 0
          GETFIELD org/nlogo/prim/_asm_proceduresetupfood_if_0.world : Lorg/nlogo/agent/World;
          INVOKEVIRTUAL org/nlogo/agent/World.maxPxcor ()I
          I2D
         L2
          DSTORE 4
          DSTORE 2
          ALOAD 0
          DLOAD 2
          DLOAD 4
          DMUL
          INVOKEVIRTUAL org/nlogo/prim/_asm_proceduresetupfood_if_0.validDouble (D)D
         L3
          DCONST_0
         L4
          DSTORE 4
          DSTORE 2
          ALOAD 0
          ALOAD 0
          GETFIELD org/nlogo/prim/_asm_proceduresetupfood_if_0.world : Lorg/nlogo/agent/World;
          INVOKEVIRTUAL org/nlogo/agent/World.protractor ()Lorg/nlogo/agent/Protractor;
          ALOAD 1
          GETFIELD org/nlogo/nvm/Context.agent : Lorg/nlogo/agent/Agent;
          DLOAD 2
          DLOAD 4
          ICONST_1
          INVOKEVIRTUAL org/nlogo/agent/Protractor.distance (Lorg/nlogo/api/Agent;DDZ)D
          INVOKEVIRTUAL org/nlogo/prim/_asm_proceduresetupfood_if_0.validDouble (D)D
         L5
          LDC 5.0
         L6
          DSTORE 4
          DSTORE 2
          DLOAD 2
          DLOAD 4
          DCMPG
          IFGE L7
          ICONST_1
          GOTO L8
         L7
         FRAME APPEND [D D]
          ICONST_0
         L8
         FRAME SAME1 I
          ISTORE 2
          ALOAD 1
          ILOAD 2
          IFEQ L9
          ICONST_1
          GOTO L10
         L9
         FRAME FULL [org/nlogo/prim/_asm_proceduresetupfood_if_0 org/nlogo/nvm/Context I T D] [org/nlogo/nvm/Context]
          ICONST_2
         L10
         FRAME FULL [org/nlogo/prim/_asm_proceduresetupfood_if_0 org/nlogo/nvm/Context I T D] [org/nlogo/nvm/Context I]
          PUTFIELD org/nlogo/nvm/Context.ip : I
         L11
          RETURN
[1]_asm_proceduresetupfood_setpatchvariable_1 "set food-source-number 1" Object => void
      _constdouble:1.0 "1" => Double
          TRYCATCHBLOCK L0 L1 L2 org/nlogo/api/AgentException
         L3
          ALOAD 0
          GETFIELD org/nlogo/prim/_asm_proceduresetupfood_setpatchvariable_1.kept2_value : Ljava/lang/Double;
         L4
          ASTORE 2
         L0
          ALOAD 1
          GETFIELD org/nlogo/nvm/Context.agent : Lorg/nlogo/agent/Agent;
          BIPUSH 9
          ALOAD 2
          INVOKEVIRTUAL org/nlogo/agent/Agent.setPatchVariable (ILjava/lang/Object;)V
         L1
          GOTO L5
         L2
         FRAME FULL [org/nlogo/prim/_asm_proceduresetupfood_setpatchvariable_1 org/nlogo/nvm/Context java/lang/Double] [org/nlogo/api/AgentException]
          ASTORE 3
          NEW org/nlogo/nvm/EngineException
          DUP
          ALOAD 1
          ALOAD 0
          ALOAD 3
          INVOKEVIRTUAL org/nlogo/api/AgentException.getMessage ()Ljava/lang/String;
          INVOKESPECIAL org/nlogo/nvm/EngineException.<init> (Lorg/nlogo/nvm/Context;Lorg/nlogo/nvm/Instruction;Ljava/lang/String;)V
          ATHROW
         L5
         FRAME SAME
          ALOAD 1
          ICONST_2
          PUTFIELD org/nlogo/nvm/Context.ip : I
         L6
          RETURN
[2]_asm_proceduresetupfood_if_2 "if distancexy -0.6 * max-pxcor -0.6 * max-pycor < 5 [ set food-source-number 2 ]" boolean => void
      _lessthan "distancexy -0.6 * max-pxcor -0.6 * max-pycor < 5" double,double => boolean
        _distancexy "distancexy -0.6 * max-pxcor -0.6 * max-pycor" double,double => double
          _mult "-0.6 * max-pxcor" double,double => double
            _constdouble:-0.6 "-0.6" => double
            _maxpxcor "max-pxcor" => double
          _mult "-0.6 * max-pycor" double,double => double
            _constdouble:-0.6 "-0.6" => double
            _maxpycor "max-pycor" => double
        _constdouble:5.0 "5" => double
         L0
          LDC -0.6
         L1
          ALOAD 0
          GETFIELD org/nlogo/prim/_asm_proceduresetupfood_if_2.world : Lorg/nlogo/agent/World;
          INVOKEVIRTUAL org/nlogo/agent/World.maxPxcor ()I
          I2D
         L2
          DSTORE 4
          DSTORE 2
          ALOAD 0
          DLOAD 2
          DLOAD 4
          DMUL
          INVOKEVIRTUAL org/nlogo/prim/_asm_proceduresetupfood_if_2.validDouble (D)D
         L3
          LDC -0.6
         L4
          ALOAD 0
          GETFIELD org/nlogo/prim/_asm_proceduresetupfood_if_2.world : Lorg/nlogo/agent/World;
          INVOKEVIRTUAL org/nlogo/agent/World.maxPycor ()I
          I2D
         L5
          DSTORE 4
          DSTORE 2
          ALOAD 0
          DLOAD 2
          DLOAD 4
          DMUL
          INVOKEVIRTUAL org/nlogo/prim/_asm_proceduresetupfood_if_2.validDouble (D)D
         L6
          DSTORE 4
          DSTORE 2
          ALOAD 0
          ALOAD 0
          GETFIELD org/nlogo/prim/_asm_proceduresetupfood_if_2.world : Lorg/nlogo/agent/World;
          INVOKEVIRTUAL org/nlogo/agent/World.protractor ()Lorg/nlogo/agent/Protractor;
          ALOAD 1
          GETFIELD org/nlogo/nvm/Context.agent : Lorg/nlogo/agent/Agent;
          DLOAD 2
          DLOAD 4
          ICONST_1
          INVOKEVIRTUAL org/nlogo/agent/Protractor.distance (Lorg/nlogo/api/Agent;DDZ)D
          INVOKEVIRTUAL org/nlogo/prim/_asm_proceduresetupfood_if_2.validDouble (D)D
         L7
          LDC 5.0
         L8
          DSTORE 4
          DSTORE 2
          DLOAD 2
          DLOAD 4
          DCMPG
          IFGE L9
          ICONST_1
          GOTO L10
         L9
         FRAME APPEND [D D]
          ICONST_0
         L10
         FRAME SAME1 I
          ISTORE 2
          ALOAD 1
          ILOAD 2
          IFEQ L11
          ICONST_3
          GOTO L12
         L11
         FRAME FULL [org/nlogo/prim/_asm_proceduresetupfood_if_2 org/nlogo/nvm/Context I T D] [org/nlogo/nvm/Context]
          ICONST_4
         L12
         FRAME FULL [org/nlogo/prim/_asm_proceduresetupfood_if_2 org/nlogo/nvm/Context I T D] [org/nlogo/nvm/Context I]
          PUTFIELD org/nlogo/nvm/Context.ip : I
         L13
          RETURN
[3]_asm_proceduresetupfood_setpatchvariable_3 "set food-source-number 2" Object => void
      _constdouble:2.0 "2" => Double
          TRYCATCHBLOCK L0 L1 L2 org/nlogo/api/AgentException
         L3
          ALOAD 0
          GETFIELD org/nlogo/prim/_asm_proceduresetupfood_setpatchvariable_3.kept2_value : Ljava/lang/Double;
         L4
          ASTORE 2
         L0
          ALOAD 1
          GETFIELD org/nlogo/nvm/Context.agent : Lorg/nlogo/agent/Agent;
          BIPUSH 9
          ALOAD 2
          INVOKEVIRTUAL org/nlogo/agent/Agent.setPatchVariable (ILjava/lang/Object;)V
         L1
          GOTO L5
         L2
         FRAME FULL [org/nlogo/prim/_asm_proceduresetupfood_setpatchvariable_3 org/nlogo/nvm/Context java/lang/Double] [org/nlogo/api/AgentException]
          ASTORE 3
          NEW org/nlogo/nvm/EngineException
          DUP
          ALOAD 1
          ALOAD 0
          ALOAD 3
          INVOKEVIRTUAL org/nlogo/api/AgentException.getMessage ()Ljava/lang/String;
          INVOKESPECIAL org/nlogo/nvm/EngineException.<init> (Lorg/nlogo/nvm/Context;Lorg/nlogo/nvm/Instruction;Ljava/lang/String;)V
          ATHROW
         L5
         FRAME SAME
          ALOAD 1
          ICONST_4
          PUTFIELD org/nlogo/nvm/Context.ip : I
         L6
          RETURN
[4]_asm_proceduresetupfood_if_4 "if distancexy -0.8 * max-pxcor 0.8 * max-pycor < 5 [ set food-source-number 3 ]" boolean => void
      _lessthan "distancexy -0.8 * max-pxcor 0.8 * max-pycor < 5" double,double => boolean
        _distancexy "distancexy -0.8 * max-pxcor 0.8 * max-pycor" double,double => double
          _mult "-0.8 * max-pxcor" double,double => double
            _constdouble:-0.8 "-0.8" => double
            _maxpxcor "max-pxcor" => double
          _mult "0.8 * max-pycor" double,double => double
            _constdouble:0.8 "0.8" => double
            _maxpycor "max-pycor" => double
        _constdouble:5.0 "5" => double
         L0
          LDC -0.8
         L1
          ALOAD 0
          GETFIELD org/nlogo/prim/_asm_proceduresetupfood_if_4.world : Lorg/nlogo/agent/World;
          INVOKEVIRTUAL org/nlogo/agent/World.maxPxcor ()I
          I2D
         L2
          DSTORE 4
          DSTORE 2
          ALOAD 0
          DLOAD 2
          DLOAD 4
          DMUL
          INVOKEVIRTUAL org/nlogo/prim/_asm_proceduresetupfood_if_4.validDouble (D)D
         L3
          LDC 0.8
         L4
          ALOAD 0
          GETFIELD org/nlogo/prim/_asm_proceduresetupfood_if_4.world : Lorg/nlogo/agent/World;
          INVOKEVIRTUAL org/nlogo/agent/World.maxPycor ()I
          I2D
         L5
          DSTORE 4
          DSTORE 2
          ALOAD 0
          DLOAD 2
          DLOAD 4
          DMUL
          INVOKEVIRTUAL org/nlogo/prim/_asm_proceduresetupfood_if_4.validDouble (D)D
         L6
          DSTORE 4
          DSTORE 2
          ALOAD 0
          ALOAD 0
          GETFIELD org/nlogo/prim/_asm_proceduresetupfood_if_4.world : Lorg/nlogo/agent/World;
          INVOKEVIRTUAL org/nlogo/agent/World.protractor ()Lorg/nlogo/agent/Protractor;
          ALOAD 1
          GETFIELD org/nlogo/nvm/Context.agent : Lorg/nlogo/agent/Agent;
          DLOAD 2
          DLOAD 4
          ICONST_1
          INVOKEVIRTUAL org/nlogo/agent/Protractor.distance (Lorg/nlogo/api/Agent;DDZ)D
          INVOKEVIRTUAL org/nlogo/prim/_asm_proceduresetupfood_if_4.validDouble (D)D
         L7
          LDC 5.0
         L8
          DSTORE 4
          DSTORE 2
          DLOAD 2
          DLOAD 4
          DCMPG
          IFGE L9
          ICONST_1
          GOTO L10
         L9
         FRAME APPEND [D D]
          ICONST_0
         L10
         FRAME SAME1 I
          ISTORE 2
          ALOAD 1
          ILOAD 2
          IFEQ L11
          ICONST_5
          GOTO L12
         L11
         FRAME FULL [org/nlogo/prim/_asm_proceduresetupfood_if_4 org/nlogo/nvm/Context I T D] [org/nlogo/nvm/Context]
          BIPUSH 6
         L12
         FRAME FULL [org/nlogo/prim/_asm_proceduresetupfood_if_4 org/nlogo/nvm/Context I T D] [org/nlogo/nvm/Context I]
          PUTFIELD org/nlogo/nvm/Context.ip : I
         L13
          RETURN
[5]_asm_proceduresetupfood_setpatchvariable_5 "set food-source-number 3" Object => void
      _constdouble:3.0 "3" => Double
          TRYCATCHBLOCK L0 L1 L2 org/nlogo/api/AgentException
         L3
          ALOAD 0
          GETFIELD org/nlogo/prim/_asm_proceduresetupfood_setpatchvariable_5.kept2_value : Ljava/lang/Double;
         L4
          ASTORE 2
         L0
          ALOAD 1
          GETFIELD org/nlogo/nvm/Context.agent : Lorg/nlogo/agent/Agent;
          BIPUSH 9
          ALOAD 2
          INVOKEVIRTUAL org/nlogo/agent/Agent.setPatchVariable (ILjava/lang/Object;)V
         L1
          GOTO L5
         L2
         FRAME FULL [org/nlogo/prim/_asm_proceduresetupfood_setpatchvariable_5 org/nlogo/nvm/Context java/lang/Double] [org/nlogo/api/AgentException]
          ASTORE 3
          NEW org/nlogo/nvm/EngineException
          DUP
          ALOAD 1
          ALOAD 0
          ALOAD 3
          INVOKEVIRTUAL org/nlogo/api/AgentException.getMessage ()Ljava/lang/String;
          INVOKESPECIAL org/nlogo/nvm/EngineException.<init> (Lorg/nlogo/nvm/Context;Lorg/nlogo/nvm/Instruction;Ljava/lang/String;)V
          ATHROW
         L5
         FRAME SAME
          ALOAD 1
          BIPUSH 6
          PUTFIELD org/nlogo/nvm/Context.ip : I
         L6
          RETURN
[6]_asm_proceduresetupfood_if_6 "if food-source-number > 0 [ set food 1 + random 2 ]" boolean => void
      _greaterthan "food-source-number > 0" Object,double => boolean
        _patchvariable:FOOD-SOURCE-NUMBER "food-source-number" => Object
        _constdouble:0.0 "0" => double
          TRYCATCHBLOCK L0 L1 L2 org/nlogo/api/AgentException
         L0
          ALOAD 1
          GETFIELD org/nlogo/nvm/Context.agent : Lorg/nlogo/agent/Agent;
          BIPUSH 9
          INVOKEVIRTUAL org/nlogo/agent/Agent.getPatchVariable (I)Ljava/lang/Object;
         L1
          GOTO L3
         L2
         FRAME SAME1 org/nlogo/api/AgentException
          ASTORE 2
          NEW org/nlogo/nvm/EngineException
          DUP
          ALOAD 1
          ALOAD 0
          ALOAD 2
          INVOKEVIRTUAL org/nlogo/api/AgentException.getMessage ()Ljava/lang/String;
          INVOKESPECIAL org/nlogo/nvm/EngineException.<init> (Lorg/nlogo/nvm/Context;Lorg/nlogo/nvm/Instruction;Ljava/lang/String;)V
          ATHROW
         L3
         FRAME SAME1 java/lang/Object
          DCONST_0
         L4
          DSTORE 3
          ASTORE 2
          ALOAD 2
          INSTANCEOF java/lang/Double
          IFEQ L5
          ALOAD 2
          CHECKCAST java/lang/Double
          INVOKEVIRTUAL java/lang/Double.doubleValue ()D
          DLOAD 3
          DCMPL
          IFLE L6
          ICONST_1
          GOTO L7
         L6
         FRAME APPEND [java/lang/Object D]
          ICONST_0
         L7
         FRAME SAME1 I
          GOTO L8
         L5
         FRAME SAME
          NEW org/nlogo/nvm/EngineException
          DUP
          ALOAD 1
          ALOAD 0
          INVOKESTATIC org/nlogo/core/I18N.errorsJ ()Lorg/nlogo/core/I18NJava;
          LDC "org.nlogo.prim._greaterthan.cannotCompareParameters"
          ICONST_2
          ANEWARRAY java/lang/Object
          DUP
          ICONST_0
          ALOAD 2
          INVOKESTATIC org/nlogo/api/TypeNames.aName (Ljava/lang/Object;)Ljava/lang/String;
          AASTORE
          DUP
          ICONST_1
          DLOAD 3
          INVOKESTATIC java/lang/Double.valueOf (D)Ljava/lang/Double;
          INVOKESTATIC org/nlogo/api/TypeNames.aName (Ljava/lang/Object;)Ljava/lang/String;
          AASTORE
          INVOKEINTERFACE org/nlogo/core/I18NJava.getN (Ljava/lang/String;[Ljava/lang/Object;)Ljava/lang/String;
          INVOKESPECIAL org/nlogo/nvm/EngineException.<init> (Lorg/nlogo/nvm/Context;Lorg/nlogo/nvm/Instruction;Ljava/lang/String;)V
          ATHROW
         L8
         FRAME SAME1 I
          ISTORE 2
          ALOAD 1
          ILOAD 2
          IFEQ L9
          BIPUSH 7
          GOTO L10
         L9
         FRAME FULL [org/nlogo/prim/_asm_proceduresetupfood_if_6 org/nlogo/nvm/Context I D] [org/nlogo/nvm/Context]
          BIPUSH 8
         L10
         FRAME FULL [org/nlogo/prim/_asm_proceduresetupfood_if_6 org/nlogo/nvm/Context I D] [org/nlogo/nvm/Context I]
          PUTFIELD org/nlogo/nvm/Context.ip : I
         L11
          RETURN
[7]_asm_proceduresetupfood_setpatchvariable_7 "set food 1 + random 2" Object => void
      _plus "1 + random 2" double,double => double
        _constdouble:1.0 "1" => double
        _randomconst:2 "random 2" => double
          TRYCATCHBLOCK L0 L1 L2 org/nlogo/api/AgentException
         L3
          DCONST_1
         L4
          ALOAD 1
          GETFIELD org/nlogo/nvm/Context.job : Lorg/nlogo/nvm/Job;
          GETFIELD org/nlogo/nvm/Job.random : Lorg/nlogo/api/MersenneTwisterFast;
          LDC 2
          INVOKEVIRTUAL org/nlogo/api/MersenneTwisterFast.nextLong (J)J
          L2D
         L5
          DSTORE 4
          DSTORE 2
          ALOAD 0
          DLOAD 2
          DLOAD 4
          DADD
          INVOKEVIRTUAL org/nlogo/prim/_asm_proceduresetupfood_setpatchvariable_7.validDouble (D)D
         L6
          DSTORE 2
          NEW java/lang/Double
          DUP
          DLOAD 2
          INVOKESPECIAL java/lang/Double.<init> (D)V
          ASTORE 2
         L0
          ALOAD 1
          GETFIELD org/nlogo/nvm/Context.agent : Lorg/nlogo/agent/Agent;
          BIPUSH 6
          ALOAD 2
          INVOKEVIRTUAL org/nlogo/agent/Agent.setPatchVariable (ILjava/lang/Object;)V
         L1
          GOTO L7
         L2
         FRAME FULL [org/nlogo/prim/_asm_proceduresetupfood_setpatchvariable_7 org/nlogo/nvm/Context java/lang/Double T D] [org/nlogo/api/AgentException]
          ASTORE 3
          NEW org/nlogo/nvm/EngineException
          DUP
          ALOAD 1
          ALOAD 0
          ALOAD 3
          INVOKEVIRTUAL org/nlogo/api/AgentException.getMessage ()Ljava/lang/String;
          INVOKESPECIAL org/nlogo/nvm/EngineException.<init> (Lorg/nlogo/nvm/Context;Lorg/nlogo/nvm/Instruction;Ljava/lang/String;)V
          ATHROW
         L7
         FRAME SAME
          ALOAD 1
          BIPUSH 8
          PUTFIELD org/nlogo/nvm/Context.ip : I
         L8
          RETURN
[8]_asm_proceduresetupfood_return_8 => void
         L0
          ALOAD 1
          INVOKEVIRTUAL org/nlogo/nvm/Context.returnFromProcedure ()V
          ALOAD 1
          ICONST_0
          PUTFIELD org/nlogo/nvm/Context.stopping : Z
         L1
          RETURN

