globals [PLOT? TOTAL RESULT]
interfaceGlobals [plot?]
turtles-own [WHO COLOR HEADING XCOR YCOR SHAPE LABEL LABEL-COLOR BREED HIDDEN? SIZE PEN-SIZE PEN-MODE]
patches-own [PXCOR PYCOR PCOLOR PLABEL PLABEL-COLOR N]
links-own [END1 END2 COLOR LABEL LABEL-COLOR HIDDEN? BREED THICKNESS SHAPE TIE-MODE]
breeds 
link-breeds 

procedure BENCHMARK:[_repeatlocal:0]{O---}:
[0]_asm_procedurebenchmark_randomseed_0 "random-seed 0" double => void
      _constdouble:0.0 => double
         L0
          DCONST_0
         L1
          DSTORE 2
          DLOAD 2
          D2L
          LSTORE 4
          LLOAD 4
          LDC -2147483648
          LCMP
          IFLT L2
          LLOAD 4
          LDC 2147483647
          LCMP
          IFLE L3
         L2
          NEW org/nlogo/nvm/EngineException
          DUP
          ALOAD 1
          ALOAD 0
          NEW scala/collection/mutable/StringBuilder
          DUP
          INVOKESPECIAL scala/collection/mutable/StringBuilder.<init> ()V
          GETSTATIC org/nlogo/api/Dump$.MODULE$ : Lorg/nlogo/api/Dump$;
          DLOAD 2
          INVOKEVIRTUAL org/nlogo/api/Dump$.number (D)Ljava/lang/String;
          INVOKEVIRTUAL scala/collection/mutable/StringBuilder.append (Ljava/lang/Object;)Lscala/collection/mutable/StringBuilder;
          LDC " is not in the allowable range for random seeds (-2147483648 to 2147483647)"
          INVOKEVIRTUAL scala/collection/mutable/StringBuilder.append (Ljava/lang/Object;)Lscala/collection/mutable/StringBuilder;
          INVOKEVIRTUAL scala/collection/mutable/StringBuilder.toString ()Ljava/lang/String;
          INVOKESPECIAL org/nlogo/nvm/EngineException.<init> (Lorg/nlogo/nvm/Context;Lorg/nlogo/nvm/Instruction;Ljava/lang/String;)V
          ATHROW
         L3
          ALOAD 1
          GETFIELD org/nlogo/nvm/Context.job : Lorg/nlogo/nvm/Job;
          GETFIELD org/nlogo/nvm/Job.random : Lorg/nlogo/util/MersenneTwisterFast;
          LLOAD 4
          L2I
          I2L
          INVOKEVIRTUAL org/nlogo/util/MersenneTwisterFast.setSeed (J)V
          ALOAD 1
          ICONST_1
          PUTFIELD org/nlogo/nvm/Context.ip : I
         L4
          RETURN
[1]_resettimer
[2]_asm_procedurebenchmark_call_1 "setup"
         L0
          NEW org/nlogo/nvm/Activation
          DUP
          ALOAD 0
          GETFIELD org/nlogo/prim/_asm_procedurebenchmark_call_1.kept1_procedure : Lorg/nlogo/nvm/Procedure;
          ALOAD 1
          GETFIELD org/nlogo/nvm/Context.activation : Lorg/nlogo/nvm/Activation;
          ICONST_3
          INVOKESPECIAL org/nlogo/nvm/Activation.<init> (Lorg/nlogo/nvm/Procedure;Lorg/nlogo/nvm/Activation;I)V
          ALOAD 1
          SWAP
          PUTFIELD org/nlogo/nvm/Context.activation : Lorg/nlogo/nvm/Activation;
          ALOAD 1
          ICONST_0
          PUTFIELD org/nlogo/nvm/Context.ip : I
         L1
          RETURN
[3]_asm_procedurebenchmark_repeatlocal_2 "" double => void
      _constdouble:5000.0 => double
         L0
          LDC 5000.0
         L1
          DSTORE 2
          ALOAD 1
          GETFIELD org/nlogo/nvm/Context.activation : Lorg/nlogo/nvm/Activation;
          INVOKEVIRTUAL org/nlogo/nvm/Activation.args ()[Ljava/lang/Object;
          ICONST_0
          NEW org/nlogo/nvm/MutableLong
          DUP
          ALOAD 0
          DLOAD 2
          INVOKEVIRTUAL org/nlogo/prim/_asm_procedurebenchmark_repeatlocal_2.validLong (D)J
          INVOKESPECIAL org/nlogo/nvm/MutableLong.<init> (J)V
          AASTORE
          ALOAD 1
          ICONST_5
          PUTFIELD org/nlogo/nvm/Context.ip : I
         L2
          RETURN
[4]_asm_procedurebenchmark_call_3 "go"
         L0
          NEW org/nlogo/nvm/Activation
          DUP
          ALOAD 0
          GETFIELD org/nlogo/prim/_asm_procedurebenchmark_call_3.kept1_procedure : Lorg/nlogo/nvm/Procedure;
          ALOAD 1
          GETFIELD org/nlogo/nvm/Context.activation : Lorg/nlogo/nvm/Activation;
          ICONST_5
          INVOKESPECIAL org/nlogo/nvm/Activation.<init> (Lorg/nlogo/nvm/Procedure;Lorg/nlogo/nvm/Activation;I)V
          ALOAD 1
          SWAP
          PUTFIELD org/nlogo/nvm/Context.activation : Lorg/nlogo/nvm/Activation;
          ALOAD 1
          ICONST_0
          PUTFIELD org/nlogo/nvm/Context.ip : I
         L1
          RETURN
[5]_asm_procedurebenchmark_repeatlocalinternal_4 "" => void
         L0
          ALOAD 1
          GETFIELD org/nlogo/nvm/Context.activation : Lorg/nlogo/nvm/Activation;
          INVOKEVIRTUAL org/nlogo/nvm/Activation.args ()[Ljava/lang/Object;
          ICONST_0
          AALOAD
          CHECKCAST org/nlogo/nvm/MutableLong
          ASTORE 2
          ALOAD 2
          INVOKEVIRTUAL org/nlogo/nvm/MutableLong.value ()J
          LCONST_0
          LCMP
          IFGT L1
          ALOAD 1
          BIPUSH 6
          PUTFIELD org/nlogo/nvm/Context.ip : I
          GOTO L2
         L1
          ALOAD 2
          ALOAD 2
          INVOKEVIRTUAL org/nlogo/nvm/MutableLong.value ()J
          LCONST_1
          LSUB
          INVOKEVIRTUAL org/nlogo/nvm/MutableLong.value_$eq (J)V
          ALOAD 1
          ICONST_4
          PUTFIELD org/nlogo/nvm/Context.ip : I
         L2
          RETURN
[6]_asm_procedurebenchmark_setobservervariable_5 "set result timer" Object => void
      _timer => double
          TRYCATCHBLOCK L0 L1 L2 org/nlogo/api/AgentException
         L3
          ALOAD 0
          GETFIELD org/nlogo/prim/_asm_procedurebenchmark_setobservervariable_5.world : Lorg/nlogo/agent/World;
          INVOKEVIRTUAL org/nlogo/agent/World.timer ()Lorg/nlogo/api/Timer;
          INVOKEVIRTUAL org/nlogo/api/Timer.read ()D
         L4
          DSTORE 2
          NEW java/lang/Double
          DUP
          DLOAD 2
          INVOKESPECIAL java/lang/Double.<init> (D)V
          ASTORE 2
         L0
          ALOAD 0
          GETFIELD org/nlogo/prim/_asm_procedurebenchmark_setobservervariable_5.world : Lorg/nlogo/agent/World;
          INVOKEVIRTUAL org/nlogo/agent/World.observer ()Lorg/nlogo/agent/Observer;
          ICONST_2
          ALOAD 2
          INVOKEVIRTUAL org/nlogo/agent/Observer.setVariable (ILjava/lang/Object;)V
         L1
          ALOAD 1
          BIPUSH 7
          PUTFIELD org/nlogo/nvm/Context.ip : I
          GOTO L5
         L2
          ASTORE 3
          NEW org/nlogo/nvm/EngineException
          DUP
          ALOAD 1
          ALOAD 0
          ALOAD 3
          INVOKEVIRTUAL org/nlogo/api/AgentException.getMessage ()Ljava/lang/String;
          INVOKESPECIAL org/nlogo/nvm/EngineException.<init> (Lorg/nlogo/nvm/Context;Lorg/nlogo/nvm/Instruction;Ljava/lang/String;)V
          ATHROW
         L5
          RETURN
[7]_asm_procedurebenchmark_return_6 "" => void
         L0
          ALOAD 1
          INVOKEVIRTUAL org/nlogo/nvm/Context.returnFromProcedure ()V
          ALOAD 1
          ICONST_0
          PUTFIELD org/nlogo/nvm/Context.stopping : Z
         L1
          RETURN

procedure SETUP:[]{O---}:
[0]_clearall
[1]_asm_proceduresetup_ask_0 "ask patches" AgentSet => void
      _patches => AgentSet
         L0
          ALOAD 0
          GETFIELD org/nlogo/prim/_asm_proceduresetup_ask_0.world : Lorg/nlogo/agent/World;
          INVOKEVIRTUAL org/nlogo/agent/World.patches ()Lorg/nlogo/agent/AgentSet;
         L1
          ASTORE 2
          ALOAD 1
          GETFIELD org/nlogo/nvm/Context.agent : Lorg/nlogo/agent/Agent;
          INSTANCEOF org/nlogo/agent/Observer
          IFNE L2
          ALOAD 2
          ALOAD 0
          GETFIELD org/nlogo/prim/_asm_proceduresetup_ask_0.world : Lorg/nlogo/agent/World;
          INVOKEVIRTUAL org/nlogo/agent/World.turtles ()Lorg/nlogo/agent/AgentSet;
          IF_ACMPNE L3
          NEW org/nlogo/nvm/EngineException
          DUP
          ALOAD 1
          ALOAD 0
          GETSTATIC org/nlogo/api/I18N$.MODULE$ : Lorg/nlogo/api/I18N$;
          INVOKEVIRTUAL org/nlogo/api/I18N$.errors ()Lorg/nlogo/api/I18N$BundleKind;
          LDC "org.nlogo.prim.$common.onlyObserverCanAskAllTurtles"
          INVOKEVIRTUAL org/nlogo/api/I18N$BundleKind.get (Ljava/lang/String;)Ljava/lang/String;
          INVOKESPECIAL org/nlogo/nvm/EngineException.<init> (Lorg/nlogo/nvm/Context;Lorg/nlogo/nvm/Instruction;Ljava/lang/String;)V
          ATHROW
         L3
          ALOAD 2
          ALOAD 0
          GETFIELD org/nlogo/prim/_asm_proceduresetup_ask_0.world : Lorg/nlogo/agent/World;
          INVOKEVIRTUAL org/nlogo/agent/World.patches ()Lorg/nlogo/agent/AgentSet;
          IF_ACMPNE L2
          NEW org/nlogo/nvm/EngineException
          DUP
          ALOAD 1
          ALOAD 0
          GETSTATIC org/nlogo/api/I18N$.MODULE$ : Lorg/nlogo/api/I18N$;
          INVOKEVIRTUAL org/nlogo/api/I18N$.errors ()Lorg/nlogo/api/I18N$BundleKind;
          LDC "org.nlogo.prim.$common.onlyObserverCanAskAllPatches"
          INVOKEVIRTUAL org/nlogo/api/I18N$BundleKind.get (Ljava/lang/String;)Ljava/lang/String;
          INVOKESPECIAL org/nlogo/nvm/EngineException.<init> (Lorg/nlogo/nvm/Context;Lorg/nlogo/nvm/Instruction;Ljava/lang/String;)V
          ATHROW
         L2
          ALOAD 1
          ALOAD 2
          ICONST_2
          INVOKEVIRTUAL org/nlogo/nvm/Context.runExclusiveJob (Lorg/nlogo/agent/AgentSet;I)V
          ALOAD 1
          ICONST_5
          PUTFIELD org/nlogo/nvm/Context.ip : I
         L4
          RETURN
[2]_asm_proceduresetup_setpatchvariable_1 "set n 2" Object => void
      _constdouble:2.0 => Double
          TRYCATCHBLOCK L0 L1 L2 org/nlogo/api/AgentException
         L3
          ALOAD 0
          GETFIELD org/nlogo/prim/_asm_proceduresetup_setpatchvariable_1.kept2_value : Ljava/lang/Double;
         L4
          ASTORE 2
         L0
          ALOAD 1
          GETFIELD org/nlogo/nvm/Context.agent : Lorg/nlogo/agent/Agent;
          ICONST_5
          ALOAD 2
          INVOKEVIRTUAL org/nlogo/agent/Agent.setPatchVariable (ILjava/lang/Object;)V
         L1
          ALOAD 1
          ICONST_3
          PUTFIELD org/nlogo/nvm/Context.ip : I
          GOTO L5
         L2
          ASTORE 3
          NEW org/nlogo/nvm/EngineException
          DUP
          ALOAD 1
          ALOAD 0
          ALOAD 3
          INVOKEVIRTUAL org/nlogo/api/AgentException.getMessage ()Ljava/lang/String;
          INVOKESPECIAL org/nlogo/nvm/EngineException.<init> (Lorg/nlogo/nvm/Context;Lorg/nlogo/nvm/Instruction;Ljava/lang/String;)V
          ATHROW
         L5
          RETURN
[3]_asm_proceduresetup_call_2 "colorize"
         L0
          NEW org/nlogo/nvm/Activation
          DUP
          ALOAD 0
          GETFIELD org/nlogo/prim/_asm_proceduresetup_call_2.kept1_procedure : Lorg/nlogo/nvm/Procedure;
          ALOAD 1
          GETFIELD org/nlogo/nvm/Context.activation : Lorg/nlogo/nvm/Activation;
          ICONST_4
          INVOKESPECIAL org/nlogo/nvm/Activation.<init> (Lorg/nlogo/nvm/Procedure;Lorg/nlogo/nvm/Activation;I)V
          ALOAD 1
          SWAP
          PUTFIELD org/nlogo/nvm/Context.activation : Lorg/nlogo/nvm/Activation;
          ALOAD 1
          ICONST_0
          PUTFIELD org/nlogo/nvm/Context.ip : I
         L1
          RETURN
[4]_asm_proceduresetup_done_3 "" => void
         L0
          ALOAD 1
          ICONST_1
          PUTFIELD org/nlogo/nvm/Context.finished : Z
         L1
          RETURN
[5]_asm_proceduresetup_setobservervariable_4 "set total 2 * count patches" Object => void
      _mult double,double => double
        _constdouble:2.0 => double
        _count AgentSet => double
          _patches => AgentSet
          TRYCATCHBLOCK L0 L1 L2 org/nlogo/api/AgentException
         L3
          LDC 2.0
         L4
          ALOAD 0
          GETFIELD org/nlogo/prim/_asm_proceduresetup_setobservervariable_4.world : Lorg/nlogo/agent/World;
          INVOKEVIRTUAL org/nlogo/agent/World.patches ()Lorg/nlogo/agent/AgentSet;
         L5
          ASTORE 2
          ALOAD 2
          INVOKEVIRTUAL org/nlogo/agent/AgentSet.count ()I
          I2D
         L6
          DSTORE 4
          DSTORE 2
          DLOAD 2
          DLOAD 4
          DMUL
         L7
          DSTORE 2
          NEW java/lang/Double
          DUP
          DLOAD 2
          INVOKESPECIAL java/lang/Double.<init> (D)V
          ASTORE 2
         L0
          ALOAD 0
          GETFIELD org/nlogo/prim/_asm_proceduresetup_setobservervariable_4.world : Lorg/nlogo/agent/World;
          INVOKEVIRTUAL org/nlogo/agent/World.observer ()Lorg/nlogo/agent/Observer;
          ICONST_1
          ALOAD 2
          INVOKEVIRTUAL org/nlogo/agent/Observer.setVariable (ILjava/lang/Object;)V
         L1
          ALOAD 1
          BIPUSH 6
          PUTFIELD org/nlogo/nvm/Context.ip : I
          GOTO L8
         L2
          ASTORE 3
          NEW org/nlogo/nvm/EngineException
          DUP
          ALOAD 1
          ALOAD 0
          ALOAD 3
          INVOKEVIRTUAL org/nlogo/api/AgentException.getMessage ()Ljava/lang/String;
          INVOKESPECIAL org/nlogo/nvm/EngineException.<init> (Lorg/nlogo/nvm/Context;Lorg/nlogo/nvm/Instruction;Ljava/lang/String;)V
          ATHROW
         L8
          RETURN
[6]_resetticks
[7]_asm_proceduresetup_return_5 "" => void
         L0
          ALOAD 1
          INVOKEVIRTUAL org/nlogo/nvm/Context.returnFromProcedure ()V
          ALOAD 1
          ICONST_0
          PUTFIELD org/nlogo/nvm/Context.stopping : Z
         L1
          RETURN

procedure GO:[ACTIVE-PATCHES OVERLOADED-PATCHES]{O---}:
[0]_asm_procedurego_setprocedurevariable_0 "" Object => void
      _patchset
        _asm_procedurego_oneof_1 "one-of patches" AgentSet => Object
          _patches => AgentSet
             L0
              ALOAD 0
              GETFIELD org/nlogo/prim/_asm_procedurego_oneof_1.world : Lorg/nlogo/agent/World;
              INVOKEVIRTUAL org/nlogo/agent/World.patches ()Lorg/nlogo/agent/AgentSet;
             L1
              ASTORE 2
              ALOAD 2
              INVOKEVIRTUAL org/nlogo/agent/AgentSet.count ()I
              ISTORE 3
              ILOAD 3
              ICONST_0
              IF_ICMPNE L2
              GETSTATIC org/nlogo/api/Nobody$.MODULE$ : Lorg/nlogo/api/Nobody$;
              GOTO L3
             L2
              ALOAD 2
              ILOAD 3
              ALOAD 1
              GETFIELD org/nlogo/nvm/Context.job : Lorg/nlogo/nvm/Job;
              GETFIELD org/nlogo/nvm/Job.random : Lorg/nlogo/util/MersenneTwisterFast;
              ILOAD 3
              INVOKEVIRTUAL org/nlogo/util/MersenneTwisterFast.nextInt (I)I
              INVOKEVIRTUAL org/nlogo/agent/AgentSet.randomOne (II)Lorg/nlogo/agent/Agent;
             L3
              ARETURN
          ALOAD 0
          GETFIELD org/nlogo/prim/_asm_procedurego_setprocedurevariable_0.keptinstr2 : Lorg/nlogo/prim/etc/_patchset;
          ALOAD 1
          INVOKEVIRTUAL org/nlogo/prim/etc/_patchset.report (Lorg/nlogo/nvm/Context;)Ljava/lang/Object;
         L0
          ASTORE 2
          ALOAD 1
          GETFIELD org/nlogo/nvm/Context.activation : Lorg/nlogo/nvm/Activation;
          INVOKEVIRTUAL org/nlogo/nvm/Activation.args ()[Ljava/lang/Object;
          ICONST_0
          ALOAD 2
          AASTORE
          ALOAD 1
          ICONST_1
          PUTFIELD org/nlogo/nvm/Context.ip : I
         L1
          RETURN
[1]_asm_procedurego_ask_2 "ask active-patches" Object => void
      _procedurevariable:ACTIVE-PATCHES => Object
         L0
          ALOAD 1
          GETFIELD org/nlogo/nvm/Context.activation : Lorg/nlogo/nvm/Activation;
          INVOKEVIRTUAL org/nlogo/nvm/Activation.args ()[Ljava/lang/Object;
          ICONST_0
          AALOAD
         L1
          ASTORE 2
          ALOAD 2
          ASTORE 4
          ALOAD 4
          INSTANCEOF org/nlogo/agent/AgentSet
          IFEQ L2
          ALOAD 4
          CHECKCAST org/nlogo/agent/AgentSet
          ASTORE 5
          ALOAD 1
          GETFIELD org/nlogo/nvm/Context.agent : Lorg/nlogo/agent/Agent;
          INSTANCEOF org/nlogo/agent/Observer
          IFNE L3
          ALOAD 5
          ALOAD 0
          GETFIELD org/nlogo/prim/_asm_procedurego_ask_2.world : Lorg/nlogo/agent/World;
          INVOKEVIRTUAL org/nlogo/agent/World.turtles ()Lorg/nlogo/agent/AgentSet;
          IF_ACMPNE L4
          NEW org/nlogo/nvm/EngineException
          DUP
          ALOAD 1
          ALOAD 0
          GETSTATIC org/nlogo/api/I18N$.MODULE$ : Lorg/nlogo/api/I18N$;
          INVOKEVIRTUAL org/nlogo/api/I18N$.errors ()Lorg/nlogo/api/I18N$BundleKind;
          LDC "org.nlogo.prim.$common.onlyObserverCanAskAllTurtles"
          INVOKEVIRTUAL org/nlogo/api/I18N$BundleKind.get (Ljava/lang/String;)Ljava/lang/String;
          INVOKESPECIAL org/nlogo/nvm/EngineException.<init> (Lorg/nlogo/nvm/Context;Lorg/nlogo/nvm/Instruction;Ljava/lang/String;)V
          ATHROW
         L4
          ALOAD 5
          ALOAD 0
          GETFIELD org/nlogo/prim/_asm_procedurego_ask_2.world : Lorg/nlogo/agent/World;
          INVOKEVIRTUAL org/nlogo/agent/World.patches ()Lorg/nlogo/agent/AgentSet;
          IF_ACMPNE L3
          NEW org/nlogo/nvm/EngineException
          DUP
          ALOAD 1
          ALOAD 0
          GETSTATIC org/nlogo/api/I18N$.MODULE$ : Lorg/nlogo/api/I18N$;
          INVOKEVIRTUAL org/nlogo/api/I18N$.errors ()Lorg/nlogo/api/I18N$BundleKind;
          LDC "org.nlogo.prim.$common.onlyObserverCanAskAllPatches"
          INVOKEVIRTUAL org/nlogo/api/I18N$BundleKind.get (Ljava/lang/String;)Ljava/lang/String;
          INVOKESPECIAL org/nlogo/nvm/EngineException.<init> (Lorg/nlogo/nvm/Context;Lorg/nlogo/nvm/Instruction;Ljava/lang/String;)V
          ATHROW
         L3
          ALOAD 5
          ASTORE 6
          GOTO L5
         L2
          ALOAD 4
          INSTANCEOF org/nlogo/agent/Agent
          IFEQ L6
          ALOAD 4
          CHECKCAST org/nlogo/agent/Agent
          ASTORE 7
          ALOAD 7
          INVOKEVIRTUAL org/nlogo/agent/Agent.id ()J
          LDC -1
          LCMP
          IFNE L7
          NEW org/nlogo/nvm/EngineException
          DUP
          ALOAD 1
          ALOAD 0
          GETSTATIC org/nlogo/api/I18N$.MODULE$ : Lorg/nlogo/api/I18N$;
          INVOKEVIRTUAL org/nlogo/api/I18N$.errors ()Lorg/nlogo/api/I18N$BundleKind;
          LDC "org.nlogo.$common.thatAgentIsDead"
          GETSTATIC scala/Predef$.MODULE$ : Lscala/Predef$;
          ICONST_1
          ANEWARRAY java/lang/Object
          DUP
          ICONST_0
          ALOAD 7
          INVOKEVIRTUAL org/nlogo/agent/Agent.classDisplayName ()Ljava/lang/String;
          AASTORE
          INVOKEVIRTUAL scala/Predef$.wrapRefArray ([Ljava/lang/Object;)Lscala/collection/mutable/WrappedArray;
          INVOKEVIRTUAL org/nlogo/api/I18N$BundleKind.getN (Ljava/lang/String;Lscala/collection/Seq;)Ljava/lang/String;
          INVOKESPECIAL org/nlogo/nvm/EngineException.<init> (Lorg/nlogo/nvm/Context;Lorg/nlogo/nvm/Instruction;Ljava/lang/String;)V
          ATHROW
         L7
          GETSTATIC org/nlogo/agent/AgentSet$.MODULE$ : Lorg/nlogo/agent/AgentSet$;
          ALOAD 7
          INVOKEVIRTUAL org/nlogo/agent/AgentSet$.fromAgent (Lorg/nlogo/agent/Agent;)Lorg/nlogo/agent/AgentSet;
          ASTORE 6
         L5
          ALOAD 6
          ASTORE 3
          ALOAD 1
          ALOAD 3
          ICONST_2
          INVOKEVIRTUAL org/nlogo/nvm/Context.runExclusiveJob (Lorg/nlogo/agent/AgentSet;I)V
          ALOAD 1
          BIPUSH 6
          PUTFIELD org/nlogo/nvm/Context.ip : I
          GOTO L8
         L6
          NEW org/nlogo/nvm/ArgumentTypeException
          DUP
          ALOAD 1
          ALOAD 0
          ICONST_0
          GETSTATIC org/nlogo/api/Syntax$.MODULE$ : Lorg/nlogo/api/Syntax$;
          INVOKEVIRTUAL org/nlogo/api/Syntax$.AgentsetType ()I
          GETSTATIC org/nlogo/api/Syntax$.MODULE$ : Lorg/nlogo/api/Syntax$;
          INVOKEVIRTUAL org/nlogo/api/Syntax$.AgentType ()I
          IOR
          ALOAD 2
          INVOKESPECIAL org/nlogo/nvm/ArgumentTypeException.<init> (Lorg/nlogo/nvm/Context;Lorg/nlogo/nvm/Instruction;IILjava/lang/Object;)V
          ATHROW
         L8
          RETURN
[2]_asm_procedurego_setpatchvariable_3 "set n n + 1" Object => void
      _plus double,double => double
        _patchvariable:N => Object
        _constdouble:1.0 => double
          TRYCATCHBLOCK L0 L1 L2 org/nlogo/api/AgentException
          TRYCATCHBLOCK L3 L4 L4 java/lang/ClassCastException
          TRYCATCHBLOCK L5 L6 L7 org/nlogo/api/AgentException
         L0
          ALOAD 1
          GETFIELD org/nlogo/nvm/Context.agent : Lorg/nlogo/agent/Agent;
          ICONST_5
          INVOKEVIRTUAL org/nlogo/agent/Agent.getPatchVariable (I)Ljava/lang/Object;
         L1
          GOTO L8
         L2
          ASTORE 2
          NEW org/nlogo/nvm/EngineException
          DUP
          ALOAD 1
          ALOAD 0
          ALOAD 2
          INVOKEVIRTUAL org/nlogo/api/AgentException.getMessage ()Ljava/lang/String;
          INVOKESPECIAL org/nlogo/nvm/EngineException.<init> (Lorg/nlogo/nvm/Context;Lorg/nlogo/nvm/Instruction;Ljava/lang/String;)V
          ATHROW
         L8
          ASTORE 2
         L3
          ALOAD 2
          CHECKCAST java/lang/Double
          INVOKEVIRTUAL java/lang/Double.doubleValue ()D
          GOTO L9
         L4
          POP
          NEW org/nlogo/nvm/ArgumentTypeException
          DUP
          ALOAD 1
          ALOAD 0
          BIPUSH 0
          LDC 1
          ALOAD 2
          INVOKESPECIAL org/nlogo/nvm/ArgumentTypeException.<init> (Lorg/nlogo/nvm/Context;Lorg/nlogo/nvm/Instruction;IILjava/lang/Object;)V
          ATHROW
         L9
          DCONST_1
         L10
          DSTORE 4
          DSTORE 2
          DLOAD 2
          DLOAD 4
          DADD
         L11
          DSTORE 2
          NEW java/lang/Double
          DUP
          DLOAD 2
          INVOKESPECIAL java/lang/Double.<init> (D)V
          ASTORE 2
         L5
          ALOAD 1
          GETFIELD org/nlogo/nvm/Context.agent : Lorg/nlogo/agent/Agent;
          ICONST_5
          ALOAD 2
          INVOKEVIRTUAL org/nlogo/agent/Agent.setPatchVariable (ILjava/lang/Object;)V
         L6
          ALOAD 1
          ICONST_3
          PUTFIELD org/nlogo/nvm/Context.ip : I
          GOTO L12
         L7
          ASTORE 3
          NEW org/nlogo/nvm/EngineException
          DUP
          ALOAD 1
          ALOAD 0
          ALOAD 3
          INVOKEVIRTUAL org/nlogo/api/AgentException.getMessage ()Ljava/lang/String;
          INVOKESPECIAL org/nlogo/nvm/EngineException.<init> (Lorg/nlogo/nvm/Context;Lorg/nlogo/nvm/Instruction;Ljava/lang/String;)V
          ATHROW
         L12
          RETURN
[3]_asm_procedurego_setobservervariable_4 "set total total + 1" Object => void
      _plus double,double => double
        _observervariable:TOTAL => Object
        _constdouble:1.0 => double
          TRYCATCHBLOCK L0 L1 L1 java/lang/ClassCastException
          TRYCATCHBLOCK L2 L3 L4 org/nlogo/api/AgentException
         L5
          ALOAD 0
          GETFIELD org/nlogo/prim/_asm_procedurego_setobservervariable_4.world : Lorg/nlogo/agent/World;
          INVOKEVIRTUAL org/nlogo/agent/World.observer ()Lorg/nlogo/agent/Observer;
          ICONST_1
          INVOKEVIRTUAL org/nlogo/agent/Observer.getVariable (I)Ljava/lang/Object;
         L6
          ASTORE 2
         L0
          ALOAD 2
          CHECKCAST java/lang/Double
          INVOKEVIRTUAL java/lang/Double.doubleValue ()D
          GOTO L7
         L1
          POP
          NEW org/nlogo/nvm/ArgumentTypeException
          DUP
          ALOAD 1
          ALOAD 0
          BIPUSH 0
          LDC 1
          ALOAD 2
          INVOKESPECIAL org/nlogo/nvm/ArgumentTypeException.<init> (Lorg/nlogo/nvm/Context;Lorg/nlogo/nvm/Instruction;IILjava/lang/Object;)V
          ATHROW
         L7
          DCONST_1
         L8
          DSTORE 4
          DSTORE 2
          DLOAD 2
          DLOAD 4
          DADD
         L9
          DSTORE 2
          NEW java/lang/Double
          DUP
          DLOAD 2
          INVOKESPECIAL java/lang/Double.<init> (D)V
          ASTORE 2
         L2
          ALOAD 0
          GETFIELD org/nlogo/prim/_asm_procedurego_setobservervariable_4.world : Lorg/nlogo/agent/World;
          INVOKEVIRTUAL org/nlogo/agent/World.observer ()Lorg/nlogo/agent/Observer;
          ICONST_1
          ALOAD 2
          INVOKEVIRTUAL org/nlogo/agent/Observer.setVariable (ILjava/lang/Object;)V
         L3
          ALOAD 1
          ICONST_4
          PUTFIELD org/nlogo/nvm/Context.ip : I
          GOTO L10
         L4
          ASTORE 3
          NEW org/nlogo/nvm/EngineException
          DUP
          ALOAD 1
          ALOAD 0
          ALOAD 3
          INVOKEVIRTUAL org/nlogo/api/AgentException.getMessage ()Ljava/lang/String;
          INVOKESPECIAL org/nlogo/nvm/EngineException.<init> (Lorg/nlogo/nvm/Context;Lorg/nlogo/nvm/Instruction;Ljava/lang/String;)V
          ATHROW
         L10
          RETURN
[4]_asm_procedurego_call_5 "colorize"
         L0
          NEW org/nlogo/nvm/Activation
          DUP
          ALOAD 0
          GETFIELD org/nlogo/prim/_asm_procedurego_call_5.kept1_procedure : Lorg/nlogo/nvm/Procedure;
          ALOAD 1
          GETFIELD org/nlogo/nvm/Context.activation : Lorg/nlogo/nvm/Activation;
          ICONST_5
          INVOKESPECIAL org/nlogo/nvm/Activation.<init> (Lorg/nlogo/nvm/Procedure;Lorg/nlogo/nvm/Activation;I)V
          ALOAD 1
          SWAP
          PUTFIELD org/nlogo/nvm/Context.activation : Lorg/nlogo/nvm/Activation;
          ALOAD 1
          ICONST_0
          PUTFIELD org/nlogo/nvm/Context.ip : I
         L1
          RETURN
[5]_asm_procedurego_done_6 "" => void
         L0
          ALOAD 1
          ICONST_1
          PUTFIELD org/nlogo/nvm/Context.finished : Z
         L1
          RETURN
[6]_asm_procedurego_goto_7 "" => void
         L0
          ALOAD 1
          BIPUSH 19
          PUTFIELD org/nlogo/nvm/Context.ip : I
         L1
          RETURN
[7]_asm_procedurego_setprocedurevariable_8 "" Object => void
      _with AgentSet,Reporter => AgentSet
        _procedurevariable:ACTIVE-PATCHES => Object
        _asm_procedurego_greaterthan_9 "n > 3" Object,double => boolean
          _patchvariable:N => Object
          _constdouble:3.0 => double
              TRYCATCHBLOCK L0 L1 L2 org/nlogo/api/AgentException
             L0
              ALOAD 1
              GETFIELD org/nlogo/nvm/Context.agent : Lorg/nlogo/agent/Agent;
              ICONST_5
              INVOKEVIRTUAL org/nlogo/agent/Agent.getPatchVariable (I)Ljava/lang/Object;
             L1
              GOTO L3
             L2
              ASTORE 2
              NEW org/nlogo/nvm/EngineException
              DUP
              ALOAD 1
              ALOAD 0
              ALOAD 2
              INVOKEVIRTUAL org/nlogo/api/AgentException.getMessage ()Ljava/lang/String;
              INVOKESPECIAL org/nlogo/nvm/EngineException.<init> (Lorg/nlogo/nvm/Context;Lorg/nlogo/nvm/Instruction;Ljava/lang/String;)V
              ATHROW
             L3
              LDC 3.0
             L4
              DSTORE 3
              ASTORE 2
              ALOAD 2
              ASTORE 5
              ALOAD 5
              INSTANCEOF java/lang/Double
              IFEQ L5
              ALOAD 5
              CHECKCAST java/lang/Double
              ASTORE 6
              ALOAD 6
              INVOKEVIRTUAL java/lang/Double.doubleValue ()D
              DLOAD 3
              DCMPL
              IFLE L6
              ICONST_1
              GOTO L7
             L6
              ICONST_0
             L7
              ISTORE 7
              ILOAD 7
              GOTO L8
             L5
              NEW org/nlogo/nvm/EngineException
              DUP
              ALOAD 1
              ALOAD 0
              GETSTATIC org/nlogo/api/I18N$.MODULE$ : Lorg/nlogo/api/I18N$;
              INVOKEVIRTUAL org/nlogo/api/I18N$.errors ()Lorg/nlogo/api/I18N$BundleKind;
              LDC "org.nlogo.prim._greaterthan.cannotCompareParameters"
              GETSTATIC scala/Predef$.MODULE$ : Lscala/Predef$;
              ICONST_2
              ANEWARRAY java/lang/Object
              DUP
              ICONST_0
              GETSTATIC org/nlogo/api/TypeNames$.MODULE$ : Lorg/nlogo/api/TypeNames$;
              ALOAD 2
              INVOKEVIRTUAL org/nlogo/api/TypeNames$.aName (Ljava/lang/Object;)Ljava/lang/String;
              AASTORE
              DUP
              ICONST_1
              GETSTATIC org/nlogo/api/TypeNames$.MODULE$ : Lorg/nlogo/api/TypeNames$;
              DLOAD 3
              INVOKESTATIC scala/runtime/BoxesRunTime.boxToDouble (D)Ljava/lang/Double;
              INVOKEVIRTUAL org/nlogo/api/TypeNames$.aName (Ljava/lang/Object;)Ljava/lang/String;
              AASTORE
              INVOKEVIRTUAL scala/Predef$.wrapRefArray ([Ljava/lang/Object;)Lscala/collection/mutable/WrappedArray;
              INVOKEVIRTUAL org/nlogo/api/I18N$BundleKind.getN (Ljava/lang/String;Lscala/collection/Seq;)Ljava/lang/String;
              INVOKESPECIAL org/nlogo/nvm/EngineException.<init> (Lorg/nlogo/nvm/Context;Lorg/nlogo/nvm/Instruction;Ljava/lang/String;)V
              ATHROW
             L8
              IFEQ L9
              GETSTATIC java/lang/Boolean.TRUE : Ljava/lang/Boolean;
              GOTO L10
             L9
              GETSTATIC java/lang/Boolean.FALSE : Ljava/lang/Boolean;
             L10
              ARETURN
          TRYCATCHBLOCK L0 L1 L1 java/lang/ClassCastException
         L2
          ALOAD 1
          GETFIELD org/nlogo/nvm/Context.activation : Lorg/nlogo/nvm/Activation;
          INVOKEVIRTUAL org/nlogo/nvm/Activation.args ()[Ljava/lang/Object;
          ICONST_0
          AALOAD
         L3
          ASTORE 2
         L0
          ALOAD 2
          CHECKCAST org/nlogo/agent/AgentSet
          GOTO L4
         L1
          POP
          NEW org/nlogo/nvm/ArgumentTypeException
          DUP
          ALOAD 1
          ALOAD 0
          BIPUSH 0
          LDC 112
          ALOAD 2
          INVOKESPECIAL org/nlogo/nvm/ArgumentTypeException.<init> (Lorg/nlogo/nvm/Context;Lorg/nlogo/nvm/Instruction;IILjava/lang/Object;)V
          ATHROW
         L4
          ALOAD 0
          GETFIELD org/nlogo/prim/_asm_procedurego_setprocedurevariable_8.keptinstr4 : Lorg/nlogo/prim/_asm_procedurego_greaterthan_9;
          ASTORE 3
          ASTORE 2
          NEW org/nlogo/nvm/Context
          DUP
          ALOAD 1
          ALOAD 2
          INVOKESPECIAL org/nlogo/nvm/Context.<init> (Lorg/nlogo/nvm/Context;Lorg/nlogo/agent/AgentSet;)V
          ASTORE 4
          GETSTATIC scala/collection/mutable/ArrayBuffer$.MODULE$ : Lscala/collection/mutable/ArrayBuffer$;
          GETSTATIC scala/collection/immutable/Nil$.MODULE$ : Lscala/collection/immutable/Nil$;
          INVOKEVIRTUAL scala/collection/mutable/ArrayBuffer$.apply (Lscala/collection/Seq;)Lscala/collection/GenTraversable;
          CHECKCAST scala/collection/mutable/ArrayBuffer
          ASTORE 5
          ALOAD 3
          ALOAD 2
          ALOAD 1
          INVOKEVIRTUAL org/nlogo/nvm/Reporter.checkAgentSetClass (Lorg/nlogo/agent/AgentSet;Lorg/nlogo/nvm/Context;)V
          ALOAD 2
          INVOKEVIRTUAL org/nlogo/agent/AgentSet.iterator ()Lorg/nlogo/agent/AgentIterator;
          ASTORE 6
         L5
          ALOAD 6
          INVOKEINTERFACE org/nlogo/agent/AgentIterator.hasNext ()Z
          IFEQ L6
          ALOAD 6
          INVOKEINTERFACE org/nlogo/agent/AgentIterator.next ()Lorg/nlogo/agent/Agent;
          ASTORE 7
          ALOAD 4
          ALOAD 7
          ALOAD 3
          INVOKEVIRTUAL org/nlogo/nvm/Context.evaluateReporter (Lorg/nlogo/agent/Agent;Lorg/nlogo/nvm/Reporter;)Ljava/lang/Object;
          ASTORE 8
          ALOAD 8
          INSTANCEOF java/lang/Boolean
          IFEQ L7
          ALOAD 8
          CHECKCAST java/lang/Boolean
          ASTORE 9
          ALOAD 9
          INVOKEVIRTUAL java/lang/Boolean.booleanValue ()Z
          IFEQ L8
          ALOAD 5
          ALOAD 7
          INVOKEVIRTUAL scala/collection/mutable/ArrayBuffer.$plus$eq (Ljava/lang/Object;)Lscala/collection/mutable/ArrayBuffer;
          GOTO L9
         L8
          GETSTATIC scala/runtime/BoxedUnit.UNIT : Lscala/runtime/BoxedUnit;
         L9
          ASTORE 10
          ALOAD 10
          POP
          GOTO L5
         L7
          NEW org/nlogo/nvm/EngineException
          DUP
          ALOAD 1
          ALOAD 0
          GETSTATIC org/nlogo/api/I18N$.MODULE$ : Lorg/nlogo/api/I18N$;
          INVOKEVIRTUAL org/nlogo/api/I18N$.errors ()Lorg/nlogo/api/I18N$BundleKind;
          LDC "org.nlogo.prim.$common.expectedBooleanValue"
          GETSTATIC scala/Predef$.MODULE$ : Lscala/Predef$;
          ICONST_3
          ANEWARRAY java/lang/Object
          DUP
          ICONST_0
          LDC "WITH"
          AASTORE
          DUP
          ICONST_1
          GETSTATIC org/nlogo/api/Dump$.MODULE$ : Lorg/nlogo/api/Dump$;
          ALOAD 7
          INVOKEVIRTUAL org/nlogo/api/Dump$.logoObject (Ljava/lang/Object;)Ljava/lang/String;
          AASTORE
          DUP
          ICONST_2
          GETSTATIC org/nlogo/api/Dump$.MODULE$ : Lorg/nlogo/api/Dump$;
          ALOAD 8
          INVOKEVIRTUAL org/nlogo/api/Dump$.logoObject (Ljava/lang/Object;)Ljava/lang/String;
          AASTORE
          INVOKEVIRTUAL scala/Predef$.wrapRefArray ([Ljava/lang/Object;)Lscala/collection/mutable/WrappedArray;
          INVOKEVIRTUAL org/nlogo/api/I18N$BundleKind.getN (Ljava/lang/String;Lscala/collection/Seq;)Ljava/lang/String;
          INVOKESPECIAL org/nlogo/nvm/EngineException.<init> (Lorg/nlogo/nvm/Context;Lorg/nlogo/nvm/Instruction;Ljava/lang/String;)V
          ATHROW
         L6
          GETSTATIC org/nlogo/agent/AgentSet$.MODULE$ : Lorg/nlogo/agent/AgentSet$;
          ALOAD 2
          INVOKEVIRTUAL org/nlogo/agent/AgentSet.kind ()Lorg/nlogo/api/AgentKind;
          ALOAD 5
          GETSTATIC scala/reflect/ClassTag$.MODULE$ : Lscala/reflect/ClassTag$;
          LDC Lorg/nlogo/agent/Agent;.class
          INVOKEVIRTUAL scala/reflect/ClassTag$.apply (Ljava/lang/Class;)Lscala/reflect/ClassTag;
          INVOKEVIRTUAL scala/collection/mutable/ArrayBuffer.toArray (Lscala/reflect/ClassTag;)Ljava/lang/Object;
          CHECKCAST [Lorg/nlogo/agent/Agent;
          INVOKEVIRTUAL org/nlogo/agent/AgentSet$.fromArray (Lorg/nlogo/api/AgentKind;[Lorg/nlogo/agent/Agent;)Lorg/nlogo/agent/AgentSet;
         L10
          ASTORE 2
          ALOAD 1
          GETFIELD org/nlogo/nvm/Context.activation : Lorg/nlogo/nvm/Activation;
          INVOKEVIRTUAL org/nlogo/nvm/Activation.args ()[Ljava/lang/Object;
          ICONST_1
          ALOAD 2
          AASTORE
          ALOAD 1
          BIPUSH 8
          PUTFIELD org/nlogo/nvm/Context.ip : I
         L11
          RETURN
[8]_asm_procedurego_ask_10 "ask overloaded-patches" Object => void
      _procedurevariable:OVERLOADED-PATCHES => Object
         L0
          ALOAD 1
          GETFIELD org/nlogo/nvm/Context.activation : Lorg/nlogo/nvm/Activation;
          INVOKEVIRTUAL org/nlogo/nvm/Activation.args ()[Ljava/lang/Object;
          ICONST_1
          AALOAD
         L1
          ASTORE 2
          ALOAD 2
          ASTORE 4
          ALOAD 4
          INSTANCEOF org/nlogo/agent/AgentSet
          IFEQ L2
          ALOAD 4
          CHECKCAST org/nlogo/agent/AgentSet
          ASTORE 5
          ALOAD 1
          GETFIELD org/nlogo/nvm/Context.agent : Lorg/nlogo/agent/Agent;
          INSTANCEOF org/nlogo/agent/Observer
          IFNE L3
          ALOAD 5
          ALOAD 0
          GETFIELD org/nlogo/prim/_asm_procedurego_ask_10.world : Lorg/nlogo/agent/World;
          INVOKEVIRTUAL org/nlogo/agent/World.turtles ()Lorg/nlogo/agent/AgentSet;
          IF_ACMPNE L4
          NEW org/nlogo/nvm/EngineException
          DUP
          ALOAD 1
          ALOAD 0
          GETSTATIC org/nlogo/api/I18N$.MODULE$ : Lorg/nlogo/api/I18N$;
          INVOKEVIRTUAL org/nlogo/api/I18N$.errors ()Lorg/nlogo/api/I18N$BundleKind;
          LDC "org.nlogo.prim.$common.onlyObserverCanAskAllTurtles"
          INVOKEVIRTUAL org/nlogo/api/I18N$BundleKind.get (Ljava/lang/String;)Ljava/lang/String;
          INVOKESPECIAL org/nlogo/nvm/EngineException.<init> (Lorg/nlogo/nvm/Context;Lorg/nlogo/nvm/Instruction;Ljava/lang/String;)V
          ATHROW
         L4
          ALOAD 5
          ALOAD 0
          GETFIELD org/nlogo/prim/_asm_procedurego_ask_10.world : Lorg/nlogo/agent/World;
          INVOKEVIRTUAL org/nlogo/agent/World.patches ()Lorg/nlogo/agent/AgentSet;
          IF_ACMPNE L3
          NEW org/nlogo/nvm/EngineException
          DUP
          ALOAD 1
          ALOAD 0
          GETSTATIC org/nlogo/api/I18N$.MODULE$ : Lorg/nlogo/api/I18N$;
          INVOKEVIRTUAL org/nlogo/api/I18N$.errors ()Lorg/nlogo/api/I18N$BundleKind;
          LDC "org.nlogo.prim.$common.onlyObserverCanAskAllPatches"
          INVOKEVIRTUAL org/nlogo/api/I18N$BundleKind.get (Ljava/lang/String;)Ljava/lang/String;
          INVOKESPECIAL org/nlogo/nvm/EngineException.<init> (Lorg/nlogo/nvm/Context;Lorg/nlogo/nvm/Instruction;Ljava/lang/String;)V
          ATHROW
         L3
          ALOAD 5
          ASTORE 6
          GOTO L5
         L2
          ALOAD 4
          INSTANCEOF org/nlogo/agent/Agent
          IFEQ L6
          ALOAD 4
          CHECKCAST org/nlogo/agent/Agent
          ASTORE 7
          ALOAD 7
          INVOKEVIRTUAL org/nlogo/agent/Agent.id ()J
          LDC -1
          LCMP
          IFNE L7
          NEW org/nlogo/nvm/EngineException
          DUP
          ALOAD 1
          ALOAD 0
          GETSTATIC org/nlogo/api/I18N$.MODULE$ : Lorg/nlogo/api/I18N$;
          INVOKEVIRTUAL org/nlogo/api/I18N$.errors ()Lorg/nlogo/api/I18N$BundleKind;
          LDC "org.nlogo.$common.thatAgentIsDead"
          GETSTATIC scala/Predef$.MODULE$ : Lscala/Predef$;
          ICONST_1
          ANEWARRAY java/lang/Object
          DUP
          ICONST_0
          ALOAD 7
          INVOKEVIRTUAL org/nlogo/agent/Agent.classDisplayName ()Ljava/lang/String;
          AASTORE
          INVOKEVIRTUAL scala/Predef$.wrapRefArray ([Ljava/lang/Object;)Lscala/collection/mutable/WrappedArray;
          INVOKEVIRTUAL org/nlogo/api/I18N$BundleKind.getN (Ljava/lang/String;Lscala/collection/Seq;)Ljava/lang/String;
          INVOKESPECIAL org/nlogo/nvm/EngineException.<init> (Lorg/nlogo/nvm/Context;Lorg/nlogo/nvm/Instruction;Ljava/lang/String;)V
          ATHROW
         L7
          GETSTATIC org/nlogo/agent/AgentSet$.MODULE$ : Lorg/nlogo/agent/AgentSet$;
          ALOAD 7
          INVOKEVIRTUAL org/nlogo/agent/AgentSet$.fromAgent (Lorg/nlogo/agent/Agent;)Lorg/nlogo/agent/AgentSet;
          ASTORE 6
         L5
          ALOAD 6
          ASTORE 3
          ALOAD 1
          ALOAD 3
          BIPUSH 9
          INVOKEVIRTUAL org/nlogo/nvm/Context.runExclusiveJob (Lorg/nlogo/agent/AgentSet;I)V
          ALOAD 1
          BIPUSH 18
          PUTFIELD org/nlogo/nvm/Context.ip : I
          GOTO L8
         L6
          NEW org/nlogo/nvm/ArgumentTypeException
          DUP
          ALOAD 1
          ALOAD 0
          ICONST_0
          GETSTATIC org/nlogo/api/Syntax$.MODULE$ : Lorg/nlogo/api/Syntax$;
          INVOKEVIRTUAL org/nlogo/api/Syntax$.AgentsetType ()I
          GETSTATIC org/nlogo/api/Syntax$.MODULE$ : Lorg/nlogo/api/Syntax$;
          INVOKEVIRTUAL org/nlogo/api/Syntax$.AgentType ()I
          IOR
          ALOAD 2
          INVOKESPECIAL org/nlogo/nvm/ArgumentTypeException.<init> (Lorg/nlogo/nvm/Context;Lorg/nlogo/nvm/Instruction;IILjava/lang/Object;)V
          ATHROW
         L8
          RETURN
[9]_asm_procedurego_setpatchvariable_11 "set n n - 4" Object => void
      _minus double,double => double
        _patchvariable:N => Object
        _constdouble:4.0 => double
          TRYCATCHBLOCK L0 L1 L2 org/nlogo/api/AgentException
          TRYCATCHBLOCK L3 L4 L4 java/lang/ClassCastException
          TRYCATCHBLOCK L5 L6 L7 org/nlogo/api/AgentException
         L0
          ALOAD 1
          GETFIELD org/nlogo/nvm/Context.agent : Lorg/nlogo/agent/Agent;
          ICONST_5
          INVOKEVIRTUAL org/nlogo/agent/Agent.getPatchVariable (I)Ljava/lang/Object;
         L1
          GOTO L8
         L2
          ASTORE 2
          NEW org/nlogo/nvm/EngineException
          DUP
          ALOAD 1
          ALOAD 0
          ALOAD 2
          INVOKEVIRTUAL org/nlogo/api/AgentException.getMessage ()Ljava/lang/String;
          INVOKESPECIAL org/nlogo/nvm/EngineException.<init> (Lorg/nlogo/nvm/Context;Lorg/nlogo/nvm/Instruction;Ljava/lang/String;)V
          ATHROW
         L8
          ASTORE 2
         L3
          ALOAD 2
          CHECKCAST java/lang/Double
          INVOKEVIRTUAL java/lang/Double.doubleValue ()D
          GOTO L9
         L4
          POP
          NEW org/nlogo/nvm/ArgumentTypeException
          DUP
          ALOAD 1
          ALOAD 0
          BIPUSH 0
          LDC 1
          ALOAD 2
          INVOKESPECIAL org/nlogo/nvm/ArgumentTypeException.<init> (Lorg/nlogo/nvm/Context;Lorg/nlogo/nvm/Instruction;IILjava/lang/Object;)V
          ATHROW
         L9
          LDC 4.0
         L10
          DSTORE 4
          DSTORE 2
          DLOAD 2
          DLOAD 4
          DSUB
         L11
          DSTORE 2
          NEW java/lang/Double
          DUP
          DLOAD 2
          INVOKESPECIAL java/lang/Double.<init> (D)V
          ASTORE 2
         L5
          ALOAD 1
          GETFIELD org/nlogo/nvm/Context.agent : Lorg/nlogo/agent/Agent;
          ICONST_5
          ALOAD 2
          INVOKEVIRTUAL org/nlogo/agent/Agent.setPatchVariable (ILjava/lang/Object;)V
         L6
          ALOAD 1
          BIPUSH 10
          PUTFIELD org/nlogo/nvm/Context.ip : I
          GOTO L12
         L7
          ASTORE 3
          NEW org/nlogo/nvm/EngineException
          DUP
          ALOAD 1
          ALOAD 0
          ALOAD 3
          INVOKEVIRTUAL org/nlogo/api/AgentException.getMessage ()Ljava/lang/String;
          INVOKESPECIAL org/nlogo/nvm/EngineException.<init> (Lorg/nlogo/nvm/Context;Lorg/nlogo/nvm/Instruction;Ljava/lang/String;)V
          ATHROW
         L12
          RETURN
[10]_asm_procedurego_setobservervariable_12 "set total total - 4" Object => void
      _minus double,double => double
        _observervariable:TOTAL => Object
        _constdouble:4.0 => double
          TRYCATCHBLOCK L0 L1 L1 java/lang/ClassCastException
          TRYCATCHBLOCK L2 L3 L4 org/nlogo/api/AgentException
         L5
          ALOAD 0
          GETFIELD org/nlogo/prim/_asm_procedurego_setobservervariable_12.world : Lorg/nlogo/agent/World;
          INVOKEVIRTUAL org/nlogo/agent/World.observer ()Lorg/nlogo/agent/Observer;
          ICONST_1
          INVOKEVIRTUAL org/nlogo/agent/Observer.getVariable (I)Ljava/lang/Object;
         L6
          ASTORE 2
         L0
          ALOAD 2
          CHECKCAST java/lang/Double
          INVOKEVIRTUAL java/lang/Double.doubleValue ()D
          GOTO L7
         L1
          POP
          NEW org/nlogo/nvm/ArgumentTypeException
          DUP
          ALOAD 1
          ALOAD 0
          BIPUSH 0
          LDC 1
          ALOAD 2
          INVOKESPECIAL org/nlogo/nvm/ArgumentTypeException.<init> (Lorg/nlogo/nvm/Context;Lorg/nlogo/nvm/Instruction;IILjava/lang/Object;)V
          ATHROW
         L7
          LDC 4.0
         L8
          DSTORE 4
          DSTORE 2
          DLOAD 2
          DLOAD 4
          DSUB
         L9
          DSTORE 2
          NEW java/lang/Double
          DUP
          DLOAD 2
          INVOKESPECIAL java/lang/Double.<init> (D)V
          ASTORE 2
         L2
          ALOAD 0
          GETFIELD org/nlogo/prim/_asm_procedurego_setobservervariable_12.world : Lorg/nlogo/agent/World;
          INVOKEVIRTUAL org/nlogo/agent/World.observer ()Lorg/nlogo/agent/Observer;
          ICONST_1
          ALOAD 2
          INVOKEVIRTUAL org/nlogo/agent/Observer.setVariable (ILjava/lang/Object;)V
         L3
          ALOAD 1
          BIPUSH 11
          PUTFIELD org/nlogo/nvm/Context.ip : I
          GOTO L10
         L4
          ASTORE 3
          NEW org/nlogo/nvm/EngineException
          DUP
          ALOAD 1
          ALOAD 0
          ALOAD 3
          INVOKEVIRTUAL org/nlogo/api/AgentException.getMessage ()Ljava/lang/String;
          INVOKESPECIAL org/nlogo/nvm/EngineException.<init> (Lorg/nlogo/nvm/Context;Lorg/nlogo/nvm/Instruction;Ljava/lang/String;)V
          ATHROW
         L10
          RETURN
[11]_asm_procedurego_call_13 "colorize"
         L0
          NEW org/nlogo/nvm/Activation
          DUP
          ALOAD 0
          GETFIELD org/nlogo/prim/_asm_procedurego_call_13.kept1_procedure : Lorg/nlogo/nvm/Procedure;
          ALOAD 1
          GETFIELD org/nlogo/nvm/Context.activation : Lorg/nlogo/nvm/Activation;
          BIPUSH 12
          INVOKESPECIAL org/nlogo/nvm/Activation.<init> (Lorg/nlogo/nvm/Procedure;Lorg/nlogo/nvm/Activation;I)V
          ALOAD 1
          SWAP
          PUTFIELD org/nlogo/nvm/Context.activation : Lorg/nlogo/nvm/Activation;
          ALOAD 1
          ICONST_0
          PUTFIELD org/nlogo/nvm/Context.ip : I
         L1
          RETURN
[12]_asm_procedurego_ask_14 "ask neighbors4" AgentSet => void
      _neighbors4 => AgentSet
         L0
          ALOAD 1
          GETFIELD org/nlogo/nvm/Context.agent : Lorg/nlogo/agent/Agent;
          ASTORE 2
          ALOAD 2
          INSTANCEOF org/nlogo/agent/Turtle
          IFEQ L1
          ALOAD 2
          CHECKCAST org/nlogo/agent/Turtle
          ASTORE 3
          ALOAD 3
          INVOKEVIRTUAL org/nlogo/agent/Turtle.getPatchHere ()Lorg/nlogo/agent/Patch;
          ASTORE 4
          GOTO L2
         L1
          ALOAD 2
          INSTANCEOF org/nlogo/agent/Patch
          IFEQ L3
          ALOAD 2
          CHECKCAST org/nlogo/agent/Patch
          ASTORE 5
          ALOAD 5
          ASTORE 4
         L2
          ALOAD 4
          INVOKEVIRTUAL org/nlogo/agent/Patch.getNeighbors4 ()Lorg/nlogo/agent/AgentSet;
          GOTO L4
         L3
          NEW scala/MatchError
          DUP
          ALOAD 2
          INVOKESPECIAL scala/MatchError.<init> (Ljava/lang/Object;)V
          ATHROW
         L4
          ASTORE 2
          ALOAD 1
          GETFIELD org/nlogo/nvm/Context.agent : Lorg/nlogo/agent/Agent;
          INSTANCEOF org/nlogo/agent/Observer
          IFNE L5
          ALOAD 2
          ALOAD 0
          GETFIELD org/nlogo/prim/_asm_procedurego_ask_14.world : Lorg/nlogo/agent/World;
          INVOKEVIRTUAL org/nlogo/agent/World.turtles ()Lorg/nlogo/agent/AgentSet;
          IF_ACMPNE L6
          NEW org/nlogo/nvm/EngineException
          DUP
          ALOAD 1
          ALOAD 0
          GETSTATIC org/nlogo/api/I18N$.MODULE$ : Lorg/nlogo/api/I18N$;
          INVOKEVIRTUAL org/nlogo/api/I18N$.errors ()Lorg/nlogo/api/I18N$BundleKind;
          LDC "org.nlogo.prim.$common.onlyObserverCanAskAllTurtles"
          INVOKEVIRTUAL org/nlogo/api/I18N$BundleKind.get (Ljava/lang/String;)Ljava/lang/String;
          INVOKESPECIAL org/nlogo/nvm/EngineException.<init> (Lorg/nlogo/nvm/Context;Lorg/nlogo/nvm/Instruction;Ljava/lang/String;)V
          ATHROW
         L6
          ALOAD 2
          ALOAD 0
          GETFIELD org/nlogo/prim/_asm_procedurego_ask_14.world : Lorg/nlogo/agent/World;
          INVOKEVIRTUAL org/nlogo/agent/World.patches ()Lorg/nlogo/agent/AgentSet;
          IF_ACMPNE L5
          NEW org/nlogo/nvm/EngineException
          DUP
          ALOAD 1
          ALOAD 0
          GETSTATIC org/nlogo/api/I18N$.MODULE$ : Lorg/nlogo/api/I18N$;
          INVOKEVIRTUAL org/nlogo/api/I18N$.errors ()Lorg/nlogo/api/I18N$BundleKind;
          LDC "org.nlogo.prim.$common.onlyObserverCanAskAllPatches"
          INVOKEVIRTUAL org/nlogo/api/I18N$BundleKind.get (Ljava/lang/String;)Ljava/lang/String;
          INVOKESPECIAL org/nlogo/nvm/EngineException.<init> (Lorg/nlogo/nvm/Context;Lorg/nlogo/nvm/Instruction;Ljava/lang/String;)V
          ATHROW
         L5
          ALOAD 1
          ALOAD 2
          BIPUSH 13
          INVOKEVIRTUAL org/nlogo/nvm/Context.runExclusiveJob (Lorg/nlogo/agent/AgentSet;I)V
          ALOAD 1
          BIPUSH 17
          PUTFIELD org/nlogo/nvm/Context.ip : I
         L7
          RETURN
[13]_asm_procedurego_setpatchvariable_15 "set n n + 1" Object => void
      _plus double,double => double
        _patchvariable:N => Object
        _constdouble:1.0 => double
          TRYCATCHBLOCK L0 L1 L2 org/nlogo/api/AgentException
          TRYCATCHBLOCK L3 L4 L4 java/lang/ClassCastException
          TRYCATCHBLOCK L5 L6 L7 org/nlogo/api/AgentException
         L0
          ALOAD 1
          GETFIELD org/nlogo/nvm/Context.agent : Lorg/nlogo/agent/Agent;
          ICONST_5
          INVOKEVIRTUAL org/nlogo/agent/Agent.getPatchVariable (I)Ljava/lang/Object;
         L1
          GOTO L8
         L2
          ASTORE 2
          NEW org/nlogo/nvm/EngineException
          DUP
          ALOAD 1
          ALOAD 0
          ALOAD 2
          INVOKEVIRTUAL org/nlogo/api/AgentException.getMessage ()Ljava/lang/String;
          INVOKESPECIAL org/nlogo/nvm/EngineException.<init> (Lorg/nlogo/nvm/Context;Lorg/nlogo/nvm/Instruction;Ljava/lang/String;)V
          ATHROW
         L8
          ASTORE 2
         L3
          ALOAD 2
          CHECKCAST java/lang/Double
          INVOKEVIRTUAL java/lang/Double.doubleValue ()D
          GOTO L9
         L4
          POP
          NEW org/nlogo/nvm/ArgumentTypeException
          DUP
          ALOAD 1
          ALOAD 0
          BIPUSH 0
          LDC 1
          ALOAD 2
          INVOKESPECIAL org/nlogo/nvm/ArgumentTypeException.<init> (Lorg/nlogo/nvm/Context;Lorg/nlogo/nvm/Instruction;IILjava/lang/Object;)V
          ATHROW
         L9
          DCONST_1
         L10
          DSTORE 4
          DSTORE 2
          DLOAD 2
          DLOAD 4
          DADD
         L11
          DSTORE 2
          NEW java/lang/Double
          DUP
          DLOAD 2
          INVOKESPECIAL java/lang/Double.<init> (D)V
          ASTORE 2
         L5
          ALOAD 1
          GETFIELD org/nlogo/nvm/Context.agent : Lorg/nlogo/agent/Agent;
          ICONST_5
          ALOAD 2
          INVOKEVIRTUAL org/nlogo/agent/Agent.setPatchVariable (ILjava/lang/Object;)V
         L6
          ALOAD 1
          BIPUSH 14
          PUTFIELD org/nlogo/nvm/Context.ip : I
          GOTO L12
         L7
          ASTORE 3
          NEW org/nlogo/nvm/EngineException
          DUP
          ALOAD 1
          ALOAD 0
          ALOAD 3
          INVOKEVIRTUAL org/nlogo/api/AgentException.getMessage ()Ljava/lang/String;
          INVOKESPECIAL org/nlogo/nvm/EngineException.<init> (Lorg/nlogo/nvm/Context;Lorg/nlogo/nvm/Instruction;Ljava/lang/String;)V
          ATHROW
         L12
          RETURN
[14]_asm_procedurego_setobservervariable_16 "set total total + 1" Object => void
      _plus double,double => double
        _observervariable:TOTAL => Object
        _constdouble:1.0 => double
          TRYCATCHBLOCK L0 L1 L1 java/lang/ClassCastException
          TRYCATCHBLOCK L2 L3 L4 org/nlogo/api/AgentException
         L5
          ALOAD 0
          GETFIELD org/nlogo/prim/_asm_procedurego_setobservervariable_16.world : Lorg/nlogo/agent/World;
          INVOKEVIRTUAL org/nlogo/agent/World.observer ()Lorg/nlogo/agent/Observer;
          ICONST_1
          INVOKEVIRTUAL org/nlogo/agent/Observer.getVariable (I)Ljava/lang/Object;
         L6
          ASTORE 2
         L0
          ALOAD 2
          CHECKCAST java/lang/Double
          INVOKEVIRTUAL java/lang/Double.doubleValue ()D
          GOTO L7
         L1
          POP
          NEW org/nlogo/nvm/ArgumentTypeException
          DUP
          ALOAD 1
          ALOAD 0
          BIPUSH 0
          LDC 1
          ALOAD 2
          INVOKESPECIAL org/nlogo/nvm/ArgumentTypeException.<init> (Lorg/nlogo/nvm/Context;Lorg/nlogo/nvm/Instruction;IILjava/lang/Object;)V
          ATHROW
         L7
          DCONST_1
         L8
          DSTORE 4
          DSTORE 2
          DLOAD 2
          DLOAD 4
          DADD
         L9
          DSTORE 2
          NEW java/lang/Double
          DUP
          DLOAD 2
          INVOKESPECIAL java/lang/Double.<init> (D)V
          ASTORE 2
         L2
          ALOAD 0
          GETFIELD org/nlogo/prim/_asm_procedurego_setobservervariable_16.world : Lorg/nlogo/agent/World;
          INVOKEVIRTUAL org/nlogo/agent/World.observer ()Lorg/nlogo/agent/Observer;
          ICONST_1
          ALOAD 2
          INVOKEVIRTUAL org/nlogo/agent/Observer.setVariable (ILjava/lang/Object;)V
         L3
          ALOAD 1
          BIPUSH 15
          PUTFIELD org/nlogo/nvm/Context.ip : I
          GOTO L10
         L4
          ASTORE 3
          NEW org/nlogo/nvm/EngineException
          DUP
          ALOAD 1
          ALOAD 0
          ALOAD 3
          INVOKEVIRTUAL org/nlogo/api/AgentException.getMessage ()Ljava/lang/String;
          INVOKESPECIAL org/nlogo/nvm/EngineException.<init> (Lorg/nlogo/nvm/Context;Lorg/nlogo/nvm/Instruction;Ljava/lang/String;)V
          ATHROW
         L10
          RETURN
[15]_asm_procedurego_call_17 "colorize"
         L0
          NEW org/nlogo/nvm/Activation
          DUP
          ALOAD 0
          GETFIELD org/nlogo/prim/_asm_procedurego_call_17.kept1_procedure : Lorg/nlogo/nvm/Procedure;
          ALOAD 1
          GETFIELD org/nlogo/nvm/Context.activation : Lorg/nlogo/nvm/Activation;
          BIPUSH 16
          INVOKESPECIAL org/nlogo/nvm/Activation.<init> (Lorg/nlogo/nvm/Procedure;Lorg/nlogo/nvm/Activation;I)V
          ALOAD 1
          SWAP
          PUTFIELD org/nlogo/nvm/Context.activation : Lorg/nlogo/nvm/Activation;
          ALOAD 1
          ICONST_0
          PUTFIELD org/nlogo/nvm/Context.ip : I
         L1
          RETURN
[16]_asm_procedurego_done_18 "" => void
         L0
          ALOAD 1
          ICONST_1
          PUTFIELD org/nlogo/nvm/Context.finished : Z
         L1
          RETURN
[17]_asm_procedurego_done_19 "" => void
         L0
          ALOAD 1
          ICONST_1
          PUTFIELD org/nlogo/nvm/Context.finished : Z
         L1
          RETURN
[18]_asm_procedurego_setprocedurevariable_20 "set active-patches patch-set [neighbors4] of overloaded-patches" Object => void
      _patchset
        _of
          _asm_procedurego_neighbors4_21 "neighbors4" => AgentSet
               L0
                ALOAD 1
                GETFIELD org/nlogo/nvm/Context.agent : Lorg/nlogo/agent/Agent;
                ASTORE 2
                ALOAD 2
                INSTANCEOF org/nlogo/agent/Turtle
                IFEQ L1
                ALOAD 2
                CHECKCAST org/nlogo/agent/Turtle
                ASTORE 3
                ALOAD 3
                INVOKEVIRTUAL org/nlogo/agent/Turtle.getPatchHere ()Lorg/nlogo/agent/Patch;
                ASTORE 4
                GOTO L2
               L1
                ALOAD 2
                INSTANCEOF org/nlogo/agent/Patch
                IFEQ L3
                ALOAD 2
                CHECKCAST org/nlogo/agent/Patch
                ASTORE 5
                ALOAD 5
                ASTORE 4
               L2
                ALOAD 4
                INVOKEVIRTUAL org/nlogo/agent/Patch.getNeighbors4 ()Lorg/nlogo/agent/AgentSet;
                GOTO L4
               L3
                NEW scala/MatchError
                DUP
                ALOAD 2
                INVOKESPECIAL scala/MatchError.<init> (Ljava/lang/Object;)V
                ATHROW
               L4
                ARETURN
          _asm_procedurego_procedurevariable_22 "overloaded-patches" => Object
               L0
                ALOAD 1
                GETFIELD org/nlogo/nvm/Context.activation : Lorg/nlogo/nvm/Activation;
                INVOKEVIRTUAL org/nlogo/nvm/Activation.args ()[Ljava/lang/Object;
                ICONST_1
                AALOAD
               L1
                ARETURN
          ALOAD 0
          GETFIELD org/nlogo/prim/_asm_procedurego_setprocedurevariable_20.keptinstr2 : Lorg/nlogo/prim/etc/_patchset;
          ALOAD 1
          INVOKEVIRTUAL org/nlogo/prim/etc/_patchset.report (Lorg/nlogo/nvm/Context;)Ljava/lang/Object;
         L0
          ASTORE 2
          ALOAD 1
          GETFIELD org/nlogo/nvm/Context.activation : Lorg/nlogo/nvm/Activation;
          INVOKEVIRTUAL org/nlogo/nvm/Activation.args ()[Ljava/lang/Object;
          ICONST_0
          ALOAD 2
          AASTORE
          ALOAD 1
          BIPUSH 19
          PUTFIELD org/nlogo/nvm/Context.ip : I
         L1
          RETURN
[19]_asm_procedurego_while_23 "while [any? active-patches" boolean => void
      _any AgentSet => boolean
        _procedurevariable:ACTIVE-PATCHES => Object
          TRYCATCHBLOCK L0 L1 L1 java/lang/ClassCastException
         L2
          ALOAD 1
          GETFIELD org/nlogo/nvm/Context.activation : Lorg/nlogo/nvm/Activation;
          INVOKEVIRTUAL org/nlogo/nvm/Activation.args ()[Ljava/lang/Object;
          ICONST_0
          AALOAD
         L3
          ASTORE 2
         L0
          ALOAD 2
          CHECKCAST org/nlogo/agent/AgentSet
          GOTO L4
         L1
          POP
          NEW org/nlogo/nvm/ArgumentTypeException
          DUP
          ALOAD 1
          ALOAD 0
          BIPUSH 0
          LDC 112
          ALOAD 2
          INVOKESPECIAL org/nlogo/nvm/ArgumentTypeException.<init> (Lorg/nlogo/nvm/Context;Lorg/nlogo/nvm/Instruction;IILjava/lang/Object;)V
          ATHROW
         L4
          ASTORE 2
          ALOAD 2
          INVOKEVIRTUAL org/nlogo/agent/AgentSet.isEmpty ()Z
          IFEQ L5
          ICONST_0
          GOTO L6
         L5
          ICONST_1
         L6
          ISTORE 2
          ALOAD 1
          ILOAD 2
          IFEQ L7
          BIPUSH 7
          GOTO L8
         L7
          BIPUSH 20
         L8
          PUTFIELD org/nlogo/nvm/Context.ip : I
         L9
          RETURN
[20]_tick
[21]_asm_procedurego_return_24 "" => void
         L0
          ALOAD 1
          INVOKEVIRTUAL org/nlogo/nvm/Context.returnFromProcedure ()V
          ALOAD 1
          ICONST_0
          PUTFIELD org/nlogo/nvm/Context.stopping : Z
         L1
          RETURN

procedure COLORIZE:[]{-TP-}:
[0]_asm_procedurecolorize_ifelse_0 "ifelse n <= 3" boolean => void
      _lessorequal Object,double => boolean
        _patchvariable:N => Object
        _constdouble:3.0 => double
          TRYCATCHBLOCK L0 L1 L2 org/nlogo/api/AgentException
         L0
          ALOAD 1
          GETFIELD org/nlogo/nvm/Context.agent : Lorg/nlogo/agent/Agent;
          ICONST_5
          INVOKEVIRTUAL org/nlogo/agent/Agent.getPatchVariable (I)Ljava/lang/Object;
         L1
          GOTO L3
         L2
          ASTORE 2
          NEW org/nlogo/nvm/EngineException
          DUP
          ALOAD 1
          ALOAD 0
          ALOAD 2
          INVOKEVIRTUAL org/nlogo/api/AgentException.getMessage ()Ljava/lang/String;
          INVOKESPECIAL org/nlogo/nvm/EngineException.<init> (Lorg/nlogo/nvm/Context;Lorg/nlogo/nvm/Instruction;Ljava/lang/String;)V
          ATHROW
         L3
          LDC 3.0
         L4
          DSTORE 3
          ASTORE 2
          ALOAD 2
          INSTANCEOF java/lang/Double
          IFEQ L5
          ALOAD 2
          CHECKCAST java/lang/Double
          INVOKEVIRTUAL java/lang/Double.doubleValue ()D
          DLOAD 3
          DCMPG
          IFGT L6
          ICONST_1
          GOTO L7
         L6
          ICONST_0
         L7
          GOTO L8
         L5
          NEW org/nlogo/nvm/EngineException
          DUP
          ALOAD 1
          ALOAD 0
          INVOKESTATIC org/nlogo/api/I18N.errorsJ ()Lorg/nlogo/api/I18NJava;
          LDC "org.nlogo.prim._lessorequal.cannotCompareParameters"
          ICONST_2
          ANEWARRAY java/lang/Object
          DUP
          ICONST_0
          ALOAD 2
          INVOKESTATIC org/nlogo/api/TypeNames.aName (Ljava/lang/Object;)Ljava/lang/String;
          AASTORE
          DUP
          ICONST_1
          DLOAD 3
          INVOKESTATIC java/lang/Double.valueOf (D)Ljava/lang/Double;
          INVOKESTATIC org/nlogo/api/TypeNames.aName (Ljava/lang/Object;)Ljava/lang/String;
          AASTORE
          INVOKEINTERFACE org/nlogo/api/I18NJava.getN (Ljava/lang/String;[Ljava/lang/Object;)Ljava/lang/String;
          INVOKESPECIAL org/nlogo/nvm/EngineException.<init> (Lorg/nlogo/nvm/Context;Lorg/nlogo/nvm/Instruction;Ljava/lang/String;)V
          ATHROW
         L8
          ISTORE 2
          ALOAD 1
          ILOAD 2
          IFEQ L9
          ICONST_1
          GOTO L10
         L9
          ICONST_3
         L10
          PUTFIELD org/nlogo/nvm/Context.ip : I
         L11
          RETURN
[1]_asm_procedurecolorize_setpatchvariable_1 "set pcolor item n" Object => void
      _item
        _asm_procedurecolorize_patchvariable_2 "n" => Object
              TRYCATCHBLOCK L0 L1 L2 org/nlogo/api/AgentException
             L0
              ALOAD 1
              GETFIELD org/nlogo/nvm/Context.agent : Lorg/nlogo/agent/Agent;
              ICONST_5
              INVOKEVIRTUAL org/nlogo/agent/Agent.getPatchVariable (I)Ljava/lang/Object;
             L1
              GOTO L3
             L2
              ASTORE 2
              NEW org/nlogo/nvm/EngineException
              DUP
              ALOAD 1
              ALOAD 0
              ALOAD 2
              INVOKEVIRTUAL org/nlogo/api/AgentException.getMessage ()Ljava/lang/String;
              INVOKESPECIAL org/nlogo/nvm/EngineException.<init> (Lorg/nlogo/nvm/Context;Lorg/nlogo/nvm/Instruction;Ljava/lang/String;)V
              ATHROW
             L3
              ARETURN
        _asm_procedurecolorize_constlist_3 "" => LogoList
             L0
              ALOAD 0
              GETFIELD org/nlogo/prim/_asm_procedurecolorize_constlist_3.kept1_value : Lorg/nlogo/api/LogoList;
             L1
              ARETURN
          TRYCATCHBLOCK L0 L1 L2 org/nlogo/api/AgentException
          ALOAD 0
          GETFIELD org/nlogo/prim/_asm_procedurecolorize_setpatchvariable_1.keptinstr2 : Lorg/nlogo/prim/etc/_item;
          ALOAD 1
          INVOKEVIRTUAL org/nlogo/prim/etc/_item.report (Lorg/nlogo/nvm/Context;)Ljava/lang/Object;
         L3
          ASTORE 2
         L0
          ALOAD 1
          GETFIELD org/nlogo/nvm/Context.agent : Lorg/nlogo/agent/Agent;
          ICONST_2
          ALOAD 2
          INVOKEVIRTUAL org/nlogo/agent/Agent.setPatchVariable (ILjava/lang/Object;)V
         L1
          ALOAD 1
          ICONST_2
          PUTFIELD org/nlogo/nvm/Context.ip : I
          GOTO L4
         L2
          ASTORE 3
          NEW org/nlogo/nvm/EngineException
          DUP
          ALOAD 1
          ALOAD 0
          ALOAD 3
          INVOKEVIRTUAL org/nlogo/api/AgentException.getMessage ()Ljava/lang/String;
          INVOKESPECIAL org/nlogo/nvm/EngineException.<init> (Lorg/nlogo/nvm/Context;Lorg/nlogo/nvm/Instruction;Ljava/lang/String;)V
          ATHROW
         L4
          RETURN
[2]_asm_procedurecolorize_goto_4 "" => void
         L0
          ALOAD 1
          ICONST_4
          PUTFIELD org/nlogo/nvm/Context.ip : I
         L1
          RETURN
[3]_asm_procedurecolorize_setpatchvariable_5 "set pcolor red" Object => void
      _constdouble:15.0 => Double
          TRYCATCHBLOCK L0 L1 L2 org/nlogo/api/AgentException
         L3
          ALOAD 0
          GETFIELD org/nlogo/prim/_asm_procedurecolorize_setpatchvariable_5.kept2_value : Ljava/lang/Double;
         L4
          ASTORE 2
         L0
          ALOAD 1
          GETFIELD org/nlogo/nvm/Context.agent : Lorg/nlogo/agent/Agent;
          ICONST_2
          ALOAD 2
          INVOKEVIRTUAL org/nlogo/agent/Agent.setPatchVariable (ILjava/lang/Object;)V
         L1
          ALOAD 1
          ICONST_4
          PUTFIELD org/nlogo/nvm/Context.ip : I
          GOTO L5
         L2
          ASTORE 3
          NEW org/nlogo/nvm/EngineException
          DUP
          ALOAD 1
          ALOAD 0
          ALOAD 3
          INVOKEVIRTUAL org/nlogo/api/AgentException.getMessage ()Ljava/lang/String;
          INVOKESPECIAL org/nlogo/nvm/EngineException.<init> (Lorg/nlogo/nvm/Context;Lorg/nlogo/nvm/Instruction;Ljava/lang/String;)V
          ATHROW
         L5
          RETURN
[4]_asm_procedurecolorize_return_6 "" => void
         L0
          ALOAD 1
          INVOKEVIRTUAL org/nlogo/nvm/Context.returnFromProcedure ()V
          ALOAD 1
          ICONST_0
          PUTFIELD org/nlogo/nvm/Context.stopping : Z
         L1
          RETURN

