globals [PLOT? TOTAL RESULT]
interfaceGlobals [plot?]
turtles-own [WHO COLOR HEADING XCOR YCOR SHAPE LABEL LABEL-COLOR BREED HIDDEN? SIZE PEN-SIZE PEN-MODE]
patches-own [PXCOR PYCOR PCOLOR PLABEL PLABEL-COLOR N]
links-own [END1 END2 COLOR LABEL LABEL-COLOR HIDDEN? BREED THICKNESS SHAPE TIE-MODE]
breeds 
link-breeds 

procedure BENCHMARK:[_repeatlocal:0]{O---}:
[0]_asm_procedurebenchmark_randomseed_0 "random-seed 0" double => void
      _constdouble:0.0 "0" => double
          // parameter final  context
          // parameter final  arg0
         L0
          DCONST_0
         L1
          DSTORE 2
          DLOAD 2
          D2L
          LSTORE 4
          LLOAD 4
          LDC -2147483648
          LCMP
          IFLT L2
          LLOAD 4
          LDC 2147483647
          LCMP
          IFLE L3
         L2
         FRAME APPEND [D J]
          NEW org/nlogo/nvm/RuntimePrimitiveException
          DUP
          ALOAD 1
          ALOAD 0
          NEW java/lang/StringBuilder
          DUP
          INVOKESPECIAL java/lang/StringBuilder.<init> ()V
          GETSTATIC org/nlogo/api/Dump$.MODULE$ : Lorg/nlogo/api/Dump$;
          DLOAD 2
          INVOKEVIRTUAL org/nlogo/api/Dump$.number (D)Ljava/lang/String;
          INVOKEVIRTUAL java/lang/StringBuilder.append (Ljava/lang/String;)Ljava/lang/StringBuilder;
          LDC " is not in the allowable range for random seeds (-2147483648 to 2147483647)"
          INVOKEVIRTUAL java/lang/StringBuilder.append (Ljava/lang/String;)Ljava/lang/StringBuilder;
          INVOKEVIRTUAL java/lang/StringBuilder.toString ()Ljava/lang/String;
          INVOKESPECIAL org/nlogo/nvm/RuntimePrimitiveException.<init> (Lorg/nlogo/api/Context;Lorg/nlogo/nvm/Instruction;Ljava/lang/String;)V
          ATHROW
         L3
         FRAME SAME
          ALOAD 1
          GETFIELD org/nlogo/nvm/Context.job : Lorg/nlogo/nvm/Job;
          GETFIELD org/nlogo/nvm/Job.random : Lorg/nlogo/api/MersenneTwisterFast;
          LLOAD 4
          L2I
          I2L
          INVOKEVIRTUAL org/nlogo/api/MersenneTwisterFast.setSeed (J)V
          ALOAD 1
          ICONST_1
          PUTFIELD org/nlogo/nvm/Context.ip : I
         L4
          RETURN
[1]_resettimer "reset-timer"
[2]_asm_procedurebenchmark_call_1 "setup"
         L0
          NEW org/nlogo/nvm/Activation
          DUP
          ALOAD 0
          GETFIELD org/nlogo/prim/_asm_procedurebenchmark_call_1.kept1_procedure : Lorg/nlogo/nvm/Procedure;
          ALOAD 1
          GETFIELD org/nlogo/nvm/Context.activation : Lorg/nlogo/nvm/Activation;
          ICONST_3
          INVOKESPECIAL org/nlogo/nvm/Activation.<init> (Lorg/nlogo/nvm/Procedure;Lorg/nlogo/nvm/Activation;I)V
          ALOAD 1
          SWAP
          PUTFIELD org/nlogo/nvm/Context.activation : Lorg/nlogo/nvm/Activation;
          ALOAD 1
          ICONST_0
          PUTFIELD org/nlogo/nvm/Context.ip : I
         L1
          RETURN
[3]_asm_procedurebenchmark_repeatlocal_2 "repeat 5000 [ go ]" double => void
      _constdouble:5000.0 "5000" => double
          // parameter final  context
          // parameter final  arg0
         L0
          LDC 5000.0
         L1
          DSTORE 2
          ALOAD 1
          GETFIELD org/nlogo/nvm/Context.activation : Lorg/nlogo/nvm/Activation;
          GETFIELD org/nlogo/nvm/Activation.args : [Ljava/lang/Object;
          ICONST_0
          NEW org/nlogo/nvm/MutableLong
          DUP
          ALOAD 0
          DLOAD 2
          INVOKEVIRTUAL org/nlogo/prim/_asm_procedurebenchmark_repeatlocal_2.validLong (D)J
          INVOKESPECIAL org/nlogo/nvm/MutableLong.<init> (J)V
          AASTORE
          ALOAD 1
          ICONST_5
          PUTFIELD org/nlogo/nvm/Context.ip : I
         L2
          RETURN
[4]_asm_procedurebenchmark_call_3 "go"
         L0
          NEW org/nlogo/nvm/Activation
          DUP
          ALOAD 0
          GETFIELD org/nlogo/prim/_asm_procedurebenchmark_call_3.kept1_procedure : Lorg/nlogo/nvm/Procedure;
          ALOAD 1
          GETFIELD org/nlogo/nvm/Context.activation : Lorg/nlogo/nvm/Activation;
          ICONST_5
          INVOKESPECIAL org/nlogo/nvm/Activation.<init> (Lorg/nlogo/nvm/Procedure;Lorg/nlogo/nvm/Activation;I)V
          ALOAD 1
          SWAP
          PUTFIELD org/nlogo/nvm/Context.activation : Lorg/nlogo/nvm/Activation;
          ALOAD 1
          ICONST_0
          PUTFIELD org/nlogo/nvm/Context.ip : I
         L1
          RETURN
[5]_asm_procedurebenchmark_repeatlocalinternal_4 => void
          // parameter final  context
         L0
          ALOAD 1
          GETFIELD org/nlogo/nvm/Context.activation : Lorg/nlogo/nvm/Activation;
          GETFIELD org/nlogo/nvm/Activation.args : [Ljava/lang/Object;
          ICONST_0
          AALOAD
          CHECKCAST org/nlogo/nvm/MutableLong
          ASTORE 2
          ALOAD 2
          INVOKEVIRTUAL org/nlogo/nvm/MutableLong.value ()J
          LCONST_0
          LCMP
          IFGT L1
          ALOAD 1
          BIPUSH 6
          PUTFIELD org/nlogo/nvm/Context.ip : I
          GOTO L2
         L1
         FRAME APPEND [org/nlogo/nvm/MutableLong]
          ALOAD 2
          ALOAD 2
          INVOKEVIRTUAL org/nlogo/nvm/MutableLong.value ()J
          LCONST_1
          LSUB
          INVOKEVIRTUAL org/nlogo/nvm/MutableLong.value_$eq (J)V
          ALOAD 1
          ICONST_4
          PUTFIELD org/nlogo/nvm/Context.ip : I
         L2
         FRAME SAME
          RETURN
[6]_asm_procedurebenchmark_setobservervariable_5 "set result timer" Object => void
      _timer "timer" => double
          // parameter final  context
          TRYCATCHBLOCK L0 L1 L2 org/nlogo/api/AgentException
         L3
          ALOAD 0
          GETFIELD org/nlogo/prim/_asm_procedurebenchmark_setobservervariable_5.world : Lorg/nlogo/agent/World;
          INVOKEVIRTUAL org/nlogo/agent/World.timer ()Lorg/nlogo/api/Timer;
          INVOKEVIRTUAL org/nlogo/api/Timer.read ()D
         L4
          DSTORE 2
          NEW java/lang/Double
          DUP
          DLOAD 2
          INVOKESPECIAL java/lang/Double.<init> (D)V
          ASTORE 2
         L0
          ALOAD 1
          GETFIELD org/nlogo/nvm/Context.agent : Lorg/nlogo/agent/Agent;
          ICONST_2
          ALOAD 2
          INVOKEVIRTUAL org/nlogo/agent/Agent.setObserverVariable (ILjava/lang/Object;)V
         L1
          GOTO L5
         L2
         FRAME FULL [org/nlogo/prim/_asm_procedurebenchmark_setobservervariable_5 org/nlogo/nvm/Context java/lang/Double] [org/nlogo/api/AgentException]
          ASTORE 3
          NEW org/nlogo/nvm/RuntimePrimitiveException
          DUP
          ALOAD 1
          ALOAD 0
          ALOAD 3
          INVOKEVIRTUAL org/nlogo/api/AgentException.getMessage ()Ljava/lang/String;
          INVOKESPECIAL org/nlogo/nvm/RuntimePrimitiveException.<init> (Lorg/nlogo/api/Context;Lorg/nlogo/nvm/Instruction;Ljava/lang/String;)V
          ATHROW
         L5
         FRAME SAME
          ALOAD 1
          BIPUSH 7
          PUTFIELD org/nlogo/nvm/Context.ip : I
         L6
          RETURN
[7]_asm_procedurebenchmark_return_6 => void
         L0
          ALOAD 1
          INVOKEVIRTUAL org/nlogo/nvm/Context.returnFromProcedure ()V
          ALOAD 1
          ICONST_0
          PUTFIELD org/nlogo/nvm/Context.stopping : Z
         L1
          RETURN

procedure COLORIZE:[]{-TP-}:
[0]_asm_procedurecolorize_ifelse_0 "ifelse n <= 3 [ set pcolor item n [83 54 45 25] ] [ set pcolor red ]" boolean => void
      _lessorequal "n <= 3" Object,double => boolean
        _patchvariable:N "n" => Object
        _constdouble:3.0 "3" => double
          // parameter final  context
          TRYCATCHBLOCK L0 L1 L2 org/nlogo/api/AgentException
         L0
          ALOAD 1
          GETFIELD org/nlogo/nvm/Context.agent : Lorg/nlogo/agent/Agent;
          ICONST_5
          INVOKEVIRTUAL org/nlogo/agent/Agent.getPatchVariable (I)Ljava/lang/Object;
         L1
          GOTO L3
         L2
         FRAME SAME1 org/nlogo/api/AgentException
          ASTORE 2
          NEW org/nlogo/nvm/RuntimePrimitiveException
          DUP
          ALOAD 1
          ALOAD 0
          ALOAD 2
          INVOKEVIRTUAL org/nlogo/api/AgentException.getMessage ()Ljava/lang/String;
          INVOKESPECIAL org/nlogo/nvm/RuntimePrimitiveException.<init> (Lorg/nlogo/api/Context;Lorg/nlogo/nvm/Instruction;Ljava/lang/String;)V
          ATHROW
         L3
         FRAME SAME1 java/lang/Object
          LDC 3.0
         L4
          DSTORE 3
          ASTORE 2
          ALOAD 2
          INSTANCEOF java/lang/Double
          IFEQ L5
          ALOAD 2
          CHECKCAST java/lang/Double
          INVOKEVIRTUAL java/lang/Double.doubleValue ()D
          DLOAD 3
          DCMPG
          IFGT L6
          ICONST_1
          GOTO L7
         L6
         FRAME APPEND [java/lang/Object D]
          ICONST_0
         L7
         FRAME SAME1 I
          GOTO L8
         L5
         FRAME SAME
          NEW org/nlogo/nvm/RuntimePrimitiveException
          DUP
          ALOAD 1
          ALOAD 0
          INVOKESTATIC org/nlogo/core/I18N.errorsJ ()Lorg/nlogo/core/I18NJava;
          LDC "org.nlogo.prim._lessorequal.cannotCompareParameters"
          ICONST_2
          ANEWARRAY java/lang/Object
          DUP
          ICONST_0
          ALOAD 2
          INVOKESTATIC org/nlogo/api/TypeNames.aName (Ljava/lang/Object;)Ljava/lang/String;
          AASTORE
          DUP
          ICONST_1
          DLOAD 3
          INVOKESTATIC java/lang/Double.valueOf (D)Ljava/lang/Double;
          INVOKESTATIC org/nlogo/api/TypeNames.aName (Ljava/lang/Object;)Ljava/lang/String;
          AASTORE
          INVOKEINTERFACE org/nlogo/core/I18NJava.getN (Ljava/lang/String;[Ljava/lang/Object;)Ljava/lang/String;
          INVOKESPECIAL org/nlogo/nvm/RuntimePrimitiveException.<init> (Lorg/nlogo/api/Context;Lorg/nlogo/nvm/Instruction;Ljava/lang/String;)V
          ATHROW
         L8
         FRAME SAME1 I
          ISTORE 2
          ALOAD 1
          ILOAD 2
          IFEQ L9
          ICONST_1
          GOTO L10
         L9
         FRAME FULL [org/nlogo/prim/_asm_procedurecolorize_ifelse_0 org/nlogo/nvm/Context I D] [org/nlogo/nvm/Context]
          ICONST_3
         L10
         FRAME FULL [org/nlogo/prim/_asm_procedurecolorize_ifelse_0 org/nlogo/nvm/Context I D] [org/nlogo/nvm/Context I]
          PUTFIELD org/nlogo/nvm/Context.ip : I
         L11
          RETURN
[1]_asm_procedurecolorize_setpatchvariable_1 "set pcolor item n [83 54 45 25]" Object => void
      _item "item n [83 54 45 25]"
        _asm_procedurecolorize_patchvariable_2 "n" => Object
              // parameter final  context
              TRYCATCHBLOCK L0 L1 L2 org/nlogo/api/AgentException
             L0
              ALOAD 1
              GETFIELD org/nlogo/nvm/Context.agent : Lorg/nlogo/agent/Agent;
              ICONST_5
              INVOKEVIRTUAL org/nlogo/agent/Agent.getPatchVariable (I)Ljava/lang/Object;
             L1
              GOTO L3
             L2
             FRAME SAME1 org/nlogo/api/AgentException
              ASTORE 2
              NEW org/nlogo/nvm/RuntimePrimitiveException
              DUP
              ALOAD 1
              ALOAD 0
              ALOAD 2
              INVOKEVIRTUAL org/nlogo/api/AgentException.getMessage ()Ljava/lang/String;
              INVOKESPECIAL org/nlogo/nvm/RuntimePrimitiveException.<init> (Lorg/nlogo/api/Context;Lorg/nlogo/nvm/Instruction;Ljava/lang/String;)V
              ATHROW
             L3
             FRAME SAME1 java/lang/Object
              ARETURN
        _asm_procedurecolorize_constlist_3 "[83 54 45 25]" => LogoList
             L0
              ALOAD 0
              GETFIELD org/nlogo/prim/_asm_procedurecolorize_constlist_3.kept1_value : Lorg/nlogo/core/LogoList;
             L1
              ARETURN
          TRYCATCHBLOCK L0 L1 L2 org/nlogo/api/AgentException
          ALOAD 0
          GETFIELD org/nlogo/prim/_asm_procedurecolorize_setpatchvariable_1.keptinstr2 : Lorg/nlogo/prim/etc/_item;
          ALOAD 1
          INVOKEVIRTUAL org/nlogo/prim/etc/_item.report (Lorg/nlogo/nvm/Context;)Ljava/lang/Object;
         L3
          ASTORE 2
         L0
          ALOAD 1
          GETFIELD org/nlogo/nvm/Context.agent : Lorg/nlogo/agent/Agent;
          ICONST_2
          ALOAD 2
          INVOKEVIRTUAL org/nlogo/agent/Agent.setPatchVariable (ILjava/lang/Object;)V
         L1
          GOTO L4
         L2
         FRAME FULL [org/nlogo/prim/_asm_procedurecolorize_setpatchvariable_1 org/nlogo/nvm/Context java/lang/Object] [org/nlogo/api/AgentException]
          ASTORE 3
          NEW org/nlogo/nvm/RuntimePrimitiveException
          DUP
          ALOAD 1
          ALOAD 0
          ALOAD 3
          INVOKEVIRTUAL org/nlogo/api/AgentException.getMessage ()Ljava/lang/String;
          INVOKESPECIAL org/nlogo/nvm/RuntimePrimitiveException.<init> (Lorg/nlogo/api/Context;Lorg/nlogo/nvm/Instruction;Ljava/lang/String;)V
          ATHROW
         L4
         FRAME SAME
          ALOAD 1
          ICONST_2
          PUTFIELD org/nlogo/nvm/Context.ip : I
         L5
          RETURN
[2]_asm_procedurecolorize_goto_4 => void
         L0
          ALOAD 1
          ICONST_4
          PUTFIELD org/nlogo/nvm/Context.ip : I
         L1
          RETURN
[3]_asm_procedurecolorize_setpatchvariable_5 "set pcolor red" Object => void
      _constdouble:15.0 "red" => Double
          TRYCATCHBLOCK L0 L1 L2 org/nlogo/api/AgentException
         L3
          ALOAD 0
          GETFIELD org/nlogo/prim/_asm_procedurecolorize_setpatchvariable_5.kept2_value : Ljava/lang/Double;
         L4
          ASTORE 2
         L0
          ALOAD 1
          GETFIELD org/nlogo/nvm/Context.agent : Lorg/nlogo/agent/Agent;
          ICONST_2
          ALOAD 2
          INVOKEVIRTUAL org/nlogo/agent/Agent.setPatchVariable (ILjava/lang/Object;)V
         L1
          GOTO L5
         L2
         FRAME FULL [org/nlogo/prim/_asm_procedurecolorize_setpatchvariable_5 org/nlogo/nvm/Context java/lang/Double] [org/nlogo/api/AgentException]
          ASTORE 3
          NEW org/nlogo/nvm/RuntimePrimitiveException
          DUP
          ALOAD 1
          ALOAD 0
          ALOAD 3
          INVOKEVIRTUAL org/nlogo/api/AgentException.getMessage ()Ljava/lang/String;
          INVOKESPECIAL org/nlogo/nvm/RuntimePrimitiveException.<init> (Lorg/nlogo/api/Context;Lorg/nlogo/nvm/Instruction;Ljava/lang/String;)V
          ATHROW
         L5
         FRAME SAME
          ALOAD 1
          ICONST_4
          PUTFIELD org/nlogo/nvm/Context.ip : I
         L6
          RETURN
[4]_asm_procedurecolorize_return_6 => void
         L0
          ALOAD 1
          INVOKEVIRTUAL org/nlogo/nvm/Context.returnFromProcedure ()V
          ALOAD 1
          ICONST_0
          PUTFIELD org/nlogo/nvm/Context.stopping : Z
         L1
          RETURN

procedure GO:[ACTIVE-PATCHES OVERLOADED-PATCHES]{O---}:
[0]_asm_procedurego_setprocedurevariable_0 "let patch-set one-of patches" Object => void
      _patchset "patch-set one-of patches"
        _asm_procedurego_oneof_1 "one-of patches" AgentSet => Object
          _patches "patches" => AgentSet
              // parameter final  context
             L0
              ALOAD 0
              GETFIELD org/nlogo/prim/_asm_procedurego_oneof_1.world : Lorg/nlogo/agent/World;
              INVOKEVIRTUAL org/nlogo/agent/World.patches ()Lorg/nlogo/agent/AgentSet;
             L1
              ASTORE 2
              ALOAD 2
              INVOKEVIRTUAL org/nlogo/agent/AgentSet.count ()I
              ISTORE 3
              ILOAD 3
              IFNE L2
              GETSTATIC org/nlogo/core/Nobody$.MODULE$ : Lorg/nlogo/core/Nobody$;
              GOTO L3
             L2
             FRAME APPEND [org/nlogo/agent/AgentSet I]
              ALOAD 2
              ILOAD 3
              ALOAD 1
              GETFIELD org/nlogo/nvm/Context.job : Lorg/nlogo/nvm/Job;
              GETFIELD org/nlogo/nvm/Job.random : Lorg/nlogo/api/MersenneTwisterFast;
              ILOAD 3
              INVOKEVIRTUAL org/nlogo/api/MersenneTwisterFast.nextInt (I)I
              INVOKEVIRTUAL org/nlogo/agent/AgentSet.randomOne (II)Lorg/nlogo/agent/Agent;
             L3
             FRAME SAME1 java/lang/Object
              ARETURN
          ALOAD 0
          GETFIELD org/nlogo/prim/_asm_procedurego_setprocedurevariable_0.keptinstr2 : Lorg/nlogo/prim/etc/_patchset;
          ALOAD 1
          INVOKEVIRTUAL org/nlogo/prim/etc/_patchset.report (Lorg/nlogo/nvm/Context;)Ljava/lang/Object;
         L0
          ASTORE 2
          ALOAD 1
          GETFIELD org/nlogo/nvm/Context.activation : Lorg/nlogo/nvm/Activation;
          GETFIELD org/nlogo/nvm/Activation.args : [Ljava/lang/Object;
          ICONST_0
          ALOAD 2
          AASTORE
          ALOAD 1
          ICONST_1
          PUTFIELD org/nlogo/nvm/Context.ip : I
         L1
          RETURN
[1]_asm_procedurego_ask_2 "ask active-patches set n n + 1 set total total + 1 [ colorize ]" Object => void
      _procedurevariable:ACTIVE-PATCHES "active-patches" => Object
          // parameter final  context
         L0
          ALOAD 1
          GETFIELD org/nlogo/nvm/Context.activation : Lorg/nlogo/nvm/Activation;
          GETFIELD org/nlogo/nvm/Activation.args : [Ljava/lang/Object;
          ICONST_0
          AALOAD
         L1
          ASTORE 2
          ALOAD 2
          INSTANCEOF org/nlogo/agent/AgentSet
          IFEQ L2
          ALOAD 2
          CHECKCAST org/nlogo/agent/AgentSet
          ASTORE 3
          ALOAD 1
          GETFIELD org/nlogo/nvm/Context.agent : Lorg/nlogo/agent/Agent;
          INSTANCEOF org/nlogo/agent/Observer
          IFNE L3
          ALOAD 3
          ALOAD 0
          GETFIELD org/nlogo/prim/_asm_procedurego_ask_2.world : Lorg/nlogo/agent/World;
          INVOKEVIRTUAL org/nlogo/agent/World.turtles ()Lorg/nlogo/agent/TreeAgentSet;
          IF_ACMPNE L4
          NEW org/nlogo/nvm/RuntimePrimitiveException
          DUP
          ALOAD 1
          ALOAD 0
          INVOKESTATIC org/nlogo/core/I18N.errorsJ ()Lorg/nlogo/core/I18NJava;
          LDC "org.nlogo.prim.$common.onlyObserverCanAskAllTurtles"
          INVOKEINTERFACE org/nlogo/core/I18NJava.get (Ljava/lang/String;)Ljava/lang/String;
          INVOKESPECIAL org/nlogo/nvm/RuntimePrimitiveException.<init> (Lorg/nlogo/api/Context;Lorg/nlogo/nvm/Instruction;Ljava/lang/String;)V
          ATHROW
         L4
         FRAME APPEND [java/lang/Object org/nlogo/agent/AgentSet]
          ALOAD 3
          ALOAD 0
          GETFIELD org/nlogo/prim/_asm_procedurego_ask_2.world : Lorg/nlogo/agent/World;
          INVOKEVIRTUAL org/nlogo/agent/World.patches ()Lorg/nlogo/agent/AgentSet;
          IF_ACMPNE L3
          NEW org/nlogo/nvm/RuntimePrimitiveException
          DUP
          ALOAD 1
          ALOAD 0
          INVOKESTATIC org/nlogo/core/I18N.errorsJ ()Lorg/nlogo/core/I18NJava;
          LDC "org.nlogo.prim.$common.onlyObserverCanAskAllPatches"
          INVOKEINTERFACE org/nlogo/core/I18NJava.get (Ljava/lang/String;)Ljava/lang/String;
          INVOKESPECIAL org/nlogo/nvm/RuntimePrimitiveException.<init> (Lorg/nlogo/api/Context;Lorg/nlogo/nvm/Instruction;Ljava/lang/String;)V
          ATHROW
         L2
         FRAME CHOP 1
          ALOAD 2
          INSTANCEOF org/nlogo/agent/Agent
          IFEQ L5
          ALOAD 2
          CHECKCAST org/nlogo/agent/Agent
          ASTORE 4
          ALOAD 4
          GETFIELD org/nlogo/agent/Agent.id : J
          LDC -1
          LCMP
          IFNE L6
          NEW org/nlogo/nvm/RuntimePrimitiveException
          DUP
          ALOAD 1
          ALOAD 0
          INVOKESTATIC org/nlogo/core/I18N.errorsJ ()Lorg/nlogo/core/I18NJava;
          LDC "org.nlogo.$common.thatAgentIsDead"
          ICONST_1
          ANEWARRAY java/lang/Object
          DUP
          ICONST_0
          ALOAD 4
          INVOKEVIRTUAL org/nlogo/agent/Agent.classDisplayName ()Ljava/lang/String;
          AASTORE
          INVOKEINTERFACE org/nlogo/core/I18NJava.getN (Ljava/lang/String;[Ljava/lang/Object;)Ljava/lang/String;
          INVOKESPECIAL org/nlogo/nvm/RuntimePrimitiveException.<init> (Lorg/nlogo/api/Context;Lorg/nlogo/nvm/Instruction;Ljava/lang/String;)V
          ATHROW
         L6
         FRAME APPEND [T org/nlogo/agent/Agent]
          ALOAD 4
          INVOKESTATIC org/nlogo/agent/AgentSet.fromAgent (Lorg/nlogo/agent/Agent;)Lorg/nlogo/agent/IndexedAgentSet;
          ASTORE 3
          GOTO L3
         L5
         FRAME CHOP 2
          NEW org/nlogo/nvm/ArgumentTypeException
          DUP
          ALOAD 1
          ALOAD 0
          ICONST_0
          INVOKESTATIC org/nlogo/core/Syntax.AgentsetType ()I
          INVOKESTATIC org/nlogo/core/Syntax.AgentType ()I
          IOR
          ALOAD 2
          INVOKESPECIAL org/nlogo/nvm/ArgumentTypeException.<init> (Lorg/nlogo/nvm/Context;Lorg/nlogo/nvm/Instruction;IILjava/lang/Object;)V
          ATHROW
         L3
         FRAME APPEND [org/nlogo/agent/AgentSet]
          ALOAD 1
          ALOAD 3
          ICONST_2
          INVOKEVIRTUAL org/nlogo/nvm/Context.runExclusiveJob (Lorg/nlogo/agent/AgentSet;I)V
          ALOAD 1
          BIPUSH 6
          PUTFIELD org/nlogo/nvm/Context.ip : I
         L7
          RETURN
[2]_asm_procedurego_setpatchvariable_3 "set n n + 1" Object => void
      _plus "n + 1" double,double => double
        _patchvariable:N "n" => Object
        _constdouble:1.0 "1" => double
          // parameter final  context
          TRYCATCHBLOCK L0 L1 L2 org/nlogo/api/AgentException
          TRYCATCHBLOCK L3 L4 L4 java/lang/ClassCastException
          TRYCATCHBLOCK L5 L6 L7 org/nlogo/api/AgentException
         L0
          ALOAD 1
          GETFIELD org/nlogo/nvm/Context.agent : Lorg/nlogo/agent/Agent;
          ICONST_5
          INVOKEVIRTUAL org/nlogo/agent/Agent.getPatchVariable (I)Ljava/lang/Object;
         L1
          GOTO L8
         L2
         FRAME SAME1 org/nlogo/api/AgentException
          ASTORE 2
          NEW org/nlogo/nvm/RuntimePrimitiveException
          DUP
          ALOAD 1
          ALOAD 0
          ALOAD 2
          INVOKEVIRTUAL org/nlogo/api/AgentException.getMessage ()Ljava/lang/String;
          INVOKESPECIAL org/nlogo/nvm/RuntimePrimitiveException.<init> (Lorg/nlogo/api/Context;Lorg/nlogo/nvm/Instruction;Ljava/lang/String;)V
          ATHROW
         L8
         FRAME SAME1 java/lang/Object
          ASTORE 2
         L3
          ALOAD 2
          CHECKCAST java/lang/Double
          INVOKEVIRTUAL java/lang/Double.doubleValue ()D
          GOTO L9
         L4
         FRAME FULL [org/nlogo/prim/_asm_procedurego_setpatchvariable_3 org/nlogo/nvm/Context java/lang/Object] [java/lang/ClassCastException]
          POP
          NEW org/nlogo/nvm/ArgumentTypeException
          DUP
          ALOAD 1
          ALOAD 0
          BIPUSH 0
          LDC 1
          ALOAD 2
          INVOKESPECIAL org/nlogo/nvm/ArgumentTypeException.<init> (Lorg/nlogo/nvm/Context;Lorg/nlogo/nvm/Instruction;IILjava/lang/Object;)V
          ATHROW
         L9
         FRAME SAME1 D
          DCONST_1
         L10
          DSTORE 4
          DSTORE 2
          ALOAD 0
          DLOAD 2
          DLOAD 4
          DADD
          INVOKEVIRTUAL org/nlogo/prim/_asm_procedurego_setpatchvariable_3.validDouble (D)D
         L11
          DSTORE 2
          NEW java/lang/Double
          DUP
          DLOAD 2
          INVOKESPECIAL java/lang/Double.<init> (D)V
          ASTORE 2
         L5
          ALOAD 1
          GETFIELD org/nlogo/nvm/Context.agent : Lorg/nlogo/agent/Agent;
          ICONST_5
          ALOAD 2
          INVOKEVIRTUAL org/nlogo/agent/Agent.setPatchVariable (ILjava/lang/Object;)V
         L6
          GOTO L12
         L7
         FRAME FULL [org/nlogo/prim/_asm_procedurego_setpatchvariable_3 org/nlogo/nvm/Context java/lang/Double T D] [org/nlogo/api/AgentException]
          ASTORE 3
          NEW org/nlogo/nvm/RuntimePrimitiveException
          DUP
          ALOAD 1
          ALOAD 0
          ALOAD 3
          INVOKEVIRTUAL org/nlogo/api/AgentException.getMessage ()Ljava/lang/String;
          INVOKESPECIAL org/nlogo/nvm/RuntimePrimitiveException.<init> (Lorg/nlogo/api/Context;Lorg/nlogo/nvm/Instruction;Ljava/lang/String;)V
          ATHROW
         L12
         FRAME SAME
          ALOAD 1
          ICONST_3
          PUTFIELD org/nlogo/nvm/Context.ip : I
         L13
          RETURN
[3]_asm_procedurego_setobservervariable_4 "set total total + 1" Object => void
      _plus "total + 1" double,double => double
        _observervariable:TOTAL "total" => Object
        _constdouble:1.0 "1" => double
          TRYCATCHBLOCK L0 L1 L1 java/lang/ClassCastException
          TRYCATCHBLOCK L2 L3 L4 org/nlogo/api/AgentException
         L5
          ALOAD 1
          GETFIELD org/nlogo/nvm/Context.agent : Lorg/nlogo/agent/Agent;
          ICONST_1
          INVOKEVIRTUAL org/nlogo/agent/Agent.getObserverVariable (I)Ljava/lang/Object;
         L6
          ASTORE 2
         L0
          ALOAD 2
          CHECKCAST java/lang/Double
          INVOKEVIRTUAL java/lang/Double.doubleValue ()D
          GOTO L7
         L1
         FRAME FULL [org/nlogo/prim/_asm_procedurego_setobservervariable_4 org/nlogo/nvm/Context java/lang/Object] [java/lang/ClassCastException]
          POP
          NEW org/nlogo/nvm/ArgumentTypeException
          DUP
          ALOAD 1
          ALOAD 0
          BIPUSH 0
          LDC 1
          ALOAD 2
          INVOKESPECIAL org/nlogo/nvm/ArgumentTypeException.<init> (Lorg/nlogo/nvm/Context;Lorg/nlogo/nvm/Instruction;IILjava/lang/Object;)V
          ATHROW
         L7
         FRAME SAME1 D
          DCONST_1
         L8
          DSTORE 4
          DSTORE 2
          ALOAD 0
          DLOAD 2
          DLOAD 4
          DADD
          INVOKEVIRTUAL org/nlogo/prim/_asm_procedurego_setobservervariable_4.validDouble (D)D
         L9
          DSTORE 2
          NEW java/lang/Double
          DUP
          DLOAD 2
          INVOKESPECIAL java/lang/Double.<init> (D)V
          ASTORE 2
         L2
          ALOAD 1
          GETFIELD org/nlogo/nvm/Context.agent : Lorg/nlogo/agent/Agent;
          ICONST_1
          ALOAD 2
          INVOKEVIRTUAL org/nlogo/agent/Agent.setObserverVariable (ILjava/lang/Object;)V
         L3
          GOTO L10
         L4
         FRAME FULL [org/nlogo/prim/_asm_procedurego_setobservervariable_4 org/nlogo/nvm/Context java/lang/Double T D] [org/nlogo/api/AgentException]
          ASTORE 3
          NEW org/nlogo/nvm/RuntimePrimitiveException
          DUP
          ALOAD 1
          ALOAD 0
          ALOAD 3
          INVOKEVIRTUAL org/nlogo/api/AgentException.getMessage ()Ljava/lang/String;
          INVOKESPECIAL org/nlogo/nvm/RuntimePrimitiveException.<init> (Lorg/nlogo/api/Context;Lorg/nlogo/nvm/Instruction;Ljava/lang/String;)V
          ATHROW
         L10
         FRAME SAME
          ALOAD 1
          ICONST_4
          PUTFIELD org/nlogo/nvm/Context.ip : I
         L11
          RETURN
[4]_asm_procedurego_call_5 "colorize"
         L0
          NEW org/nlogo/nvm/Activation
          DUP
          ALOAD 0
          GETFIELD org/nlogo/prim/_asm_procedurego_call_5.kept1_procedure : Lorg/nlogo/nvm/Procedure;
          ALOAD 1
          GETFIELD org/nlogo/nvm/Context.activation : Lorg/nlogo/nvm/Activation;
          ICONST_5
          INVOKESPECIAL org/nlogo/nvm/Activation.<init> (Lorg/nlogo/nvm/Procedure;Lorg/nlogo/nvm/Activation;I)V
          ALOAD 1
          SWAP
          PUTFIELD org/nlogo/nvm/Context.activation : Lorg/nlogo/nvm/Activation;
          ALOAD 1
          ICONST_0
          PUTFIELD org/nlogo/nvm/Context.ip : I
         L1
          RETURN
[5]_asm_procedurego_done_6 => void
          // parameter final  context
         L0
          ALOAD 1
          ICONST_1
          PUTFIELD org/nlogo/nvm/Context.finished : Z
         L1
          RETURN
[6]_asm_procedurego_goto_7 => void
         L0
          ALOAD 1
          BIPUSH 19
          PUTFIELD org/nlogo/nvm/Context.ip : I
         L1
          RETURN
[7]_asm_procedurego_setprocedurevariable_8 "let active-patches with [ n > 3 ]" Object => void
      _with "active-patches with [ n > 3 ]" AgentSet,Reporter => AgentSet
        _procedurevariable:ACTIVE-PATCHES "active-patches" => Object
        _asm_procedurego_greaterthan_9 "n > 3" Object,double => boolean
          _patchvariable:N "n" => Object
          _constdouble:3.0 "3" => double
              // parameter final  context
              TRYCATCHBLOCK L0 L1 L2 org/nlogo/api/AgentException
             L0
              ALOAD 1
              GETFIELD org/nlogo/nvm/Context.agent : Lorg/nlogo/agent/Agent;
              ICONST_5
              INVOKEVIRTUAL org/nlogo/agent/Agent.getPatchVariable (I)Ljava/lang/Object;
             L1
              GOTO L3
             L2
             FRAME SAME1 org/nlogo/api/AgentException
              ASTORE 2
              NEW org/nlogo/nvm/RuntimePrimitiveException
              DUP
              ALOAD 1
              ALOAD 0
              ALOAD 2
              INVOKEVIRTUAL org/nlogo/api/AgentException.getMessage ()Ljava/lang/String;
              INVOKESPECIAL org/nlogo/nvm/RuntimePrimitiveException.<init> (Lorg/nlogo/api/Context;Lorg/nlogo/nvm/Instruction;Ljava/lang/String;)V
              ATHROW
             L3
             FRAME SAME1 java/lang/Object
              LDC 3.0
             L4
              DSTORE 3
              ASTORE 2
              ALOAD 2
              INSTANCEOF java/lang/Double
              IFEQ L5
              ALOAD 2
              CHECKCAST java/lang/Double
              INVOKEVIRTUAL java/lang/Double.doubleValue ()D
              DLOAD 3
              DCMPL
              IFLE L6
              ICONST_1
              GOTO L7
             L6
             FRAME APPEND [java/lang/Object D]
              ICONST_0
             L7
             FRAME SAME1 I
              GOTO L8
             L5
             FRAME SAME
              NEW org/nlogo/nvm/RuntimePrimitiveException
              DUP
              ALOAD 1
              ALOAD 0
              INVOKESTATIC org/nlogo/core/I18N.errorsJ ()Lorg/nlogo/core/I18NJava;
              LDC "org.nlogo.prim._greaterthan.cannotCompareParameters"
              ICONST_2
              ANEWARRAY java/lang/Object
              DUP
              ICONST_0
              ALOAD 2
              INVOKESTATIC org/nlogo/api/TypeNames.aName (Ljava/lang/Object;)Ljava/lang/String;
              AASTORE
              DUP
              ICONST_1
              DLOAD 3
              INVOKESTATIC java/lang/Double.valueOf (D)Ljava/lang/Double;
              INVOKESTATIC org/nlogo/api/TypeNames.aName (Ljava/lang/Object;)Ljava/lang/String;
              AASTORE
              INVOKEINTERFACE org/nlogo/core/I18NJava.getN (Ljava/lang/String;[Ljava/lang/Object;)Ljava/lang/String;
              INVOKESPECIAL org/nlogo/nvm/RuntimePrimitiveException.<init> (Lorg/nlogo/api/Context;Lorg/nlogo/nvm/Instruction;Ljava/lang/String;)V
              ATHROW
             L8
             FRAME SAME1 I
              IFEQ L9
              GETSTATIC java/lang/Boolean.TRUE : Ljava/lang/Boolean;
              GOTO L10
             L9
             FRAME SAME
              GETSTATIC java/lang/Boolean.FALSE : Ljava/lang/Boolean;
             L10
             FRAME SAME1 java/lang/Boolean
              ARETURN
          // parameter final  context
          TRYCATCHBLOCK L0 L1 L1 java/lang/ClassCastException
         L2
          ALOAD 1
          GETFIELD org/nlogo/nvm/Context.activation : Lorg/nlogo/nvm/Activation;
          GETFIELD org/nlogo/nvm/Activation.args : [Ljava/lang/Object;
          ICONST_0
          AALOAD
         L3
          ASTORE 2
         L0
          ALOAD 2
          CHECKCAST org/nlogo/agent/AgentSet
          GOTO L4
         L1
         FRAME FULL [org/nlogo/prim/_asm_procedurego_setprocedurevariable_8 org/nlogo/nvm/Context java/lang/Object] [java/lang/ClassCastException]
          POP
          NEW org/nlogo/nvm/ArgumentTypeException
          DUP
          ALOAD 1
          ALOAD 0
          BIPUSH 0
          LDC 112
          ALOAD 2
          INVOKESPECIAL org/nlogo/nvm/ArgumentTypeException.<init> (Lorg/nlogo/nvm/Context;Lorg/nlogo/nvm/Instruction;IILjava/lang/Object;)V
          ATHROW
         L4
         FRAME SAME1 org/nlogo/agent/AgentSet
          ALOAD 0
          GETFIELD org/nlogo/prim/_asm_procedurego_setprocedurevariable_8.keptinstr4 : Lorg/nlogo/nvm/Reporter;
          ASTORE 3
          ASTORE 2
          NEW org/nlogo/nvm/Context
          DUP
          ALOAD 1
          ALOAD 2
          INVOKESPECIAL org/nlogo/nvm/Context.<init> (Lorg/nlogo/nvm/Context;Lorg/nlogo/agent/AgentSet;)V
          ASTORE 4
          NEW java/util/ArrayList
          DUP
          INVOKESPECIAL java/util/ArrayList.<init> ()V
          ASTORE 5
          ALOAD 3
          ALOAD 2
          ALOAD 1
          INVOKEVIRTUAL org/nlogo/nvm/Reporter.checkAgentSetClass (Lorg/nlogo/agent/AgentSet;Lorg/nlogo/nvm/Context;)V
          ALOAD 2
          INVOKEVIRTUAL org/nlogo/agent/AgentSet.iterator ()Lorg/nlogo/agent/AgentIterator;
          ASTORE 6
         L5
         FRAME FULL [org/nlogo/prim/_asm_procedurego_setprocedurevariable_8 org/nlogo/nvm/Context org/nlogo/agent/AgentSet org/nlogo/nvm/Reporter org/nlogo/nvm/Context java/util/ArrayList org/nlogo/agent/AgentIterator] []
          ALOAD 6
          INVOKEINTERFACE org/nlogo/agent/AgentIterator.hasNext ()Z
          IFEQ L6
          ALOAD 6
          INVOKEINTERFACE org/nlogo/agent/AgentIterator.next ()Lorg/nlogo/agent/Agent;
          ASTORE 7
          ALOAD 4
          ALOAD 7
          ALOAD 3
          INVOKEVIRTUAL org/nlogo/nvm/Context.evaluateReporter (Lorg/nlogo/agent/Agent;Lorg/nlogo/nvm/Reporter;)Ljava/lang/Object;
          ASTORE 8
          ALOAD 8
          INSTANCEOF java/lang/Boolean
          IFNE L7
          NEW org/nlogo/nvm/RuntimePrimitiveException
          DUP
          ALOAD 1
          ALOAD 0
          INVOKESTATIC org/nlogo/core/I18N.errorsJ ()Lorg/nlogo/core/I18NJava;
          LDC "org.nlogo.prim.$common.expectedBooleanValue"
          ICONST_3
          ANEWARRAY java/lang/Object
          DUP
          ICONST_0
          LDC "WITH"
          AASTORE
          DUP
          ICONST_1
          ALOAD 7
          INVOKESTATIC org/nlogo/api/Dump.logoObject (Ljava/lang/Object;)Ljava/lang/String;
          AASTORE
          DUP
          ICONST_2
          ALOAD 8
          INVOKESTATIC org/nlogo/api/Dump.logoObject (Ljava/lang/Object;)Ljava/lang/String;
          AASTORE
          INVOKEINTERFACE org/nlogo/core/I18NJava.getN (Ljava/lang/String;[Ljava/lang/Object;)Ljava/lang/String;
          INVOKESPECIAL org/nlogo/nvm/RuntimePrimitiveException.<init> (Lorg/nlogo/api/Context;Lorg/nlogo/nvm/Instruction;Ljava/lang/String;)V
          ATHROW
         L7
         FRAME APPEND [org/nlogo/agent/Agent java/lang/Object]
          ALOAD 8
          CHECKCAST java/lang/Boolean
          INVOKEVIRTUAL java/lang/Boolean.booleanValue ()Z
          IFEQ L8
          ALOAD 5
          ALOAD 7
          INVOKEINTERFACE java/util/List.add (Ljava/lang/Object;)Z
          POP
         L8
         FRAME SAME
          GOTO L5
         L6
         FRAME CHOP 2
          ALOAD 2
          INVOKEVIRTUAL org/nlogo/agent/AgentSet.kind ()Lorg/nlogo/core/AgentKind;
          ALOAD 5
          ALOAD 5
          INVOKEINTERFACE java/util/List.size ()I
          ANEWARRAY org/nlogo/agent/Agent
          INVOKEINTERFACE java/util/List.toArray ([Ljava/lang/Object;)[Ljava/lang/Object;
          CHECKCAST [Lorg/nlogo/agent/Agent;
          INVOKESTATIC org/nlogo/agent/AgentSet.fromArray (Lorg/nlogo/core/AgentKind;[Lorg/nlogo/agent/Agent;)Lorg/nlogo/agent/IndexedAgentSet;
         L9
          ASTORE 2
          ALOAD 1
          GETFIELD org/nlogo/nvm/Context.activation : Lorg/nlogo/nvm/Activation;
          GETFIELD org/nlogo/nvm/Activation.args : [Ljava/lang/Object;
          ICONST_1
          ALOAD 2
          AASTORE
          ALOAD 1
          BIPUSH 8
          PUTFIELD org/nlogo/nvm/Context.ip : I
         L10
          RETURN
[8]_asm_procedurego_ask_10 "ask overloaded-patches set n n - 4 set total total - 4 colorize [ ask neighbors4 set n n + 1 set total total + 1 [ colorize ] ]" Object => void
      _procedurevariable:OVERLOADED-PATCHES "overloaded-patches" => Object
          // parameter final  context
         L0
          ALOAD 1
          GETFIELD org/nlogo/nvm/Context.activation : Lorg/nlogo/nvm/Activation;
          GETFIELD org/nlogo/nvm/Activation.args : [Ljava/lang/Object;
          ICONST_1
          AALOAD
         L1
          ASTORE 2
          ALOAD 2
          INSTANCEOF org/nlogo/agent/AgentSet
          IFEQ L2
          ALOAD 2
          CHECKCAST org/nlogo/agent/AgentSet
          ASTORE 3
          ALOAD 1
          GETFIELD org/nlogo/nvm/Context.agent : Lorg/nlogo/agent/Agent;
          INSTANCEOF org/nlogo/agent/Observer
          IFNE L3
          ALOAD 3
          ALOAD 0
          GETFIELD org/nlogo/prim/_asm_procedurego_ask_10.world : Lorg/nlogo/agent/World;
          INVOKEVIRTUAL org/nlogo/agent/World.turtles ()Lorg/nlogo/agent/TreeAgentSet;
          IF_ACMPNE L4
          NEW org/nlogo/nvm/RuntimePrimitiveException
          DUP
          ALOAD 1
          ALOAD 0
          INVOKESTATIC org/nlogo/core/I18N.errorsJ ()Lorg/nlogo/core/I18NJava;
          LDC "org.nlogo.prim.$common.onlyObserverCanAskAllTurtles"
          INVOKEINTERFACE org/nlogo/core/I18NJava.get (Ljava/lang/String;)Ljava/lang/String;
          INVOKESPECIAL org/nlogo/nvm/RuntimePrimitiveException.<init> (Lorg/nlogo/api/Context;Lorg/nlogo/nvm/Instruction;Ljava/lang/String;)V
          ATHROW
         L4
         FRAME APPEND [java/lang/Object org/nlogo/agent/AgentSet]
          ALOAD 3
          ALOAD 0
          GETFIELD org/nlogo/prim/_asm_procedurego_ask_10.world : Lorg/nlogo/agent/World;
          INVOKEVIRTUAL org/nlogo/agent/World.patches ()Lorg/nlogo/agent/AgentSet;
          IF_ACMPNE L3
          NEW org/nlogo/nvm/RuntimePrimitiveException
          DUP
          ALOAD 1
          ALOAD 0
          INVOKESTATIC org/nlogo/core/I18N.errorsJ ()Lorg/nlogo/core/I18NJava;
          LDC "org.nlogo.prim.$common.onlyObserverCanAskAllPatches"
          INVOKEINTERFACE org/nlogo/core/I18NJava.get (Ljava/lang/String;)Ljava/lang/String;
          INVOKESPECIAL org/nlogo/nvm/RuntimePrimitiveException.<init> (Lorg/nlogo/api/Context;Lorg/nlogo/nvm/Instruction;Ljava/lang/String;)V
          ATHROW
         L2
         FRAME CHOP 1
          ALOAD 2
          INSTANCEOF org/nlogo/agent/Agent
          IFEQ L5
          ALOAD 2
          CHECKCAST org/nlogo/agent/Agent
          ASTORE 4
          ALOAD 4
          GETFIELD org/nlogo/agent/Agent.id : J
          LDC -1
          LCMP
          IFNE L6
          NEW org/nlogo/nvm/RuntimePrimitiveException
          DUP
          ALOAD 1
          ALOAD 0
          INVOKESTATIC org/nlogo/core/I18N.errorsJ ()Lorg/nlogo/core/I18NJava;
          LDC "org.nlogo.$common.thatAgentIsDead"
          ICONST_1
          ANEWARRAY java/lang/Object
          DUP
          ICONST_0
          ALOAD 4
          INVOKEVIRTUAL org/nlogo/agent/Agent.classDisplayName ()Ljava/lang/String;
          AASTORE
          INVOKEINTERFACE org/nlogo/core/I18NJava.getN (Ljava/lang/String;[Ljava/lang/Object;)Ljava/lang/String;
          INVOKESPECIAL org/nlogo/nvm/RuntimePrimitiveException.<init> (Lorg/nlogo/api/Context;Lorg/nlogo/nvm/Instruction;Ljava/lang/String;)V
          ATHROW
         L6
         FRAME APPEND [T org/nlogo/agent/Agent]
          ALOAD 4
          INVOKESTATIC org/nlogo/agent/AgentSet.fromAgent (Lorg/nlogo/agent/Agent;)Lorg/nlogo/agent/IndexedAgentSet;
          ASTORE 3
          GOTO L3
         L5
         FRAME CHOP 2
          NEW org/nlogo/nvm/ArgumentTypeException
          DUP
          ALOAD 1
          ALOAD 0
          ICONST_0
          INVOKESTATIC org/nlogo/core/Syntax.AgentsetType ()I
          INVOKESTATIC org/nlogo/core/Syntax.AgentType ()I
          IOR
          ALOAD 2
          INVOKESPECIAL org/nlogo/nvm/ArgumentTypeException.<init> (Lorg/nlogo/nvm/Context;Lorg/nlogo/nvm/Instruction;IILjava/lang/Object;)V
          ATHROW
         L3
         FRAME APPEND [org/nlogo/agent/AgentSet]
          ALOAD 1
          ALOAD 3
          BIPUSH 9
          INVOKEVIRTUAL org/nlogo/nvm/Context.runExclusiveJob (Lorg/nlogo/agent/AgentSet;I)V
          ALOAD 1
          BIPUSH 18
          PUTFIELD org/nlogo/nvm/Context.ip : I
         L7
          RETURN
[9]_asm_procedurego_setpatchvariable_11 "set n n - 4" Object => void
      _minus "n - 4" double,double => double
        _patchvariable:N "n" => Object
        _constdouble:4.0 "4" => double
          // parameter final  context
          TRYCATCHBLOCK L0 L1 L2 org/nlogo/api/AgentException
          TRYCATCHBLOCK L3 L4 L4 java/lang/ClassCastException
          TRYCATCHBLOCK L5 L6 L7 org/nlogo/api/AgentException
         L0
          ALOAD 1
          GETFIELD org/nlogo/nvm/Context.agent : Lorg/nlogo/agent/Agent;
          ICONST_5
          INVOKEVIRTUAL org/nlogo/agent/Agent.getPatchVariable (I)Ljava/lang/Object;
         L1
          GOTO L8
         L2
         FRAME SAME1 org/nlogo/api/AgentException
          ASTORE 2
          NEW org/nlogo/nvm/RuntimePrimitiveException
          DUP
          ALOAD 1
          ALOAD 0
          ALOAD 2
          INVOKEVIRTUAL org/nlogo/api/AgentException.getMessage ()Ljava/lang/String;
          INVOKESPECIAL org/nlogo/nvm/RuntimePrimitiveException.<init> (Lorg/nlogo/api/Context;Lorg/nlogo/nvm/Instruction;Ljava/lang/String;)V
          ATHROW
         L8
         FRAME SAME1 java/lang/Object
          ASTORE 2
         L3
          ALOAD 2
          CHECKCAST java/lang/Double
          INVOKEVIRTUAL java/lang/Double.doubleValue ()D
          GOTO L9
         L4
         FRAME FULL [org/nlogo/prim/_asm_procedurego_setpatchvariable_11 org/nlogo/nvm/Context java/lang/Object] [java/lang/ClassCastException]
          POP
          NEW org/nlogo/nvm/ArgumentTypeException
          DUP
          ALOAD 1
          ALOAD 0
          BIPUSH 0
          LDC 1
          ALOAD 2
          INVOKESPECIAL org/nlogo/nvm/ArgumentTypeException.<init> (Lorg/nlogo/nvm/Context;Lorg/nlogo/nvm/Instruction;IILjava/lang/Object;)V
          ATHROW
         L9
         FRAME SAME1 D
          LDC 4.0
         L10
          DSTORE 4
          DSTORE 2
          ALOAD 0
          DLOAD 2
          DLOAD 4
          DSUB
          INVOKEVIRTUAL org/nlogo/prim/_asm_procedurego_setpatchvariable_11.validDouble (D)D
         L11
          DSTORE 2
          NEW java/lang/Double
          DUP
          DLOAD 2
          INVOKESPECIAL java/lang/Double.<init> (D)V
          ASTORE 2
         L5
          ALOAD 1
          GETFIELD org/nlogo/nvm/Context.agent : Lorg/nlogo/agent/Agent;
          ICONST_5
          ALOAD 2
          INVOKEVIRTUAL org/nlogo/agent/Agent.setPatchVariable (ILjava/lang/Object;)V
         L6
          GOTO L12
         L7
         FRAME FULL [org/nlogo/prim/_asm_procedurego_setpatchvariable_11 org/nlogo/nvm/Context java/lang/Double T D] [org/nlogo/api/AgentException]
          ASTORE 3
          NEW org/nlogo/nvm/RuntimePrimitiveException
          DUP
          ALOAD 1
          ALOAD 0
          ALOAD 3
          INVOKEVIRTUAL org/nlogo/api/AgentException.getMessage ()Ljava/lang/String;
          INVOKESPECIAL org/nlogo/nvm/RuntimePrimitiveException.<init> (Lorg/nlogo/api/Context;Lorg/nlogo/nvm/Instruction;Ljava/lang/String;)V
          ATHROW
         L12
         FRAME SAME
          ALOAD 1
          BIPUSH 10
          PUTFIELD org/nlogo/nvm/Context.ip : I
         L13
          RETURN
[10]_asm_procedurego_setobservervariable_12 "set total total - 4" Object => void
      _minus "total - 4" double,double => double
        _observervariable:TOTAL "total" => Object
        _constdouble:4.0 "4" => double
          TRYCATCHBLOCK L0 L1 L1 java/lang/ClassCastException
          TRYCATCHBLOCK L2 L3 L4 org/nlogo/api/AgentException
         L5
          ALOAD 1
          GETFIELD org/nlogo/nvm/Context.agent : Lorg/nlogo/agent/Agent;
          ICONST_1
          INVOKEVIRTUAL org/nlogo/agent/Agent.getObserverVariable (I)Ljava/lang/Object;
         L6
          ASTORE 2
         L0
          ALOAD 2
          CHECKCAST java/lang/Double
          INVOKEVIRTUAL java/lang/Double.doubleValue ()D
          GOTO L7
         L1
         FRAME FULL [org/nlogo/prim/_asm_procedurego_setobservervariable_12 org/nlogo/nvm/Context java/lang/Object] [java/lang/ClassCastException]
          POP
          NEW org/nlogo/nvm/ArgumentTypeException
          DUP
          ALOAD 1
          ALOAD 0
          BIPUSH 0
          LDC 1
          ALOAD 2
          INVOKESPECIAL org/nlogo/nvm/ArgumentTypeException.<init> (Lorg/nlogo/nvm/Context;Lorg/nlogo/nvm/Instruction;IILjava/lang/Object;)V
          ATHROW
         L7
         FRAME SAME1 D
          LDC 4.0
         L8
          DSTORE 4
          DSTORE 2
          ALOAD 0
          DLOAD 2
          DLOAD 4
          DSUB
          INVOKEVIRTUAL org/nlogo/prim/_asm_procedurego_setobservervariable_12.validDouble (D)D
         L9
          DSTORE 2
          NEW java/lang/Double
          DUP
          DLOAD 2
          INVOKESPECIAL java/lang/Double.<init> (D)V
          ASTORE 2
         L2
          ALOAD 1
          GETFIELD org/nlogo/nvm/Context.agent : Lorg/nlogo/agent/Agent;
          ICONST_1
          ALOAD 2
          INVOKEVIRTUAL org/nlogo/agent/Agent.setObserverVariable (ILjava/lang/Object;)V
         L3
          GOTO L10
         L4
         FRAME FULL [org/nlogo/prim/_asm_procedurego_setobservervariable_12 org/nlogo/nvm/Context java/lang/Double T D] [org/nlogo/api/AgentException]
          ASTORE 3
          NEW org/nlogo/nvm/RuntimePrimitiveException
          DUP
          ALOAD 1
          ALOAD 0
          ALOAD 3
          INVOKEVIRTUAL org/nlogo/api/AgentException.getMessage ()Ljava/lang/String;
          INVOKESPECIAL org/nlogo/nvm/RuntimePrimitiveException.<init> (Lorg/nlogo/api/Context;Lorg/nlogo/nvm/Instruction;Ljava/lang/String;)V
          ATHROW
         L10
         FRAME SAME
          ALOAD 1
          BIPUSH 11
          PUTFIELD org/nlogo/nvm/Context.ip : I
         L11
          RETURN
[11]_asm_procedurego_call_13 "colorize"
         L0
          NEW org/nlogo/nvm/Activation
          DUP
          ALOAD 0
          GETFIELD org/nlogo/prim/_asm_procedurego_call_13.kept1_procedure : Lorg/nlogo/nvm/Procedure;
          ALOAD 1
          GETFIELD org/nlogo/nvm/Context.activation : Lorg/nlogo/nvm/Activation;
          BIPUSH 12
          INVOKESPECIAL org/nlogo/nvm/Activation.<init> (Lorg/nlogo/nvm/Procedure;Lorg/nlogo/nvm/Activation;I)V
          ALOAD 1
          SWAP
          PUTFIELD org/nlogo/nvm/Context.activation : Lorg/nlogo/nvm/Activation;
          ALOAD 1
          ICONST_0
          PUTFIELD org/nlogo/nvm/Context.ip : I
         L1
          RETURN
[12]_asm_procedurego_ask_14 "ask neighbors4 set n n + 1 set total total + 1 [ colorize ]" AgentSet => void
      _neighbors4 "neighbors4" => AgentSet
         L0
          ALOAD 1
          GETFIELD org/nlogo/nvm/Context.agent : Lorg/nlogo/agent/Agent;
          INSTANCEOF org/nlogo/agent/Turtle
          IFEQ L1
          ALOAD 1
          GETFIELD org/nlogo/nvm/Context.agent : Lorg/nlogo/agent/Agent;
          CHECKCAST org/nlogo/agent/Turtle
          INVOKEVIRTUAL org/nlogo/agent/Turtle.getPatchHere ()Lorg/nlogo/agent/Patch;
          INVOKEVIRTUAL org/nlogo/agent/Patch.getNeighbors4 ()Lorg/nlogo/agent/IndexedAgentSet;
          GOTO L2
         L1
         FRAME SAME
          ALOAD 1
          GETFIELD org/nlogo/nvm/Context.agent : Lorg/nlogo/agent/Agent;
          CHECKCAST org/nlogo/agent/Patch
          INVOKEVIRTUAL org/nlogo/agent/Patch.getNeighbors4 ()Lorg/nlogo/agent/IndexedAgentSet;
         L2
         FRAME SAME1 org/nlogo/agent/IndexedAgentSet
          ASTORE 2
          ALOAD 1
          GETFIELD org/nlogo/nvm/Context.agent : Lorg/nlogo/agent/Agent;
          INSTANCEOF org/nlogo/agent/Observer
          IFNE L3
          ALOAD 2
          ALOAD 0
          GETFIELD org/nlogo/prim/_asm_procedurego_ask_14.world : Lorg/nlogo/agent/World;
          INVOKEVIRTUAL org/nlogo/agent/World.turtles ()Lorg/nlogo/agent/TreeAgentSet;
          IF_ACMPNE L4
          NEW org/nlogo/nvm/RuntimePrimitiveException
          DUP
          ALOAD 1
          ALOAD 0
          INVOKESTATIC org/nlogo/core/I18N.errorsJ ()Lorg/nlogo/core/I18NJava;
          LDC "org.nlogo.prim.$common.onlyObserverCanAskAllTurtles"
          INVOKEINTERFACE org/nlogo/core/I18NJava.get (Ljava/lang/String;)Ljava/lang/String;
          INVOKESPECIAL org/nlogo/nvm/RuntimePrimitiveException.<init> (Lorg/nlogo/api/Context;Lorg/nlogo/nvm/Instruction;Ljava/lang/String;)V
          ATHROW
         L4
         FRAME APPEND [org/nlogo/agent/IndexedAgentSet]
          ALOAD 2
          ALOAD 0
          GETFIELD org/nlogo/prim/_asm_procedurego_ask_14.world : Lorg/nlogo/agent/World;
          INVOKEVIRTUAL org/nlogo/agent/World.patches ()Lorg/nlogo/agent/AgentSet;
          IF_ACMPNE L3
          NEW org/nlogo/nvm/RuntimePrimitiveException
          DUP
          ALOAD 1
          ALOAD 0
          INVOKESTATIC org/nlogo/core/I18N.errorsJ ()Lorg/nlogo/core/I18NJava;
          LDC "org.nlogo.prim.$common.onlyObserverCanAskAllPatches"
          INVOKEINTERFACE org/nlogo/core/I18NJava.get (Ljava/lang/String;)Ljava/lang/String;
          INVOKESPECIAL org/nlogo/nvm/RuntimePrimitiveException.<init> (Lorg/nlogo/api/Context;Lorg/nlogo/nvm/Instruction;Ljava/lang/String;)V
          ATHROW
         L3
         FRAME SAME
          ALOAD 1
          ALOAD 2
          BIPUSH 13
          INVOKEVIRTUAL org/nlogo/nvm/Context.runExclusiveJob (Lorg/nlogo/agent/AgentSet;I)V
          ALOAD 1
          BIPUSH 17
          PUTFIELD org/nlogo/nvm/Context.ip : I
         L5
          RETURN
[13]_asm_procedurego_setpatchvariable_15 "set n n + 1" Object => void
      _plus "n + 1" double,double => double
        _patchvariable:N "n" => Object
        _constdouble:1.0 "1" => double
          // parameter final  context
          TRYCATCHBLOCK L0 L1 L2 org/nlogo/api/AgentException
          TRYCATCHBLOCK L3 L4 L4 java/lang/ClassCastException
          TRYCATCHBLOCK L5 L6 L7 org/nlogo/api/AgentException
         L0
          ALOAD 1
          GETFIELD org/nlogo/nvm/Context.agent : Lorg/nlogo/agent/Agent;
          ICONST_5
          INVOKEVIRTUAL org/nlogo/agent/Agent.getPatchVariable (I)Ljava/lang/Object;
         L1
          GOTO L8
         L2
         FRAME SAME1 org/nlogo/api/AgentException
          ASTORE 2
          NEW org/nlogo/nvm/RuntimePrimitiveException
          DUP
          ALOAD 1
          ALOAD 0
          ALOAD 2
          INVOKEVIRTUAL org/nlogo/api/AgentException.getMessage ()Ljava/lang/String;
          INVOKESPECIAL org/nlogo/nvm/RuntimePrimitiveException.<init> (Lorg/nlogo/api/Context;Lorg/nlogo/nvm/Instruction;Ljava/lang/String;)V
          ATHROW
         L8
         FRAME SAME1 java/lang/Object
          ASTORE 2
         L3
          ALOAD 2
          CHECKCAST java/lang/Double
          INVOKEVIRTUAL java/lang/Double.doubleValue ()D
          GOTO L9
         L4
         FRAME FULL [org/nlogo/prim/_asm_procedurego_setpatchvariable_15 org/nlogo/nvm/Context java/lang/Object] [java/lang/ClassCastException]
          POP
          NEW org/nlogo/nvm/ArgumentTypeException
          DUP
          ALOAD 1
          ALOAD 0
          BIPUSH 0
          LDC 1
          ALOAD 2
          INVOKESPECIAL org/nlogo/nvm/ArgumentTypeException.<init> (Lorg/nlogo/nvm/Context;Lorg/nlogo/nvm/Instruction;IILjava/lang/Object;)V
          ATHROW
         L9
         FRAME SAME1 D
          DCONST_1
         L10
          DSTORE 4
          DSTORE 2
          ALOAD 0
          DLOAD 2
          DLOAD 4
          DADD
          INVOKEVIRTUAL org/nlogo/prim/_asm_procedurego_setpatchvariable_15.validDouble (D)D
         L11
          DSTORE 2
          NEW java/lang/Double
          DUP
          DLOAD 2
          INVOKESPECIAL java/lang/Double.<init> (D)V
          ASTORE 2
         L5
          ALOAD 1
          GETFIELD org/nlogo/nvm/Context.agent : Lorg/nlogo/agent/Agent;
          ICONST_5
          ALOAD 2
          INVOKEVIRTUAL org/nlogo/agent/Agent.setPatchVariable (ILjava/lang/Object;)V
         L6
          GOTO L12
         L7
         FRAME FULL [org/nlogo/prim/_asm_procedurego_setpatchvariable_15 org/nlogo/nvm/Context java/lang/Double T D] [org/nlogo/api/AgentException]
          ASTORE 3
          NEW org/nlogo/nvm/RuntimePrimitiveException
          DUP
          ALOAD 1
          ALOAD 0
          ALOAD 3
          INVOKEVIRTUAL org/nlogo/api/AgentException.getMessage ()Ljava/lang/String;
          INVOKESPECIAL org/nlogo/nvm/RuntimePrimitiveException.<init> (Lorg/nlogo/api/Context;Lorg/nlogo/nvm/Instruction;Ljava/lang/String;)V
          ATHROW
         L12
         FRAME SAME
          ALOAD 1
          BIPUSH 14
          PUTFIELD org/nlogo/nvm/Context.ip : I
         L13
          RETURN
[14]_asm_procedurego_setobservervariable_16 "set total total + 1" Object => void
      _plus "total + 1" double,double => double
        _observervariable:TOTAL "total" => Object
        _constdouble:1.0 "1" => double
          TRYCATCHBLOCK L0 L1 L1 java/lang/ClassCastException
          TRYCATCHBLOCK L2 L3 L4 org/nlogo/api/AgentException
         L5
          ALOAD 1
          GETFIELD org/nlogo/nvm/Context.agent : Lorg/nlogo/agent/Agent;
          ICONST_1
          INVOKEVIRTUAL org/nlogo/agent/Agent.getObserverVariable (I)Ljava/lang/Object;
         L6
          ASTORE 2
         L0
          ALOAD 2
          CHECKCAST java/lang/Double
          INVOKEVIRTUAL java/lang/Double.doubleValue ()D
          GOTO L7
         L1
         FRAME FULL [org/nlogo/prim/_asm_procedurego_setobservervariable_16 org/nlogo/nvm/Context java/lang/Object] [java/lang/ClassCastException]
          POP
          NEW org/nlogo/nvm/ArgumentTypeException
          DUP
          ALOAD 1
          ALOAD 0
          BIPUSH 0
          LDC 1
          ALOAD 2
          INVOKESPECIAL org/nlogo/nvm/ArgumentTypeException.<init> (Lorg/nlogo/nvm/Context;Lorg/nlogo/nvm/Instruction;IILjava/lang/Object;)V
          ATHROW
         L7
         FRAME SAME1 D
          DCONST_1
         L8
          DSTORE 4
          DSTORE 2
          ALOAD 0
          DLOAD 2
          DLOAD 4
          DADD
          INVOKEVIRTUAL org/nlogo/prim/_asm_procedurego_setobservervariable_16.validDouble (D)D
         L9
          DSTORE 2
          NEW java/lang/Double
          DUP
          DLOAD 2
          INVOKESPECIAL java/lang/Double.<init> (D)V
          ASTORE 2
         L2
          ALOAD 1
          GETFIELD org/nlogo/nvm/Context.agent : Lorg/nlogo/agent/Agent;
          ICONST_1
          ALOAD 2
          INVOKEVIRTUAL org/nlogo/agent/Agent.setObserverVariable (ILjava/lang/Object;)V
         L3
          GOTO L10
         L4
         FRAME FULL [org/nlogo/prim/_asm_procedurego_setobservervariable_16 org/nlogo/nvm/Context java/lang/Double T D] [org/nlogo/api/AgentException]
          ASTORE 3
          NEW org/nlogo/nvm/RuntimePrimitiveException
          DUP
          ALOAD 1
          ALOAD 0
          ALOAD 3
          INVOKEVIRTUAL org/nlogo/api/AgentException.getMessage ()Ljava/lang/String;
          INVOKESPECIAL org/nlogo/nvm/RuntimePrimitiveException.<init> (Lorg/nlogo/api/Context;Lorg/nlogo/nvm/Instruction;Ljava/lang/String;)V
          ATHROW
         L10
         FRAME SAME
          ALOAD 1
          BIPUSH 15
          PUTFIELD org/nlogo/nvm/Context.ip : I
         L11
          RETURN
[15]_asm_procedurego_call_17 "colorize"
         L0
          NEW org/nlogo/nvm/Activation
          DUP
          ALOAD 0
          GETFIELD org/nlogo/prim/_asm_procedurego_call_17.kept1_procedure : Lorg/nlogo/nvm/Procedure;
          ALOAD 1
          GETFIELD org/nlogo/nvm/Context.activation : Lorg/nlogo/nvm/Activation;
          BIPUSH 16
          INVOKESPECIAL org/nlogo/nvm/Activation.<init> (Lorg/nlogo/nvm/Procedure;Lorg/nlogo/nvm/Activation;I)V
          ALOAD 1
          SWAP
          PUTFIELD org/nlogo/nvm/Context.activation : Lorg/nlogo/nvm/Activation;
          ALOAD 1
          ICONST_0
          PUTFIELD org/nlogo/nvm/Context.ip : I
         L1
          RETURN
[16]_asm_procedurego_done_18 => void
          // parameter final  context
         L0
          ALOAD 1
          ICONST_1
          PUTFIELD org/nlogo/nvm/Context.finished : Z
         L1
          RETURN
[17]_asm_procedurego_done_19 => void
          // parameter final  context
         L0
          ALOAD 1
          ICONST_1
          PUTFIELD org/nlogo/nvm/Context.finished : Z
         L1
          RETURN
[18]_asm_procedurego_setprocedurevariable_20 "set active-patches patch-set [ neighbors4 ] of overloaded-patches" Object => void
      _patchset "patch-set [ neighbors4 ] of overloaded-patches"
        _of "[ neighbors4 ] of overloaded-patches"
          _asm_procedurego_neighbors4_21 "neighbors4" => AgentSet
               L0
                ALOAD 1
                GETFIELD org/nlogo/nvm/Context.agent : Lorg/nlogo/agent/Agent;
                INSTANCEOF org/nlogo/agent/Turtle
                IFEQ L1
                ALOAD 1
                GETFIELD org/nlogo/nvm/Context.agent : Lorg/nlogo/agent/Agent;
                CHECKCAST org/nlogo/agent/Turtle
                INVOKEVIRTUAL org/nlogo/agent/Turtle.getPatchHere ()Lorg/nlogo/agent/Patch;
                INVOKEVIRTUAL org/nlogo/agent/Patch.getNeighbors4 ()Lorg/nlogo/agent/IndexedAgentSet;
                GOTO L2
               L1
               FRAME SAME
                ALOAD 1
                GETFIELD org/nlogo/nvm/Context.agent : Lorg/nlogo/agent/Agent;
                CHECKCAST org/nlogo/agent/Patch
                INVOKEVIRTUAL org/nlogo/agent/Patch.getNeighbors4 ()Lorg/nlogo/agent/IndexedAgentSet;
               L2
               FRAME SAME1 org/nlogo/agent/IndexedAgentSet
                ARETURN
          _asm_procedurego_procedurevariable_22 "overloaded-patches" => Object
                // parameter final  context
               L0
                ALOAD 1
                GETFIELD org/nlogo/nvm/Context.activation : Lorg/nlogo/nvm/Activation;
                GETFIELD org/nlogo/nvm/Activation.args : [Ljava/lang/Object;
                ICONST_1
                AALOAD
               L1
                ARETURN
          ALOAD 0
          GETFIELD org/nlogo/prim/_asm_procedurego_setprocedurevariable_20.keptinstr2 : Lorg/nlogo/prim/etc/_patchset;
          ALOAD 1
          INVOKEVIRTUAL org/nlogo/prim/etc/_patchset.report (Lorg/nlogo/nvm/Context;)Ljava/lang/Object;
         L0
          ASTORE 2
          ALOAD 1
          GETFIELD org/nlogo/nvm/Context.activation : Lorg/nlogo/nvm/Activation;
          GETFIELD org/nlogo/nvm/Activation.args : [Ljava/lang/Object;
          ICONST_0
          ALOAD 2
          AASTORE
          ALOAD 1
          BIPUSH 19
          PUTFIELD org/nlogo/nvm/Context.ip : I
         L1
          RETURN
[19]_asm_procedurego_while_23 "while [ any? active-patches ] let active-patches with [ n > 3 ] ask overloaded-patches set n n - 4 set total total - 4 colorize [ ask neighbors4 set n n + 1 set total total + 1 [ colorize ] ] [ set active-patches patch-set [ neighbors4 ] of overloaded-patches ]" boolean => void
      _any "any? active-patches" AgentSet => boolean
        _procedurevariable:ACTIVE-PATCHES "active-patches" => Object
          // parameter final  context
          TRYCATCHBLOCK L0 L1 L1 java/lang/ClassCastException
         L2
          ALOAD 1
          GETFIELD org/nlogo/nvm/Context.activation : Lorg/nlogo/nvm/Activation;
          GETFIELD org/nlogo/nvm/Activation.args : [Ljava/lang/Object;
          ICONST_0
          AALOAD
         L3
          ASTORE 2
         L0
          ALOAD 2
          CHECKCAST org/nlogo/agent/AgentSet
          GOTO L4
         L1
         FRAME FULL [org/nlogo/prim/_asm_procedurego_while_23 org/nlogo/nvm/Context java/lang/Object] [java/lang/ClassCastException]
          POP
          NEW org/nlogo/nvm/ArgumentTypeException
          DUP
          ALOAD 1
          ALOAD 0
          BIPUSH 0
          LDC 112
          ALOAD 2
          INVOKESPECIAL org/nlogo/nvm/ArgumentTypeException.<init> (Lorg/nlogo/nvm/Context;Lorg/nlogo/nvm/Instruction;IILjava/lang/Object;)V
          ATHROW
         L4
         FRAME SAME1 org/nlogo/agent/AgentSet
          ASTORE 2
          ALOAD 2
          INVOKEVIRTUAL org/nlogo/agent/AgentSet.isEmpty ()Z
          IFNE L5
          ICONST_1
          GOTO L6
         L5
         FRAME FULL [org/nlogo/prim/_asm_procedurego_while_23 org/nlogo/nvm/Context org/nlogo/agent/AgentSet] []
          ICONST_0
         L6
         FRAME SAME1 I
          ISTORE 2
          ALOAD 1
          ILOAD 2
          IFEQ L7
          BIPUSH 7
          GOTO L8
         L7
         FRAME FULL [org/nlogo/prim/_asm_procedurego_while_23 org/nlogo/nvm/Context I] [org/nlogo/nvm/Context]
          BIPUSH 20
         L8
         FRAME FULL [org/nlogo/prim/_asm_procedurego_while_23 org/nlogo/nvm/Context I] [org/nlogo/nvm/Context I]
          PUTFIELD org/nlogo/nvm/Context.ip : I
         L9
          RETURN
[20]_tick "tick"
[21]_asm_procedurego_return_24 => void
         L0
          ALOAD 1
          INVOKEVIRTUAL org/nlogo/nvm/Context.returnFromProcedure ()V
          ALOAD 1
          ICONST_0
          PUTFIELD org/nlogo/nvm/Context.stopping : Z
         L1
          RETURN

procedure SETUP:[]{O---}:
[0]_clearall "clear-all"
[1]_asm_proceduresetup_ask_0 "ask patches set n 2 [ colorize ]" AgentSet => void
      _patches "patches" => AgentSet
          // parameter final  context
         L0
          ALOAD 0
          GETFIELD org/nlogo/prim/_asm_proceduresetup_ask_0.world : Lorg/nlogo/agent/World;
          INVOKEVIRTUAL org/nlogo/agent/World.patches ()Lorg/nlogo/agent/AgentSet;
         L1
          ASTORE 2
          ALOAD 1
          GETFIELD org/nlogo/nvm/Context.agent : Lorg/nlogo/agent/Agent;
          INSTANCEOF org/nlogo/agent/Observer
          IFNE L2
          ALOAD 2
          ALOAD 0
          GETFIELD org/nlogo/prim/_asm_proceduresetup_ask_0.world : Lorg/nlogo/agent/World;
          INVOKEVIRTUAL org/nlogo/agent/World.turtles ()Lorg/nlogo/agent/TreeAgentSet;
          IF_ACMPNE L3
          NEW org/nlogo/nvm/RuntimePrimitiveException
          DUP
          ALOAD 1
          ALOAD 0
          INVOKESTATIC org/nlogo/core/I18N.errorsJ ()Lorg/nlogo/core/I18NJava;
          LDC "org.nlogo.prim.$common.onlyObserverCanAskAllTurtles"
          INVOKEINTERFACE org/nlogo/core/I18NJava.get (Ljava/lang/String;)Ljava/lang/String;
          INVOKESPECIAL org/nlogo/nvm/RuntimePrimitiveException.<init> (Lorg/nlogo/api/Context;Lorg/nlogo/nvm/Instruction;Ljava/lang/String;)V
          ATHROW
         L3
         FRAME APPEND [org/nlogo/agent/AgentSet]
          ALOAD 2
          ALOAD 0
          GETFIELD org/nlogo/prim/_asm_proceduresetup_ask_0.world : Lorg/nlogo/agent/World;
          INVOKEVIRTUAL org/nlogo/agent/World.patches ()Lorg/nlogo/agent/AgentSet;
          IF_ACMPNE L2
          NEW org/nlogo/nvm/RuntimePrimitiveException
          DUP
          ALOAD 1
          ALOAD 0
          INVOKESTATIC org/nlogo/core/I18N.errorsJ ()Lorg/nlogo/core/I18NJava;
          LDC "org.nlogo.prim.$common.onlyObserverCanAskAllPatches"
          INVOKEINTERFACE org/nlogo/core/I18NJava.get (Ljava/lang/String;)Ljava/lang/String;
          INVOKESPECIAL org/nlogo/nvm/RuntimePrimitiveException.<init> (Lorg/nlogo/api/Context;Lorg/nlogo/nvm/Instruction;Ljava/lang/String;)V
          ATHROW
         L2
         FRAME SAME
          ALOAD 1
          ALOAD 2
          ICONST_2
          INVOKEVIRTUAL org/nlogo/nvm/Context.runExclusiveJob (Lorg/nlogo/agent/AgentSet;I)V
          ALOAD 1
          ICONST_5
          PUTFIELD org/nlogo/nvm/Context.ip : I
         L4
          RETURN
[2]_asm_proceduresetup_setpatchvariable_1 "set n 2" Object => void
      _constdouble:2.0 "2" => Double
          TRYCATCHBLOCK L0 L1 L2 org/nlogo/api/AgentException
         L3
          ALOAD 0
          GETFIELD org/nlogo/prim/_asm_proceduresetup_setpatchvariable_1.kept2_value : Ljava/lang/Double;
         L4
          ASTORE 2
         L0
          ALOAD 1
          GETFIELD org/nlogo/nvm/Context.agent : Lorg/nlogo/agent/Agent;
          ICONST_5
          ALOAD 2
          INVOKEVIRTUAL org/nlogo/agent/Agent.setPatchVariable (ILjava/lang/Object;)V
         L1
          GOTO L5
         L2
         FRAME FULL [org/nlogo/prim/_asm_proceduresetup_setpatchvariable_1 org/nlogo/nvm/Context java/lang/Double] [org/nlogo/api/AgentException]
          ASTORE 3
          NEW org/nlogo/nvm/RuntimePrimitiveException
          DUP
          ALOAD 1
          ALOAD 0
          ALOAD 3
          INVOKEVIRTUAL org/nlogo/api/AgentException.getMessage ()Ljava/lang/String;
          INVOKESPECIAL org/nlogo/nvm/RuntimePrimitiveException.<init> (Lorg/nlogo/api/Context;Lorg/nlogo/nvm/Instruction;Ljava/lang/String;)V
          ATHROW
         L5
         FRAME SAME
          ALOAD 1
          ICONST_3
          PUTFIELD org/nlogo/nvm/Context.ip : I
         L6
          RETURN
[3]_asm_proceduresetup_call_2 "colorize"
         L0
          NEW org/nlogo/nvm/Activation
          DUP
          ALOAD 0
          GETFIELD org/nlogo/prim/_asm_proceduresetup_call_2.kept1_procedure : Lorg/nlogo/nvm/Procedure;
          ALOAD 1
          GETFIELD org/nlogo/nvm/Context.activation : Lorg/nlogo/nvm/Activation;
          ICONST_4
          INVOKESPECIAL org/nlogo/nvm/Activation.<init> (Lorg/nlogo/nvm/Procedure;Lorg/nlogo/nvm/Activation;I)V
          ALOAD 1
          SWAP
          PUTFIELD org/nlogo/nvm/Context.activation : Lorg/nlogo/nvm/Activation;
          ALOAD 1
          ICONST_0
          PUTFIELD org/nlogo/nvm/Context.ip : I
         L1
          RETURN
[4]_asm_proceduresetup_done_3 => void
          // parameter final  context
         L0
          ALOAD 1
          ICONST_1
          PUTFIELD org/nlogo/nvm/Context.finished : Z
         L1
          RETURN
[5]_asm_proceduresetup_setobservervariable_4 "set total 2 * count patches" Object => void
      _mult "2 * count patches" double,double => double
        _constdouble:2.0 "2" => double
        _count "count patches" AgentSet => double
          _patches "patches" => AgentSet
          // parameter final  context
          TRYCATCHBLOCK L0 L1 L2 org/nlogo/api/AgentException
         L3
          LDC 2.0
         L4
          ALOAD 0
          GETFIELD org/nlogo/prim/_asm_proceduresetup_setobservervariable_4.world : Lorg/nlogo/agent/World;
          INVOKEVIRTUAL org/nlogo/agent/World.patches ()Lorg/nlogo/agent/AgentSet;
         L5
          ASTORE 2
          ALOAD 2
          INVOKEVIRTUAL org/nlogo/agent/AgentSet.count ()I
          I2D
         L6
          DSTORE 4
          DSTORE 2
          ALOAD 0
          DLOAD 2
          DLOAD 4
          DMUL
          INVOKEVIRTUAL org/nlogo/prim/_asm_proceduresetup_setobservervariable_4.validDouble (D)D
         L7
          DSTORE 2
          NEW java/lang/Double
          DUP
          DLOAD 2
          INVOKESPECIAL java/lang/Double.<init> (D)V
          ASTORE 2
         L0
          ALOAD 1
          GETFIELD org/nlogo/nvm/Context.agent : Lorg/nlogo/agent/Agent;
          ICONST_1
          ALOAD 2
          INVOKEVIRTUAL org/nlogo/agent/Agent.setObserverVariable (ILjava/lang/Object;)V
         L1
          GOTO L8
         L2
         FRAME FULL [org/nlogo/prim/_asm_proceduresetup_setobservervariable_4 org/nlogo/nvm/Context java/lang/Double T D] [org/nlogo/api/AgentException]
          ASTORE 3
          NEW org/nlogo/nvm/RuntimePrimitiveException
          DUP
          ALOAD 1
          ALOAD 0
          ALOAD 3
          INVOKEVIRTUAL org/nlogo/api/AgentException.getMessage ()Ljava/lang/String;
          INVOKESPECIAL org/nlogo/nvm/RuntimePrimitiveException.<init> (Lorg/nlogo/api/Context;Lorg/nlogo/nvm/Instruction;Ljava/lang/String;)V
          ATHROW
         L8
         FRAME SAME
          ALOAD 1
          BIPUSH 6
          PUTFIELD org/nlogo/nvm/Context.ip : I
         L9
          RETURN
[6]_resetticks "reset-ticks"
[7]_asm_proceduresetup_return_5 => void
         L0
          ALOAD 1
          INVOKEVIRTUAL org/nlogo/nvm/Context.returnFromProcedure ()V
          ALOAD 1
          ICONST_0
          PUTFIELD org/nlogo/nvm/Context.stopping : Z
         L1
          RETURN

