globals [TERRAIN-SMOOTHNESS RAINFALL BUMPY? SOIL-HARDNESS HILL? RESULT SHOW-WATER? DRAINS LAND]
interfaceGlobals [terrain-smoothness rainfall bumpy? soil-hardness hill?]
turtles-own [WHO COLOR HEADING XCOR YCOR SHAPE LABEL LABEL-COLOR BREED HIDDEN? SIZE PEN-SIZE PEN-MODE]
patches-own [PXCOR PYCOR PCOLOR PLABEL PLABEL-COLOR ELEVATION WATER DRAIN?]
links-own [END1 END2 COLOR LABEL LABEL-COLOR HIDDEN? BREED THICKNESS SHAPE TIE-MODE]
breeds 
link-breeds 

procedure GO:[]{O---}:
[0]_asm_procedurego_ask_0 "ask land [ if random-float 1.0 < rainfall [ set water water + 1 ] ]" Object => void
      _observervariable:LAND "land" => Object
         L0
          ALOAD 1
          GETFIELD org/nlogo/nvm/Context.agent : Lorg/nlogo/agent/Agent;
          BIPUSH 8
          INVOKEVIRTUAL org/nlogo/agent/Agent.getObserverVariable (I)Ljava/lang/Object;
         L1
          ASTORE 2
          ALOAD 2
          INSTANCEOF org/nlogo/agent/AgentSet
          IFEQ L2
          ALOAD 2
          CHECKCAST org/nlogo/agent/AgentSet
          ASTORE 3
          ALOAD 1
          GETFIELD org/nlogo/nvm/Context.agent : Lorg/nlogo/agent/Agent;
          INSTANCEOF org/nlogo/agent/Observer
          IFNE L3
          ALOAD 3
          ALOAD 0
          GETFIELD org/nlogo/prim/_asm_procedurego_ask_0.world : Lorg/nlogo/agent/World;
          INVOKEVIRTUAL org/nlogo/agent/World.turtles ()Lorg/nlogo/agent/AgentSet;
          IF_ACMPNE L4
          NEW org/nlogo/nvm/EngineException
          DUP
          ALOAD 1
          ALOAD 0
          INVOKESTATIC org/nlogo/core/I18N.errorsJ ()Lorg/nlogo/core/I18NJava;
          LDC "org.nlogo.prim.$common.onlyObserverCanAskAllTurtles"
          INVOKEINTERFACE org/nlogo/core/I18NJava.get (Ljava/lang/String;)Ljava/lang/String;
          INVOKESPECIAL org/nlogo/nvm/EngineException.<init> (Lorg/nlogo/nvm/Context;Lorg/nlogo/nvm/Instruction;Ljava/lang/String;)V
          ATHROW
         L4
         FRAME APPEND [java/lang/Object org/nlogo/agent/AgentSet]
          ALOAD 3
          ALOAD 0
          GETFIELD org/nlogo/prim/_asm_procedurego_ask_0.world : Lorg/nlogo/agent/World;
          INVOKEVIRTUAL org/nlogo/agent/World.patches ()Lorg/nlogo/agent/AgentSet;
          IF_ACMPNE L3
          NEW org/nlogo/nvm/EngineException
          DUP
          ALOAD 1
          ALOAD 0
          INVOKESTATIC org/nlogo/core/I18N.errorsJ ()Lorg/nlogo/core/I18NJava;
          LDC "org.nlogo.prim.$common.onlyObserverCanAskAllPatches"
          INVOKEINTERFACE org/nlogo/core/I18NJava.get (Ljava/lang/String;)Ljava/lang/String;
          INVOKESPECIAL org/nlogo/nvm/EngineException.<init> (Lorg/nlogo/nvm/Context;Lorg/nlogo/nvm/Instruction;Ljava/lang/String;)V
          ATHROW
         L2
         FRAME CHOP 1
          ALOAD 2
          INSTANCEOF org/nlogo/agent/Agent
          IFEQ L5
          ALOAD 2
          CHECKCAST org/nlogo/agent/Agent
          ASTORE 4
          ALOAD 4
          GETFIELD org/nlogo/agent/Agent.id : J
          LDC -1
          LCMP
          IFNE L6
          NEW org/nlogo/nvm/EngineException
          DUP
          ALOAD 1
          ALOAD 0
          INVOKESTATIC org/nlogo/core/I18N.errorsJ ()Lorg/nlogo/core/I18NJava;
          LDC "org.nlogo.$common.thatAgentIsDead"
          ICONST_1
          ANEWARRAY java/lang/Object
          DUP
          ICONST_0
          ALOAD 4
          INVOKEVIRTUAL org/nlogo/agent/Agent.classDisplayName ()Ljava/lang/String;
          AASTORE
          INVOKEINTERFACE org/nlogo/core/I18NJava.getN (Ljava/lang/String;[Ljava/lang/Object;)Ljava/lang/String;
          INVOKESPECIAL org/nlogo/nvm/EngineException.<init> (Lorg/nlogo/nvm/Context;Lorg/nlogo/nvm/Instruction;Ljava/lang/String;)V
          ATHROW
         L6
         FRAME APPEND [T org/nlogo/agent/Agent]
          NEW org/nlogo/agent/ArrayAgentSet
          DUP
          ALOAD 4
          INVOKEVIRTUAL org/nlogo/agent/Agent.kind ()Lorg/nlogo/core/AgentKind;
          ICONST_1
          ICONST_0
          INVOKESPECIAL org/nlogo/agent/ArrayAgentSet.<init> (Lorg/nlogo/core/AgentKind;IZ)V
          ASTORE 3
          ALOAD 3
          ALOAD 4
          INVOKEVIRTUAL org/nlogo/agent/AgentSet.add (Lorg/nlogo/agent/Agent;)V
          GOTO L3
         L5
         FRAME CHOP 2
          NEW org/nlogo/nvm/ArgumentTypeException
          DUP
          ALOAD 1
          ALOAD 0
          ICONST_0
          INVOKESTATIC org/nlogo/core/Syntax.AgentsetType ()I
          INVOKESTATIC org/nlogo/core/Syntax.AgentType ()I
          IOR
          ALOAD 2
          INVOKESPECIAL org/nlogo/nvm/ArgumentTypeException.<init> (Lorg/nlogo/nvm/Context;Lorg/nlogo/nvm/Instruction;IILjava/lang/Object;)V
          ATHROW
         L3
         FRAME APPEND [org/nlogo/agent/AgentSet]
          ALOAD 1
          ALOAD 3
          ICONST_1
          INVOKEVIRTUAL org/nlogo/nvm/Context.runExclusiveJob (Lorg/nlogo/agent/AgentSet;I)V
          ALOAD 1
          ICONST_4
          PUTFIELD org/nlogo/nvm/Context.ip : I
         L7
          RETURN
[1]_asm_procedurego_if_1 "if random-float 1.0 < rainfall [ set water water + 1 ]" boolean => void
      _lessthan "random-float 1.0 < rainfall" double,Object => boolean
        _randomfloat "random-float 1.0" double => double
          _constdouble:1.0 "1.0" => double
        _observervariable:RAINFALL "rainfall" => Object
         L0
          DCONST_1
         L1
          DSTORE 2
          ALOAD 0
          DLOAD 2
          ALOAD 1
          GETFIELD org/nlogo/nvm/Context.job : Lorg/nlogo/nvm/Job;
          GETFIELD org/nlogo/nvm/Job.random : Lorg/nlogo/api/MersenneTwisterFast;
          INVOKEVIRTUAL org/nlogo/api/MersenneTwisterFast.nextDouble ()D
          DMUL
          INVOKEVIRTUAL org/nlogo/prim/_asm_procedurego_if_1.validDouble (D)D
         L2
          ALOAD 1
          GETFIELD org/nlogo/nvm/Context.agent : Lorg/nlogo/agent/Agent;
          ICONST_1
          INVOKEVIRTUAL org/nlogo/agent/Agent.getObserverVariable (I)Ljava/lang/Object;
         L3
          ASTORE 4
          DSTORE 2
          ALOAD 4
          INSTANCEOF java/lang/Double
          IFEQ L4
          DLOAD 2
          ALOAD 4
          CHECKCAST java/lang/Double
          INVOKEVIRTUAL java/lang/Double.doubleValue ()D
          DCMPG
          IFGE L5
          ICONST_1
          GOTO L6
         L5
         FRAME APPEND [D java/lang/Object]
          ICONST_0
         L6
         FRAME SAME1 I
          GOTO L7
         L4
         FRAME SAME
          NEW org/nlogo/nvm/EngineException
          DUP
          ALOAD 1
          ALOAD 0
          INVOKESTATIC org/nlogo/core/I18N.errorsJ ()Lorg/nlogo/core/I18NJava;
          LDC "org.nlogo.prim._lessthan.cantUseLessthanOnDifferentArgs"
          ICONST_2
          ANEWARRAY java/lang/Object
          DUP
          ICONST_0
          DLOAD 2
          INVOKESTATIC java/lang/Double.valueOf (D)Ljava/lang/Double;
          INVOKESTATIC org/nlogo/api/TypeNames.aName (Ljava/lang/Object;)Ljava/lang/String;
          AASTORE
          DUP
          ICONST_1
          ALOAD 4
          INVOKESTATIC org/nlogo/api/TypeNames.aName (Ljava/lang/Object;)Ljava/lang/String;
          AASTORE
          INVOKEINTERFACE org/nlogo/core/I18NJava.getN (Ljava/lang/String;[Ljava/lang/Object;)Ljava/lang/String;
          INVOKESPECIAL org/nlogo/nvm/EngineException.<init> (Lorg/nlogo/nvm/Context;Lorg/nlogo/nvm/Instruction;Ljava/lang/String;)V
          ATHROW
         L7
         FRAME SAME1 I
          ISTORE 2
          ALOAD 1
          ILOAD 2
          IFEQ L8
          ICONST_2
          GOTO L9
         L8
         FRAME FULL [org/nlogo/prim/_asm_procedurego_if_1 org/nlogo/nvm/Context I T java/lang/Object] [org/nlogo/nvm/Context]
          ICONST_3
         L9
         FRAME FULL [org/nlogo/prim/_asm_procedurego_if_1 org/nlogo/nvm/Context I T java/lang/Object] [org/nlogo/nvm/Context I]
          PUTFIELD org/nlogo/nvm/Context.ip : I
         L10
          RETURN
[2]_asm_procedurego_setpatchvariable_2 "set water water + 1" Object => void
      _plus "water + 1" double,double => double
        _patchvariable:WATER "water" => Object
        _constdouble:1.0 "1" => double
          TRYCATCHBLOCK L0 L1 L2 org/nlogo/api/AgentException
          TRYCATCHBLOCK L3 L4 L4 java/lang/ClassCastException
          TRYCATCHBLOCK L5 L6 L7 org/nlogo/api/AgentException
         L0
          ALOAD 1
          GETFIELD org/nlogo/nvm/Context.agent : Lorg/nlogo/agent/Agent;
          BIPUSH 6
          INVOKEVIRTUAL org/nlogo/agent/Agent.getPatchVariable (I)Ljava/lang/Object;
         L1
          GOTO L8
         L2
         FRAME SAME1 org/nlogo/api/AgentException
          ASTORE 2
          NEW org/nlogo/nvm/EngineException
          DUP
          ALOAD 1
          ALOAD 0
          ALOAD 2
          INVOKEVIRTUAL org/nlogo/api/AgentException.getMessage ()Ljava/lang/String;
          INVOKESPECIAL org/nlogo/nvm/EngineException.<init> (Lorg/nlogo/nvm/Context;Lorg/nlogo/nvm/Instruction;Ljava/lang/String;)V
          ATHROW
         L8
         FRAME SAME1 java/lang/Object
          ASTORE 2
         L3
          ALOAD 2
          CHECKCAST java/lang/Double
          INVOKEVIRTUAL java/lang/Double.doubleValue ()D
          GOTO L9
         L4
         FRAME FULL [org/nlogo/prim/_asm_procedurego_setpatchvariable_2 org/nlogo/nvm/Context java/lang/Object] [java/lang/ClassCastException]
          POP
          NEW org/nlogo/nvm/ArgumentTypeException
          DUP
          ALOAD 1
          ALOAD 0
          BIPUSH 0
          LDC 1
          ALOAD 2
          INVOKESPECIAL org/nlogo/nvm/ArgumentTypeException.<init> (Lorg/nlogo/nvm/Context;Lorg/nlogo/nvm/Instruction;IILjava/lang/Object;)V
          ATHROW
         L9
         FRAME SAME1 D
          DCONST_1
         L10
          DSTORE 4
          DSTORE 2
          ALOAD 0
          DLOAD 2
          DLOAD 4
          DADD
          INVOKEVIRTUAL org/nlogo/prim/_asm_procedurego_setpatchvariable_2.validDouble (D)D
         L11
          DSTORE 2
          NEW java/lang/Double
          DUP
          DLOAD 2
          INVOKESPECIAL java/lang/Double.<init> (D)V
          ASTORE 2
         L5
          ALOAD 1
          GETFIELD org/nlogo/nvm/Context.agent : Lorg/nlogo/agent/Agent;
          BIPUSH 6
          ALOAD 2
          INVOKEVIRTUAL org/nlogo/agent/Agent.setPatchVariable (ILjava/lang/Object;)V
         L6
          GOTO L12
         L7
         FRAME FULL [org/nlogo/prim/_asm_procedurego_setpatchvariable_2 org/nlogo/nvm/Context java/lang/Double T D] [org/nlogo/api/AgentException]
          ASTORE 3
          NEW org/nlogo/nvm/EngineException
          DUP
          ALOAD 1
          ALOAD 0
          ALOAD 3
          INVOKEVIRTUAL org/nlogo/api/AgentException.getMessage ()Ljava/lang/String;
          INVOKESPECIAL org/nlogo/nvm/EngineException.<init> (Lorg/nlogo/nvm/Context;Lorg/nlogo/nvm/Instruction;Ljava/lang/String;)V
          ATHROW
         L12
         FRAME SAME
          ALOAD 1
          ICONST_3
          PUTFIELD org/nlogo/nvm/Context.ip : I
         L13
          RETURN
[3]_asm_procedurego_done_3 => void
         L0
          ALOAD 1
          ICONST_1
          PUTFIELD org/nlogo/nvm/Context.finished : Z
         L1
          RETURN
[4]_asm_procedurego_ask_4 "ask land [ if water > 0 [ flow ] ]" Object => void
      _observervariable:LAND "land" => Object
         L0
          ALOAD 1
          GETFIELD org/nlogo/nvm/Context.agent : Lorg/nlogo/agent/Agent;
          BIPUSH 8
          INVOKEVIRTUAL org/nlogo/agent/Agent.getObserverVariable (I)Ljava/lang/Object;
         L1
          ASTORE 2
          ALOAD 2
          INSTANCEOF org/nlogo/agent/AgentSet
          IFEQ L2
          ALOAD 2
          CHECKCAST org/nlogo/agent/AgentSet
          ASTORE 3
          ALOAD 1
          GETFIELD org/nlogo/nvm/Context.agent : Lorg/nlogo/agent/Agent;
          INSTANCEOF org/nlogo/agent/Observer
          IFNE L3
          ALOAD 3
          ALOAD 0
          GETFIELD org/nlogo/prim/_asm_procedurego_ask_4.world : Lorg/nlogo/agent/World;
          INVOKEVIRTUAL org/nlogo/agent/World.turtles ()Lorg/nlogo/agent/AgentSet;
          IF_ACMPNE L4
          NEW org/nlogo/nvm/EngineException
          DUP
          ALOAD 1
          ALOAD 0
          INVOKESTATIC org/nlogo/core/I18N.errorsJ ()Lorg/nlogo/core/I18NJava;
          LDC "org.nlogo.prim.$common.onlyObserverCanAskAllTurtles"
          INVOKEINTERFACE org/nlogo/core/I18NJava.get (Ljava/lang/String;)Ljava/lang/String;
          INVOKESPECIAL org/nlogo/nvm/EngineException.<init> (Lorg/nlogo/nvm/Context;Lorg/nlogo/nvm/Instruction;Ljava/lang/String;)V
          ATHROW
         L4
         FRAME APPEND [java/lang/Object org/nlogo/agent/AgentSet]
          ALOAD 3
          ALOAD 0
          GETFIELD org/nlogo/prim/_asm_procedurego_ask_4.world : Lorg/nlogo/agent/World;
          INVOKEVIRTUAL org/nlogo/agent/World.patches ()Lorg/nlogo/agent/AgentSet;
          IF_ACMPNE L3
          NEW org/nlogo/nvm/EngineException
          DUP
          ALOAD 1
          ALOAD 0
          INVOKESTATIC org/nlogo/core/I18N.errorsJ ()Lorg/nlogo/core/I18NJava;
          LDC "org.nlogo.prim.$common.onlyObserverCanAskAllPatches"
          INVOKEINTERFACE org/nlogo/core/I18NJava.get (Ljava/lang/String;)Ljava/lang/String;
          INVOKESPECIAL org/nlogo/nvm/EngineException.<init> (Lorg/nlogo/nvm/Context;Lorg/nlogo/nvm/Instruction;Ljava/lang/String;)V
          ATHROW
         L2
         FRAME CHOP 1
          ALOAD 2
          INSTANCEOF org/nlogo/agent/Agent
          IFEQ L5
          ALOAD 2
          CHECKCAST org/nlogo/agent/Agent
          ASTORE 4
          ALOAD 4
          GETFIELD org/nlogo/agent/Agent.id : J
          LDC -1
          LCMP
          IFNE L6
          NEW org/nlogo/nvm/EngineException
          DUP
          ALOAD 1
          ALOAD 0
          INVOKESTATIC org/nlogo/core/I18N.errorsJ ()Lorg/nlogo/core/I18NJava;
          LDC "org.nlogo.$common.thatAgentIsDead"
          ICONST_1
          ANEWARRAY java/lang/Object
          DUP
          ICONST_0
          ALOAD 4
          INVOKEVIRTUAL org/nlogo/agent/Agent.classDisplayName ()Ljava/lang/String;
          AASTORE
          INVOKEINTERFACE org/nlogo/core/I18NJava.getN (Ljava/lang/String;[Ljava/lang/Object;)Ljava/lang/String;
          INVOKESPECIAL org/nlogo/nvm/EngineException.<init> (Lorg/nlogo/nvm/Context;Lorg/nlogo/nvm/Instruction;Ljava/lang/String;)V
          ATHROW
         L6
         FRAME APPEND [T org/nlogo/agent/Agent]
          NEW org/nlogo/agent/ArrayAgentSet
          DUP
          ALOAD 4
          INVOKEVIRTUAL org/nlogo/agent/Agent.kind ()Lorg/nlogo/core/AgentKind;
          ICONST_1
          ICONST_0
          INVOKESPECIAL org/nlogo/agent/ArrayAgentSet.<init> (Lorg/nlogo/core/AgentKind;IZ)V
          ASTORE 3
          ALOAD 3
          ALOAD 4
          INVOKEVIRTUAL org/nlogo/agent/AgentSet.add (Lorg/nlogo/agent/Agent;)V
          GOTO L3
         L5
         FRAME CHOP 2
          NEW org/nlogo/nvm/ArgumentTypeException
          DUP
          ALOAD 1
          ALOAD 0
          ICONST_0
          INVOKESTATIC org/nlogo/core/Syntax.AgentsetType ()I
          INVOKESTATIC org/nlogo/core/Syntax.AgentType ()I
          IOR
          ALOAD 2
          INVOKESPECIAL org/nlogo/nvm/ArgumentTypeException.<init> (Lorg/nlogo/nvm/Context;Lorg/nlogo/nvm/Instruction;IILjava/lang/Object;)V
          ATHROW
         L3
         FRAME APPEND [org/nlogo/agent/AgentSet]
          ALOAD 1
          ALOAD 3
          ICONST_5
          INVOKEVIRTUAL org/nlogo/nvm/Context.runExclusiveJob (Lorg/nlogo/agent/AgentSet;I)V
          ALOAD 1
          BIPUSH 8
          PUTFIELD org/nlogo/nvm/Context.ip : I
         L7
          RETURN
[5]_asm_procedurego_if_5 "if water > 0 [ flow ]" boolean => void
      _greaterthan "water > 0" Object,double => boolean
        _patchvariable:WATER "water" => Object
        _constdouble:0.0 "0" => double
          TRYCATCHBLOCK L0 L1 L2 org/nlogo/api/AgentException
         L0
          ALOAD 1
          GETFIELD org/nlogo/nvm/Context.agent : Lorg/nlogo/agent/Agent;
          BIPUSH 6
          INVOKEVIRTUAL org/nlogo/agent/Agent.getPatchVariable (I)Ljava/lang/Object;
         L1
          GOTO L3
         L2
         FRAME SAME1 org/nlogo/api/AgentException
          ASTORE 2
          NEW org/nlogo/nvm/EngineException
          DUP
          ALOAD 1
          ALOAD 0
          ALOAD 2
          INVOKEVIRTUAL org/nlogo/api/AgentException.getMessage ()Ljava/lang/String;
          INVOKESPECIAL org/nlogo/nvm/EngineException.<init> (Lorg/nlogo/nvm/Context;Lorg/nlogo/nvm/Instruction;Ljava/lang/String;)V
          ATHROW
         L3
         FRAME SAME1 java/lang/Object
          DCONST_0
         L4
          DSTORE 3
          ASTORE 2
          ALOAD 2
          INSTANCEOF java/lang/Double
          IFEQ L5
          ALOAD 2
          CHECKCAST java/lang/Double
          INVOKEVIRTUAL java/lang/Double.doubleValue ()D
          DLOAD 3
          DCMPL
          IFLE L6
          ICONST_1
          GOTO L7
         L6
         FRAME APPEND [java/lang/Object D]
          ICONST_0
         L7
         FRAME SAME1 I
          GOTO L8
         L5
         FRAME SAME
          NEW org/nlogo/nvm/EngineException
          DUP
          ALOAD 1
          ALOAD 0
          INVOKESTATIC org/nlogo/core/I18N.errorsJ ()Lorg/nlogo/core/I18NJava;
          LDC "org.nlogo.prim._greaterthan.cannotCompareParameters"
          ICONST_2
          ANEWARRAY java/lang/Object
          DUP
          ICONST_0
          ALOAD 2
          INVOKESTATIC org/nlogo/api/TypeNames.aName (Ljava/lang/Object;)Ljava/lang/String;
          AASTORE
          DUP
          ICONST_1
          DLOAD 3
          INVOKESTATIC java/lang/Double.valueOf (D)Ljava/lang/Double;
          INVOKESTATIC org/nlogo/api/TypeNames.aName (Ljava/lang/Object;)Ljava/lang/String;
          AASTORE
          INVOKEINTERFACE org/nlogo/core/I18NJava.getN (Ljava/lang/String;[Ljava/lang/Object;)Ljava/lang/String;
          INVOKESPECIAL org/nlogo/nvm/EngineException.<init> (Lorg/nlogo/nvm/Context;Lorg/nlogo/nvm/Instruction;Ljava/lang/String;)V
          ATHROW
         L8
         FRAME SAME1 I
          ISTORE 2
          ALOAD 1
          ILOAD 2
          IFEQ L9
          BIPUSH 6
          GOTO L10
         L9
         FRAME FULL [org/nlogo/prim/_asm_procedurego_if_5 org/nlogo/nvm/Context I D] [org/nlogo/nvm/Context]
          BIPUSH 7
         L10
         FRAME FULL [org/nlogo/prim/_asm_procedurego_if_5 org/nlogo/nvm/Context I D] [org/nlogo/nvm/Context I]
          PUTFIELD org/nlogo/nvm/Context.ip : I
         L11
          RETURN
[6]_asm_procedurego_call_6 "flow"
         L0
          NEW org/nlogo/nvm/Activation
          DUP
          ALOAD 0
          GETFIELD org/nlogo/prim/_asm_procedurego_call_6.kept1_procedure : Lorg/nlogo/nvm/Procedure;
          ALOAD 1
          GETFIELD org/nlogo/nvm/Context.activation : Lorg/nlogo/nvm/Activation;
          BIPUSH 7
          INVOKESPECIAL org/nlogo/nvm/Activation.<init> (Lorg/nlogo/nvm/Procedure;Lorg/nlogo/nvm/Activation;I)V
          ALOAD 1
          SWAP
          PUTFIELD org/nlogo/nvm/Context.activation : Lorg/nlogo/nvm/Activation;
          ALOAD 1
          ICONST_0
          PUTFIELD org/nlogo/nvm/Context.ip : I
         L1
          RETURN
[7]_asm_procedurego_done_7 => void
         L0
          ALOAD 1
          ICONST_1
          PUTFIELD org/nlogo/nvm/Context.finished : Z
         L1
          RETURN
[8]_asm_procedurego_ask_8 "ask drains set water 0 [ set elevation -10000000 ]" Object => void
      _observervariable:DRAINS "drains" => Object
         L0
          ALOAD 1
          GETFIELD org/nlogo/nvm/Context.agent : Lorg/nlogo/agent/Agent;
          BIPUSH 7
          INVOKEVIRTUAL org/nlogo/agent/Agent.getObserverVariable (I)Ljava/lang/Object;
         L1
          ASTORE 2
          ALOAD 2
          INSTANCEOF org/nlogo/agent/AgentSet
          IFEQ L2
          ALOAD 2
          CHECKCAST org/nlogo/agent/AgentSet
          ASTORE 3
          ALOAD 1
          GETFIELD org/nlogo/nvm/Context.agent : Lorg/nlogo/agent/Agent;
          INSTANCEOF org/nlogo/agent/Observer
          IFNE L3
          ALOAD 3
          ALOAD 0
          GETFIELD org/nlogo/prim/_asm_procedurego_ask_8.world : Lorg/nlogo/agent/World;
          INVOKEVIRTUAL org/nlogo/agent/World.turtles ()Lorg/nlogo/agent/AgentSet;
          IF_ACMPNE L4
          NEW org/nlogo/nvm/EngineException
          DUP
          ALOAD 1
          ALOAD 0
          INVOKESTATIC org/nlogo/core/I18N.errorsJ ()Lorg/nlogo/core/I18NJava;
          LDC "org.nlogo.prim.$common.onlyObserverCanAskAllTurtles"
          INVOKEINTERFACE org/nlogo/core/I18NJava.get (Ljava/lang/String;)Ljava/lang/String;
          INVOKESPECIAL org/nlogo/nvm/EngineException.<init> (Lorg/nlogo/nvm/Context;Lorg/nlogo/nvm/Instruction;Ljava/lang/String;)V
          ATHROW
         L4
         FRAME APPEND [java/lang/Object org/nlogo/agent/AgentSet]
          ALOAD 3
          ALOAD 0
          GETFIELD org/nlogo/prim/_asm_procedurego_ask_8.world : Lorg/nlogo/agent/World;
          INVOKEVIRTUAL org/nlogo/agent/World.patches ()Lorg/nlogo/agent/AgentSet;
          IF_ACMPNE L3
          NEW org/nlogo/nvm/EngineException
          DUP
          ALOAD 1
          ALOAD 0
          INVOKESTATIC org/nlogo/core/I18N.errorsJ ()Lorg/nlogo/core/I18NJava;
          LDC "org.nlogo.prim.$common.onlyObserverCanAskAllPatches"
          INVOKEINTERFACE org/nlogo/core/I18NJava.get (Ljava/lang/String;)Ljava/lang/String;
          INVOKESPECIAL org/nlogo/nvm/EngineException.<init> (Lorg/nlogo/nvm/Context;Lorg/nlogo/nvm/Instruction;Ljava/lang/String;)V
          ATHROW
         L2
         FRAME CHOP 1
          ALOAD 2
          INSTANCEOF org/nlogo/agent/Agent
          IFEQ L5
          ALOAD 2
          CHECKCAST org/nlogo/agent/Agent
          ASTORE 4
          ALOAD 4
          GETFIELD org/nlogo/agent/Agent.id : J
          LDC -1
          LCMP
          IFNE L6
          NEW org/nlogo/nvm/EngineException
          DUP
          ALOAD 1
          ALOAD 0
          INVOKESTATIC org/nlogo/core/I18N.errorsJ ()Lorg/nlogo/core/I18NJava;
          LDC "org.nlogo.$common.thatAgentIsDead"
          ICONST_1
          ANEWARRAY java/lang/Object
          DUP
          ICONST_0
          ALOAD 4
          INVOKEVIRTUAL org/nlogo/agent/Agent.classDisplayName ()Ljava/lang/String;
          AASTORE
          INVOKEINTERFACE org/nlogo/core/I18NJava.getN (Ljava/lang/String;[Ljava/lang/Object;)Ljava/lang/String;
          INVOKESPECIAL org/nlogo/nvm/EngineException.<init> (Lorg/nlogo/nvm/Context;Lorg/nlogo/nvm/Instruction;Ljava/lang/String;)V
          ATHROW
         L6
         FRAME APPEND [T org/nlogo/agent/Agent]
          NEW org/nlogo/agent/ArrayAgentSet
          DUP
          ALOAD 4
          INVOKEVIRTUAL org/nlogo/agent/Agent.kind ()Lorg/nlogo/core/AgentKind;
          ICONST_1
          ICONST_0
          INVOKESPECIAL org/nlogo/agent/ArrayAgentSet.<init> (Lorg/nlogo/core/AgentKind;IZ)V
          ASTORE 3
          ALOAD 3
          ALOAD 4
          INVOKEVIRTUAL org/nlogo/agent/AgentSet.add (Lorg/nlogo/agent/Agent;)V
          GOTO L3
         L5
         FRAME CHOP 2
          NEW org/nlogo/nvm/ArgumentTypeException
          DUP
          ALOAD 1
          ALOAD 0
          ICONST_0
          INVOKESTATIC org/nlogo/core/Syntax.AgentsetType ()I
          INVOKESTATIC org/nlogo/core/Syntax.AgentType ()I
          IOR
          ALOAD 2
          INVOKESPECIAL org/nlogo/nvm/ArgumentTypeException.<init> (Lorg/nlogo/nvm/Context;Lorg/nlogo/nvm/Instruction;IILjava/lang/Object;)V
          ATHROW
         L3
         FRAME APPEND [org/nlogo/agent/AgentSet]
          ALOAD 1
          ALOAD 3
          BIPUSH 9
          INVOKEVIRTUAL org/nlogo/nvm/Context.runExclusiveJob (Lorg/nlogo/agent/AgentSet;I)V
          ALOAD 1
          BIPUSH 12
          PUTFIELD org/nlogo/nvm/Context.ip : I
         L7
          RETURN
[9]_asm_procedurego_setpatchvariable_9 "set water 0" Object => void
      _constdouble:0.0 "0" => Double
          TRYCATCHBLOCK L0 L1 L2 org/nlogo/api/AgentException
         L3
          ALOAD 0
          GETFIELD org/nlogo/prim/_asm_procedurego_setpatchvariable_9.kept2_value : Ljava/lang/Double;
         L4
          ASTORE 2
         L0
          ALOAD 1
          GETFIELD org/nlogo/nvm/Context.agent : Lorg/nlogo/agent/Agent;
          BIPUSH 6
          ALOAD 2
          INVOKEVIRTUAL org/nlogo/agent/Agent.setPatchVariable (ILjava/lang/Object;)V
         L1
          GOTO L5
         L2
         FRAME FULL [org/nlogo/prim/_asm_procedurego_setpatchvariable_9 org/nlogo/nvm/Context java/lang/Double] [org/nlogo/api/AgentException]
          ASTORE 3
          NEW org/nlogo/nvm/EngineException
          DUP
          ALOAD 1
          ALOAD 0
          ALOAD 3
          INVOKEVIRTUAL org/nlogo/api/AgentException.getMessage ()Ljava/lang/String;
          INVOKESPECIAL org/nlogo/nvm/EngineException.<init> (Lorg/nlogo/nvm/Context;Lorg/nlogo/nvm/Instruction;Ljava/lang/String;)V
          ATHROW
         L5
         FRAME SAME
          ALOAD 1
          BIPUSH 10
          PUTFIELD org/nlogo/nvm/Context.ip : I
         L6
          RETURN
[10]_asm_procedurego_setpatchvariable_10 "set elevation -10000000" Object => void
      _constdouble:-1.0E7 "-10000000" => Double
          TRYCATCHBLOCK L0 L1 L2 org/nlogo/api/AgentException
         L3
          ALOAD 0
          GETFIELD org/nlogo/prim/_asm_procedurego_setpatchvariable_10.kept2_value : Ljava/lang/Double;
         L4
          ASTORE 2
         L0
          ALOAD 1
          GETFIELD org/nlogo/nvm/Context.agent : Lorg/nlogo/agent/Agent;
          ICONST_5
          ALOAD 2
          INVOKEVIRTUAL org/nlogo/agent/Agent.setPatchVariable (ILjava/lang/Object;)V
         L1
          GOTO L5
         L2
         FRAME FULL [org/nlogo/prim/_asm_procedurego_setpatchvariable_10 org/nlogo/nvm/Context java/lang/Double] [org/nlogo/api/AgentException]
          ASTORE 3
          NEW org/nlogo/nvm/EngineException
          DUP
          ALOAD 1
          ALOAD 0
          ALOAD 3
          INVOKEVIRTUAL org/nlogo/api/AgentException.getMessage ()Ljava/lang/String;
          INVOKESPECIAL org/nlogo/nvm/EngineException.<init> (Lorg/nlogo/nvm/Context;Lorg/nlogo/nvm/Instruction;Ljava/lang/String;)V
          ATHROW
         L5
         FRAME SAME
          ALOAD 1
          BIPUSH 11
          PUTFIELD org/nlogo/nvm/Context.ip : I
         L6
          RETURN
[11]_asm_procedurego_done_11 => void
         L0
          ALOAD 1
          ICONST_1
          PUTFIELD org/nlogo/nvm/Context.finished : Z
         L1
          RETURN
[12]_asm_procedurego_ask_12 "ask land [ recolor ]" Object => void
      _observervariable:LAND "land" => Object
         L0
          ALOAD 1
          GETFIELD org/nlogo/nvm/Context.agent : Lorg/nlogo/agent/Agent;
          BIPUSH 8
          INVOKEVIRTUAL org/nlogo/agent/Agent.getObserverVariable (I)Ljava/lang/Object;
         L1
          ASTORE 2
          ALOAD 2
          INSTANCEOF org/nlogo/agent/AgentSet
          IFEQ L2
          ALOAD 2
          CHECKCAST org/nlogo/agent/AgentSet
          ASTORE 3
          ALOAD 1
          GETFIELD org/nlogo/nvm/Context.agent : Lorg/nlogo/agent/Agent;
          INSTANCEOF org/nlogo/agent/Observer
          IFNE L3
          ALOAD 3
          ALOAD 0
          GETFIELD org/nlogo/prim/_asm_procedurego_ask_12.world : Lorg/nlogo/agent/World;
          INVOKEVIRTUAL org/nlogo/agent/World.turtles ()Lorg/nlogo/agent/AgentSet;
          IF_ACMPNE L4
          NEW org/nlogo/nvm/EngineException
          DUP
          ALOAD 1
          ALOAD 0
          INVOKESTATIC org/nlogo/core/I18N.errorsJ ()Lorg/nlogo/core/I18NJava;
          LDC "org.nlogo.prim.$common.onlyObserverCanAskAllTurtles"
          INVOKEINTERFACE org/nlogo/core/I18NJava.get (Ljava/lang/String;)Ljava/lang/String;
          INVOKESPECIAL org/nlogo/nvm/EngineException.<init> (Lorg/nlogo/nvm/Context;Lorg/nlogo/nvm/Instruction;Ljava/lang/String;)V
          ATHROW
         L4
         FRAME APPEND [java/lang/Object org/nlogo/agent/AgentSet]
          ALOAD 3
          ALOAD 0
          GETFIELD org/nlogo/prim/_asm_procedurego_ask_12.world : Lorg/nlogo/agent/World;
          INVOKEVIRTUAL org/nlogo/agent/World.patches ()Lorg/nlogo/agent/AgentSet;
          IF_ACMPNE L3
          NEW org/nlogo/nvm/EngineException
          DUP
          ALOAD 1
          ALOAD 0
          INVOKESTATIC org/nlogo/core/I18N.errorsJ ()Lorg/nlogo/core/I18NJava;
          LDC "org.nlogo.prim.$common.onlyObserverCanAskAllPatches"
          INVOKEINTERFACE org/nlogo/core/I18NJava.get (Ljava/lang/String;)Ljava/lang/String;
          INVOKESPECIAL org/nlogo/nvm/EngineException.<init> (Lorg/nlogo/nvm/Context;Lorg/nlogo/nvm/Instruction;Ljava/lang/String;)V
          ATHROW
         L2
         FRAME CHOP 1
          ALOAD 2
          INSTANCEOF org/nlogo/agent/Agent
          IFEQ L5
          ALOAD 2
          CHECKCAST org/nlogo/agent/Agent
          ASTORE 4
          ALOAD 4
          GETFIELD org/nlogo/agent/Agent.id : J
          LDC -1
          LCMP
          IFNE L6
          NEW org/nlogo/nvm/EngineException
          DUP
          ALOAD 1
          ALOAD 0
          INVOKESTATIC org/nlogo/core/I18N.errorsJ ()Lorg/nlogo/core/I18NJava;
          LDC "org.nlogo.$common.thatAgentIsDead"
          ICONST_1
          ANEWARRAY java/lang/Object
          DUP
          ICONST_0
          ALOAD 4
          INVOKEVIRTUAL org/nlogo/agent/Agent.classDisplayName ()Ljava/lang/String;
          AASTORE
          INVOKEINTERFACE org/nlogo/core/I18NJava.getN (Ljava/lang/String;[Ljava/lang/Object;)Ljava/lang/String;
          INVOKESPECIAL org/nlogo/nvm/EngineException.<init> (Lorg/nlogo/nvm/Context;Lorg/nlogo/nvm/Instruction;Ljava/lang/String;)V
          ATHROW
         L6
         FRAME APPEND [T org/nlogo/agent/Agent]
          NEW org/nlogo/agent/ArrayAgentSet
          DUP
          ALOAD 4
          INVOKEVIRTUAL org/nlogo/agent/Agent.kind ()Lorg/nlogo/core/AgentKind;
          ICONST_1
          ICONST_0
          INVOKESPECIAL org/nlogo/agent/ArrayAgentSet.<init> (Lorg/nlogo/core/AgentKind;IZ)V
          ASTORE 3
          ALOAD 3
          ALOAD 4
          INVOKEVIRTUAL org/nlogo/agent/AgentSet.add (Lorg/nlogo/agent/Agent;)V
          GOTO L3
         L5
         FRAME CHOP 2
          NEW org/nlogo/nvm/ArgumentTypeException
          DUP
          ALOAD 1
          ALOAD 0
          ICONST_0
          INVOKESTATIC org/nlogo/core/Syntax.AgentsetType ()I
          INVOKESTATIC org/nlogo/core/Syntax.AgentType ()I
          IOR
          ALOAD 2
          INVOKESPECIAL org/nlogo/nvm/ArgumentTypeException.<init> (Lorg/nlogo/nvm/Context;Lorg/nlogo/nvm/Instruction;IILjava/lang/Object;)V
          ATHROW
         L3
         FRAME APPEND [org/nlogo/agent/AgentSet]
          ALOAD 1
          ALOAD 3
          BIPUSH 13
          INVOKEVIRTUAL org/nlogo/nvm/Context.runExclusiveJob (Lorg/nlogo/agent/AgentSet;I)V
          ALOAD 1
          BIPUSH 15
          PUTFIELD org/nlogo/nvm/Context.ip : I
         L7
          RETURN
[13]_asm_procedurego_call_13 "recolor"
         L0
          NEW org/nlogo/nvm/Activation
          DUP
          ALOAD 0
          GETFIELD org/nlogo/prim/_asm_procedurego_call_13.kept1_procedure : Lorg/nlogo/nvm/Procedure;
          ALOAD 1
          GETFIELD org/nlogo/nvm/Context.activation : Lorg/nlogo/nvm/Activation;
          BIPUSH 14
          INVOKESPECIAL org/nlogo/nvm/Activation.<init> (Lorg/nlogo/nvm/Procedure;Lorg/nlogo/nvm/Activation;I)V
          ALOAD 1
          SWAP
          PUTFIELD org/nlogo/nvm/Context.activation : Lorg/nlogo/nvm/Activation;
          ALOAD 1
          ICONST_0
          PUTFIELD org/nlogo/nvm/Context.ip : I
         L1
          RETURN
[14]_asm_procedurego_done_14 => void
         L0
          ALOAD 1
          ICONST_1
          PUTFIELD org/nlogo/nvm/Context.finished : Z
         L1
          RETURN
[15]_tick "tick"
[16]_asm_procedurego_return_15 => void
         L0
          ALOAD 1
          INVOKEVIRTUAL org/nlogo/nvm/Context.returnFromProcedure ()V
          ALOAD 1
          ICONST_0
          PUTFIELD org/nlogo/nvm/Context.stopping : Z
         L1
          RETURN

procedure RECOLOR:[]{-TP-}:
[0]_asm_procedurerecolor_ifelse_0 "ifelse water = 0 or not show-water? [ set pcolor scale-color white elevation -250 100 ] [ set pcolor scale-color blue min list water 75 100 -10 ]" boolean => void
      _or "water = 0 or not show-water?"
        _equal "water = 0" Object,double => boolean
          _patchvariable:WATER "water" => Object
          _constdouble:0.0 "0" => double
        _not "not show-water?" boolean => boolean
          _observervariable:SHOW-WATER? "show-water?" => Object
          TRYCATCHBLOCK L0 L1 L2 org/nlogo/api/AgentException
          TRYCATCHBLOCK L3 L4 L4 java/lang/ClassCastException
         L0
          ALOAD 1
          GETFIELD org/nlogo/nvm/Context.agent : Lorg/nlogo/agent/Agent;
          BIPUSH 6
          INVOKEVIRTUAL org/nlogo/agent/Agent.getPatchVariable (I)Ljava/lang/Object;
         L1
          GOTO L5
         L2
         FRAME SAME1 org/nlogo/api/AgentException
          ASTORE 2
          NEW org/nlogo/nvm/EngineException
          DUP
          ALOAD 1
          ALOAD 0
          ALOAD 2
          INVOKEVIRTUAL org/nlogo/api/AgentException.getMessage ()Ljava/lang/String;
          INVOKESPECIAL org/nlogo/nvm/EngineException.<init> (Lorg/nlogo/nvm/Context;Lorg/nlogo/nvm/Instruction;Ljava/lang/String;)V
          ATHROW
         L5
         FRAME SAME1 java/lang/Object
          DCONST_0
         L6
          DSTORE 3
          ASTORE 2
          ALOAD 2
          INSTANCEOF java/lang/Double
          IFEQ L7
          DLOAD 3
          ALOAD 2
          CHECKCAST java/lang/Double
          INVOKEVIRTUAL java/lang/Double.doubleValue ()D
          DCMPL
          IFNE L7
          ICONST_1
          GOTO L8
         L7
         FRAME APPEND [java/lang/Object D]
          ICONST_0
         L8
         FRAME SAME1 I
          IFNE L9
         L10
          ALOAD 1
          GETFIELD org/nlogo/nvm/Context.agent : Lorg/nlogo/agent/Agent;
          BIPUSH 6
          INVOKEVIRTUAL org/nlogo/agent/Agent.getObserverVariable (I)Ljava/lang/Object;
         L11
          ASTORE 2
         L3
          ALOAD 2
          CHECKCAST java/lang/Boolean
          INVOKEVIRTUAL java/lang/Boolean.booleanValue ()Z
          GOTO L12
         L4
         FRAME SAME1 java/lang/ClassCastException
          POP
          NEW org/nlogo/nvm/ArgumentTypeException
          DUP
          ALOAD 1
          ALOAD 0
          BIPUSH 0
          LDC 2
          ALOAD 2
          INVOKESPECIAL org/nlogo/nvm/ArgumentTypeException.<init> (Lorg/nlogo/nvm/Context;Lorg/nlogo/nvm/Instruction;IILjava/lang/Object;)V
          ATHROW
         L12
         FRAME SAME1 I
          ISTORE 2
          ILOAD 2
          IFNE L13
          ICONST_1
          GOTO L14
         L13
         FRAME FULL [org/nlogo/prim/_asm_procedurerecolor_ifelse_0 org/nlogo/nvm/Context I D] []
          ICONST_0
         L14
         FRAME SAME1 I
          GOTO L15
         L9
         FRAME FULL [org/nlogo/prim/_asm_procedurerecolor_ifelse_0 org/nlogo/nvm/Context java/lang/Object D] []
          ICONST_1
         L15
         FRAME FULL [org/nlogo/prim/_asm_procedurerecolor_ifelse_0 org/nlogo/nvm/Context T D] [I]
          ISTORE 2
          ALOAD 1
          ILOAD 2
          IFEQ L16
          ICONST_1
          GOTO L17
         L16
         FRAME FULL [org/nlogo/prim/_asm_procedurerecolor_ifelse_0 org/nlogo/nvm/Context I D] [org/nlogo/nvm/Context]
          ICONST_3
         L17
         FRAME FULL [org/nlogo/prim/_asm_procedurerecolor_ifelse_0 org/nlogo/nvm/Context I D] [org/nlogo/nvm/Context I]
          PUTFIELD org/nlogo/nvm/Context.ip : I
         L18
          RETURN
[1]_asm_procedurerecolor_setpatchvariable_1 "set pcolor scale-color white elevation -250 100" Object => void
      _scalecolor "scale-color white elevation -250 100" double,double,double,double => double
        _constdouble:9.9 "white" => double
        _patchvariable:ELEVATION "elevation" => Object
        _constdouble:-250.0 "-250" => double
        _constdouble:100.0 "100" => double
          TRYCATCHBLOCK L0 L1 L2 org/nlogo/api/AgentException
          TRYCATCHBLOCK L3 L4 L4 java/lang/ClassCastException
          TRYCATCHBLOCK L5 L6 L7 org/nlogo/api/AgentException
         L8
          LDC 9.9
         L0
          ALOAD 1
          GETFIELD org/nlogo/nvm/Context.agent : Lorg/nlogo/agent/Agent;
          ICONST_5
          INVOKEVIRTUAL org/nlogo/agent/Agent.getPatchVariable (I)Ljava/lang/Object;
         L1
          GOTO L9
         L2
         FRAME SAME1 org/nlogo/api/AgentException
          ASTORE 2
          NEW org/nlogo/nvm/EngineException
          DUP
          ALOAD 1
          ALOAD 0
          ALOAD 2
          INVOKEVIRTUAL org/nlogo/api/AgentException.getMessage ()Ljava/lang/String;
          INVOKESPECIAL org/nlogo/nvm/EngineException.<init> (Lorg/nlogo/nvm/Context;Lorg/nlogo/nvm/Instruction;Ljava/lang/String;)V
          ATHROW
         L9
         FRAME FULL [org/nlogo/prim/_asm_procedurerecolor_setpatchvariable_1 org/nlogo/nvm/Context] [D java/lang/Object]
          ASTORE 2
         L3
          ALOAD 2
          CHECKCAST java/lang/Double
          INVOKEVIRTUAL java/lang/Double.doubleValue ()D
          GOTO L10
         L4
         FRAME FULL [org/nlogo/prim/_asm_procedurerecolor_setpatchvariable_1 org/nlogo/nvm/Context java/lang/Object] [java/lang/ClassCastException]
          POP
          NEW org/nlogo/nvm/ArgumentTypeException
          DUP
          ALOAD 1
          ALOAD 0
          BIPUSH 1
          LDC 1
          ALOAD 2
          INVOKESPECIAL org/nlogo/nvm/ArgumentTypeException.<init> (Lorg/nlogo/nvm/Context;Lorg/nlogo/nvm/Instruction;IILjava/lang/Object;)V
          ATHROW
         L10
         FRAME FULL [org/nlogo/prim/_asm_procedurerecolor_setpatchvariable_1 org/nlogo/nvm/Context java/lang/Object] [D D]
          LDC -250.0
         L11
          LDC 100.0
         L12
          DSTORE 8
          DSTORE 6
          DSTORE 4
          DSTORE 2
          DLOAD 2
          INVOKESTATIC org/nlogo/api/Color.findCentralColorNumber (D)D
          LDC 5.0
          DSUB
          DSTORE 2
          DCONST_0
          DSTORE 10
          DLOAD 6
          DLOAD 8
          DCMPL
          IFLE L13
          DLOAD 4
          DLOAD 8
          DCMPG
          IFGE L14
          DCONST_1
          DSTORE 10
          GOTO L15
         L14
         FRAME FULL [org/nlogo/prim/_asm_procedurerecolor_setpatchvariable_1 org/nlogo/nvm/Context D D D D D] []
          DLOAD 4
          DLOAD 6
          DCMPL
          IFLE L16
          DCONST_0
          DSTORE 10
          GOTO L15
         L16
         FRAME SAME
          DLOAD 6
          DLOAD 4
          DSUB
          DSTORE 12
          DLOAD 6
          DLOAD 8
          DSUB
          DSTORE 14
          DLOAD 12
          DLOAD 14
          DDIV
          DSTORE 10
          GOTO L15
         L13
         FRAME SAME
          DLOAD 4
          DLOAD 8
          DCMPL
          IFLE L17
          DCONST_1
          DSTORE 10
          GOTO L15
         L17
         FRAME SAME
          DLOAD 4
          DLOAD 6
          DCMPG
          IFGE L18
          DCONST_0
          DSTORE 10
          GOTO L15
         L18
         FRAME SAME
          DLOAD 4
          DLOAD 6
          DSUB
          DSTORE 12
          DLOAD 8
          DLOAD 6
          DSUB
          DSTORE 14
          DLOAD 12
          DLOAD 14
          DDIV
          DSTORE 10
         L15
         FRAME SAME
          DLOAD 10
          LDC 10.0
          DMUL
          DSTORE 10
          DLOAD 10
          LDC 9.9999
          DCMPL
          IFLT L19
          LDC 9.9999
          DSTORE 10
          GOTO L20
         L19
         FRAME SAME
          DLOAD 10
          DCONST_0
          DCMPG
          IFGE L20
          DCONST_0
          DSTORE 10
         L20
         FRAME SAME
          ALOAD 0
          DLOAD 2
          DLOAD 10
          DADD
          INVOKEVIRTUAL org/nlogo/prim/_asm_procedurerecolor_setpatchvariable_1.validDouble (D)D
         L21
          DSTORE 2
          NEW java/lang/Double
          DUP
          DLOAD 2
          INVOKESPECIAL java/lang/Double.<init> (D)V
          ASTORE 2
         L5
          ALOAD 1
          GETFIELD org/nlogo/nvm/Context.agent : Lorg/nlogo/agent/Agent;
          ICONST_2
          ALOAD 2
          INVOKEVIRTUAL org/nlogo/agent/Agent.setPatchVariable (ILjava/lang/Object;)V
         L6
          GOTO L22
         L7
         FRAME FULL [org/nlogo/prim/_asm_procedurerecolor_setpatchvariable_1 org/nlogo/nvm/Context java/lang/Double T D D D D] [org/nlogo/api/AgentException]
          ASTORE 3
          NEW org/nlogo/nvm/EngineException
          DUP
          ALOAD 1
          ALOAD 0
          ALOAD 3
          INVOKEVIRTUAL org/nlogo/api/AgentException.getMessage ()Ljava/lang/String;
          INVOKESPECIAL org/nlogo/nvm/EngineException.<init> (Lorg/nlogo/nvm/Context;Lorg/nlogo/nvm/Instruction;Ljava/lang/String;)V
          ATHROW
         L22
         FRAME SAME
          ALOAD 1
          ICONST_2
          PUTFIELD org/nlogo/nvm/Context.ip : I
         L23
          RETURN
[2]_asm_procedurerecolor_goto_2 => void
         L0
          ALOAD 1
          ICONST_4
          PUTFIELD org/nlogo/nvm/Context.ip : I
         L1
          RETURN
[3]_asm_procedurerecolor_setpatchvariable_3 "set pcolor scale-color blue min list water 75 100 -10" Object => void
      _scalecolor "scale-color blue min list water 75 100 -10" double,double,double,double => double
        _constdouble:105.0 "blue" => double
        _min "min list water 75" LogoList => double
          _list "list water 75"
            _patchvariable:WATER "water" => Object
            _constdouble:75.0 "75" => Double
        _constdouble:100.0 "100" => double
        _constdouble:-10.0 "-10" => double
          TRYCATCHBLOCK L0 L1 L2 org/nlogo/api/AgentException
          TRYCATCHBLOCK L3 L4 L5 org/nlogo/api/AgentException
         L6
          LDC 105.0
         L7
          NEW org/nlogo/api/LogoListBuilder
          DUP
          INVOKESPECIAL org/nlogo/api/LogoListBuilder.<init> ()V
          DUP
         L0
          ALOAD 1
          GETFIELD org/nlogo/nvm/Context.agent : Lorg/nlogo/agent/Agent;
          BIPUSH 6
          INVOKEVIRTUAL org/nlogo/agent/Agent.getPatchVariable (I)Ljava/lang/Object;
         L1
          GOTO L8
         L2
         FRAME SAME1 org/nlogo/api/AgentException
          ASTORE 2
          NEW org/nlogo/nvm/EngineException
          DUP
          ALOAD 1
          ALOAD 0
          ALOAD 2
          INVOKEVIRTUAL org/nlogo/api/AgentException.getMessage ()Ljava/lang/String;
          INVOKESPECIAL org/nlogo/nvm/EngineException.<init> (Lorg/nlogo/nvm/Context;Lorg/nlogo/nvm/Instruction;Ljava/lang/String;)V
          ATHROW
         L8
         FRAME FULL [org/nlogo/prim/_asm_procedurerecolor_setpatchvariable_3 org/nlogo/nvm/Context] [D org/nlogo/api/LogoListBuilder org/nlogo/api/LogoListBuilder java/lang/Object]
          INVOKEVIRTUAL org/nlogo/api/LogoListBuilder.add (Ljava/lang/Object;)V
          DUP
         L9
          ALOAD 0
          GETFIELD org/nlogo/prim/_asm_procedurerecolor_setpatchvariable_3.kept7_value : Ljava/lang/Double;
         L10
          INVOKEVIRTUAL org/nlogo/api/LogoListBuilder.add (Ljava/lang/Object;)V
          INVOKEVIRTUAL org/nlogo/api/LogoListBuilder.toLogoList ()Lorg/nlogo/core/LogoList;
         L11
          ASTORE 2
          DCONST_0
          DSTORE 3
          ACONST_NULL
          ASTORE 5
          ALOAD 2
          INVOKEVIRTUAL org/nlogo/core/LogoList.javaIterable ()Ljava/lang/Iterable;
          INVOKEINTERFACE java/lang/Iterable.iterator ()Ljava/util/Iterator;
          ASTORE 6
         L12
         FRAME FULL [org/nlogo/prim/_asm_procedurerecolor_setpatchvariable_3 org/nlogo/nvm/Context org/nlogo/core/LogoList D java/lang/Double java/util/Iterator] [D]
          ALOAD 6
          INVOKEINTERFACE java/util/Iterator.hasNext ()Z
          IFEQ L13
          ALOAD 6
          INVOKEINTERFACE java/util/Iterator.next ()Ljava/lang/Object;
          ASTORE 7
          ALOAD 7
          INSTANCEOF java/lang/Double
          IFEQ L14
          ALOAD 7
          CHECKCAST java/lang/Double
          ASTORE 8
          ALOAD 8
          INVOKEVIRTUAL java/lang/Double.doubleValue ()D
          DSTORE 9
          ALOAD 5
          IFNULL L15
          DLOAD 9
          DLOAD 3
          DCMPG
          IFGE L14
         L15
         FRAME FULL [org/nlogo/prim/_asm_procedurerecolor_setpatchvariable_3 org/nlogo/nvm/Context org/nlogo/core/LogoList D java/lang/Double java/util/Iterator java/lang/Object java/lang/Double D] [D]
          DLOAD 9
          DSTORE 3
          ALOAD 8
          ASTORE 5
         L14
         FRAME FULL [org/nlogo/prim/_asm_procedurerecolor_setpatchvariable_3 org/nlogo/nvm/Context org/nlogo/core/LogoList D java/lang/Double java/util/Iterator java/lang/Object] [D]
          GOTO L12
         L13
         FRAME FULL [org/nlogo/prim/_asm_procedurerecolor_setpatchvariable_3 org/nlogo/nvm/Context org/nlogo/core/LogoList D java/lang/Double java/util/Iterator] [D]
          ALOAD 5
          IFNONNULL L16
          NEW org/nlogo/nvm/EngineException
          DUP
          ALOAD 1
          ALOAD 0
          INVOKESTATIC org/nlogo/core/I18N.errorsJ ()Lorg/nlogo/core/I18NJava;
          LDC "org.nlogo.prim._min.cantFindMinOfListWithNoNumbers"
          ICONST_1
          ANEWARRAY java/lang/Object
          DUP
          ICONST_0
          ALOAD 2
          INVOKESTATIC org/nlogo/api/Dump.logoObject (Ljava/lang/Object;)Ljava/lang/String;
          AASTORE
          INVOKEINTERFACE org/nlogo/core/I18NJava.getN (Ljava/lang/String;[Ljava/lang/Object;)Ljava/lang/String;
          INVOKESPECIAL org/nlogo/nvm/EngineException.<init> (Lorg/nlogo/nvm/Context;Lorg/nlogo/nvm/Instruction;Ljava/lang/String;)V
          ATHROW
         L16
         FRAME SAME1 D
          ALOAD 5
          INVOKEVIRTUAL java/lang/Double.doubleValue ()D
         L17
          LDC 100.0
         L18
          LDC -10.0
         L19
          DSTORE 8
          DSTORE 6
          DSTORE 4
          DSTORE 2
          DLOAD 2
          INVOKESTATIC org/nlogo/api/Color.findCentralColorNumber (D)D
          LDC 5.0
          DSUB
          DSTORE 2
          DCONST_0
          DSTORE 10
          DLOAD 6
          DLOAD 8
          DCMPL
          IFLE L20
          DLOAD 4
          DLOAD 8
          DCMPG
          IFGE L21
          DCONST_1
          DSTORE 10
          GOTO L22
         L21
         FRAME FULL [org/nlogo/prim/_asm_procedurerecolor_setpatchvariable_3 org/nlogo/nvm/Context D D D D D] []
          DLOAD 4
          DLOAD 6
          DCMPL
          IFLE L23
          DCONST_0
          DSTORE 10
          GOTO L22
         L23
         FRAME SAME
          DLOAD 6
          DLOAD 4
          DSUB
          DSTORE 12
          DLOAD 6
          DLOAD 8
          DSUB
          DSTORE 14
          DLOAD 12
          DLOAD 14
          DDIV
          DSTORE 10
          GOTO L22
         L20
         FRAME SAME
          DLOAD 4
          DLOAD 8
          DCMPL
          IFLE L24
          DCONST_1
          DSTORE 10
          GOTO L22
         L24
         FRAME SAME
          DLOAD 4
          DLOAD 6
          DCMPG
          IFGE L25
          DCONST_0
          DSTORE 10
          GOTO L22
         L25
         FRAME SAME
          DLOAD 4
          DLOAD 6
          DSUB
          DSTORE 12
          DLOAD 8
          DLOAD 6
          DSUB
          DSTORE 14
          DLOAD 12
          DLOAD 14
          DDIV
          DSTORE 10
         L22
         FRAME SAME
          DLOAD 10
          LDC 10.0
          DMUL
          DSTORE 10
          DLOAD 10
          LDC 9.9999
          DCMPL
          IFLT L26
          LDC 9.9999
          DSTORE 10
          GOTO L27
         L26
         FRAME SAME
          DLOAD 10
          DCONST_0
          DCMPG
          IFGE L27
          DCONST_0
          DSTORE 10
         L27
         FRAME SAME
          ALOAD 0
          DLOAD 2
          DLOAD 10
          DADD
          INVOKEVIRTUAL org/nlogo/prim/_asm_procedurerecolor_setpatchvariable_3.validDouble (D)D
         L28
          DSTORE 2
          NEW java/lang/Double
          DUP
          DLOAD 2
          INVOKESPECIAL java/lang/Double.<init> (D)V
          ASTORE 2
         L3
          ALOAD 1
          GETFIELD org/nlogo/nvm/Context.agent : Lorg/nlogo/agent/Agent;
          ICONST_2
          ALOAD 2
          INVOKEVIRTUAL org/nlogo/agent/Agent.setPatchVariable (ILjava/lang/Object;)V
         L4
          GOTO L29
         L5
         FRAME FULL [org/nlogo/prim/_asm_procedurerecolor_setpatchvariable_3 org/nlogo/nvm/Context java/lang/Double T D D D D] [org/nlogo/api/AgentException]
          ASTORE 3
          NEW org/nlogo/nvm/EngineException
          DUP
          ALOAD 1
          ALOAD 0
          ALOAD 3
          INVOKEVIRTUAL org/nlogo/api/AgentException.getMessage ()Ljava/lang/String;
          INVOKESPECIAL org/nlogo/nvm/EngineException.<init> (Lorg/nlogo/nvm/Context;Lorg/nlogo/nvm/Instruction;Ljava/lang/String;)V
          ATHROW
         L29
         FRAME SAME
          ALOAD 1
          ICONST_4
          PUTFIELD org/nlogo/nvm/Context.ip : I
         L30
          RETURN
[4]_asm_procedurerecolor_return_4 => void
         L0
          ALOAD 1
          INVOKEVIRTUAL org/nlogo/nvm/Context.returnFromProcedure ()V
          ALOAD 1
          ICONST_0
          PUTFIELD org/nlogo/nvm/Context.stopping : Z
         L1
          RETURN

procedure BENCHMARK:[_repeatlocal:0]{O---}:
[0]_asm_procedurebenchmark_randomseed_0 "random-seed 19192" double => void
      _constdouble:19192.0 "19192" => double
         L0
          LDC 19192.0
         L1
          DSTORE 2
          DLOAD 2
          D2L
          LSTORE 4
          LLOAD 4
          LDC -2147483648
          LCMP
          IFLT L2
          LLOAD 4
          LDC 2147483647
          LCMP
          IFLE L3
         L2
         FRAME APPEND [D J]
          NEW org/nlogo/nvm/EngineException
          DUP
          ALOAD 1
          ALOAD 0
          NEW scala/collection/mutable/StringBuilder
          DUP
          INVOKESPECIAL scala/collection/mutable/StringBuilder.<init> ()V
          GETSTATIC org/nlogo/api/Dump$.MODULE$ : Lorg/nlogo/api/Dump$;
          DLOAD 2
          INVOKEVIRTUAL org/nlogo/api/Dump$.number (D)Ljava/lang/String;
          INVOKEVIRTUAL scala/collection/mutable/StringBuilder.append (Ljava/lang/Object;)Lscala/collection/mutable/StringBuilder;
          LDC " is not in the allowable range for random seeds (-2147483648 to 2147483647)"
          INVOKEVIRTUAL scala/collection/mutable/StringBuilder.append (Ljava/lang/Object;)Lscala/collection/mutable/StringBuilder;
          INVOKEVIRTUAL scala/collection/mutable/StringBuilder.toString ()Ljava/lang/String;
          INVOKESPECIAL org/nlogo/nvm/EngineException.<init> (Lorg/nlogo/nvm/Context;Lorg/nlogo/nvm/Instruction;Ljava/lang/String;)V
          ATHROW
         L3
         FRAME SAME
          ALOAD 1
          GETFIELD org/nlogo/nvm/Context.job : Lorg/nlogo/nvm/Job;
          GETFIELD org/nlogo/nvm/Job.random : Lorg/nlogo/api/MersenneTwisterFast;
          LLOAD 4
          L2I
          I2L
          INVOKEVIRTUAL org/nlogo/api/MersenneTwisterFast.setSeed (J)V
          ALOAD 1
          ICONST_1
          PUTFIELD org/nlogo/nvm/Context.ip : I
         L4
          RETURN
[1]_resettimer "reset-timer"
[2]_asm_procedurebenchmark_call_1 "setup"
         L0
          NEW org/nlogo/nvm/Activation
          DUP
          ALOAD 0
          GETFIELD org/nlogo/prim/_asm_procedurebenchmark_call_1.kept1_procedure : Lorg/nlogo/nvm/Procedure;
          ALOAD 1
          GETFIELD org/nlogo/nvm/Context.activation : Lorg/nlogo/nvm/Activation;
          ICONST_3
          INVOKESPECIAL org/nlogo/nvm/Activation.<init> (Lorg/nlogo/nvm/Procedure;Lorg/nlogo/nvm/Activation;I)V
          ALOAD 1
          SWAP
          PUTFIELD org/nlogo/nvm/Context.activation : Lorg/nlogo/nvm/Activation;
          ALOAD 1
          ICONST_0
          PUTFIELD org/nlogo/nvm/Context.ip : I
         L1
          RETURN
[3]_asm_procedurebenchmark_repeatlocal_2 "repeat 250 [ go ]" double => void
      _constdouble:250.0 "250" => double
         L0
          LDC 250.0
         L1
          DSTORE 2
          ALOAD 1
          GETFIELD org/nlogo/nvm/Context.activation : Lorg/nlogo/nvm/Activation;
          GETFIELD org/nlogo/nvm/Activation.args : [Ljava/lang/Object;
          ICONST_0
          NEW org/nlogo/nvm/MutableLong
          DUP
          ALOAD 0
          DLOAD 2
          INVOKEVIRTUAL org/nlogo/prim/_asm_procedurebenchmark_repeatlocal_2.validLong (D)J
          INVOKESPECIAL org/nlogo/nvm/MutableLong.<init> (J)V
          AASTORE
          ALOAD 1
          ICONST_5
          PUTFIELD org/nlogo/nvm/Context.ip : I
         L2
          RETURN
[4]_asm_procedurebenchmark_call_3 "go"
         L0
          NEW org/nlogo/nvm/Activation
          DUP
          ALOAD 0
          GETFIELD org/nlogo/prim/_asm_procedurebenchmark_call_3.kept1_procedure : Lorg/nlogo/nvm/Procedure;
          ALOAD 1
          GETFIELD org/nlogo/nvm/Context.activation : Lorg/nlogo/nvm/Activation;
          ICONST_5
          INVOKESPECIAL org/nlogo/nvm/Activation.<init> (Lorg/nlogo/nvm/Procedure;Lorg/nlogo/nvm/Activation;I)V
          ALOAD 1
          SWAP
          PUTFIELD org/nlogo/nvm/Context.activation : Lorg/nlogo/nvm/Activation;
          ALOAD 1
          ICONST_0
          PUTFIELD org/nlogo/nvm/Context.ip : I
         L1
          RETURN
[5]_asm_procedurebenchmark_repeatlocalinternal_4 => void
         L0
          ALOAD 1
          GETFIELD org/nlogo/nvm/Context.activation : Lorg/nlogo/nvm/Activation;
          GETFIELD org/nlogo/nvm/Activation.args : [Ljava/lang/Object;
          ICONST_0
          AALOAD
          CHECKCAST org/nlogo/nvm/MutableLong
          ASTORE 2
          ALOAD 2
          INVOKEVIRTUAL org/nlogo/nvm/MutableLong.value ()J
          LCONST_0
          LCMP
          IFGT L1
          ALOAD 1
          BIPUSH 6
          PUTFIELD org/nlogo/nvm/Context.ip : I
          GOTO L2
         L1
         FRAME APPEND [org/nlogo/nvm/MutableLong]
          ALOAD 2
          ALOAD 2
          INVOKEVIRTUAL org/nlogo/nvm/MutableLong.value ()J
          LCONST_1
          LSUB
          INVOKEVIRTUAL org/nlogo/nvm/MutableLong.value_$eq (J)V
          ALOAD 1
          ICONST_4
          PUTFIELD org/nlogo/nvm/Context.ip : I
         L2
         FRAME SAME
          RETURN
[6]_asm_procedurebenchmark_setobservervariable_5 "set result timer" Object => void
      _timer "timer" => double
          TRYCATCHBLOCK L0 L1 L2 org/nlogo/api/AgentException
         L3
          ALOAD 0
          GETFIELD org/nlogo/prim/_asm_procedurebenchmark_setobservervariable_5.world : Lorg/nlogo/agent/World;
          INVOKEVIRTUAL org/nlogo/agent/World.timer ()Lorg/nlogo/api/Timer;
          INVOKEVIRTUAL org/nlogo/api/Timer.read ()D
         L4
          DSTORE 2
          NEW java/lang/Double
          DUP
          DLOAD 2
          INVOKESPECIAL java/lang/Double.<init> (D)V
          ASTORE 2
         L0
          ALOAD 1
          GETFIELD org/nlogo/nvm/Context.agent : Lorg/nlogo/agent/Agent;
          ICONST_5
          ALOAD 2
          INVOKEVIRTUAL org/nlogo/agent/Agent.setObserverVariable (ILjava/lang/Object;)V
         L1
          GOTO L5
         L2
         FRAME FULL [org/nlogo/prim/_asm_procedurebenchmark_setobservervariable_5 org/nlogo/nvm/Context java/lang/Double] [org/nlogo/api/AgentException]
          ASTORE 3
          NEW org/nlogo/nvm/EngineException
          DUP
          ALOAD 1
          ALOAD 0
          ALOAD 3
          INVOKEVIRTUAL org/nlogo/api/AgentException.getMessage ()Ljava/lang/String;
          INVOKESPECIAL org/nlogo/nvm/EngineException.<init> (Lorg/nlogo/nvm/Context;Lorg/nlogo/nvm/Instruction;Ljava/lang/String;)V
          ATHROW
         L5
         FRAME SAME
          ALOAD 1
          BIPUSH 7
          PUTFIELD org/nlogo/nvm/Context.ip : I
         L6
          RETURN
[7]_asm_procedurebenchmark_return_6 => void
         L0
          ALOAD 1
          INVOKEVIRTUAL org/nlogo/nvm/Context.returnFromProcedure ()V
          ALOAD 1
          ICONST_0
          PUTFIELD org/nlogo/nvm/Context.stopping : Z
         L1
          RETURN

procedure FLOW:[TARGET AMOUNT EROSION]{-TP-}:
[0]_asm_procedureflow_setprocedurevariable_0 "let min-one-of neighbors [ elevation + water ]" Object => void
      _minoneof "min-one-of neighbors [ elevation + water ]"
        _asm_procedureflow_neighbors_1 "neighbors" => AgentSet
             L0
              ALOAD 1
              GETFIELD org/nlogo/nvm/Context.agent : Lorg/nlogo/agent/Agent;
              INSTANCEOF org/nlogo/agent/Turtle
              IFEQ L1
              ALOAD 1
              GETFIELD org/nlogo/nvm/Context.agent : Lorg/nlogo/agent/Agent;
              CHECKCAST org/nlogo/agent/Turtle
              INVOKEVIRTUAL org/nlogo/agent/Turtle.getPatchHere ()Lorg/nlogo/agent/Patch;
              INVOKEVIRTUAL org/nlogo/agent/Patch.getNeighbors ()Lorg/nlogo/agent/AgentSet;
              GOTO L2
             L1
             FRAME SAME
              ALOAD 1
              GETFIELD org/nlogo/nvm/Context.agent : Lorg/nlogo/agent/Agent;
              CHECKCAST org/nlogo/agent/Patch
              INVOKEVIRTUAL org/nlogo/agent/Patch.getNeighbors ()Lorg/nlogo/agent/AgentSet;
             L2
             FRAME SAME1 org/nlogo/agent/AgentSet
              ARETURN
        _asm_procedureflow_plus_2 "elevation + water" double,double => double
          _patchvariable:ELEVATION "elevation" => Object
          _patchvariable:WATER "water" => Object
              TRYCATCHBLOCK L0 L1 L2 org/nlogo/api/AgentException
              TRYCATCHBLOCK L3 L4 L4 java/lang/ClassCastException
              TRYCATCHBLOCK L5 L6 L7 org/nlogo/api/AgentException
              TRYCATCHBLOCK L8 L9 L9 java/lang/ClassCastException
             L0
              ALOAD 1
              GETFIELD org/nlogo/nvm/Context.agent : Lorg/nlogo/agent/Agent;
              ICONST_5
              INVOKEVIRTUAL org/nlogo/agent/Agent.getPatchVariable (I)Ljava/lang/Object;
             L1
              GOTO L10
             L2
             FRAME SAME1 org/nlogo/api/AgentException
              ASTORE 2
              NEW org/nlogo/nvm/EngineException
              DUP
              ALOAD 1
              ALOAD 0
              ALOAD 2
              INVOKEVIRTUAL org/nlogo/api/AgentException.getMessage ()Ljava/lang/String;
              INVOKESPECIAL org/nlogo/nvm/EngineException.<init> (Lorg/nlogo/nvm/Context;Lorg/nlogo/nvm/Instruction;Ljava/lang/String;)V
              ATHROW
             L10
             FRAME SAME1 java/lang/Object
              ASTORE 2
             L3
              ALOAD 2
              CHECKCAST java/lang/Double
              INVOKEVIRTUAL java/lang/Double.doubleValue ()D
              GOTO L5
             L4
             FRAME FULL [org/nlogo/prim/_asm_procedureflow_plus_2 org/nlogo/nvm/Context java/lang/Object] [java/lang/ClassCastException]
              POP
              NEW org/nlogo/nvm/ArgumentTypeException
              DUP
              ALOAD 1
              ALOAD 0
              BIPUSH 0
              LDC 1
              ALOAD 2
              INVOKESPECIAL org/nlogo/nvm/ArgumentTypeException.<init> (Lorg/nlogo/nvm/Context;Lorg/nlogo/nvm/Instruction;IILjava/lang/Object;)V
              ATHROW
             L5
             FRAME SAME1 D
              ALOAD 1
              GETFIELD org/nlogo/nvm/Context.agent : Lorg/nlogo/agent/Agent;
              BIPUSH 6
              INVOKEVIRTUAL org/nlogo/agent/Agent.getPatchVariable (I)Ljava/lang/Object;
             L6
              GOTO L11
             L7
             FRAME SAME1 org/nlogo/api/AgentException
              ASTORE 2
              NEW org/nlogo/nvm/EngineException
              DUP
              ALOAD 1
              ALOAD 0
              ALOAD 2
              INVOKEVIRTUAL org/nlogo/api/AgentException.getMessage ()Ljava/lang/String;
              INVOKESPECIAL org/nlogo/nvm/EngineException.<init> (Lorg/nlogo/nvm/Context;Lorg/nlogo/nvm/Instruction;Ljava/lang/String;)V
              ATHROW
             L11
             FRAME FULL [org/nlogo/prim/_asm_procedureflow_plus_2 org/nlogo/nvm/Context java/lang/Object] [D java/lang/Object]
              ASTORE 2
             L8
              ALOAD 2
              CHECKCAST java/lang/Double
              INVOKEVIRTUAL java/lang/Double.doubleValue ()D
              GOTO L12
             L9
             FRAME SAME1 java/lang/ClassCastException
              POP
              NEW org/nlogo/nvm/ArgumentTypeException
              DUP
              ALOAD 1
              ALOAD 0
              BIPUSH 1
              LDC 1
              ALOAD 2
              INVOKESPECIAL org/nlogo/nvm/ArgumentTypeException.<init> (Lorg/nlogo/nvm/Context;Lorg/nlogo/nvm/Instruction;IILjava/lang/Object;)V
              ATHROW
             L12
             FRAME FULL [org/nlogo/prim/_asm_procedureflow_plus_2 org/nlogo/nvm/Context java/lang/Object] [D D]
              DSTORE 4
              DSTORE 2
              ALOAD 0
              DLOAD 2
              DLOAD 4
              DADD
              INVOKEVIRTUAL org/nlogo/prim/_asm_procedureflow_plus_2.validDouble (D)D
             L13
              DSTORE 2
              NEW java/lang/Double
              DUP
              DLOAD 2
              INVOKESPECIAL java/lang/Double.<init> (D)V
              ARETURN
          ALOAD 0
          GETFIELD org/nlogo/prim/_asm_procedureflow_setprocedurevariable_0.keptinstr2 : Lorg/nlogo/prim/etc/_minoneof;
          ALOAD 1
          INVOKEVIRTUAL org/nlogo/prim/etc/_minoneof.report (Lorg/nlogo/nvm/Context;)Ljava/lang/Object;
         L0
          ASTORE 2
          ALOAD 1
          GETFIELD org/nlogo/nvm/Context.activation : Lorg/nlogo/nvm/Activation;
          GETFIELD org/nlogo/nvm/Activation.args : [Ljava/lang/Object;
          ICONST_0
          ALOAD 2
          AASTORE
          ALOAD 1
          ICONST_1
          PUTFIELD org/nlogo/nvm/Context.ip : I
         L1
          RETURN
[1]_asm_procedureflow_setprocedurevariable_3 "let min list water 0.5 * elevation + water - [ elevation ] of target - [ water ] of target" Object => void
      _min "min list water 0.5 * elevation + water - [ elevation ] of target - [ water ] of target" LogoList => double
        _list "list water 0.5 * elevation + water - [ elevation ] of target - [ water ] of target"
          _patchvariable:WATER "water" => Object
          _mult "0.5 * elevation + water - [ elevation ] of target - [ water ] of target" double,double => double
            _constdouble:0.5 "0.5" => double
            _minus "elevation + water - [ elevation ] of target - [ water ] of target" double,double => double
              _minus "elevation + water - [ elevation ] of target" double,double => double
                _plus "elevation + water" double,double => double
                  _patchvariable:ELEVATION "elevation" => Object
                  _patchvariable:WATER "water" => Object
                _patchvariableof:ELEVATION "[ elevation ] of target" Object => Object
                  _procedurevariable:TARGET "target" => Object
              _patchvariableof:WATER "[ water ] of target" Object => Object
                _procedurevariable:TARGET "target" => Object
          TRYCATCHBLOCK L0 L1 L2 org/nlogo/api/AgentException
          TRYCATCHBLOCK L3 L4 L5 org/nlogo/api/AgentException
          TRYCATCHBLOCK L6 L7 L7 java/lang/ClassCastException
          TRYCATCHBLOCK L8 L9 L10 org/nlogo/api/AgentException
          TRYCATCHBLOCK L11 L12 L12 java/lang/ClassCastException
          TRYCATCHBLOCK L13 L14 L15 org/nlogo/api/AgentException
          TRYCATCHBLOCK L16 L17 L18 org/nlogo/api/AgentException
          TRYCATCHBLOCK L19 L20 L20 java/lang/ClassCastException
          TRYCATCHBLOCK L21 L22 L23 org/nlogo/api/AgentException
          TRYCATCHBLOCK L24 L25 L26 org/nlogo/api/AgentException
          TRYCATCHBLOCK L27 L28 L28 java/lang/ClassCastException
         L29
          NEW org/nlogo/api/LogoListBuilder
          DUP
          INVOKESPECIAL org/nlogo/api/LogoListBuilder.<init> ()V
          DUP
         L0
          ALOAD 1
          GETFIELD org/nlogo/nvm/Context.agent : Lorg/nlogo/agent/Agent;
          BIPUSH 6
          INVOKEVIRTUAL org/nlogo/agent/Agent.getPatchVariable (I)Ljava/lang/Object;
         L1
          GOTO L30
         L2
         FRAME SAME1 org/nlogo/api/AgentException
          ASTORE 2
          NEW org/nlogo/nvm/EngineException
          DUP
          ALOAD 1
          ALOAD 0
          ALOAD 2
          INVOKEVIRTUAL org/nlogo/api/AgentException.getMessage ()Ljava/lang/String;
          INVOKESPECIAL org/nlogo/nvm/EngineException.<init> (Lorg/nlogo/nvm/Context;Lorg/nlogo/nvm/Instruction;Ljava/lang/String;)V
          ATHROW
         L30
         FRAME FULL [org/nlogo/prim/_asm_procedureflow_setprocedurevariable_3 org/nlogo/nvm/Context] [org/nlogo/api/LogoListBuilder org/nlogo/api/LogoListBuilder java/lang/Object]
          INVOKEVIRTUAL org/nlogo/api/LogoListBuilder.add (Ljava/lang/Object;)V
          DUP
         L31
          LDC 0.5
         L3
          ALOAD 1
          GETFIELD org/nlogo/nvm/Context.agent : Lorg/nlogo/agent/Agent;
          ICONST_5
          INVOKEVIRTUAL org/nlogo/agent/Agent.getPatchVariable (I)Ljava/lang/Object;
         L4
          GOTO L32
         L5
         FRAME SAME1 org/nlogo/api/AgentException
          ASTORE 2
          NEW org/nlogo/nvm/EngineException
          DUP
          ALOAD 1
          ALOAD 0
          ALOAD 2
          INVOKEVIRTUAL org/nlogo/api/AgentException.getMessage ()Ljava/lang/String;
          INVOKESPECIAL org/nlogo/nvm/EngineException.<init> (Lorg/nlogo/nvm/Context;Lorg/nlogo/nvm/Instruction;Ljava/lang/String;)V
          ATHROW
         L32
         FRAME FULL [org/nlogo/prim/_asm_procedureflow_setprocedurevariable_3 org/nlogo/nvm/Context] [org/nlogo/api/LogoListBuilder org/nlogo/api/LogoListBuilder D java/lang/Object]
          ASTORE 2
         L6
          ALOAD 2
          CHECKCAST java/lang/Double
          INVOKEVIRTUAL java/lang/Double.doubleValue ()D
          GOTO L8
         L7
         FRAME FULL [org/nlogo/prim/_asm_procedureflow_setprocedurevariable_3 org/nlogo/nvm/Context java/lang/Object] [java/lang/ClassCastException]
          POP
          NEW org/nlogo/nvm/ArgumentTypeException
          DUP
          ALOAD 1
          ALOAD 0
          BIPUSH 0
          LDC 1
          ALOAD 2
          INVOKESPECIAL org/nlogo/nvm/ArgumentTypeException.<init> (Lorg/nlogo/nvm/Context;Lorg/nlogo/nvm/Instruction;IILjava/lang/Object;)V
          ATHROW
         L8
         FRAME FULL [org/nlogo/prim/_asm_procedureflow_setprocedurevariable_3 org/nlogo/nvm/Context java/lang/Object] [org/nlogo/api/LogoListBuilder org/nlogo/api/LogoListBuilder D D]
          ALOAD 1
          GETFIELD org/nlogo/nvm/Context.agent : Lorg/nlogo/agent/Agent;
          BIPUSH 6
          INVOKEVIRTUAL org/nlogo/agent/Agent.getPatchVariable (I)Ljava/lang/Object;
         L9
          GOTO L33
         L10
         FRAME SAME1 org/nlogo/api/AgentException
          ASTORE 2
          NEW org/nlogo/nvm/EngineException
          DUP
          ALOAD 1
          ALOAD 0
          ALOAD 2
          INVOKEVIRTUAL org/nlogo/api/AgentException.getMessage ()Ljava/lang/String;
          INVOKESPECIAL org/nlogo/nvm/EngineException.<init> (Lorg/nlogo/nvm/Context;Lorg/nlogo/nvm/Instruction;Ljava/lang/String;)V
          ATHROW
         L33
         FRAME FULL [org/nlogo/prim/_asm_procedureflow_setprocedurevariable_3 org/nlogo/nvm/Context java/lang/Object] [org/nlogo/api/LogoListBuilder org/nlogo/api/LogoListBuilder D D java/lang/Object]
          ASTORE 2
         L11
          ALOAD 2
          CHECKCAST java/lang/Double
          INVOKEVIRTUAL java/lang/Double.doubleValue ()D
          GOTO L34
         L12
         FRAME SAME1 java/lang/ClassCastException
          POP
          NEW org/nlogo/nvm/ArgumentTypeException
          DUP
          ALOAD 1
          ALOAD 0
          BIPUSH 1
          LDC 1
          ALOAD 2
          INVOKESPECIAL org/nlogo/nvm/ArgumentTypeException.<init> (Lorg/nlogo/nvm/Context;Lorg/nlogo/nvm/Instruction;IILjava/lang/Object;)V
          ATHROW
         L34
         FRAME FULL [org/nlogo/prim/_asm_procedureflow_setprocedurevariable_3 org/nlogo/nvm/Context java/lang/Object] [org/nlogo/api/LogoListBuilder org/nlogo/api/LogoListBuilder D D D]
          DSTORE 4
          DSTORE 2
          ALOAD 0
          DLOAD 2
          DLOAD 4
          DADD
          INVOKEVIRTUAL org/nlogo/prim/_asm_procedureflow_setprocedurevariable_3.validDouble (D)D
         L35
          ALOAD 1
          GETFIELD org/nlogo/nvm/Context.activation : Lorg/nlogo/nvm/Activation;
          GETFIELD org/nlogo/nvm/Activation.args : [Ljava/lang/Object;
          ICONST_0
          AALOAD
         L36
          ASTORE 2
          ALOAD 2
          ASTORE 3
          ALOAD 3
          INSTANCEOF org/nlogo/agent/Agent
          IFEQ L37
          ALOAD 3
          CHECKCAST org/nlogo/agent/Agent
          ASTORE 4
          ALOAD 4
          GETFIELD org/nlogo/agent/Agent.id : J
          LDC -1
          LCMP
          IFNE L16
          NEW org/nlogo/nvm/EngineException
          DUP
          ALOAD 1
          ALOAD 0
          GETSTATIC org/nlogo/core/I18N$.MODULE$ : Lorg/nlogo/core/I18N$;
          INVOKEVIRTUAL org/nlogo/core/I18N$.errors ()Lorg/nlogo/core/I18N$BundleKind;
          LDC "org.nlogo.$common.thatAgentIsDead"
          GETSTATIC scala/Predef$.MODULE$ : Lscala/Predef$;
          ICONST_1
          ANEWARRAY java/lang/Object
          DUP
          ICONST_0
          ALOAD 4
          INVOKEVIRTUAL org/nlogo/agent/Agent.classDisplayName ()Ljava/lang/String;
          AASTORE
          INVOKEVIRTUAL scala/Predef$.wrapRefArray ([Ljava/lang/Object;)Lscala/collection/mutable/WrappedArray;
          INVOKEVIRTUAL org/nlogo/core/I18N$BundleKind.getN (Ljava/lang/String;Lscala/collection/Seq;)Ljava/lang/String;
          INVOKESPECIAL org/nlogo/nvm/EngineException.<init> (Lorg/nlogo/nvm/Context;Lorg/nlogo/nvm/Instruction;Ljava/lang/String;)V
          ATHROW
         L16
         FRAME FULL [org/nlogo/prim/_asm_procedureflow_setprocedurevariable_3 org/nlogo/nvm/Context java/lang/Object java/lang/Object org/nlogo/agent/Agent] [org/nlogo/api/LogoListBuilder org/nlogo/api/LogoListBuilder D D]
          ALOAD 4
          ICONST_5
          INVOKEVIRTUAL org/nlogo/agent/Agent.getPatchVariable (I)Ljava/lang/Object;
         L17
          ASTORE 5
          GOTO L38
         L37
         FRAME FULL [org/nlogo/prim/_asm_procedureflow_setprocedurevariable_3 org/nlogo/nvm/Context java/lang/Object java/lang/Object D] [org/nlogo/api/LogoListBuilder org/nlogo/api/LogoListBuilder D D]
          ALOAD 3
          INSTANCEOF org/nlogo/agent/AgentSet
          IFEQ L39
          ALOAD 3
          CHECKCAST org/nlogo/agent/AgentSet
          ASTORE 7
          NEW org/nlogo/api/LogoListBuilder
          DUP
          INVOKESPECIAL org/nlogo/api/LogoListBuilder.<init> ()V
          ASTORE 8
         L13
          ALOAD 7
          ALOAD 1
          GETFIELD org/nlogo/nvm/Context.job : Lorg/nlogo/nvm/Job;
          GETFIELD org/nlogo/nvm/Job.random : Lorg/nlogo/api/MersenneTwisterFast;
          INVOKEVIRTUAL org/nlogo/agent/AgentSet.shufflerator (Lorg/nlogo/api/MersenneTwisterFast;)Lorg/nlogo/agent/AgentSet$Iterator;
          ASTORE 10
         L40
         FRAME FULL [org/nlogo/prim/_asm_procedureflow_setprocedurevariable_3 org/nlogo/nvm/Context java/lang/Object java/lang/Object D T org/nlogo/agent/AgentSet org/nlogo/api/LogoListBuilder T org/nlogo/agent/AgentSet$Iterator] [org/nlogo/api/LogoListBuilder org/nlogo/api/LogoListBuilder D D]
          ALOAD 10
          INVOKEINTERFACE org/nlogo/agent/AgentSet$Iterator.hasNext ()Z
          IFEQ L14
          ALOAD 8
          ALOAD 10
          INVOKEINTERFACE org/nlogo/agent/AgentSet$Iterator.next ()Lorg/nlogo/agent/Agent;
          ICONST_5
          INVOKEVIRTUAL org/nlogo/agent/Agent.getPatchVariable (I)Ljava/lang/Object;
          INVOKEVIRTUAL org/nlogo/api/LogoListBuilder.add (Ljava/lang/Object;)V
          GOTO L40
         L14
         FRAME FULL [org/nlogo/prim/_asm_procedureflow_setprocedurevariable_3 org/nlogo/nvm/Context java/lang/Object java/lang/Object D T org/nlogo/agent/AgentSet org/nlogo/api/LogoListBuilder T org/nlogo/agent/AgentSet$Iterator] [org/nlogo/api/LogoListBuilder org/nlogo/api/LogoListBuilder D D]
          ALOAD 8
          INVOKEVIRTUAL org/nlogo/api/LogoListBuilder.toLogoList ()Lorg/nlogo/core/LogoList;
          ASTORE 5
         L38
         FRAME FULL [org/nlogo/prim/_asm_procedureflow_setprocedurevariable_3 org/nlogo/nvm/Context java/lang/Object java/lang/Object T java/lang/Object] [org/nlogo/api/LogoListBuilder org/nlogo/api/LogoListBuilder D D]
          ALOAD 5
          GOTO L41
         L39
         FRAME FULL [org/nlogo/prim/_asm_procedureflow_setprocedurevariable_3 org/nlogo/nvm/Context java/lang/Object java/lang/Object D] [org/nlogo/api/LogoListBuilder org/nlogo/api/LogoListBuilder D D]
          NEW org/nlogo/nvm/ArgumentTypeException
          DUP
          ALOAD 1
          ALOAD 0
          ICONST_0
          GETSTATIC org/nlogo/core/Syntax$.MODULE$ : Lorg/nlogo/core/Syntax$;
          INVOKEVIRTUAL org/nlogo/core/Syntax$.TurtleType ()I
          GETSTATIC org/nlogo/core/Syntax$.MODULE$ : Lorg/nlogo/core/Syntax$;
          INVOKEVIRTUAL org/nlogo/core/Syntax$.PatchType ()I
          IOR
          GETSTATIC org/nlogo/core/Syntax$.MODULE$ : Lorg/nlogo/core/Syntax$;
          INVOKEVIRTUAL org/nlogo/core/Syntax$.TurtlesetType ()I
          IOR
          GETSTATIC org/nlogo/core/Syntax$.MODULE$ : Lorg/nlogo/core/Syntax$;
          INVOKEVIRTUAL org/nlogo/core/Syntax$.PatchsetType ()I
          IOR
          ALOAD 2
          INVOKESPECIAL org/nlogo/nvm/ArgumentTypeException.<init> (Lorg/nlogo/nvm/Context;Lorg/nlogo/nvm/Instruction;IILjava/lang/Object;)V
          ATHROW
         L18
         FRAME FULL [org/nlogo/prim/_asm_procedureflow_setprocedurevariable_3 org/nlogo/nvm/Context java/lang/Object java/lang/Object org/nlogo/agent/Agent] [org/nlogo/api/AgentException]
          ASTORE 6
          NEW org/nlogo/nvm/EngineException
          DUP
          ALOAD 1
          ALOAD 0
          ALOAD 6
          INVOKEVIRTUAL org/nlogo/api/AgentException.getMessage ()Ljava/lang/String;
          INVOKESPECIAL org/nlogo/nvm/EngineException.<init> (Lorg/nlogo/nvm/Context;Lorg/nlogo/nvm/Instruction;Ljava/lang/String;)V
          ATHROW
         L15
         FRAME FULL [org/nlogo/prim/_asm_procedureflow_setprocedurevariable_3 org/nlogo/nvm/Context java/lang/Object java/lang/Object D T org/nlogo/agent/AgentSet org/nlogo/api/LogoListBuilder] [org/nlogo/api/AgentException]
          ASTORE 9
          NEW org/nlogo/nvm/EngineException
          DUP
          ALOAD 1
          ALOAD 0
          ALOAD 9
          INVOKEVIRTUAL org/nlogo/api/AgentException.getMessage ()Ljava/lang/String;
          INVOKESPECIAL org/nlogo/nvm/EngineException.<init> (Lorg/nlogo/nvm/Context;Lorg/nlogo/nvm/Instruction;Ljava/lang/String;)V
          ATHROW
         L41
         FRAME FULL [org/nlogo/prim/_asm_procedureflow_setprocedurevariable_3 org/nlogo/nvm/Context java/lang/Object java/lang/Object T java/lang/Object] [org/nlogo/api/LogoListBuilder org/nlogo/api/LogoListBuilder D D java/lang/Object]
          ASTORE 2
         L19
          ALOAD 2
          CHECKCAST java/lang/Double
          INVOKEVIRTUAL java/lang/Double.doubleValue ()D
          GOTO L42
         L20
         FRAME SAME1 java/lang/ClassCastException
          POP
          NEW org/nlogo/nvm/ArgumentTypeException
          DUP
          ALOAD 1
          ALOAD 0
          BIPUSH 1
          LDC 1
          ALOAD 2
          INVOKESPECIAL org/nlogo/nvm/ArgumentTypeException.<init> (Lorg/nlogo/nvm/Context;Lorg/nlogo/nvm/Instruction;IILjava/lang/Object;)V
          ATHROW
         L42
         FRAME FULL [org/nlogo/prim/_asm_procedureflow_setprocedurevariable_3 org/nlogo/nvm/Context java/lang/Object java/lang/Object T java/lang/Object] [org/nlogo/api/LogoListBuilder org/nlogo/api/LogoListBuilder D D D]
          DSTORE 4
          DSTORE 2
          ALOAD 0
          DLOAD 2
          DLOAD 4
          DSUB
          INVOKEVIRTUAL org/nlogo/prim/_asm_procedureflow_setprocedurevariable_3.validDouble (D)D
         L43
          ALOAD 1
          GETFIELD org/nlogo/nvm/Context.activation : Lorg/nlogo/nvm/Activation;
          GETFIELD org/nlogo/nvm/Activation.args : [Ljava/lang/Object;
          ICONST_0
          AALOAD
         L44
          ASTORE 2
          ALOAD 2
          ASTORE 3
          ALOAD 3
          INSTANCEOF org/nlogo/agent/Agent
          IFEQ L45
          ALOAD 3
          CHECKCAST org/nlogo/agent/Agent
          ASTORE 4
          ALOAD 4
          GETFIELD org/nlogo/agent/Agent.id : J
          LDC -1
          LCMP
          IFNE L24
          NEW org/nlogo/nvm/EngineException
          DUP
          ALOAD 1
          ALOAD 0
          GETSTATIC org/nlogo/core/I18N$.MODULE$ : Lorg/nlogo/core/I18N$;
          INVOKEVIRTUAL org/nlogo/core/I18N$.errors ()Lorg/nlogo/core/I18N$BundleKind;
          LDC "org.nlogo.$common.thatAgentIsDead"
          GETSTATIC scala/Predef$.MODULE$ : Lscala/Predef$;
          ICONST_1
          ANEWARRAY java/lang/Object
          DUP
          ICONST_0
          ALOAD 4
          INVOKEVIRTUAL org/nlogo/agent/Agent.classDisplayName ()Ljava/lang/String;
          AASTORE
          INVOKEVIRTUAL scala/Predef$.wrapRefArray ([Ljava/lang/Object;)Lscala/collection/mutable/WrappedArray;
          INVOKEVIRTUAL org/nlogo/core/I18N$BundleKind.getN (Ljava/lang/String;Lscala/collection/Seq;)Ljava/lang/String;
          INVOKESPECIAL org/nlogo/nvm/EngineException.<init> (Lorg/nlogo/nvm/Context;Lorg/nlogo/nvm/Instruction;Ljava/lang/String;)V
          ATHROW
         L24
         FRAME FULL [org/nlogo/prim/_asm_procedureflow_setprocedurevariable_3 org/nlogo/nvm/Context java/lang/Object java/lang/Object org/nlogo/agent/Agent] [org/nlogo/api/LogoListBuilder org/nlogo/api/LogoListBuilder D D]
          ALOAD 4
          BIPUSH 6
          INVOKEVIRTUAL org/nlogo/agent/Agent.getPatchVariable (I)Ljava/lang/Object;
         L25
          ASTORE 5
          GOTO L46
         L45
         FRAME FULL [org/nlogo/prim/_asm_procedureflow_setprocedurevariable_3 org/nlogo/nvm/Context java/lang/Object java/lang/Object D] [org/nlogo/api/LogoListBuilder org/nlogo/api/LogoListBuilder D D]
          ALOAD 3
          INSTANCEOF org/nlogo/agent/AgentSet
          IFEQ L47
          ALOAD 3
          CHECKCAST org/nlogo/agent/AgentSet
          ASTORE 7
          NEW org/nlogo/api/LogoListBuilder
          DUP
          INVOKESPECIAL org/nlogo/api/LogoListBuilder.<init> ()V
          ASTORE 8
         L21
          ALOAD 7
          ALOAD 1
          GETFIELD org/nlogo/nvm/Context.job : Lorg/nlogo/nvm/Job;
          GETFIELD org/nlogo/nvm/Job.random : Lorg/nlogo/api/MersenneTwisterFast;
          INVOKEVIRTUAL org/nlogo/agent/AgentSet.shufflerator (Lorg/nlogo/api/MersenneTwisterFast;)Lorg/nlogo/agent/AgentSet$Iterator;
          ASTORE 10
         L48
         FRAME FULL [org/nlogo/prim/_asm_procedureflow_setprocedurevariable_3 org/nlogo/nvm/Context java/lang/Object java/lang/Object D T org/nlogo/agent/AgentSet org/nlogo/api/LogoListBuilder T org/nlogo/agent/AgentSet$Iterator] [org/nlogo/api/LogoListBuilder org/nlogo/api/LogoListBuilder D D]
          ALOAD 10
          INVOKEINTERFACE org/nlogo/agent/AgentSet$Iterator.hasNext ()Z
          IFEQ L22
          ALOAD 8
          ALOAD 10
          INVOKEINTERFACE org/nlogo/agent/AgentSet$Iterator.next ()Lorg/nlogo/agent/Agent;
          BIPUSH 6
          INVOKEVIRTUAL org/nlogo/agent/Agent.getPatchVariable (I)Ljava/lang/Object;
          INVOKEVIRTUAL org/nlogo/api/LogoListBuilder.add (Ljava/lang/Object;)V
          GOTO L48
         L22
         FRAME FULL [org/nlogo/prim/_asm_procedureflow_setprocedurevariable_3 org/nlogo/nvm/Context java/lang/Object java/lang/Object D T org/nlogo/agent/AgentSet org/nlogo/api/LogoListBuilder T org/nlogo/agent/AgentSet$Iterator] [org/nlogo/api/LogoListBuilder org/nlogo/api/LogoListBuilder D D]
          ALOAD 8
          INVOKEVIRTUAL org/nlogo/api/LogoListBuilder.toLogoList ()Lorg/nlogo/core/LogoList;
          ASTORE 5
         L46
         FRAME FULL [org/nlogo/prim/_asm_procedureflow_setprocedurevariable_3 org/nlogo/nvm/Context java/lang/Object java/lang/Object T java/lang/Object] [org/nlogo/api/LogoListBuilder org/nlogo/api/LogoListBuilder D D]
          ALOAD 5
          GOTO L49
         L47
         FRAME FULL [org/nlogo/prim/_asm_procedureflow_setprocedurevariable_3 org/nlogo/nvm/Context java/lang/Object java/lang/Object D] [org/nlogo/api/LogoListBuilder org/nlogo/api/LogoListBuilder D D]
          NEW org/nlogo/nvm/ArgumentTypeException
          DUP
          ALOAD 1
          ALOAD 0
          ICONST_0
          GETSTATIC org/nlogo/core/Syntax$.MODULE$ : Lorg/nlogo/core/Syntax$;
          INVOKEVIRTUAL org/nlogo/core/Syntax$.TurtleType ()I
          GETSTATIC org/nlogo/core/Syntax$.MODULE$ : Lorg/nlogo/core/Syntax$;
          INVOKEVIRTUAL org/nlogo/core/Syntax$.PatchType ()I
          IOR
          GETSTATIC org/nlogo/core/Syntax$.MODULE$ : Lorg/nlogo/core/Syntax$;
          INVOKEVIRTUAL org/nlogo/core/Syntax$.TurtlesetType ()I
          IOR
          GETSTATIC org/nlogo/core/Syntax$.MODULE$ : Lorg/nlogo/core/Syntax$;
          INVOKEVIRTUAL org/nlogo/core/Syntax$.PatchsetType ()I
          IOR
          ALOAD 2
          INVOKESPECIAL org/nlogo/nvm/ArgumentTypeException.<init> (Lorg/nlogo/nvm/Context;Lorg/nlogo/nvm/Instruction;IILjava/lang/Object;)V
          ATHROW
         L26
         FRAME FULL [org/nlogo/prim/_asm_procedureflow_setprocedurevariable_3 org/nlogo/nvm/Context java/lang/Object java/lang/Object org/nlogo/agent/Agent] [org/nlogo/api/AgentException]
          ASTORE 6
          NEW org/nlogo/nvm/EngineException
          DUP
          ALOAD 1
          ALOAD 0
          ALOAD 6
          INVOKEVIRTUAL org/nlogo/api/AgentException.getMessage ()Ljava/lang/String;
          INVOKESPECIAL org/nlogo/nvm/EngineException.<init> (Lorg/nlogo/nvm/Context;Lorg/nlogo/nvm/Instruction;Ljava/lang/String;)V
          ATHROW
         L23
         FRAME FULL [org/nlogo/prim/_asm_procedureflow_setprocedurevariable_3 org/nlogo/nvm/Context java/lang/Object java/lang/Object D T org/nlogo/agent/AgentSet org/nlogo/api/LogoListBuilder] [org/nlogo/api/AgentException]
          ASTORE 9
          NEW org/nlogo/nvm/EngineException
          DUP
          ALOAD 1
          ALOAD 0
          ALOAD 9
          INVOKEVIRTUAL org/nlogo/api/AgentException.getMessage ()Ljava/lang/String;
          INVOKESPECIAL org/nlogo/nvm/EngineException.<init> (Lorg/nlogo/nvm/Context;Lorg/nlogo/nvm/Instruction;Ljava/lang/String;)V
          ATHROW
         L49
         FRAME FULL [org/nlogo/prim/_asm_procedureflow_setprocedurevariable_3 org/nlogo/nvm/Context java/lang/Object java/lang/Object T java/lang/Object] [org/nlogo/api/LogoListBuilder org/nlogo/api/LogoListBuilder D D java/lang/Object]
          ASTORE 2
         L27
          ALOAD 2
          CHECKCAST java/lang/Double
          INVOKEVIRTUAL java/lang/Double.doubleValue ()D
          GOTO L50
         L28
         FRAME SAME1 java/lang/ClassCastException
          POP
          NEW org/nlogo/nvm/ArgumentTypeException
          DUP
          ALOAD 1
          ALOAD 0
          BIPUSH 1
          LDC 1
          ALOAD 2
          INVOKESPECIAL org/nlogo/nvm/ArgumentTypeException.<init> (Lorg/nlogo/nvm/Context;Lorg/nlogo/nvm/Instruction;IILjava/lang/Object;)V
          ATHROW
         L50
         FRAME FULL [org/nlogo/prim/_asm_procedureflow_setprocedurevariable_3 org/nlogo/nvm/Context java/lang/Object java/lang/Object T java/lang/Object] [org/nlogo/api/LogoListBuilder org/nlogo/api/LogoListBuilder D D D]
          DSTORE 4
          DSTORE 2
          ALOAD 0
          DLOAD 2
          DLOAD 4
          DSUB
          INVOKEVIRTUAL org/nlogo/prim/_asm_procedureflow_setprocedurevariable_3.validDouble (D)D
         L51
          DSTORE 4
          DSTORE 2
          ALOAD 0
          DLOAD 2
          DLOAD 4
          DMUL
          INVOKEVIRTUAL org/nlogo/prim/_asm_procedureflow_setprocedurevariable_3.validDouble (D)D
         L52
          DSTORE 2
          NEW java/lang/Double
          DUP
          DLOAD 2
          INVOKESPECIAL java/lang/Double.<init> (D)V
          INVOKEVIRTUAL org/nlogo/api/LogoListBuilder.add (Ljava/lang/Object;)V
          INVOKEVIRTUAL org/nlogo/api/LogoListBuilder.toLogoList ()Lorg/nlogo/core/LogoList;
         L53
          ASTORE 2
          DCONST_0
          DSTORE 3
          ACONST_NULL
          ASTORE 5
          ALOAD 2
          INVOKEVIRTUAL org/nlogo/core/LogoList.javaIterable ()Ljava/lang/Iterable;
          INVOKEINTERFACE java/lang/Iterable.iterator ()Ljava/util/Iterator;
          ASTORE 6
         L54
         FRAME FULL [org/nlogo/prim/_asm_procedureflow_setprocedurevariable_3 org/nlogo/nvm/Context org/nlogo/core/LogoList D java/lang/Double java/util/Iterator] []
          ALOAD 6
          INVOKEINTERFACE java/util/Iterator.hasNext ()Z
          IFEQ L55
          ALOAD 6
          INVOKEINTERFACE java/util/Iterator.next ()Ljava/lang/Object;
          ASTORE 7
          ALOAD 7
          INSTANCEOF java/lang/Double
          IFEQ L56
          ALOAD 7
          CHECKCAST java/lang/Double
          ASTORE 8
          ALOAD 8
          INVOKEVIRTUAL java/lang/Double.doubleValue ()D
          DSTORE 9
          ALOAD 5
          IFNULL L57
          DLOAD 9
          DLOAD 3
          DCMPG
          IFGE L56
         L57
         FRAME APPEND [java/lang/Object java/lang/Double D]
          DLOAD 9
          DSTORE 3
          ALOAD 8
          ASTORE 5
         L56
         FRAME CHOP 2
          GOTO L54
         L55
         FRAME CHOP 1
          ALOAD 5
          IFNONNULL L58
          NEW org/nlogo/nvm/EngineException
          DUP
          ALOAD 1
          ALOAD 0
          INVOKESTATIC org/nlogo/core/I18N.errorsJ ()Lorg/nlogo/core/I18NJava;
          LDC "org.nlogo.prim._min.cantFindMinOfListWithNoNumbers"
          ICONST_1
          ANEWARRAY java/lang/Object
          DUP
          ICONST_0
          ALOAD 2
          INVOKESTATIC org/nlogo/api/Dump.logoObject (Ljava/lang/Object;)Ljava/lang/String;
          AASTORE
          INVOKEINTERFACE org/nlogo/core/I18NJava.getN (Ljava/lang/String;[Ljava/lang/Object;)Ljava/lang/String;
          INVOKESPECIAL org/nlogo/nvm/EngineException.<init> (Lorg/nlogo/nvm/Context;Lorg/nlogo/nvm/Instruction;Ljava/lang/String;)V
          ATHROW
         L58
         FRAME SAME
          ALOAD 5
          INVOKEVIRTUAL java/lang/Double.doubleValue ()D
         L59
          DSTORE 2
          NEW java/lang/Double
          DUP
          DLOAD 2
          INVOKESPECIAL java/lang/Double.<init> (D)V
          ASTORE 2
          ALOAD 1
          GETFIELD org/nlogo/nvm/Context.activation : Lorg/nlogo/nvm/Activation;
          GETFIELD org/nlogo/nvm/Activation.args : [Ljava/lang/Object;
          ICONST_1
          ALOAD 2
          AASTORE
          ALOAD 1
          ICONST_2
          PUTFIELD org/nlogo/nvm/Context.ip : I
         L60
          RETURN
[2]_asm_procedureflow_if_4 "if amount > 0 let amount * 1 - soil-hardness set elevation elevation - erosion set amount min list water 0.5 * elevation + water - [ elevation ] of target - [ water ] of target set water water - amount [ ask target [ set water water + amount ] ]" boolean => void
      _greaterthan "amount > 0" Object,double => boolean
        _procedurevariable:AMOUNT "amount" => Object
        _constdouble:0.0 "0" => double
         L0
          ALOAD 1
          GETFIELD org/nlogo/nvm/Context.activation : Lorg/nlogo/nvm/Activation;
          GETFIELD org/nlogo/nvm/Activation.args : [Ljava/lang/Object;
          ICONST_1
          AALOAD
         L1
          DCONST_0
         L2
          DSTORE 3
          ASTORE 2
          ALOAD 2
          INSTANCEOF java/lang/Double
          IFEQ L3
          ALOAD 2
          CHECKCAST java/lang/Double
          INVOKEVIRTUAL java/lang/Double.doubleValue ()D
          DLOAD 3
          DCMPL
          IFLE L4
          ICONST_1
          GOTO L5
         L4
         FRAME APPEND [java/lang/Object D]
          ICONST_0
         L5
         FRAME SAME1 I
          GOTO L6
         L3
         FRAME SAME
          NEW org/nlogo/nvm/EngineException
          DUP
          ALOAD 1
          ALOAD 0
          INVOKESTATIC org/nlogo/core/I18N.errorsJ ()Lorg/nlogo/core/I18NJava;
          LDC "org.nlogo.prim._greaterthan.cannotCompareParameters"
          ICONST_2
          ANEWARRAY java/lang/Object
          DUP
          ICONST_0
          ALOAD 2
          INVOKESTATIC org/nlogo/api/TypeNames.aName (Ljava/lang/Object;)Ljava/lang/String;
          AASTORE
          DUP
          ICONST_1
          DLOAD 3
          INVOKESTATIC java/lang/Double.valueOf (D)Ljava/lang/Double;
          INVOKESTATIC org/nlogo/api/TypeNames.aName (Ljava/lang/Object;)Ljava/lang/String;
          AASTORE
          INVOKEINTERFACE org/nlogo/core/I18NJava.getN (Ljava/lang/String;[Ljava/lang/Object;)Ljava/lang/String;
          INVOKESPECIAL org/nlogo/nvm/EngineException.<init> (Lorg/nlogo/nvm/Context;Lorg/nlogo/nvm/Instruction;Ljava/lang/String;)V
          ATHROW
         L6
         FRAME SAME1 I
          ISTORE 2
          ALOAD 1
          ILOAD 2
          IFEQ L7
          ICONST_3
          GOTO L8
         L7
         FRAME FULL [org/nlogo/prim/_asm_procedureflow_if_4 org/nlogo/nvm/Context I D] [org/nlogo/nvm/Context]
          BIPUSH 10
         L8
         FRAME FULL [org/nlogo/prim/_asm_procedureflow_if_4 org/nlogo/nvm/Context I D] [org/nlogo/nvm/Context I]
          PUTFIELD org/nlogo/nvm/Context.ip : I
         L9
          RETURN
[3]_asm_procedureflow_setprocedurevariable_5 "let amount * 1 - soil-hardness" Object => void
      _mult "amount * 1 - soil-hardness" double,double => double
        _procedurevariable:AMOUNT "amount" => Object
        _minus "1 - soil-hardness" double,double => double
          _constdouble:1.0 "1" => double
          _observervariable:SOIL-HARDNESS "soil-hardness" => Object
          TRYCATCHBLOCK L0 L1 L1 java/lang/ClassCastException
          TRYCATCHBLOCK L2 L3 L3 java/lang/ClassCastException
         L4
          ALOAD 1
          GETFIELD org/nlogo/nvm/Context.activation : Lorg/nlogo/nvm/Activation;
          GETFIELD org/nlogo/nvm/Activation.args : [Ljava/lang/Object;
          ICONST_1
          AALOAD
         L5
          ASTORE 2
         L0
          ALOAD 2
          CHECKCAST java/lang/Double
          INVOKEVIRTUAL java/lang/Double.doubleValue ()D
          GOTO L6
         L1
         FRAME FULL [org/nlogo/prim/_asm_procedureflow_setprocedurevariable_5 org/nlogo/nvm/Context java/lang/Object] [java/lang/ClassCastException]
          POP
          NEW org/nlogo/nvm/ArgumentTypeException
          DUP
          ALOAD 1
          ALOAD 0
          BIPUSH 0
          LDC 1
          ALOAD 2
          INVOKESPECIAL org/nlogo/nvm/ArgumentTypeException.<init> (Lorg/nlogo/nvm/Context;Lorg/nlogo/nvm/Instruction;IILjava/lang/Object;)V
          ATHROW
         L6
         FRAME SAME1 D
          DCONST_1
         L7
          ALOAD 1
          GETFIELD org/nlogo/nvm/Context.agent : Lorg/nlogo/agent/Agent;
          ICONST_3
          INVOKEVIRTUAL org/nlogo/agent/Agent.getObserverVariable (I)Ljava/lang/Object;
         L8
          ASTORE 2
         L2
          ALOAD 2
          CHECKCAST java/lang/Double
          INVOKEVIRTUAL java/lang/Double.doubleValue ()D
          GOTO L9
         L3
         FRAME SAME1 java/lang/ClassCastException
          POP
          NEW org/nlogo/nvm/ArgumentTypeException
          DUP
          ALOAD 1
          ALOAD 0
          BIPUSH 1
          LDC 1
          ALOAD 2
          INVOKESPECIAL org/nlogo/nvm/ArgumentTypeException.<init> (Lorg/nlogo/nvm/Context;Lorg/nlogo/nvm/Instruction;IILjava/lang/Object;)V
          ATHROW
         L9
         FRAME FULL [org/nlogo/prim/_asm_procedureflow_setprocedurevariable_5 org/nlogo/nvm/Context java/lang/Object] [D D D]
          DSTORE 4
          DSTORE 2
          ALOAD 0
          DLOAD 2
          DLOAD 4
          DSUB
          INVOKEVIRTUAL org/nlogo/prim/_asm_procedureflow_setprocedurevariable_5.validDouble (D)D
         L10
          DSTORE 4
          DSTORE 2
          ALOAD 0
          DLOAD 2
          DLOAD 4
          DMUL
          INVOKEVIRTUAL org/nlogo/prim/_asm_procedureflow_setprocedurevariable_5.validDouble (D)D
         L11
          DSTORE 2
          NEW java/lang/Double
          DUP
          DLOAD 2
          INVOKESPECIAL java/lang/Double.<init> (D)V
          ASTORE 2
          ALOAD 1
          GETFIELD org/nlogo/nvm/Context.activation : Lorg/nlogo/nvm/Activation;
          GETFIELD org/nlogo/nvm/Activation.args : [Ljava/lang/Object;
          ICONST_2
          ALOAD 2
          AASTORE
          ALOAD 1
          ICONST_4
          PUTFIELD org/nlogo/nvm/Context.ip : I
         L12
          RETURN
[4]_asm_procedureflow_setpatchvariable_6 "set elevation elevation - erosion" Object => void
      _minus "elevation - erosion" double,double => double
        _patchvariable:ELEVATION "elevation" => Object
        _procedurevariable:EROSION "erosion" => Object
          TRYCATCHBLOCK L0 L1 L2 org/nlogo/api/AgentException
          TRYCATCHBLOCK L3 L4 L4 java/lang/ClassCastException
          TRYCATCHBLOCK L5 L6 L6 java/lang/ClassCastException
          TRYCATCHBLOCK L7 L8 L9 org/nlogo/api/AgentException
         L0
          ALOAD 1
          GETFIELD org/nlogo/nvm/Context.agent : Lorg/nlogo/agent/Agent;
          ICONST_5
          INVOKEVIRTUAL org/nlogo/agent/Agent.getPatchVariable (I)Ljava/lang/Object;
         L1
          GOTO L10
         L2
         FRAME SAME1 org/nlogo/api/AgentException
          ASTORE 2
          NEW org/nlogo/nvm/EngineException
          DUP
          ALOAD 1
          ALOAD 0
          ALOAD 2
          INVOKEVIRTUAL org/nlogo/api/AgentException.getMessage ()Ljava/lang/String;
          INVOKESPECIAL org/nlogo/nvm/EngineException.<init> (Lorg/nlogo/nvm/Context;Lorg/nlogo/nvm/Instruction;Ljava/lang/String;)V
          ATHROW
         L10
         FRAME SAME1 java/lang/Object
          ASTORE 2
         L3
          ALOAD 2
          CHECKCAST java/lang/Double
          INVOKEVIRTUAL java/lang/Double.doubleValue ()D
          GOTO L11
         L4
         FRAME FULL [org/nlogo/prim/_asm_procedureflow_setpatchvariable_6 org/nlogo/nvm/Context java/lang/Object] [java/lang/ClassCastException]
          POP
          NEW org/nlogo/nvm/ArgumentTypeException
          DUP
          ALOAD 1
          ALOAD 0
          BIPUSH 0
          LDC 1
          ALOAD 2
          INVOKESPECIAL org/nlogo/nvm/ArgumentTypeException.<init> (Lorg/nlogo/nvm/Context;Lorg/nlogo/nvm/Instruction;IILjava/lang/Object;)V
          ATHROW
         L11
         FRAME SAME1 D
          ALOAD 1
          GETFIELD org/nlogo/nvm/Context.activation : Lorg/nlogo/nvm/Activation;
          GETFIELD org/nlogo/nvm/Activation.args : [Ljava/lang/Object;
          ICONST_2
          AALOAD
         L12
          ASTORE 2
         L5
          ALOAD 2
          CHECKCAST java/lang/Double
          INVOKEVIRTUAL java/lang/Double.doubleValue ()D
          GOTO L13
         L6
         FRAME SAME1 java/lang/ClassCastException
          POP
          NEW org/nlogo/nvm/ArgumentTypeException
          DUP
          ALOAD 1
          ALOAD 0
          BIPUSH 1
          LDC 1
          ALOAD 2
          INVOKESPECIAL org/nlogo/nvm/ArgumentTypeException.<init> (Lorg/nlogo/nvm/Context;Lorg/nlogo/nvm/Instruction;IILjava/lang/Object;)V
          ATHROW
         L13
         FRAME FULL [org/nlogo/prim/_asm_procedureflow_setpatchvariable_6 org/nlogo/nvm/Context java/lang/Object] [D D]
          DSTORE 4
          DSTORE 2
          ALOAD 0
          DLOAD 2
          DLOAD 4
          DSUB
          INVOKEVIRTUAL org/nlogo/prim/_asm_procedureflow_setpatchvariable_6.validDouble (D)D
         L14
          DSTORE 2
          NEW java/lang/Double
          DUP
          DLOAD 2
          INVOKESPECIAL java/lang/Double.<init> (D)V
          ASTORE 2
         L7
          ALOAD 1
          GETFIELD org/nlogo/nvm/Context.agent : Lorg/nlogo/agent/Agent;
          ICONST_5
          ALOAD 2
          INVOKEVIRTUAL org/nlogo/agent/Agent.setPatchVariable (ILjava/lang/Object;)V
         L8
          GOTO L15
         L9
         FRAME FULL [org/nlogo/prim/_asm_procedureflow_setpatchvariable_6 org/nlogo/nvm/Context java/lang/Double T D] [org/nlogo/api/AgentException]
          ASTORE 3
          NEW org/nlogo/nvm/EngineException
          DUP
          ALOAD 1
          ALOAD 0
          ALOAD 3
          INVOKEVIRTUAL org/nlogo/api/AgentException.getMessage ()Ljava/lang/String;
          INVOKESPECIAL org/nlogo/nvm/EngineException.<init> (Lorg/nlogo/nvm/Context;Lorg/nlogo/nvm/Instruction;Ljava/lang/String;)V
          ATHROW
         L15
         FRAME SAME
          ALOAD 1
          ICONST_5
          PUTFIELD org/nlogo/nvm/Context.ip : I
         L16
          RETURN
[5]_asm_procedureflow_setprocedurevariable_7 "set amount min list water 0.5 * elevation + water - [ elevation ] of target - [ water ] of target" Object => void
      _min "min list water 0.5 * elevation + water - [ elevation ] of target - [ water ] of target" LogoList => double
        _list "list water 0.5 * elevation + water - [ elevation ] of target - [ water ] of target"
          _patchvariable:WATER "water" => Object
          _mult "0.5 * elevation + water - [ elevation ] of target - [ water ] of target" double,double => double
            _constdouble:0.5 "0.5" => double
            _minus "elevation + water - [ elevation ] of target - [ water ] of target" double,double => double
              _minus "elevation + water - [ elevation ] of target" double,double => double
                _plus "elevation + water" double,double => double
                  _patchvariable:ELEVATION "elevation" => Object
                  _patchvariable:WATER "water" => Object
                _patchvariableof:ELEVATION "[ elevation ] of target" Object => Object
                  _procedurevariable:TARGET "target" => Object
              _patchvariableof:WATER "[ water ] of target" Object => Object
                _procedurevariable:TARGET "target" => Object
          TRYCATCHBLOCK L0 L1 L2 org/nlogo/api/AgentException
          TRYCATCHBLOCK L3 L4 L5 org/nlogo/api/AgentException
          TRYCATCHBLOCK L6 L7 L7 java/lang/ClassCastException
          TRYCATCHBLOCK L8 L9 L10 org/nlogo/api/AgentException
          TRYCATCHBLOCK L11 L12 L12 java/lang/ClassCastException
          TRYCATCHBLOCK L13 L14 L15 org/nlogo/api/AgentException
          TRYCATCHBLOCK L16 L17 L18 org/nlogo/api/AgentException
          TRYCATCHBLOCK L19 L20 L20 java/lang/ClassCastException
          TRYCATCHBLOCK L21 L22 L23 org/nlogo/api/AgentException
          TRYCATCHBLOCK L24 L25 L26 org/nlogo/api/AgentException
          TRYCATCHBLOCK L27 L28 L28 java/lang/ClassCastException
         L29
          NEW org/nlogo/api/LogoListBuilder
          DUP
          INVOKESPECIAL org/nlogo/api/LogoListBuilder.<init> ()V
          DUP
         L0
          ALOAD 1
          GETFIELD org/nlogo/nvm/Context.agent : Lorg/nlogo/agent/Agent;
          BIPUSH 6
          INVOKEVIRTUAL org/nlogo/agent/Agent.getPatchVariable (I)Ljava/lang/Object;
         L1
          GOTO L30
         L2
         FRAME SAME1 org/nlogo/api/AgentException
          ASTORE 2
          NEW org/nlogo/nvm/EngineException
          DUP
          ALOAD 1
          ALOAD 0
          ALOAD 2
          INVOKEVIRTUAL org/nlogo/api/AgentException.getMessage ()Ljava/lang/String;
          INVOKESPECIAL org/nlogo/nvm/EngineException.<init> (Lorg/nlogo/nvm/Context;Lorg/nlogo/nvm/Instruction;Ljava/lang/String;)V
          ATHROW
         L30
         FRAME FULL [org/nlogo/prim/_asm_procedureflow_setprocedurevariable_7 org/nlogo/nvm/Context] [org/nlogo/api/LogoListBuilder org/nlogo/api/LogoListBuilder java/lang/Object]
          INVOKEVIRTUAL org/nlogo/api/LogoListBuilder.add (Ljava/lang/Object;)V
          DUP
         L31
          LDC 0.5
         L3
          ALOAD 1
          GETFIELD org/nlogo/nvm/Context.agent : Lorg/nlogo/agent/Agent;
          ICONST_5
          INVOKEVIRTUAL org/nlogo/agent/Agent.getPatchVariable (I)Ljava/lang/Object;
         L4
          GOTO L32
         L5
         FRAME SAME1 org/nlogo/api/AgentException
          ASTORE 2
          NEW org/nlogo/nvm/EngineException
          DUP
          ALOAD 1
          ALOAD 0
          ALOAD 2
          INVOKEVIRTUAL org/nlogo/api/AgentException.getMessage ()Ljava/lang/String;
          INVOKESPECIAL org/nlogo/nvm/EngineException.<init> (Lorg/nlogo/nvm/Context;Lorg/nlogo/nvm/Instruction;Ljava/lang/String;)V
          ATHROW
         L32
         FRAME FULL [org/nlogo/prim/_asm_procedureflow_setprocedurevariable_7 org/nlogo/nvm/Context] [org/nlogo/api/LogoListBuilder org/nlogo/api/LogoListBuilder D java/lang/Object]
          ASTORE 2
         L6
          ALOAD 2
          CHECKCAST java/lang/Double
          INVOKEVIRTUAL java/lang/Double.doubleValue ()D
          GOTO L8
         L7
         FRAME FULL [org/nlogo/prim/_asm_procedureflow_setprocedurevariable_7 org/nlogo/nvm/Context java/lang/Object] [java/lang/ClassCastException]
          POP
          NEW org/nlogo/nvm/ArgumentTypeException
          DUP
          ALOAD 1
          ALOAD 0
          BIPUSH 0
          LDC 1
          ALOAD 2
          INVOKESPECIAL org/nlogo/nvm/ArgumentTypeException.<init> (Lorg/nlogo/nvm/Context;Lorg/nlogo/nvm/Instruction;IILjava/lang/Object;)V
          ATHROW
         L8
         FRAME FULL [org/nlogo/prim/_asm_procedureflow_setprocedurevariable_7 org/nlogo/nvm/Context java/lang/Object] [org/nlogo/api/LogoListBuilder org/nlogo/api/LogoListBuilder D D]
          ALOAD 1
          GETFIELD org/nlogo/nvm/Context.agent : Lorg/nlogo/agent/Agent;
          BIPUSH 6
          INVOKEVIRTUAL org/nlogo/agent/Agent.getPatchVariable (I)Ljava/lang/Object;
         L9
          GOTO L33
         L10
         FRAME SAME1 org/nlogo/api/AgentException
          ASTORE 2
          NEW org/nlogo/nvm/EngineException
          DUP
          ALOAD 1
          ALOAD 0
          ALOAD 2
          INVOKEVIRTUAL org/nlogo/api/AgentException.getMessage ()Ljava/lang/String;
          INVOKESPECIAL org/nlogo/nvm/EngineException.<init> (Lorg/nlogo/nvm/Context;Lorg/nlogo/nvm/Instruction;Ljava/lang/String;)V
          ATHROW
         L33
         FRAME FULL [org/nlogo/prim/_asm_procedureflow_setprocedurevariable_7 org/nlogo/nvm/Context java/lang/Object] [org/nlogo/api/LogoListBuilder org/nlogo/api/LogoListBuilder D D java/lang/Object]
          ASTORE 2
         L11
          ALOAD 2
          CHECKCAST java/lang/Double
          INVOKEVIRTUAL java/lang/Double.doubleValue ()D
          GOTO L34
         L12
         FRAME SAME1 java/lang/ClassCastException
          POP
          NEW org/nlogo/nvm/ArgumentTypeException
          DUP
          ALOAD 1
          ALOAD 0
          BIPUSH 1
          LDC 1
          ALOAD 2
          INVOKESPECIAL org/nlogo/nvm/ArgumentTypeException.<init> (Lorg/nlogo/nvm/Context;Lorg/nlogo/nvm/Instruction;IILjava/lang/Object;)V
          ATHROW
         L34
         FRAME FULL [org/nlogo/prim/_asm_procedureflow_setprocedurevariable_7 org/nlogo/nvm/Context java/lang/Object] [org/nlogo/api/LogoListBuilder org/nlogo/api/LogoListBuilder D D D]
          DSTORE 4
          DSTORE 2
          ALOAD 0
          DLOAD 2
          DLOAD 4
          DADD
          INVOKEVIRTUAL org/nlogo/prim/_asm_procedureflow_setprocedurevariable_7.validDouble (D)D
         L35
          ALOAD 1
          GETFIELD org/nlogo/nvm/Context.activation : Lorg/nlogo/nvm/Activation;
          GETFIELD org/nlogo/nvm/Activation.args : [Ljava/lang/Object;
          ICONST_0
          AALOAD
         L36
          ASTORE 2
          ALOAD 2
          ASTORE 3
          ALOAD 3
          INSTANCEOF org/nlogo/agent/Agent
          IFEQ L37
          ALOAD 3
          CHECKCAST org/nlogo/agent/Agent
          ASTORE 4
          ALOAD 4
          GETFIELD org/nlogo/agent/Agent.id : J
          LDC -1
          LCMP
          IFNE L16
          NEW org/nlogo/nvm/EngineException
          DUP
          ALOAD 1
          ALOAD 0
          GETSTATIC org/nlogo/core/I18N$.MODULE$ : Lorg/nlogo/core/I18N$;
          INVOKEVIRTUAL org/nlogo/core/I18N$.errors ()Lorg/nlogo/core/I18N$BundleKind;
          LDC "org.nlogo.$common.thatAgentIsDead"
          GETSTATIC scala/Predef$.MODULE$ : Lscala/Predef$;
          ICONST_1
          ANEWARRAY java/lang/Object
          DUP
          ICONST_0
          ALOAD 4
          INVOKEVIRTUAL org/nlogo/agent/Agent.classDisplayName ()Ljava/lang/String;
          AASTORE
          INVOKEVIRTUAL scala/Predef$.wrapRefArray ([Ljava/lang/Object;)Lscala/collection/mutable/WrappedArray;
          INVOKEVIRTUAL org/nlogo/core/I18N$BundleKind.getN (Ljava/lang/String;Lscala/collection/Seq;)Ljava/lang/String;
          INVOKESPECIAL org/nlogo/nvm/EngineException.<init> (Lorg/nlogo/nvm/Context;Lorg/nlogo/nvm/Instruction;Ljava/lang/String;)V
          ATHROW
         L16
         FRAME FULL [org/nlogo/prim/_asm_procedureflow_setprocedurevariable_7 org/nlogo/nvm/Context java/lang/Object java/lang/Object org/nlogo/agent/Agent] [org/nlogo/api/LogoListBuilder org/nlogo/api/LogoListBuilder D D]
          ALOAD 4
          ICONST_5
          INVOKEVIRTUAL org/nlogo/agent/Agent.getPatchVariable (I)Ljava/lang/Object;
         L17
          ASTORE 5
          GOTO L38
         L37
         FRAME FULL [org/nlogo/prim/_asm_procedureflow_setprocedurevariable_7 org/nlogo/nvm/Context java/lang/Object java/lang/Object D] [org/nlogo/api/LogoListBuilder org/nlogo/api/LogoListBuilder D D]
          ALOAD 3
          INSTANCEOF org/nlogo/agent/AgentSet
          IFEQ L39
          ALOAD 3
          CHECKCAST org/nlogo/agent/AgentSet
          ASTORE 7
          NEW org/nlogo/api/LogoListBuilder
          DUP
          INVOKESPECIAL org/nlogo/api/LogoListBuilder.<init> ()V
          ASTORE 8
         L13
          ALOAD 7
          ALOAD 1
          GETFIELD org/nlogo/nvm/Context.job : Lorg/nlogo/nvm/Job;
          GETFIELD org/nlogo/nvm/Job.random : Lorg/nlogo/api/MersenneTwisterFast;
          INVOKEVIRTUAL org/nlogo/agent/AgentSet.shufflerator (Lorg/nlogo/api/MersenneTwisterFast;)Lorg/nlogo/agent/AgentSet$Iterator;
          ASTORE 10
         L40
         FRAME FULL [org/nlogo/prim/_asm_procedureflow_setprocedurevariable_7 org/nlogo/nvm/Context java/lang/Object java/lang/Object D T org/nlogo/agent/AgentSet org/nlogo/api/LogoListBuilder T org/nlogo/agent/AgentSet$Iterator] [org/nlogo/api/LogoListBuilder org/nlogo/api/LogoListBuilder D D]
          ALOAD 10
          INVOKEINTERFACE org/nlogo/agent/AgentSet$Iterator.hasNext ()Z
          IFEQ L14
          ALOAD 8
          ALOAD 10
          INVOKEINTERFACE org/nlogo/agent/AgentSet$Iterator.next ()Lorg/nlogo/agent/Agent;
          ICONST_5
          INVOKEVIRTUAL org/nlogo/agent/Agent.getPatchVariable (I)Ljava/lang/Object;
          INVOKEVIRTUAL org/nlogo/api/LogoListBuilder.add (Ljava/lang/Object;)V
          GOTO L40
         L14
         FRAME FULL [org/nlogo/prim/_asm_procedureflow_setprocedurevariable_7 org/nlogo/nvm/Context java/lang/Object java/lang/Object D T org/nlogo/agent/AgentSet org/nlogo/api/LogoListBuilder T org/nlogo/agent/AgentSet$Iterator] [org/nlogo/api/LogoListBuilder org/nlogo/api/LogoListBuilder D D]
          ALOAD 8
          INVOKEVIRTUAL org/nlogo/api/LogoListBuilder.toLogoList ()Lorg/nlogo/core/LogoList;
          ASTORE 5
         L38
         FRAME FULL [org/nlogo/prim/_asm_procedureflow_setprocedurevariable_7 org/nlogo/nvm/Context java/lang/Object java/lang/Object T java/lang/Object] [org/nlogo/api/LogoListBuilder org/nlogo/api/LogoListBuilder D D]
          ALOAD 5
          GOTO L41
         L39
         FRAME FULL [org/nlogo/prim/_asm_procedureflow_setprocedurevariable_7 org/nlogo/nvm/Context java/lang/Object java/lang/Object D] [org/nlogo/api/LogoListBuilder org/nlogo/api/LogoListBuilder D D]
          NEW org/nlogo/nvm/ArgumentTypeException
          DUP
          ALOAD 1
          ALOAD 0
          ICONST_0
          GETSTATIC org/nlogo/core/Syntax$.MODULE$ : Lorg/nlogo/core/Syntax$;
          INVOKEVIRTUAL org/nlogo/core/Syntax$.TurtleType ()I
          GETSTATIC org/nlogo/core/Syntax$.MODULE$ : Lorg/nlogo/core/Syntax$;
          INVOKEVIRTUAL org/nlogo/core/Syntax$.PatchType ()I
          IOR
          GETSTATIC org/nlogo/core/Syntax$.MODULE$ : Lorg/nlogo/core/Syntax$;
          INVOKEVIRTUAL org/nlogo/core/Syntax$.TurtlesetType ()I
          IOR
          GETSTATIC org/nlogo/core/Syntax$.MODULE$ : Lorg/nlogo/core/Syntax$;
          INVOKEVIRTUAL org/nlogo/core/Syntax$.PatchsetType ()I
          IOR
          ALOAD 2
          INVOKESPECIAL org/nlogo/nvm/ArgumentTypeException.<init> (Lorg/nlogo/nvm/Context;Lorg/nlogo/nvm/Instruction;IILjava/lang/Object;)V
          ATHROW
         L18
         FRAME FULL [org/nlogo/prim/_asm_procedureflow_setprocedurevariable_7 org/nlogo/nvm/Context java/lang/Object java/lang/Object org/nlogo/agent/Agent] [org/nlogo/api/AgentException]
          ASTORE 6
          NEW org/nlogo/nvm/EngineException
          DUP
          ALOAD 1
          ALOAD 0
          ALOAD 6
          INVOKEVIRTUAL org/nlogo/api/AgentException.getMessage ()Ljava/lang/String;
          INVOKESPECIAL org/nlogo/nvm/EngineException.<init> (Lorg/nlogo/nvm/Context;Lorg/nlogo/nvm/Instruction;Ljava/lang/String;)V
          ATHROW
         L15
         FRAME FULL [org/nlogo/prim/_asm_procedureflow_setprocedurevariable_7 org/nlogo/nvm/Context java/lang/Object java/lang/Object D T org/nlogo/agent/AgentSet org/nlogo/api/LogoListBuilder] [org/nlogo/api/AgentException]
          ASTORE 9
          NEW org/nlogo/nvm/EngineException
          DUP
          ALOAD 1
          ALOAD 0
          ALOAD 9
          INVOKEVIRTUAL org/nlogo/api/AgentException.getMessage ()Ljava/lang/String;
          INVOKESPECIAL org/nlogo/nvm/EngineException.<init> (Lorg/nlogo/nvm/Context;Lorg/nlogo/nvm/Instruction;Ljava/lang/String;)V
          ATHROW
         L41
         FRAME FULL [org/nlogo/prim/_asm_procedureflow_setprocedurevariable_7 org/nlogo/nvm/Context java/lang/Object java/lang/Object T java/lang/Object] [org/nlogo/api/LogoListBuilder org/nlogo/api/LogoListBuilder D D java/lang/Object]
          ASTORE 2
         L19
          ALOAD 2
          CHECKCAST java/lang/Double
          INVOKEVIRTUAL java/lang/Double.doubleValue ()D
          GOTO L42
         L20
         FRAME SAME1 java/lang/ClassCastException
          POP
          NEW org/nlogo/nvm/ArgumentTypeException
          DUP
          ALOAD 1
          ALOAD 0
          BIPUSH 1
          LDC 1
          ALOAD 2
          INVOKESPECIAL org/nlogo/nvm/ArgumentTypeException.<init> (Lorg/nlogo/nvm/Context;Lorg/nlogo/nvm/Instruction;IILjava/lang/Object;)V
          ATHROW
         L42
         FRAME FULL [org/nlogo/prim/_asm_procedureflow_setprocedurevariable_7 org/nlogo/nvm/Context java/lang/Object java/lang/Object T java/lang/Object] [org/nlogo/api/LogoListBuilder org/nlogo/api/LogoListBuilder D D D]
          DSTORE 4
          DSTORE 2
          ALOAD 0
          DLOAD 2
          DLOAD 4
          DSUB
          INVOKEVIRTUAL org/nlogo/prim/_asm_procedureflow_setprocedurevariable_7.validDouble (D)D
         L43
          ALOAD 1
          GETFIELD org/nlogo/nvm/Context.activation : Lorg/nlogo/nvm/Activation;
          GETFIELD org/nlogo/nvm/Activation.args : [Ljava/lang/Object;
          ICONST_0
          AALOAD
         L44
          ASTORE 2
          ALOAD 2
          ASTORE 3
          ALOAD 3
          INSTANCEOF org/nlogo/agent/Agent
          IFEQ L45
          ALOAD 3
          CHECKCAST org/nlogo/agent/Agent
          ASTORE 4
          ALOAD 4
          GETFIELD org/nlogo/agent/Agent.id : J
          LDC -1
          LCMP
          IFNE L24
          NEW org/nlogo/nvm/EngineException
          DUP
          ALOAD 1
          ALOAD 0
          GETSTATIC org/nlogo/core/I18N$.MODULE$ : Lorg/nlogo/core/I18N$;
          INVOKEVIRTUAL org/nlogo/core/I18N$.errors ()Lorg/nlogo/core/I18N$BundleKind;
          LDC "org.nlogo.$common.thatAgentIsDead"
          GETSTATIC scala/Predef$.MODULE$ : Lscala/Predef$;
          ICONST_1
          ANEWARRAY java/lang/Object
          DUP
          ICONST_0
          ALOAD 4
          INVOKEVIRTUAL org/nlogo/agent/Agent.classDisplayName ()Ljava/lang/String;
          AASTORE
          INVOKEVIRTUAL scala/Predef$.wrapRefArray ([Ljava/lang/Object;)Lscala/collection/mutable/WrappedArray;
          INVOKEVIRTUAL org/nlogo/core/I18N$BundleKind.getN (Ljava/lang/String;Lscala/collection/Seq;)Ljava/lang/String;
          INVOKESPECIAL org/nlogo/nvm/EngineException.<init> (Lorg/nlogo/nvm/Context;Lorg/nlogo/nvm/Instruction;Ljava/lang/String;)V
          ATHROW
         L24
         FRAME FULL [org/nlogo/prim/_asm_procedureflow_setprocedurevariable_7 org/nlogo/nvm/Context java/lang/Object java/lang/Object org/nlogo/agent/Agent] [org/nlogo/api/LogoListBuilder org/nlogo/api/LogoListBuilder D D]
          ALOAD 4
          BIPUSH 6
          INVOKEVIRTUAL org/nlogo/agent/Agent.getPatchVariable (I)Ljava/lang/Object;
         L25
          ASTORE 5
          GOTO L46
         L45
         FRAME FULL [org/nlogo/prim/_asm_procedureflow_setprocedurevariable_7 org/nlogo/nvm/Context java/lang/Object java/lang/Object D] [org/nlogo/api/LogoListBuilder org/nlogo/api/LogoListBuilder D D]
          ALOAD 3
          INSTANCEOF org/nlogo/agent/AgentSet
          IFEQ L47
          ALOAD 3
          CHECKCAST org/nlogo/agent/AgentSet
          ASTORE 7
          NEW org/nlogo/api/LogoListBuilder
          DUP
          INVOKESPECIAL org/nlogo/api/LogoListBuilder.<init> ()V
          ASTORE 8
         L21
          ALOAD 7
          ALOAD 1
          GETFIELD org/nlogo/nvm/Context.job : Lorg/nlogo/nvm/Job;
          GETFIELD org/nlogo/nvm/Job.random : Lorg/nlogo/api/MersenneTwisterFast;
          INVOKEVIRTUAL org/nlogo/agent/AgentSet.shufflerator (Lorg/nlogo/api/MersenneTwisterFast;)Lorg/nlogo/agent/AgentSet$Iterator;
          ASTORE 10
         L48
         FRAME FULL [org/nlogo/prim/_asm_procedureflow_setprocedurevariable_7 org/nlogo/nvm/Context java/lang/Object java/lang/Object D T org/nlogo/agent/AgentSet org/nlogo/api/LogoListBuilder T org/nlogo/agent/AgentSet$Iterator] [org/nlogo/api/LogoListBuilder org/nlogo/api/LogoListBuilder D D]
          ALOAD 10
          INVOKEINTERFACE org/nlogo/agent/AgentSet$Iterator.hasNext ()Z
          IFEQ L22
          ALOAD 8
          ALOAD 10
          INVOKEINTERFACE org/nlogo/agent/AgentSet$Iterator.next ()Lorg/nlogo/agent/Agent;
          BIPUSH 6
          INVOKEVIRTUAL org/nlogo/agent/Agent.getPatchVariable (I)Ljava/lang/Object;
          INVOKEVIRTUAL org/nlogo/api/LogoListBuilder.add (Ljava/lang/Object;)V
          GOTO L48
         L22
         FRAME FULL [org/nlogo/prim/_asm_procedureflow_setprocedurevariable_7 org/nlogo/nvm/Context java/lang/Object java/lang/Object D T org/nlogo/agent/AgentSet org/nlogo/api/LogoListBuilder T org/nlogo/agent/AgentSet$Iterator] [org/nlogo/api/LogoListBuilder org/nlogo/api/LogoListBuilder D D]
          ALOAD 8
          INVOKEVIRTUAL org/nlogo/api/LogoListBuilder.toLogoList ()Lorg/nlogo/core/LogoList;
          ASTORE 5
         L46
         FRAME FULL [org/nlogo/prim/_asm_procedureflow_setprocedurevariable_7 org/nlogo/nvm/Context java/lang/Object java/lang/Object T java/lang/Object] [org/nlogo/api/LogoListBuilder org/nlogo/api/LogoListBuilder D D]
          ALOAD 5
          GOTO L49
         L47
         FRAME FULL [org/nlogo/prim/_asm_procedureflow_setprocedurevariable_7 org/nlogo/nvm/Context java/lang/Object java/lang/Object D] [org/nlogo/api/LogoListBuilder org/nlogo/api/LogoListBuilder D D]
          NEW org/nlogo/nvm/ArgumentTypeException
          DUP
          ALOAD 1
          ALOAD 0
          ICONST_0
          GETSTATIC org/nlogo/core/Syntax$.MODULE$ : Lorg/nlogo/core/Syntax$;
          INVOKEVIRTUAL org/nlogo/core/Syntax$.TurtleType ()I
          GETSTATIC org/nlogo/core/Syntax$.MODULE$ : Lorg/nlogo/core/Syntax$;
          INVOKEVIRTUAL org/nlogo/core/Syntax$.PatchType ()I
          IOR
          GETSTATIC org/nlogo/core/Syntax$.MODULE$ : Lorg/nlogo/core/Syntax$;
          INVOKEVIRTUAL org/nlogo/core/Syntax$.TurtlesetType ()I
          IOR
          GETSTATIC org/nlogo/core/Syntax$.MODULE$ : Lorg/nlogo/core/Syntax$;
          INVOKEVIRTUAL org/nlogo/core/Syntax$.PatchsetType ()I
          IOR
          ALOAD 2
          INVOKESPECIAL org/nlogo/nvm/ArgumentTypeException.<init> (Lorg/nlogo/nvm/Context;Lorg/nlogo/nvm/Instruction;IILjava/lang/Object;)V
          ATHROW
         L26
         FRAME FULL [org/nlogo/prim/_asm_procedureflow_setprocedurevariable_7 org/nlogo/nvm/Context java/lang/Object java/lang/Object org/nlogo/agent/Agent] [org/nlogo/api/AgentException]
          ASTORE 6
          NEW org/nlogo/nvm/EngineException
          DUP
          ALOAD 1
          ALOAD 0
          ALOAD 6
          INVOKEVIRTUAL org/nlogo/api/AgentException.getMessage ()Ljava/lang/String;
          INVOKESPECIAL org/nlogo/nvm/EngineException.<init> (Lorg/nlogo/nvm/Context;Lorg/nlogo/nvm/Instruction;Ljava/lang/String;)V
          ATHROW
         L23
         FRAME FULL [org/nlogo/prim/_asm_procedureflow_setprocedurevariable_7 org/nlogo/nvm/Context java/lang/Object java/lang/Object D T org/nlogo/agent/AgentSet org/nlogo/api/LogoListBuilder] [org/nlogo/api/AgentException]
          ASTORE 9
          NEW org/nlogo/nvm/EngineException
          DUP
          ALOAD 1
          ALOAD 0
          ALOAD 9
          INVOKEVIRTUAL org/nlogo/api/AgentException.getMessage ()Ljava/lang/String;
          INVOKESPECIAL org/nlogo/nvm/EngineException.<init> (Lorg/nlogo/nvm/Context;Lorg/nlogo/nvm/Instruction;Ljava/lang/String;)V
          ATHROW
         L49
         FRAME FULL [org/nlogo/prim/_asm_procedureflow_setprocedurevariable_7 org/nlogo/nvm/Context java/lang/Object java/lang/Object T java/lang/Object] [org/nlogo/api/LogoListBuilder org/nlogo/api/LogoListBuilder D D java/lang/Object]
          ASTORE 2
         L27
          ALOAD 2
          CHECKCAST java/lang/Double
          INVOKEVIRTUAL java/lang/Double.doubleValue ()D
          GOTO L50
         L28
         FRAME SAME1 java/lang/ClassCastException
          POP
          NEW org/nlogo/nvm/ArgumentTypeException
          DUP
          ALOAD 1
          ALOAD 0
          BIPUSH 1
          LDC 1
          ALOAD 2
          INVOKESPECIAL org/nlogo/nvm/ArgumentTypeException.<init> (Lorg/nlogo/nvm/Context;Lorg/nlogo/nvm/Instruction;IILjava/lang/Object;)V
          ATHROW
         L50
         FRAME FULL [org/nlogo/prim/_asm_procedureflow_setprocedurevariable_7 org/nlogo/nvm/Context java/lang/Object java/lang/Object T java/lang/Object] [org/nlogo/api/LogoListBuilder org/nlogo/api/LogoListBuilder D D D]
          DSTORE 4
          DSTORE 2
          ALOAD 0
          DLOAD 2
          DLOAD 4
          DSUB
          INVOKEVIRTUAL org/nlogo/prim/_asm_procedureflow_setprocedurevariable_7.validDouble (D)D
         L51
          DSTORE 4
          DSTORE 2
          ALOAD 0
          DLOAD 2
          DLOAD 4
          DMUL
          INVOKEVIRTUAL org/nlogo/prim/_asm_procedureflow_setprocedurevariable_7.validDouble (D)D
         L52
          DSTORE 2
          NEW java/lang/Double
          DUP
          DLOAD 2
          INVOKESPECIAL java/lang/Double.<init> (D)V
          INVOKEVIRTUAL org/nlogo/api/LogoListBuilder.add (Ljava/lang/Object;)V
          INVOKEVIRTUAL org/nlogo/api/LogoListBuilder.toLogoList ()Lorg/nlogo/core/LogoList;
         L53
          ASTORE 2
          DCONST_0
          DSTORE 3
          ACONST_NULL
          ASTORE 5
          ALOAD 2
          INVOKEVIRTUAL org/nlogo/core/LogoList.javaIterable ()Ljava/lang/Iterable;
          INVOKEINTERFACE java/lang/Iterable.iterator ()Ljava/util/Iterator;
          ASTORE 6
         L54
         FRAME FULL [org/nlogo/prim/_asm_procedureflow_setprocedurevariable_7 org/nlogo/nvm/Context org/nlogo/core/LogoList D java/lang/Double java/util/Iterator] []
          ALOAD 6
          INVOKEINTERFACE java/util/Iterator.hasNext ()Z
          IFEQ L55
          ALOAD 6
          INVOKEINTERFACE java/util/Iterator.next ()Ljava/lang/Object;
          ASTORE 7
          ALOAD 7
          INSTANCEOF java/lang/Double
          IFEQ L56
          ALOAD 7
          CHECKCAST java/lang/Double
          ASTORE 8
          ALOAD 8
          INVOKEVIRTUAL java/lang/Double.doubleValue ()D
          DSTORE 9
          ALOAD 5
          IFNULL L57
          DLOAD 9
          DLOAD 3
          DCMPG
          IFGE L56
         L57
         FRAME APPEND [java/lang/Object java/lang/Double D]
          DLOAD 9
          DSTORE 3
          ALOAD 8
          ASTORE 5
         L56
         FRAME CHOP 2
          GOTO L54
         L55
         FRAME CHOP 1
          ALOAD 5
          IFNONNULL L58
          NEW org/nlogo/nvm/EngineException
          DUP
          ALOAD 1
          ALOAD 0
          INVOKESTATIC org/nlogo/core/I18N.errorsJ ()Lorg/nlogo/core/I18NJava;
          LDC "org.nlogo.prim._min.cantFindMinOfListWithNoNumbers"
          ICONST_1
          ANEWARRAY java/lang/Object
          DUP
          ICONST_0
          ALOAD 2
          INVOKESTATIC org/nlogo/api/Dump.logoObject (Ljava/lang/Object;)Ljava/lang/String;
          AASTORE
          INVOKEINTERFACE org/nlogo/core/I18NJava.getN (Ljava/lang/String;[Ljava/lang/Object;)Ljava/lang/String;
          INVOKESPECIAL org/nlogo/nvm/EngineException.<init> (Lorg/nlogo/nvm/Context;Lorg/nlogo/nvm/Instruction;Ljava/lang/String;)V
          ATHROW
         L58
         FRAME SAME
          ALOAD 5
          INVOKEVIRTUAL java/lang/Double.doubleValue ()D
         L59
          DSTORE 2
          NEW java/lang/Double
          DUP
          DLOAD 2
          INVOKESPECIAL java/lang/Double.<init> (D)V
          ASTORE 2
          ALOAD 1
          GETFIELD org/nlogo/nvm/Context.activation : Lorg/nlogo/nvm/Activation;
          GETFIELD org/nlogo/nvm/Activation.args : [Ljava/lang/Object;
          ICONST_1
          ALOAD 2
          AASTORE
          ALOAD 1
          BIPUSH 6
          PUTFIELD org/nlogo/nvm/Context.ip : I
         L60
          RETURN
[6]_asm_procedureflow_setpatchvariable_8 "set water water - amount" Object => void
      _minus "water - amount" double,double => double
        _patchvariable:WATER "water" => Object
        _procedurevariable:AMOUNT "amount" => Object
          TRYCATCHBLOCK L0 L1 L2 org/nlogo/api/AgentException
          TRYCATCHBLOCK L3 L4 L4 java/lang/ClassCastException
          TRYCATCHBLOCK L5 L6 L6 java/lang/ClassCastException
          TRYCATCHBLOCK L7 L8 L9 org/nlogo/api/AgentException
         L0
          ALOAD 1
          GETFIELD org/nlogo/nvm/Context.agent : Lorg/nlogo/agent/Agent;
          BIPUSH 6
          INVOKEVIRTUAL org/nlogo/agent/Agent.getPatchVariable (I)Ljava/lang/Object;
         L1
          GOTO L10
         L2
         FRAME SAME1 org/nlogo/api/AgentException
          ASTORE 2
          NEW org/nlogo/nvm/EngineException
          DUP
          ALOAD 1
          ALOAD 0
          ALOAD 2
          INVOKEVIRTUAL org/nlogo/api/AgentException.getMessage ()Ljava/lang/String;
          INVOKESPECIAL org/nlogo/nvm/EngineException.<init> (Lorg/nlogo/nvm/Context;Lorg/nlogo/nvm/Instruction;Ljava/lang/String;)V
          ATHROW
         L10
         FRAME SAME1 java/lang/Object
          ASTORE 2
         L3
          ALOAD 2
          CHECKCAST java/lang/Double
          INVOKEVIRTUAL java/lang/Double.doubleValue ()D
          GOTO L11
         L4
         FRAME FULL [org/nlogo/prim/_asm_procedureflow_setpatchvariable_8 org/nlogo/nvm/Context java/lang/Object] [java/lang/ClassCastException]
          POP
          NEW org/nlogo/nvm/ArgumentTypeException
          DUP
          ALOAD 1
          ALOAD 0
          BIPUSH 0
          LDC 1
          ALOAD 2
          INVOKESPECIAL org/nlogo/nvm/ArgumentTypeException.<init> (Lorg/nlogo/nvm/Context;Lorg/nlogo/nvm/Instruction;IILjava/lang/Object;)V
          ATHROW
         L11
         FRAME SAME1 D
          ALOAD 1
          GETFIELD org/nlogo/nvm/Context.activation : Lorg/nlogo/nvm/Activation;
          GETFIELD org/nlogo/nvm/Activation.args : [Ljava/lang/Object;
          ICONST_1
          AALOAD
         L12
          ASTORE 2
         L5
          ALOAD 2
          CHECKCAST java/lang/Double
          INVOKEVIRTUAL java/lang/Double.doubleValue ()D
          GOTO L13
         L6
         FRAME SAME1 java/lang/ClassCastException
          POP
          NEW org/nlogo/nvm/ArgumentTypeException
          DUP
          ALOAD 1
          ALOAD 0
          BIPUSH 1
          LDC 1
          ALOAD 2
          INVOKESPECIAL org/nlogo/nvm/ArgumentTypeException.<init> (Lorg/nlogo/nvm/Context;Lorg/nlogo/nvm/Instruction;IILjava/lang/Object;)V
          ATHROW
         L13
         FRAME FULL [org/nlogo/prim/_asm_procedureflow_setpatchvariable_8 org/nlogo/nvm/Context java/lang/Object] [D D]
          DSTORE 4
          DSTORE 2
          ALOAD 0
          DLOAD 2
          DLOAD 4
          DSUB
          INVOKEVIRTUAL org/nlogo/prim/_asm_procedureflow_setpatchvariable_8.validDouble (D)D
         L14
          DSTORE 2
          NEW java/lang/Double
          DUP
          DLOAD 2
          INVOKESPECIAL java/lang/Double.<init> (D)V
          ASTORE 2
         L7
          ALOAD 1
          GETFIELD org/nlogo/nvm/Context.agent : Lorg/nlogo/agent/Agent;
          BIPUSH 6
          ALOAD 2
          INVOKEVIRTUAL org/nlogo/agent/Agent.setPatchVariable (ILjava/lang/Object;)V
         L8
          GOTO L15
         L9
         FRAME FULL [org/nlogo/prim/_asm_procedureflow_setpatchvariable_8 org/nlogo/nvm/Context java/lang/Double T D] [org/nlogo/api/AgentException]
          ASTORE 3
          NEW org/nlogo/nvm/EngineException
          DUP
          ALOAD 1
          ALOAD 0
          ALOAD 3
          INVOKEVIRTUAL org/nlogo/api/AgentException.getMessage ()Ljava/lang/String;
          INVOKESPECIAL org/nlogo/nvm/EngineException.<init> (Lorg/nlogo/nvm/Context;Lorg/nlogo/nvm/Instruction;Ljava/lang/String;)V
          ATHROW
         L15
         FRAME SAME
          ALOAD 1
          BIPUSH 7
          PUTFIELD org/nlogo/nvm/Context.ip : I
         L16
          RETURN
[7]_asm_procedureflow_ask_9 "ask target [ set water water + amount ]" Object => void
      _procedurevariable:TARGET "target" => Object
         L0
          ALOAD 1
          GETFIELD org/nlogo/nvm/Context.activation : Lorg/nlogo/nvm/Activation;
          GETFIELD org/nlogo/nvm/Activation.args : [Ljava/lang/Object;
          ICONST_0
          AALOAD
         L1
          ASTORE 2
          ALOAD 2
          INSTANCEOF org/nlogo/agent/AgentSet
          IFEQ L2
          ALOAD 2
          CHECKCAST org/nlogo/agent/AgentSet
          ASTORE 3
          ALOAD 1
          GETFIELD org/nlogo/nvm/Context.agent : Lorg/nlogo/agent/Agent;
          INSTANCEOF org/nlogo/agent/Observer
          IFNE L3
          ALOAD 3
          ALOAD 0
          GETFIELD org/nlogo/prim/_asm_procedureflow_ask_9.world : Lorg/nlogo/agent/World;
          INVOKEVIRTUAL org/nlogo/agent/World.turtles ()Lorg/nlogo/agent/AgentSet;
          IF_ACMPNE L4
          NEW org/nlogo/nvm/EngineException
          DUP
          ALOAD 1
          ALOAD 0
          INVOKESTATIC org/nlogo/core/I18N.errorsJ ()Lorg/nlogo/core/I18NJava;
          LDC "org.nlogo.prim.$common.onlyObserverCanAskAllTurtles"
          INVOKEINTERFACE org/nlogo/core/I18NJava.get (Ljava/lang/String;)Ljava/lang/String;
          INVOKESPECIAL org/nlogo/nvm/EngineException.<init> (Lorg/nlogo/nvm/Context;Lorg/nlogo/nvm/Instruction;Ljava/lang/String;)V
          ATHROW
         L4
         FRAME APPEND [java/lang/Object org/nlogo/agent/AgentSet]
          ALOAD 3
          ALOAD 0
          GETFIELD org/nlogo/prim/_asm_procedureflow_ask_9.world : Lorg/nlogo/agent/World;
          INVOKEVIRTUAL org/nlogo/agent/World.patches ()Lorg/nlogo/agent/AgentSet;
          IF_ACMPNE L3
          NEW org/nlogo/nvm/EngineException
          DUP
          ALOAD 1
          ALOAD 0
          INVOKESTATIC org/nlogo/core/I18N.errorsJ ()Lorg/nlogo/core/I18NJava;
          LDC "org.nlogo.prim.$common.onlyObserverCanAskAllPatches"
          INVOKEINTERFACE org/nlogo/core/I18NJava.get (Ljava/lang/String;)Ljava/lang/String;
          INVOKESPECIAL org/nlogo/nvm/EngineException.<init> (Lorg/nlogo/nvm/Context;Lorg/nlogo/nvm/Instruction;Ljava/lang/String;)V
          ATHROW
         L2
         FRAME CHOP 1
          ALOAD 2
          INSTANCEOF org/nlogo/agent/Agent
          IFEQ L5
          ALOAD 2
          CHECKCAST org/nlogo/agent/Agent
          ASTORE 4
          ALOAD 4
          GETFIELD org/nlogo/agent/Agent.id : J
          LDC -1
          LCMP
          IFNE L6
          NEW org/nlogo/nvm/EngineException
          DUP
          ALOAD 1
          ALOAD 0
          INVOKESTATIC org/nlogo/core/I18N.errorsJ ()Lorg/nlogo/core/I18NJava;
          LDC "org.nlogo.$common.thatAgentIsDead"
          ICONST_1
          ANEWARRAY java/lang/Object
          DUP
          ICONST_0
          ALOAD 4
          INVOKEVIRTUAL org/nlogo/agent/Agent.classDisplayName ()Ljava/lang/String;
          AASTORE
          INVOKEINTERFACE org/nlogo/core/I18NJava.getN (Ljava/lang/String;[Ljava/lang/Object;)Ljava/lang/String;
          INVOKESPECIAL org/nlogo/nvm/EngineException.<init> (Lorg/nlogo/nvm/Context;Lorg/nlogo/nvm/Instruction;Ljava/lang/String;)V
          ATHROW
         L6
         FRAME APPEND [T org/nlogo/agent/Agent]
          NEW org/nlogo/agent/ArrayAgentSet
          DUP
          ALOAD 4
          INVOKEVIRTUAL org/nlogo/agent/Agent.kind ()Lorg/nlogo/core/AgentKind;
          ICONST_1
          ICONST_0
          INVOKESPECIAL org/nlogo/agent/ArrayAgentSet.<init> (Lorg/nlogo/core/AgentKind;IZ)V
          ASTORE 3
          ALOAD 3
          ALOAD 4
          INVOKEVIRTUAL org/nlogo/agent/AgentSet.add (Lorg/nlogo/agent/Agent;)V
          GOTO L3
         L5
         FRAME CHOP 2
          NEW org/nlogo/nvm/ArgumentTypeException
          DUP
          ALOAD 1
          ALOAD 0
          ICONST_0
          INVOKESTATIC org/nlogo/core/Syntax.AgentsetType ()I
          INVOKESTATIC org/nlogo/core/Syntax.AgentType ()I
          IOR
          ALOAD 2
          INVOKESPECIAL org/nlogo/nvm/ArgumentTypeException.<init> (Lorg/nlogo/nvm/Context;Lorg/nlogo/nvm/Instruction;IILjava/lang/Object;)V
          ATHROW
         L3
         FRAME APPEND [org/nlogo/agent/AgentSet]
          ALOAD 1
          ALOAD 3
          BIPUSH 8
          INVOKEVIRTUAL org/nlogo/nvm/Context.runExclusiveJob (Lorg/nlogo/agent/AgentSet;I)V
          ALOAD 1
          BIPUSH 10
          PUTFIELD org/nlogo/nvm/Context.ip : I
         L7
          RETURN
[8]_asm_procedureflow_setpatchvariable_10 "set water water + amount" Object => void
      _plus "water + amount" double,double => double
        _patchvariable:WATER "water" => Object
        _procedurevariable:AMOUNT "amount" => Object
          TRYCATCHBLOCK L0 L1 L2 org/nlogo/api/AgentException
          TRYCATCHBLOCK L3 L4 L4 java/lang/ClassCastException
          TRYCATCHBLOCK L5 L6 L6 java/lang/ClassCastException
          TRYCATCHBLOCK L7 L8 L9 org/nlogo/api/AgentException
         L0
          ALOAD 1
          GETFIELD org/nlogo/nvm/Context.agent : Lorg/nlogo/agent/Agent;
          BIPUSH 6
          INVOKEVIRTUAL org/nlogo/agent/Agent.getPatchVariable (I)Ljava/lang/Object;
         L1
          GOTO L10
         L2
         FRAME SAME1 org/nlogo/api/AgentException
          ASTORE 2
          NEW org/nlogo/nvm/EngineException
          DUP
          ALOAD 1
          ALOAD 0
          ALOAD 2
          INVOKEVIRTUAL org/nlogo/api/AgentException.getMessage ()Ljava/lang/String;
          INVOKESPECIAL org/nlogo/nvm/EngineException.<init> (Lorg/nlogo/nvm/Context;Lorg/nlogo/nvm/Instruction;Ljava/lang/String;)V
          ATHROW
         L10
         FRAME SAME1 java/lang/Object
          ASTORE 2
         L3
          ALOAD 2
          CHECKCAST java/lang/Double
          INVOKEVIRTUAL java/lang/Double.doubleValue ()D
          GOTO L11
         L4
         FRAME FULL [org/nlogo/prim/_asm_procedureflow_setpatchvariable_10 org/nlogo/nvm/Context java/lang/Object] [java/lang/ClassCastException]
          POP
          NEW org/nlogo/nvm/ArgumentTypeException
          DUP
          ALOAD 1
          ALOAD 0
          BIPUSH 0
          LDC 1
          ALOAD 2
          INVOKESPECIAL org/nlogo/nvm/ArgumentTypeException.<init> (Lorg/nlogo/nvm/Context;Lorg/nlogo/nvm/Instruction;IILjava/lang/Object;)V
          ATHROW
         L11
         FRAME SAME1 D
          ALOAD 1
          GETFIELD org/nlogo/nvm/Context.activation : Lorg/nlogo/nvm/Activation;
          GETFIELD org/nlogo/nvm/Activation.args : [Ljava/lang/Object;
          ICONST_1
          AALOAD
         L12
          ASTORE 2
         L5
          ALOAD 2
          CHECKCAST java/lang/Double
          INVOKEVIRTUAL java/lang/Double.doubleValue ()D
          GOTO L13
         L6
         FRAME SAME1 java/lang/ClassCastException
          POP
          NEW org/nlogo/nvm/ArgumentTypeException
          DUP
          ALOAD 1
          ALOAD 0
          BIPUSH 1
          LDC 1
          ALOAD 2
          INVOKESPECIAL org/nlogo/nvm/ArgumentTypeException.<init> (Lorg/nlogo/nvm/Context;Lorg/nlogo/nvm/Instruction;IILjava/lang/Object;)V
          ATHROW
         L13
         FRAME FULL [org/nlogo/prim/_asm_procedureflow_setpatchvariable_10 org/nlogo/nvm/Context java/lang/Object] [D D]
          DSTORE 4
          DSTORE 2
          ALOAD 0
          DLOAD 2
          DLOAD 4
          DADD
          INVOKEVIRTUAL org/nlogo/prim/_asm_procedureflow_setpatchvariable_10.validDouble (D)D
         L14
          DSTORE 2
          NEW java/lang/Double
          DUP
          DLOAD 2
          INVOKESPECIAL java/lang/Double.<init> (D)V
          ASTORE 2
         L7
          ALOAD 1
          GETFIELD org/nlogo/nvm/Context.agent : Lorg/nlogo/agent/Agent;
          BIPUSH 6
          ALOAD 2
          INVOKEVIRTUAL org/nlogo/agent/Agent.setPatchVariable (ILjava/lang/Object;)V
         L8
          GOTO L15
         L9
         FRAME FULL [org/nlogo/prim/_asm_procedureflow_setpatchvariable_10 org/nlogo/nvm/Context java/lang/Double T D] [org/nlogo/api/AgentException]
          ASTORE 3
          NEW org/nlogo/nvm/EngineException
          DUP
          ALOAD 1
          ALOAD 0
          ALOAD 3
          INVOKEVIRTUAL org/nlogo/api/AgentException.getMessage ()Ljava/lang/String;
          INVOKESPECIAL org/nlogo/nvm/EngineException.<init> (Lorg/nlogo/nvm/Context;Lorg/nlogo/nvm/Instruction;Ljava/lang/String;)V
          ATHROW
         L15
         FRAME SAME
          ALOAD 1
          BIPUSH 9
          PUTFIELD org/nlogo/nvm/Context.ip : I
         L16
          RETURN
[9]_asm_procedureflow_done_11 => void
         L0
          ALOAD 1
          ICONST_1
          PUTFIELD org/nlogo/nvm/Context.finished : Z
         L1
          RETURN
[10]_asm_procedureflow_return_12 => void
         L0
          ALOAD 1
          INVOKEVIRTUAL org/nlogo/nvm/Context.returnFromProcedure ()V
          ALOAD 1
          ICONST_0
          PUTFIELD org/nlogo/nvm/Context.stopping : Z
         L1
          RETURN

procedure SETUP:[_repeatlocal:0]{O---}:
[0]_clearall "clear-all"
[1]_resetticks "reset-ticks"
[2]_asm_proceduresetup_setobservervariable_0 "set show-water? true" Object => void
      _constboolean:true "true" => Boolean
          TRYCATCHBLOCK L0 L1 L2 org/nlogo/api/AgentException
         L3
          ALOAD 0
          GETFIELD org/nlogo/prim/_asm_proceduresetup_setobservervariable_0.kept2_value : Ljava/lang/Boolean;
         L4
          ASTORE 2
         L0
          ALOAD 1
          GETFIELD org/nlogo/nvm/Context.agent : Lorg/nlogo/agent/Agent;
          BIPUSH 6
          ALOAD 2
          INVOKEVIRTUAL org/nlogo/agent/Agent.setObserverVariable (ILjava/lang/Object;)V
         L1
          GOTO L5
         L2
         FRAME FULL [org/nlogo/prim/_asm_proceduresetup_setobservervariable_0 org/nlogo/nvm/Context java/lang/Boolean] [org/nlogo/api/AgentException]
          ASTORE 3
          NEW org/nlogo/nvm/EngineException
          DUP
          ALOAD 1
          ALOAD 0
          ALOAD 3
          INVOKEVIRTUAL org/nlogo/api/AgentException.getMessage ()Ljava/lang/String;
          INVOKESPECIAL org/nlogo/nvm/EngineException.<init> (Lorg/nlogo/nvm/Context;Lorg/nlogo/nvm/Instruction;Ljava/lang/String;)V
          ATHROW
         L5
         FRAME SAME
          ALOAD 1
          ICONST_3
          PUTFIELD org/nlogo/nvm/Context.ip : I
         L6
          RETURN
[3]_asm_proceduresetup_ask_1 "ask patches ifelse bumpy? [ ifelse hill? [ set elevation -100 * distancexy 0 0 / max-pxcor + 100 + random 100 ] [ set elevation random 125 ] ] [ set elevation 100 ] set water 0 [ set drain? false ]" AgentSet => void
      _patches "patches" => AgentSet
         L0
          ALOAD 0
          GETFIELD org/nlogo/prim/_asm_proceduresetup_ask_1.world : Lorg/nlogo/agent/World;
          INVOKEVIRTUAL org/nlogo/agent/World.patches ()Lorg/nlogo/agent/AgentSet;
         L1
          ASTORE 2
          ALOAD 1
          GETFIELD org/nlogo/nvm/Context.agent : Lorg/nlogo/agent/Agent;
          INSTANCEOF org/nlogo/agent/Observer
          IFNE L2
          ALOAD 2
          ALOAD 0
          GETFIELD org/nlogo/prim/_asm_proceduresetup_ask_1.world : Lorg/nlogo/agent/World;
          INVOKEVIRTUAL org/nlogo/agent/World.turtles ()Lorg/nlogo/agent/AgentSet;
          IF_ACMPNE L3
          NEW org/nlogo/nvm/EngineException
          DUP
          ALOAD 1
          ALOAD 0
          INVOKESTATIC org/nlogo/core/I18N.errorsJ ()Lorg/nlogo/core/I18NJava;
          LDC "org.nlogo.prim.$common.onlyObserverCanAskAllTurtles"
          INVOKEINTERFACE org/nlogo/core/I18NJava.get (Ljava/lang/String;)Ljava/lang/String;
          INVOKESPECIAL org/nlogo/nvm/EngineException.<init> (Lorg/nlogo/nvm/Context;Lorg/nlogo/nvm/Instruction;Ljava/lang/String;)V
          ATHROW
         L3
         FRAME APPEND [org/nlogo/agent/AgentSet]
          ALOAD 2
          ALOAD 0
          GETFIELD org/nlogo/prim/_asm_proceduresetup_ask_1.world : Lorg/nlogo/agent/World;
          INVOKEVIRTUAL org/nlogo/agent/World.patches ()Lorg/nlogo/agent/AgentSet;
          IF_ACMPNE L2
          NEW org/nlogo/nvm/EngineException
          DUP
          ALOAD 1
          ALOAD 0
          INVOKESTATIC org/nlogo/core/I18N.errorsJ ()Lorg/nlogo/core/I18NJava;
          LDC "org.nlogo.prim.$common.onlyObserverCanAskAllPatches"
          INVOKEINTERFACE org/nlogo/core/I18NJava.get (Ljava/lang/String;)Ljava/lang/String;
          INVOKESPECIAL org/nlogo/nvm/EngineException.<init> (Lorg/nlogo/nvm/Context;Lorg/nlogo/nvm/Instruction;Ljava/lang/String;)V
          ATHROW
         L2
         FRAME SAME
          ALOAD 1
          ALOAD 2
          ICONST_4
          INVOKEVIRTUAL org/nlogo/nvm/Context.runExclusiveJob (Lorg/nlogo/agent/AgentSet;I)V
          ALOAD 1
          BIPUSH 14
          PUTFIELD org/nlogo/nvm/Context.ip : I
         L4
          RETURN
[4]_asm_proceduresetup_ifelse_2 "ifelse bumpy? [ ifelse hill? [ set elevation -100 * distancexy 0 0 / max-pxcor + 100 + random 100 ] [ set elevation random 125 ] ] [ set elevation 100 ]" boolean => void
      _observervariable:BUMPY? "bumpy?" => Object
          TRYCATCHBLOCK L0 L1 L1 java/lang/ClassCastException
         L2
          ALOAD 1
          GETFIELD org/nlogo/nvm/Context.agent : Lorg/nlogo/agent/Agent;
          ICONST_2
          INVOKEVIRTUAL org/nlogo/agent/Agent.getObserverVariable (I)Ljava/lang/Object;
         L3
          ASTORE 2
         L0
          ALOAD 2
          CHECKCAST java/lang/Boolean
          INVOKEVIRTUAL java/lang/Boolean.booleanValue ()Z
          GOTO L4
         L1
         FRAME FULL [org/nlogo/prim/_asm_proceduresetup_ifelse_2 org/nlogo/nvm/Context java/lang/Object] [java/lang/ClassCastException]
          POP
          NEW org/nlogo/nvm/ArgumentTypeException
          DUP
          ALOAD 1
          ALOAD 0
          BIPUSH 0
          LDC 2
          ALOAD 2
          INVOKESPECIAL org/nlogo/nvm/ArgumentTypeException.<init> (Lorg/nlogo/nvm/Context;Lorg/nlogo/nvm/Instruction;IILjava/lang/Object;)V
          ATHROW
         L4
         FRAME SAME1 I
          ISTORE 2
          ALOAD 1
          ILOAD 2
          IFEQ L5
          ICONST_5
          GOTO L6
         L5
         FRAME FULL [org/nlogo/prim/_asm_proceduresetup_ifelse_2 org/nlogo/nvm/Context I] [org/nlogo/nvm/Context]
          BIPUSH 10
         L6
         FRAME FULL [org/nlogo/prim/_asm_proceduresetup_ifelse_2 org/nlogo/nvm/Context I] [org/nlogo/nvm/Context I]
          PUTFIELD org/nlogo/nvm/Context.ip : I
         L7
          RETURN
[5]_asm_proceduresetup_ifelse_3 "ifelse hill? [ set elevation -100 * distancexy 0 0 / max-pxcor + 100 + random 100 ] [ set elevation random 125 ]" boolean => void
      _observervariable:HILL? "hill?" => Object
          TRYCATCHBLOCK L0 L1 L1 java/lang/ClassCastException
         L2
          ALOAD 1
          GETFIELD org/nlogo/nvm/Context.agent : Lorg/nlogo/agent/Agent;
          ICONST_4
          INVOKEVIRTUAL org/nlogo/agent/Agent.getObserverVariable (I)Ljava/lang/Object;
         L3
          ASTORE 2
         L0
          ALOAD 2
          CHECKCAST java/lang/Boolean
          INVOKEVIRTUAL java/lang/Boolean.booleanValue ()Z
          GOTO L4
         L1
         FRAME FULL [org/nlogo/prim/_asm_proceduresetup_ifelse_3 org/nlogo/nvm/Context java/lang/Object] [java/lang/ClassCastException]
          POP
          NEW org/nlogo/nvm/ArgumentTypeException
          DUP
          ALOAD 1
          ALOAD 0
          BIPUSH 0
          LDC 2
          ALOAD 2
          INVOKESPECIAL org/nlogo/nvm/ArgumentTypeException.<init> (Lorg/nlogo/nvm/Context;Lorg/nlogo/nvm/Instruction;IILjava/lang/Object;)V
          ATHROW
         L4
         FRAME SAME1 I
          ISTORE 2
          ALOAD 1
          ILOAD 2
          IFEQ L5
          BIPUSH 6
          GOTO L6
         L5
         FRAME FULL [org/nlogo/prim/_asm_proceduresetup_ifelse_3 org/nlogo/nvm/Context I] [org/nlogo/nvm/Context]
          BIPUSH 8
         L6
         FRAME FULL [org/nlogo/prim/_asm_proceduresetup_ifelse_3 org/nlogo/nvm/Context I] [org/nlogo/nvm/Context I]
          PUTFIELD org/nlogo/nvm/Context.ip : I
         L7
          RETURN
[6]_asm_proceduresetup_setpatchvariable_4 "set elevation -100 * distancexy 0 0 / max-pxcor + 100 + random 100" Object => void
      _plus "-100 * distancexy 0 0 / max-pxcor + 100 + random 100" double,double => double
        _plus "-100 * distancexy 0 0 / max-pxcor + 100" double,double => double
          _mult "-100 * distancexy 0 0 / max-pxcor" double,double => double
            _constdouble:-100.0 "-100" => double
            _div "distancexy 0 0 / max-pxcor" double,double => double
              _distancexy "distancexy 0 0" double,double => double
                _constdouble:0.0 "0" => double
                _constdouble:0.0 "0" => double
              _maxpxcor "max-pxcor" => double
          _constdouble:100.0 "100" => double
        _randomconst:100 "random 100" => double
          TRYCATCHBLOCK L0 L1 L2 org/nlogo/api/AgentException
         L3
          LDC -100.0
         L4
          DCONST_0
         L5
          DCONST_0
         L6
          DSTORE 4
          DSTORE 2
          ALOAD 0
          ALOAD 0
          GETFIELD org/nlogo/prim/_asm_proceduresetup_setpatchvariable_4.world : Lorg/nlogo/agent/World;
          INVOKEVIRTUAL org/nlogo/agent/World.protractor ()Lorg/nlogo/agent/Protractor;
          ALOAD 1
          GETFIELD org/nlogo/nvm/Context.agent : Lorg/nlogo/agent/Agent;
          DLOAD 2
          DLOAD 4
          ICONST_1
          INVOKEVIRTUAL org/nlogo/agent/Protractor.distance (Lorg/nlogo/api/Agent;DDZ)D
          INVOKEVIRTUAL org/nlogo/prim/_asm_proceduresetup_setpatchvariable_4.validDouble (D)D
         L7
          ALOAD 0
          GETFIELD org/nlogo/prim/_asm_proceduresetup_setpatchvariable_4.world : Lorg/nlogo/agent/World;
          INVOKEVIRTUAL org/nlogo/agent/World.maxPxcor ()I
          I2D
         L8
          DSTORE 4
          DSTORE 2
          DLOAD 4
          DCONST_0
          DCMPL
          IFNE L9
          NEW org/nlogo/nvm/EngineException
          DUP
          ALOAD 1
          ALOAD 0
          INVOKESTATIC org/nlogo/core/I18N.errorsJ ()Lorg/nlogo/core/I18NJava;
          LDC "org.nlogo.prim.etc.$common.divByZero"
          INVOKEINTERFACE org/nlogo/core/I18NJava.get (Ljava/lang/String;)Ljava/lang/String;
          INVOKESPECIAL org/nlogo/nvm/EngineException.<init> (Lorg/nlogo/nvm/Context;Lorg/nlogo/nvm/Instruction;Ljava/lang/String;)V
          ATHROW
         L9
         FRAME FULL [org/nlogo/prim/_asm_proceduresetup_setpatchvariable_4 org/nlogo/nvm/Context D D] [D]
          ALOAD 0
          DLOAD 2
          DLOAD 4
          DDIV
          INVOKEVIRTUAL org/nlogo/prim/_asm_proceduresetup_setpatchvariable_4.validDouble (D)D
         L10
          DSTORE 4
          DSTORE 2
          ALOAD 0
          DLOAD 2
          DLOAD 4
          DMUL
          INVOKEVIRTUAL org/nlogo/prim/_asm_proceduresetup_setpatchvariable_4.validDouble (D)D
         L11
          LDC 100.0
         L12
          DSTORE 4
          DSTORE 2
          ALOAD 0
          DLOAD 2
          DLOAD 4
          DADD
          INVOKEVIRTUAL org/nlogo/prim/_asm_proceduresetup_setpatchvariable_4.validDouble (D)D
         L13
          ALOAD 1
          GETFIELD org/nlogo/nvm/Context.job : Lorg/nlogo/nvm/Job;
          GETFIELD org/nlogo/nvm/Job.random : Lorg/nlogo/api/MersenneTwisterFast;
          LDC 100
          INVOKEVIRTUAL org/nlogo/api/MersenneTwisterFast.nextLong (J)J
          L2D
         L14
          DSTORE 4
          DSTORE 2
          ALOAD 0
          DLOAD 2
          DLOAD 4
          DADD
          INVOKEVIRTUAL org/nlogo/prim/_asm_proceduresetup_setpatchvariable_4.validDouble (D)D
         L15
          DSTORE 2
          NEW java/lang/Double
          DUP
          DLOAD 2
          INVOKESPECIAL java/lang/Double.<init> (D)V
          ASTORE 2
         L0
          ALOAD 1
          GETFIELD org/nlogo/nvm/Context.agent : Lorg/nlogo/agent/Agent;
          ICONST_5
          ALOAD 2
          INVOKEVIRTUAL org/nlogo/agent/Agent.setPatchVariable (ILjava/lang/Object;)V
         L1
          GOTO L16
         L2
         FRAME FULL [org/nlogo/prim/_asm_proceduresetup_setpatchvariable_4 org/nlogo/nvm/Context java/lang/Double T D] [org/nlogo/api/AgentException]
          ASTORE 3
          NEW org/nlogo/nvm/EngineException
          DUP
          ALOAD 1
          ALOAD 0
          ALOAD 3
          INVOKEVIRTUAL org/nlogo/api/AgentException.getMessage ()Ljava/lang/String;
          INVOKESPECIAL org/nlogo/nvm/EngineException.<init> (Lorg/nlogo/nvm/Context;Lorg/nlogo/nvm/Instruction;Ljava/lang/String;)V
          ATHROW
         L16
         FRAME SAME
          ALOAD 1
          BIPUSH 7
          PUTFIELD org/nlogo/nvm/Context.ip : I
         L17
          RETURN
[7]_asm_proceduresetup_goto_5 => void
         L0
          ALOAD 1
          BIPUSH 9
          PUTFIELD org/nlogo/nvm/Context.ip : I
         L1
          RETURN
[8]_asm_proceduresetup_setpatchvariable_6 "set elevation random 125" Object => void
      _randomconst:125 "random 125" => double
          TRYCATCHBLOCK L0 L1 L2 org/nlogo/api/AgentException
         L3
          ALOAD 1
          GETFIELD org/nlogo/nvm/Context.job : Lorg/nlogo/nvm/Job;
          GETFIELD org/nlogo/nvm/Job.random : Lorg/nlogo/api/MersenneTwisterFast;
          LDC 125
          INVOKEVIRTUAL org/nlogo/api/MersenneTwisterFast.nextLong (J)J
          L2D
         L4
          DSTORE 2
          NEW java/lang/Double
          DUP
          DLOAD 2
          INVOKESPECIAL java/lang/Double.<init> (D)V
          ASTORE 2
         L0
          ALOAD 1
          GETFIELD org/nlogo/nvm/Context.agent : Lorg/nlogo/agent/Agent;
          ICONST_5
          ALOAD 2
          INVOKEVIRTUAL org/nlogo/agent/Agent.setPatchVariable (ILjava/lang/Object;)V
         L1
          GOTO L5
         L2
         FRAME FULL [org/nlogo/prim/_asm_proceduresetup_setpatchvariable_6 org/nlogo/nvm/Context java/lang/Double] [org/nlogo/api/AgentException]
          ASTORE 3
          NEW org/nlogo/nvm/EngineException
          DUP
          ALOAD 1
          ALOAD 0
          ALOAD 3
          INVOKEVIRTUAL org/nlogo/api/AgentException.getMessage ()Ljava/lang/String;
          INVOKESPECIAL org/nlogo/nvm/EngineException.<init> (Lorg/nlogo/nvm/Context;Lorg/nlogo/nvm/Instruction;Ljava/lang/String;)V
          ATHROW
         L5
         FRAME SAME
          ALOAD 1
          BIPUSH 9
          PUTFIELD org/nlogo/nvm/Context.ip : I
         L6
          RETURN
[9]_asm_proceduresetup_goto_7 => void
         L0
          ALOAD 1
          BIPUSH 11
          PUTFIELD org/nlogo/nvm/Context.ip : I
         L1
          RETURN
[10]_asm_proceduresetup_setpatchvariable_8 "set elevation 100" Object => void
      _constdouble:100.0 "100" => Double
          TRYCATCHBLOCK L0 L1 L2 org/nlogo/api/AgentException
         L3
          ALOAD 0
          GETFIELD org/nlogo/prim/_asm_proceduresetup_setpatchvariable_8.kept2_value : Ljava/lang/Double;
         L4
          ASTORE 2
         L0
          ALOAD 1
          GETFIELD org/nlogo/nvm/Context.agent : Lorg/nlogo/agent/Agent;
          ICONST_5
          ALOAD 2
          INVOKEVIRTUAL org/nlogo/agent/Agent.setPatchVariable (ILjava/lang/Object;)V
         L1
          GOTO L5
         L2
         FRAME FULL [org/nlogo/prim/_asm_proceduresetup_setpatchvariable_8 org/nlogo/nvm/Context java/lang/Double] [org/nlogo/api/AgentException]
          ASTORE 3
          NEW org/nlogo/nvm/EngineException
          DUP
          ALOAD 1
          ALOAD 0
          ALOAD 3
          INVOKEVIRTUAL org/nlogo/api/AgentException.getMessage ()Ljava/lang/String;
          INVOKESPECIAL org/nlogo/nvm/EngineException.<init> (Lorg/nlogo/nvm/Context;Lorg/nlogo/nvm/Instruction;Ljava/lang/String;)V
          ATHROW
         L5
         FRAME SAME
          ALOAD 1
          BIPUSH 11
          PUTFIELD org/nlogo/nvm/Context.ip : I
         L6
          RETURN
[11]_asm_proceduresetup_setpatchvariable_9 "set water 0" Object => void
      _constdouble:0.0 "0" => Double
          TRYCATCHBLOCK L0 L1 L2 org/nlogo/api/AgentException
         L3
          ALOAD 0
          GETFIELD org/nlogo/prim/_asm_proceduresetup_setpatchvariable_9.kept2_value : Ljava/lang/Double;
         L4
          ASTORE 2
         L0
          ALOAD 1
          GETFIELD org/nlogo/nvm/Context.agent : Lorg/nlogo/agent/Agent;
          BIPUSH 6
          ALOAD 2
          INVOKEVIRTUAL org/nlogo/agent/Agent.setPatchVariable (ILjava/lang/Object;)V
         L1
          GOTO L5
         L2
         FRAME FULL [org/nlogo/prim/_asm_proceduresetup_setpatchvariable_9 org/nlogo/nvm/Context java/lang/Double] [org/nlogo/api/AgentException]
          ASTORE 3
          NEW org/nlogo/nvm/EngineException
          DUP
          ALOAD 1
          ALOAD 0
          ALOAD 3
          INVOKEVIRTUAL org/nlogo/api/AgentException.getMessage ()Ljava/lang/String;
          INVOKESPECIAL org/nlogo/nvm/EngineException.<init> (Lorg/nlogo/nvm/Context;Lorg/nlogo/nvm/Instruction;Ljava/lang/String;)V
          ATHROW
         L5
         FRAME SAME
          ALOAD 1
          BIPUSH 12
          PUTFIELD org/nlogo/nvm/Context.ip : I
         L6
          RETURN
[12]_asm_proceduresetup_setpatchvariable_10 "set drain? false" Object => void
      _constboolean:false "false" => Boolean
          TRYCATCHBLOCK L0 L1 L2 org/nlogo/api/AgentException
         L3
          ALOAD 0
          GETFIELD org/nlogo/prim/_asm_proceduresetup_setpatchvariable_10.kept2_value : Ljava/lang/Boolean;
         L4
          ASTORE 2
         L0
          ALOAD 1
          GETFIELD org/nlogo/nvm/Context.agent : Lorg/nlogo/agent/Agent;
          BIPUSH 7
          ALOAD 2
          INVOKEVIRTUAL org/nlogo/agent/Agent.setPatchVariable (ILjava/lang/Object;)V
         L1
          GOTO L5
         L2
         FRAME FULL [org/nlogo/prim/_asm_proceduresetup_setpatchvariable_10 org/nlogo/nvm/Context java/lang/Boolean] [org/nlogo/api/AgentException]
          ASTORE 3
          NEW org/nlogo/nvm/EngineException
          DUP
          ALOAD 1
          ALOAD 0
          ALOAD 3
          INVOKEVIRTUAL org/nlogo/api/AgentException.getMessage ()Ljava/lang/String;
          INVOKESPECIAL org/nlogo/nvm/EngineException.<init> (Lorg/nlogo/nvm/Context;Lorg/nlogo/nvm/Instruction;Ljava/lang/String;)V
          ATHROW
         L5
         FRAME SAME
          ALOAD 1
          BIPUSH 13
          PUTFIELD org/nlogo/nvm/Context.ip : I
         L6
          RETURN
[13]_asm_proceduresetup_done_11 => void
         L0
          ALOAD 1
          ICONST_1
          PUTFIELD org/nlogo/nvm/Context.finished : Z
         L1
          RETURN
[14]_asm_proceduresetup_if_12 "if bumpy? [ repeat terrain-smoothness [ diffuse 0.5 ] ]" boolean => void
      _observervariable:BUMPY? "bumpy?" => Object
          TRYCATCHBLOCK L0 L1 L1 java/lang/ClassCastException
         L2
          ALOAD 1
          GETFIELD org/nlogo/nvm/Context.agent : Lorg/nlogo/agent/Agent;
          ICONST_2
          INVOKEVIRTUAL org/nlogo/agent/Agent.getObserverVariable (I)Ljava/lang/Object;
         L3
          ASTORE 2
         L0
          ALOAD 2
          CHECKCAST java/lang/Boolean
          INVOKEVIRTUAL java/lang/Boolean.booleanValue ()Z
          GOTO L4
         L1
         FRAME FULL [org/nlogo/prim/_asm_proceduresetup_if_12 org/nlogo/nvm/Context java/lang/Object] [java/lang/ClassCastException]
          POP
          NEW org/nlogo/nvm/ArgumentTypeException
          DUP
          ALOAD 1
          ALOAD 0
          BIPUSH 0
          LDC 2
          ALOAD 2
          INVOKESPECIAL org/nlogo/nvm/ArgumentTypeException.<init> (Lorg/nlogo/nvm/Context;Lorg/nlogo/nvm/Instruction;IILjava/lang/Object;)V
          ATHROW
         L4
         FRAME SAME1 I
          ISTORE 2
          ALOAD 1
          ILOAD 2
          IFEQ L5
          BIPUSH 15
          GOTO L6
         L5
         FRAME FULL [org/nlogo/prim/_asm_proceduresetup_if_12 org/nlogo/nvm/Context I] [org/nlogo/nvm/Context]
          BIPUSH 18
         L6
         FRAME FULL [org/nlogo/prim/_asm_proceduresetup_if_12 org/nlogo/nvm/Context I] [org/nlogo/nvm/Context I]
          PUTFIELD org/nlogo/nvm/Context.ip : I
         L7
          RETURN
[15]_asm_proceduresetup_repeatlocal_13 "repeat terrain-smoothness [ diffuse 0.5 ]" double => void
      _observervariable:TERRAIN-SMOOTHNESS "terrain-smoothness" => Object
          TRYCATCHBLOCK L0 L1 L1 java/lang/ClassCastException
         L2
          ALOAD 1
          GETFIELD org/nlogo/nvm/Context.agent : Lorg/nlogo/agent/Agent;
          ICONST_0
          INVOKEVIRTUAL org/nlogo/agent/Agent.getObserverVariable (I)Ljava/lang/Object;
         L3
          ASTORE 2
         L0
          ALOAD 2
          CHECKCAST java/lang/Double
          INVOKEVIRTUAL java/lang/Double.doubleValue ()D
          GOTO L4
         L1
         FRAME FULL [org/nlogo/prim/_asm_proceduresetup_repeatlocal_13 org/nlogo/nvm/Context java/lang/Object] [java/lang/ClassCastException]
          POP
          NEW org/nlogo/nvm/ArgumentTypeException
          DUP
          ALOAD 1
          ALOAD 0
          BIPUSH 0
          LDC 1
          ALOAD 2
          INVOKESPECIAL org/nlogo/nvm/ArgumentTypeException.<init> (Lorg/nlogo/nvm/Context;Lorg/nlogo/nvm/Instruction;IILjava/lang/Object;)V
          ATHROW
         L4
         FRAME SAME1 D
          DSTORE 2
          ALOAD 1
          GETFIELD org/nlogo/nvm/Context.activation : Lorg/nlogo/nvm/Activation;
          GETFIELD org/nlogo/nvm/Activation.args : [Ljava/lang/Object;
          ICONST_0
          NEW org/nlogo/nvm/MutableLong
          DUP
          ALOAD 0
          DLOAD 2
          INVOKEVIRTUAL org/nlogo/prim/_asm_proceduresetup_repeatlocal_13.validLong (D)J
          INVOKESPECIAL org/nlogo/nvm/MutableLong.<init> (J)V
          AASTORE
          ALOAD 1
          BIPUSH 17
          PUTFIELD org/nlogo/nvm/Context.ip : I
         L5
          RETURN
[16]_diffuse:ELEVATION "diffuse 0.5"
      _asm_proceduresetup_constdouble_14 "0.5" => Double
           L0
            ALOAD 0
            GETFIELD org/nlogo/prim/_asm_proceduresetup_constdouble_14.kept1_value : Ljava/lang/Double;
           L1
            ARETURN
[17]_asm_proceduresetup_repeatlocalinternal_15 => void
         L0
          ALOAD 1
          GETFIELD org/nlogo/nvm/Context.activation : Lorg/nlogo/nvm/Activation;
          GETFIELD org/nlogo/nvm/Activation.args : [Ljava/lang/Object;
          ICONST_0
          AALOAD
          CHECKCAST org/nlogo/nvm/MutableLong
          ASTORE 2
          ALOAD 2
          INVOKEVIRTUAL org/nlogo/nvm/MutableLong.value ()J
          LCONST_0
          LCMP
          IFGT L1
          ALOAD 1
          BIPUSH 18
          PUTFIELD org/nlogo/nvm/Context.ip : I
          GOTO L2
         L1
         FRAME APPEND [org/nlogo/nvm/MutableLong]
          ALOAD 2
          ALOAD 2
          INVOKEVIRTUAL org/nlogo/nvm/MutableLong.value ()J
          LCONST_1
          LSUB
          INVOKEVIRTUAL org/nlogo/nvm/MutableLong.value_$eq (J)V
          ALOAD 1
          BIPUSH 16
          PUTFIELD org/nlogo/nvm/Context.ip : I
         L2
         FRAME SAME
          RETURN
[18]_asm_proceduresetup_ask_16 "ask patches with [ count neighbors != 8 ] set drain? true [ set elevation -10000000 ]" AgentSet => void
      _with "patches with [ count neighbors != 8 ]" AgentSet,Reporter => AgentSet
        _patches "patches" => AgentSet
        _asm_proceduresetup_notequal_17 "count neighbors != 8" double,double => boolean
          _count "count neighbors" AgentSet => double
            _neighbors "neighbors" => AgentSet
          _constdouble:8.0 "8" => double
             L0
              ALOAD 1
              GETFIELD org/nlogo/nvm/Context.agent : Lorg/nlogo/agent/Agent;
              INSTANCEOF org/nlogo/agent/Turtle
              IFEQ L1
              ALOAD 1
              GETFIELD org/nlogo/nvm/Context.agent : Lorg/nlogo/agent/Agent;
              CHECKCAST org/nlogo/agent/Turtle
              INVOKEVIRTUAL org/nlogo/agent/Turtle.getPatchHere ()Lorg/nlogo/agent/Patch;
              INVOKEVIRTUAL org/nlogo/agent/Patch.getNeighbors ()Lorg/nlogo/agent/AgentSet;
              GOTO L2
             L1
             FRAME SAME
              ALOAD 1
              GETFIELD org/nlogo/nvm/Context.agent : Lorg/nlogo/agent/Agent;
              CHECKCAST org/nlogo/agent/Patch
              INVOKEVIRTUAL org/nlogo/agent/Patch.getNeighbors ()Lorg/nlogo/agent/AgentSet;
             L2
             FRAME SAME1 org/nlogo/agent/AgentSet
              ASTORE 2
              ALOAD 2
              INVOKEVIRTUAL org/nlogo/agent/AgentSet.count ()I
              I2D
             L3
              LDC 8.0
             L4
              DSTORE 4
              DSTORE 2
              DLOAD 2
              DLOAD 4
              DCMPL
              IFEQ L5
              ICONST_1
              GOTO L6
             L5
             FRAME APPEND [D D]
              ICONST_0
             L6
             FRAME SAME1 I
              IFEQ L7
              GETSTATIC java/lang/Boolean.TRUE : Ljava/lang/Boolean;
              GOTO L8
             L7
             FRAME SAME
              GETSTATIC java/lang/Boolean.FALSE : Ljava/lang/Boolean;
             L8
             FRAME SAME1 java/lang/Boolean
              ARETURN
         L0
          ALOAD 0
          GETFIELD org/nlogo/prim/_asm_proceduresetup_ask_16.world : Lorg/nlogo/agent/World;
          INVOKEVIRTUAL org/nlogo/agent/World.patches ()Lorg/nlogo/agent/AgentSet;
         L1
          ALOAD 0
          GETFIELD org/nlogo/prim/_asm_proceduresetup_ask_16.keptinstr4 : Lorg/nlogo/nvm/Reporter;
          ASTORE 3
          ASTORE 2
          NEW org/nlogo/nvm/Context
          DUP
          ALOAD 1
          ALOAD 2
          INVOKESPECIAL org/nlogo/nvm/Context.<init> (Lorg/nlogo/nvm/Context;Lorg/nlogo/agent/AgentSet;)V
          ASTORE 4
          NEW java/util/ArrayList
          DUP
          INVOKESPECIAL java/util/ArrayList.<init> ()V
          ASTORE 5
          ALOAD 3
          ALOAD 2
          ALOAD 1
          INVOKEVIRTUAL org/nlogo/nvm/Reporter.checkAgentSetClass (Lorg/nlogo/agent/AgentSet;Lorg/nlogo/nvm/Context;)V
          ALOAD 2
          INVOKEVIRTUAL org/nlogo/agent/AgentSet.iterator ()Lorg/nlogo/agent/AgentSet$Iterator;
          ASTORE 6
         L2
         FRAME FULL [org/nlogo/prim/_asm_proceduresetup_ask_16 org/nlogo/nvm/Context org/nlogo/agent/AgentSet org/nlogo/nvm/Reporter org/nlogo/nvm/Context java/util/ArrayList org/nlogo/agent/AgentSet$Iterator] []
          ALOAD 6
          INVOKEINTERFACE org/nlogo/agent/AgentSet$Iterator.hasNext ()Z
          IFEQ L3
          ALOAD 6
          INVOKEINTERFACE org/nlogo/agent/AgentSet$Iterator.next ()Lorg/nlogo/agent/Agent;
          ASTORE 7
          ALOAD 4
          ALOAD 7
          ALOAD 3
          INVOKEVIRTUAL org/nlogo/nvm/Context.evaluateReporter (Lorg/nlogo/agent/Agent;Lorg/nlogo/nvm/Reporter;)Ljava/lang/Object;
          ASTORE 8
          ALOAD 8
          INSTANCEOF java/lang/Boolean
          IFNE L4
          NEW org/nlogo/nvm/EngineException
          DUP
          ALOAD 1
          ALOAD 0
          INVOKESTATIC org/nlogo/core/I18N.errorsJ ()Lorg/nlogo/core/I18NJava;
          LDC "org.nlogo.prim.$common.expectedBooleanValue"
          ICONST_3
          ANEWARRAY java/lang/Object
          DUP
          ICONST_0
          LDC "WITH"
          AASTORE
          DUP
          ICONST_1
          ALOAD 7
          INVOKESTATIC org/nlogo/api/Dump.logoObject (Ljava/lang/Object;)Ljava/lang/String;
          AASTORE
          DUP
          ICONST_2
          ALOAD 8
          INVOKESTATIC org/nlogo/api/Dump.logoObject (Ljava/lang/Object;)Ljava/lang/String;
          AASTORE
          INVOKEINTERFACE org/nlogo/core/I18NJava.getN (Ljava/lang/String;[Ljava/lang/Object;)Ljava/lang/String;
          INVOKESPECIAL org/nlogo/nvm/EngineException.<init> (Lorg/nlogo/nvm/Context;Lorg/nlogo/nvm/Instruction;Ljava/lang/String;)V
          ATHROW
         L4
         FRAME APPEND [org/nlogo/agent/Agent java/lang/Object]
          ALOAD 8
          CHECKCAST java/lang/Boolean
          INVOKEVIRTUAL java/lang/Boolean.booleanValue ()Z
          IFEQ L5
          ALOAD 5
          ALOAD 7
          INVOKEINTERFACE java/util/List.add (Ljava/lang/Object;)Z
          POP
         L5
         FRAME SAME
          GOTO L2
         L3
         FRAME CHOP 2
          NEW org/nlogo/agent/ArrayAgentSet
          DUP
          ALOAD 2
          INVOKEVIRTUAL org/nlogo/agent/AgentSet.kind ()Lorg/nlogo/core/AgentKind;
          ALOAD 5
          ALOAD 5
          INVOKEINTERFACE java/util/List.size ()I
          ANEWARRAY org/nlogo/agent/Agent
          INVOKEINTERFACE java/util/List.toArray ([Ljava/lang/Object;)[Ljava/lang/Object;
          CHECKCAST [Lorg/nlogo/agent/Agent;
          INVOKESPECIAL org/nlogo/agent/ArrayAgentSet.<init> (Lorg/nlogo/core/AgentKind;[Lorg/nlogo/agent/Agent;)V
         L6
          ASTORE 2
          ALOAD 1
          GETFIELD org/nlogo/nvm/Context.agent : Lorg/nlogo/agent/Agent;
          INSTANCEOF org/nlogo/agent/Observer
          IFNE L7
          ALOAD 2
          ALOAD 0
          GETFIELD org/nlogo/prim/_asm_proceduresetup_ask_16.world : Lorg/nlogo/agent/World;
          INVOKEVIRTUAL org/nlogo/agent/World.turtles ()Lorg/nlogo/agent/AgentSet;
          IF_ACMPNE L8
          NEW org/nlogo/nvm/EngineException
          DUP
          ALOAD 1
          ALOAD 0
          INVOKESTATIC org/nlogo/core/I18N.errorsJ ()Lorg/nlogo/core/I18NJava;
          LDC "org.nlogo.prim.$common.onlyObserverCanAskAllTurtles"
          INVOKEINTERFACE org/nlogo/core/I18NJava.get (Ljava/lang/String;)Ljava/lang/String;
          INVOKESPECIAL org/nlogo/nvm/EngineException.<init> (Lorg/nlogo/nvm/Context;Lorg/nlogo/nvm/Instruction;Ljava/lang/String;)V
          ATHROW
         L8
         FRAME FULL [org/nlogo/prim/_asm_proceduresetup_ask_16 org/nlogo/nvm/Context org/nlogo/agent/ArrayAgentSet org/nlogo/nvm/Reporter org/nlogo/nvm/Context java/util/ArrayList org/nlogo/agent/AgentSet$Iterator] []
          ALOAD 2
          ALOAD 0
          GETFIELD org/nlogo/prim/_asm_proceduresetup_ask_16.world : Lorg/nlogo/agent/World;
          INVOKEVIRTUAL org/nlogo/agent/World.patches ()Lorg/nlogo/agent/AgentSet;
          IF_ACMPNE L7
          NEW org/nlogo/nvm/EngineException
          DUP
          ALOAD 1
          ALOAD 0
          INVOKESTATIC org/nlogo/core/I18N.errorsJ ()Lorg/nlogo/core/I18NJava;
          LDC "org.nlogo.prim.$common.onlyObserverCanAskAllPatches"
          INVOKEINTERFACE org/nlogo/core/I18NJava.get (Ljava/lang/String;)Ljava/lang/String;
          INVOKESPECIAL org/nlogo/nvm/EngineException.<init> (Lorg/nlogo/nvm/Context;Lorg/nlogo/nvm/Instruction;Ljava/lang/String;)V
          ATHROW
         L7
         FRAME SAME
          ALOAD 1
          ALOAD 2
          BIPUSH 19
          INVOKEVIRTUAL org/nlogo/nvm/Context.runExclusiveJob (Lorg/nlogo/agent/AgentSet;I)V
          ALOAD 1
          BIPUSH 22
          PUTFIELD org/nlogo/nvm/Context.ip : I
         L9
          RETURN
[19]_asm_proceduresetup_setpatchvariable_18 "set drain? true" Object => void
      _constboolean:true "true" => Boolean
          TRYCATCHBLOCK L0 L1 L2 org/nlogo/api/AgentException
         L3
          ALOAD 0
          GETFIELD org/nlogo/prim/_asm_proceduresetup_setpatchvariable_18.kept2_value : Ljava/lang/Boolean;
         L4
          ASTORE 2
         L0
          ALOAD 1
          GETFIELD org/nlogo/nvm/Context.agent : Lorg/nlogo/agent/Agent;
          BIPUSH 7
          ALOAD 2
          INVOKEVIRTUAL org/nlogo/agent/Agent.setPatchVariable (ILjava/lang/Object;)V
         L1
          GOTO L5
         L2
         FRAME FULL [org/nlogo/prim/_asm_proceduresetup_setpatchvariable_18 org/nlogo/nvm/Context java/lang/Boolean] [org/nlogo/api/AgentException]
          ASTORE 3
          NEW org/nlogo/nvm/EngineException
          DUP
          ALOAD 1
          ALOAD 0
          ALOAD 3
          INVOKEVIRTUAL org/nlogo/api/AgentException.getMessage ()Ljava/lang/String;
          INVOKESPECIAL org/nlogo/nvm/EngineException.<init> (Lorg/nlogo/nvm/Context;Lorg/nlogo/nvm/Instruction;Ljava/lang/String;)V
          ATHROW
         L5
         FRAME SAME
          ALOAD 1
          BIPUSH 20
          PUTFIELD org/nlogo/nvm/Context.ip : I
         L6
          RETURN
[20]_asm_proceduresetup_setpatchvariable_19 "set elevation -10000000" Object => void
      _constdouble:-1.0E7 "-10000000" => Double
          TRYCATCHBLOCK L0 L1 L2 org/nlogo/api/AgentException
         L3
          ALOAD 0
          GETFIELD org/nlogo/prim/_asm_proceduresetup_setpatchvariable_19.kept2_value : Ljava/lang/Double;
         L4
          ASTORE 2
         L0
          ALOAD 1
          GETFIELD org/nlogo/nvm/Context.agent : Lorg/nlogo/agent/Agent;
          ICONST_5
          ALOAD 2
          INVOKEVIRTUAL org/nlogo/agent/Agent.setPatchVariable (ILjava/lang/Object;)V
         L1
          GOTO L5
         L2
         FRAME FULL [org/nlogo/prim/_asm_proceduresetup_setpatchvariable_19 org/nlogo/nvm/Context java/lang/Double] [org/nlogo/api/AgentException]
          ASTORE 3
          NEW org/nlogo/nvm/EngineException
          DUP
          ALOAD 1
          ALOAD 0
          ALOAD 3
          INVOKEVIRTUAL org/nlogo/api/AgentException.getMessage ()Ljava/lang/String;
          INVOKESPECIAL org/nlogo/nvm/EngineException.<init> (Lorg/nlogo/nvm/Context;Lorg/nlogo/nvm/Instruction;Ljava/lang/String;)V
          ATHROW
         L5
         FRAME SAME
          ALOAD 1
          BIPUSH 21
          PUTFIELD org/nlogo/nvm/Context.ip : I
         L6
          RETURN
[21]_asm_proceduresetup_done_20 => void
         L0
          ALOAD 1
          ICONST_1
          PUTFIELD org/nlogo/nvm/Context.finished : Z
         L1
          RETURN
[22]_asm_proceduresetup_setobservervariable_21 "set drains patches with [ drain? ]" Object => void
      _with "patches with [ drain? ]" AgentSet,Reporter => AgentSet
        _patches "patches" => AgentSet
        _asm_proceduresetup_patchvariable_22 "drain?" => Object
              TRYCATCHBLOCK L0 L1 L2 org/nlogo/api/AgentException
             L0
              ALOAD 1
              GETFIELD org/nlogo/nvm/Context.agent : Lorg/nlogo/agent/Agent;
              BIPUSH 7
              INVOKEVIRTUAL org/nlogo/agent/Agent.getPatchVariable (I)Ljava/lang/Object;
             L1
              GOTO L3
             L2
             FRAME SAME1 org/nlogo/api/AgentException
              ASTORE 2
              NEW org/nlogo/nvm/EngineException
              DUP
              ALOAD 1
              ALOAD 0
              ALOAD 2
              INVOKEVIRTUAL org/nlogo/api/AgentException.getMessage ()Ljava/lang/String;
              INVOKESPECIAL org/nlogo/nvm/EngineException.<init> (Lorg/nlogo/nvm/Context;Lorg/nlogo/nvm/Instruction;Ljava/lang/String;)V
              ATHROW
             L3
             FRAME SAME1 java/lang/Object
              ARETURN
          TRYCATCHBLOCK L0 L1 L2 org/nlogo/api/AgentException
         L3
          ALOAD 0
          GETFIELD org/nlogo/prim/_asm_proceduresetup_setobservervariable_21.world : Lorg/nlogo/agent/World;
          INVOKEVIRTUAL org/nlogo/agent/World.patches ()Lorg/nlogo/agent/AgentSet;
         L4
          ALOAD 0
          GETFIELD org/nlogo/prim/_asm_proceduresetup_setobservervariable_21.keptinstr4 : Lorg/nlogo/nvm/Reporter;
          ASTORE 3
          ASTORE 2
          NEW org/nlogo/nvm/Context
          DUP
          ALOAD 1
          ALOAD 2
          INVOKESPECIAL org/nlogo/nvm/Context.<init> (Lorg/nlogo/nvm/Context;Lorg/nlogo/agent/AgentSet;)V
          ASTORE 4
          NEW java/util/ArrayList
          DUP
          INVOKESPECIAL java/util/ArrayList.<init> ()V
          ASTORE 5
          ALOAD 3
          ALOAD 2
          ALOAD 1
          INVOKEVIRTUAL org/nlogo/nvm/Reporter.checkAgentSetClass (Lorg/nlogo/agent/AgentSet;Lorg/nlogo/nvm/Context;)V
          ALOAD 2
          INVOKEVIRTUAL org/nlogo/agent/AgentSet.iterator ()Lorg/nlogo/agent/AgentSet$Iterator;
          ASTORE 6
         L5
         FRAME FULL [org/nlogo/prim/_asm_proceduresetup_setobservervariable_21 org/nlogo/nvm/Context org/nlogo/agent/AgentSet org/nlogo/nvm/Reporter org/nlogo/nvm/Context java/util/ArrayList org/nlogo/agent/AgentSet$Iterator] []
          ALOAD 6
          INVOKEINTERFACE org/nlogo/agent/AgentSet$Iterator.hasNext ()Z
          IFEQ L6
          ALOAD 6
          INVOKEINTERFACE org/nlogo/agent/AgentSet$Iterator.next ()Lorg/nlogo/agent/Agent;
          ASTORE 7
          ALOAD 4
          ALOAD 7
          ALOAD 3
          INVOKEVIRTUAL org/nlogo/nvm/Context.evaluateReporter (Lorg/nlogo/agent/Agent;Lorg/nlogo/nvm/Reporter;)Ljava/lang/Object;
          ASTORE 8
          ALOAD 8
          INSTANCEOF java/lang/Boolean
          IFNE L7
          NEW org/nlogo/nvm/EngineException
          DUP
          ALOAD 1
          ALOAD 0
          INVOKESTATIC org/nlogo/core/I18N.errorsJ ()Lorg/nlogo/core/I18NJava;
          LDC "org.nlogo.prim.$common.expectedBooleanValue"
          ICONST_3
          ANEWARRAY java/lang/Object
          DUP
          ICONST_0
          LDC "WITH"
          AASTORE
          DUP
          ICONST_1
          ALOAD 7
          INVOKESTATIC org/nlogo/api/Dump.logoObject (Ljava/lang/Object;)Ljava/lang/String;
          AASTORE
          DUP
          ICONST_2
          ALOAD 8
          INVOKESTATIC org/nlogo/api/Dump.logoObject (Ljava/lang/Object;)Ljava/lang/String;
          AASTORE
          INVOKEINTERFACE org/nlogo/core/I18NJava.getN (Ljava/lang/String;[Ljava/lang/Object;)Ljava/lang/String;
          INVOKESPECIAL org/nlogo/nvm/EngineException.<init> (Lorg/nlogo/nvm/Context;Lorg/nlogo/nvm/Instruction;Ljava/lang/String;)V
          ATHROW
         L7
         FRAME APPEND [org/nlogo/agent/Agent java/lang/Object]
          ALOAD 8
          CHECKCAST java/lang/Boolean
          INVOKEVIRTUAL java/lang/Boolean.booleanValue ()Z
          IFEQ L8
          ALOAD 5
          ALOAD 7
          INVOKEINTERFACE java/util/List.add (Ljava/lang/Object;)Z
          POP
         L8
         FRAME SAME
          GOTO L5
         L6
         FRAME CHOP 2
          NEW org/nlogo/agent/ArrayAgentSet
          DUP
          ALOAD 2
          INVOKEVIRTUAL org/nlogo/agent/AgentSet.kind ()Lorg/nlogo/core/AgentKind;
          ALOAD 5
          ALOAD 5
          INVOKEINTERFACE java/util/List.size ()I
          ANEWARRAY org/nlogo/agent/Agent
          INVOKEINTERFACE java/util/List.toArray ([Ljava/lang/Object;)[Ljava/lang/Object;
          CHECKCAST [Lorg/nlogo/agent/Agent;
          INVOKESPECIAL org/nlogo/agent/ArrayAgentSet.<init> (Lorg/nlogo/core/AgentKind;[Lorg/nlogo/agent/Agent;)V
         L9
          ASTORE 2
         L0
          ALOAD 1
          GETFIELD org/nlogo/nvm/Context.agent : Lorg/nlogo/agent/Agent;
          BIPUSH 7
          ALOAD 2
          INVOKEVIRTUAL org/nlogo/agent/Agent.setObserverVariable (ILjava/lang/Object;)V
         L1
          GOTO L10
         L2
         FRAME FULL [org/nlogo/prim/_asm_proceduresetup_setobservervariable_21 org/nlogo/nvm/Context org/nlogo/agent/ArrayAgentSet org/nlogo/nvm/Reporter org/nlogo/nvm/Context java/util/ArrayList org/nlogo/agent/AgentSet$Iterator] [org/nlogo/api/AgentException]
          ASTORE 3
          NEW org/nlogo/nvm/EngineException
          DUP
          ALOAD 1
          ALOAD 0
          ALOAD 3
          INVOKEVIRTUAL org/nlogo/api/AgentException.getMessage ()Ljava/lang/String;
          INVOKESPECIAL org/nlogo/nvm/EngineException.<init> (Lorg/nlogo/nvm/Context;Lorg/nlogo/nvm/Instruction;Ljava/lang/String;)V
          ATHROW
         L10
         FRAME SAME
          ALOAD 1
          BIPUSH 23
          PUTFIELD org/nlogo/nvm/Context.ip : I
         L11
          RETURN
[23]_asm_proceduresetup_setobservervariable_23 "set land patches with [ not drain? ]" Object => void
      _with "patches with [ not drain? ]" AgentSet,Reporter => AgentSet
        _patches "patches" => AgentSet
        _asm_proceduresetup_not_24 "not drain?" boolean => boolean
          _patchvariable:DRAIN? "drain?" => Object
              TRYCATCHBLOCK L0 L1 L2 org/nlogo/api/AgentException
              TRYCATCHBLOCK L3 L4 L4 java/lang/ClassCastException
             L0
              ALOAD 1
              GETFIELD org/nlogo/nvm/Context.agent : Lorg/nlogo/agent/Agent;
              BIPUSH 7
              INVOKEVIRTUAL org/nlogo/agent/Agent.getPatchVariable (I)Ljava/lang/Object;
             L1
              GOTO L5
             L2
             FRAME SAME1 org/nlogo/api/AgentException
              ASTORE 2
              NEW org/nlogo/nvm/EngineException
              DUP
              ALOAD 1
              ALOAD 0
              ALOAD 2
              INVOKEVIRTUAL org/nlogo/api/AgentException.getMessage ()Ljava/lang/String;
              INVOKESPECIAL org/nlogo/nvm/EngineException.<init> (Lorg/nlogo/nvm/Context;Lorg/nlogo/nvm/Instruction;Ljava/lang/String;)V
              ATHROW
             L5
             FRAME SAME1 java/lang/Object
              ASTORE 2
             L3
              ALOAD 2
              CHECKCAST java/lang/Boolean
              INVOKEVIRTUAL java/lang/Boolean.booleanValue ()Z
              GOTO L6
             L4
             FRAME FULL [org/nlogo/prim/_asm_proceduresetup_not_24 org/nlogo/nvm/Context java/lang/Object] [java/lang/ClassCastException]
              POP
              NEW org/nlogo/nvm/ArgumentTypeException
              DUP
              ALOAD 1
              ALOAD 0
              BIPUSH 0
              LDC 2
              ALOAD 2
              INVOKESPECIAL org/nlogo/nvm/ArgumentTypeException.<init> (Lorg/nlogo/nvm/Context;Lorg/nlogo/nvm/Instruction;IILjava/lang/Object;)V
              ATHROW
             L6
             FRAME SAME1 I
              ISTORE 2
              ILOAD 2
              IFNE L7
              ICONST_1
              GOTO L8
             L7
             FRAME FULL [org/nlogo/prim/_asm_proceduresetup_not_24 org/nlogo/nvm/Context I] []
              ICONST_0
             L8
             FRAME SAME1 I
              IFEQ L9
              GETSTATIC java/lang/Boolean.TRUE : Ljava/lang/Boolean;
              GOTO L10
             L9
             FRAME SAME
              GETSTATIC java/lang/Boolean.FALSE : Ljava/lang/Boolean;
             L10
             FRAME SAME1 java/lang/Boolean
              ARETURN
          TRYCATCHBLOCK L0 L1 L2 org/nlogo/api/AgentException
         L3
          ALOAD 0
          GETFIELD org/nlogo/prim/_asm_proceduresetup_setobservervariable_23.world : Lorg/nlogo/agent/World;
          INVOKEVIRTUAL org/nlogo/agent/World.patches ()Lorg/nlogo/agent/AgentSet;
         L4
          ALOAD 0
          GETFIELD org/nlogo/prim/_asm_proceduresetup_setobservervariable_23.keptinstr4 : Lorg/nlogo/nvm/Reporter;
          ASTORE 3
          ASTORE 2
          NEW org/nlogo/nvm/Context
          DUP
          ALOAD 1
          ALOAD 2
          INVOKESPECIAL org/nlogo/nvm/Context.<init> (Lorg/nlogo/nvm/Context;Lorg/nlogo/agent/AgentSet;)V
          ASTORE 4
          NEW java/util/ArrayList
          DUP
          INVOKESPECIAL java/util/ArrayList.<init> ()V
          ASTORE 5
          ALOAD 3
          ALOAD 2
          ALOAD 1
          INVOKEVIRTUAL org/nlogo/nvm/Reporter.checkAgentSetClass (Lorg/nlogo/agent/AgentSet;Lorg/nlogo/nvm/Context;)V
          ALOAD 2
          INVOKEVIRTUAL org/nlogo/agent/AgentSet.iterator ()Lorg/nlogo/agent/AgentSet$Iterator;
          ASTORE 6
         L5
         FRAME FULL [org/nlogo/prim/_asm_proceduresetup_setobservervariable_23 org/nlogo/nvm/Context org/nlogo/agent/AgentSet org/nlogo/nvm/Reporter org/nlogo/nvm/Context java/util/ArrayList org/nlogo/agent/AgentSet$Iterator] []
          ALOAD 6
          INVOKEINTERFACE org/nlogo/agent/AgentSet$Iterator.hasNext ()Z
          IFEQ L6
          ALOAD 6
          INVOKEINTERFACE org/nlogo/agent/AgentSet$Iterator.next ()Lorg/nlogo/agent/Agent;
          ASTORE 7
          ALOAD 4
          ALOAD 7
          ALOAD 3
          INVOKEVIRTUAL org/nlogo/nvm/Context.evaluateReporter (Lorg/nlogo/agent/Agent;Lorg/nlogo/nvm/Reporter;)Ljava/lang/Object;
          ASTORE 8
          ALOAD 8
          INSTANCEOF java/lang/Boolean
          IFNE L7
          NEW org/nlogo/nvm/EngineException
          DUP
          ALOAD 1
          ALOAD 0
          INVOKESTATIC org/nlogo/core/I18N.errorsJ ()Lorg/nlogo/core/I18NJava;
          LDC "org.nlogo.prim.$common.expectedBooleanValue"
          ICONST_3
          ANEWARRAY java/lang/Object
          DUP
          ICONST_0
          LDC "WITH"
          AASTORE
          DUP
          ICONST_1
          ALOAD 7
          INVOKESTATIC org/nlogo/api/Dump.logoObject (Ljava/lang/Object;)Ljava/lang/String;
          AASTORE
          DUP
          ICONST_2
          ALOAD 8
          INVOKESTATIC org/nlogo/api/Dump.logoObject (Ljava/lang/Object;)Ljava/lang/String;
          AASTORE
          INVOKEINTERFACE org/nlogo/core/I18NJava.getN (Ljava/lang/String;[Ljava/lang/Object;)Ljava/lang/String;
          INVOKESPECIAL org/nlogo/nvm/EngineException.<init> (Lorg/nlogo/nvm/Context;Lorg/nlogo/nvm/Instruction;Ljava/lang/String;)V
          ATHROW
         L7
         FRAME APPEND [org/nlogo/agent/Agent java/lang/Object]
          ALOAD 8
          CHECKCAST java/lang/Boolean
          INVOKEVIRTUAL java/lang/Boolean.booleanValue ()Z
          IFEQ L8
          ALOAD 5
          ALOAD 7
          INVOKEINTERFACE java/util/List.add (Ljava/lang/Object;)Z
          POP
         L8
         FRAME SAME
          GOTO L5
         L6
         FRAME CHOP 2
          NEW org/nlogo/agent/ArrayAgentSet
          DUP
          ALOAD 2
          INVOKEVIRTUAL org/nlogo/agent/AgentSet.kind ()Lorg/nlogo/core/AgentKind;
          ALOAD 5
          ALOAD 5
          INVOKEINTERFACE java/util/List.size ()I
          ANEWARRAY org/nlogo/agent/Agent
          INVOKEINTERFACE java/util/List.toArray ([Ljava/lang/Object;)[Ljava/lang/Object;
          CHECKCAST [Lorg/nlogo/agent/Agent;
          INVOKESPECIAL org/nlogo/agent/ArrayAgentSet.<init> (Lorg/nlogo/core/AgentKind;[Lorg/nlogo/agent/Agent;)V
         L9
          ASTORE 2
         L0
          ALOAD 1
          GETFIELD org/nlogo/nvm/Context.agent : Lorg/nlogo/agent/Agent;
          BIPUSH 8
          ALOAD 2
          INVOKEVIRTUAL org/nlogo/agent/Agent.setObserverVariable (ILjava/lang/Object;)V
         L1
          GOTO L10
         L2
         FRAME FULL [org/nlogo/prim/_asm_proceduresetup_setobservervariable_23 org/nlogo/nvm/Context org/nlogo/agent/ArrayAgentSet org/nlogo/nvm/Reporter org/nlogo/nvm/Context java/util/ArrayList org/nlogo/agent/AgentSet$Iterator] [org/nlogo/api/AgentException]
          ASTORE 3
          NEW org/nlogo/nvm/EngineException
          DUP
          ALOAD 1
          ALOAD 0
          ALOAD 3
          INVOKEVIRTUAL org/nlogo/api/AgentException.getMessage ()Ljava/lang/String;
          INVOKESPECIAL org/nlogo/nvm/EngineException.<init> (Lorg/nlogo/nvm/Context;Lorg/nlogo/nvm/Instruction;Ljava/lang/String;)V
          ATHROW
         L10
         FRAME SAME
          ALOAD 1
          BIPUSH 24
          PUTFIELD org/nlogo/nvm/Context.ip : I
         L11
          RETURN
[24]_asm_proceduresetup_ask_25 "ask land [ recolor ]" Object => void
      _observervariable:LAND "land" => Object
         L0
          ALOAD 1
          GETFIELD org/nlogo/nvm/Context.agent : Lorg/nlogo/agent/Agent;
          BIPUSH 8
          INVOKEVIRTUAL org/nlogo/agent/Agent.getObserverVariable (I)Ljava/lang/Object;
         L1
          ASTORE 2
          ALOAD 2
          INSTANCEOF org/nlogo/agent/AgentSet
          IFEQ L2
          ALOAD 2
          CHECKCAST org/nlogo/agent/AgentSet
          ASTORE 3
          ALOAD 1
          GETFIELD org/nlogo/nvm/Context.agent : Lorg/nlogo/agent/Agent;
          INSTANCEOF org/nlogo/agent/Observer
          IFNE L3
          ALOAD 3
          ALOAD 0
          GETFIELD org/nlogo/prim/_asm_proceduresetup_ask_25.world : Lorg/nlogo/agent/World;
          INVOKEVIRTUAL org/nlogo/agent/World.turtles ()Lorg/nlogo/agent/AgentSet;
          IF_ACMPNE L4
          NEW org/nlogo/nvm/EngineException
          DUP
          ALOAD 1
          ALOAD 0
          INVOKESTATIC org/nlogo/core/I18N.errorsJ ()Lorg/nlogo/core/I18NJava;
          LDC "org.nlogo.prim.$common.onlyObserverCanAskAllTurtles"
          INVOKEINTERFACE org/nlogo/core/I18NJava.get (Ljava/lang/String;)Ljava/lang/String;
          INVOKESPECIAL org/nlogo/nvm/EngineException.<init> (Lorg/nlogo/nvm/Context;Lorg/nlogo/nvm/Instruction;Ljava/lang/String;)V
          ATHROW
         L4
         FRAME APPEND [java/lang/Object org/nlogo/agent/AgentSet]
          ALOAD 3
          ALOAD 0
          GETFIELD org/nlogo/prim/_asm_proceduresetup_ask_25.world : Lorg/nlogo/agent/World;
          INVOKEVIRTUAL org/nlogo/agent/World.patches ()Lorg/nlogo/agent/AgentSet;
          IF_ACMPNE L3
          NEW org/nlogo/nvm/EngineException
          DUP
          ALOAD 1
          ALOAD 0
          INVOKESTATIC org/nlogo/core/I18N.errorsJ ()Lorg/nlogo/core/I18NJava;
          LDC "org.nlogo.prim.$common.onlyObserverCanAskAllPatches"
          INVOKEINTERFACE org/nlogo/core/I18NJava.get (Ljava/lang/String;)Ljava/lang/String;
          INVOKESPECIAL org/nlogo/nvm/EngineException.<init> (Lorg/nlogo/nvm/Context;Lorg/nlogo/nvm/Instruction;Ljava/lang/String;)V
          ATHROW
         L2
         FRAME CHOP 1
          ALOAD 2
          INSTANCEOF org/nlogo/agent/Agent
          IFEQ L5
          ALOAD 2
          CHECKCAST org/nlogo/agent/Agent
          ASTORE 4
          ALOAD 4
          GETFIELD org/nlogo/agent/Agent.id : J
          LDC -1
          LCMP
          IFNE L6
          NEW org/nlogo/nvm/EngineException
          DUP
          ALOAD 1
          ALOAD 0
          INVOKESTATIC org/nlogo/core/I18N.errorsJ ()Lorg/nlogo/core/I18NJava;
          LDC "org.nlogo.$common.thatAgentIsDead"
          ICONST_1
          ANEWARRAY java/lang/Object
          DUP
          ICONST_0
          ALOAD 4
          INVOKEVIRTUAL org/nlogo/agent/Agent.classDisplayName ()Ljava/lang/String;
          AASTORE
          INVOKEINTERFACE org/nlogo/core/I18NJava.getN (Ljava/lang/String;[Ljava/lang/Object;)Ljava/lang/String;
          INVOKESPECIAL org/nlogo/nvm/EngineException.<init> (Lorg/nlogo/nvm/Context;Lorg/nlogo/nvm/Instruction;Ljava/lang/String;)V
          ATHROW
         L6
         FRAME APPEND [T org/nlogo/agent/Agent]
          NEW org/nlogo/agent/ArrayAgentSet
          DUP
          ALOAD 4
          INVOKEVIRTUAL org/nlogo/agent/Agent.kind ()Lorg/nlogo/core/AgentKind;
          ICONST_1
          ICONST_0
          INVOKESPECIAL org/nlogo/agent/ArrayAgentSet.<init> (Lorg/nlogo/core/AgentKind;IZ)V
          ASTORE 3
          ALOAD 3
          ALOAD 4
          INVOKEVIRTUAL org/nlogo/agent/AgentSet.add (Lorg/nlogo/agent/Agent;)V
          GOTO L3
         L5
         FRAME CHOP 2
          NEW org/nlogo/nvm/ArgumentTypeException
          DUP
          ALOAD 1
          ALOAD 0
          ICONST_0
          INVOKESTATIC org/nlogo/core/Syntax.AgentsetType ()I
          INVOKESTATIC org/nlogo/core/Syntax.AgentType ()I
          IOR
          ALOAD 2
          INVOKESPECIAL org/nlogo/nvm/ArgumentTypeException.<init> (Lorg/nlogo/nvm/Context;Lorg/nlogo/nvm/Instruction;IILjava/lang/Object;)V
          ATHROW
         L3
         FRAME APPEND [org/nlogo/agent/AgentSet]
          ALOAD 1
          ALOAD 3
          BIPUSH 25
          INVOKEVIRTUAL org/nlogo/nvm/Context.runExclusiveJob (Lorg/nlogo/agent/AgentSet;I)V
          ALOAD 1
          BIPUSH 27
          PUTFIELD org/nlogo/nvm/Context.ip : I
         L7
          RETURN
[25]_asm_proceduresetup_call_26 "recolor"
         L0
          NEW org/nlogo/nvm/Activation
          DUP
          ALOAD 0
          GETFIELD org/nlogo/prim/_asm_proceduresetup_call_26.kept1_procedure : Lorg/nlogo/nvm/Procedure;
          ALOAD 1
          GETFIELD org/nlogo/nvm/Context.activation : Lorg/nlogo/nvm/Activation;
          BIPUSH 26
          INVOKESPECIAL org/nlogo/nvm/Activation.<init> (Lorg/nlogo/nvm/Procedure;Lorg/nlogo/nvm/Activation;I)V
          ALOAD 1
          SWAP
          PUTFIELD org/nlogo/nvm/Context.activation : Lorg/nlogo/nvm/Activation;
          ALOAD 1
          ICONST_0
          PUTFIELD org/nlogo/nvm/Context.ip : I
         L1
          RETURN
[26]_asm_proceduresetup_done_27 => void
         L0
          ALOAD 1
          ICONST_1
          PUTFIELD org/nlogo/nvm/Context.finished : Z
         L1
          RETURN
[27]_asm_proceduresetup_return_28 => void
         L0
          ALOAD 1
          INVOKEVIRTUAL org/nlogo/nvm/Context.returnFromProcedure ()V
          ALOAD 1
          ICONST_0
          PUTFIELD org/nlogo/nvm/Context.stopping : Z
         L1
          RETURN

procedure HIDE-WATER:[]{OTPL}:
[0]_asm_procedurehidewater_setobservervariable_0 "set show-water? false" Object => void
      _constboolean:false "false" => Boolean
          TRYCATCHBLOCK L0 L1 L2 org/nlogo/api/AgentException
         L3
          ALOAD 0
          GETFIELD org/nlogo/prim/_asm_procedurehidewater_setobservervariable_0.kept2_value : Ljava/lang/Boolean;
         L4
          ASTORE 2
         L0
          ALOAD 1
          GETFIELD org/nlogo/nvm/Context.agent : Lorg/nlogo/agent/Agent;
          BIPUSH 6
          ALOAD 2
          INVOKEVIRTUAL org/nlogo/agent/Agent.setObserverVariable (ILjava/lang/Object;)V
         L1
          GOTO L5
         L2
         FRAME FULL [org/nlogo/prim/_asm_procedurehidewater_setobservervariable_0 org/nlogo/nvm/Context java/lang/Boolean] [org/nlogo/api/AgentException]
          ASTORE 3
          NEW org/nlogo/nvm/EngineException
          DUP
          ALOAD 1
          ALOAD 0
          ALOAD 3
          INVOKEVIRTUAL org/nlogo/api/AgentException.getMessage ()Ljava/lang/String;
          INVOKESPECIAL org/nlogo/nvm/EngineException.<init> (Lorg/nlogo/nvm/Context;Lorg/nlogo/nvm/Instruction;Ljava/lang/String;)V
          ATHROW
         L5
         FRAME SAME
          ALOAD 1
          ICONST_1
          PUTFIELD org/nlogo/nvm/Context.ip : I
         L6
          RETURN
[1]_asm_procedurehidewater_ask_1 "ask land [ recolor ]" Object => void
      _observervariable:LAND "land" => Object
         L0
          ALOAD 1
          GETFIELD org/nlogo/nvm/Context.agent : Lorg/nlogo/agent/Agent;
          BIPUSH 8
          INVOKEVIRTUAL org/nlogo/agent/Agent.getObserverVariable (I)Ljava/lang/Object;
         L1
          ASTORE 2
          ALOAD 2
          INSTANCEOF org/nlogo/agent/AgentSet
          IFEQ L2
          ALOAD 2
          CHECKCAST org/nlogo/agent/AgentSet
          ASTORE 3
          ALOAD 1
          GETFIELD org/nlogo/nvm/Context.agent : Lorg/nlogo/agent/Agent;
          INSTANCEOF org/nlogo/agent/Observer
          IFNE L3
          ALOAD 3
          ALOAD 0
          GETFIELD org/nlogo/prim/_asm_procedurehidewater_ask_1.world : Lorg/nlogo/agent/World;
          INVOKEVIRTUAL org/nlogo/agent/World.turtles ()Lorg/nlogo/agent/AgentSet;
          IF_ACMPNE L4
          NEW org/nlogo/nvm/EngineException
          DUP
          ALOAD 1
          ALOAD 0
          INVOKESTATIC org/nlogo/core/I18N.errorsJ ()Lorg/nlogo/core/I18NJava;
          LDC "org.nlogo.prim.$common.onlyObserverCanAskAllTurtles"
          INVOKEINTERFACE org/nlogo/core/I18NJava.get (Ljava/lang/String;)Ljava/lang/String;
          INVOKESPECIAL org/nlogo/nvm/EngineException.<init> (Lorg/nlogo/nvm/Context;Lorg/nlogo/nvm/Instruction;Ljava/lang/String;)V
          ATHROW
         L4
         FRAME APPEND [java/lang/Object org/nlogo/agent/AgentSet]
          ALOAD 3
          ALOAD 0
          GETFIELD org/nlogo/prim/_asm_procedurehidewater_ask_1.world : Lorg/nlogo/agent/World;
          INVOKEVIRTUAL org/nlogo/agent/World.patches ()Lorg/nlogo/agent/AgentSet;
          IF_ACMPNE L3
          NEW org/nlogo/nvm/EngineException
          DUP
          ALOAD 1
          ALOAD 0
          INVOKESTATIC org/nlogo/core/I18N.errorsJ ()Lorg/nlogo/core/I18NJava;
          LDC "org.nlogo.prim.$common.onlyObserverCanAskAllPatches"
          INVOKEINTERFACE org/nlogo/core/I18NJava.get (Ljava/lang/String;)Ljava/lang/String;
          INVOKESPECIAL org/nlogo/nvm/EngineException.<init> (Lorg/nlogo/nvm/Context;Lorg/nlogo/nvm/Instruction;Ljava/lang/String;)V
          ATHROW
         L2
         FRAME CHOP 1
          ALOAD 2
          INSTANCEOF org/nlogo/agent/Agent
          IFEQ L5
          ALOAD 2
          CHECKCAST org/nlogo/agent/Agent
          ASTORE 4
          ALOAD 4
          GETFIELD org/nlogo/agent/Agent.id : J
          LDC -1
          LCMP
          IFNE L6
          NEW org/nlogo/nvm/EngineException
          DUP
          ALOAD 1
          ALOAD 0
          INVOKESTATIC org/nlogo/core/I18N.errorsJ ()Lorg/nlogo/core/I18NJava;
          LDC "org.nlogo.$common.thatAgentIsDead"
          ICONST_1
          ANEWARRAY java/lang/Object
          DUP
          ICONST_0
          ALOAD 4
          INVOKEVIRTUAL org/nlogo/agent/Agent.classDisplayName ()Ljava/lang/String;
          AASTORE
          INVOKEINTERFACE org/nlogo/core/I18NJava.getN (Ljava/lang/String;[Ljava/lang/Object;)Ljava/lang/String;
          INVOKESPECIAL org/nlogo/nvm/EngineException.<init> (Lorg/nlogo/nvm/Context;Lorg/nlogo/nvm/Instruction;Ljava/lang/String;)V
          ATHROW
         L6
         FRAME APPEND [T org/nlogo/agent/Agent]
          NEW org/nlogo/agent/ArrayAgentSet
          DUP
          ALOAD 4
          INVOKEVIRTUAL org/nlogo/agent/Agent.kind ()Lorg/nlogo/core/AgentKind;
          ICONST_1
          ICONST_0
          INVOKESPECIAL org/nlogo/agent/ArrayAgentSet.<init> (Lorg/nlogo/core/AgentKind;IZ)V
          ASTORE 3
          ALOAD 3
          ALOAD 4
          INVOKEVIRTUAL org/nlogo/agent/AgentSet.add (Lorg/nlogo/agent/Agent;)V
          GOTO L3
         L5
         FRAME CHOP 2
          NEW org/nlogo/nvm/ArgumentTypeException
          DUP
          ALOAD 1
          ALOAD 0
          ICONST_0
          INVOKESTATIC org/nlogo/core/Syntax.AgentsetType ()I
          INVOKESTATIC org/nlogo/core/Syntax.AgentType ()I
          IOR
          ALOAD 2
          INVOKESPECIAL org/nlogo/nvm/ArgumentTypeException.<init> (Lorg/nlogo/nvm/Context;Lorg/nlogo/nvm/Instruction;IILjava/lang/Object;)V
          ATHROW
         L3
         FRAME APPEND [org/nlogo/agent/AgentSet]
          ALOAD 1
          ALOAD 3
          ICONST_2
          INVOKEVIRTUAL org/nlogo/nvm/Context.runExclusiveJob (Lorg/nlogo/agent/AgentSet;I)V
          ALOAD 1
          ICONST_4
          PUTFIELD org/nlogo/nvm/Context.ip : I
         L7
          RETURN
[2]_asm_procedurehidewater_call_2 "recolor"
         L0
          NEW org/nlogo/nvm/Activation
          DUP
          ALOAD 0
          GETFIELD org/nlogo/prim/_asm_procedurehidewater_call_2.kept1_procedure : Lorg/nlogo/nvm/Procedure;
          ALOAD 1
          GETFIELD org/nlogo/nvm/Context.activation : Lorg/nlogo/nvm/Activation;
          ICONST_3
          INVOKESPECIAL org/nlogo/nvm/Activation.<init> (Lorg/nlogo/nvm/Procedure;Lorg/nlogo/nvm/Activation;I)V
          ALOAD 1
          SWAP
          PUTFIELD org/nlogo/nvm/Context.activation : Lorg/nlogo/nvm/Activation;
          ALOAD 1
          ICONST_0
          PUTFIELD org/nlogo/nvm/Context.ip : I
         L1
          RETURN
[3]_asm_procedurehidewater_done_3 => void
         L0
          ALOAD 1
          ICONST_1
          PUTFIELD org/nlogo/nvm/Context.finished : Z
         L1
          RETURN
[4]_asm_procedurehidewater_return_4 => void
         L0
          ALOAD 1
          INVOKEVIRTUAL org/nlogo/nvm/Context.returnFromProcedure ()V
          ALOAD 1
          ICONST_0
          PUTFIELD org/nlogo/nvm/Context.stopping : Z
         L1
          RETURN

procedure SHOW-WATER:[]{OTPL}:
[0]_asm_procedureshowwater_setobservervariable_0 "set show-water? true" Object => void
      _constboolean:true "true" => Boolean
          TRYCATCHBLOCK L0 L1 L2 org/nlogo/api/AgentException
         L3
          ALOAD 0
          GETFIELD org/nlogo/prim/_asm_procedureshowwater_setobservervariable_0.kept2_value : Ljava/lang/Boolean;
         L4
          ASTORE 2
         L0
          ALOAD 1
          GETFIELD org/nlogo/nvm/Context.agent : Lorg/nlogo/agent/Agent;
          BIPUSH 6
          ALOAD 2
          INVOKEVIRTUAL org/nlogo/agent/Agent.setObserverVariable (ILjava/lang/Object;)V
         L1
          GOTO L5
         L2
         FRAME FULL [org/nlogo/prim/_asm_procedureshowwater_setobservervariable_0 org/nlogo/nvm/Context java/lang/Boolean] [org/nlogo/api/AgentException]
          ASTORE 3
          NEW org/nlogo/nvm/EngineException
          DUP
          ALOAD 1
          ALOAD 0
          ALOAD 3
          INVOKEVIRTUAL org/nlogo/api/AgentException.getMessage ()Ljava/lang/String;
          INVOKESPECIAL org/nlogo/nvm/EngineException.<init> (Lorg/nlogo/nvm/Context;Lorg/nlogo/nvm/Instruction;Ljava/lang/String;)V
          ATHROW
         L5
         FRAME SAME
          ALOAD 1
          ICONST_1
          PUTFIELD org/nlogo/nvm/Context.ip : I
         L6
          RETURN
[1]_asm_procedureshowwater_ask_1 "ask land [ recolor ]" Object => void
      _observervariable:LAND "land" => Object
         L0
          ALOAD 1
          GETFIELD org/nlogo/nvm/Context.agent : Lorg/nlogo/agent/Agent;
          BIPUSH 8
          INVOKEVIRTUAL org/nlogo/agent/Agent.getObserverVariable (I)Ljava/lang/Object;
         L1
          ASTORE 2
          ALOAD 2
          INSTANCEOF org/nlogo/agent/AgentSet
          IFEQ L2
          ALOAD 2
          CHECKCAST org/nlogo/agent/AgentSet
          ASTORE 3
          ALOAD 1
          GETFIELD org/nlogo/nvm/Context.agent : Lorg/nlogo/agent/Agent;
          INSTANCEOF org/nlogo/agent/Observer
          IFNE L3
          ALOAD 3
          ALOAD 0
          GETFIELD org/nlogo/prim/_asm_procedureshowwater_ask_1.world : Lorg/nlogo/agent/World;
          INVOKEVIRTUAL org/nlogo/agent/World.turtles ()Lorg/nlogo/agent/AgentSet;
          IF_ACMPNE L4
          NEW org/nlogo/nvm/EngineException
          DUP
          ALOAD 1
          ALOAD 0
          INVOKESTATIC org/nlogo/core/I18N.errorsJ ()Lorg/nlogo/core/I18NJava;
          LDC "org.nlogo.prim.$common.onlyObserverCanAskAllTurtles"
          INVOKEINTERFACE org/nlogo/core/I18NJava.get (Ljava/lang/String;)Ljava/lang/String;
          INVOKESPECIAL org/nlogo/nvm/EngineException.<init> (Lorg/nlogo/nvm/Context;Lorg/nlogo/nvm/Instruction;Ljava/lang/String;)V
          ATHROW
         L4
         FRAME APPEND [java/lang/Object org/nlogo/agent/AgentSet]
          ALOAD 3
          ALOAD 0
          GETFIELD org/nlogo/prim/_asm_procedureshowwater_ask_1.world : Lorg/nlogo/agent/World;
          INVOKEVIRTUAL org/nlogo/agent/World.patches ()Lorg/nlogo/agent/AgentSet;
          IF_ACMPNE L3
          NEW org/nlogo/nvm/EngineException
          DUP
          ALOAD 1
          ALOAD 0
          INVOKESTATIC org/nlogo/core/I18N.errorsJ ()Lorg/nlogo/core/I18NJava;
          LDC "org.nlogo.prim.$common.onlyObserverCanAskAllPatches"
          INVOKEINTERFACE org/nlogo/core/I18NJava.get (Ljava/lang/String;)Ljava/lang/String;
          INVOKESPECIAL org/nlogo/nvm/EngineException.<init> (Lorg/nlogo/nvm/Context;Lorg/nlogo/nvm/Instruction;Ljava/lang/String;)V
          ATHROW
         L2
         FRAME CHOP 1
          ALOAD 2
          INSTANCEOF org/nlogo/agent/Agent
          IFEQ L5
          ALOAD 2
          CHECKCAST org/nlogo/agent/Agent
          ASTORE 4
          ALOAD 4
          GETFIELD org/nlogo/agent/Agent.id : J
          LDC -1
          LCMP
          IFNE L6
          NEW org/nlogo/nvm/EngineException
          DUP
          ALOAD 1
          ALOAD 0
          INVOKESTATIC org/nlogo/core/I18N.errorsJ ()Lorg/nlogo/core/I18NJava;
          LDC "org.nlogo.$common.thatAgentIsDead"
          ICONST_1
          ANEWARRAY java/lang/Object
          DUP
          ICONST_0
          ALOAD 4
          INVOKEVIRTUAL org/nlogo/agent/Agent.classDisplayName ()Ljava/lang/String;
          AASTORE
          INVOKEINTERFACE org/nlogo/core/I18NJava.getN (Ljava/lang/String;[Ljava/lang/Object;)Ljava/lang/String;
          INVOKESPECIAL org/nlogo/nvm/EngineException.<init> (Lorg/nlogo/nvm/Context;Lorg/nlogo/nvm/Instruction;Ljava/lang/String;)V
          ATHROW
         L6
         FRAME APPEND [T org/nlogo/agent/Agent]
          NEW org/nlogo/agent/ArrayAgentSet
          DUP
          ALOAD 4
          INVOKEVIRTUAL org/nlogo/agent/Agent.kind ()Lorg/nlogo/core/AgentKind;
          ICONST_1
          ICONST_0
          INVOKESPECIAL org/nlogo/agent/ArrayAgentSet.<init> (Lorg/nlogo/core/AgentKind;IZ)V
          ASTORE 3
          ALOAD 3
          ALOAD 4
          INVOKEVIRTUAL org/nlogo/agent/AgentSet.add (Lorg/nlogo/agent/Agent;)V
          GOTO L3
         L5
         FRAME CHOP 2
          NEW org/nlogo/nvm/ArgumentTypeException
          DUP
          ALOAD 1
          ALOAD 0
          ICONST_0
          INVOKESTATIC org/nlogo/core/Syntax.AgentsetType ()I
          INVOKESTATIC org/nlogo/core/Syntax.AgentType ()I
          IOR
          ALOAD 2
          INVOKESPECIAL org/nlogo/nvm/ArgumentTypeException.<init> (Lorg/nlogo/nvm/Context;Lorg/nlogo/nvm/Instruction;IILjava/lang/Object;)V
          ATHROW
         L3
         FRAME APPEND [org/nlogo/agent/AgentSet]
          ALOAD 1
          ALOAD 3
          ICONST_2
          INVOKEVIRTUAL org/nlogo/nvm/Context.runExclusiveJob (Lorg/nlogo/agent/AgentSet;I)V
          ALOAD 1
          ICONST_4
          PUTFIELD org/nlogo/nvm/Context.ip : I
         L7
          RETURN
[2]_asm_procedureshowwater_call_2 "recolor"
         L0
          NEW org/nlogo/nvm/Activation
          DUP
          ALOAD 0
          GETFIELD org/nlogo/prim/_asm_procedureshowwater_call_2.kept1_procedure : Lorg/nlogo/nvm/Procedure;
          ALOAD 1
          GETFIELD org/nlogo/nvm/Context.activation : Lorg/nlogo/nvm/Activation;
          ICONST_3
          INVOKESPECIAL org/nlogo/nvm/Activation.<init> (Lorg/nlogo/nvm/Procedure;Lorg/nlogo/nvm/Activation;I)V
          ALOAD 1
          SWAP
          PUTFIELD org/nlogo/nvm/Context.activation : Lorg/nlogo/nvm/Activation;
          ALOAD 1
          ICONST_0
          PUTFIELD org/nlogo/nvm/Context.ip : I
         L1
          RETURN
[3]_asm_procedureshowwater_done_3 => void
         L0
          ALOAD 1
          ICONST_1
          PUTFIELD org/nlogo/nvm/Context.finished : Z
         L1
          RETURN
[4]_asm_procedureshowwater_return_4 => void
         L0
          ALOAD 1
          INVOKEVIRTUAL org/nlogo/nvm/Context.returnFromProcedure ()V
          ALOAD 1
          ICONST_0
          PUTFIELD org/nlogo/nvm/Context.stopping : Z
         L1
          RETURN

