globals [RESULT]
interfaceGlobals []
turtles-own [WHO COLOR HEADING XCOR YCOR SHAPE LABEL LABEL-COLOR BREED HIDDEN? SIZE PEN-SIZE PEN-MODE]
patches-own [PXCOR PYCOR PCOLOR PLABEL PLABEL-COLOR]
links-own [END1 END2 COLOR LABEL LABEL-COLOR HIDDEN? BREED THICKNESS SHAPE TIE-MODE]
breeds 
link-breeds 

procedure BENCHMARK:[_repeatlocal:0]{O---}:
[0]_asm_procedurebenchmark_randomseed_0 "random-seed 362" double => void
      _constdouble:362.0 "362" => double
         L0
          LDC 362.0
         L1
          DSTORE 2
          DLOAD 2
          D2L
          LSTORE 4
          LLOAD 4
          LDC -2147483648
          LCMP
          IFLT L2
          LLOAD 4
          LDC 2147483647
          LCMP
          IFLE L3
         L2
         FRAME APPEND [D J]
          NEW org/nlogo/nvm/EngineException
          DUP
          ALOAD 1
          ALOAD 0
          NEW scala/collection/mutable/StringBuilder
          DUP
          INVOKESPECIAL scala/collection/mutable/StringBuilder.<init> ()V
          GETSTATIC org/nlogo/api/Dump$.MODULE$ : Lorg/nlogo/api/Dump$;
          DLOAD 2
          INVOKEVIRTUAL org/nlogo/api/Dump$.number (D)Ljava/lang/String;
          INVOKEVIRTUAL scala/collection/mutable/StringBuilder.append (Ljava/lang/Object;)Lscala/collection/mutable/StringBuilder;
          LDC " is not in the allowable range for random seeds (-2147483648 to 2147483647)"
          INVOKEVIRTUAL scala/collection/mutable/StringBuilder.append (Ljava/lang/Object;)Lscala/collection/mutable/StringBuilder;
          INVOKEVIRTUAL scala/collection/mutable/StringBuilder.toString ()Ljava/lang/String;
          INVOKESPECIAL org/nlogo/nvm/EngineException.<init> (Lorg/nlogo/nvm/Context;Lorg/nlogo/nvm/Instruction;Ljava/lang/String;)V
          ATHROW
         L3
         FRAME SAME
          ALOAD 1
          GETFIELD org/nlogo/nvm/Context.job : Lorg/nlogo/nvm/Job;
          GETFIELD org/nlogo/nvm/Job.random : Lorg/nlogo/api/MersenneTwisterFast;
          LLOAD 4
          L2I
          I2L
          INVOKEVIRTUAL org/nlogo/api/MersenneTwisterFast.setSeed (J)V
          ALOAD 1
          ICONST_1
          PUTFIELD org/nlogo/nvm/Context.ip : I
         L4
          RETURN
[1]_asm_procedurebenchmark_call_1 "setup"
         L0
          NEW org/nlogo/nvm/Activation
          DUP
          ALOAD 0
          GETFIELD org/nlogo/prim/_asm_procedurebenchmark_call_1.kept1_procedure : Lorg/nlogo/nvm/Procedure;
          ALOAD 1
          GETFIELD org/nlogo/nvm/Context.activation : Lorg/nlogo/nvm/Activation;
          ICONST_2
          INVOKESPECIAL org/nlogo/nvm/Activation.<init> (Lorg/nlogo/nvm/Procedure;Lorg/nlogo/nvm/Activation;I)V
          ALOAD 1
          SWAP
          PUTFIELD org/nlogo/nvm/Context.activation : Lorg/nlogo/nvm/Activation;
          ALOAD 1
          ICONST_0
          PUTFIELD org/nlogo/nvm/Context.ip : I
         L1
          RETURN
[2]_resettimer "reset-timer"
[3]_asm_procedurebenchmark_repeatlocal_2 "repeat 20000 [ go ]" double => void
      _constdouble:20000.0 "20000" => double
         L0
          LDC 20000.0
         L1
          DSTORE 2
          ALOAD 1
          GETFIELD org/nlogo/nvm/Context.activation : Lorg/nlogo/nvm/Activation;
          GETFIELD org/nlogo/nvm/Activation.args : [Ljava/lang/Object;
          ICONST_0
          NEW org/nlogo/nvm/MutableLong
          DUP
          ALOAD 0
          DLOAD 2
          INVOKEVIRTUAL org/nlogo/prim/_asm_procedurebenchmark_repeatlocal_2.validLong (D)J
          INVOKESPECIAL org/nlogo/nvm/MutableLong.<init> (J)V
          AASTORE
          ALOAD 1
          ICONST_5
          PUTFIELD org/nlogo/nvm/Context.ip : I
         L2
          RETURN
[4]_asm_procedurebenchmark_call_3 "go"
         L0
          NEW org/nlogo/nvm/Activation
          DUP
          ALOAD 0
          GETFIELD org/nlogo/prim/_asm_procedurebenchmark_call_3.kept1_procedure : Lorg/nlogo/nvm/Procedure;
          ALOAD 1
          GETFIELD org/nlogo/nvm/Context.activation : Lorg/nlogo/nvm/Activation;
          ICONST_5
          INVOKESPECIAL org/nlogo/nvm/Activation.<init> (Lorg/nlogo/nvm/Procedure;Lorg/nlogo/nvm/Activation;I)V
          ALOAD 1
          SWAP
          PUTFIELD org/nlogo/nvm/Context.activation : Lorg/nlogo/nvm/Activation;
          ALOAD 1
          ICONST_0
          PUTFIELD org/nlogo/nvm/Context.ip : I
         L1
          RETURN
[5]_asm_procedurebenchmark_repeatlocalinternal_4 => void
         L0
          ALOAD 1
          GETFIELD org/nlogo/nvm/Context.activation : Lorg/nlogo/nvm/Activation;
          GETFIELD org/nlogo/nvm/Activation.args : [Ljava/lang/Object;
          ICONST_0
          AALOAD
          CHECKCAST org/nlogo/nvm/MutableLong
          ASTORE 2
          ALOAD 2
          INVOKEVIRTUAL org/nlogo/nvm/MutableLong.value ()J
          LCONST_0
          LCMP
          IFGT L1
          ALOAD 1
          BIPUSH 6
          PUTFIELD org/nlogo/nvm/Context.ip : I
          GOTO L2
         L1
         FRAME APPEND [org/nlogo/nvm/MutableLong]
          ALOAD 2
          ALOAD 2
          INVOKEVIRTUAL org/nlogo/nvm/MutableLong.value ()J
          LCONST_1
          LSUB
          INVOKEVIRTUAL org/nlogo/nvm/MutableLong.value_$eq (J)V
          ALOAD 1
          ICONST_4
          PUTFIELD org/nlogo/nvm/Context.ip : I
         L2
         FRAME SAME
          RETURN
[6]_asm_procedurebenchmark_setobservervariable_5 "set result timer" Object => void
      _timer "timer" => double
          TRYCATCHBLOCK L0 L1 L2 org/nlogo/api/AgentException
         L3
          ALOAD 0
          GETFIELD org/nlogo/prim/_asm_procedurebenchmark_setobservervariable_5.world : Lorg/nlogo/agent/World;
          INVOKEVIRTUAL org/nlogo/agent/World.timer ()Lorg/nlogo/api/Timer;
          INVOKEVIRTUAL org/nlogo/api/Timer.read ()D
         L4
          DSTORE 2
          NEW java/lang/Double
          DUP
          DLOAD 2
          INVOKESPECIAL java/lang/Double.<init> (D)V
          ASTORE 2
         L0
          ALOAD 1
          GETFIELD org/nlogo/nvm/Context.agent : Lorg/nlogo/agent/Agent;
          ICONST_0
          ALOAD 2
          INVOKEVIRTUAL org/nlogo/agent/Agent.setObserverVariable (ILjava/lang/Object;)V
         L1
          GOTO L5
         L2
         FRAME FULL [org/nlogo/prim/_asm_procedurebenchmark_setobservervariable_5 org/nlogo/nvm/Context java/lang/Double] [org/nlogo/api/AgentException]
          ASTORE 3
          NEW org/nlogo/nvm/EngineException
          DUP
          ALOAD 1
          ALOAD 0
          ALOAD 3
          INVOKEVIRTUAL org/nlogo/api/AgentException.getMessage ()Ljava/lang/String;
          INVOKESPECIAL org/nlogo/nvm/EngineException.<init> (Lorg/nlogo/nvm/Context;Lorg/nlogo/nvm/Instruction;Ljava/lang/String;)V
          ATHROW
         L5
         FRAME SAME
          ALOAD 1
          BIPUSH 7
          PUTFIELD org/nlogo/nvm/Context.ip : I
         L6
          RETURN
[7]_asm_procedurebenchmark_return_6 => void
         L0
          ALOAD 1
          INVOKEVIRTUAL org/nlogo/nvm/Context.returnFromProcedure ()V
          ALOAD 1
          ICONST_0
          PUTFIELD org/nlogo/nvm/Context.stopping : Z
         L1
          RETURN

procedure SETUP:[]{O---}:
[0]_clearall "ca"
[1]_resetticks "reset-ticks"
[2]_createorderedturtles:,+6 "cro 1000 move-to one-of patches [ face one-of neighbors4 ]"
      _asm_proceduresetup_constdouble_0 "1000" => Double
           L0
            ALOAD 0
            GETFIELD org/nlogo/prim/_asm_proceduresetup_constdouble_0.kept1_value : Ljava/lang/Double;
           L1
            ARETURN
[3]_moveto "move-to one-of patches"
      _asm_proceduresetup_oneof_1 "one-of patches" AgentSet => Object
        _patches "patches" => AgentSet
           L0
            ALOAD 0
            GETFIELD org/nlogo/prim/_asm_proceduresetup_oneof_1.world : Lorg/nlogo/agent/World;
            INVOKEVIRTUAL org/nlogo/agent/World.patches ()Lorg/nlogo/agent/AgentSet;
           L1
            ASTORE 2
            ALOAD 2
            INVOKEVIRTUAL org/nlogo/agent/AgentSet.count ()I
            ISTORE 3
            ILOAD 3
            IFNE L2
            GETSTATIC org/nlogo/core/Nobody$.MODULE$ : Lorg/nlogo/core/Nobody$;
            GOTO L3
           L2
           FRAME APPEND [org/nlogo/agent/AgentSet I]
            ALOAD 2
            ILOAD 3
            ALOAD 1
            GETFIELD org/nlogo/nvm/Context.job : Lorg/nlogo/nvm/Job;
            GETFIELD org/nlogo/nvm/Job.random : Lorg/nlogo/api/MersenneTwisterFast;
            ILOAD 3
            INVOKEVIRTUAL org/nlogo/api/MersenneTwisterFast.nextInt (I)I
            INVOKEVIRTUAL org/nlogo/agent/AgentSet.randomOne (II)Lorg/nlogo/agent/Agent;
           L3
           FRAME SAME1 java/lang/Object
            ARETURN
[4]_asm_proceduresetup_face_2 "face one-of neighbors4" Agent => void
      _oneof "one-of neighbors4" AgentSet => Object
        _neighbors4 "neighbors4" => AgentSet
          TRYCATCHBLOCK L0 L1 L1 java/lang/ClassCastException
         L2
          ALOAD 1
          GETFIELD org/nlogo/nvm/Context.agent : Lorg/nlogo/agent/Agent;
          INSTANCEOF org/nlogo/agent/Turtle
          IFEQ L3
          ALOAD 1
          GETFIELD org/nlogo/nvm/Context.agent : Lorg/nlogo/agent/Agent;
          CHECKCAST org/nlogo/agent/Turtle
          INVOKEVIRTUAL org/nlogo/agent/Turtle.getPatchHere ()Lorg/nlogo/agent/Patch;
          INVOKEVIRTUAL org/nlogo/agent/Patch.getNeighbors4 ()Lorg/nlogo/agent/AgentSet;
          GOTO L4
         L3
         FRAME SAME
          ALOAD 1
          GETFIELD org/nlogo/nvm/Context.agent : Lorg/nlogo/agent/Agent;
          CHECKCAST org/nlogo/agent/Patch
          INVOKEVIRTUAL org/nlogo/agent/Patch.getNeighbors4 ()Lorg/nlogo/agent/AgentSet;
         L4
         FRAME SAME1 org/nlogo/agent/AgentSet
          ASTORE 2
          ALOAD 2
          INVOKEVIRTUAL org/nlogo/agent/AgentSet.count ()I
          ISTORE 3
          ILOAD 3
          IFNE L5
          GETSTATIC org/nlogo/core/Nobody$.MODULE$ : Lorg/nlogo/core/Nobody$;
          GOTO L6
         L5
         FRAME APPEND [org/nlogo/agent/AgentSet I]
          ALOAD 2
          ILOAD 3
          ALOAD 1
          GETFIELD org/nlogo/nvm/Context.job : Lorg/nlogo/nvm/Job;
          GETFIELD org/nlogo/nvm/Job.random : Lorg/nlogo/api/MersenneTwisterFast;
          ILOAD 3
          INVOKEVIRTUAL org/nlogo/api/MersenneTwisterFast.nextInt (I)I
          INVOKEVIRTUAL org/nlogo/agent/AgentSet.randomOne (II)Lorg/nlogo/agent/Agent;
         L6
         FRAME SAME1 java/lang/Object
          ASTORE 2
         L0
          ALOAD 2
          CHECKCAST org/nlogo/agent/Agent
          GOTO L7
         L1
         FRAME FULL [org/nlogo/prim/_asm_proceduresetup_face_2 org/nlogo/nvm/Context java/lang/Object I] [java/lang/ClassCastException]
          POP
          NEW org/nlogo/nvm/ArgumentTypeException
          DUP
          ALOAD 1
          ALOAD 0
          BIPUSH 0
          LDC 1792
          ALOAD 2
          INVOKESPECIAL org/nlogo/nvm/ArgumentTypeException.<init> (Lorg/nlogo/nvm/Context;Lorg/nlogo/nvm/Instruction;IILjava/lang/Object;)V
          ATHROW
         L7
         FRAME SAME1 org/nlogo/agent/Agent
          ASTORE 2
          ALOAD 2
          INSTANCEOF org/nlogo/agent/Link
          IFEQ L8
          NEW org/nlogo/nvm/EngineException
          DUP
          ALOAD 1
          ALOAD 0
          INVOKESTATIC org/nlogo/core/I18N.errorsJ ()Lorg/nlogo/core/I18NJava;
          LDC "org.nlogo.prim.etc.$common.expectedTurtleOrPatchButGotLink"
          INVOKEINTERFACE org/nlogo/core/I18NJava.get (Ljava/lang/String;)Ljava/lang/String;
          INVOKESPECIAL org/nlogo/nvm/EngineException.<init> (Lorg/nlogo/nvm/Context;Lorg/nlogo/nvm/Instruction;Ljava/lang/String;)V
          ATHROW
         L8
         FRAME FULL [org/nlogo/prim/_asm_proceduresetup_face_2 org/nlogo/nvm/Context org/nlogo/agent/Agent I] []
          ALOAD 2
          GETFIELD org/nlogo/agent/Agent.id : J
          LDC -1
          LCMP
          IFNE L9
          NEW org/nlogo/nvm/EngineException
          DUP
          ALOAD 1
          ALOAD 0
          INVOKESTATIC org/nlogo/core/I18N.errorsJ ()Lorg/nlogo/core/I18NJava;
          LDC "org.nlogo.$common.thatAgentIsDead"
          ICONST_1
          ANEWARRAY java/lang/Object
          DUP
          ICONST_0
          ALOAD 2
          INVOKEVIRTUAL org/nlogo/agent/Agent.classDisplayName ()Ljava/lang/String;
          AASTORE
          INVOKEINTERFACE org/nlogo/core/I18NJava.getN (Ljava/lang/String;[Ljava/lang/Object;)Ljava/lang/String;
          INVOKESPECIAL org/nlogo/nvm/EngineException.<init> (Lorg/nlogo/nvm/Context;Lorg/nlogo/nvm/Instruction;Ljava/lang/String;)V
          ATHROW
         L9
         FRAME SAME
          ALOAD 1
          GETFIELD org/nlogo/nvm/Context.agent : Lorg/nlogo/agent/Agent;
          INSTANCEOF org/nlogo/agent/Turtle
          IFEQ L10
          ALOAD 1
          GETFIELD org/nlogo/nvm/Context.agent : Lorg/nlogo/agent/Agent;
          CHECKCAST org/nlogo/agent/Turtle
          ALOAD 2
          ICONST_1
          INVOKEVIRTUAL org/nlogo/agent/Turtle.face (Lorg/nlogo/agent/Agent;Z)V
          GOTO L11
         L10
         FRAME SAME
          ALOAD 0
          GETFIELD org/nlogo/prim/_asm_proceduresetup_face_2.world : Lorg/nlogo/agent/World;
          INVOKEVIRTUAL org/nlogo/agent/World.observer ()Lorg/nlogo/agent/Observer;
          ALOAD 2
          INVOKEVIRTUAL org/nlogo/agent/Observer.face (Lorg/nlogo/api/Agent;)V
         L11
         FRAME SAME
          ALOAD 1
          ICONST_5
          PUTFIELD org/nlogo/nvm/Context.ip : I
         L12
          RETURN
[5]_asm_proceduresetup_done_3 => void
         L0
          ALOAD 1
          ICONST_1
          PUTFIELD org/nlogo/nvm/Context.finished : Z
         L1
          RETURN
[6]_asm_proceduresetup_return_4 => void
         L0
          ALOAD 1
          INVOKEVIRTUAL org/nlogo/nvm/Context.returnFromProcedure ()V
          ALOAD 1
          ICONST_0
          PUTFIELD org/nlogo/nvm/Context.stopping : Z
         L1
          RETURN

procedure GO:[]{O---}:
[0]_asm_procedurego_ask_0 "ask turtles face one-of neighbors4 [ fd 1 ]" AgentSet => void
      _turtles "turtles" => AgentSet
         L0
          ALOAD 0
          GETFIELD org/nlogo/prim/_asm_procedurego_ask_0.world : Lorg/nlogo/agent/World;
          INVOKEVIRTUAL org/nlogo/agent/World.turtles ()Lorg/nlogo/agent/AgentSet;
         L1
          ASTORE 2
          ALOAD 1
          GETFIELD org/nlogo/nvm/Context.agent : Lorg/nlogo/agent/Agent;
          INSTANCEOF org/nlogo/agent/Observer
          IFNE L2
          ALOAD 2
          ALOAD 0
          GETFIELD org/nlogo/prim/_asm_procedurego_ask_0.world : Lorg/nlogo/agent/World;
          INVOKEVIRTUAL org/nlogo/agent/World.turtles ()Lorg/nlogo/agent/AgentSet;
          IF_ACMPNE L3
          NEW org/nlogo/nvm/EngineException
          DUP
          ALOAD 1
          ALOAD 0
          INVOKESTATIC org/nlogo/core/I18N.errorsJ ()Lorg/nlogo/core/I18NJava;
          LDC "org.nlogo.prim.$common.onlyObserverCanAskAllTurtles"
          INVOKEINTERFACE org/nlogo/core/I18NJava.get (Ljava/lang/String;)Ljava/lang/String;
          INVOKESPECIAL org/nlogo/nvm/EngineException.<init> (Lorg/nlogo/nvm/Context;Lorg/nlogo/nvm/Instruction;Ljava/lang/String;)V
          ATHROW
         L3
         FRAME APPEND [org/nlogo/agent/AgentSet]
          ALOAD 2
          ALOAD 0
          GETFIELD org/nlogo/prim/_asm_procedurego_ask_0.world : Lorg/nlogo/agent/World;
          INVOKEVIRTUAL org/nlogo/agent/World.patches ()Lorg/nlogo/agent/AgentSet;
          IF_ACMPNE L2
          NEW org/nlogo/nvm/EngineException
          DUP
          ALOAD 1
          ALOAD 0
          INVOKESTATIC org/nlogo/core/I18N.errorsJ ()Lorg/nlogo/core/I18NJava;
          LDC "org.nlogo.prim.$common.onlyObserverCanAskAllPatches"
          INVOKEINTERFACE org/nlogo/core/I18NJava.get (Ljava/lang/String;)Ljava/lang/String;
          INVOKESPECIAL org/nlogo/nvm/EngineException.<init> (Lorg/nlogo/nvm/Context;Lorg/nlogo/nvm/Instruction;Ljava/lang/String;)V
          ATHROW
         L2
         FRAME SAME
          ALOAD 1
          ALOAD 2
          ICONST_1
          INVOKEVIRTUAL org/nlogo/nvm/Context.runExclusiveJob (Lorg/nlogo/agent/AgentSet;I)V
          ALOAD 1
          ICONST_4
          PUTFIELD org/nlogo/nvm/Context.ip : I
         L4
          RETURN
[1]_asm_procedurego_face_1 "face one-of neighbors4" Agent => void
      _oneof "one-of neighbors4" AgentSet => Object
        _neighbors4 "neighbors4" => AgentSet
          TRYCATCHBLOCK L0 L1 L1 java/lang/ClassCastException
         L2
          ALOAD 1
          GETFIELD org/nlogo/nvm/Context.agent : Lorg/nlogo/agent/Agent;
          INSTANCEOF org/nlogo/agent/Turtle
          IFEQ L3
          ALOAD 1
          GETFIELD org/nlogo/nvm/Context.agent : Lorg/nlogo/agent/Agent;
          CHECKCAST org/nlogo/agent/Turtle
          INVOKEVIRTUAL org/nlogo/agent/Turtle.getPatchHere ()Lorg/nlogo/agent/Patch;
          INVOKEVIRTUAL org/nlogo/agent/Patch.getNeighbors4 ()Lorg/nlogo/agent/AgentSet;
          GOTO L4
         L3
         FRAME SAME
          ALOAD 1
          GETFIELD org/nlogo/nvm/Context.agent : Lorg/nlogo/agent/Agent;
          CHECKCAST org/nlogo/agent/Patch
          INVOKEVIRTUAL org/nlogo/agent/Patch.getNeighbors4 ()Lorg/nlogo/agent/AgentSet;
         L4
         FRAME SAME1 org/nlogo/agent/AgentSet
          ASTORE 2
          ALOAD 2
          INVOKEVIRTUAL org/nlogo/agent/AgentSet.count ()I
          ISTORE 3
          ILOAD 3
          IFNE L5
          GETSTATIC org/nlogo/core/Nobody$.MODULE$ : Lorg/nlogo/core/Nobody$;
          GOTO L6
         L5
         FRAME APPEND [org/nlogo/agent/AgentSet I]
          ALOAD 2
          ILOAD 3
          ALOAD 1
          GETFIELD org/nlogo/nvm/Context.job : Lorg/nlogo/nvm/Job;
          GETFIELD org/nlogo/nvm/Job.random : Lorg/nlogo/api/MersenneTwisterFast;
          ILOAD 3
          INVOKEVIRTUAL org/nlogo/api/MersenneTwisterFast.nextInt (I)I
          INVOKEVIRTUAL org/nlogo/agent/AgentSet.randomOne (II)Lorg/nlogo/agent/Agent;
         L6
         FRAME SAME1 java/lang/Object
          ASTORE 2
         L0
          ALOAD 2
          CHECKCAST org/nlogo/agent/Agent
          GOTO L7
         L1
         FRAME FULL [org/nlogo/prim/_asm_procedurego_face_1 org/nlogo/nvm/Context java/lang/Object I] [java/lang/ClassCastException]
          POP
          NEW org/nlogo/nvm/ArgumentTypeException
          DUP
          ALOAD 1
          ALOAD 0
          BIPUSH 0
          LDC 1792
          ALOAD 2
          INVOKESPECIAL org/nlogo/nvm/ArgumentTypeException.<init> (Lorg/nlogo/nvm/Context;Lorg/nlogo/nvm/Instruction;IILjava/lang/Object;)V
          ATHROW
         L7
         FRAME SAME1 org/nlogo/agent/Agent
          ASTORE 2
          ALOAD 2
          INSTANCEOF org/nlogo/agent/Link
          IFEQ L8
          NEW org/nlogo/nvm/EngineException
          DUP
          ALOAD 1
          ALOAD 0
          INVOKESTATIC org/nlogo/core/I18N.errorsJ ()Lorg/nlogo/core/I18NJava;
          LDC "org.nlogo.prim.etc.$common.expectedTurtleOrPatchButGotLink"
          INVOKEINTERFACE org/nlogo/core/I18NJava.get (Ljava/lang/String;)Ljava/lang/String;
          INVOKESPECIAL org/nlogo/nvm/EngineException.<init> (Lorg/nlogo/nvm/Context;Lorg/nlogo/nvm/Instruction;Ljava/lang/String;)V
          ATHROW
         L8
         FRAME FULL [org/nlogo/prim/_asm_procedurego_face_1 org/nlogo/nvm/Context org/nlogo/agent/Agent I] []
          ALOAD 2
          GETFIELD org/nlogo/agent/Agent.id : J
          LDC -1
          LCMP
          IFNE L9
          NEW org/nlogo/nvm/EngineException
          DUP
          ALOAD 1
          ALOAD 0
          INVOKESTATIC org/nlogo/core/I18N.errorsJ ()Lorg/nlogo/core/I18NJava;
          LDC "org.nlogo.$common.thatAgentIsDead"
          ICONST_1
          ANEWARRAY java/lang/Object
          DUP
          ICONST_0
          ALOAD 2
          INVOKEVIRTUAL org/nlogo/agent/Agent.classDisplayName ()Ljava/lang/String;
          AASTORE
          INVOKEINTERFACE org/nlogo/core/I18NJava.getN (Ljava/lang/String;[Ljava/lang/Object;)Ljava/lang/String;
          INVOKESPECIAL org/nlogo/nvm/EngineException.<init> (Lorg/nlogo/nvm/Context;Lorg/nlogo/nvm/Instruction;Ljava/lang/String;)V
          ATHROW
         L9
         FRAME SAME
          ALOAD 1
          GETFIELD org/nlogo/nvm/Context.agent : Lorg/nlogo/agent/Agent;
          INSTANCEOF org/nlogo/agent/Turtle
          IFEQ L10
          ALOAD 1
          GETFIELD org/nlogo/nvm/Context.agent : Lorg/nlogo/agent/Agent;
          CHECKCAST org/nlogo/agent/Turtle
          ALOAD 2
          ICONST_1
          INVOKEVIRTUAL org/nlogo/agent/Turtle.face (Lorg/nlogo/agent/Agent;Z)V
          GOTO L11
         L10
         FRAME SAME
          ALOAD 0
          GETFIELD org/nlogo/prim/_asm_procedurego_face_1.world : Lorg/nlogo/agent/World;
          INVOKEVIRTUAL org/nlogo/agent/World.observer ()Lorg/nlogo/agent/Observer;
          ALOAD 2
          INVOKEVIRTUAL org/nlogo/agent/Observer.face (Lorg/nlogo/api/Agent;)V
         L11
         FRAME SAME
          ALOAD 1
          ICONST_2
          PUTFIELD org/nlogo/nvm/Context.ip : I
         L12
          RETURN
[2]_asm_procedurego_fd1_2 "fd 1" => void
          TRYCATCHBLOCK L0 L1 L2 org/nlogo/api/AgentException
         L0
          ALOAD 1
          GETFIELD org/nlogo/nvm/Context.agent : Lorg/nlogo/agent/Agent;
          CHECKCAST org/nlogo/agent/Turtle
          DCONST_1
          INVOKEVIRTUAL org/nlogo/agent/Turtle.jump (D)V
         L1
          GOTO L3
         L2
         FRAME SAME1 org/nlogo/api/AgentException
          ASTORE 2
         L3
         FRAME SAME
          ALOAD 1
          ICONST_3
          PUTFIELD org/nlogo/nvm/Context.ip : I
         L4
          RETURN
[3]_asm_procedurego_done_3 => void
         L0
          ALOAD 1
          ICONST_1
          PUTFIELD org/nlogo/nvm/Context.finished : Z
         L1
          RETURN
[4]_tick "tick"
[5]_asm_procedurego_return_4 => void
         L0
          ALOAD 1
          INVOKEVIRTUAL org/nlogo/nvm/Context.returnFromProcedure ()V
          ALOAD 1
          ICONST_0
          PUTFIELD org/nlogo/nvm/Context.stopping : Z
         L1
          RETURN

