globals [DENSITY RESULT]
interfaceGlobals [density]
turtles-own [WHO COLOR HEADING XCOR YCOR SHAPE LABEL LABEL-COLOR BREED HIDDEN? SIZE PEN-SIZE PEN-MODE]
patches-own [PXCOR PYCOR PCOLOR PLABEL PLABEL-COLOR P1 P2]
links-own [END1 END2 COLOR LABEL LABEL-COLOR HIDDEN? BREED THICKNESS SHAPE TIE-MODE]
breeds 
link-breeds 

procedure BENCHMARK:[NAME SALT]{O---}:
[0]_asm_procedurebenchmark_randomseed_0 "random-seed 362" double => void
      _constdouble:362.0 => double
         L0
          LDC 362.0
         L1
          DSTORE 2
          DLOAD 2
          D2L
          LSTORE 4
          LLOAD 4
          LDC -2147483648
          LCMP
          IFLT L2
          LLOAD 4
          LDC 2147483647
          LCMP
          IFLE L3
         L2
          NEW org/nlogo/nvm/EngineException
          DUP
          ALOAD 1
          ALOAD 0
          NEW scala/collection/mutable/StringBuilder
          DUP
          INVOKESPECIAL scala/collection/mutable/StringBuilder.<init> ()V
          GETSTATIC org/nlogo/api/Dump$.MODULE$ : Lorg/nlogo/api/Dump$;
          DLOAD 2
          INVOKEVIRTUAL org/nlogo/api/Dump$.number (D)Ljava/lang/String;
          INVOKEVIRTUAL scala/collection/mutable/StringBuilder.append (Ljava/lang/Object;)Lscala/collection/mutable/StringBuilder;
          LDC " is not in the allowable range for random seeds (-2147483648 to 2147483647)"
          INVOKEVIRTUAL scala/collection/mutable/StringBuilder.append (Ljava/lang/Object;)Lscala/collection/mutable/StringBuilder;
          INVOKEVIRTUAL scala/collection/mutable/StringBuilder.toString ()Ljava/lang/String;
          INVOKESPECIAL org/nlogo/nvm/EngineException.<init> (Lorg/nlogo/nvm/Context;Lorg/nlogo/nvm/Instruction;Ljava/lang/String;)V
          ATHROW
         L3
          ALOAD 1
          GETFIELD org/nlogo/nvm/Context.job : Lorg/nlogo/nvm/Job;
          GETFIELD org/nlogo/nvm/Job.random : Lorg/nlogo/util/MersenneTwisterFast;
          LLOAD 4
          L2I
          I2L
          INVOKEVIRTUAL org/nlogo/util/MersenneTwisterFast.setSeed (J)V
          ALOAD 1
          ICONST_1
          PUTFIELD org/nlogo/nvm/Context.ip : I
         L4
          RETURN
[1]_asm_procedurebenchmark_ask_1 "ask patches" AgentSet => void
      _patches => AgentSet
         L0
          ALOAD 0
          GETFIELD org/nlogo/prim/_asm_procedurebenchmark_ask_1.world : Lorg/nlogo/agent/World;
          INVOKEVIRTUAL org/nlogo/agent/World.patches ()Lorg/nlogo/agent/AgentSet;
         L1
          ASTORE 2
          ALOAD 1
          GETFIELD org/nlogo/nvm/Context.agent : Lorg/nlogo/agent/Agent;
          INSTANCEOF org/nlogo/agent/Observer
          IFNE L2
          ALOAD 2
          ALOAD 0
          GETFIELD org/nlogo/prim/_asm_procedurebenchmark_ask_1.world : Lorg/nlogo/agent/World;
          INVOKEVIRTUAL org/nlogo/agent/World.turtles ()Lorg/nlogo/agent/AgentSet;
          IF_ACMPNE L3
          NEW org/nlogo/nvm/EngineException
          DUP
          ALOAD 1
          ALOAD 0
          GETSTATIC org/nlogo/api/I18N$.MODULE$ : Lorg/nlogo/api/I18N$;
          INVOKEVIRTUAL org/nlogo/api/I18N$.errors ()Lorg/nlogo/api/I18N$BundleKind;
          LDC "org.nlogo.prim.$common.onlyObserverCanAskAllTurtles"
          INVOKEVIRTUAL org/nlogo/api/I18N$BundleKind.get (Ljava/lang/String;)Ljava/lang/String;
          INVOKESPECIAL org/nlogo/nvm/EngineException.<init> (Lorg/nlogo/nvm/Context;Lorg/nlogo/nvm/Instruction;Ljava/lang/String;)V
          ATHROW
         L3
          ALOAD 2
          ALOAD 0
          GETFIELD org/nlogo/prim/_asm_procedurebenchmark_ask_1.world : Lorg/nlogo/agent/World;
          INVOKEVIRTUAL org/nlogo/agent/World.patches ()Lorg/nlogo/agent/AgentSet;
          IF_ACMPNE L2
          NEW org/nlogo/nvm/EngineException
          DUP
          ALOAD 1
          ALOAD 0
          GETSTATIC org/nlogo/api/I18N$.MODULE$ : Lorg/nlogo/api/I18N$;
          INVOKEVIRTUAL org/nlogo/api/I18N$.errors ()Lorg/nlogo/api/I18N$BundleKind;
          LDC "org.nlogo.prim.$common.onlyObserverCanAskAllPatches"
          INVOKEVIRTUAL org/nlogo/api/I18N$BundleKind.get (Ljava/lang/String;)Ljava/lang/String;
          INVOKESPECIAL org/nlogo/nvm/EngineException.<init> (Lorg/nlogo/nvm/Context;Lorg/nlogo/nvm/Instruction;Ljava/lang/String;)V
          ATHROW
         L2
          ALOAD 1
          ALOAD 2
          ICONST_2
          INVOKEVIRTUAL org/nlogo/nvm/Context.runExclusiveJob (Lorg/nlogo/agent/AgentSet;I)V
          ALOAD 1
          BIPUSH 6
          PUTFIELD org/nlogo/nvm/Context.ip : I
         L4
          RETURN
[2]_asm_procedurebenchmark_setpatchvariable_2 "set p1 random" Object => void
      _randomconst:100 => double
          TRYCATCHBLOCK L0 L1 L2 org/nlogo/api/AgentException
         L3
          ALOAD 1
          GETFIELD org/nlogo/nvm/Context.job : Lorg/nlogo/nvm/Job;
          GETFIELD org/nlogo/nvm/Job.random : Lorg/nlogo/util/MersenneTwisterFast;
          LDC 100
          INVOKEVIRTUAL org/nlogo/util/MersenneTwisterFast.nextLong (J)J
          L2D
         L4
          DSTORE 2
          NEW java/lang/Double
          DUP
          DLOAD 2
          INVOKESPECIAL java/lang/Double.<init> (D)V
          ASTORE 2
         L0
          ALOAD 1
          GETFIELD org/nlogo/nvm/Context.agent : Lorg/nlogo/agent/Agent;
          ICONST_5
          ALOAD 2
          INVOKEVIRTUAL org/nlogo/agent/Agent.setPatchVariable (ILjava/lang/Object;)V
         L1
          ALOAD 1
          ICONST_3
          PUTFIELD org/nlogo/nvm/Context.ip : I
          GOTO L5
         L2
          ASTORE 3
          NEW org/nlogo/nvm/EngineException
          DUP
          ALOAD 1
          ALOAD 0
          ALOAD 3
          INVOKEVIRTUAL java/lang/Throwable.getMessage ()Ljava/lang/String;
          INVOKESPECIAL org/nlogo/nvm/EngineException.<init> (Lorg/nlogo/nvm/Context;Lorg/nlogo/nvm/Instruction;Ljava/lang/String;)V
          ATHROW
         L5
          RETURN
[3]_asm_procedurebenchmark_setpatchvariable_3 "set p2 random" Object => void
      _randomconst:100 => double
          TRYCATCHBLOCK L0 L1 L2 org/nlogo/api/AgentException
         L3
          ALOAD 1
          GETFIELD org/nlogo/nvm/Context.job : Lorg/nlogo/nvm/Job;
          GETFIELD org/nlogo/nvm/Job.random : Lorg/nlogo/util/MersenneTwisterFast;
          LDC 100
          INVOKEVIRTUAL org/nlogo/util/MersenneTwisterFast.nextLong (J)J
          L2D
         L4
          DSTORE 2
          NEW java/lang/Double
          DUP
          DLOAD 2
          INVOKESPECIAL java/lang/Double.<init> (D)V
          ASTORE 2
         L0
          ALOAD 1
          GETFIELD org/nlogo/nvm/Context.agent : Lorg/nlogo/agent/Agent;
          BIPUSH 6
          ALOAD 2
          INVOKEVIRTUAL org/nlogo/agent/Agent.setPatchVariable (ILjava/lang/Object;)V
         L1
          ALOAD 1
          ICONST_4
          PUTFIELD org/nlogo/nvm/Context.ip : I
          GOTO L5
         L2
          ASTORE 3
          NEW org/nlogo/nvm/EngineException
          DUP
          ALOAD 1
          ALOAD 0
          ALOAD 3
          INVOKEVIRTUAL java/lang/Throwable.getMessage ()Ljava/lang/String;
          INVOKESPECIAL org/nlogo/nvm/EngineException.<init> (Lorg/nlogo/nvm/Context;Lorg/nlogo/nvm/Instruction;Ljava/lang/String;)V
          ATHROW
         L5
          RETURN
[4]_asm_procedurebenchmark_setpatchvariable_4 "set pcolor one-of base-colors" Object => void
      _oneof LogoList => Object
        _basecolors => LogoList
          TRYCATCHBLOCK L0 L1 L2 org/nlogo/api/AgentException
         L3
          GETSTATIC org/nlogo/prim/etc/_basecolors$.MODULE$ : Lorg/nlogo/prim/etc/_basecolors$;
          INVOKEVIRTUAL org/nlogo/prim/etc/_basecolors$.cached ()Lorg/nlogo/api/LogoList;
         L4
          ASTORE 2
          ALOAD 2
          INVOKEVIRTUAL org/nlogo/api/LogoList.size ()I
          ISTORE 3
          ILOAD 3
          ICONST_0
          IF_ICMPNE L5
          NEW org/nlogo/nvm/EngineException
          DUP
          ALOAD 1
          ALOAD 0
          GETSTATIC org/nlogo/api/I18N$.MODULE$ : Lorg/nlogo/api/I18N$;
          INVOKEVIRTUAL org/nlogo/api/I18N$.errors ()Lorg/nlogo/api/I18N$BundleKind;
          LDC "org.nlogo.prim.etc.$common.emptyListInput"
          GETSTATIC scala/Predef$.MODULE$ : Lscala/Predef$;
          ICONST_1
          ANEWARRAY java/lang/Object
          DUP
          ICONST_0
          LDC "ONE-OF"
          AASTORE
          INVOKEVIRTUAL scala/LowPriorityImplicits.wrapRefArray ([Ljava/lang/Object;)Lscala/collection/mutable/WrappedArray;
          INVOKEVIRTUAL org/nlogo/api/I18N$BundleKind.getN (Ljava/lang/String;Lscala/collection/Seq;)Ljava/lang/String;
          INVOKESPECIAL org/nlogo/nvm/EngineException.<init> (Lorg/nlogo/nvm/Context;Lorg/nlogo/nvm/Instruction;Ljava/lang/String;)V
          ATHROW
         L5
          ALOAD 2
          ALOAD 1
          GETFIELD org/nlogo/nvm/Context.job : Lorg/nlogo/nvm/Job;
          GETFIELD org/nlogo/nvm/Job.random : Lorg/nlogo/util/MersenneTwisterFast;
          ILOAD 3
          INVOKEVIRTUAL org/nlogo/util/MersenneTwisterFast.nextInt (I)I
          INVOKEVIRTUAL org/nlogo/api/LogoList.get (I)Ljava/lang/Object;
         L6
          ASTORE 2
         L0
          ALOAD 1
          GETFIELD org/nlogo/nvm/Context.agent : Lorg/nlogo/agent/Agent;
          ICONST_2
          ALOAD 2
          INVOKEVIRTUAL org/nlogo/agent/Agent.setPatchVariable (ILjava/lang/Object;)V
         L1
          ALOAD 1
          ICONST_5
          PUTFIELD org/nlogo/nvm/Context.ip : I
          GOTO L7
         L2
          ASTORE 3
          NEW org/nlogo/nvm/EngineException
          DUP
          ALOAD 1
          ALOAD 0
          ALOAD 3
          INVOKEVIRTUAL java/lang/Throwable.getMessage ()Ljava/lang/String;
          INVOKESPECIAL org/nlogo/nvm/EngineException.<init> (Lorg/nlogo/nvm/Context;Lorg/nlogo/nvm/Instruction;Ljava/lang/String;)V
          ATHROW
         L7
          RETURN
[5]_asm_procedurebenchmark_done_5 "" => void
         L0
          ALOAD 1
          ICONST_1
          PUTFIELD org/nlogo/nvm/Context.finished : Z
         L1
          RETURN
[6]_asm_procedurebenchmark_setprocedurevariable_6 "" Object => void
      _conststring:"" => String
         L0
          LDC ""
         L1
          ASTORE 2
          ALOAD 1
          GETFIELD org/nlogo/nvm/Context.activation : Lorg/nlogo/nvm/Activation;
          INVOKEVIRTUAL org/nlogo/nvm/Activation.args ()[Ljava/lang/Object;
          ICONST_0
          ALOAD 2
          AASTORE
          ALOAD 1
          BIPUSH 7
          PUTFIELD org/nlogo/nvm/Context.ip : I
         L2
          RETURN
[7]_asm_procedurebenchmark_withlocalrandomness_7 "with-local-randomness" => void
         L0
          ALOAD 1
          GETFIELD org/nlogo/nvm/Context.agent : Lorg/nlogo/agent/Agent;
          INVOKESTATIC org/nlogo/agent/AgentSet.fromAgent (Lorg/nlogo/agent/Agent;)Lorg/nlogo/agent/AgentSet;
          ASTORE 2
          ALOAD 1
          GETFIELD org/nlogo/nvm/Context.job : Lorg/nlogo/nvm/Job;
          GETFIELD org/nlogo/nvm/Job.random : Lorg/nlogo/util/MersenneTwisterFast;
          ASTORE 3
          ALOAD 1
          GETFIELD org/nlogo/nvm/Context.job : Lorg/nlogo/nvm/Job;
          ALOAD 0
          GETFIELD org/nlogo/prim/_asm_procedurebenchmark_withlocalrandomness_7.world : Lorg/nlogo/agent/World;
          INVOKEVIRTUAL org/nlogo/agent/World.mainRNG ()Lorg/nlogo/util/MersenneTwisterFast;
          INVOKEVIRTUAL org/nlogo/util/MersenneTwisterFast.clone ()Lorg/nlogo/util/MersenneTwisterFast;
          PUTFIELD org/nlogo/nvm/Job.random : Lorg/nlogo/util/MersenneTwisterFast;
          ALOAD 1
          ALOAD 2
          BIPUSH 8
          INVOKEVIRTUAL org/nlogo/nvm/Context.runExclusiveJob (Lorg/nlogo/agent/AgentSet;I)V
          ALOAD 1
          GETFIELD org/nlogo/nvm/Context.job : Lorg/nlogo/nvm/Job;
          ALOAD 3
          PUTFIELD org/nlogo/nvm/Job.random : Lorg/nlogo/util/MersenneTwisterFast;
          ALOAD 1
          BIPUSH 12
          PUTFIELD org/nlogo/nvm/Context.ip : I
         L1
          RETURN
[8]_asm_procedurebenchmark_randomseed_8 "random-seed new-seed" double => void
      _newseed => double
         L0
          ALOAD 0
          GETFIELD org/nlogo/prim/_asm_procedurebenchmark_randomseed_8.world : Lorg/nlogo/agent/World;
          INVOKEVIRTUAL org/nlogo/agent/World.generateSeed ()D
         L1
          DSTORE 2
          DLOAD 2
          D2L
          LSTORE 4
          LLOAD 4
          LDC -2147483648
          LCMP
          IFLT L2
          LLOAD 4
          LDC 2147483647
          LCMP
          IFLE L3
         L2
          NEW org/nlogo/nvm/EngineException
          DUP
          ALOAD 1
          ALOAD 0
          NEW scala/collection/mutable/StringBuilder
          DUP
          INVOKESPECIAL scala/collection/mutable/StringBuilder.<init> ()V
          GETSTATIC org/nlogo/api/Dump$.MODULE$ : Lorg/nlogo/api/Dump$;
          DLOAD 2
          INVOKEVIRTUAL org/nlogo/api/Dump$.number (D)Ljava/lang/String;
          INVOKEVIRTUAL scala/collection/mutable/StringBuilder.append (Ljava/lang/Object;)Lscala/collection/mutable/StringBuilder;
          LDC " is not in the allowable range for random seeds (-2147483648 to 2147483647)"
          INVOKEVIRTUAL scala/collection/mutable/StringBuilder.append (Ljava/lang/Object;)Lscala/collection/mutable/StringBuilder;
          INVOKEVIRTUAL scala/collection/mutable/StringBuilder.toString ()Ljava/lang/String;
          INVOKESPECIAL org/nlogo/nvm/EngineException.<init> (Lorg/nlogo/nvm/Context;Lorg/nlogo/nvm/Instruction;Ljava/lang/String;)V
          ATHROW
         L3
          ALOAD 1
          GETFIELD org/nlogo/nvm/Context.job : Lorg/nlogo/nvm/Job;
          GETFIELD org/nlogo/nvm/Job.random : Lorg/nlogo/util/MersenneTwisterFast;
          LLOAD 4
          L2I
          I2L
          INVOKEVIRTUAL org/nlogo/util/MersenneTwisterFast.setSeed (J)V
          ALOAD 1
          BIPUSH 9
          PUTFIELD org/nlogo/nvm/Context.ip : I
         L4
          RETURN
[9]_asm_procedurebenchmark_setprocedurevariable_9 "" Object => void
      _randomconst:10000000 => double
         L0
          ALOAD 1
          GETFIELD org/nlogo/nvm/Context.job : Lorg/nlogo/nvm/Job;
          GETFIELD org/nlogo/nvm/Job.random : Lorg/nlogo/util/MersenneTwisterFast;
          LDC 10000000
          INVOKEVIRTUAL org/nlogo/util/MersenneTwisterFast.nextLong (J)J
          L2D
         L1
          DSTORE 2
          NEW java/lang/Double
          DUP
          DLOAD 2
          INVOKESPECIAL java/lang/Double.<init> (D)V
          ASTORE 2
          ALOAD 1
          GETFIELD org/nlogo/nvm/Context.activation : Lorg/nlogo/nvm/Activation;
          INVOKEVIRTUAL org/nlogo/nvm/Activation.args ()[Ljava/lang/Object;
          ICONST_1
          ALOAD 2
          AASTORE
          ALOAD 1
          BIPUSH 10
          PUTFIELD org/nlogo/nvm/Context.ip : I
         L2
          RETURN
[10]_asm_procedurebenchmark_setprocedurevariable_10 "set name (word "firebig-" salt ".csv"" Object => void
      _word
        _conststring:"firebig-" => String
        _procedurevariable:SALT => Object
        _conststring:".csv" => String
         L0
          NEW java/lang/StringBuilder
          DUP
          INVOKESPECIAL java/lang/StringBuilder.<init> ()V
         L1
          LDC "firebig-"
         L2
          INVOKESTATIC org/nlogo/api/Dump.logoObject (Ljava/lang/Object;)Ljava/lang/String;
          INVOKEVIRTUAL java/lang/StringBuilder.append (Ljava/lang/String;)Ljava/lang/StringBuilder;
         L3
          ALOAD 1
          GETFIELD org/nlogo/nvm/Context.activation : Lorg/nlogo/nvm/Activation;
          INVOKEVIRTUAL org/nlogo/nvm/Activation.args ()[Ljava/lang/Object;
          ICONST_1
          AALOAD
         L4
          INVOKESTATIC org/nlogo/api/Dump.logoObject (Ljava/lang/Object;)Ljava/lang/String;
          INVOKEVIRTUAL java/lang/StringBuilder.append (Ljava/lang/String;)Ljava/lang/StringBuilder;
         L5
          LDC ".csv"
         L6
          INVOKESTATIC org/nlogo/api/Dump.logoObject (Ljava/lang/Object;)Ljava/lang/String;
          INVOKEVIRTUAL java/lang/StringBuilder.append (Ljava/lang/String;)Ljava/lang/StringBuilder;
          INVOKEVIRTUAL java/lang/StringBuilder.toString ()Ljava/lang/String;
         L7
          ASTORE 2
          ALOAD 1
          GETFIELD org/nlogo/nvm/Context.activation : Lorg/nlogo/nvm/Activation;
          INVOKEVIRTUAL org/nlogo/nvm/Activation.args ()[Ljava/lang/Object;
          ICONST_0
          ALOAD 2
          AASTORE
          ALOAD 1
          BIPUSH 11
          PUTFIELD org/nlogo/nvm/Context.ip : I
         L8
          RETURN
[11]_asm_procedurebenchmark_done_11 "" => void
         L0
          ALOAD 1
          ICONST_1
          PUTFIELD org/nlogo/nvm/Context.finished : Z
         L1
          RETURN
[12]_exportworld
      _asm_procedurebenchmark_procedurevariable_12 "name" => Object
           L0
            ALOAD 1
            GETFIELD org/nlogo/nvm/Context.activation : Lorg/nlogo/nvm/Activation;
            INVOKEVIRTUAL org/nlogo/nvm/Activation.args ()[Ljava/lang/Object;
            ICONST_0
            AALOAD
           L1
            ARETURN
[13]_resettimer
[14]_importworld
      _asm_procedurebenchmark_procedurevariable_13 "name" => Object
           L0
            ALOAD 1
            GETFIELD org/nlogo/nvm/Context.activation : Lorg/nlogo/nvm/Activation;
            INVOKEVIRTUAL org/nlogo/nvm/Activation.args ()[Ljava/lang/Object;
            ICONST_0
            AALOAD
           L1
            ARETURN
[15]_asm_procedurebenchmark_setobservervariable_14 "set result timer" Object => void
      _timer => double
          TRYCATCHBLOCK L0 L1 L2 org/nlogo/api/AgentException
         L3
          ALOAD 0
          GETFIELD org/nlogo/prim/_asm_procedurebenchmark_setobservervariable_14.world : Lorg/nlogo/agent/World;
          INVOKEVIRTUAL org/nlogo/agent/World.timer ()Lorg/nlogo/api/Timer;
          INVOKEVIRTUAL org/nlogo/api/Timer.read ()D
         L4
          DSTORE 2
          NEW java/lang/Double
          DUP
          DLOAD 2
          INVOKESPECIAL java/lang/Double.<init> (D)V
          ASTORE 2
         L0
          ALOAD 0
          GETFIELD org/nlogo/prim/_asm_procedurebenchmark_setobservervariable_14.world : Lorg/nlogo/agent/World;
          INVOKEVIRTUAL org/nlogo/agent/World.observer ()Lorg/nlogo/agent/Observer;
          ICONST_1
          ALOAD 2
          INVOKEVIRTUAL org/nlogo/agent/Observer.setVariable (ILjava/lang/Object;)V
         L1
          ALOAD 1
          BIPUSH 16
          PUTFIELD org/nlogo/nvm/Context.ip : I
          GOTO L5
         L2
          ASTORE 3
          NEW org/nlogo/nvm/EngineException
          DUP
          ALOAD 1
          ALOAD 0
          ALOAD 3
          INVOKEVIRTUAL java/lang/Throwable.getMessage ()Ljava/lang/String;
          INVOKESPECIAL org/nlogo/nvm/EngineException.<init> (Lorg/nlogo/nvm/Context;Lorg/nlogo/nvm/Instruction;Ljava/lang/String;)V
          ATHROW
         L5
          RETURN
[16]_asm_procedurebenchmark_return_15 "" => void
         L0
          ALOAD 1
          INVOKEVIRTUAL org/nlogo/nvm/Context.returnFromProcedure ()V
          ALOAD 1
          ICONST_0
          PUTFIELD org/nlogo/nvm/Context.stopping : Z
         L1
          RETURN

