globals [DENSITY RESULT]
interfaceGlobals [density]
turtles-own [WHO COLOR HEADING XCOR YCOR SHAPE LABEL LABEL-COLOR BREED HIDDEN? SIZE PEN-SIZE PEN-MODE]
patches-own [PXCOR PYCOR PCOLOR PLABEL PLABEL-COLOR P1 P2]
links-own [END1 END2 COLOR LABEL LABEL-COLOR HIDDEN? BREED THICKNESS SHAPE TIE-MODE]
breeds 
link-breeds 

procedure BENCHMARK:[NAME SALT]{O---}:
[0]_asm_procedurebenchmark_randomseed_0 "random-seed 362" double => void
      _constdouble:362.0 "362" => double
         L0
          LDC 362.0
         L1
          DSTORE 2
          DLOAD 2
          D2L
          LSTORE 4
          LLOAD 4
          LDC -2147483648
          LCMP
          IFLT L2
          LLOAD 4
          LDC 2147483647
          LCMP
          IFLE L3
         L2
         FRAME APPEND [D J]
          NEW org/nlogo/nvm/EngineException
          DUP
          ALOAD 1
          ALOAD 0
          NEW scala/collection/mutable/StringBuilder
          DUP
          INVOKESPECIAL scala/collection/mutable/StringBuilder.<init> ()V
          GETSTATIC org/nlogo/api/Dump$.MODULE$ : Lorg/nlogo/api/Dump$;
          DLOAD 2
          INVOKEVIRTUAL org/nlogo/api/Dump$.number (D)Ljava/lang/String;
          INVOKEVIRTUAL scala/collection/mutable/StringBuilder.append (Ljava/lang/Object;)Lscala/collection/mutable/StringBuilder;
          LDC " is not in the allowable range for random seeds (-2147483648 to 2147483647)"
          INVOKEVIRTUAL scala/collection/mutable/StringBuilder.append (Ljava/lang/Object;)Lscala/collection/mutable/StringBuilder;
          INVOKEVIRTUAL scala/collection/mutable/StringBuilder.toString ()Ljava/lang/String;
          INVOKESPECIAL org/nlogo/nvm/EngineException.<init> (Lorg/nlogo/nvm/Context;Lorg/nlogo/nvm/Instruction;Ljava/lang/String;)V
          ATHROW
         L3
         FRAME SAME
          ALOAD 1
          GETFIELD org/nlogo/nvm/Context.job : Lorg/nlogo/nvm/Job;
          GETFIELD org/nlogo/nvm/Job.random : Lorg/nlogo/api/MersenneTwisterFast;
          LLOAD 4
          L2I
          I2L
          INVOKEVIRTUAL org/nlogo/api/MersenneTwisterFast.setSeed (J)V
          ALOAD 1
          ICONST_1
          PUTFIELD org/nlogo/nvm/Context.ip : I
         L4
          RETURN
[1]_asm_procedurebenchmark_ask_1 "ask patches set p1 random 100 set p2 random 100 [ set pcolor one-of base-colors ]" AgentSet => void
      _patches "patches" => AgentSet
         L0
          ALOAD 0
          GETFIELD org/nlogo/prim/_asm_procedurebenchmark_ask_1.world : Lorg/nlogo/agent/World;
          INVOKEVIRTUAL org/nlogo/agent/World.patches ()Lorg/nlogo/agent/AgentSet;
         L1
          ASTORE 2
          ALOAD 1
          GETFIELD org/nlogo/nvm/Context.agent : Lorg/nlogo/agent/Agent;
          INSTANCEOF org/nlogo/agent/Observer
          IFNE L2
          ALOAD 2
          ALOAD 0
          GETFIELD org/nlogo/prim/_asm_procedurebenchmark_ask_1.world : Lorg/nlogo/agent/World;
          INVOKEVIRTUAL org/nlogo/agent/World.turtles ()Lorg/nlogo/agent/AgentSet;
          IF_ACMPNE L3
          NEW org/nlogo/nvm/EngineException
          DUP
          ALOAD 1
          ALOAD 0
          INVOKESTATIC org/nlogo/core/I18N.errorsJ ()Lorg/nlogo/core/I18NJava;
          LDC "org.nlogo.prim.$common.onlyObserverCanAskAllTurtles"
          INVOKEINTERFACE org/nlogo/core/I18NJava.get (Ljava/lang/String;)Ljava/lang/String;
          INVOKESPECIAL org/nlogo/nvm/EngineException.<init> (Lorg/nlogo/nvm/Context;Lorg/nlogo/nvm/Instruction;Ljava/lang/String;)V
          ATHROW
         L3
         FRAME APPEND [org/nlogo/agent/AgentSet]
          ALOAD 2
          ALOAD 0
          GETFIELD org/nlogo/prim/_asm_procedurebenchmark_ask_1.world : Lorg/nlogo/agent/World;
          INVOKEVIRTUAL org/nlogo/agent/World.patches ()Lorg/nlogo/agent/AgentSet;
          IF_ACMPNE L2
          NEW org/nlogo/nvm/EngineException
          DUP
          ALOAD 1
          ALOAD 0
          INVOKESTATIC org/nlogo/core/I18N.errorsJ ()Lorg/nlogo/core/I18NJava;
          LDC "org.nlogo.prim.$common.onlyObserverCanAskAllPatches"
          INVOKEINTERFACE org/nlogo/core/I18NJava.get (Ljava/lang/String;)Ljava/lang/String;
          INVOKESPECIAL org/nlogo/nvm/EngineException.<init> (Lorg/nlogo/nvm/Context;Lorg/nlogo/nvm/Instruction;Ljava/lang/String;)V
          ATHROW
         L2
         FRAME SAME
          ALOAD 1
          ALOAD 2
          ICONST_2
          INVOKEVIRTUAL org/nlogo/nvm/Context.runExclusiveJob (Lorg/nlogo/agent/AgentSet;I)V
          ALOAD 1
          BIPUSH 6
          PUTFIELD org/nlogo/nvm/Context.ip : I
         L4
          RETURN
[2]_asm_procedurebenchmark_setpatchvariable_2 "set p1 random 100" Object => void
      _randomconst:100 "random 100" => double
          TRYCATCHBLOCK L0 L1 L2 org/nlogo/api/AgentException
         L3
          ALOAD 1
          GETFIELD org/nlogo/nvm/Context.job : Lorg/nlogo/nvm/Job;
          GETFIELD org/nlogo/nvm/Job.random : Lorg/nlogo/api/MersenneTwisterFast;
          LDC 100
          INVOKEVIRTUAL org/nlogo/api/MersenneTwisterFast.nextLong (J)J
          L2D
         L4
          DSTORE 2
          NEW java/lang/Double
          DUP
          DLOAD 2
          INVOKESPECIAL java/lang/Double.<init> (D)V
          ASTORE 2
         L0
          ALOAD 1
          GETFIELD org/nlogo/nvm/Context.agent : Lorg/nlogo/agent/Agent;
          ICONST_5
          ALOAD 2
          INVOKEVIRTUAL org/nlogo/agent/Agent.setPatchVariable (ILjava/lang/Object;)V
         L1
          GOTO L5
         L2
         FRAME FULL [org/nlogo/prim/_asm_procedurebenchmark_setpatchvariable_2 org/nlogo/nvm/Context java/lang/Double] [org/nlogo/api/AgentException]
          ASTORE 3
          NEW org/nlogo/nvm/EngineException
          DUP
          ALOAD 1
          ALOAD 0
          ALOAD 3
          INVOKEVIRTUAL org/nlogo/api/AgentException.getMessage ()Ljava/lang/String;
          INVOKESPECIAL org/nlogo/nvm/EngineException.<init> (Lorg/nlogo/nvm/Context;Lorg/nlogo/nvm/Instruction;Ljava/lang/String;)V
          ATHROW
         L5
         FRAME SAME
          ALOAD 1
          ICONST_3
          PUTFIELD org/nlogo/nvm/Context.ip : I
         L6
          RETURN
[3]_asm_procedurebenchmark_setpatchvariable_3 "set p2 random 100" Object => void
      _randomconst:100 "random 100" => double
          TRYCATCHBLOCK L0 L1 L2 org/nlogo/api/AgentException
         L3
          ALOAD 1
          GETFIELD org/nlogo/nvm/Context.job : Lorg/nlogo/nvm/Job;
          GETFIELD org/nlogo/nvm/Job.random : Lorg/nlogo/api/MersenneTwisterFast;
          LDC 100
          INVOKEVIRTUAL org/nlogo/api/MersenneTwisterFast.nextLong (J)J
          L2D
         L4
          DSTORE 2
          NEW java/lang/Double
          DUP
          DLOAD 2
          INVOKESPECIAL java/lang/Double.<init> (D)V
          ASTORE 2
         L0
          ALOAD 1
          GETFIELD org/nlogo/nvm/Context.agent : Lorg/nlogo/agent/Agent;
          BIPUSH 6
          ALOAD 2
          INVOKEVIRTUAL org/nlogo/agent/Agent.setPatchVariable (ILjava/lang/Object;)V
         L1
          GOTO L5
         L2
         FRAME FULL [org/nlogo/prim/_asm_procedurebenchmark_setpatchvariable_3 org/nlogo/nvm/Context java/lang/Double] [org/nlogo/api/AgentException]
          ASTORE 3
          NEW org/nlogo/nvm/EngineException
          DUP
          ALOAD 1
          ALOAD 0
          ALOAD 3
          INVOKEVIRTUAL org/nlogo/api/AgentException.getMessage ()Ljava/lang/String;
          INVOKESPECIAL org/nlogo/nvm/EngineException.<init> (Lorg/nlogo/nvm/Context;Lorg/nlogo/nvm/Instruction;Ljava/lang/String;)V
          ATHROW
         L5
         FRAME SAME
          ALOAD 1
          ICONST_4
          PUTFIELD org/nlogo/nvm/Context.ip : I
         L6
          RETURN
[4]_asm_procedurebenchmark_setpatchvariable_4 "set pcolor one-of base-colors" Object => void
      _oneof "one-of base-colors" LogoList => Object
        _basecolors "base-colors" => LogoList
          TRYCATCHBLOCK L0 L1 L2 org/nlogo/api/AgentException
         L3
          GETSTATIC org/nlogo/prim/_asm_procedurebenchmark_setpatchvariable_4.kept3_colors : Lorg/nlogo/core/LogoList;
         L4
          ASTORE 2
          ALOAD 2
          INVOKEVIRTUAL org/nlogo/core/LogoList.size ()I
          ISTORE 3
          ILOAD 3
          IFNE L5
          NEW org/nlogo/nvm/EngineException
          DUP
          ALOAD 1
          ALOAD 0
          INVOKESTATIC org/nlogo/core/I18N.errorsJ ()Lorg/nlogo/core/I18NJava;
          LDC "org.nlogo.prim.etc.$common.emptyListInput"
          ICONST_1
          ANEWARRAY java/lang/Object
          DUP
          ICONST_0
          LDC "ONE-OF"
          AASTORE
          INVOKEINTERFACE org/nlogo/core/I18NJava.getN (Ljava/lang/String;[Ljava/lang/Object;)Ljava/lang/String;
          INVOKESPECIAL org/nlogo/nvm/EngineException.<init> (Lorg/nlogo/nvm/Context;Lorg/nlogo/nvm/Instruction;Ljava/lang/String;)V
          ATHROW
         L5
         FRAME APPEND [org/nlogo/core/LogoList I]
          ALOAD 2
          ALOAD 1
          GETFIELD org/nlogo/nvm/Context.job : Lorg/nlogo/nvm/Job;
          GETFIELD org/nlogo/nvm/Job.random : Lorg/nlogo/api/MersenneTwisterFast;
          ILOAD 3
          INVOKEVIRTUAL org/nlogo/api/MersenneTwisterFast.nextInt (I)I
          INVOKEVIRTUAL org/nlogo/core/LogoList.get (I)Ljava/lang/Object;
         L6
          ASTORE 2
         L0
          ALOAD 1
          GETFIELD org/nlogo/nvm/Context.agent : Lorg/nlogo/agent/Agent;
          ICONST_2
          ALOAD 2
          INVOKEVIRTUAL org/nlogo/agent/Agent.setPatchVariable (ILjava/lang/Object;)V
         L1
          GOTO L7
         L2
         FRAME FULL [org/nlogo/prim/_asm_procedurebenchmark_setpatchvariable_4 org/nlogo/nvm/Context java/lang/Object I] [org/nlogo/api/AgentException]
          ASTORE 3
          NEW org/nlogo/nvm/EngineException
          DUP
          ALOAD 1
          ALOAD 0
          ALOAD 3
          INVOKEVIRTUAL org/nlogo/api/AgentException.getMessage ()Ljava/lang/String;
          INVOKESPECIAL org/nlogo/nvm/EngineException.<init> (Lorg/nlogo/nvm/Context;Lorg/nlogo/nvm/Instruction;Ljava/lang/String;)V
          ATHROW
         L7
         FRAME SAME
          ALOAD 1
          ICONST_5
          PUTFIELD org/nlogo/nvm/Context.ip : I
         L8
          RETURN
[5]_asm_procedurebenchmark_done_5 => void
         L0
          ALOAD 1
          ICONST_1
          PUTFIELD org/nlogo/nvm/Context.finished : Z
         L1
          RETURN
[6]_asm_procedurebenchmark_setprocedurevariable_6 "let """ Object => void
      _conststring:"" """" => String
         L0
          LDC ""
         L1
          ASTORE 2
          ALOAD 1
          GETFIELD org/nlogo/nvm/Context.activation : Lorg/nlogo/nvm/Activation;
          GETFIELD org/nlogo/nvm/Activation.args : [Ljava/lang/Object;
          ICONST_0
          ALOAD 2
          AASTORE
          ALOAD 1
          BIPUSH 7
          PUTFIELD org/nlogo/nvm/Context.ip : I
         L2
          RETURN
[7]_asm_procedurebenchmark_withlocalrandomness_7 "with-local-randomness random-seed new-seed let random 10000000 [ set name (word "firebig-" salt ".csv") ]" => void
         L0
          NEW org/nlogo/agent/ArrayAgentSet
          DUP
          ALOAD 1
          GETFIELD org/nlogo/nvm/Context.agent : Lorg/nlogo/agent/Agent;
          INVOKEVIRTUAL org/nlogo/agent/Agent.kind ()Lorg/nlogo/core/AgentKind;
          ICONST_1
          ICONST_0
          INVOKESPECIAL org/nlogo/agent/ArrayAgentSet.<init> (Lorg/nlogo/core/AgentKind;IZ)V
          ASTORE 2
          ALOAD 2
          ALOAD 1
          GETFIELD org/nlogo/nvm/Context.agent : Lorg/nlogo/agent/Agent;
          INVOKEVIRTUAL org/nlogo/agent/AgentSet.add (Lorg/nlogo/agent/Agent;)V
          ALOAD 1
          GETFIELD org/nlogo/nvm/Context.job : Lorg/nlogo/nvm/Job;
          GETFIELD org/nlogo/nvm/Job.random : Lorg/nlogo/api/MersenneTwisterFast;
          ASTORE 3
          ALOAD 1
          GETFIELD org/nlogo/nvm/Context.job : Lorg/nlogo/nvm/Job;
          ALOAD 0
          GETFIELD org/nlogo/prim/_asm_procedurebenchmark_withlocalrandomness_7.world : Lorg/nlogo/agent/World;
          INVOKEVIRTUAL org/nlogo/agent/World.mainRNG ()Lorg/nlogo/api/MersenneTwisterFast;
          INVOKEVIRTUAL org/nlogo/api/MersenneTwisterFast.clone ()Lorg/nlogo/api/MersenneTwisterFast;
          PUTFIELD org/nlogo/nvm/Job.random : Lorg/nlogo/api/MersenneTwisterFast;
          ALOAD 1
          ALOAD 2
          BIPUSH 8
          INVOKEVIRTUAL org/nlogo/nvm/Context.runExclusiveJob (Lorg/nlogo/agent/AgentSet;I)V
          ALOAD 1
          GETFIELD org/nlogo/nvm/Context.job : Lorg/nlogo/nvm/Job;
          ALOAD 3
          PUTFIELD org/nlogo/nvm/Job.random : Lorg/nlogo/api/MersenneTwisterFast;
          ALOAD 1
          BIPUSH 12
          PUTFIELD org/nlogo/nvm/Context.ip : I
         L1
          RETURN
[8]_asm_procedurebenchmark_randomseed_8 "random-seed new-seed" double => void
      _newseed "new-seed" => double
         L0
          ALOAD 0
          GETFIELD org/nlogo/prim/_asm_procedurebenchmark_randomseed_8.world : Lorg/nlogo/agent/World;
          INVOKEVIRTUAL org/nlogo/agent/World.generateSeed ()D
         L1
          DSTORE 2
          DLOAD 2
          D2L
          LSTORE 4
          LLOAD 4
          LDC -2147483648
          LCMP
          IFLT L2
          LLOAD 4
          LDC 2147483647
          LCMP
          IFLE L3
         L2
         FRAME APPEND [D J]
          NEW org/nlogo/nvm/EngineException
          DUP
          ALOAD 1
          ALOAD 0
          NEW scala/collection/mutable/StringBuilder
          DUP
          INVOKESPECIAL scala/collection/mutable/StringBuilder.<init> ()V
          GETSTATIC org/nlogo/api/Dump$.MODULE$ : Lorg/nlogo/api/Dump$;
          DLOAD 2
          INVOKEVIRTUAL org/nlogo/api/Dump$.number (D)Ljava/lang/String;
          INVOKEVIRTUAL scala/collection/mutable/StringBuilder.append (Ljava/lang/Object;)Lscala/collection/mutable/StringBuilder;
          LDC " is not in the allowable range for random seeds (-2147483648 to 2147483647)"
          INVOKEVIRTUAL scala/collection/mutable/StringBuilder.append (Ljava/lang/Object;)Lscala/collection/mutable/StringBuilder;
          INVOKEVIRTUAL scala/collection/mutable/StringBuilder.toString ()Ljava/lang/String;
          INVOKESPECIAL org/nlogo/nvm/EngineException.<init> (Lorg/nlogo/nvm/Context;Lorg/nlogo/nvm/Instruction;Ljava/lang/String;)V
          ATHROW
         L3
         FRAME SAME
          ALOAD 1
          GETFIELD org/nlogo/nvm/Context.job : Lorg/nlogo/nvm/Job;
          GETFIELD org/nlogo/nvm/Job.random : Lorg/nlogo/api/MersenneTwisterFast;
          LLOAD 4
          L2I
          I2L
          INVOKEVIRTUAL org/nlogo/api/MersenneTwisterFast.setSeed (J)V
          ALOAD 1
          BIPUSH 9
          PUTFIELD org/nlogo/nvm/Context.ip : I
         L4
          RETURN
[9]_asm_procedurebenchmark_setprocedurevariable_9 "let random 10000000" Object => void
      _randomconst:10000000 "random 10000000" => double
         L0
          ALOAD 1
          GETFIELD org/nlogo/nvm/Context.job : Lorg/nlogo/nvm/Job;
          GETFIELD org/nlogo/nvm/Job.random : Lorg/nlogo/api/MersenneTwisterFast;
          LDC 10000000
          INVOKEVIRTUAL org/nlogo/api/MersenneTwisterFast.nextLong (J)J
          L2D
         L1
          DSTORE 2
          NEW java/lang/Double
          DUP
          DLOAD 2
          INVOKESPECIAL java/lang/Double.<init> (D)V
          ASTORE 2
          ALOAD 1
          GETFIELD org/nlogo/nvm/Context.activation : Lorg/nlogo/nvm/Activation;
          GETFIELD org/nlogo/nvm/Activation.args : [Ljava/lang/Object;
          ICONST_1
          ALOAD 2
          AASTORE
          ALOAD 1
          BIPUSH 10
          PUTFIELD org/nlogo/nvm/Context.ip : I
         L2
          RETURN
[10]_asm_procedurebenchmark_setprocedurevariable_10 "set name (word "firebig-" salt ".csv")" Object => void
      _word "(word "firebig-" salt ".csv")"
        _conststring:"firebig-" ""firebig-"" => String
        _procedurevariable:SALT "salt" => Object
        _conststring:".csv" "".csv"" => String
         L0
          NEW java/lang/StringBuilder
          DUP
          INVOKESPECIAL java/lang/StringBuilder.<init> ()V
         L1
          LDC "firebig-"
         L2
          INVOKESTATIC org/nlogo/api/Dump.logoObject (Ljava/lang/Object;)Ljava/lang/String;
          INVOKEVIRTUAL java/lang/StringBuilder.append (Ljava/lang/String;)Ljava/lang/StringBuilder;
         L3
          ALOAD 1
          GETFIELD org/nlogo/nvm/Context.activation : Lorg/nlogo/nvm/Activation;
          GETFIELD org/nlogo/nvm/Activation.args : [Ljava/lang/Object;
          ICONST_1
          AALOAD
         L4
          INVOKESTATIC org/nlogo/api/Dump.logoObject (Ljava/lang/Object;)Ljava/lang/String;
          INVOKEVIRTUAL java/lang/StringBuilder.append (Ljava/lang/String;)Ljava/lang/StringBuilder;
         L5
          LDC ".csv"
         L6
          INVOKESTATIC org/nlogo/api/Dump.logoObject (Ljava/lang/Object;)Ljava/lang/String;
          INVOKEVIRTUAL java/lang/StringBuilder.append (Ljava/lang/String;)Ljava/lang/StringBuilder;
          INVOKEVIRTUAL java/lang/StringBuilder.toString ()Ljava/lang/String;
         L7
          ASTORE 2
          ALOAD 1
          GETFIELD org/nlogo/nvm/Context.activation : Lorg/nlogo/nvm/Activation;
          GETFIELD org/nlogo/nvm/Activation.args : [Ljava/lang/Object;
          ICONST_0
          ALOAD 2
          AASTORE
          ALOAD 1
          BIPUSH 11
          PUTFIELD org/nlogo/nvm/Context.ip : I
         L8
          RETURN
[11]_asm_procedurebenchmark_done_11 => void
         L0
          ALOAD 1
          ICONST_1
          PUTFIELD org/nlogo/nvm/Context.finished : Z
         L1
          RETURN
[12]_exportworld "export-world name"
      _asm_procedurebenchmark_procedurevariable_12 "name" => Object
           L0
            ALOAD 1
            GETFIELD org/nlogo/nvm/Context.activation : Lorg/nlogo/nvm/Activation;
            GETFIELD org/nlogo/nvm/Activation.args : [Ljava/lang/Object;
            ICONST_0
            AALOAD
           L1
            ARETURN
[13]_resettimer "reset-timer"
[14]_importworld "import-world name"
      _asm_procedurebenchmark_procedurevariable_13 "name" => Object
           L0
            ALOAD 1
            GETFIELD org/nlogo/nvm/Context.activation : Lorg/nlogo/nvm/Activation;
            GETFIELD org/nlogo/nvm/Activation.args : [Ljava/lang/Object;
            ICONST_0
            AALOAD
           L1
            ARETURN
[15]_asm_procedurebenchmark_setobservervariable_14 "set result timer" Object => void
      _timer "timer" => double
          TRYCATCHBLOCK L0 L1 L2 org/nlogo/api/AgentException
         L3
          ALOAD 0
          GETFIELD org/nlogo/prim/_asm_procedurebenchmark_setobservervariable_14.world : Lorg/nlogo/agent/World;
          INVOKEVIRTUAL org/nlogo/agent/World.timer ()Lorg/nlogo/api/Timer;
          INVOKEVIRTUAL org/nlogo/api/Timer.read ()D
         L4
          DSTORE 2
          NEW java/lang/Double
          DUP
          DLOAD 2
          INVOKESPECIAL java/lang/Double.<init> (D)V
          ASTORE 2
         L0
          ALOAD 1
          GETFIELD org/nlogo/nvm/Context.agent : Lorg/nlogo/agent/Agent;
          ICONST_1
          ALOAD 2
          INVOKEVIRTUAL org/nlogo/agent/Agent.setObserverVariable (ILjava/lang/Object;)V
         L1
          GOTO L5
         L2
         FRAME FULL [org/nlogo/prim/_asm_procedurebenchmark_setobservervariable_14 org/nlogo/nvm/Context java/lang/Double] [org/nlogo/api/AgentException]
          ASTORE 3
          NEW org/nlogo/nvm/EngineException
          DUP
          ALOAD 1
          ALOAD 0
          ALOAD 3
          INVOKEVIRTUAL org/nlogo/api/AgentException.getMessage ()Ljava/lang/String;
          INVOKESPECIAL org/nlogo/nvm/EngineException.<init> (Lorg/nlogo/nvm/Context;Lorg/nlogo/nvm/Instruction;Ljava/lang/String;)V
          ATHROW
         L5
         FRAME SAME
          ALOAD 1
          BIPUSH 16
          PUTFIELD org/nlogo/nvm/Context.ip : I
         L6
          RETURN
[16]_asm_procedurebenchmark_return_15 => void
         L0
          ALOAD 1
          INVOKEVIRTUAL org/nlogo/nvm/Context.returnFromProcedure ()V
          ALOAD 1
          ICONST_0
          PUTFIELD org/nlogo/nvm/Context.stopping : Z
         L1
          RETURN

