globals [RESULT]
interfaceGlobals []
turtles-own [WHO COLOR HEADING XCOR YCOR SHAPE LABEL LABEL-COLOR BREED HIDDEN? SIZE PEN-SIZE PEN-MODE]
patches-own [PXCOR PYCOR PCOLOR PLABEL PLABEL-COLOR]
links-own [END1 END2 COLOR LABEL LABEL-COLOR HIDDEN? BREED THICKNESS SHAPE TIE-MODE]
breeds 
link-breeds 

procedure BENCHMARK:[_repeatlocal:0]{O---}:
[0]_asm_procedurebenchmark_randomseed_0 "random-seed 121862" double => void
      _constdouble:121862.0 => double
         L0
          LDC 121862.0
         L1
          DSTORE 2
          DLOAD 2
          D2L
          LSTORE 4
          LLOAD 4
          LDC -2147483648
          LCMP
          IFLT L2
          LLOAD 4
          LDC 2147483647
          LCMP
          IFLE L3
         L2
          NEW org/nlogo/nvm/EngineException
          DUP
          ALOAD 1
          ALOAD 0
          NEW scala/collection/mutable/StringBuilder
          DUP
          INVOKESPECIAL scala/collection/mutable/StringBuilder.<init> ()V
          GETSTATIC org/nlogo/api/Dump$.MODULE$ : Lorg/nlogo/api/Dump$;
          DLOAD 2
          INVOKEVIRTUAL org/nlogo/api/Dump$.number (D)Ljava/lang/String;
          INVOKEVIRTUAL scala/collection/mutable/StringBuilder.append (Ljava/lang/Object;)Lscala/collection/mutable/StringBuilder;
          LDC " is not in the allowable range for random seeds (-2147483648 to 2147483647)"
          INVOKEVIRTUAL scala/collection/mutable/StringBuilder.append (Ljava/lang/Object;)Lscala/collection/mutable/StringBuilder;
          INVOKEVIRTUAL scala/collection/mutable/StringBuilder.toString ()Ljava/lang/String;
          INVOKESPECIAL org/nlogo/nvm/EngineException.<init> (Lorg/nlogo/nvm/Context;Lorg/nlogo/nvm/Instruction;Ljava/lang/String;)V
          ATHROW
         L3
          ALOAD 1
          GETFIELD org/nlogo/nvm/Context.job : Lorg/nlogo/nvm/Job;
          GETFIELD org/nlogo/nvm/Job.random : Lorg/nlogo/util/MersenneTwisterFast;
          LLOAD 4
          L2I
          I2L
          INVOKEVIRTUAL org/nlogo/util/MersenneTwisterFast.setSeed (J)V
          ALOAD 1
          ICONST_1
          PUTFIELD org/nlogo/nvm/Context.ip : I
         L4
          RETURN
[1]_resettimer
[2]_asm_procedurebenchmark_call_1 "setup"
         L0
          NEW org/nlogo/nvm/Activation
          DUP
          ALOAD 0
          GETFIELD org/nlogo/prim/_asm_procedurebenchmark_call_1.kept1_procedure : Lorg/nlogo/nvm/Procedure;
          ALOAD 1
          GETFIELD org/nlogo/nvm/Context.activation : Lorg/nlogo/nvm/Activation;
          ICONST_3
          INVOKESPECIAL org/nlogo/nvm/Activation.<init> (Lorg/nlogo/nvm/Procedure;Lorg/nlogo/nvm/Activation;I)V
          ALOAD 1
          SWAP
          PUTFIELD org/nlogo/nvm/Context.activation : Lorg/nlogo/nvm/Activation;
          ALOAD 1
          ICONST_0
          PUTFIELD org/nlogo/nvm/Context.ip : I
         L1
          RETURN
[3]_asm_procedurebenchmark_repeatlocal_2 "" double => void
      _constdouble:3000.0 => double
         L0
          LDC 3000.0
         L1
          DSTORE 2
          ALOAD 1
          GETFIELD org/nlogo/nvm/Context.activation : Lorg/nlogo/nvm/Activation;
          INVOKEVIRTUAL org/nlogo/nvm/Activation.args ()[Ljava/lang/Object;
          ICONST_0
          NEW org/nlogo/nvm/MutableLong
          DUP
          ALOAD 0
          DLOAD 2
          INVOKEVIRTUAL org/nlogo/nvm/Instruction.validLong (D)J
          INVOKESPECIAL org/nlogo/nvm/MutableLong.<init> (J)V
          AASTORE
          ALOAD 1
          ICONST_5
          PUTFIELD org/nlogo/nvm/Context.ip : I
         L2
          RETURN
[4]_asm_procedurebenchmark_call_3 "go"
         L0
          NEW org/nlogo/nvm/Activation
          DUP
          ALOAD 0
          GETFIELD org/nlogo/prim/_asm_procedurebenchmark_call_3.kept1_procedure : Lorg/nlogo/nvm/Procedure;
          ALOAD 1
          GETFIELD org/nlogo/nvm/Context.activation : Lorg/nlogo/nvm/Activation;
          ICONST_5
          INVOKESPECIAL org/nlogo/nvm/Activation.<init> (Lorg/nlogo/nvm/Procedure;Lorg/nlogo/nvm/Activation;I)V
          ALOAD 1
          SWAP
          PUTFIELD org/nlogo/nvm/Context.activation : Lorg/nlogo/nvm/Activation;
          ALOAD 1
          ICONST_0
          PUTFIELD org/nlogo/nvm/Context.ip : I
         L1
          RETURN
[5]_asm_procedurebenchmark_repeatlocalinternal_4 "" => void
         L0
          ALOAD 1
          GETFIELD org/nlogo/nvm/Context.activation : Lorg/nlogo/nvm/Activation;
          INVOKEVIRTUAL org/nlogo/nvm/Activation.args ()[Ljava/lang/Object;
          ICONST_0
          AALOAD
          CHECKCAST org/nlogo/nvm/MutableLong
          ASTORE 2
          ALOAD 2
          INVOKEVIRTUAL org/nlogo/nvm/MutableLong.value ()J
          LCONST_0
          LCMP
          IFGT L1
          ALOAD 1
          BIPUSH 6
          PUTFIELD org/nlogo/nvm/Context.ip : I
          GOTO L2
         L1
          ALOAD 2
          ALOAD 2
          INVOKEVIRTUAL org/nlogo/nvm/MutableLong.value ()J
          LCONST_1
          LSUB
          INVOKEVIRTUAL org/nlogo/nvm/MutableLong.value_$eq (J)V
          ALOAD 1
          ICONST_4
          PUTFIELD org/nlogo/nvm/Context.ip : I
         L2
          RETURN
[6]_asm_procedurebenchmark_setobservervariable_5 "set result timer" Object => void
      _timer => double
          TRYCATCHBLOCK L0 L1 L2 org/nlogo/api/AgentException
         L3
          ALOAD 0
          GETFIELD org/nlogo/prim/_asm_procedurebenchmark_setobservervariable_5.world : Lorg/nlogo/agent/World;
          INVOKEVIRTUAL org/nlogo/agent/World.timer ()Lorg/nlogo/api/Timer;
          INVOKEVIRTUAL org/nlogo/api/Timer.read ()D
         L4
          DSTORE 2
          NEW java/lang/Double
          DUP
          DLOAD 2
          INVOKESPECIAL java/lang/Double.<init> (D)V
          ASTORE 2
         L0
          ALOAD 0
          GETFIELD org/nlogo/prim/_asm_procedurebenchmark_setobservervariable_5.world : Lorg/nlogo/agent/World;
          INVOKEVIRTUAL org/nlogo/agent/World.observer ()Lorg/nlogo/agent/Observer;
          ICONST_0
          ALOAD 2
          INVOKEVIRTUAL org/nlogo/agent/Observer.setVariable (ILjava/lang/Object;)V
         L1
          ALOAD 1
          BIPUSH 7
          PUTFIELD org/nlogo/nvm/Context.ip : I
          GOTO L5
         L2
          ASTORE 3
          NEW org/nlogo/nvm/EngineException
          DUP
          ALOAD 1
          ALOAD 0
          ALOAD 3
          INVOKEVIRTUAL java/lang/Throwable.getMessage ()Ljava/lang/String;
          INVOKESPECIAL org/nlogo/nvm/EngineException.<init> (Lorg/nlogo/nvm/Context;Lorg/nlogo/nvm/Instruction;Ljava/lang/String;)V
          ATHROW
         L5
          RETURN
[7]_asm_procedurebenchmark_return_6 "" => void
         L0
          ALOAD 1
          INVOKEVIRTUAL org/nlogo/nvm/Context.returnFromProcedure ()V
          ALOAD 1
          ICONST_0
          PUTFIELD org/nlogo/nvm/Context.stopping : Z
         L1
          RETURN

procedure SETUP:[]{O---}:
[0]_clearall
[1]_resetticks
[2]_setdefaultshape
      _asm_proceduresetup_turtles_0 "turtles" => AgentSet
           L0
            ALOAD 0
            GETFIELD org/nlogo/prim/_asm_proceduresetup_turtles_0.world : Lorg/nlogo/agent/World;
            INVOKEVIRTUAL org/nlogo/agent/World.turtles ()Lorg/nlogo/agent/AgentSet;
           L1
            ARETURN
      _asm_proceduresetup_conststring_1 ""circle"" => String
           L0
            LDC "circle"
           L1
            ARETURN
[3]_asm_proceduresetup_call_2 "make-node nobody"
      _nobody => Nobody$
         L0
          NEW org/nlogo/nvm/Activation
          DUP
          ALOAD 0
          GETFIELD org/nlogo/prim/_asm_proceduresetup_call_2.kept1_procedure : Lorg/nlogo/nvm/Procedure;
          ALOAD 1
          GETFIELD org/nlogo/nvm/Context.activation : Lorg/nlogo/nvm/Activation;
          ICONST_4
          INVOKESPECIAL org/nlogo/nvm/Activation.<init> (Lorg/nlogo/nvm/Procedure;Lorg/nlogo/nvm/Activation;I)V
          DUP
          INVOKEVIRTUAL org/nlogo/nvm/Activation.args ()[Ljava/lang/Object;
          ICONST_0
         L1
          GETSTATIC org/nlogo/api/Nobody$.MODULE$ : Lorg/nlogo/api/Nobody$;
         L2
          AASTORE
          ALOAD 1
          SWAP
          PUTFIELD org/nlogo/nvm/Context.activation : Lorg/nlogo/nvm/Activation;
          ALOAD 1
          ICONST_0
          PUTFIELD org/nlogo/nvm/Context.ip : I
         L3
          RETURN
[4]_asm_proceduresetup_call_3 "make-node turtle 0"
      _turtle double => Object
        _constdouble:0.0 => double
         L0
          NEW org/nlogo/nvm/Activation
          DUP
          ALOAD 0
          GETFIELD org/nlogo/prim/_asm_proceduresetup_call_3.kept1_procedure : Lorg/nlogo/nvm/Procedure;
          ALOAD 1
          GETFIELD org/nlogo/nvm/Context.activation : Lorg/nlogo/nvm/Activation;
          ICONST_5
          INVOKESPECIAL org/nlogo/nvm/Activation.<init> (Lorg/nlogo/nvm/Procedure;Lorg/nlogo/nvm/Activation;I)V
          DUP
          INVOKEVIRTUAL org/nlogo/nvm/Activation.args ()[Ljava/lang/Object;
          ICONST_0
         L1
          DCONST_0
         L2
          DSTORE 2
          ALOAD 0
          DLOAD 2
          INVOKEVIRTUAL org/nlogo/nvm/Instruction.validLong (D)J
          LSTORE 4
          LLOAD 4
          L2D
          DLOAD 2
          DCMPL
          IFEQ L3
          NEW org/nlogo/nvm/EngineException
          DUP
          ALOAD 1
          ALOAD 0
          NEW scala/collection/mutable/StringBuilder
          DUP
          INVOKESPECIAL scala/collection/mutable/StringBuilder.<init> ()V
          DLOAD 2
          INVOKEVIRTUAL scala/collection/mutable/StringBuilder.append (D)Lscala/collection/mutable/StringBuilder;
          LDC " is not an integer"
          INVOKEVIRTUAL scala/collection/mutable/StringBuilder.append (Ljava/lang/Object;)Lscala/collection/mutable/StringBuilder;
          INVOKEVIRTUAL scala/collection/mutable/StringBuilder.toString ()Ljava/lang/String;
          INVOKESPECIAL org/nlogo/nvm/EngineException.<init> (Lorg/nlogo/nvm/Context;Lorg/nlogo/nvm/Instruction;Ljava/lang/String;)V
          ATHROW
         L3
          ALOAD 0
          GETFIELD org/nlogo/prim/_asm_proceduresetup_call_3.world : Lorg/nlogo/agent/World;
          LLOAD 4
          INVOKEVIRTUAL org/nlogo/agent/World.getTurtle (J)Lorg/nlogo/agent/Turtle;
          ASTORE 6
          ALOAD 6
          IFNONNULL L4
          GETSTATIC org/nlogo/api/Nobody$.MODULE$ : Lorg/nlogo/api/Nobody$;
          GOTO L5
         L4
          ALOAD 6
         L5
          AASTORE
          ALOAD 1
          SWAP
          PUTFIELD org/nlogo/nvm/Context.activation : Lorg/nlogo/nvm/Activation;
          ALOAD 1
          ICONST_0
          PUTFIELD org/nlogo/nvm/Context.ip : I
         L6
          RETURN
[5]_asm_proceduresetup_return_4 "" => void
         L0
          ALOAD 1
          INVOKEVIRTUAL org/nlogo/nvm/Context.returnFromProcedure ()V
          ALOAD 1
          ICONST_0
          PUTFIELD org/nlogo/nvm/Context.stopping : Z
         L1
          RETURN

procedure GO:[]{O---}:
[0]_asm_procedurego_ask_0 "ask links" AgentSet => void
      _links => AgentSet
         L0
          ALOAD 0
          GETFIELD org/nlogo/prim/_asm_procedurego_ask_0.world : Lorg/nlogo/agent/World;
          INVOKEVIRTUAL org/nlogo/agent/World.links ()Lorg/nlogo/agent/AgentSet;
         L1
          ASTORE 2
          ALOAD 1
          GETFIELD org/nlogo/nvm/Context.agent : Lorg/nlogo/agent/Agent;
          INSTANCEOF org/nlogo/agent/Observer
          IFNE L2
          ALOAD 2
          ALOAD 0
          GETFIELD org/nlogo/prim/_asm_procedurego_ask_0.world : Lorg/nlogo/agent/World;
          INVOKEVIRTUAL org/nlogo/agent/World.turtles ()Lorg/nlogo/agent/AgentSet;
          IF_ACMPNE L3
          NEW org/nlogo/nvm/EngineException
          DUP
          ALOAD 1
          ALOAD 0
          GETSTATIC org/nlogo/api/I18N$.MODULE$ : Lorg/nlogo/api/I18N$;
          INVOKEVIRTUAL org/nlogo/api/I18N$.errors ()Lorg/nlogo/api/I18N$BundleKind;
          LDC "org.nlogo.prim.$common.onlyObserverCanAskAllTurtles"
          INVOKEVIRTUAL org/nlogo/api/I18N$BundleKind.get (Ljava/lang/String;)Ljava/lang/String;
          INVOKESPECIAL org/nlogo/nvm/EngineException.<init> (Lorg/nlogo/nvm/Context;Lorg/nlogo/nvm/Instruction;Ljava/lang/String;)V
          ATHROW
         L3
          ALOAD 2
          ALOAD 0
          GETFIELD org/nlogo/prim/_asm_procedurego_ask_0.world : Lorg/nlogo/agent/World;
          INVOKEVIRTUAL org/nlogo/agent/World.patches ()Lorg/nlogo/agent/AgentSet;
          IF_ACMPNE L2
          NEW org/nlogo/nvm/EngineException
          DUP
          ALOAD 1
          ALOAD 0
          GETSTATIC org/nlogo/api/I18N$.MODULE$ : Lorg/nlogo/api/I18N$;
          INVOKEVIRTUAL org/nlogo/api/I18N$.errors ()Lorg/nlogo/api/I18N$BundleKind;
          LDC "org.nlogo.prim.$common.onlyObserverCanAskAllPatches"
          INVOKEVIRTUAL org/nlogo/api/I18N$BundleKind.get (Ljava/lang/String;)Ljava/lang/String;
          INVOKESPECIAL org/nlogo/nvm/EngineException.<init> (Lorg/nlogo/nvm/Context;Lorg/nlogo/nvm/Instruction;Ljava/lang/String;)V
          ATHROW
         L2
          ALOAD 1
          ALOAD 2
          ICONST_1
          INVOKEVIRTUAL org/nlogo/nvm/Context.runExclusiveJob (Lorg/nlogo/agent/AgentSet;I)V
          ALOAD 1
          ICONST_3
          PUTFIELD org/nlogo/nvm/Context.ip : I
         L4
          RETURN
[1]_asm_procedurego_setturtleorlinkvariable_1 "set color gray" Object => void
      _constdouble:5.0 => Double
          TRYCATCHBLOCK L0 L1 L2 org/nlogo/api/AgentException
         L3
          ALOAD 0
          GETFIELD org/nlogo/prim/_asm_procedurego_setturtleorlinkvariable_1.kept2_value : Ljava/lang/Double;
         L4
          ASTORE 2
         L0
          ALOAD 1
          GETFIELD org/nlogo/nvm/Context.agent : Lorg/nlogo/agent/Agent;
          LDC "COLOR"
          ALOAD 2
          INVOKEVIRTUAL org/nlogo/agent/Agent.setTurtleOrLinkVariable (Ljava/lang/String;Ljava/lang/Object;)V
         L1
          ALOAD 1
          ICONST_2
          PUTFIELD org/nlogo/nvm/Context.ip : I
          GOTO L5
         L2
          ASTORE 3
          NEW org/nlogo/nvm/EngineException
          DUP
          ALOAD 1
          ALOAD 0
          ALOAD 3
          INVOKEVIRTUAL java/lang/Throwable.getMessage ()Ljava/lang/String;
          INVOKESPECIAL org/nlogo/nvm/EngineException.<init> (Lorg/nlogo/nvm/Context;Lorg/nlogo/nvm/Instruction;Ljava/lang/String;)V
          ATHROW
         L5
          RETURN
[2]_asm_procedurego_done_2 "" => void
         L0
          ALOAD 1
          ICONST_1
          PUTFIELD org/nlogo/nvm/Context.finished : Z
         L1
          RETURN
[3]_asm_procedurego_call_3 "make-node find-partner"
      _callreport:FIND-PARTNER
         L0
          NEW org/nlogo/nvm/Activation
          DUP
          ALOAD 0
          GETFIELD org/nlogo/prim/_asm_procedurego_call_3.kept1_procedure : Lorg/nlogo/nvm/Procedure;
          ALOAD 1
          GETFIELD org/nlogo/nvm/Context.activation : Lorg/nlogo/nvm/Activation;
          ICONST_4
          INVOKESPECIAL org/nlogo/nvm/Activation.<init> (Lorg/nlogo/nvm/Procedure;Lorg/nlogo/nvm/Activation;I)V
          DUP
          INVOKEVIRTUAL org/nlogo/nvm/Activation.args ()[Ljava/lang/Object;
          ICONST_0
         L1
          NEW org/nlogo/nvm/Activation
          DUP
          ALOAD 0
          GETFIELD org/nlogo/prim/_asm_procedurego_call_3.kept2_procedure : Lorg/nlogo/nvm/Procedure;
          ALOAD 1
          GETFIELD org/nlogo/nvm/Context.activation : Lorg/nlogo/nvm/Activation;
          ICONST_3
          INVOKESPECIAL org/nlogo/nvm/Activation.<init> (Lorg/nlogo/nvm/Procedure;Lorg/nlogo/nvm/Activation;I)V
          ALOAD 1
          SWAP
          INVOKEVIRTUAL org/nlogo/nvm/Context.callReporterProcedure (Lorg/nlogo/nvm/Activation;)Ljava/lang/Object;
          DUP
          IFNONNULL L2
          NEW org/nlogo/nvm/EngineException
          DUP
          ALOAD 1
          ALOAD 0
          LDC "the FIND-PARTNER procedure failed to report a result"
          INVOKESPECIAL org/nlogo/nvm/EngineException.<init> (Lorg/nlogo/nvm/Context;Lorg/nlogo/nvm/Instruction;Ljava/lang/String;)V
          ATHROW
         L2
          AASTORE
          ALOAD 1
          SWAP
          PUTFIELD org/nlogo/nvm/Context.activation : Lorg/nlogo/nvm/Activation;
          ALOAD 1
          ICONST_0
          PUTFIELD org/nlogo/nvm/Context.ip : I
         L3
          RETURN
[4]_tick
[5]_asm_procedurego_return_4 "" => void
         L0
          ALOAD 1
          INVOKEVIRTUAL org/nlogo/nvm/Context.returnFromProcedure ()V
          ALOAD 1
          ICONST_0
          PUTFIELD org/nlogo/nvm/Context.stopping : Z
         L1
          RETURN

procedure MAKE-NODE:[OLD-NODE]{O---}:
[0]_createorderedturtles:,+11
      _asm_proceduremakenode_constdouble_0 "1" => Double
           L0
            ALOAD 0
            GETFIELD org/nlogo/prim/_asm_proceduremakenode_constdouble_0.kept1_value : Ljava/lang/Double;
           L1
            ARETURN
[1]_asm_proceduremakenode_setturtleorlinkvariable_1 "set color red" Object => void
      _constdouble:15.0 => Double
          TRYCATCHBLOCK L0 L1 L2 org/nlogo/api/AgentException
         L3
          ALOAD 0
          GETFIELD org/nlogo/prim/_asm_proceduremakenode_setturtleorlinkvariable_1.kept2_value : Ljava/lang/Double;
         L4
          ASTORE 2
         L0
          ALOAD 1
          GETFIELD org/nlogo/nvm/Context.agent : Lorg/nlogo/agent/Agent;
          LDC "COLOR"
          ALOAD 2
          INVOKEVIRTUAL org/nlogo/agent/Agent.setTurtleOrLinkVariable (Ljava/lang/String;Ljava/lang/Object;)V
         L1
          ALOAD 1
          ICONST_2
          PUTFIELD org/nlogo/nvm/Context.ip : I
          GOTO L5
         L2
          ASTORE 3
          NEW org/nlogo/nvm/EngineException
          DUP
          ALOAD 1
          ALOAD 0
          ALOAD 3
          INVOKEVIRTUAL java/lang/Throwable.getMessage ()Ljava/lang/String;
          INVOKESPECIAL org/nlogo/nvm/EngineException.<init> (Lorg/nlogo/nvm/Context;Lorg/nlogo/nvm/Instruction;Ljava/lang/String;)V
          ATHROW
         L5
          RETURN
[2]_asm_proceduremakenode_if_2 "if old-node != nobody" boolean => void
      _notequal Object,Object => boolean
        _procedurevariable:OLD-NODE => Object
        _nobody => Nobody$
         L0
          ALOAD 1
          GETFIELD org/nlogo/nvm/Context.activation : Lorg/nlogo/nvm/Activation;
          INVOKEVIRTUAL org/nlogo/nvm/Activation.args ()[Ljava/lang/Object;
          ICONST_0
          AALOAD
         L1
          GETSTATIC org/nlogo/api/Nobody$.MODULE$ : Lorg/nlogo/api/Nobody$;
         L2
          ASTORE 3
          ASTORE 2
          GETSTATIC org/nlogo/api/Equality$.MODULE$ : Lorg/nlogo/api/Equality$;
          ALOAD 2
          ALOAD 3
          INVOKEVIRTUAL org/nlogo/api/Equality$.equals (Ljava/lang/Object;Ljava/lang/Object;)Z
          IFEQ L3
          ICONST_0
          GOTO L4
         L3
          ICONST_1
         L4
          ISTORE 2
          ALOAD 1
          ILOAD 2
          IFEQ L5
          ICONST_3
          GOTO L6
         L5
          BIPUSH 10
         L6
          PUTFIELD org/nlogo/nvm/Context.ip : I
         L7
          RETURN
[3]_createlinkwith:,+6
      _asm_proceduremakenode_procedurevariable_3 "old-node" => Object
           L0
            ALOAD 1
            GETFIELD org/nlogo/nvm/Context.activation : Lorg/nlogo/nvm/Activation;
            INVOKEVIRTUAL org/nlogo/nvm/Activation.args ()[Ljava/lang/Object;
            ICONST_0
            AALOAD
           L1
            ARETURN
[4]_asm_proceduremakenode_setturtleorlinkvariable_4 "set color green" Object => void
      _constdouble:55.0 => Double
          TRYCATCHBLOCK L0 L1 L2 org/nlogo/api/AgentException
         L3
          ALOAD 0
          GETFIELD org/nlogo/prim/_asm_proceduremakenode_setturtleorlinkvariable_4.kept2_value : Ljava/lang/Double;
         L4
          ASTORE 2
         L0
          ALOAD 1
          GETFIELD org/nlogo/nvm/Context.agent : Lorg/nlogo/agent/Agent;
          LDC "COLOR"
          ALOAD 2
          INVOKEVIRTUAL org/nlogo/agent/Agent.setTurtleOrLinkVariable (Ljava/lang/String;Ljava/lang/Object;)V
         L1
          ALOAD 1
          ICONST_5
          PUTFIELD org/nlogo/nvm/Context.ip : I
          GOTO L5
         L2
          ASTORE 3
          NEW org/nlogo/nvm/EngineException
          DUP
          ALOAD 1
          ALOAD 0
          ALOAD 3
          INVOKEVIRTUAL java/lang/Throwable.getMessage ()Ljava/lang/String;
          INVOKESPECIAL org/nlogo/nvm/EngineException.<init> (Lorg/nlogo/nvm/Context;Lorg/nlogo/nvm/Instruction;Ljava/lang/String;)V
          ATHROW
         L5
          RETURN
[5]_asm_proceduremakenode_done_5 "" => void
         L0
          ALOAD 1
          ICONST_1
          PUTFIELD org/nlogo/nvm/Context.finished : Z
         L1
          RETURN
[6]_moveto
      _asm_proceduremakenode_procedurevariable_6 "old-node" => Object
           L0
            ALOAD 1
            GETFIELD org/nlogo/nvm/Context.activation : Lorg/nlogo/nvm/Activation;
            INVOKEVIRTUAL org/nlogo/nvm/Activation.args ()[Ljava/lang/Object;
            ICONST_0
            AALOAD
           L1
            ARETURN
[7]_asm_proceduremakenode_right_7 "rt random" double => void
      _randomconst:360 => double
         L0
          ALOAD 1
          GETFIELD org/nlogo/nvm/Context.job : Lorg/nlogo/nvm/Job;
          GETFIELD org/nlogo/nvm/Job.random : Lorg/nlogo/util/MersenneTwisterFast;
          LDC 360
          INVOKEVIRTUAL org/nlogo/util/MersenneTwisterFast.nextLong (J)J
          L2D
         L1
          DSTORE 2
          ALOAD 1
          GETFIELD org/nlogo/nvm/Context.agent : Lorg/nlogo/agent/Agent;
          CHECKCAST org/nlogo/agent/Turtle
          DLOAD 2
          INVOKEVIRTUAL org/nlogo/agent/Turtle.turnRight (D)V
          ALOAD 1
          BIPUSH 8
          PUTFIELD org/nlogo/nvm/Context.ip : I
         L2
          RETURN
[8]_asm_proceduremakenode_fd_8 "fd 8" double => void
      _constdouble:8.0 => double
         L0
          LDC 8.0
         L1
          DSTORE 2
          ALOAD 1
          ALOAD 0
          GETFIELD org/nlogo/prim/_asm_proceduremakenode_fd_8.kept1__let : Lorg/nlogo/api/Let;
          NEW org/nlogo/nvm/MutableDouble
          DUP
          DLOAD 2
          INVOKESPECIAL org/nlogo/nvm/MutableDouble.<init> (D)V
          INVOKEVIRTUAL org/nlogo/nvm/Context.let (Lorg/nlogo/api/Let;Ljava/lang/Object;)V
          ALOAD 1
          BIPUSH 9
          PUTFIELD org/nlogo/nvm/Context.ip : I
         L2
          RETURN
[9]_asm_proceduremakenode_fdinternal_9 "" => void
          TRYCATCHBLOCK L0 L1 L2 org/nlogo/api/AgentException
          TRYCATCHBLOCK L3 L4 L1 org/nlogo/api/AgentException
         L5
          ALOAD 1
          GETFIELD org/nlogo/nvm/Context.agent : Lorg/nlogo/agent/Agent;
          CHECKCAST org/nlogo/agent/Turtle
          ASTORE 2
          ALOAD 1
          ALOAD 0
          GETFIELD org/nlogo/prim/_asm_proceduremakenode_fdinternal_9.kept1_let : Lorg/nlogo/api/Let;
          INVOKEVIRTUAL org/nlogo/nvm/Context.getLet (Lorg/nlogo/api/Let;)Ljava/lang/Object;
          CHECKCAST org/nlogo/nvm/MutableDouble
          ASTORE 3
          ALOAD 3
          INVOKEVIRTUAL org/nlogo/nvm/MutableDouble.value ()D
          DSTORE 4
          DLOAD 4
          INVOKESTATIC java/lang/StrictMath.abs (D)D
          DSTORE 6
          DLOAD 6
          GETSTATIC org/nlogo/api/Constants$.MODULE$ : Lorg/nlogo/api/Constants$;
          INVOKEVIRTUAL org/nlogo/api/Constants$.Infinitesimal ()D
          DCMPG
          IFGT L6
          ALOAD 1
          BIPUSH 10
          PUTFIELD org/nlogo/nvm/Context.ip : I
          GOTO L7
         L6
          DLOAD 6
          DCONST_1
          DCMPG
          IFGT L4
         L3
          ALOAD 2
          DLOAD 4
          INVOKEVIRTUAL org/nlogo/agent/Turtle.jump (D)V
          GOTO L8
         L4
          DLOAD 4
          ICONST_0
          I2D
          DCMPL
          IFLE L9
          ICONST_1
          GOTO L10
         L9
          ICONST_M1
         L10
          ISTORE 8
         L0
          ALOAD 2
          ILOAD 8
          I2D
          INVOKEVIRTUAL org/nlogo/agent/Turtle.jump (D)V
          ALOAD 3
          ALOAD 3
          INVOKEVIRTUAL org/nlogo/nvm/MutableDouble.value ()D
          ILOAD 8
          I2D
          DSUB
          INVOKEVIRTUAL org/nlogo/nvm/MutableDouble.value_$eq (D)V
          GOTO L7
         L1
          POP
         L8
          ALOAD 1
          BIPUSH 10
          PUTFIELD org/nlogo/nvm/Context.ip : I
          GOTO L7
         L2
          POP
          ALOAD 1
          BIPUSH 10
          PUTFIELD org/nlogo/nvm/Context.ip : I
         L7
          RETURN
[10]_asm_proceduremakenode_done_10 "" => void
         L0
          ALOAD 1
          ICONST_1
          PUTFIELD org/nlogo/nvm/Context.finished : Z
         L1
          RETURN
[11]_asm_proceduremakenode_return_11 "" => void
         L0
          ALOAD 1
          INVOKEVIRTUAL org/nlogo/nvm/Context.returnFromProcedure ()V
          ALOAD 1
          ICONST_0
          PUTFIELD org/nlogo/nvm/Context.stopping : Z
         L1
          RETURN

reporter procedure FIND-PARTNER:[TOTAL PARTNER]{OTPL}:
[0]_asm_procedurefindpartner_setprocedurevariable_0 "" Object => void
      _randomfloat double => double
        _sum LogoList => double
          _of
            _asm_procedurefindpartner_count_1 "count link-neighbors" AgentSet => double
              _linkneighbors:null => AgentSet
                 L0
                  ALOAD 0
                  GETFIELD org/nlogo/prim/_asm_procedurefindpartner_count_1.kept2_breedName : Ljava/lang/String;
                  IFNONNULL L1
                  ALOAD 0
                  GETFIELD org/nlogo/prim/_asm_procedurefindpartner_count_1.world : Lorg/nlogo/agent/World;
                  INVOKEVIRTUAL org/nlogo/agent/World.links ()Lorg/nlogo/agent/AgentSet;
                  GOTO L2
                 L1
                  ALOAD 0
                  GETFIELD org/nlogo/prim/_asm_procedurefindpartner_count_1.world : Lorg/nlogo/agent/World;
                  ALOAD 0
                  GETFIELD org/nlogo/prim/_asm_procedurefindpartner_count_1.kept2_breedName : Ljava/lang/String;
                  INVOKEVIRTUAL org/nlogo/agent/World.getLinkBreed (Ljava/lang/String;)Lorg/nlogo/agent/AgentSet;
                 L2
                  ASTORE 2
                  GETSTATIC org/nlogo/agent/LinkManager$.MODULE$ : Lorg/nlogo/agent/LinkManager$;
                  ALOAD 2
                  INVOKEVIRTUAL org/nlogo/agent/LinkManager$.mustNotBeDirected (Lorg/nlogo/agent/AgentSet;)Lscala/Option;
                  DUP
                  ASTORE 3
                  INVOKEVIRTUAL scala/Option.isEmpty ()Z
                  IFEQ L3
                  GETSTATIC org/nlogo/agent/AgentSet$.MODULE$ : Lorg/nlogo/agent/AgentSet$;
                  GETSTATIC org/nlogo/api/AgentKind$Turtle$.MODULE$ : Lorg/nlogo/api/AgentKind$Turtle$;
                  ALOAD 0
                  GETFIELD org/nlogo/prim/_asm_procedurefindpartner_count_1.world : Lorg/nlogo/agent/World;
                  INVOKEVIRTUAL org/nlogo/agent/World.linkManager ()Lorg/nlogo/agent/LinkManager;
                  ALOAD 1
                  GETFIELD org/nlogo/nvm/Context.agent : Lorg/nlogo/agent/Agent;
                  CHECKCAST org/nlogo/agent/Turtle
                  ALOAD 2
                  INVOKEINTERFACE org/nlogo/agent/LinkManager.findLinkedWith (Lorg/nlogo/agent/Turtle;Lorg/nlogo/agent/AgentSet;)Lscala/collection/Iterator;
                  INVOKEVIRTUAL org/nlogo/agent/AgentSet$.fromIterator (Lorg/nlogo/api/AgentKind;Lscala/collection/Iterator;)Lorg/nlogo/agent/AgentSet;
                  GOTO L4
                 L3
                  ALOAD 3
                  INVOKEVIRTUAL scala/Option.get ()Ljava/lang/Object;
                  CHECKCAST java/lang/String
                  ASTORE 5
                  NEW org/nlogo/nvm/EngineException
                  DUP
                  ALOAD 1
                  ALOAD 0
                  ALOAD 5
                  INVOKESPECIAL org/nlogo/nvm/EngineException.<init> (Lorg/nlogo/nvm/Context;Lorg/nlogo/nvm/Instruction;Ljava/lang/String;)V
                  ATHROW
                 L4
                  ASTORE 2
                  ALOAD 2
                  INVOKEINTERFACE org/nlogo/api/AgentSet.count ()I
                  I2D
                 L5
                  DSTORE 2
                  NEW java/lang/Double
                  DUP
                  DLOAD 2
                  INVOKESPECIAL java/lang/Double.<init> (D)V
                  ARETURN
            _asm_procedurefindpartner_turtles_2 "turtles" => AgentSet
                 L0
                  ALOAD 0
                  GETFIELD org/nlogo/prim/_asm_procedurefindpartner_turtles_2.world : Lorg/nlogo/agent/World;
                  INVOKEVIRTUAL org/nlogo/agent/World.turtles ()Lorg/nlogo/agent/AgentSet;
                 L1
                  ARETURN
          TRYCATCHBLOCK L0 L1 L1 java/lang/ClassCastException
          ALOAD 0
          GETFIELD org/nlogo/prim/_asm_procedurefindpartner_setprocedurevariable_0.keptinstr4 : Lorg/nlogo/prim/_of;
          ALOAD 1
          INVOKEVIRTUAL org/nlogo/prim/_of.report (Lorg/nlogo/nvm/Context;)Ljava/lang/Object;
         L2
          ASTORE 2
         L0
          ALOAD 2
          CHECKCAST org/nlogo/api/LogoList
          GOTO L3
         L1
          POP
          NEW org/nlogo/nvm/ArgumentTypeException
          DUP
          ALOAD 1
          ALOAD 0
          BIPUSH 0
          LDC 8
          ALOAD 2
          INVOKESPECIAL org/nlogo/nvm/ArgumentTypeException.<init> (Lorg/nlogo/nvm/Context;Lorg/nlogo/nvm/Instruction;IILjava/lang/Object;)V
          ATHROW
         L3
          ASTORE 2
          DCONST_0
          DSTORE 6
          ALOAD 2
          INVOKEVIRTUAL org/nlogo/api/LogoList.iterator ()Ljava/util/Iterator;
          ASTORE 3
         L4
          ALOAD 3
          INVOKEINTERFACE java/util/Iterator.hasNext ()Z
          IFEQ L5
          ALOAD 3
          INVOKEINTERFACE java/util/Iterator.next ()Ljava/lang/Object;
          ASTORE 4
          ALOAD 4
          INSTANCEOF java/lang/Double
          IFEQ L4
          ALOAD 4
          CHECKCAST java/lang/Double
          ASTORE 5
          DLOAD 6
          ALOAD 5
          INVOKEVIRTUAL java/lang/Double.doubleValue ()D
          DADD
          DSTORE 6
          GOTO L4
         L5
          ALOAD 0
          DLOAD 6
          INVOKEVIRTUAL org/nlogo/nvm/Instruction.validDouble (D)D
         L6
          DSTORE 2
          DLOAD 2
          ALOAD 1
          GETFIELD org/nlogo/nvm/Context.job : Lorg/nlogo/nvm/Job;
          GETFIELD org/nlogo/nvm/Job.random : Lorg/nlogo/util/MersenneTwisterFast;
          INVOKEVIRTUAL org/nlogo/util/MersenneTwisterFast.nextDouble ()D
          DMUL
         L7
          DSTORE 2
          NEW java/lang/Double
          DUP
          DLOAD 2
          INVOKESPECIAL java/lang/Double.<init> (D)V
          ASTORE 2
          ALOAD 1
          GETFIELD org/nlogo/nvm/Context.activation : Lorg/nlogo/nvm/Activation;
          INVOKEVIRTUAL org/nlogo/nvm/Activation.args ()[Ljava/lang/Object;
          ICONST_0
          ALOAD 2
          AASTORE
          ALOAD 1
          ICONST_1
          PUTFIELD org/nlogo/nvm/Context.ip : I
         L8
          RETURN
[1]_asm_procedurefindpartner_setprocedurevariable_3 "" Object => void
      _nobody => Nobody$
         L0
          GETSTATIC org/nlogo/api/Nobody$.MODULE$ : Lorg/nlogo/api/Nobody$;
         L1
          ASTORE 2
          ALOAD 1
          GETFIELD org/nlogo/nvm/Context.activation : Lorg/nlogo/nvm/Activation;
          INVOKEVIRTUAL org/nlogo/nvm/Activation.args ()[Ljava/lang/Object;
          ICONST_1
          ALOAD 2
          AASTORE
          ALOAD 1
          ICONST_2
          PUTFIELD org/nlogo/nvm/Context.ip : I
         L2
          RETURN
[2]_asm_procedurefindpartner_ask_4 "ask turtles" AgentSet => void
      _turtles => AgentSet
         L0
          ALOAD 0
          GETFIELD org/nlogo/prim/_asm_procedurefindpartner_ask_4.world : Lorg/nlogo/agent/World;
          INVOKEVIRTUAL org/nlogo/agent/World.turtles ()Lorg/nlogo/agent/AgentSet;
         L1
          ASTORE 2
          ALOAD 1
          GETFIELD org/nlogo/nvm/Context.agent : Lorg/nlogo/agent/Agent;
          INSTANCEOF org/nlogo/agent/Observer
          IFNE L2
          ALOAD 2
          ALOAD 0
          GETFIELD org/nlogo/prim/_asm_procedurefindpartner_ask_4.world : Lorg/nlogo/agent/World;
          INVOKEVIRTUAL org/nlogo/agent/World.turtles ()Lorg/nlogo/agent/AgentSet;
          IF_ACMPNE L3
          NEW org/nlogo/nvm/EngineException
          DUP
          ALOAD 1
          ALOAD 0
          GETSTATIC org/nlogo/api/I18N$.MODULE$ : Lorg/nlogo/api/I18N$;
          INVOKEVIRTUAL org/nlogo/api/I18N$.errors ()Lorg/nlogo/api/I18N$BundleKind;
          LDC "org.nlogo.prim.$common.onlyObserverCanAskAllTurtles"
          INVOKEVIRTUAL org/nlogo/api/I18N$BundleKind.get (Ljava/lang/String;)Ljava/lang/String;
          INVOKESPECIAL org/nlogo/nvm/EngineException.<init> (Lorg/nlogo/nvm/Context;Lorg/nlogo/nvm/Instruction;Ljava/lang/String;)V
          ATHROW
         L3
          ALOAD 2
          ALOAD 0
          GETFIELD org/nlogo/prim/_asm_procedurefindpartner_ask_4.world : Lorg/nlogo/agent/World;
          INVOKEVIRTUAL org/nlogo/agent/World.patches ()Lorg/nlogo/agent/AgentSet;
          IF_ACMPNE L2
          NEW org/nlogo/nvm/EngineException
          DUP
          ALOAD 1
          ALOAD 0
          GETSTATIC org/nlogo/api/I18N$.MODULE$ : Lorg/nlogo/api/I18N$;
          INVOKEVIRTUAL org/nlogo/api/I18N$.errors ()Lorg/nlogo/api/I18N$BundleKind;
          LDC "org.nlogo.prim.$common.onlyObserverCanAskAllPatches"
          INVOKEVIRTUAL org/nlogo/api/I18N$BundleKind.get (Ljava/lang/String;)Ljava/lang/String;
          INVOKESPECIAL org/nlogo/nvm/EngineException.<init> (Lorg/nlogo/nvm/Context;Lorg/nlogo/nvm/Instruction;Ljava/lang/String;)V
          ATHROW
         L2
          ALOAD 1
          ALOAD 2
          ICONST_3
          INVOKEVIRTUAL org/nlogo/nvm/Context.runExclusiveJob (Lorg/nlogo/agent/AgentSet;I)V
          ALOAD 1
          BIPUSH 10
          PUTFIELD org/nlogo/nvm/Context.ip : I
         L4
          RETURN
[3]_let
      _asm_procedurefindpartner_letvariable_5 "nc" => Object
           L0
            ALOAD 1
            ALOAD 0
            GETFIELD org/nlogo/prim/_asm_procedurefindpartner_letvariable_5.kept1__let : Lorg/nlogo/api/Let;
            INVOKEVIRTUAL org/nlogo/nvm/Context.getLet (Lorg/nlogo/api/Let;)Ljava/lang/Object;
           L1
            ARETURN
      _asm_procedurefindpartner_count_6 "count link-neighbors" AgentSet => double
        _linkneighbors:null => AgentSet
           L0
            ALOAD 0
            GETFIELD org/nlogo/prim/_asm_procedurefindpartner_count_6.kept2_breedName : Ljava/lang/String;
            IFNONNULL L1
            ALOAD 0
            GETFIELD org/nlogo/prim/_asm_procedurefindpartner_count_6.world : Lorg/nlogo/agent/World;
            INVOKEVIRTUAL org/nlogo/agent/World.links ()Lorg/nlogo/agent/AgentSet;
            GOTO L2
           L1
            ALOAD 0
            GETFIELD org/nlogo/prim/_asm_procedurefindpartner_count_6.world : Lorg/nlogo/agent/World;
            ALOAD 0
            GETFIELD org/nlogo/prim/_asm_procedurefindpartner_count_6.kept2_breedName : Ljava/lang/String;
            INVOKEVIRTUAL org/nlogo/agent/World.getLinkBreed (Ljava/lang/String;)Lorg/nlogo/agent/AgentSet;
           L2
            ASTORE 2
            GETSTATIC org/nlogo/agent/LinkManager$.MODULE$ : Lorg/nlogo/agent/LinkManager$;
            ALOAD 2
            INVOKEVIRTUAL org/nlogo/agent/LinkManager$.mustNotBeDirected (Lorg/nlogo/agent/AgentSet;)Lscala/Option;
            DUP
            ASTORE 3
            INVOKEVIRTUAL scala/Option.isEmpty ()Z
            IFEQ L3
            GETSTATIC org/nlogo/agent/AgentSet$.MODULE$ : Lorg/nlogo/agent/AgentSet$;
            GETSTATIC org/nlogo/api/AgentKind$Turtle$.MODULE$ : Lorg/nlogo/api/AgentKind$Turtle$;
            ALOAD 0
            GETFIELD org/nlogo/prim/_asm_procedurefindpartner_count_6.world : Lorg/nlogo/agent/World;
            INVOKEVIRTUAL org/nlogo/agent/World.linkManager ()Lorg/nlogo/agent/LinkManager;
            ALOAD 1
            GETFIELD org/nlogo/nvm/Context.agent : Lorg/nlogo/agent/Agent;
            CHECKCAST org/nlogo/agent/Turtle
            ALOAD 2
            INVOKEINTERFACE org/nlogo/agent/LinkManager.findLinkedWith (Lorg/nlogo/agent/Turtle;Lorg/nlogo/agent/AgentSet;)Lscala/collection/Iterator;
            INVOKEVIRTUAL org/nlogo/agent/AgentSet$.fromIterator (Lorg/nlogo/api/AgentKind;Lscala/collection/Iterator;)Lorg/nlogo/agent/AgentSet;
            GOTO L4
           L3
            ALOAD 3
            INVOKEVIRTUAL scala/Option.get ()Ljava/lang/Object;
            CHECKCAST java/lang/String
            ASTORE 5
            NEW org/nlogo/nvm/EngineException
            DUP
            ALOAD 1
            ALOAD 0
            ALOAD 5
            INVOKESPECIAL org/nlogo/nvm/EngineException.<init> (Lorg/nlogo/nvm/Context;Lorg/nlogo/nvm/Instruction;Ljava/lang/String;)V
            ATHROW
           L4
            ASTORE 2
            ALOAD 2
            INVOKEINTERFACE org/nlogo/api/AgentSet.count ()I
            I2D
           L5
            DSTORE 2
            NEW java/lang/Double
            DUP
            DLOAD 2
            INVOKESPECIAL java/lang/Double.<init> (D)V
            ARETURN
[4]_asm_procedurefindpartner_if_7 "if partner = nobody" boolean => void
      _equal Object,Object => boolean
        _procedurevariable:PARTNER => Object
        _nobody => Nobody$
         L0
          ALOAD 1
          GETFIELD org/nlogo/nvm/Context.activation : Lorg/nlogo/nvm/Activation;
          INVOKEVIRTUAL org/nlogo/nvm/Activation.args ()[Ljava/lang/Object;
          ICONST_1
          AALOAD
         L1
          GETSTATIC org/nlogo/api/Nobody$.MODULE$ : Lorg/nlogo/api/Nobody$;
         L2
          ASTORE 3
          ASTORE 2
          GETSTATIC org/nlogo/api/Equality$.MODULE$ : Lorg/nlogo/api/Equality$;
          ALOAD 2
          ALOAD 3
          INVOKEVIRTUAL org/nlogo/api/Equality$.equals (Ljava/lang/Object;Ljava/lang/Object;)Z
         L3
          ISTORE 2
          ALOAD 1
          ILOAD 2
          IFEQ L4
          ICONST_5
          GOTO L5
         L4
          BIPUSH 9
         L5
          PUTFIELD org/nlogo/nvm/Context.ip : I
         L6
          RETURN
[5]_asm_procedurefindpartner_ifelse_8 "ifelse nc > total" boolean => void
      _greaterthan Object,Object => boolean
        _letvariable(NC) => Object
        _procedurevariable:TOTAL => Object
         L0
          ALOAD 1
          ALOAD 0
          GETFIELD org/nlogo/prim/_asm_procedurefindpartner_ifelse_8.kept3__let : Lorg/nlogo/api/Let;
          INVOKEVIRTUAL org/nlogo/nvm/Context.getLet (Lorg/nlogo/api/Let;)Ljava/lang/Object;
         L1
          ALOAD 1
          GETFIELD org/nlogo/nvm/Context.activation : Lorg/nlogo/nvm/Activation;
          INVOKEVIRTUAL org/nlogo/nvm/Activation.args ()[Ljava/lang/Object;
          ICONST_0
          AALOAD
         L2
          ASTORE 3
          ASTORE 2
          ALOAD 2
          INSTANCEOF java/lang/Double
          IFEQ L3
          ALOAD 3
          INSTANCEOF java/lang/Double
          IFEQ L3
          ALOAD 2
          CHECKCAST java/lang/Double
          INVOKEVIRTUAL java/lang/Double.doubleValue ()D
          ALOAD 3
          CHECKCAST java/lang/Double
          INVOKEVIRTUAL java/lang/Double.doubleValue ()D
          DCMPL
          IFLE L4
          ICONST_1
          GOTO L5
         L4
          ICONST_0
         L5
          GOTO L6
         L3
          ALOAD 2
          INSTANCEOF java/lang/String
          IFEQ L7
          ALOAD 3
          INSTANCEOF java/lang/String
          IFEQ L7
          ALOAD 2
          CHECKCAST java/lang/String
          ALOAD 3
          CHECKCAST java/lang/String
          INVOKEVIRTUAL java/lang/String.compareTo (Ljava/lang/String;)I
          ICONST_0
          IF_ICMPLE L8
          ICONST_1
          GOTO L9
         L8
          ICONST_0
         L9
          GOTO L6
         L7
          ALOAD 2
          INSTANCEOF org/nlogo/agent/Agent
          IFEQ L10
          ALOAD 3
          INSTANCEOF org/nlogo/agent/Agent
          IFEQ L10
          ALOAD 2
          CHECKCAST org/nlogo/agent/Agent
          ASTORE 4
          ALOAD 3
          CHECKCAST org/nlogo/agent/Agent
          ASTORE 5
          ALOAD 4
          INVOKEVIRTUAL org/nlogo/agent/Agent.agentBit ()I
          ALOAD 5
          INVOKEVIRTUAL org/nlogo/agent/Agent.agentBit ()I
          IF_ICMPNE L10
          ALOAD 4
          ALOAD 5
          INVOKEVIRTUAL org/nlogo/agent/Agent.compareTo (Lorg/nlogo/agent/Agent;)I
          ICONST_0
          IF_ICMPLE L11
          ICONST_1
          GOTO L12
         L11
          ICONST_0
         L12
          GOTO L6
         L10
          NEW org/nlogo/nvm/EngineException
          DUP
          ALOAD 1
          ALOAD 0
          GETSTATIC org/nlogo/api/I18N$.MODULE$ : Lorg/nlogo/api/I18N$;
          INVOKEVIRTUAL org/nlogo/api/I18N$.errors ()Lorg/nlogo/api/I18N$BundleKind;
          LDC "org.nlogo.prim._greaterthan.cannotCompareParameters"
          GETSTATIC scala/Predef$.MODULE$ : Lscala/Predef$;
          ICONST_2
          ANEWARRAY java/lang/Object
          DUP
          ICONST_0
          GETSTATIC org/nlogo/api/TypeNames$.MODULE$ : Lorg/nlogo/api/TypeNames$;
          ALOAD 2
          INVOKEVIRTUAL org/nlogo/api/TypeNames$.aName (Ljava/lang/Object;)Ljava/lang/String;
          AASTORE
          DUP
          ICONST_1
          GETSTATIC org/nlogo/api/TypeNames$.MODULE$ : Lorg/nlogo/api/TypeNames$;
          ALOAD 3
          INVOKEVIRTUAL org/nlogo/api/TypeNames$.aName (Ljava/lang/Object;)Ljava/lang/String;
          AASTORE
          INVOKEVIRTUAL scala/LowPriorityImplicits.wrapRefArray ([Ljava/lang/Object;)Lscala/collection/mutable/WrappedArray;
          INVOKEVIRTUAL org/nlogo/api/I18N$BundleKind.getN (Ljava/lang/String;Lscala/collection/Seq;)Ljava/lang/String;
          INVOKESPECIAL org/nlogo/nvm/EngineException.<init> (Lorg/nlogo/nvm/Context;Lorg/nlogo/nvm/Instruction;Ljava/lang/String;)V
          ATHROW
         L6
          ISTORE 2
          ALOAD 1
          ILOAD 2
          IFEQ L13
          BIPUSH 6
          GOTO L14
         L13
          BIPUSH 8
         L14
          PUTFIELD org/nlogo/nvm/Context.ip : I
         L15
          RETURN
[6]_asm_procedurefindpartner_setprocedurevariable_9 "set partner self" Object => void
      _self => Agent
         L0
          ALOAD 1
          GETFIELD org/nlogo/nvm/Context.agent : Lorg/nlogo/agent/Agent;
         L1
          ASTORE 2
          ALOAD 1
          GETFIELD org/nlogo/nvm/Context.activation : Lorg/nlogo/nvm/Activation;
          INVOKEVIRTUAL org/nlogo/nvm/Activation.args ()[Ljava/lang/Object;
          ICONST_1
          ALOAD 2
          AASTORE
          ALOAD 1
          BIPUSH 7
          PUTFIELD org/nlogo/nvm/Context.ip : I
         L2
          RETURN
[7]_asm_procedurefindpartner_goto_10 "" => void
         L0
          ALOAD 1
          BIPUSH 9
          PUTFIELD org/nlogo/nvm/Context.ip : I
         L1
          RETURN
[8]_asm_procedurefindpartner_setprocedurevariable_11 "set total total - nc" Object => void
      _minus double,double => double
        _procedurevariable:TOTAL => Object
        _letvariable(NC) => Object
          TRYCATCHBLOCK L0 L1 L1 java/lang/ClassCastException
          TRYCATCHBLOCK L2 L3 L3 java/lang/ClassCastException
         L4
          ALOAD 1
          GETFIELD org/nlogo/nvm/Context.activation : Lorg/nlogo/nvm/Activation;
          INVOKEVIRTUAL org/nlogo/nvm/Activation.args ()[Ljava/lang/Object;
          ICONST_0
          AALOAD
         L5
          ASTORE 2
         L0
          ALOAD 2
          CHECKCAST java/lang/Double
          INVOKEVIRTUAL java/lang/Double.doubleValue ()D
          GOTO L6
         L1
          POP
          NEW org/nlogo/nvm/ArgumentTypeException
          DUP
          ALOAD 1
          ALOAD 0
          BIPUSH 0
          LDC 1
          ALOAD 2
          INVOKESPECIAL org/nlogo/nvm/ArgumentTypeException.<init> (Lorg/nlogo/nvm/Context;Lorg/nlogo/nvm/Instruction;IILjava/lang/Object;)V
          ATHROW
         L6
          ALOAD 1
          ALOAD 0
          GETFIELD org/nlogo/prim/_asm_procedurefindpartner_setprocedurevariable_11.kept4__let : Lorg/nlogo/api/Let;
          INVOKEVIRTUAL org/nlogo/nvm/Context.getLet (Lorg/nlogo/api/Let;)Ljava/lang/Object;
         L7
          ASTORE 2
         L2
          ALOAD 2
          CHECKCAST java/lang/Double
          INVOKEVIRTUAL java/lang/Double.doubleValue ()D
          GOTO L8
         L3
          POP
          NEW org/nlogo/nvm/ArgumentTypeException
          DUP
          ALOAD 1
          ALOAD 0
          BIPUSH 1
          LDC 1
          ALOAD 2
          INVOKESPECIAL org/nlogo/nvm/ArgumentTypeException.<init> (Lorg/nlogo/nvm/Context;Lorg/nlogo/nvm/Instruction;IILjava/lang/Object;)V
          ATHROW
         L8
          DSTORE 4
          DSTORE 2
          DLOAD 2
          DLOAD 4
          DSUB
         L9
          DSTORE 2
          NEW java/lang/Double
          DUP
          DLOAD 2
          INVOKESPECIAL java/lang/Double.<init> (D)V
          ASTORE 2
          ALOAD 1
          GETFIELD org/nlogo/nvm/Context.activation : Lorg/nlogo/nvm/Activation;
          INVOKEVIRTUAL org/nlogo/nvm/Activation.args ()[Ljava/lang/Object;
          ICONST_0
          ALOAD 2
          AASTORE
          ALOAD 1
          BIPUSH 9
          PUTFIELD org/nlogo/nvm/Context.ip : I
         L10
          RETURN
[9]_asm_procedurefindpartner_done_12 "" => void
         L0
          ALOAD 1
          ICONST_1
          PUTFIELD org/nlogo/nvm/Context.finished : Z
         L1
          RETURN
[10]_asm_procedurefindpartner_report_13 "report partner" Object => void
      _procedurevariable:PARTNER => Object
         L0
          ALOAD 1
          GETFIELD org/nlogo/nvm/Context.activation : Lorg/nlogo/nvm/Activation;
          INVOKEVIRTUAL org/nlogo/nvm/Activation.args ()[Ljava/lang/Object;
          ICONST_1
          AALOAD
         L1
          ASTORE 2
          ALOAD 1
          GETFIELD org/nlogo/nvm/Context.job : Lorg/nlogo/nvm/Job;
          ALOAD 2
          PUTFIELD org/nlogo/nvm/Job.result : Ljava/lang/Object;
          ALOAD 1
          ICONST_0
          PUTFIELD org/nlogo/nvm/Context.stopping : Z
          ALOAD 1
          BIPUSH 11
          PUTFIELD org/nlogo/nvm/Context.ip : I
          ALOAD 1
          GETFIELD org/nlogo/nvm/Context.activation : Lorg/nlogo/nvm/Activation;
          INVOKEVIRTUAL org/nlogo/nvm/Activation.procedure ()Lorg/nlogo/nvm/Procedure;
          INVOKEVIRTUAL org/nlogo/nvm/Procedure.isTask ()Z
          IFEQ L2
          GETSTATIC org/nlogo/nvm/NonLocalExit$.MODULE$ : Lorg/nlogo/nvm/NonLocalExit$;
          ATHROW
         L2
          ALOAD 1
          GETFIELD org/nlogo/nvm/Context.activation : Lorg/nlogo/nvm/Activation;
          INVOKEVIRTUAL org/nlogo/nvm/Activation.procedure ()Lorg/nlogo/nvm/Procedure;
          INVOKEVIRTUAL org/nlogo/nvm/Procedure.isReporter ()Z
          IFNE L3
          NEW org/nlogo/nvm/EngineException
          DUP
          ALOAD 1
          ALOAD 0
          INVOKESTATIC org/nlogo/api/I18N.errorsJ ()Lorg/nlogo/api/I18NJava;
          LDC "org.nlogo.prim._report.canOnlyUseInToReport"
          ICONST_1
          ANEWARRAY java/lang/Object
          DUP
          ICONST_0
          LDC "REPORT"
          AASTORE
          INVOKEINTERFACE org/nlogo/api/I18NJava.getN (Ljava/lang/String;[Ljava/lang/Object;)Ljava/lang/String;
          INVOKESPECIAL org/nlogo/nvm/EngineException.<init> (Lorg/nlogo/nvm/Context;Lorg/nlogo/nvm/Instruction;Ljava/lang/String;)V
          ATHROW
         L3
          ALOAD 1
          INVOKEVIRTUAL org/nlogo/nvm/Context.atTopActivation ()Z
          IFNE L4
          NEW org/nlogo/nvm/EngineException
          DUP
          ALOAD 1
          ALOAD 0
          INVOKESTATIC org/nlogo/api/I18N.errorsJ ()Lorg/nlogo/api/I18NJava;
          LDC "org.nlogo.prim._report.mustImmediatelyBeUsedInToReport"
          ICONST_1
          ANEWARRAY java/lang/Object
          DUP
          ICONST_0
          LDC "REPORT"
          AASTORE
          INVOKEINTERFACE org/nlogo/api/I18NJava.getN (Ljava/lang/String;[Ljava/lang/Object;)Ljava/lang/String;
          INVOKESPECIAL org/nlogo/nvm/EngineException.<init> (Lorg/nlogo/nvm/Context;Lorg/nlogo/nvm/Instruction;Ljava/lang/String;)V
          ATHROW
         L4
          RETURN
[11]_asm_procedurefindpartner_returnreport_14 "" => void
         L0
          NEW org/nlogo/nvm/EngineException
          DUP
          ALOAD 1
          ALOAD 0
          GETSTATIC org/nlogo/api/I18N$.MODULE$ : Lorg/nlogo/api/I18N$;
          INVOKEVIRTUAL org/nlogo/api/I18N$.errors ()Lorg/nlogo/api/I18N$BundleKind;
          LDC "org.nlogo.prim._returnreport.reportNotCalledInReportProcedure"
          INVOKEVIRTUAL org/nlogo/api/I18N$BundleKind.get (Ljava/lang/String;)Ljava/lang/String;
          INVOKESPECIAL org/nlogo/nvm/EngineException.<init> (Lorg/nlogo/nvm/Context;Lorg/nlogo/nvm/Instruction;Ljava/lang/String;)V
          ATHROW
         L1
          RETURN

procedure LAYOUT:[_repeatlocal:0]{OTPL}:
[0]_asm_procedurelayout_repeatlocal_0 "" double => void
      _constdouble:3.0 => double
         L0
          LDC 3.0
         L1
          DSTORE 2
          ALOAD 1
          GETFIELD org/nlogo/nvm/Context.activation : Lorg/nlogo/nvm/Activation;
          INVOKEVIRTUAL org/nlogo/nvm/Activation.args ()[Ljava/lang/Object;
          ICONST_0
          NEW org/nlogo/nvm/MutableLong
          DUP
          ALOAD 0
          DLOAD 2
          INVOKEVIRTUAL org/nlogo/nvm/Instruction.validLong (D)J
          INVOKESPECIAL org/nlogo/nvm/MutableLong.<init> (J)V
          AASTORE
          ALOAD 1
          ICONST_3
          PUTFIELD org/nlogo/nvm/Context.ip : I
         L2
          RETURN
[1]_layoutspring
      _asm_procedurelayout_turtles_1 "turtles" => AgentSet
           L0
            ALOAD 0
            GETFIELD org/nlogo/prim/_asm_procedurelayout_turtles_1.world : Lorg/nlogo/agent/World;
            INVOKEVIRTUAL org/nlogo/agent/World.turtles ()Lorg/nlogo/agent/AgentSet;
           L1
            ARETURN
      _asm_procedurelayout_links_2 "links" => AgentSet
           L0
            ALOAD 0
            GETFIELD org/nlogo/prim/_asm_procedurelayout_links_2.world : Lorg/nlogo/agent/World;
            INVOKEVIRTUAL org/nlogo/agent/World.links ()Lorg/nlogo/agent/AgentSet;
           L1
            ARETURN
      _asm_procedurelayout_constdouble_3 "0.5" => Double
           L0
            ALOAD 0
            GETFIELD org/nlogo/prim/_asm_procedurelayout_constdouble_3.kept1_value : Ljava/lang/Double;
           L1
            ARETURN
      _asm_procedurelayout_constdouble_4 "1.0" => Double
           L0
            ALOAD 0
            GETFIELD org/nlogo/prim/_asm_procedurelayout_constdouble_4.kept1_value : Ljava/lang/Double;
           L1
            ARETURN
      _asm_procedurelayout_constdouble_5 "0.4" => Double
           L0
            ALOAD 0
            GETFIELD org/nlogo/prim/_asm_procedurelayout_constdouble_5.kept1_value : Ljava/lang/Double;
           L1
            ARETURN
[2]_display
[3]_asm_procedurelayout_repeatlocalinternal_6 "" => void
         L0
          ALOAD 1
          GETFIELD org/nlogo/nvm/Context.activation : Lorg/nlogo/nvm/Activation;
          INVOKEVIRTUAL org/nlogo/nvm/Activation.args ()[Ljava/lang/Object;
          ICONST_0
          AALOAD
          CHECKCAST org/nlogo/nvm/MutableLong
          ASTORE 2
          ALOAD 2
          INVOKEVIRTUAL org/nlogo/nvm/MutableLong.value ()J
          LCONST_0
          LCMP
          IFGT L1
          ALOAD 1
          ICONST_4
          PUTFIELD org/nlogo/nvm/Context.ip : I
          GOTO L2
         L1
          ALOAD 2
          ALOAD 2
          INVOKEVIRTUAL org/nlogo/nvm/MutableLong.value ()J
          LCONST_1
          LSUB
          INVOKEVIRTUAL org/nlogo/nvm/MutableLong.value_$eq (J)V
          ALOAD 1
          ICONST_1
          PUTFIELD org/nlogo/nvm/Context.ip : I
         L2
          RETURN
[4]_asm_procedurelayout_return_7 "" => void
         L0
          ALOAD 1
          INVOKEVIRTUAL org/nlogo/nvm/Context.returnFromProcedure ()V
          ALOAD 1
          ICONST_0
          PUTFIELD org/nlogo/nvm/Context.stopping : Z
         L1
          RETURN

