globals [GAIN-RESISTANCE-CHANCE RECOVERY-CHANCE VIRUS-SPREAD-CHANCE NUMBER-OF-NODES VIRUS-CHECK-FREQUENCY INITIAL-OUTBREAK-SIZE AVERAGE-NODE-DEGREE RESULT]
interfaceGlobals [gain-resistance-chance recovery-chance virus-spread-chance number-of-nodes virus-check-frequency initial-outbreak-size average-node-degree]
turtles-own [WHO COLOR HEADING XCOR YCOR SHAPE LABEL LABEL-COLOR BREED HIDDEN? SIZE PEN-SIZE PEN-MODE INFECTED? RESISTANT? VIRUS-CHECK-TIMER]
patches-own [PXCOR PYCOR PCOLOR PLABEL PLABEL-COLOR]
links-own [END1 END2 COLOR LABEL LABEL-COLOR HIDDEN? BREED THICKNESS SHAPE TIE-MODE]
breeds 
link-breeds 

procedure GO:[]{O---}:
[0]_asm_procedurego_if_0 "if all? turtles [ not infected? ] [ stop ]" boolean => void
      _all "all? turtles [ not infected? ]" AgentSet,Reporter => boolean
        _turtles "turtles" => AgentSet
        _asm_procedurego_not_1 "not infected?" boolean => boolean
          _turtlevariable:INFECTED? "infected?" => Object
              TRYCATCHBLOCK L0 L1 L2 org/nlogo/api/AgentException
              TRYCATCHBLOCK L3 L4 L4 java/lang/ClassCastException
             L0
              ALOAD 1
              GETFIELD org/nlogo/nvm/Context.agent : Lorg/nlogo/agent/Agent;
              BIPUSH 13
              INVOKEVIRTUAL org/nlogo/agent/Agent.getTurtleVariable (I)Ljava/lang/Object;
             L1
              GOTO L5
             L2
             FRAME SAME1 org/nlogo/api/AgentException
              ASTORE 2
              NEW org/nlogo/nvm/EngineException
              DUP
              ALOAD 1
              ALOAD 0
              ALOAD 2
              INVOKEVIRTUAL org/nlogo/api/AgentException.getMessage ()Ljava/lang/String;
              INVOKESPECIAL org/nlogo/nvm/EngineException.<init> (Lorg/nlogo/nvm/Context;Lorg/nlogo/nvm/Instruction;Ljava/lang/String;)V
              ATHROW
             L5
             FRAME SAME1 java/lang/Object
              ASTORE 2
             L3
              ALOAD 2
              CHECKCAST java/lang/Boolean
              INVOKEVIRTUAL java/lang/Boolean.booleanValue ()Z
              GOTO L6
             L4
             FRAME FULL [org/nlogo/prim/_asm_procedurego_not_1 org/nlogo/nvm/Context java/lang/Object] [java/lang/ClassCastException]
              POP
              NEW org/nlogo/nvm/ArgumentTypeException
              DUP
              ALOAD 1
              ALOAD 0
              BIPUSH 0
              LDC 2
              ALOAD 2
              INVOKESPECIAL org/nlogo/nvm/ArgumentTypeException.<init> (Lorg/nlogo/nvm/Context;Lorg/nlogo/nvm/Instruction;IILjava/lang/Object;)V
              ATHROW
             L6
             FRAME SAME1 I
              ISTORE 2
              ILOAD 2
              IFNE L7
              ICONST_1
              GOTO L8
             L7
             FRAME FULL [org/nlogo/prim/_asm_procedurego_not_1 org/nlogo/nvm/Context I] []
              ICONST_0
             L8
             FRAME SAME1 I
              IFEQ L9
              GETSTATIC java/lang/Boolean.TRUE : Ljava/lang/Boolean;
              GOTO L10
             L9
             FRAME SAME
              GETSTATIC java/lang/Boolean.FALSE : Ljava/lang/Boolean;
             L10
             FRAME SAME1 java/lang/Boolean
              ARETURN
         L0
          ALOAD 0
          GETFIELD org/nlogo/prim/_asm_procedurego_if_0.world : Lorg/nlogo/agent/World;
          INVOKEVIRTUAL org/nlogo/agent/World.turtles ()Lorg/nlogo/agent/AgentSet;
         L1
          ALOAD 0
          GETFIELD org/nlogo/prim/_asm_procedurego_if_0.keptinstr4 : Lorg/nlogo/nvm/Reporter;
          ASTORE 3
          ASTORE 2
          NEW org/nlogo/nvm/Context
          DUP
          ALOAD 1
          ALOAD 2
          INVOKESPECIAL org/nlogo/nvm/Context.<init> (Lorg/nlogo/nvm/Context;Lorg/nlogo/agent/AgentSet;)V
          ASTORE 4
          ALOAD 3
          ALOAD 2
          ALOAD 1
          INVOKEVIRTUAL org/nlogo/nvm/Reporter.checkAgentSetClass (Lorg/nlogo/agent/AgentSet;Lorg/nlogo/nvm/Context;)V
          ALOAD 2
          INVOKEVIRTUAL org/nlogo/agent/AgentSet.iterator ()Lorg/nlogo/agent/AgentSet$Iterator;
          ASTORE 5
         L2
         FRAME FULL [org/nlogo/prim/_asm_procedurego_if_0 org/nlogo/nvm/Context org/nlogo/agent/AgentSet org/nlogo/nvm/Reporter org/nlogo/nvm/Context org/nlogo/agent/AgentSet$Iterator] []
          ALOAD 5
          INVOKEINTERFACE org/nlogo/agent/AgentSet$Iterator.hasNext ()Z
          IFEQ L3
          ALOAD 5
          INVOKEINTERFACE org/nlogo/agent/AgentSet$Iterator.next ()Lorg/nlogo/agent/Agent;
          ASTORE 6
          ALOAD 4
          ALOAD 6
          ALOAD 3
          INVOKEVIRTUAL org/nlogo/nvm/Context.evaluateReporter (Lorg/nlogo/agent/Agent;Lorg/nlogo/nvm/Reporter;)Ljava/lang/Object;
          ASTORE 7
          ALOAD 7
          INSTANCEOF java/lang/Boolean
          IFNE L4
          NEW org/nlogo/nvm/EngineException
          DUP
          ALOAD 1
          ALOAD 0
          INVOKESTATIC org/nlogo/core/I18N.errorsJ ()Lorg/nlogo/core/I18NJava;
          LDC "org.nlogo.prim.$common.expectedBooleanValue"
          ICONST_3
          ANEWARRAY java/lang/Object
          DUP
          ICONST_0
          LDC "ALL?"
          AASTORE
          DUP
          ICONST_1
          ALOAD 6
          INVOKESTATIC org/nlogo/api/Dump.logoObject (Ljava/lang/Object;)Ljava/lang/String;
          AASTORE
          DUP
          ICONST_2
          ALOAD 7
          INVOKESTATIC org/nlogo/api/Dump.logoObject (Ljava/lang/Object;)Ljava/lang/String;
          AASTORE
          INVOKEINTERFACE org/nlogo/core/I18NJava.getN (Ljava/lang/String;[Ljava/lang/Object;)Ljava/lang/String;
          INVOKESPECIAL org/nlogo/nvm/EngineException.<init> (Lorg/nlogo/nvm/Context;Lorg/nlogo/nvm/Instruction;Ljava/lang/String;)V
          ATHROW
         L4
         FRAME APPEND [org/nlogo/agent/Agent java/lang/Object]
          ALOAD 7
          CHECKCAST java/lang/Boolean
          INVOKEVIRTUAL java/lang/Boolean.booleanValue ()Z
          IFNE L5
          ICONST_0
          GOTO L6
         L5
         FRAME SAME
          GOTO L2
         L3
         FRAME CHOP 2
          ICONST_1
         L6
         FRAME SAME1 I
          ISTORE 2
          ALOAD 1
          ILOAD 2
          IFEQ L7
          ICONST_1
          GOTO L8
         L7
         FRAME FULL [org/nlogo/prim/_asm_procedurego_if_0 org/nlogo/nvm/Context I org/nlogo/nvm/Reporter org/nlogo/nvm/Context org/nlogo/agent/AgentSet$Iterator] [org/nlogo/nvm/Context]
          ICONST_2
         L8
         FRAME FULL [org/nlogo/prim/_asm_procedurego_if_0 org/nlogo/nvm/Context I org/nlogo/nvm/Reporter org/nlogo/nvm/Context org/nlogo/agent/AgentSet$Iterator] [org/nlogo/nvm/Context I]
          PUTFIELD org/nlogo/nvm/Context.ip : I
         L9
          RETURN
[1]_asm_procedurego_stop_2 "stop" => void
         L0
          ALOAD 1
          INVOKEVIRTUAL org/nlogo/nvm/Context.atTopActivation ()Z
          IFNE L1
          ALOAD 1
          ICONST_1
          PUTFIELD org/nlogo/nvm/Context.finished : Z
          GOTO L2
         L1
         FRAME SAME
          ALOAD 1
          GETFIELD org/nlogo/nvm/Context.activation : Lorg/nlogo/nvm/Activation;
          GETFIELD org/nlogo/nvm/Activation.procedure : Lorg/nlogo/nvm/Procedure;
          INVOKEVIRTUAL org/nlogo/nvm/Procedure.isReporter ()Z
          IFNE L3
          ALOAD 1
          GETFIELD org/nlogo/nvm/Context.activation : Lorg/nlogo/nvm/Activation;
          GETFIELD org/nlogo/nvm/Activation.procedure : Lorg/nlogo/nvm/Procedure;
          INVOKEVIRTUAL org/nlogo/nvm/Procedure.isTask ()Z
          IFEQ L4
          ALOAD 1
          GETFIELD org/nlogo/nvm/Context.activation : Lorg/nlogo/nvm/Activation;
          GETFIELD org/nlogo/nvm/Activation.procedure : Lorg/nlogo/nvm/Procedure;
          INVOKEVIRTUAL org/nlogo/nvm/Procedure.parent ()Lorg/nlogo/nvm/Procedure;
          INVOKEVIRTUAL org/nlogo/nvm/Procedure.isReporter ()Z
          IFEQ L4
         L3
         FRAME SAME
          NEW org/nlogo/nvm/EngineException
          DUP
          ALOAD 1
          ALOAD 0
          INVOKESTATIC org/nlogo/core/I18N.errorsJ ()Lorg/nlogo/core/I18NJava;
          LDC "org.nlogo.prim.etc._stop.notAllowedInsideToReport"
          ICONST_1
          ANEWARRAY java/lang/Object
          DUP
          ICONST_0
          LDC "STOP"
          AASTORE
          INVOKEINTERFACE org/nlogo/core/I18NJava.getN (Ljava/lang/String;[Ljava/lang/Object;)Ljava/lang/String;
          INVOKESPECIAL org/nlogo/nvm/EngineException.<init> (Lorg/nlogo/nvm/Context;Lorg/nlogo/nvm/Instruction;Ljava/lang/String;)V
          ATHROW
         L4
         FRAME SAME
          ALOAD 1
          INVOKEVIRTUAL org/nlogo/nvm/Context.stop ()V
         L2
         FRAME SAME
          RETURN
[2]_asm_procedurego_ask_3 "ask turtles set virus-check-timer virus-check-timer + 1 [ if virus-check-timer >= virus-check-frequency [ set virus-check-timer 0 ] ]" AgentSet => void
      _turtles "turtles" => AgentSet
         L0
          ALOAD 0
          GETFIELD org/nlogo/prim/_asm_procedurego_ask_3.world : Lorg/nlogo/agent/World;
          INVOKEVIRTUAL org/nlogo/agent/World.turtles ()Lorg/nlogo/agent/AgentSet;
         L1
          ASTORE 2
          ALOAD 1
          GETFIELD org/nlogo/nvm/Context.agent : Lorg/nlogo/agent/Agent;
          INSTANCEOF org/nlogo/agent/Observer
          IFNE L2
          ALOAD 2
          ALOAD 0
          GETFIELD org/nlogo/prim/_asm_procedurego_ask_3.world : Lorg/nlogo/agent/World;
          INVOKEVIRTUAL org/nlogo/agent/World.turtles ()Lorg/nlogo/agent/AgentSet;
          IF_ACMPNE L3
          NEW org/nlogo/nvm/EngineException
          DUP
          ALOAD 1
          ALOAD 0
          INVOKESTATIC org/nlogo/core/I18N.errorsJ ()Lorg/nlogo/core/I18NJava;
          LDC "org.nlogo.prim.$common.onlyObserverCanAskAllTurtles"
          INVOKEINTERFACE org/nlogo/core/I18NJava.get (Ljava/lang/String;)Ljava/lang/String;
          INVOKESPECIAL org/nlogo/nvm/EngineException.<init> (Lorg/nlogo/nvm/Context;Lorg/nlogo/nvm/Instruction;Ljava/lang/String;)V
          ATHROW
         L3
         FRAME APPEND [org/nlogo/agent/AgentSet]
          ALOAD 2
          ALOAD 0
          GETFIELD org/nlogo/prim/_asm_procedurego_ask_3.world : Lorg/nlogo/agent/World;
          INVOKEVIRTUAL org/nlogo/agent/World.patches ()Lorg/nlogo/agent/AgentSet;
          IF_ACMPNE L2
          NEW org/nlogo/nvm/EngineException
          DUP
          ALOAD 1
          ALOAD 0
          INVOKESTATIC org/nlogo/core/I18N.errorsJ ()Lorg/nlogo/core/I18NJava;
          LDC "org.nlogo.prim.$common.onlyObserverCanAskAllPatches"
          INVOKEINTERFACE org/nlogo/core/I18NJava.get (Ljava/lang/String;)Ljava/lang/String;
          INVOKESPECIAL org/nlogo/nvm/EngineException.<init> (Lorg/nlogo/nvm/Context;Lorg/nlogo/nvm/Instruction;Ljava/lang/String;)V
          ATHROW
         L2
         FRAME SAME
          ALOAD 1
          ALOAD 2
          ICONST_3
          INVOKEVIRTUAL org/nlogo/nvm/Context.runExclusiveJob (Lorg/nlogo/agent/AgentSet;I)V
          ALOAD 1
          BIPUSH 7
          PUTFIELD org/nlogo/nvm/Context.ip : I
         L4
          RETURN
[3]_asm_procedurego_setturtlevariable_4 "set virus-check-timer virus-check-timer + 1" Object => void
      _plus "virus-check-timer + 1" double,double => double
        _turtlevariable:VIRUS-CHECK-TIMER "virus-check-timer" => Object
        _constdouble:1.0 "1" => double
          TRYCATCHBLOCK L0 L1 L2 org/nlogo/api/AgentException
          TRYCATCHBLOCK L3 L4 L4 java/lang/ClassCastException
          TRYCATCHBLOCK L5 L6 L7 org/nlogo/api/AgentException
         L0
          ALOAD 1
          GETFIELD org/nlogo/nvm/Context.agent : Lorg/nlogo/agent/Agent;
          BIPUSH 15
          INVOKEVIRTUAL org/nlogo/agent/Agent.getTurtleVariable (I)Ljava/lang/Object;
         L1
          GOTO L8
         L2
         FRAME SAME1 org/nlogo/api/AgentException
          ASTORE 2
          NEW org/nlogo/nvm/EngineException
          DUP
          ALOAD 1
          ALOAD 0
          ALOAD 2
          INVOKEVIRTUAL org/nlogo/api/AgentException.getMessage ()Ljava/lang/String;
          INVOKESPECIAL org/nlogo/nvm/EngineException.<init> (Lorg/nlogo/nvm/Context;Lorg/nlogo/nvm/Instruction;Ljava/lang/String;)V
          ATHROW
         L8
         FRAME SAME1 java/lang/Object
          ASTORE 2
         L3
          ALOAD 2
          CHECKCAST java/lang/Double
          INVOKEVIRTUAL java/lang/Double.doubleValue ()D
          GOTO L9
         L4
         FRAME FULL [org/nlogo/prim/_asm_procedurego_setturtlevariable_4 org/nlogo/nvm/Context java/lang/Object] [java/lang/ClassCastException]
          POP
          NEW org/nlogo/nvm/ArgumentTypeException
          DUP
          ALOAD 1
          ALOAD 0
          BIPUSH 0
          LDC 1
          ALOAD 2
          INVOKESPECIAL org/nlogo/nvm/ArgumentTypeException.<init> (Lorg/nlogo/nvm/Context;Lorg/nlogo/nvm/Instruction;IILjava/lang/Object;)V
          ATHROW
         L9
         FRAME SAME1 D
          DCONST_1
         L10
          DSTORE 4
          DSTORE 2
          ALOAD 0
          DLOAD 2
          DLOAD 4
          DADD
          INVOKEVIRTUAL org/nlogo/prim/_asm_procedurego_setturtlevariable_4.validDouble (D)D
         L11
          DSTORE 2
          NEW java/lang/Double
          DUP
          DLOAD 2
          INVOKESPECIAL java/lang/Double.<init> (D)V
          ASTORE 2
         L5
          ALOAD 1
          GETFIELD org/nlogo/nvm/Context.agent : Lorg/nlogo/agent/Agent;
          BIPUSH 15
          ALOAD 2
          INVOKEVIRTUAL org/nlogo/agent/Agent.setTurtleVariable (ILjava/lang/Object;)V
         L6
          GOTO L12
         L7
         FRAME FULL [org/nlogo/prim/_asm_procedurego_setturtlevariable_4 org/nlogo/nvm/Context java/lang/Double T D] [org/nlogo/api/AgentException]
          ASTORE 3
          NEW org/nlogo/nvm/EngineException
          DUP
          ALOAD 1
          ALOAD 0
          ALOAD 3
          INVOKEVIRTUAL org/nlogo/api/AgentException.getMessage ()Ljava/lang/String;
          INVOKESPECIAL org/nlogo/nvm/EngineException.<init> (Lorg/nlogo/nvm/Context;Lorg/nlogo/nvm/Instruction;Ljava/lang/String;)V
          ATHROW
         L12
         FRAME SAME
          ALOAD 1
          ICONST_4
          PUTFIELD org/nlogo/nvm/Context.ip : I
         L13
          RETURN
[4]_asm_procedurego_if_5 "if virus-check-timer >= virus-check-frequency [ set virus-check-timer 0 ]" boolean => void
      _greaterorequal "virus-check-timer >= virus-check-frequency" Object,Object => boolean
        _turtlevariable:VIRUS-CHECK-TIMER "virus-check-timer" => Object
        _observervariable:VIRUS-CHECK-FREQUENCY "virus-check-frequency" => Object
          TRYCATCHBLOCK L0 L1 L2 org/nlogo/api/AgentException
         L0
          ALOAD 1
          GETFIELD org/nlogo/nvm/Context.agent : Lorg/nlogo/agent/Agent;
          BIPUSH 15
          INVOKEVIRTUAL org/nlogo/agent/Agent.getTurtleVariable (I)Ljava/lang/Object;
         L1
          GOTO L3
         L2
         FRAME SAME1 org/nlogo/api/AgentException
          ASTORE 2
          NEW org/nlogo/nvm/EngineException
          DUP
          ALOAD 1
          ALOAD 0
          ALOAD 2
          INVOKEVIRTUAL org/nlogo/api/AgentException.getMessage ()Ljava/lang/String;
          INVOKESPECIAL org/nlogo/nvm/EngineException.<init> (Lorg/nlogo/nvm/Context;Lorg/nlogo/nvm/Instruction;Ljava/lang/String;)V
          ATHROW
         L3
         FRAME SAME1 java/lang/Object
          ALOAD 1
          GETFIELD org/nlogo/nvm/Context.agent : Lorg/nlogo/agent/Agent;
          ICONST_4
          INVOKEVIRTUAL org/nlogo/agent/Agent.getObserverVariable (I)Ljava/lang/Object;
         L4
          ASTORE 3
          ASTORE 2
          ALOAD 2
          INSTANCEOF java/lang/Double
          IFEQ L5
          ALOAD 3
          INSTANCEOF java/lang/Double
          IFEQ L5
          ALOAD 2
          CHECKCAST java/lang/Double
          INVOKEVIRTUAL java/lang/Double.doubleValue ()D
          ALOAD 3
          CHECKCAST java/lang/Double
          INVOKEVIRTUAL java/lang/Double.doubleValue ()D
          DCMPL
          IFLT L6
          ICONST_1
          GOTO L7
         L6
         FRAME APPEND [java/lang/Object java/lang/Object]
          ICONST_0
         L7
         FRAME SAME1 I
          GOTO L8
         L5
         FRAME SAME
          ALOAD 2
          INSTANCEOF java/lang/String
          IFEQ L9
          ALOAD 3
          INSTANCEOF java/lang/String
          IFEQ L9
          ALOAD 2
          CHECKCAST java/lang/String
          ALOAD 3
          CHECKCAST java/lang/String
          INVOKEVIRTUAL java/lang/String.compareTo (Ljava/lang/String;)I
          IFLT L10
          ICONST_1
          GOTO L11
         L10
         FRAME SAME
          ICONST_0
         L11
         FRAME SAME1 I
          GOTO L8
         L9
         FRAME SAME
          ALOAD 2
          INSTANCEOF org/nlogo/agent/Agent
          IFEQ L12
          ALOAD 3
          INSTANCEOF org/nlogo/agent/Agent
          IFEQ L12
          ALOAD 2
          CHECKCAST org/nlogo/agent/Agent
          ASTORE 4
          ALOAD 3
          CHECKCAST org/nlogo/agent/Agent
          ASTORE 5
          ALOAD 4
          INVOKEVIRTUAL org/nlogo/agent/Agent.getAgentBit ()I
          ALOAD 5
          INVOKEVIRTUAL org/nlogo/agent/Agent.getAgentBit ()I
          IF_ICMPNE L12
          ALOAD 4
          ALOAD 5
          INVOKEVIRTUAL org/nlogo/agent/Agent.compareTo (Lorg/nlogo/agent/Agent;)I
          IFLT L13
          ICONST_1
          GOTO L14
         L13
         FRAME APPEND [org/nlogo/agent/Agent org/nlogo/agent/Agent]
          ICONST_0
         L14
         FRAME SAME1 I
          GOTO L8
         L12
         FRAME CHOP 2
          NEW org/nlogo/nvm/EngineException
          DUP
          ALOAD 1
          ALOAD 0
          INVOKESTATIC org/nlogo/core/I18N.errorsJ ()Lorg/nlogo/core/I18NJava;
          LDC "org.nlogo.prim._greaterorequal.cannotCompareParameters"
          ICONST_2
          ANEWARRAY java/lang/Object
          DUP
          ICONST_0
          ALOAD 2
          INVOKESTATIC org/nlogo/api/TypeNames.aName (Ljava/lang/Object;)Ljava/lang/String;
          AASTORE
          DUP
          ICONST_1
          ALOAD 3
          INVOKESTATIC org/nlogo/api/TypeNames.aName (Ljava/lang/Object;)Ljava/lang/String;
          AASTORE
          INVOKEINTERFACE org/nlogo/core/I18NJava.getN (Ljava/lang/String;[Ljava/lang/Object;)Ljava/lang/String;
          INVOKESPECIAL org/nlogo/nvm/EngineException.<init> (Lorg/nlogo/nvm/Context;Lorg/nlogo/nvm/Instruction;Ljava/lang/String;)V
          ATHROW
         L8
         FRAME SAME1 I
          ISTORE 2
          ALOAD 1
          ILOAD 2
          IFEQ L15
          ICONST_5
          GOTO L16
         L15
         FRAME FULL [org/nlogo/prim/_asm_procedurego_if_5 org/nlogo/nvm/Context I java/lang/Object] [org/nlogo/nvm/Context]
          BIPUSH 6
         L16
         FRAME FULL [org/nlogo/prim/_asm_procedurego_if_5 org/nlogo/nvm/Context I java/lang/Object] [org/nlogo/nvm/Context I]
          PUTFIELD org/nlogo/nvm/Context.ip : I
         L17
          RETURN
[5]_asm_procedurego_setturtlevariable_6 "set virus-check-timer 0" Object => void
      _constdouble:0.0 "0" => Double
          TRYCATCHBLOCK L0 L1 L2 org/nlogo/api/AgentException
         L3
          ALOAD 0
          GETFIELD org/nlogo/prim/_asm_procedurego_setturtlevariable_6.kept2_value : Ljava/lang/Double;
         L4
          ASTORE 2
         L0
          ALOAD 1
          GETFIELD org/nlogo/nvm/Context.agent : Lorg/nlogo/agent/Agent;
          BIPUSH 15
          ALOAD 2
          INVOKEVIRTUAL org/nlogo/agent/Agent.setTurtleVariable (ILjava/lang/Object;)V
         L1
          GOTO L5
         L2
         FRAME FULL [org/nlogo/prim/_asm_procedurego_setturtlevariable_6 org/nlogo/nvm/Context java/lang/Double] [org/nlogo/api/AgentException]
          ASTORE 3
          NEW org/nlogo/nvm/EngineException
          DUP
          ALOAD 1
          ALOAD 0
          ALOAD 3
          INVOKEVIRTUAL org/nlogo/api/AgentException.getMessage ()Ljava/lang/String;
          INVOKESPECIAL org/nlogo/nvm/EngineException.<init> (Lorg/nlogo/nvm/Context;Lorg/nlogo/nvm/Instruction;Ljava/lang/String;)V
          ATHROW
         L5
         FRAME SAME
          ALOAD 1
          BIPUSH 6
          PUTFIELD org/nlogo/nvm/Context.ip : I
         L6
          RETURN
[6]_asm_procedurego_done_7 => void
         L0
          ALOAD 1
          ICONST_1
          PUTFIELD org/nlogo/nvm/Context.finished : Z
         L1
          RETURN
[7]_asm_procedurego_call_8 "spread-virus"
         L0
          NEW org/nlogo/nvm/Activation
          DUP
          ALOAD 0
          GETFIELD org/nlogo/prim/_asm_procedurego_call_8.kept1_procedure : Lorg/nlogo/nvm/Procedure;
          ALOAD 1
          GETFIELD org/nlogo/nvm/Context.activation : Lorg/nlogo/nvm/Activation;
          BIPUSH 8
          INVOKESPECIAL org/nlogo/nvm/Activation.<init> (Lorg/nlogo/nvm/Procedure;Lorg/nlogo/nvm/Activation;I)V
          ALOAD 1
          SWAP
          PUTFIELD org/nlogo/nvm/Context.activation : Lorg/nlogo/nvm/Activation;
          ALOAD 1
          ICONST_0
          PUTFIELD org/nlogo/nvm/Context.ip : I
         L1
          RETURN
[8]_asm_procedurego_call_9 "do-virus-checks"
         L0
          NEW org/nlogo/nvm/Activation
          DUP
          ALOAD 0
          GETFIELD org/nlogo/prim/_asm_procedurego_call_9.kept1_procedure : Lorg/nlogo/nvm/Procedure;
          ALOAD 1
          GETFIELD org/nlogo/nvm/Context.activation : Lorg/nlogo/nvm/Activation;
          BIPUSH 9
          INVOKESPECIAL org/nlogo/nvm/Activation.<init> (Lorg/nlogo/nvm/Procedure;Lorg/nlogo/nvm/Activation;I)V
          ALOAD 1
          SWAP
          PUTFIELD org/nlogo/nvm/Context.activation : Lorg/nlogo/nvm/Activation;
          ALOAD 1
          ICONST_0
          PUTFIELD org/nlogo/nvm/Context.ip : I
         L1
          RETURN
[9]_tick "tick"
[10]_asm_procedurego_call_10 "update-plot"
         L0
          NEW org/nlogo/nvm/Activation
          DUP
          ALOAD 0
          GETFIELD org/nlogo/prim/_asm_procedurego_call_10.kept1_procedure : Lorg/nlogo/nvm/Procedure;
          ALOAD 1
          GETFIELD org/nlogo/nvm/Context.activation : Lorg/nlogo/nvm/Activation;
          BIPUSH 11
          INVOKESPECIAL org/nlogo/nvm/Activation.<init> (Lorg/nlogo/nvm/Procedure;Lorg/nlogo/nvm/Activation;I)V
          ALOAD 1
          SWAP
          PUTFIELD org/nlogo/nvm/Context.activation : Lorg/nlogo/nvm/Activation;
          ALOAD 1
          ICONST_0
          PUTFIELD org/nlogo/nvm/Context.ip : I
         L1
          RETURN
[11]_asm_procedurego_return_11 => void
         L0
          ALOAD 1
          INVOKEVIRTUAL org/nlogo/nvm/Context.returnFromProcedure ()V
          ALOAD 1
          ICONST_0
          PUTFIELD org/nlogo/nvm/Context.stopping : Z
         L1
          RETURN

procedure BECOME-SUSCEPTIBLE:[]{-T--}:
[0]_asm_procedurebecomesusceptible_setturtlevariable_0 "set infected? false" Object => void
      _constboolean:false "false" => Boolean
          TRYCATCHBLOCK L0 L1 L2 org/nlogo/api/AgentException
         L3
          ALOAD 0
          GETFIELD org/nlogo/prim/_asm_procedurebecomesusceptible_setturtlevariable_0.kept2_value : Ljava/lang/Boolean;
         L4
          ASTORE 2
         L0
          ALOAD 1
          GETFIELD org/nlogo/nvm/Context.agent : Lorg/nlogo/agent/Agent;
          BIPUSH 13
          ALOAD 2
          INVOKEVIRTUAL org/nlogo/agent/Agent.setTurtleVariable (ILjava/lang/Object;)V
         L1
          GOTO L5
         L2
         FRAME FULL [org/nlogo/prim/_asm_procedurebecomesusceptible_setturtlevariable_0 org/nlogo/nvm/Context java/lang/Boolean] [org/nlogo/api/AgentException]
          ASTORE 3
          NEW org/nlogo/nvm/EngineException
          DUP
          ALOAD 1
          ALOAD 0
          ALOAD 3
          INVOKEVIRTUAL org/nlogo/api/AgentException.getMessage ()Ljava/lang/String;
          INVOKESPECIAL org/nlogo/nvm/EngineException.<init> (Lorg/nlogo/nvm/Context;Lorg/nlogo/nvm/Instruction;Ljava/lang/String;)V
          ATHROW
         L5
         FRAME SAME
          ALOAD 1
          ICONST_1
          PUTFIELD org/nlogo/nvm/Context.ip : I
         L6
          RETURN
[1]_asm_procedurebecomesusceptible_setturtlevariable_1 "set resistant? false" Object => void
      _constboolean:false "false" => Boolean
          TRYCATCHBLOCK L0 L1 L2 org/nlogo/api/AgentException
         L3
          ALOAD 0
          GETFIELD org/nlogo/prim/_asm_procedurebecomesusceptible_setturtlevariable_1.kept2_value : Ljava/lang/Boolean;
         L4
          ASTORE 2
         L0
          ALOAD 1
          GETFIELD org/nlogo/nvm/Context.agent : Lorg/nlogo/agent/Agent;
          BIPUSH 14
          ALOAD 2
          INVOKEVIRTUAL org/nlogo/agent/Agent.setTurtleVariable (ILjava/lang/Object;)V
         L1
          GOTO L5
         L2
         FRAME FULL [org/nlogo/prim/_asm_procedurebecomesusceptible_setturtlevariable_1 org/nlogo/nvm/Context java/lang/Boolean] [org/nlogo/api/AgentException]
          ASTORE 3
          NEW org/nlogo/nvm/EngineException
          DUP
          ALOAD 1
          ALOAD 0
          ALOAD 3
          INVOKEVIRTUAL org/nlogo/api/AgentException.getMessage ()Ljava/lang/String;
          INVOKESPECIAL org/nlogo/nvm/EngineException.<init> (Lorg/nlogo/nvm/Context;Lorg/nlogo/nvm/Instruction;Ljava/lang/String;)V
          ATHROW
         L5
         FRAME SAME
          ALOAD 1
          ICONST_2
          PUTFIELD org/nlogo/nvm/Context.ip : I
         L6
          RETURN
[2]_asm_procedurebecomesusceptible_setturtleorlinkvariable_2 "set color green" Object => void
      _constdouble:55.0 "green" => Double
          TRYCATCHBLOCK L0 L1 L2 org/nlogo/api/AgentException
         L3
          ALOAD 0
          GETFIELD org/nlogo/prim/_asm_procedurebecomesusceptible_setturtleorlinkvariable_2.kept2_value : Ljava/lang/Double;
         L4
          ASTORE 2
         L0
          ALOAD 1
          GETFIELD org/nlogo/nvm/Context.agent : Lorg/nlogo/agent/Agent;
          LDC "COLOR"
          ALOAD 2
          INVOKEVIRTUAL org/nlogo/agent/Agent.setTurtleOrLinkVariable (Ljava/lang/String;Ljava/lang/Object;)V
         L1
          GOTO L5
         L2
         FRAME FULL [org/nlogo/prim/_asm_procedurebecomesusceptible_setturtleorlinkvariable_2 org/nlogo/nvm/Context java/lang/Double] [org/nlogo/api/AgentException]
          ASTORE 3
          NEW org/nlogo/nvm/EngineException
          DUP
          ALOAD 1
          ALOAD 0
          ALOAD 3
          INVOKEVIRTUAL org/nlogo/api/AgentException.getMessage ()Ljava/lang/String;
          INVOKESPECIAL org/nlogo/nvm/EngineException.<init> (Lorg/nlogo/nvm/Context;Lorg/nlogo/nvm/Instruction;Ljava/lang/String;)V
          ATHROW
         L5
         FRAME SAME
          ALOAD 1
          ICONST_3
          PUTFIELD org/nlogo/nvm/Context.ip : I
         L6
          RETURN
[3]_asm_procedurebecomesusceptible_return_3 => void
         L0
          ALOAD 1
          INVOKEVIRTUAL org/nlogo/nvm/Context.returnFromProcedure ()V
          ALOAD 1
          ICONST_0
          PUTFIELD org/nlogo/nvm/Context.stopping : Z
         L1
          RETURN

procedure SETUP-SPATIALLY-CLUSTERED-NETWORK:[NUM-LINKS _repeatlocal:1]{OTPL}:
[0]_asm_proceduresetupspatiallyclusterednetwork_setprocedurevariable_0 "let average-node-degree * number-of-nodes / 2" Object => void
      _div "average-node-degree * number-of-nodes / 2" double,double => double
        _mult "average-node-degree * number-of-nodes" double,double => double
          _observervariable:AVERAGE-NODE-DEGREE "average-node-degree" => Object
          _observervariable:NUMBER-OF-NODES "number-of-nodes" => Object
        _constdouble:2.0 "2" => double
          TRYCATCHBLOCK L0 L1 L1 java/lang/ClassCastException
          TRYCATCHBLOCK L2 L3 L3 java/lang/ClassCastException
         L4
          ALOAD 1
          GETFIELD org/nlogo/nvm/Context.agent : Lorg/nlogo/agent/Agent;
          BIPUSH 6
          INVOKEVIRTUAL org/nlogo/agent/Agent.getObserverVariable (I)Ljava/lang/Object;
         L5
          ASTORE 2
         L0
          ALOAD 2
          CHECKCAST java/lang/Double
          INVOKEVIRTUAL java/lang/Double.doubleValue ()D
          GOTO L6
         L1
         FRAME FULL [org/nlogo/prim/_asm_proceduresetupspatiallyclusterednetwork_setprocedurevariable_0 org/nlogo/nvm/Context java/lang/Object] [java/lang/ClassCastException]
          POP
          NEW org/nlogo/nvm/ArgumentTypeException
          DUP
          ALOAD 1
          ALOAD 0
          BIPUSH 0
          LDC 1
          ALOAD 2
          INVOKESPECIAL org/nlogo/nvm/ArgumentTypeException.<init> (Lorg/nlogo/nvm/Context;Lorg/nlogo/nvm/Instruction;IILjava/lang/Object;)V
          ATHROW
         L6
         FRAME SAME1 D
          ALOAD 1
          GETFIELD org/nlogo/nvm/Context.agent : Lorg/nlogo/agent/Agent;
          ICONST_3
          INVOKEVIRTUAL org/nlogo/agent/Agent.getObserverVariable (I)Ljava/lang/Object;
         L7
          ASTORE 2
         L2
          ALOAD 2
          CHECKCAST java/lang/Double
          INVOKEVIRTUAL java/lang/Double.doubleValue ()D
          GOTO L8
         L3
         FRAME SAME1 java/lang/ClassCastException
          POP
          NEW org/nlogo/nvm/ArgumentTypeException
          DUP
          ALOAD 1
          ALOAD 0
          BIPUSH 1
          LDC 1
          ALOAD 2
          INVOKESPECIAL org/nlogo/nvm/ArgumentTypeException.<init> (Lorg/nlogo/nvm/Context;Lorg/nlogo/nvm/Instruction;IILjava/lang/Object;)V
          ATHROW
         L8
         FRAME FULL [org/nlogo/prim/_asm_proceduresetupspatiallyclusterednetwork_setprocedurevariable_0 org/nlogo/nvm/Context java/lang/Object] [D D]
          DSTORE 4
          DSTORE 2
          ALOAD 0
          DLOAD 2
          DLOAD 4
          DMUL
          INVOKEVIRTUAL org/nlogo/prim/_asm_proceduresetupspatiallyclusterednetwork_setprocedurevariable_0.validDouble (D)D
         L9
          LDC 2.0
         L10
          DSTORE 4
          DSTORE 2
          DLOAD 4
          DCONST_0
          DCMPL
          IFNE L11
          NEW org/nlogo/nvm/EngineException
          DUP
          ALOAD 1
          ALOAD 0
          INVOKESTATIC org/nlogo/core/I18N.errorsJ ()Lorg/nlogo/core/I18NJava;
          LDC "org.nlogo.prim.etc.$common.divByZero"
          INVOKEINTERFACE org/nlogo/core/I18NJava.get (Ljava/lang/String;)Ljava/lang/String;
          INVOKESPECIAL org/nlogo/nvm/EngineException.<init> (Lorg/nlogo/nvm/Context;Lorg/nlogo/nvm/Instruction;Ljava/lang/String;)V
          ATHROW
         L11
         FRAME FULL [org/nlogo/prim/_asm_proceduresetupspatiallyclusterednetwork_setprocedurevariable_0 org/nlogo/nvm/Context D D] []
          ALOAD 0
          DLOAD 2
          DLOAD 4
          DDIV
          INVOKEVIRTUAL org/nlogo/prim/_asm_proceduresetupspatiallyclusterednetwork_setprocedurevariable_0.validDouble (D)D
         L12
          DSTORE 2
          NEW java/lang/Double
          DUP
          DLOAD 2
          INVOKESPECIAL java/lang/Double.<init> (D)V
          ASTORE 2
          ALOAD 1
          GETFIELD org/nlogo/nvm/Context.activation : Lorg/nlogo/nvm/Activation;
          GETFIELD org/nlogo/nvm/Activation.args : [Ljava/lang/Object;
          ICONST_0
          ALOAD 2
          AASTORE
          ALOAD 1
          ICONST_1
          PUTFIELD org/nlogo/nvm/Context.ip : I
         L13
          RETURN
[1]_asm_proceduresetupspatiallyclusterednetwork_goto_1 => void
         L0
          ALOAD 1
          BIPUSH 8
          PUTFIELD org/nlogo/nvm/Context.ip : I
         L1
          RETURN
[2]_asm_proceduresetupspatiallyclusterednetwork_ask_2 "ask one-of turtles let min-one-of other turtles with [ not link-neighbor? myself ] [ distance myself ] [ if choice != nobody [ create-link-with [ choice ] ] ]" Object => void
      _oneof "one-of turtles" AgentSet => Object
        _turtles "turtles" => AgentSet
         L0
          ALOAD 0
          GETFIELD org/nlogo/prim/_asm_proceduresetupspatiallyclusterednetwork_ask_2.world : Lorg/nlogo/agent/World;
          INVOKEVIRTUAL org/nlogo/agent/World.turtles ()Lorg/nlogo/agent/AgentSet;
         L1
          ASTORE 2
          ALOAD 2
          INVOKEVIRTUAL org/nlogo/agent/AgentSet.count ()I
          ISTORE 3
          ILOAD 3
          IFNE L2
          GETSTATIC org/nlogo/core/Nobody$.MODULE$ : Lorg/nlogo/core/Nobody$;
          GOTO L3
         L2
         FRAME APPEND [org/nlogo/agent/AgentSet I]
          ALOAD 2
          ILOAD 3
          ALOAD 1
          GETFIELD org/nlogo/nvm/Context.job : Lorg/nlogo/nvm/Job;
          GETFIELD org/nlogo/nvm/Job.random : Lorg/nlogo/api/MersenneTwisterFast;
          ILOAD 3
          INVOKEVIRTUAL org/nlogo/api/MersenneTwisterFast.nextInt (I)I
          INVOKEVIRTUAL org/nlogo/agent/AgentSet.randomOne (II)Lorg/nlogo/agent/Agent;
         L3
         FRAME SAME1 java/lang/Object
          ASTORE 2
          ALOAD 2
          INSTANCEOF org/nlogo/agent/AgentSet
          IFEQ L4
          ALOAD 2
          CHECKCAST org/nlogo/agent/AgentSet
          ASTORE 3
          ALOAD 1
          GETFIELD org/nlogo/nvm/Context.agent : Lorg/nlogo/agent/Agent;
          INSTANCEOF org/nlogo/agent/Observer
          IFNE L5
          ALOAD 3
          ALOAD 0
          GETFIELD org/nlogo/prim/_asm_proceduresetupspatiallyclusterednetwork_ask_2.world : Lorg/nlogo/agent/World;
          INVOKEVIRTUAL org/nlogo/agent/World.turtles ()Lorg/nlogo/agent/AgentSet;
          IF_ACMPNE L6
          NEW org/nlogo/nvm/EngineException
          DUP
          ALOAD 1
          ALOAD 0
          INVOKESTATIC org/nlogo/core/I18N.errorsJ ()Lorg/nlogo/core/I18NJava;
          LDC "org.nlogo.prim.$common.onlyObserverCanAskAllTurtles"
          INVOKEINTERFACE org/nlogo/core/I18NJava.get (Ljava/lang/String;)Ljava/lang/String;
          INVOKESPECIAL org/nlogo/nvm/EngineException.<init> (Lorg/nlogo/nvm/Context;Lorg/nlogo/nvm/Instruction;Ljava/lang/String;)V
          ATHROW
         L6
         FRAME FULL [org/nlogo/prim/_asm_proceduresetupspatiallyclusterednetwork_ask_2 org/nlogo/nvm/Context java/lang/Object org/nlogo/agent/AgentSet] []
          ALOAD 3
          ALOAD 0
          GETFIELD org/nlogo/prim/_asm_proceduresetupspatiallyclusterednetwork_ask_2.world : Lorg/nlogo/agent/World;
          INVOKEVIRTUAL org/nlogo/agent/World.patches ()Lorg/nlogo/agent/AgentSet;
          IF_ACMPNE L5
          NEW org/nlogo/nvm/EngineException
          DUP
          ALOAD 1
          ALOAD 0
          INVOKESTATIC org/nlogo/core/I18N.errorsJ ()Lorg/nlogo/core/I18NJava;
          LDC "org.nlogo.prim.$common.onlyObserverCanAskAllPatches"
          INVOKEINTERFACE org/nlogo/core/I18NJava.get (Ljava/lang/String;)Ljava/lang/String;
          INVOKESPECIAL org/nlogo/nvm/EngineException.<init> (Lorg/nlogo/nvm/Context;Lorg/nlogo/nvm/Instruction;Ljava/lang/String;)V
          ATHROW
         L4
         FRAME FULL [org/nlogo/prim/_asm_proceduresetupspatiallyclusterednetwork_ask_2 org/nlogo/nvm/Context java/lang/Object I] []
          ALOAD 2
          INSTANCEOF org/nlogo/agent/Agent
          IFEQ L7
          ALOAD 2
          CHECKCAST org/nlogo/agent/Agent
          ASTORE 4
          ALOAD 4
          GETFIELD org/nlogo/agent/Agent.id : J
          LDC -1
          LCMP
          IFNE L8
          NEW org/nlogo/nvm/EngineException
          DUP
          ALOAD 1
          ALOAD 0
          INVOKESTATIC org/nlogo/core/I18N.errorsJ ()Lorg/nlogo/core/I18NJava;
          LDC "org.nlogo.$common.thatAgentIsDead"
          ICONST_1
          ANEWARRAY java/lang/Object
          DUP
          ICONST_0
          ALOAD 4
          INVOKEVIRTUAL org/nlogo/agent/Agent.classDisplayName ()Ljava/lang/String;
          AASTORE
          INVOKEINTERFACE org/nlogo/core/I18NJava.getN (Ljava/lang/String;[Ljava/lang/Object;)Ljava/lang/String;
          INVOKESPECIAL org/nlogo/nvm/EngineException.<init> (Lorg/nlogo/nvm/Context;Lorg/nlogo/nvm/Instruction;Ljava/lang/String;)V
          ATHROW
         L8
         FRAME APPEND [org/nlogo/agent/Agent]
          NEW org/nlogo/agent/ArrayAgentSet
          DUP
          ALOAD 4
          INVOKEVIRTUAL org/nlogo/agent/Agent.kind ()Lorg/nlogo/core/AgentKind;
          ICONST_1
          ICONST_0
          INVOKESPECIAL org/nlogo/agent/ArrayAgentSet.<init> (Lorg/nlogo/core/AgentKind;IZ)V
          ASTORE 3
          ALOAD 3
          ALOAD 4
          INVOKEVIRTUAL org/nlogo/agent/AgentSet.add (Lorg/nlogo/agent/Agent;)V
          GOTO L5
         L7
         FRAME CHOP 1
          NEW org/nlogo/nvm/ArgumentTypeException
          DUP
          ALOAD 1
          ALOAD 0
          ICONST_0
          INVOKESTATIC org/nlogo/core/Syntax.AgentsetType ()I
          INVOKESTATIC org/nlogo/core/Syntax.AgentType ()I
          IOR
          ALOAD 2
          INVOKESPECIAL org/nlogo/nvm/ArgumentTypeException.<init> (Lorg/nlogo/nvm/Context;Lorg/nlogo/nvm/Instruction;IILjava/lang/Object;)V
          ATHROW
         L5
         FRAME FULL [org/nlogo/prim/_asm_proceduresetupspatiallyclusterednetwork_ask_2 org/nlogo/nvm/Context java/lang/Object org/nlogo/agent/AgentSet] []
          ALOAD 1
          ALOAD 3
          ICONST_3
          INVOKEVIRTUAL org/nlogo/nvm/Context.runExclusiveJob (Lorg/nlogo/agent/AgentSet;I)V
          ALOAD 1
          BIPUSH 8
          PUTFIELD org/nlogo/nvm/Context.ip : I
         L9
          RETURN
[3]_let "let min-one-of other turtles with [ not link-neighbor? myself ] [ distance myself ]"
      _minoneof "min-one-of other turtles with [ not link-neighbor? myself ] [ distance myself ]"
        _asm_proceduresetupspatiallyclusterednetwork_otherwith_3 "other turtles with [ not link-neighbor? myself ]" AgentSet,Reporter => AgentSet
          _turtles "turtles" => AgentSet
          _asm_proceduresetupspatiallyclusterednetwork_not_4 "not link-neighbor? myself" boolean => boolean
            _linkneighbor:null "link-neighbor? myself" Turtle => boolean
              _myself "myself" => Agent
                TRYCATCHBLOCK L0 L1 L1 java/lang/ClassCastException
               L2
                ALOAD 1
                INVOKEVIRTUAL org/nlogo/nvm/Context.myself ()Lorg/nlogo/agent/Agent;
                ASTORE 2
                ALOAD 2
                IFNULL L3
                ALOAD 2
                INSTANCEOF org/nlogo/agent/Observer
                IFEQ L4
               L3
               FRAME APPEND [org/nlogo/agent/Agent]
                NEW org/nlogo/nvm/EngineException
                DUP
                ALOAD 1
                ALOAD 0
                INVOKESTATIC org/nlogo/core/I18N.errorsJ ()Lorg/nlogo/core/I18NJava;
                LDC "org.nlogo.prim.etc._myself.noAgentMyself"
                INVOKEINTERFACE org/nlogo/core/I18NJava.get (Ljava/lang/String;)Ljava/lang/String;
                INVOKESPECIAL org/nlogo/nvm/EngineException.<init> (Lorg/nlogo/nvm/Context;Lorg/nlogo/nvm/Instruction;Ljava/lang/String;)V
                ATHROW
               L4
               FRAME SAME
                ALOAD 2
               L5
                ASTORE 2
               L0
                ALOAD 2
                CHECKCAST org/nlogo/agent/Turtle
                GOTO L6
               L1
               FRAME SAME1 java/lang/ClassCastException
                POP
                NEW org/nlogo/nvm/ArgumentTypeException
                DUP
                ALOAD 1
                ALOAD 0
                BIPUSH 0
                LDC 1792
                ALOAD 2
                INVOKESPECIAL org/nlogo/nvm/ArgumentTypeException.<init> (Lorg/nlogo/nvm/Context;Lorg/nlogo/nvm/Instruction;IILjava/lang/Object;)V
                ATHROW
               L6
               FRAME SAME1 org/nlogo/agent/Turtle
                ASTORE 2
                ALOAD 1
                GETFIELD org/nlogo/nvm/Context.agent : Lorg/nlogo/agent/Agent;
                CHECKCAST org/nlogo/agent/Turtle
                ASTORE 3
                ALOAD 0
                GETFIELD org/nlogo/prim/_asm_proceduresetupspatiallyclusterednetwork_not_4.kept2_breedName : Ljava/lang/String;
                IFNONNULL L7
                ALOAD 0
                GETFIELD org/nlogo/prim/_asm_proceduresetupspatiallyclusterednetwork_not_4.world : Lorg/nlogo/agent/World;
                INVOKEVIRTUAL org/nlogo/agent/World.links ()Lorg/nlogo/agent/AgentSet;
                GOTO L8
               L7
               FRAME FULL [org/nlogo/prim/_asm_proceduresetupspatiallyclusterednetwork_not_4 org/nlogo/nvm/Context org/nlogo/agent/Turtle org/nlogo/agent/Turtle] []
                ALOAD 0
                GETFIELD org/nlogo/prim/_asm_proceduresetupspatiallyclusterednetwork_not_4.world : Lorg/nlogo/agent/World;
                ALOAD 0
                GETFIELD org/nlogo/prim/_asm_proceduresetupspatiallyclusterednetwork_not_4.kept2_breedName : Ljava/lang/String;
                INVOKEVIRTUAL org/nlogo/agent/World.getLinkBreed (Ljava/lang/String;)Lorg/nlogo/agent/AgentSet;
               L8
               FRAME SAME1 org/nlogo/agent/AgentSet
                ASTORE 4
                ALOAD 0
                ALOAD 4
                ALOAD 1
                INVOKEVIRTUAL org/nlogo/prim/_asm_proceduresetupspatiallyclusterednetwork_not_4.mustNotBeDirected (Lorg/nlogo/agent/AgentSet;Lorg/nlogo/nvm/Context;)V
                ALOAD 0
                GETFIELD org/nlogo/prim/_asm_proceduresetupspatiallyclusterednetwork_not_4.world : Lorg/nlogo/agent/World;
                GETFIELD org/nlogo/agent/World.linkManager : Lorg/nlogo/agent/LinkManager;
                ASTORE 5
                ALOAD 5
                ALOAD 3
                ALOAD 2
                ALOAD 4
                ICONST_1
                INVOKEVIRTUAL org/nlogo/agent/LinkManager.findLinkEitherWay (Lorg/nlogo/agent/Turtle;Lorg/nlogo/agent/Turtle;Lorg/nlogo/agent/AgentSet;Z)Lorg/nlogo/agent/Link;
                ASTORE 6
                ALOAD 6
                IFNULL L9
                ALOAD 6
                INVOKEVIRTUAL org/nlogo/agent/Link.isDirectedLink ()Z
                IFEQ L10
               L9
               FRAME APPEND [org/nlogo/agent/AgentSet org/nlogo/agent/LinkManager org/nlogo/agent/Link]
                ICONST_0
                GOTO L11
               L10
               FRAME SAME
                ICONST_1
               L11
               FRAME SAME1 I
                ISTORE 2
                ILOAD 2
                IFNE L12
                ICONST_1
                GOTO L13
               L12
               FRAME FULL [org/nlogo/prim/_asm_proceduresetupspatiallyclusterednetwork_not_4 org/nlogo/nvm/Context I org/nlogo/agent/Turtle org/nlogo/agent/AgentSet org/nlogo/agent/LinkManager org/nlogo/agent/Link] []
                ICONST_0
               L13
               FRAME SAME1 I
                IFEQ L14
                GETSTATIC java/lang/Boolean.TRUE : Ljava/lang/Boolean;
                GOTO L15
               L14
               FRAME SAME
                GETSTATIC java/lang/Boolean.FALSE : Ljava/lang/Boolean;
               L15
               FRAME SAME1 java/lang/Boolean
                ARETURN
             L0
              ALOAD 0
              GETFIELD org/nlogo/prim/_asm_proceduresetupspatiallyclusterednetwork_otherwith_3.world : Lorg/nlogo/agent/World;
              INVOKEVIRTUAL org/nlogo/agent/World.turtles ()Lorg/nlogo/agent/AgentSet;
             L1
              ALOAD 0
              GETFIELD org/nlogo/prim/_asm_proceduresetupspatiallyclusterednetwork_otherwith_3.keptinstr3 : Lorg/nlogo/nvm/Reporter;
              ASTORE 3
              ASTORE 2
              NEW org/nlogo/nvm/Context
              DUP
              ALOAD 1
              ALOAD 2
              INVOKESPECIAL org/nlogo/nvm/Context.<init> (Lorg/nlogo/nvm/Context;Lorg/nlogo/agent/AgentSet;)V
              ASTORE 4
              NEW java/util/ArrayList
              DUP
              INVOKESPECIAL java/util/ArrayList.<init> ()V
              ASTORE 5
              ALOAD 3
              ALOAD 2
              ALOAD 1
              INVOKEVIRTUAL org/nlogo/nvm/Reporter.checkAgentSetClass (Lorg/nlogo/agent/AgentSet;Lorg/nlogo/nvm/Context;)V
              ALOAD 2
              INVOKEVIRTUAL org/nlogo/agent/AgentSet.iterator ()Lorg/nlogo/agent/AgentSet$Iterator;
              ASTORE 6
             L2
             FRAME FULL [org/nlogo/prim/_asm_proceduresetupspatiallyclusterednetwork_otherwith_3 org/nlogo/nvm/Context org/nlogo/agent/AgentSet org/nlogo/nvm/Reporter org/nlogo/nvm/Context java/util/ArrayList org/nlogo/agent/AgentSet$Iterator] []
              ALOAD 6
              INVOKEINTERFACE org/nlogo/agent/AgentSet$Iterator.hasNext ()Z
              IFEQ L3
              ALOAD 6
              INVOKEINTERFACE org/nlogo/agent/AgentSet$Iterator.next ()Lorg/nlogo/agent/Agent;
              ASTORE 7
              ALOAD 7
              ALOAD 1
              GETFIELD org/nlogo/nvm/Context.agent : Lorg/nlogo/agent/Agent;
              IF_ACMPNE L4
              GOTO L2
             L4
             FRAME APPEND [org/nlogo/agent/Agent]
              ALOAD 4
              ALOAD 7
              ALOAD 3
              INVOKEVIRTUAL org/nlogo/nvm/Context.evaluateReporter (Lorg/nlogo/agent/Agent;Lorg/nlogo/nvm/Reporter;)Ljava/lang/Object;
              ASTORE 8
              ALOAD 8
              INSTANCEOF java/lang/Boolean
              IFNE L5
              NEW org/nlogo/nvm/EngineException
              DUP
              ALOAD 1
              ALOAD 0
              INVOKESTATIC org/nlogo/core/I18N.errorsJ ()Lorg/nlogo/core/I18NJava;
              LDC "org.nlogo.prim.$common.expectedBooleanValue"
              ICONST_3
              ANEWARRAY java/lang/Object
              DUP
              ICONST_0
              LDC "OTHER"
              AASTORE
              DUP
              ICONST_1
              ALOAD 7
              INVOKESTATIC org/nlogo/api/Dump.logoObject (Ljava/lang/Object;)Ljava/lang/String;
              AASTORE
              DUP
              ICONST_2
              ALOAD 8
              INVOKESTATIC org/nlogo/api/Dump.logoObject (Ljava/lang/Object;)Ljava/lang/String;
              AASTORE
              INVOKEINTERFACE org/nlogo/core/I18NJava.getN (Ljava/lang/String;[Ljava/lang/Object;)Ljava/lang/String;
              INVOKESPECIAL org/nlogo/nvm/EngineException.<init> (Lorg/nlogo/nvm/Context;Lorg/nlogo/nvm/Instruction;Ljava/lang/String;)V
              ATHROW
             L5
             FRAME APPEND [java/lang/Object]
              ALOAD 8
              CHECKCAST java/lang/Boolean
              INVOKEVIRTUAL java/lang/Boolean.booleanValue ()Z
              IFEQ L6
              ALOAD 5
              ALOAD 7
              INVOKEINTERFACE java/util/List.add (Ljava/lang/Object;)Z
              POP
             L6
             FRAME SAME
              GOTO L2
             L3
             FRAME CHOP 2
              NEW org/nlogo/agent/ArrayAgentSet
              DUP
              ALOAD 2
              INVOKEVIRTUAL org/nlogo/agent/AgentSet.kind ()Lorg/nlogo/core/AgentKind;
              ALOAD 5
              ALOAD 5
              INVOKEINTERFACE java/util/List.size ()I
              ANEWARRAY org/nlogo/agent/Agent
              INVOKEINTERFACE java/util/List.toArray ([Ljava/lang/Object;)[Ljava/lang/Object;
              CHECKCAST [Lorg/nlogo/agent/Agent;
              INVOKESPECIAL org/nlogo/agent/ArrayAgentSet.<init> (Lorg/nlogo/core/AgentKind;[Lorg/nlogo/agent/Agent;)V
             L7
              ARETURN
        _asm_proceduresetupspatiallyclusterednetwork_distance_5 "distance myself" Agent => double
          _myself "myself" => Agent
             L0
              ALOAD 1
              INVOKEVIRTUAL org/nlogo/nvm/Context.myself ()Lorg/nlogo/agent/Agent;
              ASTORE 2
              ALOAD 2
              IFNULL L1
              ALOAD 2
              INSTANCEOF org/nlogo/agent/Observer
              IFEQ L2
             L1
             FRAME APPEND [org/nlogo/agent/Agent]
              NEW org/nlogo/nvm/EngineException
              DUP
              ALOAD 1
              ALOAD 0
              INVOKESTATIC org/nlogo/core/I18N.errorsJ ()Lorg/nlogo/core/I18NJava;
              LDC "org.nlogo.prim.etc._myself.noAgentMyself"
              INVOKEINTERFACE org/nlogo/core/I18NJava.get (Ljava/lang/String;)Ljava/lang/String;
              INVOKESPECIAL org/nlogo/nvm/EngineException.<init> (Lorg/nlogo/nvm/Context;Lorg/nlogo/nvm/Instruction;Ljava/lang/String;)V
              ATHROW
             L2
             FRAME SAME
              ALOAD 2
             L3
              ASTORE 2
              ALOAD 2
              INSTANCEOF org/nlogo/agent/Link
              IFEQ L4
              NEW org/nlogo/nvm/EngineException
              DUP
              ALOAD 1
              ALOAD 0
              INVOKESTATIC org/nlogo/core/I18N.errorsJ ()Lorg/nlogo/core/I18NJava;
              LDC "org.nlogo.prim.etc.$common.expectedTurtleOrPatchButGotLink"
              INVOKEINTERFACE org/nlogo/core/I18NJava.get (Ljava/lang/String;)Ljava/lang/String;
              INVOKESPECIAL org/nlogo/nvm/EngineException.<init> (Lorg/nlogo/nvm/Context;Lorg/nlogo/nvm/Instruction;Ljava/lang/String;)V
              ATHROW
             L4
             FRAME SAME
              ALOAD 2
              GETFIELD org/nlogo/agent/Agent.id : J
              LDC -1
              LCMP
              IFNE L5
              NEW org/nlogo/nvm/EngineException
              DUP
              ALOAD 1
              ALOAD 0
              INVOKESTATIC org/nlogo/core/I18N.errorsJ ()Lorg/nlogo/core/I18NJava;
              LDC "org.nlogo.$common.thatAgentIsDead"
              ICONST_1
              ANEWARRAY java/lang/Object
              DUP
              ICONST_0
              ALOAD 2
              INVOKEVIRTUAL org/nlogo/agent/Agent.classDisplayName ()Ljava/lang/String;
              AASTORE
              INVOKEINTERFACE org/nlogo/core/I18NJava.getN (Ljava/lang/String;[Ljava/lang/Object;)Ljava/lang/String;
              INVOKESPECIAL org/nlogo/nvm/EngineException.<init> (Lorg/nlogo/nvm/Context;Lorg/nlogo/nvm/Instruction;Ljava/lang/String;)V
              ATHROW
             L5
             FRAME SAME
              ALOAD 0
              GETFIELD org/nlogo/prim/_asm_proceduresetupspatiallyclusterednetwork_distance_5.world : Lorg/nlogo/agent/World;
              INVOKEVIRTUAL org/nlogo/agent/World.protractor ()Lorg/nlogo/agent/Protractor;
              ALOAD 1
              GETFIELD org/nlogo/nvm/Context.agent : Lorg/nlogo/agent/Agent;
              ALOAD 2
              ICONST_1
              INVOKEVIRTUAL org/nlogo/agent/Protractor.distance (Lorg/nlogo/api/Agent;Lorg/nlogo/api/Agent;Z)D
             L6
              DSTORE 2
              NEW java/lang/Double
              DUP
              DLOAD 2
              INVOKESPECIAL java/lang/Double.<init> (D)V
              ARETURN
[4]_asm_proceduresetupspatiallyclusterednetwork_if_6 "if choice != nobody [ create-link-with [ choice ] ]" boolean => void
      _notequal "choice != nobody" Object,Object => boolean
        _letvariable(CHOICE) "choice" => Object
        _nobody "nobody" => Nobody$
         L0
          ALOAD 1
          ALOAD 0
          GETFIELD org/nlogo/prim/_asm_proceduresetupspatiallyclusterednetwork_if_6.kept3_let : Lorg/nlogo/core/Let;
          INVOKEVIRTUAL org/nlogo/nvm/Context.getLet (Lorg/nlogo/core/Let;)Ljava/lang/Object;
         L1
          GETSTATIC org/nlogo/core/Nobody$.MODULE$ : Lorg/nlogo/core/Nobody$;
         L2
          ASTORE 3
          ASTORE 2
          ALOAD 2
          ALOAD 3
          INVOKESTATIC org/nlogo/api/Equality.equals (Ljava/lang/Object;Ljava/lang/Object;)Z
          IFNE L3
          ICONST_1
          GOTO L4
         L3
         FRAME APPEND [java/lang/Object org/nlogo/core/Nobody$]
          ICONST_0
         L4
         FRAME SAME1 I
          ISTORE 2
          ALOAD 1
          ILOAD 2
          IFEQ L5
          ICONST_5
          GOTO L6
         L5
         FRAME FULL [org/nlogo/prim/_asm_proceduresetupspatiallyclusterednetwork_if_6 org/nlogo/nvm/Context I org/nlogo/core/Nobody$] [org/nlogo/nvm/Context]
          BIPUSH 7
         L6
         FRAME FULL [org/nlogo/prim/_asm_proceduresetupspatiallyclusterednetwork_if_6 org/nlogo/nvm/Context I org/nlogo/core/Nobody$] [org/nlogo/nvm/Context I]
          PUTFIELD org/nlogo/nvm/Context.ip : I
         L7
          RETURN
[5]_createlinkwith:null,+7 "create-link-with [ choice ]"
      _asm_proceduresetupspatiallyclusterednetwork_letvariable_7 "choice" => Object
           L0
            ALOAD 1
            ALOAD 0
            GETFIELD org/nlogo/prim/_asm_proceduresetupspatiallyclusterednetwork_letvariable_7.kept1_let : Lorg/nlogo/core/Let;
            INVOKEVIRTUAL org/nlogo/nvm/Context.getLet (Lorg/nlogo/core/Let;)Ljava/lang/Object;
           L1
            ARETURN
[6]_asm_proceduresetupspatiallyclusterednetwork_done_8 => void
         L0
          ALOAD 1
          ICONST_1
          PUTFIELD org/nlogo/nvm/Context.finished : Z
         L1
          RETURN
[7]_asm_proceduresetupspatiallyclusterednetwork_done_9 => void
         L0
          ALOAD 1
          ICONST_1
          PUTFIELD org/nlogo/nvm/Context.finished : Z
         L1
          RETURN
[8]_asm_proceduresetupspatiallyclusterednetwork_while_10 "while [ count links < num-links ] [ ask one-of turtles let min-one-of other turtles with [ not link-neighbor? myself ] [ distance myself ] [ if choice != nobody [ create-link-with [ choice ] ] ] ]" boolean => void
      _lessthan "count links < num-links" double,Object => boolean
        _count "count links" AgentSet => double
          _links "links" => AgentSet
        _procedurevariable:NUM-LINKS "num-links" => Object
         L0
          ALOAD 0
          GETFIELD org/nlogo/prim/_asm_proceduresetupspatiallyclusterednetwork_while_10.world : Lorg/nlogo/agent/World;
          INVOKEVIRTUAL org/nlogo/agent/World.links ()Lorg/nlogo/agent/AgentSet;
         L1
          ASTORE 2
          ALOAD 2
          INVOKEVIRTUAL org/nlogo/agent/AgentSet.count ()I
          I2D
         L2
          ALOAD 1
          GETFIELD org/nlogo/nvm/Context.activation : Lorg/nlogo/nvm/Activation;
          GETFIELD org/nlogo/nvm/Activation.args : [Ljava/lang/Object;
          ICONST_0
          AALOAD
         L3
          ASTORE 4
          DSTORE 2
          ALOAD 4
          INSTANCEOF java/lang/Double
          IFEQ L4
          DLOAD 2
          ALOAD 4
          CHECKCAST java/lang/Double
          INVOKEVIRTUAL java/lang/Double.doubleValue ()D
          DCMPG
          IFGE L5
          ICONST_1
          GOTO L6
         L5
         FRAME APPEND [D java/lang/Object]
          ICONST_0
         L6
         FRAME SAME1 I
          GOTO L7
         L4
         FRAME SAME
          NEW org/nlogo/nvm/EngineException
          DUP
          ALOAD 1
          ALOAD 0
          INVOKESTATIC org/nlogo/core/I18N.errorsJ ()Lorg/nlogo/core/I18NJava;
          LDC "org.nlogo.prim._lessthan.cantUseLessthanOnDifferentArgs"
          ICONST_2
          ANEWARRAY java/lang/Object
          DUP
          ICONST_0
          DLOAD 2
          INVOKESTATIC java/lang/Double.valueOf (D)Ljava/lang/Double;
          INVOKESTATIC org/nlogo/api/TypeNames.aName (Ljava/lang/Object;)Ljava/lang/String;
          AASTORE
          DUP
          ICONST_1
          ALOAD 4
          INVOKESTATIC org/nlogo/api/TypeNames.aName (Ljava/lang/Object;)Ljava/lang/String;
          AASTORE
          INVOKEINTERFACE org/nlogo/core/I18NJava.getN (Ljava/lang/String;[Ljava/lang/Object;)Ljava/lang/String;
          INVOKESPECIAL org/nlogo/nvm/EngineException.<init> (Lorg/nlogo/nvm/Context;Lorg/nlogo/nvm/Instruction;Ljava/lang/String;)V
          ATHROW
         L7
         FRAME SAME1 I
          ISTORE 2
          ALOAD 1
          ILOAD 2
          IFEQ L8
          ICONST_2
          GOTO L9
         L8
         FRAME FULL [org/nlogo/prim/_asm_proceduresetupspatiallyclusterednetwork_while_10 org/nlogo/nvm/Context I T java/lang/Object] [org/nlogo/nvm/Context]
          BIPUSH 9
         L9
         FRAME FULL [org/nlogo/prim/_asm_proceduresetupspatiallyclusterednetwork_while_10 org/nlogo/nvm/Context I T java/lang/Object] [org/nlogo/nvm/Context I]
          PUTFIELD org/nlogo/nvm/Context.ip : I
         L10
          RETURN
[9]_asm_proceduresetupspatiallyclusterednetwork_repeatlocal_11 "repeat 10 [ layout-spring turtles links 0.3 world-width / sqrt number-of-nodes 1 ]" double => void
      _constdouble:10.0 "10" => double
         L0
          LDC 10.0
         L1
          DSTORE 2
          ALOAD 1
          GETFIELD org/nlogo/nvm/Context.activation : Lorg/nlogo/nvm/Activation;
          GETFIELD org/nlogo/nvm/Activation.args : [Ljava/lang/Object;
          ICONST_1
          NEW org/nlogo/nvm/MutableLong
          DUP
          ALOAD 0
          DLOAD 2
          INVOKEVIRTUAL org/nlogo/prim/_asm_proceduresetupspatiallyclusterednetwork_repeatlocal_11.validLong (D)J
          INVOKESPECIAL org/nlogo/nvm/MutableLong.<init> (J)V
          AASTORE
          ALOAD 1
          BIPUSH 11
          PUTFIELD org/nlogo/nvm/Context.ip : I
         L2
          RETURN
[10]_layoutspring "layout-spring turtles links 0.3 world-width / sqrt number-of-nodes 1"
      _asm_proceduresetupspatiallyclusterednetwork_turtles_12 "turtles" => AgentSet
           L0
            ALOAD 0
            GETFIELD org/nlogo/prim/_asm_proceduresetupspatiallyclusterednetwork_turtles_12.world : Lorg/nlogo/agent/World;
            INVOKEVIRTUAL org/nlogo/agent/World.turtles ()Lorg/nlogo/agent/AgentSet;
           L1
            ARETURN
      _asm_proceduresetupspatiallyclusterednetwork_links_13 "links" => AgentSet
           L0
            ALOAD 0
            GETFIELD org/nlogo/prim/_asm_proceduresetupspatiallyclusterednetwork_links_13.world : Lorg/nlogo/agent/World;
            INVOKEVIRTUAL org/nlogo/agent/World.links ()Lorg/nlogo/agent/AgentSet;
           L1
            ARETURN
      _asm_proceduresetupspatiallyclusterednetwork_constdouble_14 "0.3" => Double
           L0
            ALOAD 0
            GETFIELD org/nlogo/prim/_asm_proceduresetupspatiallyclusterednetwork_constdouble_14.kept1_value : Ljava/lang/Double;
           L1
            ARETURN
      _asm_proceduresetupspatiallyclusterednetwork_div_15 "world-width / sqrt number-of-nodes" double,double => double
        _worldwidth "world-width" => double
        _sqrt "sqrt number-of-nodes" double => double
          _observervariable:NUMBER-OF-NODES "number-of-nodes" => Object
            TRYCATCHBLOCK L0 L1 L1 java/lang/ClassCastException
           L2
            ALOAD 0
            GETFIELD org/nlogo/prim/_asm_proceduresetupspatiallyclusterednetwork_div_15.world : Lorg/nlogo/agent/World;
            INVOKEVIRTUAL org/nlogo/agent/World.worldWidth ()I
            I2D
           L3
            ALOAD 1
            GETFIELD org/nlogo/nvm/Context.agent : Lorg/nlogo/agent/Agent;
            ICONST_3
            INVOKEVIRTUAL org/nlogo/agent/Agent.getObserverVariable (I)Ljava/lang/Object;
           L4
            ASTORE 2
           L0
            ALOAD 2
            CHECKCAST java/lang/Double
            INVOKEVIRTUAL java/lang/Double.doubleValue ()D
            GOTO L5
           L1
           FRAME FULL [org/nlogo/prim/_asm_proceduresetupspatiallyclusterednetwork_div_15 org/nlogo/nvm/Context java/lang/Object] [java/lang/ClassCastException]
            POP
            NEW org/nlogo/nvm/ArgumentTypeException
            DUP
            ALOAD 1
            ALOAD 0
            BIPUSH 0
            LDC 1
            ALOAD 2
            INVOKESPECIAL org/nlogo/nvm/ArgumentTypeException.<init> (Lorg/nlogo/nvm/Context;Lorg/nlogo/nvm/Instruction;IILjava/lang/Object;)V
            ATHROW
           L5
           FRAME FULL [org/nlogo/prim/_asm_proceduresetupspatiallyclusterednetwork_div_15 org/nlogo/nvm/Context java/lang/Object] [D D]
            DSTORE 2
            DLOAD 2
            DCONST_0
            DCMPG
            IFGE L6
            NEW org/nlogo/nvm/EngineException
            DUP
            ALOAD 1
            ALOAD 0
            INVOKESTATIC org/nlogo/core/I18N.errorsJ ()Lorg/nlogo/core/I18NJava;
            LDC "org.nlogo.prim.etc._sqrt.squareRootIsImaginary"
            ICONST_1
            ANEWARRAY java/lang/Object
            DUP
            ICONST_0
            DLOAD 2
            INVOKESTATIC java/lang/Double.valueOf (D)Ljava/lang/Double;
            AASTORE
            INVOKEINTERFACE org/nlogo/core/I18NJava.getN (Ljava/lang/String;[Ljava/lang/Object;)Ljava/lang/String;
            INVOKESPECIAL org/nlogo/nvm/EngineException.<init> (Lorg/nlogo/nvm/Context;Lorg/nlogo/nvm/Instruction;Ljava/lang/String;)V
            ATHROW
           L6
           FRAME FULL [org/nlogo/prim/_asm_proceduresetupspatiallyclusterednetwork_div_15 org/nlogo/nvm/Context D] [D]
            DLOAD 2
            INVOKESTATIC java/lang/StrictMath.sqrt (D)D
           L7
            DSTORE 4
            DSTORE 2
            DLOAD 4
            DCONST_0
            DCMPL
            IFNE L8
            NEW org/nlogo/nvm/EngineException
            DUP
            ALOAD 1
            ALOAD 0
            INVOKESTATIC org/nlogo/core/I18N.errorsJ ()Lorg/nlogo/core/I18NJava;
            LDC "org.nlogo.prim.etc.$common.divByZero"
            INVOKEINTERFACE org/nlogo/core/I18NJava.get (Ljava/lang/String;)Ljava/lang/String;
            INVOKESPECIAL org/nlogo/nvm/EngineException.<init> (Lorg/nlogo/nvm/Context;Lorg/nlogo/nvm/Instruction;Ljava/lang/String;)V
            ATHROW
           L8
           FRAME APPEND [D]
            ALOAD 0
            DLOAD 2
            DLOAD 4
            DDIV
            INVOKEVIRTUAL org/nlogo/prim/_asm_proceduresetupspatiallyclusterednetwork_div_15.validDouble (D)D
           L9
            DSTORE 2
            NEW java/lang/Double
            DUP
            DLOAD 2
            INVOKESPECIAL java/lang/Double.<init> (D)V
            ARETURN
      _asm_proceduresetupspatiallyclusterednetwork_constdouble_16 "1" => Double
           L0
            ALOAD 0
            GETFIELD org/nlogo/prim/_asm_proceduresetupspatiallyclusterednetwork_constdouble_16.kept1_value : Ljava/lang/Double;
           L1
            ARETURN
[11]_asm_proceduresetupspatiallyclusterednetwork_repeatlocalinternal_17 => void
         L0
          ALOAD 1
          GETFIELD org/nlogo/nvm/Context.activation : Lorg/nlogo/nvm/Activation;
          GETFIELD org/nlogo/nvm/Activation.args : [Ljava/lang/Object;
          ICONST_1
          AALOAD
          CHECKCAST org/nlogo/nvm/MutableLong
          ASTORE 2
          ALOAD 2
          INVOKEVIRTUAL org/nlogo/nvm/MutableLong.value ()J
          LCONST_0
          LCMP
          IFGT L1
          ALOAD 1
          BIPUSH 12
          PUTFIELD org/nlogo/nvm/Context.ip : I
          GOTO L2
         L1
         FRAME APPEND [org/nlogo/nvm/MutableLong]
          ALOAD 2
          ALOAD 2
          INVOKEVIRTUAL org/nlogo/nvm/MutableLong.value ()J
          LCONST_1
          LSUB
          INVOKEVIRTUAL org/nlogo/nvm/MutableLong.value_$eq (J)V
          ALOAD 1
          BIPUSH 10
          PUTFIELD org/nlogo/nvm/Context.ip : I
         L2
         FRAME SAME
          RETURN
[12]_asm_proceduresetupspatiallyclusterednetwork_return_18 => void
         L0
          ALOAD 1
          INVOKEVIRTUAL org/nlogo/nvm/Context.returnFromProcedure ()V
          ALOAD 1
          ICONST_0
          PUTFIELD org/nlogo/nvm/Context.stopping : Z
         L1
          RETURN

procedure BENCHMARK:[_repeatlocal:0]{O---}:
[0]_asm_procedurebenchmark_randomseed_0 "random-seed 2468" double => void
      _constdouble:2468.0 "2468" => double
         L0
          LDC 2468.0
         L1
          DSTORE 2
          DLOAD 2
          D2L
          LSTORE 4
          LLOAD 4
          LDC -2147483648
          LCMP
          IFLT L2
          LLOAD 4
          LDC 2147483647
          LCMP
          IFLE L3
         L2
         FRAME APPEND [D J]
          NEW org/nlogo/nvm/EngineException
          DUP
          ALOAD 1
          ALOAD 0
          NEW scala/collection/mutable/StringBuilder
          DUP
          INVOKESPECIAL scala/collection/mutable/StringBuilder.<init> ()V
          GETSTATIC org/nlogo/api/Dump$.MODULE$ : Lorg/nlogo/api/Dump$;
          DLOAD 2
          INVOKEVIRTUAL org/nlogo/api/Dump$.number (D)Ljava/lang/String;
          INVOKEVIRTUAL scala/collection/mutable/StringBuilder.append (Ljava/lang/Object;)Lscala/collection/mutable/StringBuilder;
          LDC " is not in the allowable range for random seeds (-2147483648 to 2147483647)"
          INVOKEVIRTUAL scala/collection/mutable/StringBuilder.append (Ljava/lang/Object;)Lscala/collection/mutable/StringBuilder;
          INVOKEVIRTUAL scala/collection/mutable/StringBuilder.toString ()Ljava/lang/String;
          INVOKESPECIAL org/nlogo/nvm/EngineException.<init> (Lorg/nlogo/nvm/Context;Lorg/nlogo/nvm/Instruction;Ljava/lang/String;)V
          ATHROW
         L3
         FRAME SAME
          ALOAD 1
          GETFIELD org/nlogo/nvm/Context.job : Lorg/nlogo/nvm/Job;
          GETFIELD org/nlogo/nvm/Job.random : Lorg/nlogo/api/MersenneTwisterFast;
          LLOAD 4
          L2I
          I2L
          INVOKEVIRTUAL org/nlogo/api/MersenneTwisterFast.setSeed (J)V
          ALOAD 1
          ICONST_1
          PUTFIELD org/nlogo/nvm/Context.ip : I
         L4
          RETURN
[1]_resettimer "reset-timer"
[2]_asm_procedurebenchmark_call_1 "setup"
         L0
          NEW org/nlogo/nvm/Activation
          DUP
          ALOAD 0
          GETFIELD org/nlogo/prim/_asm_procedurebenchmark_call_1.kept1_procedure : Lorg/nlogo/nvm/Procedure;
          ALOAD 1
          GETFIELD org/nlogo/nvm/Context.activation : Lorg/nlogo/nvm/Activation;
          ICONST_3
          INVOKESPECIAL org/nlogo/nvm/Activation.<init> (Lorg/nlogo/nvm/Procedure;Lorg/nlogo/nvm/Activation;I)V
          ALOAD 1
          SWAP
          PUTFIELD org/nlogo/nvm/Context.activation : Lorg/nlogo/nvm/Activation;
          ALOAD 1
          ICONST_0
          PUTFIELD org/nlogo/nvm/Context.ip : I
         L1
          RETURN
[3]_asm_procedurebenchmark_repeatlocal_2 "repeat 2000 [ go ]" double => void
      _constdouble:2000.0 "2000" => double
         L0
          LDC 2000.0
         L1
          DSTORE 2
          ALOAD 1
          GETFIELD org/nlogo/nvm/Context.activation : Lorg/nlogo/nvm/Activation;
          GETFIELD org/nlogo/nvm/Activation.args : [Ljava/lang/Object;
          ICONST_0
          NEW org/nlogo/nvm/MutableLong
          DUP
          ALOAD 0
          DLOAD 2
          INVOKEVIRTUAL org/nlogo/prim/_asm_procedurebenchmark_repeatlocal_2.validLong (D)J
          INVOKESPECIAL org/nlogo/nvm/MutableLong.<init> (J)V
          AASTORE
          ALOAD 1
          ICONST_5
          PUTFIELD org/nlogo/nvm/Context.ip : I
         L2
          RETURN
[4]_asm_procedurebenchmark_call_3 "go"
         L0
          NEW org/nlogo/nvm/Activation
          DUP
          ALOAD 0
          GETFIELD org/nlogo/prim/_asm_procedurebenchmark_call_3.kept1_procedure : Lorg/nlogo/nvm/Procedure;
          ALOAD 1
          GETFIELD org/nlogo/nvm/Context.activation : Lorg/nlogo/nvm/Activation;
          ICONST_5
          INVOKESPECIAL org/nlogo/nvm/Activation.<init> (Lorg/nlogo/nvm/Procedure;Lorg/nlogo/nvm/Activation;I)V
          ALOAD 1
          SWAP
          PUTFIELD org/nlogo/nvm/Context.activation : Lorg/nlogo/nvm/Activation;
          ALOAD 1
          ICONST_0
          PUTFIELD org/nlogo/nvm/Context.ip : I
         L1
          RETURN
[5]_asm_procedurebenchmark_repeatlocalinternal_4 => void
         L0
          ALOAD 1
          GETFIELD org/nlogo/nvm/Context.activation : Lorg/nlogo/nvm/Activation;
          GETFIELD org/nlogo/nvm/Activation.args : [Ljava/lang/Object;
          ICONST_0
          AALOAD
          CHECKCAST org/nlogo/nvm/MutableLong
          ASTORE 2
          ALOAD 2
          INVOKEVIRTUAL org/nlogo/nvm/MutableLong.value ()J
          LCONST_0
          LCMP
          IFGT L1
          ALOAD 1
          BIPUSH 6
          PUTFIELD org/nlogo/nvm/Context.ip : I
          GOTO L2
         L1
         FRAME APPEND [org/nlogo/nvm/MutableLong]
          ALOAD 2
          ALOAD 2
          INVOKEVIRTUAL org/nlogo/nvm/MutableLong.value ()J
          LCONST_1
          LSUB
          INVOKEVIRTUAL org/nlogo/nvm/MutableLong.value_$eq (J)V
          ALOAD 1
          ICONST_4
          PUTFIELD org/nlogo/nvm/Context.ip : I
         L2
         FRAME SAME
          RETURN
[6]_asm_procedurebenchmark_setobservervariable_5 "set result timer" Object => void
      _timer "timer" => double
          TRYCATCHBLOCK L0 L1 L2 org/nlogo/api/AgentException
         L3
          ALOAD 0
          GETFIELD org/nlogo/prim/_asm_procedurebenchmark_setobservervariable_5.world : Lorg/nlogo/agent/World;
          INVOKEVIRTUAL org/nlogo/agent/World.timer ()Lorg/nlogo/api/Timer;
          INVOKEVIRTUAL org/nlogo/api/Timer.read ()D
         L4
          DSTORE 2
          NEW java/lang/Double
          DUP
          DLOAD 2
          INVOKESPECIAL java/lang/Double.<init> (D)V
          ASTORE 2
         L0
          ALOAD 1
          GETFIELD org/nlogo/nvm/Context.agent : Lorg/nlogo/agent/Agent;
          BIPUSH 7
          ALOAD 2
          INVOKEVIRTUAL org/nlogo/agent/Agent.setObserverVariable (ILjava/lang/Object;)V
         L1
          GOTO L5
         L2
         FRAME FULL [org/nlogo/prim/_asm_procedurebenchmark_setobservervariable_5 org/nlogo/nvm/Context java/lang/Double] [org/nlogo/api/AgentException]
          ASTORE 3
          NEW org/nlogo/nvm/EngineException
          DUP
          ALOAD 1
          ALOAD 0
          ALOAD 3
          INVOKEVIRTUAL org/nlogo/api/AgentException.getMessage ()Ljava/lang/String;
          INVOKESPECIAL org/nlogo/nvm/EngineException.<init> (Lorg/nlogo/nvm/Context;Lorg/nlogo/nvm/Instruction;Ljava/lang/String;)V
          ATHROW
         L5
         FRAME SAME
          ALOAD 1
          BIPUSH 7
          PUTFIELD org/nlogo/nvm/Context.ip : I
         L6
          RETURN
[7]_asm_procedurebenchmark_return_6 => void
         L0
          ALOAD 1
          INVOKEVIRTUAL org/nlogo/nvm/Context.returnFromProcedure ()V
          ALOAD 1
          ICONST_0
          PUTFIELD org/nlogo/nvm/Context.stopping : Z
         L1
          RETURN

procedure DO-VIRUS-CHECKS:[]{OTPL}:
[0]_asm_proceduredoviruschecks_ask_0 "ask turtles with [ infected? and virus-check-timer = 0 ] [ if random 100 < recovery-chance [ ifelse random 100 < gain-resistance-chance [ become-resistant ] [ become-susceptible ] ] ]" AgentSet => void
      _with "turtles with [ infected? and virus-check-timer = 0 ]" AgentSet,Reporter => AgentSet
        _turtles "turtles" => AgentSet
        _asm_proceduredoviruschecks_and_1 "infected? and virus-check-timer = 0"
          _turtlevariable:INFECTED? "infected?" => Object
          _equal "virus-check-timer = 0" Object,double => boolean
            _turtlevariable:VIRUS-CHECK-TIMER "virus-check-timer" => Object
            _constdouble:0.0 "0" => double
              TRYCATCHBLOCK L0 L1 L2 org/nlogo/api/AgentException
              TRYCATCHBLOCK L3 L4 L4 java/lang/ClassCastException
              TRYCATCHBLOCK L5 L6 L7 org/nlogo/api/AgentException
             L0
              ALOAD 1
              GETFIELD org/nlogo/nvm/Context.agent : Lorg/nlogo/agent/Agent;
              BIPUSH 13
              INVOKEVIRTUAL org/nlogo/agent/Agent.getTurtleVariable (I)Ljava/lang/Object;
             L1
              GOTO L8
             L2
             FRAME SAME1 org/nlogo/api/AgentException
              ASTORE 2
              NEW org/nlogo/nvm/EngineException
              DUP
              ALOAD 1
              ALOAD 0
              ALOAD 2
              INVOKEVIRTUAL org/nlogo/api/AgentException.getMessage ()Ljava/lang/String;
              INVOKESPECIAL org/nlogo/nvm/EngineException.<init> (Lorg/nlogo/nvm/Context;Lorg/nlogo/nvm/Instruction;Ljava/lang/String;)V
              ATHROW
             L8
             FRAME SAME1 java/lang/Object
              ASTORE 2
             L3
              ALOAD 2
              CHECKCAST java/lang/Boolean
              INVOKEVIRTUAL java/lang/Boolean.booleanValue ()Z
              GOTO L9
             L4
             FRAME FULL [org/nlogo/prim/_asm_proceduredoviruschecks_and_1 org/nlogo/nvm/Context java/lang/Object] [java/lang/ClassCastException]
              POP
              NEW org/nlogo/nvm/ArgumentTypeException
              DUP
              ALOAD 1
              ALOAD 0
              BIPUSH 0
              LDC 2
              ALOAD 2
              INVOKESPECIAL org/nlogo/nvm/ArgumentTypeException.<init> (Lorg/nlogo/nvm/Context;Lorg/nlogo/nvm/Instruction;IILjava/lang/Object;)V
              ATHROW
             L9
             FRAME SAME1 I
              IFEQ L10
             L5
              ALOAD 1
              GETFIELD org/nlogo/nvm/Context.agent : Lorg/nlogo/agent/Agent;
              BIPUSH 15
              INVOKEVIRTUAL org/nlogo/agent/Agent.getTurtleVariable (I)Ljava/lang/Object;
             L6
              GOTO L11
             L7
             FRAME SAME1 org/nlogo/api/AgentException
              ASTORE 2
              NEW org/nlogo/nvm/EngineException
              DUP
              ALOAD 1
              ALOAD 0
              ALOAD 2
              INVOKEVIRTUAL org/nlogo/api/AgentException.getMessage ()Ljava/lang/String;
              INVOKESPECIAL org/nlogo/nvm/EngineException.<init> (Lorg/nlogo/nvm/Context;Lorg/nlogo/nvm/Instruction;Ljava/lang/String;)V
              ATHROW
             L11
             FRAME SAME1 java/lang/Object
              DCONST_0
             L12
              DSTORE 3
              ASTORE 2
              ALOAD 2
              INSTANCEOF java/lang/Double
              IFEQ L13
              DLOAD 3
              ALOAD 2
              CHECKCAST java/lang/Double
              INVOKEVIRTUAL java/lang/Double.doubleValue ()D
              DCMPL
              IFNE L13
              ICONST_1
              GOTO L14
             L13
             FRAME APPEND [D]
              ICONST_0
             L14
             FRAME SAME1 I
              GOTO L15
             L10
             FRAME CHOP 1
              ICONST_0
             L15
             FRAME SAME1 I
              IFEQ L16
              GETSTATIC java/lang/Boolean.TRUE : Ljava/lang/Boolean;
              GOTO L17
             L16
             FRAME SAME
              GETSTATIC java/lang/Boolean.FALSE : Ljava/lang/Boolean;
             L17
             FRAME SAME1 java/lang/Boolean
              ARETURN
         L0
          ALOAD 0
          GETFIELD org/nlogo/prim/_asm_proceduredoviruschecks_ask_0.world : Lorg/nlogo/agent/World;
          INVOKEVIRTUAL org/nlogo/agent/World.turtles ()Lorg/nlogo/agent/AgentSet;
         L1
          ALOAD 0
          GETFIELD org/nlogo/prim/_asm_proceduredoviruschecks_ask_0.keptinstr4 : Lorg/nlogo/nvm/Reporter;
          ASTORE 3
          ASTORE 2
          NEW org/nlogo/nvm/Context
          DUP
          ALOAD 1
          ALOAD 2
          INVOKESPECIAL org/nlogo/nvm/Context.<init> (Lorg/nlogo/nvm/Context;Lorg/nlogo/agent/AgentSet;)V
          ASTORE 4
          NEW java/util/ArrayList
          DUP
          INVOKESPECIAL java/util/ArrayList.<init> ()V
          ASTORE 5
          ALOAD 3
          ALOAD 2
          ALOAD 1
          INVOKEVIRTUAL org/nlogo/nvm/Reporter.checkAgentSetClass (Lorg/nlogo/agent/AgentSet;Lorg/nlogo/nvm/Context;)V
          ALOAD 2
          INVOKEVIRTUAL org/nlogo/agent/AgentSet.iterator ()Lorg/nlogo/agent/AgentSet$Iterator;
          ASTORE 6
         L2
         FRAME FULL [org/nlogo/prim/_asm_proceduredoviruschecks_ask_0 org/nlogo/nvm/Context org/nlogo/agent/AgentSet org/nlogo/nvm/Reporter org/nlogo/nvm/Context java/util/ArrayList org/nlogo/agent/AgentSet$Iterator] []
          ALOAD 6
          INVOKEINTERFACE org/nlogo/agent/AgentSet$Iterator.hasNext ()Z
          IFEQ L3
          ALOAD 6
          INVOKEINTERFACE org/nlogo/agent/AgentSet$Iterator.next ()Lorg/nlogo/agent/Agent;
          ASTORE 7
          ALOAD 4
          ALOAD 7
          ALOAD 3
          INVOKEVIRTUAL org/nlogo/nvm/Context.evaluateReporter (Lorg/nlogo/agent/Agent;Lorg/nlogo/nvm/Reporter;)Ljava/lang/Object;
          ASTORE 8
          ALOAD 8
          INSTANCEOF java/lang/Boolean
          IFNE L4
          NEW org/nlogo/nvm/EngineException
          DUP
          ALOAD 1
          ALOAD 0
          INVOKESTATIC org/nlogo/core/I18N.errorsJ ()Lorg/nlogo/core/I18NJava;
          LDC "org.nlogo.prim.$common.expectedBooleanValue"
          ICONST_3
          ANEWARRAY java/lang/Object
          DUP
          ICONST_0
          LDC "WITH"
          AASTORE
          DUP
          ICONST_1
          ALOAD 7
          INVOKESTATIC org/nlogo/api/Dump.logoObject (Ljava/lang/Object;)Ljava/lang/String;
          AASTORE
          DUP
          ICONST_2
          ALOAD 8
          INVOKESTATIC org/nlogo/api/Dump.logoObject (Ljava/lang/Object;)Ljava/lang/String;
          AASTORE
          INVOKEINTERFACE org/nlogo/core/I18NJava.getN (Ljava/lang/String;[Ljava/lang/Object;)Ljava/lang/String;
          INVOKESPECIAL org/nlogo/nvm/EngineException.<init> (Lorg/nlogo/nvm/Context;Lorg/nlogo/nvm/Instruction;Ljava/lang/String;)V
          ATHROW
         L4
         FRAME APPEND [org/nlogo/agent/Agent java/lang/Object]
          ALOAD 8
          CHECKCAST java/lang/Boolean
          INVOKEVIRTUAL java/lang/Boolean.booleanValue ()Z
          IFEQ L5
          ALOAD 5
          ALOAD 7
          INVOKEINTERFACE java/util/List.add (Ljava/lang/Object;)Z
          POP
         L5
         FRAME SAME
          GOTO L2
         L3
         FRAME CHOP 2
          NEW org/nlogo/agent/ArrayAgentSet
          DUP
          ALOAD 2
          INVOKEVIRTUAL org/nlogo/agent/AgentSet.kind ()Lorg/nlogo/core/AgentKind;
          ALOAD 5
          ALOAD 5
          INVOKEINTERFACE java/util/List.size ()I
          ANEWARRAY org/nlogo/agent/Agent
          INVOKEINTERFACE java/util/List.toArray ([Ljava/lang/Object;)[Ljava/lang/Object;
          CHECKCAST [Lorg/nlogo/agent/Agent;
          INVOKESPECIAL org/nlogo/agent/ArrayAgentSet.<init> (Lorg/nlogo/core/AgentKind;[Lorg/nlogo/agent/Agent;)V
         L6
          ASTORE 2
          ALOAD 1
          GETFIELD org/nlogo/nvm/Context.agent : Lorg/nlogo/agent/Agent;
          INSTANCEOF org/nlogo/agent/Observer
          IFNE L7
          ALOAD 2
          ALOAD 0
          GETFIELD org/nlogo/prim/_asm_proceduredoviruschecks_ask_0.world : Lorg/nlogo/agent/World;
          INVOKEVIRTUAL org/nlogo/agent/World.turtles ()Lorg/nlogo/agent/AgentSet;
          IF_ACMPNE L8
          NEW org/nlogo/nvm/EngineException
          DUP
          ALOAD 1
          ALOAD 0
          INVOKESTATIC org/nlogo/core/I18N.errorsJ ()Lorg/nlogo/core/I18NJava;
          LDC "org.nlogo.prim.$common.onlyObserverCanAskAllTurtles"
          INVOKEINTERFACE org/nlogo/core/I18NJava.get (Ljava/lang/String;)Ljava/lang/String;
          INVOKESPECIAL org/nlogo/nvm/EngineException.<init> (Lorg/nlogo/nvm/Context;Lorg/nlogo/nvm/Instruction;Ljava/lang/String;)V
          ATHROW
         L8
         FRAME FULL [org/nlogo/prim/_asm_proceduredoviruschecks_ask_0 org/nlogo/nvm/Context org/nlogo/agent/ArrayAgentSet org/nlogo/nvm/Reporter org/nlogo/nvm/Context java/util/ArrayList org/nlogo/agent/AgentSet$Iterator] []
          ALOAD 2
          ALOAD 0
          GETFIELD org/nlogo/prim/_asm_proceduredoviruschecks_ask_0.world : Lorg/nlogo/agent/World;
          INVOKEVIRTUAL org/nlogo/agent/World.patches ()Lorg/nlogo/agent/AgentSet;
          IF_ACMPNE L7
          NEW org/nlogo/nvm/EngineException
          DUP
          ALOAD 1
          ALOAD 0
          INVOKESTATIC org/nlogo/core/I18N.errorsJ ()Lorg/nlogo/core/I18NJava;
          LDC "org.nlogo.prim.$common.onlyObserverCanAskAllPatches"
          INVOKEINTERFACE org/nlogo/core/I18NJava.get (Ljava/lang/String;)Ljava/lang/String;
          INVOKESPECIAL org/nlogo/nvm/EngineException.<init> (Lorg/nlogo/nvm/Context;Lorg/nlogo/nvm/Instruction;Ljava/lang/String;)V
          ATHROW
         L7
         FRAME SAME
          ALOAD 1
          ALOAD 2
          ICONST_1
          INVOKEVIRTUAL org/nlogo/nvm/Context.runExclusiveJob (Lorg/nlogo/agent/AgentSet;I)V
          ALOAD 1
          BIPUSH 7
          PUTFIELD org/nlogo/nvm/Context.ip : I
         L9
          RETURN
[1]_asm_proceduredoviruschecks_if_2 "if random 100 < recovery-chance [ ifelse random 100 < gain-resistance-chance [ become-resistant ] [ become-susceptible ] ]" boolean => void
      _lessthan "random 100 < recovery-chance" double,Object => boolean
        _randomconst:100 "random 100" => double
        _observervariable:RECOVERY-CHANCE "recovery-chance" => Object
         L0
          ALOAD 1
          GETFIELD org/nlogo/nvm/Context.job : Lorg/nlogo/nvm/Job;
          GETFIELD org/nlogo/nvm/Job.random : Lorg/nlogo/api/MersenneTwisterFast;
          LDC 100
          INVOKEVIRTUAL org/nlogo/api/MersenneTwisterFast.nextLong (J)J
          L2D
         L1
          ALOAD 1
          GETFIELD org/nlogo/nvm/Context.agent : Lorg/nlogo/agent/Agent;
          ICONST_1
          INVOKEVIRTUAL org/nlogo/agent/Agent.getObserverVariable (I)Ljava/lang/Object;
         L2
          ASTORE 4
          DSTORE 2
          ALOAD 4
          INSTANCEOF java/lang/Double
          IFEQ L3
          DLOAD 2
          ALOAD 4
          CHECKCAST java/lang/Double
          INVOKEVIRTUAL java/lang/Double.doubleValue ()D
          DCMPG
          IFGE L4
          ICONST_1
          GOTO L5
         L4
         FRAME APPEND [D java/lang/Object]
          ICONST_0
         L5
         FRAME SAME1 I
          GOTO L6
         L3
         FRAME SAME
          NEW org/nlogo/nvm/EngineException
          DUP
          ALOAD 1
          ALOAD 0
          INVOKESTATIC org/nlogo/core/I18N.errorsJ ()Lorg/nlogo/core/I18NJava;
          LDC "org.nlogo.prim._lessthan.cantUseLessthanOnDifferentArgs"
          ICONST_2
          ANEWARRAY java/lang/Object
          DUP
          ICONST_0
          DLOAD 2
          INVOKESTATIC java/lang/Double.valueOf (D)Ljava/lang/Double;
          INVOKESTATIC org/nlogo/api/TypeNames.aName (Ljava/lang/Object;)Ljava/lang/String;
          AASTORE
          DUP
          ICONST_1
          ALOAD 4
          INVOKESTATIC org/nlogo/api/TypeNames.aName (Ljava/lang/Object;)Ljava/lang/String;
          AASTORE
          INVOKEINTERFACE org/nlogo/core/I18NJava.getN (Ljava/lang/String;[Ljava/lang/Object;)Ljava/lang/String;
          INVOKESPECIAL org/nlogo/nvm/EngineException.<init> (Lorg/nlogo/nvm/Context;Lorg/nlogo/nvm/Instruction;Ljava/lang/String;)V
          ATHROW
         L6
         FRAME SAME1 I
          ISTORE 2
          ALOAD 1
          ILOAD 2
          IFEQ L7
          ICONST_2
          GOTO L8
         L7
         FRAME FULL [org/nlogo/prim/_asm_proceduredoviruschecks_if_2 org/nlogo/nvm/Context I T java/lang/Object] [org/nlogo/nvm/Context]
          BIPUSH 6
         L8
         FRAME FULL [org/nlogo/prim/_asm_proceduredoviruschecks_if_2 org/nlogo/nvm/Context I T java/lang/Object] [org/nlogo/nvm/Context I]
          PUTFIELD org/nlogo/nvm/Context.ip : I
         L9
          RETURN
[2]_asm_proceduredoviruschecks_ifelse_3 "ifelse random 100 < gain-resistance-chance [ become-resistant ] [ become-susceptible ]" boolean => void
      _lessthan "random 100 < gain-resistance-chance" double,Object => boolean
        _randomconst:100 "random 100" => double
        _observervariable:GAIN-RESISTANCE-CHANCE "gain-resistance-chance" => Object
         L0
          ALOAD 1
          GETFIELD org/nlogo/nvm/Context.job : Lorg/nlogo/nvm/Job;
          GETFIELD org/nlogo/nvm/Job.random : Lorg/nlogo/api/MersenneTwisterFast;
          LDC 100
          INVOKEVIRTUAL org/nlogo/api/MersenneTwisterFast.nextLong (J)J
          L2D
         L1
          ALOAD 1
          GETFIELD org/nlogo/nvm/Context.agent : Lorg/nlogo/agent/Agent;
          ICONST_0
          INVOKEVIRTUAL org/nlogo/agent/Agent.getObserverVariable (I)Ljava/lang/Object;
         L2
          ASTORE 4
          DSTORE 2
          ALOAD 4
          INSTANCEOF java/lang/Double
          IFEQ L3
          DLOAD 2
          ALOAD 4
          CHECKCAST java/lang/Double
          INVOKEVIRTUAL java/lang/Double.doubleValue ()D
          DCMPG
          IFGE L4
          ICONST_1
          GOTO L5
         L4
         FRAME APPEND [D java/lang/Object]
          ICONST_0
         L5
         FRAME SAME1 I
          GOTO L6
         L3
         FRAME SAME
          NEW org/nlogo/nvm/EngineException
          DUP
          ALOAD 1
          ALOAD 0
          INVOKESTATIC org/nlogo/core/I18N.errorsJ ()Lorg/nlogo/core/I18NJava;
          LDC "org.nlogo.prim._lessthan.cantUseLessthanOnDifferentArgs"
          ICONST_2
          ANEWARRAY java/lang/Object
          DUP
          ICONST_0
          DLOAD 2
          INVOKESTATIC java/lang/Double.valueOf (D)Ljava/lang/Double;
          INVOKESTATIC org/nlogo/api/TypeNames.aName (Ljava/lang/Object;)Ljava/lang/String;
          AASTORE
          DUP
          ICONST_1
          ALOAD 4
          INVOKESTATIC org/nlogo/api/TypeNames.aName (Ljava/lang/Object;)Ljava/lang/String;
          AASTORE
          INVOKEINTERFACE org/nlogo/core/I18NJava.getN (Ljava/lang/String;[Ljava/lang/Object;)Ljava/lang/String;
          INVOKESPECIAL org/nlogo/nvm/EngineException.<init> (Lorg/nlogo/nvm/Context;Lorg/nlogo/nvm/Instruction;Ljava/lang/String;)V
          ATHROW
         L6
         FRAME SAME1 I
          ISTORE 2
          ALOAD 1
          ILOAD 2
          IFEQ L7
          ICONST_3
          GOTO L8
         L7
         FRAME FULL [org/nlogo/prim/_asm_proceduredoviruschecks_ifelse_3 org/nlogo/nvm/Context I T java/lang/Object] [org/nlogo/nvm/Context]
          ICONST_5
         L8
         FRAME FULL [org/nlogo/prim/_asm_proceduredoviruschecks_ifelse_3 org/nlogo/nvm/Context I T java/lang/Object] [org/nlogo/nvm/Context I]
          PUTFIELD org/nlogo/nvm/Context.ip : I
         L9
          RETURN
[3]_asm_proceduredoviruschecks_call_4 "become-resistant"
         L0
          NEW org/nlogo/nvm/Activation
          DUP
          ALOAD 0
          GETFIELD org/nlogo/prim/_asm_proceduredoviruschecks_call_4.kept1_procedure : Lorg/nlogo/nvm/Procedure;
          ALOAD 1
          GETFIELD org/nlogo/nvm/Context.activation : Lorg/nlogo/nvm/Activation;
          ICONST_4
          INVOKESPECIAL org/nlogo/nvm/Activation.<init> (Lorg/nlogo/nvm/Procedure;Lorg/nlogo/nvm/Activation;I)V
          ALOAD 1
          SWAP
          PUTFIELD org/nlogo/nvm/Context.activation : Lorg/nlogo/nvm/Activation;
          ALOAD 1
          ICONST_0
          PUTFIELD org/nlogo/nvm/Context.ip : I
         L1
          RETURN
[4]_asm_proceduredoviruschecks_goto_5 => void
         L0
          ALOAD 1
          BIPUSH 6
          PUTFIELD org/nlogo/nvm/Context.ip : I
         L1
          RETURN
[5]_asm_proceduredoviruschecks_call_6 "become-susceptible"
         L0
          NEW org/nlogo/nvm/Activation
          DUP
          ALOAD 0
          GETFIELD org/nlogo/prim/_asm_proceduredoviruschecks_call_6.kept1_procedure : Lorg/nlogo/nvm/Procedure;
          ALOAD 1
          GETFIELD org/nlogo/nvm/Context.activation : Lorg/nlogo/nvm/Activation;
          BIPUSH 6
          INVOKESPECIAL org/nlogo/nvm/Activation.<init> (Lorg/nlogo/nvm/Procedure;Lorg/nlogo/nvm/Activation;I)V
          ALOAD 1
          SWAP
          PUTFIELD org/nlogo/nvm/Context.activation : Lorg/nlogo/nvm/Activation;
          ALOAD 1
          ICONST_0
          PUTFIELD org/nlogo/nvm/Context.ip : I
         L1
          RETURN
[6]_asm_proceduredoviruschecks_done_7 => void
         L0
          ALOAD 1
          ICONST_1
          PUTFIELD org/nlogo/nvm/Context.finished : Z
         L1
          RETURN
[7]_asm_proceduredoviruschecks_return_8 => void
         L0
          ALOAD 1
          INVOKEVIRTUAL org/nlogo/nvm/Context.returnFromProcedure ()V
          ALOAD 1
          ICONST_0
          PUTFIELD org/nlogo/nvm/Context.stopping : Z
         L1
          RETURN

procedure BECOME-RESISTANT:[]{-T--}:
[0]_asm_procedurebecomeresistant_setturtlevariable_0 "set infected? false" Object => void
      _constboolean:false "false" => Boolean
          TRYCATCHBLOCK L0 L1 L2 org/nlogo/api/AgentException
         L3
          ALOAD 0
          GETFIELD org/nlogo/prim/_asm_procedurebecomeresistant_setturtlevariable_0.kept2_value : Ljava/lang/Boolean;
         L4
          ASTORE 2
         L0
          ALOAD 1
          GETFIELD org/nlogo/nvm/Context.agent : Lorg/nlogo/agent/Agent;
          BIPUSH 13
          ALOAD 2
          INVOKEVIRTUAL org/nlogo/agent/Agent.setTurtleVariable (ILjava/lang/Object;)V
         L1
          GOTO L5
         L2
         FRAME FULL [org/nlogo/prim/_asm_procedurebecomeresistant_setturtlevariable_0 org/nlogo/nvm/Context java/lang/Boolean] [org/nlogo/api/AgentException]
          ASTORE 3
          NEW org/nlogo/nvm/EngineException
          DUP
          ALOAD 1
          ALOAD 0
          ALOAD 3
          INVOKEVIRTUAL org/nlogo/api/AgentException.getMessage ()Ljava/lang/String;
          INVOKESPECIAL org/nlogo/nvm/EngineException.<init> (Lorg/nlogo/nvm/Context;Lorg/nlogo/nvm/Instruction;Ljava/lang/String;)V
          ATHROW
         L5
         FRAME SAME
          ALOAD 1
          ICONST_1
          PUTFIELD org/nlogo/nvm/Context.ip : I
         L6
          RETURN
[1]_asm_procedurebecomeresistant_setturtlevariable_1 "set resistant? true" Object => void
      _constboolean:true "true" => Boolean
          TRYCATCHBLOCK L0 L1 L2 org/nlogo/api/AgentException
         L3
          ALOAD 0
          GETFIELD org/nlogo/prim/_asm_procedurebecomeresistant_setturtlevariable_1.kept2_value : Ljava/lang/Boolean;
         L4
          ASTORE 2
         L0
          ALOAD 1
          GETFIELD org/nlogo/nvm/Context.agent : Lorg/nlogo/agent/Agent;
          BIPUSH 14
          ALOAD 2
          INVOKEVIRTUAL org/nlogo/agent/Agent.setTurtleVariable (ILjava/lang/Object;)V
         L1
          GOTO L5
         L2
         FRAME FULL [org/nlogo/prim/_asm_procedurebecomeresistant_setturtlevariable_1 org/nlogo/nvm/Context java/lang/Boolean] [org/nlogo/api/AgentException]
          ASTORE 3
          NEW org/nlogo/nvm/EngineException
          DUP
          ALOAD 1
          ALOAD 0
          ALOAD 3
          INVOKEVIRTUAL org/nlogo/api/AgentException.getMessage ()Ljava/lang/String;
          INVOKESPECIAL org/nlogo/nvm/EngineException.<init> (Lorg/nlogo/nvm/Context;Lorg/nlogo/nvm/Instruction;Ljava/lang/String;)V
          ATHROW
         L5
         FRAME SAME
          ALOAD 1
          ICONST_2
          PUTFIELD org/nlogo/nvm/Context.ip : I
         L6
          RETURN
[2]_asm_procedurebecomeresistant_setturtleorlinkvariable_2 "set color gray" Object => void
      _constdouble:5.0 "gray" => Double
          TRYCATCHBLOCK L0 L1 L2 org/nlogo/api/AgentException
         L3
          ALOAD 0
          GETFIELD org/nlogo/prim/_asm_procedurebecomeresistant_setturtleorlinkvariable_2.kept2_value : Ljava/lang/Double;
         L4
          ASTORE 2
         L0
          ALOAD 1
          GETFIELD org/nlogo/nvm/Context.agent : Lorg/nlogo/agent/Agent;
          LDC "COLOR"
          ALOAD 2
          INVOKEVIRTUAL org/nlogo/agent/Agent.setTurtleOrLinkVariable (Ljava/lang/String;Ljava/lang/Object;)V
         L1
          GOTO L5
         L2
         FRAME FULL [org/nlogo/prim/_asm_procedurebecomeresistant_setturtleorlinkvariable_2 org/nlogo/nvm/Context java/lang/Double] [org/nlogo/api/AgentException]
          ASTORE 3
          NEW org/nlogo/nvm/EngineException
          DUP
          ALOAD 1
          ALOAD 0
          ALOAD 3
          INVOKEVIRTUAL org/nlogo/api/AgentException.getMessage ()Ljava/lang/String;
          INVOKESPECIAL org/nlogo/nvm/EngineException.<init> (Lorg/nlogo/nvm/Context;Lorg/nlogo/nvm/Instruction;Ljava/lang/String;)V
          ATHROW
         L5
         FRAME SAME
          ALOAD 1
          ICONST_3
          PUTFIELD org/nlogo/nvm/Context.ip : I
         L6
          RETURN
[3]_asm_procedurebecomeresistant_ask_3 "ask my-links [ set color gray - 2 ]" Object => void
      _mylinks:null "my-links"
          ALOAD 0
          GETFIELD org/nlogo/prim/_asm_procedurebecomeresistant_ask_3.keptinstr2 : Lorg/nlogo/prim/_mylinks;
          ALOAD 1
          INVOKEVIRTUAL org/nlogo/prim/_mylinks.report (Lorg/nlogo/nvm/Context;)Ljava/lang/Object;
         L0
          ASTORE 2
          ALOAD 2
          INSTANCEOF org/nlogo/agent/AgentSet
          IFEQ L1
          ALOAD 2
          CHECKCAST org/nlogo/agent/AgentSet
          ASTORE 3
          ALOAD 1
          GETFIELD org/nlogo/nvm/Context.agent : Lorg/nlogo/agent/Agent;
          INSTANCEOF org/nlogo/agent/Observer
          IFNE L2
          ALOAD 3
          ALOAD 0
          GETFIELD org/nlogo/prim/_asm_procedurebecomeresistant_ask_3.world : Lorg/nlogo/agent/World;
          INVOKEVIRTUAL org/nlogo/agent/World.turtles ()Lorg/nlogo/agent/AgentSet;
          IF_ACMPNE L3
          NEW org/nlogo/nvm/EngineException
          DUP
          ALOAD 1
          ALOAD 0
          INVOKESTATIC org/nlogo/core/I18N.errorsJ ()Lorg/nlogo/core/I18NJava;
          LDC "org.nlogo.prim.$common.onlyObserverCanAskAllTurtles"
          INVOKEINTERFACE org/nlogo/core/I18NJava.get (Ljava/lang/String;)Ljava/lang/String;
          INVOKESPECIAL org/nlogo/nvm/EngineException.<init> (Lorg/nlogo/nvm/Context;Lorg/nlogo/nvm/Instruction;Ljava/lang/String;)V
          ATHROW
         L3
         FRAME APPEND [java/lang/Object org/nlogo/agent/AgentSet]
          ALOAD 3
          ALOAD 0
          GETFIELD org/nlogo/prim/_asm_procedurebecomeresistant_ask_3.world : Lorg/nlogo/agent/World;
          INVOKEVIRTUAL org/nlogo/agent/World.patches ()Lorg/nlogo/agent/AgentSet;
          IF_ACMPNE L2
          NEW org/nlogo/nvm/EngineException
          DUP
          ALOAD 1
          ALOAD 0
          INVOKESTATIC org/nlogo/core/I18N.errorsJ ()Lorg/nlogo/core/I18NJava;
          LDC "org.nlogo.prim.$common.onlyObserverCanAskAllPatches"
          INVOKEINTERFACE org/nlogo/core/I18NJava.get (Ljava/lang/String;)Ljava/lang/String;
          INVOKESPECIAL org/nlogo/nvm/EngineException.<init> (Lorg/nlogo/nvm/Context;Lorg/nlogo/nvm/Instruction;Ljava/lang/String;)V
          ATHROW
         L1
         FRAME CHOP 1
          ALOAD 2
          INSTANCEOF org/nlogo/agent/Agent
          IFEQ L4
          ALOAD 2
          CHECKCAST org/nlogo/agent/Agent
          ASTORE 4
          ALOAD 4
          GETFIELD org/nlogo/agent/Agent.id : J
          LDC -1
          LCMP
          IFNE L5
          NEW org/nlogo/nvm/EngineException
          DUP
          ALOAD 1
          ALOAD 0
          INVOKESTATIC org/nlogo/core/I18N.errorsJ ()Lorg/nlogo/core/I18NJava;
          LDC "org.nlogo.$common.thatAgentIsDead"
          ICONST_1
          ANEWARRAY java/lang/Object
          DUP
          ICONST_0
          ALOAD 4
          INVOKEVIRTUAL org/nlogo/agent/Agent.classDisplayName ()Ljava/lang/String;
          AASTORE
          INVOKEINTERFACE org/nlogo/core/I18NJava.getN (Ljava/lang/String;[Ljava/lang/Object;)Ljava/lang/String;
          INVOKESPECIAL org/nlogo/nvm/EngineException.<init> (Lorg/nlogo/nvm/Context;Lorg/nlogo/nvm/Instruction;Ljava/lang/String;)V
          ATHROW
         L5
         FRAME APPEND [T org/nlogo/agent/Agent]
          NEW org/nlogo/agent/ArrayAgentSet
          DUP
          ALOAD 4
          INVOKEVIRTUAL org/nlogo/agent/Agent.kind ()Lorg/nlogo/core/AgentKind;
          ICONST_1
          ICONST_0
          INVOKESPECIAL org/nlogo/agent/ArrayAgentSet.<init> (Lorg/nlogo/core/AgentKind;IZ)V
          ASTORE 3
          ALOAD 3
          ALOAD 4
          INVOKEVIRTUAL org/nlogo/agent/AgentSet.add (Lorg/nlogo/agent/Agent;)V
          GOTO L2
         L4
         FRAME CHOP 2
          NEW org/nlogo/nvm/ArgumentTypeException
          DUP
          ALOAD 1
          ALOAD 0
          ICONST_0
          INVOKESTATIC org/nlogo/core/Syntax.AgentsetType ()I
          INVOKESTATIC org/nlogo/core/Syntax.AgentType ()I
          IOR
          ALOAD 2
          INVOKESPECIAL org/nlogo/nvm/ArgumentTypeException.<init> (Lorg/nlogo/nvm/Context;Lorg/nlogo/nvm/Instruction;IILjava/lang/Object;)V
          ATHROW
         L2
         FRAME APPEND [org/nlogo/agent/AgentSet]
          ALOAD 1
          ALOAD 3
          ICONST_4
          INVOKEVIRTUAL org/nlogo/nvm/Context.runExclusiveJob (Lorg/nlogo/agent/AgentSet;I)V
          ALOAD 1
          BIPUSH 6
          PUTFIELD org/nlogo/nvm/Context.ip : I
         L6
          RETURN
[4]_asm_procedurebecomeresistant_setturtleorlinkvariable_4 "set color gray - 2" Object => void
      _constdouble:3.0 "gray - 2" => Double
          TRYCATCHBLOCK L0 L1 L2 org/nlogo/api/AgentException
         L3
          ALOAD 0
          GETFIELD org/nlogo/prim/_asm_procedurebecomeresistant_setturtleorlinkvariable_4.kept2_value : Ljava/lang/Double;
         L4
          ASTORE 2
         L0
          ALOAD 1
          GETFIELD org/nlogo/nvm/Context.agent : Lorg/nlogo/agent/Agent;
          LDC "COLOR"
          ALOAD 2
          INVOKEVIRTUAL org/nlogo/agent/Agent.setTurtleOrLinkVariable (Ljava/lang/String;Ljava/lang/Object;)V
         L1
          GOTO L5
         L2
         FRAME FULL [org/nlogo/prim/_asm_procedurebecomeresistant_setturtleorlinkvariable_4 org/nlogo/nvm/Context java/lang/Double] [org/nlogo/api/AgentException]
          ASTORE 3
          NEW org/nlogo/nvm/EngineException
          DUP
          ALOAD 1
          ALOAD 0
          ALOAD 3
          INVOKEVIRTUAL org/nlogo/api/AgentException.getMessage ()Ljava/lang/String;
          INVOKESPECIAL org/nlogo/nvm/EngineException.<init> (Lorg/nlogo/nvm/Context;Lorg/nlogo/nvm/Instruction;Ljava/lang/String;)V
          ATHROW
         L5
         FRAME SAME
          ALOAD 1
          ICONST_5
          PUTFIELD org/nlogo/nvm/Context.ip : I
         L6
          RETURN
[5]_asm_procedurebecomeresistant_done_5 => void
         L0
          ALOAD 1
          ICONST_1
          PUTFIELD org/nlogo/nvm/Context.finished : Z
         L1
          RETURN
[6]_asm_procedurebecomeresistant_return_6 => void
         L0
          ALOAD 1
          INVOKEVIRTUAL org/nlogo/nvm/Context.returnFromProcedure ()V
          ALOAD 1
          ICONST_0
          PUTFIELD org/nlogo/nvm/Context.stopping : Z
         L1
          RETURN

procedure SETUP:[]{O---}:
[0]_clearall "clear-all"
[1]_resetticks "reset-ticks"
[2]_asm_proceduresetup_call_0 "setup-nodes"
         L0
          NEW org/nlogo/nvm/Activation
          DUP
          ALOAD 0
          GETFIELD org/nlogo/prim/_asm_proceduresetup_call_0.kept1_procedure : Lorg/nlogo/nvm/Procedure;
          ALOAD 1
          GETFIELD org/nlogo/nvm/Context.activation : Lorg/nlogo/nvm/Activation;
          ICONST_3
          INVOKESPECIAL org/nlogo/nvm/Activation.<init> (Lorg/nlogo/nvm/Procedure;Lorg/nlogo/nvm/Activation;I)V
          ALOAD 1
          SWAP
          PUTFIELD org/nlogo/nvm/Context.activation : Lorg/nlogo/nvm/Activation;
          ALOAD 1
          ICONST_0
          PUTFIELD org/nlogo/nvm/Context.ip : I
         L1
          RETURN
[3]_asm_proceduresetup_call_1 "setup-spatially-clustered-network"
         L0
          NEW org/nlogo/nvm/Activation
          DUP
          ALOAD 0
          GETFIELD org/nlogo/prim/_asm_proceduresetup_call_1.kept1_procedure : Lorg/nlogo/nvm/Procedure;
          ALOAD 1
          GETFIELD org/nlogo/nvm/Context.activation : Lorg/nlogo/nvm/Activation;
          ICONST_4
          INVOKESPECIAL org/nlogo/nvm/Activation.<init> (Lorg/nlogo/nvm/Procedure;Lorg/nlogo/nvm/Activation;I)V
          ALOAD 1
          SWAP
          PUTFIELD org/nlogo/nvm/Context.activation : Lorg/nlogo/nvm/Activation;
          ALOAD 1
          ICONST_0
          PUTFIELD org/nlogo/nvm/Context.ip : I
         L1
          RETURN
[4]_asm_proceduresetup_ask_2 "ask n-of initial-outbreak-size turtles [ become-infected ]" Object => void
      _nof "n-of initial-outbreak-size turtles"
        _asm_proceduresetup_observervariable_3 "initial-outbreak-size" => Object
             L0
              ALOAD 1
              GETFIELD org/nlogo/nvm/Context.agent : Lorg/nlogo/agent/Agent;
              ICONST_5
              INVOKEVIRTUAL org/nlogo/agent/Agent.getObserverVariable (I)Ljava/lang/Object;
             L1
              ARETURN
        _asm_proceduresetup_turtles_4 "turtles" => AgentSet
             L0
              ALOAD 0
              GETFIELD org/nlogo/prim/_asm_proceduresetup_turtles_4.world : Lorg/nlogo/agent/World;
              INVOKEVIRTUAL org/nlogo/agent/World.turtles ()Lorg/nlogo/agent/AgentSet;
             L1
              ARETURN
          ALOAD 0
          GETFIELD org/nlogo/prim/_asm_proceduresetup_ask_2.keptinstr2 : Lorg/nlogo/prim/etc/_nof;
          ALOAD 1
          INVOKEVIRTUAL org/nlogo/prim/etc/_nof.report (Lorg/nlogo/nvm/Context;)Ljava/lang/Object;
         L0
          ASTORE 2
          ALOAD 2
          INSTANCEOF org/nlogo/agent/AgentSet
          IFEQ L1
          ALOAD 2
          CHECKCAST org/nlogo/agent/AgentSet
          ASTORE 3
          ALOAD 1
          GETFIELD org/nlogo/nvm/Context.agent : Lorg/nlogo/agent/Agent;
          INSTANCEOF org/nlogo/agent/Observer
          IFNE L2
          ALOAD 3
          ALOAD 0
          GETFIELD org/nlogo/prim/_asm_proceduresetup_ask_2.world : Lorg/nlogo/agent/World;
          INVOKEVIRTUAL org/nlogo/agent/World.turtles ()Lorg/nlogo/agent/AgentSet;
          IF_ACMPNE L3
          NEW org/nlogo/nvm/EngineException
          DUP
          ALOAD 1
          ALOAD 0
          INVOKESTATIC org/nlogo/core/I18N.errorsJ ()Lorg/nlogo/core/I18NJava;
          LDC "org.nlogo.prim.$common.onlyObserverCanAskAllTurtles"
          INVOKEINTERFACE org/nlogo/core/I18NJava.get (Ljava/lang/String;)Ljava/lang/String;
          INVOKESPECIAL org/nlogo/nvm/EngineException.<init> (Lorg/nlogo/nvm/Context;Lorg/nlogo/nvm/Instruction;Ljava/lang/String;)V
          ATHROW
         L3
         FRAME APPEND [java/lang/Object org/nlogo/agent/AgentSet]
          ALOAD 3
          ALOAD 0
          GETFIELD org/nlogo/prim/_asm_proceduresetup_ask_2.world : Lorg/nlogo/agent/World;
          INVOKEVIRTUAL org/nlogo/agent/World.patches ()Lorg/nlogo/agent/AgentSet;
          IF_ACMPNE L2
          NEW org/nlogo/nvm/EngineException
          DUP
          ALOAD 1
          ALOAD 0
          INVOKESTATIC org/nlogo/core/I18N.errorsJ ()Lorg/nlogo/core/I18NJava;
          LDC "org.nlogo.prim.$common.onlyObserverCanAskAllPatches"
          INVOKEINTERFACE org/nlogo/core/I18NJava.get (Ljava/lang/String;)Ljava/lang/String;
          INVOKESPECIAL org/nlogo/nvm/EngineException.<init> (Lorg/nlogo/nvm/Context;Lorg/nlogo/nvm/Instruction;Ljava/lang/String;)V
          ATHROW
         L1
         FRAME CHOP 1
          ALOAD 2
          INSTANCEOF org/nlogo/agent/Agent
          IFEQ L4
          ALOAD 2
          CHECKCAST org/nlogo/agent/Agent
          ASTORE 4
          ALOAD 4
          GETFIELD org/nlogo/agent/Agent.id : J
          LDC -1
          LCMP
          IFNE L5
          NEW org/nlogo/nvm/EngineException
          DUP
          ALOAD 1
          ALOAD 0
          INVOKESTATIC org/nlogo/core/I18N.errorsJ ()Lorg/nlogo/core/I18NJava;
          LDC "org.nlogo.$common.thatAgentIsDead"
          ICONST_1
          ANEWARRAY java/lang/Object
          DUP
          ICONST_0
          ALOAD 4
          INVOKEVIRTUAL org/nlogo/agent/Agent.classDisplayName ()Ljava/lang/String;
          AASTORE
          INVOKEINTERFACE org/nlogo/core/I18NJava.getN (Ljava/lang/String;[Ljava/lang/Object;)Ljava/lang/String;
          INVOKESPECIAL org/nlogo/nvm/EngineException.<init> (Lorg/nlogo/nvm/Context;Lorg/nlogo/nvm/Instruction;Ljava/lang/String;)V
          ATHROW
         L5
         FRAME APPEND [T org/nlogo/agent/Agent]
          NEW org/nlogo/agent/ArrayAgentSet
          DUP
          ALOAD 4
          INVOKEVIRTUAL org/nlogo/agent/Agent.kind ()Lorg/nlogo/core/AgentKind;
          ICONST_1
          ICONST_0
          INVOKESPECIAL org/nlogo/agent/ArrayAgentSet.<init> (Lorg/nlogo/core/AgentKind;IZ)V
          ASTORE 3
          ALOAD 3
          ALOAD 4
          INVOKEVIRTUAL org/nlogo/agent/AgentSet.add (Lorg/nlogo/agent/Agent;)V
          GOTO L2
         L4
         FRAME CHOP 2
          NEW org/nlogo/nvm/ArgumentTypeException
          DUP
          ALOAD 1
          ALOAD 0
          ICONST_0
          INVOKESTATIC org/nlogo/core/Syntax.AgentsetType ()I
          INVOKESTATIC org/nlogo/core/Syntax.AgentType ()I
          IOR
          ALOAD 2
          INVOKESPECIAL org/nlogo/nvm/ArgumentTypeException.<init> (Lorg/nlogo/nvm/Context;Lorg/nlogo/nvm/Instruction;IILjava/lang/Object;)V
          ATHROW
         L2
         FRAME APPEND [org/nlogo/agent/AgentSet]
          ALOAD 1
          ALOAD 3
          ICONST_5
          INVOKEVIRTUAL org/nlogo/nvm/Context.runExclusiveJob (Lorg/nlogo/agent/AgentSet;I)V
          ALOAD 1
          BIPUSH 7
          PUTFIELD org/nlogo/nvm/Context.ip : I
         L6
          RETURN
[5]_asm_proceduresetup_call_5 "become-infected"
         L0
          NEW org/nlogo/nvm/Activation
          DUP
          ALOAD 0
          GETFIELD org/nlogo/prim/_asm_proceduresetup_call_5.kept1_procedure : Lorg/nlogo/nvm/Procedure;
          ALOAD 1
          GETFIELD org/nlogo/nvm/Context.activation : Lorg/nlogo/nvm/Activation;
          BIPUSH 6
          INVOKESPECIAL org/nlogo/nvm/Activation.<init> (Lorg/nlogo/nvm/Procedure;Lorg/nlogo/nvm/Activation;I)V
          ALOAD 1
          SWAP
          PUTFIELD org/nlogo/nvm/Context.activation : Lorg/nlogo/nvm/Activation;
          ALOAD 1
          ICONST_0
          PUTFIELD org/nlogo/nvm/Context.ip : I
         L1
          RETURN
[6]_asm_proceduresetup_done_6 => void
         L0
          ALOAD 1
          ICONST_1
          PUTFIELD org/nlogo/nvm/Context.finished : Z
         L1
          RETURN
[7]_asm_proceduresetup_ask_7 "ask links [ set color white ]" AgentSet => void
      _links "links" => AgentSet
         L0
          ALOAD 0
          GETFIELD org/nlogo/prim/_asm_proceduresetup_ask_7.world : Lorg/nlogo/agent/World;
          INVOKEVIRTUAL org/nlogo/agent/World.links ()Lorg/nlogo/agent/AgentSet;
         L1
          ASTORE 2
          ALOAD 1
          GETFIELD org/nlogo/nvm/Context.agent : Lorg/nlogo/agent/Agent;
          INSTANCEOF org/nlogo/agent/Observer
          IFNE L2
          ALOAD 2
          ALOAD 0
          GETFIELD org/nlogo/prim/_asm_proceduresetup_ask_7.world : Lorg/nlogo/agent/World;
          INVOKEVIRTUAL org/nlogo/agent/World.turtles ()Lorg/nlogo/agent/AgentSet;
          IF_ACMPNE L3
          NEW org/nlogo/nvm/EngineException
          DUP
          ALOAD 1
          ALOAD 0
          INVOKESTATIC org/nlogo/core/I18N.errorsJ ()Lorg/nlogo/core/I18NJava;
          LDC "org.nlogo.prim.$common.onlyObserverCanAskAllTurtles"
          INVOKEINTERFACE org/nlogo/core/I18NJava.get (Ljava/lang/String;)Ljava/lang/String;
          INVOKESPECIAL org/nlogo/nvm/EngineException.<init> (Lorg/nlogo/nvm/Context;Lorg/nlogo/nvm/Instruction;Ljava/lang/String;)V
          ATHROW
         L3
         FRAME APPEND [org/nlogo/agent/AgentSet]
          ALOAD 2
          ALOAD 0
          GETFIELD org/nlogo/prim/_asm_proceduresetup_ask_7.world : Lorg/nlogo/agent/World;
          INVOKEVIRTUAL org/nlogo/agent/World.patches ()Lorg/nlogo/agent/AgentSet;
          IF_ACMPNE L2
          NEW org/nlogo/nvm/EngineException
          DUP
          ALOAD 1
          ALOAD 0
          INVOKESTATIC org/nlogo/core/I18N.errorsJ ()Lorg/nlogo/core/I18NJava;
          LDC "org.nlogo.prim.$common.onlyObserverCanAskAllPatches"
          INVOKEINTERFACE org/nlogo/core/I18NJava.get (Ljava/lang/String;)Ljava/lang/String;
          INVOKESPECIAL org/nlogo/nvm/EngineException.<init> (Lorg/nlogo/nvm/Context;Lorg/nlogo/nvm/Instruction;Ljava/lang/String;)V
          ATHROW
         L2
         FRAME SAME
          ALOAD 1
          ALOAD 2
          BIPUSH 8
          INVOKEVIRTUAL org/nlogo/nvm/Context.runExclusiveJob (Lorg/nlogo/agent/AgentSet;I)V
          ALOAD 1
          BIPUSH 10
          PUTFIELD org/nlogo/nvm/Context.ip : I
         L4
          RETURN
[8]_asm_proceduresetup_setturtleorlinkvariable_8 "set color white" Object => void
      _constdouble:9.9 "white" => Double
          TRYCATCHBLOCK L0 L1 L2 org/nlogo/api/AgentException
         L3
          ALOAD 0
          GETFIELD org/nlogo/prim/_asm_proceduresetup_setturtleorlinkvariable_8.kept2_value : Ljava/lang/Double;
         L4
          ASTORE 2
         L0
          ALOAD 1
          GETFIELD org/nlogo/nvm/Context.agent : Lorg/nlogo/agent/Agent;
          LDC "COLOR"
          ALOAD 2
          INVOKEVIRTUAL org/nlogo/agent/Agent.setTurtleOrLinkVariable (Ljava/lang/String;Ljava/lang/Object;)V
         L1
          GOTO L5
         L2
         FRAME FULL [org/nlogo/prim/_asm_proceduresetup_setturtleorlinkvariable_8 org/nlogo/nvm/Context java/lang/Double] [org/nlogo/api/AgentException]
          ASTORE 3
          NEW org/nlogo/nvm/EngineException
          DUP
          ALOAD 1
          ALOAD 0
          ALOAD 3
          INVOKEVIRTUAL org/nlogo/api/AgentException.getMessage ()Ljava/lang/String;
          INVOKESPECIAL org/nlogo/nvm/EngineException.<init> (Lorg/nlogo/nvm/Context;Lorg/nlogo/nvm/Instruction;Ljava/lang/String;)V
          ATHROW
         L5
         FRAME SAME
          ALOAD 1
          BIPUSH 9
          PUTFIELD org/nlogo/nvm/Context.ip : I
         L6
          RETURN
[9]_asm_proceduresetup_done_9 => void
         L0
          ALOAD 1
          ICONST_1
          PUTFIELD org/nlogo/nvm/Context.finished : Z
         L1
          RETURN
[10]_asm_proceduresetup_call_10 "update-plot"
         L0
          NEW org/nlogo/nvm/Activation
          DUP
          ALOAD 0
          GETFIELD org/nlogo/prim/_asm_proceduresetup_call_10.kept1_procedure : Lorg/nlogo/nvm/Procedure;
          ALOAD 1
          GETFIELD org/nlogo/nvm/Context.activation : Lorg/nlogo/nvm/Activation;
          BIPUSH 11
          INVOKESPECIAL org/nlogo/nvm/Activation.<init> (Lorg/nlogo/nvm/Procedure;Lorg/nlogo/nvm/Activation;I)V
          ALOAD 1
          SWAP
          PUTFIELD org/nlogo/nvm/Context.activation : Lorg/nlogo/nvm/Activation;
          ALOAD 1
          ICONST_0
          PUTFIELD org/nlogo/nvm/Context.ip : I
         L1
          RETURN
[11]_asm_proceduresetup_return_11 => void
         L0
          ALOAD 1
          INVOKEVIRTUAL org/nlogo/nvm/Context.returnFromProcedure ()V
          ALOAD 1
          ICONST_0
          PUTFIELD org/nlogo/nvm/Context.stopping : Z
         L1
          RETURN

procedure UPDATE-PLOT:[]{OTPL}:
[0]_setcurrentplot "set-current-plot "Network Status""
      _asm_procedureupdateplot_conststring_0 ""Network Status"" => String
           L0
            LDC "Network Status"
           L1
            ARETURN
[1]_setcurrentplotpen "set-current-plot-pen "susceptible""
      _asm_procedureupdateplot_conststring_1 ""susceptible"" => String
           L0
            LDC "susceptible"
           L1
            ARETURN
[2]_plot "plot count turtles with [ not infected? and not resistant? ] / count turtles * 100"
      _asm_procedureupdateplot_mult_2 "count turtles with [ not infected? and not resistant? ] / count turtles * 100" double,double => double
        _div "count turtles with [ not infected? and not resistant? ] / count turtles" double,double => double
          _countwith "count turtles with [ not infected? and not resistant? ]" AgentSet,Reporter => double
            _turtles "turtles" => AgentSet
            _asm_procedureupdateplot_and_3 "not infected? and not resistant?"
              _not "not infected?" boolean => boolean
                _turtlevariable:INFECTED? "infected?" => Object
              _not "not resistant?" boolean => boolean
                _turtlevariable:RESISTANT? "resistant?" => Object
                  TRYCATCHBLOCK L0 L1 L2 org/nlogo/api/AgentException
                  TRYCATCHBLOCK L3 L4 L4 java/lang/ClassCastException
                  TRYCATCHBLOCK L5 L6 L7 org/nlogo/api/AgentException
                  TRYCATCHBLOCK L8 L9 L9 java/lang/ClassCastException
                 L0
                  ALOAD 1
                  GETFIELD org/nlogo/nvm/Context.agent : Lorg/nlogo/agent/Agent;
                  BIPUSH 13
                  INVOKEVIRTUAL org/nlogo/agent/Agent.getTurtleVariable (I)Ljava/lang/Object;
                 L1
                  GOTO L10
                 L2
                 FRAME SAME1 org/nlogo/api/AgentException
                  ASTORE 2
                  NEW org/nlogo/nvm/EngineException
                  DUP
                  ALOAD 1
                  ALOAD 0
                  ALOAD 2
                  INVOKEVIRTUAL org/nlogo/api/AgentException.getMessage ()Ljava/lang/String;
                  INVOKESPECIAL org/nlogo/nvm/EngineException.<init> (Lorg/nlogo/nvm/Context;Lorg/nlogo/nvm/Instruction;Ljava/lang/String;)V
                  ATHROW
                 L10
                 FRAME SAME1 java/lang/Object
                  ASTORE 2
                 L3
                  ALOAD 2
                  CHECKCAST java/lang/Boolean
                  INVOKEVIRTUAL java/lang/Boolean.booleanValue ()Z
                  GOTO L11
                 L4
                 FRAME FULL [org/nlogo/prim/_asm_procedureupdateplot_and_3 org/nlogo/nvm/Context java/lang/Object] [java/lang/ClassCastException]
                  POP
                  NEW org/nlogo/nvm/ArgumentTypeException
                  DUP
                  ALOAD 1
                  ALOAD 0
                  BIPUSH 0
                  LDC 2
                  ALOAD 2
                  INVOKESPECIAL org/nlogo/nvm/ArgumentTypeException.<init> (Lorg/nlogo/nvm/Context;Lorg/nlogo/nvm/Instruction;IILjava/lang/Object;)V
                  ATHROW
                 L11
                 FRAME SAME1 I
                  ISTORE 2
                  ILOAD 2
                  IFNE L12
                  ICONST_1
                  GOTO L13
                 L12
                 FRAME FULL [org/nlogo/prim/_asm_procedureupdateplot_and_3 org/nlogo/nvm/Context I] []
                  ICONST_0
                 L13
                 FRAME SAME1 I
                  IFEQ L14
                 L5
                  ALOAD 1
                  GETFIELD org/nlogo/nvm/Context.agent : Lorg/nlogo/agent/Agent;
                  BIPUSH 14
                  INVOKEVIRTUAL org/nlogo/agent/Agent.getTurtleVariable (I)Ljava/lang/Object;
                 L6
                  GOTO L15
                 L7
                 FRAME SAME1 org/nlogo/api/AgentException
                  ASTORE 2
                  NEW org/nlogo/nvm/EngineException
                  DUP
                  ALOAD 1
                  ALOAD 0
                  ALOAD 2
                  INVOKEVIRTUAL org/nlogo/api/AgentException.getMessage ()Ljava/lang/String;
                  INVOKESPECIAL org/nlogo/nvm/EngineException.<init> (Lorg/nlogo/nvm/Context;Lorg/nlogo/nvm/Instruction;Ljava/lang/String;)V
                  ATHROW
                 L15
                 FRAME SAME1 java/lang/Object
                  ASTORE 2
                 L8
                  ALOAD 2
                  CHECKCAST java/lang/Boolean
                  INVOKEVIRTUAL java/lang/Boolean.booleanValue ()Z
                  GOTO L16
                 L9
                 FRAME FULL [org/nlogo/prim/_asm_procedureupdateplot_and_3 org/nlogo/nvm/Context java/lang/Object] [java/lang/ClassCastException]
                  POP
                  NEW org/nlogo/nvm/ArgumentTypeException
                  DUP
                  ALOAD 1
                  ALOAD 0
                  BIPUSH 0
                  LDC 2
                  ALOAD 2
                  INVOKESPECIAL org/nlogo/nvm/ArgumentTypeException.<init> (Lorg/nlogo/nvm/Context;Lorg/nlogo/nvm/Instruction;IILjava/lang/Object;)V
                  ATHROW
                 L16
                 FRAME SAME1 I
                  ISTORE 2
                  ILOAD 2
                  IFNE L17
                  ICONST_1
                  GOTO L18
                 L17
                 FRAME FULL [org/nlogo/prim/_asm_procedureupdateplot_and_3 org/nlogo/nvm/Context I] []
                  ICONST_0
                 L18
                 FRAME SAME1 I
                  GOTO L19
                 L14
                 FRAME SAME
                  ICONST_0
                 L19
                 FRAME SAME1 I
                  IFEQ L20
                  GETSTATIC java/lang/Boolean.TRUE : Ljava/lang/Boolean;
                  GOTO L21
                 L20
                 FRAME SAME
                  GETSTATIC java/lang/Boolean.FALSE : Ljava/lang/Boolean;
                 L21
                 FRAME SAME1 java/lang/Boolean
                  ARETURN
          _count "count turtles" AgentSet => double
            _turtles "turtles" => AgentSet
        _constdouble:100.0 "100" => double
           L0
            ALOAD 0
            GETFIELD org/nlogo/prim/_asm_procedureupdateplot_mult_2.world : Lorg/nlogo/agent/World;
            INVOKEVIRTUAL org/nlogo/agent/World.turtles ()Lorg/nlogo/agent/AgentSet;
           L1
            ALOAD 0
            GETFIELD org/nlogo/prim/_asm_procedureupdateplot_mult_2.keptinstr5 : Lorg/nlogo/nvm/Reporter;
            ASTORE 3
            ASTORE 2
            ALOAD 3
            ALOAD 2
            ALOAD 1
            INVOKEVIRTUAL org/nlogo/nvm/Reporter.checkAgentSetClass (Lorg/nlogo/agent/AgentSet;Lorg/nlogo/nvm/Context;)V
            NEW org/nlogo/nvm/Context
            DUP
            ALOAD 1
            ALOAD 2
            INVOKESPECIAL org/nlogo/nvm/Context.<init> (Lorg/nlogo/nvm/Context;Lorg/nlogo/agent/AgentSet;)V
            ASTORE 4
            ICONST_0
            ISTORE 5
            ALOAD 2
            INVOKEVIRTUAL org/nlogo/agent/AgentSet.iterator ()Lorg/nlogo/agent/AgentSet$Iterator;
            ASTORE 6
           L2
           FRAME FULL [org/nlogo/prim/_asm_procedureupdateplot_mult_2 org/nlogo/nvm/Context org/nlogo/agent/AgentSet org/nlogo/nvm/Reporter org/nlogo/nvm/Context I org/nlogo/agent/AgentSet$Iterator] []
            ALOAD 6
            INVOKEINTERFACE org/nlogo/agent/AgentSet$Iterator.hasNext ()Z
            IFEQ L3
            ALOAD 6
            INVOKEINTERFACE org/nlogo/agent/AgentSet$Iterator.next ()Lorg/nlogo/agent/Agent;
            ASTORE 7
            ALOAD 4
            ALOAD 7
            ALOAD 3
            INVOKEVIRTUAL org/nlogo/nvm/Context.evaluateReporter (Lorg/nlogo/agent/Agent;Lorg/nlogo/nvm/Reporter;)Ljava/lang/Object;
            ASTORE 8
            ALOAD 8
            INSTANCEOF java/lang/Boolean
            IFNE L4
            NEW org/nlogo/nvm/EngineException
            DUP
            ALOAD 1
            ALOAD 0
            INVOKESTATIC org/nlogo/core/I18N.errorsJ ()Lorg/nlogo/core/I18NJava;
            LDC "org.nlogo.prim.$common.expectedBooleanValue"
            ICONST_3
            ANEWARRAY java/lang/Object
            DUP
            ICONST_0
            LDC "COUNT"
            AASTORE
            DUP
            ICONST_1
            ALOAD 7
            INVOKESTATIC org/nlogo/api/Dump.logoObject (Ljava/lang/Object;)Ljava/lang/String;
            AASTORE
            DUP
            ICONST_2
            ALOAD 8
            INVOKESTATIC org/nlogo/api/Dump.logoObject (Ljava/lang/Object;)Ljava/lang/String;
            AASTORE
            INVOKEINTERFACE org/nlogo/core/I18NJava.getN (Ljava/lang/String;[Ljava/lang/Object;)Ljava/lang/String;
            INVOKESPECIAL org/nlogo/nvm/EngineException.<init> (Lorg/nlogo/nvm/Context;Lorg/nlogo/nvm/Instruction;Ljava/lang/String;)V
            ATHROW
           L4
           FRAME APPEND [org/nlogo/agent/Agent java/lang/Object]
            ALOAD 8
            CHECKCAST java/lang/Boolean
            INVOKEVIRTUAL java/lang/Boolean.booleanValue ()Z
            IFEQ L5
            IINC 5 1
           L5
           FRAME SAME
            GOTO L2
           L3
           FRAME CHOP 2
            ILOAD 5
            I2D
           L6
            ALOAD 0
            GETFIELD org/nlogo/prim/_asm_procedureupdateplot_mult_2.world : Lorg/nlogo/agent/World;
            INVOKEVIRTUAL org/nlogo/agent/World.turtles ()Lorg/nlogo/agent/AgentSet;
           L7
            ASTORE 2
            ALOAD 2
            INVOKEVIRTUAL org/nlogo/agent/AgentSet.count ()I
            I2D
           L8
            DSTORE 4
            DSTORE 2
            DLOAD 4
            DCONST_0
            DCMPL
            IFNE L9
            NEW org/nlogo/nvm/EngineException
            DUP
            ALOAD 1
            ALOAD 0
            INVOKESTATIC org/nlogo/core/I18N.errorsJ ()Lorg/nlogo/core/I18NJava;
            LDC "org.nlogo.prim.etc.$common.divByZero"
            INVOKEINTERFACE org/nlogo/core/I18NJava.get (Ljava/lang/String;)Ljava/lang/String;
            INVOKESPECIAL org/nlogo/nvm/EngineException.<init> (Lorg/nlogo/nvm/Context;Lorg/nlogo/nvm/Instruction;Ljava/lang/String;)V
            ATHROW
           L9
           FRAME FULL [org/nlogo/prim/_asm_procedureupdateplot_mult_2 org/nlogo/nvm/Context D D org/nlogo/agent/AgentSet$Iterator] []
            ALOAD 0
            DLOAD 2
            DLOAD 4
            DDIV
            INVOKEVIRTUAL org/nlogo/prim/_asm_procedureupdateplot_mult_2.validDouble (D)D
           L10
            LDC 100.0
           L11
            DSTORE 4
            DSTORE 2
            ALOAD 0
            DLOAD 2
            DLOAD 4
            DMUL
            INVOKEVIRTUAL org/nlogo/prim/_asm_procedureupdateplot_mult_2.validDouble (D)D
           L12
            DSTORE 2
            NEW java/lang/Double
            DUP
            DLOAD 2
            INVOKESPECIAL java/lang/Double.<init> (D)V
            ARETURN
[3]_setcurrentplotpen "set-current-plot-pen "infected""
      _asm_procedureupdateplot_conststring_4 ""infected"" => String
           L0
            LDC "infected"
           L1
            ARETURN
[4]_plot "plot count turtles with [ infected? ] / count turtles * 100"
      _asm_procedureupdateplot_mult_5 "count turtles with [ infected? ] / count turtles * 100" double,double => double
        _div "count turtles with [ infected? ] / count turtles" double,double => double
          _countwith "count turtles with [ infected? ]" AgentSet,Reporter => double
            _turtles "turtles" => AgentSet
            _asm_procedureupdateplot_turtlevariable_6 "infected?" => Object
                  TRYCATCHBLOCK L0 L1 L2 org/nlogo/api/AgentException
                 L0
                  ALOAD 1
                  GETFIELD org/nlogo/nvm/Context.agent : Lorg/nlogo/agent/Agent;
                  BIPUSH 13
                  INVOKEVIRTUAL org/nlogo/agent/Agent.getTurtleVariable (I)Ljava/lang/Object;
                 L1
                  GOTO L3
                 L2
                 FRAME SAME1 org/nlogo/api/AgentException
                  ASTORE 2
                  NEW org/nlogo/nvm/EngineException
                  DUP
                  ALOAD 1
                  ALOAD 0
                  ALOAD 2
                  INVOKEVIRTUAL org/nlogo/api/AgentException.getMessage ()Ljava/lang/String;
                  INVOKESPECIAL org/nlogo/nvm/EngineException.<init> (Lorg/nlogo/nvm/Context;Lorg/nlogo/nvm/Instruction;Ljava/lang/String;)V
                  ATHROW
                 L3
                 FRAME SAME1 java/lang/Object
                  ARETURN
          _count "count turtles" AgentSet => double
            _turtles "turtles" => AgentSet
        _constdouble:100.0 "100" => double
           L0
            ALOAD 0
            GETFIELD org/nlogo/prim/_asm_procedureupdateplot_mult_5.world : Lorg/nlogo/agent/World;
            INVOKEVIRTUAL org/nlogo/agent/World.turtles ()Lorg/nlogo/agent/AgentSet;
           L1
            ALOAD 0
            GETFIELD org/nlogo/prim/_asm_procedureupdateplot_mult_5.keptinstr5 : Lorg/nlogo/nvm/Reporter;
            ASTORE 3
            ASTORE 2
            ALOAD 3
            ALOAD 2
            ALOAD 1
            INVOKEVIRTUAL org/nlogo/nvm/Reporter.checkAgentSetClass (Lorg/nlogo/agent/AgentSet;Lorg/nlogo/nvm/Context;)V
            NEW org/nlogo/nvm/Context
            DUP
            ALOAD 1
            ALOAD 2
            INVOKESPECIAL org/nlogo/nvm/Context.<init> (Lorg/nlogo/nvm/Context;Lorg/nlogo/agent/AgentSet;)V
            ASTORE 4
            ICONST_0
            ISTORE 5
            ALOAD 2
            INVOKEVIRTUAL org/nlogo/agent/AgentSet.iterator ()Lorg/nlogo/agent/AgentSet$Iterator;
            ASTORE 6
           L2
           FRAME FULL [org/nlogo/prim/_asm_procedureupdateplot_mult_5 org/nlogo/nvm/Context org/nlogo/agent/AgentSet org/nlogo/nvm/Reporter org/nlogo/nvm/Context I org/nlogo/agent/AgentSet$Iterator] []
            ALOAD 6
            INVOKEINTERFACE org/nlogo/agent/AgentSet$Iterator.hasNext ()Z
            IFEQ L3
            ALOAD 6
            INVOKEINTERFACE org/nlogo/agent/AgentSet$Iterator.next ()Lorg/nlogo/agent/Agent;
            ASTORE 7
            ALOAD 4
            ALOAD 7
            ALOAD 3
            INVOKEVIRTUAL org/nlogo/nvm/Context.evaluateReporter (Lorg/nlogo/agent/Agent;Lorg/nlogo/nvm/Reporter;)Ljava/lang/Object;
            ASTORE 8
            ALOAD 8
            INSTANCEOF java/lang/Boolean
            IFNE L4
            NEW org/nlogo/nvm/EngineException
            DUP
            ALOAD 1
            ALOAD 0
            INVOKESTATIC org/nlogo/core/I18N.errorsJ ()Lorg/nlogo/core/I18NJava;
            LDC "org.nlogo.prim.$common.expectedBooleanValue"
            ICONST_3
            ANEWARRAY java/lang/Object
            DUP
            ICONST_0
            LDC "COUNT"
            AASTORE
            DUP
            ICONST_1
            ALOAD 7
            INVOKESTATIC org/nlogo/api/Dump.logoObject (Ljava/lang/Object;)Ljava/lang/String;
            AASTORE
            DUP
            ICONST_2
            ALOAD 8
            INVOKESTATIC org/nlogo/api/Dump.logoObject (Ljava/lang/Object;)Ljava/lang/String;
            AASTORE
            INVOKEINTERFACE org/nlogo/core/I18NJava.getN (Ljava/lang/String;[Ljava/lang/Object;)Ljava/lang/String;
            INVOKESPECIAL org/nlogo/nvm/EngineException.<init> (Lorg/nlogo/nvm/Context;Lorg/nlogo/nvm/Instruction;Ljava/lang/String;)V
            ATHROW
           L4
           FRAME APPEND [org/nlogo/agent/Agent java/lang/Object]
            ALOAD 8
            CHECKCAST java/lang/Boolean
            INVOKEVIRTUAL java/lang/Boolean.booleanValue ()Z
            IFEQ L5
            IINC 5 1
           L5
           FRAME SAME
            GOTO L2
           L3
           FRAME CHOP 2
            ILOAD 5
            I2D
           L6
            ALOAD 0
            GETFIELD org/nlogo/prim/_asm_procedureupdateplot_mult_5.world : Lorg/nlogo/agent/World;
            INVOKEVIRTUAL org/nlogo/agent/World.turtles ()Lorg/nlogo/agent/AgentSet;
           L7
            ASTORE 2
            ALOAD 2
            INVOKEVIRTUAL org/nlogo/agent/AgentSet.count ()I
            I2D
           L8
            DSTORE 4
            DSTORE 2
            DLOAD 4
            DCONST_0
            DCMPL
            IFNE L9
            NEW org/nlogo/nvm/EngineException
            DUP
            ALOAD 1
            ALOAD 0
            INVOKESTATIC org/nlogo/core/I18N.errorsJ ()Lorg/nlogo/core/I18NJava;
            LDC "org.nlogo.prim.etc.$common.divByZero"
            INVOKEINTERFACE org/nlogo/core/I18NJava.get (Ljava/lang/String;)Ljava/lang/String;
            INVOKESPECIAL org/nlogo/nvm/EngineException.<init> (Lorg/nlogo/nvm/Context;Lorg/nlogo/nvm/Instruction;Ljava/lang/String;)V
            ATHROW
           L9
           FRAME FULL [org/nlogo/prim/_asm_procedureupdateplot_mult_5 org/nlogo/nvm/Context D D org/nlogo/agent/AgentSet$Iterator] []
            ALOAD 0
            DLOAD 2
            DLOAD 4
            DDIV
            INVOKEVIRTUAL org/nlogo/prim/_asm_procedureupdateplot_mult_5.validDouble (D)D
           L10
            LDC 100.0
           L11
            DSTORE 4
            DSTORE 2
            ALOAD 0
            DLOAD 2
            DLOAD 4
            DMUL
            INVOKEVIRTUAL org/nlogo/prim/_asm_procedureupdateplot_mult_5.validDouble (D)D
           L12
            DSTORE 2
            NEW java/lang/Double
            DUP
            DLOAD 2
            INVOKESPECIAL java/lang/Double.<init> (D)V
            ARETURN
[5]_setcurrentplotpen "set-current-plot-pen "resistant""
      _asm_procedureupdateplot_conststring_7 ""resistant"" => String
           L0
            LDC "resistant"
           L1
            ARETURN
[6]_plot "plot count turtles with [ resistant? ] / count turtles * 100"
      _asm_procedureupdateplot_mult_8 "count turtles with [ resistant? ] / count turtles * 100" double,double => double
        _div "count turtles with [ resistant? ] / count turtles" double,double => double
          _countwith "count turtles with [ resistant? ]" AgentSet,Reporter => double
            _turtles "turtles" => AgentSet
            _asm_procedureupdateplot_turtlevariable_9 "resistant?" => Object
                  TRYCATCHBLOCK L0 L1 L2 org/nlogo/api/AgentException
                 L0
                  ALOAD 1
                  GETFIELD org/nlogo/nvm/Context.agent : Lorg/nlogo/agent/Agent;
                  BIPUSH 14
                  INVOKEVIRTUAL org/nlogo/agent/Agent.getTurtleVariable (I)Ljava/lang/Object;
                 L1
                  GOTO L3
                 L2
                 FRAME SAME1 org/nlogo/api/AgentException
                  ASTORE 2
                  NEW org/nlogo/nvm/EngineException
                  DUP
                  ALOAD 1
                  ALOAD 0
                  ALOAD 2
                  INVOKEVIRTUAL org/nlogo/api/AgentException.getMessage ()Ljava/lang/String;
                  INVOKESPECIAL org/nlogo/nvm/EngineException.<init> (Lorg/nlogo/nvm/Context;Lorg/nlogo/nvm/Instruction;Ljava/lang/String;)V
                  ATHROW
                 L3
                 FRAME SAME1 java/lang/Object
                  ARETURN
          _count "count turtles" AgentSet => double
            _turtles "turtles" => AgentSet
        _constdouble:100.0 "100" => double
           L0
            ALOAD 0
            GETFIELD org/nlogo/prim/_asm_procedureupdateplot_mult_8.world : Lorg/nlogo/agent/World;
            INVOKEVIRTUAL org/nlogo/agent/World.turtles ()Lorg/nlogo/agent/AgentSet;
           L1
            ALOAD 0
            GETFIELD org/nlogo/prim/_asm_procedureupdateplot_mult_8.keptinstr5 : Lorg/nlogo/nvm/Reporter;
            ASTORE 3
            ASTORE 2
            ALOAD 3
            ALOAD 2
            ALOAD 1
            INVOKEVIRTUAL org/nlogo/nvm/Reporter.checkAgentSetClass (Lorg/nlogo/agent/AgentSet;Lorg/nlogo/nvm/Context;)V
            NEW org/nlogo/nvm/Context
            DUP
            ALOAD 1
            ALOAD 2
            INVOKESPECIAL org/nlogo/nvm/Context.<init> (Lorg/nlogo/nvm/Context;Lorg/nlogo/agent/AgentSet;)V
            ASTORE 4
            ICONST_0
            ISTORE 5
            ALOAD 2
            INVOKEVIRTUAL org/nlogo/agent/AgentSet.iterator ()Lorg/nlogo/agent/AgentSet$Iterator;
            ASTORE 6
           L2
           FRAME FULL [org/nlogo/prim/_asm_procedureupdateplot_mult_8 org/nlogo/nvm/Context org/nlogo/agent/AgentSet org/nlogo/nvm/Reporter org/nlogo/nvm/Context I org/nlogo/agent/AgentSet$Iterator] []
            ALOAD 6
            INVOKEINTERFACE org/nlogo/agent/AgentSet$Iterator.hasNext ()Z
            IFEQ L3
            ALOAD 6
            INVOKEINTERFACE org/nlogo/agent/AgentSet$Iterator.next ()Lorg/nlogo/agent/Agent;
            ASTORE 7
            ALOAD 4
            ALOAD 7
            ALOAD 3
            INVOKEVIRTUAL org/nlogo/nvm/Context.evaluateReporter (Lorg/nlogo/agent/Agent;Lorg/nlogo/nvm/Reporter;)Ljava/lang/Object;
            ASTORE 8
            ALOAD 8
            INSTANCEOF java/lang/Boolean
            IFNE L4
            NEW org/nlogo/nvm/EngineException
            DUP
            ALOAD 1
            ALOAD 0
            INVOKESTATIC org/nlogo/core/I18N.errorsJ ()Lorg/nlogo/core/I18NJava;
            LDC "org.nlogo.prim.$common.expectedBooleanValue"
            ICONST_3
            ANEWARRAY java/lang/Object
            DUP
            ICONST_0
            LDC "COUNT"
            AASTORE
            DUP
            ICONST_1
            ALOAD 7
            INVOKESTATIC org/nlogo/api/Dump.logoObject (Ljava/lang/Object;)Ljava/lang/String;
            AASTORE
            DUP
            ICONST_2
            ALOAD 8
            INVOKESTATIC org/nlogo/api/Dump.logoObject (Ljava/lang/Object;)Ljava/lang/String;
            AASTORE
            INVOKEINTERFACE org/nlogo/core/I18NJava.getN (Ljava/lang/String;[Ljava/lang/Object;)Ljava/lang/String;
            INVOKESPECIAL org/nlogo/nvm/EngineException.<init> (Lorg/nlogo/nvm/Context;Lorg/nlogo/nvm/Instruction;Ljava/lang/String;)V
            ATHROW
           L4
           FRAME APPEND [org/nlogo/agent/Agent java/lang/Object]
            ALOAD 8
            CHECKCAST java/lang/Boolean
            INVOKEVIRTUAL java/lang/Boolean.booleanValue ()Z
            IFEQ L5
            IINC 5 1
           L5
           FRAME SAME
            GOTO L2
           L3
           FRAME CHOP 2
            ILOAD 5
            I2D
           L6
            ALOAD 0
            GETFIELD org/nlogo/prim/_asm_procedureupdateplot_mult_8.world : Lorg/nlogo/agent/World;
            INVOKEVIRTUAL org/nlogo/agent/World.turtles ()Lorg/nlogo/agent/AgentSet;
           L7
            ASTORE 2
            ALOAD 2
            INVOKEVIRTUAL org/nlogo/agent/AgentSet.count ()I
            I2D
           L8
            DSTORE 4
            DSTORE 2
            DLOAD 4
            DCONST_0
            DCMPL
            IFNE L9
            NEW org/nlogo/nvm/EngineException
            DUP
            ALOAD 1
            ALOAD 0
            INVOKESTATIC org/nlogo/core/I18N.errorsJ ()Lorg/nlogo/core/I18NJava;
            LDC "org.nlogo.prim.etc.$common.divByZero"
            INVOKEINTERFACE org/nlogo/core/I18NJava.get (Ljava/lang/String;)Ljava/lang/String;
            INVOKESPECIAL org/nlogo/nvm/EngineException.<init> (Lorg/nlogo/nvm/Context;Lorg/nlogo/nvm/Instruction;Ljava/lang/String;)V
            ATHROW
           L9
           FRAME FULL [org/nlogo/prim/_asm_procedureupdateplot_mult_8 org/nlogo/nvm/Context D D org/nlogo/agent/AgentSet$Iterator] []
            ALOAD 0
            DLOAD 2
            DLOAD 4
            DDIV
            INVOKEVIRTUAL org/nlogo/prim/_asm_procedureupdateplot_mult_8.validDouble (D)D
           L10
            LDC 100.0
           L11
            DSTORE 4
            DSTORE 2
            ALOAD 0
            DLOAD 2
            DLOAD 4
            DMUL
            INVOKEVIRTUAL org/nlogo/prim/_asm_procedureupdateplot_mult_8.validDouble (D)D
           L12
            DSTORE 2
            NEW java/lang/Double
            DUP
            DLOAD 2
            INVOKESPECIAL java/lang/Double.<init> (D)V
            ARETURN
[7]_asm_procedureupdateplot_return_10 => void
         L0
          ALOAD 1
          INVOKEVIRTUAL org/nlogo/nvm/Context.returnFromProcedure ()V
          ALOAD 1
          ICONST_0
          PUTFIELD org/nlogo/nvm/Context.stopping : Z
         L1
          RETURN

procedure SPREAD-VIRUS:[]{OTPL}:
[0]_asm_procedurespreadvirus_ask_0 "ask turtles with [ infected? ] [ ask link-neighbors with [ not resistant? ] [ if random-float 100 < virus-spread-chance [ become-infected ] ] ]" AgentSet => void
      _with "turtles with [ infected? ]" AgentSet,Reporter => AgentSet
        _turtles "turtles" => AgentSet
        _asm_procedurespreadvirus_turtlevariable_1 "infected?" => Object
              TRYCATCHBLOCK L0 L1 L2 org/nlogo/api/AgentException
             L0
              ALOAD 1
              GETFIELD org/nlogo/nvm/Context.agent : Lorg/nlogo/agent/Agent;
              BIPUSH 13
              INVOKEVIRTUAL org/nlogo/agent/Agent.getTurtleVariable (I)Ljava/lang/Object;
             L1
              GOTO L3
             L2
             FRAME SAME1 org/nlogo/api/AgentException
              ASTORE 2
              NEW org/nlogo/nvm/EngineException
              DUP
              ALOAD 1
              ALOAD 0
              ALOAD 2
              INVOKEVIRTUAL org/nlogo/api/AgentException.getMessage ()Ljava/lang/String;
              INVOKESPECIAL org/nlogo/nvm/EngineException.<init> (Lorg/nlogo/nvm/Context;Lorg/nlogo/nvm/Instruction;Ljava/lang/String;)V
              ATHROW
             L3
             FRAME SAME1 java/lang/Object
              ARETURN
         L0
          ALOAD 0
          GETFIELD org/nlogo/prim/_asm_procedurespreadvirus_ask_0.world : Lorg/nlogo/agent/World;
          INVOKEVIRTUAL org/nlogo/agent/World.turtles ()Lorg/nlogo/agent/AgentSet;
         L1
          ALOAD 0
          GETFIELD org/nlogo/prim/_asm_procedurespreadvirus_ask_0.keptinstr4 : Lorg/nlogo/nvm/Reporter;
          ASTORE 3
          ASTORE 2
          NEW org/nlogo/nvm/Context
          DUP
          ALOAD 1
          ALOAD 2
          INVOKESPECIAL org/nlogo/nvm/Context.<init> (Lorg/nlogo/nvm/Context;Lorg/nlogo/agent/AgentSet;)V
          ASTORE 4
          NEW java/util/ArrayList
          DUP
          INVOKESPECIAL java/util/ArrayList.<init> ()V
          ASTORE 5
          ALOAD 3
          ALOAD 2
          ALOAD 1
          INVOKEVIRTUAL org/nlogo/nvm/Reporter.checkAgentSetClass (Lorg/nlogo/agent/AgentSet;Lorg/nlogo/nvm/Context;)V
          ALOAD 2
          INVOKEVIRTUAL org/nlogo/agent/AgentSet.iterator ()Lorg/nlogo/agent/AgentSet$Iterator;
          ASTORE 6
         L2
         FRAME FULL [org/nlogo/prim/_asm_procedurespreadvirus_ask_0 org/nlogo/nvm/Context org/nlogo/agent/AgentSet org/nlogo/nvm/Reporter org/nlogo/nvm/Context java/util/ArrayList org/nlogo/agent/AgentSet$Iterator] []
          ALOAD 6
          INVOKEINTERFACE org/nlogo/agent/AgentSet$Iterator.hasNext ()Z
          IFEQ L3
          ALOAD 6
          INVOKEINTERFACE org/nlogo/agent/AgentSet$Iterator.next ()Lorg/nlogo/agent/Agent;
          ASTORE 7
          ALOAD 4
          ALOAD 7
          ALOAD 3
          INVOKEVIRTUAL org/nlogo/nvm/Context.evaluateReporter (Lorg/nlogo/agent/Agent;Lorg/nlogo/nvm/Reporter;)Ljava/lang/Object;
          ASTORE 8
          ALOAD 8
          INSTANCEOF java/lang/Boolean
          IFNE L4
          NEW org/nlogo/nvm/EngineException
          DUP
          ALOAD 1
          ALOAD 0
          INVOKESTATIC org/nlogo/core/I18N.errorsJ ()Lorg/nlogo/core/I18NJava;
          LDC "org.nlogo.prim.$common.expectedBooleanValue"
          ICONST_3
          ANEWARRAY java/lang/Object
          DUP
          ICONST_0
          LDC "WITH"
          AASTORE
          DUP
          ICONST_1
          ALOAD 7
          INVOKESTATIC org/nlogo/api/Dump.logoObject (Ljava/lang/Object;)Ljava/lang/String;
          AASTORE
          DUP
          ICONST_2
          ALOAD 8
          INVOKESTATIC org/nlogo/api/Dump.logoObject (Ljava/lang/Object;)Ljava/lang/String;
          AASTORE
          INVOKEINTERFACE org/nlogo/core/I18NJava.getN (Ljava/lang/String;[Ljava/lang/Object;)Ljava/lang/String;
          INVOKESPECIAL org/nlogo/nvm/EngineException.<init> (Lorg/nlogo/nvm/Context;Lorg/nlogo/nvm/Instruction;Ljava/lang/String;)V
          ATHROW
         L4
         FRAME APPEND [org/nlogo/agent/Agent java/lang/Object]
          ALOAD 8
          CHECKCAST java/lang/Boolean
          INVOKEVIRTUAL java/lang/Boolean.booleanValue ()Z
          IFEQ L5
          ALOAD 5
          ALOAD 7
          INVOKEINTERFACE java/util/List.add (Ljava/lang/Object;)Z
          POP
         L5
         FRAME SAME
          GOTO L2
         L3
         FRAME CHOP 2
          NEW org/nlogo/agent/ArrayAgentSet
          DUP
          ALOAD 2
          INVOKEVIRTUAL org/nlogo/agent/AgentSet.kind ()Lorg/nlogo/core/AgentKind;
          ALOAD 5
          ALOAD 5
          INVOKEINTERFACE java/util/List.size ()I
          ANEWARRAY org/nlogo/agent/Agent
          INVOKEINTERFACE java/util/List.toArray ([Ljava/lang/Object;)[Ljava/lang/Object;
          CHECKCAST [Lorg/nlogo/agent/Agent;
          INVOKESPECIAL org/nlogo/agent/ArrayAgentSet.<init> (Lorg/nlogo/core/AgentKind;[Lorg/nlogo/agent/Agent;)V
         L6
          ASTORE 2
          ALOAD 1
          GETFIELD org/nlogo/nvm/Context.agent : Lorg/nlogo/agent/Agent;
          INSTANCEOF org/nlogo/agent/Observer
          IFNE L7
          ALOAD 2
          ALOAD 0
          GETFIELD org/nlogo/prim/_asm_procedurespreadvirus_ask_0.world : Lorg/nlogo/agent/World;
          INVOKEVIRTUAL org/nlogo/agent/World.turtles ()Lorg/nlogo/agent/AgentSet;
          IF_ACMPNE L8
          NEW org/nlogo/nvm/EngineException
          DUP
          ALOAD 1
          ALOAD 0
          INVOKESTATIC org/nlogo/core/I18N.errorsJ ()Lorg/nlogo/core/I18NJava;
          LDC "org.nlogo.prim.$common.onlyObserverCanAskAllTurtles"
          INVOKEINTERFACE org/nlogo/core/I18NJava.get (Ljava/lang/String;)Ljava/lang/String;
          INVOKESPECIAL org/nlogo/nvm/EngineException.<init> (Lorg/nlogo/nvm/Context;Lorg/nlogo/nvm/Instruction;Ljava/lang/String;)V
          ATHROW
         L8
         FRAME FULL [org/nlogo/prim/_asm_procedurespreadvirus_ask_0 org/nlogo/nvm/Context org/nlogo/agent/ArrayAgentSet org/nlogo/nvm/Reporter org/nlogo/nvm/Context java/util/ArrayList org/nlogo/agent/AgentSet$Iterator] []
          ALOAD 2
          ALOAD 0
          GETFIELD org/nlogo/prim/_asm_procedurespreadvirus_ask_0.world : Lorg/nlogo/agent/World;
          INVOKEVIRTUAL org/nlogo/agent/World.patches ()Lorg/nlogo/agent/AgentSet;
          IF_ACMPNE L7
          NEW org/nlogo/nvm/EngineException
          DUP
          ALOAD 1
          ALOAD 0
          INVOKESTATIC org/nlogo/core/I18N.errorsJ ()Lorg/nlogo/core/I18NJava;
          LDC "org.nlogo.prim.$common.onlyObserverCanAskAllPatches"
          INVOKEINTERFACE org/nlogo/core/I18NJava.get (Ljava/lang/String;)Ljava/lang/String;
          INVOKESPECIAL org/nlogo/nvm/EngineException.<init> (Lorg/nlogo/nvm/Context;Lorg/nlogo/nvm/Instruction;Ljava/lang/String;)V
          ATHROW
         L7
         FRAME SAME
          ALOAD 1
          ALOAD 2
          ICONST_1
          INVOKEVIRTUAL org/nlogo/nvm/Context.runExclusiveJob (Lorg/nlogo/agent/AgentSet;I)V
          ALOAD 1
          BIPUSH 6
          PUTFIELD org/nlogo/nvm/Context.ip : I
         L9
          RETURN
[1]_asm_procedurespreadvirus_ask_2 "ask link-neighbors with [ not resistant? ] [ if random-float 100 < virus-spread-chance [ become-infected ] ]" AgentSet => void
      _with "link-neighbors with [ not resistant? ]" AgentSet,Reporter => AgentSet
        _linkneighbors:null "link-neighbors" => AgentSet
        _asm_procedurespreadvirus_not_3 "not resistant?" boolean => boolean
          _turtlevariable:RESISTANT? "resistant?" => Object
              TRYCATCHBLOCK L0 L1 L2 org/nlogo/api/AgentException
              TRYCATCHBLOCK L3 L4 L4 java/lang/ClassCastException
             L0
              ALOAD 1
              GETFIELD org/nlogo/nvm/Context.agent : Lorg/nlogo/agent/Agent;
              BIPUSH 14
              INVOKEVIRTUAL org/nlogo/agent/Agent.getTurtleVariable (I)Ljava/lang/Object;
             L1
              GOTO L5
             L2
             FRAME SAME1 org/nlogo/api/AgentException
              ASTORE 2
              NEW org/nlogo/nvm/EngineException
              DUP
              ALOAD 1
              ALOAD 0
              ALOAD 2
              INVOKEVIRTUAL org/nlogo/api/AgentException.getMessage ()Ljava/lang/String;
              INVOKESPECIAL org/nlogo/nvm/EngineException.<init> (Lorg/nlogo/nvm/Context;Lorg/nlogo/nvm/Instruction;Ljava/lang/String;)V
              ATHROW
             L5
             FRAME SAME1 java/lang/Object
              ASTORE 2
             L3
              ALOAD 2
              CHECKCAST java/lang/Boolean
              INVOKEVIRTUAL java/lang/Boolean.booleanValue ()Z
              GOTO L6
             L4
             FRAME FULL [org/nlogo/prim/_asm_procedurespreadvirus_not_3 org/nlogo/nvm/Context java/lang/Object] [java/lang/ClassCastException]
              POP
              NEW org/nlogo/nvm/ArgumentTypeException
              DUP
              ALOAD 1
              ALOAD 0
              BIPUSH 0
              LDC 2
              ALOAD 2
              INVOKESPECIAL org/nlogo/nvm/ArgumentTypeException.<init> (Lorg/nlogo/nvm/Context;Lorg/nlogo/nvm/Instruction;IILjava/lang/Object;)V
              ATHROW
             L6
             FRAME SAME1 I
              ISTORE 2
              ILOAD 2
              IFNE L7
              ICONST_1
              GOTO L8
             L7
             FRAME FULL [org/nlogo/prim/_asm_procedurespreadvirus_not_3 org/nlogo/nvm/Context I] []
              ICONST_0
             L8
             FRAME SAME1 I
              IFEQ L9
              GETSTATIC java/lang/Boolean.TRUE : Ljava/lang/Boolean;
              GOTO L10
             L9
             FRAME SAME
              GETSTATIC java/lang/Boolean.FALSE : Ljava/lang/Boolean;
             L10
             FRAME SAME1 java/lang/Boolean
              ARETURN
         L0
          ALOAD 0
          GETFIELD org/nlogo/prim/_asm_procedurespreadvirus_ask_2.kept3_breedName : Ljava/lang/String;
          IFNONNULL L1
          ALOAD 0
          GETFIELD org/nlogo/prim/_asm_procedurespreadvirus_ask_2.world : Lorg/nlogo/agent/World;
          INVOKEVIRTUAL org/nlogo/agent/World.links ()Lorg/nlogo/agent/AgentSet;
          GOTO L2
         L1
         FRAME SAME
          ALOAD 0
          GETFIELD org/nlogo/prim/_asm_procedurespreadvirus_ask_2.world : Lorg/nlogo/agent/World;
          ALOAD 0
          GETFIELD org/nlogo/prim/_asm_procedurespreadvirus_ask_2.kept3_breedName : Ljava/lang/String;
          INVOKEVIRTUAL org/nlogo/agent/World.getLinkBreed (Ljava/lang/String;)Lorg/nlogo/agent/AgentSet;
         L2
         FRAME SAME1 org/nlogo/agent/AgentSet
          ASTORE 2
          ALOAD 0
          ALOAD 2
          ALOAD 1
          INVOKEVIRTUAL org/nlogo/prim/_asm_procedurespreadvirus_ask_2.mustNotBeDirected (Lorg/nlogo/agent/AgentSet;Lorg/nlogo/nvm/Context;)V
          ALOAD 0
          GETFIELD org/nlogo/prim/_asm_procedurespreadvirus_ask_2.world : Lorg/nlogo/agent/World;
          GETFIELD org/nlogo/agent/World.linkManager : Lorg/nlogo/agent/LinkManager;
          ALOAD 1
          GETFIELD org/nlogo/nvm/Context.agent : Lorg/nlogo/agent/Agent;
          CHECKCAST org/nlogo/agent/Turtle
          ALOAD 2
          INVOKEVIRTUAL org/nlogo/agent/LinkManager.findLinkedWith (Lorg/nlogo/agent/Turtle;Lorg/nlogo/agent/AgentSet;)Lorg/nlogo/agent/AgentSet;
         L3
          ALOAD 0
          GETFIELD org/nlogo/prim/_asm_procedurespreadvirus_ask_2.keptinstr4 : Lorg/nlogo/nvm/Reporter;
          ASTORE 3
          ASTORE 2
          NEW org/nlogo/nvm/Context
          DUP
          ALOAD 1
          ALOAD 2
          INVOKESPECIAL org/nlogo/nvm/Context.<init> (Lorg/nlogo/nvm/Context;Lorg/nlogo/agent/AgentSet;)V
          ASTORE 4
          NEW java/util/ArrayList
          DUP
          INVOKESPECIAL java/util/ArrayList.<init> ()V
          ASTORE 5
          ALOAD 3
          ALOAD 2
          ALOAD 1
          INVOKEVIRTUAL org/nlogo/nvm/Reporter.checkAgentSetClass (Lorg/nlogo/agent/AgentSet;Lorg/nlogo/nvm/Context;)V
          ALOAD 2
          INVOKEVIRTUAL org/nlogo/agent/AgentSet.iterator ()Lorg/nlogo/agent/AgentSet$Iterator;
          ASTORE 6
         L4
         FRAME FULL [org/nlogo/prim/_asm_procedurespreadvirus_ask_2 org/nlogo/nvm/Context org/nlogo/agent/AgentSet org/nlogo/nvm/Reporter org/nlogo/nvm/Context java/util/ArrayList org/nlogo/agent/AgentSet$Iterator] []
          ALOAD 6
          INVOKEINTERFACE org/nlogo/agent/AgentSet$Iterator.hasNext ()Z
          IFEQ L5
          ALOAD 6
          INVOKEINTERFACE org/nlogo/agent/AgentSet$Iterator.next ()Lorg/nlogo/agent/Agent;
          ASTORE 7
          ALOAD 4
          ALOAD 7
          ALOAD 3
          INVOKEVIRTUAL org/nlogo/nvm/Context.evaluateReporter (Lorg/nlogo/agent/Agent;Lorg/nlogo/nvm/Reporter;)Ljava/lang/Object;
          ASTORE 8
          ALOAD 8
          INSTANCEOF java/lang/Boolean
          IFNE L6
          NEW org/nlogo/nvm/EngineException
          DUP
          ALOAD 1
          ALOAD 0
          INVOKESTATIC org/nlogo/core/I18N.errorsJ ()Lorg/nlogo/core/I18NJava;
          LDC "org.nlogo.prim.$common.expectedBooleanValue"
          ICONST_3
          ANEWARRAY java/lang/Object
          DUP
          ICONST_0
          LDC "WITH"
          AASTORE
          DUP
          ICONST_1
          ALOAD 7
          INVOKESTATIC org/nlogo/api/Dump.logoObject (Ljava/lang/Object;)Ljava/lang/String;
          AASTORE
          DUP
          ICONST_2
          ALOAD 8
          INVOKESTATIC org/nlogo/api/Dump.logoObject (Ljava/lang/Object;)Ljava/lang/String;
          AASTORE
          INVOKEINTERFACE org/nlogo/core/I18NJava.getN (Ljava/lang/String;[Ljava/lang/Object;)Ljava/lang/String;
          INVOKESPECIAL org/nlogo/nvm/EngineException.<init> (Lorg/nlogo/nvm/Context;Lorg/nlogo/nvm/Instruction;Ljava/lang/String;)V
          ATHROW
         L6
         FRAME APPEND [org/nlogo/agent/Agent java/lang/Object]
          ALOAD 8
          CHECKCAST java/lang/Boolean
          INVOKEVIRTUAL java/lang/Boolean.booleanValue ()Z
          IFEQ L7
          ALOAD 5
          ALOAD 7
          INVOKEINTERFACE java/util/List.add (Ljava/lang/Object;)Z
          POP
         L7
         FRAME SAME
          GOTO L4
         L5
         FRAME CHOP 2
          NEW org/nlogo/agent/ArrayAgentSet
          DUP
          ALOAD 2
          INVOKEVIRTUAL org/nlogo/agent/AgentSet.kind ()Lorg/nlogo/core/AgentKind;
          ALOAD 5
          ALOAD 5
          INVOKEINTERFACE java/util/List.size ()I
          ANEWARRAY org/nlogo/agent/Agent
          INVOKEINTERFACE java/util/List.toArray ([Ljava/lang/Object;)[Ljava/lang/Object;
          CHECKCAST [Lorg/nlogo/agent/Agent;
          INVOKESPECIAL org/nlogo/agent/ArrayAgentSet.<init> (Lorg/nlogo/core/AgentKind;[Lorg/nlogo/agent/Agent;)V
         L8
          ASTORE 2
          ALOAD 1
          GETFIELD org/nlogo/nvm/Context.agent : Lorg/nlogo/agent/Agent;
          INSTANCEOF org/nlogo/agent/Observer
          IFNE L9
          ALOAD 2
          ALOAD 0
          GETFIELD org/nlogo/prim/_asm_procedurespreadvirus_ask_2.world : Lorg/nlogo/agent/World;
          INVOKEVIRTUAL org/nlogo/agent/World.turtles ()Lorg/nlogo/agent/AgentSet;
          IF_ACMPNE L10
          NEW org/nlogo/nvm/EngineException
          DUP
          ALOAD 1
          ALOAD 0
          INVOKESTATIC org/nlogo/core/I18N.errorsJ ()Lorg/nlogo/core/I18NJava;
          LDC "org.nlogo.prim.$common.onlyObserverCanAskAllTurtles"
          INVOKEINTERFACE org/nlogo/core/I18NJava.get (Ljava/lang/String;)Ljava/lang/String;
          INVOKESPECIAL org/nlogo/nvm/EngineException.<init> (Lorg/nlogo/nvm/Context;Lorg/nlogo/nvm/Instruction;Ljava/lang/String;)V
          ATHROW
         L10
         FRAME FULL [org/nlogo/prim/_asm_procedurespreadvirus_ask_2 org/nlogo/nvm/Context org/nlogo/agent/ArrayAgentSet org/nlogo/nvm/Reporter org/nlogo/nvm/Context java/util/ArrayList org/nlogo/agent/AgentSet$Iterator] []
          ALOAD 2
          ALOAD 0
          GETFIELD org/nlogo/prim/_asm_procedurespreadvirus_ask_2.world : Lorg/nlogo/agent/World;
          INVOKEVIRTUAL org/nlogo/agent/World.patches ()Lorg/nlogo/agent/AgentSet;
          IF_ACMPNE L9
          NEW org/nlogo/nvm/EngineException
          DUP
          ALOAD 1
          ALOAD 0
          INVOKESTATIC org/nlogo/core/I18N.errorsJ ()Lorg/nlogo/core/I18NJava;
          LDC "org.nlogo.prim.$common.onlyObserverCanAskAllPatches"
          INVOKEINTERFACE org/nlogo/core/I18NJava.get (Ljava/lang/String;)Ljava/lang/String;
          INVOKESPECIAL org/nlogo/nvm/EngineException.<init> (Lorg/nlogo/nvm/Context;Lorg/nlogo/nvm/Instruction;Ljava/lang/String;)V
          ATHROW
         L9
         FRAME SAME
          ALOAD 1
          ALOAD 2
          ICONST_2
          INVOKEVIRTUAL org/nlogo/nvm/Context.runExclusiveJob (Lorg/nlogo/agent/AgentSet;I)V
          ALOAD 1
          ICONST_5
          PUTFIELD org/nlogo/nvm/Context.ip : I
         L11
          RETURN
[2]_asm_procedurespreadvirus_if_4 "if random-float 100 < virus-spread-chance [ become-infected ]" boolean => void
      _lessthan "random-float 100 < virus-spread-chance" double,Object => boolean
        _randomfloat "random-float 100" double => double
          _constdouble:100.0 "100" => double
        _observervariable:VIRUS-SPREAD-CHANCE "virus-spread-chance" => Object
         L0
          LDC 100.0
         L1
          DSTORE 2
          ALOAD 0
          DLOAD 2
          ALOAD 1
          GETFIELD org/nlogo/nvm/Context.job : Lorg/nlogo/nvm/Job;
          GETFIELD org/nlogo/nvm/Job.random : Lorg/nlogo/api/MersenneTwisterFast;
          INVOKEVIRTUAL org/nlogo/api/MersenneTwisterFast.nextDouble ()D
          DMUL
          INVOKEVIRTUAL org/nlogo/prim/_asm_procedurespreadvirus_if_4.validDouble (D)D
         L2
          ALOAD 1
          GETFIELD org/nlogo/nvm/Context.agent : Lorg/nlogo/agent/Agent;
          ICONST_2
          INVOKEVIRTUAL org/nlogo/agent/Agent.getObserverVariable (I)Ljava/lang/Object;
         L3
          ASTORE 4
          DSTORE 2
          ALOAD 4
          INSTANCEOF java/lang/Double
          IFEQ L4
          DLOAD 2
          ALOAD 4
          CHECKCAST java/lang/Double
          INVOKEVIRTUAL java/lang/Double.doubleValue ()D
          DCMPG
          IFGE L5
          ICONST_1
          GOTO L6
         L5
         FRAME APPEND [D java/lang/Object]
          ICONST_0
         L6
         FRAME SAME1 I
          GOTO L7
         L4
         FRAME SAME
          NEW org/nlogo/nvm/EngineException
          DUP
          ALOAD 1
          ALOAD 0
          INVOKESTATIC org/nlogo/core/I18N.errorsJ ()Lorg/nlogo/core/I18NJava;
          LDC "org.nlogo.prim._lessthan.cantUseLessthanOnDifferentArgs"
          ICONST_2
          ANEWARRAY java/lang/Object
          DUP
          ICONST_0
          DLOAD 2
          INVOKESTATIC java/lang/Double.valueOf (D)Ljava/lang/Double;
          INVOKESTATIC org/nlogo/api/TypeNames.aName (Ljava/lang/Object;)Ljava/lang/String;
          AASTORE
          DUP
          ICONST_1
          ALOAD 4
          INVOKESTATIC org/nlogo/api/TypeNames.aName (Ljava/lang/Object;)Ljava/lang/String;
          AASTORE
          INVOKEINTERFACE org/nlogo/core/I18NJava.getN (Ljava/lang/String;[Ljava/lang/Object;)Ljava/lang/String;
          INVOKESPECIAL org/nlogo/nvm/EngineException.<init> (Lorg/nlogo/nvm/Context;Lorg/nlogo/nvm/Instruction;Ljava/lang/String;)V
          ATHROW
         L7
         FRAME SAME1 I
          ISTORE 2
          ALOAD 1
          ILOAD 2
          IFEQ L8
          ICONST_3
          GOTO L9
         L8
         FRAME FULL [org/nlogo/prim/_asm_procedurespreadvirus_if_4 org/nlogo/nvm/Context I T java/lang/Object] [org/nlogo/nvm/Context]
          ICONST_4
         L9
         FRAME FULL [org/nlogo/prim/_asm_procedurespreadvirus_if_4 org/nlogo/nvm/Context I T java/lang/Object] [org/nlogo/nvm/Context I]
          PUTFIELD org/nlogo/nvm/Context.ip : I
         L10
          RETURN
[3]_asm_procedurespreadvirus_call_5 "become-infected"
         L0
          NEW org/nlogo/nvm/Activation
          DUP
          ALOAD 0
          GETFIELD org/nlogo/prim/_asm_procedurespreadvirus_call_5.kept1_procedure : Lorg/nlogo/nvm/Procedure;
          ALOAD 1
          GETFIELD org/nlogo/nvm/Context.activation : Lorg/nlogo/nvm/Activation;
          ICONST_4
          INVOKESPECIAL org/nlogo/nvm/Activation.<init> (Lorg/nlogo/nvm/Procedure;Lorg/nlogo/nvm/Activation;I)V
          ALOAD 1
          SWAP
          PUTFIELD org/nlogo/nvm/Context.activation : Lorg/nlogo/nvm/Activation;
          ALOAD 1
          ICONST_0
          PUTFIELD org/nlogo/nvm/Context.ip : I
         L1
          RETURN
[4]_asm_procedurespreadvirus_done_6 => void
         L0
          ALOAD 1
          ICONST_1
          PUTFIELD org/nlogo/nvm/Context.finished : Z
         L1
          RETURN
[5]_asm_procedurespreadvirus_done_7 => void
         L0
          ALOAD 1
          ICONST_1
          PUTFIELD org/nlogo/nvm/Context.finished : Z
         L1
          RETURN
[6]_asm_procedurespreadvirus_return_8 => void
         L0
          ALOAD 1
          INVOKEVIRTUAL org/nlogo/nvm/Context.returnFromProcedure ()V
          ALOAD 1
          ICONST_0
          PUTFIELD org/nlogo/nvm/Context.stopping : Z
         L1
          RETURN

procedure SETUP-NODES:[]{O---}:
[0]_setdefaultshape "set-default-shape turtles "circle""
      _asm_proceduresetupnodes_turtles_0 "turtles" => AgentSet
           L0
            ALOAD 0
            GETFIELD org/nlogo/prim/_asm_proceduresetupnodes_turtles_0.world : Lorg/nlogo/agent/World;
            INVOKEVIRTUAL org/nlogo/agent/World.turtles ()Lorg/nlogo/agent/AgentSet;
           L1
            ARETURN
      _asm_proceduresetupnodes_conststring_1 ""circle"" => String
           L0
            LDC "circle"
           L1
            ARETURN
[1]_createturtles:,+6 "crt number-of-nodes setxy random-xcor * 0.95 random-ycor * 0.95 become-susceptible [ set virus-check-timer random virus-check-frequency ]"
      _asm_proceduresetupnodes_observervariable_2 "number-of-nodes" => Object
           L0
            ALOAD 1
            GETFIELD org/nlogo/nvm/Context.agent : Lorg/nlogo/agent/Agent;
            ICONST_3
            INVOKEVIRTUAL org/nlogo/agent/Agent.getObserverVariable (I)Ljava/lang/Object;
           L1
            ARETURN
[2]_asm_proceduresetupnodes_setxy_3 "setxy random-xcor * 0.95 random-ycor * 0.95" double,double => void
      _mult "random-xcor * 0.95" double,double => double
        _randomxcor "random-xcor" => double
        _constdouble:0.95 "0.95" => double
      _mult "random-ycor * 0.95" double,double => double
        _randomycor "random-ycor" => double
        _constdouble:0.95 "0.95" => double
          TRYCATCHBLOCK L0 L1 L2 org/nlogo/api/AgentException
         L3
          ALOAD 0
          GETFIELD org/nlogo/prim/_asm_proceduresetupnodes_setxy_3.world : Lorg/nlogo/agent/World;
          INVOKEVIRTUAL org/nlogo/agent/World.minPxcor ()I
          I2D
          LDC 0.5
          DSUB
          DSTORE 2
          ALOAD 0
          GETFIELD org/nlogo/prim/_asm_proceduresetupnodes_setxy_3.world : Lorg/nlogo/agent/World;
          INVOKEVIRTUAL org/nlogo/agent/World.maxPxcor ()I
          I2D
          LDC 0.5
          DADD
          DSTORE 4
          DLOAD 2
          ALOAD 1
          GETFIELD org/nlogo/nvm/Context.job : Lorg/nlogo/nvm/Job;
          GETFIELD org/nlogo/nvm/Job.random : Lorg/nlogo/api/MersenneTwisterFast;
          INVOKEVIRTUAL org/nlogo/api/MersenneTwisterFast.nextDouble ()D
          DLOAD 4
          DLOAD 2
          DSUB
          DMUL
          DADD
         L4
          LDC 0.95
         L5
          DSTORE 4
          DSTORE 2
          ALOAD 0
          DLOAD 2
          DLOAD 4
          DMUL
          INVOKEVIRTUAL org/nlogo/prim/_asm_proceduresetupnodes_setxy_3.validDouble (D)D
         L6
          ALOAD 0
          GETFIELD org/nlogo/prim/_asm_proceduresetupnodes_setxy_3.world : Lorg/nlogo/agent/World;
          INVOKEVIRTUAL org/nlogo/agent/World.minPycor ()I
          I2D
          LDC 0.5
          DSUB
          DSTORE 2
          ALOAD 0
          GETFIELD org/nlogo/prim/_asm_proceduresetupnodes_setxy_3.world : Lorg/nlogo/agent/World;
          INVOKEVIRTUAL org/nlogo/agent/World.maxPycor ()I
          I2D
          LDC 0.5
          DADD
          DSTORE 4
          DLOAD 2
          ALOAD 1
          GETFIELD org/nlogo/nvm/Context.job : Lorg/nlogo/nvm/Job;
          GETFIELD org/nlogo/nvm/Job.random : Lorg/nlogo/api/MersenneTwisterFast;
          INVOKEVIRTUAL org/nlogo/api/MersenneTwisterFast.nextDouble ()D
          DLOAD 4
          DLOAD 2
          DSUB
          DMUL
          DADD
         L7
          LDC 0.95
         L8
          DSTORE 4
          DSTORE 2
          ALOAD 0
          DLOAD 2
          DLOAD 4
          DMUL
          INVOKEVIRTUAL org/nlogo/prim/_asm_proceduresetupnodes_setxy_3.validDouble (D)D
         L9
          DSTORE 4
          DSTORE 2
          ALOAD 1
          GETFIELD org/nlogo/nvm/Context.agent : Lorg/nlogo/agent/Agent;
          CHECKCAST org/nlogo/agent/Turtle
          ASTORE 6
         L0
          ALOAD 6
          ALOAD 6
          DLOAD 2
          INVOKEVIRTUAL org/nlogo/agent/Turtle.shortestPathX (D)D
          ALOAD 6
          DLOAD 4
          INVOKEVIRTUAL org/nlogo/agent/Turtle.shortestPathY (D)D
          INVOKEVIRTUAL org/nlogo/agent/Turtle.xandycor (DD)V
         L1
          GOTO L10
         L2
         FRAME FULL [org/nlogo/prim/_asm_proceduresetupnodes_setxy_3 org/nlogo/nvm/Context D D org/nlogo/agent/Turtle] [org/nlogo/api/AgentException]
          ASTORE 7
          NEW org/nlogo/nvm/EngineException
          DUP
          ALOAD 1
          ALOAD 0
          INVOKESTATIC org/nlogo/core/I18N.errorsJ ()Lorg/nlogo/core/I18NJava;
          LDC "org.nlogo.prim.etc._setxy.pointOutsideWorld"
          ICONST_2
          ANEWARRAY java/lang/Object
          DUP
          ICONST_0
          DLOAD 2
          INVOKESTATIC java/lang/Double.valueOf (D)Ljava/lang/Double;
          AASTORE
          DUP
          ICONST_1
          DLOAD 4
          INVOKESTATIC java/lang/Double.valueOf (D)Ljava/lang/Double;
          AASTORE
          INVOKEINTERFACE org/nlogo/core/I18NJava.getN (Ljava/lang/String;[Ljava/lang/Object;)Ljava/lang/String;
          INVOKESPECIAL org/nlogo/nvm/EngineException.<init> (Lorg/nlogo/nvm/Context;Lorg/nlogo/nvm/Instruction;Ljava/lang/String;)V
          ATHROW
         L10
         FRAME SAME
          ALOAD 1
          ICONST_3
          PUTFIELD org/nlogo/nvm/Context.ip : I
         L11
          RETURN
[3]_asm_proceduresetupnodes_call_4 "become-susceptible"
         L0
          NEW org/nlogo/nvm/Activation
          DUP
          ALOAD 0
          GETFIELD org/nlogo/prim/_asm_proceduresetupnodes_call_4.kept1_procedure : Lorg/nlogo/nvm/Procedure;
          ALOAD 1
          GETFIELD org/nlogo/nvm/Context.activation : Lorg/nlogo/nvm/Activation;
          ICONST_4
          INVOKESPECIAL org/nlogo/nvm/Activation.<init> (Lorg/nlogo/nvm/Procedure;Lorg/nlogo/nvm/Activation;I)V
          ALOAD 1
          SWAP
          PUTFIELD org/nlogo/nvm/Context.activation : Lorg/nlogo/nvm/Activation;
          ALOAD 1
          ICONST_0
          PUTFIELD org/nlogo/nvm/Context.ip : I
         L1
          RETURN
[4]_asm_proceduresetupnodes_setturtlevariable_5 "set virus-check-timer random virus-check-frequency" Object => void
      _random "random virus-check-frequency" double => double
        _observervariable:VIRUS-CHECK-FREQUENCY "virus-check-frequency" => Object
          TRYCATCHBLOCK L0 L1 L1 java/lang/ClassCastException
          TRYCATCHBLOCK L2 L3 L4 org/nlogo/api/AgentException
         L5
          ALOAD 1
          GETFIELD org/nlogo/nvm/Context.agent : Lorg/nlogo/agent/Agent;
          ICONST_4
          INVOKEVIRTUAL org/nlogo/agent/Agent.getObserverVariable (I)Ljava/lang/Object;
         L6
          ASTORE 2
         L0
          ALOAD 2
          CHECKCAST java/lang/Double
          INVOKEVIRTUAL java/lang/Double.doubleValue ()D
          GOTO L7
         L1
         FRAME FULL [org/nlogo/prim/_asm_proceduresetupnodes_setturtlevariable_5 org/nlogo/nvm/Context java/lang/Object] [java/lang/ClassCastException]
          POP
          NEW org/nlogo/nvm/ArgumentTypeException
          DUP
          ALOAD 1
          ALOAD 0
          BIPUSH 0
          LDC 1
          ALOAD 2
          INVOKESPECIAL org/nlogo/nvm/ArgumentTypeException.<init> (Lorg/nlogo/nvm/Context;Lorg/nlogo/nvm/Instruction;IILjava/lang/Object;)V
          ATHROW
         L7
         FRAME SAME1 D
          DSTORE 2
          ALOAD 0
          DLOAD 2
          INVOKEVIRTUAL org/nlogo/prim/_asm_proceduresetupnodes_setturtlevariable_5.validLong (D)J
          LSTORE 4
          DLOAD 2
          LLOAD 4
          L2D
          DCMPL
          IFEQ L8
          LLOAD 4
          DLOAD 2
          DCONST_0
          DCMPL
          IFLT L9
          LCONST_1
          GOTO L10
         L9
         FRAME FULL [org/nlogo/prim/_asm_proceduresetupnodes_setturtlevariable_5 org/nlogo/nvm/Context D J] [J]
          LDC -1
         L10
         FRAME FULL [org/nlogo/prim/_asm_proceduresetupnodes_setturtlevariable_5 org/nlogo/nvm/Context D J] [J J]
          LADD
          LSTORE 4
         L8
         FRAME SAME
          LLOAD 4
          LCONST_0
          LCMP
          IFLE L11
          ALOAD 1
          GETFIELD org/nlogo/nvm/Context.job : Lorg/nlogo/nvm/Job;
          GETFIELD org/nlogo/nvm/Job.random : Lorg/nlogo/api/MersenneTwisterFast;
          LLOAD 4
          INVOKEVIRTUAL org/nlogo/api/MersenneTwisterFast.nextLong (J)J
          L2D
          GOTO L12
         L11
         FRAME SAME
          LLOAD 4
          LCONST_0
          LCMP
          IFGE L13
          ALOAD 1
          GETFIELD org/nlogo/nvm/Context.job : Lorg/nlogo/nvm/Job;
          GETFIELD org/nlogo/nvm/Job.random : Lorg/nlogo/api/MersenneTwisterFast;
          LLOAD 4
          LNEG
          INVOKEVIRTUAL org/nlogo/api/MersenneTwisterFast.nextLong (J)J
          LNEG
          L2D
          GOTO L12
         L13
         FRAME SAME
          DCONST_0
         L12
         FRAME SAME1 D
          DSTORE 2
          NEW java/lang/Double
          DUP
          DLOAD 2
          INVOKESPECIAL java/lang/Double.<init> (D)V
          ASTORE 2
         L2
          ALOAD 1
          GETFIELD org/nlogo/nvm/Context.agent : Lorg/nlogo/agent/Agent;
          BIPUSH 15
          ALOAD 2
          INVOKEVIRTUAL org/nlogo/agent/Agent.setTurtleVariable (ILjava/lang/Object;)V
         L3
          GOTO L14
         L4
         FRAME FULL [org/nlogo/prim/_asm_proceduresetupnodes_setturtlevariable_5 org/nlogo/nvm/Context java/lang/Double T J] [org/nlogo/api/AgentException]
          ASTORE 3
          NEW org/nlogo/nvm/EngineException
          DUP
          ALOAD 1
          ALOAD 0
          ALOAD 3
          INVOKEVIRTUAL org/nlogo/api/AgentException.getMessage ()Ljava/lang/String;
          INVOKESPECIAL org/nlogo/nvm/EngineException.<init> (Lorg/nlogo/nvm/Context;Lorg/nlogo/nvm/Instruction;Ljava/lang/String;)V
          ATHROW
         L14
         FRAME SAME
          ALOAD 1
          ICONST_5
          PUTFIELD org/nlogo/nvm/Context.ip : I
         L15
          RETURN
[5]_asm_proceduresetupnodes_done_6 => void
         L0
          ALOAD 1
          ICONST_1
          PUTFIELD org/nlogo/nvm/Context.finished : Z
         L1
          RETURN
[6]_asm_proceduresetupnodes_return_7 => void
         L0
          ALOAD 1
          INVOKEVIRTUAL org/nlogo/nvm/Context.returnFromProcedure ()V
          ALOAD 1
          ICONST_0
          PUTFIELD org/nlogo/nvm/Context.stopping : Z
         L1
          RETURN

procedure BECOME-INFECTED:[]{-T--}:
[0]_asm_procedurebecomeinfected_setturtlevariable_0 "set infected? true" Object => void
      _constboolean:true "true" => Boolean
          TRYCATCHBLOCK L0 L1 L2 org/nlogo/api/AgentException
         L3
          ALOAD 0
          GETFIELD org/nlogo/prim/_asm_procedurebecomeinfected_setturtlevariable_0.kept2_value : Ljava/lang/Boolean;
         L4
          ASTORE 2
         L0
          ALOAD 1
          GETFIELD org/nlogo/nvm/Context.agent : Lorg/nlogo/agent/Agent;
          BIPUSH 13
          ALOAD 2
          INVOKEVIRTUAL org/nlogo/agent/Agent.setTurtleVariable (ILjava/lang/Object;)V
         L1
          GOTO L5
         L2
         FRAME FULL [org/nlogo/prim/_asm_procedurebecomeinfected_setturtlevariable_0 org/nlogo/nvm/Context java/lang/Boolean] [org/nlogo/api/AgentException]
          ASTORE 3
          NEW org/nlogo/nvm/EngineException
          DUP
          ALOAD 1
          ALOAD 0
          ALOAD 3
          INVOKEVIRTUAL org/nlogo/api/AgentException.getMessage ()Ljava/lang/String;
          INVOKESPECIAL org/nlogo/nvm/EngineException.<init> (Lorg/nlogo/nvm/Context;Lorg/nlogo/nvm/Instruction;Ljava/lang/String;)V
          ATHROW
         L5
         FRAME SAME
          ALOAD 1
          ICONST_1
          PUTFIELD org/nlogo/nvm/Context.ip : I
         L6
          RETURN
[1]_asm_procedurebecomeinfected_setturtlevariable_1 "set resistant? false" Object => void
      _constboolean:false "false" => Boolean
          TRYCATCHBLOCK L0 L1 L2 org/nlogo/api/AgentException
         L3
          ALOAD 0
          GETFIELD org/nlogo/prim/_asm_procedurebecomeinfected_setturtlevariable_1.kept2_value : Ljava/lang/Boolean;
         L4
          ASTORE 2
         L0
          ALOAD 1
          GETFIELD org/nlogo/nvm/Context.agent : Lorg/nlogo/agent/Agent;
          BIPUSH 14
          ALOAD 2
          INVOKEVIRTUAL org/nlogo/agent/Agent.setTurtleVariable (ILjava/lang/Object;)V
         L1
          GOTO L5
         L2
         FRAME FULL [org/nlogo/prim/_asm_procedurebecomeinfected_setturtlevariable_1 org/nlogo/nvm/Context java/lang/Boolean] [org/nlogo/api/AgentException]
          ASTORE 3
          NEW org/nlogo/nvm/EngineException
          DUP
          ALOAD 1
          ALOAD 0
          ALOAD 3
          INVOKEVIRTUAL org/nlogo/api/AgentException.getMessage ()Ljava/lang/String;
          INVOKESPECIAL org/nlogo/nvm/EngineException.<init> (Lorg/nlogo/nvm/Context;Lorg/nlogo/nvm/Instruction;Ljava/lang/String;)V
          ATHROW
         L5
         FRAME SAME
          ALOAD 1
          ICONST_2
          PUTFIELD org/nlogo/nvm/Context.ip : I
         L6
          RETURN
[2]_asm_procedurebecomeinfected_setturtleorlinkvariable_2 "set color red" Object => void
      _constdouble:15.0 "red" => Double
          TRYCATCHBLOCK L0 L1 L2 org/nlogo/api/AgentException
         L3
          ALOAD 0
          GETFIELD org/nlogo/prim/_asm_procedurebecomeinfected_setturtleorlinkvariable_2.kept2_value : Ljava/lang/Double;
         L4
          ASTORE 2
         L0
          ALOAD 1
          GETFIELD org/nlogo/nvm/Context.agent : Lorg/nlogo/agent/Agent;
          LDC "COLOR"
          ALOAD 2
          INVOKEVIRTUAL org/nlogo/agent/Agent.setTurtleOrLinkVariable (Ljava/lang/String;Ljava/lang/Object;)V
         L1
          GOTO L5
         L2
         FRAME FULL [org/nlogo/prim/_asm_procedurebecomeinfected_setturtleorlinkvariable_2 org/nlogo/nvm/Context java/lang/Double] [org/nlogo/api/AgentException]
          ASTORE 3
          NEW org/nlogo/nvm/EngineException
          DUP
          ALOAD 1
          ALOAD 0
          ALOAD 3
          INVOKEVIRTUAL org/nlogo/api/AgentException.getMessage ()Ljava/lang/String;
          INVOKESPECIAL org/nlogo/nvm/EngineException.<init> (Lorg/nlogo/nvm/Context;Lorg/nlogo/nvm/Instruction;Ljava/lang/String;)V
          ATHROW
         L5
         FRAME SAME
          ALOAD 1
          ICONST_3
          PUTFIELD org/nlogo/nvm/Context.ip : I
         L6
          RETURN
[3]_asm_procedurebecomeinfected_return_3 => void
         L0
          ALOAD 1
          INVOKEVIRTUAL org/nlogo/nvm/Context.returnFromProcedure ()V
          ALOAD 1
          ICONST_0
          PUTFIELD org/nlogo/nvm/Context.stopping : Z
         L1
          RETURN

