globals [INIT-SHEEP SHEEP-METABOLISM SHEEP-REPRODUCE INIT-WOLVES WOLF-METABOLISM WOLF-REPRODUCE GRASS? GRASS-DELAY PLOT? RESULT]
interfaceGlobals [init-sheep sheep-metabolism sheep-reproduce init-wolves wolf-metabolism wolf-reproduce grass? grass-delay plot?]
turtles-own [WHO COLOR HEADING XCOR YCOR SHAPE LABEL LABEL-COLOR BREED HIDDEN? SIZE PEN-SIZE PEN-MODE ENERGY PREY]
patches-own [PXCOR PYCOR PCOLOR PLABEL PLABEL-COLOR COUNTDOWN]
links-own [END1 END2 COLOR LABEL LABEL-COLOR HIDDEN? BREED THICKNESS SHAPE TIE-MODE]
breeds SHEEP = Breed(SHEEP, A-SHEEP, , false)
WOLVES = Breed(WOLVES, WOLF, , false)
link-breeds 

procedure BENCHMARK:[_repeatlocal:0]{O---}:
[0]_asm_procedurebenchmark_randomseed_0 "random-seed 579" double => void
      _constdouble:579.0 => double
         L0
          LDC 579.0
         L1
          DSTORE 2
          DLOAD 2
          D2L
          LSTORE 4
          LLOAD 4
          LDC -2147483648
          LCMP
          IFLT L2
          LLOAD 4
          LDC 2147483647
          LCMP
          IFLE L3
         L2
          NEW org/nlogo/nvm/EngineException
          DUP
          ALOAD 1
          ALOAD 0
          NEW scala/collection/mutable/StringBuilder
          DUP
          INVOKESPECIAL scala/collection/mutable/StringBuilder.<init> ()V
          GETSTATIC org/nlogo/api/Dump$.MODULE$ : Lorg/nlogo/api/Dump$;
          DLOAD 2
          INVOKEVIRTUAL org/nlogo/api/Dump$.number (D)Ljava/lang/String;
          INVOKEVIRTUAL scala/collection/mutable/StringBuilder.append (Ljava/lang/Object;)Lscala/collection/mutable/StringBuilder;
          LDC " is not in the allowable range for random seeds (-2147483648 to 2147483647)"
          INVOKEVIRTUAL scala/collection/mutable/StringBuilder.append (Ljava/lang/Object;)Lscala/collection/mutable/StringBuilder;
          INVOKEVIRTUAL scala/collection/mutable/StringBuilder.toString ()Ljava/lang/String;
          INVOKESPECIAL org/nlogo/nvm/EngineException.<init> (Lorg/nlogo/nvm/Context;Lorg/nlogo/nvm/Instruction;Ljava/lang/String;)V
          ATHROW
         L3
          ALOAD 1
          GETFIELD org/nlogo/nvm/Context.job : Lorg/nlogo/nvm/Job;
          GETFIELD org/nlogo/nvm/Job.random : Lorg/nlogo/util/MersenneTwisterFast;
          LLOAD 4
          L2I
          I2L
          INVOKEVIRTUAL org/nlogo/util/MersenneTwisterFast.setSeed (J)V
          ALOAD 1
          ICONST_1
          PUTFIELD org/nlogo/nvm/Context.ip : I
         L4
          RETURN
[1]_asm_procedurebenchmark_call_1 "setup"
         L0
          NEW org/nlogo/nvm/Activation
          DUP
          ALOAD 0
          GETFIELD org/nlogo/prim/_asm_procedurebenchmark_call_1.kept1_procedure : Lorg/nlogo/nvm/Procedure;
          ALOAD 1
          GETFIELD org/nlogo/nvm/Context.activation : Lorg/nlogo/nvm/Activation;
          ICONST_2
          INVOKESPECIAL org/nlogo/nvm/Activation.<init> (Lorg/nlogo/nvm/Procedure;Lorg/nlogo/nvm/Activation;I)V
          ALOAD 1
          SWAP
          PUTFIELD org/nlogo/nvm/Context.activation : Lorg/nlogo/nvm/Activation;
          ALOAD 1
          ICONST_0
          PUTFIELD org/nlogo/nvm/Context.ip : I
         L1
          RETURN
[2]_resettimer
[3]_asm_procedurebenchmark_repeatlocal_2 "" double => void
      _constdouble:10000.0 => double
         L0
          LDC 10000.0
         L1
          DSTORE 2
          ALOAD 1
          GETFIELD org/nlogo/nvm/Context.activation : Lorg/nlogo/nvm/Activation;
          INVOKEVIRTUAL org/nlogo/nvm/Activation.args ()[Ljava/lang/Object;
          ICONST_0
          NEW org/nlogo/nvm/MutableLong
          DUP
          ALOAD 0
          DLOAD 2
          INVOKEVIRTUAL org/nlogo/prim/_asm_procedurebenchmark_repeatlocal_2.validLong (D)J
          INVOKESPECIAL org/nlogo/nvm/MutableLong.<init> (J)V
          AASTORE
          ALOAD 1
          ICONST_5
          PUTFIELD org/nlogo/nvm/Context.ip : I
         L2
          RETURN
[4]_asm_procedurebenchmark_call_3 "go"
         L0
          NEW org/nlogo/nvm/Activation
          DUP
          ALOAD 0
          GETFIELD org/nlogo/prim/_asm_procedurebenchmark_call_3.kept1_procedure : Lorg/nlogo/nvm/Procedure;
          ALOAD 1
          GETFIELD org/nlogo/nvm/Context.activation : Lorg/nlogo/nvm/Activation;
          ICONST_5
          INVOKESPECIAL org/nlogo/nvm/Activation.<init> (Lorg/nlogo/nvm/Procedure;Lorg/nlogo/nvm/Activation;I)V
          ALOAD 1
          SWAP
          PUTFIELD org/nlogo/nvm/Context.activation : Lorg/nlogo/nvm/Activation;
          ALOAD 1
          ICONST_0
          PUTFIELD org/nlogo/nvm/Context.ip : I
         L1
          RETURN
[5]_asm_procedurebenchmark_repeatlocalinternal_4 "" => void
         L0
          ALOAD 1
          GETFIELD org/nlogo/nvm/Context.activation : Lorg/nlogo/nvm/Activation;
          INVOKEVIRTUAL org/nlogo/nvm/Activation.args ()[Ljava/lang/Object;
          ICONST_0
          AALOAD
          CHECKCAST org/nlogo/nvm/MutableLong
          ASTORE 2
          ALOAD 2
          INVOKEVIRTUAL org/nlogo/nvm/MutableLong.value ()J
          LCONST_0
          LCMP
          IFGT L1
          ALOAD 1
          BIPUSH 6
          PUTFIELD org/nlogo/nvm/Context.ip : I
          GOTO L2
         L1
          ALOAD 2
          ALOAD 2
          INVOKEVIRTUAL org/nlogo/nvm/MutableLong.value ()J
          LCONST_1
          LSUB
          INVOKEVIRTUAL org/nlogo/nvm/MutableLong.value_$eq (J)V
          ALOAD 1
          ICONST_4
          PUTFIELD org/nlogo/nvm/Context.ip : I
         L2
          RETURN
[6]_asm_procedurebenchmark_setobservervariable_5 "set result timer" Object => void
      _timer => double
          TRYCATCHBLOCK L0 L1 L2 org/nlogo/api/AgentException
         L3
          ALOAD 0
          GETFIELD org/nlogo/prim/_asm_procedurebenchmark_setobservervariable_5.world : Lorg/nlogo/agent/World;
          INVOKEVIRTUAL org/nlogo/agent/World.timer ()Lorg/nlogo/api/Timer;
          INVOKEVIRTUAL org/nlogo/api/Timer.read ()D
         L4
          DSTORE 2
          NEW java/lang/Double
          DUP
          DLOAD 2
          INVOKESPECIAL java/lang/Double.<init> (D)V
          ASTORE 2
         L0
          ALOAD 1
          GETFIELD org/nlogo/nvm/Context.agent : Lorg/nlogo/agent/Agent;
          BIPUSH 9
          ALOAD 2
          INVOKEVIRTUAL org/nlogo/agent/Agent.setObserverVariable (ILjava/lang/Object;)V
         L1
          ALOAD 1
          BIPUSH 7
          PUTFIELD org/nlogo/nvm/Context.ip : I
          GOTO L5
         L2
          ASTORE 3
          NEW org/nlogo/nvm/EngineException
          DUP
          ALOAD 1
          ALOAD 0
          ALOAD 3
          INVOKEVIRTUAL org/nlogo/api/AgentException.getMessage ()Ljava/lang/String;
          INVOKESPECIAL org/nlogo/nvm/EngineException.<init> (Lorg/nlogo/nvm/Context;Lorg/nlogo/nvm/Instruction;Ljava/lang/String;)V
          ATHROW
         L5
          RETURN
[7]_asm_procedurebenchmark_return_6 "" => void
         L0
          ALOAD 1
          INVOKEVIRTUAL org/nlogo/nvm/Context.returnFromProcedure ()V
          ALOAD 1
          ICONST_0
          PUTFIELD org/nlogo/nvm/Context.stopping : Z
         L1
          RETURN

procedure SETUP:[]{O---}:
[0]_clearall
[1]_resetticks
[2]_asm_proceduresetup_ask_0 "ask patches" AgentSet => void
      _patches => AgentSet
         L0
          ALOAD 0
          GETFIELD org/nlogo/prim/_asm_proceduresetup_ask_0.world : Lorg/nlogo/agent/World;
          INVOKEVIRTUAL org/nlogo/agent/World.patches ()Lorg/nlogo/agent/AgentSet;
         L1
          ASTORE 2
          ALOAD 1
          GETFIELD org/nlogo/nvm/Context.agent : Lorg/nlogo/agent/Agent;
          INSTANCEOF org/nlogo/agent/Observer
          IFNE L2
          ALOAD 2
          ALOAD 0
          GETFIELD org/nlogo/prim/_asm_proceduresetup_ask_0.world : Lorg/nlogo/agent/World;
          INVOKEVIRTUAL org/nlogo/agent/World.turtles ()Lorg/nlogo/agent/AgentSet;
          IF_ACMPNE L3
          NEW org/nlogo/nvm/EngineException
          DUP
          ALOAD 1
          ALOAD 0
          GETSTATIC org/nlogo/api/I18N$.MODULE$ : Lorg/nlogo/api/I18N$;
          INVOKEVIRTUAL org/nlogo/api/I18N$.errors ()Lorg/nlogo/api/I18N$BundleKind;
          LDC "org.nlogo.prim.$common.onlyObserverCanAskAllTurtles"
          INVOKEVIRTUAL org/nlogo/api/I18N$BundleKind.get (Ljava/lang/String;)Ljava/lang/String;
          INVOKESPECIAL org/nlogo/nvm/EngineException.<init> (Lorg/nlogo/nvm/Context;Lorg/nlogo/nvm/Instruction;Ljava/lang/String;)V
          ATHROW
         L3
          ALOAD 2
          ALOAD 0
          GETFIELD org/nlogo/prim/_asm_proceduresetup_ask_0.world : Lorg/nlogo/agent/World;
          INVOKEVIRTUAL org/nlogo/agent/World.patches ()Lorg/nlogo/agent/AgentSet;
          IF_ACMPNE L2
          NEW org/nlogo/nvm/EngineException
          DUP
          ALOAD 1
          ALOAD 0
          GETSTATIC org/nlogo/api/I18N$.MODULE$ : Lorg/nlogo/api/I18N$;
          INVOKEVIRTUAL org/nlogo/api/I18N$.errors ()Lorg/nlogo/api/I18N$BundleKind;
          LDC "org.nlogo.prim.$common.onlyObserverCanAskAllPatches"
          INVOKEVIRTUAL org/nlogo/api/I18N$BundleKind.get (Ljava/lang/String;)Ljava/lang/String;
          INVOKESPECIAL org/nlogo/nvm/EngineException.<init> (Lorg/nlogo/nvm/Context;Lorg/nlogo/nvm/Instruction;Ljava/lang/String;)V
          ATHROW
         L2
          ALOAD 1
          ALOAD 2
          ICONST_3
          INVOKEVIRTUAL org/nlogo/nvm/Context.runExclusiveJob (Lorg/nlogo/agent/AgentSet;I)V
          ALOAD 1
          ICONST_5
          PUTFIELD org/nlogo/nvm/Context.ip : I
         L4
          RETURN
[3]_asm_proceduresetup_setpatchvariable_1 "set pcolor green" Object => void
      _constdouble:55.0 => Double
          TRYCATCHBLOCK L0 L1 L2 org/nlogo/api/AgentException
         L3
          ALOAD 0
          GETFIELD org/nlogo/prim/_asm_proceduresetup_setpatchvariable_1.kept2_value : Ljava/lang/Double;
         L4
          ASTORE 2
         L0
          ALOAD 1
          GETFIELD org/nlogo/nvm/Context.agent : Lorg/nlogo/agent/Agent;
          ICONST_2
          ALOAD 2
          INVOKEVIRTUAL org/nlogo/agent/Agent.setPatchVariable (ILjava/lang/Object;)V
         L1
          ALOAD 1
          ICONST_4
          PUTFIELD org/nlogo/nvm/Context.ip : I
          GOTO L5
         L2
          ASTORE 3
          NEW org/nlogo/nvm/EngineException
          DUP
          ALOAD 1
          ALOAD 0
          ALOAD 3
          INVOKEVIRTUAL org/nlogo/api/AgentException.getMessage ()Ljava/lang/String;
          INVOKESPECIAL org/nlogo/nvm/EngineException.<init> (Lorg/nlogo/nvm/Context;Lorg/nlogo/nvm/Instruction;Ljava/lang/String;)V
          ATHROW
         L5
          RETURN
[4]_asm_proceduresetup_done_2 "" => void
         L0
          ALOAD 1
          ICONST_1
          PUTFIELD org/nlogo/nvm/Context.finished : Z
         L1
          RETURN
[5]_asm_proceduresetup_if_3 "if grass?" boolean => void
      _observervariable:GRASS? => Object
          TRYCATCHBLOCK L0 L1 L1 java/lang/ClassCastException
         L2
          ALOAD 1
          GETFIELD org/nlogo/nvm/Context.agent : Lorg/nlogo/agent/Agent;
          BIPUSH 6
          INVOKEVIRTUAL org/nlogo/agent/Agent.getObserverVariable (I)Ljava/lang/Object;
         L3
          ASTORE 2
         L0
          ALOAD 2
          CHECKCAST java/lang/Boolean
          INVOKEVIRTUAL java/lang/Boolean.booleanValue ()Z
          GOTO L4
         L1
          POP
          NEW org/nlogo/nvm/ArgumentTypeException
          DUP
          ALOAD 1
          ALOAD 0
          BIPUSH 0
          LDC 2
          ALOAD 2
          INVOKESPECIAL org/nlogo/nvm/ArgumentTypeException.<init> (Lorg/nlogo/nvm/Context;Lorg/nlogo/nvm/Instruction;IILjava/lang/Object;)V
          ATHROW
         L4
          ISTORE 2
          ALOAD 1
          ILOAD 2
          IFEQ L5
          BIPUSH 6
          GOTO L6
         L5
          BIPUSH 11
         L6
          PUTFIELD org/nlogo/nvm/Context.ip : I
         L7
          RETURN
[6]_asm_proceduresetup_ask_4 "ask patches" AgentSet => void
      _patches => AgentSet
         L0
          ALOAD 0
          GETFIELD org/nlogo/prim/_asm_proceduresetup_ask_4.world : Lorg/nlogo/agent/World;
          INVOKEVIRTUAL org/nlogo/agent/World.patches ()Lorg/nlogo/agent/AgentSet;
         L1
          ASTORE 2
          ALOAD 1
          GETFIELD org/nlogo/nvm/Context.agent : Lorg/nlogo/agent/Agent;
          INSTANCEOF org/nlogo/agent/Observer
          IFNE L2
          ALOAD 2
          ALOAD 0
          GETFIELD org/nlogo/prim/_asm_proceduresetup_ask_4.world : Lorg/nlogo/agent/World;
          INVOKEVIRTUAL org/nlogo/agent/World.turtles ()Lorg/nlogo/agent/AgentSet;
          IF_ACMPNE L3
          NEW org/nlogo/nvm/EngineException
          DUP
          ALOAD 1
          ALOAD 0
          GETSTATIC org/nlogo/api/I18N$.MODULE$ : Lorg/nlogo/api/I18N$;
          INVOKEVIRTUAL org/nlogo/api/I18N$.errors ()Lorg/nlogo/api/I18N$BundleKind;
          LDC "org.nlogo.prim.$common.onlyObserverCanAskAllTurtles"
          INVOKEVIRTUAL org/nlogo/api/I18N$BundleKind.get (Ljava/lang/String;)Ljava/lang/String;
          INVOKESPECIAL org/nlogo/nvm/EngineException.<init> (Lorg/nlogo/nvm/Context;Lorg/nlogo/nvm/Instruction;Ljava/lang/String;)V
          ATHROW
         L3
          ALOAD 2
          ALOAD 0
          GETFIELD org/nlogo/prim/_asm_proceduresetup_ask_4.world : Lorg/nlogo/agent/World;
          INVOKEVIRTUAL org/nlogo/agent/World.patches ()Lorg/nlogo/agent/AgentSet;
          IF_ACMPNE L2
          NEW org/nlogo/nvm/EngineException
          DUP
          ALOAD 1
          ALOAD 0
          GETSTATIC org/nlogo/api/I18N$.MODULE$ : Lorg/nlogo/api/I18N$;
          INVOKEVIRTUAL org/nlogo/api/I18N$.errors ()Lorg/nlogo/api/I18N$BundleKind;
          LDC "org.nlogo.prim.$common.onlyObserverCanAskAllPatches"
          INVOKEVIRTUAL org/nlogo/api/I18N$BundleKind.get (Ljava/lang/String;)Ljava/lang/String;
          INVOKESPECIAL org/nlogo/nvm/EngineException.<init> (Lorg/nlogo/nvm/Context;Lorg/nlogo/nvm/Instruction;Ljava/lang/String;)V
          ATHROW
         L2
          ALOAD 1
          ALOAD 2
          BIPUSH 7
          INVOKEVIRTUAL org/nlogo/nvm/Context.runExclusiveJob (Lorg/nlogo/agent/AgentSet;I)V
          ALOAD 1
          BIPUSH 11
          PUTFIELD org/nlogo/nvm/Context.ip : I
         L4
          RETURN
[7]_asm_proceduresetup_setpatchvariable_5 "set countdown random grass-delay" Object => void
      _random double => double
        _observervariable:GRASS-DELAY => Object
          TRYCATCHBLOCK L0 L1 L1 java/lang/ClassCastException
          TRYCATCHBLOCK L2 L3 L4 org/nlogo/api/AgentException
         L5
          ALOAD 1
          GETFIELD org/nlogo/nvm/Context.agent : Lorg/nlogo/agent/Agent;
          BIPUSH 7
          INVOKEVIRTUAL org/nlogo/agent/Agent.getObserverVariable (I)Ljava/lang/Object;
         L6
          ASTORE 2
         L0
          ALOAD 2
          CHECKCAST java/lang/Double
          INVOKEVIRTUAL java/lang/Double.doubleValue ()D
          GOTO L7
         L1
          POP
          NEW org/nlogo/nvm/ArgumentTypeException
          DUP
          ALOAD 1
          ALOAD 0
          BIPUSH 0
          LDC 1
          ALOAD 2
          INVOKESPECIAL org/nlogo/nvm/ArgumentTypeException.<init> (Lorg/nlogo/nvm/Context;Lorg/nlogo/nvm/Instruction;IILjava/lang/Object;)V
          ATHROW
         L7
          DSTORE 2
          ALOAD 0
          DLOAD 2
          INVOKEVIRTUAL org/nlogo/prim/_asm_proceduresetup_setpatchvariable_5.validLong (D)J
          LSTORE 4
          DLOAD 2
          LLOAD 4
          L2D
          DCMPL
          IFEQ L8
          LLOAD 4
          DLOAD 2
          ICONST_0
          I2D
          DCMPL
          IFLT L9
          ICONST_1
          GOTO L10
         L9
          ICONST_M1
         L10
          I2L
          LADD
          LSTORE 4
         L8
          LLOAD 4
          LCONST_0
          LCMP
          IFLE L11
          ALOAD 1
          GETFIELD org/nlogo/nvm/Context.job : Lorg/nlogo/nvm/Job;
          GETFIELD org/nlogo/nvm/Job.random : Lorg/nlogo/util/MersenneTwisterFast;
          LLOAD 4
          INVOKEVIRTUAL org/nlogo/util/MersenneTwisterFast.nextLong (J)J
          L2D
          GOTO L12
         L11
          LLOAD 4
          LCONST_0
          LCMP
          IFGE L13
          ALOAD 1
          GETFIELD org/nlogo/nvm/Context.job : Lorg/nlogo/nvm/Job;
          GETFIELD org/nlogo/nvm/Job.random : Lorg/nlogo/util/MersenneTwisterFast;
          LLOAD 4
          LNEG
          INVOKEVIRTUAL org/nlogo/util/MersenneTwisterFast.nextLong (J)J
          LNEG
          L2D
          GOTO L12
         L13
          DCONST_0
         L12
          DSTORE 2
          NEW java/lang/Double
          DUP
          DLOAD 2
          INVOKESPECIAL java/lang/Double.<init> (D)V
          ASTORE 2
         L2
          ALOAD 1
          GETFIELD org/nlogo/nvm/Context.agent : Lorg/nlogo/agent/Agent;
          ICONST_5
          ALOAD 2
          INVOKEVIRTUAL org/nlogo/agent/Agent.setPatchVariable (ILjava/lang/Object;)V
         L3
          ALOAD 1
          BIPUSH 8
          PUTFIELD org/nlogo/nvm/Context.ip : I
          GOTO L14
         L4
          ASTORE 3
          NEW org/nlogo/nvm/EngineException
          DUP
          ALOAD 1
          ALOAD 0
          ALOAD 3
          INVOKEVIRTUAL org/nlogo/api/AgentException.getMessage ()Ljava/lang/String;
          INVOKESPECIAL org/nlogo/nvm/EngineException.<init> (Lorg/nlogo/nvm/Context;Lorg/nlogo/nvm/Instruction;Ljava/lang/String;)V
          ATHROW
         L14
          RETURN
[8]_asm_proceduresetup_if_6 "if (random 2) = 0" boolean => void
      _equal double,double => boolean
        _randomconst:2 => double
        _constdouble:0.0 => double
         L0
          ALOAD 1
          GETFIELD org/nlogo/nvm/Context.job : Lorg/nlogo/nvm/Job;
          GETFIELD org/nlogo/nvm/Job.random : Lorg/nlogo/util/MersenneTwisterFast;
          LDC 2
          INVOKEVIRTUAL org/nlogo/util/MersenneTwisterFast.nextLong (J)J
          L2D
         L1
          DCONST_0
         L2
          DSTORE 4
          DSTORE 2
          DLOAD 2
          DLOAD 4
          DCMPL
          IFNE L3
          ICONST_1
          GOTO L4
         L3
          ICONST_0
         L4
          ISTORE 2
          ALOAD 1
          ILOAD 2
          IFEQ L5
          BIPUSH 9
          GOTO L6
         L5
          BIPUSH 10
         L6
          PUTFIELD org/nlogo/nvm/Context.ip : I
         L7
          RETURN
[9]_asm_proceduresetup_setpatchvariable_7 "set pcolor brown" Object => void
      _constdouble:35.0 => Double
          TRYCATCHBLOCK L0 L1 L2 org/nlogo/api/AgentException
         L3
          ALOAD 0
          GETFIELD org/nlogo/prim/_asm_proceduresetup_setpatchvariable_7.kept2_value : Ljava/lang/Double;
         L4
          ASTORE 2
         L0
          ALOAD 1
          GETFIELD org/nlogo/nvm/Context.agent : Lorg/nlogo/agent/Agent;
          ICONST_2
          ALOAD 2
          INVOKEVIRTUAL org/nlogo/agent/Agent.setPatchVariable (ILjava/lang/Object;)V
         L1
          ALOAD 1
          BIPUSH 10
          PUTFIELD org/nlogo/nvm/Context.ip : I
          GOTO L5
         L2
          ASTORE 3
          NEW org/nlogo/nvm/EngineException
          DUP
          ALOAD 1
          ALOAD 0
          ALOAD 3
          INVOKEVIRTUAL org/nlogo/api/AgentException.getMessage ()Ljava/lang/String;
          INVOKESPECIAL org/nlogo/nvm/EngineException.<init> (Lorg/nlogo/nvm/Context;Lorg/nlogo/nvm/Instruction;Ljava/lang/String;)V
          ATHROW
         L5
          RETURN
[10]_asm_proceduresetup_done_8 "" => void
         L0
          ALOAD 1
          ICONST_1
          PUTFIELD org/nlogo/nvm/Context.finished : Z
         L1
          RETURN
[11]_crofast:SHEEP
      _asm_proceduresetup_observervariable_9 "init-sheep" => Object
           L0
            ALOAD 1
            GETFIELD org/nlogo/nvm/Context.agent : Lorg/nlogo/agent/Agent;
            ICONST_0
            INVOKEVIRTUAL org/nlogo/agent/Agent.getObserverVariable (I)Ljava/lang/Object;
           L1
            ARETURN
[12]_asm_proceduresetup_ask_10 "ask sheep" AgentSet => void
      _breed:SHEEP => AgentSet
         L0
          ALOAD 0
          GETFIELD org/nlogo/prim/_asm_proceduresetup_ask_10.world : Lorg/nlogo/agent/World;
          LDC "SHEEP"
          INVOKEVIRTUAL org/nlogo/agent/World.getBreed (Ljava/lang/String;)Lorg/nlogo/agent/AgentSet;
         L1
          ASTORE 2
          ALOAD 1
          GETFIELD org/nlogo/nvm/Context.agent : Lorg/nlogo/agent/Agent;
          INSTANCEOF org/nlogo/agent/Observer
          IFNE L2
          ALOAD 2
          ALOAD 0
          GETFIELD org/nlogo/prim/_asm_proceduresetup_ask_10.world : Lorg/nlogo/agent/World;
          INVOKEVIRTUAL org/nlogo/agent/World.turtles ()Lorg/nlogo/agent/AgentSet;
          IF_ACMPNE L3
          NEW org/nlogo/nvm/EngineException
          DUP
          ALOAD 1
          ALOAD 0
          GETSTATIC org/nlogo/api/I18N$.MODULE$ : Lorg/nlogo/api/I18N$;
          INVOKEVIRTUAL org/nlogo/api/I18N$.errors ()Lorg/nlogo/api/I18N$BundleKind;
          LDC "org.nlogo.prim.$common.onlyObserverCanAskAllTurtles"
          INVOKEVIRTUAL org/nlogo/api/I18N$BundleKind.get (Ljava/lang/String;)Ljava/lang/String;
          INVOKESPECIAL org/nlogo/nvm/EngineException.<init> (Lorg/nlogo/nvm/Context;Lorg/nlogo/nvm/Instruction;Ljava/lang/String;)V
          ATHROW
         L3
          ALOAD 2
          ALOAD 0
          GETFIELD org/nlogo/prim/_asm_proceduresetup_ask_10.world : Lorg/nlogo/agent/World;
          INVOKEVIRTUAL org/nlogo/agent/World.patches ()Lorg/nlogo/agent/AgentSet;
          IF_ACMPNE L2
          NEW org/nlogo/nvm/EngineException
          DUP
          ALOAD 1
          ALOAD 0
          GETSTATIC org/nlogo/api/I18N$.MODULE$ : Lorg/nlogo/api/I18N$;
          INVOKEVIRTUAL org/nlogo/api/I18N$.errors ()Lorg/nlogo/api/I18N$BundleKind;
          LDC "org.nlogo.prim.$common.onlyObserverCanAskAllPatches"
          INVOKEVIRTUAL org/nlogo/api/I18N$BundleKind.get (Ljava/lang/String;)Ljava/lang/String;
          INVOKESPECIAL org/nlogo/nvm/EngineException.<init> (Lorg/nlogo/nvm/Context;Lorg/nlogo/nvm/Instruction;Ljava/lang/String;)V
          ATHROW
         L2
          ALOAD 1
          ALOAD 2
          BIPUSH 13
          INVOKEVIRTUAL org/nlogo/nvm/Context.runExclusiveJob (Lorg/nlogo/agent/AgentSet;I)V
          ALOAD 1
          BIPUSH 18
          PUTFIELD org/nlogo/nvm/Context.ip : I
         L4
          RETURN
[13]_asm_proceduresetup_setturtleorlinkvariable_11 "set color white" Object => void
      _constdouble:9.9 => Double
          TRYCATCHBLOCK L0 L1 L2 org/nlogo/api/AgentException
         L3
          ALOAD 0
          GETFIELD org/nlogo/prim/_asm_proceduresetup_setturtleorlinkvariable_11.kept2_value : Ljava/lang/Double;
         L4
          ASTORE 2
         L0
          ALOAD 1
          GETFIELD org/nlogo/nvm/Context.agent : Lorg/nlogo/agent/Agent;
          LDC "COLOR"
          ALOAD 2
          INVOKEVIRTUAL org/nlogo/agent/Agent.setTurtleOrLinkVariable (Ljava/lang/String;Ljava/lang/Object;)V
         L1
          ALOAD 1
          BIPUSH 14
          PUTFIELD org/nlogo/nvm/Context.ip : I
          GOTO L5
         L2
          ASTORE 3
          NEW org/nlogo/nvm/EngineException
          DUP
          ALOAD 1
          ALOAD 0
          ALOAD 3
          INVOKEVIRTUAL org/nlogo/api/AgentException.getMessage ()Ljava/lang/String;
          INVOKESPECIAL org/nlogo/nvm/EngineException.<init> (Lorg/nlogo/nvm/Context;Lorg/nlogo/nvm/Instruction;Ljava/lang/String;)V
          ATHROW
         L5
          RETURN
[14]_asm_proceduresetup_setturtlevariable_12 "set energy random-float (2 * sheep-metabolism" Object => void
      _randomfloat double => double
        _mult double,double => double
          _constdouble:2.0 => double
          _observervariable:SHEEP-METABOLISM => Object
          TRYCATCHBLOCK L0 L1 L1 java/lang/ClassCastException
          TRYCATCHBLOCK L2 L3 L4 org/nlogo/api/AgentException
         L5
          LDC 2.0
         L6
          ALOAD 1
          GETFIELD org/nlogo/nvm/Context.agent : Lorg/nlogo/agent/Agent;
          ICONST_1
          INVOKEVIRTUAL org/nlogo/agent/Agent.getObserverVariable (I)Ljava/lang/Object;
         L7
          ASTORE 2
         L0
          ALOAD 2
          CHECKCAST java/lang/Double
          INVOKEVIRTUAL java/lang/Double.doubleValue ()D
          GOTO L8
         L1
          POP
          NEW org/nlogo/nvm/ArgumentTypeException
          DUP
          ALOAD 1
          ALOAD 0
          BIPUSH 1
          LDC 1
          ALOAD 2
          INVOKESPECIAL org/nlogo/nvm/ArgumentTypeException.<init> (Lorg/nlogo/nvm/Context;Lorg/nlogo/nvm/Instruction;IILjava/lang/Object;)V
          ATHROW
         L8
          DSTORE 4
          DSTORE 2
          DLOAD 2
          DLOAD 4
          DMUL
         L9
          DSTORE 2
          DLOAD 2
          ALOAD 1
          GETFIELD org/nlogo/nvm/Context.job : Lorg/nlogo/nvm/Job;
          GETFIELD org/nlogo/nvm/Job.random : Lorg/nlogo/util/MersenneTwisterFast;
          INVOKEVIRTUAL org/nlogo/util/MersenneTwisterFast.nextDouble ()D
          DMUL
         L10
          DSTORE 2
          NEW java/lang/Double
          DUP
          DLOAD 2
          INVOKESPECIAL java/lang/Double.<init> (D)V
          ASTORE 2
         L2
          ALOAD 1
          GETFIELD org/nlogo/nvm/Context.agent : Lorg/nlogo/agent/Agent;
          BIPUSH 13
          ALOAD 2
          INVOKEVIRTUAL org/nlogo/agent/Agent.setTurtleVariable (ILjava/lang/Object;)V
         L3
          ALOAD 1
          BIPUSH 15
          PUTFIELD org/nlogo/nvm/Context.ip : I
          GOTO L11
         L4
          ASTORE 3
          NEW org/nlogo/nvm/EngineException
          DUP
          ALOAD 1
          ALOAD 0
          ALOAD 3
          INVOKEVIRTUAL org/nlogo/api/AgentException.getMessage ()Ljava/lang/String;
          INVOKESPECIAL org/nlogo/nvm/EngineException.<init> (Lorg/nlogo/nvm/Context;Lorg/nlogo/nvm/Instruction;Ljava/lang/String;)V
          ATHROW
         L11
          RETURN
[15]_asm_proceduresetup_setturtleorlinkvariable_13 "set shape "sheep"" Object => void
      _conststring:"sheep" => String
          TRYCATCHBLOCK L0 L1 L2 org/nlogo/api/AgentException
         L3
          LDC "sheep"
         L4
          ASTORE 2
         L0
          ALOAD 1
          GETFIELD org/nlogo/nvm/Context.agent : Lorg/nlogo/agent/Agent;
          LDC "SHAPE"
          ALOAD 2
          INVOKEVIRTUAL org/nlogo/agent/Agent.setTurtleOrLinkVariable (Ljava/lang/String;Ljava/lang/Object;)V
         L1
          ALOAD 1
          BIPUSH 16
          PUTFIELD org/nlogo/nvm/Context.ip : I
          GOTO L5
         L2
          ASTORE 3
          NEW org/nlogo/nvm/EngineException
          DUP
          ALOAD 1
          ALOAD 0
          ALOAD 3
          INVOKEVIRTUAL org/nlogo/api/AgentException.getMessage ()Ljava/lang/String;
          INVOKESPECIAL org/nlogo/nvm/EngineException.<init> (Lorg/nlogo/nvm/Context;Lorg/nlogo/nvm/Instruction;Ljava/lang/String;)V
          ATHROW
         L5
          RETURN
[16]_asm_proceduresetup_setxy_14 "setxy random world-width random world-height" double,double => void
      _random double => double
        _worldwidth => double
      _random double => double
        _worldheight => double
          TRYCATCHBLOCK L0 L1 L2 org/nlogo/api/AgentException
         L3
          ALOAD 0
          GETFIELD org/nlogo/prim/_asm_proceduresetup_setxy_14.world : Lorg/nlogo/agent/World;
          INVOKEVIRTUAL org/nlogo/agent/World.worldWidth ()I
          I2D
         L4
          DSTORE 2
          ALOAD 0
          DLOAD 2
          INVOKEVIRTUAL org/nlogo/prim/_asm_proceduresetup_setxy_14.validLong (D)J
          LSTORE 4
          DLOAD 2
          LLOAD 4
          L2D
          DCMPL
          IFEQ L5
          LLOAD 4
          DLOAD 2
          ICONST_0
          I2D
          DCMPL
          IFLT L6
          ICONST_1
          GOTO L7
         L6
          ICONST_M1
         L7
          I2L
          LADD
          LSTORE 4
         L5
          LLOAD 4
          LCONST_0
          LCMP
          IFLE L8
          ALOAD 1
          GETFIELD org/nlogo/nvm/Context.job : Lorg/nlogo/nvm/Job;
          GETFIELD org/nlogo/nvm/Job.random : Lorg/nlogo/util/MersenneTwisterFast;
          LLOAD 4
          INVOKEVIRTUAL org/nlogo/util/MersenneTwisterFast.nextLong (J)J
          L2D
          GOTO L9
         L8
          LLOAD 4
          LCONST_0
          LCMP
          IFGE L10
          ALOAD 1
          GETFIELD org/nlogo/nvm/Context.job : Lorg/nlogo/nvm/Job;
          GETFIELD org/nlogo/nvm/Job.random : Lorg/nlogo/util/MersenneTwisterFast;
          LLOAD 4
          LNEG
          INVOKEVIRTUAL org/nlogo/util/MersenneTwisterFast.nextLong (J)J
          LNEG
          L2D
          GOTO L9
         L10
          DCONST_0
         L9
          ALOAD 0
          GETFIELD org/nlogo/prim/_asm_proceduresetup_setxy_14.world : Lorg/nlogo/agent/World;
          INVOKEVIRTUAL org/nlogo/agent/World.worldHeight ()I
          I2D
         L11
          DSTORE 2
          ALOAD 0
          DLOAD 2
          INVOKEVIRTUAL org/nlogo/prim/_asm_proceduresetup_setxy_14.validLong (D)J
          LSTORE 4
          DLOAD 2
          LLOAD 4
          L2D
          DCMPL
          IFEQ L12
          LLOAD 4
          DLOAD 2
          ICONST_0
          I2D
          DCMPL
          IFLT L13
          ICONST_1
          GOTO L14
         L13
          ICONST_M1
         L14
          I2L
          LADD
          LSTORE 4
         L12
          LLOAD 4
          LCONST_0
          LCMP
          IFLE L15
          ALOAD 1
          GETFIELD org/nlogo/nvm/Context.job : Lorg/nlogo/nvm/Job;
          GETFIELD org/nlogo/nvm/Job.random : Lorg/nlogo/util/MersenneTwisterFast;
          LLOAD 4
          INVOKEVIRTUAL org/nlogo/util/MersenneTwisterFast.nextLong (J)J
          L2D
          GOTO L16
         L15
          LLOAD 4
          LCONST_0
          LCMP
          IFGE L17
          ALOAD 1
          GETFIELD org/nlogo/nvm/Context.job : Lorg/nlogo/nvm/Job;
          GETFIELD org/nlogo/nvm/Job.random : Lorg/nlogo/util/MersenneTwisterFast;
          LLOAD 4
          LNEG
          INVOKEVIRTUAL org/nlogo/util/MersenneTwisterFast.nextLong (J)J
          LNEG
          L2D
          GOTO L16
         L17
          DCONST_0
         L16
          DSTORE 4
          DSTORE 2
          ALOAD 1
          GETFIELD org/nlogo/nvm/Context.agent : Lorg/nlogo/agent/Agent;
          CHECKCAST org/nlogo/agent/Turtle
          ASTORE 6
         L0
          ALOAD 6
          ALOAD 6
          DLOAD 2
          INVOKEVIRTUAL org/nlogo/agent/Turtle.shortestPathX (D)D
          ALOAD 6
          DLOAD 4
          INVOKEVIRTUAL org/nlogo/agent/Turtle.shortestPathY (D)D
          INVOKEVIRTUAL org/nlogo/agent/Turtle.xandycor (DD)V
         L1
          GOTO L18
         L2
          ASTORE 7
          NEW org/nlogo/nvm/EngineException
          DUP
          ALOAD 1
          ALOAD 0
          INVOKESTATIC org/nlogo/api/I18N.errorsJ ()Lorg/nlogo/api/I18NJava;
          LDC "org.nlogo.prim.etc._setxy.pointOutsideWorld"
          ICONST_2
          ANEWARRAY java/lang/Object
          DUP
          ICONST_0
          DLOAD 2
          INVOKESTATIC java/lang/Double.valueOf (D)Ljava/lang/Double;
          AASTORE
          DUP
          ICONST_1
          DLOAD 4
          INVOKESTATIC java/lang/Double.valueOf (D)Ljava/lang/Double;
          AASTORE
          INVOKEINTERFACE org/nlogo/api/I18NJava.getN (Ljava/lang/String;[Ljava/lang/Object;)Ljava/lang/String;
          INVOKESPECIAL org/nlogo/nvm/EngineException.<init> (Lorg/nlogo/nvm/Context;Lorg/nlogo/nvm/Instruction;Ljava/lang/String;)V
          ATHROW
         L18
          ALOAD 1
          BIPUSH 17
          PUTFIELD org/nlogo/nvm/Context.ip : I
         L19
          RETURN
[17]_asm_proceduresetup_done_15 "" => void
         L0
          ALOAD 1
          ICONST_1
          PUTFIELD org/nlogo/nvm/Context.finished : Z
         L1
          RETURN
[18]_crofast:WOLVES
      _asm_proceduresetup_observervariable_16 "init-wolves" => Object
           L0
            ALOAD 1
            GETFIELD org/nlogo/nvm/Context.agent : Lorg/nlogo/agent/Agent;
            ICONST_3
            INVOKEVIRTUAL org/nlogo/agent/Agent.getObserverVariable (I)Ljava/lang/Object;
           L1
            ARETURN
[19]_asm_proceduresetup_ask_17 "ask wolves" AgentSet => void
      _breed:WOLVES => AgentSet
         L0
          ALOAD 0
          GETFIELD org/nlogo/prim/_asm_proceduresetup_ask_17.world : Lorg/nlogo/agent/World;
          LDC "WOLVES"
          INVOKEVIRTUAL org/nlogo/agent/World.getBreed (Ljava/lang/String;)Lorg/nlogo/agent/AgentSet;
         L1
          ASTORE 2
          ALOAD 1
          GETFIELD org/nlogo/nvm/Context.agent : Lorg/nlogo/agent/Agent;
          INSTANCEOF org/nlogo/agent/Observer
          IFNE L2
          ALOAD 2
          ALOAD 0
          GETFIELD org/nlogo/prim/_asm_proceduresetup_ask_17.world : Lorg/nlogo/agent/World;
          INVOKEVIRTUAL org/nlogo/agent/World.turtles ()Lorg/nlogo/agent/AgentSet;
          IF_ACMPNE L3
          NEW org/nlogo/nvm/EngineException
          DUP
          ALOAD 1
          ALOAD 0
          GETSTATIC org/nlogo/api/I18N$.MODULE$ : Lorg/nlogo/api/I18N$;
          INVOKEVIRTUAL org/nlogo/api/I18N$.errors ()Lorg/nlogo/api/I18N$BundleKind;
          LDC "org.nlogo.prim.$common.onlyObserverCanAskAllTurtles"
          INVOKEVIRTUAL org/nlogo/api/I18N$BundleKind.get (Ljava/lang/String;)Ljava/lang/String;
          INVOKESPECIAL org/nlogo/nvm/EngineException.<init> (Lorg/nlogo/nvm/Context;Lorg/nlogo/nvm/Instruction;Ljava/lang/String;)V
          ATHROW
         L3
          ALOAD 2
          ALOAD 0
          GETFIELD org/nlogo/prim/_asm_proceduresetup_ask_17.world : Lorg/nlogo/agent/World;
          INVOKEVIRTUAL org/nlogo/agent/World.patches ()Lorg/nlogo/agent/AgentSet;
          IF_ACMPNE L2
          NEW org/nlogo/nvm/EngineException
          DUP
          ALOAD 1
          ALOAD 0
          GETSTATIC org/nlogo/api/I18N$.MODULE$ : Lorg/nlogo/api/I18N$;
          INVOKEVIRTUAL org/nlogo/api/I18N$.errors ()Lorg/nlogo/api/I18N$BundleKind;
          LDC "org.nlogo.prim.$common.onlyObserverCanAskAllPatches"
          INVOKEVIRTUAL org/nlogo/api/I18N$BundleKind.get (Ljava/lang/String;)Ljava/lang/String;
          INVOKESPECIAL org/nlogo/nvm/EngineException.<init> (Lorg/nlogo/nvm/Context;Lorg/nlogo/nvm/Instruction;Ljava/lang/String;)V
          ATHROW
         L2
          ALOAD 1
          ALOAD 2
          BIPUSH 20
          INVOKEVIRTUAL org/nlogo/nvm/Context.runExclusiveJob (Lorg/nlogo/agent/AgentSet;I)V
          ALOAD 1
          BIPUSH 25
          PUTFIELD org/nlogo/nvm/Context.ip : I
         L4
          RETURN
[20]_asm_proceduresetup_setturtleorlinkvariable_18 "set color black" Object => void
      _constdouble:0.0 => Double
          TRYCATCHBLOCK L0 L1 L2 org/nlogo/api/AgentException
         L3
          ALOAD 0
          GETFIELD org/nlogo/prim/_asm_proceduresetup_setturtleorlinkvariable_18.kept2_value : Ljava/lang/Double;
         L4
          ASTORE 2
         L0
          ALOAD 1
          GETFIELD org/nlogo/nvm/Context.agent : Lorg/nlogo/agent/Agent;
          LDC "COLOR"
          ALOAD 2
          INVOKEVIRTUAL org/nlogo/agent/Agent.setTurtleOrLinkVariable (Ljava/lang/String;Ljava/lang/Object;)V
         L1
          ALOAD 1
          BIPUSH 21
          PUTFIELD org/nlogo/nvm/Context.ip : I
          GOTO L5
         L2
          ASTORE 3
          NEW org/nlogo/nvm/EngineException
          DUP
          ALOAD 1
          ALOAD 0
          ALOAD 3
          INVOKEVIRTUAL org/nlogo/api/AgentException.getMessage ()Ljava/lang/String;
          INVOKESPECIAL org/nlogo/nvm/EngineException.<init> (Lorg/nlogo/nvm/Context;Lorg/nlogo/nvm/Instruction;Ljava/lang/String;)V
          ATHROW
         L5
          RETURN
[21]_asm_proceduresetup_setturtlevariable_19 "set energy random-float (2 * wolf-metabolism" Object => void
      _randomfloat double => double
        _mult double,double => double
          _constdouble:2.0 => double
          _observervariable:WOLF-METABOLISM => Object
          TRYCATCHBLOCK L0 L1 L1 java/lang/ClassCastException
          TRYCATCHBLOCK L2 L3 L4 org/nlogo/api/AgentException
         L5
          LDC 2.0
         L6
          ALOAD 1
          GETFIELD org/nlogo/nvm/Context.agent : Lorg/nlogo/agent/Agent;
          ICONST_4
          INVOKEVIRTUAL org/nlogo/agent/Agent.getObserverVariable (I)Ljava/lang/Object;
         L7
          ASTORE 2
         L0
          ALOAD 2
          CHECKCAST java/lang/Double
          INVOKEVIRTUAL java/lang/Double.doubleValue ()D
          GOTO L8
         L1
          POP
          NEW org/nlogo/nvm/ArgumentTypeException
          DUP
          ALOAD 1
          ALOAD 0
          BIPUSH 1
          LDC 1
          ALOAD 2
          INVOKESPECIAL org/nlogo/nvm/ArgumentTypeException.<init> (Lorg/nlogo/nvm/Context;Lorg/nlogo/nvm/Instruction;IILjava/lang/Object;)V
          ATHROW
         L8
          DSTORE 4
          DSTORE 2
          DLOAD 2
          DLOAD 4
          DMUL
         L9
          DSTORE 2
          DLOAD 2
          ALOAD 1
          GETFIELD org/nlogo/nvm/Context.job : Lorg/nlogo/nvm/Job;
          GETFIELD org/nlogo/nvm/Job.random : Lorg/nlogo/util/MersenneTwisterFast;
          INVOKEVIRTUAL org/nlogo/util/MersenneTwisterFast.nextDouble ()D
          DMUL
         L10
          DSTORE 2
          NEW java/lang/Double
          DUP
          DLOAD 2
          INVOKESPECIAL java/lang/Double.<init> (D)V
          ASTORE 2
         L2
          ALOAD 1
          GETFIELD org/nlogo/nvm/Context.agent : Lorg/nlogo/agent/Agent;
          BIPUSH 13
          ALOAD 2
          INVOKEVIRTUAL org/nlogo/agent/Agent.setTurtleVariable (ILjava/lang/Object;)V
         L3
          ALOAD 1
          BIPUSH 22
          PUTFIELD org/nlogo/nvm/Context.ip : I
          GOTO L11
         L4
          ASTORE 3
          NEW org/nlogo/nvm/EngineException
          DUP
          ALOAD 1
          ALOAD 0
          ALOAD 3
          INVOKEVIRTUAL org/nlogo/api/AgentException.getMessage ()Ljava/lang/String;
          INVOKESPECIAL org/nlogo/nvm/EngineException.<init> (Lorg/nlogo/nvm/Context;Lorg/nlogo/nvm/Instruction;Ljava/lang/String;)V
          ATHROW
         L11
          RETURN
[22]_asm_proceduresetup_setturtleorlinkvariable_20 "set shape "wolf"" Object => void
      _conststring:"wolf" => String
          TRYCATCHBLOCK L0 L1 L2 org/nlogo/api/AgentException
         L3
          LDC "wolf"
         L4
          ASTORE 2
         L0
          ALOAD 1
          GETFIELD org/nlogo/nvm/Context.agent : Lorg/nlogo/agent/Agent;
          LDC "SHAPE"
          ALOAD 2
          INVOKEVIRTUAL org/nlogo/agent/Agent.setTurtleOrLinkVariable (Ljava/lang/String;Ljava/lang/Object;)V
         L1
          ALOAD 1
          BIPUSH 23
          PUTFIELD org/nlogo/nvm/Context.ip : I
          GOTO L5
         L2
          ASTORE 3
          NEW org/nlogo/nvm/EngineException
          DUP
          ALOAD 1
          ALOAD 0
          ALOAD 3
          INVOKEVIRTUAL org/nlogo/api/AgentException.getMessage ()Ljava/lang/String;
          INVOKESPECIAL org/nlogo/nvm/EngineException.<init> (Lorg/nlogo/nvm/Context;Lorg/nlogo/nvm/Instruction;Ljava/lang/String;)V
          ATHROW
         L5
          RETURN
[23]_asm_proceduresetup_setxy_21 "setxy random world-width random world-height" double,double => void
      _random double => double
        _worldwidth => double
      _random double => double
        _worldheight => double
          TRYCATCHBLOCK L0 L1 L2 org/nlogo/api/AgentException
         L3
          ALOAD 0
          GETFIELD org/nlogo/prim/_asm_proceduresetup_setxy_21.world : Lorg/nlogo/agent/World;
          INVOKEVIRTUAL org/nlogo/agent/World.worldWidth ()I
          I2D
         L4
          DSTORE 2
          ALOAD 0
          DLOAD 2
          INVOKEVIRTUAL org/nlogo/prim/_asm_proceduresetup_setxy_21.validLong (D)J
          LSTORE 4
          DLOAD 2
          LLOAD 4
          L2D
          DCMPL
          IFEQ L5
          LLOAD 4
          DLOAD 2
          ICONST_0
          I2D
          DCMPL
          IFLT L6
          ICONST_1
          GOTO L7
         L6
          ICONST_M1
         L7
          I2L
          LADD
          LSTORE 4
         L5
          LLOAD 4
          LCONST_0
          LCMP
          IFLE L8
          ALOAD 1
          GETFIELD org/nlogo/nvm/Context.job : Lorg/nlogo/nvm/Job;
          GETFIELD org/nlogo/nvm/Job.random : Lorg/nlogo/util/MersenneTwisterFast;
          LLOAD 4
          INVOKEVIRTUAL org/nlogo/util/MersenneTwisterFast.nextLong (J)J
          L2D
          GOTO L9
         L8
          LLOAD 4
          LCONST_0
          LCMP
          IFGE L10
          ALOAD 1
          GETFIELD org/nlogo/nvm/Context.job : Lorg/nlogo/nvm/Job;
          GETFIELD org/nlogo/nvm/Job.random : Lorg/nlogo/util/MersenneTwisterFast;
          LLOAD 4
          LNEG
          INVOKEVIRTUAL org/nlogo/util/MersenneTwisterFast.nextLong (J)J
          LNEG
          L2D
          GOTO L9
         L10
          DCONST_0
         L9
          ALOAD 0
          GETFIELD org/nlogo/prim/_asm_proceduresetup_setxy_21.world : Lorg/nlogo/agent/World;
          INVOKEVIRTUAL org/nlogo/agent/World.worldHeight ()I
          I2D
         L11
          DSTORE 2
          ALOAD 0
          DLOAD 2
          INVOKEVIRTUAL org/nlogo/prim/_asm_proceduresetup_setxy_21.validLong (D)J
          LSTORE 4
          DLOAD 2
          LLOAD 4
          L2D
          DCMPL
          IFEQ L12
          LLOAD 4
          DLOAD 2
          ICONST_0
          I2D
          DCMPL
          IFLT L13
          ICONST_1
          GOTO L14
         L13
          ICONST_M1
         L14
          I2L
          LADD
          LSTORE 4
         L12
          LLOAD 4
          LCONST_0
          LCMP
          IFLE L15
          ALOAD 1
          GETFIELD org/nlogo/nvm/Context.job : Lorg/nlogo/nvm/Job;
          GETFIELD org/nlogo/nvm/Job.random : Lorg/nlogo/util/MersenneTwisterFast;
          LLOAD 4
          INVOKEVIRTUAL org/nlogo/util/MersenneTwisterFast.nextLong (J)J
          L2D
          GOTO L16
         L15
          LLOAD 4
          LCONST_0
          LCMP
          IFGE L17
          ALOAD 1
          GETFIELD org/nlogo/nvm/Context.job : Lorg/nlogo/nvm/Job;
          GETFIELD org/nlogo/nvm/Job.random : Lorg/nlogo/util/MersenneTwisterFast;
          LLOAD 4
          LNEG
          INVOKEVIRTUAL org/nlogo/util/MersenneTwisterFast.nextLong (J)J
          LNEG
          L2D
          GOTO L16
         L17
          DCONST_0
         L16
          DSTORE 4
          DSTORE 2
          ALOAD 1
          GETFIELD org/nlogo/nvm/Context.agent : Lorg/nlogo/agent/Agent;
          CHECKCAST org/nlogo/agent/Turtle
          ASTORE 6
         L0
          ALOAD 6
          ALOAD 6
          DLOAD 2
          INVOKEVIRTUAL org/nlogo/agent/Turtle.shortestPathX (D)D
          ALOAD 6
          DLOAD 4
          INVOKEVIRTUAL org/nlogo/agent/Turtle.shortestPathY (D)D
          INVOKEVIRTUAL org/nlogo/agent/Turtle.xandycor (DD)V
         L1
          GOTO L18
         L2
          ASTORE 7
          NEW org/nlogo/nvm/EngineException
          DUP
          ALOAD 1
          ALOAD 0
          INVOKESTATIC org/nlogo/api/I18N.errorsJ ()Lorg/nlogo/api/I18NJava;
          LDC "org.nlogo.prim.etc._setxy.pointOutsideWorld"
          ICONST_2
          ANEWARRAY java/lang/Object
          DUP
          ICONST_0
          DLOAD 2
          INVOKESTATIC java/lang/Double.valueOf (D)Ljava/lang/Double;
          AASTORE
          DUP
          ICONST_1
          DLOAD 4
          INVOKESTATIC java/lang/Double.valueOf (D)Ljava/lang/Double;
          AASTORE
          INVOKEINTERFACE org/nlogo/api/I18NJava.getN (Ljava/lang/String;[Ljava/lang/Object;)Ljava/lang/String;
          INVOKESPECIAL org/nlogo/nvm/EngineException.<init> (Lorg/nlogo/nvm/Context;Lorg/nlogo/nvm/Instruction;Ljava/lang/String;)V
          ATHROW
         L18
          ALOAD 1
          BIPUSH 24
          PUTFIELD org/nlogo/nvm/Context.ip : I
         L19
          RETURN
[24]_asm_proceduresetup_done_22 "" => void
         L0
          ALOAD 1
          ICONST_1
          PUTFIELD org/nlogo/nvm/Context.finished : Z
         L1
          RETURN
[25]_asm_proceduresetup_if_23 "if plot?" boolean => void
      _observervariable:PLOT? => Object
          TRYCATCHBLOCK L0 L1 L1 java/lang/ClassCastException
         L2
          ALOAD 1
          GETFIELD org/nlogo/nvm/Context.agent : Lorg/nlogo/agent/Agent;
          BIPUSH 8
          INVOKEVIRTUAL org/nlogo/agent/Agent.getObserverVariable (I)Ljava/lang/Object;
         L3
          ASTORE 2
         L0
          ALOAD 2
          CHECKCAST java/lang/Boolean
          INVOKEVIRTUAL java/lang/Boolean.booleanValue ()Z
          GOTO L4
         L1
          POP
          NEW org/nlogo/nvm/ArgumentTypeException
          DUP
          ALOAD 1
          ALOAD 0
          BIPUSH 0
          LDC 2
          ALOAD 2
          INVOKESPECIAL org/nlogo/nvm/ArgumentTypeException.<init> (Lorg/nlogo/nvm/Context;Lorg/nlogo/nvm/Instruction;IILjava/lang/Object;)V
          ATHROW
         L4
          ISTORE 2
          ALOAD 1
          ILOAD 2
          IFEQ L5
          BIPUSH 26
          GOTO L6
         L5
          BIPUSH 27
         L6
          PUTFIELD org/nlogo/nvm/Context.ip : I
         L7
          RETURN
[26]_asm_proceduresetup_call_24 "graph"
         L0
          NEW org/nlogo/nvm/Activation
          DUP
          ALOAD 0
          GETFIELD org/nlogo/prim/_asm_proceduresetup_call_24.kept1_procedure : Lorg/nlogo/nvm/Procedure;
          ALOAD 1
          GETFIELD org/nlogo/nvm/Context.activation : Lorg/nlogo/nvm/Activation;
          BIPUSH 27
          INVOKESPECIAL org/nlogo/nvm/Activation.<init> (Lorg/nlogo/nvm/Procedure;Lorg/nlogo/nvm/Activation;I)V
          ALOAD 1
          SWAP
          PUTFIELD org/nlogo/nvm/Context.activation : Lorg/nlogo/nvm/Activation;
          ALOAD 1
          ICONST_0
          PUTFIELD org/nlogo/nvm/Context.ip : I
         L1
          RETURN
[27]_asm_proceduresetup_return_25 "" => void
         L0
          ALOAD 1
          INVOKEVIRTUAL org/nlogo/nvm/Context.returnFromProcedure ()V
          ALOAD 1
          ICONST_0
          PUTFIELD org/nlogo/nvm/Context.stopping : Z
         L1
          RETURN

procedure GO:[]{O---}:
[0]_asm_procedurego_ask_0 "ask sheep" AgentSet => void
      _breed:SHEEP => AgentSet
         L0
          ALOAD 0
          GETFIELD org/nlogo/prim/_asm_procedurego_ask_0.world : Lorg/nlogo/agent/World;
          LDC "SHEEP"
          INVOKEVIRTUAL org/nlogo/agent/World.getBreed (Ljava/lang/String;)Lorg/nlogo/agent/AgentSet;
         L1
          ASTORE 2
          ALOAD 1
          GETFIELD org/nlogo/nvm/Context.agent : Lorg/nlogo/agent/Agent;
          INSTANCEOF org/nlogo/agent/Observer
          IFNE L2
          ALOAD 2
          ALOAD 0
          GETFIELD org/nlogo/prim/_asm_procedurego_ask_0.world : Lorg/nlogo/agent/World;
          INVOKEVIRTUAL org/nlogo/agent/World.turtles ()Lorg/nlogo/agent/AgentSet;
          IF_ACMPNE L3
          NEW org/nlogo/nvm/EngineException
          DUP
          ALOAD 1
          ALOAD 0
          GETSTATIC org/nlogo/api/I18N$.MODULE$ : Lorg/nlogo/api/I18N$;
          INVOKEVIRTUAL org/nlogo/api/I18N$.errors ()Lorg/nlogo/api/I18N$BundleKind;
          LDC "org.nlogo.prim.$common.onlyObserverCanAskAllTurtles"
          INVOKEVIRTUAL org/nlogo/api/I18N$BundleKind.get (Ljava/lang/String;)Ljava/lang/String;
          INVOKESPECIAL org/nlogo/nvm/EngineException.<init> (Lorg/nlogo/nvm/Context;Lorg/nlogo/nvm/Instruction;Ljava/lang/String;)V
          ATHROW
         L3
          ALOAD 2
          ALOAD 0
          GETFIELD org/nlogo/prim/_asm_procedurego_ask_0.world : Lorg/nlogo/agent/World;
          INVOKEVIRTUAL org/nlogo/agent/World.patches ()Lorg/nlogo/agent/AgentSet;
          IF_ACMPNE L2
          NEW org/nlogo/nvm/EngineException
          DUP
          ALOAD 1
          ALOAD 0
          GETSTATIC org/nlogo/api/I18N$.MODULE$ : Lorg/nlogo/api/I18N$;
          INVOKEVIRTUAL org/nlogo/api/I18N$.errors ()Lorg/nlogo/api/I18N$BundleKind;
          LDC "org.nlogo.prim.$common.onlyObserverCanAskAllPatches"
          INVOKEVIRTUAL org/nlogo/api/I18N$BundleKind.get (Ljava/lang/String;)Ljava/lang/String;
          INVOKESPECIAL org/nlogo/nvm/EngineException.<init> (Lorg/nlogo/nvm/Context;Lorg/nlogo/nvm/Instruction;Ljava/lang/String;)V
          ATHROW
         L2
          ALOAD 1
          ALOAD 2
          ICONST_1
          INVOKEVIRTUAL org/nlogo/nvm/Context.runExclusiveJob (Lorg/nlogo/agent/AgentSet;I)V
          ALOAD 1
          BIPUSH 8
          PUTFIELD org/nlogo/nvm/Context.ip : I
         L4
          RETURN
[1]_asm_procedurego_call_1 "move"
         L0
          NEW org/nlogo/nvm/Activation
          DUP
          ALOAD 0
          GETFIELD org/nlogo/prim/_asm_procedurego_call_1.kept1_procedure : Lorg/nlogo/nvm/Procedure;
          ALOAD 1
          GETFIELD org/nlogo/nvm/Context.activation : Lorg/nlogo/nvm/Activation;
          ICONST_2
          INVOKESPECIAL org/nlogo/nvm/Activation.<init> (Lorg/nlogo/nvm/Procedure;Lorg/nlogo/nvm/Activation;I)V
          ALOAD 1
          SWAP
          PUTFIELD org/nlogo/nvm/Context.activation : Lorg/nlogo/nvm/Activation;
          ALOAD 1
          ICONST_0
          PUTFIELD org/nlogo/nvm/Context.ip : I
         L1
          RETURN
[2]_asm_procedurego_if_2 "if grass?" boolean => void
      _observervariable:GRASS? => Object
          TRYCATCHBLOCK L0 L1 L1 java/lang/ClassCastException
         L2
          ALOAD 1
          GETFIELD org/nlogo/nvm/Context.agent : Lorg/nlogo/agent/Agent;
          BIPUSH 6
          INVOKEVIRTUAL org/nlogo/agent/Agent.getObserverVariable (I)Ljava/lang/Object;
         L3
          ASTORE 2
         L0
          ALOAD 2
          CHECKCAST java/lang/Boolean
          INVOKEVIRTUAL java/lang/Boolean.booleanValue ()Z
          GOTO L4
         L1
          POP
          NEW org/nlogo/nvm/ArgumentTypeException
          DUP
          ALOAD 1
          ALOAD 0
          BIPUSH 0
          LDC 2
          ALOAD 2
          INVOKESPECIAL org/nlogo/nvm/ArgumentTypeException.<init> (Lorg/nlogo/nvm/Context;Lorg/nlogo/nvm/Instruction;IILjava/lang/Object;)V
          ATHROW
         L4
          ISTORE 2
          ALOAD 1
          ILOAD 2
          IFEQ L5
          ICONST_3
          GOTO L6
         L5
          ICONST_5
         L6
          PUTFIELD org/nlogo/nvm/Context.ip : I
         L7
          RETURN
[3]_asm_procedurego_setturtlevariable_3 "set energy energy - 1" Object => void
      _minus double,double => double
        _turtlevariable:ENERGY => Object
        _constdouble:1.0 => double
          TRYCATCHBLOCK L0 L1 L2 org/nlogo/api/AgentException
          TRYCATCHBLOCK L3 L4 L4 java/lang/ClassCastException
          TRYCATCHBLOCK L5 L6 L7 org/nlogo/api/AgentException
         L8
          ACONST_NULL
          ASTORE 2
         L0
          ALOAD 1
          GETFIELD org/nlogo/nvm/Context.agent : Lorg/nlogo/agent/Agent;
          BIPUSH 13
          INVOKEVIRTUAL org/nlogo/agent/Agent.getTurtleVariable (I)Ljava/lang/Object;
          ASTORE 2
         L1
          ALOAD 2
          GOTO L9
         L2
          ASTORE 3
          NEW org/nlogo/nvm/EngineException
          DUP
          ALOAD 1
          ALOAD 0
          ALOAD 3
          INVOKEVIRTUAL org/nlogo/api/AgentException.getMessage ()Ljava/lang/String;
          INVOKESPECIAL org/nlogo/nvm/EngineException.<init> (Lorg/nlogo/nvm/Context;Lorg/nlogo/nvm/Instruction;Ljava/lang/String;)V
          ATHROW
         L9
          ASTORE 2
         L3
          ALOAD 2
          CHECKCAST java/lang/Double
          INVOKEVIRTUAL java/lang/Double.doubleValue ()D
          GOTO L10
         L4
          POP
          NEW org/nlogo/nvm/ArgumentTypeException
          DUP
          ALOAD 1
          ALOAD 0
          BIPUSH 0
          LDC 1
          ALOAD 2
          INVOKESPECIAL org/nlogo/nvm/ArgumentTypeException.<init> (Lorg/nlogo/nvm/Context;Lorg/nlogo/nvm/Instruction;IILjava/lang/Object;)V
          ATHROW
         L10
          DCONST_1
         L11
          DSTORE 4
          DSTORE 2
          DLOAD 2
          DLOAD 4
          DSUB
         L12
          DSTORE 2
          NEW java/lang/Double
          DUP
          DLOAD 2
          INVOKESPECIAL java/lang/Double.<init> (D)V
          ASTORE 2
         L5
          ALOAD 1
          GETFIELD org/nlogo/nvm/Context.agent : Lorg/nlogo/agent/Agent;
          BIPUSH 13
          ALOAD 2
          INVOKEVIRTUAL org/nlogo/agent/Agent.setTurtleVariable (ILjava/lang/Object;)V
         L6
          ALOAD 1
          ICONST_4
          PUTFIELD org/nlogo/nvm/Context.ip : I
          GOTO L13
         L7
          ASTORE 3
          NEW org/nlogo/nvm/EngineException
          DUP
          ALOAD 1
          ALOAD 0
          ALOAD 3
          INVOKEVIRTUAL org/nlogo/api/AgentException.getMessage ()Ljava/lang/String;
          INVOKESPECIAL org/nlogo/nvm/EngineException.<init> (Lorg/nlogo/nvm/Context;Lorg/nlogo/nvm/Instruction;Ljava/lang/String;)V
          ATHROW
         L13
          RETURN
[4]_asm_procedurego_call_4 "eat-grass"
         L0
          NEW org/nlogo/nvm/Activation
          DUP
          ALOAD 0
          GETFIELD org/nlogo/prim/_asm_procedurego_call_4.kept1_procedure : Lorg/nlogo/nvm/Procedure;
          ALOAD 1
          GETFIELD org/nlogo/nvm/Context.activation : Lorg/nlogo/nvm/Activation;
          ICONST_5
          INVOKESPECIAL org/nlogo/nvm/Activation.<init> (Lorg/nlogo/nvm/Procedure;Lorg/nlogo/nvm/Activation;I)V
          ALOAD 1
          SWAP
          PUTFIELD org/nlogo/nvm/Context.activation : Lorg/nlogo/nvm/Activation;
          ALOAD 1
          ICONST_0
          PUTFIELD org/nlogo/nvm/Context.ip : I
         L1
          RETURN
[5]_asm_procedurego_call_5 "reproduce-sheep"
         L0
          NEW org/nlogo/nvm/Activation
          DUP
          ALOAD 0
          GETFIELD org/nlogo/prim/_asm_procedurego_call_5.kept1_procedure : Lorg/nlogo/nvm/Procedure;
          ALOAD 1
          GETFIELD org/nlogo/nvm/Context.activation : Lorg/nlogo/nvm/Activation;
          BIPUSH 6
          INVOKESPECIAL org/nlogo/nvm/Activation.<init> (Lorg/nlogo/nvm/Procedure;Lorg/nlogo/nvm/Activation;I)V
          ALOAD 1
          SWAP
          PUTFIELD org/nlogo/nvm/Context.activation : Lorg/nlogo/nvm/Activation;
          ALOAD 1
          ICONST_0
          PUTFIELD org/nlogo/nvm/Context.ip : I
         L1
          RETURN
[6]_asm_procedurego_call_6 "death"
         L0
          NEW org/nlogo/nvm/Activation
          DUP
          ALOAD 0
          GETFIELD org/nlogo/prim/_asm_procedurego_call_6.kept1_procedure : Lorg/nlogo/nvm/Procedure;
          ALOAD 1
          GETFIELD org/nlogo/nvm/Context.activation : Lorg/nlogo/nvm/Activation;
          BIPUSH 7
          INVOKESPECIAL org/nlogo/nvm/Activation.<init> (Lorg/nlogo/nvm/Procedure;Lorg/nlogo/nvm/Activation;I)V
          ALOAD 1
          SWAP
          PUTFIELD org/nlogo/nvm/Context.activation : Lorg/nlogo/nvm/Activation;
          ALOAD 1
          ICONST_0
          PUTFIELD org/nlogo/nvm/Context.ip : I
         L1
          RETURN
[7]_asm_procedurego_done_7 "" => void
         L0
          ALOAD 1
          ICONST_1
          PUTFIELD org/nlogo/nvm/Context.finished : Z
         L1
          RETURN
[8]_asm_procedurego_ask_8 "ask wolves" AgentSet => void
      _breed:WOLVES => AgentSet
         L0
          ALOAD 0
          GETFIELD org/nlogo/prim/_asm_procedurego_ask_8.world : Lorg/nlogo/agent/World;
          LDC "WOLVES"
          INVOKEVIRTUAL org/nlogo/agent/World.getBreed (Ljava/lang/String;)Lorg/nlogo/agent/AgentSet;
         L1
          ASTORE 2
          ALOAD 1
          GETFIELD org/nlogo/nvm/Context.agent : Lorg/nlogo/agent/Agent;
          INSTANCEOF org/nlogo/agent/Observer
          IFNE L2
          ALOAD 2
          ALOAD 0
          GETFIELD org/nlogo/prim/_asm_procedurego_ask_8.world : Lorg/nlogo/agent/World;
          INVOKEVIRTUAL org/nlogo/agent/World.turtles ()Lorg/nlogo/agent/AgentSet;
          IF_ACMPNE L3
          NEW org/nlogo/nvm/EngineException
          DUP
          ALOAD 1
          ALOAD 0
          GETSTATIC org/nlogo/api/I18N$.MODULE$ : Lorg/nlogo/api/I18N$;
          INVOKEVIRTUAL org/nlogo/api/I18N$.errors ()Lorg/nlogo/api/I18N$BundleKind;
          LDC "org.nlogo.prim.$common.onlyObserverCanAskAllTurtles"
          INVOKEVIRTUAL org/nlogo/api/I18N$BundleKind.get (Ljava/lang/String;)Ljava/lang/String;
          INVOKESPECIAL org/nlogo/nvm/EngineException.<init> (Lorg/nlogo/nvm/Context;Lorg/nlogo/nvm/Instruction;Ljava/lang/String;)V
          ATHROW
         L3
          ALOAD 2
          ALOAD 0
          GETFIELD org/nlogo/prim/_asm_procedurego_ask_8.world : Lorg/nlogo/agent/World;
          INVOKEVIRTUAL org/nlogo/agent/World.patches ()Lorg/nlogo/agent/AgentSet;
          IF_ACMPNE L2
          NEW org/nlogo/nvm/EngineException
          DUP
          ALOAD 1
          ALOAD 0
          GETSTATIC org/nlogo/api/I18N$.MODULE$ : Lorg/nlogo/api/I18N$;
          INVOKEVIRTUAL org/nlogo/api/I18N$.errors ()Lorg/nlogo/api/I18N$BundleKind;
          LDC "org.nlogo.prim.$common.onlyObserverCanAskAllPatches"
          INVOKEVIRTUAL org/nlogo/api/I18N$BundleKind.get (Ljava/lang/String;)Ljava/lang/String;
          INVOKESPECIAL org/nlogo/nvm/EngineException.<init> (Lorg/nlogo/nvm/Context;Lorg/nlogo/nvm/Instruction;Ljava/lang/String;)V
          ATHROW
         L2
          ALOAD 1
          ALOAD 2
          BIPUSH 9
          INVOKEVIRTUAL org/nlogo/nvm/Context.runExclusiveJob (Lorg/nlogo/agent/AgentSet;I)V
          ALOAD 1
          BIPUSH 15
          PUTFIELD org/nlogo/nvm/Context.ip : I
         L4
          RETURN
[9]_asm_procedurego_call_9 "move"
         L0
          NEW org/nlogo/nvm/Activation
          DUP
          ALOAD 0
          GETFIELD org/nlogo/prim/_asm_procedurego_call_9.kept1_procedure : Lorg/nlogo/nvm/Procedure;
          ALOAD 1
          GETFIELD org/nlogo/nvm/Context.activation : Lorg/nlogo/nvm/Activation;
          BIPUSH 10
          INVOKESPECIAL org/nlogo/nvm/Activation.<init> (Lorg/nlogo/nvm/Procedure;Lorg/nlogo/nvm/Activation;I)V
          ALOAD 1
          SWAP
          PUTFIELD org/nlogo/nvm/Context.activation : Lorg/nlogo/nvm/Activation;
          ALOAD 1
          ICONST_0
          PUTFIELD org/nlogo/nvm/Context.ip : I
         L1
          RETURN
[10]_asm_procedurego_setturtlevariable_10 "set energy energy - 1" Object => void
      _minus double,double => double
        _turtlevariable:ENERGY => Object
        _constdouble:1.0 => double
          TRYCATCHBLOCK L0 L1 L2 org/nlogo/api/AgentException
          TRYCATCHBLOCK L3 L4 L4 java/lang/ClassCastException
          TRYCATCHBLOCK L5 L6 L7 org/nlogo/api/AgentException
         L8
          ACONST_NULL
          ASTORE 2
         L0
          ALOAD 1
          GETFIELD org/nlogo/nvm/Context.agent : Lorg/nlogo/agent/Agent;
          BIPUSH 13
          INVOKEVIRTUAL org/nlogo/agent/Agent.getTurtleVariable (I)Ljava/lang/Object;
          ASTORE 2
         L1
          ALOAD 2
          GOTO L9
         L2
          ASTORE 3
          NEW org/nlogo/nvm/EngineException
          DUP
          ALOAD 1
          ALOAD 0
          ALOAD 3
          INVOKEVIRTUAL org/nlogo/api/AgentException.getMessage ()Ljava/lang/String;
          INVOKESPECIAL org/nlogo/nvm/EngineException.<init> (Lorg/nlogo/nvm/Context;Lorg/nlogo/nvm/Instruction;Ljava/lang/String;)V
          ATHROW
         L9
          ASTORE 2
         L3
          ALOAD 2
          CHECKCAST java/lang/Double
          INVOKEVIRTUAL java/lang/Double.doubleValue ()D
          GOTO L10
         L4
          POP
          NEW org/nlogo/nvm/ArgumentTypeException
          DUP
          ALOAD 1
          ALOAD 0
          BIPUSH 0
          LDC 1
          ALOAD 2
          INVOKESPECIAL org/nlogo/nvm/ArgumentTypeException.<init> (Lorg/nlogo/nvm/Context;Lorg/nlogo/nvm/Instruction;IILjava/lang/Object;)V
          ATHROW
         L10
          DCONST_1
         L11
          DSTORE 4
          DSTORE 2
          DLOAD 2
          DLOAD 4
          DSUB
         L12
          DSTORE 2
          NEW java/lang/Double
          DUP
          DLOAD 2
          INVOKESPECIAL java/lang/Double.<init> (D)V
          ASTORE 2
         L5
          ALOAD 1
          GETFIELD org/nlogo/nvm/Context.agent : Lorg/nlogo/agent/Agent;
          BIPUSH 13
          ALOAD 2
          INVOKEVIRTUAL org/nlogo/agent/Agent.setTurtleVariable (ILjava/lang/Object;)V
         L6
          ALOAD 1
          BIPUSH 11
          PUTFIELD org/nlogo/nvm/Context.ip : I
          GOTO L13
         L7
          ASTORE 3
          NEW org/nlogo/nvm/EngineException
          DUP
          ALOAD 1
          ALOAD 0
          ALOAD 3
          INVOKEVIRTUAL org/nlogo/api/AgentException.getMessage ()Ljava/lang/String;
          INVOKESPECIAL org/nlogo/nvm/EngineException.<init> (Lorg/nlogo/nvm/Context;Lorg/nlogo/nvm/Instruction;Ljava/lang/String;)V
          ATHROW
         L13
          RETURN
[11]_asm_procedurego_call_11 "catch-sheep"
         L0
          NEW org/nlogo/nvm/Activation
          DUP
          ALOAD 0
          GETFIELD org/nlogo/prim/_asm_procedurego_call_11.kept1_procedure : Lorg/nlogo/nvm/Procedure;
          ALOAD 1
          GETFIELD org/nlogo/nvm/Context.activation : Lorg/nlogo/nvm/Activation;
          BIPUSH 12
          INVOKESPECIAL org/nlogo/nvm/Activation.<init> (Lorg/nlogo/nvm/Procedure;Lorg/nlogo/nvm/Activation;I)V
          ALOAD 1
          SWAP
          PUTFIELD org/nlogo/nvm/Context.activation : Lorg/nlogo/nvm/Activation;
          ALOAD 1
          ICONST_0
          PUTFIELD org/nlogo/nvm/Context.ip : I
         L1
          RETURN
[12]_asm_procedurego_call_12 "reproduce-wolves"
         L0
          NEW org/nlogo/nvm/Activation
          DUP
          ALOAD 0
          GETFIELD org/nlogo/prim/_asm_procedurego_call_12.kept1_procedure : Lorg/nlogo/nvm/Procedure;
          ALOAD 1
          GETFIELD org/nlogo/nvm/Context.activation : Lorg/nlogo/nvm/Activation;
          BIPUSH 13
          INVOKESPECIAL org/nlogo/nvm/Activation.<init> (Lorg/nlogo/nvm/Procedure;Lorg/nlogo/nvm/Activation;I)V
          ALOAD 1
          SWAP
          PUTFIELD org/nlogo/nvm/Context.activation : Lorg/nlogo/nvm/Activation;
          ALOAD 1
          ICONST_0
          PUTFIELD org/nlogo/nvm/Context.ip : I
         L1
          RETURN
[13]_asm_procedurego_call_13 "death"
         L0
          NEW org/nlogo/nvm/Activation
          DUP
          ALOAD 0
          GETFIELD org/nlogo/prim/_asm_procedurego_call_13.kept1_procedure : Lorg/nlogo/nvm/Procedure;
          ALOAD 1
          GETFIELD org/nlogo/nvm/Context.activation : Lorg/nlogo/nvm/Activation;
          BIPUSH 14
          INVOKESPECIAL org/nlogo/nvm/Activation.<init> (Lorg/nlogo/nvm/Procedure;Lorg/nlogo/nvm/Activation;I)V
          ALOAD 1
          SWAP
          PUTFIELD org/nlogo/nvm/Context.activation : Lorg/nlogo/nvm/Activation;
          ALOAD 1
          ICONST_0
          PUTFIELD org/nlogo/nvm/Context.ip : I
         L1
          RETURN
[14]_asm_procedurego_done_14 "" => void
         L0
          ALOAD 1
          ICONST_1
          PUTFIELD org/nlogo/nvm/Context.finished : Z
         L1
          RETURN
[15]_asm_procedurego_if_15 "if grass?" boolean => void
      _observervariable:GRASS? => Object
          TRYCATCHBLOCK L0 L1 L1 java/lang/ClassCastException
         L2
          ALOAD 1
          GETFIELD org/nlogo/nvm/Context.agent : Lorg/nlogo/agent/Agent;
          BIPUSH 6
          INVOKEVIRTUAL org/nlogo/agent/Agent.getObserverVariable (I)Ljava/lang/Object;
         L3
          ASTORE 2
         L0
          ALOAD 2
          CHECKCAST java/lang/Boolean
          INVOKEVIRTUAL java/lang/Boolean.booleanValue ()Z
          GOTO L4
         L1
          POP
          NEW org/nlogo/nvm/ArgumentTypeException
          DUP
          ALOAD 1
          ALOAD 0
          BIPUSH 0
          LDC 2
          ALOAD 2
          INVOKESPECIAL org/nlogo/nvm/ArgumentTypeException.<init> (Lorg/nlogo/nvm/Context;Lorg/nlogo/nvm/Instruction;IILjava/lang/Object;)V
          ATHROW
         L4
          ISTORE 2
          ALOAD 1
          ILOAD 2
          IFEQ L5
          BIPUSH 16
          GOTO L6
         L5
          BIPUSH 19
         L6
          PUTFIELD org/nlogo/nvm/Context.ip : I
         L7
          RETURN
[16]_asm_procedurego_ask_16 "ask patches" AgentSet => void
      _patches => AgentSet
         L0
          ALOAD 0
          GETFIELD org/nlogo/prim/_asm_procedurego_ask_16.world : Lorg/nlogo/agent/World;
          INVOKEVIRTUAL org/nlogo/agent/World.patches ()Lorg/nlogo/agent/AgentSet;
         L1
          ASTORE 2
          ALOAD 1
          GETFIELD org/nlogo/nvm/Context.agent : Lorg/nlogo/agent/Agent;
          INSTANCEOF org/nlogo/agent/Observer
          IFNE L2
          ALOAD 2
          ALOAD 0
          GETFIELD org/nlogo/prim/_asm_procedurego_ask_16.world : Lorg/nlogo/agent/World;
          INVOKEVIRTUAL org/nlogo/agent/World.turtles ()Lorg/nlogo/agent/AgentSet;
          IF_ACMPNE L3
          NEW org/nlogo/nvm/EngineException
          DUP
          ALOAD 1
          ALOAD 0
          GETSTATIC org/nlogo/api/I18N$.MODULE$ : Lorg/nlogo/api/I18N$;
          INVOKEVIRTUAL org/nlogo/api/I18N$.errors ()Lorg/nlogo/api/I18N$BundleKind;
          LDC "org.nlogo.prim.$common.onlyObserverCanAskAllTurtles"
          INVOKEVIRTUAL org/nlogo/api/I18N$BundleKind.get (Ljava/lang/String;)Ljava/lang/String;
          INVOKESPECIAL org/nlogo/nvm/EngineException.<init> (Lorg/nlogo/nvm/Context;Lorg/nlogo/nvm/Instruction;Ljava/lang/String;)V
          ATHROW
         L3
          ALOAD 2
          ALOAD 0
          GETFIELD org/nlogo/prim/_asm_procedurego_ask_16.world : Lorg/nlogo/agent/World;
          INVOKEVIRTUAL org/nlogo/agent/World.patches ()Lorg/nlogo/agent/AgentSet;
          IF_ACMPNE L2
          NEW org/nlogo/nvm/EngineException
          DUP
          ALOAD 1
          ALOAD 0
          GETSTATIC org/nlogo/api/I18N$.MODULE$ : Lorg/nlogo/api/I18N$;
          INVOKEVIRTUAL org/nlogo/api/I18N$.errors ()Lorg/nlogo/api/I18N$BundleKind;
          LDC "org.nlogo.prim.$common.onlyObserverCanAskAllPatches"
          INVOKEVIRTUAL org/nlogo/api/I18N$BundleKind.get (Ljava/lang/String;)Ljava/lang/String;
          INVOKESPECIAL org/nlogo/nvm/EngineException.<init> (Lorg/nlogo/nvm/Context;Lorg/nlogo/nvm/Instruction;Ljava/lang/String;)V
          ATHROW
         L2
          ALOAD 1
          ALOAD 2
          BIPUSH 17
          INVOKEVIRTUAL org/nlogo/nvm/Context.runExclusiveJob (Lorg/nlogo/agent/AgentSet;I)V
          ALOAD 1
          BIPUSH 19
          PUTFIELD org/nlogo/nvm/Context.ip : I
         L4
          RETURN
[17]_asm_procedurego_call_17 "grow-grass"
         L0
          NEW org/nlogo/nvm/Activation
          DUP
          ALOAD 0
          GETFIELD org/nlogo/prim/_asm_procedurego_call_17.kept1_procedure : Lorg/nlogo/nvm/Procedure;
          ALOAD 1
          GETFIELD org/nlogo/nvm/Context.activation : Lorg/nlogo/nvm/Activation;
          BIPUSH 18
          INVOKESPECIAL org/nlogo/nvm/Activation.<init> (Lorg/nlogo/nvm/Procedure;Lorg/nlogo/nvm/Activation;I)V
          ALOAD 1
          SWAP
          PUTFIELD org/nlogo/nvm/Context.activation : Lorg/nlogo/nvm/Activation;
          ALOAD 1
          ICONST_0
          PUTFIELD org/nlogo/nvm/Context.ip : I
         L1
          RETURN
[18]_asm_procedurego_done_18 "" => void
         L0
          ALOAD 1
          ICONST_1
          PUTFIELD org/nlogo/nvm/Context.finished : Z
         L1
          RETURN
[19]_asm_procedurego_if_19 "if plot?" boolean => void
      _observervariable:PLOT? => Object
          TRYCATCHBLOCK L0 L1 L1 java/lang/ClassCastException
         L2
          ALOAD 1
          GETFIELD org/nlogo/nvm/Context.agent : Lorg/nlogo/agent/Agent;
          BIPUSH 8
          INVOKEVIRTUAL org/nlogo/agent/Agent.getObserverVariable (I)Ljava/lang/Object;
         L3
          ASTORE 2
         L0
          ALOAD 2
          CHECKCAST java/lang/Boolean
          INVOKEVIRTUAL java/lang/Boolean.booleanValue ()Z
          GOTO L4
         L1
          POP
          NEW org/nlogo/nvm/ArgumentTypeException
          DUP
          ALOAD 1
          ALOAD 0
          BIPUSH 0
          LDC 2
          ALOAD 2
          INVOKESPECIAL org/nlogo/nvm/ArgumentTypeException.<init> (Lorg/nlogo/nvm/Context;Lorg/nlogo/nvm/Instruction;IILjava/lang/Object;)V
          ATHROW
         L4
          ISTORE 2
          ALOAD 1
          ILOAD 2
          IFEQ L5
          BIPUSH 20
          GOTO L6
         L5
          BIPUSH 21
         L6
          PUTFIELD org/nlogo/nvm/Context.ip : I
         L7
          RETURN
[20]_asm_procedurego_call_20 "graph"
         L0
          NEW org/nlogo/nvm/Activation
          DUP
          ALOAD 0
          GETFIELD org/nlogo/prim/_asm_procedurego_call_20.kept1_procedure : Lorg/nlogo/nvm/Procedure;
          ALOAD 1
          GETFIELD org/nlogo/nvm/Context.activation : Lorg/nlogo/nvm/Activation;
          BIPUSH 21
          INVOKESPECIAL org/nlogo/nvm/Activation.<init> (Lorg/nlogo/nvm/Procedure;Lorg/nlogo/nvm/Activation;I)V
          ALOAD 1
          SWAP
          PUTFIELD org/nlogo/nvm/Context.activation : Lorg/nlogo/nvm/Activation;
          ALOAD 1
          ICONST_0
          PUTFIELD org/nlogo/nvm/Context.ip : I
         L1
          RETURN
[21]_tick
[22]_asm_procedurego_if_21 "if (count turtles = 0" boolean => void
      _equal double,double => boolean
        _count AgentSet => double
          _turtles => AgentSet
        _constdouble:0.0 => double
         L0
          ALOAD 0
          GETFIELD org/nlogo/prim/_asm_procedurego_if_21.world : Lorg/nlogo/agent/World;
          INVOKEVIRTUAL org/nlogo/agent/World.turtles ()Lorg/nlogo/agent/AgentSet;
         L1
          ASTORE 2
          ALOAD 2
          INVOKEINTERFACE org/nlogo/api/AgentSet.count ()I
          I2D
         L2
          DCONST_0
         L3
          DSTORE 4
          DSTORE 2
          DLOAD 2
          DLOAD 4
          DCMPL
          IFNE L4
          ICONST_1
          GOTO L5
         L4
          ICONST_0
         L5
          ISTORE 2
          ALOAD 1
          ILOAD 2
          IFEQ L6
          BIPUSH 23
          GOTO L7
         L6
          BIPUSH 24
         L7
          PUTFIELD org/nlogo/nvm/Context.ip : I
         L8
          RETURN
[23]_asm_procedurego_stop_22 "stop" => void
         L0
          ALOAD 1
          INVOKEVIRTUAL org/nlogo/nvm/Context.atTopActivation ()Z
          IFNE L1
          ALOAD 1
          ICONST_1
          PUTFIELD org/nlogo/nvm/Context.finished : Z
          GOTO L2
         L1
          ALOAD 1
          GETFIELD org/nlogo/nvm/Context.activation : Lorg/nlogo/nvm/Activation;
          INVOKEVIRTUAL org/nlogo/nvm/Activation.procedure ()Lorg/nlogo/nvm/Procedure;
          INVOKEVIRTUAL org/nlogo/nvm/Procedure.isReporter ()Z
          IFNE L3
          ALOAD 1
          GETFIELD org/nlogo/nvm/Context.activation : Lorg/nlogo/nvm/Activation;
          INVOKEVIRTUAL org/nlogo/nvm/Activation.procedure ()Lorg/nlogo/nvm/Procedure;
          INVOKEVIRTUAL org/nlogo/nvm/Procedure.isTask ()Z
          IFEQ L4
          ALOAD 1
          GETFIELD org/nlogo/nvm/Context.activation : Lorg/nlogo/nvm/Activation;
          INVOKEVIRTUAL org/nlogo/nvm/Activation.procedure ()Lorg/nlogo/nvm/Procedure;
          INVOKEVIRTUAL org/nlogo/nvm/Procedure.parent ()Lorg/nlogo/nvm/Procedure;
          INVOKEVIRTUAL org/nlogo/nvm/Procedure.isReporter ()Z
          IFEQ L4
         L3
          NEW org/nlogo/nvm/EngineException
          DUP
          ALOAD 1
          ALOAD 0
          INVOKESTATIC org/nlogo/api/I18N.errorsJ ()Lorg/nlogo/api/I18NJava;
          LDC "org.nlogo.prim.etc._stop.notAllowedInsideToReport"
          ICONST_1
          ANEWARRAY java/lang/Object
          DUP
          ICONST_0
          LDC "STOP"
          AASTORE
          INVOKEINTERFACE org/nlogo/api/I18NJava.getN (Ljava/lang/String;[Ljava/lang/Object;)Ljava/lang/String;
          INVOKESPECIAL org/nlogo/nvm/EngineException.<init> (Lorg/nlogo/nvm/Context;Lorg/nlogo/nvm/Instruction;Ljava/lang/String;)V
          ATHROW
         L4
          ALOAD 1
          INVOKEVIRTUAL org/nlogo/nvm/Context.stop ()V
         L2
          RETURN
[24]_asm_procedurego_return_23 "" => void
         L0
          ALOAD 1
          INVOKEVIRTUAL org/nlogo/nvm/Context.returnFromProcedure ()V
          ALOAD 1
          ICONST_0
          PUTFIELD org/nlogo/nvm/Context.stopping : Z
         L1
          RETURN

procedure MOVE:[]{-T--}:
[0]_asm_proceduremove_right_0 "rt random 50 - random" double => void
      _minus double,double => double
        _randomconst:50 => double
        _randomconst:50 => double
         L0
          ALOAD 1
          GETFIELD org/nlogo/nvm/Context.job : Lorg/nlogo/nvm/Job;
          GETFIELD org/nlogo/nvm/Job.random : Lorg/nlogo/util/MersenneTwisterFast;
          LDC 50
          INVOKEVIRTUAL org/nlogo/util/MersenneTwisterFast.nextLong (J)J
          L2D
         L1
          ALOAD 1
          GETFIELD org/nlogo/nvm/Context.job : Lorg/nlogo/nvm/Job;
          GETFIELD org/nlogo/nvm/Job.random : Lorg/nlogo/util/MersenneTwisterFast;
          LDC 50
          INVOKEVIRTUAL org/nlogo/util/MersenneTwisterFast.nextLong (J)J
          L2D
         L2
          DSTORE 4
          DSTORE 2
          DLOAD 2
          DLOAD 4
          DSUB
         L3
          DSTORE 2
          ALOAD 1
          GETFIELD org/nlogo/nvm/Context.agent : Lorg/nlogo/agent/Agent;
          CHECKCAST org/nlogo/agent/Turtle
          DLOAD 2
          INVOKEVIRTUAL org/nlogo/agent/Turtle.turnRight (D)V
          ALOAD 1
          ICONST_1
          PUTFIELD org/nlogo/nvm/Context.ip : I
         L4
          RETURN
[1]_asm_proceduremove_fd1_1 "fd" => void
          TRYCATCHBLOCK L0 L1 L1 org/nlogo/api/AgentException
         L0
          ALOAD 1
          GETFIELD org/nlogo/nvm/Context.agent : Lorg/nlogo/agent/Agent;
          CHECKCAST org/nlogo/agent/Turtle
          DCONST_1
          INVOKEVIRTUAL org/nlogo/agent/Turtle.jump (D)V
          GOTO L2
         L1
          ASTORE 2
         L2
          ALOAD 1
          ICONST_2
          PUTFIELD org/nlogo/nvm/Context.ip : I
         L3
          RETURN
[2]_asm_proceduremove_return_2 "" => void
         L0
          ALOAD 1
          INVOKEVIRTUAL org/nlogo/nvm/Context.returnFromProcedure ()V
          ALOAD 1
          ICONST_0
          PUTFIELD org/nlogo/nvm/Context.stopping : Z
         L1
          RETURN

procedure EAT-GRASS:[]{-T--}:
[0]_asm_procedureeatgrass_if_0 "if pcolor = green" boolean => void
      _equal Object,double => boolean
        _patchvariable:PCOLOR => Object
        _constdouble:55.0 => double
          TRYCATCHBLOCK L0 L1 L2 org/nlogo/api/AgentException
         L3
          ACONST_NULL
          ASTORE 2
         L0
          ALOAD 1
          GETFIELD org/nlogo/nvm/Context.agent : Lorg/nlogo/agent/Agent;
          ICONST_2
          INVOKEVIRTUAL org/nlogo/agent/Agent.getPatchVariable (I)Ljava/lang/Object;
          ASTORE 2
         L1
          ALOAD 2
          GOTO L4
         L2
          ASTORE 3
          NEW org/nlogo/nvm/EngineException
          DUP
          ALOAD 1
          ALOAD 0
          ALOAD 3
          INVOKEVIRTUAL org/nlogo/api/AgentException.getMessage ()Ljava/lang/String;
          INVOKESPECIAL org/nlogo/nvm/EngineException.<init> (Lorg/nlogo/nvm/Context;Lorg/nlogo/nvm/Instruction;Ljava/lang/String;)V
          ATHROW
         L4
          LDC 55.0
         L5
          DSTORE 3
          ASTORE 2
          ALOAD 2
          ASTORE 5
          ALOAD 5
          INSTANCEOF java/lang/Double
          IFEQ L6
          DLOAD 3
          ALOAD 5
          CHECKCAST java/lang/Double
          INVOKEVIRTUAL java/lang/Double.doubleValue ()D
          DCMPL
          IFNE L7
          ICONST_1
          GOTO L8
         L7
          ICONST_0
          GOTO L8
         L6
          ICONST_0
         L8
          ISTORE 2
          ALOAD 1
          ILOAD 2
          IFEQ L9
          ICONST_1
          GOTO L10
         L9
          ICONST_3
         L10
          PUTFIELD org/nlogo/nvm/Context.ip : I
         L11
          RETURN
[1]_asm_procedureeatgrass_setpatchvariable_1 "set pcolor brown" Object => void
      _constdouble:35.0 => Double
          TRYCATCHBLOCK L0 L1 L2 org/nlogo/api/AgentException
         L3
          ALOAD 0
          GETFIELD org/nlogo/prim/_asm_procedureeatgrass_setpatchvariable_1.kept2_value : Ljava/lang/Double;
         L4
          ASTORE 2
         L0
          ALOAD 1
          GETFIELD org/nlogo/nvm/Context.agent : Lorg/nlogo/agent/Agent;
          ICONST_2
          ALOAD 2
          INVOKEVIRTUAL org/nlogo/agent/Agent.setPatchVariable (ILjava/lang/Object;)V
         L1
          ALOAD 1
          ICONST_2
          PUTFIELD org/nlogo/nvm/Context.ip : I
          GOTO L5
         L2
          ASTORE 3
          NEW org/nlogo/nvm/EngineException
          DUP
          ALOAD 1
          ALOAD 0
          ALOAD 3
          INVOKEVIRTUAL org/nlogo/api/AgentException.getMessage ()Ljava/lang/String;
          INVOKESPECIAL org/nlogo/nvm/EngineException.<init> (Lorg/nlogo/nvm/Context;Lorg/nlogo/nvm/Instruction;Ljava/lang/String;)V
          ATHROW
         L5
          RETURN
[2]_asm_procedureeatgrass_setturtlevariable_2 "set energy energy + sheep-metabolism" Object => void
      _plus double,double => double
        _turtlevariable:ENERGY => Object
        _observervariable:SHEEP-METABOLISM => Object
          TRYCATCHBLOCK L0 L1 L2 org/nlogo/api/AgentException
          TRYCATCHBLOCK L3 L4 L4 java/lang/ClassCastException
          TRYCATCHBLOCK L5 L6 L6 java/lang/ClassCastException
          TRYCATCHBLOCK L7 L8 L9 org/nlogo/api/AgentException
         L10
          ACONST_NULL
          ASTORE 2
         L0
          ALOAD 1
          GETFIELD org/nlogo/nvm/Context.agent : Lorg/nlogo/agent/Agent;
          BIPUSH 13
          INVOKEVIRTUAL org/nlogo/agent/Agent.getTurtleVariable (I)Ljava/lang/Object;
          ASTORE 2
         L1
          ALOAD 2
          GOTO L11
         L2
          ASTORE 3
          NEW org/nlogo/nvm/EngineException
          DUP
          ALOAD 1
          ALOAD 0
          ALOAD 3
          INVOKEVIRTUAL org/nlogo/api/AgentException.getMessage ()Ljava/lang/String;
          INVOKESPECIAL org/nlogo/nvm/EngineException.<init> (Lorg/nlogo/nvm/Context;Lorg/nlogo/nvm/Instruction;Ljava/lang/String;)V
          ATHROW
         L11
          ASTORE 2
         L3
          ALOAD 2
          CHECKCAST java/lang/Double
          INVOKEVIRTUAL java/lang/Double.doubleValue ()D
          GOTO L12
         L4
          POP
          NEW org/nlogo/nvm/ArgumentTypeException
          DUP
          ALOAD 1
          ALOAD 0
          BIPUSH 0
          LDC 1
          ALOAD 2
          INVOKESPECIAL org/nlogo/nvm/ArgumentTypeException.<init> (Lorg/nlogo/nvm/Context;Lorg/nlogo/nvm/Instruction;IILjava/lang/Object;)V
          ATHROW
         L12
          ALOAD 1
          GETFIELD org/nlogo/nvm/Context.agent : Lorg/nlogo/agent/Agent;
          ICONST_1
          INVOKEVIRTUAL org/nlogo/agent/Agent.getObserverVariable (I)Ljava/lang/Object;
         L13
          ASTORE 2
         L5
          ALOAD 2
          CHECKCAST java/lang/Double
          INVOKEVIRTUAL java/lang/Double.doubleValue ()D
          GOTO L14
         L6
          POP
          NEW org/nlogo/nvm/ArgumentTypeException
          DUP
          ALOAD 1
          ALOAD 0
          BIPUSH 1
          LDC 1
          ALOAD 2
          INVOKESPECIAL org/nlogo/nvm/ArgumentTypeException.<init> (Lorg/nlogo/nvm/Context;Lorg/nlogo/nvm/Instruction;IILjava/lang/Object;)V
          ATHROW
         L14
          DSTORE 4
          DSTORE 2
          DLOAD 2
          DLOAD 4
          DADD
         L15
          DSTORE 2
          NEW java/lang/Double
          DUP
          DLOAD 2
          INVOKESPECIAL java/lang/Double.<init> (D)V
          ASTORE 2
         L7
          ALOAD 1
          GETFIELD org/nlogo/nvm/Context.agent : Lorg/nlogo/agent/Agent;
          BIPUSH 13
          ALOAD 2
          INVOKEVIRTUAL org/nlogo/agent/Agent.setTurtleVariable (ILjava/lang/Object;)V
         L8
          ALOAD 1
          ICONST_3
          PUTFIELD org/nlogo/nvm/Context.ip : I
          GOTO L16
         L9
          ASTORE 3
          NEW org/nlogo/nvm/EngineException
          DUP
          ALOAD 1
          ALOAD 0
          ALOAD 3
          INVOKEVIRTUAL org/nlogo/api/AgentException.getMessage ()Ljava/lang/String;
          INVOKESPECIAL org/nlogo/nvm/EngineException.<init> (Lorg/nlogo/nvm/Context;Lorg/nlogo/nvm/Instruction;Ljava/lang/String;)V
          ATHROW
         L16
          RETURN
[3]_asm_procedureeatgrass_return_3 "" => void
         L0
          ALOAD 1
          INVOKEVIRTUAL org/nlogo/nvm/Context.returnFromProcedure ()V
          ALOAD 1
          ICONST_0
          PUTFIELD org/nlogo/nvm/Context.stopping : Z
         L1
          RETURN

procedure REPRODUCE-SHEEP:[]{-T--}:
[0]_asm_procedurereproducesheep_if_0 "if random-float 100 < sheep-reproduce" boolean => void
      _lessthan double,Object => boolean
        _randomfloat double => double
          _constdouble:100.0 => double
        _observervariable:SHEEP-REPRODUCE => Object
         L0
          LDC 100.0
         L1
          DSTORE 2
          DLOAD 2
          ALOAD 1
          GETFIELD org/nlogo/nvm/Context.job : Lorg/nlogo/nvm/Job;
          GETFIELD org/nlogo/nvm/Job.random : Lorg/nlogo/util/MersenneTwisterFast;
          INVOKEVIRTUAL org/nlogo/util/MersenneTwisterFast.nextDouble ()D
          DMUL
         L2
          ALOAD 1
          GETFIELD org/nlogo/nvm/Context.agent : Lorg/nlogo/agent/Agent;
          ICONST_2
          INVOKEVIRTUAL org/nlogo/agent/Agent.getObserverVariable (I)Ljava/lang/Object;
         L3
          ASTORE 4
          DSTORE 2
          ALOAD 4
          ASTORE 5
          ALOAD 5
          INSTANCEOF java/lang/Double
          IFEQ L4
          DLOAD 2
          ALOAD 5
          CHECKCAST java/lang/Double
          INVOKEVIRTUAL java/lang/Double.doubleValue ()D
          DCMPG
          IFGE L5
          ICONST_1
          GOTO L6
         L5
          ICONST_0
         L6
          GOTO L7
         L4
          NEW org/nlogo/nvm/EngineException
          DUP
          ALOAD 1
          ALOAD 0
          GETSTATIC org/nlogo/api/I18N$.MODULE$ : Lorg/nlogo/api/I18N$;
          INVOKEVIRTUAL org/nlogo/api/I18N$.errors ()Lorg/nlogo/api/I18N$BundleKind;
          LDC "org.nlogo.prim._lessthan.cantUseLessthanOnDifferentArgs"
          GETSTATIC scala/Predef$.MODULE$ : Lscala/Predef$;
          ICONST_2
          ANEWARRAY java/lang/Object
          DUP
          ICONST_0
          GETSTATIC org/nlogo/api/TypeNames$.MODULE$ : Lorg/nlogo/api/TypeNames$;
          DLOAD 2
          INVOKESTATIC scala/runtime/BoxesRunTime.boxToDouble (D)Ljava/lang/Double;
          INVOKEVIRTUAL org/nlogo/api/TypeNames$.aName (Ljava/lang/Object;)Ljava/lang/String;
          AASTORE
          DUP
          ICONST_1
          GETSTATIC org/nlogo/api/TypeNames$.MODULE$ : Lorg/nlogo/api/TypeNames$;
          ALOAD 4
          INVOKEVIRTUAL org/nlogo/api/TypeNames$.aName (Ljava/lang/Object;)Ljava/lang/String;
          AASTORE
          INVOKEVIRTUAL scala/Predef$.wrapRefArray ([Ljava/lang/Object;)Lscala/collection/mutable/WrappedArray;
          INVOKEVIRTUAL org/nlogo/api/I18N$BundleKind.getN (Ljava/lang/String;Lscala/collection/Seq;)Ljava/lang/String;
          INVOKESPECIAL org/nlogo/nvm/EngineException.<init> (Lorg/nlogo/nvm/Context;Lorg/nlogo/nvm/Instruction;Ljava/lang/String;)V
          ATHROW
         L7
          ISTORE 2
          ALOAD 1
          ILOAD 2
          IFEQ L8
          ICONST_1
          GOTO L9
         L8
          BIPUSH 6
         L9
          PUTFIELD org/nlogo/nvm/Context.ip : I
         L10
          RETURN
[1]_asm_procedurereproducesheep_setturtlevariable_1 "set energy round (energy / 2" Object => void
      _round double => double
        _div double,double => double
          _turtlevariable:ENERGY => Object
          _constdouble:2.0 => double
          TRYCATCHBLOCK L0 L1 L2 org/nlogo/api/AgentException
          TRYCATCHBLOCK L3 L4 L4 java/lang/ClassCastException
          TRYCATCHBLOCK L5 L6 L7 org/nlogo/api/AgentException
         L8
          ACONST_NULL
          ASTORE 2
         L0
          ALOAD 1
          GETFIELD org/nlogo/nvm/Context.agent : Lorg/nlogo/agent/Agent;
          BIPUSH 13
          INVOKEVIRTUAL org/nlogo/agent/Agent.getTurtleVariable (I)Ljava/lang/Object;
          ASTORE 2
         L1
          ALOAD 2
          GOTO L9
         L2
          ASTORE 3
          NEW org/nlogo/nvm/EngineException
          DUP
          ALOAD 1
          ALOAD 0
          ALOAD 3
          INVOKEVIRTUAL org/nlogo/api/AgentException.getMessage ()Ljava/lang/String;
          INVOKESPECIAL org/nlogo/nvm/EngineException.<init> (Lorg/nlogo/nvm/Context;Lorg/nlogo/nvm/Instruction;Ljava/lang/String;)V
          ATHROW
         L9
          ASTORE 2
         L3
          ALOAD 2
          CHECKCAST java/lang/Double
          INVOKEVIRTUAL java/lang/Double.doubleValue ()D
          GOTO L10
         L4
          POP
          NEW org/nlogo/nvm/ArgumentTypeException
          DUP
          ALOAD 1
          ALOAD 0
          BIPUSH 0
          LDC 1
          ALOAD 2
          INVOKESPECIAL org/nlogo/nvm/ArgumentTypeException.<init> (Lorg/nlogo/nvm/Context;Lorg/nlogo/nvm/Instruction;IILjava/lang/Object;)V
          ATHROW
         L10
          LDC 2.0
         L11
          DSTORE 4
          DSTORE 2
          DLOAD 4
          DCONST_0
          DCMPL
          IFNE L12
          NEW org/nlogo/nvm/EngineException
          DUP
          ALOAD 1
          ALOAD 0
          INVOKESTATIC org/nlogo/api/I18N.errorsJ ()Lorg/nlogo/api/I18NJava;
          LDC "org.nlogo.prim.etc.$common.divByZero"
          INVOKEINTERFACE org/nlogo/api/I18NJava.get (Ljava/lang/String;)Ljava/lang/String;
          INVOKESPECIAL org/nlogo/nvm/EngineException.<init> (Lorg/nlogo/nvm/Context;Lorg/nlogo/nvm/Instruction;Ljava/lang/String;)V
          ATHROW
         L12
          DLOAD 2
          DLOAD 4
          DDIV
         L13
          DSTORE 2
          GETSTATIC org/nlogo/api/Approximate$.MODULE$ : Lorg/nlogo/api/Approximate$;
          DLOAD 2
          ICONST_0
          INVOKEVIRTUAL org/nlogo/api/Approximate$.approximate (DI)D
         L14
          DSTORE 2
          NEW java/lang/Double
          DUP
          DLOAD 2
          INVOKESPECIAL java/lang/Double.<init> (D)V
          ASTORE 2
         L5
          ALOAD 1
          GETFIELD org/nlogo/nvm/Context.agent : Lorg/nlogo/agent/Agent;
          BIPUSH 13
          ALOAD 2
          INVOKEVIRTUAL org/nlogo/agent/Agent.setTurtleVariable (ILjava/lang/Object;)V
         L6
          ALOAD 1
          ICONST_2
          PUTFIELD org/nlogo/nvm/Context.ip : I
          GOTO L15
         L7
          ASTORE 3
          NEW org/nlogo/nvm/EngineException
          DUP
          ALOAD 1
          ALOAD 0
          ALOAD 3
          INVOKEVIRTUAL org/nlogo/api/AgentException.getMessage ()Ljava/lang/String;
          INVOKESPECIAL org/nlogo/nvm/EngineException.<init> (Lorg/nlogo/nvm/Context;Lorg/nlogo/nvm/Instruction;Ljava/lang/String;)V
          ATHROW
         L15
          RETURN
[2]_hatch:,+6
      _asm_procedurereproducesheep_constdouble_2 "1" => Double
           L0
            ALOAD 0
            GETFIELD org/nlogo/prim/_asm_procedurereproducesheep_constdouble_2.kept1_value : Ljava/lang/Double;
           L1
            ARETURN
[3]_asm_procedurereproducesheep_right_3 "rt random" double => void
      _randomconst:360 => double
         L0
          ALOAD 1
          GETFIELD org/nlogo/nvm/Context.job : Lorg/nlogo/nvm/Job;
          GETFIELD org/nlogo/nvm/Job.random : Lorg/nlogo/util/MersenneTwisterFast;
          LDC 360
          INVOKEVIRTUAL org/nlogo/util/MersenneTwisterFast.nextLong (J)J
          L2D
         L1
          DSTORE 2
          ALOAD 1
          GETFIELD org/nlogo/nvm/Context.agent : Lorg/nlogo/agent/Agent;
          CHECKCAST org/nlogo/agent/Turtle
          DLOAD 2
          INVOKEVIRTUAL org/nlogo/agent/Turtle.turnRight (D)V
          ALOAD 1
          ICONST_4
          PUTFIELD org/nlogo/nvm/Context.ip : I
         L2
          RETURN
[4]_asm_procedurereproducesheep_fd1_4 "fd" => void
          TRYCATCHBLOCK L0 L1 L1 org/nlogo/api/AgentException
         L0
          ALOAD 1
          GETFIELD org/nlogo/nvm/Context.agent : Lorg/nlogo/agent/Agent;
          CHECKCAST org/nlogo/agent/Turtle
          DCONST_1
          INVOKEVIRTUAL org/nlogo/agent/Turtle.jump (D)V
          GOTO L2
         L1
          ASTORE 2
         L2
          ALOAD 1
          ICONST_5
          PUTFIELD org/nlogo/nvm/Context.ip : I
         L3
          RETURN
[5]_asm_procedurereproducesheep_done_5 "" => void
         L0
          ALOAD 1
          ICONST_1
          PUTFIELD org/nlogo/nvm/Context.finished : Z
         L1
          RETURN
[6]_asm_procedurereproducesheep_return_6 "" => void
         L0
          ALOAD 1
          INVOKEVIRTUAL org/nlogo/nvm/Context.returnFromProcedure ()V
          ALOAD 1
          ICONST_0
          PUTFIELD org/nlogo/nvm/Context.stopping : Z
         L1
          RETURN

procedure REPRODUCE-WOLVES:[]{-T--}:
[0]_asm_procedurereproducewolves_if_0 "if random-float 100 < wolf-reproduce" boolean => void
      _lessthan double,Object => boolean
        _randomfloat double => double
          _constdouble:100.0 => double
        _observervariable:WOLF-REPRODUCE => Object
         L0
          LDC 100.0
         L1
          DSTORE 2
          DLOAD 2
          ALOAD 1
          GETFIELD org/nlogo/nvm/Context.job : Lorg/nlogo/nvm/Job;
          GETFIELD org/nlogo/nvm/Job.random : Lorg/nlogo/util/MersenneTwisterFast;
          INVOKEVIRTUAL org/nlogo/util/MersenneTwisterFast.nextDouble ()D
          DMUL
         L2
          ALOAD 1
          GETFIELD org/nlogo/nvm/Context.agent : Lorg/nlogo/agent/Agent;
          ICONST_5
          INVOKEVIRTUAL org/nlogo/agent/Agent.getObserverVariable (I)Ljava/lang/Object;
         L3
          ASTORE 4
          DSTORE 2
          ALOAD 4
          ASTORE 5
          ALOAD 5
          INSTANCEOF java/lang/Double
          IFEQ L4
          DLOAD 2
          ALOAD 5
          CHECKCAST java/lang/Double
          INVOKEVIRTUAL java/lang/Double.doubleValue ()D
          DCMPG
          IFGE L5
          ICONST_1
          GOTO L6
         L5
          ICONST_0
         L6
          GOTO L7
         L4
          NEW org/nlogo/nvm/EngineException
          DUP
          ALOAD 1
          ALOAD 0
          GETSTATIC org/nlogo/api/I18N$.MODULE$ : Lorg/nlogo/api/I18N$;
          INVOKEVIRTUAL org/nlogo/api/I18N$.errors ()Lorg/nlogo/api/I18N$BundleKind;
          LDC "org.nlogo.prim._lessthan.cantUseLessthanOnDifferentArgs"
          GETSTATIC scala/Predef$.MODULE$ : Lscala/Predef$;
          ICONST_2
          ANEWARRAY java/lang/Object
          DUP
          ICONST_0
          GETSTATIC org/nlogo/api/TypeNames$.MODULE$ : Lorg/nlogo/api/TypeNames$;
          DLOAD 2
          INVOKESTATIC scala/runtime/BoxesRunTime.boxToDouble (D)Ljava/lang/Double;
          INVOKEVIRTUAL org/nlogo/api/TypeNames$.aName (Ljava/lang/Object;)Ljava/lang/String;
          AASTORE
          DUP
          ICONST_1
          GETSTATIC org/nlogo/api/TypeNames$.MODULE$ : Lorg/nlogo/api/TypeNames$;
          ALOAD 4
          INVOKEVIRTUAL org/nlogo/api/TypeNames$.aName (Ljava/lang/Object;)Ljava/lang/String;
          AASTORE
          INVOKEVIRTUAL scala/Predef$.wrapRefArray ([Ljava/lang/Object;)Lscala/collection/mutable/WrappedArray;
          INVOKEVIRTUAL org/nlogo/api/I18N$BundleKind.getN (Ljava/lang/String;Lscala/collection/Seq;)Ljava/lang/String;
          INVOKESPECIAL org/nlogo/nvm/EngineException.<init> (Lorg/nlogo/nvm/Context;Lorg/nlogo/nvm/Instruction;Ljava/lang/String;)V
          ATHROW
         L7
          ISTORE 2
          ALOAD 1
          ILOAD 2
          IFEQ L8
          ICONST_1
          GOTO L9
         L8
          BIPUSH 6
         L9
          PUTFIELD org/nlogo/nvm/Context.ip : I
         L10
          RETURN
[1]_asm_procedurereproducewolves_setturtlevariable_1 "set energy round (energy / 2" Object => void
      _round double => double
        _div double,double => double
          _turtlevariable:ENERGY => Object
          _constdouble:2.0 => double
          TRYCATCHBLOCK L0 L1 L2 org/nlogo/api/AgentException
          TRYCATCHBLOCK L3 L4 L4 java/lang/ClassCastException
          TRYCATCHBLOCK L5 L6 L7 org/nlogo/api/AgentException
         L8
          ACONST_NULL
          ASTORE 2
         L0
          ALOAD 1
          GETFIELD org/nlogo/nvm/Context.agent : Lorg/nlogo/agent/Agent;
          BIPUSH 13
          INVOKEVIRTUAL org/nlogo/agent/Agent.getTurtleVariable (I)Ljava/lang/Object;
          ASTORE 2
         L1
          ALOAD 2
          GOTO L9
         L2
          ASTORE 3
          NEW org/nlogo/nvm/EngineException
          DUP
          ALOAD 1
          ALOAD 0
          ALOAD 3
          INVOKEVIRTUAL org/nlogo/api/AgentException.getMessage ()Ljava/lang/String;
          INVOKESPECIAL org/nlogo/nvm/EngineException.<init> (Lorg/nlogo/nvm/Context;Lorg/nlogo/nvm/Instruction;Ljava/lang/String;)V
          ATHROW
         L9
          ASTORE 2
         L3
          ALOAD 2
          CHECKCAST java/lang/Double
          INVOKEVIRTUAL java/lang/Double.doubleValue ()D
          GOTO L10
         L4
          POP
          NEW org/nlogo/nvm/ArgumentTypeException
          DUP
          ALOAD 1
          ALOAD 0
          BIPUSH 0
          LDC 1
          ALOAD 2
          INVOKESPECIAL org/nlogo/nvm/ArgumentTypeException.<init> (Lorg/nlogo/nvm/Context;Lorg/nlogo/nvm/Instruction;IILjava/lang/Object;)V
          ATHROW
         L10
          LDC 2.0
         L11
          DSTORE 4
          DSTORE 2
          DLOAD 4
          DCONST_0
          DCMPL
          IFNE L12
          NEW org/nlogo/nvm/EngineException
          DUP
          ALOAD 1
          ALOAD 0
          INVOKESTATIC org/nlogo/api/I18N.errorsJ ()Lorg/nlogo/api/I18NJava;
          LDC "org.nlogo.prim.etc.$common.divByZero"
          INVOKEINTERFACE org/nlogo/api/I18NJava.get (Ljava/lang/String;)Ljava/lang/String;
          INVOKESPECIAL org/nlogo/nvm/EngineException.<init> (Lorg/nlogo/nvm/Context;Lorg/nlogo/nvm/Instruction;Ljava/lang/String;)V
          ATHROW
         L12
          DLOAD 2
          DLOAD 4
          DDIV
         L13
          DSTORE 2
          GETSTATIC org/nlogo/api/Approximate$.MODULE$ : Lorg/nlogo/api/Approximate$;
          DLOAD 2
          ICONST_0
          INVOKEVIRTUAL org/nlogo/api/Approximate$.approximate (DI)D
         L14
          DSTORE 2
          NEW java/lang/Double
          DUP
          DLOAD 2
          INVOKESPECIAL java/lang/Double.<init> (D)V
          ASTORE 2
         L5
          ALOAD 1
          GETFIELD org/nlogo/nvm/Context.agent : Lorg/nlogo/agent/Agent;
          BIPUSH 13
          ALOAD 2
          INVOKEVIRTUAL org/nlogo/agent/Agent.setTurtleVariable (ILjava/lang/Object;)V
         L6
          ALOAD 1
          ICONST_2
          PUTFIELD org/nlogo/nvm/Context.ip : I
          GOTO L15
         L7
          ASTORE 3
          NEW org/nlogo/nvm/EngineException
          DUP
          ALOAD 1
          ALOAD 0
          ALOAD 3
          INVOKEVIRTUAL org/nlogo/api/AgentException.getMessage ()Ljava/lang/String;
          INVOKESPECIAL org/nlogo/nvm/EngineException.<init> (Lorg/nlogo/nvm/Context;Lorg/nlogo/nvm/Instruction;Ljava/lang/String;)V
          ATHROW
         L15
          RETURN
[2]_hatch:,+6
      _asm_procedurereproducewolves_constdouble_2 "1" => Double
           L0
            ALOAD 0
            GETFIELD org/nlogo/prim/_asm_procedurereproducewolves_constdouble_2.kept1_value : Ljava/lang/Double;
           L1
            ARETURN
[3]_asm_procedurereproducewolves_right_3 "rt random" double => void
      _randomconst:360 => double
         L0
          ALOAD 1
          GETFIELD org/nlogo/nvm/Context.job : Lorg/nlogo/nvm/Job;
          GETFIELD org/nlogo/nvm/Job.random : Lorg/nlogo/util/MersenneTwisterFast;
          LDC 360
          INVOKEVIRTUAL org/nlogo/util/MersenneTwisterFast.nextLong (J)J
          L2D
         L1
          DSTORE 2
          ALOAD 1
          GETFIELD org/nlogo/nvm/Context.agent : Lorg/nlogo/agent/Agent;
          CHECKCAST org/nlogo/agent/Turtle
          DLOAD 2
          INVOKEVIRTUAL org/nlogo/agent/Turtle.turnRight (D)V
          ALOAD 1
          ICONST_4
          PUTFIELD org/nlogo/nvm/Context.ip : I
         L2
          RETURN
[4]_asm_procedurereproducewolves_fd1_4 "fd" => void
          TRYCATCHBLOCK L0 L1 L1 org/nlogo/api/AgentException
         L0
          ALOAD 1
          GETFIELD org/nlogo/nvm/Context.agent : Lorg/nlogo/agent/Agent;
          CHECKCAST org/nlogo/agent/Turtle
          DCONST_1
          INVOKEVIRTUAL org/nlogo/agent/Turtle.jump (D)V
          GOTO L2
         L1
          ASTORE 2
         L2
          ALOAD 1
          ICONST_5
          PUTFIELD org/nlogo/nvm/Context.ip : I
         L3
          RETURN
[5]_asm_procedurereproducewolves_done_5 "" => void
         L0
          ALOAD 1
          ICONST_1
          PUTFIELD org/nlogo/nvm/Context.finished : Z
         L1
          RETURN
[6]_asm_procedurereproducewolves_return_6 "" => void
         L0
          ALOAD 1
          INVOKEVIRTUAL org/nlogo/nvm/Context.returnFromProcedure ()V
          ALOAD 1
          ICONST_0
          PUTFIELD org/nlogo/nvm/Context.stopping : Z
         L1
          RETURN

procedure CATCH-SHEEP:[]{-T--}:
[0]_asm_procedurecatchsheep_setturtlevariable_0 "set prey one-of sheep-here" Object => void
      _oneof AgentSet => Object
        _breedhere:SHEEP => AgentSet
          TRYCATCHBLOCK L0 L1 L2 org/nlogo/api/AgentException
         L3
          ALOAD 1
          GETFIELD org/nlogo/nvm/Context.agent : Lorg/nlogo/agent/Agent;
          ASTORE 3
          ALOAD 3
          INSTANCEOF org/nlogo/agent/Turtle
          IFEQ L4
          ALOAD 3
          CHECKCAST org/nlogo/agent/Turtle
          INVOKEVIRTUAL org/nlogo/agent/Turtle.getPatchHere ()Lorg/nlogo/agent/Patch;
          GOTO L5
         L4
          ALOAD 3
          INSTANCEOF org/nlogo/agent/Patch
          IFEQ L6
          ALOAD 3
          CHECKCAST org/nlogo/agent/Patch
         L5
          ASTORE 2
          NEW org/nlogo/agent/ArrayAgentSet
          DUP
          GETSTATIC org/nlogo/api/AgentKind$Turtle$.MODULE$ : Lorg/nlogo/api/AgentKind$Turtle$;
          ALOAD 2
          INVOKEVIRTUAL org/nlogo/agent/Patch.turtleCount ()I
          ICONST_0
          ALOAD 0
          GETFIELD org/nlogo/prim/_asm_procedurecatchsheep_setturtlevariable_0.world : Lorg/nlogo/agent/World;
          INVOKESPECIAL org/nlogo/agent/ArrayAgentSet.<init> (Lorg/nlogo/api/AgentKind;IZLorg/nlogo/agent/World;)V
          ASTORE 4
          ALOAD 0
          GETFIELD org/nlogo/prim/_asm_procedurecatchsheep_setturtlevariable_0.world : Lorg/nlogo/agent/World;
          LDC "SHEEP"
          INVOKEVIRTUAL org/nlogo/agent/World.getBreed (Ljava/lang/String;)Lorg/nlogo/agent/AgentSet;
          ASTORE 5
          ALOAD 2
          INVOKEVIRTUAL org/nlogo/agent/Patch.turtlesHere ()Ljava/lang/Iterable;
          INVOKEINTERFACE java/lang/Iterable.iterator ()Ljava/util/Iterator;
          ASTORE 6
         L7
          ALOAD 6
          INVOKEINTERFACE java/util/Iterator.hasNext ()Z
          IFEQ L8
          ALOAD 6
          INVOKEINTERFACE java/util/Iterator.next ()Ljava/lang/Object;
          CHECKCAST org/nlogo/agent/Turtle
          ASTORE 7
          ALOAD 7
          INVOKEVIRTUAL org/nlogo/agent/Turtle.getBreed ()Lorg/nlogo/agent/AgentSet;
          ALOAD 5
          IF_ACMPNE L7
          ALOAD 4
          ALOAD 7
          INVOKEVIRTUAL org/nlogo/agent/ArrayAgentSet.add (Lorg/nlogo/agent/Agent;)V
          GOTO L7
         L8
          ALOAD 4
          GOTO L9
         L6
          NEW scala/MatchError
          DUP
          ALOAD 3
          INVOKESPECIAL scala/MatchError.<init> (Ljava/lang/Object;)V
          ATHROW
         L9
          ASTORE 2
          ALOAD 2
          INVOKEINTERFACE org/nlogo/api/AgentSet.count ()I
          ISTORE 3
          ILOAD 3
          ICONST_0
          IF_ICMPNE L10
          GETSTATIC org/nlogo/api/Nobody$.MODULE$ : Lorg/nlogo/api/Nobody$;
          GOTO L11
         L10
          ALOAD 2
          ILOAD 3
          ALOAD 1
          GETFIELD org/nlogo/nvm/Context.job : Lorg/nlogo/nvm/Job;
          GETFIELD org/nlogo/nvm/Job.random : Lorg/nlogo/util/MersenneTwisterFast;
          ILOAD 3
          INVOKEVIRTUAL org/nlogo/util/MersenneTwisterFast.nextInt (I)I
          INVOKEVIRTUAL org/nlogo/agent/AgentSet.randomOne (II)Lorg/nlogo/agent/Agent;
         L11
          ASTORE 2
         L0
          ALOAD 1
          GETFIELD org/nlogo/nvm/Context.agent : Lorg/nlogo/agent/Agent;
          BIPUSH 14
          ALOAD 2
          INVOKEVIRTUAL org/nlogo/agent/Agent.setTurtleVariable (ILjava/lang/Object;)V
         L1
          ALOAD 1
          ICONST_1
          PUTFIELD org/nlogo/nvm/Context.ip : I
          GOTO L12
         L2
          ASTORE 3
          NEW org/nlogo/nvm/EngineException
          DUP
          ALOAD 1
          ALOAD 0
          ALOAD 3
          INVOKEVIRTUAL org/nlogo/api/AgentException.getMessage ()Ljava/lang/String;
          INVOKESPECIAL org/nlogo/nvm/EngineException.<init> (Lorg/nlogo/nvm/Context;Lorg/nlogo/nvm/Instruction;Ljava/lang/String;)V
          ATHROW
         L12
          RETURN
[1]_asm_procedurecatchsheep_if_1 "if (prey != nobody" boolean => void
      _notequal Object,Object => boolean
        _turtlevariable:PREY => Object
        _nobody => Nobody$
          TRYCATCHBLOCK L0 L1 L2 org/nlogo/api/AgentException
         L3
          ACONST_NULL
          ASTORE 2
         L0
          ALOAD 1
          GETFIELD org/nlogo/nvm/Context.agent : Lorg/nlogo/agent/Agent;
          BIPUSH 14
          INVOKEVIRTUAL org/nlogo/agent/Agent.getTurtleVariable (I)Ljava/lang/Object;
          ASTORE 2
         L1
          ALOAD 2
          GOTO L4
         L2
          ASTORE 3
          NEW org/nlogo/nvm/EngineException
          DUP
          ALOAD 1
          ALOAD 0
          ALOAD 3
          INVOKEVIRTUAL org/nlogo/api/AgentException.getMessage ()Ljava/lang/String;
          INVOKESPECIAL org/nlogo/nvm/EngineException.<init> (Lorg/nlogo/nvm/Context;Lorg/nlogo/nvm/Instruction;Ljava/lang/String;)V
          ATHROW
         L4
          GETSTATIC org/nlogo/api/Nobody$.MODULE$ : Lorg/nlogo/api/Nobody$;
         L5
          ASTORE 3
          ASTORE 2
          GETSTATIC org/nlogo/api/Equality$.MODULE$ : Lorg/nlogo/api/Equality$;
          ALOAD 2
          ALOAD 3
          INVOKEVIRTUAL org/nlogo/api/Equality$.equals (Ljava/lang/Object;Ljava/lang/Object;)Z
          IFEQ L6
          ICONST_0
          GOTO L7
         L6
          ICONST_1
         L7
          ISTORE 2
          ALOAD 1
          ILOAD 2
          IFEQ L8
          ICONST_2
          GOTO L9
         L8
          BIPUSH 6
         L9
          PUTFIELD org/nlogo/nvm/Context.ip : I
         L10
          RETURN
[2]_asm_procedurecatchsheep_ask_2 "ask prey" Object => void
      _turtlevariable:PREY => Object
          TRYCATCHBLOCK L0 L1 L2 org/nlogo/api/AgentException
         L3
          ACONST_NULL
          ASTORE 2
         L0
          ALOAD 1
          GETFIELD org/nlogo/nvm/Context.agent : Lorg/nlogo/agent/Agent;
          BIPUSH 14
          INVOKEVIRTUAL org/nlogo/agent/Agent.getTurtleVariable (I)Ljava/lang/Object;
          ASTORE 2
         L1
          ALOAD 2
          GOTO L4
         L2
          ASTORE 3
          NEW org/nlogo/nvm/EngineException
          DUP
          ALOAD 1
          ALOAD 0
          ALOAD 3
          INVOKEVIRTUAL org/nlogo/api/AgentException.getMessage ()Ljava/lang/String;
          INVOKESPECIAL org/nlogo/nvm/EngineException.<init> (Lorg/nlogo/nvm/Context;Lorg/nlogo/nvm/Instruction;Ljava/lang/String;)V
          ATHROW
         L4
          ASTORE 2
          ALOAD 2
          ASTORE 4
          ALOAD 4
          INSTANCEOF org/nlogo/agent/AgentSet
          IFEQ L5
          ALOAD 4
          CHECKCAST org/nlogo/agent/AgentSet
          ASTORE 5
          ALOAD 5
          ASTORE 6
          ALOAD 1
          GETFIELD org/nlogo/nvm/Context.agent : Lorg/nlogo/agent/Agent;
          INSTANCEOF org/nlogo/agent/Observer
          IFNE L6
          ALOAD 6
          ALOAD 0
          GETFIELD org/nlogo/prim/_asm_procedurecatchsheep_ask_2.world : Lorg/nlogo/agent/World;
          INVOKEVIRTUAL org/nlogo/agent/World.turtles ()Lorg/nlogo/agent/AgentSet;
          IF_ACMPNE L7
          NEW org/nlogo/nvm/EngineException
          DUP
          ALOAD 1
          ALOAD 0
          GETSTATIC org/nlogo/api/I18N$.MODULE$ : Lorg/nlogo/api/I18N$;
          INVOKEVIRTUAL org/nlogo/api/I18N$.errors ()Lorg/nlogo/api/I18N$BundleKind;
          LDC "org.nlogo.prim.$common.onlyObserverCanAskAllTurtles"
          INVOKEVIRTUAL org/nlogo/api/I18N$BundleKind.get (Ljava/lang/String;)Ljava/lang/String;
          INVOKESPECIAL org/nlogo/nvm/EngineException.<init> (Lorg/nlogo/nvm/Context;Lorg/nlogo/nvm/Instruction;Ljava/lang/String;)V
          ATHROW
         L7
          ALOAD 6
          ALOAD 0
          GETFIELD org/nlogo/prim/_asm_procedurecatchsheep_ask_2.world : Lorg/nlogo/agent/World;
          INVOKEVIRTUAL org/nlogo/agent/World.patches ()Lorg/nlogo/agent/AgentSet;
          IF_ACMPNE L6
          NEW org/nlogo/nvm/EngineException
          DUP
          ALOAD 1
          ALOAD 0
          GETSTATIC org/nlogo/api/I18N$.MODULE$ : Lorg/nlogo/api/I18N$;
          INVOKEVIRTUAL org/nlogo/api/I18N$.errors ()Lorg/nlogo/api/I18N$BundleKind;
          LDC "org.nlogo.prim.$common.onlyObserverCanAskAllPatches"
          INVOKEVIRTUAL org/nlogo/api/I18N$BundleKind.get (Ljava/lang/String;)Ljava/lang/String;
          INVOKESPECIAL org/nlogo/nvm/EngineException.<init> (Lorg/nlogo/nvm/Context;Lorg/nlogo/nvm/Instruction;Ljava/lang/String;)V
          ATHROW
         L6
          ALOAD 6
          GOTO L8
         L5
          ALOAD 4
          INSTANCEOF org/nlogo/agent/Agent
          IFEQ L9
          ALOAD 4
          CHECKCAST org/nlogo/agent/Agent
          ASTORE 7
          ALOAD 7
          ASTORE 8
          ALOAD 8
          GETFIELD org/nlogo/agent/Agent.id : J
          LDC -1
          LCMP
          IFNE L10
          NEW org/nlogo/nvm/EngineException
          DUP
          ALOAD 1
          ALOAD 0
          GETSTATIC org/nlogo/api/I18N$.MODULE$ : Lorg/nlogo/api/I18N$;
          INVOKEVIRTUAL org/nlogo/api/I18N$.errors ()Lorg/nlogo/api/I18N$BundleKind;
          LDC "org.nlogo.$common.thatAgentIsDead"
          GETSTATIC scala/Predef$.MODULE$ : Lscala/Predef$;
          ICONST_1
          ANEWARRAY java/lang/Object
          DUP
          ICONST_0
          ALOAD 8
          INVOKEVIRTUAL org/nlogo/agent/Agent.classDisplayName ()Ljava/lang/String;
          AASTORE
          INVOKEVIRTUAL scala/Predef$.wrapRefArray ([Ljava/lang/Object;)Lscala/collection/mutable/WrappedArray;
          INVOKEVIRTUAL org/nlogo/api/I18N$BundleKind.getN (Ljava/lang/String;Lscala/collection/Seq;)Ljava/lang/String;
          INVOKESPECIAL org/nlogo/nvm/EngineException.<init> (Lorg/nlogo/nvm/Context;Lorg/nlogo/nvm/Instruction;Ljava/lang/String;)V
          ATHROW
         L10
          NEW org/nlogo/agent/ArrayAgentSet
          DUP
          ALOAD 8
          INVOKEINTERFACE org/nlogo/api/Agent.kind ()Lorg/nlogo/api/AgentKind;
          ICONST_1
          ICONST_0
          ALOAD 0
          GETFIELD org/nlogo/prim/_asm_procedurecatchsheep_ask_2.world : Lorg/nlogo/agent/World;
          INVOKESPECIAL org/nlogo/agent/ArrayAgentSet.<init> (Lorg/nlogo/api/AgentKind;IZLorg/nlogo/agent/World;)V
          ASTORE 9
          ALOAD 9
          ALOAD 8
          INVOKEVIRTUAL org/nlogo/agent/ArrayAgentSet.add (Lorg/nlogo/agent/Agent;)V
          ALOAD 9
         L8
          ASTORE 3
          ALOAD 1
          ALOAD 3
          ICONST_3
          INVOKEVIRTUAL org/nlogo/nvm/Context.runExclusiveJob (Lorg/nlogo/agent/AgentSet;I)V
          ALOAD 1
          ICONST_5
          PUTFIELD org/nlogo/nvm/Context.ip : I
          GOTO L11
         L9
          NEW org/nlogo/nvm/ArgumentTypeException
          DUP
          ALOAD 1
          ALOAD 0
          ICONST_0
          GETSTATIC org/nlogo/api/Syntax$.MODULE$ : Lorg/nlogo/api/Syntax$;
          INVOKEVIRTUAL org/nlogo/api/Syntax$.AgentsetType ()I
          GETSTATIC org/nlogo/api/Syntax$.MODULE$ : Lorg/nlogo/api/Syntax$;
          INVOKEVIRTUAL org/nlogo/api/Syntax$.AgentType ()I
          IOR
          ALOAD 2
          INVOKESPECIAL org/nlogo/nvm/ArgumentTypeException.<init> (Lorg/nlogo/nvm/Context;Lorg/nlogo/nvm/Instruction;IILjava/lang/Object;)V
          ATHROW
         L11
          RETURN
[3]_asm_procedurecatchsheep_setturtlevariable_3 "set energy -1" Object => void
      _constdouble:-1.0 => Double
          TRYCATCHBLOCK L0 L1 L2 org/nlogo/api/AgentException
         L3
          ALOAD 0
          GETFIELD org/nlogo/prim/_asm_procedurecatchsheep_setturtlevariable_3.kept2_value : Ljava/lang/Double;
         L4
          ASTORE 2
         L0
          ALOAD 1
          GETFIELD org/nlogo/nvm/Context.agent : Lorg/nlogo/agent/Agent;
          BIPUSH 13
          ALOAD 2
          INVOKEVIRTUAL org/nlogo/agent/Agent.setTurtleVariable (ILjava/lang/Object;)V
         L1
          ALOAD 1
          ICONST_4
          PUTFIELD org/nlogo/nvm/Context.ip : I
          GOTO L5
         L2
          ASTORE 3
          NEW org/nlogo/nvm/EngineException
          DUP
          ALOAD 1
          ALOAD 0
          ALOAD 3
          INVOKEVIRTUAL org/nlogo/api/AgentException.getMessage ()Ljava/lang/String;
          INVOKESPECIAL org/nlogo/nvm/EngineException.<init> (Lorg/nlogo/nvm/Context;Lorg/nlogo/nvm/Instruction;Ljava/lang/String;)V
          ATHROW
         L5
          RETURN
[4]_asm_procedurecatchsheep_done_4 "" => void
         L0
          ALOAD 1
          ICONST_1
          PUTFIELD org/nlogo/nvm/Context.finished : Z
         L1
          RETURN
[5]_asm_procedurecatchsheep_setturtlevariable_5 "set energy energy + wolf-metabolism" Object => void
      _plus double,double => double
        _turtlevariable:ENERGY => Object
        _observervariable:WOLF-METABOLISM => Object
          TRYCATCHBLOCK L0 L1 L2 org/nlogo/api/AgentException
          TRYCATCHBLOCK L3 L4 L4 java/lang/ClassCastException
          TRYCATCHBLOCK L5 L6 L6 java/lang/ClassCastException
          TRYCATCHBLOCK L7 L8 L9 org/nlogo/api/AgentException
         L10
          ACONST_NULL
          ASTORE 2
         L0
          ALOAD 1
          GETFIELD org/nlogo/nvm/Context.agent : Lorg/nlogo/agent/Agent;
          BIPUSH 13
          INVOKEVIRTUAL org/nlogo/agent/Agent.getTurtleVariable (I)Ljava/lang/Object;
          ASTORE 2
         L1
          ALOAD 2
          GOTO L11
         L2
          ASTORE 3
          NEW org/nlogo/nvm/EngineException
          DUP
          ALOAD 1
          ALOAD 0
          ALOAD 3
          INVOKEVIRTUAL org/nlogo/api/AgentException.getMessage ()Ljava/lang/String;
          INVOKESPECIAL org/nlogo/nvm/EngineException.<init> (Lorg/nlogo/nvm/Context;Lorg/nlogo/nvm/Instruction;Ljava/lang/String;)V
          ATHROW
         L11
          ASTORE 2
         L3
          ALOAD 2
          CHECKCAST java/lang/Double
          INVOKEVIRTUAL java/lang/Double.doubleValue ()D
          GOTO L12
         L4
          POP
          NEW org/nlogo/nvm/ArgumentTypeException
          DUP
          ALOAD 1
          ALOAD 0
          BIPUSH 0
          LDC 1
          ALOAD 2
          INVOKESPECIAL org/nlogo/nvm/ArgumentTypeException.<init> (Lorg/nlogo/nvm/Context;Lorg/nlogo/nvm/Instruction;IILjava/lang/Object;)V
          ATHROW
         L12
          ALOAD 1
          GETFIELD org/nlogo/nvm/Context.agent : Lorg/nlogo/agent/Agent;
          ICONST_4
          INVOKEVIRTUAL org/nlogo/agent/Agent.getObserverVariable (I)Ljava/lang/Object;
         L13
          ASTORE 2
         L5
          ALOAD 2
          CHECKCAST java/lang/Double
          INVOKEVIRTUAL java/lang/Double.doubleValue ()D
          GOTO L14
         L6
          POP
          NEW org/nlogo/nvm/ArgumentTypeException
          DUP
          ALOAD 1
          ALOAD 0
          BIPUSH 1
          LDC 1
          ALOAD 2
          INVOKESPECIAL org/nlogo/nvm/ArgumentTypeException.<init> (Lorg/nlogo/nvm/Context;Lorg/nlogo/nvm/Instruction;IILjava/lang/Object;)V
          ATHROW
         L14
          DSTORE 4
          DSTORE 2
          DLOAD 2
          DLOAD 4
          DADD
         L15
          DSTORE 2
          NEW java/lang/Double
          DUP
          DLOAD 2
          INVOKESPECIAL java/lang/Double.<init> (D)V
          ASTORE 2
         L7
          ALOAD 1
          GETFIELD org/nlogo/nvm/Context.agent : Lorg/nlogo/agent/Agent;
          BIPUSH 13
          ALOAD 2
          INVOKEVIRTUAL org/nlogo/agent/Agent.setTurtleVariable (ILjava/lang/Object;)V
         L8
          ALOAD 1
          BIPUSH 6
          PUTFIELD org/nlogo/nvm/Context.ip : I
          GOTO L16
         L9
          ASTORE 3
          NEW org/nlogo/nvm/EngineException
          DUP
          ALOAD 1
          ALOAD 0
          ALOAD 3
          INVOKEVIRTUAL org/nlogo/api/AgentException.getMessage ()Ljava/lang/String;
          INVOKESPECIAL org/nlogo/nvm/EngineException.<init> (Lorg/nlogo/nvm/Context;Lorg/nlogo/nvm/Instruction;Ljava/lang/String;)V
          ATHROW
         L16
          RETURN
[6]_asm_procedurecatchsheep_return_6 "" => void
         L0
          ALOAD 1
          INVOKEVIRTUAL org/nlogo/nvm/Context.returnFromProcedure ()V
          ALOAD 1
          ICONST_0
          PUTFIELD org/nlogo/nvm/Context.stopping : Z
         L1
          RETURN

procedure DEATH:[]{-T--}:
[0]_asm_proceduredeath_if_0 "if energy < 0" boolean => void
      _lessthan Object,double => boolean
        _turtlevariable:ENERGY => Object
        _constdouble:0.0 => double
          TRYCATCHBLOCK L0 L1 L2 org/nlogo/api/AgentException
         L3
          ACONST_NULL
          ASTORE 2
         L0
          ALOAD 1
          GETFIELD org/nlogo/nvm/Context.agent : Lorg/nlogo/agent/Agent;
          BIPUSH 13
          INVOKEVIRTUAL org/nlogo/agent/Agent.getTurtleVariable (I)Ljava/lang/Object;
          ASTORE 2
         L1
          ALOAD 2
          GOTO L4
         L2
          ASTORE 3
          NEW org/nlogo/nvm/EngineException
          DUP
          ALOAD 1
          ALOAD 0
          ALOAD 3
          INVOKEVIRTUAL org/nlogo/api/AgentException.getMessage ()Ljava/lang/String;
          INVOKESPECIAL org/nlogo/nvm/EngineException.<init> (Lorg/nlogo/nvm/Context;Lorg/nlogo/nvm/Instruction;Ljava/lang/String;)V
          ATHROW
         L4
          DCONST_0
         L5
          DSTORE 3
          ASTORE 2
          ALOAD 2
          ASTORE 5
          ALOAD 5
          INSTANCEOF java/lang/Double
          IFEQ L6
          ALOAD 5
          CHECKCAST java/lang/Double
          INVOKEVIRTUAL java/lang/Double.doubleValue ()D
          DLOAD 3
          DCMPG
          IFGE L7
          ICONST_1
          GOTO L8
         L7
          ICONST_0
         L8
          GOTO L9
         L6
          NEW org/nlogo/nvm/EngineException
          DUP
          ALOAD 1
          ALOAD 0
          GETSTATIC org/nlogo/api/I18N$.MODULE$ : Lorg/nlogo/api/I18N$;
          INVOKEVIRTUAL org/nlogo/api/I18N$.errors ()Lorg/nlogo/api/I18N$BundleKind;
          LDC "org.nlogo.prim._lessthan.cantUseLessthanOnDifferentArgs"
          GETSTATIC scala/Predef$.MODULE$ : Lscala/Predef$;
          ICONST_2
          ANEWARRAY java/lang/Object
          DUP
          ICONST_0
          GETSTATIC org/nlogo/api/TypeNames$.MODULE$ : Lorg/nlogo/api/TypeNames$;
          ALOAD 2
          INVOKEVIRTUAL org/nlogo/api/TypeNames$.aName (Ljava/lang/Object;)Ljava/lang/String;
          AASTORE
          DUP
          ICONST_1
          GETSTATIC org/nlogo/api/TypeNames$.MODULE$ : Lorg/nlogo/api/TypeNames$;
          DLOAD 3
          INVOKESTATIC scala/runtime/BoxesRunTime.boxToDouble (D)Ljava/lang/Double;
          INVOKEVIRTUAL org/nlogo/api/TypeNames$.aName (Ljava/lang/Object;)Ljava/lang/String;
          AASTORE
          INVOKEVIRTUAL scala/Predef$.wrapRefArray ([Ljava/lang/Object;)Lscala/collection/mutable/WrappedArray;
          INVOKEVIRTUAL org/nlogo/api/I18N$BundleKind.getN (Ljava/lang/String;Lscala/collection/Seq;)Ljava/lang/String;
          INVOKESPECIAL org/nlogo/nvm/EngineException.<init> (Lorg/nlogo/nvm/Context;Lorg/nlogo/nvm/Instruction;Ljava/lang/String;)V
          ATHROW
         L9
          ISTORE 2
          ALOAD 1
          ILOAD 2
          IFEQ L10
          ICONST_1
          GOTO L11
         L10
          ICONST_2
         L11
          PUTFIELD org/nlogo/nvm/Context.ip : I
         L12
          RETURN
[1]_asm_proceduredeath_die_1 "die" => void
         L0
          ALOAD 1
          GETFIELD org/nlogo/nvm/Context.agent : Lorg/nlogo/agent/Agent;
          INSTANCEOF org/nlogo/agent/Turtle
          IFEQ L1
          ALOAD 1
          GETFIELD org/nlogo/nvm/Context.agent : Lorg/nlogo/agent/Agent;
          CHECKCAST org/nlogo/agent/Turtle
          INVOKEVIRTUAL org/nlogo/agent/Turtle.die ()V
          GOTO L2
         L1
          ALOAD 1
          GETFIELD org/nlogo/nvm/Context.agent : Lorg/nlogo/agent/Agent;
          CHECKCAST org/nlogo/agent/Link
          INVOKEVIRTUAL org/nlogo/agent/Link.die ()V
         L2
          ALOAD 1
          ICONST_1
          PUTFIELD org/nlogo/nvm/Context.finished : Z
         L3
          RETURN
[2]_asm_proceduredeath_return_2 "" => void
         L0
          ALOAD 1
          INVOKEVIRTUAL org/nlogo/nvm/Context.returnFromProcedure ()V
          ALOAD 1
          ICONST_0
          PUTFIELD org/nlogo/nvm/Context.stopping : Z
         L1
          RETURN

procedure GROW-GRASS:[]{-TP-}:
[0]_asm_proceduregrowgrass_if_0 "if pcolor = brown" boolean => void
      _equal Object,double => boolean
        _patchvariable:PCOLOR => Object
        _constdouble:35.0 => double
          TRYCATCHBLOCK L0 L1 L2 org/nlogo/api/AgentException
         L3
          ACONST_NULL
          ASTORE 2
         L0
          ALOAD 1
          GETFIELD org/nlogo/nvm/Context.agent : Lorg/nlogo/agent/Agent;
          ICONST_2
          INVOKEVIRTUAL org/nlogo/agent/Agent.getPatchVariable (I)Ljava/lang/Object;
          ASTORE 2
         L1
          ALOAD 2
          GOTO L4
         L2
          ASTORE 3
          NEW org/nlogo/nvm/EngineException
          DUP
          ALOAD 1
          ALOAD 0
          ALOAD 3
          INVOKEVIRTUAL org/nlogo/api/AgentException.getMessage ()Ljava/lang/String;
          INVOKESPECIAL org/nlogo/nvm/EngineException.<init> (Lorg/nlogo/nvm/Context;Lorg/nlogo/nvm/Instruction;Ljava/lang/String;)V
          ATHROW
         L4
          LDC 35.0
         L5
          DSTORE 3
          ASTORE 2
          ALOAD 2
          ASTORE 5
          ALOAD 5
          INSTANCEOF java/lang/Double
          IFEQ L6
          DLOAD 3
          ALOAD 5
          CHECKCAST java/lang/Double
          INVOKEVIRTUAL java/lang/Double.doubleValue ()D
          DCMPL
          IFNE L7
          ICONST_1
          GOTO L8
         L7
          ICONST_0
          GOTO L8
         L6
          ICONST_0
         L8
          ISTORE 2
          ALOAD 1
          ILOAD 2
          IFEQ L9
          ICONST_1
          GOTO L10
         L9
          BIPUSH 6
         L10
          PUTFIELD org/nlogo/nvm/Context.ip : I
         L11
          RETURN
[1]_asm_proceduregrowgrass_ifelse_1 "ifelse countdown <= 0" boolean => void
      _lessorequal Object,double => boolean
        _patchvariable:COUNTDOWN => Object
        _constdouble:0.0 => double
          TRYCATCHBLOCK L0 L1 L2 org/nlogo/api/AgentException
         L3
          ACONST_NULL
          ASTORE 2
         L0
          ALOAD 1
          GETFIELD org/nlogo/nvm/Context.agent : Lorg/nlogo/agent/Agent;
          ICONST_5
          INVOKEVIRTUAL org/nlogo/agent/Agent.getPatchVariable (I)Ljava/lang/Object;
          ASTORE 2
         L1
          ALOAD 2
          GOTO L4
         L2
          ASTORE 3
          NEW org/nlogo/nvm/EngineException
          DUP
          ALOAD 1
          ALOAD 0
          ALOAD 3
          INVOKEVIRTUAL org/nlogo/api/AgentException.getMessage ()Ljava/lang/String;
          INVOKESPECIAL org/nlogo/nvm/EngineException.<init> (Lorg/nlogo/nvm/Context;Lorg/nlogo/nvm/Instruction;Ljava/lang/String;)V
          ATHROW
         L4
          DCONST_0
         L5
          DSTORE 3
          ASTORE 2
          ALOAD 2
          INSTANCEOF java/lang/Double
          IFEQ L6
          ALOAD 2
          CHECKCAST java/lang/Double
          INVOKEVIRTUAL java/lang/Double.doubleValue ()D
          DLOAD 3
          DCMPG
          IFGT L7
          ICONST_1
          GOTO L8
         L7
          ICONST_0
         L8
          GOTO L9
         L6
          NEW org/nlogo/nvm/EngineException
          DUP
          ALOAD 1
          ALOAD 0
          INVOKESTATIC org/nlogo/api/I18N.errorsJ ()Lorg/nlogo/api/I18NJava;
          LDC "org.nlogo.prim._lessorequal.cannotCompareParameters"
          ICONST_2
          ANEWARRAY java/lang/Object
          DUP
          ICONST_0
          ALOAD 2
          INVOKESTATIC org/nlogo/api/TypeNames.aName (Ljava/lang/Object;)Ljava/lang/String;
          AASTORE
          DUP
          ICONST_1
          DLOAD 3
          INVOKESTATIC java/lang/Double.valueOf (D)Ljava/lang/Double;
          INVOKESTATIC org/nlogo/api/TypeNames.aName (Ljava/lang/Object;)Ljava/lang/String;
          AASTORE
          INVOKEINTERFACE org/nlogo/api/I18NJava.getN (Ljava/lang/String;[Ljava/lang/Object;)Ljava/lang/String;
          INVOKESPECIAL org/nlogo/nvm/EngineException.<init> (Lorg/nlogo/nvm/Context;Lorg/nlogo/nvm/Instruction;Ljava/lang/String;)V
          ATHROW
         L9
          ISTORE 2
          ALOAD 1
          ILOAD 2
          IFEQ L10
          ICONST_2
          GOTO L11
         L10
          ICONST_5
         L11
          PUTFIELD org/nlogo/nvm/Context.ip : I
         L12
          RETURN
[2]_asm_proceduregrowgrass_setpatchvariable_2 "set pcolor green" Object => void
      _constdouble:55.0 => Double
          TRYCATCHBLOCK L0 L1 L2 org/nlogo/api/AgentException
         L3
          ALOAD 0
          GETFIELD org/nlogo/prim/_asm_proceduregrowgrass_setpatchvariable_2.kept2_value : Ljava/lang/Double;
         L4
          ASTORE 2
         L0
          ALOAD 1
          GETFIELD org/nlogo/nvm/Context.agent : Lorg/nlogo/agent/Agent;
          ICONST_2
          ALOAD 2
          INVOKEVIRTUAL org/nlogo/agent/Agent.setPatchVariable (ILjava/lang/Object;)V
         L1
          ALOAD 1
          ICONST_3
          PUTFIELD org/nlogo/nvm/Context.ip : I
          GOTO L5
         L2
          ASTORE 3
          NEW org/nlogo/nvm/EngineException
          DUP
          ALOAD 1
          ALOAD 0
          ALOAD 3
          INVOKEVIRTUAL org/nlogo/api/AgentException.getMessage ()Ljava/lang/String;
          INVOKESPECIAL org/nlogo/nvm/EngineException.<init> (Lorg/nlogo/nvm/Context;Lorg/nlogo/nvm/Instruction;Ljava/lang/String;)V
          ATHROW
         L5
          RETURN
[3]_asm_proceduregrowgrass_setpatchvariable_3 "set countdown grass-delay" Object => void
      _observervariable:GRASS-DELAY => Object
          TRYCATCHBLOCK L0 L1 L2 org/nlogo/api/AgentException
         L3
          ALOAD 1
          GETFIELD org/nlogo/nvm/Context.agent : Lorg/nlogo/agent/Agent;
          BIPUSH 7
          INVOKEVIRTUAL org/nlogo/agent/Agent.getObserverVariable (I)Ljava/lang/Object;
         L4
          ASTORE 2
         L0
          ALOAD 1
          GETFIELD org/nlogo/nvm/Context.agent : Lorg/nlogo/agent/Agent;
          ICONST_5
          ALOAD 2
          INVOKEVIRTUAL org/nlogo/agent/Agent.setPatchVariable (ILjava/lang/Object;)V
         L1
          ALOAD 1
          ICONST_4
          PUTFIELD org/nlogo/nvm/Context.ip : I
          GOTO L5
         L2
          ASTORE 3
          NEW org/nlogo/nvm/EngineException
          DUP
          ALOAD 1
          ALOAD 0
          ALOAD 3
          INVOKEVIRTUAL org/nlogo/api/AgentException.getMessage ()Ljava/lang/String;
          INVOKESPECIAL org/nlogo/nvm/EngineException.<init> (Lorg/nlogo/nvm/Context;Lorg/nlogo/nvm/Instruction;Ljava/lang/String;)V
          ATHROW
         L5
          RETURN
[4]_asm_proceduregrowgrass_goto_4 "" => void
         L0
          ALOAD 1
          BIPUSH 6
          PUTFIELD org/nlogo/nvm/Context.ip : I
         L1
          RETURN
[5]_asm_proceduregrowgrass_setpatchvariable_5 "set countdown (countdown - 1" Object => void
      _minus double,double => double
        _patchvariable:COUNTDOWN => Object
        _constdouble:1.0 => double
          TRYCATCHBLOCK L0 L1 L2 org/nlogo/api/AgentException
          TRYCATCHBLOCK L3 L4 L4 java/lang/ClassCastException
          TRYCATCHBLOCK L5 L6 L7 org/nlogo/api/AgentException
         L8
          ACONST_NULL
          ASTORE 2
         L0
          ALOAD 1
          GETFIELD org/nlogo/nvm/Context.agent : Lorg/nlogo/agent/Agent;
          ICONST_5
          INVOKEVIRTUAL org/nlogo/agent/Agent.getPatchVariable (I)Ljava/lang/Object;
          ASTORE 2
         L1
          ALOAD 2
          GOTO L9
         L2
          ASTORE 3
          NEW org/nlogo/nvm/EngineException
          DUP
          ALOAD 1
          ALOAD 0
          ALOAD 3
          INVOKEVIRTUAL org/nlogo/api/AgentException.getMessage ()Ljava/lang/String;
          INVOKESPECIAL org/nlogo/nvm/EngineException.<init> (Lorg/nlogo/nvm/Context;Lorg/nlogo/nvm/Instruction;Ljava/lang/String;)V
          ATHROW
         L9
          ASTORE 2
         L3
          ALOAD 2
          CHECKCAST java/lang/Double
          INVOKEVIRTUAL java/lang/Double.doubleValue ()D
          GOTO L10
         L4
          POP
          NEW org/nlogo/nvm/ArgumentTypeException
          DUP
          ALOAD 1
          ALOAD 0
          BIPUSH 0
          LDC 1
          ALOAD 2
          INVOKESPECIAL org/nlogo/nvm/ArgumentTypeException.<init> (Lorg/nlogo/nvm/Context;Lorg/nlogo/nvm/Instruction;IILjava/lang/Object;)V
          ATHROW
         L10
          DCONST_1
         L11
          DSTORE 4
          DSTORE 2
          DLOAD 2
          DLOAD 4
          DSUB
         L12
          DSTORE 2
          NEW java/lang/Double
          DUP
          DLOAD 2
          INVOKESPECIAL java/lang/Double.<init> (D)V
          ASTORE 2
         L5
          ALOAD 1
          GETFIELD org/nlogo/nvm/Context.agent : Lorg/nlogo/agent/Agent;
          ICONST_5
          ALOAD 2
          INVOKEVIRTUAL org/nlogo/agent/Agent.setPatchVariable (ILjava/lang/Object;)V
         L6
          ALOAD 1
          BIPUSH 6
          PUTFIELD org/nlogo/nvm/Context.ip : I
          GOTO L13
         L7
          ASTORE 3
          NEW org/nlogo/nvm/EngineException
          DUP
          ALOAD 1
          ALOAD 0
          ALOAD 3
          INVOKEVIRTUAL org/nlogo/api/AgentException.getMessage ()Ljava/lang/String;
          INVOKESPECIAL org/nlogo/nvm/EngineException.<init> (Lorg/nlogo/nvm/Context;Lorg/nlogo/nvm/Instruction;Ljava/lang/String;)V
          ATHROW
         L13
          RETURN
[6]_asm_proceduregrowgrass_return_6 "" => void
         L0
          ALOAD 1
          INVOKEVIRTUAL org/nlogo/nvm/Context.returnFromProcedure ()V
          ALOAD 1
          ICONST_0
          PUTFIELD org/nlogo/nvm/Context.stopping : Z
         L1
          RETURN

procedure GRAPH:[]{OTPL}:
[0]_setcurrentplotpen
      _asm_proceduregraph_conststring_0 ""sheep"" => String
           L0
            LDC "sheep"
           L1
            ARETURN
[1]_plot
      _asm_proceduregraph_count_1 "count sheep" AgentSet => double
        _breed:SHEEP => AgentSet
           L0
            ALOAD 0
            GETFIELD org/nlogo/prim/_asm_proceduregraph_count_1.world : Lorg/nlogo/agent/World;
            LDC "SHEEP"
            INVOKEVIRTUAL org/nlogo/agent/World.getBreed (Ljava/lang/String;)Lorg/nlogo/agent/AgentSet;
           L1
            ASTORE 2
            ALOAD 2
            INVOKEINTERFACE org/nlogo/api/AgentSet.count ()I
            I2D
           L2
            DSTORE 2
            NEW java/lang/Double
            DUP
            DLOAD 2
            INVOKESPECIAL java/lang/Double.<init> (D)V
            ARETURN
[2]_setcurrentplotpen
      _asm_proceduregraph_conststring_2 ""wolves"" => String
           L0
            LDC "wolves"
           L1
            ARETURN
[3]_plot
      _asm_proceduregraph_count_3 "count wolves" AgentSet => double
        _breed:WOLVES => AgentSet
           L0
            ALOAD 0
            GETFIELD org/nlogo/prim/_asm_proceduregraph_count_3.world : Lorg/nlogo/agent/World;
            LDC "WOLVES"
            INVOKEVIRTUAL org/nlogo/agent/World.getBreed (Ljava/lang/String;)Lorg/nlogo/agent/AgentSet;
           L1
            ASTORE 2
            ALOAD 2
            INVOKEINTERFACE org/nlogo/api/AgentSet.count ()I
            I2D
           L2
            DSTORE 2
            NEW java/lang/Double
            DUP
            DLOAD 2
            INVOKESPECIAL java/lang/Double.<init> (D)V
            ARETURN
[4]_asm_proceduregraph_if_4 "if grass?" boolean => void
      _observervariable:GRASS? => Object
          TRYCATCHBLOCK L0 L1 L1 java/lang/ClassCastException
         L2
          ALOAD 1
          GETFIELD org/nlogo/nvm/Context.agent : Lorg/nlogo/agent/Agent;
          BIPUSH 6
          INVOKEVIRTUAL org/nlogo/agent/Agent.getObserverVariable (I)Ljava/lang/Object;
         L3
          ASTORE 2
         L0
          ALOAD 2
          CHECKCAST java/lang/Boolean
          INVOKEVIRTUAL java/lang/Boolean.booleanValue ()Z
          GOTO L4
         L1
          POP
          NEW org/nlogo/nvm/ArgumentTypeException
          DUP
          ALOAD 1
          ALOAD 0
          BIPUSH 0
          LDC 2
          ALOAD 2
          INVOKESPECIAL org/nlogo/nvm/ArgumentTypeException.<init> (Lorg/nlogo/nvm/Context;Lorg/nlogo/nvm/Instruction;IILjava/lang/Object;)V
          ATHROW
         L4
          ISTORE 2
          ALOAD 1
          ILOAD 2
          IFEQ L5
          ICONST_5
          GOTO L6
         L5
          BIPUSH 7
         L6
          PUTFIELD org/nlogo/nvm/Context.ip : I
         L7
          RETURN
[5]_setcurrentplotpen
      _asm_proceduregraph_conststring_5 ""grass / 4"" => String
           L0
            LDC "grass / 4"
           L1
            ARETURN
[6]_plot
      _asm_proceduregraph_div_6 "count patches with [ pcolor = green ] / 4" double,double => double
        _countwith AgentSet,Reporter => double
          _patches => AgentSet
          _asm_proceduregraph_equal_7 "pcolor = green" Object,double => boolean
            _patchvariable:PCOLOR => Object
            _constdouble:55.0 => double
                TRYCATCHBLOCK L0 L1 L2 org/nlogo/api/AgentException
               L3
                ACONST_NULL
                ASTORE 2
               L0
                ALOAD 1
                GETFIELD org/nlogo/nvm/Context.agent : Lorg/nlogo/agent/Agent;
                ICONST_2
                INVOKEVIRTUAL org/nlogo/agent/Agent.getPatchVariable (I)Ljava/lang/Object;
                ASTORE 2
               L1
                ALOAD 2
                GOTO L4
               L2
                ASTORE 3
                NEW org/nlogo/nvm/EngineException
                DUP
                ALOAD 1
                ALOAD 0
                ALOAD 3
                INVOKEVIRTUAL org/nlogo/api/AgentException.getMessage ()Ljava/lang/String;
                INVOKESPECIAL org/nlogo/nvm/EngineException.<init> (Lorg/nlogo/nvm/Context;Lorg/nlogo/nvm/Instruction;Ljava/lang/String;)V
                ATHROW
               L4
                LDC 55.0
               L5
                DSTORE 3
                ASTORE 2
                ALOAD 2
                ASTORE 5
                ALOAD 5
                INSTANCEOF java/lang/Double
                IFEQ L6
                DLOAD 3
                ALOAD 5
                CHECKCAST java/lang/Double
                INVOKEVIRTUAL java/lang/Double.doubleValue ()D
                DCMPL
                IFNE L7
                ICONST_1
                GOTO L8
               L7
                ICONST_0
                GOTO L8
               L6
                ICONST_0
               L8
                IFEQ L9
                GETSTATIC java/lang/Boolean.TRUE : Ljava/lang/Boolean;
                GOTO L10
               L9
                GETSTATIC java/lang/Boolean.FALSE : Ljava/lang/Boolean;
               L10
                ARETURN
        _constdouble:4.0 => double
           L0
            ALOAD 0
            GETFIELD org/nlogo/prim/_asm_proceduregraph_div_6.world : Lorg/nlogo/agent/World;
            INVOKEVIRTUAL org/nlogo/agent/World.patches ()Lorg/nlogo/agent/AgentSet;
           L1
            ALOAD 0
            GETFIELD org/nlogo/prim/_asm_proceduregraph_div_6.keptinstr4 : Lorg/nlogo/prim/_asm_proceduregraph_equal_7;
            ASTORE 3
            ASTORE 2
            ALOAD 3
            ALOAD 2
            ALOAD 1
            INVOKEVIRTUAL org/nlogo/nvm/Reporter.checkAgentSetClass (Lorg/nlogo/agent/AgentSet;Lorg/nlogo/nvm/Context;)V
            NEW org/nlogo/nvm/Context
            DUP
            ALOAD 1
            ALOAD 2
            INVOKESPECIAL org/nlogo/nvm/Context.<init> (Lorg/nlogo/nvm/Context;Lorg/nlogo/agent/AgentSet;)V
            ASTORE 4
            ICONST_0
            ISTORE 5
            ALOAD 2
            INVOKEVIRTUAL org/nlogo/agent/AgentSet.iterator ()Lorg/nlogo/agent/AgentIterator;
            ASTORE 6
           L2
            ALOAD 6
            INVOKEINTERFACE org/nlogo/agent/AgentIterator.hasNext ()Z
            IFEQ L3
            ALOAD 6
            INVOKEINTERFACE org/nlogo/agent/AgentIterator.next ()Lorg/nlogo/agent/Agent;
            ASTORE 7
            ALOAD 4
            ALOAD 7
            ALOAD 3
            INVOKEVIRTUAL org/nlogo/nvm/Context.evaluateReporter (Lorg/nlogo/agent/Agent;Lorg/nlogo/nvm/Reporter;)Ljava/lang/Object;
            ASTORE 8
            ALOAD 8
            INSTANCEOF java/lang/Boolean
            IFEQ L4
            ALOAD 8
            CHECKCAST java/lang/Boolean
            INVOKEVIRTUAL java/lang/Boolean.booleanValue ()Z
            IFEQ L2
            ILOAD 5
            ICONST_1
            IADD
            ISTORE 5
            GOTO L2
           L4
            NEW org/nlogo/nvm/EngineException
            DUP
            ALOAD 1
            ALOAD 0
            GETSTATIC org/nlogo/api/I18N$.MODULE$ : Lorg/nlogo/api/I18N$;
            INVOKEVIRTUAL org/nlogo/api/I18N$.errors ()Lorg/nlogo/api/I18N$BundleKind;
            LDC "org.nlogo.prim.$common.expectedBooleanValue"
            GETSTATIC scala/Predef$.MODULE$ : Lscala/Predef$;
            ICONST_3
            ANEWARRAY java/lang/Object
            DUP
            ICONST_0
            LDC "COUNT"
            AASTORE
            DUP
            ICONST_1
            GETSTATIC org/nlogo/api/Dump$.MODULE$ : Lorg/nlogo/api/Dump$;
            ALOAD 7
            INVOKEVIRTUAL org/nlogo/api/Dump$.logoObject (Ljava/lang/Object;)Ljava/lang/String;
            AASTORE
            DUP
            ICONST_2
            GETSTATIC org/nlogo/api/Dump$.MODULE$ : Lorg/nlogo/api/Dump$;
            ALOAD 8
            INVOKEVIRTUAL org/nlogo/api/Dump$.logoObject (Ljava/lang/Object;)Ljava/lang/String;
            AASTORE
            INVOKEVIRTUAL scala/Predef$.wrapRefArray ([Ljava/lang/Object;)Lscala/collection/mutable/WrappedArray;
            INVOKEVIRTUAL org/nlogo/api/I18N$BundleKind.getN (Ljava/lang/String;Lscala/collection/Seq;)Ljava/lang/String;
            INVOKESPECIAL org/nlogo/nvm/EngineException.<init> (Lorg/nlogo/nvm/Context;Lorg/nlogo/nvm/Instruction;Ljava/lang/String;)V
            ATHROW
           L3
            ILOAD 5
            I2D
           L5
            LDC 4.0
           L6
            DSTORE 4
            DSTORE 2
            DLOAD 4
            DCONST_0
            DCMPL
            IFNE L7
            NEW org/nlogo/nvm/EngineException
            DUP
            ALOAD 1
            ALOAD 0
            INVOKESTATIC org/nlogo/api/I18N.errorsJ ()Lorg/nlogo/api/I18NJava;
            LDC "org.nlogo.prim.etc.$common.divByZero"
            INVOKEINTERFACE org/nlogo/api/I18NJava.get (Ljava/lang/String;)Ljava/lang/String;
            INVOKESPECIAL org/nlogo/nvm/EngineException.<init> (Lorg/nlogo/nvm/Context;Lorg/nlogo/nvm/Instruction;Ljava/lang/String;)V
            ATHROW
           L7
            DLOAD 2
            DLOAD 4
            DDIV
           L8
            DSTORE 2
            NEW java/lang/Double
            DUP
            DLOAD 2
            INVOKESPECIAL java/lang/Double.<init> (D)V
            ARETURN
[7]_asm_proceduregraph_return_8 "" => void
         L0
          ALOAD 1
          INVOKEVIRTUAL org/nlogo/nvm/Context.returnFromProcedure ()V
          ALOAD 1
          ICONST_0
          PUTFIELD org/nlogo/nvm/Context.stopping : Z
         L1
          RETURN

