globals [INIT-SHEEP SHEEP-METABOLISM SHEEP-REPRODUCE INIT-WOLVES WOLF-METABOLISM WOLF-REPRODUCE GRASS? GRASS-DELAY PLOT? RESULT]
interfaceGlobals [init-sheep sheep-metabolism sheep-reproduce init-wolves wolf-metabolism wolf-reproduce grass? grass-delay plot?]
turtles-own [WHO COLOR HEADING XCOR YCOR SHAPE LABEL LABEL-COLOR BREED HIDDEN? SIZE PEN-SIZE PEN-MODE ENERGY PREY]
patches-own [PXCOR PYCOR PCOLOR PLABEL PLABEL-COLOR COUNTDOWN]
links-own [END1 END2 COLOR LABEL LABEL-COLOR HIDDEN? BREED THICKNESS SHAPE TIE-MODE]
breeds SHEEP = Breed(SHEEP, A-SHEEP, , false)
WOLVES = Breed(WOLVES, WOLF, , false)
link-breeds 

procedure BENCHMARK:[_repeatlocal:0]{O---}:
[0]_asm_procedurebenchmark_randomseed_0 "random-seed 579" double => void
      _constdouble:579.0 "579" => double
          // parameter final  context
          // parameter final  arg0
         L0
          LDC 579.0
         L1
          DSTORE 2
          DLOAD 2
          D2L
          LSTORE 4
          LLOAD 4
          LDC -2147483648
          LCMP
          IFLT L2
          LLOAD 4
          LDC 2147483647
          LCMP
          IFLE L3
         L2
         FRAME APPEND [D J]
          NEW org/nlogo/nvm/RuntimePrimitiveException
          DUP
          ALOAD 1
          ALOAD 0
          NEW java/lang/StringBuilder
          DUP
          INVOKESPECIAL java/lang/StringBuilder.<init> ()V
          GETSTATIC org/nlogo/api/Dump$.MODULE$ : Lorg/nlogo/api/Dump$;
          DLOAD 2
          INVOKEVIRTUAL org/nlogo/api/Dump$.number (D)Ljava/lang/String;
          INVOKEVIRTUAL java/lang/StringBuilder.append (Ljava/lang/String;)Ljava/lang/StringBuilder;
          LDC " is not in the allowable range for random seeds (-2147483648 to 2147483647)"
          INVOKEVIRTUAL java/lang/StringBuilder.append (Ljava/lang/String;)Ljava/lang/StringBuilder;
          INVOKEVIRTUAL java/lang/StringBuilder.toString ()Ljava/lang/String;
          INVOKESPECIAL org/nlogo/nvm/RuntimePrimitiveException.<init> (Lorg/nlogo/api/Context;Lorg/nlogo/nvm/Instruction;Ljava/lang/String;)V
          ATHROW
         L3
         FRAME SAME
          ALOAD 1
          GETFIELD org/nlogo/nvm/Context.job : Lorg/nlogo/nvm/Job;
          GETFIELD org/nlogo/nvm/Job.random : Lorg/nlogo/api/MersenneTwisterFast;
          LLOAD 4
          L2I
          I2L
          INVOKEVIRTUAL org/nlogo/api/MersenneTwisterFast.setSeed (J)V
          ALOAD 1
          ICONST_1
          PUTFIELD org/nlogo/nvm/Context.ip : I
         L4
          RETURN
[1]_asm_procedurebenchmark_call_1 "setup"
         L0
          NEW org/nlogo/nvm/Activation
          DUP
          ALOAD 0
          GETFIELD org/nlogo/prim/_asm_procedurebenchmark_call_1.kept1_procedure : Lorg/nlogo/nvm/Procedure;
          ALOAD 1
          GETFIELD org/nlogo/nvm/Context.activation : Lorg/nlogo/nvm/Activation;
          ICONST_2
          INVOKESPECIAL org/nlogo/nvm/Activation.<init> (Lorg/nlogo/nvm/Procedure;Lorg/nlogo/nvm/Activation;I)V
          ALOAD 1
          SWAP
          PUTFIELD org/nlogo/nvm/Context.activation : Lorg/nlogo/nvm/Activation;
          ALOAD 1
          ICONST_0
          PUTFIELD org/nlogo/nvm/Context.ip : I
         L1
          RETURN
[2]_resettimer "reset-timer"
[3]_asm_procedurebenchmark_repeatlocal_2 "repeat 10000 [ go ]" double => void
      _constdouble:10000.0 "10000" => double
          // parameter final  context
          // parameter final  arg0
         L0
          LDC 10000.0
         L1
          DSTORE 2
          ALOAD 1
          GETFIELD org/nlogo/nvm/Context.activation : Lorg/nlogo/nvm/Activation;
          GETFIELD org/nlogo/nvm/Activation.args : [Ljava/lang/Object;
          ICONST_0
          NEW org/nlogo/nvm/MutableLong
          DUP
          ALOAD 0
          DLOAD 2
          INVOKEVIRTUAL org/nlogo/prim/_asm_procedurebenchmark_repeatlocal_2.validLong (D)J
          INVOKESPECIAL org/nlogo/nvm/MutableLong.<init> (J)V
          AASTORE
          ALOAD 1
          ICONST_5
          PUTFIELD org/nlogo/nvm/Context.ip : I
         L2
          RETURN
[4]_asm_procedurebenchmark_call_3 "go"
         L0
          NEW org/nlogo/nvm/Activation
          DUP
          ALOAD 0
          GETFIELD org/nlogo/prim/_asm_procedurebenchmark_call_3.kept1_procedure : Lorg/nlogo/nvm/Procedure;
          ALOAD 1
          GETFIELD org/nlogo/nvm/Context.activation : Lorg/nlogo/nvm/Activation;
          ICONST_5
          INVOKESPECIAL org/nlogo/nvm/Activation.<init> (Lorg/nlogo/nvm/Procedure;Lorg/nlogo/nvm/Activation;I)V
          ALOAD 1
          SWAP
          PUTFIELD org/nlogo/nvm/Context.activation : Lorg/nlogo/nvm/Activation;
          ALOAD 1
          ICONST_0
          PUTFIELD org/nlogo/nvm/Context.ip : I
         L1
          RETURN
[5]_asm_procedurebenchmark_repeatlocalinternal_4 => void
          // parameter final  context
         L0
          ALOAD 1
          GETFIELD org/nlogo/nvm/Context.activation : Lorg/nlogo/nvm/Activation;
          GETFIELD org/nlogo/nvm/Activation.args : [Ljava/lang/Object;
          ICONST_0
          AALOAD
          CHECKCAST org/nlogo/nvm/MutableLong
          ASTORE 2
          ALOAD 2
          INVOKEVIRTUAL org/nlogo/nvm/MutableLong.value ()J
          LCONST_0
          LCMP
          IFGT L1
          ALOAD 1
          BIPUSH 6
          PUTFIELD org/nlogo/nvm/Context.ip : I
          GOTO L2
         L1
         FRAME APPEND [org/nlogo/nvm/MutableLong]
          ALOAD 2
          ALOAD 2
          INVOKEVIRTUAL org/nlogo/nvm/MutableLong.value ()J
          LCONST_1
          LSUB
          INVOKEVIRTUAL org/nlogo/nvm/MutableLong.value_$eq (J)V
          ALOAD 1
          ICONST_4
          PUTFIELD org/nlogo/nvm/Context.ip : I
         L2
         FRAME SAME
          RETURN
[6]_asm_procedurebenchmark_setobservervariable_5 "set result timer" Object => void
      _timer "timer" => double
          // parameter final  context
          TRYCATCHBLOCK L0 L1 L2 org/nlogo/api/AgentException
         L3
          ALOAD 0
          GETFIELD org/nlogo/prim/_asm_procedurebenchmark_setobservervariable_5.world : Lorg/nlogo/agent/World;
          INVOKEVIRTUAL org/nlogo/agent/World.timer ()Lorg/nlogo/api/Timer;
          INVOKEVIRTUAL org/nlogo/api/Timer.read ()D
         L4
          DSTORE 2
          NEW java/lang/Double
          DUP
          DLOAD 2
          INVOKESPECIAL java/lang/Double.<init> (D)V
          ASTORE 2
         L0
          ALOAD 1
          GETFIELD org/nlogo/nvm/Context.agent : Lorg/nlogo/agent/Agent;
          BIPUSH 9
          ALOAD 2
          INVOKEVIRTUAL org/nlogo/agent/Agent.setObserverVariable (ILjava/lang/Object;)V
         L1
          GOTO L5
         L2
         FRAME FULL [org/nlogo/prim/_asm_procedurebenchmark_setobservervariable_5 org/nlogo/nvm/Context java/lang/Double] [org/nlogo/api/AgentException]
          ASTORE 3
          NEW org/nlogo/nvm/RuntimePrimitiveException
          DUP
          ALOAD 1
          ALOAD 0
          ALOAD 3
          INVOKEVIRTUAL org/nlogo/api/AgentException.getMessage ()Ljava/lang/String;
          INVOKESPECIAL org/nlogo/nvm/RuntimePrimitiveException.<init> (Lorg/nlogo/api/Context;Lorg/nlogo/nvm/Instruction;Ljava/lang/String;)V
          ATHROW
         L5
         FRAME SAME
          ALOAD 1
          BIPUSH 7
          PUTFIELD org/nlogo/nvm/Context.ip : I
         L6
          RETURN
[7]_asm_procedurebenchmark_return_6 => void
         L0
          ALOAD 1
          INVOKEVIRTUAL org/nlogo/nvm/Context.returnFromProcedure ()V
          ALOAD 1
          ICONST_0
          PUTFIELD org/nlogo/nvm/Context.stopping : Z
         L1
          RETURN

procedure CATCH-SHEEP:[]{-T--}:
[0]_asm_procedurecatchsheep_setturtlevariable_0 "set prey one-of sheep-here" Object => void
      _oneof "one-of sheep-here" AgentSet => Object
        _breedhere:SHEEP "sheep-here" => AgentSet
          // parameter final  context
          TRYCATCHBLOCK L0 L1 L2 org/nlogo/api/AgentException
         L3
          ALOAD 1
          GETFIELD org/nlogo/nvm/Context.agent : Lorg/nlogo/agent/Agent;
          ASTORE 3
          ALOAD 3
          INSTANCEOF org/nlogo/agent/Turtle
          IFEQ L4
          ALOAD 3
          CHECKCAST org/nlogo/agent/Turtle
          INVOKEVIRTUAL org/nlogo/agent/Turtle.getPatchHere ()Lorg/nlogo/agent/Patch;
          ASTORE 2
          GOTO L5
         L4
         FRAME APPEND [T org/nlogo/agent/Agent]
          ALOAD 3
          INSTANCEOF org/nlogo/agent/Patch
          IFEQ L6
          ALOAD 3
          CHECKCAST org/nlogo/agent/Patch
          ASTORE 2
          GOTO L5
         L6
         FRAME SAME
          NEW scala/MatchError
          DUP
          ALOAD 3
          INVOKESPECIAL scala/MatchError.<init> (Ljava/lang/Object;)V
          ATHROW
         L5
         FRAME FULL [org/nlogo/prim/_asm_procedurecatchsheep_setturtlevariable_0 org/nlogo/nvm/Context org/nlogo/agent/Patch org/nlogo/agent/Agent] []
          ALOAD 0
          GETFIELD org/nlogo/prim/_asm_procedurecatchsheep_setturtlevariable_0.world : Lorg/nlogo/agent/World;
          LDC "SHEEP"
          INVOKEVIRTUAL org/nlogo/agent/World.getBreed (Ljava/lang/String;)Lorg/nlogo/agent/AgentSet;
          ASTORE 4
          NEW org/nlogo/agent/AgentSetBuilder
          DUP
          GETSTATIC org/nlogo/core/AgentKind$Turtle$.MODULE$ : Lorg/nlogo/core/AgentKind$Turtle$;
          ALOAD 2
          INVOKEVIRTUAL org/nlogo/agent/Patch.turtleCount ()I
          INVOKESPECIAL org/nlogo/agent/AgentSetBuilder.<init> (Lorg/nlogo/core/AgentKind;I)V
          ASTORE 5
          ALOAD 2
          INVOKEVIRTUAL org/nlogo/agent/Patch.turtlesHere ()Ljava/lang/Iterable;
          INVOKEINTERFACE java/lang/Iterable.iterator ()Ljava/util/Iterator;
          ASTORE 6
         L7
         FRAME APPEND [org/nlogo/agent/AgentSet org/nlogo/agent/AgentSetBuilder java/util/Iterator]
          ALOAD 6
          INVOKEINTERFACE java/util/Iterator.hasNext ()Z
          IFEQ L8
          ALOAD 6
          INVOKEINTERFACE java/util/Iterator.next ()Ljava/lang/Object;
          CHECKCAST org/nlogo/agent/Turtle
          ASTORE 7
          ALOAD 7
          INVOKEVIRTUAL org/nlogo/agent/Turtle.getBreed ()Lorg/nlogo/agent/AgentSet;
          DUP
          IFNONNULL L9
          POP
          ALOAD 4
          IFNULL L10
          GOTO L7
         L9
         FRAME FULL [org/nlogo/prim/_asm_procedurecatchsheep_setturtlevariable_0 org/nlogo/nvm/Context org/nlogo/agent/Patch org/nlogo/agent/Agent org/nlogo/agent/AgentSet org/nlogo/agent/AgentSetBuilder java/util/Iterator org/nlogo/agent/Turtle] [org/nlogo/agent/AgentSet]
          ALOAD 4
          INVOKEVIRTUAL java/lang/Object.equals (Ljava/lang/Object;)Z
          IFEQ L7
         L10
         FRAME SAME
          ALOAD 5
          ALOAD 7
          INVOKEVIRTUAL org/nlogo/agent/AgentSetBuilder.add (Lorg/nlogo/agent/Agent;)V
          GOTO L7
         L8
         FRAME CHOP 1
          ALOAD 5
          INVOKEVIRTUAL org/nlogo/agent/AgentSetBuilder.build ()Lorg/nlogo/agent/IndexedAgentSet;
         L11
          ASTORE 2
          ALOAD 2
          INVOKEVIRTUAL org/nlogo/agent/AgentSet.count ()I
          ISTORE 3
          ILOAD 3
          IFNE L12
          GETSTATIC org/nlogo/core/Nobody$.MODULE$ : Lorg/nlogo/core/Nobody$;
          GOTO L13
         L12
         FRAME FULL [org/nlogo/prim/_asm_procedurecatchsheep_setturtlevariable_0 org/nlogo/nvm/Context org/nlogo/agent/IndexedAgentSet I org/nlogo/agent/AgentSet org/nlogo/agent/AgentSetBuilder java/util/Iterator] []
          ALOAD 2
          ILOAD 3
          ALOAD 1
          GETFIELD org/nlogo/nvm/Context.job : Lorg/nlogo/nvm/Job;
          GETFIELD org/nlogo/nvm/Job.random : Lorg/nlogo/api/MersenneTwisterFast;
          ILOAD 3
          INVOKEVIRTUAL org/nlogo/api/MersenneTwisterFast.nextInt (I)I
          INVOKEVIRTUAL org/nlogo/agent/AgentSet.randomOne (II)Lorg/nlogo/agent/Agent;
         L13
         FRAME SAME1 java/lang/Object
          ASTORE 2
         L0
          ALOAD 1
          GETFIELD org/nlogo/nvm/Context.agent : Lorg/nlogo/agent/Agent;
          BIPUSH 14
          ALOAD 2
          INVOKEVIRTUAL org/nlogo/agent/Agent.setTurtleVariable (ILjava/lang/Object;)V
         L1
          GOTO L14
         L2
         FRAME FULL [org/nlogo/prim/_asm_procedurecatchsheep_setturtlevariable_0 org/nlogo/nvm/Context java/lang/Object I org/nlogo/agent/AgentSet org/nlogo/agent/AgentSetBuilder java/util/Iterator] [org/nlogo/api/AgentException]
          ASTORE 3
          NEW org/nlogo/nvm/RuntimePrimitiveException
          DUP
          ALOAD 1
          ALOAD 0
          ALOAD 3
          INVOKEVIRTUAL org/nlogo/api/AgentException.getMessage ()Ljava/lang/String;
          INVOKESPECIAL org/nlogo/nvm/RuntimePrimitiveException.<init> (Lorg/nlogo/api/Context;Lorg/nlogo/nvm/Instruction;Ljava/lang/String;)V
          ATHROW
         L14
         FRAME SAME
          ALOAD 1
          ICONST_1
          PUTFIELD org/nlogo/nvm/Context.ip : I
         L15
          RETURN
[1]_asm_procedurecatchsheep_if_1 "if prey != nobody ask prey [ set energy -1 ] [ set energy energy + wolf-metabolism ]" boolean => void
      _notequal "prey != nobody" Object,Object => boolean
        _turtlevariable:PREY "prey" => Object
        _nobody "nobody" => Nobody$
          // parameter final  context
          TRYCATCHBLOCK L0 L1 L2 org/nlogo/api/AgentException
         L0
          ALOAD 1
          GETFIELD org/nlogo/nvm/Context.agent : Lorg/nlogo/agent/Agent;
          BIPUSH 14
          INVOKEVIRTUAL org/nlogo/agent/Agent.getTurtleVariable (I)Ljava/lang/Object;
         L1
          GOTO L3
         L2
         FRAME SAME1 org/nlogo/api/AgentException
          ASTORE 2
          NEW org/nlogo/nvm/RuntimePrimitiveException
          DUP
          ALOAD 1
          ALOAD 0
          ALOAD 2
          INVOKEVIRTUAL org/nlogo/api/AgentException.getMessage ()Ljava/lang/String;
          INVOKESPECIAL org/nlogo/nvm/RuntimePrimitiveException.<init> (Lorg/nlogo/api/Context;Lorg/nlogo/nvm/Instruction;Ljava/lang/String;)V
          ATHROW
         L3
         FRAME SAME1 java/lang/Object
          GETSTATIC org/nlogo/core/Nobody$.MODULE$ : Lorg/nlogo/core/Nobody$;
         L4
          ASTORE 3
          ASTORE 2
          ALOAD 2
          ALOAD 3
          INVOKESTATIC org/nlogo/api/Equality.equals (Ljava/lang/Object;Ljava/lang/Object;)Z
          IFNE L5
          ICONST_1
          GOTO L6
         L5
         FRAME APPEND [java/lang/Object org/nlogo/core/Nobody$]
          ICONST_0
         L6
         FRAME SAME1 I
          ISTORE 2
          ALOAD 1
          ILOAD 2
          IFEQ L7
          ICONST_2
          GOTO L8
         L7
         FRAME FULL [org/nlogo/prim/_asm_procedurecatchsheep_if_1 org/nlogo/nvm/Context I org/nlogo/core/Nobody$] [org/nlogo/nvm/Context]
          BIPUSH 6
         L8
         FRAME FULL [org/nlogo/prim/_asm_procedurecatchsheep_if_1 org/nlogo/nvm/Context I org/nlogo/core/Nobody$] [org/nlogo/nvm/Context I]
          PUTFIELD org/nlogo/nvm/Context.ip : I
         L9
          RETURN
[2]_asm_procedurecatchsheep_ask_2 "ask prey [ set energy -1 ]" Object => void
      _turtlevariable:PREY "prey" => Object
          TRYCATCHBLOCK L0 L1 L2 org/nlogo/api/AgentException
         L0
          ALOAD 1
          GETFIELD org/nlogo/nvm/Context.agent : Lorg/nlogo/agent/Agent;
          BIPUSH 14
          INVOKEVIRTUAL org/nlogo/agent/Agent.getTurtleVariable (I)Ljava/lang/Object;
         L1
          GOTO L3
         L2
         FRAME SAME1 org/nlogo/api/AgentException
          ASTORE 2
          NEW org/nlogo/nvm/RuntimePrimitiveException
          DUP
          ALOAD 1
          ALOAD 0
          ALOAD 2
          INVOKEVIRTUAL org/nlogo/api/AgentException.getMessage ()Ljava/lang/String;
          INVOKESPECIAL org/nlogo/nvm/RuntimePrimitiveException.<init> (Lorg/nlogo/api/Context;Lorg/nlogo/nvm/Instruction;Ljava/lang/String;)V
          ATHROW
         L3
         FRAME SAME1 java/lang/Object
          ASTORE 2
          ALOAD 2
          INSTANCEOF org/nlogo/agent/AgentSet
          IFEQ L4
          ALOAD 2
          CHECKCAST org/nlogo/agent/AgentSet
          ASTORE 3
          ALOAD 1
          GETFIELD org/nlogo/nvm/Context.agent : Lorg/nlogo/agent/Agent;
          INSTANCEOF org/nlogo/agent/Observer
          IFNE L5
          ALOAD 3
          ALOAD 0
          GETFIELD org/nlogo/prim/_asm_procedurecatchsheep_ask_2.world : Lorg/nlogo/agent/World;
          INVOKEVIRTUAL org/nlogo/agent/World.turtles ()Lorg/nlogo/agent/TreeAgentSet;
          IF_ACMPNE L6
          NEW org/nlogo/nvm/RuntimePrimitiveException
          DUP
          ALOAD 1
          ALOAD 0
          INVOKESTATIC org/nlogo/core/I18N.errorsJ ()Lorg/nlogo/core/I18NJava;
          LDC "org.nlogo.prim.$common.onlyObserverCanAskAllTurtles"
          INVOKEINTERFACE org/nlogo/core/I18NJava.get (Ljava/lang/String;)Ljava/lang/String;
          INVOKESPECIAL org/nlogo/nvm/RuntimePrimitiveException.<init> (Lorg/nlogo/api/Context;Lorg/nlogo/nvm/Instruction;Ljava/lang/String;)V
          ATHROW
         L6
         FRAME APPEND [java/lang/Object org/nlogo/agent/AgentSet]
          ALOAD 3
          ALOAD 0
          GETFIELD org/nlogo/prim/_asm_procedurecatchsheep_ask_2.world : Lorg/nlogo/agent/World;
          INVOKEVIRTUAL org/nlogo/agent/World.patches ()Lorg/nlogo/agent/AgentSet;
          IF_ACMPNE L5
          NEW org/nlogo/nvm/RuntimePrimitiveException
          DUP
          ALOAD 1
          ALOAD 0
          INVOKESTATIC org/nlogo/core/I18N.errorsJ ()Lorg/nlogo/core/I18NJava;
          LDC "org.nlogo.prim.$common.onlyObserverCanAskAllPatches"
          INVOKEINTERFACE org/nlogo/core/I18NJava.get (Ljava/lang/String;)Ljava/lang/String;
          INVOKESPECIAL org/nlogo/nvm/RuntimePrimitiveException.<init> (Lorg/nlogo/api/Context;Lorg/nlogo/nvm/Instruction;Ljava/lang/String;)V
          ATHROW
         L4
         FRAME CHOP 1
          ALOAD 2
          INSTANCEOF org/nlogo/agent/Agent
          IFEQ L7
          ALOAD 2
          CHECKCAST org/nlogo/agent/Agent
          ASTORE 4
          ALOAD 4
          GETFIELD org/nlogo/agent/Agent.id : J
          LDC -1
          LCMP
          IFNE L8
          NEW org/nlogo/nvm/RuntimePrimitiveException
          DUP
          ALOAD 1
          ALOAD 0
          INVOKESTATIC org/nlogo/core/I18N.errorsJ ()Lorg/nlogo/core/I18NJava;
          LDC "org.nlogo.$common.thatAgentIsDead"
          ICONST_1
          ANEWARRAY java/lang/Object
          DUP
          ICONST_0
          ALOAD 4
          INVOKEVIRTUAL org/nlogo/agent/Agent.classDisplayName ()Ljava/lang/String;
          AASTORE
          INVOKEINTERFACE org/nlogo/core/I18NJava.getN (Ljava/lang/String;[Ljava/lang/Object;)Ljava/lang/String;
          INVOKESPECIAL org/nlogo/nvm/RuntimePrimitiveException.<init> (Lorg/nlogo/api/Context;Lorg/nlogo/nvm/Instruction;Ljava/lang/String;)V
          ATHROW
         L8
         FRAME APPEND [T org/nlogo/agent/Agent]
          ALOAD 4
          INVOKESTATIC org/nlogo/agent/AgentSet.fromAgent (Lorg/nlogo/agent/Agent;)Lorg/nlogo/agent/IndexedAgentSet;
          ASTORE 3
          GOTO L5
         L7
         FRAME CHOP 2
          NEW org/nlogo/nvm/ArgumentTypeException
          DUP
          ALOAD 1
          ALOAD 0
          ICONST_0
          INVOKESTATIC org/nlogo/core/Syntax.AgentsetType ()I
          INVOKESTATIC org/nlogo/core/Syntax.AgentType ()I
          IOR
          ALOAD 2
          INVOKESPECIAL org/nlogo/nvm/ArgumentTypeException.<init> (Lorg/nlogo/nvm/Context;Lorg/nlogo/nvm/Instruction;IILjava/lang/Object;)V
          ATHROW
         L5
         FRAME APPEND [org/nlogo/agent/AgentSet]
          ALOAD 1
          ALOAD 3
          ICONST_3
          INVOKEVIRTUAL org/nlogo/nvm/Context.runExclusiveJob (Lorg/nlogo/agent/AgentSet;I)V
          ALOAD 1
          ICONST_5
          PUTFIELD org/nlogo/nvm/Context.ip : I
         L9
          RETURN
[3]_asm_procedurecatchsheep_setturtlevariable_3 "set energy -1" Object => void
      _constdouble:-1.0 "-1" => Double
          TRYCATCHBLOCK L0 L1 L2 org/nlogo/api/AgentException
         L3
          ALOAD 0
          GETFIELD org/nlogo/prim/_asm_procedurecatchsheep_setturtlevariable_3.kept2_value : Ljava/lang/Double;
         L4
          ASTORE 2
         L0
          ALOAD 1
          GETFIELD org/nlogo/nvm/Context.agent : Lorg/nlogo/agent/Agent;
          BIPUSH 13
          ALOAD 2
          INVOKEVIRTUAL org/nlogo/agent/Agent.setTurtleVariable (ILjava/lang/Object;)V
         L1
          GOTO L5
         L2
         FRAME FULL [org/nlogo/prim/_asm_procedurecatchsheep_setturtlevariable_3 org/nlogo/nvm/Context java/lang/Double] [org/nlogo/api/AgentException]
          ASTORE 3
          NEW org/nlogo/nvm/RuntimePrimitiveException
          DUP
          ALOAD 1
          ALOAD 0
          ALOAD 3
          INVOKEVIRTUAL org/nlogo/api/AgentException.getMessage ()Ljava/lang/String;
          INVOKESPECIAL org/nlogo/nvm/RuntimePrimitiveException.<init> (Lorg/nlogo/api/Context;Lorg/nlogo/nvm/Instruction;Ljava/lang/String;)V
          ATHROW
         L5
         FRAME SAME
          ALOAD 1
          ICONST_4
          PUTFIELD org/nlogo/nvm/Context.ip : I
         L6
          RETURN
[4]_asm_procedurecatchsheep_done_4 => void
          // parameter final  context
         L0
          ALOAD 1
          ICONST_1
          PUTFIELD org/nlogo/nvm/Context.finished : Z
         L1
          RETURN
[5]_asm_procedurecatchsheep_setturtlevariable_5 "set energy energy + wolf-metabolism" Object => void
      _plus "energy + wolf-metabolism" double,double => double
        _turtlevariable:ENERGY "energy" => Object
        _observervariable:WOLF-METABOLISM "wolf-metabolism" => Object
          TRYCATCHBLOCK L0 L1 L2 org/nlogo/api/AgentException
          TRYCATCHBLOCK L3 L4 L4 java/lang/ClassCastException
          TRYCATCHBLOCK L5 L6 L6 java/lang/ClassCastException
          TRYCATCHBLOCK L7 L8 L9 org/nlogo/api/AgentException
         L0
          ALOAD 1
          GETFIELD org/nlogo/nvm/Context.agent : Lorg/nlogo/agent/Agent;
          BIPUSH 13
          INVOKEVIRTUAL org/nlogo/agent/Agent.getTurtleVariable (I)Ljava/lang/Object;
         L1
          GOTO L10
         L2
         FRAME SAME1 org/nlogo/api/AgentException
          ASTORE 2
          NEW org/nlogo/nvm/RuntimePrimitiveException
          DUP
          ALOAD 1
          ALOAD 0
          ALOAD 2
          INVOKEVIRTUAL org/nlogo/api/AgentException.getMessage ()Ljava/lang/String;
          INVOKESPECIAL org/nlogo/nvm/RuntimePrimitiveException.<init> (Lorg/nlogo/api/Context;Lorg/nlogo/nvm/Instruction;Ljava/lang/String;)V
          ATHROW
         L10
         FRAME SAME1 java/lang/Object
          ASTORE 2
         L3
          ALOAD 2
          CHECKCAST java/lang/Double
          INVOKEVIRTUAL java/lang/Double.doubleValue ()D
          GOTO L11
         L4
         FRAME FULL [org/nlogo/prim/_asm_procedurecatchsheep_setturtlevariable_5 org/nlogo/nvm/Context java/lang/Object] [java/lang/ClassCastException]
          POP
          NEW org/nlogo/nvm/ArgumentTypeException
          DUP
          ALOAD 1
          ALOAD 0
          BIPUSH 0
          LDC 1
          ALOAD 2
          INVOKESPECIAL org/nlogo/nvm/ArgumentTypeException.<init> (Lorg/nlogo/nvm/Context;Lorg/nlogo/nvm/Instruction;IILjava/lang/Object;)V
          ATHROW
         L11
         FRAME SAME1 D
          ALOAD 1
          GETFIELD org/nlogo/nvm/Context.agent : Lorg/nlogo/agent/Agent;
          ICONST_4
          INVOKEVIRTUAL org/nlogo/agent/Agent.getObserverVariable (I)Ljava/lang/Object;
         L12
          ASTORE 2
         L5
          ALOAD 2
          CHECKCAST java/lang/Double
          INVOKEVIRTUAL java/lang/Double.doubleValue ()D
          GOTO L13
         L6
         FRAME SAME1 java/lang/ClassCastException
          POP
          NEW org/nlogo/nvm/ArgumentTypeException
          DUP
          ALOAD 1
          ALOAD 0
          BIPUSH 1
          LDC 1
          ALOAD 2
          INVOKESPECIAL org/nlogo/nvm/ArgumentTypeException.<init> (Lorg/nlogo/nvm/Context;Lorg/nlogo/nvm/Instruction;IILjava/lang/Object;)V
          ATHROW
         L13
         FRAME FULL [org/nlogo/prim/_asm_procedurecatchsheep_setturtlevariable_5 org/nlogo/nvm/Context java/lang/Object] [D D]
          DSTORE 4
          DSTORE 2
          ALOAD 0
          DLOAD 2
          DLOAD 4
          DADD
          INVOKEVIRTUAL org/nlogo/prim/_asm_procedurecatchsheep_setturtlevariable_5.validDouble (D)D
         L14
          DSTORE 2
          NEW java/lang/Double
          DUP
          DLOAD 2
          INVOKESPECIAL java/lang/Double.<init> (D)V
          ASTORE 2
         L7
          ALOAD 1
          GETFIELD org/nlogo/nvm/Context.agent : Lorg/nlogo/agent/Agent;
          BIPUSH 13
          ALOAD 2
          INVOKEVIRTUAL org/nlogo/agent/Agent.setTurtleVariable (ILjava/lang/Object;)V
         L8
          GOTO L15
         L9
         FRAME FULL [org/nlogo/prim/_asm_procedurecatchsheep_setturtlevariable_5 org/nlogo/nvm/Context java/lang/Double T D] [org/nlogo/api/AgentException]
          ASTORE 3
          NEW org/nlogo/nvm/RuntimePrimitiveException
          DUP
          ALOAD 1
          ALOAD 0
          ALOAD 3
          INVOKEVIRTUAL org/nlogo/api/AgentException.getMessage ()Ljava/lang/String;
          INVOKESPECIAL org/nlogo/nvm/RuntimePrimitiveException.<init> (Lorg/nlogo/api/Context;Lorg/nlogo/nvm/Instruction;Ljava/lang/String;)V
          ATHROW
         L15
         FRAME SAME
          ALOAD 1
          BIPUSH 6
          PUTFIELD org/nlogo/nvm/Context.ip : I
         L16
          RETURN
[6]_asm_procedurecatchsheep_return_6 => void
         L0
          ALOAD 1
          INVOKEVIRTUAL org/nlogo/nvm/Context.returnFromProcedure ()V
          ALOAD 1
          ICONST_0
          PUTFIELD org/nlogo/nvm/Context.stopping : Z
         L1
          RETURN

procedure DEATH:[]{-T--}:
[0]_asm_proceduredeath_if_0 "if energy < 0 [ die ]" boolean => void
      _lessthan "energy < 0" Object,double => boolean
        _turtlevariable:ENERGY "energy" => Object
        _constdouble:0.0 "0" => double
          TRYCATCHBLOCK L0 L1 L2 org/nlogo/api/AgentException
         L0
          ALOAD 1
          GETFIELD org/nlogo/nvm/Context.agent : Lorg/nlogo/agent/Agent;
          BIPUSH 13
          INVOKEVIRTUAL org/nlogo/agent/Agent.getTurtleVariable (I)Ljava/lang/Object;
         L1
          GOTO L3
         L2
         FRAME SAME1 org/nlogo/api/AgentException
          ASTORE 2
          NEW org/nlogo/nvm/RuntimePrimitiveException
          DUP
          ALOAD 1
          ALOAD 0
          ALOAD 2
          INVOKEVIRTUAL org/nlogo/api/AgentException.getMessage ()Ljava/lang/String;
          INVOKESPECIAL org/nlogo/nvm/RuntimePrimitiveException.<init> (Lorg/nlogo/api/Context;Lorg/nlogo/nvm/Instruction;Ljava/lang/String;)V
          ATHROW
         L3
         FRAME SAME1 java/lang/Object
          DCONST_0
         L4
          DSTORE 3
          ASTORE 2
          ALOAD 2
          INSTANCEOF java/lang/Double
          IFEQ L5
          ALOAD 2
          CHECKCAST java/lang/Double
          INVOKEVIRTUAL java/lang/Double.doubleValue ()D
          DLOAD 3
          DCMPG
          IFGE L6
          ICONST_1
          GOTO L7
         L6
         FRAME APPEND [java/lang/Object D]
          ICONST_0
         L7
         FRAME SAME1 I
          GOTO L8
         L5
         FRAME SAME
          NEW org/nlogo/nvm/RuntimePrimitiveException
          DUP
          ALOAD 1
          ALOAD 0
          INVOKESTATIC org/nlogo/core/I18N.errorsJ ()Lorg/nlogo/core/I18NJava;
          LDC "org.nlogo.prim._lessthan.cantUseLessthanOnDifferentArgs"
          ICONST_2
          ANEWARRAY java/lang/Object
          DUP
          ICONST_0
          ALOAD 2
          INVOKESTATIC org/nlogo/api/TypeNames.aName (Ljava/lang/Object;)Ljava/lang/String;
          AASTORE
          DUP
          ICONST_1
          DLOAD 3
          INVOKESTATIC java/lang/Double.valueOf (D)Ljava/lang/Double;
          INVOKESTATIC org/nlogo/api/TypeNames.aName (Ljava/lang/Object;)Ljava/lang/String;
          AASTORE
          INVOKEINTERFACE org/nlogo/core/I18NJava.getN (Ljava/lang/String;[Ljava/lang/Object;)Ljava/lang/String;
          INVOKESPECIAL org/nlogo/nvm/RuntimePrimitiveException.<init> (Lorg/nlogo/api/Context;Lorg/nlogo/nvm/Instruction;Ljava/lang/String;)V
          ATHROW
         L8
         FRAME SAME1 I
          ISTORE 2
          ALOAD 1
          ILOAD 2
          IFEQ L9
          ICONST_1
          GOTO L10
         L9
         FRAME FULL [org/nlogo/prim/_asm_proceduredeath_if_0 org/nlogo/nvm/Context I D] [org/nlogo/nvm/Context]
          ICONST_2
         L10
         FRAME FULL [org/nlogo/prim/_asm_proceduredeath_if_0 org/nlogo/nvm/Context I D] [org/nlogo/nvm/Context I]
          PUTFIELD org/nlogo/nvm/Context.ip : I
         L11
          RETURN
[1]_asm_proceduredeath_die_1 "die" => void
         L0
          ALOAD 1
          GETFIELD org/nlogo/nvm/Context.agent : Lorg/nlogo/agent/Agent;
          INSTANCEOF org/nlogo/agent/Turtle
          IFEQ L1
          ALOAD 1
          GETFIELD org/nlogo/nvm/Context.agent : Lorg/nlogo/agent/Agent;
          CHECKCAST org/nlogo/agent/Turtle
          INVOKEVIRTUAL org/nlogo/agent/Turtle.die ()V
          GOTO L2
         L1
         FRAME SAME
          ALOAD 1
          GETFIELD org/nlogo/nvm/Context.agent : Lorg/nlogo/agent/Agent;
          CHECKCAST org/nlogo/agent/Link
          INVOKEVIRTUAL org/nlogo/agent/Link.die ()V
         L2
         FRAME SAME
          ALOAD 1
          ICONST_1
          PUTFIELD org/nlogo/nvm/Context.finished : Z
         L3
          RETURN
[2]_asm_proceduredeath_return_2 => void
         L0
          ALOAD 1
          INVOKEVIRTUAL org/nlogo/nvm/Context.returnFromProcedure ()V
          ALOAD 1
          ICONST_0
          PUTFIELD org/nlogo/nvm/Context.stopping : Z
         L1
          RETURN

procedure EAT-GRASS:[]{-T--}:
[0]_asm_procedureeatgrass_if_0 "if pcolor = green set pcolor brown [ set energy energy + sheep-metabolism ]" boolean => void
      _equal "pcolor = green" Object,double => boolean
        _patchvariable:PCOLOR "pcolor" => Object
        _constdouble:55.0 "green" => double
          // parameter final  context
          TRYCATCHBLOCK L0 L1 L2 org/nlogo/api/AgentException
         L0
          ALOAD 1
          GETFIELD org/nlogo/nvm/Context.agent : Lorg/nlogo/agent/Agent;
          ICONST_2
          INVOKEVIRTUAL org/nlogo/agent/Agent.getPatchVariable (I)Ljava/lang/Object;
         L1
          GOTO L3
         L2
         FRAME SAME1 org/nlogo/api/AgentException
          ASTORE 2
          NEW org/nlogo/nvm/RuntimePrimitiveException
          DUP
          ALOAD 1
          ALOAD 0
          ALOAD 2
          INVOKEVIRTUAL org/nlogo/api/AgentException.getMessage ()Ljava/lang/String;
          INVOKESPECIAL org/nlogo/nvm/RuntimePrimitiveException.<init> (Lorg/nlogo/api/Context;Lorg/nlogo/nvm/Instruction;Ljava/lang/String;)V
          ATHROW
         L3
         FRAME SAME1 java/lang/Object
          LDC 55.0
         L4
          DSTORE 3
          ASTORE 2
          ALOAD 2
          INSTANCEOF java/lang/Double
          IFEQ L5
          DLOAD 3
          ALOAD 2
          CHECKCAST java/lang/Double
          INVOKEVIRTUAL java/lang/Double.doubleValue ()D
          DCMPL
          IFNE L5
          ICONST_1
          GOTO L6
         L5
         FRAME APPEND [java/lang/Object D]
          ICONST_0
         L6
         FRAME SAME1 I
          ISTORE 2
          ALOAD 1
          ILOAD 2
          IFEQ L7
          ICONST_1
          GOTO L8
         L7
         FRAME FULL [org/nlogo/prim/_asm_procedureeatgrass_if_0 org/nlogo/nvm/Context I D] [org/nlogo/nvm/Context]
          ICONST_3
         L8
         FRAME FULL [org/nlogo/prim/_asm_procedureeatgrass_if_0 org/nlogo/nvm/Context I D] [org/nlogo/nvm/Context I]
          PUTFIELD org/nlogo/nvm/Context.ip : I
         L9
          RETURN
[1]_asm_procedureeatgrass_setpatchvariable_1 "set pcolor brown" Object => void
      _constdouble:35.0 "brown" => Double
          TRYCATCHBLOCK L0 L1 L2 org/nlogo/api/AgentException
         L3
          ALOAD 0
          GETFIELD org/nlogo/prim/_asm_procedureeatgrass_setpatchvariable_1.kept2_value : Ljava/lang/Double;
         L4
          ASTORE 2
         L0
          ALOAD 1
          GETFIELD org/nlogo/nvm/Context.agent : Lorg/nlogo/agent/Agent;
          ICONST_2
          ALOAD 2
          INVOKEVIRTUAL org/nlogo/agent/Agent.setPatchVariable (ILjava/lang/Object;)V
         L1
          GOTO L5
         L2
         FRAME FULL [org/nlogo/prim/_asm_procedureeatgrass_setpatchvariable_1 org/nlogo/nvm/Context java/lang/Double] [org/nlogo/api/AgentException]
          ASTORE 3
          NEW org/nlogo/nvm/RuntimePrimitiveException
          DUP
          ALOAD 1
          ALOAD 0
          ALOAD 3
          INVOKEVIRTUAL org/nlogo/api/AgentException.getMessage ()Ljava/lang/String;
          INVOKESPECIAL org/nlogo/nvm/RuntimePrimitiveException.<init> (Lorg/nlogo/api/Context;Lorg/nlogo/nvm/Instruction;Ljava/lang/String;)V
          ATHROW
         L5
         FRAME SAME
          ALOAD 1
          ICONST_2
          PUTFIELD org/nlogo/nvm/Context.ip : I
         L6
          RETURN
[2]_asm_procedureeatgrass_setturtlevariable_2 "set energy energy + sheep-metabolism" Object => void
      _plus "energy + sheep-metabolism" double,double => double
        _turtlevariable:ENERGY "energy" => Object
        _observervariable:SHEEP-METABOLISM "sheep-metabolism" => Object
          TRYCATCHBLOCK L0 L1 L2 org/nlogo/api/AgentException
          TRYCATCHBLOCK L3 L4 L4 java/lang/ClassCastException
          TRYCATCHBLOCK L5 L6 L6 java/lang/ClassCastException
          TRYCATCHBLOCK L7 L8 L9 org/nlogo/api/AgentException
         L0
          ALOAD 1
          GETFIELD org/nlogo/nvm/Context.agent : Lorg/nlogo/agent/Agent;
          BIPUSH 13
          INVOKEVIRTUAL org/nlogo/agent/Agent.getTurtleVariable (I)Ljava/lang/Object;
         L1
          GOTO L10
         L2
         FRAME SAME1 org/nlogo/api/AgentException
          ASTORE 2
          NEW org/nlogo/nvm/RuntimePrimitiveException
          DUP
          ALOAD 1
          ALOAD 0
          ALOAD 2
          INVOKEVIRTUAL org/nlogo/api/AgentException.getMessage ()Ljava/lang/String;
          INVOKESPECIAL org/nlogo/nvm/RuntimePrimitiveException.<init> (Lorg/nlogo/api/Context;Lorg/nlogo/nvm/Instruction;Ljava/lang/String;)V
          ATHROW
         L10
         FRAME SAME1 java/lang/Object
          ASTORE 2
         L3
          ALOAD 2
          CHECKCAST java/lang/Double
          INVOKEVIRTUAL java/lang/Double.doubleValue ()D
          GOTO L11
         L4
         FRAME FULL [org/nlogo/prim/_asm_procedureeatgrass_setturtlevariable_2 org/nlogo/nvm/Context java/lang/Object] [java/lang/ClassCastException]
          POP
          NEW org/nlogo/nvm/ArgumentTypeException
          DUP
          ALOAD 1
          ALOAD 0
          BIPUSH 0
          LDC 1
          ALOAD 2
          INVOKESPECIAL org/nlogo/nvm/ArgumentTypeException.<init> (Lorg/nlogo/nvm/Context;Lorg/nlogo/nvm/Instruction;IILjava/lang/Object;)V
          ATHROW
         L11
         FRAME SAME1 D
          ALOAD 1
          GETFIELD org/nlogo/nvm/Context.agent : Lorg/nlogo/agent/Agent;
          ICONST_1
          INVOKEVIRTUAL org/nlogo/agent/Agent.getObserverVariable (I)Ljava/lang/Object;
         L12
          ASTORE 2
         L5
          ALOAD 2
          CHECKCAST java/lang/Double
          INVOKEVIRTUAL java/lang/Double.doubleValue ()D
          GOTO L13
         L6
         FRAME SAME1 java/lang/ClassCastException
          POP
          NEW org/nlogo/nvm/ArgumentTypeException
          DUP
          ALOAD 1
          ALOAD 0
          BIPUSH 1
          LDC 1
          ALOAD 2
          INVOKESPECIAL org/nlogo/nvm/ArgumentTypeException.<init> (Lorg/nlogo/nvm/Context;Lorg/nlogo/nvm/Instruction;IILjava/lang/Object;)V
          ATHROW
         L13
         FRAME FULL [org/nlogo/prim/_asm_procedureeatgrass_setturtlevariable_2 org/nlogo/nvm/Context java/lang/Object] [D D]
          DSTORE 4
          DSTORE 2
          ALOAD 0
          DLOAD 2
          DLOAD 4
          DADD
          INVOKEVIRTUAL org/nlogo/prim/_asm_procedureeatgrass_setturtlevariable_2.validDouble (D)D
         L14
          DSTORE 2
          NEW java/lang/Double
          DUP
          DLOAD 2
          INVOKESPECIAL java/lang/Double.<init> (D)V
          ASTORE 2
         L7
          ALOAD 1
          GETFIELD org/nlogo/nvm/Context.agent : Lorg/nlogo/agent/Agent;
          BIPUSH 13
          ALOAD 2
          INVOKEVIRTUAL org/nlogo/agent/Agent.setTurtleVariable (ILjava/lang/Object;)V
         L8
          GOTO L15
         L9
         FRAME FULL [org/nlogo/prim/_asm_procedureeatgrass_setturtlevariable_2 org/nlogo/nvm/Context java/lang/Double T D] [org/nlogo/api/AgentException]
          ASTORE 3
          NEW org/nlogo/nvm/RuntimePrimitiveException
          DUP
          ALOAD 1
          ALOAD 0
          ALOAD 3
          INVOKEVIRTUAL org/nlogo/api/AgentException.getMessage ()Ljava/lang/String;
          INVOKESPECIAL org/nlogo/nvm/RuntimePrimitiveException.<init> (Lorg/nlogo/api/Context;Lorg/nlogo/nvm/Instruction;Ljava/lang/String;)V
          ATHROW
         L15
         FRAME SAME
          ALOAD 1
          ICONST_3
          PUTFIELD org/nlogo/nvm/Context.ip : I
         L16
          RETURN
[3]_asm_procedureeatgrass_return_3 => void
         L0
          ALOAD 1
          INVOKEVIRTUAL org/nlogo/nvm/Context.returnFromProcedure ()V
          ALOAD 1
          ICONST_0
          PUTFIELD org/nlogo/nvm/Context.stopping : Z
         L1
          RETURN

procedure GO:[]{O---}:
[0]_asm_procedurego_ask_0 "ask sheep move if grass? set energy energy - 1 [ eat-grass ] reproduce-sheep [ death ]" AgentSet => void
      _breed:SHEEP "sheep" => AgentSet
          // parameter final  context
         L0
          ALOAD 0
          GETFIELD org/nlogo/prim/_asm_procedurego_ask_0.world : Lorg/nlogo/agent/World;
          LDC "SHEEP"
          INVOKEVIRTUAL org/nlogo/agent/World.getBreed (Ljava/lang/String;)Lorg/nlogo/agent/AgentSet;
         L1
          ASTORE 2
          ALOAD 1
          GETFIELD org/nlogo/nvm/Context.agent : Lorg/nlogo/agent/Agent;
          INSTANCEOF org/nlogo/agent/Observer
          IFNE L2
          ALOAD 2
          ALOAD 0
          GETFIELD org/nlogo/prim/_asm_procedurego_ask_0.world : Lorg/nlogo/agent/World;
          INVOKEVIRTUAL org/nlogo/agent/World.turtles ()Lorg/nlogo/agent/TreeAgentSet;
          IF_ACMPNE L3
          NEW org/nlogo/nvm/RuntimePrimitiveException
          DUP
          ALOAD 1
          ALOAD 0
          INVOKESTATIC org/nlogo/core/I18N.errorsJ ()Lorg/nlogo/core/I18NJava;
          LDC "org.nlogo.prim.$common.onlyObserverCanAskAllTurtles"
          INVOKEINTERFACE org/nlogo/core/I18NJava.get (Ljava/lang/String;)Ljava/lang/String;
          INVOKESPECIAL org/nlogo/nvm/RuntimePrimitiveException.<init> (Lorg/nlogo/api/Context;Lorg/nlogo/nvm/Instruction;Ljava/lang/String;)V
          ATHROW
         L3
         FRAME APPEND [org/nlogo/agent/AgentSet]
          ALOAD 2
          ALOAD 0
          GETFIELD org/nlogo/prim/_asm_procedurego_ask_0.world : Lorg/nlogo/agent/World;
          INVOKEVIRTUAL org/nlogo/agent/World.patches ()Lorg/nlogo/agent/AgentSet;
          IF_ACMPNE L2
          NEW org/nlogo/nvm/RuntimePrimitiveException
          DUP
          ALOAD 1
          ALOAD 0
          INVOKESTATIC org/nlogo/core/I18N.errorsJ ()Lorg/nlogo/core/I18NJava;
          LDC "org.nlogo.prim.$common.onlyObserverCanAskAllPatches"
          INVOKEINTERFACE org/nlogo/core/I18NJava.get (Ljava/lang/String;)Ljava/lang/String;
          INVOKESPECIAL org/nlogo/nvm/RuntimePrimitiveException.<init> (Lorg/nlogo/api/Context;Lorg/nlogo/nvm/Instruction;Ljava/lang/String;)V
          ATHROW
         L2
         FRAME SAME
          ALOAD 1
          ALOAD 2
          ICONST_1
          INVOKEVIRTUAL org/nlogo/nvm/Context.runExclusiveJob (Lorg/nlogo/agent/AgentSet;I)V
          ALOAD 1
          BIPUSH 8
          PUTFIELD org/nlogo/nvm/Context.ip : I
         L4
          RETURN
[1]_asm_procedurego_call_1 "move"
         L0
          NEW org/nlogo/nvm/Activation
          DUP
          ALOAD 0
          GETFIELD org/nlogo/prim/_asm_procedurego_call_1.kept1_procedure : Lorg/nlogo/nvm/Procedure;
          ALOAD 1
          GETFIELD org/nlogo/nvm/Context.activation : Lorg/nlogo/nvm/Activation;
          ICONST_2
          INVOKESPECIAL org/nlogo/nvm/Activation.<init> (Lorg/nlogo/nvm/Procedure;Lorg/nlogo/nvm/Activation;I)V
          ALOAD 1
          SWAP
          PUTFIELD org/nlogo/nvm/Context.activation : Lorg/nlogo/nvm/Activation;
          ALOAD 1
          ICONST_0
          PUTFIELD org/nlogo/nvm/Context.ip : I
         L1
          RETURN
[2]_asm_procedurego_if_2 "if grass? set energy energy - 1 [ eat-grass ]" boolean => void
      _observervariable:GRASS? "grass?" => Object
          TRYCATCHBLOCK L0 L1 L1 java/lang/ClassCastException
         L2
          ALOAD 1
          GETFIELD org/nlogo/nvm/Context.agent : Lorg/nlogo/agent/Agent;
          BIPUSH 6
          INVOKEVIRTUAL org/nlogo/agent/Agent.getObserverVariable (I)Ljava/lang/Object;
         L3
          ASTORE 2
         L0
          ALOAD 2
          CHECKCAST java/lang/Boolean
          INVOKEVIRTUAL java/lang/Boolean.booleanValue ()Z
          GOTO L4
         L1
         FRAME FULL [org/nlogo/prim/_asm_procedurego_if_2 org/nlogo/nvm/Context java/lang/Object] [java/lang/ClassCastException]
          POP
          NEW org/nlogo/nvm/ArgumentTypeException
          DUP
          ALOAD 1
          ALOAD 0
          BIPUSH 0
          LDC 2
          ALOAD 2
          INVOKESPECIAL org/nlogo/nvm/ArgumentTypeException.<init> (Lorg/nlogo/nvm/Context;Lorg/nlogo/nvm/Instruction;IILjava/lang/Object;)V
          ATHROW
         L4
         FRAME SAME1 I
          ISTORE 2
          ALOAD 1
          ILOAD 2
          IFEQ L5
          ICONST_3
          GOTO L6
         L5
         FRAME FULL [org/nlogo/prim/_asm_procedurego_if_2 org/nlogo/nvm/Context I] [org/nlogo/nvm/Context]
          ICONST_5
         L6
         FRAME FULL [org/nlogo/prim/_asm_procedurego_if_2 org/nlogo/nvm/Context I] [org/nlogo/nvm/Context I]
          PUTFIELD org/nlogo/nvm/Context.ip : I
         L7
          RETURN
[3]_asm_procedurego_setturtlevariable_3 "set energy energy - 1" Object => void
      _minus "energy - 1" double,double => double
        _turtlevariable:ENERGY "energy" => Object
        _constdouble:1.0 "1" => double
          TRYCATCHBLOCK L0 L1 L2 org/nlogo/api/AgentException
          TRYCATCHBLOCK L3 L4 L4 java/lang/ClassCastException
          TRYCATCHBLOCK L5 L6 L7 org/nlogo/api/AgentException
         L0
          ALOAD 1
          GETFIELD org/nlogo/nvm/Context.agent : Lorg/nlogo/agent/Agent;
          BIPUSH 13
          INVOKEVIRTUAL org/nlogo/agent/Agent.getTurtleVariable (I)Ljava/lang/Object;
         L1
          GOTO L8
         L2
         FRAME SAME1 org/nlogo/api/AgentException
          ASTORE 2
          NEW org/nlogo/nvm/RuntimePrimitiveException
          DUP
          ALOAD 1
          ALOAD 0
          ALOAD 2
          INVOKEVIRTUAL org/nlogo/api/AgentException.getMessage ()Ljava/lang/String;
          INVOKESPECIAL org/nlogo/nvm/RuntimePrimitiveException.<init> (Lorg/nlogo/api/Context;Lorg/nlogo/nvm/Instruction;Ljava/lang/String;)V
          ATHROW
         L8
         FRAME SAME1 java/lang/Object
          ASTORE 2
         L3
          ALOAD 2
          CHECKCAST java/lang/Double
          INVOKEVIRTUAL java/lang/Double.doubleValue ()D
          GOTO L9
         L4
         FRAME FULL [org/nlogo/prim/_asm_procedurego_setturtlevariable_3 org/nlogo/nvm/Context java/lang/Object] [java/lang/ClassCastException]
          POP
          NEW org/nlogo/nvm/ArgumentTypeException
          DUP
          ALOAD 1
          ALOAD 0
          BIPUSH 0
          LDC 1
          ALOAD 2
          INVOKESPECIAL org/nlogo/nvm/ArgumentTypeException.<init> (Lorg/nlogo/nvm/Context;Lorg/nlogo/nvm/Instruction;IILjava/lang/Object;)V
          ATHROW
         L9
         FRAME SAME1 D
          DCONST_1
         L10
          DSTORE 4
          DSTORE 2
          ALOAD 0
          DLOAD 2
          DLOAD 4
          DSUB
          INVOKEVIRTUAL org/nlogo/prim/_asm_procedurego_setturtlevariable_3.validDouble (D)D
         L11
          DSTORE 2
          NEW java/lang/Double
          DUP
          DLOAD 2
          INVOKESPECIAL java/lang/Double.<init> (D)V
          ASTORE 2
         L5
          ALOAD 1
          GETFIELD org/nlogo/nvm/Context.agent : Lorg/nlogo/agent/Agent;
          BIPUSH 13
          ALOAD 2
          INVOKEVIRTUAL org/nlogo/agent/Agent.setTurtleVariable (ILjava/lang/Object;)V
         L6
          GOTO L12
         L7
         FRAME FULL [org/nlogo/prim/_asm_procedurego_setturtlevariable_3 org/nlogo/nvm/Context java/lang/Double T D] [org/nlogo/api/AgentException]
          ASTORE 3
          NEW org/nlogo/nvm/RuntimePrimitiveException
          DUP
          ALOAD 1
          ALOAD 0
          ALOAD 3
          INVOKEVIRTUAL org/nlogo/api/AgentException.getMessage ()Ljava/lang/String;
          INVOKESPECIAL org/nlogo/nvm/RuntimePrimitiveException.<init> (Lorg/nlogo/api/Context;Lorg/nlogo/nvm/Instruction;Ljava/lang/String;)V
          ATHROW
         L12
         FRAME SAME
          ALOAD 1
          ICONST_4
          PUTFIELD org/nlogo/nvm/Context.ip : I
         L13
          RETURN
[4]_asm_procedurego_call_4 "eat-grass"
         L0
          NEW org/nlogo/nvm/Activation
          DUP
          ALOAD 0
          GETFIELD org/nlogo/prim/_asm_procedurego_call_4.kept1_procedure : Lorg/nlogo/nvm/Procedure;
          ALOAD 1
          GETFIELD org/nlogo/nvm/Context.activation : Lorg/nlogo/nvm/Activation;
          ICONST_5
          INVOKESPECIAL org/nlogo/nvm/Activation.<init> (Lorg/nlogo/nvm/Procedure;Lorg/nlogo/nvm/Activation;I)V
          ALOAD 1
          SWAP
          PUTFIELD org/nlogo/nvm/Context.activation : Lorg/nlogo/nvm/Activation;
          ALOAD 1
          ICONST_0
          PUTFIELD org/nlogo/nvm/Context.ip : I
         L1
          RETURN
[5]_asm_procedurego_call_5 "reproduce-sheep"
         L0
          NEW org/nlogo/nvm/Activation
          DUP
          ALOAD 0
          GETFIELD org/nlogo/prim/_asm_procedurego_call_5.kept1_procedure : Lorg/nlogo/nvm/Procedure;
          ALOAD 1
          GETFIELD org/nlogo/nvm/Context.activation : Lorg/nlogo/nvm/Activation;
          BIPUSH 6
          INVOKESPECIAL org/nlogo/nvm/Activation.<init> (Lorg/nlogo/nvm/Procedure;Lorg/nlogo/nvm/Activation;I)V
          ALOAD 1
          SWAP
          PUTFIELD org/nlogo/nvm/Context.activation : Lorg/nlogo/nvm/Activation;
          ALOAD 1
          ICONST_0
          PUTFIELD org/nlogo/nvm/Context.ip : I
         L1
          RETURN
[6]_asm_procedurego_call_6 "death"
         L0
          NEW org/nlogo/nvm/Activation
          DUP
          ALOAD 0
          GETFIELD org/nlogo/prim/_asm_procedurego_call_6.kept1_procedure : Lorg/nlogo/nvm/Procedure;
          ALOAD 1
          GETFIELD org/nlogo/nvm/Context.activation : Lorg/nlogo/nvm/Activation;
          BIPUSH 7
          INVOKESPECIAL org/nlogo/nvm/Activation.<init> (Lorg/nlogo/nvm/Procedure;Lorg/nlogo/nvm/Activation;I)V
          ALOAD 1
          SWAP
          PUTFIELD org/nlogo/nvm/Context.activation : Lorg/nlogo/nvm/Activation;
          ALOAD 1
          ICONST_0
          PUTFIELD org/nlogo/nvm/Context.ip : I
         L1
          RETURN
[7]_asm_procedurego_done_7 => void
          // parameter final  context
         L0
          ALOAD 1
          ICONST_1
          PUTFIELD org/nlogo/nvm/Context.finished : Z
         L1
          RETURN
[8]_asm_procedurego_ask_8 "ask wolves move set energy energy - 1 catch-sheep reproduce-wolves [ death ]" AgentSet => void
      _breed:WOLVES "wolves" => AgentSet
          // parameter final  context
         L0
          ALOAD 0
          GETFIELD org/nlogo/prim/_asm_procedurego_ask_8.world : Lorg/nlogo/agent/World;
          LDC "WOLVES"
          INVOKEVIRTUAL org/nlogo/agent/World.getBreed (Ljava/lang/String;)Lorg/nlogo/agent/AgentSet;
         L1
          ASTORE 2
          ALOAD 1
          GETFIELD org/nlogo/nvm/Context.agent : Lorg/nlogo/agent/Agent;
          INSTANCEOF org/nlogo/agent/Observer
          IFNE L2
          ALOAD 2
          ALOAD 0
          GETFIELD org/nlogo/prim/_asm_procedurego_ask_8.world : Lorg/nlogo/agent/World;
          INVOKEVIRTUAL org/nlogo/agent/World.turtles ()Lorg/nlogo/agent/TreeAgentSet;
          IF_ACMPNE L3
          NEW org/nlogo/nvm/RuntimePrimitiveException
          DUP
          ALOAD 1
          ALOAD 0
          INVOKESTATIC org/nlogo/core/I18N.errorsJ ()Lorg/nlogo/core/I18NJava;
          LDC "org.nlogo.prim.$common.onlyObserverCanAskAllTurtles"
          INVOKEINTERFACE org/nlogo/core/I18NJava.get (Ljava/lang/String;)Ljava/lang/String;
          INVOKESPECIAL org/nlogo/nvm/RuntimePrimitiveException.<init> (Lorg/nlogo/api/Context;Lorg/nlogo/nvm/Instruction;Ljava/lang/String;)V
          ATHROW
         L3
         FRAME APPEND [org/nlogo/agent/AgentSet]
          ALOAD 2
          ALOAD 0
          GETFIELD org/nlogo/prim/_asm_procedurego_ask_8.world : Lorg/nlogo/agent/World;
          INVOKEVIRTUAL org/nlogo/agent/World.patches ()Lorg/nlogo/agent/AgentSet;
          IF_ACMPNE L2
          NEW org/nlogo/nvm/RuntimePrimitiveException
          DUP
          ALOAD 1
          ALOAD 0
          INVOKESTATIC org/nlogo/core/I18N.errorsJ ()Lorg/nlogo/core/I18NJava;
          LDC "org.nlogo.prim.$common.onlyObserverCanAskAllPatches"
          INVOKEINTERFACE org/nlogo/core/I18NJava.get (Ljava/lang/String;)Ljava/lang/String;
          INVOKESPECIAL org/nlogo/nvm/RuntimePrimitiveException.<init> (Lorg/nlogo/api/Context;Lorg/nlogo/nvm/Instruction;Ljava/lang/String;)V
          ATHROW
         L2
         FRAME SAME
          ALOAD 1
          ALOAD 2
          BIPUSH 9
          INVOKEVIRTUAL org/nlogo/nvm/Context.runExclusiveJob (Lorg/nlogo/agent/AgentSet;I)V
          ALOAD 1
          BIPUSH 15
          PUTFIELD org/nlogo/nvm/Context.ip : I
         L4
          RETURN
[9]_asm_procedurego_call_9 "move"
         L0
          NEW org/nlogo/nvm/Activation
          DUP
          ALOAD 0
          GETFIELD org/nlogo/prim/_asm_procedurego_call_9.kept1_procedure : Lorg/nlogo/nvm/Procedure;
          ALOAD 1
          GETFIELD org/nlogo/nvm/Context.activation : Lorg/nlogo/nvm/Activation;
          BIPUSH 10
          INVOKESPECIAL org/nlogo/nvm/Activation.<init> (Lorg/nlogo/nvm/Procedure;Lorg/nlogo/nvm/Activation;I)V
          ALOAD 1
          SWAP
          PUTFIELD org/nlogo/nvm/Context.activation : Lorg/nlogo/nvm/Activation;
          ALOAD 1
          ICONST_0
          PUTFIELD org/nlogo/nvm/Context.ip : I
         L1
          RETURN
[10]_asm_procedurego_setturtlevariable_10 "set energy energy - 1" Object => void
      _minus "energy - 1" double,double => double
        _turtlevariable:ENERGY "energy" => Object
        _constdouble:1.0 "1" => double
          TRYCATCHBLOCK L0 L1 L2 org/nlogo/api/AgentException
          TRYCATCHBLOCK L3 L4 L4 java/lang/ClassCastException
          TRYCATCHBLOCK L5 L6 L7 org/nlogo/api/AgentException
         L0
          ALOAD 1
          GETFIELD org/nlogo/nvm/Context.agent : Lorg/nlogo/agent/Agent;
          BIPUSH 13
          INVOKEVIRTUAL org/nlogo/agent/Agent.getTurtleVariable (I)Ljava/lang/Object;
         L1
          GOTO L8
         L2
         FRAME SAME1 org/nlogo/api/AgentException
          ASTORE 2
          NEW org/nlogo/nvm/RuntimePrimitiveException
          DUP
          ALOAD 1
          ALOAD 0
          ALOAD 2
          INVOKEVIRTUAL org/nlogo/api/AgentException.getMessage ()Ljava/lang/String;
          INVOKESPECIAL org/nlogo/nvm/RuntimePrimitiveException.<init> (Lorg/nlogo/api/Context;Lorg/nlogo/nvm/Instruction;Ljava/lang/String;)V
          ATHROW
         L8
         FRAME SAME1 java/lang/Object
          ASTORE 2
         L3
          ALOAD 2
          CHECKCAST java/lang/Double
          INVOKEVIRTUAL java/lang/Double.doubleValue ()D
          GOTO L9
         L4
         FRAME FULL [org/nlogo/prim/_asm_procedurego_setturtlevariable_10 org/nlogo/nvm/Context java/lang/Object] [java/lang/ClassCastException]
          POP
          NEW org/nlogo/nvm/ArgumentTypeException
          DUP
          ALOAD 1
          ALOAD 0
          BIPUSH 0
          LDC 1
          ALOAD 2
          INVOKESPECIAL org/nlogo/nvm/ArgumentTypeException.<init> (Lorg/nlogo/nvm/Context;Lorg/nlogo/nvm/Instruction;IILjava/lang/Object;)V
          ATHROW
         L9
         FRAME SAME1 D
          DCONST_1
         L10
          DSTORE 4
          DSTORE 2
          ALOAD 0
          DLOAD 2
          DLOAD 4
          DSUB
          INVOKEVIRTUAL org/nlogo/prim/_asm_procedurego_setturtlevariable_10.validDouble (D)D
         L11
          DSTORE 2
          NEW java/lang/Double
          DUP
          DLOAD 2
          INVOKESPECIAL java/lang/Double.<init> (D)V
          ASTORE 2
         L5
          ALOAD 1
          GETFIELD org/nlogo/nvm/Context.agent : Lorg/nlogo/agent/Agent;
          BIPUSH 13
          ALOAD 2
          INVOKEVIRTUAL org/nlogo/agent/Agent.setTurtleVariable (ILjava/lang/Object;)V
         L6
          GOTO L12
         L7
         FRAME FULL [org/nlogo/prim/_asm_procedurego_setturtlevariable_10 org/nlogo/nvm/Context java/lang/Double T D] [org/nlogo/api/AgentException]
          ASTORE 3
          NEW org/nlogo/nvm/RuntimePrimitiveException
          DUP
          ALOAD 1
          ALOAD 0
          ALOAD 3
          INVOKEVIRTUAL org/nlogo/api/AgentException.getMessage ()Ljava/lang/String;
          INVOKESPECIAL org/nlogo/nvm/RuntimePrimitiveException.<init> (Lorg/nlogo/api/Context;Lorg/nlogo/nvm/Instruction;Ljava/lang/String;)V
          ATHROW
         L12
         FRAME SAME
          ALOAD 1
          BIPUSH 11
          PUTFIELD org/nlogo/nvm/Context.ip : I
         L13
          RETURN
[11]_asm_procedurego_call_11 "catch-sheep"
         L0
          NEW org/nlogo/nvm/Activation
          DUP
          ALOAD 0
          GETFIELD org/nlogo/prim/_asm_procedurego_call_11.kept1_procedure : Lorg/nlogo/nvm/Procedure;
          ALOAD 1
          GETFIELD org/nlogo/nvm/Context.activation : Lorg/nlogo/nvm/Activation;
          BIPUSH 12
          INVOKESPECIAL org/nlogo/nvm/Activation.<init> (Lorg/nlogo/nvm/Procedure;Lorg/nlogo/nvm/Activation;I)V
          ALOAD 1
          SWAP
          PUTFIELD org/nlogo/nvm/Context.activation : Lorg/nlogo/nvm/Activation;
          ALOAD 1
          ICONST_0
          PUTFIELD org/nlogo/nvm/Context.ip : I
         L1
          RETURN
[12]_asm_procedurego_call_12 "reproduce-wolves"
         L0
          NEW org/nlogo/nvm/Activation
          DUP
          ALOAD 0
          GETFIELD org/nlogo/prim/_asm_procedurego_call_12.kept1_procedure : Lorg/nlogo/nvm/Procedure;
          ALOAD 1
          GETFIELD org/nlogo/nvm/Context.activation : Lorg/nlogo/nvm/Activation;
          BIPUSH 13
          INVOKESPECIAL org/nlogo/nvm/Activation.<init> (Lorg/nlogo/nvm/Procedure;Lorg/nlogo/nvm/Activation;I)V
          ALOAD 1
          SWAP
          PUTFIELD org/nlogo/nvm/Context.activation : Lorg/nlogo/nvm/Activation;
          ALOAD 1
          ICONST_0
          PUTFIELD org/nlogo/nvm/Context.ip : I
         L1
          RETURN
[13]_asm_procedurego_call_13 "death"
         L0
          NEW org/nlogo/nvm/Activation
          DUP
          ALOAD 0
          GETFIELD org/nlogo/prim/_asm_procedurego_call_13.kept1_procedure : Lorg/nlogo/nvm/Procedure;
          ALOAD 1
          GETFIELD org/nlogo/nvm/Context.activation : Lorg/nlogo/nvm/Activation;
          BIPUSH 14
          INVOKESPECIAL org/nlogo/nvm/Activation.<init> (Lorg/nlogo/nvm/Procedure;Lorg/nlogo/nvm/Activation;I)V
          ALOAD 1
          SWAP
          PUTFIELD org/nlogo/nvm/Context.activation : Lorg/nlogo/nvm/Activation;
          ALOAD 1
          ICONST_0
          PUTFIELD org/nlogo/nvm/Context.ip : I
         L1
          RETURN
[14]_asm_procedurego_done_14 => void
          // parameter final  context
         L0
          ALOAD 1
          ICONST_1
          PUTFIELD org/nlogo/nvm/Context.finished : Z
         L1
          RETURN
[15]_asm_procedurego_if_15 "if grass? [ ask patches [ grow-grass ] ]" boolean => void
      _observervariable:GRASS? "grass?" => Object
          TRYCATCHBLOCK L0 L1 L1 java/lang/ClassCastException
         L2
          ALOAD 1
          GETFIELD org/nlogo/nvm/Context.agent : Lorg/nlogo/agent/Agent;
          BIPUSH 6
          INVOKEVIRTUAL org/nlogo/agent/Agent.getObserverVariable (I)Ljava/lang/Object;
         L3
          ASTORE 2
         L0
          ALOAD 2
          CHECKCAST java/lang/Boolean
          INVOKEVIRTUAL java/lang/Boolean.booleanValue ()Z
          GOTO L4
         L1
         FRAME FULL [org/nlogo/prim/_asm_procedurego_if_15 org/nlogo/nvm/Context java/lang/Object] [java/lang/ClassCastException]
          POP
          NEW org/nlogo/nvm/ArgumentTypeException
          DUP
          ALOAD 1
          ALOAD 0
          BIPUSH 0
          LDC 2
          ALOAD 2
          INVOKESPECIAL org/nlogo/nvm/ArgumentTypeException.<init> (Lorg/nlogo/nvm/Context;Lorg/nlogo/nvm/Instruction;IILjava/lang/Object;)V
          ATHROW
         L4
         FRAME SAME1 I
          ISTORE 2
          ALOAD 1
          ILOAD 2
          IFEQ L5
          BIPUSH 16
          GOTO L6
         L5
         FRAME FULL [org/nlogo/prim/_asm_procedurego_if_15 org/nlogo/nvm/Context I] [org/nlogo/nvm/Context]
          BIPUSH 19
         L6
         FRAME FULL [org/nlogo/prim/_asm_procedurego_if_15 org/nlogo/nvm/Context I] [org/nlogo/nvm/Context I]
          PUTFIELD org/nlogo/nvm/Context.ip : I
         L7
          RETURN
[16]_asm_procedurego_ask_16 "ask patches [ grow-grass ]" AgentSet => void
      _patches "patches" => AgentSet
          // parameter final  context
         L0
          ALOAD 0
          GETFIELD org/nlogo/prim/_asm_procedurego_ask_16.world : Lorg/nlogo/agent/World;
          INVOKEVIRTUAL org/nlogo/agent/World.patches ()Lorg/nlogo/agent/AgentSet;
         L1
          ASTORE 2
          ALOAD 1
          GETFIELD org/nlogo/nvm/Context.agent : Lorg/nlogo/agent/Agent;
          INSTANCEOF org/nlogo/agent/Observer
          IFNE L2
          ALOAD 2
          ALOAD 0
          GETFIELD org/nlogo/prim/_asm_procedurego_ask_16.world : Lorg/nlogo/agent/World;
          INVOKEVIRTUAL org/nlogo/agent/World.turtles ()Lorg/nlogo/agent/TreeAgentSet;
          IF_ACMPNE L3
          NEW org/nlogo/nvm/RuntimePrimitiveException
          DUP
          ALOAD 1
          ALOAD 0
          INVOKESTATIC org/nlogo/core/I18N.errorsJ ()Lorg/nlogo/core/I18NJava;
          LDC "org.nlogo.prim.$common.onlyObserverCanAskAllTurtles"
          INVOKEINTERFACE org/nlogo/core/I18NJava.get (Ljava/lang/String;)Ljava/lang/String;
          INVOKESPECIAL org/nlogo/nvm/RuntimePrimitiveException.<init> (Lorg/nlogo/api/Context;Lorg/nlogo/nvm/Instruction;Ljava/lang/String;)V
          ATHROW
         L3
         FRAME APPEND [org/nlogo/agent/AgentSet]
          ALOAD 2
          ALOAD 0
          GETFIELD org/nlogo/prim/_asm_procedurego_ask_16.world : Lorg/nlogo/agent/World;
          INVOKEVIRTUAL org/nlogo/agent/World.patches ()Lorg/nlogo/agent/AgentSet;
          IF_ACMPNE L2
          NEW org/nlogo/nvm/RuntimePrimitiveException
          DUP
          ALOAD 1
          ALOAD 0
          INVOKESTATIC org/nlogo/core/I18N.errorsJ ()Lorg/nlogo/core/I18NJava;
          LDC "org.nlogo.prim.$common.onlyObserverCanAskAllPatches"
          INVOKEINTERFACE org/nlogo/core/I18NJava.get (Ljava/lang/String;)Ljava/lang/String;
          INVOKESPECIAL org/nlogo/nvm/RuntimePrimitiveException.<init> (Lorg/nlogo/api/Context;Lorg/nlogo/nvm/Instruction;Ljava/lang/String;)V
          ATHROW
         L2
         FRAME SAME
          ALOAD 1
          ALOAD 2
          BIPUSH 17
          INVOKEVIRTUAL org/nlogo/nvm/Context.runExclusiveJob (Lorg/nlogo/agent/AgentSet;I)V
          ALOAD 1
          BIPUSH 19
          PUTFIELD org/nlogo/nvm/Context.ip : I
         L4
          RETURN
[17]_asm_procedurego_call_17 "grow-grass"
         L0
          NEW org/nlogo/nvm/Activation
          DUP
          ALOAD 0
          GETFIELD org/nlogo/prim/_asm_procedurego_call_17.kept1_procedure : Lorg/nlogo/nvm/Procedure;
          ALOAD 1
          GETFIELD org/nlogo/nvm/Context.activation : Lorg/nlogo/nvm/Activation;
          BIPUSH 18
          INVOKESPECIAL org/nlogo/nvm/Activation.<init> (Lorg/nlogo/nvm/Procedure;Lorg/nlogo/nvm/Activation;I)V
          ALOAD 1
          SWAP
          PUTFIELD org/nlogo/nvm/Context.activation : Lorg/nlogo/nvm/Activation;
          ALOAD 1
          ICONST_0
          PUTFIELD org/nlogo/nvm/Context.ip : I
         L1
          RETURN
[18]_asm_procedurego_done_18 => void
          // parameter final  context
         L0
          ALOAD 1
          ICONST_1
          PUTFIELD org/nlogo/nvm/Context.finished : Z
         L1
          RETURN
[19]_asm_procedurego_if_19 "if plot? [ graph ]" boolean => void
      _observervariable:PLOT? "plot?" => Object
          TRYCATCHBLOCK L0 L1 L1 java/lang/ClassCastException
         L2
          ALOAD 1
          GETFIELD org/nlogo/nvm/Context.agent : Lorg/nlogo/agent/Agent;
          BIPUSH 8
          INVOKEVIRTUAL org/nlogo/agent/Agent.getObserverVariable (I)Ljava/lang/Object;
         L3
          ASTORE 2
         L0
          ALOAD 2
          CHECKCAST java/lang/Boolean
          INVOKEVIRTUAL java/lang/Boolean.booleanValue ()Z
          GOTO L4
         L1
         FRAME FULL [org/nlogo/prim/_asm_procedurego_if_19 org/nlogo/nvm/Context java/lang/Object] [java/lang/ClassCastException]
          POP
          NEW org/nlogo/nvm/ArgumentTypeException
          DUP
          ALOAD 1
          ALOAD 0
          BIPUSH 0
          LDC 2
          ALOAD 2
          INVOKESPECIAL org/nlogo/nvm/ArgumentTypeException.<init> (Lorg/nlogo/nvm/Context;Lorg/nlogo/nvm/Instruction;IILjava/lang/Object;)V
          ATHROW
         L4
         FRAME SAME1 I
          ISTORE 2
          ALOAD 1
          ILOAD 2
          IFEQ L5
          BIPUSH 20
          GOTO L6
         L5
         FRAME FULL [org/nlogo/prim/_asm_procedurego_if_19 org/nlogo/nvm/Context I] [org/nlogo/nvm/Context]
          BIPUSH 21
         L6
         FRAME FULL [org/nlogo/prim/_asm_procedurego_if_19 org/nlogo/nvm/Context I] [org/nlogo/nvm/Context I]
          PUTFIELD org/nlogo/nvm/Context.ip : I
         L7
          RETURN
[20]_asm_procedurego_call_20 "graph"
         L0
          NEW org/nlogo/nvm/Activation
          DUP
          ALOAD 0
          GETFIELD org/nlogo/prim/_asm_procedurego_call_20.kept1_procedure : Lorg/nlogo/nvm/Procedure;
          ALOAD 1
          GETFIELD org/nlogo/nvm/Context.activation : Lorg/nlogo/nvm/Activation;
          BIPUSH 21
          INVOKESPECIAL org/nlogo/nvm/Activation.<init> (Lorg/nlogo/nvm/Procedure;Lorg/nlogo/nvm/Activation;I)V
          ALOAD 1
          SWAP
          PUTFIELD org/nlogo/nvm/Context.activation : Lorg/nlogo/nvm/Activation;
          ALOAD 1
          ICONST_0
          PUTFIELD org/nlogo/nvm/Context.ip : I
         L1
          RETURN
[21]_tick "tick"
[22]_asm_procedurego_if_21 "if count turtles = 0 [ stop ]" boolean => void
      _equal "count turtles = 0" double,double => boolean
        _count "count turtles" AgentSet => double
          _turtles "turtles" => AgentSet
        _constdouble:0.0 "0" => double
          // parameter final  context
         L0
          ALOAD 0
          GETFIELD org/nlogo/prim/_asm_procedurego_if_21.world : Lorg/nlogo/agent/World;
          INVOKEVIRTUAL org/nlogo/agent/World.turtles ()Lorg/nlogo/agent/TreeAgentSet;
         L1
          ASTORE 2
          ALOAD 2
          INVOKEVIRTUAL org/nlogo/agent/AgentSet.count ()I
          I2D
         L2
          DCONST_0
         L3
          DSTORE 4
          DSTORE 2
          DLOAD 2
          DLOAD 4
          DCMPL
          IFNE L4
          ICONST_1
          GOTO L5
         L4
         FRAME APPEND [D D]
          ICONST_0
         L5
         FRAME SAME1 I
          ISTORE 2
          ALOAD 1
          ILOAD 2
          IFEQ L6
          BIPUSH 23
          GOTO L7
         L6
         FRAME FULL [org/nlogo/prim/_asm_procedurego_if_21 org/nlogo/nvm/Context I T D] [org/nlogo/nvm/Context]
          BIPUSH 24
         L7
         FRAME FULL [org/nlogo/prim/_asm_procedurego_if_21 org/nlogo/nvm/Context I T D] [org/nlogo/nvm/Context I]
          PUTFIELD org/nlogo/nvm/Context.ip : I
         L8
          RETURN
[23]_asm_procedurego_stop_22 "stop" => void
         L0
          ALOAD 1
          INVOKEVIRTUAL org/nlogo/nvm/Context.atTopActivation ()Z
          IFNE L1
          ALOAD 1
          ICONST_1
          PUTFIELD org/nlogo/nvm/Context.finished : Z
          GOTO L2
         L1
         FRAME SAME
          ALOAD 1
          GETFIELD org/nlogo/nvm/Context.activation : Lorg/nlogo/nvm/Activation;
          INVOKEVIRTUAL org/nlogo/nvm/Activation.nonLambdaActivation ()Lorg/nlogo/nvm/Activation;
          GETFIELD org/nlogo/nvm/Activation.procedure : Lorg/nlogo/nvm/Procedure;
          INVOKEVIRTUAL org/nlogo/nvm/Procedure.isReporter ()Z
          IFEQ L2
          NEW org/nlogo/nvm/RuntimePrimitiveException
          DUP
          ALOAD 1
          ALOAD 0
          INVOKESTATIC org/nlogo/core/I18N.errorsJ ()Lorg/nlogo/core/I18NJava;
          LDC "org.nlogo.prim.etc._stop.notAllowedInsideToReport"
          ICONST_1
          ANEWARRAY java/lang/Object
          DUP
          ICONST_0
          LDC "STOP"
          AASTORE
          INVOKEINTERFACE org/nlogo/core/I18NJava.getN (Ljava/lang/String;[Ljava/lang/Object;)Ljava/lang/String;
          INVOKESPECIAL org/nlogo/nvm/RuntimePrimitiveException.<init> (Lorg/nlogo/api/Context;Lorg/nlogo/nvm/Instruction;Ljava/lang/String;)V
          ATHROW
         L2
         FRAME SAME
          ALOAD 1
          INVOKEVIRTUAL org/nlogo/nvm/Context.stop ()V
         L3
          RETURN
[24]_asm_procedurego_return_23 => void
         L0
          ALOAD 1
          INVOKEVIRTUAL org/nlogo/nvm/Context.returnFromProcedure ()V
          ALOAD 1
          ICONST_0
          PUTFIELD org/nlogo/nvm/Context.stopping : Z
         L1
          RETURN

procedure GRAPH:[]{OTPL}:
[0]_setcurrentplotpen "set-current-plot-pen "sheep""
      _asm_proceduregraph_conststring_0 ""sheep"" => String
           L0
            LDC "sheep"
           L1
            ARETURN
[1]_plot "plot count sheep"
      _asm_proceduregraph_count_1 "count sheep" AgentSet => double
        _breed:SHEEP "sheep" => AgentSet
            // parameter final  context
           L0
            ALOAD 0
            GETFIELD org/nlogo/prim/_asm_proceduregraph_count_1.world : Lorg/nlogo/agent/World;
            LDC "SHEEP"
            INVOKEVIRTUAL org/nlogo/agent/World.getBreed (Ljava/lang/String;)Lorg/nlogo/agent/AgentSet;
           L1
            ASTORE 2
            ALOAD 2
            INVOKEVIRTUAL org/nlogo/agent/AgentSet.count ()I
            I2D
           L2
            DSTORE 2
            NEW java/lang/Double
            DUP
            DLOAD 2
            INVOKESPECIAL java/lang/Double.<init> (D)V
            ARETURN
[2]_setcurrentplotpen "set-current-plot-pen "wolves""
      _asm_proceduregraph_conststring_2 ""wolves"" => String
           L0
            LDC "wolves"
           L1
            ARETURN
[3]_plot "plot count wolves"
      _asm_proceduregraph_count_3 "count wolves" AgentSet => double
        _breed:WOLVES "wolves" => AgentSet
            // parameter final  context
           L0
            ALOAD 0
            GETFIELD org/nlogo/prim/_asm_proceduregraph_count_3.world : Lorg/nlogo/agent/World;
            LDC "WOLVES"
            INVOKEVIRTUAL org/nlogo/agent/World.getBreed (Ljava/lang/String;)Lorg/nlogo/agent/AgentSet;
           L1
            ASTORE 2
            ALOAD 2
            INVOKEVIRTUAL org/nlogo/agent/AgentSet.count ()I
            I2D
           L2
            DSTORE 2
            NEW java/lang/Double
            DUP
            DLOAD 2
            INVOKESPECIAL java/lang/Double.<init> (D)V
            ARETURN
[4]_asm_proceduregraph_if_4 "if grass? set-current-plot-pen "grass / 4" [ plot count patches with [ pcolor = green ] / 4 ]" boolean => void
      _observervariable:GRASS? "grass?" => Object
          TRYCATCHBLOCK L0 L1 L1 java/lang/ClassCastException
         L2
          ALOAD 1
          GETFIELD org/nlogo/nvm/Context.agent : Lorg/nlogo/agent/Agent;
          BIPUSH 6
          INVOKEVIRTUAL org/nlogo/agent/Agent.getObserverVariable (I)Ljava/lang/Object;
         L3
          ASTORE 2
         L0
          ALOAD 2
          CHECKCAST java/lang/Boolean
          INVOKEVIRTUAL java/lang/Boolean.booleanValue ()Z
          GOTO L4
         L1
         FRAME FULL [org/nlogo/prim/_asm_proceduregraph_if_4 org/nlogo/nvm/Context java/lang/Object] [java/lang/ClassCastException]
          POP
          NEW org/nlogo/nvm/ArgumentTypeException
          DUP
          ALOAD 1
          ALOAD 0
          BIPUSH 0
          LDC 2
          ALOAD 2
          INVOKESPECIAL org/nlogo/nvm/ArgumentTypeException.<init> (Lorg/nlogo/nvm/Context;Lorg/nlogo/nvm/Instruction;IILjava/lang/Object;)V
          ATHROW
         L4
         FRAME SAME1 I
          ISTORE 2
          ALOAD 1
          ILOAD 2
          IFEQ L5
          ICONST_5
          GOTO L6
         L5
         FRAME FULL [org/nlogo/prim/_asm_proceduregraph_if_4 org/nlogo/nvm/Context I] [org/nlogo/nvm/Context]
          BIPUSH 7
         L6
         FRAME FULL [org/nlogo/prim/_asm_proceduregraph_if_4 org/nlogo/nvm/Context I] [org/nlogo/nvm/Context I]
          PUTFIELD org/nlogo/nvm/Context.ip : I
         L7
          RETURN
[5]_setcurrentplotpen "set-current-plot-pen "grass / 4""
      _asm_proceduregraph_conststring_5 ""grass / 4"" => String
           L0
            LDC "grass / 4"
           L1
            ARETURN
[6]_plot "plot count patches with [ pcolor = green ] / 4"
      _asm_proceduregraph_div_6 "count patches with [ pcolor = green ] / 4" double,double => double
        _countwith "count patches with [ pcolor = green ]" AgentSet,Reporter => double
          _patches "patches" => AgentSet
          _asm_proceduregraph_equal_7 "pcolor = green" Object,double => boolean
            _patchvariable:PCOLOR "pcolor" => Object
            _constdouble:55.0 "green" => double
                // parameter final  context
                TRYCATCHBLOCK L0 L1 L2 org/nlogo/api/AgentException
               L0
                ALOAD 1
                GETFIELD org/nlogo/nvm/Context.agent : Lorg/nlogo/agent/Agent;
                ICONST_2
                INVOKEVIRTUAL org/nlogo/agent/Agent.getPatchVariable (I)Ljava/lang/Object;
               L1
                GOTO L3
               L2
               FRAME SAME1 org/nlogo/api/AgentException
                ASTORE 2
                NEW org/nlogo/nvm/RuntimePrimitiveException
                DUP
                ALOAD 1
                ALOAD 0
                ALOAD 2
                INVOKEVIRTUAL org/nlogo/api/AgentException.getMessage ()Ljava/lang/String;
                INVOKESPECIAL org/nlogo/nvm/RuntimePrimitiveException.<init> (Lorg/nlogo/api/Context;Lorg/nlogo/nvm/Instruction;Ljava/lang/String;)V
                ATHROW
               L3
               FRAME SAME1 java/lang/Object
                LDC 55.0
               L4
                DSTORE 3
                ASTORE 2
                ALOAD 2
                INSTANCEOF java/lang/Double
                IFEQ L5
                DLOAD 3
                ALOAD 2
                CHECKCAST java/lang/Double
                INVOKEVIRTUAL java/lang/Double.doubleValue ()D
                DCMPL
                IFNE L5
                ICONST_1
                GOTO L6
               L5
               FRAME APPEND [java/lang/Object D]
                ICONST_0
               L6
               FRAME SAME1 I
                IFEQ L7
                GETSTATIC java/lang/Boolean.TRUE : Ljava/lang/Boolean;
                GOTO L8
               L7
               FRAME SAME
                GETSTATIC java/lang/Boolean.FALSE : Ljava/lang/Boolean;
               L8
               FRAME SAME1 java/lang/Boolean
                ARETURN
        _constdouble:4.0 "4" => double
            // parameter final  context
           L0
            ALOAD 0
            GETFIELD org/nlogo/prim/_asm_proceduregraph_div_6.world : Lorg/nlogo/agent/World;
            INVOKEVIRTUAL org/nlogo/agent/World.patches ()Lorg/nlogo/agent/AgentSet;
           L1
            ALOAD 0
            GETFIELD org/nlogo/prim/_asm_proceduregraph_div_6.keptinstr4 : Lorg/nlogo/nvm/Reporter;
            ASTORE 3
            ASTORE 2
            ALOAD 3
            ALOAD 2
            ALOAD 1
            INVOKEVIRTUAL org/nlogo/nvm/Reporter.checkAgentSetClass (Lorg/nlogo/agent/AgentSet;Lorg/nlogo/nvm/Context;)V
            NEW org/nlogo/nvm/Context
            DUP
            ALOAD 1
            ALOAD 2
            INVOKESPECIAL org/nlogo/nvm/Context.<init> (Lorg/nlogo/nvm/Context;Lorg/nlogo/agent/AgentSet;)V
            ASTORE 4
            ICONST_0
            ISTORE 5
            ALOAD 2
            INVOKEVIRTUAL org/nlogo/agent/AgentSet.iterator ()Lorg/nlogo/agent/AgentIterator;
            ASTORE 6
           L2
           FRAME FULL [org/nlogo/prim/_asm_proceduregraph_div_6 org/nlogo/nvm/Context org/nlogo/agent/AgentSet org/nlogo/nvm/Reporter org/nlogo/nvm/Context I org/nlogo/agent/AgentIterator] []
            ALOAD 6
            INVOKEINTERFACE org/nlogo/agent/AgentIterator.hasNext ()Z
            IFEQ L3
            ALOAD 6
            INVOKEINTERFACE org/nlogo/agent/AgentIterator.next ()Lorg/nlogo/agent/Agent;
            ASTORE 7
            ALOAD 4
            ALOAD 7
            ALOAD 3
            INVOKEVIRTUAL org/nlogo/nvm/Context.evaluateReporter (Lorg/nlogo/agent/Agent;Lorg/nlogo/nvm/Reporter;)Ljava/lang/Object;
            ASTORE 8
            ALOAD 8
            INSTANCEOF java/lang/Boolean
            IFNE L4
            NEW org/nlogo/nvm/RuntimePrimitiveException
            DUP
            ALOAD 1
            ALOAD 0
            INVOKESTATIC org/nlogo/core/I18N.errorsJ ()Lorg/nlogo/core/I18NJava;
            LDC "org.nlogo.prim.$common.expectedBooleanValue"
            ICONST_3
            ANEWARRAY java/lang/Object
            DUP
            ICONST_0
            LDC "COUNT"
            AASTORE
            DUP
            ICONST_1
            ALOAD 7
            INVOKESTATIC org/nlogo/api/Dump.logoObject (Ljava/lang/Object;)Ljava/lang/String;
            AASTORE
            DUP
            ICONST_2
            ALOAD 8
            INVOKESTATIC org/nlogo/api/Dump.logoObject (Ljava/lang/Object;)Ljava/lang/String;
            AASTORE
            INVOKEINTERFACE org/nlogo/core/I18NJava.getN (Ljava/lang/String;[Ljava/lang/Object;)Ljava/lang/String;
            INVOKESPECIAL org/nlogo/nvm/RuntimePrimitiveException.<init> (Lorg/nlogo/api/Context;Lorg/nlogo/nvm/Instruction;Ljava/lang/String;)V
            ATHROW
           L4
           FRAME APPEND [org/nlogo/agent/Agent java/lang/Object]
            ALOAD 8
            CHECKCAST java/lang/Boolean
            INVOKEVIRTUAL java/lang/Boolean.booleanValue ()Z
            IFEQ L5
            IINC 5 1
           L5
           FRAME SAME
            GOTO L2
           L3
           FRAME CHOP 2
            ILOAD 5
            I2D
           L6
            LDC 4.0
           L7
            DSTORE 4
            DSTORE 2
            DLOAD 4
            DCONST_0
            DCMPL
            IFNE L8
            NEW org/nlogo/nvm/RuntimePrimitiveException
            DUP
            ALOAD 1
            ALOAD 0
            INVOKESTATIC org/nlogo/core/I18N.errorsJ ()Lorg/nlogo/core/I18NJava;
            LDC "org.nlogo.prim.etc.$common.divByZero"
            INVOKEINTERFACE org/nlogo/core/I18NJava.get (Ljava/lang/String;)Ljava/lang/String;
            INVOKESPECIAL org/nlogo/nvm/RuntimePrimitiveException.<init> (Lorg/nlogo/api/Context;Lorg/nlogo/nvm/Instruction;Ljava/lang/String;)V
            ATHROW
           L8
           FRAME FULL [org/nlogo/prim/_asm_proceduregraph_div_6 org/nlogo/nvm/Context D D org/nlogo/agent/AgentIterator] []
            ALOAD 0
            DLOAD 2
            DLOAD 4
            DDIV
            INVOKEVIRTUAL org/nlogo/prim/_asm_proceduregraph_div_6.validDouble (D)D
           L9
            DSTORE 2
            NEW java/lang/Double
            DUP
            DLOAD 2
            INVOKESPECIAL java/lang/Double.<init> (D)V
            ARETURN
[7]_asm_proceduregraph_return_8 => void
         L0
          ALOAD 1
          INVOKEVIRTUAL org/nlogo/nvm/Context.returnFromProcedure ()V
          ALOAD 1
          ICONST_0
          PUTFIELD org/nlogo/nvm/Context.stopping : Z
         L1
          RETURN

procedure GROW-GRASS:[]{-TP-}:
[0]_asm_proceduregrowgrass_if_0 "if pcolor = brown [ ifelse countdown <= 0 set pcolor green [ set countdown grass-delay ] [ set countdown countdown - 1 ] ]" boolean => void
      _equal "pcolor = brown" Object,double => boolean
        _patchvariable:PCOLOR "pcolor" => Object
        _constdouble:35.0 "brown" => double
          // parameter final  context
          TRYCATCHBLOCK L0 L1 L2 org/nlogo/api/AgentException
         L0
          ALOAD 1
          GETFIELD org/nlogo/nvm/Context.agent : Lorg/nlogo/agent/Agent;
          ICONST_2
          INVOKEVIRTUAL org/nlogo/agent/Agent.getPatchVariable (I)Ljava/lang/Object;
         L1
          GOTO L3
         L2
         FRAME SAME1 org/nlogo/api/AgentException
          ASTORE 2
          NEW org/nlogo/nvm/RuntimePrimitiveException
          DUP
          ALOAD 1
          ALOAD 0
          ALOAD 2
          INVOKEVIRTUAL org/nlogo/api/AgentException.getMessage ()Ljava/lang/String;
          INVOKESPECIAL org/nlogo/nvm/RuntimePrimitiveException.<init> (Lorg/nlogo/api/Context;Lorg/nlogo/nvm/Instruction;Ljava/lang/String;)V
          ATHROW
         L3
         FRAME SAME1 java/lang/Object
          LDC 35.0
         L4
          DSTORE 3
          ASTORE 2
          ALOAD 2
          INSTANCEOF java/lang/Double
          IFEQ L5
          DLOAD 3
          ALOAD 2
          CHECKCAST java/lang/Double
          INVOKEVIRTUAL java/lang/Double.doubleValue ()D
          DCMPL
          IFNE L5
          ICONST_1
          GOTO L6
         L5
         FRAME APPEND [java/lang/Object D]
          ICONST_0
         L6
         FRAME SAME1 I
          ISTORE 2
          ALOAD 1
          ILOAD 2
          IFEQ L7
          ICONST_1
          GOTO L8
         L7
         FRAME FULL [org/nlogo/prim/_asm_proceduregrowgrass_if_0 org/nlogo/nvm/Context I D] [org/nlogo/nvm/Context]
          BIPUSH 6
         L8
         FRAME FULL [org/nlogo/prim/_asm_proceduregrowgrass_if_0 org/nlogo/nvm/Context I D] [org/nlogo/nvm/Context I]
          PUTFIELD org/nlogo/nvm/Context.ip : I
         L9
          RETURN
[1]_asm_proceduregrowgrass_ifelse_1 "ifelse countdown <= 0 set pcolor green [ set countdown grass-delay ] [ set countdown countdown - 1 ]" boolean => void
      _lessorequal "countdown <= 0" Object,double => boolean
        _patchvariable:COUNTDOWN "countdown" => Object
        _constdouble:0.0 "0" => double
          // parameter final  context
          TRYCATCHBLOCK L0 L1 L2 org/nlogo/api/AgentException
         L0
          ALOAD 1
          GETFIELD org/nlogo/nvm/Context.agent : Lorg/nlogo/agent/Agent;
          ICONST_5
          INVOKEVIRTUAL org/nlogo/agent/Agent.getPatchVariable (I)Ljava/lang/Object;
         L1
          GOTO L3
         L2
         FRAME SAME1 org/nlogo/api/AgentException
          ASTORE 2
          NEW org/nlogo/nvm/RuntimePrimitiveException
          DUP
          ALOAD 1
          ALOAD 0
          ALOAD 2
          INVOKEVIRTUAL org/nlogo/api/AgentException.getMessage ()Ljava/lang/String;
          INVOKESPECIAL org/nlogo/nvm/RuntimePrimitiveException.<init> (Lorg/nlogo/api/Context;Lorg/nlogo/nvm/Instruction;Ljava/lang/String;)V
          ATHROW
         L3
         FRAME SAME1 java/lang/Object
          DCONST_0
         L4
          DSTORE 3
          ASTORE 2
          ALOAD 2
          INSTANCEOF java/lang/Double
          IFEQ L5
          ALOAD 2
          CHECKCAST java/lang/Double
          INVOKEVIRTUAL java/lang/Double.doubleValue ()D
          DLOAD 3
          DCMPG
          IFGT L6
          ICONST_1
          GOTO L7
         L6
         FRAME APPEND [java/lang/Object D]
          ICONST_0
         L7
         FRAME SAME1 I
          GOTO L8
         L5
         FRAME SAME
          NEW org/nlogo/nvm/RuntimePrimitiveException
          DUP
          ALOAD 1
          ALOAD 0
          INVOKESTATIC org/nlogo/core/I18N.errorsJ ()Lorg/nlogo/core/I18NJava;
          LDC "org.nlogo.prim._lessorequal.cannotCompareParameters"
          ICONST_2
          ANEWARRAY java/lang/Object
          DUP
          ICONST_0
          ALOAD 2
          INVOKESTATIC org/nlogo/api/TypeNames.aName (Ljava/lang/Object;)Ljava/lang/String;
          AASTORE
          DUP
          ICONST_1
          DLOAD 3
          INVOKESTATIC java/lang/Double.valueOf (D)Ljava/lang/Double;
          INVOKESTATIC org/nlogo/api/TypeNames.aName (Ljava/lang/Object;)Ljava/lang/String;
          AASTORE
          INVOKEINTERFACE org/nlogo/core/I18NJava.getN (Ljava/lang/String;[Ljava/lang/Object;)Ljava/lang/String;
          INVOKESPECIAL org/nlogo/nvm/RuntimePrimitiveException.<init> (Lorg/nlogo/api/Context;Lorg/nlogo/nvm/Instruction;Ljava/lang/String;)V
          ATHROW
         L8
         FRAME SAME1 I
          ISTORE 2
          ALOAD 1
          ILOAD 2
          IFEQ L9
          ICONST_2
          GOTO L10
         L9
         FRAME FULL [org/nlogo/prim/_asm_proceduregrowgrass_ifelse_1 org/nlogo/nvm/Context I D] [org/nlogo/nvm/Context]
          ICONST_5
         L10
         FRAME FULL [org/nlogo/prim/_asm_proceduregrowgrass_ifelse_1 org/nlogo/nvm/Context I D] [org/nlogo/nvm/Context I]
          PUTFIELD org/nlogo/nvm/Context.ip : I
         L11
          RETURN
[2]_asm_proceduregrowgrass_setpatchvariable_2 "set pcolor green" Object => void
      _constdouble:55.0 "green" => Double
          TRYCATCHBLOCK L0 L1 L2 org/nlogo/api/AgentException
         L3
          ALOAD 0
          GETFIELD org/nlogo/prim/_asm_proceduregrowgrass_setpatchvariable_2.kept2_value : Ljava/lang/Double;
         L4
          ASTORE 2
         L0
          ALOAD 1
          GETFIELD org/nlogo/nvm/Context.agent : Lorg/nlogo/agent/Agent;
          ICONST_2
          ALOAD 2
          INVOKEVIRTUAL org/nlogo/agent/Agent.setPatchVariable (ILjava/lang/Object;)V
         L1
          GOTO L5
         L2
         FRAME FULL [org/nlogo/prim/_asm_proceduregrowgrass_setpatchvariable_2 org/nlogo/nvm/Context java/lang/Double] [org/nlogo/api/AgentException]
          ASTORE 3
          NEW org/nlogo/nvm/RuntimePrimitiveException
          DUP
          ALOAD 1
          ALOAD 0
          ALOAD 3
          INVOKEVIRTUAL org/nlogo/api/AgentException.getMessage ()Ljava/lang/String;
          INVOKESPECIAL org/nlogo/nvm/RuntimePrimitiveException.<init> (Lorg/nlogo/api/Context;Lorg/nlogo/nvm/Instruction;Ljava/lang/String;)V
          ATHROW
         L5
         FRAME SAME
          ALOAD 1
          ICONST_3
          PUTFIELD org/nlogo/nvm/Context.ip : I
         L6
          RETURN
[3]_asm_proceduregrowgrass_setpatchvariable_3 "set countdown grass-delay" Object => void
      _observervariable:GRASS-DELAY "grass-delay" => Object
          TRYCATCHBLOCK L0 L1 L2 org/nlogo/api/AgentException
         L3
          ALOAD 1
          GETFIELD org/nlogo/nvm/Context.agent : Lorg/nlogo/agent/Agent;
          BIPUSH 7
          INVOKEVIRTUAL org/nlogo/agent/Agent.getObserverVariable (I)Ljava/lang/Object;
         L4
          ASTORE 2
         L0
          ALOAD 1
          GETFIELD org/nlogo/nvm/Context.agent : Lorg/nlogo/agent/Agent;
          ICONST_5
          ALOAD 2
          INVOKEVIRTUAL org/nlogo/agent/Agent.setPatchVariable (ILjava/lang/Object;)V
         L1
          GOTO L5
         L2
         FRAME FULL [org/nlogo/prim/_asm_proceduregrowgrass_setpatchvariable_3 org/nlogo/nvm/Context java/lang/Object] [org/nlogo/api/AgentException]
          ASTORE 3
          NEW org/nlogo/nvm/RuntimePrimitiveException
          DUP
          ALOAD 1
          ALOAD 0
          ALOAD 3
          INVOKEVIRTUAL org/nlogo/api/AgentException.getMessage ()Ljava/lang/String;
          INVOKESPECIAL org/nlogo/nvm/RuntimePrimitiveException.<init> (Lorg/nlogo/api/Context;Lorg/nlogo/nvm/Instruction;Ljava/lang/String;)V
          ATHROW
         L5
         FRAME SAME
          ALOAD 1
          ICONST_4
          PUTFIELD org/nlogo/nvm/Context.ip : I
         L6
          RETURN
[4]_asm_proceduregrowgrass_goto_4 => void
         L0
          ALOAD 1
          BIPUSH 6
          PUTFIELD org/nlogo/nvm/Context.ip : I
         L1
          RETURN
[5]_asm_proceduregrowgrass_setpatchvariable_5 "set countdown countdown - 1" Object => void
      _minus "countdown - 1" double,double => double
        _patchvariable:COUNTDOWN "countdown" => Object
        _constdouble:1.0 "1" => double
          // parameter final  context
          TRYCATCHBLOCK L0 L1 L2 org/nlogo/api/AgentException
          TRYCATCHBLOCK L3 L4 L4 java/lang/ClassCastException
          TRYCATCHBLOCK L5 L6 L7 org/nlogo/api/AgentException
         L0
          ALOAD 1
          GETFIELD org/nlogo/nvm/Context.agent : Lorg/nlogo/agent/Agent;
          ICONST_5
          INVOKEVIRTUAL org/nlogo/agent/Agent.getPatchVariable (I)Ljava/lang/Object;
         L1
          GOTO L8
         L2
         FRAME SAME1 org/nlogo/api/AgentException
          ASTORE 2
          NEW org/nlogo/nvm/RuntimePrimitiveException
          DUP
          ALOAD 1
          ALOAD 0
          ALOAD 2
          INVOKEVIRTUAL org/nlogo/api/AgentException.getMessage ()Ljava/lang/String;
          INVOKESPECIAL org/nlogo/nvm/RuntimePrimitiveException.<init> (Lorg/nlogo/api/Context;Lorg/nlogo/nvm/Instruction;Ljava/lang/String;)V
          ATHROW
         L8
         FRAME SAME1 java/lang/Object
          ASTORE 2
         L3
          ALOAD 2
          CHECKCAST java/lang/Double
          INVOKEVIRTUAL java/lang/Double.doubleValue ()D
          GOTO L9
         L4
         FRAME FULL [org/nlogo/prim/_asm_proceduregrowgrass_setpatchvariable_5 org/nlogo/nvm/Context java/lang/Object] [java/lang/ClassCastException]
          POP
          NEW org/nlogo/nvm/ArgumentTypeException
          DUP
          ALOAD 1
          ALOAD 0
          BIPUSH 0
          LDC 1
          ALOAD 2
          INVOKESPECIAL org/nlogo/nvm/ArgumentTypeException.<init> (Lorg/nlogo/nvm/Context;Lorg/nlogo/nvm/Instruction;IILjava/lang/Object;)V
          ATHROW
         L9
         FRAME SAME1 D
          DCONST_1
         L10
          DSTORE 4
          DSTORE 2
          ALOAD 0
          DLOAD 2
          DLOAD 4
          DSUB
          INVOKEVIRTUAL org/nlogo/prim/_asm_proceduregrowgrass_setpatchvariable_5.validDouble (D)D
         L11
          DSTORE 2
          NEW java/lang/Double
          DUP
          DLOAD 2
          INVOKESPECIAL java/lang/Double.<init> (D)V
          ASTORE 2
         L5
          ALOAD 1
          GETFIELD org/nlogo/nvm/Context.agent : Lorg/nlogo/agent/Agent;
          ICONST_5
          ALOAD 2
          INVOKEVIRTUAL org/nlogo/agent/Agent.setPatchVariable (ILjava/lang/Object;)V
         L6
          GOTO L12
         L7
         FRAME FULL [org/nlogo/prim/_asm_proceduregrowgrass_setpatchvariable_5 org/nlogo/nvm/Context java/lang/Double T D] [org/nlogo/api/AgentException]
          ASTORE 3
          NEW org/nlogo/nvm/RuntimePrimitiveException
          DUP
          ALOAD 1
          ALOAD 0
          ALOAD 3
          INVOKEVIRTUAL org/nlogo/api/AgentException.getMessage ()Ljava/lang/String;
          INVOKESPECIAL org/nlogo/nvm/RuntimePrimitiveException.<init> (Lorg/nlogo/api/Context;Lorg/nlogo/nvm/Instruction;Ljava/lang/String;)V
          ATHROW
         L12
         FRAME SAME
          ALOAD 1
          BIPUSH 6
          PUTFIELD org/nlogo/nvm/Context.ip : I
         L13
          RETURN
[6]_asm_proceduregrowgrass_return_6 => void
         L0
          ALOAD 1
          INVOKEVIRTUAL org/nlogo/nvm/Context.returnFromProcedure ()V
          ALOAD 1
          ICONST_0
          PUTFIELD org/nlogo/nvm/Context.stopping : Z
         L1
          RETURN

procedure MOVE:[]{-T--}:
[0]_asm_proceduremove_right_0 "rt random 50 - random 50" double => void
      _minus "random 50 - random 50" double,double => double
        _randomconst:50 "random 50" => double
        _randomconst:50 "random 50" => double
          // parameter final  context
          // parameter final  context
         L0
          ALOAD 1
          GETFIELD org/nlogo/nvm/Context.job : Lorg/nlogo/nvm/Job;
          GETFIELD org/nlogo/nvm/Job.random : Lorg/nlogo/api/MersenneTwisterFast;
          LDC 50
          INVOKEVIRTUAL org/nlogo/api/MersenneTwisterFast.nextLong (J)J
          L2D
         L1
          ALOAD 1
          GETFIELD org/nlogo/nvm/Context.job : Lorg/nlogo/nvm/Job;
          GETFIELD org/nlogo/nvm/Job.random : Lorg/nlogo/api/MersenneTwisterFast;
          LDC 50
          INVOKEVIRTUAL org/nlogo/api/MersenneTwisterFast.nextLong (J)J
          L2D
         L2
          DSTORE 4
          DSTORE 2
          ALOAD 0
          DLOAD 2
          DLOAD 4
          DSUB
          INVOKEVIRTUAL org/nlogo/prim/_asm_proceduremove_right_0.validDouble (D)D
         L3
          DSTORE 2
          ALOAD 1
          GETFIELD org/nlogo/nvm/Context.agent : Lorg/nlogo/agent/Agent;
          CHECKCAST org/nlogo/agent/Turtle
          DLOAD 2
          INVOKEVIRTUAL org/nlogo/agent/Turtle.turnRight (D)V
          ALOAD 1
          ICONST_1
          PUTFIELD org/nlogo/nvm/Context.ip : I
         L4
          RETURN
[1]_asm_proceduremove_fd1_1 "fd 1" => void
          TRYCATCHBLOCK L0 L1 L2 org/nlogo/api/AgentException
         L0
          ALOAD 1
          GETFIELD org/nlogo/nvm/Context.agent : Lorg/nlogo/agent/Agent;
          CHECKCAST org/nlogo/agent/Turtle
          DCONST_1
          INVOKEVIRTUAL org/nlogo/agent/Turtle.jump (D)V
         L1
          GOTO L3
         L2
         FRAME SAME1 org/nlogo/api/AgentException
          ASTORE 2
         L3
         FRAME SAME
          ALOAD 1
          ICONST_2
          PUTFIELD org/nlogo/nvm/Context.ip : I
         L4
          RETURN
[2]_asm_proceduremove_return_2 => void
         L0
          ALOAD 1
          INVOKEVIRTUAL org/nlogo/nvm/Context.returnFromProcedure ()V
          ALOAD 1
          ICONST_0
          PUTFIELD org/nlogo/nvm/Context.stopping : Z
         L1
          RETURN

procedure REPRODUCE-SHEEP:[]{-T--}:
[0]_asm_procedurereproducesheep_if_0 "if random-float 100 < sheep-reproduce set energy round energy / 2 [ hatch 1 rt random 360 [ fd 1 ] ]" boolean => void
      _lessthan "random-float 100 < sheep-reproduce" double,Object => boolean
        _randomfloat "random-float 100" double => double
          _constdouble:100.0 "100" => double
        _observervariable:SHEEP-REPRODUCE "sheep-reproduce" => Object
         L0
          LDC 100.0
         L1
          DSTORE 2
          ALOAD 0
          DLOAD 2
          ALOAD 1
          GETFIELD org/nlogo/nvm/Context.job : Lorg/nlogo/nvm/Job;
          GETFIELD org/nlogo/nvm/Job.random : Lorg/nlogo/api/MersenneTwisterFast;
          INVOKEVIRTUAL org/nlogo/api/MersenneTwisterFast.nextDouble ()D
          DMUL
          INVOKEVIRTUAL org/nlogo/prim/_asm_procedurereproducesheep_if_0.validDouble (D)D
         L2
          ALOAD 1
          GETFIELD org/nlogo/nvm/Context.agent : Lorg/nlogo/agent/Agent;
          ICONST_2
          INVOKEVIRTUAL org/nlogo/agent/Agent.getObserverVariable (I)Ljava/lang/Object;
         L3
          ASTORE 4
          DSTORE 2
          ALOAD 4
          INSTANCEOF java/lang/Double
          IFEQ L4
          DLOAD 2
          ALOAD 4
          CHECKCAST java/lang/Double
          INVOKEVIRTUAL java/lang/Double.doubleValue ()D
          DCMPG
          IFGE L5
          ICONST_1
          GOTO L6
         L5
         FRAME APPEND [D java/lang/Object]
          ICONST_0
         L6
         FRAME SAME1 I
          GOTO L7
         L4
         FRAME SAME
          NEW org/nlogo/nvm/RuntimePrimitiveException
          DUP
          ALOAD 1
          ALOAD 0
          INVOKESTATIC org/nlogo/core/I18N.errorsJ ()Lorg/nlogo/core/I18NJava;
          LDC "org.nlogo.prim._lessthan.cantUseLessthanOnDifferentArgs"
          ICONST_2
          ANEWARRAY java/lang/Object
          DUP
          ICONST_0
          DLOAD 2
          INVOKESTATIC java/lang/Double.valueOf (D)Ljava/lang/Double;
          INVOKESTATIC org/nlogo/api/TypeNames.aName (Ljava/lang/Object;)Ljava/lang/String;
          AASTORE
          DUP
          ICONST_1
          ALOAD 4
          INVOKESTATIC org/nlogo/api/TypeNames.aName (Ljava/lang/Object;)Ljava/lang/String;
          AASTORE
          INVOKEINTERFACE org/nlogo/core/I18NJava.getN (Ljava/lang/String;[Ljava/lang/Object;)Ljava/lang/String;
          INVOKESPECIAL org/nlogo/nvm/RuntimePrimitiveException.<init> (Lorg/nlogo/api/Context;Lorg/nlogo/nvm/Instruction;Ljava/lang/String;)V
          ATHROW
         L7
         FRAME SAME1 I
          ISTORE 2
          ALOAD 1
          ILOAD 2
          IFEQ L8
          ICONST_1
          GOTO L9
         L8
         FRAME FULL [org/nlogo/prim/_asm_procedurereproducesheep_if_0 org/nlogo/nvm/Context I T java/lang/Object] [org/nlogo/nvm/Context]
          BIPUSH 6
         L9
         FRAME FULL [org/nlogo/prim/_asm_procedurereproducesheep_if_0 org/nlogo/nvm/Context I T java/lang/Object] [org/nlogo/nvm/Context I]
          PUTFIELD org/nlogo/nvm/Context.ip : I
         L10
          RETURN
[1]_asm_procedurereproducesheep_setturtlevariable_1 "set energy round energy / 2" Object => void
      _round "round energy / 2" double => double
        _div "energy / 2" double,double => double
          _turtlevariable:ENERGY "energy" => Object
          _constdouble:2.0 "2" => double
          TRYCATCHBLOCK L0 L1 L2 org/nlogo/api/AgentException
          TRYCATCHBLOCK L3 L4 L4 java/lang/ClassCastException
          TRYCATCHBLOCK L5 L6 L7 org/nlogo/api/AgentException
         L0
          ALOAD 1
          GETFIELD org/nlogo/nvm/Context.agent : Lorg/nlogo/agent/Agent;
          BIPUSH 13
          INVOKEVIRTUAL org/nlogo/agent/Agent.getTurtleVariable (I)Ljava/lang/Object;
         L1
          GOTO L8
         L2
         FRAME SAME1 org/nlogo/api/AgentException
          ASTORE 2
          NEW org/nlogo/nvm/RuntimePrimitiveException
          DUP
          ALOAD 1
          ALOAD 0
          ALOAD 2
          INVOKEVIRTUAL org/nlogo/api/AgentException.getMessage ()Ljava/lang/String;
          INVOKESPECIAL org/nlogo/nvm/RuntimePrimitiveException.<init> (Lorg/nlogo/api/Context;Lorg/nlogo/nvm/Instruction;Ljava/lang/String;)V
          ATHROW
         L8
         FRAME SAME1 java/lang/Object
          ASTORE 2
         L3
          ALOAD 2
          CHECKCAST java/lang/Double
          INVOKEVIRTUAL java/lang/Double.doubleValue ()D
          GOTO L9
         L4
         FRAME FULL [org/nlogo/prim/_asm_procedurereproducesheep_setturtlevariable_1 org/nlogo/nvm/Context java/lang/Object] [java/lang/ClassCastException]
          POP
          NEW org/nlogo/nvm/ArgumentTypeException
          DUP
          ALOAD 1
          ALOAD 0
          BIPUSH 0
          LDC 1
          ALOAD 2
          INVOKESPECIAL org/nlogo/nvm/ArgumentTypeException.<init> (Lorg/nlogo/nvm/Context;Lorg/nlogo/nvm/Instruction;IILjava/lang/Object;)V
          ATHROW
         L9
         FRAME SAME1 D
          LDC 2.0
         L10
          DSTORE 4
          DSTORE 2
          DLOAD 4
          DCONST_0
          DCMPL
          IFNE L11
          NEW org/nlogo/nvm/RuntimePrimitiveException
          DUP
          ALOAD 1
          ALOAD 0
          INVOKESTATIC org/nlogo/core/I18N.errorsJ ()Lorg/nlogo/core/I18NJava;
          LDC "org.nlogo.prim.etc.$common.divByZero"
          INVOKEINTERFACE org/nlogo/core/I18NJava.get (Ljava/lang/String;)Ljava/lang/String;
          INVOKESPECIAL org/nlogo/nvm/RuntimePrimitiveException.<init> (Lorg/nlogo/api/Context;Lorg/nlogo/nvm/Instruction;Ljava/lang/String;)V
          ATHROW
         L11
         FRAME FULL [org/nlogo/prim/_asm_procedurereproducesheep_setturtlevariable_1 org/nlogo/nvm/Context D D] []
          ALOAD 0
          DLOAD 2
          DLOAD 4
          DDIV
          INVOKEVIRTUAL org/nlogo/prim/_asm_procedurereproducesheep_setturtlevariable_1.validDouble (D)D
         L12
          DSTORE 2
          ALOAD 0
          DLOAD 2
          ICONST_0
          INVOKESTATIC org/nlogo/api/Approximate.approximate (DI)D
          INVOKEVIRTUAL org/nlogo/prim/_asm_procedurereproducesheep_setturtlevariable_1.validDouble (D)D
         L13
          DSTORE 2
          NEW java/lang/Double
          DUP
          DLOAD 2
          INVOKESPECIAL java/lang/Double.<init> (D)V
          ASTORE 2
         L5
          ALOAD 1
          GETFIELD org/nlogo/nvm/Context.agent : Lorg/nlogo/agent/Agent;
          BIPUSH 13
          ALOAD 2
          INVOKEVIRTUAL org/nlogo/agent/Agent.setTurtleVariable (ILjava/lang/Object;)V
         L6
          GOTO L14
         L7
         FRAME FULL [org/nlogo/prim/_asm_procedurereproducesheep_setturtlevariable_1 org/nlogo/nvm/Context java/lang/Double T D] [org/nlogo/api/AgentException]
          ASTORE 3
          NEW org/nlogo/nvm/RuntimePrimitiveException
          DUP
          ALOAD 1
          ALOAD 0
          ALOAD 3
          INVOKEVIRTUAL org/nlogo/api/AgentException.getMessage ()Ljava/lang/String;
          INVOKESPECIAL org/nlogo/nvm/RuntimePrimitiveException.<init> (Lorg/nlogo/api/Context;Lorg/nlogo/nvm/Instruction;Ljava/lang/String;)V
          ATHROW
         L14
         FRAME SAME
          ALOAD 1
          ICONST_2
          PUTFIELD org/nlogo/nvm/Context.ip : I
         L15
          RETURN
[2]_hatch:,+6 "hatch 1 rt random 360 [ fd 1 ]"
      _asm_procedurereproducesheep_constdouble_2 "1" => Double
           L0
            ALOAD 0
            GETFIELD org/nlogo/prim/_asm_procedurereproducesheep_constdouble_2.kept1_value : Ljava/lang/Double;
           L1
            ARETURN
[3]_asm_procedurereproducesheep_right_3 "rt random 360" double => void
      _randomconst:360 "random 360" => double
          // parameter final  context
         L0
          ALOAD 1
          GETFIELD org/nlogo/nvm/Context.job : Lorg/nlogo/nvm/Job;
          GETFIELD org/nlogo/nvm/Job.random : Lorg/nlogo/api/MersenneTwisterFast;
          LDC 360
          INVOKEVIRTUAL org/nlogo/api/MersenneTwisterFast.nextLong (J)J
          L2D
         L1
          DSTORE 2
          ALOAD 1
          GETFIELD org/nlogo/nvm/Context.agent : Lorg/nlogo/agent/Agent;
          CHECKCAST org/nlogo/agent/Turtle
          DLOAD 2
          INVOKEVIRTUAL org/nlogo/agent/Turtle.turnRight (D)V
          ALOAD 1
          ICONST_4
          PUTFIELD org/nlogo/nvm/Context.ip : I
         L2
          RETURN
[4]_asm_procedurereproducesheep_fd1_4 "fd 1" => void
          TRYCATCHBLOCK L0 L1 L2 org/nlogo/api/AgentException
         L0
          ALOAD 1
          GETFIELD org/nlogo/nvm/Context.agent : Lorg/nlogo/agent/Agent;
          CHECKCAST org/nlogo/agent/Turtle
          DCONST_1
          INVOKEVIRTUAL org/nlogo/agent/Turtle.jump (D)V
         L1
          GOTO L3
         L2
         FRAME SAME1 org/nlogo/api/AgentException
          ASTORE 2
         L3
         FRAME SAME
          ALOAD 1
          ICONST_5
          PUTFIELD org/nlogo/nvm/Context.ip : I
         L4
          RETURN
[5]_asm_procedurereproducesheep_done_5 => void
          // parameter final  context
         L0
          ALOAD 1
          ICONST_1
          PUTFIELD org/nlogo/nvm/Context.finished : Z
         L1
          RETURN
[6]_asm_procedurereproducesheep_return_6 => void
         L0
          ALOAD 1
          INVOKEVIRTUAL org/nlogo/nvm/Context.returnFromProcedure ()V
          ALOAD 1
          ICONST_0
          PUTFIELD org/nlogo/nvm/Context.stopping : Z
         L1
          RETURN

procedure REPRODUCE-WOLVES:[]{-T--}:
[0]_asm_procedurereproducewolves_if_0 "if random-float 100 < wolf-reproduce set energy round energy / 2 [ hatch 1 rt random 360 [ fd 1 ] ]" boolean => void
      _lessthan "random-float 100 < wolf-reproduce" double,Object => boolean
        _randomfloat "random-float 100" double => double
          _constdouble:100.0 "100" => double
        _observervariable:WOLF-REPRODUCE "wolf-reproduce" => Object
         L0
          LDC 100.0
         L1
          DSTORE 2
          ALOAD 0
          DLOAD 2
          ALOAD 1
          GETFIELD org/nlogo/nvm/Context.job : Lorg/nlogo/nvm/Job;
          GETFIELD org/nlogo/nvm/Job.random : Lorg/nlogo/api/MersenneTwisterFast;
          INVOKEVIRTUAL org/nlogo/api/MersenneTwisterFast.nextDouble ()D
          DMUL
          INVOKEVIRTUAL org/nlogo/prim/_asm_procedurereproducewolves_if_0.validDouble (D)D
         L2
          ALOAD 1
          GETFIELD org/nlogo/nvm/Context.agent : Lorg/nlogo/agent/Agent;
          ICONST_5
          INVOKEVIRTUAL org/nlogo/agent/Agent.getObserverVariable (I)Ljava/lang/Object;
         L3
          ASTORE 4
          DSTORE 2
          ALOAD 4
          INSTANCEOF java/lang/Double
          IFEQ L4
          DLOAD 2
          ALOAD 4
          CHECKCAST java/lang/Double
          INVOKEVIRTUAL java/lang/Double.doubleValue ()D
          DCMPG
          IFGE L5
          ICONST_1
          GOTO L6
         L5
         FRAME APPEND [D java/lang/Object]
          ICONST_0
         L6
         FRAME SAME1 I
          GOTO L7
         L4
         FRAME SAME
          NEW org/nlogo/nvm/RuntimePrimitiveException
          DUP
          ALOAD 1
          ALOAD 0
          INVOKESTATIC org/nlogo/core/I18N.errorsJ ()Lorg/nlogo/core/I18NJava;
          LDC "org.nlogo.prim._lessthan.cantUseLessthanOnDifferentArgs"
          ICONST_2
          ANEWARRAY java/lang/Object
          DUP
          ICONST_0
          DLOAD 2
          INVOKESTATIC java/lang/Double.valueOf (D)Ljava/lang/Double;
          INVOKESTATIC org/nlogo/api/TypeNames.aName (Ljava/lang/Object;)Ljava/lang/String;
          AASTORE
          DUP
          ICONST_1
          ALOAD 4
          INVOKESTATIC org/nlogo/api/TypeNames.aName (Ljava/lang/Object;)Ljava/lang/String;
          AASTORE
          INVOKEINTERFACE org/nlogo/core/I18NJava.getN (Ljava/lang/String;[Ljava/lang/Object;)Ljava/lang/String;
          INVOKESPECIAL org/nlogo/nvm/RuntimePrimitiveException.<init> (Lorg/nlogo/api/Context;Lorg/nlogo/nvm/Instruction;Ljava/lang/String;)V
          ATHROW
         L7
         FRAME SAME1 I
          ISTORE 2
          ALOAD 1
          ILOAD 2
          IFEQ L8
          ICONST_1
          GOTO L9
         L8
         FRAME FULL [org/nlogo/prim/_asm_procedurereproducewolves_if_0 org/nlogo/nvm/Context I T java/lang/Object] [org/nlogo/nvm/Context]
          BIPUSH 6
         L9
         FRAME FULL [org/nlogo/prim/_asm_procedurereproducewolves_if_0 org/nlogo/nvm/Context I T java/lang/Object] [org/nlogo/nvm/Context I]
          PUTFIELD org/nlogo/nvm/Context.ip : I
         L10
          RETURN
[1]_asm_procedurereproducewolves_setturtlevariable_1 "set energy round energy / 2" Object => void
      _round "round energy / 2" double => double
        _div "energy / 2" double,double => double
          _turtlevariable:ENERGY "energy" => Object
          _constdouble:2.0 "2" => double
          TRYCATCHBLOCK L0 L1 L2 org/nlogo/api/AgentException
          TRYCATCHBLOCK L3 L4 L4 java/lang/ClassCastException
          TRYCATCHBLOCK L5 L6 L7 org/nlogo/api/AgentException
         L0
          ALOAD 1
          GETFIELD org/nlogo/nvm/Context.agent : Lorg/nlogo/agent/Agent;
          BIPUSH 13
          INVOKEVIRTUAL org/nlogo/agent/Agent.getTurtleVariable (I)Ljava/lang/Object;
         L1
          GOTO L8
         L2
         FRAME SAME1 org/nlogo/api/AgentException
          ASTORE 2
          NEW org/nlogo/nvm/RuntimePrimitiveException
          DUP
          ALOAD 1
          ALOAD 0
          ALOAD 2
          INVOKEVIRTUAL org/nlogo/api/AgentException.getMessage ()Ljava/lang/String;
          INVOKESPECIAL org/nlogo/nvm/RuntimePrimitiveException.<init> (Lorg/nlogo/api/Context;Lorg/nlogo/nvm/Instruction;Ljava/lang/String;)V
          ATHROW
         L8
         FRAME SAME1 java/lang/Object
          ASTORE 2
         L3
          ALOAD 2
          CHECKCAST java/lang/Double
          INVOKEVIRTUAL java/lang/Double.doubleValue ()D
          GOTO L9
         L4
         FRAME FULL [org/nlogo/prim/_asm_procedurereproducewolves_setturtlevariable_1 org/nlogo/nvm/Context java/lang/Object] [java/lang/ClassCastException]
          POP
          NEW org/nlogo/nvm/ArgumentTypeException
          DUP
          ALOAD 1
          ALOAD 0
          BIPUSH 0
          LDC 1
          ALOAD 2
          INVOKESPECIAL org/nlogo/nvm/ArgumentTypeException.<init> (Lorg/nlogo/nvm/Context;Lorg/nlogo/nvm/Instruction;IILjava/lang/Object;)V
          ATHROW
         L9
         FRAME SAME1 D
          LDC 2.0
         L10
          DSTORE 4
          DSTORE 2
          DLOAD 4
          DCONST_0
          DCMPL
          IFNE L11
          NEW org/nlogo/nvm/RuntimePrimitiveException
          DUP
          ALOAD 1
          ALOAD 0
          INVOKESTATIC org/nlogo/core/I18N.errorsJ ()Lorg/nlogo/core/I18NJava;
          LDC "org.nlogo.prim.etc.$common.divByZero"
          INVOKEINTERFACE org/nlogo/core/I18NJava.get (Ljava/lang/String;)Ljava/lang/String;
          INVOKESPECIAL org/nlogo/nvm/RuntimePrimitiveException.<init> (Lorg/nlogo/api/Context;Lorg/nlogo/nvm/Instruction;Ljava/lang/String;)V
          ATHROW
         L11
         FRAME FULL [org/nlogo/prim/_asm_procedurereproducewolves_setturtlevariable_1 org/nlogo/nvm/Context D D] []
          ALOAD 0
          DLOAD 2
          DLOAD 4
          DDIV
          INVOKEVIRTUAL org/nlogo/prim/_asm_procedurereproducewolves_setturtlevariable_1.validDouble (D)D
         L12
          DSTORE 2
          ALOAD 0
          DLOAD 2
          ICONST_0
          INVOKESTATIC org/nlogo/api/Approximate.approximate (DI)D
          INVOKEVIRTUAL org/nlogo/prim/_asm_procedurereproducewolves_setturtlevariable_1.validDouble (D)D
         L13
          DSTORE 2
          NEW java/lang/Double
          DUP
          DLOAD 2
          INVOKESPECIAL java/lang/Double.<init> (D)V
          ASTORE 2
         L5
          ALOAD 1
          GETFIELD org/nlogo/nvm/Context.agent : Lorg/nlogo/agent/Agent;
          BIPUSH 13
          ALOAD 2
          INVOKEVIRTUAL org/nlogo/agent/Agent.setTurtleVariable (ILjava/lang/Object;)V
         L6
          GOTO L14
         L7
         FRAME FULL [org/nlogo/prim/_asm_procedurereproducewolves_setturtlevariable_1 org/nlogo/nvm/Context java/lang/Double T D] [org/nlogo/api/AgentException]
          ASTORE 3
          NEW org/nlogo/nvm/RuntimePrimitiveException
          DUP
          ALOAD 1
          ALOAD 0
          ALOAD 3
          INVOKEVIRTUAL org/nlogo/api/AgentException.getMessage ()Ljava/lang/String;
          INVOKESPECIAL org/nlogo/nvm/RuntimePrimitiveException.<init> (Lorg/nlogo/api/Context;Lorg/nlogo/nvm/Instruction;Ljava/lang/String;)V
          ATHROW
         L14
         FRAME SAME
          ALOAD 1
          ICONST_2
          PUTFIELD org/nlogo/nvm/Context.ip : I
         L15
          RETURN
[2]_hatch:,+6 "hatch 1 rt random 360 [ fd 1 ]"
      _asm_procedurereproducewolves_constdouble_2 "1" => Double
           L0
            ALOAD 0
            GETFIELD org/nlogo/prim/_asm_procedurereproducewolves_constdouble_2.kept1_value : Ljava/lang/Double;
           L1
            ARETURN
[3]_asm_procedurereproducewolves_right_3 "rt random 360" double => void
      _randomconst:360 "random 360" => double
          // parameter final  context
         L0
          ALOAD 1
          GETFIELD org/nlogo/nvm/Context.job : Lorg/nlogo/nvm/Job;
          GETFIELD org/nlogo/nvm/Job.random : Lorg/nlogo/api/MersenneTwisterFast;
          LDC 360
          INVOKEVIRTUAL org/nlogo/api/MersenneTwisterFast.nextLong (J)J
          L2D
         L1
          DSTORE 2
          ALOAD 1
          GETFIELD org/nlogo/nvm/Context.agent : Lorg/nlogo/agent/Agent;
          CHECKCAST org/nlogo/agent/Turtle
          DLOAD 2
          INVOKEVIRTUAL org/nlogo/agent/Turtle.turnRight (D)V
          ALOAD 1
          ICONST_4
          PUTFIELD org/nlogo/nvm/Context.ip : I
         L2
          RETURN
[4]_asm_procedurereproducewolves_fd1_4 "fd 1" => void
          TRYCATCHBLOCK L0 L1 L2 org/nlogo/api/AgentException
         L0
          ALOAD 1
          GETFIELD org/nlogo/nvm/Context.agent : Lorg/nlogo/agent/Agent;
          CHECKCAST org/nlogo/agent/Turtle
          DCONST_1
          INVOKEVIRTUAL org/nlogo/agent/Turtle.jump (D)V
         L1
          GOTO L3
         L2
         FRAME SAME1 org/nlogo/api/AgentException
          ASTORE 2
         L3
         FRAME SAME
          ALOAD 1
          ICONST_5
          PUTFIELD org/nlogo/nvm/Context.ip : I
         L4
          RETURN
[5]_asm_procedurereproducewolves_done_5 => void
          // parameter final  context
         L0
          ALOAD 1
          ICONST_1
          PUTFIELD org/nlogo/nvm/Context.finished : Z
         L1
          RETURN
[6]_asm_procedurereproducewolves_return_6 => void
         L0
          ALOAD 1
          INVOKEVIRTUAL org/nlogo/nvm/Context.returnFromProcedure ()V
          ALOAD 1
          ICONST_0
          PUTFIELD org/nlogo/nvm/Context.stopping : Z
         L1
          RETURN

procedure SETUP:[]{O---}:
[0]_clearall "ca"
[1]_resetticks "reset-ticks"
[2]_asm_proceduresetup_ask_0 "ask patches [ set pcolor green ]" AgentSet => void
      _patches "patches" => AgentSet
          // parameter final  context
         L0
          ALOAD 0
          GETFIELD org/nlogo/prim/_asm_proceduresetup_ask_0.world : Lorg/nlogo/agent/World;
          INVOKEVIRTUAL org/nlogo/agent/World.patches ()Lorg/nlogo/agent/AgentSet;
         L1
          ASTORE 2
          ALOAD 1
          GETFIELD org/nlogo/nvm/Context.agent : Lorg/nlogo/agent/Agent;
          INSTANCEOF org/nlogo/agent/Observer
          IFNE L2
          ALOAD 2
          ALOAD 0
          GETFIELD org/nlogo/prim/_asm_proceduresetup_ask_0.world : Lorg/nlogo/agent/World;
          INVOKEVIRTUAL org/nlogo/agent/World.turtles ()Lorg/nlogo/agent/TreeAgentSet;
          IF_ACMPNE L3
          NEW org/nlogo/nvm/RuntimePrimitiveException
          DUP
          ALOAD 1
          ALOAD 0
          INVOKESTATIC org/nlogo/core/I18N.errorsJ ()Lorg/nlogo/core/I18NJava;
          LDC "org.nlogo.prim.$common.onlyObserverCanAskAllTurtles"
          INVOKEINTERFACE org/nlogo/core/I18NJava.get (Ljava/lang/String;)Ljava/lang/String;
          INVOKESPECIAL org/nlogo/nvm/RuntimePrimitiveException.<init> (Lorg/nlogo/api/Context;Lorg/nlogo/nvm/Instruction;Ljava/lang/String;)V
          ATHROW
         L3
         FRAME APPEND [org/nlogo/agent/AgentSet]
          ALOAD 2
          ALOAD 0
          GETFIELD org/nlogo/prim/_asm_proceduresetup_ask_0.world : Lorg/nlogo/agent/World;
          INVOKEVIRTUAL org/nlogo/agent/World.patches ()Lorg/nlogo/agent/AgentSet;
          IF_ACMPNE L2
          NEW org/nlogo/nvm/RuntimePrimitiveException
          DUP
          ALOAD 1
          ALOAD 0
          INVOKESTATIC org/nlogo/core/I18N.errorsJ ()Lorg/nlogo/core/I18NJava;
          LDC "org.nlogo.prim.$common.onlyObserverCanAskAllPatches"
          INVOKEINTERFACE org/nlogo/core/I18NJava.get (Ljava/lang/String;)Ljava/lang/String;
          INVOKESPECIAL org/nlogo/nvm/RuntimePrimitiveException.<init> (Lorg/nlogo/api/Context;Lorg/nlogo/nvm/Instruction;Ljava/lang/String;)V
          ATHROW
         L2
         FRAME SAME
          ALOAD 1
          ALOAD 2
          ICONST_3
          INVOKEVIRTUAL org/nlogo/nvm/Context.runExclusiveJob (Lorg/nlogo/agent/AgentSet;I)V
          ALOAD 1
          ICONST_5
          PUTFIELD org/nlogo/nvm/Context.ip : I
         L4
          RETURN
[3]_asm_proceduresetup_setpatchvariable_1 "set pcolor green" Object => void
      _constdouble:55.0 "green" => Double
          TRYCATCHBLOCK L0 L1 L2 org/nlogo/api/AgentException
         L3
          ALOAD 0
          GETFIELD org/nlogo/prim/_asm_proceduresetup_setpatchvariable_1.kept2_value : Ljava/lang/Double;
         L4
          ASTORE 2
         L0
          ALOAD 1
          GETFIELD org/nlogo/nvm/Context.agent : Lorg/nlogo/agent/Agent;
          ICONST_2
          ALOAD 2
          INVOKEVIRTUAL org/nlogo/agent/Agent.setPatchVariable (ILjava/lang/Object;)V
         L1
          GOTO L5
         L2
         FRAME FULL [org/nlogo/prim/_asm_proceduresetup_setpatchvariable_1 org/nlogo/nvm/Context java/lang/Double] [org/nlogo/api/AgentException]
          ASTORE 3
          NEW org/nlogo/nvm/RuntimePrimitiveException
          DUP
          ALOAD 1
          ALOAD 0
          ALOAD 3
          INVOKEVIRTUAL org/nlogo/api/AgentException.getMessage ()Ljava/lang/String;
          INVOKESPECIAL org/nlogo/nvm/RuntimePrimitiveException.<init> (Lorg/nlogo/api/Context;Lorg/nlogo/nvm/Instruction;Ljava/lang/String;)V
          ATHROW
         L5
         FRAME SAME
          ALOAD 1
          ICONST_4
          PUTFIELD org/nlogo/nvm/Context.ip : I
         L6
          RETURN
[4]_asm_proceduresetup_done_2 => void
          // parameter final  context
         L0
          ALOAD 1
          ICONST_1
          PUTFIELD org/nlogo/nvm/Context.finished : Z
         L1
          RETURN
[5]_asm_proceduresetup_if_3 "if grass? [ ask patches set countdown random grass-delay [ if random 2 = 0 [ set pcolor brown ] ] ]" boolean => void
      _observervariable:GRASS? "grass?" => Object
          TRYCATCHBLOCK L0 L1 L1 java/lang/ClassCastException
         L2
          ALOAD 1
          GETFIELD org/nlogo/nvm/Context.agent : Lorg/nlogo/agent/Agent;
          BIPUSH 6
          INVOKEVIRTUAL org/nlogo/agent/Agent.getObserverVariable (I)Ljava/lang/Object;
         L3
          ASTORE 2
         L0
          ALOAD 2
          CHECKCAST java/lang/Boolean
          INVOKEVIRTUAL java/lang/Boolean.booleanValue ()Z
          GOTO L4
         L1
         FRAME FULL [org/nlogo/prim/_asm_proceduresetup_if_3 org/nlogo/nvm/Context java/lang/Object] [java/lang/ClassCastException]
          POP
          NEW org/nlogo/nvm/ArgumentTypeException
          DUP
          ALOAD 1
          ALOAD 0
          BIPUSH 0
          LDC 2
          ALOAD 2
          INVOKESPECIAL org/nlogo/nvm/ArgumentTypeException.<init> (Lorg/nlogo/nvm/Context;Lorg/nlogo/nvm/Instruction;IILjava/lang/Object;)V
          ATHROW
         L4
         FRAME SAME1 I
          ISTORE 2
          ALOAD 1
          ILOAD 2
          IFEQ L5
          BIPUSH 6
          GOTO L6
         L5
         FRAME FULL [org/nlogo/prim/_asm_proceduresetup_if_3 org/nlogo/nvm/Context I] [org/nlogo/nvm/Context]
          BIPUSH 11
         L6
         FRAME FULL [org/nlogo/prim/_asm_proceduresetup_if_3 org/nlogo/nvm/Context I] [org/nlogo/nvm/Context I]
          PUTFIELD org/nlogo/nvm/Context.ip : I
         L7
          RETURN
[6]_asm_proceduresetup_ask_4 "ask patches set countdown random grass-delay [ if random 2 = 0 [ set pcolor brown ] ]" AgentSet => void
      _patches "patches" => AgentSet
          // parameter final  context
         L0
          ALOAD 0
          GETFIELD org/nlogo/prim/_asm_proceduresetup_ask_4.world : Lorg/nlogo/agent/World;
          INVOKEVIRTUAL org/nlogo/agent/World.patches ()Lorg/nlogo/agent/AgentSet;
         L1
          ASTORE 2
          ALOAD 1
          GETFIELD org/nlogo/nvm/Context.agent : Lorg/nlogo/agent/Agent;
          INSTANCEOF org/nlogo/agent/Observer
          IFNE L2
          ALOAD 2
          ALOAD 0
          GETFIELD org/nlogo/prim/_asm_proceduresetup_ask_4.world : Lorg/nlogo/agent/World;
          INVOKEVIRTUAL org/nlogo/agent/World.turtles ()Lorg/nlogo/agent/TreeAgentSet;
          IF_ACMPNE L3
          NEW org/nlogo/nvm/RuntimePrimitiveException
          DUP
          ALOAD 1
          ALOAD 0
          INVOKESTATIC org/nlogo/core/I18N.errorsJ ()Lorg/nlogo/core/I18NJava;
          LDC "org.nlogo.prim.$common.onlyObserverCanAskAllTurtles"
          INVOKEINTERFACE org/nlogo/core/I18NJava.get (Ljava/lang/String;)Ljava/lang/String;
          INVOKESPECIAL org/nlogo/nvm/RuntimePrimitiveException.<init> (Lorg/nlogo/api/Context;Lorg/nlogo/nvm/Instruction;Ljava/lang/String;)V
          ATHROW
         L3
         FRAME APPEND [org/nlogo/agent/AgentSet]
          ALOAD 2
          ALOAD 0
          GETFIELD org/nlogo/prim/_asm_proceduresetup_ask_4.world : Lorg/nlogo/agent/World;
          INVOKEVIRTUAL org/nlogo/agent/World.patches ()Lorg/nlogo/agent/AgentSet;
          IF_ACMPNE L2
          NEW org/nlogo/nvm/RuntimePrimitiveException
          DUP
          ALOAD 1
          ALOAD 0
          INVOKESTATIC org/nlogo/core/I18N.errorsJ ()Lorg/nlogo/core/I18NJava;
          LDC "org.nlogo.prim.$common.onlyObserverCanAskAllPatches"
          INVOKEINTERFACE org/nlogo/core/I18NJava.get (Ljava/lang/String;)Ljava/lang/String;
          INVOKESPECIAL org/nlogo/nvm/RuntimePrimitiveException.<init> (Lorg/nlogo/api/Context;Lorg/nlogo/nvm/Instruction;Ljava/lang/String;)V
          ATHROW
         L2
         FRAME SAME
          ALOAD 1
          ALOAD 2
          BIPUSH 7
          INVOKEVIRTUAL org/nlogo/nvm/Context.runExclusiveJob (Lorg/nlogo/agent/AgentSet;I)V
          ALOAD 1
          BIPUSH 11
          PUTFIELD org/nlogo/nvm/Context.ip : I
         L4
          RETURN
[7]_asm_proceduresetup_setpatchvariable_5 "set countdown random grass-delay" Object => void
      _random "random grass-delay" double => double
        _observervariable:GRASS-DELAY "grass-delay" => Object
          TRYCATCHBLOCK L0 L1 L1 java/lang/ClassCastException
          TRYCATCHBLOCK L2 L3 L4 org/nlogo/api/AgentException
         L5
          ALOAD 1
          GETFIELD org/nlogo/nvm/Context.agent : Lorg/nlogo/agent/Agent;
          BIPUSH 7
          INVOKEVIRTUAL org/nlogo/agent/Agent.getObserverVariable (I)Ljava/lang/Object;
         L6
          ASTORE 2
         L0
          ALOAD 2
          CHECKCAST java/lang/Double
          INVOKEVIRTUAL java/lang/Double.doubleValue ()D
          GOTO L7
         L1
         FRAME FULL [org/nlogo/prim/_asm_proceduresetup_setpatchvariable_5 org/nlogo/nvm/Context java/lang/Object] [java/lang/ClassCastException]
          POP
          NEW org/nlogo/nvm/ArgumentTypeException
          DUP
          ALOAD 1
          ALOAD 0
          BIPUSH 0
          LDC 1
          ALOAD 2
          INVOKESPECIAL org/nlogo/nvm/ArgumentTypeException.<init> (Lorg/nlogo/nvm/Context;Lorg/nlogo/nvm/Instruction;IILjava/lang/Object;)V
          ATHROW
         L7
         FRAME SAME1 D
          DSTORE 2
          ALOAD 0
          DLOAD 2
          INVOKEVIRTUAL org/nlogo/prim/_asm_proceduresetup_setpatchvariable_5.validLong (D)J
          LSTORE 4
          DLOAD 2
          LLOAD 4
          L2D
          DCMPL
          IFEQ L8
          LLOAD 4
          DLOAD 2
          DCONST_0
          DCMPL
          IFLT L9
          LCONST_1
          GOTO L10
         L9
         FRAME FULL [org/nlogo/prim/_asm_proceduresetup_setpatchvariable_5 org/nlogo/nvm/Context D J] [J]
          LDC -1
         L10
         FRAME FULL [org/nlogo/prim/_asm_proceduresetup_setpatchvariable_5 org/nlogo/nvm/Context D J] [J J]
          LADD
          LSTORE 4
         L8
         FRAME SAME
          LLOAD 4
          LCONST_0
          LCMP
          IFLE L11
          ALOAD 1
          GETFIELD org/nlogo/nvm/Context.job : Lorg/nlogo/nvm/Job;
          GETFIELD org/nlogo/nvm/Job.random : Lorg/nlogo/api/MersenneTwisterFast;
          LLOAD 4
          INVOKEVIRTUAL org/nlogo/api/MersenneTwisterFast.nextLong (J)J
          L2D
          GOTO L12
         L11
         FRAME SAME
          LLOAD 4
          LCONST_0
          LCMP
          IFGE L13
          ALOAD 1
          GETFIELD org/nlogo/nvm/Context.job : Lorg/nlogo/nvm/Job;
          GETFIELD org/nlogo/nvm/Job.random : Lorg/nlogo/api/MersenneTwisterFast;
          LLOAD 4
          LNEG
          INVOKEVIRTUAL org/nlogo/api/MersenneTwisterFast.nextLong (J)J
          LNEG
          L2D
          GOTO L12
         L13
         FRAME SAME
          DCONST_0
         L12
         FRAME SAME1 D
          DSTORE 2
          NEW java/lang/Double
          DUP
          DLOAD 2
          INVOKESPECIAL java/lang/Double.<init> (D)V
          ASTORE 2
         L2
          ALOAD 1
          GETFIELD org/nlogo/nvm/Context.agent : Lorg/nlogo/agent/Agent;
          ICONST_5
          ALOAD 2
          INVOKEVIRTUAL org/nlogo/agent/Agent.setPatchVariable (ILjava/lang/Object;)V
         L3
          GOTO L14
         L4
         FRAME FULL [org/nlogo/prim/_asm_proceduresetup_setpatchvariable_5 org/nlogo/nvm/Context java/lang/Double T J] [org/nlogo/api/AgentException]
          ASTORE 3
          NEW org/nlogo/nvm/RuntimePrimitiveException
          DUP
          ALOAD 1
          ALOAD 0
          ALOAD 3
          INVOKEVIRTUAL org/nlogo/api/AgentException.getMessage ()Ljava/lang/String;
          INVOKESPECIAL org/nlogo/nvm/RuntimePrimitiveException.<init> (Lorg/nlogo/api/Context;Lorg/nlogo/nvm/Instruction;Ljava/lang/String;)V
          ATHROW
         L14
         FRAME SAME
          ALOAD 1
          BIPUSH 8
          PUTFIELD org/nlogo/nvm/Context.ip : I
         L15
          RETURN
[8]_asm_proceduresetup_if_6 "if random 2 = 0 [ set pcolor brown ]" boolean => void
      _equal "random 2 = 0" double,double => boolean
        _randomconst:2 "random 2" => double
        _constdouble:0.0 "0" => double
          // parameter final  context
         L0
          ALOAD 1
          GETFIELD org/nlogo/nvm/Context.job : Lorg/nlogo/nvm/Job;
          GETFIELD org/nlogo/nvm/Job.random : Lorg/nlogo/api/MersenneTwisterFast;
          LDC 2
          INVOKEVIRTUAL org/nlogo/api/MersenneTwisterFast.nextLong (J)J
          L2D
         L1
          DCONST_0
         L2
          DSTORE 4
          DSTORE 2
          DLOAD 2
          DLOAD 4
          DCMPL
          IFNE L3
          ICONST_1
          GOTO L4
         L3
         FRAME APPEND [D D]
          ICONST_0
         L4
         FRAME SAME1 I
          ISTORE 2
          ALOAD 1
          ILOAD 2
          IFEQ L5
          BIPUSH 9
          GOTO L6
         L5
         FRAME FULL [org/nlogo/prim/_asm_proceduresetup_if_6 org/nlogo/nvm/Context I T D] [org/nlogo/nvm/Context]
          BIPUSH 10
         L6
         FRAME FULL [org/nlogo/prim/_asm_proceduresetup_if_6 org/nlogo/nvm/Context I T D] [org/nlogo/nvm/Context I]
          PUTFIELD org/nlogo/nvm/Context.ip : I
         L7
          RETURN
[9]_asm_proceduresetup_setpatchvariable_7 "set pcolor brown" Object => void
      _constdouble:35.0 "brown" => Double
          TRYCATCHBLOCK L0 L1 L2 org/nlogo/api/AgentException
         L3
          ALOAD 0
          GETFIELD org/nlogo/prim/_asm_proceduresetup_setpatchvariable_7.kept2_value : Ljava/lang/Double;
         L4
          ASTORE 2
         L0
          ALOAD 1
          GETFIELD org/nlogo/nvm/Context.agent : Lorg/nlogo/agent/Agent;
          ICONST_2
          ALOAD 2
          INVOKEVIRTUAL org/nlogo/agent/Agent.setPatchVariable (ILjava/lang/Object;)V
         L1
          GOTO L5
         L2
         FRAME FULL [org/nlogo/prim/_asm_proceduresetup_setpatchvariable_7 org/nlogo/nvm/Context java/lang/Double] [org/nlogo/api/AgentException]
          ASTORE 3
          NEW org/nlogo/nvm/RuntimePrimitiveException
          DUP
          ALOAD 1
          ALOAD 0
          ALOAD 3
          INVOKEVIRTUAL org/nlogo/api/AgentException.getMessage ()Ljava/lang/String;
          INVOKESPECIAL org/nlogo/nvm/RuntimePrimitiveException.<init> (Lorg/nlogo/api/Context;Lorg/nlogo/nvm/Instruction;Ljava/lang/String;)V
          ATHROW
         L5
         FRAME SAME
          ALOAD 1
          BIPUSH 10
          PUTFIELD org/nlogo/nvm/Context.ip : I
         L6
          RETURN
[10]_asm_proceduresetup_done_8 => void
          // parameter final  context
         L0
          ALOAD 1
          ICONST_1
          PUTFIELD org/nlogo/nvm/Context.finished : Z
         L1
          RETURN
[11]_crofast:SHEEP "create-ordered-sheep [ init-sheep ]"
      _asm_proceduresetup_observervariable_9 "init-sheep" => Object
           L0
            ALOAD 1
            GETFIELD org/nlogo/nvm/Context.agent : Lorg/nlogo/agent/Agent;
            ICONST_0
            INVOKEVIRTUAL org/nlogo/agent/Agent.getObserverVariable (I)Ljava/lang/Object;
           L1
            ARETURN
[12]_asm_proceduresetup_ask_10 "ask sheep set color white set energy random-float 2 * sheep-metabolism set shape "sheep" [ setxy random world-width random world-height ]" AgentSet => void
      _breed:SHEEP "sheep" => AgentSet
          // parameter final  context
         L0
          ALOAD 0
          GETFIELD org/nlogo/prim/_asm_proceduresetup_ask_10.world : Lorg/nlogo/agent/World;
          LDC "SHEEP"
          INVOKEVIRTUAL org/nlogo/agent/World.getBreed (Ljava/lang/String;)Lorg/nlogo/agent/AgentSet;
         L1
          ASTORE 2
          ALOAD 1
          GETFIELD org/nlogo/nvm/Context.agent : Lorg/nlogo/agent/Agent;
          INSTANCEOF org/nlogo/agent/Observer
          IFNE L2
          ALOAD 2
          ALOAD 0
          GETFIELD org/nlogo/prim/_asm_proceduresetup_ask_10.world : Lorg/nlogo/agent/World;
          INVOKEVIRTUAL org/nlogo/agent/World.turtles ()Lorg/nlogo/agent/TreeAgentSet;
          IF_ACMPNE L3
          NEW org/nlogo/nvm/RuntimePrimitiveException
          DUP
          ALOAD 1
          ALOAD 0
          INVOKESTATIC org/nlogo/core/I18N.errorsJ ()Lorg/nlogo/core/I18NJava;
          LDC "org.nlogo.prim.$common.onlyObserverCanAskAllTurtles"
          INVOKEINTERFACE org/nlogo/core/I18NJava.get (Ljava/lang/String;)Ljava/lang/String;
          INVOKESPECIAL org/nlogo/nvm/RuntimePrimitiveException.<init> (Lorg/nlogo/api/Context;Lorg/nlogo/nvm/Instruction;Ljava/lang/String;)V
          ATHROW
         L3
         FRAME APPEND [org/nlogo/agent/AgentSet]
          ALOAD 2
          ALOAD 0
          GETFIELD org/nlogo/prim/_asm_proceduresetup_ask_10.world : Lorg/nlogo/agent/World;
          INVOKEVIRTUAL org/nlogo/agent/World.patches ()Lorg/nlogo/agent/AgentSet;
          IF_ACMPNE L2
          NEW org/nlogo/nvm/RuntimePrimitiveException
          DUP
          ALOAD 1
          ALOAD 0
          INVOKESTATIC org/nlogo/core/I18N.errorsJ ()Lorg/nlogo/core/I18NJava;
          LDC "org.nlogo.prim.$common.onlyObserverCanAskAllPatches"
          INVOKEINTERFACE org/nlogo/core/I18NJava.get (Ljava/lang/String;)Ljava/lang/String;
          INVOKESPECIAL org/nlogo/nvm/RuntimePrimitiveException.<init> (Lorg/nlogo/api/Context;Lorg/nlogo/nvm/Instruction;Ljava/lang/String;)V
          ATHROW
         L2
         FRAME SAME
          ALOAD 1
          ALOAD 2
          BIPUSH 13
          INVOKEVIRTUAL org/nlogo/nvm/Context.runExclusiveJob (Lorg/nlogo/agent/AgentSet;I)V
          ALOAD 1
          BIPUSH 18
          PUTFIELD org/nlogo/nvm/Context.ip : I
         L4
          RETURN
[13]_asm_proceduresetup_setturtleorlinkvariable_11 "set color white" Object => void
      _constdouble:9.9 "white" => Double
          TRYCATCHBLOCK L0 L1 L2 org/nlogo/api/AgentException
         L3
          ALOAD 0
          GETFIELD org/nlogo/prim/_asm_proceduresetup_setturtleorlinkvariable_11.kept2_value : Ljava/lang/Double;
         L4
          ASTORE 2
         L0
          ALOAD 1
          GETFIELD org/nlogo/nvm/Context.agent : Lorg/nlogo/agent/Agent;
          LDC "COLOR"
          ALOAD 2
          INVOKEVIRTUAL org/nlogo/agent/Agent.setTurtleOrLinkVariable (Ljava/lang/String;Ljava/lang/Object;)V
         L1
          GOTO L5
         L2
         FRAME FULL [org/nlogo/prim/_asm_proceduresetup_setturtleorlinkvariable_11 org/nlogo/nvm/Context java/lang/Double] [org/nlogo/api/AgentException]
          ASTORE 3
          NEW org/nlogo/nvm/RuntimePrimitiveException
          DUP
          ALOAD 1
          ALOAD 0
          ALOAD 3
          INVOKEVIRTUAL org/nlogo/api/AgentException.getMessage ()Ljava/lang/String;
          INVOKESPECIAL org/nlogo/nvm/RuntimePrimitiveException.<init> (Lorg/nlogo/api/Context;Lorg/nlogo/nvm/Instruction;Ljava/lang/String;)V
          ATHROW
         L5
         FRAME SAME
          ALOAD 1
          BIPUSH 14
          PUTFIELD org/nlogo/nvm/Context.ip : I
         L6
          RETURN
[14]_asm_proceduresetup_setturtlevariable_12 "set energy random-float 2 * sheep-metabolism" Object => void
      _randomfloat "random-float 2 * sheep-metabolism" double => double
        _mult "2 * sheep-metabolism" double,double => double
          _constdouble:2.0 "2" => double
          _observervariable:SHEEP-METABOLISM "sheep-metabolism" => Object
          TRYCATCHBLOCK L0 L1 L1 java/lang/ClassCastException
          TRYCATCHBLOCK L2 L3 L4 org/nlogo/api/AgentException
         L5
          LDC 2.0
         L6
          ALOAD 1
          GETFIELD org/nlogo/nvm/Context.agent : Lorg/nlogo/agent/Agent;
          ICONST_1
          INVOKEVIRTUAL org/nlogo/agent/Agent.getObserverVariable (I)Ljava/lang/Object;
         L7
          ASTORE 2
         L0
          ALOAD 2
          CHECKCAST java/lang/Double
          INVOKEVIRTUAL java/lang/Double.doubleValue ()D
          GOTO L8
         L1
         FRAME FULL [org/nlogo/prim/_asm_proceduresetup_setturtlevariable_12 org/nlogo/nvm/Context java/lang/Object] [java/lang/ClassCastException]
          POP
          NEW org/nlogo/nvm/ArgumentTypeException
          DUP
          ALOAD 1
          ALOAD 0
          BIPUSH 1
          LDC 1
          ALOAD 2
          INVOKESPECIAL org/nlogo/nvm/ArgumentTypeException.<init> (Lorg/nlogo/nvm/Context;Lorg/nlogo/nvm/Instruction;IILjava/lang/Object;)V
          ATHROW
         L8
         FRAME FULL [org/nlogo/prim/_asm_proceduresetup_setturtlevariable_12 org/nlogo/nvm/Context java/lang/Object] [D D]
          DSTORE 4
          DSTORE 2
          ALOAD 0
          DLOAD 2
          DLOAD 4
          DMUL
          INVOKEVIRTUAL org/nlogo/prim/_asm_proceduresetup_setturtlevariable_12.validDouble (D)D
         L9
          DSTORE 2
          ALOAD 0
          DLOAD 2
          ALOAD 1
          GETFIELD org/nlogo/nvm/Context.job : Lorg/nlogo/nvm/Job;
          GETFIELD org/nlogo/nvm/Job.random : Lorg/nlogo/api/MersenneTwisterFast;
          INVOKEVIRTUAL org/nlogo/api/MersenneTwisterFast.nextDouble ()D
          DMUL
          INVOKEVIRTUAL org/nlogo/prim/_asm_proceduresetup_setturtlevariable_12.validDouble (D)D
         L10
          DSTORE 2
          NEW java/lang/Double
          DUP
          DLOAD 2
          INVOKESPECIAL java/lang/Double.<init> (D)V
          ASTORE 2
         L2
          ALOAD 1
          GETFIELD org/nlogo/nvm/Context.agent : Lorg/nlogo/agent/Agent;
          BIPUSH 13
          ALOAD 2
          INVOKEVIRTUAL org/nlogo/agent/Agent.setTurtleVariable (ILjava/lang/Object;)V
         L3
          GOTO L11
         L4
         FRAME FULL [org/nlogo/prim/_asm_proceduresetup_setturtlevariable_12 org/nlogo/nvm/Context java/lang/Double T D] [org/nlogo/api/AgentException]
          ASTORE 3
          NEW org/nlogo/nvm/RuntimePrimitiveException
          DUP
          ALOAD 1
          ALOAD 0
          ALOAD 3
          INVOKEVIRTUAL org/nlogo/api/AgentException.getMessage ()Ljava/lang/String;
          INVOKESPECIAL org/nlogo/nvm/RuntimePrimitiveException.<init> (Lorg/nlogo/api/Context;Lorg/nlogo/nvm/Instruction;Ljava/lang/String;)V
          ATHROW
         L11
         FRAME SAME
          ALOAD 1
          BIPUSH 15
          PUTFIELD org/nlogo/nvm/Context.ip : I
         L12
          RETURN
[15]_asm_proceduresetup_setturtleorlinkvariable_13 "set shape "sheep"" Object => void
      _conststring:"sheep" ""sheep"" => String
          TRYCATCHBLOCK L0 L1 L2 org/nlogo/api/AgentException
         L3
          LDC "sheep"
         L4
          ASTORE 2
         L0
          ALOAD 1
          GETFIELD org/nlogo/nvm/Context.agent : Lorg/nlogo/agent/Agent;
          LDC "SHAPE"
          ALOAD 2
          INVOKEVIRTUAL org/nlogo/agent/Agent.setTurtleOrLinkVariable (Ljava/lang/String;Ljava/lang/Object;)V
         L1
          GOTO L5
         L2
         FRAME FULL [org/nlogo/prim/_asm_proceduresetup_setturtleorlinkvariable_13 org/nlogo/nvm/Context java/lang/String] [org/nlogo/api/AgentException]
          ASTORE 3
          NEW org/nlogo/nvm/RuntimePrimitiveException
          DUP
          ALOAD 1
          ALOAD 0
          ALOAD 3
          INVOKEVIRTUAL org/nlogo/api/AgentException.getMessage ()Ljava/lang/String;
          INVOKESPECIAL org/nlogo/nvm/RuntimePrimitiveException.<init> (Lorg/nlogo/api/Context;Lorg/nlogo/nvm/Instruction;Ljava/lang/String;)V
          ATHROW
         L5
         FRAME SAME
          ALOAD 1
          BIPUSH 16
          PUTFIELD org/nlogo/nvm/Context.ip : I
         L6
          RETURN
[16]_asm_proceduresetup_setxy_14 "setxy random world-width random world-height" double,double => void
      _random "random world-width" double => double
        _worldwidth "world-width" => double
      _random "random world-height" double => double
        _worldheight "world-height" => double
          // parameter final  context
          // parameter final  context
          TRYCATCHBLOCK L0 L1 L2 org/nlogo/api/AgentException
         L3
          ALOAD 0
          GETFIELD org/nlogo/prim/_asm_proceduresetup_setxy_14.world : Lorg/nlogo/agent/World;
          INVOKEVIRTUAL org/nlogo/agent/World.worldWidth ()I
          I2D
         L4
          DSTORE 2
          ALOAD 0
          DLOAD 2
          INVOKEVIRTUAL org/nlogo/prim/_asm_proceduresetup_setxy_14.validLong (D)J
          LSTORE 4
          DLOAD 2
          LLOAD 4
          L2D
          DCMPL
          IFEQ L5
          LLOAD 4
          DLOAD 2
          DCONST_0
          DCMPL
          IFLT L6
          LCONST_1
          GOTO L7
         L6
         FRAME FULL [org/nlogo/prim/_asm_proceduresetup_setxy_14 org/nlogo/nvm/Context D J] [J]
          LDC -1
         L7
         FRAME FULL [org/nlogo/prim/_asm_proceduresetup_setxy_14 org/nlogo/nvm/Context D J] [J J]
          LADD
          LSTORE 4
         L5
         FRAME SAME
          LLOAD 4
          LCONST_0
          LCMP
          IFLE L8
          ALOAD 1
          GETFIELD org/nlogo/nvm/Context.job : Lorg/nlogo/nvm/Job;
          GETFIELD org/nlogo/nvm/Job.random : Lorg/nlogo/api/MersenneTwisterFast;
          LLOAD 4
          INVOKEVIRTUAL org/nlogo/api/MersenneTwisterFast.nextLong (J)J
          L2D
          GOTO L9
         L8
         FRAME SAME
          LLOAD 4
          LCONST_0
          LCMP
          IFGE L10
          ALOAD 1
          GETFIELD org/nlogo/nvm/Context.job : Lorg/nlogo/nvm/Job;
          GETFIELD org/nlogo/nvm/Job.random : Lorg/nlogo/api/MersenneTwisterFast;
          LLOAD 4
          LNEG
          INVOKEVIRTUAL org/nlogo/api/MersenneTwisterFast.nextLong (J)J
          LNEG
          L2D
          GOTO L9
         L10
         FRAME SAME
          DCONST_0
         L9
         FRAME SAME1 D
          ALOAD 0
          GETFIELD org/nlogo/prim/_asm_proceduresetup_setxy_14.world : Lorg/nlogo/agent/World;
          INVOKEVIRTUAL org/nlogo/agent/World.worldHeight ()I
          I2D
         L11
          DSTORE 2
          ALOAD 0
          DLOAD 2
          INVOKEVIRTUAL org/nlogo/prim/_asm_proceduresetup_setxy_14.validLong (D)J
          LSTORE 4
          DLOAD 2
          LLOAD 4
          L2D
          DCMPL
          IFEQ L12
          LLOAD 4
          DLOAD 2
          DCONST_0
          DCMPL
          IFLT L13
          LCONST_1
          GOTO L14
         L13
         FRAME FULL [org/nlogo/prim/_asm_proceduresetup_setxy_14 org/nlogo/nvm/Context D J] [D J]
          LDC -1
         L14
         FRAME FULL [org/nlogo/prim/_asm_proceduresetup_setxy_14 org/nlogo/nvm/Context D J] [D J J]
          LADD
          LSTORE 4
         L12
         FRAME SAME1 D
          LLOAD 4
          LCONST_0
          LCMP
          IFLE L15
          ALOAD 1
          GETFIELD org/nlogo/nvm/Context.job : Lorg/nlogo/nvm/Job;
          GETFIELD org/nlogo/nvm/Job.random : Lorg/nlogo/api/MersenneTwisterFast;
          LLOAD 4
          INVOKEVIRTUAL org/nlogo/api/MersenneTwisterFast.nextLong (J)J
          L2D
          GOTO L16
         L15
         FRAME SAME1 D
          LLOAD 4
          LCONST_0
          LCMP
          IFGE L17
          ALOAD 1
          GETFIELD org/nlogo/nvm/Context.job : Lorg/nlogo/nvm/Job;
          GETFIELD org/nlogo/nvm/Job.random : Lorg/nlogo/api/MersenneTwisterFast;
          LLOAD 4
          LNEG
          INVOKEVIRTUAL org/nlogo/api/MersenneTwisterFast.nextLong (J)J
          LNEG
          L2D
          GOTO L16
         L17
         FRAME SAME1 D
          DCONST_0
         L16
         FRAME FULL [org/nlogo/prim/_asm_proceduresetup_setxy_14 org/nlogo/nvm/Context D J] [D D]
          DSTORE 4
          DSTORE 2
          ALOAD 1
          GETFIELD org/nlogo/nvm/Context.agent : Lorg/nlogo/agent/Agent;
          CHECKCAST org/nlogo/agent/Turtle
          ASTORE 6
         L0
          ALOAD 6
          ALOAD 6
          DLOAD 2
          INVOKEVIRTUAL org/nlogo/agent/Turtle.shortestPathX (D)D
          ALOAD 6
          DLOAD 4
          INVOKEVIRTUAL org/nlogo/agent/Turtle.shortestPathY (D)D
          INVOKEVIRTUAL org/nlogo/agent/Turtle.xandycor (DD)V
         L1
          GOTO L18
         L2
         FRAME FULL [org/nlogo/prim/_asm_proceduresetup_setxy_14 org/nlogo/nvm/Context D D org/nlogo/agent/Turtle] [org/nlogo/api/AgentException]
          ASTORE 7
          NEW org/nlogo/nvm/RuntimePrimitiveException
          DUP
          ALOAD 1
          ALOAD 0
          INVOKESTATIC org/nlogo/core/I18N.errorsJ ()Lorg/nlogo/core/I18NJava;
          LDC "org.nlogo.prim.etc._setxy.pointOutsideWorld"
          ICONST_2
          ANEWARRAY java/lang/Object
          DUP
          ICONST_0
          DLOAD 2
          INVOKESTATIC java/lang/Double.valueOf (D)Ljava/lang/Double;
          AASTORE
          DUP
          ICONST_1
          DLOAD 4
          INVOKESTATIC java/lang/Double.valueOf (D)Ljava/lang/Double;
          AASTORE
          INVOKEINTERFACE org/nlogo/core/I18NJava.getN (Ljava/lang/String;[Ljava/lang/Object;)Ljava/lang/String;
          INVOKESPECIAL org/nlogo/nvm/RuntimePrimitiveException.<init> (Lorg/nlogo/api/Context;Lorg/nlogo/nvm/Instruction;Ljava/lang/String;)V
          ATHROW
         L18
         FRAME SAME
          ALOAD 1
          BIPUSH 17
          PUTFIELD org/nlogo/nvm/Context.ip : I
         L19
          RETURN
[17]_asm_proceduresetup_done_15 => void
          // parameter final  context
         L0
          ALOAD 1
          ICONST_1
          PUTFIELD org/nlogo/nvm/Context.finished : Z
         L1
          RETURN
[18]_crofast:WOLVES "create-ordered-wolves [ init-wolves ]"
      _asm_proceduresetup_observervariable_16 "init-wolves" => Object
           L0
            ALOAD 1
            GETFIELD org/nlogo/nvm/Context.agent : Lorg/nlogo/agent/Agent;
            ICONST_3
            INVOKEVIRTUAL org/nlogo/agent/Agent.getObserverVariable (I)Ljava/lang/Object;
           L1
            ARETURN
[19]_asm_proceduresetup_ask_17 "ask wolves set color black set energy random-float 2 * wolf-metabolism set shape "wolf" [ setxy random world-width random world-height ]" AgentSet => void
      _breed:WOLVES "wolves" => AgentSet
          // parameter final  context
         L0
          ALOAD 0
          GETFIELD org/nlogo/prim/_asm_proceduresetup_ask_17.world : Lorg/nlogo/agent/World;
          LDC "WOLVES"
          INVOKEVIRTUAL org/nlogo/agent/World.getBreed (Ljava/lang/String;)Lorg/nlogo/agent/AgentSet;
         L1
          ASTORE 2
          ALOAD 1
          GETFIELD org/nlogo/nvm/Context.agent : Lorg/nlogo/agent/Agent;
          INSTANCEOF org/nlogo/agent/Observer
          IFNE L2
          ALOAD 2
          ALOAD 0
          GETFIELD org/nlogo/prim/_asm_proceduresetup_ask_17.world : Lorg/nlogo/agent/World;
          INVOKEVIRTUAL org/nlogo/agent/World.turtles ()Lorg/nlogo/agent/TreeAgentSet;
          IF_ACMPNE L3
          NEW org/nlogo/nvm/RuntimePrimitiveException
          DUP
          ALOAD 1
          ALOAD 0
          INVOKESTATIC org/nlogo/core/I18N.errorsJ ()Lorg/nlogo/core/I18NJava;
          LDC "org.nlogo.prim.$common.onlyObserverCanAskAllTurtles"
          INVOKEINTERFACE org/nlogo/core/I18NJava.get (Ljava/lang/String;)Ljava/lang/String;
          INVOKESPECIAL org/nlogo/nvm/RuntimePrimitiveException.<init> (Lorg/nlogo/api/Context;Lorg/nlogo/nvm/Instruction;Ljava/lang/String;)V
          ATHROW
         L3
         FRAME APPEND [org/nlogo/agent/AgentSet]
          ALOAD 2
          ALOAD 0
          GETFIELD org/nlogo/prim/_asm_proceduresetup_ask_17.world : Lorg/nlogo/agent/World;
          INVOKEVIRTUAL org/nlogo/agent/World.patches ()Lorg/nlogo/agent/AgentSet;
          IF_ACMPNE L2
          NEW org/nlogo/nvm/RuntimePrimitiveException
          DUP
          ALOAD 1
          ALOAD 0
          INVOKESTATIC org/nlogo/core/I18N.errorsJ ()Lorg/nlogo/core/I18NJava;
          LDC "org.nlogo.prim.$common.onlyObserverCanAskAllPatches"
          INVOKEINTERFACE org/nlogo/core/I18NJava.get (Ljava/lang/String;)Ljava/lang/String;
          INVOKESPECIAL org/nlogo/nvm/RuntimePrimitiveException.<init> (Lorg/nlogo/api/Context;Lorg/nlogo/nvm/Instruction;Ljava/lang/String;)V
          ATHROW
         L2
         FRAME SAME
          ALOAD 1
          ALOAD 2
          BIPUSH 20
          INVOKEVIRTUAL org/nlogo/nvm/Context.runExclusiveJob (Lorg/nlogo/agent/AgentSet;I)V
          ALOAD 1
          BIPUSH 25
          PUTFIELD org/nlogo/nvm/Context.ip : I
         L4
          RETURN
[20]_asm_proceduresetup_setturtleorlinkvariable_18 "set color black" Object => void
      _constdouble:0.0 "black" => Double
          TRYCATCHBLOCK L0 L1 L2 org/nlogo/api/AgentException
         L3
          ALOAD 0
          GETFIELD org/nlogo/prim/_asm_proceduresetup_setturtleorlinkvariable_18.kept2_value : Ljava/lang/Double;
         L4
          ASTORE 2
         L0
          ALOAD 1
          GETFIELD org/nlogo/nvm/Context.agent : Lorg/nlogo/agent/Agent;
          LDC "COLOR"
          ALOAD 2
          INVOKEVIRTUAL org/nlogo/agent/Agent.setTurtleOrLinkVariable (Ljava/lang/String;Ljava/lang/Object;)V
         L1
          GOTO L5
         L2
         FRAME FULL [org/nlogo/prim/_asm_proceduresetup_setturtleorlinkvariable_18 org/nlogo/nvm/Context java/lang/Double] [org/nlogo/api/AgentException]
          ASTORE 3
          NEW org/nlogo/nvm/RuntimePrimitiveException
          DUP
          ALOAD 1
          ALOAD 0
          ALOAD 3
          INVOKEVIRTUAL org/nlogo/api/AgentException.getMessage ()Ljava/lang/String;
          INVOKESPECIAL org/nlogo/nvm/RuntimePrimitiveException.<init> (Lorg/nlogo/api/Context;Lorg/nlogo/nvm/Instruction;Ljava/lang/String;)V
          ATHROW
         L5
         FRAME SAME
          ALOAD 1
          BIPUSH 21
          PUTFIELD org/nlogo/nvm/Context.ip : I
         L6
          RETURN
[21]_asm_proceduresetup_setturtlevariable_19 "set energy random-float 2 * wolf-metabolism" Object => void
      _randomfloat "random-float 2 * wolf-metabolism" double => double
        _mult "2 * wolf-metabolism" double,double => double
          _constdouble:2.0 "2" => double
          _observervariable:WOLF-METABOLISM "wolf-metabolism" => Object
          TRYCATCHBLOCK L0 L1 L1 java/lang/ClassCastException
          TRYCATCHBLOCK L2 L3 L4 org/nlogo/api/AgentException
         L5
          LDC 2.0
         L6
          ALOAD 1
          GETFIELD org/nlogo/nvm/Context.agent : Lorg/nlogo/agent/Agent;
          ICONST_4
          INVOKEVIRTUAL org/nlogo/agent/Agent.getObserverVariable (I)Ljava/lang/Object;
         L7
          ASTORE 2
         L0
          ALOAD 2
          CHECKCAST java/lang/Double
          INVOKEVIRTUAL java/lang/Double.doubleValue ()D
          GOTO L8
         L1
         FRAME FULL [org/nlogo/prim/_asm_proceduresetup_setturtlevariable_19 org/nlogo/nvm/Context java/lang/Object] [java/lang/ClassCastException]
          POP
          NEW org/nlogo/nvm/ArgumentTypeException
          DUP
          ALOAD 1
          ALOAD 0
          BIPUSH 1
          LDC 1
          ALOAD 2
          INVOKESPECIAL org/nlogo/nvm/ArgumentTypeException.<init> (Lorg/nlogo/nvm/Context;Lorg/nlogo/nvm/Instruction;IILjava/lang/Object;)V
          ATHROW
         L8
         FRAME FULL [org/nlogo/prim/_asm_proceduresetup_setturtlevariable_19 org/nlogo/nvm/Context java/lang/Object] [D D]
          DSTORE 4
          DSTORE 2
          ALOAD 0
          DLOAD 2
          DLOAD 4
          DMUL
          INVOKEVIRTUAL org/nlogo/prim/_asm_proceduresetup_setturtlevariable_19.validDouble (D)D
         L9
          DSTORE 2
          ALOAD 0
          DLOAD 2
          ALOAD 1
          GETFIELD org/nlogo/nvm/Context.job : Lorg/nlogo/nvm/Job;
          GETFIELD org/nlogo/nvm/Job.random : Lorg/nlogo/api/MersenneTwisterFast;
          INVOKEVIRTUAL org/nlogo/api/MersenneTwisterFast.nextDouble ()D
          DMUL
          INVOKEVIRTUAL org/nlogo/prim/_asm_proceduresetup_setturtlevariable_19.validDouble (D)D
         L10
          DSTORE 2
          NEW java/lang/Double
          DUP
          DLOAD 2
          INVOKESPECIAL java/lang/Double.<init> (D)V
          ASTORE 2
         L2
          ALOAD 1
          GETFIELD org/nlogo/nvm/Context.agent : Lorg/nlogo/agent/Agent;
          BIPUSH 13
          ALOAD 2
          INVOKEVIRTUAL org/nlogo/agent/Agent.setTurtleVariable (ILjava/lang/Object;)V
         L3
          GOTO L11
         L4
         FRAME FULL [org/nlogo/prim/_asm_proceduresetup_setturtlevariable_19 org/nlogo/nvm/Context java/lang/Double T D] [org/nlogo/api/AgentException]
          ASTORE 3
          NEW org/nlogo/nvm/RuntimePrimitiveException
          DUP
          ALOAD 1
          ALOAD 0
          ALOAD 3
          INVOKEVIRTUAL org/nlogo/api/AgentException.getMessage ()Ljava/lang/String;
          INVOKESPECIAL org/nlogo/nvm/RuntimePrimitiveException.<init> (Lorg/nlogo/api/Context;Lorg/nlogo/nvm/Instruction;Ljava/lang/String;)V
          ATHROW
         L11
         FRAME SAME
          ALOAD 1
          BIPUSH 22
          PUTFIELD org/nlogo/nvm/Context.ip : I
         L12
          RETURN
[22]_asm_proceduresetup_setturtleorlinkvariable_20 "set shape "wolf"" Object => void
      _conststring:"wolf" ""wolf"" => String
          TRYCATCHBLOCK L0 L1 L2 org/nlogo/api/AgentException
         L3
          LDC "wolf"
         L4
          ASTORE 2
         L0
          ALOAD 1
          GETFIELD org/nlogo/nvm/Context.agent : Lorg/nlogo/agent/Agent;
          LDC "SHAPE"
          ALOAD 2
          INVOKEVIRTUAL org/nlogo/agent/Agent.setTurtleOrLinkVariable (Ljava/lang/String;Ljava/lang/Object;)V
         L1
          GOTO L5
         L2
         FRAME FULL [org/nlogo/prim/_asm_proceduresetup_setturtleorlinkvariable_20 org/nlogo/nvm/Context java/lang/String] [org/nlogo/api/AgentException]
          ASTORE 3
          NEW org/nlogo/nvm/RuntimePrimitiveException
          DUP
          ALOAD 1
          ALOAD 0
          ALOAD 3
          INVOKEVIRTUAL org/nlogo/api/AgentException.getMessage ()Ljava/lang/String;
          INVOKESPECIAL org/nlogo/nvm/RuntimePrimitiveException.<init> (Lorg/nlogo/api/Context;Lorg/nlogo/nvm/Instruction;Ljava/lang/String;)V
          ATHROW
         L5
         FRAME SAME
          ALOAD 1
          BIPUSH 23
          PUTFIELD org/nlogo/nvm/Context.ip : I
         L6
          RETURN
[23]_asm_proceduresetup_setxy_21 "setxy random world-width random world-height" double,double => void
      _random "random world-width" double => double
        _worldwidth "world-width" => double
      _random "random world-height" double => double
        _worldheight "world-height" => double
          // parameter final  context
          // parameter final  context
          TRYCATCHBLOCK L0 L1 L2 org/nlogo/api/AgentException
         L3
          ALOAD 0
          GETFIELD org/nlogo/prim/_asm_proceduresetup_setxy_21.world : Lorg/nlogo/agent/World;
          INVOKEVIRTUAL org/nlogo/agent/World.worldWidth ()I
          I2D
         L4
          DSTORE 2
          ALOAD 0
          DLOAD 2
          INVOKEVIRTUAL org/nlogo/prim/_asm_proceduresetup_setxy_21.validLong (D)J
          LSTORE 4
          DLOAD 2
          LLOAD 4
          L2D
          DCMPL
          IFEQ L5
          LLOAD 4
          DLOAD 2
          DCONST_0
          DCMPL
          IFLT L6
          LCONST_1
          GOTO L7
         L6
         FRAME FULL [org/nlogo/prim/_asm_proceduresetup_setxy_21 org/nlogo/nvm/Context D J] [J]
          LDC -1
         L7
         FRAME FULL [org/nlogo/prim/_asm_proceduresetup_setxy_21 org/nlogo/nvm/Context D J] [J J]
          LADD
          LSTORE 4
         L5
         FRAME SAME
          LLOAD 4
          LCONST_0
          LCMP
          IFLE L8
          ALOAD 1
          GETFIELD org/nlogo/nvm/Context.job : Lorg/nlogo/nvm/Job;
          GETFIELD org/nlogo/nvm/Job.random : Lorg/nlogo/api/MersenneTwisterFast;
          LLOAD 4
          INVOKEVIRTUAL org/nlogo/api/MersenneTwisterFast.nextLong (J)J
          L2D
          GOTO L9
         L8
         FRAME SAME
          LLOAD 4
          LCONST_0
          LCMP
          IFGE L10
          ALOAD 1
          GETFIELD org/nlogo/nvm/Context.job : Lorg/nlogo/nvm/Job;
          GETFIELD org/nlogo/nvm/Job.random : Lorg/nlogo/api/MersenneTwisterFast;
          LLOAD 4
          LNEG
          INVOKEVIRTUAL org/nlogo/api/MersenneTwisterFast.nextLong (J)J
          LNEG
          L2D
          GOTO L9
         L10
         FRAME SAME
          DCONST_0
         L9
         FRAME SAME1 D
          ALOAD 0
          GETFIELD org/nlogo/prim/_asm_proceduresetup_setxy_21.world : Lorg/nlogo/agent/World;
          INVOKEVIRTUAL org/nlogo/agent/World.worldHeight ()I
          I2D
         L11
          DSTORE 2
          ALOAD 0
          DLOAD 2
          INVOKEVIRTUAL org/nlogo/prim/_asm_proceduresetup_setxy_21.validLong (D)J
          LSTORE 4
          DLOAD 2
          LLOAD 4
          L2D
          DCMPL
          IFEQ L12
          LLOAD 4
          DLOAD 2
          DCONST_0
          DCMPL
          IFLT L13
          LCONST_1
          GOTO L14
         L13
         FRAME FULL [org/nlogo/prim/_asm_proceduresetup_setxy_21 org/nlogo/nvm/Context D J] [D J]
          LDC -1
         L14
         FRAME FULL [org/nlogo/prim/_asm_proceduresetup_setxy_21 org/nlogo/nvm/Context D J] [D J J]
          LADD
          LSTORE 4
         L12
         FRAME SAME1 D
          LLOAD 4
          LCONST_0
          LCMP
          IFLE L15
          ALOAD 1
          GETFIELD org/nlogo/nvm/Context.job : Lorg/nlogo/nvm/Job;
          GETFIELD org/nlogo/nvm/Job.random : Lorg/nlogo/api/MersenneTwisterFast;
          LLOAD 4
          INVOKEVIRTUAL org/nlogo/api/MersenneTwisterFast.nextLong (J)J
          L2D
          GOTO L16
         L15
         FRAME SAME1 D
          LLOAD 4
          LCONST_0
          LCMP
          IFGE L17
          ALOAD 1
          GETFIELD org/nlogo/nvm/Context.job : Lorg/nlogo/nvm/Job;
          GETFIELD org/nlogo/nvm/Job.random : Lorg/nlogo/api/MersenneTwisterFast;
          LLOAD 4
          LNEG
          INVOKEVIRTUAL org/nlogo/api/MersenneTwisterFast.nextLong (J)J
          LNEG
          L2D
          GOTO L16
         L17
         FRAME SAME1 D
          DCONST_0
         L16
         FRAME FULL [org/nlogo/prim/_asm_proceduresetup_setxy_21 org/nlogo/nvm/Context D J] [D D]
          DSTORE 4
          DSTORE 2
          ALOAD 1
          GETFIELD org/nlogo/nvm/Context.agent : Lorg/nlogo/agent/Agent;
          CHECKCAST org/nlogo/agent/Turtle
          ASTORE 6
         L0
          ALOAD 6
          ALOAD 6
          DLOAD 2
          INVOKEVIRTUAL org/nlogo/agent/Turtle.shortestPathX (D)D
          ALOAD 6
          DLOAD 4
          INVOKEVIRTUAL org/nlogo/agent/Turtle.shortestPathY (D)D
          INVOKEVIRTUAL org/nlogo/agent/Turtle.xandycor (DD)V
         L1
          GOTO L18
         L2
         FRAME FULL [org/nlogo/prim/_asm_proceduresetup_setxy_21 org/nlogo/nvm/Context D D org/nlogo/agent/Turtle] [org/nlogo/api/AgentException]
          ASTORE 7
          NEW org/nlogo/nvm/RuntimePrimitiveException
          DUP
          ALOAD 1
          ALOAD 0
          INVOKESTATIC org/nlogo/core/I18N.errorsJ ()Lorg/nlogo/core/I18NJava;
          LDC "org.nlogo.prim.etc._setxy.pointOutsideWorld"
          ICONST_2
          ANEWARRAY java/lang/Object
          DUP
          ICONST_0
          DLOAD 2
          INVOKESTATIC java/lang/Double.valueOf (D)Ljava/lang/Double;
          AASTORE
          DUP
          ICONST_1
          DLOAD 4
          INVOKESTATIC java/lang/Double.valueOf (D)Ljava/lang/Double;
          AASTORE
          INVOKEINTERFACE org/nlogo/core/I18NJava.getN (Ljava/lang/String;[Ljava/lang/Object;)Ljava/lang/String;
          INVOKESPECIAL org/nlogo/nvm/RuntimePrimitiveException.<init> (Lorg/nlogo/api/Context;Lorg/nlogo/nvm/Instruction;Ljava/lang/String;)V
          ATHROW
         L18
         FRAME SAME
          ALOAD 1
          BIPUSH 24
          PUTFIELD org/nlogo/nvm/Context.ip : I
         L19
          RETURN
[24]_asm_proceduresetup_done_22 => void
          // parameter final  context
         L0
          ALOAD 1
          ICONST_1
          PUTFIELD org/nlogo/nvm/Context.finished : Z
         L1
          RETURN
[25]_asm_proceduresetup_if_23 "if plot? [ graph ]" boolean => void
      _observervariable:PLOT? "plot?" => Object
          TRYCATCHBLOCK L0 L1 L1 java/lang/ClassCastException
         L2
          ALOAD 1
          GETFIELD org/nlogo/nvm/Context.agent : Lorg/nlogo/agent/Agent;
          BIPUSH 8
          INVOKEVIRTUAL org/nlogo/agent/Agent.getObserverVariable (I)Ljava/lang/Object;
         L3
          ASTORE 2
         L0
          ALOAD 2
          CHECKCAST java/lang/Boolean
          INVOKEVIRTUAL java/lang/Boolean.booleanValue ()Z
          GOTO L4
         L1
         FRAME FULL [org/nlogo/prim/_asm_proceduresetup_if_23 org/nlogo/nvm/Context java/lang/Object] [java/lang/ClassCastException]
          POP
          NEW org/nlogo/nvm/ArgumentTypeException
          DUP
          ALOAD 1
          ALOAD 0
          BIPUSH 0
          LDC 2
          ALOAD 2
          INVOKESPECIAL org/nlogo/nvm/ArgumentTypeException.<init> (Lorg/nlogo/nvm/Context;Lorg/nlogo/nvm/Instruction;IILjava/lang/Object;)V
          ATHROW
         L4
         FRAME SAME1 I
          ISTORE 2
          ALOAD 1
          ILOAD 2
          IFEQ L5
          BIPUSH 26
          GOTO L6
         L5
         FRAME FULL [org/nlogo/prim/_asm_proceduresetup_if_23 org/nlogo/nvm/Context I] [org/nlogo/nvm/Context]
          BIPUSH 27
         L6
         FRAME FULL [org/nlogo/prim/_asm_proceduresetup_if_23 org/nlogo/nvm/Context I] [org/nlogo/nvm/Context I]
          PUTFIELD org/nlogo/nvm/Context.ip : I
         L7
          RETURN
[26]_asm_proceduresetup_call_24 "graph"
         L0
          NEW org/nlogo/nvm/Activation
          DUP
          ALOAD 0
          GETFIELD org/nlogo/prim/_asm_proceduresetup_call_24.kept1_procedure : Lorg/nlogo/nvm/Procedure;
          ALOAD 1
          GETFIELD org/nlogo/nvm/Context.activation : Lorg/nlogo/nvm/Activation;
          BIPUSH 27
          INVOKESPECIAL org/nlogo/nvm/Activation.<init> (Lorg/nlogo/nvm/Procedure;Lorg/nlogo/nvm/Activation;I)V
          ALOAD 1
          SWAP
          PUTFIELD org/nlogo/nvm/Context.activation : Lorg/nlogo/nvm/Activation;
          ALOAD 1
          ICONST_0
          PUTFIELD org/nlogo/nvm/Context.ip : I
         L1
          RETURN
[27]_asm_proceduresetup_return_25 => void
         L0
          ALOAD 1
          INVOKEVIRTUAL org/nlogo/nvm/Context.returnFromProcedure ()V
          ALOAD 1
          ICONST_0
          PUTFIELD org/nlogo/nvm/Context.stopping : Z
         L1
          RETURN

